Workbook

Sheet Sheet1
A1: DOCKET NO. | B1: Base Date | C1: ITEM CODE | D1: PROPOSE ERP ITEM NAME | E1: Propose Drum Type | F1: Insulation Screening(Metallic) | G1: RM Rate(Insulation Screening(Metallic)) | H1: Weight (Insulation Screening (Metallic)) | I1: Cost Insulation Screening(Metallic) | J1: Conductor | K1: RM Rate(Conductor) | L1: Weight(Conductor) | M1: Cost(Conductor) | N1: AL ALLOY | O1: RM Rate(AL Alloy) | P1: Weight(Al Alloy) | Q1: Cost(AL Alloy) | R1: Insulation Screening(Non-Metallic) | S1: RM Rate(Insulation Screening(Non-Metallic)) | T1: Weight(Insulation Screening(Non-Metallic) | U1: Cost(Insulation Screening(Non-Metallic) | V1: Insulation | W1: RM Rate(Insulation) | X1: Weight(Insulation) | Y1: Cost(Insulation) | Z1: Poly Tape | AA1: RM Rate(Poly Tape) | AB1: Weight(Poly Tape) | AC1: Cost(Poly Tape) | AD1: Inner Sheath | AE1: RM Rate(Inner Sheath) | AF1: Weight(Inner Sheath) | AG1: Cost(Inner Sheath) | AH1: Armouring | AI1: RM Rate(Armouring) | AJ1: Weight(Armouring) | AK1: Cost(Armouring) | AL1: Outer Sheath | AM1: RM Rate(Outer Sheath) | AN1: Weight(Outer Sheath) | AO1: Cost(Outer Sheath) | AP1: Filler | AQ1: RM Rate(Filler) | AR1: Weight(Filler) | AS1: Cost(Filler) | AT1: Grease | AU1: RM Rate(Grease) | AV1: Weight(Grease) | AW1: Cost(Grease) | AX1: Water Swellable Tape | AY1: RM Rate(Water Swellable Tape) | AZ1: Weight(Water Swellable Tape) | BA1: Cost(Water Swellable Tape) | BB1: Semi Conducting Water Swellable Tape | BC1: RM Rate(Semi Conducting Water Swellable Tape) | BD1: Weight(Semi Conducting Water Swellable Tape) | BE1: Cost(Semi Conducting Water Swellable Tape) | BF1: Semicon Tape | BG1: RM Rate(Semicon Tape) | BH1: Weight(Semicon Tape) | BI1: Cost(Semicon Tape) | BJ1: Glass Fiber Tape | BK1: RM Rate(Glass Fiber Tape) | BL1: Weight(Glass Fiber Tape) | BM1: Cost(Glass Fiber Tape) | BN1: Copper Wire 0.8MM | BO1: RM Rate(Copper Wire 0.8MM) | BP1: Weight(Copper Wire 0.8MM) | BQ1: Cost(Copper Wire 0.8MM) | BR1: Rubberized Cotton Tape | BS1: RM Rate(Rubberized Cotton Tape) | BT1: Weight(Rubberized Cotton Tape) | BU1: Cost(Rubberized Cotton Tape) | BV1: Water Tight Compound | BW1: RM Rate(Water Tight Compound) | BX1: Weight(Water Tight Compound) | BY1: Cost(Water Tight Compound) | BZ1: Drum Cost Per KM | CA1: Total RM Cost | CB1: FIRM % | CC1: Firm Value | CD1: MFG% | CE1: MFG Value | CF1: PROF% | CG1: Profit Value | CH1: 1st EX-Works | CI1: Intt % | CJ1: Intt Value | CK1: insp% | CL1: Insp Value | CM1: EX-Works Per KM | CN1: Freight Per KM | CO1: Price Including Freight Per KM | CP1: GST % | CQ1: GST Value | CR1: Price Including GST & Freight Per KM | CS1: QTY | CT1: Unit | CU1: Total Price Of Full QTY(Including Freight&GST) | CV1: DRUM CODE | CW1: DRUM SIZE (FxbXtx Ft) | CX1: Party Standard Length(MTR)
A2: ENQ-15423-22-23 | B2: 45733 | C2: FA0300004 | D2: 2 CORE X 2.5 SQ. MM. CU/UNARD.(PVC) | E2: WOOD | H2: 0 | J2: Copper | K2: 910.79 | L2: 44 | M2: 40074.76 | P2: 0 | T2: 0 | V2: Type C PVC (HR) | W2: 102.22 | X2: 26 | Y2: 2657.72 | Z2: POLY TAPE | AA2: 117 | AB2: 3 | AC2: 351 | AD2: PVC Type ST-2 | AE2: 70.87 | AF2: 39 | AG2: 2763.93 | AJ2: 0 | AL2: PVC Type ST-2 | AM2: 70.87 | AN2: 100 | AO2: 7087 | AR2: 0 | AV2: 0 | AZ2: 0 | BD2: 0 | BH2: 0 | BL2: 0 | BP2: 0 | BT2: 0 | BX2: 0 | BZ2: 4260 | CA2: 57194.41 | CH2: 57194.41 | CM2: 57194.41 | CO2: 57194.41 | CP2: 0.18 | CQ2: 10294.99 | CR2: 67489.4 | CS2: 19.014 | CT2: KMS | CU2: 1283244 | CV2: MD0100003 | CW2: DRUM - 28 X 14 X 23 X 2
A3: ENQ-15423-22-23 | B3: 45733 | C3: FA0300006 | D3: 4 CORE X 2.5 SQ. MM. CU/UNARD.(PVC) | E3: WOOD | H3: 0 | J3: Copper | K3: 910.79 | L3: 89 | M3: 81060.31 | P3: 0 | T3: 0 | V3: Type C PVC | W3: 93.6 | X3: 52 | Y3: 4867.2 | Z3: POLY TAPE | AA3: 117 | AB3: 4 | AC3: 468 | AD3: PVC Type ST-2 | AE3: 70.87 | AF3: 27 | AG3: 1913.49 | AJ3: 0 | AL3: FR PVC Type ST-2 | AM3: 86.1 | AN3: 109 | AO3: 9384.9 | AR3: 0 | AV3: 0 | AZ3: 0 | BD3: 0 | BH3: 0 | BL3: 15 | BP3: 0 | BT3: 0 | BX3: 0 | BZ3: 4260 | CA3: 101953.9 | CH3: 101953.9 | CM3: 101953.9 | CO3: 101953.9 | CP3: 0.18 | CQ3: 18351.7 | CR3: 120305.6 | CS3: 35.747 | CT3: KMS | CU3: 4300564 | CV3: MD0100003 | CW3: DRUM - 28 X 14 X 23 X 2
A4: ENQ-15423-22-23 | B4: 45733 | C4: FA0300009 | D4: 7 CORE X 2.5 SQ. MM. CU/UNARD ( PVC ) | E4: WOOD | H4: 0 | J4: Copper | K4: 910.79 | L4: 155 | M4: 141172.45 | P4: 0 | T4: 0 | V4: Type C PVC | W4: 93.6 | X4: 91 | Y4: 8517.6 | Z4: POLY TAPE | AA4: 117 | AB4: 4 | AC4: 468 | AD4: PVC Type ST-2 | AE4: 70.87 | AF4: 27 | AG4: 1913.49 | AJ4: 0 | AL4: FR PVC Type ST-2 | AM4: 86.1 | AN4: 117 | AO4: 10073.7 | AR4: 0 | AV4: 0 | AZ4: 0 | BD4: 0 | BH4: 0 | BL4: 0 | BP4: 0 | BT4: 0 | BX4: 0 | BZ4: 5170 | CA4: 167315.24 | CH4: 167315.24 | CM4: 167315.24 | CO4: 167315.24 | CP4: 0.18 | CQ4: 30116.74 | CR4: 197431.98 | CS4: 40.28 | CT4: KMS | CU4: 7952560 | CV4: MD0100005 | CW4: DRUM - 36 X 14 X 23 X 2

Sheet AUTO CALCULATION SHEET (2)
A2: ODISHA POWER TRANSMISSION CORPORATION LTD.
A4: TENDER SPECIFICATION NO () | B4: CPC- 22/2024-25
A5: TENDER DESCRIPTION () | B5: Procurement of supply of Control Cables
A6: Last Date & Time of Submission () | B6: 24.03.2025 (03.00 PM).
A7: REVERSE AUCTION | B7: e-Reverse Auction (RA) will be conducted in e-tender portal of OPTCL on specified date and time, while bidders shall quote from their own offices/places of their choice. Internet connectivity shall be ensured by the respective agencies/bidders themselves.
A8: Price () | B8: The quoted price shall be variable as per IEEMA PVC • IEEMA PV formula shall be made applicable on 95% of taxable value (Discovered in OPTCL tenders/negotiated including freight and insurance) considering 5% towards freight and loading & unloading cost. •There would be ceiling of 20% on positive side and no ceiling on negative side for price variation. However increase beyond 15% can be given in exceptional cases only.
A9: Validity () | B9: Tenderer should quote Price (IEEMA variable) and the offer should be kept valid for a period of 180 days from the date of opening of Tender.
A10: Delivery Period () | B10: Time being the essence of the contract; the equipment shall be supplied within the delivery period, specified in the contract. The Purchaser, however, reserves the right to reschedule the delivery and change the destination if required. The delivery period shall be reckoned from the date of placing the Letter of Intent/Purchase order, as may be specified in LOI/Purchase order. The desired delivery period shall be as indicated at Appendix-II (Quantity & Delivery Schedule) of Section-IV (Technical Specification).
A11: Payment Terms () | B11: 100% taxable value of each consignment with 100% Goods and Services Tax in full as applicable will be paid on receipt of materials in good condition at stores/desired site and verification thereof, subject to furnishing and approval of a). Contract cum Performance Bank Guarantee at the rate of 10% [ten percent] of Taxable Value plus GST thereon [In case successful bidder is a local Micro and small Enterprise (MSEs), based in Odisha & registered with respective DICs, Khadi, Village, Cottage & Handicrafts Industries, OSIC and NSIC, 5% (five percent) in place of 10% (ten percent) will be applicable] b).Guarantee certificate, c).Test certificate by the Purchaser.
A12: Standard length () | B12: The cable shall be supplied in 500metre lengths.
A13: Packing () | B13: The cable shall be wound on strong drums or reels capable of withstanding all normal transportation and handling. Each length of cable shall be durably sealed before shipment to prevent ingress of moisture. The drums, reels or coils shall be lagged or covered with suitable material to provide physical protection for the cable during transit and during storage and handling operations.
A14: Technical Specification
N16: =Sheet1!J1 -> Conductor | S16: AL ALLOY | U16: Insulation Screening (Metallic) | AC16: Insulation Screening (Non-Metallic) | AE16: Insulation | AK16: POLY TAPE | AL16: Inner Sheath | AS16: Armouring | BC16: Outer Sheath | BD16: ATR OUTER | BM16: FILLER | BN16: GREASE | BO16: Water swellable Tape | BP16: Semi conducting Water Swellable tape | BQ16: SEMICON TAPE | BR16: GLASS FIBER TAPE | BS16: COPPER WIRE 0.8 MM | BT16: RUBBERIZED COTTON TAPE | BU16: Water Tight Compound | BZ16: DRUM COST PER KM | CA16: TOTAL RM COST | CB16: EXTRA CONSUMPTION | CC16: EXTRA CONSUMPTION VALUE
A17: DOCKET NO. | B17: =Sheet1!B1 -> Base Date | C17: ITEM CODE | D17: PROPOSE ERP ITEM NAME | E17: EX-WORKS (PER KM) | F17: FREIGHT PER KM | G17: PRICE INCLUDING FREIGHT (PER KM) | H17: GST % | I17: GST VALUE | J17: PRICE INCLUDING GST & FREIGHT (PER KM) | K17: QTY | L17: Unit | M17: TOTAL PRICE OF FULL QTY (INCLUDING FRIGHT & GST) | N17: Alumimium | O17: Alumimium ALLOY | P17: Copper | Q17: Flexible Copper | R17: Galvanized steel wire | S17: Alumimium | T17: Alumimium ALLOY | U17: Coper tape - 0.1 mm | V17: Copper Tape - 0.03 mm | W17: Copper Tape - 0.035 mm | X17: Copper Tape - 0.04 mm | Y17: Copper Tape - 0.045 mm | Z17: Copper Tape - 0.050 mm | AA17: Copper Tape - 0.060 mm | AB17: Copper Tape - 0.075 mm(DOUBLE) | AC17: Extruded semiconductive | AD17: Extruded Semiconductive(Stripable) | AE17: HT-XLPE | AF17: LT-XLPE | AG17: TR XLPE | AH17: Type C PVC | AI17: Type C PVC (HR) | AJ17: XLPE | AK17: POLY TAPE | AL17: FR PVC Type ST-1 | AM17: FR PVC Type ST-2 | AN17: FRLSH PVC Type ST-2 | AO17: PVC Type ST-1 | AP17: PVC Type ST-1-PRESSURE EXTRUDED | AQ17: PVC Type ST-2 | AR17: PVC Type ST-2-PRESSURE EXTRUDED | AS17: ACSR CORE WIRE | AT17: ACSR DOG STEEL WIRE | AU17: Aluminium Flat Strip | AV17: Aluminium Round Wire | AW17: Double Steel Tape | AX17: Galvanised Steel Flat Strip | AY17: Galvanised Steel Flat Strip (Double) | AZ17: Galvanised Steel Flat Strip-B | BA17: Galvanised Steel Round Wire | BB17: Galvanised Steel Round Wire (Double) | BC17: FR PVC Type ST-1 | BD17: FR PVC Type ST-2 | BE17: FRLSH PVC Type ST-1 | BF17: FRLSH PVC Type ST-2 | BG17: PE, ST-3 | BH17: PE, ST-7 | BI17: PVC Type ST-1 | BJ17: PVC Type ST-2 | BK17: PVC Type ST-2-PRESSURE EXTRUDED | BL17: UV & Track Resistant XLPE | BM17: FILLER | BN17: Grease | BO17: Water swellable Tape | BP17: Semi conducting Water Swellable tape | BQ17: SEMICON TAPE | BR17: GLASS FIBER TAPE | BS17: COPPER WIRE 0.8 MM | BT17: RUBBERIZED COTTON TAPE | BU17: Water Tight Compound | BV17: =Sheet1!E1 -> Propose Drum Type | BW17: =Sheet1!CV1 -> DRUM CODE | BX17: =Sheet1!CW1 -> DRUM SIZE (FxbXtx Ft) | BY17: =Sheet1!CX1 -> Party Standard Length(MTR) | CD17: MFG% | CE17: MFG VALUE | CF17: PROF% | CG17: PROFIT VALUE | CH17: 1ST EX-WORKS | CI17: Intt % | CJ17: INTT VALUE | CK17: insp% | CL17: INSP VALUE
N18: =+IFERROR(VLOOKUP($N$17,Sheet1!J:L,2,0),0) -> 0 | O18: =+IFERROR(VLOOKUP($O$17,Sheet1!J:L,2,0),0) -> 0 | P18: 872 | Q18: =+IFERROR(VLOOKUP($Q$17,Sheet1!J:M,2,0),0) -> 0 | R18: =+IFERROR(VLOOKUP($R$17,Sheet1!J:M,2,0),0) -> 0 | S18: =+IFERROR(VLOOKUP($S$17,Sheet1!N:Q,2,0),0) -> 0 | T18: =+IFERROR(VLOOKUP($T$17,Sheet1!N:O,2,0),0) -> 0 | U18: =+IFERROR(VLOOKUP($U$17,Sheet1!F:I,2,0),0) -> 0 | V18: =+IFERROR(VLOOKUP($V$17,Sheet1!F:I,2,0),0) -> 0 | W18: =+IFERROR(VLOOKUP($W$17,Sheet1!F:I,2,0),0) -> 0 | X18: =+IFERROR(VLOOKUP($X$17,Sheet1!F:I,2,0),0) -> 0 | Y18: =+IFERROR(VLOOKUP($Y$17,Sheet1!F:I,2,0),0) -> 0 | Z18: =+IFERROR(VLOOKUP($Z$17,Sheet1!F:I,2,0),0) -> 0 | AA18: =+IFERROR(VLOOKUP($AA$17,Sheet1!F:I,2,0),0) -> 0 | AB18: =+IFERROR(VLOOKUP($AB$17,Sheet1!F:I,2,0),0) -> 0 | AC18: =+IFERROR(VLOOKUP($AC$17,Sheet1!R:U,2,0),0) -> 0 | AD18: =+IFERROR(VLOOKUP($AD$17,Sheet1!R:U,2,0),0) -> 0 | AE18: =+IFERROR(VLOOKUP($AE$17,Sheet1!V:Y,2,0),0) -> 0 | AF18: =+IFERROR(VLOOKUP($AF$17,Sheet1!V:Y,2,0),0) -> 0 | AG18: =+IFERROR(VLOOKUP($AG$17,Sheet1!V:Y,2,0),0) -> 0 | AI18: 103 | AJ18: =+IFERROR(VLOOKUP($AJ$17,Sheet1!V:Y,2,0),0) -> 0 | AK18: 120 | AL18: =+IFERROR(VLOOKUP($AL$17,Sheet1!AD2:AG840,2,0),0) -> 0 | AM18: =+IFERROR(VLOOKUP($AM$17,Sheet1!AD2:AG840,2,0),0) -> 0 | AN18: =+IFERROR(VLOOKUP($AN$17,Sheet1!AD2:AG840,2,0),0) -> 0 | AO18: =+IFERROR(VLOOKUP($AO$17,Sheet1!AD2:AG840,2,0),0) -> 0 | AP18: =+IFERROR(VLOOKUP($AP$17,Sheet1!AD2:AG840,2,0),0) -> 0 | AQ18: 69 | AR18: =+IFERROR(VLOOKUP($AR$17,Sheet1!AD2:AG840,2,0),0) -> 0 | AS18: =+IFERROR(VLOOKUP($AS$17,Sheet1!AH2:AK840,2,0),0) -> 0 | AT18: =+IFERROR(VLOOKUP($AT$17,Sheet1!AH2:AK840,2,0),0) -> 0 | AU18: =+IFERROR(VLOOKUP($AU$17,Sheet1!AH2:AK840,2,0),0) -> 0 | AV18: =+IFERROR(VLOOKUP($AV$17,Sheet1!AH2:AK840,2,0),0) -> 0 | AW18: =+IFERROR(VLOOKUP($AW$17,Sheet1!AH2:AK840,2,0),0) -> 0 | AX18: =+IFERROR(VLOOKUP($AX$17,Sheet1!AH2:AK840,2,0),0) -> 0 | AY18: =+IFERROR(VLOOKUP($AY$17,Sheet1!AH2:AK840,2,0),0) -> 0 | AZ18: =+IFERROR(VLOOKUP($AZ$17,Sheet1!AH2:AK840,2,0),0) -> 0 | BA18: =+IFERROR(VLOOKUP($BA$17,Sheet1!AH2:AK840,2,0),0) -> 0 | BB18: =+IFERROR(VLOOKUP($BB$17,Sheet1!AH2:AK840,2,0),0) -> 0 | BC18: =+IFERROR(VLOOKUP($BC$17,Sheet1!AL2:AO840,2,0),0) -> 0 | BD18: =88+20 -> 108 | BE18: =+IFERROR(VLOOKUP($BE$17,Sheet1!AL2:AO840,2,0),0) -> 0 | BF18: =+IFERROR(VLOOKUP($BF$17,Sheet1!AL2:AO840,2,0),0) -> 0 | BG18: =+IFERROR(VLOOKUP($BG$17,Sheet1!AL2:AO840,2,0),0) -> 0 | BH18: =+IFERROR(VLOOKUP($BH$17,Sheet1!AL2:AO840,2,0),0) -> 0 | BI18: =+IFERROR(VLOOKUP($BI$17,Sheet1!AL2:AO840,2,0),0) -> 0 | BK18: =+IFERROR(VLOOKUP($BK$17,Sheet1!AL2:AO840,2,0),0) -> 0 | BL18: =+IFERROR(VLOOKUP($BL$17,Sheet1!AL2:AO840,2,0),0) -> 0 | BM18: =+IFERROR(VLOOKUP($BM$17,Sheet1!AP2:AS840,2,0),0) -> 0 | BN18: =+IFERROR(VLOOKUP($BN$17,Sheet1!AT2:AW840,2,0),0) -> 0 | BO18: =+IFERROR(VLOOKUP($BO$17,Sheet1!AX2:BA840,2,0),0) -> 0 | BP18: =+IFERROR(VLOOKUP($BP$17,Sheet1!BB2:BE840,2,0),0) -> 0 | BQ18: =+IFERROR(VLOOKUP($BQ$17,Sheet1!BF2:BI840,2,0),0) -> 0 | BR18: =+IFERROR(VLOOKUP($BR$17,Sheet1!BJ2:BM840,2,0),0) -> 0 | BS18: =+IFERROR(VLOOKUP($BS$17,Sheet1!BN2:BQ840,2,0),0) -> 0 | BT18: =+IFERROR(VLOOKUP($BT$17,Sheet1!BR2:BU840,2,0),0) -> 0 | BU18: =+IFERROR(VLOOKUP($BU$17,Sheet1!BV2:BY840,2,0),0) -> 0
A19: =Sheet1!A2 -> ENQ-15423-22-23 | B19: 45691 | C19: =Sheet1!C2 -> FA0300004 | D19: =Sheet1!D2 -> 2 CORE X 2.5 SQ. MM. CU/UNARD.(PVC) | E19: =CH19+CJ19+CL19 -> 76164.637 | F19: =ROUNDUP(M25,0) -> 1263 | G19: =E19+F19 -> 77427.637 | H19: =Sheet1!CP2 -> 0.18 | I19: =G19*H19 -> 13936.975 | J19: =G19+I19 -> 91364.612 | K19: =Sheet1!CS2 -> 19.014 | L19: =Sheet1!CT2 -> KMS | M19: =J19*K19 -> 1737206.7 | N19: =+IFERROR(VLOOKUP($N$17,Sheet1!J2:L2,3,0),0) -> 0 | O19: =+IFERROR(VLOOKUP($O$17,Sheet1!J2:L2,3,0),0) -> 0 | P19: =+IFERROR(VLOOKUP($P$17,Sheet1!J2:M2,3,0),0) -> 44 | Q19: =+IFERROR(VLOOKUP($Q$17,Sheet1!J2:M2,3,0),0) -> 0 | R19: =+IFERROR(VLOOKUP($R$17,Sheet1!J2:M2,3,0),0) -> 0 | S19: =+IFERROR(VLOOKUP($S$17,Sheet1!N2:Q2,3,0),0) -> 0 | T19: =+IFERROR(VLOOKUP($T$17,Sheet1!N2:Q2,3,0),0) -> 0 | U19: =+IFERROR(VLOOKUP($U$17,Sheet1!F2:I2,3,0),0) -> 0 | V19: =+IFERROR(VLOOKUP($V$17,Sheet1!F2:I2,3,0),0) -> 0 | W19: =+IFERROR(VLOOKUP($W$17,Sheet1!F2:I2,3,0),0) -> 0 | X19: =+IFERROR(VLOOKUP($X$17,Sheet1!F2:I2,3,0),0) -> 0 | Y19: =+IFERROR(VLOOKUP($Y$17,Sheet1!F2:I2,3,0),0) -> 0 | Z19: =+IFERROR(VLOOKUP($Z$17,Sheet1!F2:I2,3,0),0) -> 0 | AA19: =+IFERROR(VLOOKUP($AA$17,Sheet1!F2:I2,3,0),0) -> 0 | AB19: =+IFERROR(VLOOKUP($AB$17,Sheet1!F2:I2,3,0),0) -> 0 | AC19: =+IFERROR(VLOOKUP($AC$17,Sheet1!R2:U2,3,0),0) -> 0 | AD19: =+IFERROR(VLOOKUP($AD$17,Sheet1!R2:U2,2,0),0) -> 0 | AE19: =+IFERROR(VLOOKUP($AE$17,Sheet1!V2:Y2,3,0),0) -> 0 | AF19: =+IFERROR(VLOOKUP($AF$17,Sheet1!V2:Y2,3,0),0) -> 0 | AG19: =+IFERROR(VLOOKUP($AG$17,Sheet1!V2:Y2,3,0),0) -> 0 | AH19: =+IFERROR(VLOOKUP($AH$17,Sheet1!V2:Y2,3,0),0) -> 0 | AI19: =+IFERROR(VLOOKUP($AI$17,Sheet1!V2:Y2,3,0),0) -> 26 | AJ19: =+IFERROR(VLOOKUP($AJ$17,Sheet1!V2:Y2,3,0),0) -> 0 | AK19: =+IFERROR(VLOOKUP($AK$17,Sheet1!Z2:AB2,3,0),0) -> 3 | AL19: =+IFERROR(VLOOKUP($AL$17,Sheet1!AD2:AG2,3,0),0) -> 0 | AM19: =+IFERROR(VLOOKUP($AM$17,Sheet1!AD2:AG2,3,0),0) -> 0 | AN19: =+IFERROR(VLOOKUP($AN$17,Sheet1!AD2:AG2,3,0),0) -> 0 | AO19: =+IFERROR(VLOOKUP($AO$17,Sheet1!AD2:AG2,3,0),0) -> 0 | AP19: =+IFERROR(VLOOKUP($AP$17,Sheet1!AD2:AG2,3,0),0) -> 0 | AQ19: =+IFERROR(VLOOKUP($AQ$17,Sheet1!AD2:AG2,3,0),0) -> 39 | AR19: =+IFERROR(VLOOKUP($AR$17,Sheet1!AD2:AG2,3,0),0) -> 0 | AS19: =+IFERROR(VLOOKUP($AS$17,Sheet1!AH2:AK2,3,0),0) -> 0 | AT19: =+IFERROR(VLOOKUP($AT$17,Sheet1!AH2:AK2,3,0),0) -> 0 | AU19: =+IFERROR(VLOOKUP($AU$17,Sheet1!AH2:AK2,3,0),0) -> 0 | AV19: =+IFERROR(VLOOKUP($AV$17,Sheet1!AH2:AK2,3,0),0) -> 0 | AW19: =+IFERROR(VLOOKUP($AW$17,Sheet1!AH2:AK2,3,0),0) -> 0 | AX19: =+IFERROR(VLOOKUP($AX$17,Sheet1!AH2:AK2,3,0),0) -> 0 | AY19: =+IFERROR(VLOOKUP($AY$17,Sheet1!AH2:AK2,3,0),0) -> 0 | AZ19: =+IFERROR(VLOOKUP($AZ$17,Sheet1!AH2:AK2,3,0),0) -> 0 | BA19: =+IFERROR(VLOOKUP($BA$17,Sheet1!AH2:AK2,3,0),0) -> 0 | BB19: =+IFERROR(VLOOKUP($BB$17,Sheet1!AH2:AK2,3,0),0) -> 0 | BC19: =+IFERROR(VLOOKUP($BC$17,Sheet1!AL2:AO2,3,0),0) -> 0 | BD19: 100 | BE19: =+IFERROR(VLOOKUP($BE$17,Sheet1!AL2:AO2,3,0),0) -> 0 | BF19: =+IFERROR(VLOOKUP($BF$17,Sheet1!AL2:AO2,3,0),0) -> 0 | BG19: =+IFERROR(VLOOKUP($BG$17,Sheet1!AL2:AO2,3,0),0) -> 0 | BH19: =+IFERROR(VLOOKUP($BH$17,Sheet1!AL2:AO2,3,0),0) -> 0 | BI19: =+IFERROR(VLOOKUP($BI$17,Sheet1!AL2:AO2,3,0),0) -> 0 | BJ19: 0 | BK19: =+IFERROR(VLOOKUP($BK$17,Sheet1!AL2:AO2,3,0),0) -> 0 | BL19: =+IFERROR(VLOOKUP($BL$17,Sheet1!AL2:AO2,3,0),0) -> 0 | BM19: =+IFERROR(VLOOKUP($BM$17,Sheet1!AP2:AS2,3,0),0) -> 0 | BN19: =+IFERROR(VLOOKUP($BN$17,Sheet1!AT2:AW2,3,0),0) -> 0 | BO19: =+IFERROR(VLOOKUP($BO$17,Sheet1!AX2:BA2,3,0),0) -> 0 | BP19: =+IFERROR(VLOOKUP($BP$17,Sheet1!BB2:BE2,3,0),0) -> 0 | BQ19: =+IFERROR(VLOOKUP($BQ$17,Sheet1!BF2:BI2,3,0),0) -> 0 | BR19: =+IFERROR(VLOOKUP($BR$17,Sheet1!BJ2:BM2,3,0),0) -> 0 | BS19: =+IFERROR(VLOOKUP($BS$17,Sheet1!BN2:BQ2,3,0),0) -> 0 | BT19: =+IFERROR(VLOOKUP($BT$17,Sheet1!BR2:BU2,3,0),0) -> 0 | BU19: =+IFERROR(VLOOKUP($BU$17,Sheet1!BV2:BY2,3,0),0) -> 0 | BV19: =Sheet1!E2 -> WOOD | BW19: =Sheet1!CV2 -> MD0100003 | BX19: =Sheet1!CW2 -> DRUM - 28 X 14 X 23 X 2 | BY19: 500 | BZ19: =Sheet1!BZ2 -> 4260 | CA19: =SUMPRODUCT($N$18:$BU$18,N19:BU19)+BZ19 -> 59157 | CB19: =Sheet1!CB2 -> 0 | CC19: =CA19*CB19 -> 0 | CD19: 0.25 | CE19: =CA19*CD19 -> 14789.25 | CF19: 0 | CG19: =CA19*CF19 -> 0 | CH19: =CA19+CC19+CE19+CG19 -> 73946.25 | CI19: 0.02 | CJ19: =CH19*CI19 -> 1478.925 | CK19: 0.01 | CL19: =CH19*CK19 -> 739.4625
A20: =Sheet1!A3 -> ENQ-15423-22-23 | B20: 45691 | C20: =Sheet1!C3 -> FA0300006 | D20: =Sheet1!D3 -> 4 CORE X 2.5 SQ. MM. CU/UNARD.(PVC) | E20: =CH20+CJ20+CL20 -> 130473.96 | F20: =ROUNDUP(M26,0) -> 1343 | G20: =E20+F20 -> 131816.96 | H20: =Sheet1!CP3 -> 0.18 | I20: =G20*H20 -> 23727.053 | J20: =G20+I20 -> 155544.02 | K20: =Sheet1!CS3 -> 35.747 | L20: =Sheet1!CT3 -> KMS | M20: =J20*K20 -> 5560231.9 | N20: =+IFERROR(VLOOKUP($N$17,Sheet1!J3:L3,3,0),0) -> 0 | O20: =+IFERROR(VLOOKUP($O$17,Sheet1!J3:L3,3,0),0) -> 0 | P20: =+IFERROR(VLOOKUP($P$17,Sheet1!J3:M3,3,0),0) -> 89 | Q20: =+IFERROR(VLOOKUP($Q$17,Sheet1!J3:M3,3,0),0) -> 0 | R20: =+IFERROR(VLOOKUP($R$17,Sheet1!J3:M3,3,0),0) -> 0 | S20: =+IFERROR(VLOOKUP($S$17,Sheet1!N3:Q3,3,0),0) -> 0 | T20: =+IFERROR(VLOOKUP($T$17,Sheet1!N3:Q3,3,0),0) -> 0 | U20: =+IFERROR(VLOOKUP($U$17,Sheet1!F3:I3,3,0),0) -> 0 | V20: =+IFERROR(VLOOKUP($V$17,Sheet1!F3:I3,3,0),0) -> 0 | W20: =+IFERROR(VLOOKUP($W$17,Sheet1!F3:I3,3,0),0) -> 0 | X20: =+IFERROR(VLOOKUP($X$17,Sheet1!F3:I3,3,0),0) -> 0 | Y20: =+IFERROR(VLOOKUP($Y$17,Sheet1!F3:I3,3,0),0) -> 0 | Z20: =+IFERROR(VLOOKUP($Z$17,Sheet1!F3:I3,3,0),0) -> 0 | AA20: =+IFERROR(VLOOKUP($AA$17,Sheet1!F3:I3,3,0),0) -> 0 | AB20: =+IFERROR(VLOOKUP($AB$17,Sheet1!F3:I3,3,0),0) -> 0 | AC20: =+IFERROR(VLOOKUP($AC$17,Sheet1!R3:U3,3,0),0) -> 0 | AD20: =+IFERROR(VLOOKUP($AD$17,Sheet1!R3:U3,2,0),0) -> 0 | AE20: =+IFERROR(VLOOKUP($AE$17,Sheet1!V3:Y3,3,0),0) -> 0 | AF20: =+IFERROR(VLOOKUP($AF$17,Sheet1!V3:Y3,3,0),0) -> 0 | AG20: =+IFERROR(VLOOKUP($AG$17,Sheet1!V3:Y3,3,0),0) -> 0 | AI20: 52 | AJ20: =+IFERROR(VLOOKUP($AJ$17,Sheet1!V3:Y3,3,0),0) -> 0 | AK20: =+IFERROR(VLOOKUP($AK$17,Sheet1!Z3:AB3,3,0),0) -> 4 | AL20: =+IFERROR(VLOOKUP($AL$17,Sheet1!AD3:AG3,3,0),0) -> 0 | AM20: =+IFERROR(VLOOKUP($AM$17,Sheet1!AD3:AG3,3,0),0) -> 0 | AN20: =+IFERROR(VLOOKUP($AN$17,Sheet1!AD3:AG3,3,0),0) -> 0 | AO20: =+IFERROR(VLOOKUP($AO$17,Sheet1!AD3:AG3,3,0),0) -> 0 | AP20: =+IFERROR(VLOOKUP($AP$17,Sheet1!AD3:AG3,3,0),0) -> 0 | AQ20: =+IFERROR(VLOOKUP($AQ$17,Sheet1!AD3:AG3,3,0),0) -> 27 | AR20: =+IFERROR(VLOOKUP($AR$17,Sheet1!AD3:AG3,3,0),0) -> 0 | AS20: =+IFERROR(VLOOKUP($AS$17,Sheet1!AH3:AK3,3,0),0) -> 0 | AT20: =+IFERROR(VLOOKUP($AT$17,Sheet1!AH3:AK3,3,0),0) -> 0 | AU20: =+IFERROR(VLOOKUP($AU$17,Sheet1!AH3:AK3,3,0),0) -> 0 | AV20: =+IFERROR(VLOOKUP($AV$17,Sheet1!AH3:AK3,3,0),0) -> 0 | AW20: =+IFERROR(VLOOKUP($AW$17,Sheet1!AH3:AK3,3,0),0) -> 0 | AX20: =+IFERROR(VLOOKUP($AX$17,Sheet1!AH3:AK3,3,0),0) -> 0 | AY20: =+IFERROR(VLOOKUP($AY$17,Sheet1!AH3:AK3,3,0),0) -> 0 | AZ20: =+IFERROR(VLOOKUP($AZ$17,Sheet1!AH3:AK3,3,0),0) -> 0 | BA20: =+IFERROR(VLOOKUP($BA$17,Sheet1!AH3:AK3,3,0),0) -> 0 | BB20: =+IFERROR(VLOOKUP($BB$17,Sheet1!AH3:AK3,3,0),0) -> 0 | BC20: =+IFERROR(VLOOKUP($BC$17,Sheet1!AL3:AO3,3,0),0) -> 0 | BD20: =+IFERROR(VLOOKUP($BD$17,Sheet1!AL3:AO3,3,0),0) -> 109 | BE20: =+IFERROR(VLOOKUP($BE$17,Sheet1!AL3:AO3,3,0),0) -> 0 | BF20: =+IFERROR(VLOOKUP($BF$17,Sheet1!AL3:AO3,3,0),0) -> 0 | BG20: =+IFERROR(VLOOKUP($BG$17,Sheet1!AL3:AO3,3,0),0) -> 0 | BH20: =+IFERROR(VLOOKUP($BH$17,Sheet1!AL3:AO3,3,0),0) -> 0 | BI20: =+IFERROR(VLOOKUP($BI$17,Sheet1!AL3:AO3,3,0),0) -> 0 | BJ20: =+IFERROR(VLOOKUP($BJ$17,Sheet1!AL3:AO3,3,0),0) -> 0 | BK20: =+IFERROR(VLOOKUP($BK$17,Sheet1!AL3:AO3,3,0),0) -> 0 | BL20: =+IFERROR(VLOOKUP($BL$17,Sheet1!AL3:AO3,3,0),0) -> 0 | BM20: =+IFERROR(VLOOKUP($BM$17,Sheet1!AP3:AS3,3,0),0) -> 0 | BN20: =+IFERROR(VLOOKUP($BN$17,Sheet1!AT3:AW3,3,0),0) -> 0 | BO20: =+IFERROR(VLOOKUP($BO$17,Sheet1!AX3:BA3,3,0),0) -> 0 | BP20: =+IFERROR(VLOOKUP($BP$17,Sheet1!BB3:BE3,3,0),0) -> 0 | BQ20: =+IFERROR(VLOOKUP($BQ$17,Sheet1!BF3:BI3,3,0),0) -> 0 | BR20: =+IFERROR(VLOOKUP($BR$17,Sheet1!BJ3:BM3,3,0),0) -> 0 | BS20: =+IFERROR(VLOOKUP($BS$17,Sheet1!BN3:BQ3,3,0),0) -> 0 | BT20: =+IFERROR(VLOOKUP($BT$17,Sheet1!BR3:BU3,3,0),0) -> 0 | BU20: =+IFERROR(VLOOKUP($BU$17,Sheet1!BV3:BY3,3,0),0) -> 0 | BV20: =Sheet1!E3 -> WOOD | BW20: =Sheet1!CV3 -> MD0100003 | BX20: =Sheet1!CW3 -> DRUM - 28 X 14 X 23 X 2 | BY20: 500 | BZ20: =Sheet1!BZ3 -> 4260 | CA20: =SUMPRODUCT($N$18:$BU$18,N20:BU20)+BZ20 -> 101339 | CB20: =Sheet1!CB3 -> 0 | CC20: =CA20*CB20 -> 0 | CD20: 0.25 | CE20: =CA20*CD20 -> 25334.75 | CF20: 0 | CG20: =CA20*CF20 -> 0 | CH20: =CA20+CC20+CE20+CG20 -> 126673.75 | CI20: 0.02 | CJ20: =CH20*CI20 -> 2533.475 | CK20: 0.01 | CL20: =CH20*CK20 -> 1266.7375
A21: =Sheet1!A4 -> ENQ-15423-22-23 | B21: 45691 | C21: =Sheet1!C4 -> FA0300009 | D21: =Sheet1!D4 -> 7 CORE X 2.5 SQ. MM. CU/UNARD ( PVC ) | E21: =CH21+CJ21+CL21 -> 212028.07 | F21: =ROUNDUP(M27,0) -> 1788 | G21: =E21+F21 -> 213816.07 | H21: =Sheet1!CP4 -> 0.18 | I21: =G21*H21 -> 38486.893 | J21: =G21+I21 -> 252302.97 | K21: =Sheet1!CS4 -> 40.28 | L21: =Sheet1!CT4 -> KMS | M21: =J21*K21 -> 10162764 | N21: =+IFERROR(VLOOKUP($N$17,Sheet1!J4:L4,3,0),0) -> 0 | O21: =+IFERROR(VLOOKUP($O$17,Sheet1!J4:L4,3,0),0) -> 0 | P21: =+IFERROR(VLOOKUP($P$17,Sheet1!J4:M4,3,0),0) -> 155 | Q21: =+IFERROR(VLOOKUP($Q$17,Sheet1!J4:M4,3,0),0) -> 0 | R21: =+IFERROR(VLOOKUP($R$17,Sheet1!J4:M4,3,0),0) -> 0 | S21: =+IFERROR(VLOOKUP($S$17,Sheet1!N4:Q4,3,0),0) -> 0 | T21: =+IFERROR(VLOOKUP($T$17,Sheet1!N4:Q4,3,0),0) -> 0 | U21: =+IFERROR(VLOOKUP($U$17,Sheet1!F4:I4,3,0),0) -> 0 | V21: =+IFERROR(VLOOKUP($V$17,Sheet1!F4:I4,3,0),0) -> 0 | W21: =+IFERROR(VLOOKUP($W$17,Sheet1!F4:I4,3,0),0) -> 0 | X21: =+IFERROR(VLOOKUP($X$17,Sheet1!F4:I4,3,0),0) -> 0 | Y21: =+IFERROR(VLOOKUP($Y$17,Sheet1!F4:I4,3,0),0) -> 0 | Z21: =+IFERROR(VLOOKUP($Z$17,Sheet1!F4:I4,3,0),0) -> 0 | AA21: =+IFERROR(VLOOKUP($AA$17,Sheet1!F4:I4,3,0),0) -> 0 | AB21: =+IFERROR(VLOOKUP($AB$17,Sheet1!F4:I4,3,0),0) -> 0 | AC21: =+IFERROR(VLOOKUP($AC$17,Sheet1!R4:U4,3,0),0) -> 0 | AD21: =+IFERROR(VLOOKUP($AD$17,Sheet1!R4:U4,2,0),0) -> 0 | AE21: =+IFERROR(VLOOKUP($AE$17,Sheet1!V4:Y4,3,0),0) -> 0 | AF21: =+IFERROR(VLOOKUP($AF$17,Sheet1!V4:Y4,3,0),0) -> 0 | AG21: =+IFERROR(VLOOKUP($AG$17,Sheet1!V4:Y4,3,0),0) -> 0 | AI21: 91 | AJ21: =+IFERROR(VLOOKUP($AJ$17,Sheet1!V4:Y4,3,0),0) -> 0 | AK21: =+IFERROR(VLOOKUP($AK$17,Sheet1!Z4:AB4,3,0),0) -> 4 | AL21: =+IFERROR(VLOOKUP($AL$17,Sheet1!AD4:AG4,3,0),0) -> 0 | AM21: =+IFERROR(VLOOKUP($AM$17,Sheet1!AD4:AG4,3,0),0) -> 0 | AN21: =+IFERROR(VLOOKUP($AN$17,Sheet1!AD4:AG4,3,0),0) -> 0 | AO21: =+IFERROR(VLOOKUP($AO$17,Sheet1!AD4:AG4,3,0),0) -> 0 | AP21: =+IFERROR(VLOOKUP($AP$17,Sheet1!AD4:AG4,3,0),0) -> 0 | AQ21: =+IFERROR(VLOOKUP($AQ$17,Sheet1!AD4:AG4,3,0),0) -> 27 | AR21: =+IFERROR(VLOOKUP($AR$17,Sheet1!AD4:AG4,3,0),0) -> 0 | AS21: =+IFERROR(VLOOKUP($AS$17,Sheet1!AH4:AK4,3,0),0) -> 0 | AT21: =+IFERROR(VLOOKUP($AT$17,Sheet1!AH4:AK4,3,0),0) -> 0 | AU21: =+IFERROR(VLOOKUP($AU$17,Sheet1!AH4:AK4,3,0),0) -> 0 | AV21: =+IFERROR(VLOOKUP($AV$17,Sheet1!AH4:AK4,3,0),0) -> 0 | AW21: =+IFERROR(VLOOKUP($AW$17,Sheet1!AH4:AK4,3,0),0) -> 0 | AX21: =+IFERROR(VLOOKUP($AX$17,Sheet1!AH4:AK4,3,0),0) -> 0 | AY21: =+IFERROR(VLOOKUP($AY$17,Sheet1!AH4:AK4,3,0),0) -> 0 | AZ21: =+IFERROR(VLOOKUP($AZ$17,Sheet1!AH4:AK4,3,0),0) -> 0 | BA21: =+IFERROR(VLOOKUP($BA$17,Sheet1!AH4:AK4,3,0),0) -> 0 | BB21: =+IFERROR(VLOOKUP($BB$17,Sheet1!AH4:AK4,3,0),0) -> 0 | BC21: =+IFERROR(VLOOKUP($BC$17,Sheet1!AL4:AO4,3,0),0) -> 0 | BD21: =+IFERROR(VLOOKUP($BD$17,Sheet1!AL4:AO4,3,0),0) -> 117 | BE21: =+IFERROR(VLOOKUP($BE$17,Sheet1!AL4:AO4,3,0),0) -> 0 | BF21: =+IFERROR(VLOOKUP($BF$17,Sheet1!AL4:AO4,3,0),0) -> 0 | BG21: =+IFERROR(VLOOKUP($BG$17,Sheet1!AL4:AO4,3,0),0) -> 0 | BH21: =+IFERROR(VLOOKUP($BH$17,Sheet1!AL4:AO4,3,0),0) -> 0 | BI21: =+IFERROR(VLOOKUP($BI$17,Sheet1!AL4:AO4,3,0),0) -> 0 | BJ21: =+IFERROR(VLOOKUP($BJ$17,Sheet1!AL4:AO4,3,0),0) -> 0 | BK21: =+IFERROR(VLOOKUP($BK$17,Sheet1!AL4:AO4,3,0),0) -> 0 | BL21: =+IFERROR(VLOOKUP($BL$17,Sheet1!AL4:AO4,3,0),0) -> 0 | BM21: =+IFERROR(VLOOKUP($BM$17,Sheet1!AP4:AS4,3,0),0) -> 0 | BN21: =+IFERROR(VLOOKUP($BN$17,Sheet1!AT4:AW4,3,0),0) -> 0 | BO21: =+IFERROR(VLOOKUP($BO$17,Sheet1!AX4:BA4,3,0),0) -> 0 | BP21: =+IFERROR(VLOOKUP($BP$17,Sheet1!BB4:BE4,3,0),0) -> 0 | BQ21: =+IFERROR(VLOOKUP($BQ$17,Sheet1!BF4:BI4,3,0),0) -> 0 | BR21: =+IFERROR(VLOOKUP($BR$17,Sheet1!BJ4:BM4,3,0),0) -> 0 | BS21: =+IFERROR(VLOOKUP($BS$17,Sheet1!BN4:BQ4,3,0),0) -> 0 | BT21: =+IFERROR(VLOOKUP($BT$17,Sheet1!BR4:BU4,3,0),0) -> 0 | BU21: =+IFERROR(VLOOKUP($BU$17,Sheet1!BV4:BY4,3,0),0) -> 0 | BV21: =Sheet1!E4 -> WOOD | BW21: =Sheet1!CV4 -> MD0100005 | BX21: =Sheet1!CW4 -> DRUM - 36 X 14 X 23 X 2 | BY21: 500 | BZ21: =Sheet1!BZ4 -> 5170 | CA21: =SUMPRODUCT($N$18:$BU$18,N21:BU21)+BZ21 -> 164682 | CB21: =Sheet1!CB4 -> 0 | CC21: =CA21*CB21 -> 0 | CD21: 0.25 | CE21: =CA21*CD21 -> 41170.5 | CF21: 0 | CG21: =CA21*CF21 -> 0 | CH21: =CA21+CC21+CE21+CG21 -> 205852.5 | CI21: 0.02 | CJ21: =CH21*CI21 -> 4117.05 | CK21: 0.01 | CL21: =CH21*CK21 -> 2058.525
M22: =SUM(M19:M21) -> 17460202
E24: Order Quantity | F24: Stnd Length | G24: Truck type | H24: Fare of one truck | I24: No of Drum in one truck | J24: Total length in one Truck | K24: No of Truck | L24: Total Freight | M24: Freight per KM | AI24: CABLE WEIGHT KG/KM | AK24: DRUM WEIGHT | AQ24: CABLE+DRUM WEIGHT | BD24: TRUCK WEIGHT
D25: =D19 -> 2 CORE X 2.5 SQ. MM. CU/UNARD.(PVC) | E25: =K19 -> 19.014 | F25: =BY19/1000 -> 0.5 | G25: 16 MT | H25: 24000 | I25: 48 | J25: =F25*I25 -> 24 | K25: =ROUNDUP((E25/J25),0) -> 1 | L25: =M25*E25 -> 24000 | M25: =(H25*K25)/E25 -> 1262.2278 | AI25: =SUM(P19:BD19) -> 212 | AK25: =60+15 -> 75 | AQ25: =((F25*AI25)+AK25) -> 181 | BD25: =AQ25*I25 -> 8688
D26: =D20 -> 4 CORE X 2.5 SQ. MM. CU/UNARD.(PVC) | E26: =K20 -> 35.747 | F26: =BY20/1000 -> 0.5 | G26: 16 MT | H26: 24000 | I26: 48 | J26: =F26*I26 -> 24 | K26: =ROUNDUP((E26/J26),0) -> 2 | L26: =M26*E26 -> 48000 | M26: =(H26*K26)/E26 -> 1342.77 | AI26: =SUM(P20:BD20) -> 281 | AK26: =60+15 -> 75 | AQ26: =((F26*AI26)+AK26) -> 215.5 | BD26: =AQ26*I26 -> 10344
D27: =D21 -> 7 CORE X 2.5 SQ. MM. CU/UNARD ( PVC ) | E27: =K21 -> 40.28 | F27: =BY21/1000 -> 0.5 | G27: 16 MT | H27: 24000 | I27: 36 | J27: =F27*I27 -> 18 | K27: =ROUNDUP((E27/J27),0) -> 3 | L27: =M27*E27 -> 72000 | M27: =(H27*K27)/E27 -> 1787.4876 | AI27: =SUM(P21:BD21) -> 394 | AK27: =65+20 -> 85 | AQ27: =((F27*AI27)+AK27) -> 282 | BD27: =AQ27*I27 -> 10152
E29: ESTIMATED COST | F29: OUR COST | G29: DIFF % FROM OUR COST
E30: 17545009 | F30: =M22 -> 17460202 | G30: =((F30-E30)/F30)*100 -> -0.48571671 | H30: INCLUDING GST
E31: 17545009 | F31: =SUMPRODUCT(G19:G21,K19:K21) -> 14796782 | G31: =((F31-E31)/F31)*100 -> -18.573146 | H31: EXCLUDING GST

Sheet Cable
A1: ODISHA POWER TRANSMISSION CORPORATION LTD.
A3: Base Date | B3: 45691
A4: PV TERMS | B4: •IEEMA PV formula shall be made applicable on 95% of taxable value (Discovered in OPTCL tenders/negotiated including freight and insurance) considering 5% towards freight and loading & unloading •There would be ceiling of 20% on positive side and no ceiling on negative side for price variation. However increase beyond 15% can be given in exceptional cases only.
A6: PV FORMULA | B6: P= P0 + CuF (Cu - Cu0) + CCFCu (CC – CC0) + FeF(Fe-Fe0)
A7: For unarmoued control cables FeF = 0
A9: Item | B9: Calculation part | C9: Date of Inspection | D9: Applicable Date | H9: BASE DATE | L9: FACTORS | O9: Ex-Work Po | P9: PVC of Cu | Q9: PVC of PVC | R9: PVC of FE | S9: PV/PKM | T9: CELLING | U9: Billing Price/PKM | V9: VALUE ADDITION CALCULATION
D10: Date | E10: Cu | F10: PVC | G10: Fe | H10: Date | I10: Cuo | J10: PVCo | K10: Feo
L11: CuF | M11: CCFCu | N11: FeF | V11: ='AUTO CALCULATION SHEET (2)'!P17 -> Copper | W11: ='AUTO CALCULATION SHEET (2)'!AI17 -> Type C PVC (HR) | X11: ='AUTO CALCULATION SHEET (2)'!AK17 -> POLY TAPE | Y11: ='AUTO CALCULATION SHEET (2)'!AQ17 -> PVC Type ST-2 | Z11: ATR - FR PVC Type ST-2 | AA11: RMC | AB11: Drum | AC11: RMC+Drum | AD11: VA | AE11: Gross VA% | AF11: Mfg % | AG11: Int % | AH11: Ins% | AI11: Net VA
T12: 0.2 | V12: 907 | W12: 102 | X12: 117 | Y12: 71 | Z12: =86+20 -> 106
A13: ='AUTO CALCULATION SHEET (2)'!D19 -> 2 CORE X 2.5 SQ. MM. CU/UNARD.(PVC) | C13: Provisional | D13: 45733 | E13: 871736.9 | F13: 158825 | H13: =$B$3 -> 45691 | I13: 879199 | J13: 158825 | L13: 0.047 | M13: 0.125 | O13: ='AUTO CALCULATION SHEET (2)'!E19 -> 76164.637 | P13: =(L13*(E13-I13)) -> -350.7187 | Q13: =(M13*(F13-J13)) -> 0 | R13: =(N13*(G13-K13)) -> 0 | S13: =P13+Q13+R13 -> -350.7187 | T13: =O13*$T$12 -> 15232.927 | U13: =IF(S13>T13,O13+T13,O13+S13) -> 75813.919 | V13: ='AUTO CALCULATION SHEET (2)'!P19 -> 44 | W13: ='AUTO CALCULATION SHEET (2)'!AI19 -> 26 | X13: ='AUTO CALCULATION SHEET (2)'!AK19 -> 3 | Y13: ='AUTO CALCULATION SHEET (2)'!AQ19 -> 39 | Z13: ='AUTO CALCULATION SHEET (2)'!BD19 -> 100 | AA13: =SUMPRODUCT(V13:Z13,$V$12:$Z$12) -> 56280 | AB13: ='AUTO CALCULATION SHEET (2)'!BZ19 -> 4260 | AC13: =AA13+AB13 -> 60540 | AD13: =U13-AC13 -> 15273.919 | AE13: =ROUND((AD13/AC13)*100,2) -> 25.23 | AF13: 0 | AG13: 2 | AH13: 1 | AI13: =AE13-AF13-AG13-AH13 -> 22.23
A14: ='AUTO CALCULATION SHEET (2)'!D20 -> 4 CORE X 2.5 SQ. MM. CU/UNARD.(PVC) | C14: Provisional | D14: 45733 | E14: 871736.9 | F14: 158825 | H14: =$B$3 -> 45691 | I14: 879199 | J14: 158825 | L14: 0.094 | M14: 0.161 | O14: ='AUTO CALCULATION SHEET (2)'!E20 -> 130473.96 | P14: =(L14*(E14-I14)) -> -701.4374 | Q14: =(M14*(F14-J14)) -> 0 | R14: =(N14*(G14-K14)) -> 0 | S14: =P14+Q14+R14 -> -701.4374 | T14: =O14*$T$12 -> 26094.793 | U14: =IF(S14>T14,O14+T14,O14+S14) -> 129772.53 | V14: ='AUTO CALCULATION SHEET (2)'!P20 -> 89 | W14: ='AUTO CALCULATION SHEET (2)'!AI20 -> 52 | X14: ='AUTO CALCULATION SHEET (2)'!AK20 -> 4 | Y14: ='AUTO CALCULATION SHEET (2)'!AQ20 -> 27 | Z14: ='AUTO CALCULATION SHEET (2)'!BD20 -> 109 | AA14: =SUMPRODUCT(V14:Z14,$V$12:$Z$12) -> 99966 | AB14: ='AUTO CALCULATION SHEET (2)'!BZ20 -> 4260 | AC14: =AA14+AB14 -> 104226 | AD14: =U14-AC14 -> 25546.525 | AE14: =ROUND((AD14/AC14)*100,2) -> 24.51 | AF14: 0 | AG14: 2 | AH14: 1 | AI14: =AE14-AF14-AG14-AH14 -> 21.51
A15: ='AUTO CALCULATION SHEET (2)'!D21 -> 7 CORE X 2.5 SQ. MM. CU/UNARD ( PVC ) | C15: Provisional | D15: 45733 | E15: 871736.9 | F15: 158825 | H15: =$B$3 -> 45691 | I15: 879199 | J15: 158825 | L15: 0.164 | M15: 0.234 | O15: ='AUTO CALCULATION SHEET (2)'!E21 -> 212028.07 | P15: =(L15*(E15-I15)) -> -1223.7844 | Q15: =(M15*(F15-J15)) -> 0 | R15: =(N15*(G15-K15)) -> 0 | S15: =P15+Q15+R15 -> -1223.7844 | T15: =O15*$T$12 -> 42405.615 | U15: =IF(S15>T15,O15+T15,O15+S15) -> 210804.29 | V15: ='AUTO CALCULATION SHEET (2)'!P21 -> 155 | W15: ='AUTO CALCULATION SHEET (2)'!AI21 -> 91 | X15: ='AUTO CALCULATION SHEET (2)'!AK21 -> 4 | Y15: ='AUTO CALCULATION SHEET (2)'!AQ21 -> 27 | Z15: ='AUTO CALCULATION SHEET (2)'!BD21 -> 117 | AA15: =SUMPRODUCT(V15:Z15,$V$12:$Z$12) -> 164654 | AB15: ='AUTO CALCULATION SHEET (2)'!BZ21 -> 5170 | AC15: =AA15+AB15 -> 169824 | AD15: =U15-AC15 -> 40980.291 | AE15: =ROUND((AD15/AC15)*100,2) -> 24.13 | AF15: 0 | AG15: 2 | AH15: 1 | AI15: =AE15-AF15-AG15-AH15 -> 21.13
