Workbook

Sheet Sheet1
A1: DOCKET NO. | B1: Base Date | C1: ITEM CODE | D1: PROPOSE ERP ITEM NAME | E1: PROPOSE DRUM TYPE | F1: Insulation Screening (Metallic) | G1: RM RATE (Insulation Screening (Metallic)) | H1: Weight (Insulation Screening (Metallic)) | I1: COST(Insulation Screening (Metallic)) | J1: Conductor | K1: RM RATE(Conductor) | L1: WEIGHT(Conductor) | M1: COST(Conductor) | N1: AL ALLOY | O1: RM RATE(Alu Alloy) | P1: WEIGHT(Alu Alloy) | Q1: COST(Alu Alloy) | R1: Insulation Screening (Non-Metallic) | S1: RM RATE(Insulation Screening (Non-Metallic)) | T1: WEIGHT(Insulation Screening (Non-Metallic)) | U1: COST(Insulation Screening (Non-Metallic)) | V1: Insulation | W1: RM RATE(Insulation) | X1: WEIGHT(Insulation) | Y1: COST(Insulation) | Z1: POLY TAPE | AA1: RM RATE (Poly Tape) | AB1: WEIGHT (Poly Tape) | AC1: COST(Poly Tape) | AD1: Inner Sheath | AE1: RM RATE(Inner Sheath) | AF1: WEIGHT(Inner Sheath) | AG1: COST(Inner Sheath) | AH1: Armouring | AI1: RM RATE(Armouring) | AJ1: WEIGHT(Armouring) | AK1: COST(Armouring) | AL1: Outer Sheath | AM1: RM RATE(Outer Sheath) | AN1: WEIGHT(Outer Sheath) | AO1: COST(Outer Sheath) | AP1: FILLER | AQ1: RM RATE(Filler) | AR1: WEIGHT(Filler) | AS1: COST(Filler) | AT1: GREASE | AU1: RM RATE(Grease) | AV1: WEIGHT(Grease) | AW1: COST(Grease) | AX1: Water swellable Tape | AY1: RM RATE(Water swellable Tape) | AZ1: WEIGHT(Water swellable Tape) | BA1: COST(Water swellable Tape) | BB1: Semi conducting Water Swellable tape | BC1: RM RATE(Semi conducting Water Swellable tape) | BD1: WEIGHT(Semi conducting Water Swellable tape) | BE1: COST(Semi conducting Water Swellable tape) | BF1: SEMICON TAPE | BG1: RM RATE(SEMICON TAPE) | BH1: WEIGHT(SEMICON TAPE) | BI1: COST(SEMICON TAPE) | BJ1: GLASS FIBER TAPE | BK1: RM RATE(GLASS FIBER TAPE) | BL1: WEIGHT(GLASS FIBER TAPE) | BM1: COST(GLASS FIBER TAPE) | BN1: COPPER WIRE 0.8 MM | BO1: RM RATE(COPPER WIRE 0.8 MM) | BP1: WEIGHT(COPPER WIRE 0.8 MM) | BQ1: COST(COPPER WIRE 0.8 MM) | BR1: RUBBERIZED COTTON TAPE | BS1: RM RATE(RUBBERIZED COTTON TAPE) | BT1: WEIGHT(RUBBERIZED COTTON TAPE) | BU1: COST(RUBBERIZED COTTON TAPE) | BV1: Water Tight Compound | BW1: RM RATE(Water Tight Compound) | BX1: WEIGHT(Water Tight Compound) | BY1: COST(Water Tight Compound) | BZ1: DRUM COST PER KM | CA1: TOTAL RM COST | CB1: FIRM % | CC1: FIRM VALUE | CD1: MFG% | CE1: MFG VALUE | CF1: PROF% | CG1: PROFIT VALUE | CH1: 1ST EX-WORKS | CI1: Intt % | CJ1: INTT VALUE | CK1: insp% | CL1: INSP VALUE | CM1: EX-WORKS (PER KM) | CN1: FREIGHT PER KM | CO1: PRICE INCLUDING FREIGHT (PER KM) | CP1: GST % | CQ1: GST VALUE | CR1: PRICE INCLUDING GST & FREIGHT (PER KM) | CS1: QTY | CT1: Unit | CU1: TOTAL PRICE OF FULL QTY (INCLUDING FRIGHT & GST) | CV1: DRUM CODE | CW1: DRUM SIZE (FxbXtx Ft) | CX1: PARTY STANDARD LENGTH (MTR)
A2: ENQ-11011-22-23 | B2: 45148 | C2: FA0300023 | D2: 12 CORE X 2.5 SQ. MM. CU/UNARD. (XLPE) | E2: WOOD | J2: Copper | K2: 747 | L2: 264 | P2: 0 | T2: 0 | V2: LT-XLPE | W2: 111 | X2: 82 | Z2: POLY TAPE | AA2: 123 | AB2: 5 | AD2: PVC Type ST-2 | AE2: 60 | AF2: 58 | AJ2: 0 | AL2: PVC Type ST-2 | AM2: 60 | AN2: 175 | AR2: 0 | AV2: 0 | AZ2: 0 | BD2: 0 | BH2: 0 | BL2: 0 | BP2: 0 | BT2: 0 | BX2: 0 | CP2: 0.18 | CS2: 35 | CT2: KMS | CX2: 1000
A3: ENQ-11011-22-23 | B3: 45148 | C3: FA1000038 | D3: 2 CORE X 6 SQ. MM. CU/UNARD.(PVC) | E3: WOOD | J3: Copper | K3: 747 | L3: 106.68 | P3: 0 | T3: 0 | V3: Type A PVC-1.45 | W3: 70 | X3: 40 | AB3: 0 | AD3: PVC Type ST-1 | AE3: 58 | AF3: 68 | AJ3: 0 | AL3: PVC Type ST-1 | AM3: 58 | AN3: 109 | AR3: 0 | AV3: 0 | AZ3: 0 | BD3: 0 | BH3: 0 | BL3: 16 | BP3: 0 | BT3: 0 | BX3: 0 | BZ3: 2239.78 | CA3: 2239.78 | CH3: 2239.78 | CM3: 2239.78 | CO3: 2239.78 | CP3: 0.18 | CQ3: 403.16 | CR3: 2642.94 | CS3: 3500 | CT3: KMS | CU3: 9250291 | CV3: MD0100066 | CW3: DRUM - 40 X 15 X 23 X 2 | CX3: 1000

Sheet AUTO CALCULATION SHEET (2)
A2: JHARKHAND BIJLI VITRAN NIGAM LIMITED
A4: TENDER SPECIFICATION NO () | B4: 112/PR/JBVNL/2023-24
A5: TENDER DESCRIPTION () | B5: 1.1 KV, 2C x 6 Sq. mm. PVC Insulated & PVC sheathed multi core un-armoured copper cable & 1.1 KV, 12C x 2.5 Sq. mm, XLPE Insulated, PVC Sheathed Multi-stranded un-armoured cu. Cable.
A6: Last Date & Time of Submission () | B6: 16.08.2023
A7: REVERSE AUCTION | B7: Not mention.
A8: Price () | B8: Rate contract shall be done on L-1 rate with successful bidder for respective size of cables against NIT for the period of 02(two) years [ 1st year on FIRM Price + 2nd year on Variable Price] which may be further extended for 01 year on variable Price on mutual agreement and satisfactory performance. Price variation formula as circulated by IEEMA/CAMAI (For conductor) shall be considered for calculating the price with suitable base rate on the defined date.
A9: Validity () | B9: Tenderer should specify the validity period of their offer which should not be less than 180 (One Hundred Eighty) days from the date of opening of tender, which may be extended on discretion of the NIGAM. The offers with lesser validity period may be out- rightly rejected.
A10: Delivery Period () | B10: 1.1 KV, 2C x 6 Sq. mm. PVC Insulated & PVC sheathed multi core un-armoured copper cable - 1st month 2nd month 3rd month 4th month 15% of order quantity 25% of order quantity 30% of order quantity 30% of order quantity 1.1 KV, 12C x 2.5 Sq. mm, XLPE Insulated, PVC Sheathed Multi-stranded un armoured cu. cable - 1st month 2nd month 3rd month 4th month 20% of order quantity 40% of order quantity 40% of order quantity
A11: Payment Terms () | B11: 100% payment will be made by Sr. Manager, JBVNL, Headquarter, Ranchi on submission of 5% Bank Guarantee from any Nationalised/Scheduled Bank of ordered value on non-judicial stamp Rs. 100/-(Rupees hundred) only valid for Guarantee period as per cl-38 and on receipt of SRV duly signed by the concerned consignee after receipt of the materials in good condition along with approved routine test certificate and duly filled check list for payment from Stores & Purchase wing.
A12: Standard length () | B12: The Cables shall be supplied in Drum lengths of 1000 + 5% Mtr. which shall be subject to tolerance of not more than + 5% and the variation in the total quantity of Cables due to tolerance in individual drum length shall be limited to+ 2.5% for all types of Cable. Non-standard drum length shall not be acceptable. However, before packing the Cables on Drums, the successful bidders will be required to obtain purchaser’s approval for the drum lengths.
A13: Packing () | B13: The Cables shall be packed in non-returnable wooden drums. The wooden drums should be bearing distinguishing number with following information duly stenciled on the outer side of one flange.
A14: Technical Specification
N16: =Sheet1!J1 -> Conductor | S16: AL ALLOY | U16: Insulation Screening (Metallic) | AC16: Insulation Screening (Non-Metallic) | AE16: Insulation | AK16: POLY TAPE | AL16: Inner Sheath | AS16: Armouring | BC16: Outer Sheath | BM16: FILLER | BN16: GREASE | BO16: Water swellable Tape | BP16: Semi conducting Water Swellable tape | BQ16: SEMICON TAPE | BR16: GLASS FIBER TAPE | BS16: COPPER WIRE 0.8 MM | BT16: RUBBERIZED COTTON TAPE | BU16: Water Tight Compound | BZ16: DRUM COST PER KM | CA16: TOTAL RM COST | CB16: EXTRA CONSUMPTION | CC16: EXTRA CONSUMPTION VALUE
A17: DOCKET NO. | B17: =Sheet1!B1 -> Base Date | C17: ITEM CODE | D17: PROPOSE ERP ITEM NAME | E17: EX-WORKS (PER KM) | F17: FREIGHT PER KM | G17: PRICE INCLUDING FREIGHT (PER KM) | H17: GST % | I17: GST VALUE | J17: PRICE INCLUDING GST & FREIGHT (PER KM) | K17: QTY | L17: Unit | M17: TOTAL PRICE OF FULL QTY (INCLUDING FRIGHT & GST) | N17: Alumimium | O17: Alumimium ALLOY | P17: Copper | Q17: Flexible Copper | R17: Galvanized steel wire | S17: Alumimium | T17: Alumimium ALLOY | U17: Coper tape - 0.1 mm | V17: Copper Tape - 0.03 mm | W17: Copper Tape - 0.035 mm | X17: Copper Tape - 0.04 mm | Y17: Copper Tape - 0.045 mm | Z17: Copper Tape - 0.050 mm | AA17: Copper Tape - 0.060 mm | AB17: Copper Tape - 0.075 mm(DOUBLE) | AC17: Extruded semiconductive | AD17: Extruded Semiconductive(Stripable) | AE17: HT-XLPE | AF17: LT-XLPE | AG17: Type A PVC-1.45 | AH17: Type A PVC | AI17: Type C PVC (HR) | AJ17: XLPE | AK17: POLY TAPE | AL17: FR PVC Type ST-1 | AM17: FR PVC Type ST-2 | AN17: FRLSH PVC Type ST-2 | AO17: PVC Type ST-1 | AP17: PVC Type ST-1-PRESSURE EXTRUDED | AQ17: PVC Type ST-2 | AR17: PVC Type ST-2-PRESSURE EXTRUDED | AS17: ACSR CORE WIRE | AT17: ACSR DOG STEEL WIRE | AU17: Aluminium Flat Strip | AV17: Aluminium Round Wire | AW17: Double Steel Tape | AX17: Galvanised Steel Flat Strip | AY17: Galvanised Steel Flat Strip (Double) | AZ17: Galvanised Steel Flat Strip-B | BA17: Galvanised Steel Round Wire | BB17: Galvanised Steel Round Wire (Double) | BC17: FR PVC Type ST-1 | BD17: FR PVC Type ST-2 | BE17: FRLSH PVC Type ST-1 | BF17: FRLSH PVC Type ST-2 | BG17: PE, ST-3 | BH17: PE, ST-7 | BI17: PVC Type ST-1 | BJ17: PVC Type ST-2 | BK17: PVC Type ST-2-PRESSURE EXTRUDED | BL17: UV & Track Resistant XLPE | BM17: FILLER | BN17: Grease | BO17: Water swellable Tape | BP17: Semi conducting Water Swellable tape | BQ17: SEMICON TAPE | BR17: GLASS FIBER TAPE | BS17: COPPER WIRE 0.8 MM | BT17: RUBBERIZED COTTON TAPE | BU17: Water Tight Compound | BV17: =Sheet1!E1 -> PROPOSE DRUM TYPE | BW17: =Sheet1!CV1 -> DRUM CODE | BX17: =Sheet1!CW1 -> DRUM SIZE (FxbXtx Ft) | BY17: =Sheet1!CX1 -> PARTY STANDARD LENGTH (MTR) | CD17: MFG% | CE17: MFG VALUE | CF17: PROF% | CG17: PROFIT VALUE | CH17: 1ST EX-WORKS | CI17: Intt % | CJ17: INTT VALUE | CK17: insp% | CL17: INSP VALUE
N18: =+IFERROR(VLOOKUP($N$17,Sheet1!J:L,2,0),0) -> 0 | O18: =+IFERROR(VLOOKUP($O$17,Sheet1!J:L,2,0),0) -> 0 | P18: 749 | Q18: =+IFERROR(VLOOKUP($Q$17,Sheet1!J:M,2,0),0) -> 0 | R18: =+IFERROR(VLOOKUP($R$17,Sheet1!J:M,2,0),0) -> 0 | S18: =+IFERROR(VLOOKUP($S$17,Sheet1!N:Q,2,0),0) -> 0 | T18: =+IFERROR(VLOOKUP($T$17,Sheet1!N:O,2,0),0) -> 0 | U18: =+IFERROR(VLOOKUP($U$17,Sheet1!F:I,2,0),0) -> 0 | V18: =+IFERROR(VLOOKUP($V$17,Sheet1!F:I,2,0),0) -> 0 | W18: =+IFERROR(VLOOKUP($W$17,Sheet1!F:I,2,0),0) -> 0 | X18: =+IFERROR(VLOOKUP($X$17,Sheet1!F:I,2,0),0) -> 0 | Y18: =+IFERROR(VLOOKUP($Y$17,Sheet1!F:I,2,0),0) -> 0 | Z18: =+IFERROR(VLOOKUP($Z$17,Sheet1!F:I,2,0),0) -> 0 | AA18: =+IFERROR(VLOOKUP($AA$17,Sheet1!F:I,2,0),0) -> 0 | AB18: =+IFERROR(VLOOKUP($AB$17,Sheet1!F:I,2,0),0) -> 0 | AC18: =+IFERROR(VLOOKUP($AC$17,Sheet1!R:U,2,0),0) -> 0 | AD18: =+IFERROR(VLOOKUP($AD$17,Sheet1!R:U,2,0),0) -> 0 | AE18: =+IFERROR(VLOOKUP($AE$17,Sheet1!V:Y,2,0),0) -> 0 | AF18: 110 | AG18: 69 | AH18: =+IFERROR(VLOOKUP($AH$17,Sheet1!V:Y,2,0),0) -> 0 | AI18: =+IFERROR(VLOOKUP($AI$17,Sheet1!V:Y,2,0),0) -> 0 | AJ18: =+IFERROR(VLOOKUP($AJ$17,Sheet1!V:Y,2,0),0) -> 0 | AK18: 122 | AL18: =+IFERROR(VLOOKUP($AL$17,Sheet1!AD2:AG840,2,0),0) -> 0 | AM18: =+IFERROR(VLOOKUP($AM$17,Sheet1!AD2:AG840,2,0),0) -> 0 | AN18: =+IFERROR(VLOOKUP($AN$17,Sheet1!AD2:AG840,2,0),0) -> 0 | AO18: =+IFERROR(VLOOKUP($AO$17,Sheet1!AD2:AG840,2,0),0) -> 58 | AP18: =+IFERROR(VLOOKUP($AP$17,Sheet1!AD2:AG840,2,0),0) -> 0 | AQ18: =+IFERROR(VLOOKUP($AQ$17,Sheet1!AD2:AG840,2,0),0) -> 60 | AR18: =+IFERROR(VLOOKUP($AR$17,Sheet1!AD2:AG840,2,0),0) -> 0 | AS18: =+IFERROR(VLOOKUP($AS$17,Sheet1!AH2:AK840,2,0),0) -> 0 | AT18: =+IFERROR(VLOOKUP($AT$17,Sheet1!AH2:AK840,2,0),0) -> 0 | AU18: =+IFERROR(VLOOKUP($AU$17,Sheet1!AH2:AK840,2,0),0) -> 0 | AV18: =+IFERROR(VLOOKUP($AV$17,Sheet1!AH2:AK840,2,0),0) -> 0 | AW18: =+IFERROR(VLOOKUP($AW$17,Sheet1!AH2:AK840,2,0),0) -> 0 | AX18: =+IFERROR(VLOOKUP($AX$17,Sheet1!AH2:AK840,2,0),0) -> 0 | AY18: =+IFERROR(VLOOKUP($AY$17,Sheet1!AH2:AK840,2,0),0) -> 0 | AZ18: =+IFERROR(VLOOKUP($AZ$17,Sheet1!AH2:AK840,2,0),0) -> 0 | BA18: =+IFERROR(VLOOKUP($BA$17,Sheet1!AH2:AK840,2,0),0) -> 0 | BB18: =+IFERROR(VLOOKUP($BB$17,Sheet1!AH2:AK840,2,0),0) -> 0 | BC18: =+IFERROR(VLOOKUP($BC$17,Sheet1!AL2:AO840,2,0),0) -> 0 | BD18: =+IFERROR(VLOOKUP($BD$17,Sheet1!AL2:AO840,2,0),0) -> 0 | BE18: =+IFERROR(VLOOKUP($BE$17,Sheet1!AL2:AO840,2,0),0) -> 0 | BF18: =+IFERROR(VLOOKUP($BF$17,Sheet1!AL2:AO840,2,0),0) -> 0 | BG18: =+IFERROR(VLOOKUP($BG$17,Sheet1!AL2:AO840,2,0),0) -> 0 | BH18: =+IFERROR(VLOOKUP($BH$17,Sheet1!AL2:AO840,2,0),0) -> 0 | BI18: =+IFERROR(VLOOKUP($BI$17,Sheet1!AL2:AO840,2,0),0) -> 58 | BJ18: =+IFERROR(VLOOKUP($BJ$17,Sheet1!AL2:AO840,2,0),0) -> 60 | BK18: =+IFERROR(VLOOKUP($BK$17,Sheet1!AL2:AO840,2,0),0) -> 0 | BL18: =+IFERROR(VLOOKUP($BL$17,Sheet1!AL2:AO840,2,0),0) -> 0 | BM18: =+IFERROR(VLOOKUP($BM$17,Sheet1!AP2:AS840,2,0),0) -> 0 | BN18: =+IFERROR(VLOOKUP($BN$17,Sheet1!AT2:AW840,2,0),0) -> 0 | BO18: =+IFERROR(VLOOKUP($BO$17,Sheet1!AX2:BA840,2,0),0) -> 0 | BP18: =+IFERROR(VLOOKUP($BP$17,Sheet1!BB2:BE840,2,0),0) -> 0 | BQ18: =+IFERROR(VLOOKUP($BQ$17,Sheet1!BF2:BI840,2,0),0) -> 0 | BR18: =+IFERROR(VLOOKUP($BR$17,Sheet1!BJ2:BM840,2,0),0) -> 0 | BS18: =+IFERROR(VLOOKUP($BS$17,Sheet1!BN2:BQ840,2,0),0) -> 0 | BT18: =+IFERROR(VLOOKUP($BT$17,Sheet1!BR2:BU840,2,0),0) -> 0 | BU18: =+IFERROR(VLOOKUP($BU$17,Sheet1!BV2:BY840,2,0),0) -> 0
A19: =Sheet1!A3 -> ENQ-11011-22-23 | B19: 45108 | C19: =Sheet1!C3 -> FA1000038 | D19: =Sheet1!D3 -> 2 CORE X 6 SQ. MM. CU/UNARD.(PVC) | E19: =CH19+CJ19+CL19 -> 122097.5 | F19: =ROUNDUP(M23,0) -> 728 | G19: =E19+F19 -> 122825.5 | H19: =Sheet1!CP3 -> 0.18 | I19: =G19*H19 -> 22108.591 | J19: =G19+I19 -> 144934.09 | K19: =Sheet1!CS3 -> 3500 | L19: =Sheet1!CT3 -> KMS | M19: =J19*K19 -> 5.0726933e+08 | N19: =+IFERROR(VLOOKUP($N$17,Sheet1!J3:L3,3,0),0) -> 0 | O19: =+IFERROR(VLOOKUP($O$17,Sheet1!J3:L3,3,0),0) -> 0 | P19: 107 | Q19: =+IFERROR(VLOOKUP($Q$17,Sheet1!J3:M3,3,0),0) -> 0 | R19: =+IFERROR(VLOOKUP($R$17,Sheet1!J3:M3,3,0),0) -> 0 | S19: =+IFERROR(VLOOKUP($S$17,Sheet1!N3:Q3,3,0),0) -> 0 | T19: =+IFERROR(VLOOKUP($T$17,Sheet1!N3:Q3,3,0),0) -> 0 | U19: =+IFERROR(VLOOKUP($U$17,Sheet1!F3:I3,3,0),0) -> 0 | V19: =+IFERROR(VLOOKUP($V$17,Sheet1!F3:I3,3,0),0) -> 0 | W19: =+IFERROR(VLOOKUP($W$17,Sheet1!F3:I3,3,0),0) -> 0 | X19: =+IFERROR(VLOOKUP($X$17,Sheet1!F3:I3,3,0),0) -> 0 | Y19: =+IFERROR(VLOOKUP($Y$17,Sheet1!F3:I3,3,0),0) -> 0 | Z19: =+IFERROR(VLOOKUP($Z$17,Sheet1!F3:I3,3,0),0) -> 0 | AA19: =+IFERROR(VLOOKUP($AA$17,Sheet1!F3:I3,3,0),0) -> 0 | AB19: =+IFERROR(VLOOKUP($AB$17,Sheet1!F3:I3,3,0),0) -> 0 | AC19: =+IFERROR(VLOOKUP($AC$17,Sheet1!R3:U3,3,0),0) -> 0 | AD19: =+IFERROR(VLOOKUP($AD$17,Sheet1!R3:U3,2,0),0) -> 0 | AE19: =+IFERROR(VLOOKUP($AE$17,Sheet1!V3:Y3,3,0),0) -> 0 | AF19: =+IFERROR(VLOOKUP($AF$17,Sheet1!V3:Y3,3,0),0) -> 0 | AG19: 44 | AH19: =+IFERROR(VLOOKUP($AH$17,Sheet1!V3:Y3,3,0),0) -> 0 | AI19: =+IFERROR(VLOOKUP($AI$17,Sheet1!V3:Y3,3,0),0) -> 0 | AJ19: =+IFERROR(VLOOKUP($AJ$17,Sheet1!V3:Y3,3,0),0) -> 0 | AK19: =+IFERROR(VLOOKUP($AK$17,Sheet1!Z3:AB3,3,0),0) -> 0 | AL19: =+IFERROR(VLOOKUP($AL$17,Sheet1!AD3:AG3,3,0),0) -> 0 | AM19: =+IFERROR(VLOOKUP($AM$17,Sheet1!AD3:AG3,3,0),0) -> 0 | AN19: =+IFERROR(VLOOKUP($AN$17,Sheet1!AD3:AG3,3,0),0) -> 0 | AO19: =+IFERROR(VLOOKUP($AO$17,Sheet1!AD3:AG3,3,0),0) -> 68 | AP19: =+IFERROR(VLOOKUP($AP$17,Sheet1!AD3:AG3,3,0),0) -> 0 | AQ19: =+IFERROR(VLOOKUP($AQ$17,Sheet1!AD3:AG3,3,0),0) -> 0 | AR19: =+IFERROR(VLOOKUP($AR$17,Sheet1!AD3:AG3,3,0),0) -> 0 | AS19: =+IFERROR(VLOOKUP($AS$17,Sheet1!AH3:AK3,3,0),0) -> 0 | AT19: =+IFERROR(VLOOKUP($AT$17,Sheet1!AH3:AK3,3,0),0) -> 0 | AU19: =+IFERROR(VLOOKUP($AU$17,Sheet1!AH3:AK3,3,0),0) -> 0 | AV19: =+IFERROR(VLOOKUP($AV$17,Sheet1!AH3:AK3,3,0),0) -> 0 | AW19: =+IFERROR(VLOOKUP($AW$17,Sheet1!AH3:AK3,3,0),0) -> 0 | AX19: =+IFERROR(VLOOKUP($AX$17,Sheet1!AH3:AK3,3,0),0) -> 0 | AY19: =+IFERROR(VLOOKUP($AY$17,Sheet1!AH3:AK3,3,0),0) -> 0 | AZ19: =+IFERROR(VLOOKUP($AZ$17,Sheet1!AH3:AK3,3,0),0) -> 0 | BA19: =+IFERROR(VLOOKUP($BA$17,Sheet1!AH3:AK3,3,0),0) -> 0 | BB19: =+IFERROR(VLOOKUP($BB$17,Sheet1!AH3:AK3,3,0),0) -> 0 | BC19: =+IFERROR(VLOOKUP($BC$17,Sheet1!AL3:AO3,3,0),0) -> 0 | BD19: =+IFERROR(VLOOKUP($BD$17,Sheet1!AL3:AO3,3,0),0) -> 0 | BF19: =+IFERROR(VLOOKUP($BF$17,Sheet1!AL3:AO3,3,0),0) -> 0 | BG19: =+IFERROR(VLOOKUP($BG$17,Sheet1!AL3:AO3,3,0),0) -> 0 | BH19: =+IFERROR(VLOOKUP($BH$17,Sheet1!AL3:AO3,3,0),0) -> 0 | BI19: 130 | BJ19: =+IFERROR(VLOOKUP($BJ$17,Sheet1!AL3:AO3,3,0),0) -> 0 | BK19: =+IFERROR(VLOOKUP($BK$17,Sheet1!AL3:AO3,3,0),0) -> 0 | BL19: =+IFERROR(VLOOKUP($BL$17,Sheet1!AL3:AO3,3,0),0) -> 0 | BM19: =+IFERROR(VLOOKUP($BM$17,Sheet1!AP3:AS3,3,0),0) -> 0 | BN19: =+IFERROR(VLOOKUP($BN$17,Sheet1!AT3:AW3,3,0),0) -> 0 | BO19: =+IFERROR(VLOOKUP($BO$17,Sheet1!AX3:BA3,3,0),0) -> 0 | BP19: =+IFERROR(VLOOKUP($BP$17,Sheet1!BB3:BE3,3,0),0) -> 0 | BQ19: =+IFERROR(VLOOKUP($BQ$17,Sheet1!BF3:BI3,3,0),0) -> 0 | BR19: =+IFERROR(VLOOKUP($BR$17,Sheet1!BJ3:BM3,3,0),0) -> 0 | BS19: =+IFERROR(VLOOKUP($BS$17,Sheet1!BN3:BQ3,3,0),0) -> 0 | BT19: =+IFERROR(VLOOKUP($BT$17,Sheet1!BR3:BU3,3,0),0) -> 0 | BU19: =+IFERROR(VLOOKUP($BU$17,Sheet1!BV3:BY3,3,0),0) -> 0 | BV19: =Sheet1!E3 -> WOOD | BW19: =Sheet1!CV3 -> MD0100066 | BX19: =Sheet1!CW3 -> DRUM - 40 X 15 X 23 X 2 | BY19: =Sheet1!CX3 -> 1000 | BZ19: =Sheet1!BZ3 -> 2239.78 | CA19: =SUMPRODUCT($N$18:$BU$18,N19:BU19)+BZ19 -> 96902.78 | CB19: =Sheet1!CB3 -> 0 | CC19: =CA19*CB19 -> 0 | CD19: 0.2 | CE19: =CA19*CD19 -> 19380.556 | CF19: 0 | CG19: =CA19*CF19 -> 0 | CH19: =CA19+CC19+CE19+CG19 -> 116283.34 | CI19: 0.02 | CJ19: =CH19*CI19 -> 2325.6667 | CK19: 0.03 | CL19: =CH19*CK19 -> 3488.5001
A20: =Sheet1!A2 -> ENQ-11011-22-23 | B20: 45108 | C20: =Sheet1!C2 -> FA0300023 | D20: =Sheet1!D2 -> 12 CORE X 2.5 SQ. MM. CU/UNARD. (XLPE) | E20: =CH20+CJ20+CL20 -> 280062.72 | F20: =ROUNDUP(M24,0) -> 1486 | G20: =E20+F20 -> 281548.72 | H20: =Sheet1!CP2 -> 0.18 | I20: =G20*H20 -> 50678.77 | J20: =G20+I20 -> 332227.49 | K20: =Sheet1!CS2 -> 35 | L20: =Sheet1!CT2 -> KMS | M20: =J20*K20 -> 11627962 | N20: =+IFERROR(VLOOKUP($N$17,Sheet1!J2:L2,3,0),0) -> 0 | O20: =+IFERROR(VLOOKUP($O$17,Sheet1!J2:L2,3,0),0) -> 0 | P20: =+IFERROR(VLOOKUP($P$17,Sheet1!J2:M2,3,0),0) -> 264 | Q20: =+IFERROR(VLOOKUP($Q$17,Sheet1!J2:M2,3,0),0) -> 0 | R20: =+IFERROR(VLOOKUP($R$17,Sheet1!J2:M2,3,0),0) -> 0 | S20: =+IFERROR(VLOOKUP($S$17,Sheet1!N2:Q2,3,0),0) -> 0 | T20: =+IFERROR(VLOOKUP($T$17,Sheet1!N2:Q2,3,0),0) -> 0 | U20: =+IFERROR(VLOOKUP($U$17,Sheet1!F2:I2,3,0),0) -> 0 | V20: =+IFERROR(VLOOKUP($V$17,Sheet1!F2:I2,3,0),0) -> 0 | W20: =+IFERROR(VLOOKUP($W$17,Sheet1!F2:I2,3,0),0) -> 0 | X20: =+IFERROR(VLOOKUP($X$17,Sheet1!F2:I2,3,0),0) -> 0 | Y20: =+IFERROR(VLOOKUP($Y$17,Sheet1!F2:I2,3,0),0) -> 0 | Z20: =+IFERROR(VLOOKUP($Z$17,Sheet1!F2:I2,3,0),0) -> 0 | AA20: =+IFERROR(VLOOKUP($AA$17,Sheet1!F2:I2,3,0),0) -> 0 | AB20: =+IFERROR(VLOOKUP($AB$17,Sheet1!F2:I2,3,0),0) -> 0 | AC20: =+IFERROR(VLOOKUP($AC$17,Sheet1!R2:U2,3,0),0) -> 0 | AD20: =+IFERROR(VLOOKUP($AD$17,Sheet1!R2:U2,2,0),0) -> 0 | AE20: =+IFERROR(VLOOKUP($AE$17,Sheet1!V2:Y2,3,0),0) -> 0 | AF20: 84 | AG20: =+IFERROR(VLOOKUP($AG$17,Sheet1!V2:Y2,3,0),0) -> 0 | AH20: =+IFERROR(VLOOKUP($AH$17,Sheet1!V2:Y2,3,0),0) -> 0 | AI20: =+IFERROR(VLOOKUP($AI$17,Sheet1!V2:Y2,3,0),0) -> 0 | AJ20: =+IFERROR(VLOOKUP($AJ$17,Sheet1!V2:Y2,3,0),0) -> 0 | AK20: =+IFERROR(VLOOKUP($AK$17,Sheet1!Z2:AB2,3,0),0) -> 5 | AL20: =+IFERROR(VLOOKUP($AL$17,Sheet1!AD2:AG2,3,0),0) -> 0 | AM20: =+IFERROR(VLOOKUP($AM$17,Sheet1!AD2:AG2,3,0),0) -> 0 | AN20: =+IFERROR(VLOOKUP($AN$17,Sheet1!AD2:AG2,3,0),0) -> 0 | AO20: =+IFERROR(VLOOKUP($AO$17,Sheet1!AD2:AG2,3,0),0) -> 0 | AP20: =+IFERROR(VLOOKUP($AP$17,Sheet1!AD2:AG2,3,0),0) -> 0 | AQ20: 40 | AR20: =+IFERROR(VLOOKUP($AR$17,Sheet1!AD2:AG2,3,0),0) -> 0 | AS20: =+IFERROR(VLOOKUP($AS$17,Sheet1!AH2:AK2,3,0),0) -> 0 | AT20: =+IFERROR(VLOOKUP($AT$17,Sheet1!AH2:AK2,3,0),0) -> 0 | AU20: =+IFERROR(VLOOKUP($AU$17,Sheet1!AH2:AK2,3,0),0) -> 0 | AV20: =+IFERROR(VLOOKUP($AV$17,Sheet1!AH2:AK2,3,0),0) -> 0 | AW20: =+IFERROR(VLOOKUP($AW$17,Sheet1!AH2:AK2,3,0),0) -> 0 | AX20: =+IFERROR(VLOOKUP($AX$17,Sheet1!AH2:AK2,3,0),0) -> 0 | AY20: =+IFERROR(VLOOKUP($AY$17,Sheet1!AH2:AK2,3,0),0) -> 0 | AZ20: =+IFERROR(VLOOKUP($AZ$17,Sheet1!AH2:AK2,3,0),0) -> 0 | BA20: =+IFERROR(VLOOKUP($BA$17,Sheet1!AH2:AK2,3,0),0) -> 0 | BB20: =+IFERROR(VLOOKUP($BB$17,Sheet1!AH2:AK2,3,0),0) -> 0 | BC20: =+IFERROR(VLOOKUP($BC$17,Sheet1!AL2:AO2,3,0),0) -> 0 | BD20: =+IFERROR(VLOOKUP($BD$17,Sheet1!AL2:AO2,3,0),0) -> 0 | BE20: =+IFERROR(VLOOKUP($BE$17,Sheet1!AL2:AO2,3,0),0) -> 0 | BF20: =+IFERROR(VLOOKUP($BF$17,Sheet1!AL2:AO2,3,0),0) -> 0 | BG20: =+IFERROR(VLOOKUP($BG$17,Sheet1!AL2:AO2,3,0),0) -> 0 | BH20: =+IFERROR(VLOOKUP($BH$17,Sheet1!AL2:AO2,3,0),0) -> 0 | BI20: =+IFERROR(VLOOKUP($BI$17,Sheet1!AL2:AO2,3,0),0) -> 0 | BJ20: 160 | BK20: =+IFERROR(VLOOKUP($BK$17,Sheet1!AL2:AO2,3,0),0) -> 0 | BL20: =+IFERROR(VLOOKUP($BL$17,Sheet1!AL2:AO2,3,0),0) -> 0 | BM20: =+IFERROR(VLOOKUP($BM$17,Sheet1!AP2:AS2,3,0),0) -> 0 | BN20: =+IFERROR(VLOOKUP($BN$17,Sheet1!AT2:AW2,3,0),0) -> 0 | BO20: =+IFERROR(VLOOKUP($BO$17,Sheet1!AX2:BA2,3,0),0) -> 0 | BP20: =+IFERROR(VLOOKUP($BP$17,Sheet1!BB2:BE2,3,0),0) -> 0 | BQ20: =+IFERROR(VLOOKUP($BQ$17,Sheet1!BF2:BI2,3,0),0) -> 0 | BR20: =+IFERROR(VLOOKUP($BR$17,Sheet1!BJ2:BM2,3,0),0) -> 0 | BS20: =+IFERROR(VLOOKUP($BS$17,Sheet1!BN2:BQ2,3,0),0) -> 0 | BT20: =+IFERROR(VLOOKUP($BT$17,Sheet1!BR2:BU2,3,0),0) -> 0 | BU20: =+IFERROR(VLOOKUP($BU$17,Sheet1!BV2:BY2,3,0),0) -> 0 | BV20: =Sheet1!E2 -> WOOD | BW20: MD0100137 | BX20: DRUM - 43 X 15 X 23 X 2.25 | BY20: =Sheet1!CX2 -> 1000 | BZ20: 2686 | CA20: =SUMPRODUCT($N$18:$BU$18,N20:BU20)+BZ20 -> 222272 | CB20: =Sheet1!CB2 -> 0 | CC20: =CA20*CB20 -> 0 | CD20: 0.2 | CE20: =CA20*CD20 -> 44454.4 | CF20: 0 | CG20: =CA20*CF20 -> 0 | CH20: =CA20+CC20+CE20+CG20 -> 266726.4 | CI20: 0.02 | CJ20: =CH20*CI20 -> 5334.528 | CK20: 0.03 | CL20: =CH20*CK20 -> 8001.792
E22: Order Quantity | F22: Stnd Length | G22: Truck type | H22: Fare of one truck | I22: No of Drum in one truck | J22: Total length in one Truck | K22: No of Truck | L22: Total Freight | M22: Freight per KM
D23: =D19 -> 2 CORE X 6 SQ. MM. CU/UNARD.(PVC) | E23: =K19 -> 3500 | F23: 1 | G23: 16 MT | H23: 26000 | I23: 36 | J23: =F23*I23 -> 36 | K23: =ROUNDUP((E23/J23),0) -> 98 | L23: =M23*E23 -> 2548000 | M23: =(H23*K23)/E23 -> 728
D24: =D20 -> 12 CORE X 2.5 SQ. MM. CU/UNARD. (XLPE) | E24: =K20 -> 35 | F24: 1 | G24: 16 MT | H24: 26000 | I24: 22 | J24: =F24*I24 -> 22 | K24: =ROUNDUP((E24/J24),0) -> 2 | L24: =M24*E24 -> 52000 | M24: =(H24*K24)/E24 -> 1485.7143
I25: SOMBHU SIR CONFIRMED OVERPHONE

Sheet LT POWER & CONTROL
A1: Base Date | B1: 45108
A2: PV FORMULA
A3: P = Po + AIF (Al–Alo) + XLFAL (CC–Cco) + SMIF (SMIF1–SMIF0) + FeF (FeF1–FeF0) + CCFAI (PVCc–PVCco)
A4: Rate contract shall be done on L-1 rate with successful bidder for respective size of cables against NIT for the period of 02(two) years [ 1st year on FIRM Price + 2nd year on Variable Price] which may be further extended for 01 year on variable Price on mutual agreement and satisfactory performance. | B4: Base date for PV calculation: It is one month prior to the last date of submission of bid against the NIT i.e price is applicable on 1st working day of month, one month prior to date of tendering (due date of tender) i.e if due date of tender is in month sept’2022 then price indices shall be taken of 1st August’2022.
V9: VALUE ADDITION CALCULATION
A10: Item | B10: Calculation part | D10: Applicable Date | H10: BASE DATE | O10: Ex-Work Po | P10: PVC of Cu | Q10: PVC of XLPE | R10: PVC OF PVC | S10: PV/PKM | T10: Billing Price/PKM | U10: DIFF
D11: Date | E11: Cu | F11: Cc | G11: PVCc | H11: Date | I11: Cuo | J11: Cco | K11: PVCco | V11: ='AUTO CALCULATION SHEET (2)'!P17 -> Copper | W11: Alumimium ALLOY | X11: Copper Tape - 0.03 mm | Y11: Extruded semiconductive | Z11: HT-XLPE | AA11: ='AUTO CALCULATION SHEET (2)'!AF17 -> LT-XLPE | AB11: ='AUTO CALCULATION SHEET (2)'!AG17 -> Type A PVC-1.45 | AC11: ='AUTO CALCULATION SHEET (2)'!AK17 -> POLY TAPE | AD11: ='AUTO CALCULATION SHEET (2)'!AO17 -> PVC Type ST-1 | AE11: ='AUTO CALCULATION SHEET (2)'!AQ17 -> PVC Type ST-2 | AF11: ='AUTO CALCULATION SHEET (2)'!BI17 -> PVC Type ST-1 | AG11: ='AUTO CALCULATION SHEET (2)'!BJ17 -> PVC Type ST-2 | AH11: UV & Track Resistant XLPE | AI11: FILLER | AJ11: Semi conducting Water Swellable tape | AK11: Water Tight Compound | AL11: RMC | AM11: Drum | AN11: RMC+Drum | AO11: VA | AP11: Groos VA% | AQ11: Mfg % | AR11: Int % | AS11: Ins% | AT11: Net VA
L12: CuF | M12: XLFAL | N12: CCFAI/ CCFCu | V12: 762 | AA12: 116 | AB12: 71 | AC12: 122 | AD12: 59 | AE12: 61 | AF12: 59 | AG12: 61
V13: Kg/Km | W13: Kg/Km | X13: Kg/Km | Y13: Kg/Km | Z13: Kg/Km | AA13: Kg/Km | AB13: Kg/Km | AC13: Kg/Km | AD13: Kg/Km | AE13: Kg/Km | AF13: Kg/Km | AG13: Kg/Km
A14: ='AUTO CALCULATION SHEET (2)'!D19 -> 2 CORE X 6 SQ. MM. CU/UNARD.(PVC) | C14: Provisional | D14: 45145 | E14: 762365.04 | G14: 150075 | H14: =$B$1 -> 45108 | I14: 755667 | K14: 150075 | L14: 0.112 | N14: 0.154 | O14: ='AUTO CALCULATION SHEET (2)'!E19 -> 122097.5 | P14: =L14*(E14-I14) -> 750.18048 | Q14: =(M14*(F14-J14)) -> 0 | R14: =(N14*(G14-K14)) -> 0 | S14: =P14+Q14+R14 -> 750.18048 | T14: =O14+S14 -> 122847.68 | V14: ='AUTO CALCULATION SHEET (2)'!P19 -> 107 | AA14: ='AUTO CALCULATION SHEET (2)'!AF19 -> 0 | AB14: ='AUTO CALCULATION SHEET (2)'!AG19 -> 44 | AC14: ='AUTO CALCULATION SHEET (2)'!AK19 -> 0 | AD14: ='AUTO CALCULATION SHEET (2)'!AO19 -> 68 | AE14: ='AUTO CALCULATION SHEET (2)'!AQ19 -> 0 | AF14: ='AUTO CALCULATION SHEET (2)'!BI19 -> 130 | AG14: ='AUTO CALCULATION SHEET (2)'!BJ19 -> 0 | AH14: 0 | AI14: 0 | AJ14: 0 | AK14: 0 | AL14: =SUMPRODUCT(V14:AK14,$V$12:AK$12) -> 96340 | AM14: ='AUTO CALCULATION SHEET (2)'!BZ19 -> 2239.78 | AN14: =AL14+AM14 -> 98579.78 | AO14: =T14-AN14 -> 24267.903 | AP14: =ROUND((AO14/AN14)*100,2) -> 24.62 | AR14: 2 | AS14: 3 | AT14: =AP14-AQ14-AR14-AS14 -> 19.62
A15: ='AUTO CALCULATION SHEET (2)'!D20 -> 12 CORE X 2.5 SQ. MM. CU/UNARD. (XLPE) | C15: Provisional | D15: 45145 | E15: 762365.04 | F15: 147876 | G15: 150075 | H15: =$B$1 -> 45108 | I15: 755667 | J15: 147876 | K15: 150075 | L15: 0.282 | M15: 0.074 | N15: 0.334 | O15: ='AUTO CALCULATION SHEET (2)'!E20 -> 280062.72 | P15: =L15*(E15-I15) -> 1888.8473 | Q15: =(M15*(F15-J15)) -> 0 | R15: =(N15*(G15-K15)) -> 0 | S15: =P15+Q15+R15 -> 1888.8473 | T15: =O15+S15 -> 281951.57 | V15: ='AUTO CALCULATION SHEET (2)'!P20 -> 264 | AA15: ='AUTO CALCULATION SHEET (2)'!AF20 -> 84 | AB15: ='AUTO CALCULATION SHEET (2)'!AG20 -> 0 | AC15: ='AUTO CALCULATION SHEET (2)'!AK20 -> 5 | AD15: ='AUTO CALCULATION SHEET (2)'!AO20 -> 0 | AE15: ='AUTO CALCULATION SHEET (2)'!AQ20 -> 40 | AF15: ='AUTO CALCULATION SHEET (2)'!BI20 -> 0 | AG15: ='AUTO CALCULATION SHEET (2)'!BJ20 -> 160 | AH15: 0 | AI15: 0 | AJ15: 0 | AK15: 0 | AL15: =SUMPRODUCT(V15:AK15,$V$12:AK$12) -> 223722 | AM15: ='AUTO CALCULATION SHEET (2)'!BZ20 -> 2686 | AN15: =AL15+AM15 -> 226408 | AO15: =T15-AN15 -> 55543.567 | AP15: =ROUND((AO15/AN15)*100,2) -> 24.53 | AR15: 2 | AS15: 3 | AT15: =AP15-AQ15-AR15-AS15 -> 19.53
