Workbook

Sheet Sheet1
A1: DOCKET NO. | B1: Base Date | C1: ITEM CODE | D1: PROPOSE ERP ITEM NAME | E1: Propose Drum Type | F1: Insulation Screening(Metallic) | G1: RM Rate(Insulation Screening(Metallic)) | H1: Weight (Insulation Screening (Metallic)) | I1: Cost Insulation Screening(Metallic) | J1: Conductor | K1: RM Rate(Conductor) | L1: Weight(Conductor) | M1: Cost(Conductor) | N1: AL ALLOY | O1: RM Rate(AL Alloy) | P1: Weight(Al Alloy) | Q1: Cost(AL Alloy) | R1: Insulation Screening(Non-Metallic) | S1: RM Rate(Insulation Screening(Non-Metallic)) | T1: Weight(Insulation Screening(Non-Metallic) | U1: Cost(Insulation Screening(Non-Metallic) | V1: Insulation | W1: RM Rate(Insulation) | X1: Weight(Insulation) | Y1: Cost(Insulation) | Z1: Poly Tape | AA1: RM Rate(Poly Tape) | AB1: Weight(Poly Tape) | AC1: Cost(Poly Tape) | AD1: Inner Sheath | AE1: RM Rate(Inner Sheath) | AF1: Weight(Inner Sheath) | AG1: Cost(Inner Sheath) | AH1: Armouring | AI1: RM Rate(Armouring) | AJ1: Weight(Armouring) | AK1: Cost(Armouring) | AL1: Outer Sheath | AM1: RM Rate(Outer Sheath) | AN1: Weight(Outer Sheath) | AO1: Cost(Outer Sheath) | AP1: Filler | AQ1: RM Rate(Filler) | AR1: Weight(Filler) | AS1: Cost(Filler) | AT1: Grease | AU1: RM Rate(Grease) | AV1: Weight(Grease) | AW1: Cost(Grease) | AX1: Water Swellable Tape | AY1: RM Rate(Water Swellable Tape) | AZ1: Weight(Water Swellable Tape) | BA1: Cost(Water Swellable Tape) | BB1: Semi Conducting Water Swellable Tape | BC1: RM Rate(Semi Conducting Water Swellable Tape) | BD1: Weight(Semi Conducting Water Swellable Tape) | BE1: Cost(Semi Conducting Water Swellable Tape) | BF1: Semicon Tape | BG1: RM Rate(Semicon Tape) | BH1: Weight(Semicon Tape) | BI1: Cost(Semicon Tape) | BJ1: Glass Fiber Tape | BK1: RM Rate(Glass Fiber Tape) | BL1: Weight(Glass Fiber Tape) | BM1: Cost(Glass Fiber Tape) | BN1: Copper Wire 0.8MM | BO1: RM Rate(Copper Wire 0.8MM) | BP1: Weight(Copper Wire 0.8MM) | BQ1: Cost(Copper Wire 0.8MM) | BR1: Rubberized Cotton Tape | BS1: RM Rate(Rubberized Cotton Tape) | BT1: Weight(Rubberized Cotton Tape) | BU1: Cost(Rubberized Cotton Tape) | BV1: Water Tight Compound | BW1: RM Rate(Water Tight Compound) | BX1: Weight(Water Tight Compound) | BY1: Cost(Water Tight Compound) | BZ1: Drum Cost Per KM | CA1: Total RM Cost | CB1: FIRM % | CC1: Firm Value | CD1: MFG% | CE1: MFG Value | CF1: PROF% | CG1: Profit Value | CH1: 1st EX-Works | CI1: Intt % | CJ1: Intt Value | CK1: insp% | CL1: Insp Value | CM1: TTR CHARGES% | CN1: TTR Value | CO1: EX-Works Per KM | CP1: Freight Per KM | CQ1: Price Including Freight Per KM | CR1: GST % | CS1: GST Value | CT1: Price Including GST & Freight Per KM | CU1: QTY | CV1: Unit | CW1: Total Price Of Full QTY(Including Freight&GST) | CX1: PARTY LENGTH (IF STANDER LENGTH NOT MATCH WITH PAR | CY1: DRUM CODE | CZ1: DRUM SIZE (FxbXtx Ft)
A2: ENQ-19613-25-26 | C2: FC3700003 | D2: ACSR : PANTHER CONDUCTOR - 200 SQ. MM. (30/7/3.00) | E2: WOOD | H2: 0 | J2: Alumimium | L2: 588 | P2: 0 | T2: 0 | X2: 0 | AB2: 0 | AF2: 0 | AH2: ACSR CORE WIRE | AJ2: 388 | AN2: 0 | AR2: 0 | AT2: Grease | AV2: 0 | AZ2: 0 | BD2: 0 | BH2: 0 | BL2: 0 | BP2: 0 | BT2: 0 | BX2: 0 | BZ2: 3956 | CA2: 3956 | CH2: 3956 | CO2: 3956 | CQ2: 3956 | CR2: 0.18 | CS2: 712.08 | CT2: 4668.08 | CU2: 20 | CV2: KMS | CW2: 93362 | CY2: MD0100061 | CZ2: DRUM - 56 X 24 X 32 X 3
A3: ENQ-19613-25-26 | C3: FC6100002 | D3: ACSR : MOOSE CONDUCTOR - 520 SQ. MM. (54/7/3.53) | E3: STEEL | H3: 0 | J3: Alumimium | L3: 1467 | P3: 0 | T3: 0 | X3: 0 | AB3: 0 | AF3: 0 | AH3: ACSR CORE WIRE | AJ3: 537 | AN3: 0 | AR3: 0 | AT3: Grease | AV3: 0 | AZ3: 0 | BD3: 0 | BH3: 0 | BL3: 0 | BP3: 0 | BT3: 0 | BX3: 0 | BZ3: 20900 | CA3: 20900 | CH3: 20900 | CO3: 20900 | CQ3: 20900 | CR3: 0.18 | CS3: 3762 | CT3: 24662 | CU3: 360 | CV3: KMS | CW3: 8878320 | CY3: SP0400125 | CZ3: CORRUGATED DISPATCH STEEL DRUM 1600 X 700 X 915 MM

Sheet AUTO CALCULATION SHEET (2)
A2: The Tata Power Company Ltd, Mumbai
A4: TENDER SPECIFICATION NO () | B4: Tender Reference: CC27FK005
A5: TENDER DESCRIPTION () | B5: Supply of ACSR Moose & ACSR Panther Conductor for Tata Power Transmission, Mumbai.
A6: Last Date & Time of Submission () | B6: 27th May 2026, 1500 Hrs
A7: REVERSE AUCTION | B7: Tata Power reserves the right to conduct the reverse auction AND / OR Manual Negotiations for the products/ services being asked for in the tender. Only Technical Qualified Bids will be allowed to participate in e-auction. Date and time of e-auction will be intimated through E-Tender system to Authorized Person of Interested Bidder. Only those bidders who are techno-commercially qualified shall be eligible to participate further in RA process. However, the original H1 bidder (whose price bid is the highest post techno-commercial evaluation) shall not be allowed to participate in further RA process provided minimum three technocommercially qualified bids are available.
A8: Price () | B8: Variable Basis. Subscript ‘0’ = refers to base price, i.e. a) For Aluminium (A0) - CASH LME USD 4,200 Per MT. b) For Exchange Rate (F0) - Basic Average SBI TT SELL reference rate INR 99.00 Per USD. c) For Current Custom Duty including cess (CD0) - 8.25%. d) For Steel (B0) - For HTGS Domes􀆟c Price as per CACMAI Circular – April 2026
A9: Validity () | B9: Bids shall remain valid for 180 days from the due date of submission of the bid. Price submitted as part of E-auction / Negotiation shall remain valid for 90 days from date of E-auction / Negotiation.
A10: Delivery () | B10: iii) Delivery Schedule – Lot 1: ACSR Moose Conductor  Delivery is expected tentatively October 2026 onwards (subject to site requirement). Lot 2: ACSR Panther Conductor  Delivery is expected tentatively September 2026 onwards (subject to site requirement).
A11: Payment Terms () | B11: a. 100% payment (inclusive of taxes & duties) shall be paid through "Letter of Credit" (LC) with 60 days usance period from the date of delivery of material at buyer’s site. b. LC shall be opened along with manufacturing clearance. LC opening charges shall be to buyer’s account. c. Interest of 60 days of usance period shall be to seller's (supplier) account.
A12: Standard length () | B12: The standard length of the conductor shall be As per table below. Dog/Wolf = 3000 Mtr Tolerance 5% Panther = 2400 Mtr Tolerance 5% Moose/Bison = 2000 Mtr Tolerance 5% Only one length of conductor shall be wound on each drum.
A13: Packing () | B13: The conductor shall be supplied in non-returnable strong metal drums provided with lagging of adequate strength, and displacement during transit, storage and subsequent handling and stringing operations in the field. The drum shall confirm to IS: 1778-1980 except otherwise specified hereinafter.
A14: Technical Specification
N18: Conductor | V18: AL ALLOY | X18: Insulation Screening (Metallic) | AF18: Insulation Screening (Non-Metallic) | AH18: Insulation | AQ18: POLY TAPE | AR18: Inner Sheath | BA18: Armouring | BL18: Outer Sheath | BX18: FILLER | BY18: GREASE | BZ18: Water swellable Tape | CA18: Semi conducting Water Swellable tape | CB18: SEMICON TAPE | CC18: GLASS FIBER TAPE | CD18: COPPER WIRE 0.8 MM | CE18: RUBBERIZED COTTON TAPE | CF18: Water Tight Compound | CG18: DRUM TYPE | CK18: DRUM COST PER KM | CL18: TOTAL RM COST | CM18: EXTRA CONSUMPTION | CN18: EXTRA CONSUMPTION VALUE | CZ18: $A$1
A19: DOCKET NO. | B19: BASE DATE | C19: ITEM CODE | D19: PROPOSE ERP ITEM NAME | E19: EX-WORKS (PER KM) | F19: FREIGHT PER KM | G19: PRICE INCLUDING FREIGHT (PER KM) | H19: GST % | I19: GST VALUE | J19: PRICE INCLUDING GST & FREIGHT (PER KM) | K19: QTY | L19: Unit | M19: TOTAL PRICE OF FULL QTY (INCLUDING FRIGHT & GST) | N19: Alumimium | O19: Alumimium ALLOY | P19: Copper | Q19: AL-59 | R19: AL-4 | S19: AL-7 | T19: Flexible Copper | U19: Galvanized steel wire | V19: Alumimium | W19: Alumimium ALLOY | X19: Coper tape - 0.1 mm | Y19: Copper Tape - 0.03 mm | Z19: Copper Tape - 0.035 mm | AA19: Copper Tape - 0.04 mm | AB19: Copper Tape - 0.045 mm | AC19: Copper Tape - 0.050 mm | AD19: Copper Tape - 0.060 mm | AE19: Copper Tape - 0.075 mm(DOUBLE) | AF19: Extruded semiconductive | AG19: Extruded Semiconductive(Stripable) | AH19: HT-XLPE | AI19: LT-XLPE | AJ19: TR XLPE | AK19: Type A PVC | AL19: Type C PVC (HR) | AM19: Type A PVC-1.45 | AN19: Type A PVC-FR | AO19: Type A PVC-FRLS | AP19: Type A PVC-1.38 | AQ19: POLY TAPE | AR19: FR PVC Type ST-1 | AS19: FR PVC Type ST-2 | AT19: FRLSH PVC Type ST-1 | AU19: FRLSH PVC Type ST-2 | AV19: PVC Type ST-1 | AW19: PVC Type ST-1-PRESSURE EXTRUDED | AX19: PVC Type ST-2 | AY19: PVC COMPOUND 1.48 | AZ19: PVC Type ST-2-PRESSURE EXTRUDED | BA19: ACSR CORE WIRE | BB19: ACSR DOG STEEL WIRE | BC19: Aluminium Flat Strip | BD19: Aluminium Round Wire | BE19: Alumimium Tape | BF19: Double Steel Tape | BG19: Galvanised Steel Flat Strip | BH19: Galvanised Steel Flat Strip (Double) | BI19: Galvanised Steel Flat Strip-B | BJ19: Galvanised Steel Round Wire | BK19: Galvanised Steel Round Wire (Double) | BL19: FR PVC Type ST-1 | BM19: FR PVC Type ST-2 | BN19: FRLSH PVC Type ST-1 | BO19: FRLSH PVC Type ST-2 | BP19: ZHFR | BQ19: PE-ST-3 | BR19: PE-ST-7 | BS19: PVC Type ST-1 | BT19: PVC Type ST-2 | BU19: PVC COMPOUND 1.48 | BV19: PVC Type ST-2-PRESSURE EXTRUDED | BW19: UV & Track Resistant XLPE | BX19: FILLER | BY19: Grease | BZ19: Water swellable Tape | CA19: Semi conducting Water Swellable tape | CB19: SEMICON TAPE | CC19: GLASS FIBER TAPE | CD19: COPPER WIRE 0.8 MM | CE19: RUBBERIZED COTTON TAPE | CF19: Water Tight Compound | CG19: PROPOSE DRUM TYPE | CH19: DRUM CODE | CI19: DRUM SIZE (FxbXtx Ft) | CJ19: PARTY STANDARD LENGTH (MTR) | CO19: MFG% | CP19: MFG VALUE | CQ19: PROF% | CR19: PROFIT VALUE | CS19: 1ST EX-WORKS | CT19: Intt % | CU19: INTT VALUE | CV19: insp% | CW19: INSP VALUE | CX19: TTR Charges% | CY19: TTR Charges VALUE
N20: 450 | O20: =+IFERROR(VLOOKUP($O$19,Sheet1!J:L,2,0),0) -> 0 | P20: =+IFERROR(VLOOKUP($P$19,Sheet1!J:M,2,0),0) -> 0 | Q20: =+IFERROR(VLOOKUP($Q$19,Sheet1!J:M,2,0),0) -> 0 | R20: =+IFERROR(VLOOKUP($R$19,Sheet1!J:M,2,0),0) -> 0 | S20: =+IFERROR(VLOOKUP($S$19,Sheet1!J:M,2,0),0) -> 0 | T20: =+IFERROR(VLOOKUP($T$19,Sheet1!J:M,2,0),0) -> 0 | U20: =+IFERROR(VLOOKUP($U$19,Sheet1!J:M,2,0),0) -> 0 | V20: =+IFERROR(VLOOKUP($V$19,Sheet1!N:Q,2,0),0) -> 0 | W20: =+IFERROR(VLOOKUP($W$19,Sheet1!N:O,2,0),0) -> 0 | X20: =+IFERROR(VLOOKUP($X$19,Sheet1!F:I,2,0),0) -> 0 | Y20: =+IFERROR(VLOOKUP($Y$19,Sheet1!F:I,2,0),0) -> 0 | Z20: =+IFERROR(VLOOKUP($Z$19,Sheet1!F:I,2,0),0) -> 0 | AA20: =+IFERROR(VLOOKUP($AA$19,Sheet1!F:I,2,0),0) -> 0 | AB20: =+IFERROR(VLOOKUP($AB$19,Sheet1!F:I,2,0),0) -> 0 | AC20: =+IFERROR(VLOOKUP($AC$19,Sheet1!F:I,2,0),0) -> 0 | AD20: =+IFERROR(VLOOKUP($AD$19,Sheet1!F:I,2,0),0) -> 0 | AE20: =+IFERROR(VLOOKUP($AE$19,Sheet1!F:I,2,0),0) -> 0 | AF20: =+IFERROR(VLOOKUP($AF$19,Sheet1!R:U,2,0),0) -> 0 | AG20: =+IFERROR(VLOOKUP($AG$19,Sheet1!R:U,2,0),0) -> 0 | AH20: =+IFERROR(VLOOKUP($AH$19,Sheet1!V:Y,2,0),0) -> 0 | AI20: =+IFERROR(VLOOKUP($AI$19,Sheet1!V:Y,2,0),0) -> 0 | AJ20: =+IFERROR(VLOOKUP($AJ$19,Sheet1!V:Y,2,0),0) -> 0 | AK20: =+IFERROR(VLOOKUP($AK$19,Sheet1!V:Y,2,0),0) -> 0 | AL20: =+IFERROR(VLOOKUP($AL$19,Sheet1!V:Y,2,0),0) -> 0 | AM20: =+IFERROR(VLOOKUP($AM$19,Sheet1!V:Y,2,0),0) -> 0 | AN20: =+IFERROR(VLOOKUP($AN$19,Sheet1!V:Y,2,0),0) -> 0 | AO20: =+IFERROR(VLOOKUP($AO$19,Sheet1!V:Y,2,0),0) -> 0 | AP20: =+IFERROR(VLOOKUP($AP$19,Sheet1!V:Y,2,0),0) -> 0 | AQ20: =+IFERROR(VLOOKUP($AQ$19,Sheet1!Z2:AA840,2,0),0) -> 0 | AR20: =+IFERROR(VLOOKUP($AR$19,Sheet1!AD2:AG840,2,0),0) -> 0 | AS20: =+IFERROR(VLOOKUP($AS$19,Sheet1!AD2:AG840,2,0),0) -> 0 | AT20: =+IFERROR(VLOOKUP($AT$19,Sheet1!AD2:AG840,2,0),0) -> 0 | AU20: =+IFERROR(VLOOKUP($AU$19,Sheet1!AD2:AG840,2,0),0) -> 0 | AV20: =+IFERROR(VLOOKUP($AV$19,Sheet1!AD2:AG840,2,0),0) -> 0 | AW20: =+IFERROR(VLOOKUP($AW$19,Sheet1!AD2:AG840,2,0),0) -> 0 | AX20: =+IFERROR(VLOOKUP($AX$19,Sheet1!AD2:AG840,2,0),0) -> 0 | AY20: =+IFERROR(VLOOKUP($AY$19,Sheet1!AD2:AG840,2,0),0) -> 0 | AZ20: =+IFERROR(VLOOKUP($AZ$19,Sheet1!AD2:AG840,2,0),0) -> 0 | BA20: 84 | BB20: =+IFERROR(VLOOKUP($BB$19,Sheet1!AH2:AK840,2,0),0) -> 0 | BC20: =+IFERROR(VLOOKUP($BC$19,Sheet1!AH2:AK840,2,0),0) -> 0 | BD20: =+IFERROR(VLOOKUP($BD$19,Sheet1!AH2:AK840,2,0),0) -> 0 | BE20: =+IFERROR(VLOOKUP($BE$19,Sheet1!AH2:AK840,2,0),0) -> 0 | BF20: =+IFERROR(VLOOKUP($BF$19,Sheet1!AH2:AK840,2,0),0) -> 0 | BG20: =+IFERROR(VLOOKUP($BG$19,Sheet1!AH2:AK840,2,0),0) -> 0 | BH20: =+IFERROR(VLOOKUP($BH$19,Sheet1!AH2:AK840,2,0),0) -> 0 | BI20: =+IFERROR(VLOOKUP($BI$19,Sheet1!AH2:AK840,2,0),0) -> 0 | BJ20: =+IFERROR(VLOOKUP($BJ$19,Sheet1!AH2:AK840,2,0),0) -> 0 | BK20: =+IFERROR(VLOOKUP($BK$19,Sheet1!AH2:AK840,2,0),0) -> 0 | BL20: =+IFERROR(VLOOKUP($BL$19,Sheet1!AL2:AO840,2,0),0) -> 0 | BM20: =+IFERROR(VLOOKUP($BM$19,Sheet1!AL2:AO840,2,0),0) -> 0 | BN20: =+IFERROR(VLOOKUP($BN$19,Sheet1!AL2:AO840,2,0),0) -> 0 | BO20: =+IFERROR(VLOOKUP($BO$19,Sheet1!AL2:AO840,2,0),0) -> 0 | BP20: =+IFERROR(VLOOKUP($BP$19,Sheet1!AL2:AO840,2,0),0) -> 0 | BQ20: =+IFERROR(VLOOKUP($BQ$19,Sheet1!AL2:AO840,2,0),0) -> 0 | BR20: =+IFERROR(VLOOKUP($BR$19,Sheet1!AL2:AO840,2,0),0) -> 0 | BS20: =+IFERROR(VLOOKUP($BS$19,Sheet1!AL2:AO840,2,0),0) -> 0 | BT20: =+IFERROR(VLOOKUP($BT$19,Sheet1!AL2:AO840,2,0),0) -> 0 | BU20: =+IFERROR(VLOOKUP($BU$19,Sheet1!AL2:AO840,2,0),0) -> 0 | BV20: =+IFERROR(VLOOKUP($BV$19,Sheet1!AL2:AO840,2,0),0) -> 0 | BW20: =+IFERROR(VLOOKUP($BW$19,Sheet1!AL2:AO840,2,0),0) -> 0 | BX20: =+IFERROR(VLOOKUP($BX$19,Sheet1!AP2:AS840,2,0),0) -> 0 | BY20: 213 | BZ20: =+IFERROR(VLOOKUP($BZ$19,Sheet1!AX2:BA840,2,0),0) -> 0 | CA20: =+IFERROR(VLOOKUP($CA$19,Sheet1!BB2:BE840,2,0),0) -> 0 | CB20: =+IFERROR(VLOOKUP($CB$19,Sheet1!BF2:BI840,2,0),0) -> 0 | CC20: =+IFERROR(VLOOKUP($CC$19,Sheet1!BJ2:BM840,2,0),0) -> 0 | CD20: =+IFERROR(VLOOKUP($CD$19,Sheet1!BN2:BQ840,2,0),0) -> 0 | CE20: =+IFERROR(VLOOKUP($CE$19,Sheet1!BR2:BU840,2,0),0) -> 0 | CF20: =+IFERROR(VLOOKUP($CF$19,Sheet1!BV2:BY840,2,0),0) -> 0
A21: =Sheet1!A3 -> ENQ-19613-25-26 | B21: 46113 | C21: =Sheet1!C3 -> FC6100002 | D21: =Sheet1!D3 -> ACSR : MOOSE CONDUCTOR - 520 SQ. MM. (54/7/3.53) | E21: =CS21+CU21+CW21+CY21 -> 811377.89 | F21: =ROUNDUP(M27,0) -> 17188 | G21: =E21+F21 -> 828565.89 | H21: =Sheet1!CR3 -> 0.18 | I21: =G21*H21 -> 149141.86 | J21: =G21+I21 -> 977707.75 | K21: =Sheet1!CU3 -> 360 | L21: =Sheet1!CV3 -> KMS | M21: =J21*K21 -> 3.5197479e+08 | N21: =+IFERROR(VLOOKUP($N$19,Sheet1!J3:L3,3,0),0) -> 1467 | O21: =+IFERROR(VLOOKUP($O$19,Sheet1!J3:L3,3,0),0) -> 0 | P21: =+IFERROR(VLOOKUP($P$19,Sheet1!J3:M3,3,0),0) -> 0 | Q21: =+IFERROR(VLOOKUP($Q$19,Sheet1!J3:M3,3,0),0) -> 0 | R21: =+IFERROR(VLOOKUP($R$19,Sheet1!J3:M3,3,0),0) -> 0 | S21: =+IFERROR(VLOOKUP($S$19,Sheet1!J3:M3,3,0),0) -> 0 | T21: =+IFERROR(VLOOKUP($T$19,Sheet1!J3:M3,3,0),0) -> 0 | U21: =+IFERROR(VLOOKUP($U$19,Sheet1!J3:M3,3,0),0) -> 0 | V21: =+IFERROR(VLOOKUP($V$19,Sheet1!N3:Q3,3,0),0) -> 0 | W21: =+IFERROR(VLOOKUP($W$19,Sheet1!N3:Q3,3,0),0) -> 0 | X21: =+IFERROR(VLOOKUP($X$19,Sheet1!F3:I3,3,0),0) -> 0 | Y21: =+IFERROR(VLOOKUP($Y$19,Sheet1!F3:I3,3,0),0) -> 0 | Z21: =+IFERROR(VLOOKUP($Z$19,Sheet1!F3:I3,3,0),0) -> 0 | AA21: =+IFERROR(VLOOKUP($AA$19,Sheet1!F3:I3,3,0),0) -> 0 | AB21: =+IFERROR(VLOOKUP($AB$19,Sheet1!F3:I3,3,0),0) -> 0 | AC21: =+IFERROR(VLOOKUP($AC$19,Sheet1!F3:I3,3,0),0) -> 0 | AD21: =+IFERROR(VLOOKUP($AD$19,Sheet1!F3:I3,3,0),0) -> 0 | AE21: =+IFERROR(VLOOKUP($AE$19,Sheet1!F3:I3,3,0),0) -> 0 | AF21: =+IFERROR(VLOOKUP($AF$19,Sheet1!R3:U3,3,0),0) -> 0 | AG21: =+IFERROR(VLOOKUP($AG$19,Sheet1!R3:U3,3,0),0) -> 0 | AH21: =+IFERROR(VLOOKUP($AH$19,Sheet1!V3:Y3,3,0),0) -> 0 | AI21: =+IFERROR(VLOOKUP($AI$19,Sheet1!V3:Y3,3,0),0) -> 0 | AJ21: =+IFERROR(VLOOKUP($AJ$19,Sheet1!V3:Y3,3,0),0) -> 0 | AK21: =+IFERROR(VLOOKUP($AK$19,Sheet1!V3:Y3,3,0),0) -> 0 | AL21: =+IFERROR(VLOOKUP($AL$19,Sheet1!V3:Y3,3,0),0) -> 0 | AM21: =+IFERROR(VLOOKUP($AM$19,Sheet1!V3:Y3,3,0),0) -> 0 | AN21: =+IFERROR(VLOOKUP($AN$19,Sheet1!V3:Y3,3,0),0) -> 0 | AO21: =+IFERROR(VLOOKUP($AO$19,Sheet1!V3:Y3,3,0),0) -> 0 | AP21: =+IFERROR(VLOOKUP($AP$19,Sheet1!V3:Y3,3,0),0) -> 0 | AQ21: =+IFERROR(VLOOKUP($AQ$19,Sheet1!Z3:AB3,3,0),0) -> 0 | AR21: =+IFERROR(VLOOKUP($AR$19,Sheet1!AD3:AG3,3,0),0) -> 0 | AS21: =+IFERROR(VLOOKUP($AS$19,Sheet1!AD3:AG3,3,0),0) -> 0 | AT21: =+IFERROR(VLOOKUP($AT$19,Sheet1!AD3:AG3,3,0),0) -> 0 | AU21: =+IFERROR(VLOOKUP($AU$19,Sheet1!AD3:AG3,3,0),0) -> 0 | AV21: =+IFERROR(VLOOKUP($AV$19,Sheet1!AD3:AG3,3,0),0) -> 0 | AW21: =+IFERROR(VLOOKUP($AW$19,Sheet1!AD3:AG3,3,0),0) -> 0 | AX21: =+IFERROR(VLOOKUP($AX$19,Sheet1!AD3:AG3,3,0),0) -> 0 | AY21: =+IFERROR(VLOOKUP($AY$19,Sheet1!AD3:AG3,3,0),0) -> 0 | AZ21: =+IFERROR(VLOOKUP($AZ$19,Sheet1!AD3:AG3,3,0),0) -> 0 | BA21: =+IFERROR(VLOOKUP($BA$19,Sheet1!AH3:AK3,3,0),0) -> 537 | BB21: =+IFERROR(VLOOKUP($BB$19,Sheet1!AH3:AK3,3,0),0) -> 0 | BC21: =+IFERROR(VLOOKUP($BC$19,Sheet1!AH3:AK3,3,0),0) -> 0 | BD21: =+IFERROR(VLOOKUP($BD$19,Sheet1!AH3:AK3,3,0),0) -> 0 | BE21: =+IFERROR(VLOOKUP($BE$19,Sheet1!AH3:AK3,3,0),0) -> 0 | BF21: =+IFERROR(VLOOKUP($BF$19,Sheet1!AH3:AK3,3,0),0) -> 0 | BG21: =+IFERROR(VLOOKUP($BG$19,Sheet1!AH3:AK3,3,0),0) -> 0 | BH21: =+IFERROR(VLOOKUP($BH$19,Sheet1!AH3:AK3,3,0),0) -> 0 | BI21: =+IFERROR(VLOOKUP($BI$19,Sheet1!AH3:AK3,3,0),0) -> 0 | BJ21: =+IFERROR(VLOOKUP($BJ$19,Sheet1!AH3:AK3,3,0),0) -> 0 | BK21: =+IFERROR(VLOOKUP($BK$19,Sheet1!AH3:AK3,3,0),0) -> 0 | BL21: =+IFERROR(VLOOKUP($BL$19,Sheet1!AL3:AO3,3,0),0) -> 0 | BM21: =+IFERROR(VLOOKUP($BM$19,Sheet1!AL3:AO3,3,0),0) -> 0 | BN21: =+IFERROR(VLOOKUP($BN$19,Sheet1!AL3:AO3,3,0),0) -> 0 | BO21: =+IFERROR(VLOOKUP($BO$19,Sheet1!AL3:AO3,3,0),0) -> 0 | BP21: =+IFERROR(VLOOKUP($BP$19,Sheet1!AL3:AO3,3,0),0) -> 0 | BQ21: =+IFERROR(VLOOKUP($BQ$19,Sheet1!AL3:AO3,3,0),0) -> 0 | BR21: =+IFERROR(VLOOKUP($BR$19,Sheet1!AL3:AO3,3,0),0) -> 0 | BS21: =+IFERROR(VLOOKUP($BS$19,Sheet1!AL3:AO3,3,0),0) -> 0 | BT21: =+IFERROR(VLOOKUP($BT$19,Sheet1!AL3:AO3,3,0),0) -> 0 | BU21: =+IFERROR(VLOOKUP($BU$19,Sheet1!AL3:AO3,3,0),0) -> 0 | BV21: =+IFERROR(VLOOKUP($BV$19,Sheet1!AL3:AO3,3,0),0) -> 0 | BW21: =+IFERROR(VLOOKUP($BW$19,Sheet1!AL3:AO3,3,0),0) -> 0 | BX21: =+IFERROR(VLOOKUP($BX$19,Sheet1!AP3:AS3,3,0),0) -> 0 | BY21: 72 | BZ21: =+IFERROR(VLOOKUP($BZ$19,Sheet1!AX3:BA3,3,0),0) -> 0 | CA21: =+IFERROR(VLOOKUP($CA$19,Sheet1!BB3:BE3,3,0),0) -> 0 | CB21: =+IFERROR(VLOOKUP($CB$19,Sheet1!BF3:BI3,3,0),0) -> 0 | CC21: =+IFERROR(VLOOKUP($CC$19,Sheet1!BJ3:BM3,3,0),0) -> 0 | CD21: =+IFERROR(VLOOKUP($CD$19,Sheet1!BN3:BQ3,3,0),0) -> 0 | CE21: =+IFERROR(VLOOKUP($CE$19,Sheet1!BR3:BU3,3,0),0) -> 0 | CF21: =+IFERROR(VLOOKUP($CF$19,Sheet1!BV3:BY3,3,0),0) -> 0 | CG21: STEEL | CH21: SP0400139 | CI21: CORRUGATED DISPATCH STEEL DRUM 2130 X 890 X 965 | CJ21: 2000 | CK21: =17600/2 -> 8800 | CL21: =SUMPRODUCT($N$20:$CF$20,N21:CF21)+CK21 -> 729394 | CM21: =Sheet1!CB3 -> 0 | CN21: =CL21*CM21 -> 0 | CO21: 0.08 | CP21: =CL21*CO21 -> 58351.52 | CQ21: 0 | CR21: =CL21*CQ21 -> 0 | CS21: =CL21+CN21+CP21+CR21 -> 787745.52 | CT21: 0.02 | CU21: =CS21*CT21 -> 15754.91 | CV21: 0.01 | CW21: =CS21*CV21 -> 7877.4552 | CX21: =Sheet1!CM3 -> 0 | CY21: =CX21*CS21 -> 0
A22: =Sheet1!A2 -> ENQ-19613-25-26 | B22: 46113 | C22: =Sheet1!C2 -> FC3700003 | D22: =Sheet1!D2 -> ACSR : PANTHER CONDUCTOR - 200 SQ. MM. (30/7/3.00) | E22: =CS22+CU22+CW22+CY22 -> 342023.7 | F22: =ROUNDUP(M28,0) -> 7219 | G22: =E22+F22 -> 349242.7 | H22: =Sheet1!CR2 -> 0.18 | I22: =G22*H22 -> 62863.685 | J22: =G22+I22 -> 412106.38 | K22: =Sheet1!CU2 -> 20 | L22: =Sheet1!CV2 -> KMS | M22: =J22*K22 -> 8242127.6 | N22: 590 | O22: =+IFERROR(VLOOKUP($O$19,Sheet1!J2:L2,3,0),0) -> 0 | P22: =+IFERROR(VLOOKUP($P$19,Sheet1!J2:M2,3,0),0) -> 0 | Q22: =+IFERROR(VLOOKUP($Q$19,Sheet1!J2:M2,3,0),0) -> 0 | R22: =+IFERROR(VLOOKUP($R$19,Sheet1!J2:M2,3,0),0) -> 0 | S22: =+IFERROR(VLOOKUP($S$19,Sheet1!J2:M2,3,0),0) -> 0 | T22: =+IFERROR(VLOOKUP($T$19,Sheet1!J2:M2,3,0),0) -> 0 | U22: =+IFERROR(VLOOKUP($U$19,Sheet1!J2:M2,3,0),0) -> 0 | V22: =+IFERROR(VLOOKUP($V$19,Sheet1!N2:Q2,3,0),0) -> 0 | W22: =+IFERROR(VLOOKUP($W$19,Sheet1!N2:Q2,3,0),0) -> 0 | X22: =+IFERROR(VLOOKUP($X$19,Sheet1!F2:I2,3,0),0) -> 0 | Y22: =+IFERROR(VLOOKUP($Y$19,Sheet1!F2:I2,3,0),0) -> 0 | Z22: =+IFERROR(VLOOKUP($Z$19,Sheet1!F2:I2,3,0),0) -> 0 | AA22: =+IFERROR(VLOOKUP($AA$19,Sheet1!F2:I2,3,0),0) -> 0 | AB22: =+IFERROR(VLOOKUP($AB$19,Sheet1!F2:I2,3,0),0) -> 0 | AC22: =+IFERROR(VLOOKUP($AC$19,Sheet1!F2:I2,3,0),0) -> 0 | AD22: =+IFERROR(VLOOKUP($AD$19,Sheet1!F2:I2,3,0),0) -> 0 | AE22: =+IFERROR(VLOOKUP($AE$19,Sheet1!F2:I2,3,0),0) -> 0 | AF22: =+IFERROR(VLOOKUP($AF$19,Sheet1!R2:U2,3,0),0) -> 0 | AG22: =+IFERROR(VLOOKUP($AG$19,Sheet1!R2:U2,3,0),0) -> 0 | AH22: =+IFERROR(VLOOKUP($AH$19,Sheet1!V2:Y2,3,0),0) -> 0 | AI22: =+IFERROR(VLOOKUP($AI$19,Sheet1!V2:Y2,3,0),0) -> 0 | AJ22: =+IFERROR(VLOOKUP($AJ$19,Sheet1!V2:Y2,3,0),0) -> 0 | AK22: =+IFERROR(VLOOKUP($AK$19,Sheet1!V2:Y2,3,0),0) -> 0 | AL22: =+IFERROR(VLOOKUP($AL$19,Sheet1!V2:Y2,3,0),0) -> 0 | AM22: =+IFERROR(VLOOKUP($AM$19,Sheet1!V2:Y2,3,0),0) -> 0 | AN22: =+IFERROR(VLOOKUP($AN$19,Sheet1!V2:Y2,3,0),0) -> 0 | AO22: =+IFERROR(VLOOKUP($AO$19,Sheet1!V2:Y2,3,0),0) -> 0 | AP22: =+IFERROR(VLOOKUP($AP$19,Sheet1!V2:Y2,3,0),0) -> 0 | AQ22: =+IFERROR(VLOOKUP($AQ$19,Sheet1!Z2:AB2,3,0),0) -> 0 | AR22: =+IFERROR(VLOOKUP($AR$19,Sheet1!AD2:AG2,3,0),0) -> 0 | AS22: =+IFERROR(VLOOKUP($AS$19,Sheet1!AD2:AG2,3,0),0) -> 0 | AT22: =+IFERROR(VLOOKUP($AT$19,Sheet1!AD2:AG2,3,0),0) -> 0 | AU22: =+IFERROR(VLOOKUP($AU$19,Sheet1!AD2:AG2,3,0),0) -> 0 | AV22: =+IFERROR(VLOOKUP($AV$19,Sheet1!AD2:AG2,3,0),0) -> 0 | AW22: =+IFERROR(VLOOKUP($AW$19,Sheet1!AD2:AG2,3,0),0) -> 0 | AX22: =+IFERROR(VLOOKUP($AX$19,Sheet1!AD2:AG2,3,0),0) -> 0 | AY22: =+IFERROR(VLOOKUP($AY$19,Sheet1!AD2:AG2,3,0),0) -> 0 | AZ22: =+IFERROR(VLOOKUP($AZ$19,Sheet1!AD2:AG2,3,0),0) -> 0 | BA22: 390 | BB22: =+IFERROR(VLOOKUP($BB$19,Sheet1!AH2:AK2,3,0),0) -> 0 | BC22: =+IFERROR(VLOOKUP($BC$19,Sheet1!AH2:AK2,3,0),0) -> 0 | BD22: =+IFERROR(VLOOKUP($BD$19,Sheet1!AH2:AK2,3,0),0) -> 0 | BE22: =+IFERROR(VLOOKUP($BE$19,Sheet1!AH2:AK2,3,0),0) -> 0 | BF22: =+IFERROR(VLOOKUP($BF$19,Sheet1!AH2:AK2,3,0),0) -> 0 | BG22: =+IFERROR(VLOOKUP($BG$19,Sheet1!AH2:AK2,3,0),0) -> 0 | BH22: =+IFERROR(VLOOKUP($BH$19,Sheet1!AH2:AK2,3,0),0) -> 0 | BI22: =+IFERROR(VLOOKUP($BI$19,Sheet1!AH2:AK2,3,0),0) -> 0 | BJ22: =+IFERROR(VLOOKUP($BJ$19,Sheet1!AH2:AK2,3,0),0) -> 0 | BK22: =+IFERROR(VLOOKUP($BK$19,Sheet1!AH2:AK2,3,0),0) -> 0 | BL22: =+IFERROR(VLOOKUP($BL$19,Sheet1!AL2:AO2,3,0),0) -> 0 | BM22: =+IFERROR(VLOOKUP($BM$19,Sheet1!AL2:AO2,3,0),0) -> 0 | BN22: =+IFERROR(VLOOKUP($BN$19,Sheet1!AL2:AO2,3,0),0) -> 0 | BO22: =+IFERROR(VLOOKUP($BO$19,Sheet1!AL2:AO2,3,0),0) -> 0 | BP22: =+IFERROR(VLOOKUP($BP$19,Sheet1!AL2:AO2,3,0),0) -> 0 | BQ22: =+IFERROR(VLOOKUP($BQ$19,Sheet1!AL2:AO2,3,0),0) -> 0 | BR22: =+IFERROR(VLOOKUP($BR$19,Sheet1!AL2:AO2,3,0),0) -> 0 | BS22: =+IFERROR(VLOOKUP($BS$19,Sheet1!AL2:AO2,3,0),0) -> 0 | BT22: =+IFERROR(VLOOKUP($BT$19,Sheet1!AL2:AO2,3,0),0) -> 0 | BU22: =+IFERROR(VLOOKUP($BU$19,Sheet1!AL2:AO2,3,0),0) -> 0 | BV22: =+IFERROR(VLOOKUP($BV$19,Sheet1!AL2:AO2,3,0),0) -> 0 | BW22: =+IFERROR(VLOOKUP($BW$19,Sheet1!AL2:AO2,3,0),0) -> 0 | BX22: =+IFERROR(VLOOKUP($BX$19,Sheet1!AP2:AS2,3,0),0) -> 0 | BY22: 26 | BZ22: =+IFERROR(VLOOKUP($BZ$19,Sheet1!AX2:BA2,3,0),0) -> 0 | CA22: =+IFERROR(VLOOKUP($CA$19,Sheet1!BB2:BE2,3,0),0) -> 0 | CB22: =+IFERROR(VLOOKUP($CB$19,Sheet1!BF2:BI2,3,0),0) -> 0 | CC22: =+IFERROR(VLOOKUP($CC$19,Sheet1!BJ2:BM2,3,0),0) -> 0 | CD22: =+IFERROR(VLOOKUP($CD$19,Sheet1!BN2:BQ2,3,0),0) -> 0 | CE22: =+IFERROR(VLOOKUP($CE$19,Sheet1!BR2:BU2,3,0),0) -> 0 | CF22: =+IFERROR(VLOOKUP($CF$19,Sheet1!BV2:BY2,3,0),0) -> 0 | CG22: STEEL | CH22: SP0400125 | CI22: CORRUGATED DISPATCH STEEL DRUM 1600 X 700 X 915 MM | CJ22: 2400 | CK22: =8800/2.4 -> 3666.6667 | CL22: =SUMPRODUCT($N$20:$CF$20,N22:CF22)+CK22 -> 307464.67 | CM22: =Sheet1!CB2 -> 0 | CN22: =CL22*CM22 -> 0 | CO22: 0.08 | CP22: =CL22*CO22 -> 24597.173 | CQ22: 0 | CR22: =CL22*CQ22 -> 0 | CS22: =CL22+CN22+CP22+CR22 -> 332061.84 | CT22: 0.02 | CU22: =CS22*CT22 -> 6641.2368 | CV22: 0.01 | CW22: =CS22*CV22 -> 3320.6184 | CX22: =Sheet1!CM2 -> 0 | CY22: =CX22*CS22 -> 0
M23: =SUM(M21:M22) -> 3.6021692e+08
E26: Order Quantity | F26: Stnd Length | G26: Truck type | H26: Fare of one truck | I26: No of Drum in one truck | J26: Total length in one Truck | K26: No of Truck | L26: Total Freight | M26: Freight per KM | BA26: CONDUCTO WEIGHT KG/KM | BY26: DRUM WEIGHT | CG26: CONDUCTOR+DRUM WEIGHT | CH26: TRAOILOR WEIGHT
D27: =D21 -> ACSR : MOOSE CONDUCTOR - 520 SQ. MM. (54/7/3.53) | E27: =K21 -> 360 | F27: =CJ21/1000 -> 2 | G27: 25 MT TRAILOR | H27: =5500*25 -> 137500 | I27: 4 | J27: =F27*I27 -> 8 | K27: =ROUNDUP((E27/J27),0) -> 45 | L27: =H27*K27 -> 6187500 | M27: =L27/E27 -> 17187.5 | N27: =CH21 -> SP0400139 | BA27: =SUM(N21:BY21) -> 2076 | BY27: 320 | CG27: =((F27*BA27)+BY27) -> 4472 | CH27: =I27*CG27 -> 17888
D28: =D22 -> ACSR : PANTHER CONDUCTOR - 200 SQ. MM. (30/7/3.00) | E28: =K22 -> 20 | F28: =CJ22/1000 -> 2.4 | G28: 25 MT TRAILOR | H28: =5500*25 -> 137500 | I28: 8 | J28: =F28*I28 -> 19.2 | K28: =ROUNDUP((E28/J28),2) -> 1.05 | L28: =H28*K28 -> 144375 | M28: =L28/E28 -> 7218.75 | N28: =CH22 -> SP0400125 | BA28: =SUM(N22:BY22) -> 1006 | BY28: 160 | CG28: =((F28*BA28)+BY28) -> 2574.4 | CH28: =I28*CG28 -> 20595.2

Sheet PV AUTO CALCULATION SHEET
A2: New Price in Rs/KM (P1) = Old Price(P0) + (( Aı x Fı x(1+ Cd1)) - (Aо x Fo x (1+Cd0 )))*C + D*(B1-B0)
A3: P0 = Offered Base Price in INR/KM. A = EC grade Aluminium Ingots in USD/MT - LME. F = Exchange Rate in INR/USD. C = Weight of Aluminium in MT/KM. CD = Custom Duty. D = Weight of HTGS Wire in MT/KM. B = Price of HTGS Wire in INR/MT.
A4: Subscript ‘0’ = refers to base price, i.e. a) For Aluminium (A0) - CASH LME USD 4,200 Per MT. b) For Exchange Rate (F0) - Basic Average SBI TT SELL reference rate INR 99.00 Per USD. c) For Current Custom Duty including cess (CD0) - 8.25%. d) For Steel (B0) - For HTGS Domestic Price as per CACMAI Circular – April 2026
A7: Item | C7: Date of Inspection | D7: Applicable Date | I7: BASE DATE | N7: FACTORS | P7: Ex-Work Po | Q7: A1*f1*(1+CD1) | R7: A0*f0*(1+CD0) | S7: ((A1*F1*(1+Cd1))-(A0*F0*(1+Cd0))*C)) PVC per KM | T7: D*(B1-B0) | U7: Billing Price/PKM | V7: VALUE ADDITION CALCULATION
D8: Date | E8: A1 | F8: f1 | G8: Cd1 | H8: B1 | I8: Date | J8: Alo | K8: fo | L8: CD0 | M8: B0
N9: C | O9: D | V9: ='AUTO CALCULATION SHEET (2)'!N19 -> Alumimium | W9: ='AUTO CALCULATION SHEET (2)'!BA19 -> ACSR CORE WIRE | X9: ='AUTO CALCULATION SHEET (2)'!BY19 -> Grease | Y9: RMC | Z9: DRUM | AA9: RMC+DRUM | AB9: VA | AC9: GROSS VA% | AD9: MFG % | AE9: INT % | AF9: INS % | AG9: NET VA
V10: 410 | W10: 84 | X10: 220
A11: ='AUTO CALCULATION SHEET (2)'!D21 -> ACSR : MOOSE CONDUCTOR - 520 SQ. MM. (54/7/3.53) | C11: PROVISIONAL | D11: 46178 | E11: 3736 | F11: 95.75 | G11: 0.0825 | H11: 169250 | I11: Specify in tender document | J11: 4200 | K11: 99 | L11: 0.0825 | M11: 166750 | N11: 1.465 | O11: 0.539 | P11: ='AUTO CALCULATION SHEET (2)'!E21 -> 811377.89 | Q11: =E11*F11*(1+G11) -> 387234.07 | R11: =J11*K11*(1+L11) -> 450103.5 | S11: =(Q11-R11)*N11 -> -92103.722 | T11: =(H11-M11)*O11 -> 1347.5 | U11: =P11+S11+T11 -> 720621.66 | V11: ='AUTO CALCULATION SHEET (2)'!N21 -> 1467 | W11: ='AUTO CALCULATION SHEET (2)'!BA21 -> 537 | X11: ='AUTO CALCULATION SHEET (2)'!BY21 -> 72 | Y11: =SUMPRODUCT(V11:X11,$V$10:$X$10) -> 662418 | Z11: ='AUTO CALCULATION SHEET (2)'!CK21 -> 8800 | AA11: =Y11+Z11 -> 671218 | AB11: =+U11-AA11 -> 49403.663 | AC11: =AB11/U11*100% -> 0.068557005 | AE11: 0.02 | AF11: 0.01 | AG11: =AC11-SUM(AD11:AF11) -> 0.038557005
A12: ='AUTO CALCULATION SHEET (2)'!D22 -> ACSR : PANTHER CONDUCTOR - 200 SQ. MM. (30/7/3.00) | C12: PROVISIONAL | D12: 46178 | E12: 3736 | F12: 95.75 | G12: 0.0825 | H12: 169250 | I12: Specify in tender document | J12: 4200 | K12: 99 | L12: 0.0825 | M12: 166750 | N12: 0.586 | O12: 0.388 | P12: ='AUTO CALCULATION SHEET (2)'!E22 -> 342023.7 | Q12: =E12*F12*(1+G12) -> 387234.07 | R12: =J12*K12*(1+L12) -> 450103.5 | S12: =(Q12-R12)*N12 -> -36841.489 | T12: =(H12-M12)*O12 -> 970 | U12: =P12+S12+T12 -> 306152.21 | V12: ='AUTO CALCULATION SHEET (2)'!N22 -> 590 | W12: ='AUTO CALCULATION SHEET (2)'!BA22 -> 390 | X12: ='AUTO CALCULATION SHEET (2)'!BY22 -> 26 | Y12: =SUMPRODUCT(V12:X12,$V$10:$X$10) -> 280380 | Z12: ='AUTO CALCULATION SHEET (2)'!CK22 -> 3666.6667 | AA12: =Y12+Z12 -> 284046.67 | AB12: =+U12-AA12 -> 22105.54 | AC12: =AB12/U12*100% -> 0.072204411 | AE12: 0.02 | AF12: 0.01 | AG12: =AC12-SUM(AD12:AF12) -> 0.042204411

Sheet terms
A1: The quoted prices are on Firm inclusive of packing and forwading but exclusive of GST Statutory levies.
A2: The quoted prices are on VARIABLE basis with PV base Date: DD/MM/YYYY as per "IEEMA", inclusive of packing and forwading but exclusive of GST Statutory levies.
A4: The above prices are quoted on Ex-works basis, where freight will be charged extra.
A5: The above prices are quoted on FOR Destination basis, where freight is included, refer Price offer.
A6: The above prices are quoted on Ex-works+Freight basis.
A8: 20% Advance and Balance against PI (Proforma Invoice) prior to dispatch
A9: 100% against "90 days" LC, where 90 days usance interest will be borne by LPIPL
A10: 100% against "120 days" LC, where 120 days usance interest will be borne by LPIPL
A11: 100% against "45 days" LC, where 45 days usance interest will be borne by LPIPL
A12: 100% against "60 days" LC, where 60 days usance interest will be borne by LPIPL
A13: 100% against "30 days" LC, where 30 days usance interest will be borne by LPIPL
A14: 100% against 60 days PDC from the date of MRC/MRN
... A27: Negotiable
