Workbook

Sheet Sheet1
A1: DOCKET NO. | B1: Base Date | C1: ITEM CODE | D1: PROPOSE ERP ITEM NAME | E1: Propose Drum Type | F1: Insulation Screening(Metallic) | G1: RM Rate(Insulation Screening(Metallic)) | H1: Weight (Insulation Screening (Metallic)) | I1: Cost Insulation Screening(Metallic) | J1: Conductor | K1: RM Rate(Conductor) | L1: Weight(Conductor) | M1: Cost(Conductor) | N1: AL ALLOY | O1: RM Rate(AL Alloy) | P1: Weight(Al Alloy) | Q1: Cost(AL Alloy) | R1: Insulation Screening(Non-Metallic) | S1: RM Rate(Insulation Screening(Non-Metallic)) | T1: Weight(Insulation Screening(Non-Metallic) | U1: Cost(Insulation Screening(Non-Metallic) | V1: Insulation | W1: RM Rate(Insulation) | X1: Weight(Insulation) | Y1: Cost(Insulation) | Z1: Poly Tape | AA1: RM Rate(Poly Tape) | AB1: Weight(Poly Tape) | AC1: Cost(Poly Tape) | AD1: Inner Sheath | AE1: RM Rate(Inner Sheath) | AF1: Weight(Inner Sheath) | AG1: Cost(Inner Sheath) | AH1: Armouring | AI1: RM Rate(Armouring) | AJ1: Weight(Armouring) | AK1: Cost(Armouring) | AL1: Outer Sheath | AM1: RM Rate(Outer Sheath) | AN1: Weight(Outer Sheath) | AO1: Cost(Outer Sheath) | AP1: Filler | AQ1: RM Rate(Filler) | AR1: Weight(Filler) | AS1: Cost(Filler) | AT1: Grease | AU1: RM Rate(Grease) | AV1: Weight(Grease) | AW1: Cost(Grease) | AX1: Water Swellable Tape | AY1: RM Rate(Water Swellable Tape) | AZ1: Weight(Water Swellable Tape) | BA1: Cost(Water Swellable Tape) | BB1: Semi Conducting Water Swellable Tape | BC1: RM Rate(Semi Conducting Water Swellable Tape) | BD1: Weight(Semi Conducting Water Swellable Tape) | BE1: Cost(Semi Conducting Water Swellable Tape) | BF1: Semicon Tape | BG1: RM Rate(Semicon Tape) | BH1: Weight(Semicon Tape) | BI1: Cost(Semicon Tape) | BJ1: Glass Fiber Tape | BK1: RM Rate(Glass Fiber Tape) | BL1: Weight(Glass Fiber Tape) | BM1: Cost(Glass Fiber Tape) | BN1: Copper Wire 0.8MM | BO1: RM Rate(Copper Wire 0.8MM) | BP1: Weight(Copper Wire 0.8MM) | BQ1: Cost(Copper Wire 0.8MM) | BR1: Rubberized Cotton Tape | BS1: RM Rate(Rubberized Cotton Tape) | BT1: Weight(Rubberized Cotton Tape) | BU1: Cost(Rubberized Cotton Tape) | BV1: Water Tight Compound | BW1: RM Rate(Water Tight Compound) | BX1: Weight(Water Tight Compound) | BY1: Cost(Water Tight Compound) | BZ1: Drum Cost Per KM | CA1: Total RM Cost | CB1: FIRM % | CC1: Firm Value | CD1: MFG% | CE1: MFG Value | CF1: PROF% | CG1: Profit Value | CH1: 1st EX-Works | CI1: Intt % | CJ1: Intt Value | CK1: insp% | CL1: Insp Value | CM1: TTR CHARGES% | CN1: TTR Value | CO1: EX-Works Per KM | CP1: Freight Per KM | CQ1: Price Including Freight Per KM | CR1: GST % | CS1: GST Value | CT1: Price Including GST & Freight Per KM | CU1: QTY | CV1: Unit | CW1: Total Price Of Full QTY(Including Freight&GST) | CX1: PARTY LENGTH (IF STANDER LENGTH NOT MATCH WITH PAR | CY1: DRUM CODE | CZ1: DRUM SIZE (FxbXtx Ft)
A2: ENQ-18639-25-26 | C2: FA1300001 | D2: 3 CORE X 120 SQ. MM. AL/ARM - STRIP (XLPE) - 11 KV | E2: WOOD | F2: Copper Tape - 0.03 mm | H2: 66 | J2: Alumimium | L2: 972 | P2: 0 | R2: Extruded Semiconductive | T2: 233 | V2: HT-XLPE | X2: 564 | AB2: 0 | AD2: PVC Type ST-2 | AF2: 185 | AH2: Galvanised Steel Flat Strip | AJ2: 850 | AL2: PVC Type ST-2 | AN2: 630 | AP2: FILLER | AR2: 704 | AV2: 0 | AZ2: 0 | BD2: 0 | BH2: 0 | BL2: 74 | BP2: 0 | BR2: RUBBERIZED COTTON TAPE | BT2: 0 | BX2: 0 | BZ2: 41942 | CA2: 41942 | CH2: 41942 | CO2: 41942 | CQ2: 41942 | CR2: 0.18 | CS2: 7549.56 | CT2: 49491.56 | CU2: 100 | CV2: KMS | CW2: 4949156 | CX2: 500 | CY2: MD0100029 | CZ2: DRUM - 80 X 35 X 39 X 3"+ EXTRA SEGMENT
A3: ENQ-18639-25-26 | C3: FA1300002 | D3: 3 CORE X 185 SQ. MM AL/ARM - STRIP (XLPE) - 11 KV | E3: WOOD | F3: Copper Tape - 0.03 mm | H3: 75 | J3: Alumimium | L3: 1499 | P3: 0 | R3: Extruded Semiconductive | T3: 276 | V3: HT-XLPE | X3: 663 | AB3: 0 | AD3: PVC Type ST-2 | AF3: 237 | AH3: Galvanised Steel Flat Strip | AJ3: 975 | AL3: PVC Type ST-2 | AN3: 755 | AP3: FILLER | AR3: 914 | AV3: 0 | AZ3: 92 | BD3: 0 | BH3: 0 | BL3: 72 | BP3: 0 | BR3: RUBBERIZED COTTON TAPE | BT3: 0 | BX3: 0 | BZ3: 43820 | CA3: 43820 | CH3: 43820 | CO3: 43820 | CQ3: 43820 | CR3: 0.18 | CS3: 7887.6 | CT3: 51707.6 | CU3: 600 | CV3: KMS | CW3: 31024560 | CX3: 250 | CY3: MD0100023 | CZ3: DRUM - 68 X 34 X 36 X 3

Sheet AUTO CALCULATION SHEET (2)
A2: JAIPUR VIDYUT VITRAN NIGAM LIMITED (JVVNL)
A4: TENDER SPECIFICATION NO () | B4: TN-5028 (2026_JVVNL_537588_2)
A5: TENDER DESCRIPTION () | B5: 11 KV, 3CX185 Sq.mm and 3CX120 Sq.mm ALUMINIUM CONDUCTOR SCREENED CROSS-LINKED POLYETHYLENE (XLPE) INSULATED ARMOURED SHIELDED PVC SHEATHED POWER CABLE
A6: Last Date & Time of Submission () | B6: 09-Mar-2026 05:00 PM OPENING ON 10-Mar-2026 03:00 PM
A7: REVERSE AUCTION | B7: Not Mention
A8: Price () | B8: The prices quoted shall be variable as per PV formula given in the specification at Schedule-II without any ceiling with Base Date as 01.02.2026 The Price Variation shall be governed by Clause No. 1.10 of Section-I (Instruction to Bidder).
A9: Validity () | B9: 120 DAYS FROM THE NEXT DATE OF OPENING OF TECHNO-COMMERCIAL BID
A10: Delivery Period () | B10: Commencement : After 30 days from the date of receipt of purchase order. Completion : In Six months thereafter at equal monthly rate.
A11: Payment Terms () | B11: 1. The 70% payment shall be released after receipt of successful Test reports from CTL, Jaipur for the mandatory test checking on the samples selected from the material received at stores against first lot and subsequent lot(s) in anticipation of successful type test reports. 2. The balance 30% payment shall be released after receipt of successful type test reports on the samples selected from the material received in the stores.
A12: Standard length () | B12: The cable shall be supplied in standard length of 250 Mtrs in one Drum for size 11 KV, 3CX185 Sq.mm , and 500 Mtrs in one Drum for 3Cx120 Sq.mm .
A13: Packing () | B13: The cable shall be wound on a non returnable wooden drum conforming to IS: 10418/1982 of suitable size.
A14: Technical Specification
N17: Conductor | V17: AL ALLOY | X17: Insulation Screening (Metallic) | AF17: Insulation Screening (Non-Metallic) | AH17: Insulation | AQ17: POLY TAPE | AR17: Inner Sheath | BA17: Armouring | BL17: Outer Sheath | BX17: FILLER | BY17: GREASE | BZ17: Water swellable Tape | CA17: Semi conducting Water Swellable tape | CB17: SEMICON TAPE | CC17: GLASS FIBER TAPE | CD17: COPPER WIRE 0.8 MM | CE17: RUBBERIZED COTTON TAPE | CF17: Water Tight Compound | CG17: DRUM TYPE | CK17: DRUM COST PER KM | CL17: TOTAL RM COST | CM17: EXTRA CONSUMPTION | CN17: EXTRA CONSUMPTION VALUE | CZ17: $A$1
A18: DOCKET NO. | B18: BASE DATE | C18: ITEM CODE | D18: PROPOSE ERP ITEM NAME | E18: EX-WORKS (PER KM) | F18: FREIGHT PER KM | G18: PRICE INCLUDING FREIGHT (PER KM) | H18: GST % | I18: GST VALUE | J18: PRICE INCLUDING GST & FREIGHT (PER KM) | K18: QTY | L18: Unit | M18: TOTAL PRICE OF FULL QTY (INCLUDING FRIGHT & GST) | N18: Alumimium | O18: Alumimium ALLOY | P18: Copper | Q18: AL-59 | R18: AL-4 | S18: AL-7 | T18: Flexible Copper | U18: Galvanized steel wire | V18: Alumimium | W18: Alumimium ALLOY | X18: Coper tape - 0.1 mm | Y18: Copper Tape - 0.03 mm | Z18: Copper Tape - 0.035 mm | AA18: Copper Tape - 0.04 mm | AB18: Copper Tape - 0.045 mm | AC18: Copper Tape - 0.050 mm | AD18: Copper Tape - 0.060 mm | AE18: Copper Tape - 0.075 mm(DOUBLE) | AF18: Extruded semiconductive | AG18: Extruded Semiconductive(Stripable) | AH18: HT-XLPE | AI18: LT-XLPE | AJ18: TR XLPE | AK18: Type A PVC | AL18: Type C PVC (HR) | AM18: Type A PVC-1.45 | AN18: Type A PVC-FR | AO18: Type A PVC-FRLS | AP18: Type A PVC-1.38 | AQ18: POLY TAPE | AR18: FR PVC Type ST-1 | AS18: FR PVC Type ST-2 | AT18: FRLSH PVC Type ST-1 | AU18: FRLSH PVC Type ST-2 | AV18: PVC Type ST-1 | AW18: PVC Type ST-1-PRESSURE EXTRUDED | AX18: PVC Type ST-2 | AY18: PVC COMPOUND 1.48 | AZ18: PVC Type ST-2-PRESSURE EXTRUDED | BA18: ACSR CORE WIRE | BB18: ACSR DOG STEEL WIRE | BC18: Aluminium Flat Strip | BD18: Aluminium Round Wire | BE18: Alumimium Tape | BF18: Double Steel Tape | BG18: Galvanised Steel Flat Strip | BH18: Galvanised Steel Flat Strip (Double) | BI18: Galvanised Steel Flat Strip-B | BJ18: Galvanised Steel Round Wire | BK18: Galvanised Steel Round Wire (Double) | BL18: FR PVC Type ST-1 | BM18: FR PVC Type ST-2 | BN18: FRLSH PVC Type ST-1 | BO18: FRLSH PVC Type ST-2 | BP18: ZHFR | BQ18: PE-ST-3 | BR18: PE-ST-7 | BS18: PVC Type ST-1 | BT18: PVC Type ST-2 | BU18: PVC COMPOUND 1.48 | BV18: PVC Type ST-2-PRESSURE EXTRUDED | BW18: UV & Track Resistant XLPE | BX18: FILLER | BY18: Grease | BZ18: Water swellable Tape | CA18: Semi conducting Water Swellable tape | CB18: SEMICON TAPE | CC18: GLASS FIBER TAPE | CD18: COPPER WIRE 0.8 MM | CE18: RUBBERIZED COTTON TAPE | CF18: Water Tight Compound | CG18: PROPOSE DRUM TYPE | CH18: DRUM CODE | CI18: DRUM SIZE (FxbXtx Ft) | CJ18: PARTY STANDARD LENGTH (MTR) | CO18: MFG% | CP18: MFG VALUE | CQ18: PROF% | CR18: PROFIT VALUE | CS18: 1ST EX-WORKS | CT18: Intt % | CU18: INTT VALUE | CV18: insp% | CW18: INSP VALUE | CX18: TTR Charges% | CY18: TTR Charges VALUE
N19: 326 | O19: =+IFERROR(VLOOKUP($O$18,Sheet1!J:L,2,0),0) -> 0 | P19: =+IFERROR(VLOOKUP($P$18,Sheet1!J:M,2,0),0) -> 0 | Q19: =+IFERROR(VLOOKUP($Q$18,Sheet1!J:M,2,0),0) -> 0 | R19: =+IFERROR(VLOOKUP($R$18,Sheet1!J:M,2,0),0) -> 0 | S19: =+IFERROR(VLOOKUP($S$18,Sheet1!J:M,2,0),0) -> 0 | T19: =+IFERROR(VLOOKUP($T$18,Sheet1!J:M,2,0),0) -> 0 | U19: =+IFERROR(VLOOKUP($U$18,Sheet1!J:M,2,0),0) -> 0 | V19: =+IFERROR(VLOOKUP($V$18,Sheet1!N:Q,2,0),0) -> 0 | W19: =+IFERROR(VLOOKUP($W$18,Sheet1!N:O,2,0),0) -> 0 | X19: =+IFERROR(VLOOKUP($X$18,Sheet1!F:I,2,0),0) -> 0 | Y19: 1403 | Z19: =+IFERROR(VLOOKUP($Z$18,Sheet1!F:I,2,0),0) -> 0 | AA19: =+IFERROR(VLOOKUP($AA$18,Sheet1!F:I,2,0),0) -> 0 | AB19: =+IFERROR(VLOOKUP($AB$18,Sheet1!F:I,2,0),0) -> 0 | AC19: =+IFERROR(VLOOKUP($AC$18,Sheet1!F:I,2,0),0) -> 0 | AD19: =+IFERROR(VLOOKUP($AD$18,Sheet1!F:I,2,0),0) -> 0 | AE19: =+IFERROR(VLOOKUP($AE$18,Sheet1!F:I,2,0),0) -> 0 | AF19: 160 | AG19: =+IFERROR(VLOOKUP($AG$18,Sheet1!R:U,2,0),0) -> 0 | AH19: 125 | AI19: =+IFERROR(VLOOKUP($AI$18,Sheet1!V:Y,2,0),0) -> 0 | AJ19: =+IFERROR(VLOOKUP($AJ$18,Sheet1!V:Y,2,0),0) -> 0 | AK19: =+IFERROR(VLOOKUP($AK$18,Sheet1!V:Y,2,0),0) -> 0 | AL19: =+IFERROR(VLOOKUP($AL$18,Sheet1!V:Y,2,0),0) -> 0 | AM19: =+IFERROR(VLOOKUP($AM$18,Sheet1!V:Y,2,0),0) -> 0 | AN19: =+IFERROR(VLOOKUP($AN$18,Sheet1!V:Y,2,0),0) -> 0 | AO19: =+IFERROR(VLOOKUP($AO$18,Sheet1!V:Y,2,0),0) -> 0 | AP19: =+IFERROR(VLOOKUP($AP$18,Sheet1!V:Y,2,0),0) -> 0 | AQ19: =+IFERROR(VLOOKUP($AQ$18,Sheet1!Z2:AA840,2,0),0) -> 0 | AR19: =+IFERROR(VLOOKUP($AR$18,Sheet1!AD2:AG840,2,0),0) -> 0 | AS19: =+IFERROR(VLOOKUP($AS$18,Sheet1!AD2:AG840,2,0),0) -> 0 | AT19: =+IFERROR(VLOOKUP($AT$18,Sheet1!AD2:AG840,2,0),0) -> 0 | AU19: =+IFERROR(VLOOKUP($AU$18,Sheet1!AD2:AG840,2,0),0) -> 0 | AV19: =+IFERROR(VLOOKUP($AV$18,Sheet1!AD2:AG840,2,0),0) -> 0 | AW19: =+IFERROR(VLOOKUP($AW$18,Sheet1!AD2:AG840,2,0),0) -> 0 | AX19: 64 | AY19: =+IFERROR(VLOOKUP($AY$18,Sheet1!AD2:AG840,2,0),0) -> 0 | AZ19: =+IFERROR(VLOOKUP($AZ$18,Sheet1!AD2:AG840,2,0),0) -> 0 | BA19: =+IFERROR(VLOOKUP($BA$18,Sheet1!AH2:AK840,2,0),0) -> 0 | BB19: =+IFERROR(VLOOKUP($BB$18,Sheet1!AH2:AK840,2,0),0) -> 0 | BC19: =+IFERROR(VLOOKUP($BC$18,Sheet1!AH2:AK840,2,0),0) -> 0 | BD19: =+IFERROR(VLOOKUP($BD$18,Sheet1!AH2:AK840,2,0),0) -> 0 | BE19: =+IFERROR(VLOOKUP($BE$18,Sheet1!AH2:AK840,2,0),0) -> 0 | BF19: =+IFERROR(VLOOKUP($BF$18,Sheet1!AH2:AK840,2,0),0) -> 0 | BG19: 74 | BH19: =+IFERROR(VLOOKUP($BH$18,Sheet1!AH2:AK840,2,0),0) -> 0 | BI19: =+IFERROR(VLOOKUP($BI$18,Sheet1!AH2:AK840,2,0),0) -> 0 | BJ19: =+IFERROR(VLOOKUP($BJ$18,Sheet1!AH2:AK840,2,0),0) -> 0 | BK19: =+IFERROR(VLOOKUP($BK$18,Sheet1!AH2:AK840,2,0),0) -> 0 | BL19: =+IFERROR(VLOOKUP($BL$18,Sheet1!AL2:AO840,2,0),0) -> 0 | BM19: =+IFERROR(VLOOKUP($BM$18,Sheet1!AL2:AO840,2,0),0) -> 0 | BN19: =+IFERROR(VLOOKUP($BN$18,Sheet1!AL2:AO840,2,0),0) -> 0 | BO19: =+IFERROR(VLOOKUP($BO$18,Sheet1!AL2:AO840,2,0),0) -> 0 | BP19: =+IFERROR(VLOOKUP($BP$18,Sheet1!AL2:AO840,2,0),0) -> 0 | BQ19: =+IFERROR(VLOOKUP($BQ$18,Sheet1!AL2:AO840,2,0),0) -> 0 | BR19: =+IFERROR(VLOOKUP($BR$18,Sheet1!AL2:AO840,2,0),0) -> 0 | BS19: =+IFERROR(VLOOKUP($BS$18,Sheet1!AL2:AO840,2,0),0) -> 0 | BT19: 64 | BU19: =+IFERROR(VLOOKUP($BU$18,Sheet1!AL2:AO840,2,0),0) -> 0 | BV19: =+IFERROR(VLOOKUP($BV$18,Sheet1!AL2:AO840,2,0),0) -> 0 | BW19: =+IFERROR(VLOOKUP($BW$18,Sheet1!AL2:AO840,2,0),0) -> 0 | BX19: 27 | BY19: =+IFERROR(VLOOKUP($BY$18,Sheet1!AT2:AW840,2,0),0) -> 0 | BZ19: =+IFERROR(VLOOKUP($BZ$18,Sheet1!AX2:BA840,2,0),0) -> 0 | CA19: =+IFERROR(VLOOKUP($CA$18,Sheet1!BB2:BE840,2,0),0) -> 0 | CB19: =+IFERROR(VLOOKUP($CB$18,Sheet1!BF2:BI840,2,0),0) -> 0 | CC19: =+IFERROR(VLOOKUP($CC$18,Sheet1!BJ2:BM840,2,0),0) -> 0 | CD19: =+IFERROR(VLOOKUP($CD$18,Sheet1!BN2:BQ840,2,0),0) -> 0 | CE19: 282 | CF19: =+IFERROR(VLOOKUP($CF$18,Sheet1!BV2:BY840,2,0),0) -> 0
A20: =Sheet1!A3 -> ENQ-18639-25-26 | B20: 46054 | C20: =Sheet1!C3 -> FA1300002 | D20: =Sheet1!D3 -> 3 CORE X 185 SQ. MM AL/ARM - STRIP (XLPE) - 11 KV | E20: =CS20+CU20+CW20+CY20 -> 1111236.3 | F20: =ROUNDUP(M26,0) -> 39000 | G20: =E20+F20 -> 1150236.3 | H20: =Sheet1!CR3 -> 0.18 | I20: =G20*H20 -> 207042.54 | J20: =G20+I20 -> 1357278.8 | K20: =Sheet1!CU3 -> 600 | L20: =Sheet1!CV3 -> KMS | M20: =J20*K20 -> 8.143673e+08 | N20: 1501 | O20: =+IFERROR(VLOOKUP($O$18,Sheet1!J3:L3,3,0),0) -> 0 | P20: =+IFERROR(VLOOKUP($P$18,Sheet1!J3:M3,3,0),0) -> 0 | Q20: =+IFERROR(VLOOKUP($Q$18,Sheet1!J3:M3,3,0),0) -> 0 | R20: =+IFERROR(VLOOKUP($R$18,Sheet1!J3:M3,3,0),0) -> 0 | S20: =+IFERROR(VLOOKUP($S$18,Sheet1!J3:M3,3,0),0) -> 0 | T20: =+IFERROR(VLOOKUP($T$18,Sheet1!J3:M3,3,0),0) -> 0 | U20: =+IFERROR(VLOOKUP($U$18,Sheet1!J3:M3,3,0),0) -> 0 | V20: =+IFERROR(VLOOKUP($V$18,Sheet1!N3:Q3,3,0),0) -> 0 | W20: =+IFERROR(VLOOKUP($W$18,Sheet1!N3:Q3,3,0),0) -> 0 | X20: =+IFERROR(VLOOKUP($X$18,Sheet1!F3:I3,3,0),0) -> 0 | Y20: =+IFERROR(VLOOKUP($Y$18,Sheet1!F3:I3,3,0),0) -> 75 | Z20: =+IFERROR(VLOOKUP($Z$18,Sheet1!F3:I3,3,0),0) -> 0 | AA20: =+IFERROR(VLOOKUP($AA$18,Sheet1!F3:I3,3,0),0) -> 0 | AB20: =+IFERROR(VLOOKUP($AB$18,Sheet1!F3:I3,3,0),0) -> 0 | AC20: =+IFERROR(VLOOKUP($AC$18,Sheet1!F3:I3,3,0),0) -> 0 | AD20: =+IFERROR(VLOOKUP($AD$18,Sheet1!F3:I3,3,0),0) -> 0 | AE20: =+IFERROR(VLOOKUP($AE$18,Sheet1!F3:I3,3,0),0) -> 0 | AF20: =+IFERROR(VLOOKUP($AF$18,Sheet1!R3:U3,3,0),0) -> 276 | AG20: =+IFERROR(VLOOKUP($AG$18,Sheet1!R3:U3,3,0),0) -> 0 | AH20: =+IFERROR(VLOOKUP($AH$18,Sheet1!V3:Y3,3,0),0) -> 663 | AI20: =+IFERROR(VLOOKUP($AI$18,Sheet1!V3:Y3,3,0),0) -> 0 | AJ20: =+IFERROR(VLOOKUP($AJ$18,Sheet1!V3:Y3,3,0),0) -> 0 | AK20: =+IFERROR(VLOOKUP($AK$18,Sheet1!V3:Y3,3,0),0) -> 0 | AL20: =+IFERROR(VLOOKUP($AL$18,Sheet1!V3:Y3,3,0),0) -> 0 | AM20: =+IFERROR(VLOOKUP($AM$18,Sheet1!V3:Y3,3,0),0) -> 0 | AN20: =+IFERROR(VLOOKUP($AN$18,Sheet1!V3:Y3,3,0),0) -> 0 | AO20: =+IFERROR(VLOOKUP($AO$18,Sheet1!V3:Y3,3,0),0) -> 0 | AP20: =+IFERROR(VLOOKUP($AP$18,Sheet1!V3:Y3,3,0),0) -> 0 | AQ20: =+IFERROR(VLOOKUP($AQ$18,Sheet1!Z3:AB3,3,0),0) -> 0 | AR20: =+IFERROR(VLOOKUP($AR$18,Sheet1!AD3:AG3,3,0),0) -> 0 | AS20: =+IFERROR(VLOOKUP($AS$18,Sheet1!AD3:AG3,3,0),0) -> 0 | AT20: =+IFERROR(VLOOKUP($AT$18,Sheet1!AD3:AG3,3,0),0) -> 0 | AU20: =+IFERROR(VLOOKUP($AU$18,Sheet1!AD3:AG3,3,0),0) -> 0 | AV20: =+IFERROR(VLOOKUP($AV$18,Sheet1!AD3:AG3,3,0),0) -> 0 | AW20: =+IFERROR(VLOOKUP($AW$18,Sheet1!AD3:AG3,3,0),0) -> 0 | AX20: =+IFERROR(VLOOKUP($AX$18,Sheet1!AD3:AG3,3,0),0) -> 237 | AY20: =+IFERROR(VLOOKUP($AY$18,Sheet1!AD3:AG3,3,0),0) -> 0 | AZ20: =+IFERROR(VLOOKUP($AZ$18,Sheet1!AD3:AG3,3,0),0) -> 0 | BA20: =+IFERROR(VLOOKUP($BA$18,Sheet1!AH3:AK3,3,0),0) -> 0 | BB20: =+IFERROR(VLOOKUP($BB$18,Sheet1!AH3:AK3,3,0),0) -> 0 | BC20: =+IFERROR(VLOOKUP($BC$18,Sheet1!AH3:AK3,3,0),0) -> 0 | BD20: =+IFERROR(VLOOKUP($BD$18,Sheet1!AH3:AK3,3,0),0) -> 0 | BE20: =+IFERROR(VLOOKUP($BE$18,Sheet1!AH3:AK3,3,0),0) -> 0 | BF20: =+IFERROR(VLOOKUP($BF$18,Sheet1!AH3:AK3,3,0),0) -> 0 | BG20: =+IFERROR(VLOOKUP($BG$18,Sheet1!AH3:AK3,3,0),0) -> 975 | BH20: =+IFERROR(VLOOKUP($BH$18,Sheet1!AH3:AK3,3,0),0) -> 0 | BI20: =+IFERROR(VLOOKUP($BI$18,Sheet1!AH3:AK3,3,0),0) -> 0 | BJ20: =+IFERROR(VLOOKUP($BJ$18,Sheet1!AH3:AK3,3,0),0) -> 0 | BK20: =+IFERROR(VLOOKUP($BK$18,Sheet1!AH3:AK3,3,0),0) -> 0 | BL20: =+IFERROR(VLOOKUP($BL$18,Sheet1!AL3:AO3,3,0),0) -> 0 | BM20: =+IFERROR(VLOOKUP($BM$18,Sheet1!AL3:AO3,3,0),0) -> 0 | BN20: =+IFERROR(VLOOKUP($BN$18,Sheet1!AL3:AO3,3,0),0) -> 0 | BO20: =+IFERROR(VLOOKUP($BO$18,Sheet1!AL3:AO3,3,0),0) -> 0 | BP20: =+IFERROR(VLOOKUP($BP$18,Sheet1!AL3:AO3,3,0),0) -> 0 | BQ20: =+IFERROR(VLOOKUP($BQ$18,Sheet1!AL3:AO3,3,0),0) -> 0 | BR20: =+IFERROR(VLOOKUP($BR$18,Sheet1!AL3:AO3,3,0),0) -> 0 | BS20: =+IFERROR(VLOOKUP($BS$18,Sheet1!AL3:AO3,3,0),0) -> 0 | BT20: =+IFERROR(VLOOKUP($BT$18,Sheet1!AL3:AO3,3,0),0) -> 755 | BU20: =+IFERROR(VLOOKUP($BU$18,Sheet1!AL3:AO3,3,0),0) -> 0 | BV20: =+IFERROR(VLOOKUP($BV$18,Sheet1!AL3:AO3,3,0),0) -> 0 | BW20: =+IFERROR(VLOOKUP($BW$18,Sheet1!AL3:AO3,3,0),0) -> 0 | BX20: 946 | BY20: =+IFERROR(VLOOKUP($BY$18,Sheet1!AT3:AW3,3,0),0) -> 0 | BZ20: =+IFERROR(VLOOKUP($BZ$18,Sheet1!AX3:BA3,3,0),0) -> 0 | CA20: =+IFERROR(VLOOKUP($CA$18,Sheet1!BB3:BE3,3,0),0) -> 0 | CB20: =+IFERROR(VLOOKUP($CB$18,Sheet1!BF3:BI3,3,0),0) -> 0 | CC20: =+IFERROR(VLOOKUP($CC$18,Sheet1!BJ3:BM3,3,0),0) -> 0 | CD20: =+IFERROR(VLOOKUP($CD$18,Sheet1!BN3:BQ3,3,0),0) -> 0 | CE20: 41 | CF20: =+IFERROR(VLOOKUP($CF$18,Sheet1!BV3:BY3,3,0),0) -> 0 | CG20: =Sheet1!E3 -> WOOD | CH20: =Sheet1!CY3 -> MD0100023 | CI20: =Sheet1!CZ3 -> DRUM - 68 X 34 X 36 X 3 | CJ20: =Sheet1!CX3 -> 250 | CK20: =Sheet1!BZ3 -> 43820 | CL20: =SUMPRODUCT($N$19:$CF$19,N20:CF20)+CK20 -> 938148 | CM20: =Sheet1!CB3 -> 0 | CN20: =CL20*CM20 -> 0 | CO20: 0.15 | CP20: =CL20*CO20 -> 140722.2 | CQ20: =Sheet1!CF3 -> 0 | CR20: =CL20*CQ20 -> 0 | CS20: =CL20+CN20+CP20+CR20 -> 1078870.2 | CT20: 0.02 | CU20: =CS20*CT20 -> 21577.404 | CV20: 0.01 | CW20: =CS20*CV20 -> 10788.702 | CX20: =Sheet1!CM3 -> 0 | CY20: =CX20*CS20 -> 0
A21: =Sheet1!A2 -> ENQ-18639-25-26 | B21: 46054 | C21: =Sheet1!C2 -> FA1300001 | D21: =Sheet1!D2 -> 3 CORE X 120 SQ. MM. AL/ARM - STRIP (XLPE) - 11 KV | E21: =CS21+CU21+CW21+CY21 -> 835321.24 | F21: =ROUNDUP(M27,0) -> 39000 | G21: =E21+F21 -> 874321.24 | H21: =Sheet1!CR2 -> 0.18 | I21: =G21*H21 -> 157377.82 | J21: =G21+I21 -> 1031699.1 | K21: =Sheet1!CU2 -> 100 | L21: =Sheet1!CV2 -> KMS | M21: =J21*K21 -> 1.0316991e+08 | N21: 974 | O21: =+IFERROR(VLOOKUP($O$18,Sheet1!J2:L2,3,0),0) -> 0 | P21: =+IFERROR(VLOOKUP($P$18,Sheet1!J2:M2,3,0),0) -> 0 | Q21: =+IFERROR(VLOOKUP($Q$18,Sheet1!J2:M2,3,0),0) -> 0 | R21: =+IFERROR(VLOOKUP($R$18,Sheet1!J2:M2,3,0),0) -> 0 | S21: =+IFERROR(VLOOKUP($S$18,Sheet1!J2:M2,3,0),0) -> 0 | T21: =+IFERROR(VLOOKUP($T$18,Sheet1!J2:M2,3,0),0) -> 0 | U21: =+IFERROR(VLOOKUP($U$18,Sheet1!J2:M2,3,0),0) -> 0 | V21: =+IFERROR(VLOOKUP($V$18,Sheet1!N2:Q2,3,0),0) -> 0 | W21: =+IFERROR(VLOOKUP($W$18,Sheet1!N2:Q2,3,0),0) -> 0 | X21: =+IFERROR(VLOOKUP($X$18,Sheet1!F2:I2,3,0),0) -> 0 | Y21: =+IFERROR(VLOOKUP($Y$18,Sheet1!F2:I2,3,0),0) -> 66 | Z21: =+IFERROR(VLOOKUP($Z$18,Sheet1!F2:I2,3,0),0) -> 0 | AA21: =+IFERROR(VLOOKUP($AA$18,Sheet1!F2:I2,3,0),0) -> 0 | AB21: =+IFERROR(VLOOKUP($AB$18,Sheet1!F2:I2,3,0),0) -> 0 | AC21: =+IFERROR(VLOOKUP($AC$18,Sheet1!F2:I2,3,0),0) -> 0 | AD21: =+IFERROR(VLOOKUP($AD$18,Sheet1!F2:I2,3,0),0) -> 0 | AE21: =+IFERROR(VLOOKUP($AE$18,Sheet1!F2:I2,3,0),0) -> 0 | AF21: =+IFERROR(VLOOKUP($AF$18,Sheet1!R2:U2,3,0),0) -> 233 | AG21: =+IFERROR(VLOOKUP($AG$18,Sheet1!R2:U2,3,0),0) -> 0 | AH21: =+IFERROR(VLOOKUP($AH$18,Sheet1!V2:Y2,3,0),0) -> 564 | AI21: =+IFERROR(VLOOKUP($AI$18,Sheet1!V2:Y2,3,0),0) -> 0 | AJ21: =+IFERROR(VLOOKUP($AJ$18,Sheet1!V2:Y2,3,0),0) -> 0 | AK21: =+IFERROR(VLOOKUP($AK$18,Sheet1!V2:Y2,3,0),0) -> 0 | AL21: =+IFERROR(VLOOKUP($AL$18,Sheet1!V2:Y2,3,0),0) -> 0 | AM21: =+IFERROR(VLOOKUP($AM$18,Sheet1!V2:Y2,3,0),0) -> 0 | AN21: =+IFERROR(VLOOKUP($AN$18,Sheet1!V2:Y2,3,0),0) -> 0 | AO21: =+IFERROR(VLOOKUP($AO$18,Sheet1!V2:Y2,3,0),0) -> 0 | AP21: =+IFERROR(VLOOKUP($AP$18,Sheet1!V2:Y2,3,0),0) -> 0 | AQ21: =+IFERROR(VLOOKUP($AQ$18,Sheet1!Z2:AB2,3,0),0) -> 0 | AR21: =+IFERROR(VLOOKUP($AR$18,Sheet1!AD2:AG2,3,0),0) -> 0 | AS21: =+IFERROR(VLOOKUP($AS$18,Sheet1!AD2:AG2,3,0),0) -> 0 | AT21: =+IFERROR(VLOOKUP($AT$18,Sheet1!AD2:AG2,3,0),0) -> 0 | AU21: =+IFERROR(VLOOKUP($AU$18,Sheet1!AD2:AG2,3,0),0) -> 0 | AV21: =+IFERROR(VLOOKUP($AV$18,Sheet1!AD2:AG2,3,0),0) -> 0 | AW21: =+IFERROR(VLOOKUP($AW$18,Sheet1!AD2:AG2,3,0),0) -> 0 | AX21: =+IFERROR(VLOOKUP($AX$18,Sheet1!AD2:AG2,3,0),0) -> 185 | AY21: =+IFERROR(VLOOKUP($AY$18,Sheet1!AD2:AG2,3,0),0) -> 0 | AZ21: =+IFERROR(VLOOKUP($AZ$18,Sheet1!AD2:AG2,3,0),0) -> 0 | BA21: =+IFERROR(VLOOKUP($BA$18,Sheet1!AH2:AK2,3,0),0) -> 0 | BB21: =+IFERROR(VLOOKUP($BB$18,Sheet1!AH2:AK2,3,0),0) -> 0 | BC21: =+IFERROR(VLOOKUP($BC$18,Sheet1!AH2:AK2,3,0),0) -> 0 | BD21: =+IFERROR(VLOOKUP($BD$18,Sheet1!AH2:AK2,3,0),0) -> 0 | BE21: =+IFERROR(VLOOKUP($BE$18,Sheet1!AH2:AK2,3,0),0) -> 0 | BF21: =+IFERROR(VLOOKUP($BF$18,Sheet1!AH2:AK2,3,0),0) -> 0 | BG21: =+IFERROR(VLOOKUP($BG$18,Sheet1!AH2:AK2,3,0),0) -> 850 | BH21: =+IFERROR(VLOOKUP($BH$18,Sheet1!AH2:AK2,3,0),0) -> 0 | BI21: =+IFERROR(VLOOKUP($BI$18,Sheet1!AH2:AK2,3,0),0) -> 0 | BJ21: =+IFERROR(VLOOKUP($BJ$18,Sheet1!AH2:AK2,3,0),0) -> 0 | BK21: =+IFERROR(VLOOKUP($BK$18,Sheet1!AH2:AK2,3,0),0) -> 0 | BL21: =+IFERROR(VLOOKUP($BL$18,Sheet1!AL2:AO2,3,0),0) -> 0 | BM21: =+IFERROR(VLOOKUP($BM$18,Sheet1!AL2:AO2,3,0),0) -> 0 | BN21: =+IFERROR(VLOOKUP($BN$18,Sheet1!AL2:AO2,3,0),0) -> 0 | BO21: =+IFERROR(VLOOKUP($BO$18,Sheet1!AL2:AO2,3,0),0) -> 0 | BP21: =+IFERROR(VLOOKUP($BP$18,Sheet1!AL2:AO2,3,0),0) -> 0 | BQ21: =+IFERROR(VLOOKUP($BQ$18,Sheet1!AL2:AO2,3,0),0) -> 0 | BR21: =+IFERROR(VLOOKUP($BR$18,Sheet1!AL2:AO2,3,0),0) -> 0 | BS21: =+IFERROR(VLOOKUP($BS$18,Sheet1!AL2:AO2,3,0),0) -> 0 | BT21: =+IFERROR(VLOOKUP($BT$18,Sheet1!AL2:AO2,3,0),0) -> 630 | BU21: =+IFERROR(VLOOKUP($BU$18,Sheet1!AL2:AO2,3,0),0) -> 0 | BV21: =+IFERROR(VLOOKUP($BV$18,Sheet1!AL2:AO2,3,0),0) -> 0 | BW21: =+IFERROR(VLOOKUP($BW$18,Sheet1!AL2:AO2,3,0),0) -> 0 | BX21: 736 | BY21: =+IFERROR(VLOOKUP($BY$18,Sheet1!AT2:AW2,3,0),0) -> 0 | BZ21: =+IFERROR(VLOOKUP($BZ$18,Sheet1!AX2:BA2,3,0),0) -> 0 | CA21: =+IFERROR(VLOOKUP($CA$18,Sheet1!BB2:BE2,3,0),0) -> 0 | CB21: =+IFERROR(VLOOKUP($CB$18,Sheet1!BF2:BI2,3,0),0) -> 0 | CC21: =+IFERROR(VLOOKUP($CC$18,Sheet1!BJ2:BM2,3,0),0) -> 0 | CD21: =+IFERROR(VLOOKUP($CD$18,Sheet1!BN2:BQ2,3,0),0) -> 0 | CE21: 37 | CF21: =+IFERROR(VLOOKUP($CF$18,Sheet1!BV2:BY2,3,0),0) -> 0 | CG21: =Sheet1!E2 -> WOOD | CH21: =Sheet1!CY2 -> MD0100029 | CI21: =Sheet1!CZ2 -> DRUM - 80 X 35 X 39 X 3"+ EXTRA SEGMENT | CJ21: =Sheet1!CX2 -> 500 | CK21: =Sheet1!BZ2 -> 41942 | CL21: =SUMPRODUCT($N$19:$CF$19,N21:CF21)+CK21 -> 705210 | CM21: =Sheet1!CB2 -> 0 | CN21: =CL21*CM21 -> 0 | CO21: 0.15 | CP21: =CL21*CO21 -> 105781.5 | CQ21: =Sheet1!CF2 -> 0 | CR21: =CL21*CQ21 -> 0 | CS21: =CL21+CN21+CP21+CR21 -> 810991.5 | CT21: 0.02 | CU21: =CS21*CT21 -> 16219.83 | CV21: 0.01 | CW21: =CS21*CV21 -> 8109.915 | CX21: =Sheet1!CM2 -> 0 | CY21: =CX21*CS21 -> 0
M22: =SUM(M20:M21) -> 9.1753721e+08
E25: Order Quantity | F25: Stnd Length | G25: Truck type | H25: Fare of one truck | I25: No of Drum in one truck | J25: Total length in one Truck | K25: No of Truck | L25: Total Freight | M25: Freight per KM | Y25: CABLE WEIGHT KG/KM | AF25: DRUM WEIGHT | AH25: CABLE + DRUM WEIGHT | AX25: TRUCK WEIGHT
D26: =D20 -> 3 CORE X 185 SQ. MM AL/ARM - STRIP (XLPE) - 11 KV | E26: =K20 -> 600 | F26: =CJ20/1000 -> 0.25 | G26: 16 MT | H26: 78000 | I26: 8 | J26: =F26*I26 -> 2 | K26: =ROUNDUP((E26/J26),0) -> 300 | L26: =H26*K26 -> 23400000 | M26: =L26/E26 -> 39000 | N26: =CH20 -> MD0100023 | Y26: =SUM(N20:CE20) -> 5469 | AF26: =300+100 -> 400 | AH26: =((Y26*F26)+AF26) -> 1767.25 | AX26: =I26*AH26 -> 14138
D27: =D21 -> 3 CORE X 120 SQ. MM. AL/ARM - STRIP (XLPE) - 11 KV | E27: =K21 -> 100 | F27: =CJ21/1000 -> 0.5 | G27: 16 MT | H27: 78000 | I27: 4 | J27: =F27*I27 -> 2 | K27: =ROUNDUP((E27/J27),0) -> 50 | L27: =H27*K27 -> 3900000 | M27: =L27/E27 -> 39000 | N27: =CH21 -> MD0100029 | Y27: =SUM(N21:CE21) -> 4275 | AF27: =530+25 -> 555 | AH27: =((Y27*F27)+AF27) -> 2692.5 | AX27: =I27*AH27 -> 10770
I28: confirmed from sombhu sir overphone
E31: Estimated cost | F31: our cost | G31: diff % from our cost
E32: 744439987 | F32: =M22 -> 9.1753721e+08 | G32: =((F32-E32)/F32)*100 -> 18.865417 | H32: including GST
E35: Estimated unit FOR Destination price (in Rs.) | F35: our price | G35: diff % from our cost | I35: our price | J35: diff % from our cost
D36: =D26 -> 3 CORE X 185 SQ. MM AL/ARM - STRIP (XLPE) - 11 KV | E36: 1105933.1 | F36: =J20 -> 1357278.8 | G36: =((F36-E36)/F36)*100 -> 18.518357 | H36: including GST | I36: =G20 -> 1150236.3 | J36: =((I36-E36)/I36)*100 -> 3.8516612 | K36: excluding GST
D37: =D27 -> 3 CORE X 120 SQ. MM. AL/ARM - STRIP (XLPE) - 11 KV | E37: 808801.27 | F37: =J21 -> 1031699.1 | G37: =((F37-E37)/F37)*100 -> 21.604924 | H37: including GST | I37: =G21 -> 874321.24 | J37: =((I37-E37)/I37)*100 -> 7.4938102 | K37: excluding GST

Sheet PV AUTO CALCULATION SHEET
A1: Base Date | B1: 46054
A2: PV FORMULA
A3: The prices quoted shall be variable as per PV formula given in the specification at Schedule-II without any ceiling with Base Date as 01.02.2026
A4: P = Po + AIF (Al–Alo) + XLFAL (CC–Cco) + SMIF (SMIF1–SMIF0) + FeF (FeF1–FeF0) + CCFAI (PVCc–PVCco)
AF8: VALUE ADDITION CALCULATION
A9: Item | B9: Calculation part | C9: Date of Inspection | D9: Applicable Date | J9: BASE DATE | P9: FACTORS | W9: Ex-Work Po | X9: PVC of al | Y9: PVC of Cu | Z9: PVC of XLPE | AA9: PVC OF PVC | AB9: PVC OF FE | AC9: PVC OF CU TAPE | AD9: PV/PKM | AE9: Billing Price/PKM
D10: Date | E10: Al | F10: Cu | G10: Cc | H10: PVCc | I10: Fe | J10: Date | K10: Alo | L10: Cuo | M10: Cco | N10: PVCco | O10: Feo | AF10: ='AUTO CALCULATION SHEET (2)'!N18 -> Alumimium | AG10: ='AUTO CALCULATION SHEET (2)'!Y18 -> Copper Tape - 0.03 mm | AH10: ='AUTO CALCULATION SHEET (2)'!AF18 -> Extruded semiconductive | AI10: ='AUTO CALCULATION SHEET (2)'!AH18 -> HT-XLPE | AJ10: ='AUTO CALCULATION SHEET (2)'!AX18 -> PVC Type ST-2 | AK10: ='AUTO CALCULATION SHEET (2)'!BG18 -> Galvanised Steel Flat Strip | AL10: ='AUTO CALCULATION SHEET (2)'!BT18 -> PVC Type ST-2 | AM10: ='AUTO CALCULATION SHEET (2)'!BX18 -> FILLER | AN10: ='AUTO CALCULATION SHEET (2)'!CE18 -> RUBBERIZED COTTON TAPE | AO10: RMC | AP10: Drum | AQ10: RMC+Drum | AR10: VA | AS10: Groos VA% | AT10: Mfg % | AU10: Int % | AV10: Ins% | AW10: Net VA
P11: Alf | Q11: Cu | R11: XLFAL | S11: CCFAI | T11: CCFCu | U11: FeF | V11: Smif | AF11: 354 | AG11: 1374 | AH11: 160 | AI11: 125 | AJ11: 64 | AK11: 74 | AL11: 64 | AM11: 28 | AN11: 281
AF12: Kg/Km | AG12: Kg/Km | AH12: Kg/Km | AI12: Kg/Km | AJ12: Kg/Km | AK12: Kg/Km | AL12: Kg/Km | AM12: Kg/Km | AN12: Kg/Km
A13: ='AUTO CALCULATION SHEET (2)'!D20 -> 3 CORE X 185 SQ. MM AL/ARM - STRIP (XLPE) - 11 KV | C13: PROVISIONAL | D13: 46086 | E13: 336831.38 | F13: 1287577.6 | G13: 198367 | H13: 158825 | I13: 82250 | J13: =$B$1 -> 46054 | K13: 326508 | L13: 1263919 | M13: 198367 | N13: 158825 | O13: 82250 | P13: 1.605 | R13: 0.968 | S13: 2.406 | U13: 1.113 | V13: 0.0943 | W13: ='AUTO CALCULATION SHEET (2)'!E20 -> 1111236.3 | X13: =(P13*(E13-K13)) -> 16569.025 | Y13: =(Q13*(F13-L13)) -> 0 | Z13: =(R13*(G13-M13)) -> 0 | AA13: =(S13*(H13-N13)) -> 0 | AB13: =(U13*(I13-O13)) -> 0 | AC13: =V13*(F13-L13) -> 2231.0098 | AD13: =X13+Y13+Z13+AA13+AB13+AC13 -> 18800.035 | AE13: =+W13+AD13 -> 1130036.3 | AF13: ='AUTO CALCULATION SHEET (2)'!N20 -> 1501 | AG13: ='AUTO CALCULATION SHEET (2)'!Y20 -> 75 | AH13: ='AUTO CALCULATION SHEET (2)'!AF20 -> 276 | AI13: ='AUTO CALCULATION SHEET (2)'!AH20 -> 663 | AJ13: ='AUTO CALCULATION SHEET (2)'!AX20 -> 237 | AK13: ='AUTO CALCULATION SHEET (2)'!BG20 -> 975 | AL13: ='AUTO CALCULATION SHEET (2)'!BT20 -> 755 | AM13: ='AUTO CALCULATION SHEET (2)'!BX20 -> 946 | AN13: ='AUTO CALCULATION SHEET (2)'!CE20 -> 41 | AO13: =SUMPRODUCT(AF13:AN13,$AF$11:$AN$11) -> 935086 | AP13: ='AUTO CALCULATION SHEET (2)'!CK20 -> 43820 | AQ13: =AO13+AP13 -> 978906 | AR13: =AE13-AQ13 -> 151130.34 | AS13: =ROUND((AR13/AQ13)*100,2) -> 15.44 | AT13: 0 | AU13: 2 | AV13: 1 | AW13: =AS13-AT13-AU13-AV13 -> 12.44
A14: ='AUTO CALCULATION SHEET (2)'!D21 -> 3 CORE X 120 SQ. MM. AL/ARM - STRIP (XLPE) - 11 KV | C14: PROVISIONAL | D14: 46086 | E14: 336831.38 | F14: 1287577.6 | G14: 198367 | H14: 158825 | I14: 82250 | J14: =$B$1 -> 46054 | K14: 326508 | L14: 1263919 | M14: 198367 | N14: 158825 | O14: 82250 | P14: 1.036 | R14: 0.822 | S14: 1.877 | U14: 0.966 | V14: 0.0829 | W14: ='AUTO CALCULATION SHEET (2)'!E21 -> 835321.24 | X14: =(P14*(E14-K14)) -> 10695.022 | Y14: =(Q14*(F14-L14)) -> 0 | Z14: =(R14*(G14-M14)) -> 0 | AA14: =(S14*(H14-N14)) -> 0 | AB14: =(U14*(I14-O14)) -> 0 | AC14: =V14*(F14-L14) -> 1961.3013 | AD14: =X14+Y14+Z14+AA14+AB14+AC14 -> 12656.323 | AE14: =+W14+AD14 -> 847977.57 | AF14: ='AUTO CALCULATION SHEET (2)'!N21 -> 974 | AG14: ='AUTO CALCULATION SHEET (2)'!Y21 -> 66 | AH14: ='AUTO CALCULATION SHEET (2)'!AF21 -> 233 | AI14: ='AUTO CALCULATION SHEET (2)'!AH21 -> 564 | AJ14: ='AUTO CALCULATION SHEET (2)'!AX21 -> 185 | AK14: ='AUTO CALCULATION SHEET (2)'!BG21 -> 850 | AL14: ='AUTO CALCULATION SHEET (2)'!BT21 -> 630 | AM14: ='AUTO CALCULATION SHEET (2)'!BX21 -> 736 | AN14: ='AUTO CALCULATION SHEET (2)'!CE21 -> 37 | AO14: =SUMPRODUCT(AF14:AN14,$AF$11:$AN$11) -> 689325 | AP14: ='AUTO CALCULATION SHEET (2)'!CK21 -> 41942 | AQ14: =AO14+AP14 -> 731267 | AR14: =AE14-AQ14 -> 116710.57 | AS14: =ROUND((AR14/AQ14)*100,2) -> 15.96 | AT14: 0 | AU14: 2 | AV14: 1 | AW14: =AS14-AT14-AU14-AV14 -> 12.96

Sheet terms
A1: The quoted prices are on Firm inclusive of packing and forwading but exclusive of GST Statutory levies.
A2: The quoted prices are on VARIABLE basis with PV base Date: DD/MM/YYYY as per "IEEMA", inclusive of packing and forwading but exclusive of GST Statutory levies.
A4: The above prices are quoted on Ex-works basis, where freight will be charged extra.
A5: The above prices are quoted on FOR Destination basis, where freight is included, refer Price offer.
A6: The above prices are quoted on Ex-works+Freight basis.
A8: 20% Advance and Balance against PI (Proforma Invoice) prior to dispatch
A9: 100% against "90 days" LC, where 90 days usance interest will be borne by LPIPL
A10: 100% against "120 days" LC, where 120 days usance interest will be borne by LPIPL
A11: 100% against "45 days" LC, where 45 days usance interest will be borne by LPIPL
A12: 100% against "60 days" LC, where 60 days usance interest will be borne by LPIPL
A13: 100% against "30 days" LC, where 30 days usance interest will be borne by LPIPL
A14: 100% against 60 days PDC from the date of MRC/MRN
... A27: Negotiable
