Workbook

Sheet Sheet1
A1: DOCKET NO. | B1: Base Date | C1: ITEM CODE | D1: PROPOSE ERP ITEM NAME | E1: Propose Drum Type | F1: Insulation Screening(Metallic) | G1: RM Rate(Insulation Screening(Metallic)) | H1: Weight (Insulation Screening (Metallic)) | I1: Cost Insulation Screening(Metallic) | J1: Conductor | K1: RM Rate(Conductor) | L1: Weight(Conductor) | M1: Cost(Conductor) | N1: AL ALLOY | O1: RM Rate(AL Alloy) | P1: Weight(Al Alloy) | Q1: Cost(AL Alloy) | R1: Insulation Screening(Non-Metallic) | S1: RM Rate(Insulation Screening(Non-Metallic)) | T1: Weight(Insulation Screening(Non-Metallic) | U1: Cost(Insulation Screening(Non-Metallic) | V1: Insulation | W1: RM Rate(Insulation) | X1: Weight(Insulation) | Y1: Cost(Insulation) | Z1: Poly Tape | AA1: RM Rate(Poly Tape) | AB1: Weight(Poly Tape) | AC1: Cost(Poly Tape) | AD1: Inner Sheath | AE1: RM Rate(Inner Sheath) | AF1: Weight(Inner Sheath) | AG1: Cost(Inner Sheath) | AH1: Armouring | AI1: RM Rate(Armouring) | AJ1: Weight(Armouring) | AK1: Cost(Armouring) | AL1: Outer Sheath | AM1: RM Rate(Outer Sheath) | AN1: Weight(Outer Sheath) | AO1: Cost(Outer Sheath) | AP1: Filler | AQ1: RM Rate(Filler) | AR1: Weight(Filler) | AS1: Cost(Filler) | AT1: Grease | AU1: RM Rate(Grease) | AV1: Weight(Grease) | AW1: Cost(Grease) | AX1: Water Swellable Tape | AY1: RM Rate(Water Swellable Tape) | AZ1: Weight(Water Swellable Tape) | BA1: Cost(Water Swellable Tape) | BB1: Semi Conducting Water Swellable Tape | BC1: RM Rate(Semi Conducting Water Swellable Tape) | BD1: Weight(Semi Conducting Water Swellable Tape) | BE1: Cost(Semi Conducting Water Swellable Tape) | BF1: Semicon Tape | BG1: RM Rate(Semicon Tape) | BH1: Weight(Semicon Tape) | BI1: Cost(Semicon Tape) | BJ1: Glass Fiber Tape | BK1: RM Rate(Glass Fiber Tape) | BL1: Weight(Glass Fiber Tape) | BM1: Cost(Glass Fiber Tape) | BN1: Copper Wire 0.8MM | BO1: RM Rate(Copper Wire 0.8MM) | BP1: Weight(Copper Wire 0.8MM) | BQ1: Cost(Copper Wire 0.8MM) | BR1: Rubberized Cotton Tape | BS1: RM Rate(Rubberized Cotton Tape) | BT1: Weight(Rubberized Cotton Tape) | BU1: Cost(Rubberized Cotton Tape) | BV1: Water Tight Compound | BW1: RM Rate(Water Tight Compound) | BX1: Weight(Water Tight Compound) | BY1: Cost(Water Tight Compound) | BZ1: Drum Cost Per KM | CA1: Total RM Cost | CB1: FIRM % | CC1: Firm Value | CD1: MFG% | CE1: MFG Value | CF1: PROF% | CG1: Profit Value | CH1: 1st EX-Works | CI1: Intt % | CJ1: Intt Value | CK1: insp% | CL1: Insp Value | CM1: TTR CHARGES% | CN1: TTR Value | CO1: EX-Works Per KM | CP1: Freight Per KM | CQ1: Price Including Freight Per KM | CR1: GST % | CS1: GST Value | CT1: Price Including GST & Freight Per KM | CU1: QTY | CV1: Unit | CW1: Total Price Of Full QTY(Including Freight&GST) | CX1: PARTY LENGTH (IF STANDER LENGTH NOT MATCH WITH PAR | CY1: DRUM CODE | CZ1: DRUM SIZE (FxbXtx Ft)
A2: ENQ-20143-25-26 | C2: FA1300013 | D2: 3 CORE X 35 SQ. MM. AL/ARM - STRIP (XLPE) - 11 KV | H2: 0 | L2: 284 | P2: 0 | T2: 150 | X2: 384 | AB2: 0 | AF2: 122 | AJ2: 650 | AN2: 383 | AR2: 390 | AV2: 0 | AZ2: 0 | BD2: 0 | BH2: 0 | BL2: 55 | BP2: 0 | BT2: 0 | BX2: 0 | CR2: 0.18 | CU2: 100 | CV2: KMS

Sheet AUTO CALCULATION SHEET (2)
O1: Conductor | W1: AL ALLOY | Y1: Insulation Screening (Metallic) | AG1: Insulation Screening (Non-Metallic) | AI1: Insulation | AR1: POLY TAPE | AS1: Inner Sheath | BB1: Armouring | BM1: Outer Sheath | BY1: FILLER | BZ1: GREASE | CA1: Water swellable Tape | CB1: Semi conducting Water Swellable tape | CC1: SEMICON TAPE | CD1: GLASS FIBER TAPE | CE1: COPPER WIRE 0.8 MM | CF1: RUBBERIZED COTTON TAPE | CG1: Water Tight Compound | CH1: DRUM TYPE | CL1: DRUM COST PER KM | CM1: TOTAL RM COST | CN1: EXTRA CONSUMPTION | CO1: EXTRA CONSUMPTION VALUE | DA1: $A$1
A2: DOCKET NO. | B2: BASE DATE | C2: ITEM CODE | D2: PROPOSE ERP ITEM NAME | E2: EX-WORKS (PER KM) | F2: FREIGHT PER KM | G2: PRICE INCLUDING FREIGHT (PER KM) | H2: GST % | I2: GST VALUE | J2: PRICE INCLUDING GST & FREIGHT (PER KM) | K2: QTY | L2: Unit | M2: TOTAL PRICE OF FULL QTY (INCLUDING FRIGHT & GST) | N2: NON CHAIN BOM ID | O2: Alumimium | P2: Alumimium ALLOY | Q2: Copper | R2: AL-59 | S2: AL-4 | T2: AL-7 | U2: Flexible Copper | V2: Galvanized steel wire | W2: Alumimium | X2: Alumimium ALLOY | Y2: Coper tape - 0.1 mm | Z2: Copper Tape - 0.03 mm | AA2: Copper Tape - 0.035 mm | AB2: Copper Tape - 0.04 mm | AC2: Copper Tape - 0.045 mm | AD2: Copper Tape - 0.050 mm | AE2: Copper Tape - 0.060 mm | AF2: Copper Tape - 0.075 mm(DOUBLE) | AG2: Extruded semiconductive | AH2: Extruded Semiconductive(Stripable) | AI2: HT-XLPE | AJ2: LT-XLPE | AK2: TR XLPE | AL2: Type A PVC | AM2: Type C PVC (HR) | AN2: Type A PVC-1.45 | AO2: Type A PVC-FR | AP2: Type A PVC-FRLS | AQ2: Type A PVC-1.38 | AR2: POLY TAPE | AS2: FR PVC Type ST-1 | AT2: FR PVC Type ST-2 | AU2: FRLSH PVC Type ST-1 | AV2: FRLSH PVC Type ST-2 | AW2: PVC Type ST-1 | AX2: PVC Type ST-1-PRESSURE EXTRUDED | AY2: PVC Type ST-2 | AZ2: PVC COMPOUND 1.48 | BA2: PVC Type ST-2-PRESSURE EXTRUDED | BB2: ACSR CORE WIRE | BC2: ACSR DOG STEEL WIRE | BD2: Aluminium Flat Strip | BE2: Aluminium Round Wire | BF2: Alumimium Tape | BG2: Double Steel Tape | BH2: Galvanised Steel Flat Strip | BI2: Galvanised Steel Flat Strip (Double) | BJ2: Galvanised Steel Flat Strip-B | BK2: Galvanised Steel Round Wire | BL2: Galvanised Steel Round Wire (Double) | BM2: FR PVC Type ST-1 | BN2: FR PVC Type ST-2 | BO2: FRLSH PVC Type ST-1 | BP2: FRLSH PVC Type ST-2 | BQ2: ZHFR | BR2: PE-ST-3 | BS2: PE-ST-7 | BT2: PVC Type ST-1 | BU2: PVC Type ST-2 | BV2: PVC COMPOUND 1.48 | BW2: PVC Type ST-2-PRESSURE EXTRUDED | BX2: UV & Track Resistant XLPE | BY2: FILLER | BZ2: Grease | CA2: Water swellable Tape | CB2: Semi conducting Water Swellable tape | CC2: SEMICON TAPE | CD2: GLASS FIBER TAPE | CE2: COPPER WIRE 0.8 MM | CF2: RUBBERIZED COTTON TAPE | CG2: Water Tight Compound | CH2: PROPOSE DRUM TYPE | CI2: DRUM CODE | CJ2: DRUM SIZE (FxbXtx Ft) | CK2: PARTY STANDARD LENGTH (MTR) | CP2: MFG% | CQ2: MFG VALUE | CR2: PROF% | CS2: PROFIT VALUE | CT2: 1ST EX-WORKS | CU2: Intt % | CV2: INTT VALUE | CW2: insp% | CX2: INSP VALUE | CY2: TTR Charges% | CZ2: TTR Charges VALUE
O3: 401 | P3: =+IFERROR(VLOOKUP($P$2,Sheet1!J:L,2,0),0) -> 0 | Q3: =+IFERROR(VLOOKUP($Q$2,Sheet1!J:M,2,0),0) -> 0 | R3: =+IFERROR(VLOOKUP($R$2,Sheet1!J:M,2,0),0) -> 0 | S3: =+IFERROR(VLOOKUP($S$2,Sheet1!J:M,2,0),0) -> 0 | T3: =+IFERROR(VLOOKUP($T$2,Sheet1!J:M,2,0),0) -> 0 | U3: =+IFERROR(VLOOKUP($U$2,Sheet1!J:M,2,0),0) -> 0 | V3: =+IFERROR(VLOOKUP($V$2,Sheet1!J:M,2,0),0) -> 0 | W3: =+IFERROR(VLOOKUP($W$2,Sheet1!N:Q,2,0),0) -> 0 | X3: =+IFERROR(VLOOKUP($X$2,Sheet1!N:O,2,0),0) -> 0 | Y3: =+IFERROR(VLOOKUP($Y$2,Sheet1!F:I,2,0),0) -> 0 | Z3: 1470 | AA3: =+IFERROR(VLOOKUP($AA$2,Sheet1!F:I,2,0),0) -> 0 | AB3: =+IFERROR(VLOOKUP($AB$2,Sheet1!F:I,2,0),0) -> 0 | AC3: =+IFERROR(VLOOKUP($AC$2,Sheet1!F:I,2,0),0) -> 0 | AD3: =+IFERROR(VLOOKUP($AD$2,Sheet1!F:I,2,0),0) -> 0 | AE3: =+IFERROR(VLOOKUP($AE$2,Sheet1!F:I,2,0),0) -> 0 | AF3: =+IFERROR(VLOOKUP($AF$2,Sheet1!F:I,2,0),0) -> 0 | AG3: =+IFERROR(VLOOKUP($AG$2,Sheet1!R:U,2,0),0) -> 0 | AH3: =+IFERROR(VLOOKUP($AH$2,Sheet1!R:U,2,0),0) -> 0 | AI3: =+IFERROR(VLOOKUP($AI$2,Sheet1!V:Y,2,0),0) -> 0 | AJ3: =+IFERROR(VLOOKUP($AJ$2,Sheet1!V:Y,2,0),0) -> 0 | AK3: 275 | AL3: =+IFERROR(VLOOKUP($AL$2,Sheet1!V:Y,2,0),0) -> 0 | AM3: =+IFERROR(VLOOKUP($AM$2,Sheet1!V:Y,2,0),0) -> 0 | AN3: =+IFERROR(VLOOKUP($AN$2,Sheet1!V:Y,2,0),0) -> 0 | AO3: =+IFERROR(VLOOKUP($AO$2,Sheet1!V:Y,2,0),0) -> 0 | AP3: =+IFERROR(VLOOKUP($AP$2,Sheet1!V:Y,2,0),0) -> 0 | AQ3: =+IFERROR(VLOOKUP($AQ$2,Sheet1!V:Y,2,0),0) -> 0 | AR3: =+IFERROR(VLOOKUP($AR$2,Sheet1!Z2:AA840,2,0),0) -> 0 | AS3: =+IFERROR(VLOOKUP($AS$2,Sheet1!AD2:AG840,2,0),0) -> 0 | AT3: =+IFERROR(VLOOKUP($AT$2,Sheet1!AD2:AG840,2,0),0) -> 0 | AU3: =+IFERROR(VLOOKUP($AU$2,Sheet1!AD2:AG840,2,0),0) -> 0 | AV3: =+IFERROR(VLOOKUP($AV$2,Sheet1!AD2:AG840,2,0),0) -> 0 | AW3: =+IFERROR(VLOOKUP($AW$2,Sheet1!AD2:AG840,2,0),0) -> 0 | AX3: =+IFERROR(VLOOKUP($AX$2,Sheet1!AD2:AG840,2,0),0) -> 0 | AY3: 79 | AZ3: =+IFERROR(VLOOKUP($AZ$2,Sheet1!AD2:AG840,2,0),0) -> 0 | BA3: =+IFERROR(VLOOKUP($BA$2,Sheet1!AD2:AG840,2,0),0) -> 0 | BB3: =+IFERROR(VLOOKUP($BB$2,Sheet1!AH2:AK840,2,0),0) -> 0 | BC3: =+IFERROR(VLOOKUP($BC$2,Sheet1!AH2:AK840,2,0),0) -> 0 | BD3: =+IFERROR(VLOOKUP($BD$2,Sheet1!AH2:AK840,2,0),0) -> 0 | BE3: =+IFERROR(VLOOKUP($BE$2,Sheet1!AH2:AK840,2,0),0) -> 0 | BF3: =+IFERROR(VLOOKUP($BF$2,Sheet1!AH2:AK840,2,0),0) -> 0 | BG3: =+IFERROR(VLOOKUP($BG$2,Sheet1!AH2:AK840,2,0),0) -> 0 | BH3: 87 | BI3: =+IFERROR(VLOOKUP($BI$2,Sheet1!AH2:AK840,2,0),0) -> 0 | BJ3: =+IFERROR(VLOOKUP($BJ$2,Sheet1!AH2:AK840,2,0),0) -> 0 | BK3: =+IFERROR(VLOOKUP($BK$2,Sheet1!AH2:AK840,2,0),0) -> 0 | BL3: =+IFERROR(VLOOKUP($BL$2,Sheet1!AH2:AK840,2,0),0) -> 0 | BM3: =+IFERROR(VLOOKUP($BM$2,Sheet1!AL2:AO840,2,0),0) -> 0 | BN3: =+IFERROR(VLOOKUP($BN$2,Sheet1!AL2:AO840,2,0),0) -> 0 | BO3: =+IFERROR(VLOOKUP($BO$2,Sheet1!AL2:AO840,2,0),0) -> 0 | BP3: =+IFERROR(VLOOKUP($BP$2,Sheet1!AL2:AO840,2,0),0) -> 0 | BQ3: =+IFERROR(VLOOKUP($BQ$2,Sheet1!AL2:AO840,2,0),0) -> 0 | BR3: =+IFERROR(VLOOKUP($BR$2,Sheet1!AL2:AO840,2,0),0) -> 0 | BS3: =+IFERROR(VLOOKUP($BS$2,Sheet1!AL2:AO840,2,0),0) -> 0 | BT3: =+IFERROR(VLOOKUP($BT$2,Sheet1!AL2:AO840,2,0),0) -> 0 | BU3: =79+5 -> 84 | BV3: =+IFERROR(VLOOKUP($BV$2,Sheet1!AL2:AO840,2,0),0) -> 0 | BW3: =+IFERROR(VLOOKUP($BW$2,Sheet1!AL2:AO840,2,0),0) -> 0 | BX3: =+IFERROR(VLOOKUP($BX$2,Sheet1!AL2:AO840,2,0),0) -> 0 | BY3: 31 | BZ3: =+IFERROR(VLOOKUP($BZ$2,Sheet1!AT2:AW840,2,0),0) -> 0 | CA3: =+IFERROR(VLOOKUP($CA$2,Sheet1!AX2:BA840,2,0),0) -> 0 | CB3: =+IFERROR(VLOOKUP($CB$2,Sheet1!BB2:BE840,2,0),0) -> 0 | CC3: 419 | CD3: =+IFERROR(VLOOKUP($CD$2,Sheet1!BJ2:BM840,2,0),0) -> 0 | CE3: =+IFERROR(VLOOKUP($CE$2,Sheet1!BN2:BQ840,2,0),0) -> 0 | CF3: =+IFERROR(VLOOKUP($CF$2,Sheet1!BR2:BU840,2,0),0) -> 0 | CG3: =+IFERROR(VLOOKUP($CG$2,Sheet1!BV2:BY840,2,0),0) -> 0
A4: =Sheet1!A2 -> ENQ-20143-25-26 | B4: 46143 | C4: =Sheet1!C2 -> FA1300013 | D4: =Sheet1!D2 -> 3 CORE X 35 SQ. MM. AL/ARM - STRIP (XLPE) - 11 KV | E4: =CT4+CV4+CX4+CZ4 -> 722387.12 | F4: =ROUNDUP($M$9,0) -> 20000 | G4: =E4+F4 -> 742387.12 | H4: =Sheet1!CR2 -> 0.18 | I4: =G4*H4 -> 133629.68 | J4: =G4+I4 -> 876016.8 | K4: =Sheet1!CU2 -> 100 | L4: =Sheet1!CV2 -> KMS | M4: =J4*K4 -> 87601680 | N4: IS | O4: 284 | P4: =+IFERROR(VLOOKUP($P$2,Sheet1!J2:L2,3,0),0) -> 0 | Q4: =+IFERROR(VLOOKUP($Q$2,Sheet1!J2:M2,3,0),0) -> 0 | R4: =+IFERROR(VLOOKUP($R$2,Sheet1!J2:M2,3,0),0) -> 0 | S4: =+IFERROR(VLOOKUP($S$2,Sheet1!J2:M2,3,0),0) -> 0 | T4: =+IFERROR(VLOOKUP($T$2,Sheet1!J2:M2,3,0),0) -> 0 | U4: =+IFERROR(VLOOKUP($U$2,Sheet1!J2:M2,3,0),0) -> 0 | V4: =+IFERROR(VLOOKUP($V$2,Sheet1!J2:M2,3,0),0) -> 0 | W4: =+IFERROR(VLOOKUP($W$2,Sheet1!N2:Q2,3,0),0) -> 0 | X4: =+IFERROR(VLOOKUP($X$2,Sheet1!N2:Q2,3,0),0) -> 0 | Y4: =+IFERROR(VLOOKUP($Y$2,Sheet1!F2:I2,3,0),0) -> 0 | Z4: 64 | AA4: =+IFERROR(VLOOKUP($AA$2,Sheet1!F2:I2,3,0),0) -> 0 | AB4: =+IFERROR(VLOOKUP($AB$2,Sheet1!F2:I2,3,0),0) -> 0 | AC4: =+IFERROR(VLOOKUP($AC$2,Sheet1!F2:I2,3,0),0) -> 0 | AD4: =+IFERROR(VLOOKUP($AD$2,Sheet1!F2:I2,3,0),0) -> 0 | AE4: =+IFERROR(VLOOKUP($AE$2,Sheet1!F2:I2,3,0),0) -> 0 | AF4: =+IFERROR(VLOOKUP($AF$2,Sheet1!F2:I2,3,0),0) -> 0 | AG4: =+IFERROR(VLOOKUP($AG$2,Sheet1!R2:U2,3,0),0) -> 0 | AH4: =+IFERROR(VLOOKUP($AH$2,Sheet1!R2:U2,3,0),0) -> 0 | AI4: =+IFERROR(VLOOKUP($AI$2,Sheet1!V2:Y2,3,0),0) -> 0 | AJ4: =+IFERROR(VLOOKUP($AJ$2,Sheet1!V2:Y2,3,0),0) -> 0 | AK4: 384 | AL4: =+IFERROR(VLOOKUP($AL$2,Sheet1!V2:Y2,3,0),0) -> 0 | AM4: =+IFERROR(VLOOKUP($AM$2,Sheet1!V2:Y2,3,0),0) -> 0 | AN4: =+IFERROR(VLOOKUP($AN$2,Sheet1!V2:Y2,3,0),0) -> 0 | AO4: =+IFERROR(VLOOKUP($AO$2,Sheet1!V2:Y2,3,0),0) -> 0 | AP4: =+IFERROR(VLOOKUP($AP$2,Sheet1!V2:Y2,3,0),0) -> 0 | AQ4: =+IFERROR(VLOOKUP($AQ$2,Sheet1!V2:Y2,3,0),0) -> 0 | AR4: =+IFERROR(VLOOKUP($AR$2,Sheet1!Z2:AB2,3,0),0) -> 0 | AS4: =+IFERROR(VLOOKUP($AS$2,Sheet1!AD2:AG2,3,0),0) -> 0 | AT4: =+IFERROR(VLOOKUP($AT$2,Sheet1!AD2:AG2,3,0),0) -> 0 | AU4: =+IFERROR(VLOOKUP($AU$2,Sheet1!AD2:AG2,3,0),0) -> 0 | AV4: =+IFERROR(VLOOKUP($AV$2,Sheet1!AD2:AG2,3,0),0) -> 0 | AW4: =+IFERROR(VLOOKUP($AW$2,Sheet1!AD2:AG2,3,0),0) -> 0 | AX4: =+IFERROR(VLOOKUP($AX$2,Sheet1!AD2:AG2,3,0),0) -> 0 | AY4: 122 | AZ4: =+IFERROR(VLOOKUP($AZ$2,Sheet1!AD2:AG2,3,0),0) -> 0 | BA4: =+IFERROR(VLOOKUP($BA$2,Sheet1!AD2:AG2,3,0),0) -> 0 | BB4: =+IFERROR(VLOOKUP($BB$2,Sheet1!AH2:AK2,3,0),0) -> 0 | BC4: =+IFERROR(VLOOKUP($BC$2,Sheet1!AH2:AK2,3,0),0) -> 0 | BD4: =+IFERROR(VLOOKUP($BD$2,Sheet1!AH2:AK2,3,0),0) -> 0 | BE4: =+IFERROR(VLOOKUP($BE$2,Sheet1!AH2:AK2,3,0),0) -> 0 | BF4: =+IFERROR(VLOOKUP($BF$2,Sheet1!AH2:AK2,3,0),0) -> 0 | BG4: =+IFERROR(VLOOKUP($BG$2,Sheet1!AH2:AK2,3,0),0) -> 0 | BH4: 650 | BI4: =+IFERROR(VLOOKUP($BI$2,Sheet1!AH2:AK2,3,0),0) -> 0 | BJ4: =+IFERROR(VLOOKUP($BJ$2,Sheet1!AH2:AK2,3,0),0) -> 0 | BK4: =+IFERROR(VLOOKUP($BK$2,Sheet1!AH2:AK2,3,0),0) -> 0 | BL4: =+IFERROR(VLOOKUP($BL$2,Sheet1!AH2:AK2,3,0),0) -> 0 | BM4: =+IFERROR(VLOOKUP($BM$2,Sheet1!AL2:AO2,3,0),0) -> 0 | BN4: =+IFERROR(VLOOKUP($BN$2,Sheet1!AL2:AO2,3,0),0) -> 0 | BO4: =+IFERROR(VLOOKUP($BO$2,Sheet1!AL2:AO2,3,0),0) -> 0 | BP4: =+IFERROR(VLOOKUP($BP$2,Sheet1!AL2:AO2,3,0),0) -> 0 | BQ4: =+IFERROR(VLOOKUP($BQ$2,Sheet1!AL2:AO2,3,0),0) -> 0 | BR4: =+IFERROR(VLOOKUP($BR$2,Sheet1!AL2:AO2,3,0),0) -> 0 | BS4: =+IFERROR(VLOOKUP($BS$2,Sheet1!AL2:AO2,3,0),0) -> 0 | BT4: =+IFERROR(VLOOKUP($BT$2,Sheet1!AL2:AO2,3,0),0) -> 0 | BU4: 383 | BV4: =+IFERROR(VLOOKUP($BV$2,Sheet1!AL2:AO2,3,0),0) -> 0 | BW4: =+IFERROR(VLOOKUP($BW$2,Sheet1!AL2:AO2,3,0),0) -> 0 | BX4: =+IFERROR(VLOOKUP($BX$2,Sheet1!AL2:AO2,3,0),0) -> 0 | BY4: 422 | BZ4: =+IFERROR(VLOOKUP($BZ$2,Sheet1!AT2:AW2,3,0),0) -> 0 | CA4: =+IFERROR(VLOOKUP($CA$2,Sheet1!AX2:BA2,3,0),0) -> 0 | CB4: =+IFERROR(VLOOKUP($CB$2,Sheet1!BB2:BE2,3,0),0) -> 0 | CC4: 150 | CD4: =+IFERROR(VLOOKUP($CD$2,Sheet1!BJ2:BM2,3,0),0) -> 0 | CE4: =+IFERROR(VLOOKUP($CE$2,Sheet1!BN2:BQ2,3,0),0) -> 0 | CF4: =+IFERROR(VLOOKUP($CF$2,Sheet1!BR2:BU2,3,0),0) -> 0 | CG4: =+IFERROR(VLOOKUP($CG$2,Sheet1!BV2:BY2,3,0),0) -> 0 | CH4: WOOD | CI4: MD0100021 | CJ4: DRUM - 64 X 24 X 32 X 3 | CK4: 500 | CL4: 8289 | CM4: =SUMPRODUCT($O$3:$CG$3,O4:CG4)+CL4 -> 496145 | CN4: 0.05 | CO4: =CM4*CN4 -> 24807.25 | CP4: 0.25 | CQ4: =CM4*CP4 -> 124036.25 | CR4: 0 | CS4: =CM4*CR4 -> 0 | CT4: =CM4+CO4+CQ4+CS4 -> 644988.5 | CU4: 0.02 | CV4: =CT4*CU4 -> 12899.77 | CW4: 0.1 | CX4: =CT4*CW4 -> 64498.85 | CY4: =Sheet1!CM2 -> 0 | CZ4: =CY4*CT4 -> 0
CP6: AS CONFIRMED BY AKSHAT SIR | CU6: AS CONFIRMED BY ANIRUDDHA SIR
A8: Cable Weight | B8: Drum Weight | C8: Cable + Drum Weight | D8: Truck Weight | E8: Order Quantity | F8: Stnd Length | G8: Truck type | H8: Fare of one truck | I8: No of Drum in one truck | J8: Total length in one Truck | K8: No of Truck | L8: Total Freight | M8: Freight per KM
A9: =SUM(O4:CG4) -> 2459 | B9: 345 | C9: =((A9*F9)+B9) -> 1574.5 | D9: =C9*I9 -> 12596 | E9: =K4 -> 100 | F9: =CK4/1000 -> 0.5 | G9: 16 MT | H9: 80000 | I9: 8 | J9: =F9*I9 -> 4 | K9: =ROUNDUP((E9/J9),0) -> 25 | L9: =H9*K9 -> 2000000 | M9: =L9/E9 -> 20000
A13: DOCKET NO. | B13: BASE DATE | C13: ITEM CODE | D13: PROPOSE ERP ITEM NAME | E13: EX-WORKS (PER MTR) | F13: FREIGHT PER MTR | G13: PRICE INCLUDING FREIGHT (PER MTR) | H13: GST % | I13: GST VALUE | J13: PRICE INCLUDING GST & FREIGHT (PER MTR) | K13: QTY | L13: Unit | M13: TOTAL PRICE OF FULL QTY (INCLUDING FRIGHT & GST)
A15: =A4 -> ENQ-20143-25-26 | B15: =B4 -> 46143 | C15: =C4 -> FA1300013 | D15: =D4 -> 3 CORE X 35 SQ. MM. AL/ARM - STRIP (XLPE) - 11 KV | E15: =ROUNDUP(E4/1000,0) -> 723 | F15: =ROUNDUP(F4/1000,0) -> 20 | G15: =E15+F15 -> 743 | H15: =H4 -> 0.18 | I15: =G15*H15 -> 133.74 | J15: =G15+I15 -> 876.74 | K15: =K4*1000 -> 100000 | L15: MTR | M15: =J15*K15 -> 87674000
M18: =M15-M4 -> 72319.84

Sheet NORMAL
O1: Conductor | W1: AL ALLOY | Y1: Insulation Screening (Metallic) | AG1: Insulation Screening (Non-Metallic) | AI1: Insulation | AR1: POLY TAPE | AS1: Inner Sheath | BB1: Armouring | BM1: Outer Sheath | BY1: FILLER | BZ1: GREASE | CA1: Water swellable Tape | CB1: Semi conducting Water Swellable tape | CC1: SEMICON TAPE | CD1: GLASS FIBER TAPE | CE1: COPPER WIRE 0.8 MM | CF1: RUBBERIZED COTTON TAPE | CG1: Water Tight Compound | CH1: DRUM TYPE | CL1: DRUM COST PER KM | CM1: TOTAL RM COST | CN1: EXTRA CONSUMPTION | CO1: EXTRA CONSUMPTION VALUE | DA1: $A$1
A2: DOCKET NO. | B2: BASE DATE | C2: ITEM CODE | D2: PROPOSE ERP ITEM NAME | E2: EX-WORKS (PER KM) | F2: FREIGHT PER KM | G2: PRICE INCLUDING FREIGHT (PER KM) | H2: GST % | I2: GST VALUE | J2: PRICE INCLUDING GST & FREIGHT (PER KM) | K2: QTY | L2: Unit | M2: TOTAL PRICE OF FULL QTY (INCLUDING FRIGHT & GST) | N2: NON CHAIN BOM ID | O2: Alumimium | P2: Alumimium ALLOY | Q2: Copper | R2: AL-59 | S2: AL-4 | T2: AL-7 | U2: Flexible Copper | V2: Galvanized steel wire | W2: Alumimium | X2: Alumimium ALLOY | Y2: Coper tape - 0.1 mm | Z2: Copper Tape - 0.03 mm | AA2: Copper Tape - 0.035 mm | AB2: Copper Tape - 0.04 mm | AC2: Copper Tape - 0.045 mm | AD2: Copper Tape - 0.050 mm | AE2: Copper Tape - 0.060 mm | AF2: Copper Tape - 0.075 mm(DOUBLE) | AG2: Extruded semiconductive | AH2: Extruded Semiconductive(Stripable) | AI2: HT-XLPE | AJ2: LT-XLPE | AK2: TR XLPE | AL2: Type A PVC | AM2: Type C PVC (HR) | AN2: Type A PVC-1.45 | AO2: Type A PVC-FR | AP2: Type A PVC-FRLS | AQ2: Type A PVC-1.38 | AR2: POLY TAPE | AS2: FR PVC Type ST-1 | AT2: FR PVC Type ST-2 | AU2: FRLSH PVC Type ST-1 | AV2: FRLSH PVC Type ST-2 | AW2: PVC Type ST-1 | AX2: PVC Type ST-1-PRESSURE EXTRUDED | AY2: PVC Type ST-2 | AZ2: PVC COMPOUND 1.48 | BA2: PVC Type ST-2-PRESSURE EXTRUDED | BB2: ACSR CORE WIRE | BC2: ACSR DOG STEEL WIRE | BD2: Aluminium Flat Strip | BE2: Aluminium Round Wire | BF2: Alumimium Tape | BG2: Double Steel Tape | BH2: Galvanised Steel Flat Strip | BI2: Galvanised Steel Flat Strip (Double) | BJ2: Galvanised Steel Flat Strip-B | BK2: Galvanised Steel Round Wire | BL2: Galvanised Steel Round Wire (Double) | BM2: FR PVC Type ST-1 | BN2: FR PVC Type ST-2 | BO2: FRLSH PVC Type ST-1 | BP2: FRLSH PVC Type ST-2 | BQ2: ZHFR | BR2: PE-ST-3 | BS2: PE-ST-7 | BT2: PVC Type ST-1 | BU2: PVC Type ST-2 | BV2: PVC COMPOUND 1.48 | BW2: PVC Type ST-2-PRESSURE EXTRUDED | BX2: UV & Track Resistant XLPE | BY2: FILLER | BZ2: Grease | CA2: Water swellable Tape | CB2: Semi conducting Water Swellable tape | CC2: SEMICON TAPE | CD2: GLASS FIBER TAPE | CE2: COPPER WIRE 0.8 MM | CF2: RUBBERIZED COTTON TAPE | CG2: Water Tight Compound | CH2: PROPOSE DRUM TYPE | CI2: DRUM CODE | CJ2: DRUM SIZE (FxbXtx Ft) | CK2: PARTY STANDARD LENGTH (MTR) | CP2: MFG% | CQ2: MFG VALUE | CR2: PROF% | CS2: PROFIT VALUE | CT2: 1ST EX-WORKS | CU2: Intt % | CV2: INTT VALUE | CW2: insp% | CX2: INSP VALUE | CY2: TTR Charges% | CZ2: TTR Charges VALUE
O3: =+IFERROR(VLOOKUP($O$2,Sheet1!J:L,2,0),0) -> 0 | P3: =+IFERROR(VLOOKUP($P$2,Sheet1!J:L,2,0),0) -> 0 | Q3: =+IFERROR(VLOOKUP($Q$2,Sheet1!J:M,2,0),0) -> 0 | R3: =+IFERROR(VLOOKUP($R$2,Sheet1!J:M,2,0),0) -> 0 | S3: =+IFERROR(VLOOKUP($S$2,Sheet1!J:M,2,0),0) -> 0 | T3: =+IFERROR(VLOOKUP($T$2,Sheet1!J:M,2,0),0) -> 0 | U3: =+IFERROR(VLOOKUP($U$2,Sheet1!J:M,2,0),0) -> 0 | V3: =+IFERROR(VLOOKUP($V$2,Sheet1!J:M,2,0),0) -> 0 | W3: =+IFERROR(VLOOKUP($W$2,Sheet1!N:Q,2,0),0) -> 0 | X3: =+IFERROR(VLOOKUP($X$2,Sheet1!N:O,2,0),0) -> 0 | Y3: =+IFERROR(VLOOKUP($Y$2,Sheet1!F:I,2,0),0) -> 0 | Z3: =+IFERROR(VLOOKUP($Z$2,Sheet1!F:I,2,0),0) -> 0 | AA3: =+IFERROR(VLOOKUP($AA$2,Sheet1!F:I,2,0),0) -> 0 | AB3: =+IFERROR(VLOOKUP($AB$2,Sheet1!F:I,2,0),0) -> 0 | AC3: =+IFERROR(VLOOKUP($AC$2,Sheet1!F:I,2,0),0) -> 0 | AD3: =+IFERROR(VLOOKUP($AD$2,Sheet1!F:I,2,0),0) -> 0 | AE3: =+IFERROR(VLOOKUP($AE$2,Sheet1!F:I,2,0),0) -> 0 | AF3: =+IFERROR(VLOOKUP($AF$2,Sheet1!F:I,2,0),0) -> 0 | AG3: =+IFERROR(VLOOKUP($AG$2,Sheet1!R:U,2,0),0) -> 0 | AH3: =+IFERROR(VLOOKUP($AH$2,Sheet1!R:U,2,0),0) -> 0 | AI3: =+IFERROR(VLOOKUP($AI$2,Sheet1!V:Y,2,0),0) -> 0 | AJ3: =+IFERROR(VLOOKUP($AJ$2,Sheet1!V:Y,2,0),0) -> 0 | AK3: =+IFERROR(VLOOKUP($AK$2,Sheet1!V:Y,2,0),0) -> 0 | AL3: =+IFERROR(VLOOKUP($AL$2,Sheet1!V:Y,2,0),0) -> 0 | AM3: =+IFERROR(VLOOKUP($AM$2,Sheet1!V:Y,2,0),0) -> 0 | AN3: =+IFERROR(VLOOKUP($AN$2,Sheet1!V:Y,2,0),0) -> 0 | AO3: =+IFERROR(VLOOKUP($AO$2,Sheet1!V:Y,2,0),0) -> 0 | AP3: =+IFERROR(VLOOKUP($AP$2,Sheet1!V:Y,2,0),0) -> 0 | AQ3: =+IFERROR(VLOOKUP($AQ$2,Sheet1!V:Y,2,0),0) -> 0 | AR3: =+IFERROR(VLOOKUP($AR$2,Sheet1!Z2:AA840,2,0),0) -> 0 | AS3: =+IFERROR(VLOOKUP($AS$2,Sheet1!AD2:AG840,2,0),0) -> 0 | AT3: =+IFERROR(VLOOKUP($AT$2,Sheet1!AD2:AG840,2,0),0) -> 0 | AU3: =+IFERROR(VLOOKUP($AU$2,Sheet1!AD2:AG840,2,0),0) -> 0 | AV3: =+IFERROR(VLOOKUP($AV$2,Sheet1!AD2:AG840,2,0),0) -> 0 | AW3: =+IFERROR(VLOOKUP($AW$2,Sheet1!AD2:AG840,2,0),0) -> 0 | AX3: =+IFERROR(VLOOKUP($AX$2,Sheet1!AD2:AG840,2,0),0) -> 0 | AY3: =+IFERROR(VLOOKUP($AY$2,Sheet1!AD2:AG840,2,0),0) -> 0 | AZ3: =+IFERROR(VLOOKUP($AZ$2,Sheet1!AD2:AG840,2,0),0) -> 0 | BA3: =+IFERROR(VLOOKUP($BA$2,Sheet1!AD2:AG840,2,0),0) -> 0 | BB3: =+IFERROR(VLOOKUP($BB$2,Sheet1!AH2:AK840,2,0),0) -> 0 | BC3: =+IFERROR(VLOOKUP($BC$2,Sheet1!AH2:AK840,2,0),0) -> 0 | BD3: =+IFERROR(VLOOKUP($BD$2,Sheet1!AH2:AK840,2,0),0) -> 0 | BE3: =+IFERROR(VLOOKUP($BE$2,Sheet1!AH2:AK840,2,0),0) -> 0 | BF3: =+IFERROR(VLOOKUP($BF$2,Sheet1!AH2:AK840,2,0),0) -> 0 | BG3: =+IFERROR(VLOOKUP($BG$2,Sheet1!AH2:AK840,2,0),0) -> 0 | BH3: =+IFERROR(VLOOKUP($BH$2,Sheet1!AH2:AK840,2,0),0) -> 0 | BI3: =+IFERROR(VLOOKUP($BI$2,Sheet1!AH2:AK840,2,0),0) -> 0 | BJ3: =+IFERROR(VLOOKUP($BJ$2,Sheet1!AH2:AK840,2,0),0) -> 0 | BK3: =+IFERROR(VLOOKUP($BK$2,Sheet1!AH2:AK840,2,0),0) -> 0 | BL3: =+IFERROR(VLOOKUP($BL$2,Sheet1!AH2:AK840,2,0),0) -> 0 | BM3: =+IFERROR(VLOOKUP($BM$2,Sheet1!AL2:AO840,2,0),0) -> 0 | BN3: =+IFERROR(VLOOKUP($BN$2,Sheet1!AL2:AO840,2,0),0) -> 0 | BO3: =+IFERROR(VLOOKUP($BO$2,Sheet1!AL2:AO840,2,0),0) -> 0 | BP3: =+IFERROR(VLOOKUP($BP$2,Sheet1!AL2:AO840,2,0),0) -> 0 | BQ3: =+IFERROR(VLOOKUP($BQ$2,Sheet1!AL2:AO840,2,0),0) -> 0 | BR3: =+IFERROR(VLOOKUP($BR$2,Sheet1!AL2:AO840,2,0),0) -> 0 | BS3: =+IFERROR(VLOOKUP($BS$2,Sheet1!AL2:AO840,2,0),0) -> 0 | BT3: =+IFERROR(VLOOKUP($BT$2,Sheet1!AL2:AO840,2,0),0) -> 0 | BU3: =+IFERROR(VLOOKUP($BU$2,Sheet1!AL2:AO840,2,0),0) -> 0 | BV3: =+IFERROR(VLOOKUP($BV$2,Sheet1!AL2:AO840,2,0),0) -> 0 | BW3: =+IFERROR(VLOOKUP($BW$2,Sheet1!AL2:AO840,2,0),0) -> 0 | BX3: =+IFERROR(VLOOKUP($BX$2,Sheet1!AL2:AO840,2,0),0) -> 0 | BY3: =+IFERROR(VLOOKUP($BY$2,Sheet1!AP2:AS840,2,0),0) -> 0 | BZ3: =+IFERROR(VLOOKUP($BZ$2,Sheet1!AT2:AW840,2,0),0) -> 0 | CA3: =+IFERROR(VLOOKUP($CA$2,Sheet1!AX2:BA840,2,0),0) -> 0 | CB3: =+IFERROR(VLOOKUP($CB$2,Sheet1!BB2:BE840,2,0),0) -> 0 | CC3: =+IFERROR(VLOOKUP($CC$2,Sheet1!BF2:BI840,2,0),0) -> 0 | CD3: =+IFERROR(VLOOKUP($CD$2,Sheet1!BJ2:BM840,2,0),0) -> 0 | CE3: =+IFERROR(VLOOKUP($CE$2,Sheet1!BN2:BQ840,2,0),0) -> 0 | CF3: =+IFERROR(VLOOKUP($CF$2,Sheet1!BR2:BU840,2,0),0) -> 0 | CG3: =+IFERROR(VLOOKUP($CG$2,Sheet1!BV2:BY840,2,0),0) -> 0
A4: =Sheet1!A2 -> ENQ-20143-25-26 | B4: ='AUTO CALCULATION SHEET (2)'!B4 -> 46143 | C4: =Sheet1!C2 -> FA1300013 | D4: =Sheet1!D2 -> 3 CORE X 35 SQ. MM. AL/ARM - STRIP (XLPE) - 11 KV | E4: =CT4+CV4+CX4+CZ4 -> 722387.12 | F4: =ROUNDUP($M$9,0) -> 20000 | G4: =E4+F4 -> 742387.12 | H4: =Sheet1!CR2 -> 0.18 | I4: =G4*H4 -> 133629.68 | J4: =G4+I4 -> 876016.8 | K4: =Sheet1!CU2 -> 100 | L4: =Sheet1!CV2 -> KMS | M4: =J4*K4 -> 87601680 | CH4: =Sheet1!E2 -> 0 | CI4: =Sheet1!CY2 -> 0 | CJ4: =Sheet1!CZ2 -> 0 | CK4: ='AUTO CALCULATION SHEET (2)'!CK4 -> 500 | CL4: ='AUTO CALCULATION SHEET (2)'!CL4 -> 8289 | CM4: =SUMPRODUCT($O$3:$CG$3,O4:CG4)+CL4 -> 8289 | CN4: =Sheet1!CB2 -> 0 | CO4: =CM4*CN4 -> 0 | CP4: =((CT4-CM4)/CM4) -> 76.812583 | CQ4: =CM4*CP4 -> 636699.5 | CR4: 0 | CS4: =CM4*CR4 -> 0 | CT4: ='AUTO CALCULATION SHEET (2)'!CT4 -> 644988.5 | CU4: ='AUTO CALCULATION SHEET (2)'!CU4 -> 0.02 | CV4: =CT4*CU4 -> 12899.77 | CW4: ='AUTO CALCULATION SHEET (2)'!CW4 -> 0.1 | CX4: =CT4*CW4 -> 64498.85 | CY4: =Sheet1!CM2 -> 0 | CZ4: =CY4*CT4 -> 0
CM5: =CM4-CL4 -> 0
A8: Cable Weight | B8: Drum Weight | C8: Cable + Drum Weight | D8: Truck Weight | E8: Order Quantity | F8: Stnd Length | G8: Truck type | H8: Fare of one truck | I8: No of Drum in one truck | J8: Total length in one Truck | K8: No of Truck | L8: Total Freight | M8: Freight per KM
A9: =SUM(O4:CG4) -> 0 | B9: ='AUTO CALCULATION SHEET (2)'!B9 -> 345 | C9: =((A9*F9)+B9) -> 345 | D9: =C9*I9 -> 2760 | E9: =K4 -> 100 | F9: =CK4/1000 -> 0.5 | G9: ='AUTO CALCULATION SHEET (2)'!G9 -> 16 MT | H9: ='AUTO CALCULATION SHEET (2)'!H9 -> 80000 | I9: ='AUTO CALCULATION SHEET (2)'!I9 -> 8 | J9: =F9*I9 -> 4 | K9: ='AUTO CALCULATION SHEET (2)'!K9 -> 25 | L9: =H9*K9 -> 2000000 | M9: =L9/E9 -> 20000
A13: DOCKET NO. | B13: BASE DATE | C13: ITEM CODE | D13: PROPOSE ERP ITEM NAME | E13: EX-WORKS (PER MTR) | F13: FREIGHT PER MTR | G13: PRICE INCLUDING FREIGHT (PER MTR) | H13: GST % | I13: GST VALUE | J13: PRICE INCLUDING GST & FREIGHT (PER MTR) | K13: QTY | L13: Unit | M13: TOTAL PRICE OF FULL QTY (INCLUDING FRIGHT & GST)
A15: =A4 -> ENQ-20143-25-26 | B15: =B4 -> 46143 | C15: =C4 -> FA1300013 | D15: =D4 -> 3 CORE X 35 SQ. MM. AL/ARM - STRIP (XLPE) - 11 KV | E15: =ROUNDUP(E4/1000,0) -> 723 | F15: =ROUNDUP(F4/1000,0) -> 20 | G15: =E15+F15 -> 743 | H15: =H4 -> 0.18 | I15: =G15*H15 -> 133.74 | J15: =G15+I15 -> 876.74 | K15: =K4*1000 -> 100000 | L15: MTR | M15: =J15*K15 -> 87674000
E17: ='AUTO CALCULATION SHEET (2)'!E4 -> 722387.12 | M17: =M15-M4 -> 72319.84

Sheet HT&LT PC
A1: Base Date | B1: 46143
A2: PV FORMULA
A3: P = Po + AIF (Al–Alo) + XLFAL (CC–Cco) + SMIF (SMIF1–SMIF0) + FeF (FeF1–FeF0) + CCFAI (PVCc–PVCco) P = Po + AIF (Al–Alo) + XLFAL (CC–Cco) + FeF (FeF1–FeF0) + CCFAI (PVCc–PVCco)
AF7: VALUE ADDITION CALCULATION
A8: Item | B8: Calculation part | C8: Date of Inspection | D8: Applicable Date | J8: BASE DATE | P8: FACTORS | W8: Ex-Work Po | X8: PVC of al | Y8: PVC of Cu | Z8: PVC of XLPE | AA8: PVC OF PVC | AB8: PVC OF FE | AC8: PVC OF CU TAPE | AD8: PV/PKM | AE8: Billing Price/PKM
D9: Date | E9: Al | F9: Cu | G9: Cc | H9: PVCc | I9: Fe | J9: Date | K9: Alo | L9: Cuo | M9: Cco | N9: PVCco | O9: Feo | AF9: ='[1]AUTO CALCULATION SHEET (2)'!N2 -> Alumimium | AG9: ='[1]AUTO CALCULATION SHEET (2)'!P2 -> Copper | AH9: ='[1]AUTO CALCULATION SHEET (2)'!W2 -> Alumimium ALLOY | AI9: ='[1]AUTO CALCULATION SHEET (2)'!Y2 -> Copper Tape - 0.03 mm | AJ9: ='[1]AUTO CALCULATION SHEET (2)'!AF2 -> Extruded semiconductive | AK9: TR-XLPE | AL9: ='[1]AUTO CALCULATION SHEET (2)'!AI2 -> LT-XLPE | AM9: ='[1]AUTO CALCULATION SHEET (2)'!AM2 -> Type A PVC-1.45 | AN9: ='[1]AUTO CALCULATION SHEET (2)'!AV2 -> PVC Type ST-1 | AO9: ='[1]AUTO CALCULATION SHEET (2)'!AX2 -> PVC Type ST-2 | AP9: ='[1]AUTO CALCULATION SHEET (2)'!BA2 -> ACSR CORE WIRE | AQ9: ='[1]AUTO CALCULATION SHEET (2)'!BB2 -> ACSR DOG STEEL WIRE | AR9: ='[1]AUTO CALCULATION SHEET (2)'!BG2 -> Galvanised Steel Flat Strip | AS9: ='[1]AUTO CALCULATION SHEET (2)'!BS2 -> PVC Type ST-1 | AT9: ='[1]AUTO CALCULATION SHEET (2)'!BT2 -> PVC Type ST-2 | AU9: ='[1]AUTO CALCULATION SHEET (2)'!BX2 -> FILLER | AV9: SEMICON TAPE | AW9: RMC | AX9: Drum | AY9: RMC+Drum | AZ9: VA | BA9: Groos VA% | BB9: Mfg % | BC9: Int % | BD9: Ins% | BE9: Net VA
P10: Alf | Q10: Cu | R10: XLFAL | S10: CCFAI | T10: CCFCu | U10: FeF | V10: Smif | AF10: 380 | AI10: 1529 | AK10: 280 | AO10: 77 | AR10: 90 | AT10: =77+5 -> 82 | AU10: 32 | AV10: 365
AF11: Kg/Km | AG11: Kg/Km | AH11: Kg/Km | AI11: Kg/Km | AJ11: Kg/Km | AK11: Kg/Km | AL11: Kg/Km | AM11: Kg/Km | AN11: Kg/Km | AO11: Kg/Km | AP11: Kg/Km | AQ11: Kg/Km | AR11: Kg/Km | AS11: Kg/Km | AT11: Kg/Km | AU11: Kg/Km | AV11: Kg/Km
A12: 3 CORE X 35 SQ. MM. AL/ARM - STRIP (XLPE) - 11 KV@FA1300013 | C12: PROVISIONAL | D12: 46199 | E12: 403135.71 | F12: 1388640.9 | G12: 219178 | H12: 178375 | I12: 89250 | J12: =$B$1 -> 46143 | K12: 418401 | L12: 1385582 | M12: 219178 | N12: 178375 | O12: 89250 | P12: 0.302 | Q12: 0 | R12: 0.545 | S12: 1.142 | T12: 0 | U12: 0.731 | V12: 0.061 | W12: ='AUTO CALCULATION SHEET (2)'!E4 -> 722387.12 | X12: =(P12*(E12-K12)) -> -4610.1176 | Y12: =(Q12*(F12-L12)) -> 0 | Z12: =(R12*(G12-M12)) -> 0 | AA12: =(S12*(H12-N12)) -> 0 | AB12: =(U12*(I12-O12)) -> 0 | AC12: =V12*(F12-L12) -> 186.59046 | AD12: =X12+Y12+Z12+AA12+AB12+AC12 -> -4423.5271 | AE12: =+W12+AD12 -> 717963.59 | AF12: ='AUTO CALCULATION SHEET (2)'!O4 -> 284 | AI12: ='AUTO CALCULATION SHEET (2)'!Z4 -> 64 | AK12: ='AUTO CALCULATION SHEET (2)'!AK4 -> 384 | AO12: ='AUTO CALCULATION SHEET (2)'!AY4 -> 122 | AR12: ='AUTO CALCULATION SHEET (2)'!BH4 -> 650 | AT12: ='AUTO CALCULATION SHEET (2)'!BU4 -> 383 | AU12: ='AUTO CALCULATION SHEET (2)'!BY4 -> 422 | AV12: ='AUTO CALCULATION SHEET (2)'!CC4 -> 150 | AW12: =SUMPRODUCT(AF12:AV12,$AF$10:$AV$10) -> 480850 | AX12: ='AUTO CALCULATION SHEET (2)'!CL4 -> 8289 | AY12: =AW12+AX12 -> 489139 | AZ12: =AE12-AY12 -> 228824.59 | BA12: =ROUND((AZ12/AY12)*100,2) -> 46.78 | BB12: 25 | BC12: 2 | BD12: 10 | BE12: =BA12-BB12-BC12-BD12 -> 9.78

Sheet terms
A1: The quoted prices are on Firm inclusive of packing and forwading but exclusive of GST Statutory levies.
A2: The quoted prices are on VARIABLE basis with PV base Date: DD/MM/YYYY as per "IEEMA", inclusive of packing and forwading but exclusive of GST Statutory levies.
A4: The above prices are quoted on Ex-works basis, where freight will be charged extra.
A5: The above prices are quoted on FOR Destination basis, where freight is included, refer Price offer.
A6: The above prices are quoted on Ex-works+Freight basis.
A8: 20% Advance and Balance against PI (Proforma Invoice) prior to dispatch
A9: 100% against "90 days" LC, where 90 days usance interest will be borne by LPIPL
A10: 100% against "120 days" LC, where 120 days usance interest will be borne by LPIPL
A11: 100% against "45 days" LC, where 45 days usance interest will be borne by LPIPL
A12: 100% against "60 days" LC, where 60 days usance interest will be borne by LPIPL
A13: 100% against "30 days" LC, where 30 days usance interest will be borne by LPIPL
A14: 100% against 60 days PDC from the date of MRC/MRN
... A27: Negotiable
