Workbook

Sheet Sheet1
A1: DOCKET NO. | B1: Base Date | C1: ITEM CODE | D1: PROPOSE ERP ITEM NAME | E1: Propose Drum Type | F1: Insulation Screening(Metallic) | G1: RM Rate(Insulation Screening(Metallic)) | H1: Weight (Insulation Screening (Metallic)) | I1: Cost Insulation Screening(Metallic) | J1: Conductor | K1: RM Rate(Conductor) | L1: Weight(Conductor) | M1: Cost(Conductor) | N1: AL ALLOY | O1: RM Rate(AL Alloy) | P1: Weight(Al Alloy) | Q1: Cost(AL Alloy) | R1: Insulation Screening(Non-Metallic) | S1: RM Rate(Insulation Screening(Non-Metallic)) | T1: Weight(Insulation Screening(Non-Metallic) | U1: Cost(Insulation Screening(Non-Metallic) | V1: Insulation | W1: RM Rate(Insulation) | X1: Weight(Insulation) | Y1: Cost(Insulation) | Z1: Poly Tape | AA1: RM Rate(Poly Tape) | AB1: Weight(Poly Tape) | AC1: Cost(Poly Tape) | AD1: Inner Sheath | AE1: RM Rate(Inner Sheath) | AF1: Weight(Inner Sheath) | AG1: Cost(Inner Sheath) | AH1: Armouring | AI1: RM Rate(Armouring) | AJ1: Weight(Armouring) | AK1: Cost(Armouring) | AL1: Outer Sheath | AM1: RM Rate(Outer Sheath) | AN1: Weight(Outer Sheath) | AO1: Cost(Outer Sheath) | AP1: Filler | AQ1: RM Rate(Filler) | AR1: Weight(Filler) | AS1: Cost(Filler) | AT1: Grease | AU1: RM Rate(Grease) | AV1: Weight(Grease) | AW1: Cost(Grease) | AX1: Water Swellable Tape | AY1: RM Rate(Water Swellable Tape) | AZ1: Weight(Water Swellable Tape) | BA1: Cost(Water Swellable Tape) | BB1: Semi Conducting Water Swellable Tape | BC1: RM Rate(Semi Conducting Water Swellable Tape) | BD1: Weight(Semi Conducting Water Swellable Tape) | BE1: Cost(Semi Conducting Water Swellable Tape) | BF1: Semicon Tape | BG1: RM Rate(Semicon Tape) | BH1: Weight(Semicon Tape) | BI1: Cost(Semicon Tape) | BJ1: Glass Fiber Tape | BK1: RM Rate(Glass Fiber Tape) | BL1: Weight(Glass Fiber Tape) | BM1: Cost(Glass Fiber Tape) | BN1: Copper Wire 0.8MM | BO1: RM Rate(Copper Wire 0.8MM) | BP1: Weight(Copper Wire 0.8MM) | BQ1: Cost(Copper Wire 0.8MM) | BR1: Rubberized Cotton Tape | BS1: RM Rate(Rubberized Cotton Tape) | BT1: Weight(Rubberized Cotton Tape) | BU1: Cost(Rubberized Cotton Tape) | BV1: Water Tight Compound | BW1: RM Rate(Water Tight Compound) | BX1: Weight(Water Tight Compound) | BY1: Cost(Water Tight Compound) | BZ1: Drum Cost Per KM | CA1: Total RM Cost | CB1: FIRM % | CC1: Firm Value | CD1: MFG% | CE1: MFG Value | CF1: PROF% | CG1: Profit Value | CH1: 1st EX-Works | CI1: Intt % | CJ1: Intt Value | CK1: insp% | CL1: Insp Value | CM1: TTR CHARGES% | CN1: TTR Value | CO1: EX-Works Per KM | CP1: Freight Per KM | CQ1: Price Including Freight Per KM | CR1: GST % | CS1: GST Value | CT1: Price Including GST & Freight Per KM | CU1: QTY | CV1: Unit | CW1: Total Price Of Full QTY(Including Freight&GST) | CX1: PARTY LENGTH (IF STANDER LENGTH NOT MATCH WITH PAR | CY1: DRUM CODE | CZ1: DRUM SIZE (FxbXtx Ft)
A2: ENQ-19467-25-26 | C2: FC0700003 | D2: AAAC : RABBIT CONDUCTOR - 55 SQ. MM. (7/3.15) | E2: WOOD | H2: 0 | J2: Alumimium Alloy | L2: 150 | P2: 0 | T2: 0 | X2: 0 | AB2: 0 | AF2: 0 | AJ2: 0 | AN2: 0 | AR2: 0 | AV2: 0 | AZ2: 0 | BD2: 0 | BH2: 0 | BL2: 0 | BP2: 0 | BT2: 0 | BX2: 0 | BZ2: 739.5 | CA2: 739.5 | CH2: 739.5 | CO2: 739.5 | CQ2: 739.5 | CR2: 0.18 | CS2: 133.11 | CT2: 872.61 | CU2: 900 | CV2: KMS | CW2: 785349 | CX2: 6000 | CY2: MD0100015 | CZ2: DRUM - 48 X 20 X 28 X 2.25 - RDSO

Sheet AUTO CALCULATION SHEET (2)
A2: RAIL VIKAS NIGAM LIMITED
A4: TENDER SPECIFICATION NO () | B4: RVNL/B/E/RDSS/MPPK/Pkg-16/MAT/RE-SLT/CONDUCTORS
A5: TENDER DESCRIPTION () | B5: Manufacturing & Supply of Conductor AAAC Rabbit as per relevant IS and as per Specification of M.P. Poorv Kshetra V. V. Co. Ltd.
A6: Last Date & Time of Submission () | B6: 11-05-2026 upto 12:00:00 PM OPENING ON '11-05-2026 upto 12:30:00 PM
A7: REVERSE AUCTION | B7: Not Mention
A8: Price () | B8: The price is firm on F.O.R Destination Basis to the Supply at our Stores at Chhatarpur (Package-16). The prices include Freight, Incidental Charges, Tolls, Insurances, etc. in the account of Supplier. GST would be extra at actual as applicable at the time of dispatch on flat rate as governed by the concerned GST Rules. There shall be no price variation in the CONTRACT/ITEM and the rates shall be firm for a period of ONE Year from the date of Purchase Order.
A9: Validity () | B9: The bid must be valid up to 45 days from the date of opening of bids.
A10: Delivery Period () | B10: 10 days for Complete Order <Part/Lot delivery at Chhatarpur stores (PKG-16)
A11: Payment Terms () | B11: Advance : Payment of 20% advance of the Base Order Value (without GST) as provided manufacturing clearance, would be made on submission of Corporate Guarantee (Form-CG) After Delivery : After receipt of materials at F.O.R. Destination payment of 78% balance of the supplied material will be released after random sample testing/M.R.C. by DISCOM, within 15 (Fifteen) Working Days through RTGS/NEFT or suitable payment mode. On Acceptance : Balance payment of 2% will be released after/upon satisfactory acceptance of materials by concerned DISCOM.
A12: Standard length () | B12: The standard length of the conductors shall be 2000 meters. The conductor drum shall be adequate to wind one or more standard length of 2000 meters of SQUIRREL/WEASEL/RABIT/RACOON/DOG/PANTHER AAA conductor
A13: Packing () | B13: The conductor shall be supplied in non-returnable, strong, wooden drums provided with laggin of adequate strength, constructed to protect the conductor against any damage and displacement during transit, storage and subsequent handling and stringing operation in the field.
A14: Technical Specification
N18: Conductor | V18: AL ALLOY | X18: Insulation Screening (Metallic) | AF18: Insulation Screening (Non-Metallic) | AH18: Insulation | AQ18: POLY TAPE | AR18: Inner Sheath | BA18: Armouring | BL18: Outer Sheath | BX18: FILLER | BY18: GREASE | BZ18: Water swellable Tape | CA18: Semi conducting Water Swellable tape | CB18: SEMICON TAPE | CC18: GLASS FIBER TAPE | CD18: COPPER WIRE 0.8 MM | CE18: RUBBERIZED COTTON TAPE | CF18: Water Tight Compound | CG18: DRUM TYPE | CK18: DRUM COST PER KM | CL18: TOTAL RM COST | CM18: EXTRA CONSUMPTION | CN18: EXTRA CONSUMPTION VALUE | CZ18: $A$1
A19: DOCKET NO. | B19: BASE DATE | C19: ITEM CODE | D19: PROPOSE ERP ITEM NAME | E19: EX-WORKS (PER KM) | F19: FREIGHT PER KM | G19: PRICE INCLUDING FREIGHT (PER KM) | H19: GST % | I19: GST VALUE | J19: PRICE INCLUDING GST & FREIGHT (PER KM) | K19: QTY | L19: Unit | M19: TOTAL PRICE OF FULL QTY (INCLUDING FRIGHT & GST) | N19: Alumimium | O19: Alumimium ALLOY | P19: Copper | Q19: AL-59 | R19: AL-4 | S19: AL-7 | T19: Flexible Copper | U19: Galvanized steel wire | V19: Alumimium | W19: Alumimium ALLOY | X19: Coper tape - 0.1 mm | Y19: Copper Tape - 0.03 mm | Z19: Copper Tape - 0.035 mm | AA19: Copper Tape - 0.04 mm | AB19: Copper Tape - 0.045 mm | AC19: Copper Tape - 0.050 mm | AD19: Copper Tape - 0.060 mm | AE19: Copper Tape - 0.075 mm(DOUBLE) | AF19: Extruded semiconductive | AG19: Extruded Semiconductive(Stripable) | AH19: HT-XLPE | AI19: LT-XLPE | AJ19: TR XLPE | AK19: Type A PVC | AL19: Type C PVC (HR) | AM19: Type A PVC-1.45 | AN19: Type A PVC-FR | AO19: Type A PVC-FRLS | AP19: Type A PVC-1.38 | AQ19: POLY TAPE | AR19: FR PVC Type ST-1 | AS19: FR PVC Type ST-2 | AT19: FRLSH PVC Type ST-1 | AU19: FRLSH PVC Type ST-2 | AV19: PVC Type ST-1 | AW19: PVC Type ST-1-PRESSURE EXTRUDED | AX19: PVC Type ST-2 | AY19: PVC COMPOUND 1.48 | AZ19: PVC Type ST-2-PRESSURE EXTRUDED | BA19: ACSR CORE WIRE | BB19: ACSR DOG STEEL WIRE | BC19: Aluminium Flat Strip | BD19: Aluminium Round Wire | BE19: Alumimium Tape | BF19: Double Steel Tape | BG19: Galvanised Steel Flat Strip | BH19: Galvanised Steel Flat Strip (Double) | BI19: Galvanised Steel Flat Strip-B | BJ19: Galvanised Steel Round Wire | BK19: Galvanised Steel Round Wire (Double) | BL19: FR PVC Type ST-1 | BM19: FR PVC Type ST-2 | BN19: FRLSH PVC Type ST-1 | BO19: FRLSH PVC Type ST-2 | BP19: ZHFR | BQ19: PE-ST-3 | BR19: PE-ST-7 | BS19: PVC Type ST-1 | BT19: PVC Type ST-2 | BU19: PVC COMPOUND 1.48 | BV19: PVC Type ST-2-PRESSURE EXTRUDED | BW19: UV & Track Resistant XLPE | BX19: FILLER | BY19: Grease | BZ19: Water swellable Tape | CA19: Semi conducting Water Swellable tape | CB19: SEMICON TAPE | CC19: GLASS FIBER TAPE | CD19: COPPER WIRE 0.8 MM | CE19: RUBBERIZED COTTON TAPE | CF19: Water Tight Compound | CG19: PROPOSE DRUM TYPE | CH19: DRUM CODE | CI19: DRUM SIZE (FxbXtx Ft) | CJ19: PARTY STANDARD LENGTH (MTR) | CO19: MFG% | CP19: MFG VALUE | CQ19: PROF% | CR19: PROFIT VALUE | CS19: 1ST EX-WORKS | CT19: Intt % | CU19: INTT VALUE | CV19: insp% | CW19: INSP VALUE | CX19: TTR Charges% | CY19: TTR Charges VALUE
N20: =+IFERROR(VLOOKUP($N$19,Sheet1!J:L,2,0),0) -> 0 | O20: 398 | P20: =+IFERROR(VLOOKUP($P$19,Sheet1!J:M,2,0),0) -> 0 | Q20: =+IFERROR(VLOOKUP($Q$19,Sheet1!J:M,2,0),0) -> 0 | R20: =+IFERROR(VLOOKUP($R$19,Sheet1!J:M,2,0),0) -> 0 | S20: =+IFERROR(VLOOKUP($S$19,Sheet1!J:M,2,0),0) -> 0 | T20: =+IFERROR(VLOOKUP($T$19,Sheet1!J:M,2,0),0) -> 0 | U20: =+IFERROR(VLOOKUP($U$19,Sheet1!J:M,2,0),0) -> 0 | V20: =+IFERROR(VLOOKUP($V$19,Sheet1!N:Q,2,0),0) -> 0 | W20: =+IFERROR(VLOOKUP($W$19,Sheet1!N:O,2,0),0) -> 0 | X20: =+IFERROR(VLOOKUP($X$19,Sheet1!F:I,2,0),0) -> 0 | Y20: =+IFERROR(VLOOKUP($Y$19,Sheet1!F:I,2,0),0) -> 0 | Z20: =+IFERROR(VLOOKUP($Z$19,Sheet1!F:I,2,0),0) -> 0 | AA20: =+IFERROR(VLOOKUP($AA$19,Sheet1!F:I,2,0),0) -> 0 | AB20: =+IFERROR(VLOOKUP($AB$19,Sheet1!F:I,2,0),0) -> 0 | AC20: =+IFERROR(VLOOKUP($AC$19,Sheet1!F:I,2,0),0) -> 0 | AD20: =+IFERROR(VLOOKUP($AD$19,Sheet1!F:I,2,0),0) -> 0 | AE20: =+IFERROR(VLOOKUP($AE$19,Sheet1!F:I,2,0),0) -> 0 | AF20: =+IFERROR(VLOOKUP($AF$19,Sheet1!R:U,2,0),0) -> 0 | AG20: =+IFERROR(VLOOKUP($AG$19,Sheet1!R:U,2,0),0) -> 0 | AH20: =+IFERROR(VLOOKUP($AH$19,Sheet1!V:Y,2,0),0) -> 0 | AI20: =+IFERROR(VLOOKUP($AI$19,Sheet1!V:Y,2,0),0) -> 0 | AJ20: =+IFERROR(VLOOKUP($AJ$19,Sheet1!V:Y,2,0),0) -> 0 | AK20: =+IFERROR(VLOOKUP($AK$19,Sheet1!V:Y,2,0),0) -> 0 | AL20: =+IFERROR(VLOOKUP($AL$19,Sheet1!V:Y,2,0),0) -> 0 | AM20: =+IFERROR(VLOOKUP($AM$19,Sheet1!V:Y,2,0),0) -> 0 | AN20: =+IFERROR(VLOOKUP($AN$19,Sheet1!V:Y,2,0),0) -> 0 | AO20: =+IFERROR(VLOOKUP($AO$19,Sheet1!V:Y,2,0),0) -> 0 | AP20: =+IFERROR(VLOOKUP($AP$19,Sheet1!V:Y,2,0),0) -> 0 | AQ20: =+IFERROR(VLOOKUP($AQ$19,Sheet1!Z2:AA840,2,0),0) -> 0 | AR20: =+IFERROR(VLOOKUP($AR$19,Sheet1!AD2:AG840,2,0),0) -> 0 | AS20: =+IFERROR(VLOOKUP($AS$19,Sheet1!AD2:AG840,2,0),0) -> 0 | AT20: =+IFERROR(VLOOKUP($AT$19,Sheet1!AD2:AG840,2,0),0) -> 0 | AU20: =+IFERROR(VLOOKUP($AU$19,Sheet1!AD2:AG840,2,0),0) -> 0 | AV20: =+IFERROR(VLOOKUP($AV$19,Sheet1!AD2:AG840,2,0),0) -> 0 | AW20: =+IFERROR(VLOOKUP($AW$19,Sheet1!AD2:AG840,2,0),0) -> 0 | AX20: =+IFERROR(VLOOKUP($AX$19,Sheet1!AD2:AG840,2,0),0) -> 0 | AY20: =+IFERROR(VLOOKUP($AY$19,Sheet1!AD2:AG840,2,0),0) -> 0 | AZ20: =+IFERROR(VLOOKUP($AZ$19,Sheet1!AD2:AG840,2,0),0) -> 0 | BA20: =+IFERROR(VLOOKUP($BA$19,Sheet1!AH2:AK840,2,0),0) -> 0 | BB20: =+IFERROR(VLOOKUP($BB$19,Sheet1!AH2:AK840,2,0),0) -> 0 | BC20: =+IFERROR(VLOOKUP($BC$19,Sheet1!AH2:AK840,2,0),0) -> 0 | BD20: =+IFERROR(VLOOKUP($BD$19,Sheet1!AH2:AK840,2,0),0) -> 0 | BE20: =+IFERROR(VLOOKUP($BE$19,Sheet1!AH2:AK840,2,0),0) -> 0 | BF20: =+IFERROR(VLOOKUP($BF$19,Sheet1!AH2:AK840,2,0),0) -> 0 | BG20: =+IFERROR(VLOOKUP($BG$19,Sheet1!AH2:AK840,2,0),0) -> 0 | BH20: =+IFERROR(VLOOKUP($BH$19,Sheet1!AH2:AK840,2,0),0) -> 0 | BI20: =+IFERROR(VLOOKUP($BI$19,Sheet1!AH2:AK840,2,0),0) -> 0 | BJ20: =+IFERROR(VLOOKUP($BJ$19,Sheet1!AH2:AK840,2,0),0) -> 0 | BK20: =+IFERROR(VLOOKUP($BK$19,Sheet1!AH2:AK840,2,0),0) -> 0 | BL20: =+IFERROR(VLOOKUP($BL$19,Sheet1!AL2:AO840,2,0),0) -> 0 | BM20: =+IFERROR(VLOOKUP($BM$19,Sheet1!AL2:AO840,2,0),0) -> 0 | BN20: =+IFERROR(VLOOKUP($BN$19,Sheet1!AL2:AO840,2,0),0) -> 0 | BO20: =+IFERROR(VLOOKUP($BO$19,Sheet1!AL2:AO840,2,0),0) -> 0 | BP20: =+IFERROR(VLOOKUP($BP$19,Sheet1!AL2:AO840,2,0),0) -> 0 | BQ20: =+IFERROR(VLOOKUP($BQ$19,Sheet1!AL2:AO840,2,0),0) -> 0 | BR20: =+IFERROR(VLOOKUP($BR$19,Sheet1!AL2:AO840,2,0),0) -> 0 | BS20: =+IFERROR(VLOOKUP($BS$19,Sheet1!AL2:AO840,2,0),0) -> 0 | BT20: =+IFERROR(VLOOKUP($BT$19,Sheet1!AL2:AO840,2,0),0) -> 0 | BU20: =+IFERROR(VLOOKUP($BU$19,Sheet1!AL2:AO840,2,0),0) -> 0 | BV20: =+IFERROR(VLOOKUP($BV$19,Sheet1!AL2:AO840,2,0),0) -> 0 | BW20: =+IFERROR(VLOOKUP($BW$19,Sheet1!AL2:AO840,2,0),0) -> 0 | BX20: =+IFERROR(VLOOKUP($BX$19,Sheet1!AP2:AS840,2,0),0) -> 0 | BY20: =+IFERROR(VLOOKUP($BY$19,Sheet1!AT2:AW840,2,0),0) -> 0 | BZ20: =+IFERROR(VLOOKUP($BZ$19,Sheet1!AX2:BA840,2,0),0) -> 0 | CA20: =+IFERROR(VLOOKUP($CA$19,Sheet1!BB2:BE840,2,0),0) -> 0 | CB20: =+IFERROR(VLOOKUP($CB$19,Sheet1!BF2:BI840,2,0),0) -> 0 | CC20: =+IFERROR(VLOOKUP($CC$19,Sheet1!BJ2:BM840,2,0),0) -> 0 | CD20: =+IFERROR(VLOOKUP($CD$19,Sheet1!BN2:BQ840,2,0),0) -> 0 | CE20: =+IFERROR(VLOOKUP($CE$19,Sheet1!BR2:BU840,2,0),0) -> 0 | CF20: =+IFERROR(VLOOKUP($CF$19,Sheet1!BV2:BY840,2,0),0) -> 0
A21: =Sheet1!A2 -> ENQ-19467-25-26 | B21: 46148 | C21: =Sheet1!C2 -> FC0700003 | D21: =Sheet1!D2 -> AAAC : RABBIT CONDUCTOR - 55 SQ. MM. (7/3.15) | E21: =CS21+CU21+CW21+CY21 -> 66614.2 | F21: =ROUNDUP(M26,0) -> 623 | G21: =E21+F21 -> 67237.2 | H21: =Sheet1!CR2 -> 0.18 | I21: =G21*H21 -> 12102.696 | J21: =G21+I21 -> 79339.896 | K21: =Sheet1!CU2 -> 900 | L21: =Sheet1!CV2 -> KMS | M21: =J21*K21 -> 71405906 | N21: =+IFERROR(VLOOKUP($N$19,Sheet1!J2:L2,3,0),0) -> 0 | O21: =+IFERROR(VLOOKUP($O$19,Sheet1!J2:L2,3,0),0) -> 150 | P21: =+IFERROR(VLOOKUP($P$19,Sheet1!J2:M2,3,0),0) -> 0 | Q21: =+IFERROR(VLOOKUP($Q$19,Sheet1!J2:M2,3,0),0) -> 0 | R21: =+IFERROR(VLOOKUP($R$19,Sheet1!J2:M2,3,0),0) -> 0 | S21: =+IFERROR(VLOOKUP($S$19,Sheet1!J2:M2,3,0),0) -> 0 | T21: =+IFERROR(VLOOKUP($T$19,Sheet1!J2:M2,3,0),0) -> 0 | U21: =+IFERROR(VLOOKUP($U$19,Sheet1!J2:M2,3,0),0) -> 0 | V21: =+IFERROR(VLOOKUP($V$19,Sheet1!N2:Q2,3,0),0) -> 0 | W21: =+IFERROR(VLOOKUP($W$19,Sheet1!N2:Q2,3,0),0) -> 0 | X21: =+IFERROR(VLOOKUP($X$19,Sheet1!F2:I2,3,0),0) -> 0 | Y21: =+IFERROR(VLOOKUP($Y$19,Sheet1!F2:I2,3,0),0) -> 0 | Z21: =+IFERROR(VLOOKUP($Z$19,Sheet1!F2:I2,3,0),0) -> 0 | AA21: =+IFERROR(VLOOKUP($AA$19,Sheet1!F2:I2,3,0),0) -> 0 | AB21: =+IFERROR(VLOOKUP($AB$19,Sheet1!F2:I2,3,0),0) -> 0 | AC21: =+IFERROR(VLOOKUP($AC$19,Sheet1!F2:I2,3,0),0) -> 0 | AD21: =+IFERROR(VLOOKUP($AD$19,Sheet1!F2:I2,3,0),0) -> 0 | AE21: =+IFERROR(VLOOKUP($AE$19,Sheet1!F2:I2,3,0),0) -> 0 | AF21: =+IFERROR(VLOOKUP($AF$19,Sheet1!R2:U2,3,0),0) -> 0 | AG21: =+IFERROR(VLOOKUP($AG$19,Sheet1!R2:U2,3,0),0) -> 0 | AH21: =+IFERROR(VLOOKUP($AH$19,Sheet1!V2:Y2,3,0),0) -> 0 | AI21: =+IFERROR(VLOOKUP($AI$19,Sheet1!V2:Y2,3,0),0) -> 0 | AJ21: =+IFERROR(VLOOKUP($AJ$19,Sheet1!V2:Y2,3,0),0) -> 0 | AK21: =+IFERROR(VLOOKUP($AK$19,Sheet1!V2:Y2,3,0),0) -> 0 | AL21: =+IFERROR(VLOOKUP($AL$19,Sheet1!V2:Y2,3,0),0) -> 0 | AM21: =+IFERROR(VLOOKUP($AM$19,Sheet1!V2:Y2,3,0),0) -> 0 | AN21: =+IFERROR(VLOOKUP($AN$19,Sheet1!V2:Y2,3,0),0) -> 0 | AO21: =+IFERROR(VLOOKUP($AO$19,Sheet1!V2:Y2,3,0),0) -> 0 | AP21: =+IFERROR(VLOOKUP($AP$19,Sheet1!V2:Y2,3,0),0) -> 0 | AQ21: =+IFERROR(VLOOKUP($AQ$19,Sheet1!Z2:AB2,3,0),0) -> 0 | AR21: =+IFERROR(VLOOKUP($AR$19,Sheet1!AD2:AG2,3,0),0) -> 0 | AS21: =+IFERROR(VLOOKUP($AS$19,Sheet1!AD2:AG2,3,0),0) -> 0 | AT21: =+IFERROR(VLOOKUP($AT$19,Sheet1!AD2:AG2,3,0),0) -> 0 | AU21: =+IFERROR(VLOOKUP($AU$19,Sheet1!AD2:AG2,3,0),0) -> 0 | AV21: =+IFERROR(VLOOKUP($AV$19,Sheet1!AD2:AG2,3,0),0) -> 0 | AW21: =+IFERROR(VLOOKUP($AW$19,Sheet1!AD2:AG2,3,0),0) -> 0 | AX21: =+IFERROR(VLOOKUP($AX$19,Sheet1!AD2:AG2,3,0),0) -> 0 | AY21: =+IFERROR(VLOOKUP($AY$19,Sheet1!AD2:AG2,3,0),0) -> 0 | AZ21: =+IFERROR(VLOOKUP($AZ$19,Sheet1!AD2:AG2,3,0),0) -> 0 | BA21: =+IFERROR(VLOOKUP($BA$19,Sheet1!AH2:AK2,3,0),0) -> 0 | BB21: =+IFERROR(VLOOKUP($BB$19,Sheet1!AH2:AK2,3,0),0) -> 0 | BC21: =+IFERROR(VLOOKUP($BC$19,Sheet1!AH2:AK2,3,0),0) -> 0 | BD21: =+IFERROR(VLOOKUP($BD$19,Sheet1!AH2:AK2,3,0),0) -> 0 | BE21: =+IFERROR(VLOOKUP($BE$19,Sheet1!AH2:AK2,3,0),0) -> 0 | BF21: =+IFERROR(VLOOKUP($BF$19,Sheet1!AH2:AK2,3,0),0) -> 0 | BG21: =+IFERROR(VLOOKUP($BG$19,Sheet1!AH2:AK2,3,0),0) -> 0 | BH21: =+IFERROR(VLOOKUP($BH$19,Sheet1!AH2:AK2,3,0),0) -> 0 | BI21: =+IFERROR(VLOOKUP($BI$19,Sheet1!AH2:AK2,3,0),0) -> 0 | BJ21: =+IFERROR(VLOOKUP($BJ$19,Sheet1!AH2:AK2,3,0),0) -> 0 | BK21: =+IFERROR(VLOOKUP($BK$19,Sheet1!AH2:AK2,3,0),0) -> 0 | BL21: =+IFERROR(VLOOKUP($BL$19,Sheet1!AL2:AO2,3,0),0) -> 0 | BM21: =+IFERROR(VLOOKUP($BM$19,Sheet1!AL2:AO2,3,0),0) -> 0 | BN21: =+IFERROR(VLOOKUP($BN$19,Sheet1!AL2:AO2,3,0),0) -> 0 | BO21: =+IFERROR(VLOOKUP($BO$19,Sheet1!AL2:AO2,3,0),0) -> 0 | BP21: =+IFERROR(VLOOKUP($BP$19,Sheet1!AL2:AO2,3,0),0) -> 0 | BQ21: =+IFERROR(VLOOKUP($BQ$19,Sheet1!AL2:AO2,3,0),0) -> 0 | BR21: =+IFERROR(VLOOKUP($BR$19,Sheet1!AL2:AO2,3,0),0) -> 0 | BS21: =+IFERROR(VLOOKUP($BS$19,Sheet1!AL2:AO2,3,0),0) -> 0 | BT21: =+IFERROR(VLOOKUP($BT$19,Sheet1!AL2:AO2,3,0),0) -> 0 | BU21: =+IFERROR(VLOOKUP($BU$19,Sheet1!AL2:AO2,3,0),0) -> 0 | BV21: =+IFERROR(VLOOKUP($BV$19,Sheet1!AL2:AO2,3,0),0) -> 0 | BW21: =+IFERROR(VLOOKUP($BW$19,Sheet1!AL2:AO2,3,0),0) -> 0 | BX21: =+IFERROR(VLOOKUP($BX$19,Sheet1!AP2:AS2,3,0),0) -> 0 | BY21: =+IFERROR(VLOOKUP($BY$19,Sheet1!AT2:AW2,3,0),0) -> 0 | BZ21: =+IFERROR(VLOOKUP($BZ$19,Sheet1!AX2:BA2,3,0),0) -> 0 | CA21: =+IFERROR(VLOOKUP($CA$19,Sheet1!BB2:BE2,3,0),0) -> 0 | CB21: =+IFERROR(VLOOKUP($CB$19,Sheet1!BF2:BI2,3,0),0) -> 0 | CC21: =+IFERROR(VLOOKUP($CC$19,Sheet1!BJ2:BM2,3,0),0) -> 0 | CD21: =+IFERROR(VLOOKUP($CD$19,Sheet1!BN2:BQ2,3,0),0) -> 0 | CE21: =+IFERROR(VLOOKUP($CE$19,Sheet1!BR2:BU2,3,0),0) -> 0 | CF21: =+IFERROR(VLOOKUP($CF$19,Sheet1!BV2:BY2,3,0),0) -> 0 | CG21: =Sheet1!E2 -> WOOD | CH21: MD0100013 | CI21: 1220 X 600 X 710 | CJ21: =Sheet1!CX2 -> 6000 | CK21: =Sheet1!BZ2 -> 739.5 | CL21: =SUMPRODUCT($N$20:$CF$20,N21:CF21)+CK21 -> 60439.5 | CM21: =Sheet1!CB2 -> 0 | CN21: =CL21*CM21 -> 0 | CO21: 0.064892097 | CP21: =CL21*CO21 -> 3922.0459 | CQ21: 0 | CR21: =CL21*CQ21 -> 0 | CS21: =CL21+CN21+CP21+CR21 -> 64361.546 | CT21: 0.02 | CU21: =CS21*CT21 -> 1287.2309 | CV21: 0.015 | CW21: =CS21*CV21 -> 965.42319 | CX21: =Sheet1!CM2 -> 0 | CY21: =CX21*CS21 -> 0
E25: Order Quantity | F25: Stnd Length | G25: Truck type | H25: Fare of one truck | I25: No of Drum in one truck | J25: Total length in one Truck | K25: No of Truck | L25: Total Freight | M25: Freight per KM | CG25: CONDUCTOR WEIGHT KG/KM | CH25: CONDUCTOR WEIGHT KG/KM | CI25: CONDUCTOR+DRUM WEIGHT | CJ25: TRUCK WEIGHT
E26: =K21 -> 900 | F26: =CJ21/1000 -> 6 | G26: 16 MT | H26: 56000 | I26: 15 | J26: =F26*I26 -> 90 | K26: =ROUNDUP((E26/J26),0) -> 10 | L26: =H26*K26 -> 560000 | M26: =L26/E26 -> 622.22222 | CG26: =O21 -> 150 | CH26: =125+25 -> 150 | CI26: =((CG26*F26)+CH26) -> 1050 | CJ26: =CI26*I26 -> 15750

Sheet NORMAL
A2: RAIL VIKAS NIGAM LIMITED
A4: TENDER SPECIFICATION NO () | B4: RVNL/B/E/RDSS/MPPK/Pkg-16/MAT/RE-SLT/CONDUCTORS
A5: TENDER DESCRIPTION () | B5: Manufacturing & Supply of Conductor AAAC Rabbit as per relevant IS and as per Specification of M.P. Poorv Kshetra V. V. Co. Ltd.
A6: Last Date & Time of Submission () | B6: 11-05-2026 upto 12:00:00 PM OPENING ON '11-05-2026 upto 12:30:00 PM
A7: REVERSE AUCTION | B7: Not Mention
A8: Price () | B8: The price is firm on F.O.R Destination Basis to the Supply at our Stores at Chhatarpur (Package-16). The prices include Freight, Incidental Charges, Tolls, Insurances, etc. in the account of Supplier. GST would be extra at actual as applicable at the time of dispatch on flat rate as governed by the concerned GST Rules. There shall be no price variation in the CONTRACT/ITEM and the rates shall be firm for a period of ONE Year from the date of Purchase Order.
A9: Validity () | B9: The bid must be valid up to 45 days from the date of opening of bids.
A10: Delivery Period () | B10: 10 days for Complete Order <Part/Lot delivery at Chhatarpur stores (PKG-16)
A11: Payment Terms () | B11: Advance : Payment of 20% advance of the Base Order Value (without GST) as provided manufacturing clearance, would be made on submission of Corporate Guarantee (Form-CG) After Delivery : After receipt of materials at F.O.R. Destination payment of 78% balance of the supplied material will be released after random sample testing/M.R.C. by DISCOM, within 15 (Fifteen) Working Days through RTGS/NEFT or suitable payment mode. On Acceptance : Balance payment of 2% will be released after/upon satisfactory acceptance of materials by concerned DISCOM.
A12: Standard length () | B12: The standard length of the conductors shall be 2000 meters. The conductor drum shall be adequate to wind one or more standard length of 2000 meters of SQUIRREL/WEASEL/RABIT/RACOON/DOG/PANTHER AAA conductor
A13: Packing () | B13: The conductor shall be supplied in non-returnable, strong, wooden drums provided with laggin of adequate strength, constructed to protect the conductor against any damage and displacement during transit, storage and subsequent handling and stringing operation in the field.
A14: Technical Specification
N18: Conductor | V18: AL ALLOY | X18: Insulation Screening (Metallic) | AF18: Insulation Screening (Non-Metallic) | AH18: Insulation | AQ18: POLY TAPE | AR18: Inner Sheath | BA18: Armouring | BL18: Outer Sheath | BX18: FILLER | BY18: GREASE | BZ18: Water swellable Tape | CA18: Semi conducting Water Swellable tape | CB18: SEMICON TAPE | CC18: GLASS FIBER TAPE | CD18: COPPER WIRE 0.8 MM | CE18: RUBBERIZED COTTON TAPE | CF18: Water Tight Compound | CG18: DRUM TYPE | CK18: DRUM COST PER KM | CL18: TOTAL RM COST | CM18: EXTRA CONSUMPTION | CN18: EXTRA CONSUMPTION VALUE | CZ18: $A$1
A19: DOCKET NO. | B19: BASE DATE | C19: ITEM CODE | D19: PROPOSE ERP ITEM NAME | E19: EX-WORKS (PER KM) | F19: FREIGHT PER KM | G19: PRICE INCLUDING FREIGHT (PER KM) | H19: GST % | I19: GST VALUE | J19: PRICE INCLUDING GST & FREIGHT (PER KM) | K19: QTY | L19: Unit | M19: TOTAL PRICE OF FULL QTY (INCLUDING FRIGHT & GST) | N19: Alumimium | O19: ALLOY WIRE ROD T4 (6201) (CG) | P19: Copper | Q19: AL-59 | R19: AL-4 | S19: AL-7 | T19: Flexible Copper | U19: Galvanized steel wire | V19: Alumimium | W19: Alumimium ALLOY | X19: Coper tape - 0.1 mm | Y19: Copper Tape - 0.03 mm | Z19: Copper Tape - 0.035 mm | AA19: Copper Tape - 0.04 mm | AB19: Copper Tape - 0.045 mm | AC19: Copper Tape - 0.050 mm | AD19: Copper Tape - 0.060 mm | AE19: Copper Tape - 0.075 mm(DOUBLE) | AF19: Extruded semiconductive | AG19: Extruded Semiconductive(Stripable) | AH19: HT-XLPE | AI19: LT-XLPE | AJ19: TR XLPE | AK19: Type A PVC | AL19: Type C PVC (HR) | AM19: Type A PVC-1.45 | AN19: Type A PVC-FR | AO19: Type A PVC-FRLS | AP19: Type A PVC-1.38 | AQ19: POLY TAPE | AR19: FR PVC Type ST-1 | AS19: FR PVC Type ST-2 | AT19: FRLSH PVC Type ST-1 | AU19: FRLSH PVC Type ST-2 | AV19: PVC Type ST-1 | AW19: PVC Type ST-1-PRESSURE EXTRUDED | AX19: PVC Type ST-2 | AY19: PVC COMPOUND 1.48 | AZ19: PVC Type ST-2-PRESSURE EXTRUDED | BA19: ACSR CORE WIRE | BB19: ACSR DOG STEEL WIRE | BC19: Aluminium Flat Strip | BD19: Aluminium Round Wire | BE19: Alumimium Tape | BF19: Double Steel Tape | BG19: Galvanised Steel Flat Strip | BH19: Galvanised Steel Flat Strip (Double) | BI19: Galvanised Steel Flat Strip-B | BJ19: Galvanised Steel Round Wire | BK19: Galvanised Steel Round Wire (Double) | BL19: FR PVC Type ST-1 | BM19: FR PVC Type ST-2 | BN19: FRLSH PVC Type ST-1 | BO19: FRLSH PVC Type ST-2 | BP19: ZHFR | BQ19: PE-ST-3 | BR19: PE-ST-7 | BS19: PVC Type ST-1 | BT19: PVC Type ST-2 | BU19: PVC COMPOUND 1.48 | BV19: PVC Type ST-2-PRESSURE EXTRUDED | BW19: UV & Track Resistant XLPE | BX19: FILLER | BY19: Grease | BZ19: Water swellable Tape | CA19: Semi conducting Water Swellable tape | CB19: SEMICON TAPE | CC19: GLASS FIBER TAPE | CD19: COPPER WIRE 0.8 MM | CE19: RUBBERIZED COTTON TAPE | CF19: Water Tight Compound | CG19: PROPOSE DRUM TYPE | CH19: DRUM CODE | CI19: DRUM SIZE (FxbXtx Ft) | CJ19: PARTY STANDARD LENGTH (MTR) | CO19: MFG% | CP19: MFG VALUE | CQ19: PROF% | CR19: PROFIT VALUE | CS19: 1ST EX-WORKS | CT19: Intt % | CU19: INTT VALUE | CV19: insp% | CW19: INSP VALUE | CX19: TTR Charges% | CY19: TTR Charges VALUE
N20: =+IFERROR(VLOOKUP($N$19,Sheet1!J:L,2,0),0) -> 0 | O20: 393 | P20: =+IFERROR(VLOOKUP($P$19,Sheet1!J:M,2,0),0) -> 0 | Q20: =+IFERROR(VLOOKUP($Q$19,Sheet1!J:M,2,0),0) -> 0 | R20: =+IFERROR(VLOOKUP($R$19,Sheet1!J:M,2,0),0) -> 0 | S20: =+IFERROR(VLOOKUP($S$19,Sheet1!J:M,2,0),0) -> 0 | T20: =+IFERROR(VLOOKUP($T$19,Sheet1!J:M,2,0),0) -> 0 | U20: =+IFERROR(VLOOKUP($U$19,Sheet1!J:M,2,0),0) -> 0 | V20: =+IFERROR(VLOOKUP($V$19,Sheet1!N:Q,2,0),0) -> 0 | W20: =+IFERROR(VLOOKUP($W$19,Sheet1!N:O,2,0),0) -> 0 | X20: =+IFERROR(VLOOKUP($X$19,Sheet1!F:I,2,0),0) -> 0 | Y20: =+IFERROR(VLOOKUP($Y$19,Sheet1!F:I,2,0),0) -> 0 | Z20: =+IFERROR(VLOOKUP($Z$19,Sheet1!F:I,2,0),0) -> 0 | AA20: =+IFERROR(VLOOKUP($AA$19,Sheet1!F:I,2,0),0) -> 0 | AB20: =+IFERROR(VLOOKUP($AB$19,Sheet1!F:I,2,0),0) -> 0 | AC20: =+IFERROR(VLOOKUP($AC$19,Sheet1!F:I,2,0),0) -> 0 | AD20: =+IFERROR(VLOOKUP($AD$19,Sheet1!F:I,2,0),0) -> 0 | AE20: =+IFERROR(VLOOKUP($AE$19,Sheet1!F:I,2,0),0) -> 0 | AF20: =+IFERROR(VLOOKUP($AF$19,Sheet1!R:U,2,0),0) -> 0 | AG20: =+IFERROR(VLOOKUP($AG$19,Sheet1!R:U,2,0),0) -> 0 | AH20: =+IFERROR(VLOOKUP($AH$19,Sheet1!V:Y,2,0),0) -> 0 | AI20: =+IFERROR(VLOOKUP($AI$19,Sheet1!V:Y,2,0),0) -> 0 | AJ20: =+IFERROR(VLOOKUP($AJ$19,Sheet1!V:Y,2,0),0) -> 0 | AK20: =+IFERROR(VLOOKUP($AK$19,Sheet1!V:Y,2,0),0) -> 0 | AL20: =+IFERROR(VLOOKUP($AL$19,Sheet1!V:Y,2,0),0) -> 0 | AM20: =+IFERROR(VLOOKUP($AM$19,Sheet1!V:Y,2,0),0) -> 0 | AN20: =+IFERROR(VLOOKUP($AN$19,Sheet1!V:Y,2,0),0) -> 0 | AO20: =+IFERROR(VLOOKUP($AO$19,Sheet1!V:Y,2,0),0) -> 0 | AP20: =+IFERROR(VLOOKUP($AP$19,Sheet1!V:Y,2,0),0) -> 0 | AQ20: =+IFERROR(VLOOKUP($AQ$19,Sheet1!Z2:AA840,2,0),0) -> 0 | AR20: =+IFERROR(VLOOKUP($AR$19,Sheet1!AD2:AG840,2,0),0) -> 0 | AS20: =+IFERROR(VLOOKUP($AS$19,Sheet1!AD2:AG840,2,0),0) -> 0 | AT20: =+IFERROR(VLOOKUP($AT$19,Sheet1!AD2:AG840,2,0),0) -> 0 | AU20: =+IFERROR(VLOOKUP($AU$19,Sheet1!AD2:AG840,2,0),0) -> 0 | AV20: =+IFERROR(VLOOKUP($AV$19,Sheet1!AD2:AG840,2,0),0) -> 0 | AW20: =+IFERROR(VLOOKUP($AW$19,Sheet1!AD2:AG840,2,0),0) -> 0 | AX20: =+IFERROR(VLOOKUP($AX$19,Sheet1!AD2:AG840,2,0),0) -> 0 | AY20: =+IFERROR(VLOOKUP($AY$19,Sheet1!AD2:AG840,2,0),0) -> 0 | AZ20: =+IFERROR(VLOOKUP($AZ$19,Sheet1!AD2:AG840,2,0),0) -> 0 | BA20: =+IFERROR(VLOOKUP($BA$19,Sheet1!AH2:AK840,2,0),0) -> 0 | BB20: =+IFERROR(VLOOKUP($BB$19,Sheet1!AH2:AK840,2,0),0) -> 0 | BC20: =+IFERROR(VLOOKUP($BC$19,Sheet1!AH2:AK840,2,0),0) -> 0 | BD20: =+IFERROR(VLOOKUP($BD$19,Sheet1!AH2:AK840,2,0),0) -> 0 | BE20: =+IFERROR(VLOOKUP($BE$19,Sheet1!AH2:AK840,2,0),0) -> 0 | BF20: =+IFERROR(VLOOKUP($BF$19,Sheet1!AH2:AK840,2,0),0) -> 0 | BG20: =+IFERROR(VLOOKUP($BG$19,Sheet1!AH2:AK840,2,0),0) -> 0 | BH20: =+IFERROR(VLOOKUP($BH$19,Sheet1!AH2:AK840,2,0),0) -> 0 | BI20: =+IFERROR(VLOOKUP($BI$19,Sheet1!AH2:AK840,2,0),0) -> 0 | BJ20: =+IFERROR(VLOOKUP($BJ$19,Sheet1!AH2:AK840,2,0),0) -> 0 | BK20: =+IFERROR(VLOOKUP($BK$19,Sheet1!AH2:AK840,2,0),0) -> 0 | BL20: =+IFERROR(VLOOKUP($BL$19,Sheet1!AL2:AO840,2,0),0) -> 0 | BM20: =+IFERROR(VLOOKUP($BM$19,Sheet1!AL2:AO840,2,0),0) -> 0 | BN20: =+IFERROR(VLOOKUP($BN$19,Sheet1!AL2:AO840,2,0),0) -> 0 | BO20: =+IFERROR(VLOOKUP($BO$19,Sheet1!AL2:AO840,2,0),0) -> 0 | BP20: =+IFERROR(VLOOKUP($BP$19,Sheet1!AL2:AO840,2,0),0) -> 0 | BQ20: =+IFERROR(VLOOKUP($BQ$19,Sheet1!AL2:AO840,2,0),0) -> 0 | BR20: =+IFERROR(VLOOKUP($BR$19,Sheet1!AL2:AO840,2,0),0) -> 0 | BS20: =+IFERROR(VLOOKUP($BS$19,Sheet1!AL2:AO840,2,0),0) -> 0 | BT20: =+IFERROR(VLOOKUP($BT$19,Sheet1!AL2:AO840,2,0),0) -> 0 | BU20: =+IFERROR(VLOOKUP($BU$19,Sheet1!AL2:AO840,2,0),0) -> 0 | BV20: =+IFERROR(VLOOKUP($BV$19,Sheet1!AL2:AO840,2,0),0) -> 0 | BW20: =+IFERROR(VLOOKUP($BW$19,Sheet1!AL2:AO840,2,0),0) -> 0 | BX20: =+IFERROR(VLOOKUP($BX$19,Sheet1!AP2:AS840,2,0),0) -> 0 | BY20: =+IFERROR(VLOOKUP($BY$19,Sheet1!AT2:AW840,2,0),0) -> 0 | BZ20: =+IFERROR(VLOOKUP($BZ$19,Sheet1!AX2:BA840,2,0),0) -> 0 | CA20: =+IFERROR(VLOOKUP($CA$19,Sheet1!BB2:BE840,2,0),0) -> 0 | CB20: =+IFERROR(VLOOKUP($CB$19,Sheet1!BF2:BI840,2,0),0) -> 0 | CC20: =+IFERROR(VLOOKUP($CC$19,Sheet1!BJ2:BM840,2,0),0) -> 0 | CD20: =+IFERROR(VLOOKUP($CD$19,Sheet1!BN2:BQ840,2,0),0) -> 0 | CE20: =+IFERROR(VLOOKUP($CE$19,Sheet1!BR2:BU840,2,0),0) -> 0 | CF20: =+IFERROR(VLOOKUP($CF$19,Sheet1!BV2:BY840,2,0),0) -> 0
A21: =Sheet1!A2 -> ENQ-19467-25-26 | B21: 46148 | C21: =Sheet1!C2 -> FC0700003 | D21: =Sheet1!D2 -> AAAC : RABBIT CONDUCTOR - 55 SQ. MM. (7/3.15) | E21: =CS21+CU21+CW21+CY21 -> 66614.204 | F21: =ROUNDUP(M26,0) -> 623 | G21: =E21+F21 -> 67237.204 | H21: =Sheet1!CR2 -> 0.18 | I21: =G21*H21 -> 12102.697 | J21: =G21+I21 -> 79339.901 | K21: =Sheet1!CU2 -> 900 | L21: =Sheet1!CV2 -> KMS | M21: =J21*K21 -> 71405911 | N21: =+IFERROR(VLOOKUP($N$19,Sheet1!J2:L2,3,0),0) -> 0 | O21: 147 | P21: =+IFERROR(VLOOKUP($P$19,Sheet1!J2:M2,3,0),0) -> 0 | Q21: =+IFERROR(VLOOKUP($Q$19,Sheet1!J2:M2,3,0),0) -> 0 | R21: =+IFERROR(VLOOKUP($R$19,Sheet1!J2:M2,3,0),0) -> 0 | S21: =+IFERROR(VLOOKUP($S$19,Sheet1!J2:M2,3,0),0) -> 0 | T21: =+IFERROR(VLOOKUP($T$19,Sheet1!J2:M2,3,0),0) -> 0 | U21: =+IFERROR(VLOOKUP($U$19,Sheet1!J2:M2,3,0),0) -> 0 | V21: =+IFERROR(VLOOKUP($V$19,Sheet1!N2:Q2,3,0),0) -> 0 | W21: =+IFERROR(VLOOKUP($W$19,Sheet1!N2:Q2,3,0),0) -> 0 | X21: =+IFERROR(VLOOKUP($X$19,Sheet1!F2:I2,3,0),0) -> 0 | Y21: =+IFERROR(VLOOKUP($Y$19,Sheet1!F2:I2,3,0),0) -> 0 | Z21: =+IFERROR(VLOOKUP($Z$19,Sheet1!F2:I2,3,0),0) -> 0 | AA21: =+IFERROR(VLOOKUP($AA$19,Sheet1!F2:I2,3,0),0) -> 0 | AB21: =+IFERROR(VLOOKUP($AB$19,Sheet1!F2:I2,3,0),0) -> 0 | AC21: =+IFERROR(VLOOKUP($AC$19,Sheet1!F2:I2,3,0),0) -> 0 | AD21: =+IFERROR(VLOOKUP($AD$19,Sheet1!F2:I2,3,0),0) -> 0 | AE21: =+IFERROR(VLOOKUP($AE$19,Sheet1!F2:I2,3,0),0) -> 0 | AF21: =+IFERROR(VLOOKUP($AF$19,Sheet1!R2:U2,3,0),0) -> 0 | AG21: =+IFERROR(VLOOKUP($AG$19,Sheet1!R2:U2,3,0),0) -> 0 | AH21: =+IFERROR(VLOOKUP($AH$19,Sheet1!V2:Y2,3,0),0) -> 0 | AI21: =+IFERROR(VLOOKUP($AI$19,Sheet1!V2:Y2,3,0),0) -> 0 | AJ21: =+IFERROR(VLOOKUP($AJ$19,Sheet1!V2:Y2,3,0),0) -> 0 | AK21: =+IFERROR(VLOOKUP($AK$19,Sheet1!V2:Y2,3,0),0) -> 0 | AL21: =+IFERROR(VLOOKUP($AL$19,Sheet1!V2:Y2,3,0),0) -> 0 | AM21: =+IFERROR(VLOOKUP($AM$19,Sheet1!V2:Y2,3,0),0) -> 0 | AN21: =+IFERROR(VLOOKUP($AN$19,Sheet1!V2:Y2,3,0),0) -> 0 | AO21: =+IFERROR(VLOOKUP($AO$19,Sheet1!V2:Y2,3,0),0) -> 0 | AP21: =+IFERROR(VLOOKUP($AP$19,Sheet1!V2:Y2,3,0),0) -> 0 | AQ21: =+IFERROR(VLOOKUP($AQ$19,Sheet1!Z2:AB2,3,0),0) -> 0 | AR21: =+IFERROR(VLOOKUP($AR$19,Sheet1!AD2:AG2,3,0),0) -> 0 | AS21: =+IFERROR(VLOOKUP($AS$19,Sheet1!AD2:AG2,3,0),0) -> 0 | AT21: =+IFERROR(VLOOKUP($AT$19,Sheet1!AD2:AG2,3,0),0) -> 0 | AU21: =+IFERROR(VLOOKUP($AU$19,Sheet1!AD2:AG2,3,0),0) -> 0 | AV21: =+IFERROR(VLOOKUP($AV$19,Sheet1!AD2:AG2,3,0),0) -> 0 | AW21: =+IFERROR(VLOOKUP($AW$19,Sheet1!AD2:AG2,3,0),0) -> 0 | AX21: =+IFERROR(VLOOKUP($AX$19,Sheet1!AD2:AG2,3,0),0) -> 0 | AY21: =+IFERROR(VLOOKUP($AY$19,Sheet1!AD2:AG2,3,0),0) -> 0 | AZ21: =+IFERROR(VLOOKUP($AZ$19,Sheet1!AD2:AG2,3,0),0) -> 0 | BA21: =+IFERROR(VLOOKUP($BA$19,Sheet1!AH2:AK2,3,0),0) -> 0 | BB21: =+IFERROR(VLOOKUP($BB$19,Sheet1!AH2:AK2,3,0),0) -> 0 | BC21: =+IFERROR(VLOOKUP($BC$19,Sheet1!AH2:AK2,3,0),0) -> 0 | BD21: =+IFERROR(VLOOKUP($BD$19,Sheet1!AH2:AK2,3,0),0) -> 0 | BE21: =+IFERROR(VLOOKUP($BE$19,Sheet1!AH2:AK2,3,0),0) -> 0 | BF21: =+IFERROR(VLOOKUP($BF$19,Sheet1!AH2:AK2,3,0),0) -> 0 | BG21: =+IFERROR(VLOOKUP($BG$19,Sheet1!AH2:AK2,3,0),0) -> 0 | BH21: =+IFERROR(VLOOKUP($BH$19,Sheet1!AH2:AK2,3,0),0) -> 0 | BI21: =+IFERROR(VLOOKUP($BI$19,Sheet1!AH2:AK2,3,0),0) -> 0 | BJ21: =+IFERROR(VLOOKUP($BJ$19,Sheet1!AH2:AK2,3,0),0) -> 0 | BK21: =+IFERROR(VLOOKUP($BK$19,Sheet1!AH2:AK2,3,0),0) -> 0 | BL21: =+IFERROR(VLOOKUP($BL$19,Sheet1!AL2:AO2,3,0),0) -> 0 | BM21: =+IFERROR(VLOOKUP($BM$19,Sheet1!AL2:AO2,3,0),0) -> 0 | BN21: =+IFERROR(VLOOKUP($BN$19,Sheet1!AL2:AO2,3,0),0) -> 0 | BO21: =+IFERROR(VLOOKUP($BO$19,Sheet1!AL2:AO2,3,0),0) -> 0 | BP21: =+IFERROR(VLOOKUP($BP$19,Sheet1!AL2:AO2,3,0),0) -> 0 | BQ21: =+IFERROR(VLOOKUP($BQ$19,Sheet1!AL2:AO2,3,0),0) -> 0 | BR21: =+IFERROR(VLOOKUP($BR$19,Sheet1!AL2:AO2,3,0),0) -> 0 | BS21: =+IFERROR(VLOOKUP($BS$19,Sheet1!AL2:AO2,3,0),0) -> 0 | BT21: =+IFERROR(VLOOKUP($BT$19,Sheet1!AL2:AO2,3,0),0) -> 0 | BU21: =+IFERROR(VLOOKUP($BU$19,Sheet1!AL2:AO2,3,0),0) -> 0 | BV21: =+IFERROR(VLOOKUP($BV$19,Sheet1!AL2:AO2,3,0),0) -> 0 | BW21: =+IFERROR(VLOOKUP($BW$19,Sheet1!AL2:AO2,3,0),0) -> 0 | BX21: =+IFERROR(VLOOKUP($BX$19,Sheet1!AP2:AS2,3,0),0) -> 0 | BY21: =+IFERROR(VLOOKUP($BY$19,Sheet1!AT2:AW2,3,0),0) -> 0 | BZ21: =+IFERROR(VLOOKUP($BZ$19,Sheet1!AX2:BA2,3,0),0) -> 0 | CA21: =+IFERROR(VLOOKUP($CA$19,Sheet1!BB2:BE2,3,0),0) -> 0 | CB21: =+IFERROR(VLOOKUP($CB$19,Sheet1!BF2:BI2,3,0),0) -> 0 | CC21: =+IFERROR(VLOOKUP($CC$19,Sheet1!BJ2:BM2,3,0),0) -> 0 | CD21: =+IFERROR(VLOOKUP($CD$19,Sheet1!BN2:BQ2,3,0),0) -> 0 | CE21: =+IFERROR(VLOOKUP($CE$19,Sheet1!BR2:BU2,3,0),0) -> 0 | CF21: =+IFERROR(VLOOKUP($CF$19,Sheet1!BV2:BY2,3,0),0) -> 0 | CG21: =Sheet1!E2 -> WOOD | CH21: MD0100013 | CI21: 1220 X 600 X 710 | CJ21: =Sheet1!CX2 -> 6000 | CK21: =Sheet1!BZ2 -> 739.5 | CL21: =SUMPRODUCT($N$20:$CF$20,N21:CF21)+CK21 -> 58510.5 | CM21: =Sheet1!CB2 -> 0 | CN21: =CL21*CM21 -> 0 | CO21: 0.1 | CP21: =CL21*CO21 -> 5851.05 | CQ21: 0 | CR21: =CL21*CQ21 -> 0 | CS21: =CL21+CN21+CP21+CR21 -> 64361.55 | CT21: 0.02 | CU21: =CS21*CT21 -> 1287.231 | CV21: 0.015 | CW21: =CS21*CV21 -> 965.42325 | CX21: =Sheet1!CM2 -> 0 | CY21: =CX21*CS21 -> 0
M22: U1-C0002-193 | O22: RA0100016
E25: Order Quantity | F25: Stnd Length | G25: Truck type | H25: Fare of one truck | I25: No of Drum in one truck | J25: Total length in one Truck | K25: No of Truck | L25: Total Freight | M25: Freight per KM | CG25: CONDUCTOR WEIGHT KG/KM | CH25: CONDUCTOR WEIGHT KG/KM | CI25: CONDUCTOR+DRUM WEIGHT | CJ25: TRUCK WEIGHT
E26: =K21 -> 900 | F26: =CJ21/1000 -> 6 | G26: 16 MT | H26: 56000 | I26: 15 | J26: =F26*I26 -> 90 | K26: =ROUNDUP((E26/J26),0) -> 10 | L26: =H26*K26 -> 560000 | M26: =L26/E26 -> 622.22222 | CG26: =O21 -> 147 | CH26: =125+25 -> 150 | CI26: =((CG26*F26)+CH26) -> 1032 | CJ26: =CI26*I26 -> 15480

Sheet terms
A1: The quoted prices are on Firm inclusive of packing and forwading but exclusive of GST Statutory levies.
A2: The quoted prices are on VARIABLE basis with PV base Date: DD/MM/YYYY as per "IEEMA", inclusive of packing and forwading but exclusive of GST Statutory levies.
A4: The above prices are quoted on Ex-works basis, where freight will be charged extra.
A5: The above prices are quoted on FOR Destination basis, where freight is included, refer Price offer.
A6: The above prices are quoted on Ex-works+Freight basis.
A8: 20% Advance and Balance against PI (Proforma Invoice) prior to dispatch
A9: 100% against "90 days" LC, where 90 days usance interest will be borne by LPIPL
A10: 100% against "120 days" LC, where 120 days usance interest will be borne by LPIPL
A11: 100% against "45 days" LC, where 45 days usance interest will be borne by LPIPL
A12: 100% against "60 days" LC, where 60 days usance interest will be borne by LPIPL
A13: 100% against "30 days" LC, where 30 days usance interest will be borne by LPIPL
A14: 100% against 60 days PDC from the date of MRC/MRN
... A27: Negotiable
