Workbook

Sheet Sheet1
A1: DOCKET NO. | B1: Base Date | C1: ITEM CODE | D1: PROPOSE ERP ITEM NAME | E1: PROPOSE DRUM TYPE | F1: Insulation Screening (Metallic) | G1: RM RATE (Insulation Screening (Metallic)) | H1: Weight (Insulation Screening (Metallic)) | I1: COST(Insulation Screening (Metallic)) | J1: Conductor | K1: RM RATE(Conductor) | L1: WEIGHT(Conductor) | M1: COST(Conductor) | N1: AL ALLOY | O1: RM RATE(Alu Alloy) | P1: WEIGHT(Alu Alloy) | Q1: COST(Alu Alloy) | R1: Insulation Screening (Non-Metallic) | S1: RM RATE(Insulation Screening (Non-Metallic)) | T1: WEIGHT(Insulation Screening (Non-Metallic)) | U1: COST(Insulation Screening (Non-Metallic)) | V1: Insulation | W1: RM RATE(Insulation) | X1: WEIGHT(Insulation) | Y1: COST(Insulation) | Z1: POLY TAPE | AA1: RM RATE (Poly Tape) | AB1: WEIGHT (Poly Tape) | AC1: COST(Poly Tape) | AD1: Inner Sheath | AE1: RM RATE(Inner Sheath) | AF1: WEIGHT(Inner Sheath) | AG1: COST(Inner Sheath) | AH1: Armouring | AI1: RM RATE(Armouring) | AJ1: WEIGHT(Armouring) | AK1: COST(Armouring) | AL1: Outer Sheath | AM1: RM RATE(Outer Sheath) | AN1: WEIGHT(Outer Sheath) | AO1: COST(Outer Sheath) | AP1: FILLER | AQ1: RM RATE(Filler) | AR1: WEIGHT(Filler) | AS1: COST(Filler) | AT1: GREASE | AU1: RM RATE(Grease) | AV1: WEIGHT(Grease) | AW1: COST(Grease) | AX1: Water swellable Tape | AY1: RM RATE(Water swellable Tape) | AZ1: WEIGHT(Water swellable Tape) | BA1: COST(Water swellable Tape) | BB1: Semi conducting Water Swellable tape | BC1: RM RATE(Semi conducting Water Swellable tape) | BD1: WEIGHT(Semi conducting Water Swellable tape) | BE1: COST(Semi conducting Water Swellable tape) | BF1: SEMICON TAPE | BG1: RM RATE(SEMICON TAPE) | BH1: WEIGHT(SEMICON TAPE) | BI1: COST(SEMICON TAPE) | BJ1: GLASS FIBER TAPE | BK1: RM RATE(GLASS FIBER TAPE) | BL1: WEIGHT(GLASS FIBER TAPE) | BM1: COST(GLASS FIBER TAPE) | BN1: COPPER WIRE 0.8 MM | BO1: RM RATE(COPPER WIRE 0.8 MM) | BP1: WEIGHT(COPPER WIRE 0.8 MM) | BQ1: COST(COPPER WIRE 0.8 MM) | BR1: RUBBERIZED COTTON TAPE | BS1: RM RATE(RUBBERIZED COTTON TAPE) | BT1: WEIGHT(RUBBERIZED COTTON TAPE) | BU1: COST(RUBBERIZED COTTON TAPE) | BV1: Water Tight Compound | BW1: RM RATE(Water Tight Compound) | BX1: WEIGHT(Water Tight Compound) | BY1: COST(Water Tight Compound) | BZ1: DRUM COST PER KM | CA1: TOTAL RM COST | CB1: FIRM % | CC1: FIRM VALUE | CD1: MFG% | CE1: MFG VALUE | CF1: PROF% | CG1: PROFIT VALUE | CH1: 1ST EX-WORKS | CI1: Intt % | CJ1: INTT VALUE | CK1: insp% | CL1: INSP VALUE | CM1: EX-WORKS (PER KM) | CN1: FREIGHT PER KM | CO1: PRICE INCLUDING FREIGHT (PER KM) | CP1: GST % | CQ1: GST VALUE | CR1: PRICE INCLUDING GST & FREIGHT (PER KM) | CS1: QTY | CT1: Unit | CU1: TOTAL PRICE OF FULL QTY (INCLUDING FRIGHT & GST) | CV1: DRUM CODE | CW1: DRUM SIZE (FxbXtx Ft) | CX1: PARTY STANDARD LENGTH (MTR)
A2: ENQ-12172-22-23 | B2: 45315 | C2: FA1300022 | D2: 3 CORE X 50 SQ. MM. AL/ARD - WIRE (XLPE) - 33 KV (E) | E2: STEEL | F2: Copper Tape - 0.045 mm | G2: 860 | J2: Alumimium | K2: 215 | L2: 567 | M2: 121905 | P2: 0 | R2: Extruded Semiconductive | S2: 192 | T2: 250 | U2: 48000 | V2: HT-XLPE | W2: 150 | X2: 1545 | Y2: 231750 | AB2: 0 | AD2: PVC Type ST-2-PRESSURE EXTRUDED | AE2: 88 | AF2: 292 | AG2: 25696 | AH2: Galvanised Steel Round Wire | AI2: 82.3 | AJ2: 3818 | AK2: 314221.4 | AL2: FRLSH PVC Type ST-2 | AM2: 92 | AN2: 1125 | AO2: 103500 | AP2: Polypropylene Filler | AR2: 1300 | AV2: 0 | AX2: Water swellable Tape | AY2: 445 | AZ2: 0 | BA2: 0 | BB2: Semi conducting Water Swellable tape | BC2: 460 | BD2: 0 | BE2: 0 | BH2: 0 | BL2: 0 | BP2: 0 | BR2: RUBBERIZED COTTON TAPE | BS2: 450 | BT2: 0 | BU2: 0 | BX2: 0 | BZ2: 106400 | CA2: 951472.4 | CH2: 951472.4 | CM2: 951472.4 | CO2: 951472.4 | CR2: 951472.4 | CS2: 1 | CT2: KMS | CU2: 951472 | CV2: SP0400112 | CW2: CORRUGATED DISPATCH STEEL DRUM 2000 X 1000 X 1000 MM | CX2: 250
A3: ENQ-12172-22-23 | B3: 45315 | C3: FA1300079 | D3: 3 CORE X 185 SQ. MM AL/ARM - WIRE (XLPE) - 33 KV | E3: STEEL | F3: Copper Tape - 0.045 mm | G3: 860 | H3: 148.589 | I3: 127786.54 | J3: Alumimium | K3: 215 | L3: 1499 | M3: 322285 | P3: 0 | R3: Extruded Semiconductive | S3: 192 | T3: 326 | U3: 62592 | V3: HT-XLPE | W3: 150 | X3: 2040 | Y3: 306000 | AB3: 0 | AD3: PVC Type ST-2-PRESSURE EXTRUDED | AE3: 88 | AF3: 335 | AG3: 29480 | AH3: Galvanised Steel Round Wire | AI3: 82.3 | AJ3: 5745 | AK3: 472813.5 | AL3: FRLSH PVC Type ST-2 | AM3: 92 | AN3: 1411 | AO3: 129812 | AP3: Polypropylene Filler | AR3: 1838 | AV3: 0 | AX3: Water swellable Tape | AY3: 445 | AZ3: 0 | BA3: 0 | BB3: Semi conducting Water Swellable tape | BC3: 460 | BD3: 0 | BE3: 0 | BH3: 0 | BL3: 0 | BP3: 0 | BR3: RUBBERIZED COTTON TAPE | BS3: 450 | BT3: 0 | BU3: 0 | BX3: 0 | BZ3: 171000 | CA3: 1621769 | CH3: 1621769 | CM3: 1621769 | CO3: 1621769 | CR3: 1621769 | CS3: 1 | CT3: KMS | CU3: 1621769 | CV3: SP0400081 | CW3: CORRUGATED DISPATCH STEEL DRUM 2500 X 1400 X 1250 MM | CX3: 250
A4: ENQ-12172-22-23 | B4: 45315 | C4: FA1300120 | D4: 3 CORE X 70 SQ. MM. AL/ARM - WIRE (XLPE) - 33 KV | E4: STEEL | F4: Copper Tape - 0.045 mm | G4: 860 | H4: 123.303 | I4: 106040.58 | J4: Alumimium | K4: 215 | L4: 567 | M4: 121905 | P4: 0 | R4: Extruded Semiconductive | S4: 192 | T4: 245 | U4: 47040 | V4: HT-XLPE | W4: 150 | X4: 1561 | Y4: 234150 | AB4: 0 | AD4: PVC Type ST-2-PRESSURE EXTRUDED | AE4: 88 | AF4: 280 | AG4: 24640 | AH4: Galvanised Steel Round Wire | AI4: 82.3 | AJ4: 3818 | AK4: 314221.4 | AL4: FRLSH PVC Type ST-2 | AM4: 92 | AN4: 1124 | AO4: 103408 | AP4: Polypropylene Filler | AR4: 1267 | AV4: 0 | AX4: Water swellable Tape | AY4: 445 | AZ4: 0 | BA4: 0 | BB4: Semi conducting Water Swellable tape | BC4: 460 | BD4: 0 | BE4: 0 | BH4: 0 | BL4: 0 | BP4: 0 | BR4: RUBBERIZED COTTON TAPE | BS4: 450 | BT4: 0 | BU4: 0 | BX4: 0 | BZ4: 171000 | CA4: 1122405 | CH4: 1122405 | CM4: 1122405 | CO4: 1122405 | CR4: 1122405 | CS4: 1 | CT4: KMS | CU4: 1122405 | CV4: SP0400136 | CW4: CORRUGATED DISPATCH STEEL DRUM 2200 X 1300 X 1200 MM | CX4: 250
A5: ENQ-12172-22-23 | B5: 45315 | C5: FA1300201 | D5: 3 CORE X 240 SQ. MM. AL/ARM - WIRE (XLPE) - 33 KV | E5: STEEL | F5: Copper Tape - 0.045 mm | G5: 860 | H5: 157.709 | I5: 135629.74 | J5: Alumimium | K5: 215 | L5: 1944 | M5: 417960 | P5: 0 | R5: Extruded Semiconductive | S5: 192 | T5: 356 | U5: 68352 | V5: HT-XLPE | W5: 150 | X5: 2214 | Y5: 332100 | AB5: 0 | AD5: PVC Type ST-2-PRESSURE EXTRUDED | AE5: 88 | AF5: 355 | AG5: 31240 | AH5: Galvanised Steel Round Wire | AI5: 82.3 | AJ5: 6155 | AK5: 506556.5 | AL5: FRLSH PVC Type ST-2 | AM5: 92 | AN5: 1485 | AO5: 136620 | AP5: Polypropylene Filler | AR5: 2069 | AV5: 0 | AX5: Water swellable Tape | AY5: 445 | AZ5: 0 | BA5: 0 | BB5: Semi conducting Water Swellable tape | BC5: 460 | BD5: 0 | BE5: 0 | BH5: 0 | BL5: 0 | BP5: 0 | BR5: RUBBERIZED COTTON TAPE | BS5: 450 | BT5: 0 | BU5: 0 | BX5: 0 | CA5: 1628458.2 | CH5: 1628458.2 | CM5: 1628458.2 | CO5: 1628458.2 | CR5: 1628458.2 | CS5: 1 | CT5: KMS | CU5: 1628458 | CX5: 250
A6: ENQ-12172-22-23 | B6: 45315 | C6: FA1300297 | D6: 3 CORE X 35 SQ. MM. AL/ARM - WIRE (XLPE) - 33 KV (E) | E6: STEEL | F6: Copper Tape - 0.045 mm | G6: 860 | J6: Alumimium | K6: 215 | L6: 405 | M6: 87075 | P6: 0 | R6: Extruded Semiconductive | S6: 192 | T6: 228 | U6: 43776 | V6: HT-XLPE | W6: 150 | X6: 1422 | Y6: 213300 | AB6: 0 | AD6: PVC Type ST-2-PRESSURE EXTRUDED | AE6: 88 | AF6: 276 | AG6: 24288 | AH6: Galvanised Steel Round Wire | AI6: 82.3 | AJ6: 3626 | AK6: 298419.8 | AL6: FRLSH PVC Type ST-2 | AM6: 92 | AN6: 1038 | AO6: 95496 | AP6: Polypropylene Filler | AR6: 1160 | AV6: 0 | AX6: Water swellable Tape | AY6: 445 | AZ6: 0 | BA6: 0 | BB6: Semi conducting Water Swellable tape | BC6: 460 | BD6: 0 | BE6: 0 | BH6: 0 | BL6: 0 | BP6: 0 | BR6: RUBBERIZED COTTON TAPE | BS6: 450 | BT6: 0 | BU6: 0 | BX6: 0 | CA6: 762354.8 | CH6: 762354.8 | CM6: 762354.8 | CO6: 762354.8 | CR6: 762354.8 | CS6: 1 | CT6: KMS | CU6: 762355 | CX6: 250
A7: ENQ-12172-22-23 | B7: 45315 | C7: FA1300019 | D7: 1 CORE X 300 SQ. MM. AL/ARM (XLPE) - 33 KV | E7: STEEL | F7: Copper Tape - 0.045 mm | G7: 860 | H7: 54.919 | I7: 47230.34 | J7: Alumimium | K7: 215 | L7: 810 | M7: 174150 | P7: 0 | R7: Extruded Semiconductive | S7: 192 | T7: 128 | U7: 24576 | V7: HT-XLPE | W7: 150 | X7: 792 | Y7: 118800 | Z7: POLY TAPE | AA7: 119.6 | AB7: 0 | AC7: 0 | AD7: PVC Type ST-2 | AE7: 60.05 | AF7: 138 | AG7: 8286.9 | AH7: Aluminium Round Wire | AI7: 220 | AJ7: 648 | AK7: 142560 | AL7: FRLSH PVC Type ST-2 | AM7: 92 | AN7: 542 | AO7: 49864 | AR7: 0 | AV7: 0 | AX7: Water swellable Tape | AY7: 445 | AZ7: 0 | BA7: 0 | BB7: Semi conducting Water Swellable tape | BC7: 460 | BD7: 0 | BE7: 0 | BH7: 0 | BL7: 0 | BP7: 0 | BR7: RUBBERIZED COTTON TAPE | BS7: 450 | BT7: 0 | BU7: 0 | BX7: 0 | BZ7: 47500 | CA7: 612967.24 | CH7: 612967.24 | CM7: 612967.24 | CO7: 612967.24 | CR7: 612967.24 | CS7: 3 | CT7: KMS | CU7: 1838902 | CV7: SP0400110 | CW7: CORRUGATED DISPATCH STEEL DRUM 1600 X 900 X 1000 MM | CX7: 500
A8: ENQ-12172-22-23 | B8: 45315 | C8: FA1300200 | D8: 3 CORE X 95 SQ. MM. AL/ARM WIRE (XLPE) - 33 KV | E8: STEEL | F8: Copper Tape - 0.045 mm | G8: 860 | H8: 129.106 | I8: 111031.16 | J8: Alumimium | K8: 215 | L8: 770 | M8: 165550 | P8: 0 | R8: Extruded Semiconductive | S8: 192 | T8: 265 | U8: 50880 | V8: HT-XLPE | W8: 150 | X8: 1670 | Y8: 250500 | AB8: 0 | AD8: PVC Type ST-2-PRESSURE EXTRUDED | AE8: 88 | AF8: 292 | AG8: 25696 | AH8: Galvanised Steel Round Wire | AI8: 82.3 | AJ8: 3945 | AK8: 324673.5 | AL8: FRLSH PVC Type ST-2 | AM8: 92 | AN8: 1228 | AO8: 112976 | AP8: Polypropylene Filler | AR8: 1389 | AV8: 0 | AX8: Water swellable Tape | AY8: 445 | AZ8: 0 | BA8: 0 | BB8: Semi conducting Water Swellable tape | BC8: 460 | BD8: 0 | BE8: 0 | BH8: 0 | BL8: 0 | BP8: 0 | BR8: RUBBERIZED COTTON TAPE | BS8: 450 | BT8: 0 | BU8: 0 | BX8: 0 | BZ8: 147200 | CA8: 1188506.7 | CH8: 1188506.7 | CM8: 1188506.7 | CO8: 1188506.7 | CR8: 1188506.7 | CS8: 3 | CT8: KMS | CU8: 3565520 | CV8: SP0400136 | CW8: CORRUGATED DISPATCH STEEL DRUM 2200 X 1300 X 1200 MM | CX8: 250
A9: ENQ-12172-22-23 | B9: 45315 | C9: FA1300018 | D9: 1 CORE X 400 SQ. MM. AL/ARM (XLPE) - 33 KV | E9: STEEL | F9: Copper Tape - 0.045 mm | G9: 860 | H9: 59.755 | I9: 51389.3 | J9: Alumimium | K9: 215 | L9: 1080 | M9: 232200 | P9: 0 | R9: Extruded Semiconductive | S9: 192 | T9: 141 | U9: 27072 | V9: HT-XLPE | W9: 150 | X9: 870 | Y9: 130500 | Z9: POLY TAPE | AA9: 119.6 | AB9: 0 | AC9: 0 | AD9: PVC Type ST-2 | AE9: 60.05 | AF9: 147 | AG9: 8827.35 | AH9: Aluminium Round Wire | AI9: 220 | AJ9: 702 | AK9: 154440 | AL9: FRLSH PVC Type ST-2 | AM9: 92 | AN9: 575 | AO9: 52900 | AR9: 0 | AV9: 0 | AX9: Water swellable Tape | AY9: 445 | AZ9: 54 | BA9: 24030 | BB9: Semi conducting Water Swellable tape | BC9: 460 | BD9: 0 | BE9: 0 | BH9: 52 | BL9: 0 | BP9: 0 | BR9: RUBBERIZED COTTON TAPE | BS9: 450 | BT9: 0 | BU9: 0 | BX9: 0 | BZ9: 53200 | CA9: 734558.65 | CH9: 734558.65 | CM9: 734558.65 | CO9: 734558.65 | CR9: 734558.65 | CS9: 9.05 | CT9: KMS | CU9: 6647756 | CV9: SP0400112 | CW9: CORRUGATED DISPATCH STEEL DRUM 2000 X 1000 X 1000 MM | CX9: 500
A10: ENQ-12172-22-23 | B10: 45315 | C10: FA1300081 | D10: 3 CORE X 300 SQ. MM. AL/ARM - WIRE (XLPE) - 33 KV | E10: STEEL | F10: Copper Tape - 0.045 mm | G10: 860 | H10: 164.756 | I10: 141690.16 | J10: Alumimium | K10: 215 | L10: 2430 | M10: 522450 | P10: 0 | R10: Extruded Semiconductive | S10: 192 | T10: 386 | U10: 74112 | V10: HT-XLPE | W10: 150 | X10: 2385 | Y10: 357750 | AB10: 0 | AD10: PVC Type ST-2-PRESSURE EXTRUDED | AE10: 88 | AF10: 378 | AG10: 33264 | AH10: Galvanised Steel Round Wire | AI10: 82.3 | AJ10: 6463 | AK10: 531904.9 | AL10: FRLSH PVC Type ST-2 | AM10: 92 | AN10: 1558 | AO10: 143336 | AP10: Polypropylene Filler | AR10: 2315 | AV10: 0 | AX10: Water swellable Tape | AY10: 445 | AZ10: 0 | BA10: 0 | BB10: Semi conducting Water Swellable tape | BC10: 460 | BD10: 0 | BE10: 0 | BH10: 0 | BL10: 0 | BP10: 0 | BR10: RUBBERIZED COTTON TAPE | BS10: 450 | BT10: 0 | BU10: 0 | BX10: 0 | BZ10: 190000 | CA10: 1994507.1 | CH10: 1994507.1 | CM10: 1994507.1 | CO10: 1994507.1 | CR10: 1994507.1 | CS10: 16.92 | CT10: KMS | CU10: 33747059 | CV10: SP0400137 | CW10: CORRUGATED DISPATCH STEEL DRUM 2600 X 1600 X 1600 | CX10: 250
A11: ENQ-12172-22-23 | B11: 45315 | C11: FA1300080 | D11: 3 CORE X 400 SQ. MM AL/ARM - WIRE (XLPE) - 33 KV | E11: STEEL | F11: Copper Tape - 0.045 mm | G11: 860 | H11: 179.265 | I11: 154167.9 | J11: Alumimium | K11: 215 | L11: 3240 | M11: 696600 | P11: 0 | R11: Extruded Semiconductive | S11: 192 | T11: 427 | U11: 81984 | V11: HT-XLPE | W11: 150 | X11: 2621 | Y11: 393150 | AB11: 0 | AD11: PVC Type ST-2-PRESSURE EXTRUDED | AE11: 88 | AF11: 405 | AG11: 35640 | AH11: Galvanised Steel Round Wire | AI11: 82.3 | AJ11: 6975 | AK11: 574042.5 | AL11: FRLSH PVC Type ST-2 | AM11: 92 | AN11: 1660 | AO11: 152720 | AP11: Polypropylene Filler | AR11: 2672 | AV11: 0 | AX11: Water swellable Tape | AY11: 445 | AZ11: 120 | BA11: 53400 | BB11: Semi conducting Water Swellable tape | BC11: 460 | BD11: 0 | BE11: 0 | BH11: 144 | BL11: 0 | BP11: 0 | BR11: RUBBERIZED COTTON TAPE | BS11: 450 | BT11: 0 | BU11: 0 | BX11: 0 | BZ11: 190000 | CA11: 2331704.4 | CH11: 2331704.4 | CM11: 2331704.4 | CO11: 2331704.4 | CR11: 2331704.4 | CS11: 77 | CT11: KMS | CU11: 179541239 | CV11: SP0400137 | CW11: CORRUGATED DISPATCH STEEL DRUM 2600 X 1600 X 1600 MM | CX11: 250
A12: ENQ-12172-22-23 | B12: 45315 | C12: FA1300027 | D12: 1 CORE X 630 SQ. MM. AL/ARM (XLPE) - 33 KV | E12: STEEL | F12: Copper Tape - 0.045 mm | G12: 860 | H12: 68.737 | I12: 59113.82 | J12: Alumimium | K12: 215 | L12: 1701 | M12: 365715 | P12: 0 | R12: Extruded Semiconductive | S12: 192 | T12: 172 | U12: 33024 | V12: HT-XLPE | W12: 150 | X12: 1040 | Y12: 156000 | Z12: POLY TAPE | AA12: 119.6 | AB12: 0 | AC12: 0 | AD12: PVC Type ST-2 | AE12: 60.05 | AF12: 193 | AG12: 11589.65 | AH12: Aluminium Round Wire | AI12: 220 | AJ12: 800 | AK12: 176000 | AL12: FRLSH PVC Type ST-2 | AM12: 92 | AN12: 738 | AO12: 67896 | AR12: 0 | AV12: 0 | AX12: Water swellable Tape | AY12: 445 | AZ12: 0 | BA12: 0 | BB12: Semi conducting Water Swellable tape | BC12: 460 | BD12: 0 | BE12: 0 | BH12: 0 | BL12: 0 | BP12: 0 | BR12: RUBBERIZED COTTON TAPE | BS12: 450 | BT12: 0 | BU12: 0 | BX12: 0 | BZ12: 53200 | CA12: 922538.47 | CH12: 922538.47 | CM12: 922538.47 | CO12: 922538.47 | CR12: 922538.47 | CS12: 115 | CT12: KMS | CU12: 106091924 | CV12: SP0400123 | CW12: CORRUGATED DISPATCH STEEL DRUM 2000 X 1000 X 1200 MM | CX12: 500

Sheet AUTO CALCULATION SHEET (2)
A2: TPCODL TPNODL TPSODL TPWODL (TATA Power and Odisha Government Joint Venture)
A4: TENDER SPECIFICATION NO () | B4: TPCODL/CCG/23-24/1000000531
A5: TENDER DESCRIPTION () | B5: One Year Rate Contract for Supply of 33 kV HT Cable at TPCODL, TPNODL & TPSODL
A6: Last Date & Time of Submission () | B6: 06/Feb/2024 [17:00 Hrs.]
A7: REVERSE AUCTION | B7: CCG reserves the right to conduct the reverse auction for the products/ services being asked for in the tender. The terms and conditions for such reverse auction events shall be as per the Acceptance Form attached as Annexure VI of this document.
A8: Price () | B8: Price shall be fixed and firm during the contractual period.
A9: Validity () | B9: Bids shall remain valid for 180 days from the due date of submission of the bid. Notwithstanding clause above, CCG may solicit the Bidder’s consent to an extension of the Period of Bid Validity. The request and responses thereto shall be made in writing.
A10: Delivery Period () | B10: Delivery Period shall be 60 Days from date of receipt of release order / CAT-A issuance, whichever is later.
A11: Payment Terms () | B11: 100% payment within 60 days of submission of error-free Invoice complete in all respects. However, for MSME the payment cycle shall be 45 days.
A12: Standard length () | B12: Cable length on one drum shall be 250 meters max. +/- 5%. As per PO terms
A13: Packing () | B13: Steel drums shall be provided. Drum shall be free from sharp edges and visual defect. Stencil plate on one flange side of the drum and laminated paper sheet on other side flange of drum.
A14: Technical Specification
N16: =Sheet1!J1 -> Conductor | S16: AL ALLOY | U16: Insulation Screening (Metallic) | AC16: Insulation Screening (Non-Metallic) | AE16: Insulation | AK16: POLY TAPE | AL16: Inner Sheath | AS16: Armouring | BC16: Outer Sheath | BM16: FILLER | BN16: GREASE | BO16: Water swellable Tape | BP16: Semi conducting Water Swellable tape | BQ16: SEMICON TAPE | BR16: GLASS FIBER TAPE | BS16: COPPER WIRE 0.8 MM | BT16: RUBBERIZED COTTON TAPE | BU16: Water Tight Compound | CA16: DRUM COST PER KM | CB16: TOTAL RM COST | CC16: EXTRA CONSUMPTION | CD16: EXTRA CONSUMPTION VALUE
A17: DOCKET NO. | B17: =Sheet1!B1 -> Base Date | C17: ITEM CODE | D17: PROPOSE ERP ITEM NAME | E17: EX-WORKS (PER KM) | F17: FREIGHT PER KM | G17: PRICE INCLUDING FREIGHT (PER KM) | H17: GST % | I17: GST VALUE | J17: PRICE INCLUDING GST & FREIGHT (PER KM) | K17: QTY | L17: Unit | M17: TOTAL PRICE OF FULL QTY (INCLUDING FRIGHT & GST) | N17: Alumimium | O17: Alumimium ALLOY | P17: Copper | Q17: Flexible Copper | R17: Galvanized steel wire | S17: Alumimium | T17: Alumimium ALLOY | U17: Coper tape - 0.1 mm | V17: Copper Tape - 0.03 mm | W17: Copper Tape - 0.035 mm | X17: Copper Tape - 0.04 mm | Y17: Copper Tape - 0.045 mm | Z17: Copper Tape - 0.050 mm | AA17: Copper Tape - 0.060 mm | AB17: Copper Tape - 0.075 mm(DOUBLE) | AC17: Extruded semiconductive | AD17: Extruded Semiconductive(Stripable) | AE17: HT-XLPE | AF17: LT-XLPE | AG17: TR XLPE | AH17: Type A PVC | AI17: Type C PVC (HR) | AJ17: XLPE | AK17: POLY TAPE | AL17: FR PVC Type ST-1 | AM17: FR PVC Type ST-2 | AN17: FRLSH PVC Type ST-2 | AO17: PVC Type ST-1 | AP17: PVC Type ST-1-PRESSURE EXTRUDED | AQ17: PVC Type ST-2 | AR17: PVC Type ST-2-PRESSURE EXTRUDED | AS17: ACSR CORE WIRE | AT17: ACSR DOG STEEL WIRE | AU17: Aluminium Flat Strip | AV17: Aluminium Round Wire | AW17: Double Steel Tape | AX17: Galvanised Steel Flat Strip | AY17: Galvanised Steel Flat Strip (Double) | AZ17: Galvanised Steel Flat Strip-B | BA17: Galvanised Steel Round Wire | BB17: Galvanised Steel Round Wire (Double) | BC17: FR PVC Type ST-1 | BD17: FR PVC Type ST-2 | BE17: FRLSH PVC Type ST-1 | BF17: FRLSH PVC Type ST-2 | BG17: PE, ST-3 | BH17: PE, ST-7 | BI17: PVC Type ST-1 | BJ17: PVC Type ST-2 | BK17: PVC Type ST-2-PRESSURE EXTRUDED | BL17: UV & Track Resistant XLPE | BM17: PP FILLER | BN17: Grease | BO17: NCWBT | BP17: Semi conducting Water Swellable tape | BQ17: SEMICON TAPE | BR17: GLASS FIBER TAPE | BS17: COPPER WIRE 0.8 MM | BT17: RUBBERIZED COTTON TAPE | BU17: Water Tight Compound | BV17: =Sheet1!E1 -> PROPOSE DRUM TYPE | BX17: =Sheet1!CV1 -> DRUM CODE | BY17: =Sheet1!CW1 -> DRUM SIZE (FxbXtx Ft) | BZ17: =Sheet1!CX1 -> PARTY STANDARD LENGTH (MTR) | CE17: MFG% | CF17: MFG VALUE | CG17: PROF% | CH17: PROFIT VALUE | CI17: 1ST EX-WORKS | CJ17: Intt % | CK17: INTT VALUE | CL17: insp% | CM17: INSP VALUE
N18: 216 | O18: =+IFERROR(VLOOKUP($O$17,Sheet1!J:L,2,0),0) -> 0 | P18: =+IFERROR(VLOOKUP($P$17,Sheet1!J:M,2,0),0) -> 0 | Q18: =+IFERROR(VLOOKUP($Q$17,Sheet1!J:M,2,0),0) -> 0 | R18: =+IFERROR(VLOOKUP($R$17,Sheet1!J:M,2,0),0) -> 0 | S18: =+IFERROR(VLOOKUP($S$17,Sheet1!N:Q,2,0),0) -> 0 | T18: =+IFERROR(VLOOKUP($T$17,Sheet1!N:O,2,0),0) -> 0 | U18: =+IFERROR(VLOOKUP($U$17,Sheet1!F:I,2,0),0) -> 0 | V18: =+IFERROR(VLOOKUP($V$17,Sheet1!F:I,2,0),0) -> 0 | W18: =+IFERROR(VLOOKUP($W$17,Sheet1!F:I,2,0),0) -> 0 | X18: =+IFERROR(VLOOKUP($X$17,Sheet1!F:I,2,0),0) -> 0 | Y18: 859 | AC18: 199 | AE18: 145 | AK18: 120 | AQ18: 60 | AR18: 88 | AV18: 221 | BA18: 84 | BF18: 92 | BM18: 65 | BO18: 330 | BP18: 455 | BT18: 445 | BU18: =+IFERROR(VLOOKUP($BU$17,Sheet1!BV2:BY840,2,0),0) -> 0
A19: =Sheet1!A11 -> ENQ-12172-22-23 | B19: 45329 | C19: =Sheet1!C11 -> FA1300080 | D19: =Sheet1!D11 -> 3 CORE X 400 SQ. MM AL/ARM - WIRE (XLPE) - 33 KV | E19: =CI19+CK19+CM19 -> 3395017.3 | F19: =ROUNDUP(M32,0) -> 48312 | G19: =E19+F19 -> 3443329.3 | H19: 0.18 | I19: =G19*H19 -> 619799.27 | J19: =G19+I19 -> 4063128.5 | K19: =Sheet1!CS11 -> 77 | L19: =Sheet1!CT11 -> KMS | M19: =J19*K19 -> 3.128609e+08 | N19: 3243 | O19: =+IFERROR(VLOOKUP($O$17,Sheet1!J11:L11,3,0),0) -> 0 | P19: =+IFERROR(VLOOKUP($P$17,Sheet1!J11:M11,3,0),0) -> 0 | Q19: =+IFERROR(VLOOKUP($Q$17,Sheet1!J11:M11,3,0),0) -> 0 | R19: =+IFERROR(VLOOKUP($R$17,Sheet1!J11:M11,3,0),0) -> 0 | S19: =+IFERROR(VLOOKUP($S$17,Sheet1!N11:Q11,3,0),0) -> 0 | T19: =+IFERROR(VLOOKUP($T$17,Sheet1!N11:Q11,3,0),0) -> 0 | U19: =+IFERROR(VLOOKUP($U$17,Sheet1!F11:I11,3,0),0) -> 0 | V19: =+IFERROR(VLOOKUP($V$17,Sheet1!F11:I11,3,0),0) -> 0 | W19: =+IFERROR(VLOOKUP($W$17,Sheet1!F11:I11,3,0),0) -> 0 | X19: =+IFERROR(VLOOKUP($X$17,Sheet1!F11:I11,3,0),0) -> 0 | Y19: 212 | Z19: =+IFERROR(VLOOKUP($Z$17,Sheet1!F11:I11,3,0),0) -> 0 | AA19: =+IFERROR(VLOOKUP($AA$17,Sheet1!F11:I11,3,0),0) -> 0 | AB19: =+IFERROR(VLOOKUP($AB$17,Sheet1!F11:I11,3,0),0) -> 0 | AC19: 515 | AD19: =+IFERROR(VLOOKUP($AD$17,Sheet1!R11:U11,2,0),0) -> 0 | AE19: 2670 | AF19: =+IFERROR(VLOOKUP($AF$17,Sheet1!V11:Y11,3,0),0) -> 0 | AG19: =+IFERROR(VLOOKUP($AG$17,Sheet1!V11:Y11,3,0),0) -> 0 | AH19: =+IFERROR(VLOOKUP($AH$17,Sheet1!V11:Y11,3,0),0) -> 0 | AI19: =+IFERROR(VLOOKUP($AI$17,Sheet1!V11:Y11,3,0),0) -> 0 | AJ19: =+IFERROR(VLOOKUP($AJ$17,Sheet1!V11:Y11,3,0),0) -> 0 | AK19: =+IFERROR(VLOOKUP($AK$17,Sheet1!Z11:AB11,3,0),0) -> 0 | AL19: =+IFERROR(VLOOKUP($AL$17,Sheet1!AD11:AG11,3,0),0) -> 0 | AM19: =+IFERROR(VLOOKUP($AM$17,Sheet1!AD11:AG11,3,0),0) -> 0 | AN19: =+IFERROR(VLOOKUP($AN$17,Sheet1!AD11:AG11,3,0),0) -> 0 | AO19: =+IFERROR(VLOOKUP($AO$17,Sheet1!AD11:AG11,3,0),0) -> 0 | AP19: =+IFERROR(VLOOKUP($AP$17,Sheet1!AD11:AG11,3,0),0) -> 0 | AQ19: =+IFERROR(VLOOKUP($AQ$17,Sheet1!AD11:AG11,3,0),0) -> 0 | AR19: 1561 | AS19: =+IFERROR(VLOOKUP($AS$17,Sheet1!AH11:AK11,3,0),0) -> 0 | AT19: =+IFERROR(VLOOKUP($AT$17,Sheet1!AH11:AK11,3,0),0) -> 0 | AU19: =+IFERROR(VLOOKUP($AU$17,Sheet1!AH11:AK11,3,0),0) -> 0 | AV19: =+IFERROR(VLOOKUP($AV$17,Sheet1!AH11:AK11,3,0),0) -> 0 | AW19: =+IFERROR(VLOOKUP($AW$17,Sheet1!AH11:AK11,3,0),0) -> 0 | AX19: =+IFERROR(VLOOKUP($AX$17,Sheet1!AH11:AK11,3,0),0) -> 0 | AY19: =+IFERROR(VLOOKUP($AY$17,Sheet1!AH11:AK11,3,0),0) -> 0 | AZ19: =+IFERROR(VLOOKUP($AZ$17,Sheet1!AH11:AK11,3,0),0) -> 0 | BA19: 7182 | BB19: =+IFERROR(VLOOKUP($BB$17,Sheet1!AH11:AK11,3,0),0) -> 0 | BC19: =+IFERROR(VLOOKUP($BC$17,Sheet1!AL11:AO11,3,0),0) -> 0 | BD19: =+IFERROR(VLOOKUP($BD$17,Sheet1!AL11:AO11,3,0),0) -> 0 | BE19: =+IFERROR(VLOOKUP($BE$17,Sheet1!AL11:AO11,3,0),0) -> 0 | BF19: 1715 | BG19: =+IFERROR(VLOOKUP($BG$17,Sheet1!AL11:AO11,3,0),0) -> 0 | BH19: =+IFERROR(VLOOKUP($BH$17,Sheet1!AL11:AO11,3,0),0) -> 0 | BI19: =+IFERROR(VLOOKUP($BI$17,Sheet1!AL11:AO11,3,0),0) -> 0 | BJ19: =+IFERROR(VLOOKUP($BJ$17,Sheet1!AL11:AO11,3,0),0) -> 0 | BK19: =+IFERROR(VLOOKUP($BK$17,Sheet1!AL11:AO11,3,0),0) -> 0 | BL19: =+IFERROR(VLOOKUP($BL$17,Sheet1!AL11:AO11,3,0),0) -> 0 | BM19: 1718 | BN19: =+IFERROR(VLOOKUP($BN$17,Sheet1!AT11:AW11,3,0),0) -> 0 | BO19: 58 | BP19: 104 | BQ19: =+IFERROR(VLOOKUP($BQ$17,Sheet1!BF11:BI11,3,0),0) -> 0 | BR19: =+IFERROR(VLOOKUP($BR$17,Sheet1!BJ11:BM11,3,0),0) -> 0 | BS19: =+IFERROR(VLOOKUP($BS$17,Sheet1!BN11:BQ11,3,0),0) -> 0 | BT19: 75 | BU19: =+IFERROR(VLOOKUP($BU$17,Sheet1!BV11:BY11,3,0),0) -> 0 | BV19: =Sheet1!E11 -> STEEL | BW19: =SUM(N19:BT19) -> 19053 | BX19: SP0400137 | BY19: CORRUGATED DISPATCH STEEL DRUM 2600 X 1600 X 1600 | BZ19: =Sheet1!CX11 -> 250 | CA19: 176000 | CB19: =SUMPRODUCT($N$18:$BU$18,N19:BU19)+CA19 -> 2658172 | CC19: =Sheet1!CB11 -> 0 | CD19: =CB19*CC19 -> 0 | CE19: 0.24 | CF19: =CB19*CE19 -> 637961.28 | CG19: 0 | CH19: =CB19*CG19 -> 0 | CI19: =CB19+CD19+CF19+CH19 -> 3296133.3 | CJ19: 0.02 | CK19: =CI19*CJ19 -> 65922.666 | CL19: 0.01 | CM19: =CI19*CL19 -> 32961.333
A20: =Sheet1!A10 -> ENQ-12172-22-23 | B20: 45329 | C20: =Sheet1!C10 -> FA1300081 | D20: =Sheet1!D10 -> 3 CORE X 300 SQ. MM. AL/ARM - WIRE (XLPE) - 33 KV | E20: =CI20+CK20+CM20 -> 2957970.9 | F20: =ROUNDUP(M33,0) -> 49646 | G20: =E20+F20 -> 3007616.9 | H20: 0.18 | I20: =G20*H20 -> 541371.05 | J20: =G20+I20 -> 3548988 | K20: =Sheet1!CS10 -> 16.92 | L20: =Sheet1!CT10 -> KMS | M20: =J20*K20 -> 60048877 | N20: =+IFERROR(VLOOKUP($N$17,Sheet1!J10:L10,3,0),0) -> 2430 | O20: =+IFERROR(VLOOKUP($O$17,Sheet1!J10:L10,3,0),0) -> 0 | P20: =+IFERROR(VLOOKUP($P$17,Sheet1!J10:M10,3,0),0) -> 0 | Q20: =+IFERROR(VLOOKUP($Q$17,Sheet1!J10:M10,3,0),0) -> 0 | R20: =+IFERROR(VLOOKUP($R$17,Sheet1!J10:M10,3,0),0) -> 0 | S20: =+IFERROR(VLOOKUP($S$17,Sheet1!N10:Q10,3,0),0) -> 0 | T20: =+IFERROR(VLOOKUP($T$17,Sheet1!N10:Q10,3,0),0) -> 0 | U20: =+IFERROR(VLOOKUP($U$17,Sheet1!F10:I10,3,0),0) -> 0 | V20: =+IFERROR(VLOOKUP($V$17,Sheet1!F10:I10,3,0),0) -> 0 | W20: =+IFERROR(VLOOKUP($W$17,Sheet1!F10:I10,3,0),0) -> 0 | X20: =+IFERROR(VLOOKUP($X$17,Sheet1!F10:I10,3,0),0) -> 0 | Y20: 193 | Z20: =+IFERROR(VLOOKUP($Z$17,Sheet1!F10:I10,3,0),0) -> 0 | AA20: =+IFERROR(VLOOKUP($AA$17,Sheet1!F10:I10,3,0),0) -> 0 | AB20: =+IFERROR(VLOOKUP($AB$17,Sheet1!F10:I10,3,0),0) -> 0 | AC20: 495 | AD20: =+IFERROR(VLOOKUP($AD$17,Sheet1!R10:U10,2,0),0) -> 0 | AE20: 2434 | AF20: =+IFERROR(VLOOKUP($AF$17,Sheet1!V10:Y10,3,0),0) -> 0 | AG20: =+IFERROR(VLOOKUP($AG$17,Sheet1!V10:Y10,3,0),0) -> 0 | AH20: =+IFERROR(VLOOKUP($AH$17,Sheet1!V10:Y10,3,0),0) -> 0 | AI20: =+IFERROR(VLOOKUP($AI$17,Sheet1!V10:Y10,3,0),0) -> 0 | AJ20: =+IFERROR(VLOOKUP($AJ$17,Sheet1!V10:Y10,3,0),0) -> 0 | AK20: =+IFERROR(VLOOKUP($AK$17,Sheet1!Z10:AB10,3,0),0) -> 0 | AL20: =+IFERROR(VLOOKUP($AL$17,Sheet1!AD10:AG10,3,0),0) -> 0 | AM20: =+IFERROR(VLOOKUP($AM$17,Sheet1!AD10:AG10,3,0),0) -> 0 | AN20: =+IFERROR(VLOOKUP($AN$17,Sheet1!AD10:AG10,3,0),0) -> 0 | AO20: =+IFERROR(VLOOKUP($AO$17,Sheet1!AD10:AG10,3,0),0) -> 0 | AP20: =+IFERROR(VLOOKUP($AP$17,Sheet1!AD10:AG10,3,0),0) -> 0 | AQ20: =+IFERROR(VLOOKUP($AQ$17,Sheet1!AD10:AG10,3,0),0) -> 0 | AR20: 1382 | AS20: =+IFERROR(VLOOKUP($AS$17,Sheet1!AH10:AK10,3,0),0) -> 0 | AT20: =+IFERROR(VLOOKUP($AT$17,Sheet1!AH10:AK10,3,0),0) -> 0 | AU20: =+IFERROR(VLOOKUP($AU$17,Sheet1!AH10:AK10,3,0),0) -> 0 | AV20: =+IFERROR(VLOOKUP($AV$17,Sheet1!AH10:AK10,3,0),0) -> 0 | AW20: =+IFERROR(VLOOKUP($AW$17,Sheet1!AH10:AK10,3,0),0) -> 0 | AX20: =+IFERROR(VLOOKUP($AX$17,Sheet1!AH10:AK10,3,0),0) -> 0 | AY20: =+IFERROR(VLOOKUP($AY$17,Sheet1!AH10:AK10,3,0),0) -> 0 | AZ20: =+IFERROR(VLOOKUP($AZ$17,Sheet1!AH10:AK10,3,0),0) -> 0 | BA20: 6668 | BB20: =+IFERROR(VLOOKUP($BB$17,Sheet1!AH10:AK10,3,0),0) -> 0 | BC20: =+IFERROR(VLOOKUP($BC$17,Sheet1!AL10:AO10,3,0),0) -> 0 | BD20: =+IFERROR(VLOOKUP($BD$17,Sheet1!AL10:AO10,3,0),0) -> 0 | BE20: =+IFERROR(VLOOKUP($BE$17,Sheet1!AL10:AO10,3,0),0) -> 0 | BF20: 1613 | BG20: =+IFERROR(VLOOKUP($BG$17,Sheet1!AL10:AO10,3,0),0) -> 0 | BH20: =+IFERROR(VLOOKUP($BH$17,Sheet1!AL10:AO10,3,0),0) -> 0 | BI20: =+IFERROR(VLOOKUP($BI$17,Sheet1!AL10:AO10,3,0),0) -> 0 | BJ20: =+IFERROR(VLOOKUP($BJ$17,Sheet1!AL10:AO10,3,0),0) -> 0 | BK20: =+IFERROR(VLOOKUP($BK$17,Sheet1!AL10:AO10,3,0),0) -> 0 | BL20: =+IFERROR(VLOOKUP($BL$17,Sheet1!AL10:AO10,3,0),0) -> 0 | BM20: 1497 | BN20: =+IFERROR(VLOOKUP($BN$17,Sheet1!AT10:AW10,3,0),0) -> 0 | BO20: 38 | BP20: 93 | BQ20: =+IFERROR(VLOOKUP($BQ$17,Sheet1!BF10:BI10,3,0),0) -> 0 | BR20: =+IFERROR(VLOOKUP($BR$17,Sheet1!BJ10:BM10,3,0),0) -> 0 | BS20: =+IFERROR(VLOOKUP($BS$17,Sheet1!BN10:BQ10,3,0),0) -> 0 | BT20: 71 | BU20: =+IFERROR(VLOOKUP($BU$17,Sheet1!BV10:BY10,3,0),0) -> 0 | BV20: =Sheet1!E10 -> STEEL | BW20: =SUM(N20:BT20) -> 16914 | BX20: SP0400105 | BY20: CORRUGATED DISPATCH STEEL DRUM 2500 X 1500 X 1400 | BZ20: =Sheet1!CX10 -> 250 | CA20: 160000 | CB20: =SUMPRODUCT($N$18:$BU$18,N20:BU20)+CA20 -> 2315981 | CC20: =Sheet1!CB10 -> 0 | CD20: =CB20*CC20 -> 0 | CE20: 0.24 | CF20: =CB20*CE20 -> 555835.44 | CG20: 0 | CH20: =CB20*CG20 -> 0 | CI20: =CB20+CD20+CF20+CH20 -> 2871816.4 | CJ20: 0.02 | CK20: =CI20*CJ20 -> 57436.329 | CL20: 0.01 | CM20: =CI20*CL20 -> 28718.164
A21: =Sheet1!A5 -> ENQ-12172-22-23 | B21: 45329 | C21: =Sheet1!C5 -> FA1300201 | D21: =Sheet1!D5 -> 3 CORE X 240 SQ. MM. AL/ARM - WIRE (XLPE) - 33 KV | E21: =CI21+CK21+CM21 -> 2674169.4 | F21: =ROUNDUP(M34,0) -> 60000 | G21: =E21+F21 -> 2734169.4 | H21: 0.18 | I21: =G21*H21 -> 492150.5 | J21: =G21+I21 -> 3226319.9 | K21: =Sheet1!CS5 -> 1 | L21: =Sheet1!CT5 -> KMS | M21: =J21*K21 -> 3226319.9 | N21: =+IFERROR(VLOOKUP($N$17,Sheet1!J5:L5,3,0),0) -> 1944 | O21: =+IFERROR(VLOOKUP($O$17,Sheet1!J5:L5,3,0),0) -> 0 | P21: =+IFERROR(VLOOKUP($P$17,Sheet1!J5:M5,3,0),0) -> 0 | Q21: =+IFERROR(VLOOKUP($Q$17,Sheet1!J5:M5,3,0),0) -> 0 | R21: =+IFERROR(VLOOKUP($R$17,Sheet1!J5:M5,3,0),0) -> 0 | S21: =+IFERROR(VLOOKUP($S$17,Sheet1!N5:Q5,3,0),0) -> 0 | T21: =+IFERROR(VLOOKUP($T$17,Sheet1!N5:Q5,3,0),0) -> 0 | U21: =+IFERROR(VLOOKUP($U$17,Sheet1!F5:I5,3,0),0) -> 0 | V21: =+IFERROR(VLOOKUP($V$17,Sheet1!F5:I5,3,0),0) -> 0 | W21: =+IFERROR(VLOOKUP($W$17,Sheet1!F5:I5,3,0),0) -> 0 | X21: =+IFERROR(VLOOKUP($X$17,Sheet1!F5:I5,3,0),0) -> 0 | Y21: 183 | Z21: =+IFERROR(VLOOKUP($Z$17,Sheet1!F5:I5,3,0),0) -> 0 | AA21: =+IFERROR(VLOOKUP($AA$17,Sheet1!F5:I5,3,0),0) -> 0 | AB21: =+IFERROR(VLOOKUP($AB$17,Sheet1!F5:I5,3,0),0) -> 0 | AC21: 427 | AD21: =+IFERROR(VLOOKUP($AD$17,Sheet1!R5:U5,2,0),0) -> 0 | AE21: 2257 | AF21: =+IFERROR(VLOOKUP($AF$17,Sheet1!V5:Y5,3,0),0) -> 0 | AG21: =+IFERROR(VLOOKUP($AG$17,Sheet1!V5:Y5,3,0),0) -> 0 | AH21: =+IFERROR(VLOOKUP($AH$17,Sheet1!V5:Y5,3,0),0) -> 0 | AI21: =+IFERROR(VLOOKUP($AI$17,Sheet1!V5:Y5,3,0),0) -> 0 | AJ21: =+IFERROR(VLOOKUP($AJ$17,Sheet1!V5:Y5,3,0),0) -> 0 | AK21: =+IFERROR(VLOOKUP($AK$17,Sheet1!Z5:AB5,3,0),0) -> 0 | AL21: =+IFERROR(VLOOKUP($AL$17,Sheet1!AD5:AG5,3,0),0) -> 0 | AM21: =+IFERROR(VLOOKUP($AM$17,Sheet1!AD5:AG5,3,0),0) -> 0 | AN21: =+IFERROR(VLOOKUP($AN$17,Sheet1!AD5:AG5,3,0),0) -> 0 | AO21: =+IFERROR(VLOOKUP($AO$17,Sheet1!AD5:AG5,3,0),0) -> 0 | AP21: =+IFERROR(VLOOKUP($AP$17,Sheet1!AD5:AG5,3,0),0) -> 0 | AQ21: =+IFERROR(VLOOKUP($AQ$17,Sheet1!AD5:AG5,3,0),0) -> 0 | AR21: 1256 | AS21: =+IFERROR(VLOOKUP($AS$17,Sheet1!AH5:AK5,3,0),0) -> 0 | AT21: =+IFERROR(VLOOKUP($AT$17,Sheet1!AH5:AK5,3,0),0) -> 0 | AU21: =+IFERROR(VLOOKUP($AU$17,Sheet1!AH5:AK5,3,0),0) -> 0 | AV21: =+IFERROR(VLOOKUP($AV$17,Sheet1!AH5:AK5,3,0),0) -> 0 | AW21: =+IFERROR(VLOOKUP($AW$17,Sheet1!AH5:AK5,3,0),0) -> 0 | AX21: =+IFERROR(VLOOKUP($AX$17,Sheet1!AH5:AK5,3,0),0) -> 0 | AY21: =+IFERROR(VLOOKUP($AY$17,Sheet1!AH5:AK5,3,0),0) -> 0 | AZ21: =+IFERROR(VLOOKUP($AZ$17,Sheet1!AH5:AK5,3,0),0) -> 0 | BA21: 6258 | BB21: =+IFERROR(VLOOKUP($BB$17,Sheet1!AH5:AK5,3,0),0) -> 0 | BC21: =+IFERROR(VLOOKUP($BC$17,Sheet1!AL5:AO5,3,0),0) -> 0 | BD21: =+IFERROR(VLOOKUP($BD$17,Sheet1!AL5:AO5,3,0),0) -> 0 | BE21: =+IFERROR(VLOOKUP($BE$17,Sheet1!AL5:AO5,3,0),0) -> 0 | BF21: 1538 | BG21: =+IFERROR(VLOOKUP($BG$17,Sheet1!AL5:AO5,3,0),0) -> 0 | BH21: =+IFERROR(VLOOKUP($BH$17,Sheet1!AL5:AO5,3,0),0) -> 0 | BI21: =+IFERROR(VLOOKUP($BI$17,Sheet1!AL5:AO5,3,0),0) -> 0 | BJ21: =+IFERROR(VLOOKUP($BJ$17,Sheet1!AL5:AO5,3,0),0) -> 0 | BK21: =+IFERROR(VLOOKUP($BK$17,Sheet1!AL5:AO5,3,0),0) -> 0 | BL21: =+IFERROR(VLOOKUP($BL$17,Sheet1!AL5:AO5,3,0),0) -> 0 | BM21: 1337 | BN21: =+IFERROR(VLOOKUP($BN$17,Sheet1!AT5:AW5,3,0),0) -> 0 | BO21: 33 | BP21: 86 | BQ21: =+IFERROR(VLOOKUP($BQ$17,Sheet1!BF5:BI5,3,0),0) -> 0 | BR21: =+IFERROR(VLOOKUP($BR$17,Sheet1!BJ5:BM5,3,0),0) -> 0 | BS21: =+IFERROR(VLOOKUP($BS$17,Sheet1!BN5:BQ5,3,0),0) -> 0 | BT21: 67 | BU21: =+IFERROR(VLOOKUP($BU$17,Sheet1!BV5:BY5,3,0),0) -> 0 | BV21: =Sheet1!E5 -> STEEL | BW21: =SUM(N21:BT21) -> 15386 | BX21: SP0400105 | BY21: CORRUGATED DISPATCH STEEL DRUM 2500 X 1500 X 1400 | BZ21: =Sheet1!CX5 -> 250 | CA21: 160000 | CB21: =SUMPRODUCT($N$18:$BU$18,N21:BU21)+CA21 -> 2093775 | CC21: =Sheet1!CB5 -> 0 | CD21: =CB21*CC21 -> 0 | CE21: 0.24 | CF21: =CB21*CE21 -> 502506 | CG21: 0 | CH21: =CB21*CG21 -> 0 | CI21: =CB21+CD21+CF21+CH21 -> 2596281 | CJ21: 0.02 | CK21: =CI21*CJ21 -> 51925.62 | CL21: 0.01 | CM21: =CI21*CL21 -> 25962.81
A22: =Sheet1!A3 -> ENQ-12172-22-23 | B22: 45329 | C22: =Sheet1!C3 -> FA1300079 | D22: =Sheet1!D3 -> 3 CORE X 185 SQ. MM AL/ARM - WIRE (XLPE) - 33 KV | E22: =CI22+CK22+CM22 -> 2463587.2 | F22: =ROUNDUP(M35,0) -> 60000 | G22: =E22+F22 -> 2523587.2 | H22: 0.18 | I22: =G22*H22 -> 454245.7 | J22: =G22+I22 -> 2977833 | K22: =Sheet1!CS3 -> 1 | L22: =Sheet1!CT3 -> KMS | M22: =J22*K22 -> 2977833 | N22: =+IFERROR(VLOOKUP($N$17,Sheet1!J3:L3,3,0),0) -> 1499 | O22: =+IFERROR(VLOOKUP($O$17,Sheet1!J3:L3,3,0),0) -> 0 | P22: =+IFERROR(VLOOKUP($P$17,Sheet1!J3:M3,3,0),0) -> 0 | Q22: =+IFERROR(VLOOKUP($Q$17,Sheet1!J3:M3,3,0),0) -> 0 | R22: =+IFERROR(VLOOKUP($R$17,Sheet1!J3:M3,3,0),0) -> 0 | S22: =+IFERROR(VLOOKUP($S$17,Sheet1!N3:Q3,3,0),0) -> 0 | T22: =+IFERROR(VLOOKUP($T$17,Sheet1!N3:Q3,3,0),0) -> 0 | U22: =+IFERROR(VLOOKUP($U$17,Sheet1!F3:I3,3,0),0) -> 0 | V22: =+IFERROR(VLOOKUP($V$17,Sheet1!F3:I3,3,0),0) -> 0 | W22: =+IFERROR(VLOOKUP($W$17,Sheet1!F3:I3,3,0),0) -> 0 | X22: =+IFERROR(VLOOKUP($X$17,Sheet1!F3:I3,3,0),0) -> 0 | Y22: 175 | Z22: =+IFERROR(VLOOKUP($Z$17,Sheet1!F3:I3,3,0),0) -> 0 | AA22: =+IFERROR(VLOOKUP($AA$17,Sheet1!F3:I3,3,0),0) -> 0 | AB22: =+IFERROR(VLOOKUP($AB$17,Sheet1!F3:I3,3,0),0) -> 0 | AC22: 422 | AD22: =+IFERROR(VLOOKUP($AD$17,Sheet1!R3:U3,2,0),0) -> 0 | AE22: 2091 | AF22: =+IFERROR(VLOOKUP($AF$17,Sheet1!V3:Y3,3,0),0) -> 0 | AG22: =+IFERROR(VLOOKUP($AG$17,Sheet1!V3:Y3,3,0),0) -> 0 | AH22: =+IFERROR(VLOOKUP($AH$17,Sheet1!V3:Y3,3,0),0) -> 0 | AI22: =+IFERROR(VLOOKUP($AI$17,Sheet1!V3:Y3,3,0),0) -> 0 | AJ22: =+IFERROR(VLOOKUP($AJ$17,Sheet1!V3:Y3,3,0),0) -> 0 | AK22: =+IFERROR(VLOOKUP($AK$17,Sheet1!Z3:AB3,3,0),0) -> 0 | AL22: =+IFERROR(VLOOKUP($AL$17,Sheet1!AD3:AG3,3,0),0) -> 0 | AM22: =+IFERROR(VLOOKUP($AM$17,Sheet1!AD3:AG3,3,0),0) -> 0 | AN22: =+IFERROR(VLOOKUP($AN$17,Sheet1!AD3:AG3,3,0),0) -> 0 | AO22: =+IFERROR(VLOOKUP($AO$17,Sheet1!AD3:AG3,3,0),0) -> 0 | AP22: =+IFERROR(VLOOKUP($AP$17,Sheet1!AD3:AG3,3,0),0) -> 0 | AQ22: =+IFERROR(VLOOKUP($AQ$17,Sheet1!AD3:AG3,3,0),0) -> 0 | AR22: 1145 | AS22: =+IFERROR(VLOOKUP($AS$17,Sheet1!AH3:AK3,3,0),0) -> 0 | AT22: =+IFERROR(VLOOKUP($AT$17,Sheet1!AH3:AK3,3,0),0) -> 0 | AU22: =+IFERROR(VLOOKUP($AU$17,Sheet1!AH3:AK3,3,0),0) -> 0 | AV22: =+IFERROR(VLOOKUP($AV$17,Sheet1!AH3:AK3,3,0),0) -> 0 | AW22: =+IFERROR(VLOOKUP($AW$17,Sheet1!AH3:AK3,3,0),0) -> 0 | AX22: =+IFERROR(VLOOKUP($AX$17,Sheet1!AH3:AK3,3,0),0) -> 0 | AY22: =+IFERROR(VLOOKUP($AY$17,Sheet1!AH3:AK3,3,0),0) -> 0 | AZ22: =+IFERROR(VLOOKUP($AZ$17,Sheet1!AH3:AK3,3,0),0) -> 0 | BA22: 5950 | BB22: =+IFERROR(VLOOKUP($BB$17,Sheet1!AH3:AK3,3,0),0) -> 0 | BC22: =+IFERROR(VLOOKUP($BC$17,Sheet1!AL3:AO3,3,0),0) -> 0 | BD22: =+IFERROR(VLOOKUP($BD$17,Sheet1!AL3:AO3,3,0),0) -> 0 | BE22: =+IFERROR(VLOOKUP($BE$17,Sheet1!AL3:AO3,3,0),0) -> 0 | BF22: 1480 | BG22: =+IFERROR(VLOOKUP($BG$17,Sheet1!AL3:AO3,3,0),0) -> 0 | BH22: =+IFERROR(VLOOKUP($BH$17,Sheet1!AL3:AO3,3,0),0) -> 0 | BI22: =+IFERROR(VLOOKUP($BI$17,Sheet1!AL3:AO3,3,0),0) -> 0 | BJ22: =+IFERROR(VLOOKUP($BJ$17,Sheet1!AL3:AO3,3,0),0) -> 0 | BK22: =+IFERROR(VLOOKUP($BK$17,Sheet1!AL3:AO3,3,0),0) -> 0 | BL22: =+IFERROR(VLOOKUP($BL$17,Sheet1!AL3:AO3,3,0),0) -> 0 | BM22: 1200 | BN22: =+IFERROR(VLOOKUP($BN$17,Sheet1!AT3:AW3,3,0),0) -> 0 | BO22: 35 | BP22: 82 | BQ22: =+IFERROR(VLOOKUP($BQ$17,Sheet1!BF3:BI3,3,0),0) -> 0 | BR22: =+IFERROR(VLOOKUP($BR$17,Sheet1!BJ3:BM3,3,0),0) -> 0 | BS22: =+IFERROR(VLOOKUP($BS$17,Sheet1!BN3:BQ3,3,0),0) -> 0 | BT22: 63 | BU22: =+IFERROR(VLOOKUP($BU$17,Sheet1!BV3:BY3,3,0),0) -> 0 | BV22: =Sheet1!E3 -> STEEL | BW22: =SUM(N22:BT22) -> 14142 | BX22: SP0400081 | BY22: CORRUGATED DISPATCH STEEL DRUM 2500 X 1400 X 1250 MM | BZ22: =Sheet1!CX3 -> 250 | CA22: 176000 | CB22: =SUMPRODUCT($N$18:$BU$18,N22:BU22)+CA22 -> 1928897 | CC22: =Sheet1!CB3 -> 0 | CD22: =CB22*CC22 -> 0 | CE22: 0.24 | CF22: =CB22*CE22 -> 462935.28 | CG22: 0 | CH22: =CB22*CG22 -> 0 | CI22: =CB22+CD22+CF22+CH22 -> 2391832.3 | CJ22: 0.02 | CK22: =CI22*CJ22 -> 47836.646 | CL22: 0.01 | CM22: =CI22*CL22 -> 23918.323
A23: =Sheet1!A8 -> ENQ-12172-22-23 | B23: 45329 | C23: =Sheet1!C8 -> FA1300200 | D23: =Sheet1!D8 -> 3 CORE X 95 SQ. MM. AL/ARM WIRE (XLPE) - 33 KV | E23: =CI23+CK23+CM23 -> 1798335.9 | F23: =ROUNDUP(M36,0) -> 40000 | G23: =E23+F23 -> 1838335.9 | H23: 0.18 | I23: =G23*H23 -> 330900.46 | J23: =G23+I23 -> 2169236.4 | K23: =Sheet1!CS8 -> 3 | L23: =Sheet1!CT8 -> KMS | M23: =J23*K23 -> 6507709.1 | N23: =+IFERROR(VLOOKUP($N$17,Sheet1!J8:L8,3,0),0) -> 770 | O23: =+IFERROR(VLOOKUP($O$17,Sheet1!J8:L8,3,0),0) -> 0 | P23: =+IFERROR(VLOOKUP($P$17,Sheet1!J8:M8,3,0),0) -> 0 | Q23: =+IFERROR(VLOOKUP($Q$17,Sheet1!J8:M8,3,0),0) -> 0 | R23: =+IFERROR(VLOOKUP($R$17,Sheet1!J8:M8,3,0),0) -> 0 | S23: =+IFERROR(VLOOKUP($S$17,Sheet1!N8:Q8,3,0),0) -> 0 | T23: =+IFERROR(VLOOKUP($T$17,Sheet1!N8:Q8,3,0),0) -> 0 | U23: =+IFERROR(VLOOKUP($U$17,Sheet1!F8:I8,3,0),0) -> 0 | V23: =+IFERROR(VLOOKUP($V$17,Sheet1!F8:I8,3,0),0) -> 0 | W23: =+IFERROR(VLOOKUP($W$17,Sheet1!F8:I8,3,0),0) -> 0 | X23: =+IFERROR(VLOOKUP($X$17,Sheet1!F8:I8,3,0),0) -> 0 | Y23: 151 | Z23: =+IFERROR(VLOOKUP($Z$17,Sheet1!F8:I8,3,0),0) -> 0 | AA23: =+IFERROR(VLOOKUP($AA$17,Sheet1!F8:I8,3,0),0) -> 0 | AB23: =+IFERROR(VLOOKUP($AB$17,Sheet1!F8:I8,3,0),0) -> 0 | AC23: 345 | AD23: =+IFERROR(VLOOKUP($AD$17,Sheet1!R8:U8,2,0),0) -> 0 | AE23: 1725 | AF23: =+IFERROR(VLOOKUP($AF$17,Sheet1!V8:Y8,3,0),0) -> 0 | AG23: =+IFERROR(VLOOKUP($AG$17,Sheet1!V8:Y8,3,0),0) -> 0 | AH23: =+IFERROR(VLOOKUP($AH$17,Sheet1!V8:Y8,3,0),0) -> 0 | AI23: =+IFERROR(VLOOKUP($AI$17,Sheet1!V8:Y8,3,0),0) -> 0 | AJ23: =+IFERROR(VLOOKUP($AJ$17,Sheet1!V8:Y8,3,0),0) -> 0 | AK23: =+IFERROR(VLOOKUP($AK$17,Sheet1!Z8:AB8,3,0),0) -> 0 | AL23: =+IFERROR(VLOOKUP($AL$17,Sheet1!AD8:AG8,3,0),0) -> 0 | AM23: =+IFERROR(VLOOKUP($AM$17,Sheet1!AD8:AG8,3,0),0) -> 0 | AN23: =+IFERROR(VLOOKUP($AN$17,Sheet1!AD8:AG8,3,0),0) -> 0 | AO23: =+IFERROR(VLOOKUP($AO$17,Sheet1!AD8:AG8,3,0),0) -> 0 | AP23: =+IFERROR(VLOOKUP($AP$17,Sheet1!AD8:AG8,3,0),0) -> 0 | AQ23: =+IFERROR(VLOOKUP($AQ$17,Sheet1!AD8:AG8,3,0),0) -> 0 | AR23: 914 | AS23: =+IFERROR(VLOOKUP($AS$17,Sheet1!AH8:AK8,3,0),0) -> 0 | AT23: =+IFERROR(VLOOKUP($AT$17,Sheet1!AH8:AK8,3,0),0) -> 0 | AU23: =+IFERROR(VLOOKUP($AU$17,Sheet1!AH8:AK8,3,0),0) -> 0 | AV23: =+IFERROR(VLOOKUP($AV$17,Sheet1!AH8:AK8,3,0),0) -> 0 | AW23: =+IFERROR(VLOOKUP($AW$17,Sheet1!AH8:AK8,3,0),0) -> 0 | AX23: =+IFERROR(VLOOKUP($AX$17,Sheet1!AH8:AK8,3,0),0) -> 0 | AY23: =+IFERROR(VLOOKUP($AY$17,Sheet1!AH8:AK8,3,0),0) -> 0 | AZ23: =+IFERROR(VLOOKUP($AZ$17,Sheet1!AH8:AK8,3,0),0) -> 0 | BA23: 4135 | BB23: =+IFERROR(VLOOKUP($BB$17,Sheet1!AH8:AK8,3,0),0) -> 0 | BC23: =+IFERROR(VLOOKUP($BC$17,Sheet1!AL8:AO8,3,0),0) -> 0 | BD23: =+IFERROR(VLOOKUP($BD$17,Sheet1!AL8:AO8,3,0),0) -> 0 | BE23: =+IFERROR(VLOOKUP($BE$17,Sheet1!AL8:AO8,3,0),0) -> 0 | BF23: 1282 | BG23: =+IFERROR(VLOOKUP($BG$17,Sheet1!AL8:AO8,3,0),0) -> 0 | BH23: =+IFERROR(VLOOKUP($BH$17,Sheet1!AL8:AO8,3,0),0) -> 0 | BI23: =+IFERROR(VLOOKUP($BI$17,Sheet1!AL8:AO8,3,0),0) -> 0 | BJ23: =+IFERROR(VLOOKUP($BJ$17,Sheet1!AL8:AO8,3,0),0) -> 0 | BK23: =+IFERROR(VLOOKUP($BK$17,Sheet1!AL8:AO8,3,0),0) -> 0 | BL23: =+IFERROR(VLOOKUP($BL$17,Sheet1!AL8:AO8,3,0),0) -> 0 | BM23: 917 | BN23: =+IFERROR(VLOOKUP($BN$17,Sheet1!AT8:AW8,3,0),0) -> 0 | BO23: 15 | BP23: 66 | BQ23: =+IFERROR(VLOOKUP($BQ$17,Sheet1!BF8:BI8,3,0),0) -> 0 | BR23: =+IFERROR(VLOOKUP($BR$17,Sheet1!BJ8:BM8,3,0),0) -> 0 | BS23: =+IFERROR(VLOOKUP($BS$17,Sheet1!BN8:BQ8,3,0),0) -> 0 | BT23: 56 | BU23: =+IFERROR(VLOOKUP($BU$17,Sheet1!BV8:BY8,3,0),0) -> 0 | BV23: =Sheet1!E8 -> STEEL | BW23: =SUM(N23:BT23) -> 10376 | BX23: SP0400136 | BY23: CORRUGATED DISPATCH STEEL DRUM 2200 X 1300 X 1200 MM | BZ23: =Sheet1!CX8 -> 250 | CA23: 128000 | CB23: =SUMPRODUCT($N$18:$BU$18,N23:BU23)+CA23 -> 1408030 | CC23: =Sheet1!CB8 -> 0 | CD23: =CB23*CC23 -> 0 | CE23: 0.24 | CF23: =CB23*CE23 -> 337927.2 | CG23: 0 | CH23: =CB23*CG23 -> 0 | CI23: =CB23+CD23+CF23+CH23 -> 1745957.2 | CJ23: 0.02 | CK23: =CI23*CJ23 -> 34919.144 | CL23: 0.01 | CM23: =CI23*CL23 -> 17459.572
A24: =Sheet1!A4 -> ENQ-12172-22-23 | B24: 45329 | C24: =Sheet1!C4 -> FA1300120 | D24: =Sheet1!D4 -> 3 CORE X 70 SQ. MM. AL/ARM - WIRE (XLPE) - 33 KV | E24: =CI24+CK24+CM24 -> 1651715.9 | F24: =ROUNDUP(M37,0) -> 60000 | G24: =E24+F24 -> 1711715.9 | H24: 0.18 | I24: =G24*H24 -> 308108.86 | J24: =G24+I24 -> 2019824.8 | K24: =Sheet1!CS4 -> 1 | L24: =Sheet1!CT4 -> KMS | M24: =J24*K24 -> 2019824.8 | N24: =+IFERROR(VLOOKUP($N$17,Sheet1!J4:L4,3,0),0) -> 567 | O24: =+IFERROR(VLOOKUP($O$17,Sheet1!J4:L4,3,0),0) -> 0 | P24: =+IFERROR(VLOOKUP($P$17,Sheet1!J4:M4,3,0),0) -> 0 | Q24: =+IFERROR(VLOOKUP($Q$17,Sheet1!J4:M4,3,0),0) -> 0 | R24: =+IFERROR(VLOOKUP($R$17,Sheet1!J4:M4,3,0),0) -> 0 | S24: =+IFERROR(VLOOKUP($S$17,Sheet1!N4:Q4,3,0),0) -> 0 | T24: =+IFERROR(VLOOKUP($T$17,Sheet1!N4:Q4,3,0),0) -> 0 | U24: =+IFERROR(VLOOKUP($U$17,Sheet1!F4:I4,3,0),0) -> 0 | V24: =+IFERROR(VLOOKUP($V$17,Sheet1!F4:I4,3,0),0) -> 0 | W24: =+IFERROR(VLOOKUP($W$17,Sheet1!F4:I4,3,0),0) -> 0 | X24: =+IFERROR(VLOOKUP($X$17,Sheet1!F4:I4,3,0),0) -> 0 | Y24: 145 | Z24: =+IFERROR(VLOOKUP($Z$17,Sheet1!F4:I4,3,0),0) -> 0 | AA24: =+IFERROR(VLOOKUP($AA$17,Sheet1!F4:I4,3,0),0) -> 0 | AB24: =+IFERROR(VLOOKUP($AB$17,Sheet1!F4:I4,3,0),0) -> 0 | AC24: 301 | AD24: =+IFERROR(VLOOKUP($AD$17,Sheet1!R4:U4,2,0),0) -> 0 | AE24: 1610 | AF24: =+IFERROR(VLOOKUP($AF$17,Sheet1!V4:Y4,3,0),0) -> 0 | AG24: =+IFERROR(VLOOKUP($AG$17,Sheet1!V4:Y4,3,0),0) -> 0 | AH24: =+IFERROR(VLOOKUP($AH$17,Sheet1!V4:Y4,3,0),0) -> 0 | AI24: =+IFERROR(VLOOKUP($AI$17,Sheet1!V4:Y4,3,0),0) -> 0 | AJ24: =+IFERROR(VLOOKUP($AJ$17,Sheet1!V4:Y4,3,0),0) -> 0 | AK24: =+IFERROR(VLOOKUP($AK$17,Sheet1!Z4:AB4,3,0),0) -> 0 | AL24: =+IFERROR(VLOOKUP($AL$17,Sheet1!AD4:AG4,3,0),0) -> 0 | AM24: =+IFERROR(VLOOKUP($AM$17,Sheet1!AD4:AG4,3,0),0) -> 0 | AN24: =+IFERROR(VLOOKUP($AN$17,Sheet1!AD4:AG4,3,0),0) -> 0 | AO24: =+IFERROR(VLOOKUP($AO$17,Sheet1!AD4:AG4,3,0),0) -> 0 | AP24: =+IFERROR(VLOOKUP($AP$17,Sheet1!AD4:AG4,3,0),0) -> 0 | AQ24: =+IFERROR(VLOOKUP($AQ$17,Sheet1!AD4:AG4,3,0),0) -> 0 | AR24: 846 | AS24: =+IFERROR(VLOOKUP($AS$17,Sheet1!AH4:AK4,3,0),0) -> 0 | AT24: =+IFERROR(VLOOKUP($AT$17,Sheet1!AH4:AK4,3,0),0) -> 0 | AU24: =+IFERROR(VLOOKUP($AU$17,Sheet1!AH4:AK4,3,0),0) -> 0 | AV24: =+IFERROR(VLOOKUP($AV$17,Sheet1!AH4:AK4,3,0),0) -> 0 | AW24: =+IFERROR(VLOOKUP($AW$17,Sheet1!AH4:AK4,3,0),0) -> 0 | AX24: =+IFERROR(VLOOKUP($AX$17,Sheet1!AH4:AK4,3,0),0) -> 0 | AY24: =+IFERROR(VLOOKUP($AY$17,Sheet1!AH4:AK4,3,0),0) -> 0 | AZ24: =+IFERROR(VLOOKUP($AZ$17,Sheet1!AH4:AK4,3,0),0) -> 0 | BA24: 3945 | BB24: =+IFERROR(VLOOKUP($BB$17,Sheet1!AH4:AK4,3,0),0) -> 0 | BC24: =+IFERROR(VLOOKUP($BC$17,Sheet1!AL4:AO4,3,0),0) -> 0 | BD24: =+IFERROR(VLOOKUP($BD$17,Sheet1!AL4:AO4,3,0),0) -> 0 | BE24: =+IFERROR(VLOOKUP($BE$17,Sheet1!AL4:AO4,3,0),0) -> 0 | BF24: 1174 | BG24: =+IFERROR(VLOOKUP($BG$17,Sheet1!AL4:AO4,3,0),0) -> 0 | BH24: =+IFERROR(VLOOKUP($BH$17,Sheet1!AL4:AO4,3,0),0) -> 0 | BI24: =+IFERROR(VLOOKUP($BI$17,Sheet1!AL4:AO4,3,0),0) -> 0 | BJ24: =+IFERROR(VLOOKUP($BJ$17,Sheet1!AL4:AO4,3,0),0) -> 0 | BK24: =+IFERROR(VLOOKUP($BK$17,Sheet1!AL4:AO4,3,0),0) -> 0 | BL24: =+IFERROR(VLOOKUP($BL$17,Sheet1!AL4:AO4,3,0),0) -> 0 | BM24: 835 | BN24: =+IFERROR(VLOOKUP($BN$17,Sheet1!AT4:AW4,3,0),0) -> 0 | BO24: 15 | BP24: 62 | BQ24: =+IFERROR(VLOOKUP($BQ$17,Sheet1!BF4:BI4,3,0),0) -> 0 | BR24: =+IFERROR(VLOOKUP($BR$17,Sheet1!BJ4:BM4,3,0),0) -> 0 | BS24: =+IFERROR(VLOOKUP($BS$17,Sheet1!BN4:BQ4,3,0),0) -> 0 | BT24: 53 | BU24: =+IFERROR(VLOOKUP($BU$17,Sheet1!BV4:BY4,3,0),0) -> 0 | BV24: =Sheet1!E4 -> STEEL | BW24: =SUM(N24:BT24) -> 9553 | BX24: SP0400136 | BY24: CORRUGATED DISPATCH STEEL DRUM 2200 X 1300 X 1200 MM | BZ24: =Sheet1!CX4 -> 250 | CA24: 128000 | CB24: =SUMPRODUCT($N$18:$BU$18,N24:BU24)+CA24 -> 1293232 | CC24: =Sheet1!CB4 -> 0 | CD24: =CB24*CC24 -> 0 | CE24: 0.24 | CF24: =CB24*CE24 -> 310375.68 | CG24: 0 | CH24: =CB24*CG24 -> 0 | CI24: =CB24+CD24+CF24+CH24 -> 1603607.7 | CJ24: 0.02 | CK24: =CI24*CJ24 -> 32072.154 | CL24: 0.01 | CM24: =CI24*CL24 -> 16036.077
A25: =Sheet1!A2 -> ENQ-12172-22-23 | B25: 45329 | C25: =Sheet1!C2 -> FA1300022 | D25: =Sheet1!D2 -> 3 CORE X 50 SQ. MM. AL/ARD - WIRE (XLPE) - 33 KV (E) | E25: =CI25+CK25+CM25 -> 1454232.7 | F25: =ROUNDUP(M38,0) -> 60000 | G25: =E25+F25 -> 1514232.7 | H25: 0.18 | I25: =G25*H25 -> 272561.88 | J25: =G25+I25 -> 1786794.6 | K25: =Sheet1!CS2 -> 1 | L25: =Sheet1!CT2 -> KMS | M25: =J25*K25 -> 1786794.6 | N25: 405 | O25: =+IFERROR(VLOOKUP($O$17,Sheet1!J2:L2,3,0),0) -> 0 | P25: =+IFERROR(VLOOKUP($P$17,Sheet1!J2:M2,3,0),0) -> 0 | Q25: =+IFERROR(VLOOKUP($Q$17,Sheet1!J2:M2,3,0),0) -> 0 | R25: =+IFERROR(VLOOKUP($R$17,Sheet1!J2:M2,3,0),0) -> 0 | S25: =+IFERROR(VLOOKUP($S$17,Sheet1!N2:Q2,3,0),0) -> 0 | T25: =+IFERROR(VLOOKUP($T$17,Sheet1!N2:Q2,3,0),0) -> 0 | U25: =+IFERROR(VLOOKUP($U$17,Sheet1!F2:I2,3,0),0) -> 0 | V25: =+IFERROR(VLOOKUP($V$17,Sheet1!F2:I2,3,0),0) -> 0 | W25: =+IFERROR(VLOOKUP($W$17,Sheet1!F2:I2,3,0),0) -> 0 | X25: =+IFERROR(VLOOKUP($X$17,Sheet1!F2:I2,3,0),0) -> 0 | Y25: 137 | Z25: =+IFERROR(VLOOKUP($Z$17,Sheet1!F2:I2,3,0),0) -> 0 | AA25: =+IFERROR(VLOOKUP($AA$17,Sheet1!F2:I2,3,0),0) -> 0 | AB25: =+IFERROR(VLOOKUP($AB$17,Sheet1!F2:I2,3,0),0) -> 0 | AC25: 276 | AD25: =+IFERROR(VLOOKUP($AD$17,Sheet1!R2:U2,2,0),0) -> 0 | AE25: 1486 | AF25: =+IFERROR(VLOOKUP($AF$17,Sheet1!V2:Y2,3,0),0) -> 0 | AG25: =+IFERROR(VLOOKUP($AG$17,Sheet1!V2:Y2,3,0),0) -> 0 | AH25: =+IFERROR(VLOOKUP($AH$17,Sheet1!V2:Y2,3,0),0) -> 0 | AI25: =+IFERROR(VLOOKUP($AI$17,Sheet1!V2:Y2,3,0),0) -> 0 | AJ25: =+IFERROR(VLOOKUP($AJ$17,Sheet1!V2:Y2,3,0),0) -> 0 | AK25: =+IFERROR(VLOOKUP($AK$17,Sheet1!Z2:AB2,3,0),0) -> 0 | AL25: =+IFERROR(VLOOKUP($AL$17,Sheet1!AD2:AG2,3,0),0) -> 0 | AM25: =+IFERROR(VLOOKUP($AM$17,Sheet1!AD2:AG2,3,0),0) -> 0 | AN25: =+IFERROR(VLOOKUP($AN$17,Sheet1!AD2:AG2,3,0),0) -> 0 | AO25: =+IFERROR(VLOOKUP($AO$17,Sheet1!AD2:AG2,3,0),0) -> 0 | AP25: =+IFERROR(VLOOKUP($AP$17,Sheet1!AD2:AG2,3,0),0) -> 0 | AQ25: =+IFERROR(VLOOKUP($AQ$17,Sheet1!AD2:AG2,3,0),0) -> 0 | AR25: 776 | AS25: =+IFERROR(VLOOKUP($AS$17,Sheet1!AH2:AK2,3,0),0) -> 0 | AT25: =+IFERROR(VLOOKUP($AT$17,Sheet1!AH2:AK2,3,0),0) -> 0 | AU25: =+IFERROR(VLOOKUP($AU$17,Sheet1!AH2:AK2,3,0),0) -> 0 | AV25: =+IFERROR(VLOOKUP($AV$17,Sheet1!AH2:AK2,3,0),0) -> 0 | AW25: =+IFERROR(VLOOKUP($AW$17,Sheet1!AH2:AK2,3,0),0) -> 0 | AX25: =+IFERROR(VLOOKUP($AX$17,Sheet1!AH2:AK2,3,0),0) -> 0 | AY25: =+IFERROR(VLOOKUP($AY$17,Sheet1!AH2:AK2,3,0),0) -> 0 | AZ25: =+IFERROR(VLOOKUP($AZ$17,Sheet1!AH2:AK2,3,0),0) -> 0 | BA25: 3754 | BB25: =+IFERROR(VLOOKUP($BB$17,Sheet1!AH2:AK2,3,0),0) -> 0 | BC25: =+IFERROR(VLOOKUP($BC$17,Sheet1!AL2:AO2,3,0),0) -> 0 | BD25: =+IFERROR(VLOOKUP($BD$17,Sheet1!AL2:AO2,3,0),0) -> 0 | BE25: =+IFERROR(VLOOKUP($BE$17,Sheet1!AL2:AO2,3,0),0) -> 0 | BF25: 1067 | BG25: =+IFERROR(VLOOKUP($BG$17,Sheet1!AL2:AO2,3,0),0) -> 0 | BH25: =+IFERROR(VLOOKUP($BH$17,Sheet1!AL2:AO2,3,0),0) -> 0 | BI25: =+IFERROR(VLOOKUP($BI$17,Sheet1!AL2:AO2,3,0),0) -> 0 | BJ25: =+IFERROR(VLOOKUP($BJ$17,Sheet1!AL2:AO2,3,0),0) -> 0 | BK25: =+IFERROR(VLOOKUP($BK$17,Sheet1!AL2:AO2,3,0),0) -> 0 | BL25: =+IFERROR(VLOOKUP($BL$17,Sheet1!AL2:AO2,3,0),0) -> 0 | BM25: 752 | BN25: =+IFERROR(VLOOKUP($BN$17,Sheet1!AT2:AW2,3,0),0) -> 0 | BO25: 10 | BP25: 58 | BQ25: =+IFERROR(VLOOKUP($BQ$17,Sheet1!BF2:BI2,3,0),0) -> 0 | BR25: =+IFERROR(VLOOKUP($BR$17,Sheet1!BJ2:BM2,3,0),0) -> 0 | BS25: =+IFERROR(VLOOKUP($BS$17,Sheet1!BN2:BQ2,3,0),0) -> 0 | BT25: 51 | BU25: =+IFERROR(VLOOKUP($BU$17,Sheet1!BV2:BY2,3,0),0) -> 0 | BV25: =Sheet1!E2 -> STEEL | BW25: =SUM(N25:BT25) -> 8772 | BX25: SP0400112 | BY25: CORRUGATED DISPATCH STEEL DRUM 2000 X 1000 X 1000 MM | BZ25: =Sheet1!CX2 -> 250 | CA25: 80000 | CB25: =SUMPRODUCT($N$18:$BU$18,N25:BU25)+CA25 -> 1138610 | CC25: =Sheet1!CB2 -> 0 | CD25: =CB25*CC25 -> 0 | CE25: 0.24 | CF25: =CB25*CE25 -> 273266.4 | CG25: 0 | CH25: =CB25*CG25 -> 0 | CI25: =CB25+CD25+CF25+CH25 -> 1411876.4 | CJ25: 0.02 | CK25: =CI25*CJ25 -> 28237.528 | CL25: 0.01 | CM25: =CI25*CL25 -> 14118.764
A26: =Sheet1!A6 -> ENQ-12172-22-23 | B26: 45329 | C26: =Sheet1!C6 -> FA1300297 | D26: =Sheet1!D6 -> 3 CORE X 35 SQ. MM. AL/ARM - WIRE (XLPE) - 33 KV (E) | E26: =CI26+CK26+CM26 -> 1454232.7 | F26: =ROUNDUP(M39,0) -> 60000 | G26: =E26+F26 -> 1514232.7 | H26: 0.18 | I26: =G26*H26 -> 272561.88 | J26: =G26+I26 -> 1786794.6 | K26: =Sheet1!CS6 -> 1 | L26: =Sheet1!CT6 -> KMS | M26: =J26*K26 -> 1786794.6 | N26: =+IFERROR(VLOOKUP($N$17,Sheet1!J6:L6,3,0),0) -> 405 | O26: =+IFERROR(VLOOKUP($O$17,Sheet1!J6:L6,3,0),0) -> 0 | P26: =+IFERROR(VLOOKUP($P$17,Sheet1!J6:M6,3,0),0) -> 0 | Q26: =+IFERROR(VLOOKUP($Q$17,Sheet1!J6:M6,3,0),0) -> 0 | R26: =+IFERROR(VLOOKUP($R$17,Sheet1!J6:M6,3,0),0) -> 0 | S26: =+IFERROR(VLOOKUP($S$17,Sheet1!N6:Q6,3,0),0) -> 0 | T26: =+IFERROR(VLOOKUP($T$17,Sheet1!N6:Q6,3,0),0) -> 0 | U26: =+IFERROR(VLOOKUP($U$17,Sheet1!F6:I6,3,0),0) -> 0 | V26: =+IFERROR(VLOOKUP($V$17,Sheet1!F6:I6,3,0),0) -> 0 | W26: =+IFERROR(VLOOKUP($W$17,Sheet1!F6:I6,3,0),0) -> 0 | X26: =+IFERROR(VLOOKUP($X$17,Sheet1!F6:I6,3,0),0) -> 0 | Y26: 137 | Z26: =+IFERROR(VLOOKUP($Z$17,Sheet1!F6:I6,3,0),0) -> 0 | AA26: =+IFERROR(VLOOKUP($AA$17,Sheet1!F6:I6,3,0),0) -> 0 | AB26: =+IFERROR(VLOOKUP($AB$17,Sheet1!F6:I6,3,0),0) -> 0 | AC26: 276 | AD26: =+IFERROR(VLOOKUP($AD$17,Sheet1!R6:U6,2,0),0) -> 0 | AE26: 1486 | AF26: =+IFERROR(VLOOKUP($AF$17,Sheet1!V6:Y6,3,0),0) -> 0 | AG26: =+IFERROR(VLOOKUP($AG$17,Sheet1!V6:Y6,3,0),0) -> 0 | AH26: =+IFERROR(VLOOKUP($AH$17,Sheet1!V6:Y6,3,0),0) -> 0 | AI26: =+IFERROR(VLOOKUP($AI$17,Sheet1!V6:Y6,3,0),0) -> 0 | AJ26: =+IFERROR(VLOOKUP($AJ$17,Sheet1!V6:Y6,3,0),0) -> 0 | AK26: =+IFERROR(VLOOKUP($AK$17,Sheet1!Z6:AB6,3,0),0) -> 0 | AL26: =+IFERROR(VLOOKUP($AL$17,Sheet1!AD6:AG6,3,0),0) -> 0 | AM26: =+IFERROR(VLOOKUP($AM$17,Sheet1!AD6:AG6,3,0),0) -> 0 | AN26: =+IFERROR(VLOOKUP($AN$17,Sheet1!AD6:AG6,3,0),0) -> 0 | AO26: =+IFERROR(VLOOKUP($AO$17,Sheet1!AD6:AG6,3,0),0) -> 0 | AP26: =+IFERROR(VLOOKUP($AP$17,Sheet1!AD6:AG6,3,0),0) -> 0 | AQ26: =+IFERROR(VLOOKUP($AQ$17,Sheet1!AD6:AG6,3,0),0) -> 0 | AR26: 776 | AS26: =+IFERROR(VLOOKUP($AS$17,Sheet1!AH6:AK6,3,0),0) -> 0 | AT26: =+IFERROR(VLOOKUP($AT$17,Sheet1!AH6:AK6,3,0),0) -> 0 | AU26: =+IFERROR(VLOOKUP($AU$17,Sheet1!AH6:AK6,3,0),0) -> 0 | AV26: =+IFERROR(VLOOKUP($AV$17,Sheet1!AH6:AK6,3,0),0) -> 0 | AW26: =+IFERROR(VLOOKUP($AW$17,Sheet1!AH6:AK6,3,0),0) -> 0 | AX26: =+IFERROR(VLOOKUP($AX$17,Sheet1!AH6:AK6,3,0),0) -> 0 | AY26: =+IFERROR(VLOOKUP($AY$17,Sheet1!AH6:AK6,3,0),0) -> 0 | AZ26: =+IFERROR(VLOOKUP($AZ$17,Sheet1!AH6:AK6,3,0),0) -> 0 | BA26: 3754 | BB26: =+IFERROR(VLOOKUP($BB$17,Sheet1!AH6:AK6,3,0),0) -> 0 | BC26: =+IFERROR(VLOOKUP($BC$17,Sheet1!AL6:AO6,3,0),0) -> 0 | BD26: =+IFERROR(VLOOKUP($BD$17,Sheet1!AL6:AO6,3,0),0) -> 0 | BE26: =+IFERROR(VLOOKUP($BE$17,Sheet1!AL6:AO6,3,0),0) -> 0 | BF26: 1067 | BG26: =+IFERROR(VLOOKUP($BG$17,Sheet1!AL6:AO6,3,0),0) -> 0 | BH26: =+IFERROR(VLOOKUP($BH$17,Sheet1!AL6:AO6,3,0),0) -> 0 | BI26: =+IFERROR(VLOOKUP($BI$17,Sheet1!AL6:AO6,3,0),0) -> 0 | BJ26: =+IFERROR(VLOOKUP($BJ$17,Sheet1!AL6:AO6,3,0),0) -> 0 | BK26: =+IFERROR(VLOOKUP($BK$17,Sheet1!AL6:AO6,3,0),0) -> 0 | BL26: =+IFERROR(VLOOKUP($BL$17,Sheet1!AL6:AO6,3,0),0) -> 0 | BM26: 752 | BN26: =+IFERROR(VLOOKUP($BN$17,Sheet1!AT6:AW6,3,0),0) -> 0 | BO26: 10 | BP26: 58 | BQ26: =+IFERROR(VLOOKUP($BQ$17,Sheet1!BF6:BI6,3,0),0) -> 0 | BR26: =+IFERROR(VLOOKUP($BR$17,Sheet1!BJ6:BM6,3,0),0) -> 0 | BS26: =+IFERROR(VLOOKUP($BS$17,Sheet1!BN6:BQ6,3,0),0) -> 0 | BT26: 51 | BU26: =+IFERROR(VLOOKUP($BU$17,Sheet1!BV6:BY6,3,0),0) -> 0 | BV26: =Sheet1!E6 -> STEEL | BW26: =SUM(N26:BT26) -> 8772 | BX26: SP0400112 | BY26: CORRUGATED DISPATCH STEEL DRUM 2000 X 1000 X 1000 MM | BZ26: =Sheet1!CX6 -> 250 | CA26: 80000 | CB26: =SUMPRODUCT($N$18:$BU$18,N26:BU26)+CA26 -> 1138610 | CC26: =Sheet1!CB6 -> 0 | CD26: =CB26*CC26 -> 0 | CE26: 0.24 | CF26: =CB26*CE26 -> 273266.4 | CG26: 0 | CH26: =CB26*CG26 -> 0 | CI26: =CB26+CD26+CF26+CH26 -> 1411876.4 | CJ26: 0.02 | CK26: =CI26*CJ26 -> 28237.528 | CL26: 0.01 | CM26: =CI26*CL26 -> 14118.764
A27: =Sheet1!A12 -> ENQ-12172-22-23 | B27: 45329 | C27: =Sheet1!C12 -> FA1300027 | D27: =Sheet1!D12 -> 1 CORE X 630 SQ. MM. AL/ARM (XLPE) - 33 KV | E27: =CI27+CK27+CM27 -> 1257565.6 | F27: =ROUNDUP(M40,0) -> 15131 | G27: =E27+F27 -> 1272696.6 | H27: 0.18 | I27: =G27*H27 -> 229085.39 | J27: =G27+I27 -> 1501782 | K27: =Sheet1!CS12 -> 115 | L27: =Sheet1!CT12 -> KMS | M27: =J27*K27 -> 1.7270493e+08 | N27: =+IFERROR(VLOOKUP($N$17,Sheet1!J12:L12,3,0),0) -> 1701 | O27: =+IFERROR(VLOOKUP($O$17,Sheet1!J12:L12,3,0),0) -> 0 | P27: =+IFERROR(VLOOKUP($P$17,Sheet1!J12:M12,3,0),0) -> 0 | Q27: =+IFERROR(VLOOKUP($Q$17,Sheet1!J12:M12,3,0),0) -> 0 | R27: =+IFERROR(VLOOKUP($R$17,Sheet1!J12:M12,3,0),0) -> 0 | S27: =+IFERROR(VLOOKUP($S$17,Sheet1!N12:Q12,3,0),0) -> 0 | T27: =+IFERROR(VLOOKUP($T$17,Sheet1!N12:Q12,3,0),0) -> 0 | U27: =+IFERROR(VLOOKUP($U$17,Sheet1!F12:I12,3,0),0) -> 0 | V27: =+IFERROR(VLOOKUP($V$17,Sheet1!F12:I12,3,0),0) -> 0 | W27: =+IFERROR(VLOOKUP($W$17,Sheet1!F12:I12,3,0),0) -> 0 | X27: =+IFERROR(VLOOKUP($X$17,Sheet1!F12:I12,3,0),0) -> 0 | Y27: 79 | Z27: =+IFERROR(VLOOKUP($Z$17,Sheet1!F12:I12,3,0),0) -> 0 | AA27: =+IFERROR(VLOOKUP($AA$17,Sheet1!F12:I12,3,0),0) -> 0 | AB27: =+IFERROR(VLOOKUP($AB$17,Sheet1!F12:I12,3,0),0) -> 0 | AC27: 218 | AD27: =+IFERROR(VLOOKUP($AD$17,Sheet1!R12:U12,2,0),0) -> 0 | AE27: 1055 | AF27: =+IFERROR(VLOOKUP($AF$17,Sheet1!V12:Y12,3,0),0) -> 0 | AG27: =+IFERROR(VLOOKUP($AG$17,Sheet1!V12:Y12,3,0),0) -> 0 | AH27: =+IFERROR(VLOOKUP($AH$17,Sheet1!V12:Y12,3,0),0) -> 0 | AI27: =+IFERROR(VLOOKUP($AI$17,Sheet1!V12:Y12,3,0),0) -> 0 | AJ27: =+IFERROR(VLOOKUP($AJ$17,Sheet1!V12:Y12,3,0),0) -> 0 | AK27: 18 | AL27: =+IFERROR(VLOOKUP($AL$17,Sheet1!AD12:AG12,3,0),0) -> 0 | AM27: =+IFERROR(VLOOKUP($AM$17,Sheet1!AD12:AG12,3,0),0) -> 0 | AN27: =+IFERROR(VLOOKUP($AN$17,Sheet1!AD12:AG12,3,0),0) -> 0 | AO27: =+IFERROR(VLOOKUP($AO$17,Sheet1!AD12:AG12,3,0),0) -> 0 | AP27: =+IFERROR(VLOOKUP($AP$17,Sheet1!AD12:AG12,3,0),0) -> 0 | AQ27: 200 | AR27: =+IFERROR(VLOOKUP($AR$17,Sheet1!AD12:AG12,3,0),0) -> 0 | AS27: =+IFERROR(VLOOKUP($AS$17,Sheet1!AH12:AK12,3,0),0) -> 0 | AT27: =+IFERROR(VLOOKUP($AT$17,Sheet1!AH12:AK12,3,0),0) -> 0 | AU27: =+IFERROR(VLOOKUP($AU$17,Sheet1!AH12:AK12,3,0),0) -> 0 | AV27: 828 | AW27: =+IFERROR(VLOOKUP($AW$17,Sheet1!AH12:AK12,3,0),0) -> 0 | AX27: =+IFERROR(VLOOKUP($AX$17,Sheet1!AH12:AK12,3,0),0) -> 0 | AY27: =+IFERROR(VLOOKUP($AY$17,Sheet1!AH12:AK12,3,0),0) -> 0 | AZ27: =+IFERROR(VLOOKUP($AZ$17,Sheet1!AH12:AK12,3,0),0) -> 0 | BA27: =+IFERROR(VLOOKUP($BA$17,Sheet1!AH12:AK12,3,0),0) -> 0 | BB27: =+IFERROR(VLOOKUP($BB$17,Sheet1!AH12:AK12,3,0),0) -> 0 | BC27: =+IFERROR(VLOOKUP($BC$17,Sheet1!AL12:AO12,3,0),0) -> 0 | BD27: =+IFERROR(VLOOKUP($BD$17,Sheet1!AL12:AO12,3,0),0) -> 0 | BE27: =+IFERROR(VLOOKUP($BE$17,Sheet1!AL12:AO12,3,0),0) -> 0 | BF27: 760 | BG27: =+IFERROR(VLOOKUP($BG$17,Sheet1!AL12:AO12,3,0),0) -> 0 | BH27: =+IFERROR(VLOOKUP($BH$17,Sheet1!AL12:AO12,3,0),0) -> 0 | BI27: =+IFERROR(VLOOKUP($BI$17,Sheet1!AL12:AO12,3,0),0) -> 0 | BJ27: =+IFERROR(VLOOKUP($BJ$17,Sheet1!AL12:AO12,3,0),0) -> 0 | BK27: =+IFERROR(VLOOKUP($BK$17,Sheet1!AL12:AO12,3,0),0) -> 0 | BL27: =+IFERROR(VLOOKUP($BL$17,Sheet1!AL12:AO12,3,0),0) -> 0 | BM27: =+IFERROR(VLOOKUP($BM$17,Sheet1!AP12:AS12,3,0),0) -> 0 | BN27: =+IFERROR(VLOOKUP($BN$17,Sheet1!AT12:AW12,3,0),0) -> 0 | BO27: 26 | BP27: 41 | BQ27: =+IFERROR(VLOOKUP($BQ$17,Sheet1!BF12:BI12,3,0),0) -> 0 | BR27: =+IFERROR(VLOOKUP($BR$17,Sheet1!BJ12:BM12,3,0),0) -> 0 | BS27: =+IFERROR(VLOOKUP($BS$17,Sheet1!BN12:BQ12,3,0),0) -> 0 | BT27: 42 | BU27: =+IFERROR(VLOOKUP($BU$17,Sheet1!BV12:BY12,3,0),0) -> 0 | BV27: =Sheet1!E12 -> STEEL | BW27: =SUM(N27:BT27) -> 4968 | BX27: SP0400118 | BY27: CORRUGATED DISPATCH STEEL DRUM 1700 X 1000 X 1200 | BZ27: =Sheet1!CX12 -> 500 | CA27: 40000 | CB27: =SUMPRODUCT($N$18:$BU$18,N27:BU27)+CA27 -> 984627 | CC27: =Sheet1!CB12 -> 0 | CD27: =CB27*CC27 -> 0 | CE27: 0.24 | CF27: =CB27*CE27 -> 236310.48 | CG27: 0 | CH27: =CB27*CG27 -> 0 | CI27: =CB27+CD27+CF27+CH27 -> 1220937.5 | CJ27: 0.02 | CK27: =CI27*CJ27 -> 24418.75 | CL27: 0.01 | CM27: =CI27*CL27 -> 12209.375
A28: =Sheet1!A9 -> ENQ-12172-22-23 | B28: 45329 | C28: =Sheet1!C9 -> FA1300018 | D28: =Sheet1!D9 -> 1 CORE X 400 SQ. MM. AL/ARM (XLPE) - 33 KV | E28: =CI28+CK28+CM28 -> 960564.24 | F28: =ROUNDUP(M41,0) -> 19890 | G28: =E28+F28 -> 980454.24 | H28: 0.18 | I28: =G28*H28 -> 176481.76 | J28: =G28+I28 -> 1156936 | K28: =Sheet1!CS9 -> 9.05 | L28: =Sheet1!CT9 -> KMS | M28: =J28*K28 -> 10470271 | N28: 1081 | O28: =+IFERROR(VLOOKUP($O$17,Sheet1!J9:L9,3,0),0) -> 0 | P28: =+IFERROR(VLOOKUP($P$17,Sheet1!J9:M9,3,0),0) -> 0 | Q28: =+IFERROR(VLOOKUP($Q$17,Sheet1!J9:M9,3,0),0) -> 0 | R28: =+IFERROR(VLOOKUP($R$17,Sheet1!J9:M9,3,0),0) -> 0 | S28: =+IFERROR(VLOOKUP($S$17,Sheet1!N9:Q9,3,0),0) -> 0 | T28: =+IFERROR(VLOOKUP($T$17,Sheet1!N9:Q9,3,0),0) -> 0 | U28: =+IFERROR(VLOOKUP($U$17,Sheet1!F9:I9,3,0),0) -> 0 | V28: =+IFERROR(VLOOKUP($V$17,Sheet1!F9:I9,3,0),0) -> 0 | W28: =+IFERROR(VLOOKUP($W$17,Sheet1!F9:I9,3,0),0) -> 0 | X28: =+IFERROR(VLOOKUP($X$17,Sheet1!F9:I9,3,0),0) -> 0 | Y28: 70 | Z28: =+IFERROR(VLOOKUP($Z$17,Sheet1!F9:I9,3,0),0) -> 0 | AA28: =+IFERROR(VLOOKUP($AA$17,Sheet1!F9:I9,3,0),0) -> 0 | AB28: =+IFERROR(VLOOKUP($AB$17,Sheet1!F9:I9,3,0),0) -> 0 | AC28: 171 | AD28: =+IFERROR(VLOOKUP($AD$17,Sheet1!R9:U9,2,0),0) -> 0 | AE28: 885 | AF28: =+IFERROR(VLOOKUP($AF$17,Sheet1!V9:Y9,3,0),0) -> 0 | AG28: =+IFERROR(VLOOKUP($AG$17,Sheet1!V9:Y9,3,0),0) -> 0 | AH28: =+IFERROR(VLOOKUP($AH$17,Sheet1!V9:Y9,3,0),0) -> 0 | AI28: =+IFERROR(VLOOKUP($AI$17,Sheet1!V9:Y9,3,0),0) -> 0 | AJ28: =+IFERROR(VLOOKUP($AJ$17,Sheet1!V9:Y9,3,0),0) -> 0 | AK28: 16 | AL28: =+IFERROR(VLOOKUP($AL$17,Sheet1!AD9:AG9,3,0),0) -> 0 | AM28: =+IFERROR(VLOOKUP($AM$17,Sheet1!AD9:AG9,3,0),0) -> 0 | AN28: =+IFERROR(VLOOKUP($AN$17,Sheet1!AD9:AG9,3,0),0) -> 0 | AO28: =+IFERROR(VLOOKUP($AO$17,Sheet1!AD9:AG9,3,0),0) -> 0 | AP28: =+IFERROR(VLOOKUP($AP$17,Sheet1!AD9:AG9,3,0),0) -> 0 | AQ28: 151 | AR28: =+IFERROR(VLOOKUP($AR$17,Sheet1!AD9:AG9,3,0),0) -> 0 | AS28: =+IFERROR(VLOOKUP($AS$17,Sheet1!AH9:AK9,3,0),0) -> 0 | AT28: =+IFERROR(VLOOKUP($AT$17,Sheet1!AH9:AK9,3,0),0) -> 0 | AU28: =+IFERROR(VLOOKUP($AU$17,Sheet1!AH9:AK9,3,0),0) -> 0 | AV28: 731 | AW28: =+IFERROR(VLOOKUP($AW$17,Sheet1!AH9:AK9,3,0),0) -> 0 | AX28: =+IFERROR(VLOOKUP($AX$17,Sheet1!AH9:AK9,3,0),0) -> 0 | AY28: =+IFERROR(VLOOKUP($AY$17,Sheet1!AH9:AK9,3,0),0) -> 0 | AZ28: =+IFERROR(VLOOKUP($AZ$17,Sheet1!AH9:AK9,3,0),0) -> 0 | BA28: =+IFERROR(VLOOKUP($BA$17,Sheet1!AH9:AK9,3,0),0) -> 0 | BB28: =+IFERROR(VLOOKUP($BB$17,Sheet1!AH9:AK9,3,0),0) -> 0 | BC28: =+IFERROR(VLOOKUP($BC$17,Sheet1!AL9:AO9,3,0),0) -> 0 | BD28: =+IFERROR(VLOOKUP($BD$17,Sheet1!AL9:AO9,3,0),0) -> 0 | BE28: =+IFERROR(VLOOKUP($BE$17,Sheet1!AL9:AO9,3,0),0) -> 0 | BF28: 580 | BG28: =+IFERROR(VLOOKUP($BG$17,Sheet1!AL9:AO9,3,0),0) -> 0 | BH28: =+IFERROR(VLOOKUP($BH$17,Sheet1!AL9:AO9,3,0),0) -> 0 | BI28: =+IFERROR(VLOOKUP($BI$17,Sheet1!AL9:AO9,3,0),0) -> 0 | BJ28: =+IFERROR(VLOOKUP($BJ$17,Sheet1!AL9:AO9,3,0),0) -> 0 | BK28: =+IFERROR(VLOOKUP($BK$17,Sheet1!AL9:AO9,3,0),0) -> 0 | BL28: =+IFERROR(VLOOKUP($BL$17,Sheet1!AL9:AO9,3,0),0) -> 0 | BM28: =+IFERROR(VLOOKUP($BM$17,Sheet1!AP9:AS9,3,0),0) -> 0 | BN28: =+IFERROR(VLOOKUP($BN$17,Sheet1!AT9:AW9,3,0),0) -> 0 | BO28: 19 | BP28: 35 | BQ28: =+IFERROR(VLOOKUP($BQ$17,Sheet1!BF9:BI9,3,0),0) -> 0 | BR28: =+IFERROR(VLOOKUP($BR$17,Sheet1!BJ9:BM9,3,0),0) -> 0 | BS28: =+IFERROR(VLOOKUP($BS$17,Sheet1!BN9:BQ9,3,0),0) -> 0 | BT28: 36 | BU28: =+IFERROR(VLOOKUP($BU$17,Sheet1!BV9:BY9,3,0),0) -> 0 | BV28: =Sheet1!E9 -> STEEL | BW28: =SUM(N28:BT28) -> 3775 | BX28: SP0400126 | BY28: CORRUGATED DISPATCH STEEL DRUM 1900 X 830 X 915 MM | BZ28: =Sheet1!CX9 -> 500 | CA28: 32000 | CB28: =SUMPRODUCT($N$18:$BU$18,N28:BU28)+CA28 -> 752086 | CC28: =Sheet1!CB9 -> 0 | CD28: =CB28*CC28 -> 0 | CE28: 0.24 | CF28: =CB28*CE28 -> 180500.64 | CG28: 0 | CH28: =CB28*CG28 -> 0 | CI28: =CB28+CD28+CF28+CH28 -> 932586.64 | CJ28: 0.02 | CK28: =CI28*CJ28 -> 18651.733 | CL28: 0.01 | CM28: =CI28*CL28 -> 9325.8664
A29: =Sheet1!A7 -> ENQ-12172-22-23 | B29: 45329 | C29: =Sheet1!C7 -> FA1300019 | D29: =Sheet1!D7 -> 1 CORE X 300 SQ. MM. AL/ARM (XLPE) - 33 KV | E29: =CI29+CK29+CM29 -> 839942.92 | F29: =ROUNDUP(M42,0) -> 20000 | G29: =E29+F29 -> 859942.92 | H29: 0.18 | I29: =G29*H29 -> 154789.73 | J29: =G29+I29 -> 1014732.6 | K29: =Sheet1!CS7 -> 3 | L29: =Sheet1!CT7 -> KMS | M29: =J29*K29 -> 3044197.9 | N29: =+IFERROR(VLOOKUP($N$17,Sheet1!J7:L7,3,0),0) -> 810 | O29: =+IFERROR(VLOOKUP($O$17,Sheet1!J7:L7,3,0),0) -> 0 | P29: =+IFERROR(VLOOKUP($P$17,Sheet1!J7:M7,3,0),0) -> 0 | Q29: =+IFERROR(VLOOKUP($Q$17,Sheet1!J7:M7,3,0),0) -> 0 | R29: =+IFERROR(VLOOKUP($R$17,Sheet1!J7:M7,3,0),0) -> 0 | S29: =+IFERROR(VLOOKUP($S$17,Sheet1!N7:Q7,3,0),0) -> 0 | T29: =+IFERROR(VLOOKUP($T$17,Sheet1!N7:Q7,3,0),0) -> 0 | U29: =+IFERROR(VLOOKUP($U$17,Sheet1!F7:I7,3,0),0) -> 0 | V29: =+IFERROR(VLOOKUP($V$17,Sheet1!F7:I7,3,0),0) -> 0 | W29: =+IFERROR(VLOOKUP($W$17,Sheet1!F7:I7,3,0),0) -> 0 | X29: =+IFERROR(VLOOKUP($X$17,Sheet1!F7:I7,3,0),0) -> 0 | Y29: 65 | Z29: =+IFERROR(VLOOKUP($Z$17,Sheet1!F7:I7,3,0),0) -> 0 | AA29: =+IFERROR(VLOOKUP($AA$17,Sheet1!F7:I7,3,0),0) -> 0 | AB29: =+IFERROR(VLOOKUP($AB$17,Sheet1!F7:I7,3,0),0) -> 0 | AC29: 164 | AD29: =+IFERROR(VLOOKUP($AD$17,Sheet1!R7:U7,2,0),0) -> 0 | AE29: 808 | AF29: =+IFERROR(VLOOKUP($AF$17,Sheet1!V7:Y7,3,0),0) -> 0 | AG29: =+IFERROR(VLOOKUP($AG$17,Sheet1!V7:Y7,3,0),0) -> 0 | AH29: =+IFERROR(VLOOKUP($AH$17,Sheet1!V7:Y7,3,0),0) -> 0 | AI29: =+IFERROR(VLOOKUP($AI$17,Sheet1!V7:Y7,3,0),0) -> 0 | AJ29: =+IFERROR(VLOOKUP($AJ$17,Sheet1!V7:Y7,3,0),0) -> 0 | AK29: 12 | AL29: =+IFERROR(VLOOKUP($AL$17,Sheet1!AD7:AG7,3,0),0) -> 0 | AM29: =+IFERROR(VLOOKUP($AM$17,Sheet1!AD7:AG7,3,0),0) -> 0 | AN29: =+IFERROR(VLOOKUP($AN$17,Sheet1!AD7:AG7,3,0),0) -> 0 | AO29: =+IFERROR(VLOOKUP($AO$17,Sheet1!AD7:AG7,3,0),0) -> 0 | AP29: =+IFERROR(VLOOKUP($AP$17,Sheet1!AD7:AG7,3,0),0) -> 0 | AQ29: 144 | AR29: =+IFERROR(VLOOKUP($AR$17,Sheet1!AD7:AG7,3,0),0) -> 0 | AS29: =+IFERROR(VLOOKUP($AS$17,Sheet1!AH7:AK7,3,0),0) -> 0 | AT29: =+IFERROR(VLOOKUP($AT$17,Sheet1!AH7:AK7,3,0),0) -> 0 | AU29: =+IFERROR(VLOOKUP($AU$17,Sheet1!AH7:AK7,3,0),0) -> 0 | AV29: 676 | AW29: =+IFERROR(VLOOKUP($AW$17,Sheet1!AH7:AK7,3,0),0) -> 0 | AX29: =+IFERROR(VLOOKUP($AX$17,Sheet1!AH7:AK7,3,0),0) -> 0 | AY29: =+IFERROR(VLOOKUP($AY$17,Sheet1!AH7:AK7,3,0),0) -> 0 | AZ29: =+IFERROR(VLOOKUP($AZ$17,Sheet1!AH7:AK7,3,0),0) -> 0 | BA29: =+IFERROR(VLOOKUP($BA$17,Sheet1!AH7:AK7,3,0),0) -> 0 | BB29: =+IFERROR(VLOOKUP($BB$17,Sheet1!AH7:AK7,3,0),0) -> 0 | BC29: =+IFERROR(VLOOKUP($BC$17,Sheet1!AL7:AO7,3,0),0) -> 0 | BD29: =+IFERROR(VLOOKUP($BD$17,Sheet1!AL7:AO7,3,0),0) -> 0 | BE29: =+IFERROR(VLOOKUP($BE$17,Sheet1!AL7:AO7,3,0),0) -> 0 | BF29: 556 | BG29: =+IFERROR(VLOOKUP($BG$17,Sheet1!AL7:AO7,3,0),0) -> 0 | BH29: =+IFERROR(VLOOKUP($BH$17,Sheet1!AL7:AO7,3,0),0) -> 0 | BI29: =+IFERROR(VLOOKUP($BI$17,Sheet1!AL7:AO7,3,0),0) -> 0 | BJ29: =+IFERROR(VLOOKUP($BJ$17,Sheet1!AL7:AO7,3,0),0) -> 0 | BK29: =+IFERROR(VLOOKUP($BK$17,Sheet1!AL7:AO7,3,0),0) -> 0 | BL29: =+IFERROR(VLOOKUP($BL$17,Sheet1!AL7:AO7,3,0),0) -> 0 | BM29: =+IFERROR(VLOOKUP($BM$17,Sheet1!AP7:AS7,3,0),0) -> 0 | BN29: =+IFERROR(VLOOKUP($BN$17,Sheet1!AT7:AW7,3,0),0) -> 0 | BO29: 13 | BP29: 32 | BQ29: =+IFERROR(VLOOKUP($BQ$17,Sheet1!BF7:BI7,3,0),0) -> 0 | BR29: =+IFERROR(VLOOKUP($BR$17,Sheet1!BJ7:BM7,3,0),0) -> 0 | BS29: =+IFERROR(VLOOKUP($BS$17,Sheet1!BN7:BQ7,3,0),0) -> 0 | BT29: 35 | BU29: =+IFERROR(VLOOKUP($BU$17,Sheet1!BV7:BY7,3,0),0) -> 0 | BV29: =Sheet1!E7 -> STEEL | BW29: =SUM(N29:BT29) -> 3315 | BX29: SP0400126 | BY29: CORRUGATED DISPATCH STEEL DRUM 1900 X 830 X 915 MM | BZ29: =Sheet1!CX7 -> 500 | CA29: 32000 | CB29: =SUMPRODUCT($N$18:$BU$18,N29:BU29)+CA29 -> 657644 | CC29: =Sheet1!CB7 -> 0 | CD29: =CB29*CC29 -> 0 | CE29: 0.24 | CF29: =CB29*CE29 -> 157834.56 | CG29: 0 | CH29: =CB29*CG29 -> 0 | CI29: =CB29+CD29+CF29+CH29 -> 815478.56 | CJ29: 0.02 | CK29: =CI29*CJ29 -> 16309.571 | CL29: 0.01 | CM29: =CI29*CL29 -> 8154.7856
E31: Order Quantity | F31: Stnd Length | G31: Truck type | H31: Fare of one truck | I31: No of Drum in one truck | J31: Total length in one Truck | K31: No of Truck | L31: Total Freight | M31: Freight per KM
C32: =C19 -> FA1300080 | D32: =D19 -> 3 CORE X 400 SQ. MM AL/ARM - WIRE (XLPE) - 33 KV | E32: =K19 -> 77 | F32: =BZ19/1000 -> 0.25 | G32: 28 MT TRAILER | H32: 60000 | I32: 5 | J32: =F32*I32 -> 1.25 | K32: =ROUNDUP((E32/J32),0) -> 62 | L32: =M32*E32 -> 3720000 | M32: =(H32*K32)/E32 -> 48311.688
C33: =C20 -> FA1300081 | D33: =D20 -> 3 CORE X 300 SQ. MM. AL/ARM - WIRE (XLPE) - 33 KV | E33: =K20 -> 16.92 | F33: =BZ20/1000 -> 0.25 | G33: 28 MT TRAILER | H33: 60000 | I33: 5 | J33: =F33*I33 -> 1.25 | K33: =ROUNDUP((E33/J33),0) -> 14 | L33: =M33*E33 -> 840000 | M33: =(H33*K33)/E33 -> 49645.39
C34: =C21 -> FA1300201 | D34: =D21 -> 3 CORE X 240 SQ. MM. AL/ARM - WIRE (XLPE) - 33 KV | E34: =K21 -> 1 | F34: =BZ21/1000 -> 0.25 | G34: 28 MT TRAILER | H34: 60000 | I34: 5 | J34: =F34*I34 -> 1.25 | K34: =ROUNDUP((E34/J34),0) -> 1 | L34: =M34*E34 -> 60000 | M34: =(H34*K34)/E34 -> 60000
C35: =C22 -> FA1300079 | D35: =D22 -> 3 CORE X 185 SQ. MM AL/ARM - WIRE (XLPE) - 33 KV | E35: =K22 -> 1 | F35: =BZ22/1000 -> 0.25 | G35: 28 MT TRAILER | H35: 60000 | I35: 6 | J35: =F35*I35 -> 1.5 | K35: =ROUNDUP((E35/J35),0) -> 1 | L35: =M35*E35 -> 60000 | M35: =(H35*K35)/E35 -> 60000
C36: =C23 -> FA1300200 | D36: =D23 -> 3 CORE X 95 SQ. MM. AL/ARM WIRE (XLPE) - 33 KV | E36: =K23 -> 3 | F36: =BZ23/1000 -> 0.25 | G36: 28 MT TRAILER | H36: 60000 | I36: 8 | J36: =F36*I36 -> 2 | K36: =ROUNDUP((E36/J36),0) -> 2 | L36: =M36*E36 -> 120000 | M36: =(H36*K36)/E36 -> 40000
C37: =C24 -> FA1300120 | D37: =D24 -> 3 CORE X 70 SQ. MM. AL/ARM - WIRE (XLPE) - 33 KV | E37: =K24 -> 1 | F37: =BZ24/1000 -> 0.25 | G37: 28 MT TRAILER | H37: 60000 | I37: 8 | J37: =F37*I37 -> 2 | K37: =ROUNDUP((E37/J37),0) -> 1 | L37: =M37*E37 -> 60000 | M37: =(H37*K37)/E37 -> 60000
C38: =C25 -> FA1300022 | D38: =D25 -> 3 CORE X 50 SQ. MM. AL/ARD - WIRE (XLPE) - 33 KV (E) | E38: =K25 -> 1 | F38: =BZ25/1000 -> 0.25 | G38: 28 MT TRAILER | H38: 60000 | I38: 10 | J38: =F38*I38 -> 2.5 | K38: =ROUNDUP((E38/J38),0) -> 1 | L38: =M38*E38 -> 60000 | M38: =(H38*K38)/E38 -> 60000
C39: =C26 -> FA1300297 | D39: =D26 -> 3 CORE X 35 SQ. MM. AL/ARM - WIRE (XLPE) - 33 KV (E) | E39: =K26 -> 1 | F39: =BZ26/1000 -> 0.25 | G39: 28 MT TRAILER | H39: 60000 | I39: 10 | J39: =F39*I39 -> 2.5 | K39: =ROUNDUP((E39/J39),0) -> 1 | L39: =M39*E39 -> 60000 | M39: =(H39*K39)/E39 -> 60000
C40: =C27 -> FA1300027 | D40: =D27 -> 1 CORE X 630 SQ. MM. AL/ARM (XLPE) - 33 KV | E40: =K27 -> 115 | F40: =BZ27/1000 -> 0.5 | G40: 28 MT TRAILER | H40: 60000 | I40: 8 | J40: =F40*I40 -> 4 | K40: =ROUNDUP((E40/J40),0) -> 29 | L40: =M40*E40 -> 1740000 | M40: =(H40*K40)/E40 -> 15130.435
C41: =C28 -> FA1300018 | D41: =D28 -> 1 CORE X 400 SQ. MM. AL/ARM (XLPE) - 33 KV | E41: =K28 -> 9.05 | F41: =BZ28/1000 -> 0.5 | G41: 28 MT TRAILER | H41: 60000 | I41: 8 | J41: =F41*I41 -> 4 | K41: =ROUNDUP((E41/J41),0) -> 3 | L41: =M41*E41 -> 180000 | M41: =(H41*K41)/E41 -> 19889.503
C42: =C29 -> FA1300019 | D42: =D29 -> 1 CORE X 300 SQ. MM. AL/ARM (XLPE) - 33 KV | E42: =K29 -> 3 | F42: =BZ29/1000 -> 0.5 | G42: 28 MT TRAILER | H42: 60000 | I42: 8 | J42: =F42*I42 -> 4 | K42: =ROUNDUP((E42/J42),0) -> 1 | L42: =M42*E42 -> 60000 | M42: =(H42*K42)/E42 -> 20000
I43: sombhu sir confirmed overphone
A46: DOCKET NO. | B46: Base Date | C46: ITEM CODE | D46: PROPOSE ERP ITEM NAME | E46: EX-WORKS (PER MTR) | F46: FREIGHT PER MTR | G46: PRICE INCLUDING FREIGHT (PER MTR) | H46: GST % | I46: GST VALUE | J46: PRICE INCLUDING GST & FREIGHT (PER MTR) | K46: QTY | L46: Unit | M46: TOTAL PRICE OF FULL QTY (INCLUDING FRIGHT & GST)
A48: =A19 -> ENQ-12172-22-23 | B48: =B19 -> 45329 | C48: =C19 -> FA1300080 | D48: =D19 -> 3 CORE X 400 SQ. MM AL/ARM - WIRE (XLPE) - 33 KV | E48: =ROUNDUP(E19/1000,2) -> 3395.02 | F48: =ROUNDUP(F19/1000,2) -> 48.32 | G48: =E48+F48 -> 3443.34 | H48: 0.18 | I48: =ROUNDUP(G48*H48,2) -> 619.81 | J48: =ROUNDUP(G48+I48,2) -> 4063.15 | K48: =K19*1000 -> 77000 | L48: MTR | M48: =J48*K48 -> 312862550
A49: =A20 -> ENQ-12172-22-23 | B49: =B20 -> 45329 | C49: =C20 -> FA1300081 | D49: =D20 -> 3 CORE X 300 SQ. MM. AL/ARM - WIRE (XLPE) - 33 KV | E49: =ROUNDUP(E20/1000,2) -> 2957.98 | F49: =ROUNDUP(F20/1000,2) -> 49.65 | G49: =E49+F49 -> 3007.63 | H49: 0.18 | I49: =ROUNDUP(G49*H49,2) -> 541.38 | J49: =ROUNDUP(G49+I49,2) -> 3549.01 | K49: =K20*1000 -> 16920 | L49: MTR | M49: =J49*K49 -> 60049249
A50: =A21 -> ENQ-12172-22-23 | B50: =B21 -> 45329 | C50: =C21 -> FA1300201 | D50: =D21 -> 3 CORE X 240 SQ. MM. AL/ARM - WIRE (XLPE) - 33 KV | E50: =ROUNDUP(E21/1000,2) -> 2674.17 | F50: =ROUNDUP(F21/1000,2) -> 60 | G50: =E50+F50 -> 2734.17 | H50: 0.18 | I50: =ROUNDUP(G50*H50,2) -> 492.16 | J50: =ROUNDUP(G50+I50,2) -> 3226.33 | K50: =K21*1000 -> 1000 | L50: MTR | M50: =J50*K50 -> 3226330
A51: =A22 -> ENQ-12172-22-23 | B51: =B22 -> 45329 | C51: =C22 -> FA1300079 | D51: =D22 -> 3 CORE X 185 SQ. MM AL/ARM - WIRE (XLPE) - 33 KV | E51: =ROUNDUP(E22/1000,2) -> 2463.59 | F51: =ROUNDUP(F22/1000,2) -> 60 | G51: =E51+F51 -> 2523.59 | H51: 0.18 | I51: =ROUNDUP(G51*H51,2) -> 454.25 | J51: =ROUNDUP(G51+I51,2) -> 2977.84 | K51: =K22*1000 -> 1000 | L51: MTR | M51: =J51*K51 -> 2977840
A52: =A23 -> ENQ-12172-22-23 | B52: =B23 -> 45329 | C52: =C23 -> FA1300200 | D52: =D23 -> 3 CORE X 95 SQ. MM. AL/ARM WIRE (XLPE) - 33 KV | E52: =ROUNDUP(E23/1000,2) -> 1798.34 | F52: =ROUNDUP(F23/1000,2) -> 40 | G52: =E52+F52 -> 1838.34 | H52: 0.18 | I52: =ROUNDUP(G52*H52,2) -> 330.91 | J52: =ROUNDUP(G52+I52,2) -> 2169.25 | K52: =K23*1000 -> 3000 | L52: MTR | M52: =J52*K52 -> 6507750
A53: =A24 -> ENQ-12172-22-23 | B53: =B24 -> 45329 | C53: =C24 -> FA1300120 | D53: =D24 -> 3 CORE X 70 SQ. MM. AL/ARM - WIRE (XLPE) - 33 KV | E53: =ROUNDUP(E24/1000,2) -> 1651.72 | F53: =ROUNDUP(F24/1000,2) -> 60 | G53: =E53+F53 -> 1711.72 | H53: 0.18 | I53: =ROUNDUP(G53*H53,2) -> 308.11 | J53: =ROUNDUP(G53+I53,2) -> 2019.83 | K53: =K24*1000 -> 1000 | L53: MTR | M53: =J53*K53 -> 2019830
A54: =A25 -> ENQ-12172-22-23 | B54: =B25 -> 45329 | C54: =C25 -> FA1300022 | D54: =D25 -> 3 CORE X 50 SQ. MM. AL/ARD - WIRE (XLPE) - 33 KV (E) | E54: =ROUNDUP(E25/1000,2) -> 1454.24 | F54: =ROUNDUP(F25/1000,2) -> 60 | G54: =E54+F54 -> 1514.24 | H54: 0.18 | I54: =ROUNDUP(G54*H54,2) -> 272.57 | J54: =ROUNDUP(G54+I54,2) -> 1786.81 | K54: =K25*1000 -> 1000 | L54: MTR | M54: =J54*K54 -> 1786810
A55: =A26 -> ENQ-12172-22-23 | B55: =B26 -> 45329 | C55: =C26 -> FA1300297 | D55: =D26 -> 3 CORE X 35 SQ. MM. AL/ARM - WIRE (XLPE) - 33 KV (E) | E55: =ROUNDUP(E26/1000,2) -> 1454.24 | F55: =ROUNDUP(F26/1000,2) -> 60 | G55: =E55+F55 -> 1514.24 | H55: 0.18 | I55: =ROUNDUP(G55*H55,2) -> 272.57 | J55: =ROUNDUP(G55+I55,2) -> 1786.81 | K55: =K26*1000 -> 1000 | L55: MTR | M55: =J55*K55 -> 1786810
A56: =A27 -> ENQ-12172-22-23 | B56: =B27 -> 45329 | C56: =C27 -> FA1300027 | D56: =D27 -> 1 CORE X 630 SQ. MM. AL/ARM (XLPE) - 33 KV | E56: =ROUNDUP(E27/1000,2) -> 1257.57 | F56: =ROUNDUP(F27/1000,2) -> 15.14 | G56: =E56+F56 -> 1272.71 | H56: 0.18 | I56: =ROUNDUP(G56*H56,2) -> 229.09 | J56: =ROUNDUP(G56+I56,2) -> 1501.8 | K56: =K27*1000 -> 115000 | L56: MTR | M56: =J56*K56 -> 172707000
A57: =A28 -> ENQ-12172-22-23 | B57: =B28 -> 45329 | C57: =C28 -> FA1300018 | D57: =D28 -> 1 CORE X 400 SQ. MM. AL/ARM (XLPE) - 33 KV | E57: =ROUNDUP(E28/1000,2) -> 960.57 | F57: =ROUNDUP(F28/1000,2) -> 19.89 | G57: =E57+F57 -> 980.46 | H57: 0.18 | I57: =ROUNDUP(G57*H57,2) -> 176.49 | J57: =ROUNDUP(G57+I57,2) -> 1156.95 | K57: =K28*1000 -> 9050 | L57: MTR | M57: =J57*K57 -> 10470398
A58: =A29 -> ENQ-12172-22-23 | B58: =B29 -> 45329 | C58: =C29 -> FA1300019 | D58: =D29 -> 1 CORE X 300 SQ. MM. AL/ARM (XLPE) - 33 KV | E58: =ROUNDUP(E29/1000,2) -> 839.95 | F58: =ROUNDUP(F29/1000,2) -> 20 | G58: =E58+F58 -> 859.95 | H58: 0.18 | I58: =ROUNDUP(G58*H58,2) -> 154.8 | J58: =ROUNDUP(G58+I58,2) -> 1014.75 | K58: =K29*1000 -> 3000 | L58: MTR | M58: =J58*K58 -> 3044250
