Workbook

Sheet Sheet1
A1: DOCKET NO. | B1: Base Date | C1: ITEM CODE | D1: PROPOSE ERP ITEM NAME | E1: PROPOSE DRUM TYPE | F1: Insulation Screening (Metallic) | G1: RM RATE (Insulation Screening (Metallic)) | H1: Weight (Insulation Screening (Metallic)) | I1: COST(Insulation Screening (Metallic)) | J1: Conductor | K1: RM RATE(Conductor) | L1: WEIGHT(Conductor) | M1: COST(Conductor) | N1: AL ALLOY | O1: RM RATE(Alu Alloy) | P1: WEIGHT(Alu Alloy) | Q1: COST(Alu Alloy) | R1: Insulation Screening (Non-Metallic) | S1: RM RATE(Insulation Screening (Non-Metallic)) | T1: WEIGHT(Insulation Screening (Non-Metallic)) | U1: COST(Insulation Screening (Non-Metallic)) | V1: Insulation | W1: RM RATE(Insulation) | X1: WEIGHT(Insulation) | Y1: COST(Insulation) | Z1: POLY TAPE | AA1: RM RATE (Poly Tape) | AB1: WEIGHT (Poly Tape) | AC1: COST(Poly Tape) | AD1: Inner Sheath | AE1: RM RATE(Inner Sheath) | AF1: WEIGHT(Inner Sheath) | AG1: COST(Inner Sheath) | AH1: Armouring | AI1: RM RATE(Armouring) | AJ1: WEIGHT(Armouring) | AK1: COST(Armouring) | AL1: Outer Sheath | AM1: RM RATE(Outer Sheath) | AN1: WEIGHT(Outer Sheath) | AO1: COST(Outer Sheath) | AP1: FILLER | AQ1: RM RATE(Filler) | AR1: WEIGHT(Filler) | AS1: COST(Filler) | AT1: GREASE | AU1: RM RATE(Grease) | AV1: WEIGHT(Grease) | AW1: COST(Grease) | AX1: Water swellable Tape | AY1: RM RATE(Water swellable Tape) | AZ1: WEIGHT(Water swellable Tape) | BA1: COST(Water swellable Tape) | BB1: Semi conducting Water Swellable tape | BC1: RM RATE(Semi conducting Water Swellable tape) | BD1: WEIGHT(Semi conducting Water Swellable tape) | BE1: COST(Semi conducting Water Swellable tape) | BF1: SEMICON TAPE | BG1: RM RATE(SEMICON TAPE) | BH1: WEIGHT(SEMICON TAPE) | BI1: COST(SEMICON TAPE) | BJ1: GLASS FIBER TAPE | BK1: RM RATE(GLASS FIBER TAPE) | BL1: WEIGHT(GLASS FIBER TAPE) | BM1: COST(GLASS FIBER TAPE) | BN1: COPPER WIRE 0.8 MM | BO1: RM RATE(COPPER WIRE 0.8 MM) | BP1: WEIGHT(COPPER WIRE 0.8 MM) | BQ1: COST(COPPER WIRE 0.8 MM) | BR1: RUBBERIZED COTTON TAPE | BS1: RM RATE(RUBBERIZED COTTON TAPE) | BT1: WEIGHT(RUBBERIZED COTTON TAPE) | BU1: COST(RUBBERIZED COTTON TAPE) | BV1: Water Tight Compound | BW1: RM RATE(Water Tight Compound) | BX1: WEIGHT(Water Tight Compound) | BY1: COST(Water Tight Compound) | BZ1: DRUM COST PER KM | CA1: TOTAL RM COST | CB1: FIRM % | CC1: FIRM VALUE | CD1: MFG% | CE1: MFG VALUE | CF1: PROF% | CG1: PROFIT VALUE | CH1: 1ST EX-WORKS | CI1: Intt % | CJ1: INTT VALUE | CK1: insp% | CL1: INSP VALUE | CM1: EX-WORKS (PER KM) | CN1: FREIGHT PER KM | CO1: PRICE INCLUDING FREIGHT (PER KM) | CP1: GST % | CQ1: GST VALUE | CR1: PRICE INCLUDING GST & FREIGHT (PER KM) | CS1: QTY | CT1: Unit | CU1: TOTAL PRICE OF FULL QTY (INCLUDING FRIGHT & GST) | CV1: DRUM CODE | CW1: DRUM SIZE (FxbXtx Ft) | CX1: PARTY STANDARD LENGTH (MTR)
A2: ENQ-11009-22-23 | B2: 45110 | C2: FA1300243 | D2: 1 CORE X 300 SQ. MM. AL/ARM - STRIP (XLPE) - 11 KV | E2: WOOD | F2: Copper Tape - 0.050 mm | G2: 877.6 | J2: Alumimium | K2: 213 | L2: 810 | M2: 172530 | P2: 0 | R2: Extruded Semiconductive | S2: 190 | T2: 124 | U2: 23560 | V2: HT-XLPE | W2: 150 | X2: 267 | Y2: 40050 | AB2: 0 | AD2: PVC Type ST-2 | AE2: 60.1 | AF2: 85 | AG2: 5108.5 | AH2: Aluminium Flat Strip | AI2: 223 | AJ2: 194 | AK2: 43262 | AL2: PVC Type ST-2-PRESSURE EXTRUDED | AM2: 88 | AN2: 290 | AO2: 25520 | AR2: 0 | AV2: 0 | AZ2: 0 | BD2: 0 | BH2: 0 | BL2: 0 | BP2: 0 | BT2: 0 | BX2: 0 | BZ2: 13190.01 | CA2: 323220.51 | CH2: 323220.51 | CM2: 323220.51 | CO2: 323220.51 | CP2: 0.18 | CQ2: 58179.69 | CR2: 381400.2 | CS2: 27 | CT2: KMS | CU2: 10297805 | CV2: MD0100082 | CW2: DRUM - 60 X 30 X 32 X 3

Sheet AUTO CALCULATION SHEET (2)
A2: PUNJAB STATE POWER CORP. LTD.
A4: TENDER SPECIFICATION NO () | B4: 282/SS(D)-344 /Spares
A5: TENDER DESCRIPTION () | B5: FOR MANUFACTURE, TESTING AND SUPPLY OF ARMOURED, ISI MARKED, SINGLE CORE 11KV 300MM2 SIZE STRANDED ALUMINUM CONDUCTOR, XLPE INSULATED, PVC SHEATHED, SCREENED CABLE (54 KMS) IN ACCORDANCE WITH IS: 7098 (PART-2) WITH LATEST AMENDMENTS MANUFACTURED WITH CCV/SIOPLAS TECHNOLOGY
A6: Last Date & Time of Submission () | B6: 04.09.2023/ 11:00AM.
A7: REVERSE AUCTION | B7: In case the no. of bidders are more than 3, the H1 (Highest) bidder shall not be eligible to participate in further process of the tender and his tender shall be rejected.
A8: Price () | B8: Prices should be VARIABLE as per IEEMA without any ceiling with base date as on first working day of the month one month prior to the date of opening of tender. Bids with FIRM rates will be rejected.
A9: Validity () | B9: The offers should be kept valid for at least 120 days from the date of opening of tenders.
A10: Delivery Period () | B10: 1st lot of 50% of the ordered quantity shall be supplied within 2 months from the date of receipt of P.O. and balance 50% quantity in 2nd lot to be supplied within 2 months thereafter. In case the order is divided amongst the firms then the delivery period shall be amended/modified accordingly. However the supply shall be regulated as per requirements of PSPCL.
A11: Payment Terms () | B11: 95% payment of contract value pro-rata for each consignment of operationally complete equipment dispatched after approval of Inspecting Authority/Test Certificate etc. along with taxes & duties and Other Statutory levies as per contract shall be paid within 45 days against receipted challans & submission of requisite documents. The balance 5% Payment shall be kept as performance Guarantee which shall be released after due receipt of Goods Receipt Note from the concerned consignee(s) or expiry of three months from the date of receipted challans & submission of requisite documents, whichever is earlier. In case the due date of payment in terms of payment schedule falls on a holiday including Sunday or holiday is subsequently declared on that date, the payment shall be released on the first working day falling next to the due date. (b)For delay in payments made by PSPCL beyond the stipulated period i.e. 45 days then simple interest @ 10% shall be given to the suppliers for delayed period subject to the condition that the delay in payment is more than seven days after the stipulated period i.e. 45 days. However, all-out efforts shall be made to prioritize the payment to all suppliers those come under MSMED Act-2006.
A12: Standard length () | B12: The cable is required to be supplied in standard lengths of 500 Mtrs.
A13: Packing () | B13: The length shall be supplied in non-returnable standard wooden drums provided with cast iron bushing painted form outside with suitable paint of any colour. The drums should be such that the cable wound on the same is transported without any damage.
A14: Technical Specification
N16: =Sheet1!J1 -> Conductor | S16: AL ALLOY | U16: Insulation Screening (Metallic) | AC16: Insulation Screening (Non-Metallic) | AE16: Insulation | AK16: POLY TAPE | AL16: Inner Sheath | AS16: Armouring | BC16: Outer Sheath | BM16: FILLER | BN16: GREASE | BO16: Water swellable Tape | BP16: Semi conducting Water Swellable tape | BQ16: SEMICON TAPE | BR16: GLASS FIBER TAPE | BS16: COPPER WIRE 0.8 MM | BT16: RUBBERIZED COTTON TAPE | BU16: Water Tight Compound | BZ16: DRUM COST PER KM | CA16: TOTAL RM COST | CB16: EXTRA CONSUMPTION | CC16: EXTRA CONSUMPTION VALUE
A17: DOCKET NO. | B17: =Sheet1!B1 -> Base Date | C17: ITEM CODE | D17: PROPOSE ERP ITEM NAME | E17: EX-WORKS (PER KM) | F17: FREIGHT PER KM | G17: PRICE INCLUDING FREIGHT (PER KM) | H17: GST % | I17: GST VALUE | J17: PRICE INCLUDING GST & FREIGHT (PER KM) | K17: QTY | L17: Unit | M17: TOTAL PRICE OF FULL QTY (INCLUDING FRIGHT & GST) | N17: Alumimium | O17: Alumimium ALLOY | P17: Copper | Q17: Flexible Copper | R17: Galvanized steel wire | S17: Alumimium | T17: Alumimium ALLOY | U17: Coper tape - 0.1 mm | V17: Copper Tape - 0.03 mm | W17: Copper Tape - 0.035 mm | X17: Copper Tape - 0.04 mm | Y17: Copper Tape - 0.045 mm | Z17: Copper Tape - 0.050 mm | AA17: Copper Tape - 0.060 mm | AB17: Copper Tape - 0.075 mm(DOUBLE) | AC17: Extruded semiconductive | AD17: Extruded Semiconductive(Stripable) | AE17: HT-XLPE | AF17: LT-XLPE | AG17: TR XLPE | AH17: Type A PVC | AI17: Type C PVC (HR) | AJ17: XLPE | AK17: POLY TAPE | AL17: FR PVC Type ST-1 | AM17: FR PVC Type ST-2 | AN17: FRLSH PVC Type ST-2 | AO17: PVC Type ST-1 | AP17: PVC Type ST-1-PRESSURE EXTRUDED | AQ17: PVC Type ST-2 | AR17: PVC Type ST-2-PRESSURE EXTRUDED | AS17: ACSR CORE WIRE | AT17: ACSR DOG STEEL WIRE | AU17: Aluminium Flat Strip | AV17: Aluminium Round Wire | AW17: Double Steel Tape | AX17: Galvanised Steel Flat Strip | AY17: Galvanised Steel Flat Strip (Double) | AZ17: Galvanised Steel Flat Strip-B | BA17: Galvanised Steel Round Wire | BB17: Galvanised Steel Round Wire (Double) | BC17: FR PVC Type ST-1 | BD17: FR PVC Type ST-2 | BE17: FRLSH PVC Type ST-1 | BF17: FRLSH PVC Type ST-2 | BG17: PE, ST-3 | BH17: PE, ST-7 | BI17: PVC Type ST-1 | BJ17: PVC Type ST-2 | BK17: PVC Type ST-2-PRESSURE EXTRUDED | BL17: UV & Track Resistant XLPE | BM17: FILLER | BN17: Grease | BO17: Water swellable Tape | BP17: Semi conducting Water Swellable tape | BQ17: SEMICON TAPE | BR17: GLASS FIBER TAPE | BS17: COPPER WIRE 0.8 MM | BT17: RUBBERIZED COTTON TAPE | BU17: Water Tight Compound | BV17: =Sheet1!E1 -> PROPOSE DRUM TYPE | BW17: =Sheet1!CV1 -> DRUM CODE | BX17: =Sheet1!CW1 -> DRUM SIZE (FxbXtx Ft) | BY17: =Sheet1!CX1 -> PARTY STANDARD LENGTH (MTR) | CD17: MFG% | CE17: MFG VALUE | CF17: PROF% | CG17: PROFIT VALUE | CH17: 1ST EX-WORKS | CI17: Intt % | CJ17: INTT VALUE | CK17: insp% | CL17: INSP VALUE
N18: 208 | O18: =+IFERROR(VLOOKUP($O$17,Sheet1!J:L,2,0),0) -> 0 | P18: =+IFERROR(VLOOKUP($P$17,Sheet1!J:M,2,0),0) -> 0 | Q18: =+IFERROR(VLOOKUP($Q$17,Sheet1!J:M,2,0),0) -> 0 | R18: =+IFERROR(VLOOKUP($R$17,Sheet1!J:M,2,0),0) -> 0 | S18: =+IFERROR(VLOOKUP($S$17,Sheet1!N:Q,2,0),0) -> 0 | T18: =+IFERROR(VLOOKUP($T$17,Sheet1!N:O,2,0),0) -> 0 | U18: =+IFERROR(VLOOKUP($U$17,Sheet1!F:I,2,0),0) -> 0 | V18: =+IFERROR(VLOOKUP($V$17,Sheet1!F:I,2,0),0) -> 0 | W18: =+IFERROR(VLOOKUP($W$17,Sheet1!F:I,2,0),0) -> 0 | X18: =+IFERROR(VLOOKUP($X$17,Sheet1!F:I,2,0),0) -> 0 | Y18: =+IFERROR(VLOOKUP($Y$17,Sheet1!F:I,2,0),0) -> 0 | Z18: 878 | AC18: 196 | AE18: 152 | AQ18: 61 | AU18: 221 | BK18: 87 | BL18: =+IFERROR(VLOOKUP($BL$17,Sheet1!AL2:AO840,2,0),0) -> 0 | BM18: =+IFERROR(VLOOKUP($BM$17,Sheet1!AP2:AS840,2,0),0) -> 0 | BN18: =+IFERROR(VLOOKUP($BN$17,Sheet1!AT2:AW840,2,0),0) -> 0 | BO18: =+IFERROR(VLOOKUP($BO$17,Sheet1!AX2:BA840,2,0),0) -> 0 | BP18: =+IFERROR(VLOOKUP($BP$17,Sheet1!BB2:BE840,2,0),0) -> 0 | BQ18: =+IFERROR(VLOOKUP($BQ$17,Sheet1!BF2:BI840,2,0),0) -> 0 | BR18: =+IFERROR(VLOOKUP($BR$17,Sheet1!BJ2:BM840,2,0),0) -> 0 | BS18: =+IFERROR(VLOOKUP($BS$17,Sheet1!BN2:BQ840,2,0),0) -> 0 | BT18: =+IFERROR(VLOOKUP($BT$17,Sheet1!BR2:BU840,2,0),0) -> 0 | BU18: =+IFERROR(VLOOKUP($BU$17,Sheet1!BV2:BY840,2,0),0) -> 0
A19: =Sheet1!A2 -> ENQ-11009-22-23 | B19: 45139 | C19: =Sheet1!C2 -> FA1300243 | D19: =Sheet1!D2 -> 1 CORE X 300 SQ. MM. AL/ARM - STRIP (XLPE) - 11 KV | E19: =CH19+CJ19+CL19 -> 447991.92 | F19: =ROUNDUP(M22,0) -> 15556 | G19: =E19+F19 -> 463547.92 | H19: =Sheet1!CP2 -> 0.18 | I19: =G19*H19 -> 83438.626 | J19: =G19+I19 -> 546986.55 | K19: =Sheet1!CS2 -> 27 | L19: =Sheet1!CT2 -> KMS | M19: =J19*K19 -> 14768637 | N19: =+IFERROR(VLOOKUP($N$17,Sheet1!J2:L2,3,0),0) -> 810 | O19: =+IFERROR(VLOOKUP($O$17,Sheet1!J2:L2,3,0),0) -> 0 | P19: =+IFERROR(VLOOKUP($P$17,Sheet1!J2:M2,3,0),0) -> 0 | Q19: =+IFERROR(VLOOKUP($Q$17,Sheet1!J2:M2,3,0),0) -> 0 | R19: =+IFERROR(VLOOKUP($R$17,Sheet1!J2:M2,3,0),0) -> 0 | S19: =+IFERROR(VLOOKUP($S$17,Sheet1!N2:Q2,3,0),0) -> 0 | T19: =+IFERROR(VLOOKUP($T$17,Sheet1!N2:Q2,3,0),0) -> 0 | U19: =+IFERROR(VLOOKUP($U$17,Sheet1!F2:I2,3,0),0) -> 0 | V19: =+IFERROR(VLOOKUP($V$17,Sheet1!F2:I2,3,0),0) -> 0 | W19: =+IFERROR(VLOOKUP($W$17,Sheet1!F2:I2,3,0),0) -> 0 | X19: =+IFERROR(VLOOKUP($X$17,Sheet1!F2:I2,3,0),0) -> 0 | Y19: =+IFERROR(VLOOKUP($Y$17,Sheet1!F2:I2,3,0),0) -> 0 | Z19: 49 | AA19: =+IFERROR(VLOOKUP($AA$17,Sheet1!F2:I2,3,0),0) -> 0 | AB19: =+IFERROR(VLOOKUP($AB$17,Sheet1!F2:I2,3,0),0) -> 0 | AC19: 108 | AD19: =+IFERROR(VLOOKUP($AD$17,Sheet1!R2:U2,2,0),0) -> 0 | AE19: =+IFERROR(VLOOKUP($AE$17,Sheet1!V2:Y2,3,0),0) -> 267 | AF19: =+IFERROR(VLOOKUP($AF$17,Sheet1!V2:Y2,3,0),0) -> 0 | AG19: =+IFERROR(VLOOKUP($AG$17,Sheet1!V2:Y2,3,0),0) -> 0 | AH19: =+IFERROR(VLOOKUP($AH$17,Sheet1!V2:Y2,3,0),0) -> 0 | AI19: =+IFERROR(VLOOKUP($AI$17,Sheet1!V2:Y2,3,0),0) -> 0 | AJ19: =+IFERROR(VLOOKUP($AJ$17,Sheet1!V2:Y2,3,0),0) -> 0 | AK19: =+IFERROR(VLOOKUP($AK$17,Sheet1!Z2:AB2,3,0),0) -> 0 | AL19: =+IFERROR(VLOOKUP($AL$17,Sheet1!AD2:AG2,3,0),0) -> 0 | AM19: =+IFERROR(VLOOKUP($AM$17,Sheet1!AD2:AG2,3,0),0) -> 0 | AN19: =+IFERROR(VLOOKUP($AN$17,Sheet1!AD2:AG2,3,0),0) -> 0 | AO19: =+IFERROR(VLOOKUP($AO$17,Sheet1!AD2:AG2,3,0),0) -> 0 | AP19: =+IFERROR(VLOOKUP($AP$17,Sheet1!AD2:AG2,3,0),0) -> 0 | AQ19: 87 | AR19: =+IFERROR(VLOOKUP($AR$17,Sheet1!AD2:AG2,3,0),0) -> 0 | AS19: =+IFERROR(VLOOKUP($AS$17,Sheet1!AH2:AK2,3,0),0) -> 0 | AT19: =+IFERROR(VLOOKUP($AT$17,Sheet1!AH2:AK2,3,0),0) -> 0 | AU19: 203 | AV19: =+IFERROR(VLOOKUP($AV$17,Sheet1!AH2:AK2,3,0),0) -> 0 | AW19: =+IFERROR(VLOOKUP($AW$17,Sheet1!AH2:AK2,3,0),0) -> 0 | AX19: =+IFERROR(VLOOKUP($AX$17,Sheet1!AH2:AK2,3,0),0) -> 0 | AY19: =+IFERROR(VLOOKUP($AY$17,Sheet1!AH2:AK2,3,0),0) -> 0 | AZ19: =+IFERROR(VLOOKUP($AZ$17,Sheet1!AH2:AK2,3,0),0) -> 0 | BA19: =+IFERROR(VLOOKUP($BA$17,Sheet1!AH2:AK2,3,0),0) -> 0 | BB19: =+IFERROR(VLOOKUP($BB$17,Sheet1!AH2:AK2,3,0),0) -> 0 | BC19: =+IFERROR(VLOOKUP($BC$17,Sheet1!AL2:AO2,3,0),0) -> 0 | BD19: =+IFERROR(VLOOKUP($BD$17,Sheet1!AL2:AO2,3,0),0) -> 0 | BE19: =+IFERROR(VLOOKUP($BE$17,Sheet1!AL2:AO2,3,0),0) -> 0 | BF19: =+IFERROR(VLOOKUP($BF$17,Sheet1!AL2:AO2,3,0),0) -> 0 | BG19: =+IFERROR(VLOOKUP($BG$17,Sheet1!AL2:AO2,3,0),0) -> 0 | BH19: =+IFERROR(VLOOKUP($BH$17,Sheet1!AL2:AO2,3,0),0) -> 0 | BI19: =+IFERROR(VLOOKUP($BI$17,Sheet1!AL2:AO2,3,0),0) -> 0 | BJ19: =+IFERROR(VLOOKUP($BJ$17,Sheet1!AL2:AO2,3,0),0) -> 0 | BK19: 297 | BL19: =+IFERROR(VLOOKUP($BL$17,Sheet1!AL2:AO2,3,0),0) -> 0 | BM19: =+IFERROR(VLOOKUP($BM$17,Sheet1!AP2:AS2,3,0),0) -> 0 | BN19: =+IFERROR(VLOOKUP($BN$17,Sheet1!AT2:AW2,3,0),0) -> 0 | BO19: =+IFERROR(VLOOKUP($BO$17,Sheet1!AX2:BA2,3,0),0) -> 0 | BP19: =+IFERROR(VLOOKUP($BP$17,Sheet1!BB2:BE2,3,0),0) -> 0 | BQ19: =+IFERROR(VLOOKUP($BQ$17,Sheet1!BF2:BI2,3,0),0) -> 0 | BR19: =+IFERROR(VLOOKUP($BR$17,Sheet1!BJ2:BM2,3,0),0) -> 0 | BS19: =+IFERROR(VLOOKUP($BS$17,Sheet1!BN2:BQ2,3,0),0) -> 0 | BT19: =+IFERROR(VLOOKUP($BT$17,Sheet1!BR2:BU2,3,0),0) -> 0 | BU19: =+IFERROR(VLOOKUP($BU$17,Sheet1!BV2:BY2,3,0),0) -> 0 | BV19: =Sheet1!E2 -> WOOD | BW19: =Sheet1!CV2 -> MD0100082 | BX19: =Sheet1!CW2 -> DRUM - 60 X 30 X 32 X 3 | BY19: 500 | BZ19: =Sheet1!BZ2 -> 13190.01 | CA19: =SUMPRODUCT($N$18:$BU$18,N19:BU19)+BZ19 -> 362453.01 | CB19: =Sheet1!CB2 -> 0 | CC19: =CA19*CB19 -> 0 | CD19: 0.2 | CE19: =CA19*CD19 -> 72490.602 | CF19: 0 | CG19: =CA19*CF19 -> 0 | CH19: =CA19+CC19+CE19+CG19 -> 434943.61 | CI19: 0.02 | CJ19: =CH19*CI19 -> 8698.8722 | CK19: 0.01 | CL19: =CH19*CK19 -> 4349.4361
E21: Order Quantity | F21: Stnd Length | G21: Truck type | H21: Fare of one truck | I21: No of Drum in one truck | J21: Total length in one Truck | K21: No of Truck | L21: Total Freight | M21: Freight per KM
E22: =K19 -> 27 | F22: 0.5 | G22: 16 MT | H22: 70000 | I22: 10 | J22: =F22*I22 -> 5 | K22: =ROUNDUP((E22/J22),0) -> 6 | L22: =M22*E22 -> 420000 | M22: =(H22*K22)/E22 -> 15555.556
I23: sombhu sir confirmed over phone

Sheet HT POWER CABLE
A1: Base Date | B1: 45139
A2: PV FORMULA
A3: P= Po + AIF(Al - Alo) + XLFAL(CC-Cco)+SMIFS(SMIF1-SMIF0) + CCFAI(PVCc - PVCco)
A4: PV TERMS | B4: Prices should be VARIABLE as per IEEMA without any ceiling with base date as on first working day of the month one month prior to the date of opening of tender. Bids with FIRM rates will be rejected.
A5: TENDER OPENING | B5: 05.09.2023 11.30 AM
Y8: VALUE ADDITION CALCULATION
A9: Item | B9: Calculation part | D9: Applicable Date | I9: BASE DATE | N9: FACTORS | R9: Ex-Work Po | S9: PVC of al | T9: PVC of Cu | U9: PVC of XLPE | V9: PVC OF PVC | W9: PV/PKM | X9: Billing Price/PKM
D10: Date | E10: Al | F10: Cu | G10: Cc | H10: PVCc | I10: Date | J10: Alo | K10: Cuo | L10: Cco | M10: PVCco | Y10: ='AUTO CALCULATION SHEET (2)'!N17 -> Alumimium | Z10: ='AUTO CALCULATION SHEET (2)'!Z17 -> Copper Tape - 0.050 mm | AA10: ='AUTO CALCULATION SHEET (2)'!AC17 -> Extruded semiconductive | AB10: ='AUTO CALCULATION SHEET (2)'!AE17 -> HT-XLPE | AC10: ='AUTO CALCULATION SHEET (2)'!AQ17 -> PVC Type ST-2 | AD10: ='AUTO CALCULATION SHEET (2)'!AU17 -> Aluminium Flat Strip | AE10: ='AUTO CALCULATION SHEET (2)'!BK17 -> PVC Type ST-2-PRESSURE EXTRUDED | AF10: RMC | AG10: Drum | AH10: RMC+Drum | AI10: VA | AJ10: Groos VA% | AK10: Mfg % | AL10: Int % | AM10: Ins% | AN10: Net VA
N11: Alf | O11: Smif | P11: XLFAL | Q11: CCFAI | Y11: 211 | Z11: 885 | AA11: 198 | AB11: 154 | AC11: 61 | AD11: 221 | AE11: 87
G12: JULY CIRCULAR | I12: PROVISIONAL | L12: JULY CIRCULAR | Y12: Kg/Km | Z12: Kg/Km | AA12: Kg/Km | AB12: Kg/Km | AC12: Kg/Km | AD12: Kg/Km | AE12: Kg/Km
A13: ='AUTO CALCULATION SHEET (2)'!D19 -> 1 CORE X 300 SQ. MM. AL/ARM - STRIP (XLPE) - 11 KV | C13: PROVISIONAL | D13: 45155 | E13: 205222.68 | F13: 752906.84 | G13: 182528 | H13: 151075 | I13: =$B$1 -> 45139 | J13: 205222.68 | K13: 752906.84 | L13: 182528 | M13: 151075 | N13: 1.283 | O13: 0.0364 | P13: 0.372 | Q13: 0.506 | R13: ='AUTO CALCULATION SHEET (2)'!E19 -> 447991.92 | S13: =(N13*(E13-J13)) -> 0 | T13: =O13*(F13-K13) -> 0 | U13: =(P13*(G13-L13)) -> 0 | V13: =(Q13*(H13-M13)) -> 0 | W13: =S13+T13+U13+V13 -> 0 | X13: =R13+W13 -> 447991.92 | Y13: ='AUTO CALCULATION SHEET (2)'!N19 -> 810 | Z13: ='AUTO CALCULATION SHEET (2)'!Z19 -> 49 | AA13: ='AUTO CALCULATION SHEET (2)'!AC19 -> 108 | AB13: ='AUTO CALCULATION SHEET (2)'!AE19 -> 267 | AC13: ='AUTO CALCULATION SHEET (2)'!AQ19 -> 87 | AD13: ='AUTO CALCULATION SHEET (2)'!AU19 -> 203 | AE13: ='AUTO CALCULATION SHEET (2)'!BK19 -> 297 | AF13: =SUMPRODUCT(Y13:AE13,$Y$11:AE$11) -> 352786 | AG13: ='AUTO CALCULATION SHEET (2)'!BZ19 -> 13190.01 | AH13: =AF13+AG13 -> 365976.01 | AI13: =X13-AH13 -> 82015.91 | AJ13: =ROUND((AI13/AH13)*100,2) -> 22.41 | AN13: =AJ13-AK13-AL13-AM13 -> 22.41
