Workbook

Sheet Sheet1
A1: DOCKET NO. | B1: Base Date | C1: ITEM CODE | D1: PROPOSE ERP ITEM NAME | E1: PROPOSE DRUM TYPE | F1: Insulation Screening (Metallic) | G1: RM RATE (Insulation Screening (Metallic)) | H1: Weight (Insulation Screening (Metallic)) | I1: COST(Insulation Screening (Metallic)) | J1: Conductor | K1: RM RATE(Conductor) | L1: WEIGHT(Conductor) | M1: COST(Conductor) | N1: AL ALLOY | O1: RM RATE(Alu Alloy) | P1: WEIGHT(Alu Alloy) | Q1: COST(Alu Alloy) | R1: Insulation Screening (Non-Metallic) | S1: RM RATE(Insulation Screening (Non-Metallic)) | T1: WEIGHT(Insulation Screening (Non-Metallic)) | U1: COST(Insulation Screening (Non-Metallic)) | V1: Insulation | W1: RM RATE(Insulation) | X1: WEIGHT(Insulation) | Y1: COST(Insulation) | Z1: POLY TAPE | AA1: RM RATE (Poly Tape) | AB1: WEIGHT (Poly Tape) | AC1: COST(Poly Tape) | AD1: Inner Sheath | AE1: RM RATE(Inner Sheath) | AF1: WEIGHT(Inner Sheath) | AG1: COST(Inner Sheath) | AH1: Armouring | AI1: RM RATE(Armouring) | AJ1: WEIGHT(Armouring) | AK1: COST(Armouring) | AL1: Outer Sheath | AM1: RM RATE(Outer Sheath) | AN1: WEIGHT(Outer Sheath) | AO1: COST(Outer Sheath) | AP1: FILLER | AQ1: RM RATE(Filler) | AR1: WEIGHT(Filler) | AS1: COST(Filler) | AT1: GREASE | AU1: RM RATE(Grease) | AV1: WEIGHT(Grease) | AW1: COST(Grease) | AX1: Water swellable Tape | AY1: RM RATE(Water swellable Tape) | AZ1: WEIGHT(Water swellable Tape) | BA1: COST(Water swellable Tape) | BB1: Semi conducting Water Swellable tape | BC1: RM RATE(Semi conducting Water Swellable tape) | BD1: WEIGHT(Semi conducting Water Swellable tape) | BE1: COST(Semi conducting Water Swellable tape) | BF1: SEMICON TAPE | BG1: RM RATE(SEMICON TAPE) | BH1: WEIGHT(SEMICON TAPE) | BI1: COST(SEMICON TAPE) | BJ1: GLASS FIBER TAPE | BK1: RM RATE(GLASS FIBER TAPE) | BL1: WEIGHT(GLASS FIBER TAPE) | BM1: COST(GLASS FIBER TAPE) | BN1: COPPER WIRE 0.8 MM | BO1: RM RATE(COPPER WIRE 0.8 MM) | BP1: WEIGHT(COPPER WIRE 0.8 MM) | BQ1: COST(COPPER WIRE 0.8 MM) | BR1: RUBBERIZED COTTON TAPE | BS1: RM RATE(RUBBERIZED COTTON TAPE) | BT1: WEIGHT(RUBBERIZED COTTON TAPE) | BU1: COST(RUBBERIZED COTTON TAPE) | BV1: Water Tight Compound | BW1: RM RATE(Water Tight Compound) | BX1: WEIGHT(Water Tight Compound) | BY1: COST(Water Tight Compound) | BZ1: DRUM COST PER KM | CA1: TOTAL RM COST | CB1: FIRM % | CC1: FIRM VALUE | CD1: MFG% | CE1: MFG VALUE | CF1: PROF% | CG1: PROFIT VALUE | CH1: 1ST EX-WORKS | CI1: Intt % | CJ1: INTT VALUE | CK1: insp% | CL1: INSP VALUE | CM1: EX-WORKS (PER KM) | CN1: FREIGHT PER KM | CO1: PRICE INCLUDING FREIGHT (PER KM) | CP1: GST % | CQ1: GST VALUE | CR1: PRICE INCLUDING GST & FREIGHT (PER KM) | CS1: QTY | CT1: Unit | CU1: TOTAL PRICE OF FULL QTY (INCLUDING FRIGHT & GST) | CV1: DRUM CODE | CW1: DRUM SIZE (FxbXtx Ft) | CX1: PARTY STANDARD LENGTH (MTR)
A2: ENQ-11226-22-23 | B2: 45194 | C2: FA0900018 | D2: 4 CORE X 35 SQ. MM. AL/ARD - STRIP (XLPE) | E2: WOOD | J2: Alumimium | K2: 216 | L2: 378 | M2: 81648 | P2: 0 | T2: 0 | V2: LT-XLPE | W2: 116 | X2: 109 | Y2: 12644 | AB2: 0 | AD2: PVC Type ST-2 | AE2: 62.87 | AF2: 51 | AG2: 3206.37 | AH2: Galvanised Steel Flat Strip | AI2: 76.25 | AJ2: 407 | AK2: 31033.75 | AL2: FRLSH PVC Type ST-2 | AM2: 107 | AN2: 191 | AO2: 12008.17 | AR2: 0 | AV2: 0 | AZ2: 0 | BD2: 0 | BH2: 0 | BL2: 0 | BP2: 0 | BT2: 0 | BX2: 0 | BZ2: 7317.08 | CA2: 147857.37 | CH2: 147857.37 | CM2: 147857.37 | CO2: 147857.37 | CR2: 147857.37 | CS2: 0.5 | CT2: KMS | CU2: 73929 | CV2: MD0100015 | CW2: DRUM - 48 X 20 X 28 X 2.25 - RDSO
A3: ENQ-11226-22-23 | B3: 45194 | C3: FA1000014 | D3: 4 CORE X 16 SQ. MM. ALU/UNARD (XLPE) | E3: WOOD | J3: Alumimium | K3: 216 | L3: 172.8 | M3: 37324.8 | P3: 0 | T3: 0 | V3: LT-XLPE | W3: 116 | X3: 63 | Y3: 8700 | AB3: 0 | AD3: PVC Type ST-2 | AE3: 62.87 | AF3: 40 | AG3: 2514.8 | AJ3: 0 | AL3: FRLSH PVC Type ST-2 | AM3: 107 | AN3: 182 | AO3: 11442.34 | AR3: 0 | AV3: 0 | AZ3: 0 | BD3: 0 | BH3: 0 | BL3: 0 | BP3: 0 | BT3: 0 | BX3: 0 | BZ3: 5151.48 | CA3: 65133.42 | CH3: 65133.42 | CM3: 65133.42 | CO3: 65133.42 | CR3: 65133.42 | CS3: 0.5 | CT3: KMS | CU3: 32567 | CV3: MD0100066 | CW3: DRUM - 40 X 15 X 23 X 2
A4: ENQ-11226-22-23 | B4: 45194 | C4: FA1000016 | D4: 4 CORE X 35 SQ. MM. AL/UNARD.(XLPE) | E4: WOOD | J4: Alumimium | K4: 216 | L4: 378 | M4: 81648 | P4: 0 | T4: 0 | V4: LT-XLPE | W4: 116 | X4: 109 | Y4: 12644 | AB4: 0 | AD4: PVC Type ST-2 | AE4: 62.87 | AF4: 51 | AG4: 3206.37 | AJ4: 0 | AL4: FRLSH PVC Type ST-2 | AM4: 107 | AN4: 228 | AO4: 14334.36 | AR4: 0 | AV4: 0 | AZ4: 0 | BD4: 0 | BH4: 0 | BL4: 0 | BP4: 0 | BT4: 0 | BX4: 0 | BZ4: 7317.08 | CA4: 119149.81 | CH4: 119149.81 | CM4: 119149.81 | CO4: 119149.81 | CR4: 119149.81 | CS4: 0.5 | CT4: KMS | CU4: 59575 | CV4: MD0100015 | CW4: DRUM - 48 X 20 X 28 X 2.25 - RDSO
A5: ENQ-11226-22-23 | B5: 45194 | C5: FA1000048 | D5: 4 CORE X 10 SQ. MM. AL/UNARD (XLPE) | E5: WOOD | J5: Alumimium | K5: 216 | L5: 108 | M5: 23328 | P5: 0 | T5: 0 | V5: LT-XLPE | W5: 116 | X5: 64 | Y5: 7424 | AB5: 0 | AD5: PVC Type ST-2 | AE5: 62.87 | AF5: 35 | AG5: 2200.45 | AJ5: 0 | AL5: FRLSH PVC Type ST-2 | AM5: 107 | AN5: 145 | AO5: 9116.15 | AR5: 0 | AV5: 0 | AZ5: 0 | BD5: 0 | BH5: 0 | BL5: 0 | BP5: 0 | BT5: 0 | BX5: 0 | BZ5: 4610.79 | CA5: 46679.39 | CH5: 46679.39 | CM5: 46679.39 | CO5: 46679.39 | CR5: 46679.39 | CS5: 1 | CT5: KMS | CU5: 46679 | CV5: MD0100005 | CW5: DRUM - 36 X 14 X 23 X 2
A6: ENQ-11226-22-23 | B6: 45194 | C6: FA0900013 | D6: 4 CORE X 16 SQ. MM. ALU/ARD - STRIP (XLPE) | E6: WOOD | J6: Alumimium | K6: 216 | L6: 172.8 | M6: 37324.8 | P6: 0 | T6: 0 | V6: LT-XLPE | W6: 116 | X6: 63 | Y6: 7308 | AB6: 0 | AD6: PVC Type ST-2 | AE6: 62.87 | AF6: 40 | AG6: 2514.8 | AH6: Galvanised Steel Flat Strip | AI6: 76.25 | AJ6: 300 | AK6: 22875 | AL6: FRLSH PVC Type ST-2 | AM6: 107 | AN6: 146 | AO6: 9179.02 | AR6: 0 | AV6: 0 | AZ6: 0 | BD6: 0 | BH6: 0 | BL6: 0 | BP6: 0 | BT6: 0 | BX6: 0 | BZ6: 5151.48 | CA6: 84353.1 | CH6: 84353.1 | CM6: 84353.1 | CO6: 84353.1 | CR6: 84353.1 | CS6: 2 | CT6: KMS | CU6: 168706 | CV6: MD0100066 | CW6: DRUM - 40 X 15 X 23 X 2
A7: ENQ-11226-22-23 | B7: 45194 | C7: FA1000026 | D7: 4 CORE X 6 SQ. MM. AL/UNARD.(XLPE) | E7: WOOD | J7: Alumimium | K7: 216 | L7: 64.8 | M7: 13996.8 | P7: 0 | T7: 0 | V7: LT-XLPE | W7: 116 | X7: 53 | Y7: 6148 | AB7: 0 | AD7: PVC Type ST-2 | AE7: 62.87 | AF7: 30 | AG7: 1886.1 | AJ7: 0 | AL7: FRLSH PVC Type ST-2 | AM7: 107 | AN7: 127 | AO7: 7984.49 | AR7: 0 | AV7: 0 | AZ7: 0 | BD7: 0 | BH7: 0 | BL7: 0 | BP7: 0 | BT7: 0 | BX7: 0 | BZ7: 4610.79 | CA7: 34626.18 | CH7: 34626.18 | CM7: 34626.18 | CO7: 34626.18 | CR7: 34626.18 | CS7: 2 | CT7: KMS | CU7: 69252 | CV7: MD0100005 | CW7: DRUM - 36 X 14 X 23 X 2

Sheet AUTO CALCULATION SHEET (2)
A2: THE WEST BENGAL POWER DEVELOPMENT CORPORATION LIMITED
A4: TENDER SPECIFICATION NO () | B4: WBPDCL/SGTPP/NIT/E2518/23-24
A5: TENDER DESCRIPTION () | B5: Procurement of 1.1 KV Grade Power Cable for CHP-EM Department for one (1) year, SGTPP / WBPDCL
A6: Last Date & Time of Submission () | B6: 45196
A7: REVERSE AUCTION | B7: Not Mention.
A8: Price () | B8: Rates should remain firm till the final execution of the purchase order.In case of variation of any Govt. Taxes & Duties will occur, the same is acceptable to WBPDCL. GST will be applicable as per Government rules & regulations.
A9: Validity () | B9: The Bid should be valid for at least 180 days from the date of opening of the bid.
A10: Delivery Period () | B10: Earliest Delivery schedule is to be mentioned in the offer by the bidder and must be maintained. However, maximum delivery period will be within 120 days from the date of placement of confirmed purchase order.
A11: Payment Terms () | B11: 90% payment along with all applicable taxes and duties will be made within 45 days against SRV (Store Receipt Voucher). SRV will be issued by SgTPP Store after successful delivery of the materials. Balance 10% payment will be retained as security deposit and will be released after successful completion of the Guarantee/Warranty period (as mentioned in NIT) duly certified by the controlling officer, SgTPP or, his authorized representative. The balance 10% payment as a security deposit may be released subject to submission of Performance Bank Guarantee (PBG) @10% of order value valid for 18 months with additional claim period of 03 months on any bank as mentioned below.
A12: Technical Specification
N14: =Sheet1!J1 -> Conductor | S14: AL ALLOY | U14: Insulation Screening (Metallic) | AC14: Insulation Screening (Non-Metallic) | AE14: Insulation | AK14: POLY TAPE | AL14: Inner Sheath | AS14: Armouring | BC14: Outer Sheath | BM14: FILLER | BN14: GREASE | BO14: Water swellable Tape | BP14: Semi conducting Water Swellable tape | BQ14: SEMICON TAPE | BR14: GLASS FIBER TAPE | BS14: COPPER WIRE 0.8 MM | BT14: RUBBERIZED COTTON TAPE | BU14: Water Tight Compound | BZ14: DRUM COST PER KM | CA14: TOTAL RM COST | CB14: EXTRA CONSUMPTION | CC14: EXTRA CONSUMPTION VALUE
A15: DOCKET NO. | B15: =Sheet1!B1 -> Base Date | C15: ITEM CODE | D15: PROPOSE ERP ITEM NAME | E15: EX-WORKS (PER KM) | F15: FREIGHT PER KM | G15: PRICE INCLUDING FREIGHT (PER KM) | H15: GST % | I15: GST VALUE | J15: PRICE INCLUDING GST & FREIGHT (PER KM) | K15: QTY | L15: Unit | M15: TOTAL PRICE OF FULL QTY (INCLUDING FRIGHT & GST) | N15: Alumimium | O15: Alumimium ALLOY | P15: Copper | Q15: Flexible Copper | R15: Galvanized steel wire | S15: Alumimium | T15: Alumimium ALLOY | U15: Coper tape - 0.1 mm | V15: Copper Tape - 0.03 mm | W15: Copper Tape - 0.035 mm | X15: Copper Tape - 0.04 mm | Y15: Copper Tape - 0.045 mm | Z15: Copper Tape - 0.050 mm | AA15: Copper Tape - 0.060 mm | AB15: Copper Tape - 0.075 mm(DOUBLE) | AC15: Extruded semiconductive | AD15: Extruded Semiconductive(Stripable) | AE15: HT-XLPE | AF15: LT-XLPE | AG15: TR XLPE | AH15: Type A PVC | AI15: Type C PVC (HR) | AJ15: XLPE | AK15: POLY TAPE | AL15: FR PVC Type ST-1 | AM15: FR PVC Type ST-2 | AN15: FRLSH PVC Type ST-2 | AO15: PVC Type ST-1 | AP15: PVC Type ST-1-PRESSURE EXTRUDED | AQ15: PVC Type ST-2 | AR15: PVC Type ST-2-PRESSURE EXTRUDED | AS15: ACSR CORE WIRE | AT15: ACSR DOG STEEL WIRE | AU15: Aluminium Flat Strip | AV15: Aluminium Round Wire | AW15: Double Steel Tape | AX15: Galvanised Steel Flat Strip | AY15: Galvanised Steel Flat Strip (Double) | AZ15: Galvanised Steel Flat Strip-B | BA15: Galvanised Steel Round Wire | BB15: Galvanised Steel Round Wire (Double) | BC15: FR PVC Type ST-1 | BD15: FR PVC Type ST-2 | BE15: FRLSH PVC Type ST-1 | BF15: FRLSH PVC Type ST-2 | BG15: PE, ST-3 | BH15: PE, ST-7 | BI15: PVC Type ST-1 | BJ15: PVC Type ST-2 | BK15: PVC Type ST-2-PRESSURE EXTRUDED | BL15: UV & Track Resistant XLPE | BM15: FILLER | BN15: Grease | BO15: Water swellable Tape | BP15: Semi conducting Water Swellable tape | BQ15: SEMICON TAPE | BR15: GLASS FIBER TAPE | BS15: COPPER WIRE 0.8 MM | BT15: RUBBERIZED COTTON TAPE | BU15: Water Tight Compound | BV15: =Sheet1!E1 -> PROPOSE DRUM TYPE | BW15: =Sheet1!CV1 -> DRUM CODE | BX15: =Sheet1!CW1 -> DRUM SIZE (FxbXtx Ft) | BY15: =Sheet1!CX1 -> PARTY STANDARD LENGTH (MTR) | CD15: MFG% | CE15: MFG VALUE | CF15: PROF% | CG15: PROFIT VALUE | CH15: 1ST EX-WORKS | CI15: Intt % | CJ15: INTT VALUE | CK15: insp% | CL15: INSP VALUE
F16: 0.035 | N16: 215 | O16: =+IFERROR(VLOOKUP($O$15,Sheet1!J:L,2,0),0) -> 0 | P16: =+IFERROR(VLOOKUP($P$15,Sheet1!J:M,2,0),0) -> 0 | Q16: =+IFERROR(VLOOKUP($Q$15,Sheet1!J:M,2,0),0) -> 0 | R16: =+IFERROR(VLOOKUP($R$15,Sheet1!J:M,2,0),0) -> 0 | S16: =+IFERROR(VLOOKUP($S$15,Sheet1!N:Q,2,0),0) -> 0 | T16: =+IFERROR(VLOOKUP($T$15,Sheet1!N:O,2,0),0) -> 0 | U16: =+IFERROR(VLOOKUP($U$15,Sheet1!F:I,2,0),0) -> 0 | V16: =+IFERROR(VLOOKUP($V$15,Sheet1!F:I,2,0),0) -> 0 | W16: =+IFERROR(VLOOKUP($W$15,Sheet1!F:I,2,0),0) -> 0 | X16: =+IFERROR(VLOOKUP($X$15,Sheet1!F:I,2,0),0) -> 0 | Y16: =+IFERROR(VLOOKUP($Y$15,Sheet1!F:I,2,0),0) -> 0 | Z16: =+IFERROR(VLOOKUP($Z$15,Sheet1!F:I,2,0),0) -> 0 | AA16: =+IFERROR(VLOOKUP($AA$15,Sheet1!F:I,2,0),0) -> 0 | AB16: =+IFERROR(VLOOKUP($AB$15,Sheet1!F:I,2,0),0) -> 0 | AC16: =+IFERROR(VLOOKUP($AC$15,Sheet1!R:U,2,0),0) -> 0 | AD16: =+IFERROR(VLOOKUP($AD$15,Sheet1!R:U,2,0),0) -> 0 | AE16: =+IFERROR(VLOOKUP($AE$15,Sheet1!V:Y,2,0),0) -> 0 | AF16: =+IFERROR(VLOOKUP($AF$15,Sheet1!V:Y,2,0),0) -> 116 | AG16: =+IFERROR(VLOOKUP($AG$15,Sheet1!V:Y,2,0),0) -> 0 | AH16: =+IFERROR(VLOOKUP($AH$15,Sheet1!V:Y,2,0),0) -> 0 | AI16: =+IFERROR(VLOOKUP($AI$15,Sheet1!V:Y,2,0),0) -> 0 | AJ16: =+IFERROR(VLOOKUP($AJ$15,Sheet1!V:Y,2,0),0) -> 0 | AK16: =+IFERROR(VLOOKUP($AK$15,Sheet1!Z2:AA840,2,0),0) -> 0 | AL16: =+IFERROR(VLOOKUP($AL$15,Sheet1!AD2:AG840,2,0),0) -> 0 | AM16: =+IFERROR(VLOOKUP($AM$15,Sheet1!AD2:AG840,2,0),0) -> 0 | AN16: =+IFERROR(VLOOKUP($AN$15,Sheet1!AD2:AG840,2,0),0) -> 0 | AO16: =+IFERROR(VLOOKUP($AO$15,Sheet1!AD2:AG840,2,0),0) -> 0 | AP16: =+IFERROR(VLOOKUP($AP$15,Sheet1!AD2:AG840,2,0),0) -> 0 | AQ16: 63 | AR16: =+IFERROR(VLOOKUP($AR$15,Sheet1!AD2:AG840,2,0),0) -> 0 | AS16: =+IFERROR(VLOOKUP($AS$15,Sheet1!AH2:AK840,2,0),0) -> 0 | AT16: =+IFERROR(VLOOKUP($AT$15,Sheet1!AH2:AK840,2,0),0) -> 0 | AU16: =+IFERROR(VLOOKUP($AU$15,Sheet1!AH2:AK840,2,0),0) -> 0 | AV16: =+IFERROR(VLOOKUP($AV$15,Sheet1!AH2:AK840,2,0),0) -> 0 | AW16: =+IFERROR(VLOOKUP($AW$15,Sheet1!AH2:AK840,2,0),0) -> 0 | AX16: 79 | AY16: =+IFERROR(VLOOKUP($AY$15,Sheet1!AH2:AK840,2,0),0) -> 0 | AZ16: =+IFERROR(VLOOKUP($AZ$15,Sheet1!AH2:AK840,2,0),0) -> 0 | BA16: =+IFERROR(VLOOKUP($BA$15,Sheet1!AH2:AK840,2,0),0) -> 0 | BB16: =+IFERROR(VLOOKUP($BB$15,Sheet1!AH2:AK840,2,0),0) -> 0 | BC16: =+IFERROR(VLOOKUP($BC$15,Sheet1!AL2:AO840,2,0),0) -> 0 | BD16: =+IFERROR(VLOOKUP($BD$15,Sheet1!AL2:AO840,2,0),0) -> 0 | BE16: =+IFERROR(VLOOKUP($BE$15,Sheet1!AL2:AO840,2,0),0) -> 0 | BF16: 95 | BG16: =+IFERROR(VLOOKUP($BG$15,Sheet1!AL2:AO840,2,0),0) -> 0 | BH16: =+IFERROR(VLOOKUP($BH$15,Sheet1!AL2:AO840,2,0),0) -> 0 | BI16: =+IFERROR(VLOOKUP($BI$15,Sheet1!AL2:AO840,2,0),0) -> 0 | BJ16: =+IFERROR(VLOOKUP($BJ$15,Sheet1!AL2:AO840,2,0),0) -> 0 | BK16: =+IFERROR(VLOOKUP($BK$15,Sheet1!AL2:AO840,2,0),0) -> 0 | BL16: =+IFERROR(VLOOKUP($BL$15,Sheet1!AL2:AO840,2,0),0) -> 0 | BM16: =+IFERROR(VLOOKUP($BM$15,Sheet1!AP2:AS840,2,0),0) -> 0 | BN16: =+IFERROR(VLOOKUP($BN$15,Sheet1!AT2:AW840,2,0),0) -> 0 | BO16: =+IFERROR(VLOOKUP($BO$15,Sheet1!AX2:BA840,2,0),0) -> 0 | BP16: =+IFERROR(VLOOKUP($BP$15,Sheet1!BB2:BE840,2,0),0) -> 0 | BQ16: =+IFERROR(VLOOKUP($BQ$15,Sheet1!BF2:BI840,2,0),0) -> 0 | BR16: =+IFERROR(VLOOKUP($BR$15,Sheet1!BJ2:BM840,2,0),0) -> 0 | BS16: =+IFERROR(VLOOKUP($BS$15,Sheet1!BN2:BQ840,2,0),0) -> 0 | BT16: =+IFERROR(VLOOKUP($BT$15,Sheet1!BR2:BU840,2,0),0) -> 0 | BU16: =+IFERROR(VLOOKUP($BU$15,Sheet1!BV2:BY840,2,0),0) -> 0
A17: =Sheet1!A2 -> ENQ-11226-22-23 | B17: =Sheet1!B2 -> 45194 | C17: =Sheet1!C2 -> FA0900018 | D17: =Sheet1!D2 -> 4 CORE X 35 SQ. MM. AL/ARD - STRIP (XLPE) | E17: =CH17+CJ17+CL17 -> 215168.86 | F17: =ROUND(E17*$F$16,2) -> 7530.91 | G17: =E17+F17 -> 222699.77 | H17: 0.18 | I17: =G17*H17 -> 40085.959 | J17: =G17+I17 -> 262785.73 | K17: =Sheet1!CS2 -> 0.5 | L17: =Sheet1!CT2 -> KMS | M17: =J17*K17 -> 131392.87 | N17: =+IFERROR(VLOOKUP($N$15,Sheet1!J2:L2,3,0),0) -> 378 | O17: =+IFERROR(VLOOKUP($O$15,Sheet1!J2:L2,3,0),0) -> 0 | P17: =+IFERROR(VLOOKUP($P$15,Sheet1!J2:M2,3,0),0) -> 0 | Q17: =+IFERROR(VLOOKUP($Q$15,Sheet1!J2:M2,3,0),0) -> 0 | R17: =+IFERROR(VLOOKUP($R$15,Sheet1!J2:M2,3,0),0) -> 0 | S17: =+IFERROR(VLOOKUP($S$15,Sheet1!N2:Q2,3,0),0) -> 0 | T17: =+IFERROR(VLOOKUP($T$15,Sheet1!N2:Q2,3,0),0) -> 0 | U17: =+IFERROR(VLOOKUP($U$15,Sheet1!F2:I2,3,0),0) -> 0 | V17: =+IFERROR(VLOOKUP($V$15,Sheet1!F2:I2,3,0),0) -> 0 | W17: =+IFERROR(VLOOKUP($W$15,Sheet1!F2:I2,3,0),0) -> 0 | X17: =+IFERROR(VLOOKUP($X$15,Sheet1!F2:I2,3,0),0) -> 0 | Y17: =+IFERROR(VLOOKUP($Y$15,Sheet1!F2:I2,3,0),0) -> 0 | Z17: =+IFERROR(VLOOKUP($Z$15,Sheet1!F2:I2,3,0),0) -> 0 | AA17: =+IFERROR(VLOOKUP($AA$15,Sheet1!F2:I2,3,0),0) -> 0 | AB17: =+IFERROR(VLOOKUP($AB$15,Sheet1!F2:I2,3,0),0) -> 0 | AC17: =+IFERROR(VLOOKUP($AC$15,Sheet1!R2:U2,3,0),0) -> 0 | AD17: =+IFERROR(VLOOKUP($AD$15,Sheet1!R2:U2,2,0),0) -> 0 | AE17: =+IFERROR(VLOOKUP($AE$15,Sheet1!V2:Y2,3,0),0) -> 0 | AF17: =+IFERROR(VLOOKUP($AF$15,Sheet1!V2:Y2,3,0),0) -> 109 | AG17: =+IFERROR(VLOOKUP($AG$15,Sheet1!V2:Y2,3,0),0) -> 0 | AH17: =+IFERROR(VLOOKUP($AH$15,Sheet1!V2:Y2,3,0),0) -> 0 | AI17: =+IFERROR(VLOOKUP($AI$15,Sheet1!V2:Y2,3,0),0) -> 0 | AJ17: =+IFERROR(VLOOKUP($AJ$15,Sheet1!V2:Y2,3,0),0) -> 0 | AK17: =+IFERROR(VLOOKUP($AK$15,Sheet1!Z2:AB2,3,0),0) -> 0 | AL17: =+IFERROR(VLOOKUP($AL$15,Sheet1!AD2:AG2,3,0),0) -> 0 | AM17: =+IFERROR(VLOOKUP($AM$15,Sheet1!AD2:AG2,3,0),0) -> 0 | AN17: =+IFERROR(VLOOKUP($AN$15,Sheet1!AD2:AG2,3,0),0) -> 0 | AO17: =+IFERROR(VLOOKUP($AO$15,Sheet1!AD2:AG2,3,0),0) -> 0 | AP17: =+IFERROR(VLOOKUP($AP$15,Sheet1!AD2:AG2,3,0),0) -> 0 | AQ17: =+IFERROR(VLOOKUP($AQ$15,Sheet1!AD2:AG2,3,0),0) -> 51 | AR17: =+IFERROR(VLOOKUP($AR$15,Sheet1!AD2:AG2,3,0),0) -> 0 | AS17: =+IFERROR(VLOOKUP($AS$15,Sheet1!AH2:AK2,3,0),0) -> 0 | AT17: =+IFERROR(VLOOKUP($AT$15,Sheet1!AH2:AK2,3,0),0) -> 0 | AU17: =+IFERROR(VLOOKUP($AU$15,Sheet1!AH2:AK2,3,0),0) -> 0 | AV17: =+IFERROR(VLOOKUP($AV$15,Sheet1!AH2:AK2,3,0),0) -> 0 | AW17: =+IFERROR(VLOOKUP($AW$15,Sheet1!AH2:AK2,3,0),0) -> 0 | AX17: =+IFERROR(VLOOKUP($AX$15,Sheet1!AH2:AK2,3,0),0) -> 407 | AY17: =+IFERROR(VLOOKUP($AY$15,Sheet1!AH2:AK2,3,0),0) -> 0 | AZ17: =+IFERROR(VLOOKUP($AZ$15,Sheet1!AH2:AK2,3,0),0) -> 0 | BA17: =+IFERROR(VLOOKUP($BA$15,Sheet1!AH2:AK2,3,0),0) -> 0 | BB17: =+IFERROR(VLOOKUP($BB$15,Sheet1!AH2:AK2,3,0),0) -> 0 | BC17: =+IFERROR(VLOOKUP($BC$15,Sheet1!AL2:AO2,3,0),0) -> 0 | BD17: =+IFERROR(VLOOKUP($BD$15,Sheet1!AL2:AO2,3,0),0) -> 0 | BE17: =+IFERROR(VLOOKUP($BE$15,Sheet1!AL2:AO2,3,0),0) -> 0 | BF17: =+IFERROR(VLOOKUP($BF$15,Sheet1!AL2:AO2,3,0),0) -> 191 | BG17: =+IFERROR(VLOOKUP($BG$15,Sheet1!AL2:AO2,3,0),0) -> 0 | BH17: =+IFERROR(VLOOKUP($BH$15,Sheet1!AL2:AO2,3,0),0) -> 0 | BI17: =+IFERROR(VLOOKUP($BI$15,Sheet1!AL2:AO2,3,0),0) -> 0 | BJ17: =+IFERROR(VLOOKUP($BJ$15,Sheet1!AL2:AO2,3,0),0) -> 0 | BK17: =+IFERROR(VLOOKUP($BK$15,Sheet1!AL2:AO2,3,0),0) -> 0 | BL17: =+IFERROR(VLOOKUP($BL$15,Sheet1!AL2:AO2,3,0),0) -> 0 | BM17: =+IFERROR(VLOOKUP($BM$15,Sheet1!AP2:AS2,3,0),0) -> 0 | BN17: =+IFERROR(VLOOKUP($BN$15,Sheet1!AT2:AW2,3,0),0) -> 0 | BO17: =+IFERROR(VLOOKUP($BO$15,Sheet1!AX2:BA2,3,0),0) -> 0 | BP17: =+IFERROR(VLOOKUP($BP$15,Sheet1!BB2:BE2,3,0),0) -> 0 | BQ17: =+IFERROR(VLOOKUP($BQ$15,Sheet1!BF2:BI2,3,0),0) -> 0 | BR17: =+IFERROR(VLOOKUP($BR$15,Sheet1!BJ2:BM2,3,0),0) -> 0 | BS17: =+IFERROR(VLOOKUP($BS$15,Sheet1!BN2:BQ2,3,0),0) -> 0 | BT17: =+IFERROR(VLOOKUP($BT$15,Sheet1!BR2:BU2,3,0),0) -> 0 | BU17: =+IFERROR(VLOOKUP($BU$15,Sheet1!BV2:BY2,3,0),0) -> 0 | BV17: =Sheet1!E2 -> WOOD | BW17: =Sheet1!CV2 -> MD0100015 | BX17: =Sheet1!CW2 -> DRUM - 48 X 20 X 28 X 2.25 - RDSO | BY17: 500 | BZ17: =Sheet1!BZ2 -> 7317.08 | CA17: =SUMPRODUCT($N$16:$BU$16,N17:BU17)+BZ17 -> 154742.08 | CB17: =Sheet1!CB2 -> 0 | CC17: =CA17*CB17 -> 0 | CD17: 0.35 | CE17: =CA17*CD17 -> 54159.728 | CF17: 0 | CG17: =CA17*CF17 -> 0 | CH17: =CA17+CC17+CE17+CG17 -> 208901.81 | CI17: 0.02 | CJ17: =CH17*CI17 -> 4178.0362 | CK17: 0.01 | CL17: =CH17*CK17 -> 2089.0181
A18: =Sheet1!A4 -> ENQ-11226-22-23 | B18: =Sheet1!B4 -> 45194 | C18: =Sheet1!C4 -> FA1000016 | D18: =Sheet1!D4 -> 4 CORE X 35 SQ. MM. AL/UNARD.(XLPE) | E18: =CH18+CJ18+CL18 -> 175347.72 | F18: =ROUND(E18*$F$16,2) -> 6137.17 | G18: =E18+F18 -> 181484.89 | H18: 0.18 | I18: =G18*H18 -> 32667.281 | J18: =G18+I18 -> 214152.17 | K18: =Sheet1!CS4 -> 0.5 | L18: =Sheet1!CT4 -> KMS | M18: =J18*K18 -> 107076.09 | N18: =+IFERROR(VLOOKUP($N$15,Sheet1!J4:L4,3,0),0) -> 378 | O18: =+IFERROR(VLOOKUP($O$15,Sheet1!J4:L4,3,0),0) -> 0 | P18: =+IFERROR(VLOOKUP($P$15,Sheet1!J4:M4,3,0),0) -> 0 | Q18: =+IFERROR(VLOOKUP($Q$15,Sheet1!J4:M4,3,0),0) -> 0 | R18: =+IFERROR(VLOOKUP($R$15,Sheet1!J4:M4,3,0),0) -> 0 | S18: =+IFERROR(VLOOKUP($S$15,Sheet1!N4:Q4,3,0),0) -> 0 | T18: =+IFERROR(VLOOKUP($T$15,Sheet1!N4:Q4,3,0),0) -> 0 | U18: =+IFERROR(VLOOKUP($U$15,Sheet1!F4:I4,3,0),0) -> 0 | V18: =+IFERROR(VLOOKUP($V$15,Sheet1!F4:I4,3,0),0) -> 0 | W18: =+IFERROR(VLOOKUP($W$15,Sheet1!F4:I4,3,0),0) -> 0 | X18: =+IFERROR(VLOOKUP($X$15,Sheet1!F4:I4,3,0),0) -> 0 | Y18: =+IFERROR(VLOOKUP($Y$15,Sheet1!F4:I4,3,0),0) -> 0 | Z18: =+IFERROR(VLOOKUP($Z$15,Sheet1!F4:I4,3,0),0) -> 0 | AA18: =+IFERROR(VLOOKUP($AA$15,Sheet1!F4:I4,3,0),0) -> 0 | AB18: =+IFERROR(VLOOKUP($AB$15,Sheet1!F4:I4,3,0),0) -> 0 | AC18: =+IFERROR(VLOOKUP($AC$15,Sheet1!R4:U4,3,0),0) -> 0 | AD18: =+IFERROR(VLOOKUP($AD$15,Sheet1!R4:U4,2,0),0) -> 0 | AE18: =+IFERROR(VLOOKUP($AE$15,Sheet1!V4:Y4,3,0),0) -> 0 | AF18: =+IFERROR(VLOOKUP($AF$15,Sheet1!V4:Y4,3,0),0) -> 109 | AG18: =+IFERROR(VLOOKUP($AG$15,Sheet1!V4:Y4,3,0),0) -> 0 | AH18: =+IFERROR(VLOOKUP($AH$15,Sheet1!V4:Y4,3,0),0) -> 0 | AI18: =+IFERROR(VLOOKUP($AI$15,Sheet1!V4:Y4,3,0),0) -> 0 | AJ18: =+IFERROR(VLOOKUP($AJ$15,Sheet1!V4:Y4,3,0),0) -> 0 | AK18: =+IFERROR(VLOOKUP($AK$15,Sheet1!Z4:AB4,3,0),0) -> 0 | AL18: =+IFERROR(VLOOKUP($AL$15,Sheet1!AD4:AG4,3,0),0) -> 0 | AM18: =+IFERROR(VLOOKUP($AM$15,Sheet1!AD4:AG4,3,0),0) -> 0 | AN18: =+IFERROR(VLOOKUP($AN$15,Sheet1!AD4:AG4,3,0),0) -> 0 | AO18: =+IFERROR(VLOOKUP($AO$15,Sheet1!AD4:AG4,3,0),0) -> 0 | AP18: =+IFERROR(VLOOKUP($AP$15,Sheet1!AD4:AG4,3,0),0) -> 0 | AQ18: =+IFERROR(VLOOKUP($AQ$15,Sheet1!AD4:AG4,3,0),0) -> 51 | AR18: =+IFERROR(VLOOKUP($AR$15,Sheet1!AD4:AG4,3,0),0) -> 0 | AS18: =+IFERROR(VLOOKUP($AS$15,Sheet1!AH4:AK4,3,0),0) -> 0 | AT18: =+IFERROR(VLOOKUP($AT$15,Sheet1!AH4:AK4,3,0),0) -> 0 | AU18: =+IFERROR(VLOOKUP($AU$15,Sheet1!AH4:AK4,3,0),0) -> 0 | AV18: =+IFERROR(VLOOKUP($AV$15,Sheet1!AH4:AK4,3,0),0) -> 0 | AW18: =+IFERROR(VLOOKUP($AW$15,Sheet1!AH4:AK4,3,0),0) -> 0 | AX18: =+IFERROR(VLOOKUP($AX$15,Sheet1!AH4:AK4,3,0),0) -> 0 | AY18: =+IFERROR(VLOOKUP($AY$15,Sheet1!AH4:AK4,3,0),0) -> 0 | AZ18: =+IFERROR(VLOOKUP($AZ$15,Sheet1!AH4:AK4,3,0),0) -> 0 | BA18: =+IFERROR(VLOOKUP($BA$15,Sheet1!AH4:AK4,3,0),0) -> 0 | BB18: =+IFERROR(VLOOKUP($BB$15,Sheet1!AH4:AK4,3,0),0) -> 0 | BC18: =+IFERROR(VLOOKUP($BC$15,Sheet1!AL4:AO4,3,0),0) -> 0 | BD18: =+IFERROR(VLOOKUP($BD$15,Sheet1!AL4:AO4,3,0),0) -> 0 | BE18: =+IFERROR(VLOOKUP($BE$15,Sheet1!AL4:AO4,3,0),0) -> 0 | BF18: =+IFERROR(VLOOKUP($BF$15,Sheet1!AL4:AO4,3,0),0) -> 228 | BG18: =+IFERROR(VLOOKUP($BG$15,Sheet1!AL4:AO4,3,0),0) -> 0 | BH18: =+IFERROR(VLOOKUP($BH$15,Sheet1!AL4:AO4,3,0),0) -> 0 | BI18: =+IFERROR(VLOOKUP($BI$15,Sheet1!AL4:AO4,3,0),0) -> 0 | BJ18: =+IFERROR(VLOOKUP($BJ$15,Sheet1!AL4:AO4,3,0),0) -> 0 | BK18: =+IFERROR(VLOOKUP($BK$15,Sheet1!AL4:AO4,3,0),0) -> 0 | BL18: =+IFERROR(VLOOKUP($BL$15,Sheet1!AL4:AO4,3,0),0) -> 0 | BM18: =+IFERROR(VLOOKUP($BM$15,Sheet1!AP4:AS4,3,0),0) -> 0 | BN18: =+IFERROR(VLOOKUP($BN$15,Sheet1!AT4:AW4,3,0),0) -> 0 | BO18: =+IFERROR(VLOOKUP($BO$15,Sheet1!AX4:BA4,3,0),0) -> 0 | BP18: =+IFERROR(VLOOKUP($BP$15,Sheet1!BB4:BE4,3,0),0) -> 0 | BQ18: =+IFERROR(VLOOKUP($BQ$15,Sheet1!BF4:BI4,3,0),0) -> 0 | BR18: =+IFERROR(VLOOKUP($BR$15,Sheet1!BJ4:BM4,3,0),0) -> 0 | BS18: =+IFERROR(VLOOKUP($BS$15,Sheet1!BN4:BQ4,3,0),0) -> 0 | BT18: =+IFERROR(VLOOKUP($BT$15,Sheet1!BR4:BU4,3,0),0) -> 0 | BU18: =+IFERROR(VLOOKUP($BU$15,Sheet1!BV4:BY4,3,0),0) -> 0 | BV18: =Sheet1!E4 -> WOOD | BW18: =Sheet1!CV4 -> MD0100015 | BX18: =Sheet1!CW4 -> DRUM - 48 X 20 X 28 X 2.25 - RDSO | BY18: 500 | BZ18: =Sheet1!BZ4 -> 7317.08 | CA18: =SUMPRODUCT($N$16:$BU$16,N18:BU18)+BZ18 -> 126104.08 | CB18: =Sheet1!CB4 -> 0 | CC18: =CA18*CB18 -> 0 | CD18: 0.35 | CE18: =CA18*CD18 -> 44136.428 | CF18: 0 | CG18: =CA18*CF18 -> 0 | CH18: =CA18+CC18+CE18+CG18 -> 170240.51 | CI18: 0.02 | CJ18: =CH18*CI18 -> 3404.8102 | CK18: 0.01 | CL18: =CH18*CK18 -> 1702.4051
A19: =Sheet1!A6 -> ENQ-11226-22-23 | B19: =Sheet1!B6 -> 45194 | C19: =Sheet1!C6 -> FA0900013 | D19: =Sheet1!D6 -> 4 CORE X 16 SQ. MM. ALU/ARD - STRIP (XLPE) | E19: =CH19+CJ19+CL19 -> 124789.7 | F19: =ROUND(E19*$F$16,2) -> 4367.64 | G19: =E19+F19 -> 129157.34 | H19: 0.18 | I19: =G19*H19 -> 23248.321 | J19: =G19+I19 -> 152405.66 | K19: =Sheet1!CS6 -> 2 | L19: =Sheet1!CT6 -> KMS | M19: =J19*K19 -> 304811.32 | N19: 173 | O19: =+IFERROR(VLOOKUP($O$15,Sheet1!J6:L6,3,0),0) -> 0 | P19: =+IFERROR(VLOOKUP($P$15,Sheet1!J6:M6,3,0),0) -> 0 | Q19: =+IFERROR(VLOOKUP($Q$15,Sheet1!J6:M6,3,0),0) -> 0 | R19: =+IFERROR(VLOOKUP($R$15,Sheet1!J6:M6,3,0),0) -> 0 | S19: =+IFERROR(VLOOKUP($S$15,Sheet1!N6:Q6,3,0),0) -> 0 | T19: =+IFERROR(VLOOKUP($T$15,Sheet1!N6:Q6,3,0),0) -> 0 | U19: =+IFERROR(VLOOKUP($U$15,Sheet1!F6:I6,3,0),0) -> 0 | V19: =+IFERROR(VLOOKUP($V$15,Sheet1!F6:I6,3,0),0) -> 0 | W19: =+IFERROR(VLOOKUP($W$15,Sheet1!F6:I6,3,0),0) -> 0 | X19: =+IFERROR(VLOOKUP($X$15,Sheet1!F6:I6,3,0),0) -> 0 | Y19: =+IFERROR(VLOOKUP($Y$15,Sheet1!F6:I6,3,0),0) -> 0 | Z19: =+IFERROR(VLOOKUP($Z$15,Sheet1!F6:I6,3,0),0) -> 0 | AA19: =+IFERROR(VLOOKUP($AA$15,Sheet1!F6:I6,3,0),0) -> 0 | AB19: =+IFERROR(VLOOKUP($AB$15,Sheet1!F6:I6,3,0),0) -> 0 | AC19: =+IFERROR(VLOOKUP($AC$15,Sheet1!R6:U6,3,0),0) -> 0 | AD19: =+IFERROR(VLOOKUP($AD$15,Sheet1!R6:U6,2,0),0) -> 0 | AE19: =+IFERROR(VLOOKUP($AE$15,Sheet1!V6:Y6,3,0),0) -> 0 | AF19: =+IFERROR(VLOOKUP($AF$15,Sheet1!V6:Y6,3,0),0) -> 63 | AG19: =+IFERROR(VLOOKUP($AG$15,Sheet1!V6:Y6,3,0),0) -> 0 | AH19: =+IFERROR(VLOOKUP($AH$15,Sheet1!V6:Y6,3,0),0) -> 0 | AI19: =+IFERROR(VLOOKUP($AI$15,Sheet1!V6:Y6,3,0),0) -> 0 | AJ19: =+IFERROR(VLOOKUP($AJ$15,Sheet1!V6:Y6,3,0),0) -> 0 | AK19: =+IFERROR(VLOOKUP($AK$15,Sheet1!Z6:AB6,3,0),0) -> 0 | AL19: =+IFERROR(VLOOKUP($AL$15,Sheet1!AD6:AG6,3,0),0) -> 0 | AM19: =+IFERROR(VLOOKUP($AM$15,Sheet1!AD6:AG6,3,0),0) -> 0 | AN19: =+IFERROR(VLOOKUP($AN$15,Sheet1!AD6:AG6,3,0),0) -> 0 | AO19: =+IFERROR(VLOOKUP($AO$15,Sheet1!AD6:AG6,3,0),0) -> 0 | AP19: =+IFERROR(VLOOKUP($AP$15,Sheet1!AD6:AG6,3,0),0) -> 0 | AQ19: =+IFERROR(VLOOKUP($AQ$15,Sheet1!AD6:AG6,3,0),0) -> 40 | AR19: =+IFERROR(VLOOKUP($AR$15,Sheet1!AD6:AG6,3,0),0) -> 0 | AS19: =+IFERROR(VLOOKUP($AS$15,Sheet1!AH6:AK6,3,0),0) -> 0 | AT19: =+IFERROR(VLOOKUP($AT$15,Sheet1!AH6:AK6,3,0),0) -> 0 | AU19: =+IFERROR(VLOOKUP($AU$15,Sheet1!AH6:AK6,3,0),0) -> 0 | AV19: =+IFERROR(VLOOKUP($AV$15,Sheet1!AH6:AK6,3,0),0) -> 0 | AW19: =+IFERROR(VLOOKUP($AW$15,Sheet1!AH6:AK6,3,0),0) -> 0 | AX19: =+IFERROR(VLOOKUP($AX$15,Sheet1!AH6:AK6,3,0),0) -> 300 | AY19: =+IFERROR(VLOOKUP($AY$15,Sheet1!AH6:AK6,3,0),0) -> 0 | AZ19: =+IFERROR(VLOOKUP($AZ$15,Sheet1!AH6:AK6,3,0),0) -> 0 | BA19: =+IFERROR(VLOOKUP($BA$15,Sheet1!AH6:AK6,3,0),0) -> 0 | BB19: =+IFERROR(VLOOKUP($BB$15,Sheet1!AH6:AK6,3,0),0) -> 0 | BC19: =+IFERROR(VLOOKUP($BC$15,Sheet1!AL6:AO6,3,0),0) -> 0 | BD19: =+IFERROR(VLOOKUP($BD$15,Sheet1!AL6:AO6,3,0),0) -> 0 | BE19: =+IFERROR(VLOOKUP($BE$15,Sheet1!AL6:AO6,3,0),0) -> 0 | BF19: =+IFERROR(VLOOKUP($BF$15,Sheet1!AL6:AO6,3,0),0) -> 146 | BG19: =+IFERROR(VLOOKUP($BG$15,Sheet1!AL6:AO6,3,0),0) -> 0 | BH19: =+IFERROR(VLOOKUP($BH$15,Sheet1!AL6:AO6,3,0),0) -> 0 | BI19: =+IFERROR(VLOOKUP($BI$15,Sheet1!AL6:AO6,3,0),0) -> 0 | BJ19: =+IFERROR(VLOOKUP($BJ$15,Sheet1!AL6:AO6,3,0),0) -> 0 | BK19: =+IFERROR(VLOOKUP($BK$15,Sheet1!AL6:AO6,3,0),0) -> 0 | BL19: =+IFERROR(VLOOKUP($BL$15,Sheet1!AL6:AO6,3,0),0) -> 0 | BM19: =+IFERROR(VLOOKUP($BM$15,Sheet1!AP6:AS6,3,0),0) -> 0 | BN19: =+IFERROR(VLOOKUP($BN$15,Sheet1!AT6:AW6,3,0),0) -> 0 | BO19: =+IFERROR(VLOOKUP($BO$15,Sheet1!AX6:BA6,3,0),0) -> 0 | BP19: =+IFERROR(VLOOKUP($BP$15,Sheet1!BB6:BE6,3,0),0) -> 0 | BQ19: =+IFERROR(VLOOKUP($BQ$15,Sheet1!BF6:BI6,3,0),0) -> 0 | BR19: =+IFERROR(VLOOKUP($BR$15,Sheet1!BJ6:BM6,3,0),0) -> 0 | BS19: =+IFERROR(VLOOKUP($BS$15,Sheet1!BN6:BQ6,3,0),0) -> 0 | BT19: =+IFERROR(VLOOKUP($BT$15,Sheet1!BR6:BU6,3,0),0) -> 0 | BU19: =+IFERROR(VLOOKUP($BU$15,Sheet1!BV6:BY6,3,0),0) -> 0 | BV19: =Sheet1!E6 -> WOOD | BW19: =Sheet1!CV6 -> MD0100066 | BX19: =Sheet1!CW6 -> DRUM - 40 X 15 X 23 X 2 | BY19: 500 | BZ19: =Sheet1!BZ6 -> 5151.48 | CA19: =SUMPRODUCT($N$16:$BU$16,N19:BU19)+BZ19 -> 89744.48 | CB19: =Sheet1!CB6 -> 0 | CC19: =CA19*CB19 -> 0 | CD19: 0.35 | CE19: =CA19*CD19 -> 31410.568 | CF19: 0 | CG19: =CA19*CF19 -> 0 | CH19: =CA19+CC19+CE19+CG19 -> 121155.05 | CI19: 0.02 | CJ19: =CH19*CI19 -> 2423.101 | CK19: 0.01 | CL19: =CH19*CK19 -> 1211.5505
A20: =Sheet1!A3 -> ENQ-11226-22-23 | B20: =Sheet1!B3 -> 45194 | C20: =Sheet1!C3 -> FA1000014 | D20: =Sheet1!D3 -> 4 CORE X 16 SQ. MM. ALU/UNARD (XLPE) | E20: =CH20+CJ20+CL20 -> 93420.019 | F20: =ROUND(E20*$F$16,2) -> 3269.7 | G20: =E20+F20 -> 96689.719 | H20: 0.18 | I20: =G20*H20 -> 17404.149 | J20: =G20+I20 -> 114093.87 | K20: =Sheet1!CS3 -> 0.5 | L20: =Sheet1!CT3 -> KMS | M20: =J20*K20 -> 57046.934 | N20: 173 | O20: =+IFERROR(VLOOKUP($O$15,Sheet1!J3:L3,3,0),0) -> 0 | P20: =+IFERROR(VLOOKUP($P$15,Sheet1!J3:M3,3,0),0) -> 0 | Q20: =+IFERROR(VLOOKUP($Q$15,Sheet1!J3:M3,3,0),0) -> 0 | R20: =+IFERROR(VLOOKUP($R$15,Sheet1!J3:M3,3,0),0) -> 0 | S20: =+IFERROR(VLOOKUP($S$15,Sheet1!N3:Q3,3,0),0) -> 0 | T20: =+IFERROR(VLOOKUP($T$15,Sheet1!N3:Q3,3,0),0) -> 0 | U20: =+IFERROR(VLOOKUP($U$15,Sheet1!F3:I3,3,0),0) -> 0 | V20: =+IFERROR(VLOOKUP($V$15,Sheet1!F3:I3,3,0),0) -> 0 | W20: =+IFERROR(VLOOKUP($W$15,Sheet1!F3:I3,3,0),0) -> 0 | X20: =+IFERROR(VLOOKUP($X$15,Sheet1!F3:I3,3,0),0) -> 0 | Y20: =+IFERROR(VLOOKUP($Y$15,Sheet1!F3:I3,3,0),0) -> 0 | Z20: =+IFERROR(VLOOKUP($Z$15,Sheet1!F3:I3,3,0),0) -> 0 | AA20: =+IFERROR(VLOOKUP($AA$15,Sheet1!F3:I3,3,0),0) -> 0 | AB20: =+IFERROR(VLOOKUP($AB$15,Sheet1!F3:I3,3,0),0) -> 0 | AC20: =+IFERROR(VLOOKUP($AC$15,Sheet1!R3:U3,3,0),0) -> 0 | AD20: =+IFERROR(VLOOKUP($AD$15,Sheet1!R3:U3,2,0),0) -> 0 | AE20: =+IFERROR(VLOOKUP($AE$15,Sheet1!V3:Y3,3,0),0) -> 0 | AF20: =+IFERROR(VLOOKUP($AF$15,Sheet1!V3:Y3,3,0),0) -> 63 | AG20: =+IFERROR(VLOOKUP($AG$15,Sheet1!V3:Y3,3,0),0) -> 0 | AH20: =+IFERROR(VLOOKUP($AH$15,Sheet1!V3:Y3,3,0),0) -> 0 | AI20: =+IFERROR(VLOOKUP($AI$15,Sheet1!V3:Y3,3,0),0) -> 0 | AJ20: =+IFERROR(VLOOKUP($AJ$15,Sheet1!V3:Y3,3,0),0) -> 0 | AK20: =+IFERROR(VLOOKUP($AK$15,Sheet1!Z3:AB3,3,0),0) -> 0 | AL20: =+IFERROR(VLOOKUP($AL$15,Sheet1!AD3:AG3,3,0),0) -> 0 | AM20: =+IFERROR(VLOOKUP($AM$15,Sheet1!AD3:AG3,3,0),0) -> 0 | AN20: =+IFERROR(VLOOKUP($AN$15,Sheet1!AD3:AG3,3,0),0) -> 0 | AO20: =+IFERROR(VLOOKUP($AO$15,Sheet1!AD3:AG3,3,0),0) -> 0 | AP20: =+IFERROR(VLOOKUP($AP$15,Sheet1!AD3:AG3,3,0),0) -> 0 | AQ20: =+IFERROR(VLOOKUP($AQ$15,Sheet1!AD3:AG3,3,0),0) -> 40 | AR20: =+IFERROR(VLOOKUP($AR$15,Sheet1!AD3:AG3,3,0),0) -> 0 | AS20: =+IFERROR(VLOOKUP($AS$15,Sheet1!AH3:AK3,3,0),0) -> 0 | AT20: =+IFERROR(VLOOKUP($AT$15,Sheet1!AH3:AK3,3,0),0) -> 0 | AU20: =+IFERROR(VLOOKUP($AU$15,Sheet1!AH3:AK3,3,0),0) -> 0 | AV20: =+IFERROR(VLOOKUP($AV$15,Sheet1!AH3:AK3,3,0),0) -> 0 | AW20: =+IFERROR(VLOOKUP($AW$15,Sheet1!AH3:AK3,3,0),0) -> 0 | AX20: =+IFERROR(VLOOKUP($AX$15,Sheet1!AH3:AK3,3,0),0) -> 0 | AY20: =+IFERROR(VLOOKUP($AY$15,Sheet1!AH3:AK3,3,0),0) -> 0 | AZ20: =+IFERROR(VLOOKUP($AZ$15,Sheet1!AH3:AK3,3,0),0) -> 0 | BA20: =+IFERROR(VLOOKUP($BA$15,Sheet1!AH3:AK3,3,0),0) -> 0 | BB20: =+IFERROR(VLOOKUP($BB$15,Sheet1!AH3:AK3,3,0),0) -> 0 | BC20: =+IFERROR(VLOOKUP($BC$15,Sheet1!AL3:AO3,3,0),0) -> 0 | BD20: =+IFERROR(VLOOKUP($BD$15,Sheet1!AL3:AO3,3,0),0) -> 0 | BE20: =+IFERROR(VLOOKUP($BE$15,Sheet1!AL3:AO3,3,0),0) -> 0 | BF20: 158 | BG20: =+IFERROR(VLOOKUP($BG$15,Sheet1!AL3:AO3,3,0),0) -> 0 | BH20: =+IFERROR(VLOOKUP($BH$15,Sheet1!AL3:AO3,3,0),0) -> 0 | BI20: =+IFERROR(VLOOKUP($BI$15,Sheet1!AL3:AO3,3,0),0) -> 0 | BJ20: =+IFERROR(VLOOKUP($BJ$15,Sheet1!AL3:AO3,3,0),0) -> 0 | BK20: =+IFERROR(VLOOKUP($BK$15,Sheet1!AL3:AO3,3,0),0) -> 0 | BL20: =+IFERROR(VLOOKUP($BL$15,Sheet1!AL3:AO3,3,0),0) -> 0 | BM20: =+IFERROR(VLOOKUP($BM$15,Sheet1!AP3:AS3,3,0),0) -> 0 | BN20: =+IFERROR(VLOOKUP($BN$15,Sheet1!AT3:AW3,3,0),0) -> 0 | BO20: =+IFERROR(VLOOKUP($BO$15,Sheet1!AX3:BA3,3,0),0) -> 0 | BP20: =+IFERROR(VLOOKUP($BP$15,Sheet1!BB3:BE3,3,0),0) -> 0 | BQ20: =+IFERROR(VLOOKUP($BQ$15,Sheet1!BF3:BI3,3,0),0) -> 0 | BR20: =+IFERROR(VLOOKUP($BR$15,Sheet1!BJ3:BM3,3,0),0) -> 0 | BS20: =+IFERROR(VLOOKUP($BS$15,Sheet1!BN3:BQ3,3,0),0) -> 0 | BT20: =+IFERROR(VLOOKUP($BT$15,Sheet1!BR3:BU3,3,0),0) -> 0 | BU20: =+IFERROR(VLOOKUP($BU$15,Sheet1!BV3:BY3,3,0),0) -> 0 | BV20: =Sheet1!E3 -> WOOD | BW20: =Sheet1!CV3 -> MD0100066 | BX20: =Sheet1!CW3 -> DRUM - 40 X 15 X 23 X 2 | BY20: 500 | BZ20: =Sheet1!BZ3 -> 5151.48 | CA20: =SUMPRODUCT($N$16:$BU$16,N20:BU20)+BZ20 -> 67184.48 | CB20: =Sheet1!CB3 -> 0 | CC20: =CA20*CB20 -> 0 | CD20: 0.35 | CE20: =CA20*CD20 -> 23514.568 | CF20: 0 | CG20: =CA20*CF20 -> 0 | CH20: =CA20+CC20+CE20+CG20 -> 90699.048 | CI20: 0.02 | CJ20: =CH20*CI20 -> 1813.981 | CK20: 0.01 | CL20: =CH20*CK20 -> 906.99048
A21: =Sheet1!A5 -> ENQ-11226-22-23 | B21: =Sheet1!B5 -> 45194 | C21: =Sheet1!C5 -> FA1000048 | D21: =Sheet1!D5 -> 4 CORE X 10 SQ. MM. AL/UNARD (XLPE) | E21: =CH21+CJ21+CL21 -> 71241.975 | F21: =ROUND(E21*$F$16,2) -> 2493.47 | G21: =E21+F21 -> 73735.445 | H21: 0.18 | I21: =G21*H21 -> 13272.38 | J21: =G21+I21 -> 87007.826 | K21: =Sheet1!CS5 -> 1 | L21: =Sheet1!CT5 -> KMS | M21: =J21*K21 -> 87007.826 | N21: =+IFERROR(VLOOKUP($N$15,Sheet1!J5:L5,3,0),0) -> 108 | O21: =+IFERROR(VLOOKUP($O$15,Sheet1!J5:L5,3,0),0) -> 0 | P21: =+IFERROR(VLOOKUP($P$15,Sheet1!J5:M5,3,0),0) -> 0 | Q21: =+IFERROR(VLOOKUP($Q$15,Sheet1!J5:M5,3,0),0) -> 0 | R21: =+IFERROR(VLOOKUP($R$15,Sheet1!J5:M5,3,0),0) -> 0 | S21: =+IFERROR(VLOOKUP($S$15,Sheet1!N5:Q5,3,0),0) -> 0 | T21: =+IFERROR(VLOOKUP($T$15,Sheet1!N5:Q5,3,0),0) -> 0 | U21: =+IFERROR(VLOOKUP($U$15,Sheet1!F5:I5,3,0),0) -> 0 | V21: =+IFERROR(VLOOKUP($V$15,Sheet1!F5:I5,3,0),0) -> 0 | W21: =+IFERROR(VLOOKUP($W$15,Sheet1!F5:I5,3,0),0) -> 0 | X21: =+IFERROR(VLOOKUP($X$15,Sheet1!F5:I5,3,0),0) -> 0 | Y21: =+IFERROR(VLOOKUP($Y$15,Sheet1!F5:I5,3,0),0) -> 0 | Z21: =+IFERROR(VLOOKUP($Z$15,Sheet1!F5:I5,3,0),0) -> 0 | AA21: =+IFERROR(VLOOKUP($AA$15,Sheet1!F5:I5,3,0),0) -> 0 | AB21: =+IFERROR(VLOOKUP($AB$15,Sheet1!F5:I5,3,0),0) -> 0 | AC21: =+IFERROR(VLOOKUP($AC$15,Sheet1!R5:U5,3,0),0) -> 0 | AD21: =+IFERROR(VLOOKUP($AD$15,Sheet1!R5:U5,2,0),0) -> 0 | AE21: =+IFERROR(VLOOKUP($AE$15,Sheet1!V5:Y5,3,0),0) -> 0 | AF21: =+IFERROR(VLOOKUP($AF$15,Sheet1!V5:Y5,3,0),0) -> 64 | AG21: =+IFERROR(VLOOKUP($AG$15,Sheet1!V5:Y5,3,0),0) -> 0 | AH21: =+IFERROR(VLOOKUP($AH$15,Sheet1!V5:Y5,3,0),0) -> 0 | AI21: =+IFERROR(VLOOKUP($AI$15,Sheet1!V5:Y5,3,0),0) -> 0 | AJ21: =+IFERROR(VLOOKUP($AJ$15,Sheet1!V5:Y5,3,0),0) -> 0 | AK21: =+IFERROR(VLOOKUP($AK$15,Sheet1!Z5:AB5,3,0),0) -> 0 | AL21: =+IFERROR(VLOOKUP($AL$15,Sheet1!AD5:AG5,3,0),0) -> 0 | AM21: =+IFERROR(VLOOKUP($AM$15,Sheet1!AD5:AG5,3,0),0) -> 0 | AN21: =+IFERROR(VLOOKUP($AN$15,Sheet1!AD5:AG5,3,0),0) -> 0 | AO21: =+IFERROR(VLOOKUP($AO$15,Sheet1!AD5:AG5,3,0),0) -> 0 | AP21: =+IFERROR(VLOOKUP($AP$15,Sheet1!AD5:AG5,3,0),0) -> 0 | AQ21: =+IFERROR(VLOOKUP($AQ$15,Sheet1!AD5:AG5,3,0),0) -> 35 | AR21: =+IFERROR(VLOOKUP($AR$15,Sheet1!AD5:AG5,3,0),0) -> 0 | AS21: =+IFERROR(VLOOKUP($AS$15,Sheet1!AH5:AK5,3,0),0) -> 0 | AT21: =+IFERROR(VLOOKUP($AT$15,Sheet1!AH5:AK5,3,0),0) -> 0 | AU21: =+IFERROR(VLOOKUP($AU$15,Sheet1!AH5:AK5,3,0),0) -> 0 | AV21: =+IFERROR(VLOOKUP($AV$15,Sheet1!AH5:AK5,3,0),0) -> 0 | AW21: =+IFERROR(VLOOKUP($AW$15,Sheet1!AH5:AK5,3,0),0) -> 0 | AX21: =+IFERROR(VLOOKUP($AX$15,Sheet1!AH5:AK5,3,0),0) -> 0 | AY21: =+IFERROR(VLOOKUP($AY$15,Sheet1!AH5:AK5,3,0),0) -> 0 | AZ21: =+IFERROR(VLOOKUP($AZ$15,Sheet1!AH5:AK5,3,0),0) -> 0 | BA21: =+IFERROR(VLOOKUP($BA$15,Sheet1!AH5:AK5,3,0),0) -> 0 | BB21: =+IFERROR(VLOOKUP($BB$15,Sheet1!AH5:AK5,3,0),0) -> 0 | BC21: =+IFERROR(VLOOKUP($BC$15,Sheet1!AL5:AO5,3,0),0) -> 0 | BD21: =+IFERROR(VLOOKUP($BD$15,Sheet1!AL5:AO5,3,0),0) -> 0 | BE21: =+IFERROR(VLOOKUP($BE$15,Sheet1!AL5:AO5,3,0),0) -> 0 | BF21: =+IFERROR(VLOOKUP($BF$15,Sheet1!AL5:AO5,3,0),0) -> 145 | BG21: =+IFERROR(VLOOKUP($BG$15,Sheet1!AL5:AO5,3,0),0) -> 0 | BH21: =+IFERROR(VLOOKUP($BH$15,Sheet1!AL5:AO5,3,0),0) -> 0 | BI21: =+IFERROR(VLOOKUP($BI$15,Sheet1!AL5:AO5,3,0),0) -> 0 | BJ21: =+IFERROR(VLOOKUP($BJ$15,Sheet1!AL5:AO5,3,0),0) -> 0 | BK21: =+IFERROR(VLOOKUP($BK$15,Sheet1!AL5:AO5,3,0),0) -> 0 | BL21: =+IFERROR(VLOOKUP($BL$15,Sheet1!AL5:AO5,3,0),0) -> 0 | BM21: =+IFERROR(VLOOKUP($BM$15,Sheet1!AP5:AS5,3,0),0) -> 0 | BN21: =+IFERROR(VLOOKUP($BN$15,Sheet1!AT5:AW5,3,0),0) -> 0 | BO21: =+IFERROR(VLOOKUP($BO$15,Sheet1!AX5:BA5,3,0),0) -> 0 | BP21: =+IFERROR(VLOOKUP($BP$15,Sheet1!BB5:BE5,3,0),0) -> 0 | BQ21: =+IFERROR(VLOOKUP($BQ$15,Sheet1!BF5:BI5,3,0),0) -> 0 | BR21: =+IFERROR(VLOOKUP($BR$15,Sheet1!BJ5:BM5,3,0),0) -> 0 | BS21: =+IFERROR(VLOOKUP($BS$15,Sheet1!BN5:BQ5,3,0),0) -> 0 | BT21: =+IFERROR(VLOOKUP($BT$15,Sheet1!BR5:BU5,3,0),0) -> 0 | BU21: =+IFERROR(VLOOKUP($BU$15,Sheet1!BV5:BY5,3,0),0) -> 0 | BV21: =Sheet1!E5 -> WOOD | BW21: =Sheet1!CV5 -> MD0100005 | BX21: =Sheet1!CW5 -> DRUM - 36 X 14 X 23 X 2 | BY21: 500 | BZ21: =Sheet1!BZ5 -> 4610.79 | CA21: =SUMPRODUCT($N$16:$BU$16,N21:BU21)+BZ21 -> 51234.79 | CB21: =Sheet1!CB5 -> 0 | CC21: =CA21*CB21 -> 0 | CD21: 0.35 | CE21: =CA21*CD21 -> 17932.176 | CF21: 0 | CG21: =CA21*CF21 -> 0 | CH21: =CA21+CC21+CE21+CG21 -> 69166.966 | CI21: 0.02 | CJ21: =CH21*CI21 -> 1383.3393 | CK21: 0.01 | CL21: =CH21*CK21 -> 691.66967
A22: =Sheet1!A7 -> ENQ-11226-22-23 | B22: =Sheet1!B7 -> 45194 | C22: =Sheet1!C7 -> FA1000026 | D22: =Sheet1!D7 -> 4 CORE X 6 SQ. MM. AL/UNARD.(XLPE) | E22: =CH22+CJ22+CL22 -> 53736.971 | F22: =ROUND(E22*$F$16,2) -> 1880.79 | G22: =E22+F22 -> 55617.761 | H22: 0.18 | I22: =G22*H22 -> 10011.197 | J22: =G22+I22 -> 65628.958 | K22: =Sheet1!CS7 -> 2 | L22: =Sheet1!CT7 -> KMS | M22: =J22*K22 -> 131257.92 | N22: =+IFERROR(VLOOKUP($N$15,Sheet1!J7:L7,3,0),0) -> 64.8 | O22: =+IFERROR(VLOOKUP($O$15,Sheet1!J7:L7,3,0),0) -> 0 | P22: =+IFERROR(VLOOKUP($P$15,Sheet1!J7:M7,3,0),0) -> 0 | Q22: =+IFERROR(VLOOKUP($Q$15,Sheet1!J7:M7,3,0),0) -> 0 | R22: =+IFERROR(VLOOKUP($R$15,Sheet1!J7:M7,3,0),0) -> 0 | S22: =+IFERROR(VLOOKUP($S$15,Sheet1!N7:Q7,3,0),0) -> 0 | T22: =+IFERROR(VLOOKUP($T$15,Sheet1!N7:Q7,3,0),0) -> 0 | U22: =+IFERROR(VLOOKUP($U$15,Sheet1!F7:I7,3,0),0) -> 0 | V22: =+IFERROR(VLOOKUP($V$15,Sheet1!F7:I7,3,0),0) -> 0 | W22: =+IFERROR(VLOOKUP($W$15,Sheet1!F7:I7,3,0),0) -> 0 | X22: =+IFERROR(VLOOKUP($X$15,Sheet1!F7:I7,3,0),0) -> 0 | Y22: =+IFERROR(VLOOKUP($Y$15,Sheet1!F7:I7,3,0),0) -> 0 | Z22: =+IFERROR(VLOOKUP($Z$15,Sheet1!F7:I7,3,0),0) -> 0 | AA22: =+IFERROR(VLOOKUP($AA$15,Sheet1!F7:I7,3,0),0) -> 0 | AB22: =+IFERROR(VLOOKUP($AB$15,Sheet1!F7:I7,3,0),0) -> 0 | AC22: =+IFERROR(VLOOKUP($AC$15,Sheet1!R7:U7,3,0),0) -> 0 | AD22: =+IFERROR(VLOOKUP($AD$15,Sheet1!R7:U7,2,0),0) -> 0 | AE22: =+IFERROR(VLOOKUP($AE$15,Sheet1!V7:Y7,3,0),0) -> 0 | AF22: =+IFERROR(VLOOKUP($AF$15,Sheet1!V7:Y7,3,0),0) -> 53 | AG22: =+IFERROR(VLOOKUP($AG$15,Sheet1!V7:Y7,3,0),0) -> 0 | AH22: =+IFERROR(VLOOKUP($AH$15,Sheet1!V7:Y7,3,0),0) -> 0 | AI22: =+IFERROR(VLOOKUP($AI$15,Sheet1!V7:Y7,3,0),0) -> 0 | AJ22: =+IFERROR(VLOOKUP($AJ$15,Sheet1!V7:Y7,3,0),0) -> 0 | AK22: =+IFERROR(VLOOKUP($AK$15,Sheet1!Z7:AB7,3,0),0) -> 0 | AL22: =+IFERROR(VLOOKUP($AL$15,Sheet1!AD7:AG7,3,0),0) -> 0 | AM22: =+IFERROR(VLOOKUP($AM$15,Sheet1!AD7:AG7,3,0),0) -> 0 | AN22: =+IFERROR(VLOOKUP($AN$15,Sheet1!AD7:AG7,3,0),0) -> 0 | AO22: =+IFERROR(VLOOKUP($AO$15,Sheet1!AD7:AG7,3,0),0) -> 0 | AP22: =+IFERROR(VLOOKUP($AP$15,Sheet1!AD7:AG7,3,0),0) -> 0 | AQ22: =+IFERROR(VLOOKUP($AQ$15,Sheet1!AD7:AG7,3,0),0) -> 30 | AR22: =+IFERROR(VLOOKUP($AR$15,Sheet1!AD7:AG7,3,0),0) -> 0 | AS22: =+IFERROR(VLOOKUP($AS$15,Sheet1!AH7:AK7,3,0),0) -> 0 | AT22: =+IFERROR(VLOOKUP($AT$15,Sheet1!AH7:AK7,3,0),0) -> 0 | AU22: =+IFERROR(VLOOKUP($AU$15,Sheet1!AH7:AK7,3,0),0) -> 0 | AV22: =+IFERROR(VLOOKUP($AV$15,Sheet1!AH7:AK7,3,0),0) -> 0 | AW22: =+IFERROR(VLOOKUP($AW$15,Sheet1!AH7:AK7,3,0),0) -> 0 | AX22: =+IFERROR(VLOOKUP($AX$15,Sheet1!AH7:AK7,3,0),0) -> 0 | AY22: =+IFERROR(VLOOKUP($AY$15,Sheet1!AH7:AK7,3,0),0) -> 0 | AZ22: =+IFERROR(VLOOKUP($AZ$15,Sheet1!AH7:AK7,3,0),0) -> 0 | BA22: =+IFERROR(VLOOKUP($BA$15,Sheet1!AH7:AK7,3,0),0) -> 0 | BB22: =+IFERROR(VLOOKUP($BB$15,Sheet1!AH7:AK7,3,0),0) -> 0 | BC22: =+IFERROR(VLOOKUP($BC$15,Sheet1!AL7:AO7,3,0),0) -> 0 | BD22: =+IFERROR(VLOOKUP($BD$15,Sheet1!AL7:AO7,3,0),0) -> 0 | BE22: =+IFERROR(VLOOKUP($BE$15,Sheet1!AL7:AO7,3,0),0) -> 0 | BF22: =+IFERROR(VLOOKUP($BF$15,Sheet1!AL7:AO7,3,0),0) -> 127 | BG22: =+IFERROR(VLOOKUP($BG$15,Sheet1!AL7:AO7,3,0),0) -> 0 | BH22: =+IFERROR(VLOOKUP($BH$15,Sheet1!AL7:AO7,3,0),0) -> 0 | BI22: =+IFERROR(VLOOKUP($BI$15,Sheet1!AL7:AO7,3,0),0) -> 0 | BJ22: =+IFERROR(VLOOKUP($BJ$15,Sheet1!AL7:AO7,3,0),0) -> 0 | BK22: =+IFERROR(VLOOKUP($BK$15,Sheet1!AL7:AO7,3,0),0) -> 0 | BL22: =+IFERROR(VLOOKUP($BL$15,Sheet1!AL7:AO7,3,0),0) -> 0 | BM22: =+IFERROR(VLOOKUP($BM$15,Sheet1!AP7:AS7,3,0),0) -> 0 | BN22: =+IFERROR(VLOOKUP($BN$15,Sheet1!AT7:AW7,3,0),0) -> 0 | BO22: =+IFERROR(VLOOKUP($BO$15,Sheet1!AX7:BA7,3,0),0) -> 0 | BP22: =+IFERROR(VLOOKUP($BP$15,Sheet1!BB7:BE7,3,0),0) -> 0 | BQ22: =+IFERROR(VLOOKUP($BQ$15,Sheet1!BF7:BI7,3,0),0) -> 0 | BR22: =+IFERROR(VLOOKUP($BR$15,Sheet1!BJ7:BM7,3,0),0) -> 0 | BS22: =+IFERROR(VLOOKUP($BS$15,Sheet1!BN7:BQ7,3,0),0) -> 0 | BT22: =+IFERROR(VLOOKUP($BT$15,Sheet1!BR7:BU7,3,0),0) -> 0 | BU22: =+IFERROR(VLOOKUP($BU$15,Sheet1!BV7:BY7,3,0),0) -> 0 | BV22: =Sheet1!E7 -> WOOD | BW22: =Sheet1!CV7 -> MD0100005 | BX22: =Sheet1!CW7 -> DRUM - 36 X 14 X 23 X 2 | BY22: 500 | BZ22: =Sheet1!BZ7 -> 4610.79 | CA22: =SUMPRODUCT($N$16:$BU$16,N22:BU22)+BZ22 -> 38645.79 | CB22: =Sheet1!CB7 -> 0 | CC22: =CA22*CB22 -> 0 | CD22: 0.35 | CE22: =CA22*CD22 -> 13526.026 | CF22: 0 | CG22: =CA22*CF22 -> 0 | CH22: =CA22+CC22+CE22+CG22 -> 52171.817 | CI22: 0.02 | CJ22: =CH22*CI22 -> 1043.4363 | CK22: 0.01 | CL22: =CH22*CK22 -> 521.71816
D23: PENDENT CABLE 12 CORE,1.5 MM2 # ( Trailing Cable, 12C X 1.5 Sq.mm Rubber Insulated, flexible Cu, FRLS, 1.1kv grade,conform to IS : 9968 (Pt-1)/88 ) | E23: =CH23+CJ23+CL23 -> 0 | F23: =ROUND(E23*$F$16,2) -> 0 | G23: =E23+F23 -> 0 | H23: 0.18 | I23: =G23*H23 -> 0 | J23: =G23+I23 -> 0 | K23: 0.2 | L23: KMS | M23: =J23*K23 -> 0 | N23: =+IFERROR(VLOOKUP($N$15,Sheet1!J8:L8,3,0),0) -> 0 | O23: =+IFERROR(VLOOKUP($O$15,Sheet1!J8:L8,3,0),0) -> 0 | P23: =+IFERROR(VLOOKUP($P$15,Sheet1!J8:M8,3,0),0) -> 0 | Q23: =+IFERROR(VLOOKUP($Q$15,Sheet1!J8:M8,3,0),0) -> 0 | R23: =+IFERROR(VLOOKUP($R$15,Sheet1!J8:M8,3,0),0) -> 0 | S23: =+IFERROR(VLOOKUP($S$15,Sheet1!N8:Q8,3,0),0) -> 0 | T23: =+IFERROR(VLOOKUP($T$15,Sheet1!N8:Q8,3,0),0) -> 0 | U23: =+IFERROR(VLOOKUP($U$15,Sheet1!F8:I8,3,0),0) -> 0 | V23: =+IFERROR(VLOOKUP($V$15,Sheet1!F8:I8,3,0),0) -> 0 | W23: =+IFERROR(VLOOKUP($W$15,Sheet1!F8:I8,3,0),0) -> 0 | X23: =+IFERROR(VLOOKUP($X$15,Sheet1!F8:I8,3,0),0) -> 0 | Y23: =+IFERROR(VLOOKUP($Y$15,Sheet1!F8:I8,3,0),0) -> 0 | Z23: =+IFERROR(VLOOKUP($Z$15,Sheet1!F8:I8,3,0),0) -> 0 | AA23: =+IFERROR(VLOOKUP($AA$15,Sheet1!F8:I8,3,0),0) -> 0 | AB23: =+IFERROR(VLOOKUP($AB$15,Sheet1!F8:I8,3,0),0) -> 0 | AC23: =+IFERROR(VLOOKUP($AC$15,Sheet1!R8:U8,3,0),0) -> 0 | AD23: =+IFERROR(VLOOKUP($AD$15,Sheet1!R8:U8,2,0),0) -> 0 | AE23: =+IFERROR(VLOOKUP($AE$15,Sheet1!V8:Y8,3,0),0) -> 0 | AF23: =+IFERROR(VLOOKUP($AF$15,Sheet1!V8:Y8,3,0),0) -> 0 | AG23: =+IFERROR(VLOOKUP($AG$15,Sheet1!V8:Y8,3,0),0) -> 0 | AH23: =+IFERROR(VLOOKUP($AH$15,Sheet1!V8:Y8,3,0),0) -> 0 | AI23: =+IFERROR(VLOOKUP($AI$15,Sheet1!V8:Y8,3,0),0) -> 0 | AJ23: =+IFERROR(VLOOKUP($AJ$15,Sheet1!V8:Y8,3,0),0) -> 0 | AK23: =+IFERROR(VLOOKUP($AK$15,Sheet1!Z8:AB8,3,0),0) -> 0 | AL23: =+IFERROR(VLOOKUP($AL$15,Sheet1!AD8:AG8,3,0),0) -> 0 | AM23: =+IFERROR(VLOOKUP($AM$15,Sheet1!AD8:AG8,3,0),0) -> 0 | AN23: =+IFERROR(VLOOKUP($AN$15,Sheet1!AD8:AG8,3,0),0) -> 0 | AO23: =+IFERROR(VLOOKUP($AO$15,Sheet1!AD8:AG8,3,0),0) -> 0 | AP23: =+IFERROR(VLOOKUP($AP$15,Sheet1!AD8:AG8,3,0),0) -> 0 | AQ23: =+IFERROR(VLOOKUP($AQ$15,Sheet1!AD8:AG8,3,0),0) -> 0 | AR23: =+IFERROR(VLOOKUP($AR$15,Sheet1!AD8:AG8,3,0),0) -> 0 | AS23: =+IFERROR(VLOOKUP($AS$15,Sheet1!AH8:AK8,3,0),0) -> 0 | AT23: =+IFERROR(VLOOKUP($AT$15,Sheet1!AH8:AK8,3,0),0) -> 0 | AU23: =+IFERROR(VLOOKUP($AU$15,Sheet1!AH8:AK8,3,0),0) -> 0 | AV23: =+IFERROR(VLOOKUP($AV$15,Sheet1!AH8:AK8,3,0),0) -> 0 | AW23: =+IFERROR(VLOOKUP($AW$15,Sheet1!AH8:AK8,3,0),0) -> 0 | AX23: =+IFERROR(VLOOKUP($AX$15,Sheet1!AH8:AK8,3,0),0) -> 0 | AY23: =+IFERROR(VLOOKUP($AY$15,Sheet1!AH8:AK8,3,0),0) -> 0 | AZ23: =+IFERROR(VLOOKUP($AZ$15,Sheet1!AH8:AK8,3,0),0) -> 0 | BA23: =+IFERROR(VLOOKUP($BA$15,Sheet1!AH8:AK8,3,0),0) -> 0 | BB23: =+IFERROR(VLOOKUP($BB$15,Sheet1!AH8:AK8,3,0),0) -> 0 | BC23: =+IFERROR(VLOOKUP($BC$15,Sheet1!AL8:AO8,3,0),0) -> 0 | BD23: =+IFERROR(VLOOKUP($BD$15,Sheet1!AL8:AO8,3,0),0) -> 0 | BE23: =+IFERROR(VLOOKUP($BE$15,Sheet1!AL8:AO8,3,0),0) -> 0 | BF23: =+IFERROR(VLOOKUP($BF$15,Sheet1!AL8:AO8,3,0),0) -> 0 | BG23: =+IFERROR(VLOOKUP($BG$15,Sheet1!AL8:AO8,3,0),0) -> 0 | BH23: =+IFERROR(VLOOKUP($BH$15,Sheet1!AL8:AO8,3,0),0) -> 0 | BI23: =+IFERROR(VLOOKUP($BI$15,Sheet1!AL8:AO8,3,0),0) -> 0 | BJ23: =+IFERROR(VLOOKUP($BJ$15,Sheet1!AL8:AO8,3,0),0) -> 0 | BK23: =+IFERROR(VLOOKUP($BK$15,Sheet1!AL8:AO8,3,0),0) -> 0 | BL23: =+IFERROR(VLOOKUP($BL$15,Sheet1!AL8:AO8,3,0),0) -> 0 | BM23: =+IFERROR(VLOOKUP($BM$15,Sheet1!AP8:AS8,3,0),0) -> 0 | BN23: =+IFERROR(VLOOKUP($BN$15,Sheet1!AT8:AW8,3,0),0) -> 0 | BO23: =+IFERROR(VLOOKUP($BO$15,Sheet1!AX8:BA8,3,0),0) -> 0 | BP23: =+IFERROR(VLOOKUP($BP$15,Sheet1!BB8:BE8,3,0),0) -> 0 | BQ23: =+IFERROR(VLOOKUP($BQ$15,Sheet1!BF8:BI8,3,0),0) -> 0 | BR23: =+IFERROR(VLOOKUP($BR$15,Sheet1!BJ8:BM8,3,0),0) -> 0 | BS23: =+IFERROR(VLOOKUP($BS$15,Sheet1!BN8:BQ8,3,0),0) -> 0 | BT23: =+IFERROR(VLOOKUP($BT$15,Sheet1!BR8:BU8,3,0),0) -> 0 | BU23: =+IFERROR(VLOOKUP($BU$15,Sheet1!BV8:BY8,3,0),0) -> 0 | BV23: =Sheet1!E8 -> 0 | BW23: =Sheet1!CV8 -> 0 | BX23: =Sheet1!CW8 -> 0 | BZ23: =Sheet1!BZ8 -> 0 | CA23: =SUMPRODUCT($N$16:$BU$16,N23:BU23)+BZ23 -> 0 | CB23: =Sheet1!CB8 -> 0 | CC23: =CA23*CB23 -> 0 | CE23: =CA23*CD23 -> 0 | CF23: 0 | CG23: =CA23*CF23 -> 0 | CH23: =CA23+CC23+CE23+CG23 -> 0 | CI23: 0.02 | CJ23: =CH23*CI23 -> 0 | CK23: 0.01 | CL23: =CH23*CK23 -> 0
F24: =SUMPRODUCT(F17:F23,K17:K23) -> 23459.22 | G24: SOMBHU SIR CONFIRM ALL ITEMS CAN STUFF IN ONE 16MT LORRY
E26: Order Quantity | F26: Stnd Length | G26: Truck type | H26: Fare of one truck | I26: No of Drum in one truck | J26: Total length in one Truck | K26: No of Truck | L26: Total Freight | M26: Freight per KM
D27: =D17 -> 4 CORE X 35 SQ. MM. AL/ARD - STRIP (XLPE) | E27: =K17 -> 0.5 | F27: =BY17/1000 -> 0.5 | G27: 16 MT | H27: 23000 | I27: 23 | J27: =F27*I27 -> 11.5 | K27: =ROUNDUP((E27/J27),1) -> 0.1 | L27: =M27*E27 -> 2300 | M27: =(H27*K27)/E27 -> 4600
D28: =D18 -> 4 CORE X 35 SQ. MM. AL/UNARD.(XLPE) | E28: =K18 -> 0.5 | F28: =BY18/1000 -> 0.5 | G28: 16 MT | H28: 23000 | I28: 29 | J28: =F28*I28 -> 14.5 | K28: =ROUNDUP((E28/J28),1) -> 0.1 | L28: =M28*E28 -> 2300 | M28: =(H28*K28)/E28 -> 4600
D29: =D19 -> 4 CORE X 16 SQ. MM. ALU/ARD - STRIP (XLPE) | E29: =K19 -> 2 | F29: =BY19/1000 -> 0.5 | G29: 16 MT | H29: 23000 | I29: 37 | J29: =F29*I29 -> 18.5 | K29: =ROUNDUP((E29/J29),1) -> 0.2 | L29: =M29*E29 -> 4600 | M29: =(H29*K29)/E29 -> 2300
D30: =D20 -> 4 CORE X 16 SQ. MM. ALU/UNARD (XLPE) | E30: =K20 -> 0.5 | F30: =BY20/1000 -> 0.5 | G30: 16 MT | H30: 23000 | I30: 42 | J30: =F30*I30 -> 21 | K30: =ROUNDUP((E30/J30),1) -> 0.1 | L30: =M30*E30 -> 2300 | M30: =(H30*K30)/E30 -> 4600
D31: =D21 -> 4 CORE X 10 SQ. MM. AL/UNARD (XLPE) | E31: =K21 -> 1 | F31: =BY21/1000 -> 0.5 | G31: 16 MT | H31: 23000 | I31: 46 | J31: =F31*I31 -> 23 | K31: =ROUNDUP((E31/J31),1) -> 0.1 | L31: =M31*E31 -> 2300 | M31: =(H31*K31)/E31 -> 2300
D32: =D22 -> 4 CORE X 6 SQ. MM. AL/UNARD.(XLPE) | E32: =K22 -> 2 | F32: =BY22/1000 -> 0.5 | G32: 16 MT | H32: 23000 | I32: 46 | J32: =F32*I32 -> 23 | K32: =ROUNDUP((E32/J32),1) -> 0.1 | L32: =M32*E32 -> 2300 | M32: =(H32*K32)/E32 -> 1150
A35: DOCKET NO. | B35: Base Date | C35: ITEM CODE | D35: PROPOSE ERP ITEM NAME | E35: EX-WORKS (PER MTR) | F35: FREIGHT PER MTR | G35: PRICE INCLUDING FREIGHT (PER MTR) | H35: GST % | I35: GST VALUE | J35: PRICE INCLUDING GST & FREIGHT (PER MTR) | K35: QTY | L35: Unit | M35: TOTAL PRICE OF FULL QTY (INCLUDING FRIGHT & GST)
A37: =A17 -> ENQ-11226-22-23 | B37: =B17 -> 45194 | C37: =C17 -> FA0900018 | D37: =D17 -> 4 CORE X 35 SQ. MM. AL/ARD - STRIP (XLPE) | E37: =ROUNDUP(E17/1000,2) -> 215.17 | F37: =ROUNDUP(F17/1000,2) -> 7.54 | G37: =E37+F37 -> 222.71 | H37: =H17 -> 0.18 | I37: =G37*H37 -> 40.0878 | J37: =G37+I37 -> 262.7978 | K37: =K17*1000 -> 500 | L37: MTR | M37: =J37*K37 -> 131398.9
A38: =A18 -> ENQ-11226-22-23 | B38: =B18 -> 45194 | C38: =C18 -> FA1000016 | D38: =D18 -> 4 CORE X 35 SQ. MM. AL/UNARD.(XLPE) | E38: =ROUNDUP(E18/1000,2) -> 175.35 | F38: =ROUNDUP(F18/1000,2) -> 6.14 | G38: =E38+F38 -> 181.49 | H38: =H18 -> 0.18 | I38: =G38*H38 -> 32.6682 | J38: =G38+I38 -> 214.1582 | K38: =K18*1000 -> 500 | L38: MTR | M38: =J38*K38 -> 107079.1
A39: =A19 -> ENQ-11226-22-23 | B39: =B19 -> 45194 | C39: =C19 -> FA0900013 | D39: =D19 -> 4 CORE X 16 SQ. MM. ALU/ARD - STRIP (XLPE) | E39: =ROUNDUP(E19/1000,2) -> 124.79 | F39: =ROUNDUP(F19/1000,2) -> 4.37 | G39: =E39+F39 -> 129.16 | H39: =H19 -> 0.18 | I39: =G39*H39 -> 23.2488 | J39: =G39+I39 -> 152.4088 | K39: =K19*1000 -> 2000 | L39: MTR | M39: =J39*K39 -> 304817.6
A40: =A20 -> ENQ-11226-22-23 | B40: =B20 -> 45194 | C40: =C20 -> FA1000014 | D40: =D20 -> 4 CORE X 16 SQ. MM. ALU/UNARD (XLPE) | E40: =ROUNDUP(E20/1000,2) -> 93.43 | F40: =ROUNDUP(F20/1000,2) -> 3.27 | G40: =E40+F40 -> 96.7 | H40: =H20 -> 0.18 | I40: =G40*H40 -> 17.406 | J40: =G40+I40 -> 114.106 | K40: =K20*1000 -> 500 | L40: MTR | M40: =J40*K40 -> 57053
A41: =A21 -> ENQ-11226-22-23 | B41: =B21 -> 45194 | C41: =C21 -> FA1000048 | D41: =D21 -> 4 CORE X 10 SQ. MM. AL/UNARD (XLPE) | E41: =ROUNDUP(E21/1000,2) -> 71.25 | F41: =ROUNDUP(F21/1000,2) -> 2.5 | G41: =E41+F41 -> 73.75 | H41: =H21 -> 0.18 | I41: =G41*H41 -> 13.275 | J41: =G41+I41 -> 87.025 | K41: =K21*1000 -> 1000 | L41: MTR | M41: =J41*K41 -> 87025
A42: =A22 -> ENQ-11226-22-23 | B42: =B22 -> 45194 | C42: =C22 -> FA1000026 | D42: =D22 -> 4 CORE X 6 SQ. MM. AL/UNARD.(XLPE) | E42: =ROUNDUP(E22/1000,2) -> 53.74 | F42: =ROUNDUP(F22/1000,2) -> 1.89 | G42: =E42+F42 -> 55.63 | H42: =H22 -> 0.18 | I42: =G42*H42 -> 10.0134 | J42: =G42+I42 -> 65.6434 | K42: =K22*1000 -> 2000 | L42: MTR | M42: =J42*K42 -> 131286.8
A43: =A23 -> 0 | B43: =B23 -> 0 | C43: =C23 -> 0 | D43: =D23 -> PENDENT CABLE 12 CORE,1.5 MM2 # ( Trailing Cable, 12C X 1.5 Sq.mm Rubber Insulated, flexible Cu, FRLS, 1.1kv grade,conform to IS : 9968 (Pt-1)/88 ) | E43: =ROUNDUP(E23/1000,2) -> 0 | F43: =ROUNDUP(F23/1000,2) -> 0 | G43: =E43+F43 -> 0 | H43: =H23 -> 0.18 | I43: =G43*H43 -> 0 | J43: =G43+I43 -> 0 | K43: =K23*1000 -> 200 | L43: MTR | M43: =J43*K43 -> 0
M44: =SUM(M37:M43) -> 818660.4
