Workbook

Sheet Sheet1
A1: DOCKET NO. | B1: Base Date | C1: ITEM CODE | D1: PROPOSE ERP ITEM NAME | E1: Propose Drum Type | F1: Insulation Screening(Metallic) | G1: RM Rate(Insulation Screening(Metallic)) | H1: Weight (Insulation Screening (Metallic)) | I1: Cost Insulation Screening(Metallic) | J1: Conductor | K1: RM Rate(Conductor) | L1: Weight(Conductor) | M1: Cost(Conductor) | N1: AL ALLOY | O1: RM Rate(AL Alloy) | P1: Weight(Al Alloy) | Q1: Cost(AL Alloy) | R1: Insulation Screening(Non-Metallic) | S1: RM Rate(Insulation Screening(Non-Metallic)) | T1: Weight(Insulation Screening(Non-Metallic) | U1: Cost(Insulation Screening(Non-Metallic) | V1: Insulation | W1: RM Rate(Insulation) | X1: Weight(Insulation) | Y1: Cost(Insulation) | Z1: Poly Tape | AA1: RM Rate(Poly Tape) | AB1: Weight(Poly Tape) | AC1: Cost(Poly Tape) | AD1: Inner Sheath | AE1: RM Rate(Inner Sheath) | AF1: Weight(Inner Sheath) | AG1: Cost(Inner Sheath) | AH1: Armouring | AI1: RM Rate(Armouring) | AJ1: Weight(Armouring) | AK1: Cost(Armouring) | AL1: Outer Sheath | AM1: RM Rate(Outer Sheath) | AN1: Weight(Outer Sheath) | AO1: Cost(Outer Sheath) | AP1: Filler | AQ1: RM Rate(Filler) | AR1: Weight(Filler) | AS1: Cost(Filler) | AT1: Grease | AU1: RM Rate(Grease) | AV1: Weight(Grease) | AW1: Cost(Grease) | AX1: Water Swellable Tape | AY1: RM Rate(Water Swellable Tape) | AZ1: Weight(Water Swellable Tape) | BA1: Cost(Water Swellable Tape) | BB1: Semi Conducting Water Swellable Tape | BC1: RM Rate(Semi Conducting Water Swellable Tape) | BD1: Weight(Semi Conducting Water Swellable Tape) | BE1: Cost(Semi Conducting Water Swellable Tape) | BF1: Semicon Tape | BG1: RM Rate(Semicon Tape) | BH1: Weight(Semicon Tape) | BI1: Cost(Semicon Tape) | BJ1: Glass Fiber Tape | BK1: RM Rate(Glass Fiber Tape) | BL1: Weight(Glass Fiber Tape) | BM1: Cost(Glass Fiber Tape) | BN1: Copper Wire 0.8MM | BO1: RM Rate(Copper Wire 0.8MM) | BP1: Weight(Copper Wire 0.8MM) | BQ1: Cost(Copper Wire 0.8MM) | BR1: Rubberized Cotton Tape | BS1: RM Rate(Rubberized Cotton Tape) | BT1: Weight(Rubberized Cotton Tape) | BU1: Cost(Rubberized Cotton Tape) | BV1: Water Tight Compound | BW1: RM Rate(Water Tight Compound) | BX1: Weight(Water Tight Compound) | BY1: Cost(Water Tight Compound) | BZ1: Drum Cost Per KM | CA1: Total RM Cost | CB1: FIRM % | CC1: Firm Value | CD1: MFG% | CE1: MFG Value | CF1: PROF% | CG1: Profit Value | CH1: 1st EX-Works | CI1: Intt % | CJ1: Intt Value | CK1: insp% | CL1: Insp Value | CM1: EX-Works Per KM | CN1: Freight Per KM | CO1: Price Including Freight Per KM | CP1: GST % | CQ1: GST Value | CR1: Price Including GST & Freight Per KM | CS1: QTY | CT1: Unit | CU1: Total Price Of Full QTY(Including Freight&GST) | CV1: DRUM CODE | CW1: DRUM SIZE (FxbXtx Ft) | CX1: Party Standard Length(MTR)
A2: ENQ-15115-22-23 | B2: 45698 | C2: FA0200002 | D2: 10 CORE X 2.5 SQ. MM. CU/ARD - WIRE (PVC) | E2: WOOD | H2: 0 | J2: Copper | K2: 866 | L2: 222 | M2: 192252 | P2: 0 | T2: 0 | V2: Type C PVC (HR) | W2: 103.71 | X2: 130 | Y2: 13482.3 | Z2: POLY TAPE | AA2: 120 | AB2: 5 | AC2: 600 | AD2: PVC Type ST-2 | AE2: 67.67 | AF2: 38 | AG2: 2571.46 | AH2: Galvanised Steel Round Wire | AI2: 82.9 | AJ2: 492 | AK2: 40786.8 | AL2: FRLSH PVC Type ST-2 | AM2: 87.1 | AN2: 166 | AO2: 14458.6 | AR2: 0 | AV2: 0 | AZ2: 0 | BD2: 0 | BH2: 0 | BL2: 28 | BP2: 0 | BT2: 0 | BX2: 0 | BZ2: 5100 | CA2: 269251.16 | CH2: 269251.16 | CM2: 269251.16 | CO2: 269251.16 | CP2: 0.18 | CQ2: 48465.21 | CR2: 317716.37 | CS2: 63.965 | CT2: KMS | CU2: 20322728 | CV2: MD0100066 | CW2: DRUM - 40 X 15 X 23 X 2 | CX2: 500
A3: ENQ-15115-22-23 | B3: 45698 | C3: FA0200003 | D3: 12 CORE X 2.5 SQ. MM. CU/ARD - WIRE (PVC) | E3: WOOD | H3: 0 | J3: Copper | K3: 866 | L3: 266 | M3: 230356 | P3: 0 | T3: 0 | V3: Type C PVC (HR) | W3: 103.71 | X3: 156 | Y3: 16178.76 | Z3: POLY TAPE | AA3: 120 | AB3: 6 | AC3: 720 | AD3: PVC Type ST-2 | AE3: 67.67 | AF3: 40 | AG3: 2706.8 | AH3: Galvanised Steel Round Wire | AI3: 82.9 | AJ3: 508 | AK3: 42113.2 | AL3: FRLSH PVC Type ST-2 | AM3: 87.1 | AN3: 170 | AO3: 14807 | AR3: 0 | AV3: 0 | AZ3: 0 | BD3: 0 | BH3: 0 | BL3: 28 | BP3: 0 | BT3: 0 | BX3: 0 | BZ3: 5100 | CA3: 311981.76 | CH3: 311981.76 | CM3: 311981.76 | CO3: 311981.76 | CP3: 0.18 | CQ3: 56156.72 | CR3: 368138.48 | CS3: 26 | CT3: KMS | CU3: 9571600 | CV3: MD0100066 | CW3: DRUM - 40 X 15 X 23 X 2 | CX3: 500
A4: ENQ-15115-22-23 | B4: 45698 | C4: FA0200005 | D4: 16 CORE X 2.5 SQ. MM. CU/ARD - WIRE (PVC) | E4: WOOD | H4: 0 | J4: Copper | K4: 866 | L4: 355 | M4: 307430 | P4: 0 | T4: 0 | V4: Type C PVC (HR) | W4: 103.71 | X4: 208 | Y4: 21571.68 | Z4: POLY TAPE | AA4: 120 | AB4: 6 | AC4: 720 | AD4: PVC Type ST-2 | AE4: 67.67 | AF4: 46 | AG4: 3112.82 | AH4: Galvanised Steel Round Wire | AI4: 82.9 | AJ4: 574 | AK4: 47584.6 | AL4: FRLSH PVC Type ST-2 | AM4: 87.1 | AN4: 187 | AO4: 16287.7 | AR4: 0 | AV4: 0 | AZ4: 0 | BD4: 0 | BH4: 0 | BL4: 0 | BP4: 0 | BT4: 0 | BX4: 0 | BZ4: 7984 | CA4: 404690.8 | CH4: 404690.8 | CM4: 404690.8 | CO4: 404690.8 | CP4: 0.18 | CQ4: 72844.34 | CR4: 477535.14 | CS4: 13 | CT4: KMS | CU4: 6207957 | CV4: MD0100075 | CW4: DRUM - 42 X 15 X 23 X 2 | CX4: 500
A5: ENQ-15115-22-23 | B5: 45698 | C5: FA0200011 | D5: 4 CORE X 2.5 SQ. MM. CU/ARD - WIRE (PVC) | E5: WOOD | H5: 0 | J5: Copper | K5: 866 | L5: 89 | M5: 77074 | P5: 0 | T5: 0 | V5: Type C PVC (HR) | W5: 103.71 | X5: 52 | Y5: 5392.92 | Z5: POLY TAPE | AA5: 120 | AB5: 3 | AC5: 360 | AD5: PVC Type ST-2 | AE5: 67.67 | AF5: 27 | AG5: 1827.09 | AH5: Galvanised Steel Round Wire | AI5: 82.9 | AJ5: 289 | AK5: 23958.1 | AL5: FRLSH PVC Type ST-2 | AM5: 87.1 | AN5: 104 | AO5: 9058.4 | AR5: 0 | AV5: 0 | AZ5: 0 | BD5: 0 | BH5: 0 | BL5: 19 | BP5: 0 | BT5: 0 | BX5: 0 | BZ5: 4858 | CA5: 122528.51 | CH5: 122528.51 | CM5: 122528.51 | CO5: 122528.51 | CP5: 0.18 | CQ5: 22055.13 | CR5: 144583.64 | CS5: 56.67 | CT5: KMS | CU5: 8193555 | CV5: MD0100005 | CW5: DRUM - 36 X 14 X 23 X 2 | CX5: 500
A6: ENQ-15115-22-23 | B6: 45698 | C6: FA0200018 | D6: 7 CORE X 2.5 SQ. MM. CU/ARD - WIRE (PVC) | E6: WOOD | H6: 0 | J6: Copper | K6: 866 | L6: 155 | M6: 134230 | P6: 0 | T6: 0 | V6: Type C PVC (HR) | W6: 103.71 | X6: 91 | Y6: 9437.61 | Z6: POLY TAPE | AA6: 120 | AB6: 4 | AC6: 480 | AD6: PVC Type ST-2 | AE6: 67.67 | AF6: 30 | AG6: 2030.1 | AH6: Galvanised Steel Round Wire | AI6: 82.9 | AJ6: 339 | AK6: 28103.1 | AL6: FRLSH PVC Type ST-2 | AM6: 87.1 | AN6: 120 | AO6: 10452 | AR6: 0 | AV6: 0 | AZ6: 0 | BD6: 0 | BH6: 0 | BL6: 22 | BP6: 0 | BT6: 0 | BX6: 0 | BZ6: 4858 | CA6: 189590.81 | CH6: 189590.81 | CM6: 189590.81 | CO6: 189590.81 | CP6: 0.18 | CQ6: 34126.35 | CR6: 223717.16 | CS6: 98.845 | CT6: KMS | CU6: 22113322 | CV6: MD0100005 | CW6: DRUM - 36 X 14 X 23 X 2 | CX6: 500
A7: ENQ-15115-22-23 | B7: 45698 | C7: FA0500017 | D7: 1 CORE X 50 SQ. MM. AL/UNARD. (XLPE) | E7: WOOD | H7: 0 | J7: Alumimium | K7: 272.36 | L7: 135 | M7: 36768.6 | P7: 0 | T7: 0 | V7: LT-XLPE | W7: 114 | X7: 37 | Y7: 4218 | AB7: 0 | AF7: 0 | AJ7: 0 | AL7: FRLSH PVC Type ST-2 | AM7: 87.1 | AN7: 110 | AO7: 9581 | AR7: 0 | AV7: 0 | AZ7: 0 | BD7: 0 | BH7: 0 | BL7: 0 | BP7: 0 | BT7: 0 | BX7: 0 | BZ7: 2429 | CA7: 52996.6 | CH7: 52996.6 | CM7: 52996.6 | CO7: 52996.6 | CP7: 0.18 | CQ7: 9539.39 | CR7: 62535.99 | CS7: 24.06 | CT7: KMS | CU7: 1504616 | CV7: MD0100005 | CW7: DRUM - 36 X 14 X 23 X 2 | CX7: 1000
A8: ENQ-15115-22-23 | B8: 45698 | C8: FA0600013 | D8: 1 CORE X 95 SQ. MM. AL/UNARD(XLPE ) | E8: WOOD | H8: 0 | J8: Alumimium | K8: 272.36 | L8: 256 | M8: 69724.16 | P8: 0 | T8: 0 | V8: LT-XLPE | W8: 114 | X8: 53 | Y8: 6042 | AB8: 0 | AF8: 0 | AJ8: 0 | AL8: FRLSH PVC Type ST-2 | AM8: 87.1 | AN8: 139 | AO8: 12106.9 | AR8: 0 | AV8: 0 | AZ8: 0 | BD8: 0 | BH8: 0 | BL8: 0 | BP8: 0 | BT8: 0 | BX8: 0 | BZ8: 2550 | CA8: 90423.06 | CH8: 90423.06 | CM8: 90423.06 | CO8: 90423.06 | CP8: 0.18 | CQ8: 16276.15 | CR8: 106699.21 | CS8: 77.532 | CT8: KMS | CU8: 8272603 | CV8: MD0100066 | CW8: DRUM - 40 X 15 X 23 X 2 | CX8: 1000
A9: ENQ-15115-22-23 | B9: 45698 | C9: FA0600019 | D9: 1 CORE X 150 SQ. MM. AL/UNARD. (XLPE) | E9: WOOD | H9: 0 | J9: Alumimium | K9: 272.36 | L9: 405 | M9: 110305.8 | P9: 0 | T9: 0 | V9: LT-XLPE | W9: 114 | X9: 72 | Y9: 8208 | AB9: 0 | AF9: 0 | AJ9: 0 | AL9: FRLSH PVC Type ST-2 | AM9: 87.1 | AN9: 187 | AO9: 16287.7 | AR9: 0 | AV9: 0 | AX9: Water swellable Tape | AY9: 420 | AZ9: 0 | BA9: 0 | BD9: 0 | BH9: 0 | BL9: 0 | BP9: 0 | BT9: 0 | BX9: 0 | BZ9: 3606 | CA9: 138407.5 | CH9: 138407.5 | CM9: 138407.5 | CO9: 138407.5 | CP9: 0.18 | CQ9: 24913.35 | CR9: 163320.85 | CS9: 57.308 | CT9: KMS | CU9: 9359591 | CV9: MD0100085 | CW9: DRUM - 43 X 15 X 28 X 2.25 | CX9: 1000
A10: ENQ-15115-22-23 | B10: 45698 | C10: FA0600020 | D10: 1 CORE X 300 SQ. MM. AL/UNARD. (XLPE) | E10: WOOD | H10: 0 | J10: Alumimium | K10: 272.36 | L10: 810 | M10: 220611.6 | P10: 0 | T10: 0 | V10: LT-XLPE | W10: 114 | X10: 132 | Y10: 15048 | AB10: 0 | AF10: 0 | AJ10: 0 | AL10: FRLSH PVC Type ST-2 | AM10: 87.1 | AN10: 251 | AO10: 21862.1 | AR10: 0 | AV10: 0 | AX10: Water swellable Tape | AY10: 420 | AZ10: 0 | BA10: 0 | BD10: 0 | BH10: 0 | BL10: 0 | BP10: 0 | BT10: 0 | BX10: 0 | BZ10: 6276 | CA10: 263797.7 | CH10: 263797.7 | CM10: 263797.7 | CO10: 263797.7 | CP10: 0.18 | CQ10: 47483.59 | CR10: 311281.29 | CS10: 73.052 | CT10: KMS | CU10: 22739721 | CV10: MD0100017 | CW10: DRUM - 52 X 18 X 36 X 2.5 | CX10: 1000
A11: ENQ-15115-22-23 | B11: 45698 | C11: FA0600021 | D11: 1 CORE X 185 SQ. MM. AL/UNARD. (XLPE) | E11: WOOD | H11: 0 | J11: Alumimium | K11: 272.36 | L11: 500 | M11: 136180 | P11: 0 | T11: 0 | V11: LT-XLPE | W11: 114 | X11: 90 | Y11: 10260 | AB11: 0 | AF11: 0 | AJ11: 0 | AL11: FRLSH PVC Type ST-2 | AM11: 87.1 | AN11: 207 | AO11: 18029.7 | AR11: 0 | AV11: 0 | AX11: Water swellable Tape | AY11: 420 | AZ11: 0 | BA11: 0 | BD11: 0 | BH11: 0 | BL11: 0 | BP11: 0 | BT11: 0 | BX11: 0 | BZ11: 3881 | CA11: 168350.7 | CH11: 168350.7 | CM11: 168350.7 | CO11: 168350.7 | CP11: 0.18 | CQ11: 30303.13 | CR11: 198653.83 | CS11: 35.75 | CT11: KMS | CU11: 7101874 | CV11: MD0100090 | CW11: DRUM - 43 X 15 X 36 X 2.5 | CX11: 1000
A12: ENQ-15115-22-23 | B12: 45698 | C12: FA0600032 | D12: 1 CORE X 630 SQ. MM. ALU/UNARD (XLPE) | E12: WOOD | H12: 0 | J12: Alumimium | K12: 272.36 | L12: 1701 | M12: 463284.36 | P12: 0 | T12: 0 | V12: LT-XLPE | W12: 114 | X12: 253 | Y12: 28842 | AB12: 0 | AF12: 0 | AJ12: 0 | AL12: FRLSH PVC Type ST-2 | AM12: 87.1 | AN12: 429 | AO12: 37365.9 | AR12: 0 | AV12: 0 | AX12: Water swellable Tape | AY12: 420 | AZ12: 0 | BA12: 0 | BD12: 0 | BH12: 0 | BL12: 0 | BP12: 0 | BT12: 0 | BX12: 0 | BZ12: 13815 | CA12: 543307.26 | CH12: 543307.26 | CM12: 543307.26 | CO12: 543307.26 | CP12: 0.18 | CQ12: 97795.31 | CR12: 641102.57 | CS12: 33.704 | CT12: KMS | CU12: 21607721 | CV12: MD0100062 | CW12: DRUM - 74 X 24 X 32 X 3 | CX12: 1000
A13: ENQ-15115-22-23 | B13: 45698 | C13: FA0800001 | D13: 1 CORE X 16 SQ. MM. AL/ARD. (XLPE) | H13: 0 | L13: 43 | P13: 0 | T13: 0 | X13: 22 | AB13: 0 | AF13: 0 | AJ13: 61 | AN13: 85 | AR13: 0 | AV13: 0 | AZ13: 0 | BD13: 0 | BH13: 0 | BL13: 0 | BP13: 0 | BT13: 0 | BX13: 0 | CP13: 0.18 | CS13: 0.5 | CT13: KMS | CX13: 1000
A14: ENQ-15115-22-23 | B14: 45698 | C14: FA0900020 | D14: 2 CORE X 6 SQ. MM. AL/ARD - WIRE (XLPE) | E14: WOOD | H14: 0 | J14: Alumimium | K14: 272.36 | L14: 32 | M14: 8715.52 | P14: 0 | T14: 0 | V14: LT-XLPE | W14: 114 | X14: 22 | Y14: 2508 | AB14: 0 | AD14: PVC Type ST-2-PRESSURE EXTRUDED | AE14: 88.1 | AF14: 59 | AG14: 5197.9 | AH14: Galvanised Steel Round Wire | AI14: 82.9 | AJ14: 289 | AK14: 23958.1 | AL14: FRLSH PVC Type ST-2 | AM14: 87.1 | AN14: 112 | AO14: 9755.2 | AR14: 0 | AV14: 0 | AZ14: 0 | BD14: 0 | BH14: 0 | BL14: 0 | BP14: 0 | BR14: RUBBERIZED COTTON TAPE | BS14: 370 | BT14: 0 | BU14: 0 | BX14: 0 | BZ14: 2550 | CA14: 52684.72 | CH14: 52684.72 | CM14: 52684.72 | CO14: 52684.72 | CP14: 0.18 | CQ14: 9483.25 | CR14: 62167.97 | CS14: 3000 | CT14: KMS | CU14: 186503909 | CV14: MD0100066 | CW14: DRUM - 40 X 15 X 23 X 2 | CX14: 1000
A15: ENQ-15115-22-23 | B15: 45698 | C15: FA0900024 | D15: 4 CORE X 4 SQ. MM. CU/ARD - WIRE (PVC) | E15: WOOD | H15: 0 | J15: Copper | K15: 866 | L15: 144 | M15: 124704 | P15: 0 | T15: 0 | V15: Type C PVC (HR) | W15: 103.71 | X15: 76 | Y15: 7881.96 | Z15: POLY TAPE | AA15: 120 | AB15: 4 | AC15: 480 | AD15: PVC Type ST-2 | AE15: 67.67 | AF15: 34 | AG15: 2300.78 | AH15: Galvanised Steel Round Wire | AI15: 82.9 | AJ15: 352 | AK15: 29180.8 | AL15: FRLSH PVC Type ST-2 | AM15: 87.1 | AN15: 119 | AO15: 10364.9 | AR15: 0 | AV15: 0 | AZ15: 0 | BD15: 0 | BH15: 0 | BL15: 0 | BP15: 0 | BT15: 0 | BX15: 0 | BZ15: 2550 | CA15: 177462.44 | CH15: 177462.44 | CM15: 177462.44 | CO15: 177462.44 | CP15: 0.18 | CQ15: 31943.24 | CR15: 209405.68 | CS15: 1 | CT15: KMS | CU15: 209406 | CV15: MD0100066 | CW15: DRUM - 40 X 15 X 23 X 2 | CX15: 1000
A16: ENQ-15115-22-23 | B16: 45698 | C16: FA0900041 | D16: 2 CORE X 4 SQ. MM. AL/ARD - WIRE (XLPE) | E16: WOOD | H16: 0 | J16: Alumimium | K16: 272.36 | L16: 22 | M16: 5991.92 | P16: 0 | T16: 0 | V16: LT-XLPE | W16: 114 | X16: 19 | Y16: 2166 | AB16: 4 | AD16: PVC Type ST-2 | AE16: 67.67 | AF16: 47 | AG16: 3180.49 | AH16: Galvanised Steel Round Wire | AI16: 82.9 | AJ16: 264 | AK16: 21885.6 | AL16: FRLSH PVC Type ST-2 | AM16: 87.1 | AN16: 100 | AO16: 8710 | AR16: 0 | AV16: 0 | AZ16: 0 | BD16: 0 | BH16: 0 | BL16: 0 | BP16: 0 | BT16: 0 | BX16: 0 | BZ16: 2550 | CA16: 44484.01 | CH16: 44484.01 | CM16: 44484.01 | CO16: 44484.01 | CP16: 0.18 | CQ16: 8007.12 | CR16: 52491.13 | CS16: 2077.047 | CT16: KMS | CU16: 109026548 | CV16: MD0100066 | CW16: DRUM - 40 X 15 X 23 X 2 | CX16: 1000
A17: ENQ-15115-22-23 | B17: 45698 | C17: FA0900042 | D17: 2 CORE X 10 SQ. MM. ALU/ARD - WIRE (XLPE) | E17: WOOD | H17: 0 | J17: Alumimium | K17: 272.36 | L17: 54 | M17: 14707.44 | P17: 0 | T17: 0 | V17: LT-XLPE | W17: 114 | X17: 26 | Y17: 2964 | AB17: 0 | AD17: PVC Type ST-2-PRESSURE EXTRUDED | AE17: 88.1 | AF17: 74 | AG17: 6519.4 | AH17: Galvanised Steel Round Wire | AI17: 82.9 | AJ17: 340 | AK17: 28186 | AL17: FRLSH PVC Type ST-2 | AM17: 87.1 | AN17: 127 | AO17: 11061.7 | AR17: 0 | AV17: 0 | AZ17: 0 | BD17: 0 | BH17: 0 | BL17: 0 | BP17: 0 | BR17: RUBBERIZED COTTON TAPE | BS17: 370 | BT17: 0 | BU17: 0 | BX17: 0 | BZ17: 3992 | CA17: 67430.54 | CH17: 67430.54 | CM17: 67430.54 | CO17: 67430.54 | CP17: 0.18 | CQ17: 12137.5 | CR17: 79568.04 | CS17: 123.04 | CT17: KMS | CU17: 9790051 | CV17: MD0100075 | CW17: DRUM - 42 X 15 X 23 X 2 | CX17: 1000
A18: ENQ-15115-22-23 | B18: 45698 | C18: FA0900111 | D18: 4 CORE X 25 SQ. MM. ALU/ARD - WIRE (XLPE) | E18: WOOD | H18: 0 | J18: Alumimium | K18: 272.36 | L18: 270 | M18: 73537.2 | P18: 0 | T18: 0 | V18: LT-XLPE | W18: 114 | X18: 95 | Y18: 10830 | AB18: 0 | AD18: PVC Type ST-2 | AE18: 67.67 | AF18: 46 | AG18: 3112.82 | AH18: Galvanised Steel Round Wire | AI18: 82.9 | AJ18: 572 | AK18: 47418.8 | AL18: FRLSH PVC Type ST-2 | AM18: 87.1 | AN18: 185 | AO18: 16113.5 | AR18: 0 | AV18: 0 | AZ18: 0 | BD18: 0 | BH18: 0 | BL18: 0 | BP18: 0 | BT18: 0 | BX18: 0 | BZ18: 3881 | CA18: 154893.32 | CH18: 154893.32 | CM18: 154893.32 | CO18: 154893.32 | CP18: 0.18 | CQ18: 27880.8 | CR18: 182774.12 | CS18: 121.208 | CT18: KMS | CU18: 22153685 | CV18: MD0100090 | CW18: DRUM - 43 X 15 X 36 X 2.5 | CX18: 1000
A19: ENQ-15115-22-23 | B19: 45698 | C19: FA0900112 | D19: 4 CORE X 10 SQ. MM. AL/ARD - WIRE (XLPE) | E19: WOOD | H19: 0 | J19: Alumimium | K19: 272.36 | L19: 108 | M19: 29414.88 | P19: 0 | T19: 0 | V19: LT-XLPE | W19: 114 | X19: 64 | Y19: 7296 | AB19: 0 | AD19: PVC Type ST-2 | AE19: 67.67 | AF19: 35 | AG19: 2368.45 | AH19: Galvanised Steel Round Wire | AI19: 82.9 | AJ19: 441 | AK19: 36558.9 | AL19: FRLSH PVC Type ST-2 | AM19: 87.1 | AN19: 151 | AO19: 13152.1 | AR19: 0 | AV19: 0 | AZ19: 0 | BD19: 0 | BH19: 0 | BL19: 0 | BP19: 0 | BT19: 0 | BX19: 0 | BZ19: 4593 | CA19: 93383.33 | CH19: 93383.33 | CM19: 93383.33 | CO19: 93383.33 | CP19: 0.18 | CQ19: 16809 | CR19: 110192.33 | CS19: 136.832 | CT19: KMS | CU19: 15077837 | CV19: MD0100064 | CW19: DRUM - 42 X 15 X 32 X 2 | CX19: 1000
A20: ENQ-15115-22-23 | B20: 45698 | C20: FA0900116 | D20: 4 CORE X 50 SQ. MM. AL/ARD - WIRE (XLPE) | E20: WOOD | H20: 0 | J20: Alumimium | K20: 272.36 | L20: 541 | M20: 147346.76 | P20: 0 | T20: 0 | V20: LT-XLPE | W20: 114 | X20: 124 | Y20: 14136 | AB20: 0 | AD20: PVC Type ST-2 | AE20: 67.67 | AF20: 69 | AG20: 4669.23 | AH20: Galvanised Steel Round Wire | AI20: 82.9 | AJ20: 898 | AK20: 74444.2 | AL20: FRLSH PVC Type ST-2 | AM20: 87.1 | AN20: 260 | AO20: 22646 | AR20: 0 | AV20: 0 | AZ20: 0 | BD20: 0 | BH20: 0 | BL20: 0 | BP20: 0 | BR20: RUBBERIZED COTTON TAPE | BS20: 370 | BT20: 0 | BU20: 0 | BX20: 0 | BZ20: 6254 | CA20: 269496.19 | CH20: 269496.19 | CM20: 269496.19 | CO20: 269496.19 | CP20: 0.18 | CQ20: 48509.31 | CR20: 318005.5 | CS20: 26.605 | CT20: KMS | CU20: 8460536 | CV20: MD0100068 | CW20: DRUM - 54 X 20 X 36 X 2.5 | CX20: 1000
A21: ENQ-15115-22-23 | B21: 45698 | C21: FA0900117 | D21: 4 CORE X 35 SQ. MM. AL/ARD - WIRE (XLPE) | E21: WOOD | H21: 0 | J21: Alumimium | K21: 272.36 | L21: 378 | M21: 102952.08 | P21: 0 | T21: 0 | V21: LT-XLPE | W21: 114 | X21: 109 | Y21: 12426 | AB21: 0 | AD21: PVC Type ST-2 | AE21: 67.67 | AF21: 51 | AG21: 3451.17 | AH21: Galvanised Steel Round Wire | AI21: 82.9 | AJ21: 639 | AK21: 52973.1 | AL21: FRLSH PVC Type ST-2 | AM21: 87.1 | AN21: 230 | AO21: 20033 | AR21: 0 | AV21: 0 | AZ21: 0 | BD21: 0 | BH21: 0 | BL21: 0 | BP21: 0 | BR21: RUBBERIZED COTTON TAPE | BS21: 370 | BT21: 0 | BU21: 0 | BX21: 0 | BZ21: 4139 | CA21: 195974.35 | CH21: 195974.35 | CM21: 195974.35 | CO21: 195974.35 | CP21: 0.18 | CQ21: 35275.38 | CR21: 231249.73 | CS21: 88.208 | CT21: KMS | CU21: 20398076 | CV21: MD0100013 | CW21: DRUM - 48 X 14 X 36 X 2.25 | CX21: 1000
A22: ENQ-15115-22-23 | B22: 45698 | C22: FA0900132 | D22: 4 CORE X 16 SQ. MM. AL/ARD - WIRE (XLPE) | E22: WOOD | H22: 0 | J22: Alumimium | K22: 272.36 | L22: 173 | M22: 47118.28 | P22: 0 | T22: 0 | V22: LT-XLPE | W22: 114 | X22: 75 | Y22: 8550 | AB22: 0 | AD22: PVC Type ST-2 | AE22: 67.67 | AF22: 40 | AG22: 2706.8 | AH22: Galvanised Steel Round Wire | AI22: 82.9 | AJ22: 498 | AK22: 41284.2 | AL22: FRLSH PVC Type ST-2 | AM22: 87.1 | AN22: 166 | AO22: 14458.6 | AR22: 0 | AV22: 0 | AZ22: 0 | BD22: 0 | BH22: 0 | BL22: 0 | BP22: 0 | BR22: RUBBERIZED COTTON TAPE | BS22: 370 | BT22: 0 | BU22: 0 | BX22: 0 | BZ22: 3881 | CA22: 117998.88 | CH22: 117998.88 | CM22: 117998.88 | CO22: 117998.88 | CP22: 0.18 | CQ22: 21239.8 | CR22: 139238.68 | CS22: 1.5 | CT22: KMS | CU22: 208858 | CV22: MD0100090 | CW22: DRUM - 43 X 15 X 36 X 2.5 | CX22: 1000
A23: ENQ-15115-22-23 | B23: 45698 | C23: FA0900133 | D23: 2 CORE X 16 SQ. MM. AL/ARD - WIRE (XLPE) | E23: WOOD | H23: 0 | J23: Alumimium | K23: 272.36 | L23: 86 | M23: 23422.96 | P23: 0 | T23: 0 | V23: LT-XLPE | W23: 114 | X23: 30 | Y23: 3420 | AB23: 0 | AD23: PVC Type ST-2-PRESSURE EXTRUDED | AE23: 88.1 | AF23: 33 | AG23: 2907.3 | AH23: Galvanised Steel Round Wire | AI23: 82.9 | AJ23: 416 | AK23: 34486.4 | AL23: FRLSH PVC Type ST-2 | AM23: 87.1 | AN23: 144 | AO23: 12542.4 | AR23: 0 | AV23: 0 | AZ23: 0 | BD23: 0 | BH23: 0 | BL23: 0 | BP23: 0 | BR23: RUBBERIZED COTTON TAPE | BS23: 370 | BT23: 0 | BU23: 0 | BX23: 0 | BZ23: 4593 | CA23: 81372.06 | CH23: 81372.06 | CM23: 81372.06 | CO23: 81372.06 | CP23: 0.18 | CQ23: 14646.97 | CR23: 96019.03 | CS23: 0.5 | CT23: KMS | CU23: 48010 | CV23: MD0100064 | CW23: DRUM - 42 X 15 X 32 X 2 (LOMBU) | CX23: 1000
A24: ENQ-15115-22-23 | B24: 45698 | C24: FA0900160 | D24: 2 CORE X 50 SQ. MM. AL/ARD - WIRE (XLPE) | E24: WOOD | H24: 0 | J24: Alumimium | K24: 272.36 | L24: 270 | M24: 73537.2 | P24: 0 | T24: 0 | V24: LT-XLPE | W24: 114 | X24: 63 | Y24: 7182 | AB24: 0 | AD24: PVC Type ST-2-PRESSURE EXTRUDED | AE24: 88.1 | AF24: 38 | AG24: 3347.8 | AH24: Galvanised Steel Round Wire | AI24: 82.9 | AJ24: 483 | AK24: 40040.7 | AL24: FRLSH PVC Type ST-2 | AM24: 87.1 | AN24: 184 | AO24: 16026.4 | AR24: 0 | AV24: 0 | AZ24: 0 | BD24: 0 | BH24: 0 | BL24: 0 | BP24: 0 | BR24: RUBBERIZED COTTON TAPE | BS24: 370 | BT24: 0 | BU24: 0 | BX24: 0 | BZ24: 4139 | CA24: 144273.1 | CH24: 144273.1 | CM24: 144273.1 | CO24: 144273.1 | CP24: 0.18 | CQ24: 25969.16 | CR24: 170242.26 | CS24: 0.5 | CT24: KMS | CU24: 85121 | CV24: MD0100013 | CW24: DRUM - 48 X 14 X 36 X 2.25 | CX24: 1000
A25: ENQ-15115-22-23 | B25: 45698 | C25: FA1100091 | D25: 4 CORE X 240 SQ. MM. AL/ARD - WIRE (XLPE) | E25: WOOD | H25: 0 | J25: Alumimium | K25: 272.36 | L25: 2595 | M25: 706774.2 | P25: 0 | T25: 0 | V25: LT-XLPE | W25: 114 | X25: 438 | Y25: 49932 | AB25: 0 | AD25: PVC Type ST-2 | AE25: 67.67 | AF25: 244 | AG25: 16511.48 | AH25: Galvanised Steel Round Wire | AI25: 82.9 | AJ25: 2364 | AK25: 195975.6 | AL25: FRLSH PVC Type ST-2 | AM25: 87.1 | AN25: 735 | AO25: 64018.5 | AR25: 0 | AV25: 0 | AX25: Water swellable Tape | AY25: 420 | AZ25: 0 | BA25: 0 | BD25: 0 | BH25: 0 | BL25: 0 | BP25: 0 | BR25: RUBBERIZED COTTON TAPE | BS25: 370 | BT25: 0 | BU25: 0 | BX25: 0 | BZ25: 40364 | CA25: 1073575.8 | CH25: 1073575.8 | CM25: 1073575.8 | CO25: 1073575.8 | CP25: 0.18 | CQ25: 193243.64 | CR25: 1266819.4 | CS25: 3 | CT25: KMS | CU25: 3800458 | CV25: MD0100048 | CW25: DRUM - 74 X 35 X 39 X 3 | CX25: 500
A26: ENQ-15115-22-23 | B26: 45698 | C26: FA1100094 | D26: 4 CORE X 95 SQ. MM. ALU/ARD - WIRE (XLPE) | E26: WOOD | H26: 0 | J26: Alumimium | K26: 272.36 | L26: 1027 | M26: 279713.72 | P26: 0 | T26: 0 | V26: LT-XLPE | W26: 114 | X26: 187 | Y26: 21318 | AB26: 0 | AD26: PVC Type ST-2 | AE26: 67.67 | AF26: 93 | AG26: 6293.31 | AH26: Galvanised Steel Round Wire | AI26: 82.9 | AJ26: 1200 | AK26: 99480 | AL26: FRLSH PVC Type ST-2 | AM26: 87.1 | AN26: 370 | AO26: 32227 | AR26: 0 | AV26: 0 | AZ26: 0 | BD26: 0 | BH26: 0 | BL26: 0 | BP26: 0 | BR26: RUBBERIZED COTTON TAPE | BS26: 370 | BT26: 0 | BU26: 0 | BX26: 0 | BZ26: 14928 | CA26: 453960.03 | CH26: 453960.03 | CM26: 453960.03 | CO26: 453960.03 | CP26: 0.18 | CQ26: 81712.81 | CR26: 535672.84 | CS26: 17.586 | CT26: KMS | CU26: 9420342 | CV26: MD0100061 | CW26: DRUM - 56 X 24 X 32 X 3 | CX26: 500
A27: ENQ-15115-22-23 | B27: 45698 | C27: FA1100176 | D27: 4 CORE X 300 SQ. MM. AL/ARD - WIRE (XLPE) | E27: STEEL | H27: 0 | J27: Alumimium | K27: 272.36 | L27: 3240 | M27: 882446.4 | P27: 0 | T27: 0 | V27: LT-XLPE | W27: 114 | X27: 488 | Y27: 55632 | AB27: 0 | AD27: PVC Type ST-2 | AE27: 67.67 | AF27: 255 | AG27: 17255.85 | AH27: Galvanised Steel Round Wire | AI27: 82.9 | AJ27: 3436 | AK27: 284844.4 | AL27: FRLSH PVC Type ST-2 | AM27: 87.1 | AN27: 888 | AO27: 77344.8 | AR27: 0 | AV27: 0 | AX27: Water swellable Tape | AY27: 420 | AZ27: 0 | BA27: 0 | BD27: 90 | BH27: 0 | BL27: 0 | BP27: 0 | BR27: RUBBERIZED COTTON TAPE | BS27: 370 | BT27: 36 | BU27: 13320 | BX27: 0 | BZ27: 78780 | CA27: 1409623.4 | CH27: 1409623.4 | CM27: 1409623.4 | CO27: 1409623.4 | CP27: 0.18 | CQ27: 253732.22 | CR27: 1663355.7 | CS27: 29 | CT27: KMS | CU27: 48237314 | CV27: SP0400139 | CW27: CORRUGATED DISPATCH STEEL DRUM 2130 X 890 X 965 | CX27: 500
A28: ENQ-15115-22-23 | B28: 45698 | C28: FA1100177 | D28: 4 CORE X 150 SQ. MM. AL/ARD - WIRE (XLPE) | E28: WOOD | H28: 0 | J28: Alumimium | K28: 272.36 | L28: 1620 | M28: 441223.2 | P28: 0 | T28: 0 | V28: LT-XLPE | W28: 114 | X28: 276 | Y28: 31464 | AB28: 0 | AD28: PVC Type ST-2 | AE28: 67.67 | AF28: 148 | AG28: 10015.16 | AH28: Galvanised Steel Round Wire | AI28: 82.9 | AJ28: 1965 | AK28: 162898.5 | AL28: FRLSH PVC Type ST-2 | AM28: 87.1 | AN28: 543 | AO28: 47295.3 | AR28: 0 | AV28: 0 | AX28: Water swellable Tape | AY28: 420 | AZ28: 0 | BA28: 0 | BD28: 48 | BH28: 0 | BL28: 0 | BP28: 0 | BR28: RUBBERIZED COTTON TAPE | BS28: 370 | BT28: 26 | BU28: 9620 | BX28: 0 | BZ28: 21178 | CA28: 723694.16 | CH28: 723694.16 | CM28: 723694.16 | CO28: 723694.16 | CP28: 0.18 | CQ28: 130264.95 | CR28: 853959.11 | CS28: 6.866 | CT28: KMS | CU28: 5863283 | CV28: MD0100024 | CW28: DRUM - 70 X 30 X 36 X 3 | CX28: 500

Sheet AUTO CALCULATION SHEET (2)
C2: TPCODL TPNODL TPSODL TPWODL (TATA Power and Odisha Government Joint Venture)
C4: TENDER SPECIFICATION NO () | D4: TPCODL / CCG / FY 25-26 / 1000001917
C5: TENDER DESCRIPTION () | D5: One Year Rate Contract for Supply of 1.1 kV Power and Control Cables at TPWODL, TPCODL & TPSODL.
C6: Last Date & Time of Submission () | D6: 15/Feb/2025 [17:00 Hrs.]
C7: REVERSE AUCTION | D7: Bidders shall be allowed to participate in Reverse auction as per following criteria hence bidders are advised to quote their most competitive rates while submitting the bids to avoid disqualification from participation in Reverse Auction. No of bidders allowed to participate in RA process shall be: Total No of bidders on whom tender would be split PLUS 2 more bidders.
C8: Price () | D8: Base circular shall be January 2025 circular issued in february 2025. Base month for Bid Price shall remain same throughout the negotiation process till Outline Agreement / Rate Contract is finalized.Base month circular has to be attached in the price bid.
C9: Validity () | D9: Bids shall remain valid for 180 days from the due date of submission of the bid.
C10: Delivery Period () | D10: Delivery Period shall be Delivery period shall be 60 + 7 days (considering the approval of CAT-A / drawing / GTP) from date of receipt of release order for the first lot however for remaining lots the delivery period will be 60 days from RO date. Exact delivery location shall be specified in the Release Order. Delivery will be the store locations in TPCODL, TPNODL and TPWODL based on RO Qty.The delivery period for a quantity of up to 200 KM shall be 60 days from the date of issuance of the RO or GTP drawing approval, whichever is later. For quantities exceeding 200 KM, the delivery period shall be mutually agreed upon between the BA and the DISCOM.
C11: Payment Terms () | D11: On delivery of the materials in good condition and certification of acceptance by certified official, Associate shall submit the Bills/ Invoices in original in the name of respective Odisha discom to Invoice Desk. The payment shall be released within 45 days from the date of submission of error free certified bills/ invoices. Any change in statutory taxes, duties and levies during the contract period shall be borne by respective Odisha DISCOMs. However, in case of delay in work execution owing to reasons not attributable to Odisha Disom, any increase in total liability shall be passed on the Bidder, whereas any benefits arising owing to such statutory variation in taxes and duties shall be passed on TP Discom.
C12: Standard length () | D12: Cable length on one drum shall be: (a) 4 Core Cable – 95 sq.mm. to 300 sq.mm. – 500 meters with + 5% tolerance (b) 4 Core Cable – 16 sq.mm. to 50 sq.mm. – 1000 meters with + 5% tolerance (c) 2 Core & 1 Core Cables – 1000 meters with + 5% tolerance (as per PO terms and conditions)
C13: Packing () | D13: Wooden drums shall be free from sharp edges and visual defects
C14: Technical Specification
P16: =Sheet1!J1 -> Conductor | U16: AL ALLOY | W16: Insulation Screening (Metallic) | AE16: Insulation Screening (Non-Metallic) | AG16: Insulation | AM16: POLY TAPE | AN16: Inner Sheath | AU16: Armouring | BE16: UV resistance RS-5/kg | BO16: FILLER | BP16: GREASE | BQ16: Water swellable Tape | BR16: Semi conducting Water Swellable tape | BS16: SEMICON TAPE | BT16: GLASS FIBER TAPE | BU16: COPPER WIRE 0.8 MM | BV16: RUBBERIZED COTTON TAPE | BW16: Water Tight Compound | CB16: DRUM COST PER KM | CC16: TOTAL RM COST | CD16: EXTRA CONSUMPTION | CE16: EXTRA CONSUMPTION VALUE
C17: DOCKET NO. | D17: =Sheet1!B1 -> Base Date | E17: ITEM CODE | F17: PROPOSE ERP ITEM NAME | G17: EX-WORKS (PER KM) | H17: FREIGHT PER KM | I17: PRICE INCLUDING FREIGHT (PER KM) | J17: GST % | K17: GST VALUE | L17: PRICE INCLUDING GST & FREIGHT (PER KM) | M17: QTY | N17: Unit | O17: TOTAL PRICE OF FULL QTY (INCLUDING FRIGHT & GST) | P17: Alumimium | Q17: Alumimium ALLOY | R17: Copper | S17: Flexible Copper | T17: Galvanized steel wire | U17: Alumimium | V17: Alumimium ALLOY | W17: Coper tape - 0.1 mm | X17: Copper Tape - 0.03 mm | Y17: Copper Tape - 0.035 mm | Z17: Copper Tape - 0.04 mm | AA17: Copper Tape - 0.045 mm | AB17: Copper Tape - 0.050 mm | AC17: Copper Tape - 0.060 mm | AD17: Copper Tape - 0.075 mm(DOUBLE) | AE17: Extruded semiconductive | AF17: Extruded Semiconductive(Stripable) | AG17: HT-XLPE | AH17: LT-XLPE | AI17: TR XLPE | AJ17: Type A PVC | AK17: Type C PVC (HR) | AL17: XLPE | AM17: POLY TAPE | AN17: FR PVC Type ST-1 | AO17: FR PVC Type ST-2 | AP17: FRLSH PVC Type ST-2 | AQ17: PVC Type ST-1 | AR17: PVC Type ST-1-PRESSURE EXTRUDED | AS17: PVC Type ST-2 | AT17: PVC Type ST-2-PRESSURE EXTRUDED | AU17: ACSR CORE WIRE | AV17: ACSR DOG STEEL WIRE | AW17: Aluminium Flat Strip | AX17: Aluminium Round Wire | AY17: Double Steel Tape | AZ17: Galvanised Steel Flat Strip | BA17: Galvanised Steel Flat Strip (Double) | BB17: Galvanised Steel Flat Strip-B | BC17: Galvanised Steel Round Wire | BD17: Galvanised Steel Round Wire (Double) | BE17: FR PVC Type ST-1 | BF17: FR PVC Type ST-2 | BG17: FRLSH PVC Type ST-1 | BH17: FRLSH PVC Type ST-2 | BI17: PE, ST-3 | BJ17: PE, ST-7 | BK17: PVC Type ST-1 | BL17: PVC Type ST-2 | BM17: PVC Type ST-2-PRESSURE EXTRUDED | BN17: UV & Track Resistant XLPE | BO17: FILLER | BP17: Grease | BQ17: NCWBT | BR17: Semi conducting Water Swellable tape | BS17: SEMICON TAPE | BT17: GLASS FIBER TAPE | BU17: COPPER WIRE 0.8 MM | BV17: RUBBERIZED COTTON TAPE | BW17: Water Tight Compound | BX17: =Sheet1!E1 -> Propose Drum Type | BY17: =Sheet1!CV1 -> DRUM CODE | BZ17: =Sheet1!CW1 -> DRUM SIZE (FxbXtx Ft) | CA17: =Sheet1!CX1 -> Party Standard Length(MTR) | CD17: 1% extra cost | CF17: MFG% | CG17: MFG VALUE | CH17: PROF% | CI17: PROFIT VALUE | CJ17: 1ST EX-WORKS | CK17: Intt % | CL17: INTT VALUE | CM17: insp% | CN17: INSP VALUE
P18: 262 | R18: 826 | AH18: 114 | AK18: 103 | AM18: 119 | AS18: 69 | AT18: 88 | BC18: 87 | BH18: =88+5 -> 93 | BQ18: 340 | BV18: 375 | BW18: =+IFERROR(VLOOKUP($BW$17,Sheet1!BV2:BY840,2,0),0) -> 0
B19: 1 | C19: =Sheet1!A8 -> ENQ-15115-22-23 | D19: 45658 | E19: =Sheet1!C8 -> FA0600013 | F19: =Sheet1!D8 -> 1 CORE X 95 SQ. MM. AL/UNARD(XLPE ) | G19: =CJ19+CL19+CN19 -> 104733.78 | H19: =ROUNDUP(O49,0) -> 1321 | I19: =G19+H19 -> 106054.78 | J19: =Sheet1!CP8 -> 0.18 | K19: =I19*J19 -> 19089.86 | L19: =I19+K19 -> 125144.64 | M19: 79.532 | N19: =Sheet1!CT8 -> KMS | O19: =L19*M19 -> 9953003.4 | P19: =+IFERROR(VLOOKUP($P$17,Sheet1!J8:L8,3,0),0) -> 256 | Q19: =+IFERROR(VLOOKUP($Q$17,Sheet1!J8:L8,3,0),0) -> 0 | R19: =+IFERROR(VLOOKUP($R$17,Sheet1!J8:M8,3,0),0) -> 0 | S19: =+IFERROR(VLOOKUP($S$17,Sheet1!J8:M8,3,0),0) -> 0 | T19: =+IFERROR(VLOOKUP($T$17,Sheet1!J8:M8,3,0),0) -> 0 | U19: =+IFERROR(VLOOKUP($U$17,Sheet1!N8:Q8,3,0),0) -> 0 | V19: =+IFERROR(VLOOKUP($V$17,Sheet1!N8:Q8,3,0),0) -> 0 | W19: =+IFERROR(VLOOKUP($W$17,Sheet1!F8:I8,3,0),0) -> 0 | X19: =+IFERROR(VLOOKUP($X$17,Sheet1!F8:I8,3,0),0) -> 0 | Y19: =+IFERROR(VLOOKUP($Y$17,Sheet1!F8:I8,3,0),0) -> 0 | Z19: =+IFERROR(VLOOKUP($Z$17,Sheet1!F8:I8,3,0),0) -> 0 | AA19: =+IFERROR(VLOOKUP($AA$17,Sheet1!F8:I8,3,0),0) -> 0 | AB19: =+IFERROR(VLOOKUP($AB$17,Sheet1!F8:I8,3,0),0) -> 0 | AC19: =+IFERROR(VLOOKUP($AC$17,Sheet1!F8:I8,3,0),0) -> 0 | AD19: =+IFERROR(VLOOKUP($AD$17,Sheet1!F8:I8,3,0),0) -> 0 | AE19: =+IFERROR(VLOOKUP($AE$17,Sheet1!R8:U8,3,0),0) -> 0 | AF19: =+IFERROR(VLOOKUP($AF$17,Sheet1!R8:U8,2,0),0) -> 0 | AG19: =+IFERROR(VLOOKUP($AG$17,Sheet1!V8:Y8,3,0),0) -> 0 | AH19: 44 | AI19: =+IFERROR(VLOOKUP($AI$17,Sheet1!V8:Y8,3,0),0) -> 0 | AJ19: =+IFERROR(VLOOKUP($AJ$17,Sheet1!V8:Y8,3,0),0) -> 0 | AK19: =+IFERROR(VLOOKUP($AK$17,Sheet1!V8:Y8,3,0),0) -> 0 | AL19: =+IFERROR(VLOOKUP($AL$17,Sheet1!V8:Y8,3,0),0) -> 0 | AM19: =+IFERROR(VLOOKUP($AM$17,Sheet1!Z8:AB8,3,0),0) -> 0 | AN19: =+IFERROR(VLOOKUP($AN$17,Sheet1!AD8:AG8,3,0),0) -> 0 | AO19: =+IFERROR(VLOOKUP($AO$17,Sheet1!AD8:AG8,3,0),0) -> 0 | AP19: =+IFERROR(VLOOKUP($AP$17,Sheet1!AD8:AG8,3,0),0) -> 0 | AQ19: =+IFERROR(VLOOKUP($AQ$17,Sheet1!AD8:AG8,3,0),0) -> 0 | AR19: =+IFERROR(VLOOKUP($AR$17,Sheet1!AD8:AG8,3,0),0) -> 0 | AS19: =+IFERROR(VLOOKUP($AS$17,Sheet1!AD8:AG8,3,0),0) -> 0 | AT19: =+IFERROR(VLOOKUP($AT$17,Sheet1!AD8:AG8,3,0),0) -> 0 | AU19: =+IFERROR(VLOOKUP($AU$17,Sheet1!AH8:AK8,3,0),0) -> 0 | AV19: =+IFERROR(VLOOKUP($AV$17,Sheet1!AH8:AK8,3,0),0) -> 0 | AW19: =+IFERROR(VLOOKUP($AW$17,Sheet1!AH8:AK8,3,0),0) -> 0 | AX19: =+IFERROR(VLOOKUP($AX$17,Sheet1!AH8:AK8,3,0),0) -> 0 | AY19: =+IFERROR(VLOOKUP($AY$17,Sheet1!AH8:AK8,3,0),0) -> 0 | AZ19: =+IFERROR(VLOOKUP($AZ$17,Sheet1!AH8:AK8,3,0),0) -> 0 | BA19: =+IFERROR(VLOOKUP($BA$17,Sheet1!AH8:AK8,3,0),0) -> 0 | BB19: =+IFERROR(VLOOKUP($BB$17,Sheet1!AH8:AK8,3,0),0) -> 0 | BC19: =+IFERROR(VLOOKUP($BC$17,Sheet1!AH8:AK8,3,0),0) -> 0 | BD19: =+IFERROR(VLOOKUP($BD$17,Sheet1!AH8:AK8,3,0),0) -> 0 | BE19: =+IFERROR(VLOOKUP($BE$17,Sheet1!AL8:AO8,3,0),0) -> 0 | BF19: =+IFERROR(VLOOKUP($BF$17,Sheet1!AL8:AO8,3,0),0) -> 0 | BG19: =+IFERROR(VLOOKUP($BG$17,Sheet1!AL8:AO8,3,0),0) -> 0 | BH19: 140 | BI19: =+IFERROR(VLOOKUP($BI$17,Sheet1!AL8:AO8,3,0),0) -> 0 | BJ19: =+IFERROR(VLOOKUP($BJ$17,Sheet1!AL8:AO8,3,0),0) -> 0 | BK19: =+IFERROR(VLOOKUP($BK$17,Sheet1!AL8:AO8,3,0),0) -> 0 | BL19: =+IFERROR(VLOOKUP($BL$17,Sheet1!AL8:AO8,3,0),0) -> 0 | BM19: =+IFERROR(VLOOKUP($BM$17,Sheet1!AL8:AO8,3,0),0) -> 0 | BN19: =+IFERROR(VLOOKUP($BN$17,Sheet1!AL8:AO8,3,0),0) -> 0 | BO19: =+IFERROR(VLOOKUP($BO$17,Sheet1!AP8:AS8,3,0),0) -> 0 | BP19: =+IFERROR(VLOOKUP($BP$17,Sheet1!AT8:AW8,3,0),0) -> 0 | BQ19: =+IFERROR(VLOOKUP($BQ$17,Sheet1!AX8:BA8,3,0),0) -> 0 | BR19: =+IFERROR(VLOOKUP($BR$17,Sheet1!BB8:BE8,3,0),0) -> 0 | BS19: =+IFERROR(VLOOKUP($BS$17,Sheet1!BF8:BI8,3,0),0) -> 0 | BT19: =+IFERROR(VLOOKUP($BT$17,Sheet1!BJ8:BM8,3,0),0) -> 0 | BU19: =+IFERROR(VLOOKUP($BU$17,Sheet1!BN8:BQ8,3,0),0) -> 0 | BV19: =+IFERROR(VLOOKUP($BV$17,Sheet1!BR8:BU8,3,0),0) -> 0 | BW19: =+IFERROR(VLOOKUP($BW$17,Sheet1!BV8:BY8,3,0),0) -> 0 | BX19: =Sheet1!E8 -> WOOD | BY19: =Sheet1!CV8 -> MD0100066 | BZ19: =Sheet1!CW8 -> DRUM - 40 X 15 X 23 X 2 | CA19: =Sheet1!CX8 -> 1000 | CB19: =Sheet1!BZ8 -> 2550 | CC19: =SUMPRODUCT($P$18:$BW$18,P19:BW19)+CB19 -> 87658 | CD19: 0.01 | CE19: =CC19*CD19 -> 876.58 | CF19: 0.15 | CG19: =CC19*CF19 -> 13148.7 | CH19: 0 | CI19: =CC19*CH19 -> 0 | CJ19: =CC19+CE19+CG19+CI19 -> 101683.28 | CK19: 0.02 | CL19: =CJ19*CK19 -> 2033.6656 | CM19: 0.01 | CN19: =CJ19*CM19 -> 1016.8328
B20: 2 | C20: =Sheet1!A9 -> ENQ-15115-22-23 | D20: 45658 | E20: =Sheet1!C9 -> FA0600019 | F20: =Sheet1!D9 -> 1 CORE X 150 SQ. MM. AL/UNARD. (XLPE) | G20: =CJ20+CL20+CN20 -> 168250.54 | H20: =ROUNDUP(O50,0) -> 1833 | I20: =G20+H20 -> 170083.54 | J20: =Sheet1!CP9 -> 0.18 | K20: =I20*J20 -> 30615.037 | L20: =I20+K20 -> 200698.58 | M20: =Sheet1!CS9 -> 57.308 | N20: =Sheet1!CT9 -> KMS | O20: =L20*M20 -> 11501634 | P20: =+IFERROR(VLOOKUP($P$17,Sheet1!J9:L9,3,0),0) -> 405 | Q20: =+IFERROR(VLOOKUP($Q$17,Sheet1!J9:L9,3,0),0) -> 0 | R20: =+IFERROR(VLOOKUP($R$17,Sheet1!J9:M9,3,0),0) -> 0 | S20: =+IFERROR(VLOOKUP($S$17,Sheet1!J9:M9,3,0),0) -> 0 | T20: =+IFERROR(VLOOKUP($T$17,Sheet1!J9:M9,3,0),0) -> 0 | U20: =+IFERROR(VLOOKUP($U$17,Sheet1!N9:Q9,3,0),0) -> 0 | V20: =+IFERROR(VLOOKUP($V$17,Sheet1!N9:Q9,3,0),0) -> 0 | W20: =+IFERROR(VLOOKUP($W$17,Sheet1!F9:I9,3,0),0) -> 0 | X20: =+IFERROR(VLOOKUP($X$17,Sheet1!F9:I9,3,0),0) -> 0 | Y20: =+IFERROR(VLOOKUP($Y$17,Sheet1!F9:I9,3,0),0) -> 0 | Z20: =+IFERROR(VLOOKUP($Z$17,Sheet1!F9:I9,3,0),0) -> 0 | AA20: =+IFERROR(VLOOKUP($AA$17,Sheet1!F9:I9,3,0),0) -> 0 | AB20: =+IFERROR(VLOOKUP($AB$17,Sheet1!F9:I9,3,0),0) -> 0 | AC20: =+IFERROR(VLOOKUP($AC$17,Sheet1!F9:I9,3,0),0) -> 0 | AD20: =+IFERROR(VLOOKUP($AD$17,Sheet1!F9:I9,3,0),0) -> 0 | AE20: =+IFERROR(VLOOKUP($AE$17,Sheet1!R9:U9,3,0),0) -> 0 | AF20: =+IFERROR(VLOOKUP($AF$17,Sheet1!R9:U9,2,0),0) -> 0 | AG20: =+IFERROR(VLOOKUP($AG$17,Sheet1!V9:Y9,3,0),0) -> 0 | AH20: =+IFERROR(VLOOKUP($AH$17,Sheet1!V9:Y9,3,0),0) -> 72 | AI20: =+IFERROR(VLOOKUP($AI$17,Sheet1!V9:Y9,3,0),0) -> 0 | AJ20: =+IFERROR(VLOOKUP($AJ$17,Sheet1!V9:Y9,3,0),0) -> 0 | AK20: =+IFERROR(VLOOKUP($AK$17,Sheet1!V9:Y9,3,0),0) -> 0 | AL20: =+IFERROR(VLOOKUP($AL$17,Sheet1!V9:Y9,3,0),0) -> 0 | AM20: =+IFERROR(VLOOKUP($AM$17,Sheet1!Z9:AB9,3,0),0) -> 0 | AN20: =+IFERROR(VLOOKUP($AN$17,Sheet1!AD9:AG9,3,0),0) -> 0 | AO20: =+IFERROR(VLOOKUP($AO$17,Sheet1!AD9:AG9,3,0),0) -> 0 | AP20: =+IFERROR(VLOOKUP($AP$17,Sheet1!AD9:AG9,3,0),0) -> 0 | AQ20: =+IFERROR(VLOOKUP($AQ$17,Sheet1!AD9:AG9,3,0),0) -> 0 | AR20: =+IFERROR(VLOOKUP($AR$17,Sheet1!AD9:AG9,3,0),0) -> 0 | AS20: =+IFERROR(VLOOKUP($AS$17,Sheet1!AD9:AG9,3,0),0) -> 0 | AT20: =+IFERROR(VLOOKUP($AT$17,Sheet1!AD9:AG9,3,0),0) -> 0 | AU20: =+IFERROR(VLOOKUP($AU$17,Sheet1!AH9:AK9,3,0),0) -> 0 | AV20: =+IFERROR(VLOOKUP($AV$17,Sheet1!AH9:AK9,3,0),0) -> 0 | AW20: =+IFERROR(VLOOKUP($AW$17,Sheet1!AH9:AK9,3,0),0) -> 0 | AX20: =+IFERROR(VLOOKUP($AX$17,Sheet1!AH9:AK9,3,0),0) -> 0 | AY20: =+IFERROR(VLOOKUP($AY$17,Sheet1!AH9:AK9,3,0),0) -> 0 | AZ20: =+IFERROR(VLOOKUP($AZ$17,Sheet1!AH9:AK9,3,0),0) -> 0 | BA20: =+IFERROR(VLOOKUP($BA$17,Sheet1!AH9:AK9,3,0),0) -> 0 | BB20: =+IFERROR(VLOOKUP($BB$17,Sheet1!AH9:AK9,3,0),0) -> 0 | BC20: =+IFERROR(VLOOKUP($BC$17,Sheet1!AH9:AK9,3,0),0) -> 0 | BD20: =+IFERROR(VLOOKUP($BD$17,Sheet1!AH9:AK9,3,0),0) -> 0 | BE20: =+IFERROR(VLOOKUP($BE$17,Sheet1!AL9:AO9,3,0),0) -> 0 | BF20: =+IFERROR(VLOOKUP($BF$17,Sheet1!AL9:AO9,3,0),0) -> 0 | BG20: =+IFERROR(VLOOKUP($BG$17,Sheet1!AL9:AO9,3,0),0) -> 0 | BH20: 195 | BI20: =+IFERROR(VLOOKUP($BI$17,Sheet1!AL9:AO9,3,0),0) -> 0 | BJ20: =+IFERROR(VLOOKUP($BJ$17,Sheet1!AL9:AO9,3,0),0) -> 0 | BK20: =+IFERROR(VLOOKUP($BK$17,Sheet1!AL9:AO9,3,0),0) -> 0 | BL20: =+IFERROR(VLOOKUP($BL$17,Sheet1!AL9:AO9,3,0),0) -> 0 | BM20: =+IFERROR(VLOOKUP($BM$17,Sheet1!AL9:AO9,3,0),0) -> 0 | BN20: =+IFERROR(VLOOKUP($BN$17,Sheet1!AL9:AO9,3,0),0) -> 0 | BO20: =+IFERROR(VLOOKUP($BO$17,Sheet1!AP9:AS9,3,0),0) -> 0 | BP20: =+IFERROR(VLOOKUP($BP$17,Sheet1!AT9:AW9,3,0),0) -> 0 | BQ20: 14 | BR20: =+IFERROR(VLOOKUP($BR$17,Sheet1!BB9:BE9,3,0),0) -> 0 | BS20: =+IFERROR(VLOOKUP($BS$17,Sheet1!BF9:BI9,3,0),0) -> 0 | BT20: =+IFERROR(VLOOKUP($BT$17,Sheet1!BJ9:BM9,3,0),0) -> 0 | BU20: =+IFERROR(VLOOKUP($BU$17,Sheet1!BN9:BQ9,3,0),0) -> 0 | BV20: =+IFERROR(VLOOKUP($BV$17,Sheet1!BR9:BU9,3,0),0) -> 0 | BW20: =+IFERROR(VLOOKUP($BW$17,Sheet1!BV9:BY9,3,0),0) -> 0 | BX20: =Sheet1!E9 -> WOOD | BY20: =Sheet1!CV9 -> MD0100085 | BZ20: =Sheet1!CW9 -> DRUM - 43 X 15 X 28 X 2.25 | CA20: =Sheet1!CX9 -> 1000 | CB20: =Sheet1!BZ9 -> 3606 | CC20: =SUMPRODUCT($P$18:$BW$18,P20:BW20)+CB20 -> 140819 | CD20: 0.01 | CE20: =CC20*CD20 -> 1408.19 | CF20: 0.15 | CG20: =CC20*CF20 -> 21122.85 | CH20: 0 | CI20: =CC20*CH20 -> 0 | CJ20: =CC20+CE20+CG20+CI20 -> 163350.04 | CK20: 0.02 | CL20: =CJ20*CK20 -> 3267.0008 | CM20: 0.01 | CN20: =CJ20*CM20 -> 1633.5004
B21: 3 | C21: =Sheet1!A11 -> ENQ-15115-22-23 | D21: 45658 | E21: =Sheet1!C11 -> FA0600021 | F21: =Sheet1!D11 -> 1 CORE X 185 SQ. MM. AL/UNARD. (XLPE) | G21: =CJ21+CL21+CN21 -> 206352.71 | H21: =ROUNDUP(O51,0) -> 2938 | I21: =G21+H21 -> 209290.71 | J21: =Sheet1!CP11 -> 0.18 | K21: =I21*J21 -> 37672.328 | L21: =I21+K21 -> 246963.04 | M21: =Sheet1!CS11 -> 35.75 | N21: =Sheet1!CT11 -> KMS | O21: =L21*M21 -> 8828928.7 | P21: =+IFERROR(VLOOKUP($P$17,Sheet1!J11:L11,3,0),0) -> 500 | Q21: =+IFERROR(VLOOKUP($Q$17,Sheet1!J11:L11,3,0),0) -> 0 | R21: =+IFERROR(VLOOKUP($R$17,Sheet1!J11:M11,3,0),0) -> 0 | S21: =+IFERROR(VLOOKUP($S$17,Sheet1!J11:M11,3,0),0) -> 0 | T21: =+IFERROR(VLOOKUP($T$17,Sheet1!J11:M11,3,0),0) -> 0 | U21: =+IFERROR(VLOOKUP($U$17,Sheet1!N11:Q11,3,0),0) -> 0 | V21: =+IFERROR(VLOOKUP($V$17,Sheet1!N11:Q11,3,0),0) -> 0 | W21: =+IFERROR(VLOOKUP($W$17,Sheet1!F11:I11,3,0),0) -> 0 | X21: =+IFERROR(VLOOKUP($X$17,Sheet1!F11:I11,3,0),0) -> 0 | Y21: =+IFERROR(VLOOKUP($Y$17,Sheet1!F11:I11,3,0),0) -> 0 | Z21: =+IFERROR(VLOOKUP($Z$17,Sheet1!F11:I11,3,0),0) -> 0 | AA21: =+IFERROR(VLOOKUP($AA$17,Sheet1!F11:I11,3,0),0) -> 0 | AB21: =+IFERROR(VLOOKUP($AB$17,Sheet1!F11:I11,3,0),0) -> 0 | AC21: =+IFERROR(VLOOKUP($AC$17,Sheet1!F11:I11,3,0),0) -> 0 | AD21: =+IFERROR(VLOOKUP($AD$17,Sheet1!F11:I11,3,0),0) -> 0 | AE21: =+IFERROR(VLOOKUP($AE$17,Sheet1!R11:U11,3,0),0) -> 0 | AF21: =+IFERROR(VLOOKUP($AF$17,Sheet1!R11:U11,2,0),0) -> 0 | AG21: =+IFERROR(VLOOKUP($AG$17,Sheet1!V11:Y11,3,0),0) -> 0 | AH21: =+IFERROR(VLOOKUP($AH$17,Sheet1!V11:Y11,3,0),0) -> 90 | AI21: =+IFERROR(VLOOKUP($AI$17,Sheet1!V11:Y11,3,0),0) -> 0 | AJ21: =+IFERROR(VLOOKUP($AJ$17,Sheet1!V11:Y11,3,0),0) -> 0 | AK21: =+IFERROR(VLOOKUP($AK$17,Sheet1!V11:Y11,3,0),0) -> 0 | AL21: =+IFERROR(VLOOKUP($AL$17,Sheet1!V11:Y11,3,0),0) -> 0 | AM21: =+IFERROR(VLOOKUP($AM$17,Sheet1!Z11:AB11,3,0),0) -> 0 | AN21: =+IFERROR(VLOOKUP($AN$17,Sheet1!AD11:AG11,3,0),0) -> 0 | AO21: =+IFERROR(VLOOKUP($AO$17,Sheet1!AD11:AG11,3,0),0) -> 0 | AP21: =+IFERROR(VLOOKUP($AP$17,Sheet1!AD11:AG11,3,0),0) -> 0 | AQ21: =+IFERROR(VLOOKUP($AQ$17,Sheet1!AD11:AG11,3,0),0) -> 0 | AR21: =+IFERROR(VLOOKUP($AR$17,Sheet1!AD11:AG11,3,0),0) -> 0 | AS21: =+IFERROR(VLOOKUP($AS$17,Sheet1!AD11:AG11,3,0),0) -> 0 | AT21: =+IFERROR(VLOOKUP($AT$17,Sheet1!AD11:AG11,3,0),0) -> 0 | AU21: =+IFERROR(VLOOKUP($AU$17,Sheet1!AH11:AK11,3,0),0) -> 0 | AV21: =+IFERROR(VLOOKUP($AV$17,Sheet1!AH11:AK11,3,0),0) -> 0 | AW21: =+IFERROR(VLOOKUP($AW$17,Sheet1!AH11:AK11,3,0),0) -> 0 | AX21: =+IFERROR(VLOOKUP($AX$17,Sheet1!AH11:AK11,3,0),0) -> 0 | AY21: =+IFERROR(VLOOKUP($AY$17,Sheet1!AH11:AK11,3,0),0) -> 0 | AZ21: =+IFERROR(VLOOKUP($AZ$17,Sheet1!AH11:AK11,3,0),0) -> 0 | BA21: =+IFERROR(VLOOKUP($BA$17,Sheet1!AH11:AK11,3,0),0) -> 0 | BB21: =+IFERROR(VLOOKUP($BB$17,Sheet1!AH11:AK11,3,0),0) -> 0 | BC21: =+IFERROR(VLOOKUP($BC$17,Sheet1!AH11:AK11,3,0),0) -> 0 | BD21: =+IFERROR(VLOOKUP($BD$17,Sheet1!AH11:AK11,3,0),0) -> 0 | BE21: =+IFERROR(VLOOKUP($BE$17,Sheet1!AL11:AO11,3,0),0) -> 0 | BF21: =+IFERROR(VLOOKUP($BF$17,Sheet1!AL11:AO11,3,0),0) -> 0 | BG21: =+IFERROR(VLOOKUP($BG$17,Sheet1!AL11:AO11,3,0),0) -> 0 | BH21: 216 | BI21: =+IFERROR(VLOOKUP($BI$17,Sheet1!AL11:AO11,3,0),0) -> 0 | BJ21: =+IFERROR(VLOOKUP($BJ$17,Sheet1!AL11:AO11,3,0),0) -> 0 | BK21: =+IFERROR(VLOOKUP($BK$17,Sheet1!AL11:AO11,3,0),0) -> 0 | BL21: =+IFERROR(VLOOKUP($BL$17,Sheet1!AL11:AO11,3,0),0) -> 0 | BM21: =+IFERROR(VLOOKUP($BM$17,Sheet1!AL11:AO11,3,0),0) -> 0 | BN21: =+IFERROR(VLOOKUP($BN$17,Sheet1!AL11:AO11,3,0),0) -> 0 | BO21: =+IFERROR(VLOOKUP($BO$17,Sheet1!AP11:AS11,3,0),0) -> 0 | BP21: =+IFERROR(VLOOKUP($BP$17,Sheet1!AT11:AW11,3,0),0) -> 0 | BQ21: 22 | BR21: =+IFERROR(VLOOKUP($BR$17,Sheet1!BB11:BE11,3,0),0) -> 0 | BS21: =+IFERROR(VLOOKUP($BS$17,Sheet1!BF11:BI11,3,0),0) -> 0 | BT21: =+IFERROR(VLOOKUP($BT$17,Sheet1!BJ11:BM11,3,0),0) -> 0 | BU21: =+IFERROR(VLOOKUP($BU$17,Sheet1!BN11:BQ11,3,0),0) -> 0 | BV21: =+IFERROR(VLOOKUP($BV$17,Sheet1!BR11:BU11,3,0),0) -> 0 | BW21: =+IFERROR(VLOOKUP($BW$17,Sheet1!BV11:BY11,3,0),0) -> 0 | BX21: =Sheet1!E11 -> WOOD | BY21: =Sheet1!CV11 -> MD0100090 | BZ21: =Sheet1!CW11 -> DRUM - 43 X 15 X 36 X 2.5 | CA21: =Sheet1!CX11 -> 1000 | CB21: =Sheet1!BZ11 -> 3881 | CC21: =SUMPRODUCT($P$18:$BW$18,P21:BW21)+CB21 -> 172709 | CD21: 0.01 | CE21: =CC21*CD21 -> 1727.09 | CF21: 0.15 | CG21: =CC21*CF21 -> 25906.35 | CH21: 0 | CI21: =CC21*CH21 -> 0 | CJ21: =CC21+CE21+CG21+CI21 -> 200342.44 | CK21: 0.02 | CL21: =CJ21*CK21 -> 4006.8488 | CM21: 0.01 | CN21: =CJ21*CM21 -> 2003.4244
B22: 4 | C22: =Sheet1!A10 -> ENQ-15115-22-23 | D22: 45658 | E22: =Sheet1!C10 -> FA0600020 | F22: =Sheet1!D10 -> 1 CORE X 300 SQ. MM. AL/UNARD. (XLPE) | G22: =CJ22+CL22+CN22 -> 318747.55 | H22: =ROUNDUP(O52,0) -> 4721 | I22: =G22+H22 -> 323468.55 | J22: =Sheet1!CP10 -> 0.18 | K22: =I22*J22 -> 58224.339 | L22: =I22+K22 -> 381692.89 | M22: 81.552 | N22: =Sheet1!CT10 -> KMS | O22: =L22*M22 -> 31127818 | P22: =+IFERROR(VLOOKUP($P$17,Sheet1!J10:L10,3,0),0) -> 810 | Q22: =+IFERROR(VLOOKUP($Q$17,Sheet1!J10:L10,3,0),0) -> 0 | R22: =+IFERROR(VLOOKUP($R$17,Sheet1!J10:M10,3,0),0) -> 0 | S22: =+IFERROR(VLOOKUP($S$17,Sheet1!J10:M10,3,0),0) -> 0 | T22: =+IFERROR(VLOOKUP($T$17,Sheet1!J10:M10,3,0),0) -> 0 | U22: =+IFERROR(VLOOKUP($U$17,Sheet1!N10:Q10,3,0),0) -> 0 | V22: =+IFERROR(VLOOKUP($V$17,Sheet1!N10:Q10,3,0),0) -> 0 | W22: =+IFERROR(VLOOKUP($W$17,Sheet1!F10:I10,3,0),0) -> 0 | X22: =+IFERROR(VLOOKUP($X$17,Sheet1!F10:I10,3,0),0) -> 0 | Y22: =+IFERROR(VLOOKUP($Y$17,Sheet1!F10:I10,3,0),0) -> 0 | Z22: =+IFERROR(VLOOKUP($Z$17,Sheet1!F10:I10,3,0),0) -> 0 | AA22: =+IFERROR(VLOOKUP($AA$17,Sheet1!F10:I10,3,0),0) -> 0 | AB22: =+IFERROR(VLOOKUP($AB$17,Sheet1!F10:I10,3,0),0) -> 0 | AC22: =+IFERROR(VLOOKUP($AC$17,Sheet1!F10:I10,3,0),0) -> 0 | AD22: =+IFERROR(VLOOKUP($AD$17,Sheet1!F10:I10,3,0),0) -> 0 | AE22: =+IFERROR(VLOOKUP($AE$17,Sheet1!R10:U10,3,0),0) -> 0 | AF22: =+IFERROR(VLOOKUP($AF$17,Sheet1!R10:U10,2,0),0) -> 0 | AG22: =+IFERROR(VLOOKUP($AG$17,Sheet1!V10:Y10,3,0),0) -> 0 | AH22: =+IFERROR(VLOOKUP($AH$17,Sheet1!V10:Y10,3,0),0) -> 132 | AI22: =+IFERROR(VLOOKUP($AI$17,Sheet1!V10:Y10,3,0),0) -> 0 | AJ22: =+IFERROR(VLOOKUP($AJ$17,Sheet1!V10:Y10,3,0),0) -> 0 | AK22: =+IFERROR(VLOOKUP($AK$17,Sheet1!V10:Y10,3,0),0) -> 0 | AL22: =+IFERROR(VLOOKUP($AL$17,Sheet1!V10:Y10,3,0),0) -> 0 | AM22: =+IFERROR(VLOOKUP($AM$17,Sheet1!Z10:AB10,3,0),0) -> 0 | AN22: =+IFERROR(VLOOKUP($AN$17,Sheet1!AD10:AG10,3,0),0) -> 0 | AO22: =+IFERROR(VLOOKUP($AO$17,Sheet1!AD10:AG10,3,0),0) -> 0 | AP22: =+IFERROR(VLOOKUP($AP$17,Sheet1!AD10:AG10,3,0),0) -> 0 | AQ22: =+IFERROR(VLOOKUP($AQ$17,Sheet1!AD10:AG10,3,0),0) -> 0 | AR22: =+IFERROR(VLOOKUP($AR$17,Sheet1!AD10:AG10,3,0),0) -> 0 | AS22: =+IFERROR(VLOOKUP($AS$17,Sheet1!AD10:AG10,3,0),0) -> 0 | AT22: =+IFERROR(VLOOKUP($AT$17,Sheet1!AD10:AG10,3,0),0) -> 0 | AU22: =+IFERROR(VLOOKUP($AU$17,Sheet1!AH10:AK10,3,0),0) -> 0 | AV22: =+IFERROR(VLOOKUP($AV$17,Sheet1!AH10:AK10,3,0),0) -> 0 | AW22: =+IFERROR(VLOOKUP($AW$17,Sheet1!AH10:AK10,3,0),0) -> 0 | AX22: =+IFERROR(VLOOKUP($AX$17,Sheet1!AH10:AK10,3,0),0) -> 0 | AY22: =+IFERROR(VLOOKUP($AY$17,Sheet1!AH10:AK10,3,0),0) -> 0 | AZ22: =+IFERROR(VLOOKUP($AZ$17,Sheet1!AH10:AK10,3,0),0) -> 0 | BA22: =+IFERROR(VLOOKUP($BA$17,Sheet1!AH10:AK10,3,0),0) -> 0 | BB22: =+IFERROR(VLOOKUP($BB$17,Sheet1!AH10:AK10,3,0),0) -> 0 | BC22: =+IFERROR(VLOOKUP($BC$17,Sheet1!AH10:AK10,3,0),0) -> 0 | BD22: =+IFERROR(VLOOKUP($BD$17,Sheet1!AH10:AK10,3,0),0) -> 0 | BE22: =+IFERROR(VLOOKUP($BE$17,Sheet1!AL10:AO10,3,0),0) -> 0 | BF22: =+IFERROR(VLOOKUP($BF$17,Sheet1!AL10:AO10,3,0),0) -> 0 | BG22: =+IFERROR(VLOOKUP($BG$17,Sheet1!AL10:AO10,3,0),0) -> 0 | BH22: 255 | BI22: =+IFERROR(VLOOKUP($BI$17,Sheet1!AL10:AO10,3,0),0) -> 0 | BJ22: =+IFERROR(VLOOKUP($BJ$17,Sheet1!AL10:AO10,3,0),0) -> 0 | BK22: =+IFERROR(VLOOKUP($BK$17,Sheet1!AL10:AO10,3,0),0) -> 0 | BL22: =+IFERROR(VLOOKUP($BL$17,Sheet1!AL10:AO10,3,0),0) -> 0 | BM22: =+IFERROR(VLOOKUP($BM$17,Sheet1!AL10:AO10,3,0),0) -> 0 | BN22: =+IFERROR(VLOOKUP($BN$17,Sheet1!AL10:AO10,3,0),0) -> 0 | BO22: =+IFERROR(VLOOKUP($BO$17,Sheet1!AP10:AS10,3,0),0) -> 0 | BP22: =+IFERROR(VLOOKUP($BP$17,Sheet1!AT10:AW10,3,0),0) -> 0 | BQ22: 28 | BR22: =+IFERROR(VLOOKUP($BR$17,Sheet1!BB10:BE10,3,0),0) -> 0 | BS22: =+IFERROR(VLOOKUP($BS$17,Sheet1!BF10:BI10,3,0),0) -> 0 | BT22: =+IFERROR(VLOOKUP($BT$17,Sheet1!BJ10:BM10,3,0),0) -> 0 | BU22: =+IFERROR(VLOOKUP($BU$17,Sheet1!BN10:BQ10,3,0),0) -> 0 | BV22: =+IFERROR(VLOOKUP($BV$17,Sheet1!BR10:BU10,3,0),0) -> 0 | BW22: =+IFERROR(VLOOKUP($BW$17,Sheet1!BV10:BY10,3,0),0) -> 0 | BX22: =Sheet1!E10 -> WOOD | BY22: =Sheet1!CV10 -> MD0100017 | BZ22: =Sheet1!CW10 -> DRUM - 52 X 18 X 36 X 2.5 | CA22: =Sheet1!CX10 -> 1000 | CB22: =Sheet1!BZ10 -> 6276 | CC22: =SUMPRODUCT($P$18:$BW$18,P22:BW22)+CB22 -> 266779 | CD22: 0.01 | CE22: =CC22*CD22 -> 2667.79 | CF22: 0.15 | CG22: =CC22*CF22 -> 40016.85 | CH22: 0 | CI22: =CC22*CH22 -> 0 | CJ22: =CC22+CE22+CG22+CI22 -> 309463.64 | CK22: 0.02 | CL22: =CJ22*CK22 -> 6189.2728 | CM22: 0.01 | CN22: =CJ22*CM22 -> 3094.6364
B23: 5 | C23: =Sheet1!A12 -> ENQ-15115-22-23 | D23: 45658 | E23: =Sheet1!C12 -> FA0600032 | F23: =Sheet1!D12 -> 1 CORE X 630 SQ. MM. ALU/UNARD (XLPE) | G23: =CJ23+CL23+CN23 -> 643530.03 | H23: =ROUNDUP(O53,0) -> 7235 | I23: =G23+H23 -> 650765.03 | J23: =Sheet1!CP12 -> 0.18 | K23: =I23*J23 -> 117137.71 | L23: =I23+K23 -> 767902.74 | M23: 38.704 | N23: =Sheet1!CT12 -> KMS | O23: =L23*M23 -> 29720908 | P23: =+IFERROR(VLOOKUP($P$17,Sheet1!J12:L12,3,0),0) -> 1701 | Q23: =+IFERROR(VLOOKUP($Q$17,Sheet1!J12:L12,3,0),0) -> 0 | R23: =+IFERROR(VLOOKUP($R$17,Sheet1!J12:M12,3,0),0) -> 0 | S23: =+IFERROR(VLOOKUP($S$17,Sheet1!J12:M12,3,0),0) -> 0 | T23: =+IFERROR(VLOOKUP($T$17,Sheet1!J12:M12,3,0),0) -> 0 | U23: =+IFERROR(VLOOKUP($U$17,Sheet1!N12:Q12,3,0),0) -> 0 | V23: =+IFERROR(VLOOKUP($V$17,Sheet1!N12:Q12,3,0),0) -> 0 | W23: =+IFERROR(VLOOKUP($W$17,Sheet1!F12:I12,3,0),0) -> 0 | X23: =+IFERROR(VLOOKUP($X$17,Sheet1!F12:I12,3,0),0) -> 0 | Y23: =+IFERROR(VLOOKUP($Y$17,Sheet1!F12:I12,3,0),0) -> 0 | Z23: =+IFERROR(VLOOKUP($Z$17,Sheet1!F12:I12,3,0),0) -> 0 | AA23: =+IFERROR(VLOOKUP($AA$17,Sheet1!F12:I12,3,0),0) -> 0 | AB23: =+IFERROR(VLOOKUP($AB$17,Sheet1!F12:I12,3,0),0) -> 0 | AC23: =+IFERROR(VLOOKUP($AC$17,Sheet1!F12:I12,3,0),0) -> 0 | AD23: =+IFERROR(VLOOKUP($AD$17,Sheet1!F12:I12,3,0),0) -> 0 | AE23: =+IFERROR(VLOOKUP($AE$17,Sheet1!R12:U12,3,0),0) -> 0 | AF23: =+IFERROR(VLOOKUP($AF$17,Sheet1!R12:U12,2,0),0) -> 0 | AG23: =+IFERROR(VLOOKUP($AG$17,Sheet1!V12:Y12,3,0),0) -> 0 | AH23: 242 | AI23: =+IFERROR(VLOOKUP($AI$17,Sheet1!V12:Y12,3,0),0) -> 0 | AJ23: =+IFERROR(VLOOKUP($AJ$17,Sheet1!V12:Y12,3,0),0) -> 0 | AK23: =+IFERROR(VLOOKUP($AK$17,Sheet1!V12:Y12,3,0),0) -> 0 | AL23: =+IFERROR(VLOOKUP($AL$17,Sheet1!V12:Y12,3,0),0) -> 0 | AM23: =+IFERROR(VLOOKUP($AM$17,Sheet1!Z12:AB12,3,0),0) -> 0 | AN23: =+IFERROR(VLOOKUP($AN$17,Sheet1!AD12:AG12,3,0),0) -> 0 | AO23: =+IFERROR(VLOOKUP($AO$17,Sheet1!AD12:AG12,3,0),0) -> 0 | AP23: =+IFERROR(VLOOKUP($AP$17,Sheet1!AD12:AG12,3,0),0) -> 0 | AQ23: =+IFERROR(VLOOKUP($AQ$17,Sheet1!AD12:AG12,3,0),0) -> 0 | AR23: =+IFERROR(VLOOKUP($AR$17,Sheet1!AD12:AG12,3,0),0) -> 0 | AS23: =+IFERROR(VLOOKUP($AS$17,Sheet1!AD12:AG12,3,0),0) -> 0 | AT23: =+IFERROR(VLOOKUP($AT$17,Sheet1!AD12:AG12,3,0),0) -> 0 | AU23: =+IFERROR(VLOOKUP($AU$17,Sheet1!AH12:AK12,3,0),0) -> 0 | AV23: =+IFERROR(VLOOKUP($AV$17,Sheet1!AH12:AK12,3,0),0) -> 0 | AW23: =+IFERROR(VLOOKUP($AW$17,Sheet1!AH12:AK12,3,0),0) -> 0 | AX23: =+IFERROR(VLOOKUP($AX$17,Sheet1!AH12:AK12,3,0),0) -> 0 | AY23: =+IFERROR(VLOOKUP($AY$17,Sheet1!AH12:AK12,3,0),0) -> 0 | AZ23: =+IFERROR(VLOOKUP($AZ$17,Sheet1!AH12:AK12,3,0),0) -> 0 | BA23: =+IFERROR(VLOOKUP($BA$17,Sheet1!AH12:AK12,3,0),0) -> 0 | BB23: =+IFERROR(VLOOKUP($BB$17,Sheet1!AH12:AK12,3,0),0) -> 0 | BC23: =+IFERROR(VLOOKUP($BC$17,Sheet1!AH12:AK12,3,0),0) -> 0 | BD23: =+IFERROR(VLOOKUP($BD$17,Sheet1!AH12:AK12,3,0),0) -> 0 | BE23: =+IFERROR(VLOOKUP($BE$17,Sheet1!AL12:AO12,3,0),0) -> 0 | BF23: =+IFERROR(VLOOKUP($BF$17,Sheet1!AL12:AO12,3,0),0) -> 0 | BG23: =+IFERROR(VLOOKUP($BG$17,Sheet1!AL12:AO12,3,0),0) -> 0 | BH23: 408 | BI23: =+IFERROR(VLOOKUP($BI$17,Sheet1!AL12:AO12,3,0),0) -> 0 | BJ23: =+IFERROR(VLOOKUP($BJ$17,Sheet1!AL12:AO12,3,0),0) -> 0 | BK23: =+IFERROR(VLOOKUP($BK$17,Sheet1!AL12:AO12,3,0),0) -> 0 | BL23: =+IFERROR(VLOOKUP($BL$17,Sheet1!AL12:AO12,3,0),0) -> 0 | BM23: =+IFERROR(VLOOKUP($BM$17,Sheet1!AL12:AO12,3,0),0) -> 0 | BN23: =+IFERROR(VLOOKUP($BN$17,Sheet1!AL12:AO12,3,0),0) -> 0 | BO23: =+IFERROR(VLOOKUP($BO$17,Sheet1!AP12:AS12,3,0),0) -> 0 | BP23: =+IFERROR(VLOOKUP($BP$17,Sheet1!AT12:AW12,3,0),0) -> 0 | BQ23: 40 | BR23: =+IFERROR(VLOOKUP($BR$17,Sheet1!BB12:BE12,3,0),0) -> 0 | BS23: =+IFERROR(VLOOKUP($BS$17,Sheet1!BF12:BI12,3,0),0) -> 0 | BT23: =+IFERROR(VLOOKUP($BT$17,Sheet1!BJ12:BM12,3,0),0) -> 0 | BU23: =+IFERROR(VLOOKUP($BU$17,Sheet1!BN12:BQ12,3,0),0) -> 0 | BV23: =+IFERROR(VLOOKUP($BV$17,Sheet1!BR12:BU12,3,0),0) -> 0 | BW23: =+IFERROR(VLOOKUP($BW$17,Sheet1!BV12:BY12,3,0),0) -> 0 | BX23: =Sheet1!E12 -> WOOD | BY23: =Sheet1!CV12 -> MD0100062 | BZ23: =Sheet1!CW12 -> DRUM - 74 X 24 X 32 X 3 | CA23: =Sheet1!CX12 -> 1000 | CB23: =Sheet1!BZ12 -> 13815 | CC23: =SUMPRODUCT($P$18:$BW$18,P23:BW23)+CB23 -> 538609 | CD23: 0.01 | CE23: =CC23*CD23 -> 5386.09 | CF23: 0.15 | CG23: =CC23*CF23 -> 80791.35 | CH23: 0 | CI23: =CC23*CH23 -> 0 | CJ23: =CC23+CE23+CG23+CI23 -> 624786.44 | CK23: 0.02 | CL23: =CJ23*CK23 -> 12495.729 | CM23: 0.01 | CN23: =CJ23*CM23 -> 6247.8644
B24: 6 | C24: =Sheet1!A20 -> ENQ-15115-22-23 | D24: 45658 | E24: =Sheet1!C20 -> FA0900116 | F24: =Sheet1!D20 -> 4 CORE X 50 SQ. MM. AL/ARD - WIRE (XLPE) | G24: =CJ24+CL24+CN24 -> 343815.65 | H24: =ROUNDUP(O54,0) -> 5263 | I24: =G24+H24 -> 349078.65 | J24: =Sheet1!CP20 -> 0.18 | K24: =I24*J24 -> 62834.157 | L24: =I24+K24 -> 411912.8 | M24: =Sheet1!CS20 -> 26.605 | N24: =Sheet1!CT20 -> KMS | O24: =L24*M24 -> 10958940 | P24: =+IFERROR(VLOOKUP($P$17,Sheet1!J20:L20,3,0),0) -> 541 | Q24: =+IFERROR(VLOOKUP($Q$17,Sheet1!J20:L20,3,0),0) -> 0 | R24: =+IFERROR(VLOOKUP($R$17,Sheet1!J20:M20,3,0),0) -> 0 | S24: =+IFERROR(VLOOKUP($S$17,Sheet1!J20:M20,3,0),0) -> 0 | T24: =+IFERROR(VLOOKUP($T$17,Sheet1!J20:M20,3,0),0) -> 0 | U24: =+IFERROR(VLOOKUP($U$17,Sheet1!N20:Q20,3,0),0) -> 0 | V24: =+IFERROR(VLOOKUP($V$17,Sheet1!N20:Q20,3,0),0) -> 0 | W24: =+IFERROR(VLOOKUP($W$17,Sheet1!F20:I20,3,0),0) -> 0 | X24: =+IFERROR(VLOOKUP($X$17,Sheet1!F20:I20,3,0),0) -> 0 | Y24: =+IFERROR(VLOOKUP($Y$17,Sheet1!F20:I20,3,0),0) -> 0 | Z24: =+IFERROR(VLOOKUP($Z$17,Sheet1!F20:I20,3,0),0) -> 0 | AA24: =+IFERROR(VLOOKUP($AA$17,Sheet1!F20:I20,3,0),0) -> 0 | AB24: =+IFERROR(VLOOKUP($AB$17,Sheet1!F20:I20,3,0),0) -> 0 | AC24: =+IFERROR(VLOOKUP($AC$17,Sheet1!F20:I20,3,0),0) -> 0 | AD24: =+IFERROR(VLOOKUP($AD$17,Sheet1!F20:I20,3,0),0) -> 0 | AE24: =+IFERROR(VLOOKUP($AE$17,Sheet1!R20:U20,3,0),0) -> 0 | AF24: =+IFERROR(VLOOKUP($AF$17,Sheet1!R20:U20,2,0),0) -> 0 | AG24: =+IFERROR(VLOOKUP($AG$17,Sheet1!V20:Y20,3,0),0) -> 0 | AH24: 119 | AI24: =+IFERROR(VLOOKUP($AI$17,Sheet1!V20:Y20,3,0),0) -> 0 | AJ24: =+IFERROR(VLOOKUP($AJ$17,Sheet1!V20:Y20,3,0),0) -> 0 | AK24: =+IFERROR(VLOOKUP($AK$17,Sheet1!V20:Y20,3,0),0) -> 0 | AL24: =+IFERROR(VLOOKUP($AL$17,Sheet1!V20:Y20,3,0),0) -> 0 | AM24: =+IFERROR(VLOOKUP($AM$17,Sheet1!Z20:AB20,3,0),0) -> 0 | AN24: =+IFERROR(VLOOKUP($AN$17,Sheet1!AD20:AG20,3,0),0) -> 0 | AO24: =+IFERROR(VLOOKUP($AO$17,Sheet1!AD20:AG20,3,0),0) -> 0 | AP24: =+IFERROR(VLOOKUP($AP$17,Sheet1!AD20:AG20,3,0),0) -> 0 | AQ24: =+IFERROR(VLOOKUP($AQ$17,Sheet1!AD20:AG20,3,0),0) -> 0 | AR24: =+IFERROR(VLOOKUP($AR$17,Sheet1!AD20:AG20,3,0),0) -> 0 | AS24: 56 | AT24: =+IFERROR(VLOOKUP($AT$17,Sheet1!AD20:AG20,3,0),0) -> 0 | AU24: =+IFERROR(VLOOKUP($AU$17,Sheet1!AH20:AK20,3,0),0) -> 0 | AV24: =+IFERROR(VLOOKUP($AV$17,Sheet1!AH20:AK20,3,0),0) -> 0 | AW24: =+IFERROR(VLOOKUP($AW$17,Sheet1!AH20:AK20,3,0),0) -> 0 | AX24: =+IFERROR(VLOOKUP($AX$17,Sheet1!AH20:AK20,3,0),0) -> 0 | AY24: =+IFERROR(VLOOKUP($AY$17,Sheet1!AH20:AK20,3,0),0) -> 0 | AZ24: =+IFERROR(VLOOKUP($AZ$17,Sheet1!AH20:AK20,3,0),0) -> 0 | BA24: =+IFERROR(VLOOKUP($BA$17,Sheet1!AH20:AK20,3,0),0) -> 0 | BB24: =+IFERROR(VLOOKUP($BB$17,Sheet1!AH20:AK20,3,0),0) -> 0 | BC24: 1042 | BD24: =+IFERROR(VLOOKUP($BD$17,Sheet1!AH20:AK20,3,0),0) -> 0 | BE24: =+IFERROR(VLOOKUP($BE$17,Sheet1!AL20:AO20,3,0),0) -> 0 | BF24: =+IFERROR(VLOOKUP($BF$17,Sheet1!AL20:AO20,3,0),0) -> 0 | BG24: =+IFERROR(VLOOKUP($BG$17,Sheet1!AL20:AO20,3,0),0) -> 0 | BH24: =+IFERROR(VLOOKUP($BH$17,Sheet1!AL20:AO20,3,0),0) -> 260 | BI24: =+IFERROR(VLOOKUP($BI$17,Sheet1!AL20:AO20,3,0),0) -> 0 | BJ24: =+IFERROR(VLOOKUP($BJ$17,Sheet1!AL20:AO20,3,0),0) -> 0 | BK24: =+IFERROR(VLOOKUP($BK$17,Sheet1!AL20:AO20,3,0),0) -> 0 | BL24: =+IFERROR(VLOOKUP($BL$17,Sheet1!AL20:AO20,3,0),0) -> 0 | BM24: =+IFERROR(VLOOKUP($BM$17,Sheet1!AL20:AO20,3,0),0) -> 0 | BN24: =+IFERROR(VLOOKUP($BN$17,Sheet1!AL20:AO20,3,0),0) -> 0 | BO24: =+IFERROR(VLOOKUP($BO$17,Sheet1!AP20:AS20,3,0),0) -> 0 | BP24: =+IFERROR(VLOOKUP($BP$17,Sheet1!AT20:AW20,3,0),0) -> 0 | BQ24: =+IFERROR(VLOOKUP($BQ$17,Sheet1!AX20:BA20,3,0),0) -> 0 | BR24: =+IFERROR(VLOOKUP($BR$17,Sheet1!BB20:BE20,3,0),0) -> 0 | BS24: =+IFERROR(VLOOKUP($BS$17,Sheet1!BF20:BI20,3,0),0) -> 0 | BT24: =+IFERROR(VLOOKUP($BT$17,Sheet1!BJ20:BM20,3,0),0) -> 0 | BU24: =+IFERROR(VLOOKUP($BU$17,Sheet1!BN20:BQ20,3,0),0) -> 0 | BV24: 20 | BW24: =+IFERROR(VLOOKUP($BW$17,Sheet1!BV20:BY20,3,0),0) -> 0 | BX24: =Sheet1!E20 -> WOOD | BY24: =Sheet1!CV20 -> MD0100068 | BZ24: =Sheet1!CW20 -> DRUM - 54 X 20 X 36 X 2.5 | CA24: =Sheet1!CX20 -> 1000 | CB24: =Sheet1!BZ20 -> 6254 | CC24: =SUMPRODUCT($P$18:$BW$18,P24:BW24)+CB24 -> 287760 | CD24: 0.01 | CE24: =CC24*CD24 -> 2877.6 | CF24: 0.15 | CG24: =CC24*CF24 -> 43164 | CH24: 0 | CI24: =CC24*CH24 -> 0 | CJ24: =CC24+CE24+CG24+CI24 -> 333801.6 | CK24: 0.02 | CL24: =CJ24*CK24 -> 6676.032 | CM24: 0.01 | CN24: =CJ24*CM24 -> 3338.016
B25: 7 | C25: =Sheet1!A26 -> ENQ-15115-22-23 | D25: 45658 | E25: =Sheet1!C26 -> FA1100094 | F25: =Sheet1!D26 -> 4 CORE X 95 SQ. MM. ALU/ARD - WIRE (XLPE) | G25: =CJ25+CL25+CN25 -> 562648.05 | H25: =ROUNDUP(O55,0) -> 7961 | I25: =G25+H25 -> 570609.05 | J25: =Sheet1!CP26 -> 0.18 | K25: =I25*J25 -> 102709.63 | L25: =I25+K25 -> 673318.68 | M25: =Sheet1!CS26 -> 17.586 | N25: =Sheet1!CT26 -> KMS | O25: =L25*M25 -> 11840982 | P25: =+IFERROR(VLOOKUP($P$17,Sheet1!J26:L26,3,0),0) -> 1027 | Q25: =+IFERROR(VLOOKUP($Q$17,Sheet1!J26:L26,3,0),0) -> 0 | R25: =+IFERROR(VLOOKUP($R$17,Sheet1!J26:M26,3,0),0) -> 0 | S25: =+IFERROR(VLOOKUP($S$17,Sheet1!J26:M26,3,0),0) -> 0 | T25: =+IFERROR(VLOOKUP($T$17,Sheet1!J26:M26,3,0),0) -> 0 | U25: =+IFERROR(VLOOKUP($U$17,Sheet1!N26:Q26,3,0),0) -> 0 | V25: =+IFERROR(VLOOKUP($V$17,Sheet1!N26:Q26,3,0),0) -> 0 | W25: =+IFERROR(VLOOKUP($W$17,Sheet1!F26:I26,3,0),0) -> 0 | X25: =+IFERROR(VLOOKUP($X$17,Sheet1!F26:I26,3,0),0) -> 0 | Y25: =+IFERROR(VLOOKUP($Y$17,Sheet1!F26:I26,3,0),0) -> 0 | Z25: =+IFERROR(VLOOKUP($Z$17,Sheet1!F26:I26,3,0),0) -> 0 | AA25: =+IFERROR(VLOOKUP($AA$17,Sheet1!F26:I26,3,0),0) -> 0 | AB25: =+IFERROR(VLOOKUP($AB$17,Sheet1!F26:I26,3,0),0) -> 0 | AC25: =+IFERROR(VLOOKUP($AC$17,Sheet1!F26:I26,3,0),0) -> 0 | AD25: =+IFERROR(VLOOKUP($AD$17,Sheet1!F26:I26,3,0),0) -> 0 | AE25: =+IFERROR(VLOOKUP($AE$17,Sheet1!R26:U26,3,0),0) -> 0 | AF25: =+IFERROR(VLOOKUP($AF$17,Sheet1!R26:U26,2,0),0) -> 0 | AG25: =+IFERROR(VLOOKUP($AG$17,Sheet1!V26:Y26,3,0),0) -> 0 | AH25: 172 | AI25: =+IFERROR(VLOOKUP($AI$17,Sheet1!V26:Y26,3,0),0) -> 0 | AJ25: =+IFERROR(VLOOKUP($AJ$17,Sheet1!V26:Y26,3,0),0) -> 0 | AK25: =+IFERROR(VLOOKUP($AK$17,Sheet1!V26:Y26,3,0),0) -> 0 | AL25: =+IFERROR(VLOOKUP($AL$17,Sheet1!V26:Y26,3,0),0) -> 0 | AM25: =+IFERROR(VLOOKUP($AM$17,Sheet1!Z26:AB26,3,0),0) -> 0 | AN25: =+IFERROR(VLOOKUP($AN$17,Sheet1!AD26:AG26,3,0),0) -> 0 | AO25: =+IFERROR(VLOOKUP($AO$17,Sheet1!AD26:AG26,3,0),0) -> 0 | AP25: =+IFERROR(VLOOKUP($AP$17,Sheet1!AD26:AG26,3,0),0) -> 0 | AQ25: =+IFERROR(VLOOKUP($AQ$17,Sheet1!AD26:AG26,3,0),0) -> 0 | AR25: =+IFERROR(VLOOKUP($AR$17,Sheet1!AD26:AG26,3,0),0) -> 0 | AS25: 89 | AT25: =+IFERROR(VLOOKUP($AT$17,Sheet1!AD26:AG26,3,0),0) -> 0 | AU25: =+IFERROR(VLOOKUP($AU$17,Sheet1!AH26:AK26,3,0),0) -> 0 | AV25: =+IFERROR(VLOOKUP($AV$17,Sheet1!AH26:AK26,3,0),0) -> 0 | AW25: =+IFERROR(VLOOKUP($AW$17,Sheet1!AH26:AK26,3,0),0) -> 0 | AX25: =+IFERROR(VLOOKUP($AX$17,Sheet1!AH26:AK26,3,0),0) -> 0 | AY25: =+IFERROR(VLOOKUP($AY$17,Sheet1!AH26:AK26,3,0),0) -> 0 | AZ25: =+IFERROR(VLOOKUP($AZ$17,Sheet1!AH26:AK26,3,0),0) -> 0 | BA25: =+IFERROR(VLOOKUP($BA$17,Sheet1!AH26:AK26,3,0),0) -> 0 | BB25: =+IFERROR(VLOOKUP($BB$17,Sheet1!AH26:AK26,3,0),0) -> 0 | BC25: 1362 | BD25: =+IFERROR(VLOOKUP($BD$17,Sheet1!AH26:AK26,3,0),0) -> 0 | BE25: =+IFERROR(VLOOKUP($BE$17,Sheet1!AL26:AO26,3,0),0) -> 0 | BF25: =+IFERROR(VLOOKUP($BF$17,Sheet1!AL26:AO26,3,0),0) -> 0 | BG25: =+IFERROR(VLOOKUP($BG$17,Sheet1!AL26:AO26,3,0),0) -> 0 | BH25: 358 | BI25: =+IFERROR(VLOOKUP($BI$17,Sheet1!AL26:AO26,3,0),0) -> 0 | BJ25: =+IFERROR(VLOOKUP($BJ$17,Sheet1!AL26:AO26,3,0),0) -> 0 | BK25: =+IFERROR(VLOOKUP($BK$17,Sheet1!AL26:AO26,3,0),0) -> 0 | BL25: =+IFERROR(VLOOKUP($BL$17,Sheet1!AL26:AO26,3,0),0) -> 0 | BM25: =+IFERROR(VLOOKUP($BM$17,Sheet1!AL26:AO26,3,0),0) -> 0 | BN25: =+IFERROR(VLOOKUP($BN$17,Sheet1!AL26:AO26,3,0),0) -> 0 | BO25: =+IFERROR(VLOOKUP($BO$17,Sheet1!AP26:AS26,3,0),0) -> 0 | BP25: =+IFERROR(VLOOKUP($BP$17,Sheet1!AT26:AW26,3,0),0) -> 0 | BQ25: =+IFERROR(VLOOKUP($BQ$17,Sheet1!AX26:BA26,3,0),0) -> 0 | BR25: =+IFERROR(VLOOKUP($BR$17,Sheet1!BB26:BE26,3,0),0) -> 0 | BS25: =+IFERROR(VLOOKUP($BS$17,Sheet1!BF26:BI26,3,0),0) -> 0 | BT25: =+IFERROR(VLOOKUP($BT$17,Sheet1!BJ26:BM26,3,0),0) -> 0 | BU25: =+IFERROR(VLOOKUP($BU$17,Sheet1!BN26:BQ26,3,0),0) -> 0 | BV25: 25 | BW25: =+IFERROR(VLOOKUP($BW$17,Sheet1!BV26:BY26,3,0),0) -> 0 | BX25: =Sheet1!E26 -> WOOD | BY25: =Sheet1!CV26 -> MD0100061 | BZ25: =Sheet1!CW26 -> DRUM - 56 X 24 X 32 X 3 | CA25: =Sheet1!CX26 -> 500 | CB25: =Sheet1!BZ26 -> 14928 | CC25: =SUMPRODUCT($P$18:$BW$18,P25:BW25)+CB25 -> 470914 | CD25: 0.01 | CE25: =CC25*CD25 -> 4709.14 | CF25: 0.15 | CG25: =CC25*CF25 -> 70637.1 | CH25: 0 | CI25: =CC25*CH25 -> 0 | CJ25: =CC25+CE25+CG25+CI25 -> 546260.24 | CK25: 0.02 | CL25: =CJ25*CK25 -> 10925.205 | CM25: 0.01 | CN25: =CJ25*CM25 -> 5462.6024
B26: 8 | C26: =Sheet1!A28 -> ENQ-15115-22-23 | D26: 45658 | E26: =Sheet1!C28 -> FA1100177 | F26: =Sheet1!D28 -> 4 CORE X 150 SQ. MM. AL/ARD - WIRE (XLPE) | G26: =CJ26+CL26+CN26 -> 915207.24 | H26: =ROUNDUP(O56,0) -> 14406 | I26: =G26+H26 -> 929613.24 | J26: =Sheet1!CP28 -> 0.18 | K26: =I26*J26 -> 167330.38 | L26: =I26+K26 -> 1096943.6 | M26: 21.866 | N26: =Sheet1!CT28 -> KMS | O26: =L26*M26 -> 23985769 | P26: =+IFERROR(VLOOKUP($P$17,Sheet1!J28:L28,3,0),0) -> 1620 | Q26: =+IFERROR(VLOOKUP($Q$17,Sheet1!J28:L28,3,0),0) -> 0 | R26: =+IFERROR(VLOOKUP($R$17,Sheet1!J28:M28,3,0),0) -> 0 | S26: =+IFERROR(VLOOKUP($S$17,Sheet1!J28:M28,3,0),0) -> 0 | T26: =+IFERROR(VLOOKUP($T$17,Sheet1!J28:M28,3,0),0) -> 0 | U26: =+IFERROR(VLOOKUP($U$17,Sheet1!N28:Q28,3,0),0) -> 0 | V26: =+IFERROR(VLOOKUP($V$17,Sheet1!N28:Q28,3,0),0) -> 0 | W26: =+IFERROR(VLOOKUP($W$17,Sheet1!F28:I28,3,0),0) -> 0 | X26: =+IFERROR(VLOOKUP($X$17,Sheet1!F28:I28,3,0),0) -> 0 | Y26: =+IFERROR(VLOOKUP($Y$17,Sheet1!F28:I28,3,0),0) -> 0 | Z26: =+IFERROR(VLOOKUP($Z$17,Sheet1!F28:I28,3,0),0) -> 0 | AA26: =+IFERROR(VLOOKUP($AA$17,Sheet1!F28:I28,3,0),0) -> 0 | AB26: =+IFERROR(VLOOKUP($AB$17,Sheet1!F28:I28,3,0),0) -> 0 | AC26: =+IFERROR(VLOOKUP($AC$17,Sheet1!F28:I28,3,0),0) -> 0 | AD26: =+IFERROR(VLOOKUP($AD$17,Sheet1!F28:I28,3,0),0) -> 0 | AE26: =+IFERROR(VLOOKUP($AE$17,Sheet1!R28:U28,3,0),0) -> 0 | AF26: =+IFERROR(VLOOKUP($AF$17,Sheet1!R28:U28,2,0),0) -> 0 | AG26: =+IFERROR(VLOOKUP($AG$17,Sheet1!V28:Y28,3,0),0) -> 0 | AH26: =+IFERROR(VLOOKUP($AH$17,Sheet1!V28:Y28,3,0),0) -> 276 | AI26: =+IFERROR(VLOOKUP($AI$17,Sheet1!V28:Y28,3,0),0) -> 0 | AJ26: =+IFERROR(VLOOKUP($AJ$17,Sheet1!V28:Y28,3,0),0) -> 0 | AK26: =+IFERROR(VLOOKUP($AK$17,Sheet1!V28:Y28,3,0),0) -> 0 | AL26: =+IFERROR(VLOOKUP($AL$17,Sheet1!V28:Y28,3,0),0) -> 0 | AM26: =+IFERROR(VLOOKUP($AM$17,Sheet1!Z28:AB28,3,0),0) -> 0 | AN26: =+IFERROR(VLOOKUP($AN$17,Sheet1!AD28:AG28,3,0),0) -> 0 | AO26: =+IFERROR(VLOOKUP($AO$17,Sheet1!AD28:AG28,3,0),0) -> 0 | AP26: =+IFERROR(VLOOKUP($AP$17,Sheet1!AD28:AG28,3,0),0) -> 0 | AQ26: =+IFERROR(VLOOKUP($AQ$17,Sheet1!AD28:AG28,3,0),0) -> 0 | AR26: =+IFERROR(VLOOKUP($AR$17,Sheet1!AD28:AG28,3,0),0) -> 0 | AS26: 135 | AT26: =+IFERROR(VLOOKUP($AT$17,Sheet1!AD28:AG28,3,0),0) -> 0 | AU26: =+IFERROR(VLOOKUP($AU$17,Sheet1!AH28:AK28,3,0),0) -> 0 | AV26: =+IFERROR(VLOOKUP($AV$17,Sheet1!AH28:AK28,3,0),0) -> 0 | AW26: =+IFERROR(VLOOKUP($AW$17,Sheet1!AH28:AK28,3,0),0) -> 0 | AX26: =+IFERROR(VLOOKUP($AX$17,Sheet1!AH28:AK28,3,0),0) -> 0 | AY26: =+IFERROR(VLOOKUP($AY$17,Sheet1!AH28:AK28,3,0),0) -> 0 | AZ26: =+IFERROR(VLOOKUP($AZ$17,Sheet1!AH28:AK28,3,0),0) -> 0 | BA26: =+IFERROR(VLOOKUP($BA$17,Sheet1!AH28:AK28,3,0),0) -> 0 | BB26: =+IFERROR(VLOOKUP($BB$17,Sheet1!AH28:AK28,3,0),0) -> 0 | BC26: 2290 | BD26: =+IFERROR(VLOOKUP($BD$17,Sheet1!AH28:AK28,3,0),0) -> 0 | BE26: =+IFERROR(VLOOKUP($BE$17,Sheet1!AL28:AO28,3,0),0) -> 0 | BF26: =+IFERROR(VLOOKUP($BF$17,Sheet1!AL28:AO28,3,0),0) -> 0 | BG26: =+IFERROR(VLOOKUP($BG$17,Sheet1!AL28:AO28,3,0),0) -> 0 | BH26: 530 | BI26: =+IFERROR(VLOOKUP($BI$17,Sheet1!AL28:AO28,3,0),0) -> 0 | BJ26: =+IFERROR(VLOOKUP($BJ$17,Sheet1!AL28:AO28,3,0),0) -> 0 | BK26: =+IFERROR(VLOOKUP($BK$17,Sheet1!AL28:AO28,3,0),0) -> 0 | BL26: =+IFERROR(VLOOKUP($BL$17,Sheet1!AL28:AO28,3,0),0) -> 0 | BM26: =+IFERROR(VLOOKUP($BM$17,Sheet1!AL28:AO28,3,0),0) -> 0 | BN26: =+IFERROR(VLOOKUP($BN$17,Sheet1!AL28:AO28,3,0),0) -> 0 | BO26: =+IFERROR(VLOOKUP($BO$17,Sheet1!AP28:AS28,3,0),0) -> 0 | BP26: =+IFERROR(VLOOKUP($BP$17,Sheet1!AT28:AW28,3,0),0) -> 0 | BQ26: 55 | BR26: =+IFERROR(VLOOKUP($BR$17,Sheet1!BB28:BE28,3,0),0) -> 0 | BS26: =+IFERROR(VLOOKUP($BS$17,Sheet1!BF28:BI28,3,0),0) -> 0 | BT26: =+IFERROR(VLOOKUP($BT$17,Sheet1!BJ28:BM28,3,0),0) -> 0 | BU26: =+IFERROR(VLOOKUP($BU$17,Sheet1!BN28:BQ28,3,0),0) -> 0 | BV26: 33 | BW26: =+IFERROR(VLOOKUP($BW$17,Sheet1!BV28:BY28,3,0),0) -> 0 | BX26: =Sheet1!E28 -> WOOD | BY26: =Sheet1!CV28 -> MD0100024 | BZ26: =Sheet1!CW28 -> DRUM - 70 X 30 X 36 X 3 | CA26: =Sheet1!CX28 -> 500 | CB26: =Sheet1!BZ28 -> 21178 | CC26: =SUMPRODUCT($P$18:$BW$18,P26:BW26)+CB26 -> 765992 | CD26: 0.01 | CE26: =CC26*CD26 -> 7659.92 | CF26: 0.15 | CG26: =CC26*CF26 -> 114898.8 | CH26: 0 | CI26: =CC26*CH26 -> 0 | CJ26: =CC26+CE26+CG26+CI26 -> 888550.72 | CK26: 0.02 | CL26: =CJ26*CK26 -> 17771.014 | CM26: 0.01 | CN26: =CJ26*CM26 -> 8885.5072
B27: 9 | C27: =Sheet1!A25 -> ENQ-15115-22-23 | D27: 45658 | E27: =Sheet1!C25 -> FA1100091 | F27: =Sheet1!D25 -> 4 CORE X 240 SQ. MM. AL/ARD - WIRE (XLPE) | G27: =CJ27+CL27+CN27 -> 1367560.9 | H27: =ROUNDUP(O57,0) -> 25000 | I27: =G27+H27 -> 1392560.9 | J27: =Sheet1!CP25 -> 0.18 | K27: =I27*J27 -> 250660.96 | L27: =I27+K27 -> 1643221.9 | M27: 7 | N27: =Sheet1!CT25 -> KMS | O27: =L27*M27 -> 11502553 | P27: =+IFERROR(VLOOKUP($P$17,Sheet1!J25:L25,3,0),0) -> 2595 | Q27: =+IFERROR(VLOOKUP($Q$17,Sheet1!J25:L25,3,0),0) -> 0 | R27: =+IFERROR(VLOOKUP($R$17,Sheet1!J25:M25,3,0),0) -> 0 | S27: =+IFERROR(VLOOKUP($S$17,Sheet1!J25:M25,3,0),0) -> 0 | T27: =+IFERROR(VLOOKUP($T$17,Sheet1!J25:M25,3,0),0) -> 0 | U27: =+IFERROR(VLOOKUP($U$17,Sheet1!N25:Q25,3,0),0) -> 0 | V27: =+IFERROR(VLOOKUP($V$17,Sheet1!N25:Q25,3,0),0) -> 0 | W27: =+IFERROR(VLOOKUP($W$17,Sheet1!F25:I25,3,0),0) -> 0 | X27: =+IFERROR(VLOOKUP($X$17,Sheet1!F25:I25,3,0),0) -> 0 | Y27: =+IFERROR(VLOOKUP($Y$17,Sheet1!F25:I25,3,0),0) -> 0 | Z27: =+IFERROR(VLOOKUP($Z$17,Sheet1!F25:I25,3,0),0) -> 0 | AA27: =+IFERROR(VLOOKUP($AA$17,Sheet1!F25:I25,3,0),0) -> 0 | AB27: =+IFERROR(VLOOKUP($AB$17,Sheet1!F25:I25,3,0),0) -> 0 | AC27: =+IFERROR(VLOOKUP($AC$17,Sheet1!F25:I25,3,0),0) -> 0 | AD27: =+IFERROR(VLOOKUP($AD$17,Sheet1!F25:I25,3,0),0) -> 0 | AE27: =+IFERROR(VLOOKUP($AE$17,Sheet1!R25:U25,3,0),0) -> 0 | AF27: =+IFERROR(VLOOKUP($AF$17,Sheet1!R25:U25,2,0),0) -> 0 | AG27: =+IFERROR(VLOOKUP($AG$17,Sheet1!V25:Y25,3,0),0) -> 0 | AH27: 415 | AI27: =+IFERROR(VLOOKUP($AI$17,Sheet1!V25:Y25,3,0),0) -> 0 | AJ27: =+IFERROR(VLOOKUP($AJ$17,Sheet1!V25:Y25,3,0),0) -> 0 | AK27: =+IFERROR(VLOOKUP($AK$17,Sheet1!V25:Y25,3,0),0) -> 0 | AL27: =+IFERROR(VLOOKUP($AL$17,Sheet1!V25:Y25,3,0),0) -> 0 | AM27: =+IFERROR(VLOOKUP($AM$17,Sheet1!Z25:AB25,3,0),0) -> 0 | AN27: =+IFERROR(VLOOKUP($AN$17,Sheet1!AD25:AG25,3,0),0) -> 0 | AO27: =+IFERROR(VLOOKUP($AO$17,Sheet1!AD25:AG25,3,0),0) -> 0 | AP27: =+IFERROR(VLOOKUP($AP$17,Sheet1!AD25:AG25,3,0),0) -> 0 | AQ27: =+IFERROR(VLOOKUP($AQ$17,Sheet1!AD25:AG25,3,0),0) -> 0 | AR27: =+IFERROR(VLOOKUP($AR$17,Sheet1!AD25:AG25,3,0),0) -> 0 | AS27: 185 | AT27: =+IFERROR(VLOOKUP($AT$17,Sheet1!AD25:AG25,3,0),0) -> 0 | AU27: =+IFERROR(VLOOKUP($AU$17,Sheet1!AH25:AK25,3,0),0) -> 0 | AV27: =+IFERROR(VLOOKUP($AV$17,Sheet1!AH25:AK25,3,0),0) -> 0 | AW27: =+IFERROR(VLOOKUP($AW$17,Sheet1!AH25:AK25,3,0),0) -> 0 | AX27: =+IFERROR(VLOOKUP($AX$17,Sheet1!AH25:AK25,3,0),0) -> 0 | AY27: =+IFERROR(VLOOKUP($AY$17,Sheet1!AH25:AK25,3,0),0) -> 0 | AZ27: =+IFERROR(VLOOKUP($AZ$17,Sheet1!AH25:AK25,3,0),0) -> 0 | BA27: =+IFERROR(VLOOKUP($BA$17,Sheet1!AH25:AK25,3,0),0) -> 0 | BB27: =+IFERROR(VLOOKUP($BB$17,Sheet1!AH25:AK25,3,0),0) -> 0 | BC27: 2800 | BD27: =+IFERROR(VLOOKUP($BD$17,Sheet1!AH25:AK25,3,0),0) -> 0 | BE27: =+IFERROR(VLOOKUP($BE$17,Sheet1!AL25:AO25,3,0),0) -> 0 | BF27: =+IFERROR(VLOOKUP($BF$17,Sheet1!AL25:AO25,3,0),0) -> 0 | BG27: =+IFERROR(VLOOKUP($BG$17,Sheet1!AL25:AO25,3,0),0) -> 0 | BH27: 728 | BI27: =+IFERROR(VLOOKUP($BI$17,Sheet1!AL25:AO25,3,0),0) -> 0 | BJ27: =+IFERROR(VLOOKUP($BJ$17,Sheet1!AL25:AO25,3,0),0) -> 0 | BK27: =+IFERROR(VLOOKUP($BK$17,Sheet1!AL25:AO25,3,0),0) -> 0 | BL27: =+IFERROR(VLOOKUP($BL$17,Sheet1!AL25:AO25,3,0),0) -> 0 | BM27: =+IFERROR(VLOOKUP($BM$17,Sheet1!AL25:AO25,3,0),0) -> 0 | BN27: =+IFERROR(VLOOKUP($BN$17,Sheet1!AL25:AO25,3,0),0) -> 0 | BO27: =+IFERROR(VLOOKUP($BO$17,Sheet1!AP25:AS25,3,0),0) -> 0 | BP27: =+IFERROR(VLOOKUP($BP$17,Sheet1!AT25:AW25,3,0),0) -> 0 | BQ27: 75 | BR27: =+IFERROR(VLOOKUP($BR$17,Sheet1!BB25:BE25,3,0),0) -> 0 | BS27: =+IFERROR(VLOOKUP($BS$17,Sheet1!BF25:BI25,3,0),0) -> 0 | BT27: =+IFERROR(VLOOKUP($BT$17,Sheet1!BJ25:BM25,3,0),0) -> 0 | BU27: =+IFERROR(VLOOKUP($BU$17,Sheet1!BN25:BQ25,3,0),0) -> 0 | BV27: 39 | BW27: =+IFERROR(VLOOKUP($BW$17,Sheet1!BV25:BY25,3,0),0) -> 0 | BX27: STEEL | BY27: SP0400123 | BZ27: CORRUGATED DISPATCH STEEL DRUM 2000 X 1000 X 1200 MM | CA27: =Sheet1!CX25 -> 500 | CB27: =26600/0.5 -> 53200 | CC27: =SUMPRODUCT($P$18:$BW$18,P27:BW27)+CB27 -> 1144594 | CD27: 0.01 | CE27: =CC27*CD27 -> 11445.94 | CF27: 0.15 | CG27: =CC27*CF27 -> 171689.1 | CH27: 0 | CI27: =CC27*CH27 -> 0 | CJ27: =CC27+CE27+CG27+CI27 -> 1327729 | CK27: 0.02 | CL27: =CJ27*CK27 -> 26554.581 | CM27: 0.01 | CN27: =CJ27*CM27 -> 13277.29
B28: 10 | C28: =Sheet1!A27 -> ENQ-15115-22-23 | D28: 45658 | E28: =Sheet1!C27 -> FA1100176 | F28: =Sheet1!D27 -> 4 CORE X 300 SQ. MM. AL/ARD - WIRE (XLPE) | G28: =CJ28+CL28+CN28 -> 1683360.9 | H28: =ROUNDUP(O58,0) -> 23334 | I28: =G28+H28 -> 1706694.9 | J28: =Sheet1!CP27 -> 0.18 | K28: =I28*J28 -> 307205.08 | L28: =I28+K28 -> 2013900 | M28: 34.5 | N28: =Sheet1!CT27 -> KMS | O28: =L28*M28 -> 69479549 | P28: =+IFERROR(VLOOKUP($P$17,Sheet1!J27:L27,3,0),0) -> 3240 | Q28: =+IFERROR(VLOOKUP($Q$17,Sheet1!J27:L27,3,0),0) -> 0 | R28: =+IFERROR(VLOOKUP($R$17,Sheet1!J27:M27,3,0),0) -> 0 | S28: =+IFERROR(VLOOKUP($S$17,Sheet1!J27:M27,3,0),0) -> 0 | T28: =+IFERROR(VLOOKUP($T$17,Sheet1!J27:M27,3,0),0) -> 0 | U28: =+IFERROR(VLOOKUP($U$17,Sheet1!N27:Q27,3,0),0) -> 0 | V28: =+IFERROR(VLOOKUP($V$17,Sheet1!N27:Q27,3,0),0) -> 0 | W28: =+IFERROR(VLOOKUP($W$17,Sheet1!F27:I27,3,0),0) -> 0 | X28: =+IFERROR(VLOOKUP($X$17,Sheet1!F27:I27,3,0),0) -> 0 | Y28: =+IFERROR(VLOOKUP($Y$17,Sheet1!F27:I27,3,0),0) -> 0 | Z28: =+IFERROR(VLOOKUP($Z$17,Sheet1!F27:I27,3,0),0) -> 0 | AA28: =+IFERROR(VLOOKUP($AA$17,Sheet1!F27:I27,3,0),0) -> 0 | AB28: =+IFERROR(VLOOKUP($AB$17,Sheet1!F27:I27,3,0),0) -> 0 | AC28: =+IFERROR(VLOOKUP($AC$17,Sheet1!F27:I27,3,0),0) -> 0 | AD28: =+IFERROR(VLOOKUP($AD$17,Sheet1!F27:I27,3,0),0) -> 0 | AE28: =+IFERROR(VLOOKUP($AE$17,Sheet1!R27:U27,3,0),0) -> 0 | AF28: =+IFERROR(VLOOKUP($AF$17,Sheet1!R27:U27,2,0),0) -> 0 | AG28: =+IFERROR(VLOOKUP($AG$17,Sheet1!V27:Y27,3,0),0) -> 0 | AH28: 500 | AI28: =+IFERROR(VLOOKUP($AI$17,Sheet1!V27:Y27,3,0),0) -> 0 | AJ28: =+IFERROR(VLOOKUP($AJ$17,Sheet1!V27:Y27,3,0),0) -> 0 | AK28: =+IFERROR(VLOOKUP($AK$17,Sheet1!V27:Y27,3,0),0) -> 0 | AL28: =+IFERROR(VLOOKUP($AL$17,Sheet1!V27:Y27,3,0),0) -> 0 | AM28: =+IFERROR(VLOOKUP($AM$17,Sheet1!Z27:AB27,3,0),0) -> 0 | AN28: =+IFERROR(VLOOKUP($AN$17,Sheet1!AD27:AG27,3,0),0) -> 0 | AO28: =+IFERROR(VLOOKUP($AO$17,Sheet1!AD27:AG27,3,0),0) -> 0 | AP28: =+IFERROR(VLOOKUP($AP$17,Sheet1!AD27:AG27,3,0),0) -> 0 | AQ28: =+IFERROR(VLOOKUP($AQ$17,Sheet1!AD27:AG27,3,0),0) -> 0 | AR28: =+IFERROR(VLOOKUP($AR$17,Sheet1!AD27:AG27,3,0),0) -> 0 | AS28: 240 | AT28: =+IFERROR(VLOOKUP($AT$17,Sheet1!AD27:AG27,3,0),0) -> 0 | AU28: =+IFERROR(VLOOKUP($AU$17,Sheet1!AH27:AK27,3,0),0) -> 0 | AV28: =+IFERROR(VLOOKUP($AV$17,Sheet1!AH27:AK27,3,0),0) -> 0 | AW28: =+IFERROR(VLOOKUP($AW$17,Sheet1!AH27:AK27,3,0),0) -> 0 | AX28: =+IFERROR(VLOOKUP($AX$17,Sheet1!AH27:AK27,3,0),0) -> 0 | AY28: =+IFERROR(VLOOKUP($AY$17,Sheet1!AH27:AK27,3,0),0) -> 0 | AZ28: =+IFERROR(VLOOKUP($AZ$17,Sheet1!AH27:AK27,3,0),0) -> 0 | BA28: =+IFERROR(VLOOKUP($BA$17,Sheet1!AH27:AK27,3,0),0) -> 0 | BB28: =+IFERROR(VLOOKUP($BB$17,Sheet1!AH27:AK27,3,0),0) -> 0 | BC28: 3118 | BD28: =+IFERROR(VLOOKUP($BD$17,Sheet1!AH27:AK27,3,0),0) -> 0 | BE28: =+IFERROR(VLOOKUP($BE$17,Sheet1!AL27:AO27,3,0),0) -> 0 | BF28: =+IFERROR(VLOOKUP($BF$17,Sheet1!AL27:AO27,3,0),0) -> 0 | BG28: =+IFERROR(VLOOKUP($BG$17,Sheet1!AL27:AO27,3,0),0) -> 0 | BH28: 880 | BI28: =+IFERROR(VLOOKUP($BI$17,Sheet1!AL27:AO27,3,0),0) -> 0 | BJ28: =+IFERROR(VLOOKUP($BJ$17,Sheet1!AL27:AO27,3,0),0) -> 0 | BK28: =+IFERROR(VLOOKUP($BK$17,Sheet1!AL27:AO27,3,0),0) -> 0 | BL28: =+IFERROR(VLOOKUP($BL$17,Sheet1!AL27:AO27,3,0),0) -> 0 | BM28: =+IFERROR(VLOOKUP($BM$17,Sheet1!AL27:AO27,3,0),0) -> 0 | BN28: =+IFERROR(VLOOKUP($BN$17,Sheet1!AL27:AO27,3,0),0) -> 0 | BO28: =+IFERROR(VLOOKUP($BO$17,Sheet1!AP27:AS27,3,0),0) -> 0 | BP28: =+IFERROR(VLOOKUP($BP$17,Sheet1!AT27:AW27,3,0),0) -> 0 | BQ28: 112 | BR28: =+IFERROR(VLOOKUP($BR$17,Sheet1!BB27:BE27,3,0),0) -> 0 | BS28: =+IFERROR(VLOOKUP($BS$17,Sheet1!BF27:BI27,3,0),0) -> 0 | BT28: =+IFERROR(VLOOKUP($BT$17,Sheet1!BJ27:BM27,3,0),0) -> 0 | BU28: =+IFERROR(VLOOKUP($BU$17,Sheet1!BN27:BQ27,3,0),0) -> 0 | BV28: 44 | BW28: =+IFERROR(VLOOKUP($BW$17,Sheet1!BV27:BY27,3,0),0) -> 0 | BX28: =Sheet1!E27 -> STEEL | BY28: =Sheet1!CV27 -> SP0400139 | BZ28: =Sheet1!CW27 -> CORRUGATED DISPATCH STEEL DRUM 2130 X 890 X 965 | CA28: =Sheet1!CX27 -> 500 | CB28: =Sheet1!BZ27 -> 78780 | CC28: =SUMPRODUCT($P$18:$BW$18,P28:BW28)+CB28 -> 1408906 | CD28: 0.01 | CE28: =CC28*CD28 -> 14089.06 | CF28: 0.15 | CG28: =CC28*CF28 -> 211335.9 | CH28: 0 | CI28: =CC28*CH28 -> 0 | CJ28: =CC28+CE28+CG28+CI28 -> 1634331 | CK28: 0.02 | CL28: =CJ28*CK28 -> 32686.619 | CM28: 0.01 | CN28: =CJ28*CM28 -> 16343.31
B29: 11 | C29: =Sheet1!A7 -> ENQ-15115-22-23 | D29: 45658 | E29: =Sheet1!C7 -> FA0500017 | F29: =Sheet1!D7 -> 1 CORE X 50 SQ. MM. AL/UNARD. (XLPE) | G29: =CJ29+CL29+CN29 -> 62424.716 | H29: =ROUNDUP(O59,0) -> 1455 | I29: =G29+H29 -> 63879.716 | J29: =Sheet1!CP7 -> 0.18 | K29: =I29*J29 -> 11498.349 | L29: =I29+K29 -> 75378.064 | M29: =Sheet1!CS7 -> 24.06 | N29: =Sheet1!CT7 -> KMS | O29: =L29*M29 -> 1813596.2 | P29: =+IFERROR(VLOOKUP($P$17,Sheet1!J7:L7,3,0),0) -> 135 | Q29: =+IFERROR(VLOOKUP($Q$17,Sheet1!J7:L7,3,0),0) -> 0 | R29: =+IFERROR(VLOOKUP($R$17,Sheet1!J7:M7,3,0),0) -> 0 | S29: =+IFERROR(VLOOKUP($S$17,Sheet1!J7:M7,3,0),0) -> 0 | T29: =+IFERROR(VLOOKUP($T$17,Sheet1!J7:M7,3,0),0) -> 0 | U29: =+IFERROR(VLOOKUP($U$17,Sheet1!N7:Q7,3,0),0) -> 0 | V29: =+IFERROR(VLOOKUP($V$17,Sheet1!N7:Q7,3,0),0) -> 0 | W29: =+IFERROR(VLOOKUP($W$17,Sheet1!F7:I7,3,0),0) -> 0 | X29: =+IFERROR(VLOOKUP($X$17,Sheet1!F7:I7,3,0),0) -> 0 | Y29: =+IFERROR(VLOOKUP($Y$17,Sheet1!F7:I7,3,0),0) -> 0 | Z29: =+IFERROR(VLOOKUP($Z$17,Sheet1!F7:I7,3,0),0) -> 0 | AA29: =+IFERROR(VLOOKUP($AA$17,Sheet1!F7:I7,3,0),0) -> 0 | AB29: =+IFERROR(VLOOKUP($AB$17,Sheet1!F7:I7,3,0),0) -> 0 | AC29: =+IFERROR(VLOOKUP($AC$17,Sheet1!F7:I7,3,0),0) -> 0 | AD29: =+IFERROR(VLOOKUP($AD$17,Sheet1!F7:I7,3,0),0) -> 0 | AE29: =+IFERROR(VLOOKUP($AE$17,Sheet1!R7:U7,3,0),0) -> 0 | AF29: =+IFERROR(VLOOKUP($AF$17,Sheet1!R7:U7,2,0),0) -> 0 | AG29: =+IFERROR(VLOOKUP($AG$17,Sheet1!V7:Y7,3,0),0) -> 0 | AH29: =+IFERROR(VLOOKUP($AH$17,Sheet1!V7:Y7,3,0),0) -> 37 | AI29: =+IFERROR(VLOOKUP($AI$17,Sheet1!V7:Y7,3,0),0) -> 0 | AJ29: =+IFERROR(VLOOKUP($AJ$17,Sheet1!V7:Y7,3,0),0) -> 0 | AK29: =+IFERROR(VLOOKUP($AK$17,Sheet1!V7:Y7,3,0),0) -> 0 | AL29: =+IFERROR(VLOOKUP($AL$17,Sheet1!V7:Y7,3,0),0) -> 0 | AM29: =+IFERROR(VLOOKUP($AM$17,Sheet1!Z7:AB7,3,0),0) -> 0 | AN29: =+IFERROR(VLOOKUP($AN$17,Sheet1!AD7:AG7,3,0),0) -> 0 | AO29: =+IFERROR(VLOOKUP($AO$17,Sheet1!AD7:AG7,3,0),0) -> 0 | AP29: =+IFERROR(VLOOKUP($AP$17,Sheet1!AD7:AG7,3,0),0) -> 0 | AQ29: =+IFERROR(VLOOKUP($AQ$17,Sheet1!AD7:AG7,3,0),0) -> 0 | AR29: =+IFERROR(VLOOKUP($AR$17,Sheet1!AD7:AG7,3,0),0) -> 0 | AS29: =+IFERROR(VLOOKUP($AS$17,Sheet1!AD7:AG7,3,0),0) -> 0 | AT29: =+IFERROR(VLOOKUP($AT$17,Sheet1!AD7:AG7,3,0),0) -> 0 | AU29: =+IFERROR(VLOOKUP($AU$17,Sheet1!AH7:AK7,3,0),0) -> 0 | AV29: =+IFERROR(VLOOKUP($AV$17,Sheet1!AH7:AK7,3,0),0) -> 0 | AW29: =+IFERROR(VLOOKUP($AW$17,Sheet1!AH7:AK7,3,0),0) -> 0 | AX29: =+IFERROR(VLOOKUP($AX$17,Sheet1!AH7:AK7,3,0),0) -> 0 | AY29: =+IFERROR(VLOOKUP($AY$17,Sheet1!AH7:AK7,3,0),0) -> 0 | AZ29: =+IFERROR(VLOOKUP($AZ$17,Sheet1!AH7:AK7,3,0),0) -> 0 | BA29: =+IFERROR(VLOOKUP($BA$17,Sheet1!AH7:AK7,3,0),0) -> 0 | BB29: =+IFERROR(VLOOKUP($BB$17,Sheet1!AH7:AK7,3,0),0) -> 0 | BC29: =+IFERROR(VLOOKUP($BC$17,Sheet1!AH7:AK7,3,0),0) -> 0 | BD29: =+IFERROR(VLOOKUP($BD$17,Sheet1!AH7:AK7,3,0),0) -> 0 | BE29: =+IFERROR(VLOOKUP($BE$17,Sheet1!AL7:AO7,3,0),0) -> 0 | BF29: =+IFERROR(VLOOKUP($BF$17,Sheet1!AL7:AO7,3,0),0) -> 0 | BG29: =+IFERROR(VLOOKUP($BG$17,Sheet1!AL7:AO7,3,0),0) -> 0 | BH29: =+IFERROR(VLOOKUP($BH$17,Sheet1!AL7:AO7,3,0),0) -> 110 | BI29: =+IFERROR(VLOOKUP($BI$17,Sheet1!AL7:AO7,3,0),0) -> 0 | BJ29: =+IFERROR(VLOOKUP($BJ$17,Sheet1!AL7:AO7,3,0),0) -> 0 | BK29: =+IFERROR(VLOOKUP($BK$17,Sheet1!AL7:AO7,3,0),0) -> 0 | BL29: =+IFERROR(VLOOKUP($BL$17,Sheet1!AL7:AO7,3,0),0) -> 0 | BM29: =+IFERROR(VLOOKUP($BM$17,Sheet1!AL7:AO7,3,0),0) -> 0 | BN29: =+IFERROR(VLOOKUP($BN$17,Sheet1!AL7:AO7,3,0),0) -> 0 | BO29: =+IFERROR(VLOOKUP($BO$17,Sheet1!AP7:AS7,3,0),0) -> 0 | BP29: =+IFERROR(VLOOKUP($BP$17,Sheet1!AT7:AW7,3,0),0) -> 0 | BQ29: =+IFERROR(VLOOKUP($BQ$17,Sheet1!AX7:BA7,3,0),0) -> 0 | BR29: =+IFERROR(VLOOKUP($BR$17,Sheet1!BB7:BE7,3,0),0) -> 0 | BS29: =+IFERROR(VLOOKUP($BS$17,Sheet1!BF7:BI7,3,0),0) -> 0 | BT29: =+IFERROR(VLOOKUP($BT$17,Sheet1!BJ7:BM7,3,0),0) -> 0 | BU29: =+IFERROR(VLOOKUP($BU$17,Sheet1!BN7:BQ7,3,0),0) -> 0 | BV29: =+IFERROR(VLOOKUP($BV$17,Sheet1!BR7:BU7,3,0),0) -> 0 | BW29: =+IFERROR(VLOOKUP($BW$17,Sheet1!BV7:BY7,3,0),0) -> 0 | BX29: =Sheet1!E7 -> WOOD | BY29: =Sheet1!CV7 -> MD0100005 | BZ29: =Sheet1!CW7 -> DRUM - 36 X 14 X 23 X 2 | CA29: =Sheet1!CX7 -> 1000 | CB29: =Sheet1!BZ7 -> 2429 | CC29: =SUMPRODUCT($P$18:$BW$18,P29:BW29)+CB29 -> 52247 | CD29: 0.01 | CE29: =CC29*CD29 -> 522.47 | CF29: 0.15 | CG29: =CC29*CF29 -> 7837.05 | CH29: 0 | CI29: =CC29*CH29 -> 0 | CJ29: =CC29+CE29+CG29+CI29 -> 60606.52 | CK29: 0.02 | CL29: =CJ29*CK29 -> 1212.1304 | CM29: 0.01 | CN29: =CJ29*CM29 -> 606.0652
B30: 12 | C30: =Sheet1!A18 -> ENQ-15115-22-23 | D30: 45658 | E30: =Sheet1!C18 -> FA0900111 | F30: =Sheet1!D18 -> 4 CORE X 25 SQ. MM. ALU/ARD - WIRE (XLPE) | G30: =CJ30+CL30+CN30 -> 199954.56 | H30: =ROUNDUP(O60,0) -> 3352 | I30: =G30+H30 -> 203306.56 | J30: =Sheet1!CP18 -> 0.18 | K30: =I30*J30 -> 36595.181 | L30: =I30+K30 -> 239901.74 | M30: 146.208 | N30: =Sheet1!CT18 -> KMS | O30: =L30*M30 -> 35075554 | P30: =+IFERROR(VLOOKUP($P$17,Sheet1!J18:L18,3,0),0) -> 270 | Q30: =+IFERROR(VLOOKUP($Q$17,Sheet1!J18:L18,3,0),0) -> 0 | R30: =+IFERROR(VLOOKUP($R$17,Sheet1!J18:M18,3,0),0) -> 0 | S30: =+IFERROR(VLOOKUP($S$17,Sheet1!J18:M18,3,0),0) -> 0 | T30: =+IFERROR(VLOOKUP($T$17,Sheet1!J18:M18,3,0),0) -> 0 | U30: =+IFERROR(VLOOKUP($U$17,Sheet1!N18:Q18,3,0),0) -> 0 | V30: =+IFERROR(VLOOKUP($V$17,Sheet1!N18:Q18,3,0),0) -> 0 | W30: =+IFERROR(VLOOKUP($W$17,Sheet1!F18:I18,3,0),0) -> 0 | X30: =+IFERROR(VLOOKUP($X$17,Sheet1!F18:I18,3,0),0) -> 0 | Y30: =+IFERROR(VLOOKUP($Y$17,Sheet1!F18:I18,3,0),0) -> 0 | Z30: =+IFERROR(VLOOKUP($Z$17,Sheet1!F18:I18,3,0),0) -> 0 | AA30: =+IFERROR(VLOOKUP($AA$17,Sheet1!F18:I18,3,0),0) -> 0 | AB30: =+IFERROR(VLOOKUP($AB$17,Sheet1!F18:I18,3,0),0) -> 0 | AC30: =+IFERROR(VLOOKUP($AC$17,Sheet1!F18:I18,3,0),0) -> 0 | AD30: =+IFERROR(VLOOKUP($AD$17,Sheet1!F18:I18,3,0),0) -> 0 | AE30: =+IFERROR(VLOOKUP($AE$17,Sheet1!R18:U18,3,0),0) -> 0 | AF30: =+IFERROR(VLOOKUP($AF$17,Sheet1!R18:U18,2,0),0) -> 0 | AG30: =+IFERROR(VLOOKUP($AG$17,Sheet1!V18:Y18,3,0),0) -> 0 | AH30: 90 | AI30: =+IFERROR(VLOOKUP($AI$17,Sheet1!V18:Y18,3,0),0) -> 0 | AJ30: =+IFERROR(VLOOKUP($AJ$17,Sheet1!V18:Y18,3,0),0) -> 0 | AK30: =+IFERROR(VLOOKUP($AK$17,Sheet1!V18:Y18,3,0),0) -> 0 | AL30: =+IFERROR(VLOOKUP($AL$17,Sheet1!V18:Y18,3,0),0) -> 0 | AM30: =+IFERROR(VLOOKUP($AM$17,Sheet1!Z18:AB18,3,0),0) -> 0 | AN30: =+IFERROR(VLOOKUP($AN$17,Sheet1!AD18:AG18,3,0),0) -> 0 | AO30: =+IFERROR(VLOOKUP($AO$17,Sheet1!AD18:AG18,3,0),0) -> 0 | AP30: =+IFERROR(VLOOKUP($AP$17,Sheet1!AD18:AG18,3,0),0) -> 0 | AQ30: =+IFERROR(VLOOKUP($AQ$17,Sheet1!AD18:AG18,3,0),0) -> 0 | AR30: =+IFERROR(VLOOKUP($AR$17,Sheet1!AD18:AG18,3,0),0) -> 0 | AS30: 44 | AT30: =+IFERROR(VLOOKUP($AT$17,Sheet1!AD18:AG18,3,0),0) -> 0 | AU30: =+IFERROR(VLOOKUP($AU$17,Sheet1!AH18:AK18,3,0),0) -> 0 | AV30: =+IFERROR(VLOOKUP($AV$17,Sheet1!AH18:AK18,3,0),0) -> 0 | AW30: =+IFERROR(VLOOKUP($AW$17,Sheet1!AH18:AK18,3,0),0) -> 0 | AX30: =+IFERROR(VLOOKUP($AX$17,Sheet1!AH18:AK18,3,0),0) -> 0 | AY30: =+IFERROR(VLOOKUP($AY$17,Sheet1!AH18:AK18,3,0),0) -> 0 | AZ30: =+IFERROR(VLOOKUP($AZ$17,Sheet1!AH18:AK18,3,0),0) -> 0 | BA30: =+IFERROR(VLOOKUP($BA$17,Sheet1!AH18:AK18,3,0),0) -> 0 | BB30: =+IFERROR(VLOOKUP($BB$17,Sheet1!AH18:AK18,3,0),0) -> 0 | BC30: 641 | BD30: =+IFERROR(VLOOKUP($BD$17,Sheet1!AH18:AK18,3,0),0) -> 0 | BE30: =+IFERROR(VLOOKUP($BE$17,Sheet1!AL18:AO18,3,0),0) -> 0 | BF30: =+IFERROR(VLOOKUP($BF$17,Sheet1!AL18:AO18,3,0),0) -> 0 | BG30: =+IFERROR(VLOOKUP($BG$17,Sheet1!AL18:AO18,3,0),0) -> 0 | BH30: 190 | BI30: =+IFERROR(VLOOKUP($BI$17,Sheet1!AL18:AO18,3,0),0) -> 0 | BJ30: =+IFERROR(VLOOKUP($BJ$17,Sheet1!AL18:AO18,3,0),0) -> 0 | BK30: =+IFERROR(VLOOKUP($BK$17,Sheet1!AL18:AO18,3,0),0) -> 0 | BL30: =+IFERROR(VLOOKUP($BL$17,Sheet1!AL18:AO18,3,0),0) -> 0 | BM30: =+IFERROR(VLOOKUP($BM$17,Sheet1!AL18:AO18,3,0),0) -> 0 | BN30: =+IFERROR(VLOOKUP($BN$17,Sheet1!AL18:AO18,3,0),0) -> 0 | BO30: =+IFERROR(VLOOKUP($BO$17,Sheet1!AP18:AS18,3,0),0) -> 0 | BP30: =+IFERROR(VLOOKUP($BP$17,Sheet1!AT18:AW18,3,0),0) -> 0 | BQ30: =+IFERROR(VLOOKUP($BQ$17,Sheet1!AX18:BA18,3,0),0) -> 0 | BR30: =+IFERROR(VLOOKUP($BR$17,Sheet1!BB18:BE18,3,0),0) -> 0 | BS30: =+IFERROR(VLOOKUP($BS$17,Sheet1!BF18:BI18,3,0),0) -> 0 | BT30: =+IFERROR(VLOOKUP($BT$17,Sheet1!BJ18:BM18,3,0),0) -> 0 | BU30: =+IFERROR(VLOOKUP($BU$17,Sheet1!BN18:BQ18,3,0),0) -> 0 | BV30: 16 | BW30: =+IFERROR(VLOOKUP($BW$17,Sheet1!BV18:BY18,3,0),0) -> 0 | BX30: =Sheet1!E18 -> WOOD | BY30: =Sheet1!CV18 -> MD0100090 | BZ30: =Sheet1!CW18 -> DRUM - 43 X 15 X 36 X 2.5 | CA30: =Sheet1!CX18 -> 1000 | CB30: =Sheet1!BZ18 -> 3881 | CC30: =SUMPRODUCT($P$18:$BW$18,P30:BW30)+CB30 -> 167354 | CD30: 0.01 | CE30: =CC30*CD30 -> 1673.54 | CF30: 0.15 | CG30: =CC30*CF30 -> 25103.1 | CH30: 0 | CI30: =CC30*CH30 -> 0 | CJ30: =CC30+CE30+CG30+CI30 -> 194130.64 | CK30: 0.02 | CL30: =CJ30*CK30 -> 3882.6128 | CM30: 0.01 | CN30: =CJ30*CM30 -> 1941.3064
B31: 13 | C31: =Sheet1!A21 -> ENQ-15115-22-23 | D31: 45658 | E31: =Sheet1!C21 -> FA0900117 | F31: =Sheet1!D21 -> 4 CORE X 35 SQ. MM. AL/ARD - WIRE (XLPE) | G31: =CJ31+CL31+CN31 -> 252365.66 | H31: =ROUNDUP(O61,0) -> 3968 | I31: =G31+H31 -> 256333.66 | J31: =Sheet1!CP21 -> 0.18 | K31: =I31*J31 -> 46140.058 | L31: =I31+K31 -> 302473.71 | M31: =Sheet1!CS21 -> 88.208 | N31: =Sheet1!CT21 -> KMS | O31: =L31*M31 -> 26680601 | P31: =+IFERROR(VLOOKUP($P$17,Sheet1!J21:L21,3,0),0) -> 378 | Q31: =+IFERROR(VLOOKUP($Q$17,Sheet1!J21:L21,3,0),0) -> 0 | R31: =+IFERROR(VLOOKUP($R$17,Sheet1!J21:M21,3,0),0) -> 0 | S31: =+IFERROR(VLOOKUP($S$17,Sheet1!J21:M21,3,0),0) -> 0 | T31: =+IFERROR(VLOOKUP($T$17,Sheet1!J21:M21,3,0),0) -> 0 | U31: =+IFERROR(VLOOKUP($U$17,Sheet1!N21:Q21,3,0),0) -> 0 | V31: =+IFERROR(VLOOKUP($V$17,Sheet1!N21:Q21,3,0),0) -> 0 | W31: =+IFERROR(VLOOKUP($W$17,Sheet1!F21:I21,3,0),0) -> 0 | X31: =+IFERROR(VLOOKUP($X$17,Sheet1!F21:I21,3,0),0) -> 0 | Y31: =+IFERROR(VLOOKUP($Y$17,Sheet1!F21:I21,3,0),0) -> 0 | Z31: =+IFERROR(VLOOKUP($Z$17,Sheet1!F21:I21,3,0),0) -> 0 | AA31: =+IFERROR(VLOOKUP($AA$17,Sheet1!F21:I21,3,0),0) -> 0 | AB31: =+IFERROR(VLOOKUP($AB$17,Sheet1!F21:I21,3,0),0) -> 0 | AC31: =+IFERROR(VLOOKUP($AC$17,Sheet1!F21:I21,3,0),0) -> 0 | AD31: =+IFERROR(VLOOKUP($AD$17,Sheet1!F21:I21,3,0),0) -> 0 | AE31: =+IFERROR(VLOOKUP($AE$17,Sheet1!R21:U21,3,0),0) -> 0 | AF31: =+IFERROR(VLOOKUP($AF$17,Sheet1!R21:U21,2,0),0) -> 0 | AG31: =+IFERROR(VLOOKUP($AG$17,Sheet1!V21:Y21,3,0),0) -> 0 | AH31: 102 | AI31: =+IFERROR(VLOOKUP($AI$17,Sheet1!V21:Y21,3,0),0) -> 0 | AJ31: =+IFERROR(VLOOKUP($AJ$17,Sheet1!V21:Y21,3,0),0) -> 0 | AK31: =+IFERROR(VLOOKUP($AK$17,Sheet1!V21:Y21,3,0),0) -> 0 | AL31: =+IFERROR(VLOOKUP($AL$17,Sheet1!V21:Y21,3,0),0) -> 0 | AM31: =+IFERROR(VLOOKUP($AM$17,Sheet1!Z21:AB21,3,0),0) -> 0 | AN31: =+IFERROR(VLOOKUP($AN$17,Sheet1!AD21:AG21,3,0),0) -> 0 | AO31: =+IFERROR(VLOOKUP($AO$17,Sheet1!AD21:AG21,3,0),0) -> 0 | AP31: =+IFERROR(VLOOKUP($AP$17,Sheet1!AD21:AG21,3,0),0) -> 0 | AQ31: =+IFERROR(VLOOKUP($AQ$17,Sheet1!AD21:AG21,3,0),0) -> 0 | AR31: =+IFERROR(VLOOKUP($AR$17,Sheet1!AD21:AG21,3,0),0) -> 0 | AS31: =+IFERROR(VLOOKUP($AS$17,Sheet1!AD21:AG21,3,0),0) -> 51 | AT31: =+IFERROR(VLOOKUP($AT$17,Sheet1!AD21:AG21,3,0),0) -> 0 | AU31: =+IFERROR(VLOOKUP($AU$17,Sheet1!AH21:AK21,3,0),0) -> 0 | AV31: =+IFERROR(VLOOKUP($AV$17,Sheet1!AH21:AK21,3,0),0) -> 0 | AW31: =+IFERROR(VLOOKUP($AW$17,Sheet1!AH21:AK21,3,0),0) -> 0 | AX31: =+IFERROR(VLOOKUP($AX$17,Sheet1!AH21:AK21,3,0),0) -> 0 | AY31: =+IFERROR(VLOOKUP($AY$17,Sheet1!AH21:AK21,3,0),0) -> 0 | AZ31: =+IFERROR(VLOOKUP($AZ$17,Sheet1!AH21:AK21,3,0),0) -> 0 | BA31: =+IFERROR(VLOOKUP($BA$17,Sheet1!AH21:AK21,3,0),0) -> 0 | BB31: =+IFERROR(VLOOKUP($BB$17,Sheet1!AH21:AK21,3,0),0) -> 0 | BC31: 770 | BD31: =+IFERROR(VLOOKUP($BD$17,Sheet1!AH21:AK21,3,0),0) -> 0 | BE31: =+IFERROR(VLOOKUP($BE$17,Sheet1!AL21:AO21,3,0),0) -> 0 | BF31: =+IFERROR(VLOOKUP($BF$17,Sheet1!AL21:AO21,3,0),0) -> 0 | BG31: =+IFERROR(VLOOKUP($BG$17,Sheet1!AL21:AO21,3,0),0) -> 0 | BH31: 206 | BI31: =+IFERROR(VLOOKUP($BI$17,Sheet1!AL21:AO21,3,0),0) -> 0 | BJ31: =+IFERROR(VLOOKUP($BJ$17,Sheet1!AL21:AO21,3,0),0) -> 0 | BK31: =+IFERROR(VLOOKUP($BK$17,Sheet1!AL21:AO21,3,0),0) -> 0 | BL31: =+IFERROR(VLOOKUP($BL$17,Sheet1!AL21:AO21,3,0),0) -> 0 | BM31: =+IFERROR(VLOOKUP($BM$17,Sheet1!AL21:AO21,3,0),0) -> 0 | BN31: =+IFERROR(VLOOKUP($BN$17,Sheet1!AL21:AO21,3,0),0) -> 0 | BO31: =+IFERROR(VLOOKUP($BO$17,Sheet1!AP21:AS21,3,0),0) -> 0 | BP31: =+IFERROR(VLOOKUP($BP$17,Sheet1!AT21:AW21,3,0),0) -> 0 | BQ31: =+IFERROR(VLOOKUP($BQ$17,Sheet1!AX21:BA21,3,0),0) -> 0 | BR31: =+IFERROR(VLOOKUP($BR$17,Sheet1!BB21:BE21,3,0),0) -> 0 | BS31: =+IFERROR(VLOOKUP($BS$17,Sheet1!BF21:BI21,3,0),0) -> 0 | BT31: =+IFERROR(VLOOKUP($BT$17,Sheet1!BJ21:BM21,3,0),0) -> 0 | BU31: =+IFERROR(VLOOKUP($BU$17,Sheet1!BN21:BQ21,3,0),0) -> 0 | BV31: 18 | BW31: =+IFERROR(VLOOKUP($BW$17,Sheet1!BV21:BY21,3,0),0) -> 0 | BX31: =Sheet1!E21 -> WOOD | BY31: =Sheet1!CV21 -> MD0100013 | BZ31: =Sheet1!CW21 -> DRUM - 48 X 14 X 36 X 2.25 | CA31: =Sheet1!CX21 -> 1000 | CB31: =Sheet1!BZ21 -> 4139 | CC31: =SUMPRODUCT($P$18:$BW$18,P31:BW31)+CB31 -> 211220 | CD31: 0.01 | CE31: =CC31*CD31 -> 2112.2 | CF31: 0.15 | CG31: =CC31*CF31 -> 31683 | CH31: 0 | CI31: =CC31*CH31 -> 0 | CJ31: =CC31+CE31+CG31+CI31 -> 245015.2 | CK31: 0.02 | CL31: =CJ31*CK31 -> 4900.304 | CM31: 0.01 | CN31: =CJ31*CM31 -> 2450.152
B32: 14 | C32: =Sheet1!A16 -> ENQ-15115-22-23 | D32: 45658 | E32: =Sheet1!C16 -> FA0900041 | F32: =Sheet1!D16 -> 2 CORE X 4 SQ. MM. AL/ARD - WIRE (XLPE) | G32: =CJ32+CL32+CN32 -> 60548.88 | H32: =ROUNDUP(O62,0) -> 1264 | I32: =G32+H32 -> 61812.88 | J32: =Sheet1!CP16 -> 0.18 | K32: =I32*J32 -> 11126.318 | L32: =I32+K32 -> 72939.198 | M32: =Sheet1!CS16 -> 2077.047 | N32: =Sheet1!CT16 -> KMS | O32: =L32*M32 -> 1.5149814e+08 | P32: =+IFERROR(VLOOKUP($P$17,Sheet1!J16:L16,3,0),0) -> 22 | Q32: =+IFERROR(VLOOKUP($Q$17,Sheet1!J16:L16,3,0),0) -> 0 | R32: =+IFERROR(VLOOKUP($R$17,Sheet1!J16:M16,3,0),0) -> 0 | S32: =+IFERROR(VLOOKUP($S$17,Sheet1!J16:M16,3,0),0) -> 0 | T32: =+IFERROR(VLOOKUP($T$17,Sheet1!J16:M16,3,0),0) -> 0 | U32: =+IFERROR(VLOOKUP($U$17,Sheet1!N16:Q16,3,0),0) -> 0 | V32: =+IFERROR(VLOOKUP($V$17,Sheet1!N16:Q16,3,0),0) -> 0 | W32: =+IFERROR(VLOOKUP($W$17,Sheet1!F16:I16,3,0),0) -> 0 | X32: =+IFERROR(VLOOKUP($X$17,Sheet1!F16:I16,3,0),0) -> 0 | Y32: =+IFERROR(VLOOKUP($Y$17,Sheet1!F16:I16,3,0),0) -> 0 | Z32: =+IFERROR(VLOOKUP($Z$17,Sheet1!F16:I16,3,0),0) -> 0 | AA32: =+IFERROR(VLOOKUP($AA$17,Sheet1!F16:I16,3,0),0) -> 0 | AB32: =+IFERROR(VLOOKUP($AB$17,Sheet1!F16:I16,3,0),0) -> 0 | AC32: =+IFERROR(VLOOKUP($AC$17,Sheet1!F16:I16,3,0),0) -> 0 | AD32: =+IFERROR(VLOOKUP($AD$17,Sheet1!F16:I16,3,0),0) -> 0 | AE32: =+IFERROR(VLOOKUP($AE$17,Sheet1!R16:U16,3,0),0) -> 0 | AF32: =+IFERROR(VLOOKUP($AF$17,Sheet1!R16:U16,2,0),0) -> 0 | AG32: =+IFERROR(VLOOKUP($AG$17,Sheet1!V16:Y16,3,0),0) -> 0 | AH32: 20 | AI32: =+IFERROR(VLOOKUP($AI$17,Sheet1!V16:Y16,3,0),0) -> 0 | AJ32: =+IFERROR(VLOOKUP($AJ$17,Sheet1!V16:Y16,3,0),0) -> 0 | AK32: =+IFERROR(VLOOKUP($AK$17,Sheet1!V16:Y16,3,0),0) -> 0 | AL32: =+IFERROR(VLOOKUP($AL$17,Sheet1!V16:Y16,3,0),0) -> 0 | AM32: =+IFERROR(VLOOKUP($AM$17,Sheet1!Z16:AB16,3,0),0) -> 0 | AN32: =+IFERROR(VLOOKUP($AN$17,Sheet1!AD16:AG16,3,0),0) -> 0 | AO32: =+IFERROR(VLOOKUP($AO$17,Sheet1!AD16:AG16,3,0),0) -> 0 | AP32: =+IFERROR(VLOOKUP($AP$17,Sheet1!AD16:AG16,3,0),0) -> 0 | AQ32: =+IFERROR(VLOOKUP($AQ$17,Sheet1!AD16:AG16,3,0),0) -> 0 | AR32: =+IFERROR(VLOOKUP($AR$17,Sheet1!AD16:AG16,3,0),0) -> 0 | AS32: 70 | AT32: =+IFERROR(VLOOKUP($AT$17,Sheet1!AD16:AG16,3,0),0) -> 0 | AU32: =+IFERROR(VLOOKUP($AU$17,Sheet1!AH16:AK16,3,0),0) -> 0 | AV32: =+IFERROR(VLOOKUP($AV$17,Sheet1!AH16:AK16,3,0),0) -> 0 | AW32: =+IFERROR(VLOOKUP($AW$17,Sheet1!AH16:AK16,3,0),0) -> 0 | AX32: =+IFERROR(VLOOKUP($AX$17,Sheet1!AH16:AK16,3,0),0) -> 0 | AY32: =+IFERROR(VLOOKUP($AY$17,Sheet1!AH16:AK16,3,0),0) -> 0 | AZ32: =+IFERROR(VLOOKUP($AZ$17,Sheet1!AH16:AK16,3,0),0) -> 0 | BA32: =+IFERROR(VLOOKUP($BA$17,Sheet1!AH16:AK16,3,0),0) -> 0 | BB32: =+IFERROR(VLOOKUP($BB$17,Sheet1!AH16:AK16,3,0),0) -> 0 | BC32: 252 | BD32: =+IFERROR(VLOOKUP($BD$17,Sheet1!AH16:AK16,3,0),0) -> 0 | BE32: =+IFERROR(VLOOKUP($BE$17,Sheet1!AL16:AO16,3,0),0) -> 0 | BF32: =+IFERROR(VLOOKUP($BF$17,Sheet1!AL16:AO16,3,0),0) -> 0 | BG32: =+IFERROR(VLOOKUP($BG$17,Sheet1!AL16:AO16,3,0),0) -> 0 | BH32: 103 | BI32: =+IFERROR(VLOOKUP($BI$17,Sheet1!AL16:AO16,3,0),0) -> 0 | BJ32: =+IFERROR(VLOOKUP($BJ$17,Sheet1!AL16:AO16,3,0),0) -> 0 | BK32: =+IFERROR(VLOOKUP($BK$17,Sheet1!AL16:AO16,3,0),0) -> 0 | BL32: =+IFERROR(VLOOKUP($BL$17,Sheet1!AL16:AO16,3,0),0) -> 0 | BM32: =+IFERROR(VLOOKUP($BM$17,Sheet1!AL16:AO16,3,0),0) -> 0 | BN32: =+IFERROR(VLOOKUP($BN$17,Sheet1!AL16:AO16,3,0),0) -> 0 | BO32: =+IFERROR(VLOOKUP($BO$17,Sheet1!AP16:AS16,3,0),0) -> 0 | BP32: =+IFERROR(VLOOKUP($BP$17,Sheet1!AT16:AW16,3,0),0) -> 0 | BQ32: =+IFERROR(VLOOKUP($BQ$17,Sheet1!AX16:BA16,3,0),0) -> 0 | BR32: =+IFERROR(VLOOKUP($BR$17,Sheet1!BB16:BE16,3,0),0) -> 0 | BS32: =+IFERROR(VLOOKUP($BS$17,Sheet1!BF16:BI16,3,0),0) -> 0 | BT32: =+IFERROR(VLOOKUP($BT$17,Sheet1!BJ16:BM16,3,0),0) -> 0 | BU32: =+IFERROR(VLOOKUP($BU$17,Sheet1!BN16:BQ16,3,0),0) -> 0 | BV32: 10 | BW32: =+IFERROR(VLOOKUP($BW$17,Sheet1!BV16:BY16,3,0),0) -> 0 | BX32: =Sheet1!E16 -> WOOD | BY32: =Sheet1!CV16 -> MD0100066 | BZ32: =Sheet1!CW16 -> DRUM - 40 X 15 X 23 X 2 | CA32: =Sheet1!CX16 -> 1000 | CB32: =Sheet1!BZ16 -> 2550 | CC32: =SUMPRODUCT($P$18:$BW$18,P32:BW32)+CB32 -> 50677 | CD32: 0.01 | CE32: =CC32*CD32 -> 506.77 | CF32: 0.15 | CG32: =CC32*CF32 -> 7601.55 | CH32: 0 | CI32: =CC32*CH32 -> 0 | CJ32: =CC32+CE32+CG32+CI32 -> 58785.32 | CK32: 0.02 | CL32: =CJ32*CK32 -> 1175.7064 | CM32: 0.01 | CN32: =CJ32*CM32 -> 587.8532
B33: 15 | C33: =Sheet1!A14 -> ENQ-15115-22-23 | D33: 45658 | E33: =Sheet1!C14 -> FA0900020 | F33: =Sheet1!D14 -> 2 CORE X 6 SQ. MM. AL/ARD - WIRE (XLPE) | G33: =CJ33+CL33+CN33 -> 69881.462 | H33: =ROUNDUP(O63,0) -> 1351 | I33: =G33+H33 -> 71232.462 | J33: =Sheet1!CP14 -> 0.18 | K33: =I33*J33 -> 12821.843 | L33: =I33+K33 -> 84054.306 | M33: 5000 | N33: =Sheet1!CT14 -> KMS | O33: =L33*M33 -> 4.2027153e+08 | P33: 33 | Q33: =+IFERROR(VLOOKUP($Q$17,Sheet1!J14:L14,3,0),0) -> 0 | R33: =+IFERROR(VLOOKUP($R$17,Sheet1!J14:M14,3,0),0) -> 0 | S33: =+IFERROR(VLOOKUP($S$17,Sheet1!J14:M14,3,0),0) -> 0 | T33: =+IFERROR(VLOOKUP($T$17,Sheet1!J14:M14,3,0),0) -> 0 | U33: =+IFERROR(VLOOKUP($U$17,Sheet1!N14:Q14,3,0),0) -> 0 | V33: =+IFERROR(VLOOKUP($V$17,Sheet1!N14:Q14,3,0),0) -> 0 | W33: =+IFERROR(VLOOKUP($W$17,Sheet1!F14:I14,3,0),0) -> 0 | X33: =+IFERROR(VLOOKUP($X$17,Sheet1!F14:I14,3,0),0) -> 0 | Y33: =+IFERROR(VLOOKUP($Y$17,Sheet1!F14:I14,3,0),0) -> 0 | Z33: =+IFERROR(VLOOKUP($Z$17,Sheet1!F14:I14,3,0),0) -> 0 | AA33: =+IFERROR(VLOOKUP($AA$17,Sheet1!F14:I14,3,0),0) -> 0 | AB33: =+IFERROR(VLOOKUP($AB$17,Sheet1!F14:I14,3,0),0) -> 0 | AC33: =+IFERROR(VLOOKUP($AC$17,Sheet1!F14:I14,3,0),0) -> 0 | AD33: =+IFERROR(VLOOKUP($AD$17,Sheet1!F14:I14,3,0),0) -> 0 | AE33: =+IFERROR(VLOOKUP($AE$17,Sheet1!R14:U14,3,0),0) -> 0 | AF33: =+IFERROR(VLOOKUP($AF$17,Sheet1!R14:U14,2,0),0) -> 0 | AG33: =+IFERROR(VLOOKUP($AG$17,Sheet1!V14:Y14,3,0),0) -> 0 | AH33: 23 | AI33: =+IFERROR(VLOOKUP($AI$17,Sheet1!V14:Y14,3,0),0) -> 0 | AJ33: =+IFERROR(VLOOKUP($AJ$17,Sheet1!V14:Y14,3,0),0) -> 0 | AK33: =+IFERROR(VLOOKUP($AK$17,Sheet1!V14:Y14,3,0),0) -> 0 | AL33: =+IFERROR(VLOOKUP($AL$17,Sheet1!V14:Y14,3,0),0) -> 0 | AM33: =+IFERROR(VLOOKUP($AM$17,Sheet1!Z14:AB14,3,0),0) -> 0 | AN33: =+IFERROR(VLOOKUP($AN$17,Sheet1!AD14:AG14,3,0),0) -> 0 | AO33: =+IFERROR(VLOOKUP($AO$17,Sheet1!AD14:AG14,3,0),0) -> 0 | AP33: =+IFERROR(VLOOKUP($AP$17,Sheet1!AD14:AG14,3,0),0) -> 0 | AQ33: =+IFERROR(VLOOKUP($AQ$17,Sheet1!AD14:AG14,3,0),0) -> 0 | AR33: =+IFERROR(VLOOKUP($AR$17,Sheet1!AD14:AG14,3,0),0) -> 0 | AS33: 0 | AT33: 78 | AU33: =+IFERROR(VLOOKUP($AU$17,Sheet1!AH14:AK14,3,0),0) -> 0 | AV33: =+IFERROR(VLOOKUP($AV$17,Sheet1!AH14:AK14,3,0),0) -> 0 | AW33: =+IFERROR(VLOOKUP($AW$17,Sheet1!AH14:AK14,3,0),0) -> 0 | AX33: =+IFERROR(VLOOKUP($AX$17,Sheet1!AH14:AK14,3,0),0) -> 0 | AY33: =+IFERROR(VLOOKUP($AY$17,Sheet1!AH14:AK14,3,0),0) -> 0 | AZ33: =+IFERROR(VLOOKUP($AZ$17,Sheet1!AH14:AK14,3,0),0) -> 0 | BA33: =+IFERROR(VLOOKUP($BA$17,Sheet1!AH14:AK14,3,0),0) -> 0 | BB33: =+IFERROR(VLOOKUP($BB$17,Sheet1!AH14:AK14,3,0),0) -> 0 | BC33: 276 | BD33: =+IFERROR(VLOOKUP($BD$17,Sheet1!AH14:AK14,3,0),0) -> 0 | BE33: =+IFERROR(VLOOKUP($BE$17,Sheet1!AL14:AO14,3,0),0) -> 0 | BF33: =+IFERROR(VLOOKUP($BF$17,Sheet1!AL14:AO14,3,0),0) -> 0 | BG33: =+IFERROR(VLOOKUP($BG$17,Sheet1!AL14:AO14,3,0),0) -> 0 | BH33: 108 | BI33: =+IFERROR(VLOOKUP($BI$17,Sheet1!AL14:AO14,3,0),0) -> 0 | BJ33: =+IFERROR(VLOOKUP($BJ$17,Sheet1!AL14:AO14,3,0),0) -> 0 | BK33: =+IFERROR(VLOOKUP($BK$17,Sheet1!AL14:AO14,3,0),0) -> 0 | BL33: =+IFERROR(VLOOKUP($BL$17,Sheet1!AL14:AO14,3,0),0) -> 0 | BM33: =+IFERROR(VLOOKUP($BM$17,Sheet1!AL14:AO14,3,0),0) -> 0 | BN33: =+IFERROR(VLOOKUP($BN$17,Sheet1!AL14:AO14,3,0),0) -> 0 | BO33: =+IFERROR(VLOOKUP($BO$17,Sheet1!AP14:AS14,3,0),0) -> 0 | BP33: =+IFERROR(VLOOKUP($BP$17,Sheet1!AT14:AW14,3,0),0) -> 0 | BQ33: =+IFERROR(VLOOKUP($BQ$17,Sheet1!AX14:BA14,3,0),0) -> 0 | BR33: =+IFERROR(VLOOKUP($BR$17,Sheet1!BB14:BE14,3,0),0) -> 0 | BS33: =+IFERROR(VLOOKUP($BS$17,Sheet1!BF14:BI14,3,0),0) -> 0 | BT33: =+IFERROR(VLOOKUP($BT$17,Sheet1!BJ14:BM14,3,0),0) -> 0 | BU33: =+IFERROR(VLOOKUP($BU$17,Sheet1!BN14:BQ14,3,0),0) -> 0 | BV33: 10 | BW33: =+IFERROR(VLOOKUP($BW$17,Sheet1!BV14:BY14,3,0),0) -> 0 | BX33: =Sheet1!E14 -> WOOD | BY33: =Sheet1!CV14 -> MD0100066 | BZ33: =Sheet1!CW14 -> DRUM - 40 X 15 X 23 X 2 | CA33: =Sheet1!CX14 -> 1000 | CB33: =Sheet1!BZ14 -> 2550 | CC33: =SUMPRODUCT($P$18:$BW$18,P33:BW33)+CB33 -> 58488 | CD33: 0.01 | CE33: =CC33*CD33 -> 584.88 | CF33: 0.15 | CG33: =CC33*CF33 -> 8773.2 | CH33: 0 | CI33: =CC33*CH33 -> 0 | CJ33: =CC33+CE33+CG33+CI33 -> 67846.08 | CK33: 0.02 | CL33: =CJ33*CK33 -> 1356.9216 | CM33: 0.01 | CN33: =CJ33*CM33 -> 678.4608
B34: 16 | C34: =Sheet1!A17 -> ENQ-15115-22-23 | D34: 45658 | E34: =Sheet1!C17 -> FA0900042 | F34: =Sheet1!D17 -> 2 CORE X 10 SQ. MM. ALU/ARD - WIRE (XLPE) | G34: =CJ34+CL34+CN34 -> 92040.223 | H34: =ROUNDUP(O64,0) -> 1885 | I34: =G34+H34 -> 93925.223 | J34: =Sheet1!CP17 -> 0.18 | K34: =I34*J34 -> 16906.54 | L34: =I34+K34 -> 110831.76 | M34: 130.04 | N34: =Sheet1!CT17 -> KMS | O34: =L34*M34 -> 14412563 | P34: =+IFERROR(VLOOKUP($P$17,Sheet1!J17:L17,3,0),0) -> 54 | Q34: =+IFERROR(VLOOKUP($Q$17,Sheet1!J17:L17,3,0),0) -> 0 | R34: =+IFERROR(VLOOKUP($R$17,Sheet1!J17:M17,3,0),0) -> 0 | S34: =+IFERROR(VLOOKUP($S$17,Sheet1!J17:M17,3,0),0) -> 0 | T34: =+IFERROR(VLOOKUP($T$17,Sheet1!J17:M17,3,0),0) -> 0 | U34: =+IFERROR(VLOOKUP($U$17,Sheet1!N17:Q17,3,0),0) -> 0 | V34: =+IFERROR(VLOOKUP($V$17,Sheet1!N17:Q17,3,0),0) -> 0 | W34: =+IFERROR(VLOOKUP($W$17,Sheet1!F17:I17,3,0),0) -> 0 | X34: =+IFERROR(VLOOKUP($X$17,Sheet1!F17:I17,3,0),0) -> 0 | Y34: =+IFERROR(VLOOKUP($Y$17,Sheet1!F17:I17,3,0),0) -> 0 | Z34: =+IFERROR(VLOOKUP($Z$17,Sheet1!F17:I17,3,0),0) -> 0 | AA34: =+IFERROR(VLOOKUP($AA$17,Sheet1!F17:I17,3,0),0) -> 0 | AB34: =+IFERROR(VLOOKUP($AB$17,Sheet1!F17:I17,3,0),0) -> 0 | AC34: =+IFERROR(VLOOKUP($AC$17,Sheet1!F17:I17,3,0),0) -> 0 | AD34: =+IFERROR(VLOOKUP($AD$17,Sheet1!F17:I17,3,0),0) -> 0 | AE34: =+IFERROR(VLOOKUP($AE$17,Sheet1!R17:U17,3,0),0) -> 0 | AF34: =+IFERROR(VLOOKUP($AF$17,Sheet1!R17:U17,2,0),0) -> 0 | AG34: =+IFERROR(VLOOKUP($AG$17,Sheet1!V17:Y17,3,0),0) -> 0 | AH34: 25 | AI34: =+IFERROR(VLOOKUP($AI$17,Sheet1!V17:Y17,3,0),0) -> 0 | AJ34: =+IFERROR(VLOOKUP($AJ$17,Sheet1!V17:Y17,3,0),0) -> 0 | AK34: =+IFERROR(VLOOKUP($AK$17,Sheet1!V17:Y17,3,0),0) -> 0 | AL34: =+IFERROR(VLOOKUP($AL$17,Sheet1!V17:Y17,3,0),0) -> 0 | AM34: =+IFERROR(VLOOKUP($AM$17,Sheet1!Z17:AB17,3,0),0) -> 0 | AN34: =+IFERROR(VLOOKUP($AN$17,Sheet1!AD17:AG17,3,0),0) -> 0 | AO34: =+IFERROR(VLOOKUP($AO$17,Sheet1!AD17:AG17,3,0),0) -> 0 | AP34: =+IFERROR(VLOOKUP($AP$17,Sheet1!AD17:AG17,3,0),0) -> 0 | AQ34: =+IFERROR(VLOOKUP($AQ$17,Sheet1!AD17:AG17,3,0),0) -> 0 | AR34: =+IFERROR(VLOOKUP($AR$17,Sheet1!AD17:AG17,3,0),0) -> 0 | AS34: =+IFERROR(VLOOKUP($AS$17,Sheet1!AD17:AG17,3,0),0) -> 0 | AT34: 103 | AU34: =+IFERROR(VLOOKUP($AU$17,Sheet1!AH17:AK17,3,0),0) -> 0 | AV34: =+IFERROR(VLOOKUP($AV$17,Sheet1!AH17:AK17,3,0),0) -> 0 | AW34: =+IFERROR(VLOOKUP($AW$17,Sheet1!AH17:AK17,3,0),0) -> 0 | AX34: =+IFERROR(VLOOKUP($AX$17,Sheet1!AH17:AK17,3,0),0) -> 0 | AY34: =+IFERROR(VLOOKUP($AY$17,Sheet1!AH17:AK17,3,0),0) -> 0 | AZ34: =+IFERROR(VLOOKUP($AZ$17,Sheet1!AH17:AK17,3,0),0) -> 0 | BA34: =+IFERROR(VLOOKUP($BA$17,Sheet1!AH17:AK17,3,0),0) -> 0 | BB34: =+IFERROR(VLOOKUP($BB$17,Sheet1!AH17:AK17,3,0),0) -> 0 | BC34: 360 | BD34: =+IFERROR(VLOOKUP($BD$17,Sheet1!AH17:AK17,3,0),0) -> 0 | BE34: =+IFERROR(VLOOKUP($BE$17,Sheet1!AL17:AO17,3,0),0) -> 0 | BF34: =+IFERROR(VLOOKUP($BF$17,Sheet1!AL17:AO17,3,0),0) -> 0 | BG34: =+IFERROR(VLOOKUP($BG$17,Sheet1!AL17:AO17,3,0),0) -> 0 | BH34: 120 | BI34: =+IFERROR(VLOOKUP($BI$17,Sheet1!AL17:AO17,3,0),0) -> 0 | BJ34: =+IFERROR(VLOOKUP($BJ$17,Sheet1!AL17:AO17,3,0),0) -> 0 | BK34: =+IFERROR(VLOOKUP($BK$17,Sheet1!AL17:AO17,3,0),0) -> 0 | BL34: =+IFERROR(VLOOKUP($BL$17,Sheet1!AL17:AO17,3,0),0) -> 0 | BM34: =+IFERROR(VLOOKUP($BM$17,Sheet1!AL17:AO17,3,0),0) -> 0 | BN34: =+IFERROR(VLOOKUP($BN$17,Sheet1!AL17:AO17,3,0),0) -> 0 | BO34: =+IFERROR(VLOOKUP($BO$17,Sheet1!AP17:AS17,3,0),0) -> 0 | BP34: =+IFERROR(VLOOKUP($BP$17,Sheet1!AT17:AW17,3,0),0) -> 0 | BQ34: =+IFERROR(VLOOKUP($BQ$17,Sheet1!AX17:BA17,3,0),0) -> 0 | BR34: =+IFERROR(VLOOKUP($BR$17,Sheet1!BB17:BE17,3,0),0) -> 0 | BS34: =+IFERROR(VLOOKUP($BS$17,Sheet1!BF17:BI17,3,0),0) -> 0 | BT34: =+IFERROR(VLOOKUP($BT$17,Sheet1!BJ17:BM17,3,0),0) -> 0 | BU34: =+IFERROR(VLOOKUP($BU$17,Sheet1!BN17:BQ17,3,0),0) -> 0 | BV34: 12 | BW34: =+IFERROR(VLOOKUP($BW$17,Sheet1!BV17:BY17,3,0),0) -> 0 | BX34: =Sheet1!E17 -> WOOD | BY34: =Sheet1!CV17 -> MD0100075 | BZ34: =Sheet1!CW17 -> DRUM - 42 X 15 X 23 X 2 | CA34: =Sheet1!CX17 -> 1000 | CB34: =Sheet1!BZ17 -> 3992 | CC34: =SUMPRODUCT($P$18:$BW$18,P34:BW34)+CB34 -> 77034 | CD34: 0.01 | CE34: =CC34*CD34 -> 770.34 | CF34: 0.15 | CG34: =CC34*CF34 -> 11555.1 | CH34: 0 | CI34: =CC34*CH34 -> 0 | CJ34: =CC34+CE34+CG34+CI34 -> 89359.44 | CK34: 0.02 | CL34: =CJ34*CK34 -> 1787.1888 | CM34: 0.01 | CN34: =CJ34*CM34 -> 893.5944
B35: 17 | C35: =Sheet1!A19 -> ENQ-15115-22-23 | D35: 45658 | E35: =Sheet1!C19 -> FA0900112 | F35: =Sheet1!D19 -> 4 CORE X 10 SQ. MM. AL/ARD - WIRE (XLPE) | G35: =CJ35+CL35+CN35 -> 111007.08 | H35: =ROUNDUP(O65,0) -> 2075 | I35: =G35+H35 -> 113082.08 | J35: =Sheet1!CP19 -> 0.18 | K35: =I35*J35 -> 20354.774 | L35: =I35+K35 -> 133436.85 | M35: 151.832 | N35: =Sheet1!CT19 -> KMS | O35: =L35*M35 -> 20259984 | P35: =+IFERROR(VLOOKUP($P$17,Sheet1!J19:L19,3,0),0) -> 108 | Q35: =+IFERROR(VLOOKUP($Q$17,Sheet1!J19:L19,3,0),0) -> 0 | R35: =+IFERROR(VLOOKUP($R$17,Sheet1!J19:M19,3,0),0) -> 0 | S35: =+IFERROR(VLOOKUP($S$17,Sheet1!J19:M19,3,0),0) -> 0 | T35: =+IFERROR(VLOOKUP($T$17,Sheet1!J19:M19,3,0),0) -> 0 | U35: =+IFERROR(VLOOKUP($U$17,Sheet1!N19:Q19,3,0),0) -> 0 | V35: =+IFERROR(VLOOKUP($V$17,Sheet1!N19:Q19,3,0),0) -> 0 | W35: =+IFERROR(VLOOKUP($W$17,Sheet1!F19:I19,3,0),0) -> 0 | X35: =+IFERROR(VLOOKUP($X$17,Sheet1!F19:I19,3,0),0) -> 0 | Y35: =+IFERROR(VLOOKUP($Y$17,Sheet1!F19:I19,3,0),0) -> 0 | Z35: =+IFERROR(VLOOKUP($Z$17,Sheet1!F19:I19,3,0),0) -> 0 | AA35: =+IFERROR(VLOOKUP($AA$17,Sheet1!F19:I19,3,0),0) -> 0 | AB35: =+IFERROR(VLOOKUP($AB$17,Sheet1!F19:I19,3,0),0) -> 0 | AC35: =+IFERROR(VLOOKUP($AC$17,Sheet1!F19:I19,3,0),0) -> 0 | AD35: =+IFERROR(VLOOKUP($AD$17,Sheet1!F19:I19,3,0),0) -> 0 | AE35: =+IFERROR(VLOOKUP($AE$17,Sheet1!R19:U19,3,0),0) -> 0 | AF35: =+IFERROR(VLOOKUP($AF$17,Sheet1!R19:U19,2,0),0) -> 0 | AG35: =+IFERROR(VLOOKUP($AG$17,Sheet1!V19:Y19,3,0),0) -> 0 | AH35: 50 | AI35: =+IFERROR(VLOOKUP($AI$17,Sheet1!V19:Y19,3,0),0) -> 0 | AJ35: =+IFERROR(VLOOKUP($AJ$17,Sheet1!V19:Y19,3,0),0) -> 0 | AK35: =+IFERROR(VLOOKUP($AK$17,Sheet1!V19:Y19,3,0),0) -> 0 | AL35: =+IFERROR(VLOOKUP($AL$17,Sheet1!V19:Y19,3,0),0) -> 0 | AM35: =+IFERROR(VLOOKUP($AM$17,Sheet1!Z19:AB19,3,0),0) -> 0 | AN35: =+IFERROR(VLOOKUP($AN$17,Sheet1!AD19:AG19,3,0),0) -> 0 | AO35: =+IFERROR(VLOOKUP($AO$17,Sheet1!AD19:AG19,3,0),0) -> 0 | AP35: =+IFERROR(VLOOKUP($AP$17,Sheet1!AD19:AG19,3,0),0) -> 0 | AQ35: =+IFERROR(VLOOKUP($AQ$17,Sheet1!AD19:AG19,3,0),0) -> 0 | AR35: =+IFERROR(VLOOKUP($AR$17,Sheet1!AD19:AG19,3,0),0) -> 0 | AS35: =+IFERROR(VLOOKUP($AS$17,Sheet1!AD19:AG19,3,0),0) -> 35 | AT35: =+IFERROR(VLOOKUP($AT$17,Sheet1!AD19:AG19,3,0),0) -> 0 | AU35: =+IFERROR(VLOOKUP($AU$17,Sheet1!AH19:AK19,3,0),0) -> 0 | AV35: =+IFERROR(VLOOKUP($AV$17,Sheet1!AH19:AK19,3,0),0) -> 0 | AW35: =+IFERROR(VLOOKUP($AW$17,Sheet1!AH19:AK19,3,0),0) -> 0 | AX35: =+IFERROR(VLOOKUP($AX$17,Sheet1!AH19:AK19,3,0),0) -> 0 | AY35: =+IFERROR(VLOOKUP($AY$17,Sheet1!AH19:AK19,3,0),0) -> 0 | AZ35: =+IFERROR(VLOOKUP($AZ$17,Sheet1!AH19:AK19,3,0),0) -> 0 | BA35: =+IFERROR(VLOOKUP($BA$17,Sheet1!AH19:AK19,3,0),0) -> 0 | BB35: =+IFERROR(VLOOKUP($BB$17,Sheet1!AH19:AK19,3,0),0) -> 0 | BC35: 377 | BD35: =+IFERROR(VLOOKUP($BD$17,Sheet1!AH19:AK19,3,0),0) -> 0 | BE35: =+IFERROR(VLOOKUP($BE$17,Sheet1!AL19:AO19,3,0),0) -> 0 | BF35: =+IFERROR(VLOOKUP($BF$17,Sheet1!AL19:AO19,3,0),0) -> 0 | BG35: =+IFERROR(VLOOKUP($BG$17,Sheet1!AL19:AO19,3,0),0) -> 0 | BH35: =+IFERROR(VLOOKUP($BH$17,Sheet1!AL19:AO19,3,0),0) -> 151 | BI35: =+IFERROR(VLOOKUP($BI$17,Sheet1!AL19:AO19,3,0),0) -> 0 | BJ35: =+IFERROR(VLOOKUP($BJ$17,Sheet1!AL19:AO19,3,0),0) -> 0 | BK35: =+IFERROR(VLOOKUP($BK$17,Sheet1!AL19:AO19,3,0),0) -> 0 | BL35: =+IFERROR(VLOOKUP($BL$17,Sheet1!AL19:AO19,3,0),0) -> 0 | BM35: =+IFERROR(VLOOKUP($BM$17,Sheet1!AL19:AO19,3,0),0) -> 0 | BN35: =+IFERROR(VLOOKUP($BN$17,Sheet1!AL19:AO19,3,0),0) -> 0 | BO35: =+IFERROR(VLOOKUP($BO$17,Sheet1!AP19:AS19,3,0),0) -> 0 | BP35: =+IFERROR(VLOOKUP($BP$17,Sheet1!AT19:AW19,3,0),0) -> 0 | BQ35: =+IFERROR(VLOOKUP($BQ$17,Sheet1!AX19:BA19,3,0),0) -> 0 | BR35: =+IFERROR(VLOOKUP($BR$17,Sheet1!BB19:BE19,3,0),0) -> 0 | BS35: =+IFERROR(VLOOKUP($BS$17,Sheet1!BF19:BI19,3,0),0) -> 0 | BT35: =+IFERROR(VLOOKUP($BT$17,Sheet1!BJ19:BM19,3,0),0) -> 0 | BU35: =+IFERROR(VLOOKUP($BU$17,Sheet1!BN19:BQ19,3,0),0) -> 0 | BV35: 13.5 | BW35: =+IFERROR(VLOOKUP($BW$17,Sheet1!BV19:BY19,3,0),0) -> 0 | BX35: =Sheet1!E19 -> WOOD | BY35: =Sheet1!CV19 -> MD0100064 | BZ35: =Sheet1!CW19 -> DRUM - 42 X 15 X 32 X 2 | CA35: =Sheet1!CX19 -> 1000 | CB35: =Sheet1!BZ19 -> 4593 | CC35: =SUMPRODUCT($P$18:$BW$18,P35:BW35)+CB35 -> 92908.5 | CD35: 0.01 | CE35: =CC35*CD35 -> 929.085 | CF35: 0.15 | CG35: =CC35*CF35 -> 13936.275 | CH35: 0 | CI35: =CC35*CH35 -> 0 | CJ35: =CC35+CE35+CG35+CI35 -> 107773.86 | CK35: 0.02 | CL35: =CJ35*CK35 -> 2155.4772 | CM35: 0.01 | CN35: =CJ35*CM35 -> 1077.7386
B36: 18 | C36: =Sheet1!A5 -> ENQ-15115-22-23 | D36: 45658 | E36: =Sheet1!C5 -> FA0200011 | F36: =Sheet1!D5 -> 4 CORE X 2.5 SQ. MM. CU/ARD - WIRE (PVC) | G36: =CJ36+CL36+CN36 -> 144287.63 | H36: =ROUNDUP(O66,0) -> 2271 | I36: =G36+H36 -> 146558.63 | J36: =Sheet1!CP5 -> 0.18 | K36: =I36*J36 -> 26380.554 | L36: =I36+K36 -> 172939.19 | M36: 61.67 | N36: =Sheet1!CT5 -> KMS | O36: =L36*M36 -> 10665160 | P36: =+IFERROR(VLOOKUP($P$17,Sheet1!J5:L5,3,0),0) -> 0 | Q36: =+IFERROR(VLOOKUP($Q$17,Sheet1!J5:L5,3,0),0) -> 0 | R36: =+IFERROR(VLOOKUP($R$17,Sheet1!J5:M5,3,0),0) -> 89 | S36: =+IFERROR(VLOOKUP($S$17,Sheet1!J5:M5,3,0),0) -> 0 | T36: =+IFERROR(VLOOKUP($T$17,Sheet1!J5:M5,3,0),0) -> 0 | U36: =+IFERROR(VLOOKUP($U$17,Sheet1!N5:Q5,3,0),0) -> 0 | V36: =+IFERROR(VLOOKUP($V$17,Sheet1!N5:Q5,3,0),0) -> 0 | W36: =+IFERROR(VLOOKUP($W$17,Sheet1!F5:I5,3,0),0) -> 0 | X36: =+IFERROR(VLOOKUP($X$17,Sheet1!F5:I5,3,0),0) -> 0 | Y36: =+IFERROR(VLOOKUP($Y$17,Sheet1!F5:I5,3,0),0) -> 0 | Z36: =+IFERROR(VLOOKUP($Z$17,Sheet1!F5:I5,3,0),0) -> 0 | AA36: =+IFERROR(VLOOKUP($AA$17,Sheet1!F5:I5,3,0),0) -> 0 | AB36: =+IFERROR(VLOOKUP($AB$17,Sheet1!F5:I5,3,0),0) -> 0 | AC36: =+IFERROR(VLOOKUP($AC$17,Sheet1!F5:I5,3,0),0) -> 0 | AD36: =+IFERROR(VLOOKUP($AD$17,Sheet1!F5:I5,3,0),0) -> 0 | AE36: =+IFERROR(VLOOKUP($AE$17,Sheet1!R5:U5,3,0),0) -> 0 | AF36: =+IFERROR(VLOOKUP($AF$17,Sheet1!R5:U5,2,0),0) -> 0 | AG36: =+IFERROR(VLOOKUP($AG$17,Sheet1!V5:Y5,3,0),0) -> 0 | AH36: =+IFERROR(VLOOKUP($AH$17,Sheet1!V5:Y5,3,0),0) -> 0 | AI36: =+IFERROR(VLOOKUP($AI$17,Sheet1!V5:Y5,3,0),0) -> 0 | AJ36: =+IFERROR(VLOOKUP($AJ$17,Sheet1!V5:Y5,3,0),0) -> 0 | AK36: =+IFERROR(VLOOKUP($AK$17,Sheet1!V5:Y5,3,0),0) -> 52 | AL36: =+IFERROR(VLOOKUP($AL$17,Sheet1!V5:Y5,3,0),0) -> 0 | AM36: =+IFERROR(VLOOKUP($AM$17,Sheet1!Z5:AB5,3,0),0) -> 3 | AN36: =+IFERROR(VLOOKUP($AN$17,Sheet1!AD5:AG5,3,0),0) -> 0 | AO36: =+IFERROR(VLOOKUP($AO$17,Sheet1!AD5:AG5,3,0),0) -> 0 | AP36: =+IFERROR(VLOOKUP($AP$17,Sheet1!AD5:AG5,3,0),0) -> 0 | AQ36: =+IFERROR(VLOOKUP($AQ$17,Sheet1!AD5:AG5,3,0),0) -> 0 | AR36: =+IFERROR(VLOOKUP($AR$17,Sheet1!AD5:AG5,3,0),0) -> 0 | AS36: 27 | AT36: =+IFERROR(VLOOKUP($AT$17,Sheet1!AD5:AG5,3,0),0) -> 0 | AU36: =+IFERROR(VLOOKUP($AU$17,Sheet1!AH5:AK5,3,0),0) -> 0 | AV36: =+IFERROR(VLOOKUP($AV$17,Sheet1!AH5:AK5,3,0),0) -> 0 | AW36: =+IFERROR(VLOOKUP($AW$17,Sheet1!AH5:AK5,3,0),0) -> 0 | AX36: =+IFERROR(VLOOKUP($AX$17,Sheet1!AH5:AK5,3,0),0) -> 0 | AY36: =+IFERROR(VLOOKUP($AY$17,Sheet1!AH5:AK5,3,0),0) -> 0 | AZ36: =+IFERROR(VLOOKUP($AZ$17,Sheet1!AH5:AK5,3,0),0) -> 0 | BA36: =+IFERROR(VLOOKUP($BA$17,Sheet1!AH5:AK5,3,0),0) -> 0 | BB36: =+IFERROR(VLOOKUP($BB$17,Sheet1!AH5:AK5,3,0),0) -> 0 | BC36: 289 | BD36: =+IFERROR(VLOOKUP($BD$17,Sheet1!AH5:AK5,3,0),0) -> 0 | BE36: =+IFERROR(VLOOKUP($BE$17,Sheet1!AL5:AO5,3,0),0) -> 0 | BF36: =+IFERROR(VLOOKUP($BF$17,Sheet1!AL5:AO5,3,0),0) -> 0 | BG36: =+IFERROR(VLOOKUP($BG$17,Sheet1!AL5:AO5,3,0),0) -> 0 | BH36: 104 | BI36: =+IFERROR(VLOOKUP($BI$17,Sheet1!AL5:AO5,3,0),0) -> 0 | BJ36: =+IFERROR(VLOOKUP($BJ$17,Sheet1!AL5:AO5,3,0),0) -> 0 | BK36: =+IFERROR(VLOOKUP($BK$17,Sheet1!AL5:AO5,3,0),0) -> 0 | BL36: =+IFERROR(VLOOKUP($BL$17,Sheet1!AL5:AO5,3,0),0) -> 0 | BM36: =+IFERROR(VLOOKUP($BM$17,Sheet1!AL5:AO5,3,0),0) -> 0 | BN36: =+IFERROR(VLOOKUP($BN$17,Sheet1!AL5:AO5,3,0),0) -> 0 | BO36: =+IFERROR(VLOOKUP($BO$17,Sheet1!AP5:AS5,3,0),0) -> 0 | BP36: =+IFERROR(VLOOKUP($BP$17,Sheet1!AT5:AW5,3,0),0) -> 0 | BQ36: =+IFERROR(VLOOKUP($BQ$17,Sheet1!AX5:BA5,3,0),0) -> 0 | BR36: =+IFERROR(VLOOKUP($BR$17,Sheet1!BB5:BE5,3,0),0) -> 0 | BS36: =+IFERROR(VLOOKUP($BS$17,Sheet1!BF5:BI5,3,0),0) -> 0 | BT36: =+IFERROR(VLOOKUP($BT$17,Sheet1!BJ5:BM5,3,0),0) -> 0 | BU36: =+IFERROR(VLOOKUP($BU$17,Sheet1!BN5:BQ5,3,0),0) -> 0 | BV36: =+IFERROR(VLOOKUP($BV$17,Sheet1!BR5:BU5,3,0),0) -> 0 | BW36: =+IFERROR(VLOOKUP($BW$17,Sheet1!BV5:BY5,3,0),0) -> 0 | BX36: =Sheet1!E5 -> WOOD | BY36: =Sheet1!CV5 -> MD0100005 | BZ36: =Sheet1!CW5 -> DRUM - 36 X 14 X 23 X 2 | CA36: =Sheet1!CX5 -> 500 | CB36: =Sheet1!BZ5 -> 4858 | CC36: =SUMPRODUCT($P$18:$BW$18,P36:BW36)+CB36 -> 120763 | CD36: 0.01 | CE36: =CC36*CD36 -> 1207.63 | CF36: 0.15 | CG36: =CC36*CF36 -> 18114.45 | CH36: 0 | CI36: =CC36*CH36 -> 0 | CJ36: =CC36+CE36+CG36+CI36 -> 140085.08 | CK36: 0.02 | CL36: =CJ36*CK36 -> 2801.7016 | CM36: 0.01 | CN36: =CJ36*CM36 -> 1400.8508
B37: 19 | C37: =Sheet1!A6 -> ENQ-15115-22-23 | D37: 45658 | E37: =Sheet1!C6 -> FA0200018 | F37: =Sheet1!D6 -> 7 CORE X 2.5 SQ. MM. CU/ARD - WIRE (PVC) | G37: =CJ37+CL37+CN37 -> 223186.25 | H37: =ROUNDUP(O67,0) -> 2125 | I37: =G37+H37 -> 225311.25 | J37: =Sheet1!CP6 -> 0.18 | K37: =I37*J37 -> 40556.025 | L37: =I37+K37 -> 265867.28 | M37: =Sheet1!CS6 -> 98.845 | N37: =Sheet1!CT6 -> KMS | O37: =L37*M37 -> 26279651 | P37: =+IFERROR(VLOOKUP($P$17,Sheet1!J6:L6,3,0),0) -> 0 | Q37: =+IFERROR(VLOOKUP($Q$17,Sheet1!J6:L6,3,0),0) -> 0 | R37: =+IFERROR(VLOOKUP($R$17,Sheet1!J6:M6,3,0),0) -> 155 | S37: =+IFERROR(VLOOKUP($S$17,Sheet1!J6:M6,3,0),0) -> 0 | T37: =+IFERROR(VLOOKUP($T$17,Sheet1!J6:M6,3,0),0) -> 0 | U37: =+IFERROR(VLOOKUP($U$17,Sheet1!N6:Q6,3,0),0) -> 0 | V37: =+IFERROR(VLOOKUP($V$17,Sheet1!N6:Q6,3,0),0) -> 0 | W37: =+IFERROR(VLOOKUP($W$17,Sheet1!F6:I6,3,0),0) -> 0 | X37: =+IFERROR(VLOOKUP($X$17,Sheet1!F6:I6,3,0),0) -> 0 | Y37: =+IFERROR(VLOOKUP($Y$17,Sheet1!F6:I6,3,0),0) -> 0 | Z37: =+IFERROR(VLOOKUP($Z$17,Sheet1!F6:I6,3,0),0) -> 0 | AA37: =+IFERROR(VLOOKUP($AA$17,Sheet1!F6:I6,3,0),0) -> 0 | AB37: =+IFERROR(VLOOKUP($AB$17,Sheet1!F6:I6,3,0),0) -> 0 | AC37: =+IFERROR(VLOOKUP($AC$17,Sheet1!F6:I6,3,0),0) -> 0 | AD37: =+IFERROR(VLOOKUP($AD$17,Sheet1!F6:I6,3,0),0) -> 0 | AE37: =+IFERROR(VLOOKUP($AE$17,Sheet1!R6:U6,3,0),0) -> 0 | AF37: =+IFERROR(VLOOKUP($AF$17,Sheet1!R6:U6,2,0),0) -> 0 | AG37: =+IFERROR(VLOOKUP($AG$17,Sheet1!V6:Y6,3,0),0) -> 0 | AH37: =+IFERROR(VLOOKUP($AH$17,Sheet1!V6:Y6,3,0),0) -> 0 | AI37: =+IFERROR(VLOOKUP($AI$17,Sheet1!V6:Y6,3,0),0) -> 0 | AJ37: =+IFERROR(VLOOKUP($AJ$17,Sheet1!V6:Y6,3,0),0) -> 0 | AK37: =+IFERROR(VLOOKUP($AK$17,Sheet1!V6:Y6,3,0),0) -> 91 | AL37: =+IFERROR(VLOOKUP($AL$17,Sheet1!V6:Y6,3,0),0) -> 0 | AM37: =+IFERROR(VLOOKUP($AM$17,Sheet1!Z6:AB6,3,0),0) -> 4 | AN37: =+IFERROR(VLOOKUP($AN$17,Sheet1!AD6:AG6,3,0),0) -> 0 | AO37: =+IFERROR(VLOOKUP($AO$17,Sheet1!AD6:AG6,3,0),0) -> 0 | AP37: =+IFERROR(VLOOKUP($AP$17,Sheet1!AD6:AG6,3,0),0) -> 0 | AQ37: =+IFERROR(VLOOKUP($AQ$17,Sheet1!AD6:AG6,3,0),0) -> 0 | AR37: =+IFERROR(VLOOKUP($AR$17,Sheet1!AD6:AG6,3,0),0) -> 0 | AS37: 33 | AT37: =+IFERROR(VLOOKUP($AT$17,Sheet1!AD6:AG6,3,0),0) -> 0 | AU37: =+IFERROR(VLOOKUP($AU$17,Sheet1!AH6:AK6,3,0),0) -> 0 | AV37: =+IFERROR(VLOOKUP($AV$17,Sheet1!AH6:AK6,3,0),0) -> 0 | AW37: =+IFERROR(VLOOKUP($AW$17,Sheet1!AH6:AK6,3,0),0) -> 0 | AX37: =+IFERROR(VLOOKUP($AX$17,Sheet1!AH6:AK6,3,0),0) -> 0 | AY37: =+IFERROR(VLOOKUP($AY$17,Sheet1!AH6:AK6,3,0),0) -> 0 | AZ37: =+IFERROR(VLOOKUP($AZ$17,Sheet1!AH6:AK6,3,0),0) -> 0 | BA37: =+IFERROR(VLOOKUP($BA$17,Sheet1!AH6:AK6,3,0),0) -> 0 | BB37: =+IFERROR(VLOOKUP($BB$17,Sheet1!AH6:AK6,3,0),0) -> 0 | BC37: 352 | BD37: =+IFERROR(VLOOKUP($BD$17,Sheet1!AH6:AK6,3,0),0) -> 0 | BE37: =+IFERROR(VLOOKUP($BE$17,Sheet1!AL6:AO6,3,0),0) -> 0 | BF37: =+IFERROR(VLOOKUP($BF$17,Sheet1!AL6:AO6,3,0),0) -> 0 | BG37: =+IFERROR(VLOOKUP($BG$17,Sheet1!AL6:AO6,3,0),0) -> 0 | BH37: 120 | BI37: =+IFERROR(VLOOKUP($BI$17,Sheet1!AL6:AO6,3,0),0) -> 0 | BJ37: =+IFERROR(VLOOKUP($BJ$17,Sheet1!AL6:AO6,3,0),0) -> 0 | BK37: =+IFERROR(VLOOKUP($BK$17,Sheet1!AL6:AO6,3,0),0) -> 0 | BL37: =+IFERROR(VLOOKUP($BL$17,Sheet1!AL6:AO6,3,0),0) -> 0 | BM37: =+IFERROR(VLOOKUP($BM$17,Sheet1!AL6:AO6,3,0),0) -> 0 | BN37: =+IFERROR(VLOOKUP($BN$17,Sheet1!AL6:AO6,3,0),0) -> 0 | BO37: =+IFERROR(VLOOKUP($BO$17,Sheet1!AP6:AS6,3,0),0) -> 0 | BP37: =+IFERROR(VLOOKUP($BP$17,Sheet1!AT6:AW6,3,0),0) -> 0 | BQ37: =+IFERROR(VLOOKUP($BQ$17,Sheet1!AX6:BA6,3,0),0) -> 0 | BR37: =+IFERROR(VLOOKUP($BR$17,Sheet1!BB6:BE6,3,0),0) -> 0 | BS37: =+IFERROR(VLOOKUP($BS$17,Sheet1!BF6:BI6,3,0),0) -> 0 | BT37: =+IFERROR(VLOOKUP($BT$17,Sheet1!BJ6:BM6,3,0),0) -> 0 | BU37: =+IFERROR(VLOOKUP($BU$17,Sheet1!BN6:BQ6,3,0),0) -> 0 | BV37: =+IFERROR(VLOOKUP($BV$17,Sheet1!BR6:BU6,3,0),0) -> 0 | BW37: =+IFERROR(VLOOKUP($BW$17,Sheet1!BV6:BY6,3,0),0) -> 0 | BX37: =Sheet1!E6 -> WOOD | BY37: =Sheet1!CV6 -> MD0100005 | BZ37: =Sheet1!CW6 -> DRUM - 36 X 14 X 23 X 2 | CA37: =Sheet1!CX6 -> 500 | CB37: =Sheet1!BZ6 -> 4858 | CC37: =SUMPRODUCT($P$18:$BW$18,P37:BW37)+CB37 -> 186798 | CD37: 0.01 | CE37: =CC37*CD37 -> 1867.98 | CF37: 0.15 | CG37: =CC37*CF37 -> 28019.7 | CH37: 0 | CI37: =CC37*CH37 -> 0 | CJ37: =CC37+CE37+CG37+CI37 -> 216685.68 | CK37: 0.02 | CL37: =CJ37*CK37 -> 4333.7136 | CM37: 0.01 | CN37: =CJ37*CM37 -> 2166.8568
B38: 20 | C38: =Sheet1!A2 -> ENQ-15115-22-23 | D38: 45658 | E38: =Sheet1!C2 -> FA0200002 | F38: =Sheet1!D2 -> 10 CORE X 2.5 SQ. MM. CU/ARD - WIRE (PVC) | G38: =CJ38+CL38+CN38 -> 317379.5 | H38: =ROUNDUP(O68,0) -> 3103 | I38: =G38+H38 -> 320482.5 | J38: =Sheet1!CP2 -> 0.18 | K38: =I38*J38 -> 57686.851 | L38: =I38+K38 -> 378169.35 | M38: 78.965 | N38: =Sheet1!CT2 -> KMS | O38: =L38*M38 -> 29862143 | P38: =+IFERROR(VLOOKUP($P$17,Sheet1!J2:L2,3,0),0) -> 0 | Q38: =+IFERROR(VLOOKUP($Q$17,Sheet1!J2:L2,3,0),0) -> 0 | R38: =+IFERROR(VLOOKUP($R$17,Sheet1!J2:M2,3,0),0) -> 222 | S38: =+IFERROR(VLOOKUP($S$17,Sheet1!J2:M2,3,0),0) -> 0 | T38: =+IFERROR(VLOOKUP($T$17,Sheet1!J2:M2,3,0),0) -> 0 | U38: =+IFERROR(VLOOKUP($U$17,Sheet1!N2:Q2,3,0),0) -> 0 | V38: =+IFERROR(VLOOKUP($V$17,Sheet1!N2:Q2,3,0),0) -> 0 | W38: =+IFERROR(VLOOKUP($W$17,Sheet1!F2:I2,3,0),0) -> 0 | X38: =+IFERROR(VLOOKUP($X$17,Sheet1!F2:I2,3,0),0) -> 0 | Y38: =+IFERROR(VLOOKUP($Y$17,Sheet1!F2:I2,3,0),0) -> 0 | Z38: =+IFERROR(VLOOKUP($Z$17,Sheet1!F2:I2,3,0),0) -> 0 | AA38: =+IFERROR(VLOOKUP($AA$17,Sheet1!F2:I2,3,0),0) -> 0 | AB38: =+IFERROR(VLOOKUP($AB$17,Sheet1!F2:I2,3,0),0) -> 0 | AC38: =+IFERROR(VLOOKUP($AC$17,Sheet1!F2:I2,3,0),0) -> 0 | AD38: =+IFERROR(VLOOKUP($AD$17,Sheet1!F2:I2,3,0),0) -> 0 | AE38: =+IFERROR(VLOOKUP($AE$17,Sheet1!R2:U2,3,0),0) -> 0 | AF38: =+IFERROR(VLOOKUP($AF$17,Sheet1!R2:U2,2,0),0) -> 0 | AG38: =+IFERROR(VLOOKUP($AG$17,Sheet1!V2:Y2,3,0),0) -> 0 | AH38: =+IFERROR(VLOOKUP($AH$17,Sheet1!V2:Y2,3,0),0) -> 0 | AI38: =+IFERROR(VLOOKUP($AI$17,Sheet1!V2:Y2,3,0),0) -> 0 | AJ38: =+IFERROR(VLOOKUP($AJ$17,Sheet1!V2:Y2,3,0),0) -> 0 | AK38: =+IFERROR(VLOOKUP($AK$17,Sheet1!V2:Y2,3,0),0) -> 130 | AL38: =+IFERROR(VLOOKUP($AL$17,Sheet1!V2:Y2,3,0),0) -> 0 | AM38: =+IFERROR(VLOOKUP($AM$17,Sheet1!Z2:AB2,3,0),0) -> 5 | AN38: =+IFERROR(VLOOKUP($AN$17,Sheet1!AD2:AG2,3,0),0) -> 0 | AO38: =+IFERROR(VLOOKUP($AO$17,Sheet1!AD2:AG2,3,0),0) -> 0 | AP38: =+IFERROR(VLOOKUP($AP$17,Sheet1!AD2:AG2,3,0),0) -> 0 | AQ38: =+IFERROR(VLOOKUP($AQ$17,Sheet1!AD2:AG2,3,0),0) -> 0 | AR38: =+IFERROR(VLOOKUP($AR$17,Sheet1!AD2:AG2,3,0),0) -> 0 | AS38: 42 | AT38: =+IFERROR(VLOOKUP($AT$17,Sheet1!AD2:AG2,3,0),0) -> 0 | AU38: =+IFERROR(VLOOKUP($AU$17,Sheet1!AH2:AK2,3,0),0) -> 0 | AV38: =+IFERROR(VLOOKUP($AV$17,Sheet1!AH2:AK2,3,0),0) -> 0 | AW38: =+IFERROR(VLOOKUP($AW$17,Sheet1!AH2:AK2,3,0),0) -> 0 | AX38: =+IFERROR(VLOOKUP($AX$17,Sheet1!AH2:AK2,3,0),0) -> 0 | AY38: =+IFERROR(VLOOKUP($AY$17,Sheet1!AH2:AK2,3,0),0) -> 0 | AZ38: =+IFERROR(VLOOKUP($AZ$17,Sheet1!AH2:AK2,3,0),0) -> 0 | BA38: =+IFERROR(VLOOKUP($BA$17,Sheet1!AH2:AK2,3,0),0) -> 0 | BB38: =+IFERROR(VLOOKUP($BB$17,Sheet1!AH2:AK2,3,0),0) -> 0 | BC38: 509 | BD38: =+IFERROR(VLOOKUP($BD$17,Sheet1!AH2:AK2,3,0),0) -> 0 | BE38: =+IFERROR(VLOOKUP($BE$17,Sheet1!AL2:AO2,3,0),0) -> 0 | BF38: =+IFERROR(VLOOKUP($BF$17,Sheet1!AL2:AO2,3,0),0) -> 0 | BG38: =+IFERROR(VLOOKUP($BG$17,Sheet1!AL2:AO2,3,0),0) -> 0 | BH38: 172 | BI38: =+IFERROR(VLOOKUP($BI$17,Sheet1!AL2:AO2,3,0),0) -> 0 | BJ38: =+IFERROR(VLOOKUP($BJ$17,Sheet1!AL2:AO2,3,0),0) -> 0 | BK38: =+IFERROR(VLOOKUP($BK$17,Sheet1!AL2:AO2,3,0),0) -> 0 | BL38: =+IFERROR(VLOOKUP($BL$17,Sheet1!AL2:AO2,3,0),0) -> 0 | BM38: =+IFERROR(VLOOKUP($BM$17,Sheet1!AL2:AO2,3,0),0) -> 0 | BN38: =+IFERROR(VLOOKUP($BN$17,Sheet1!AL2:AO2,3,0),0) -> 0 | BO38: =+IFERROR(VLOOKUP($BO$17,Sheet1!AP2:AS2,3,0),0) -> 0 | BP38: =+IFERROR(VLOOKUP($BP$17,Sheet1!AT2:AW2,3,0),0) -> 0 | BQ38: =+IFERROR(VLOOKUP($BQ$17,Sheet1!AX2:BA2,3,0),0) -> 0 | BR38: =+IFERROR(VLOOKUP($BR$17,Sheet1!BB2:BE2,3,0),0) -> 0 | BS38: =+IFERROR(VLOOKUP($BS$17,Sheet1!BF2:BI2,3,0),0) -> 0 | BT38: =+IFERROR(VLOOKUP($BT$17,Sheet1!BJ2:BM2,3,0),0) -> 0 | BU38: =+IFERROR(VLOOKUP($BU$17,Sheet1!BN2:BQ2,3,0),0) -> 0 | BV38: =+IFERROR(VLOOKUP($BV$17,Sheet1!BR2:BU2,3,0),0) -> 0 | BW38: =+IFERROR(VLOOKUP($BW$17,Sheet1!BV2:BY2,3,0),0) -> 0 | BX38: =Sheet1!E2 -> WOOD | BY38: =Sheet1!CV2 -> MD0100066 | BZ38: =Sheet1!CW2 -> DRUM - 40 X 15 X 23 X 2 | CA38: =Sheet1!CX2 -> 500 | CB38: =Sheet1!BZ2 -> 5100 | CC38: =SUMPRODUCT($P$18:$BW$18,P38:BW38)+CB38 -> 265634 | CD38: 0.01 | CE38: =CC38*CD38 -> 2656.34 | CF38: 0.15 | CG38: =CC38*CF38 -> 39845.1 | CH38: 0 | CI38: =CC38*CH38 -> 0 | CJ38: =CC38+CE38+CG38+CI38 -> 308135.44 | CK38: 0.02 | CL38: =CJ38*CK38 -> 6162.7088 | CM38: 0.01 | CN38: =CJ38*CM38 -> 3081.3544
B39: 21 | C39: =Sheet1!A3 -> ENQ-15115-22-23 | D39: 45658 | E39: =Sheet1!C3 -> FA0200003 | F39: =Sheet1!D3 -> 12 CORE X 2.5 SQ. MM. CU/ARD - WIRE (PVC) | G39: =CJ39+CL39+CN39 -> 366743.86 | H39: =ROUNDUP(O69,0) -> 3590 | I39: =G39+H39 -> 370333.86 | J39: =Sheet1!CP3 -> 0.18 | K39: =I39*J39 -> 66660.095 | L39: =I39+K39 -> 436993.95 | M39: 39 | N39: =Sheet1!CT3 -> KMS | O39: =L39*M39 -> 17042764 | P39: =+IFERROR(VLOOKUP($P$17,Sheet1!J3:L3,3,0),0) -> 0 | Q39: =+IFERROR(VLOOKUP($Q$17,Sheet1!J3:L3,3,0),0) -> 0 | R39: =+IFERROR(VLOOKUP($R$17,Sheet1!J3:M3,3,0),0) -> 266 | S39: =+IFERROR(VLOOKUP($S$17,Sheet1!J3:M3,3,0),0) -> 0 | T39: =+IFERROR(VLOOKUP($T$17,Sheet1!J3:M3,3,0),0) -> 0 | U39: =+IFERROR(VLOOKUP($U$17,Sheet1!N3:Q3,3,0),0) -> 0 | V39: =+IFERROR(VLOOKUP($V$17,Sheet1!N3:Q3,3,0),0) -> 0 | W39: =+IFERROR(VLOOKUP($W$17,Sheet1!F3:I3,3,0),0) -> 0 | X39: =+IFERROR(VLOOKUP($X$17,Sheet1!F3:I3,3,0),0) -> 0 | Y39: =+IFERROR(VLOOKUP($Y$17,Sheet1!F3:I3,3,0),0) -> 0 | Z39: =+IFERROR(VLOOKUP($Z$17,Sheet1!F3:I3,3,0),0) -> 0 | AA39: =+IFERROR(VLOOKUP($AA$17,Sheet1!F3:I3,3,0),0) -> 0 | AB39: =+IFERROR(VLOOKUP($AB$17,Sheet1!F3:I3,3,0),0) -> 0 | AC39: =+IFERROR(VLOOKUP($AC$17,Sheet1!F3:I3,3,0),0) -> 0 | AD39: =+IFERROR(VLOOKUP($AD$17,Sheet1!F3:I3,3,0),0) -> 0 | AE39: =+IFERROR(VLOOKUP($AE$17,Sheet1!R3:U3,3,0),0) -> 0 | AF39: =+IFERROR(VLOOKUP($AF$17,Sheet1!R3:U3,2,0),0) -> 0 | AG39: =+IFERROR(VLOOKUP($AG$17,Sheet1!V3:Y3,3,0),0) -> 0 | AH39: =+IFERROR(VLOOKUP($AH$17,Sheet1!V3:Y3,3,0),0) -> 0 | AI39: =+IFERROR(VLOOKUP($AI$17,Sheet1!V3:Y3,3,0),0) -> 0 | AJ39: =+IFERROR(VLOOKUP($AJ$17,Sheet1!V3:Y3,3,0),0) -> 0 | AK39: =+IFERROR(VLOOKUP($AK$17,Sheet1!V3:Y3,3,0),0) -> 156 | AL39: =+IFERROR(VLOOKUP($AL$17,Sheet1!V3:Y3,3,0),0) -> 0 | AM39: =+IFERROR(VLOOKUP($AM$17,Sheet1!Z3:AB3,3,0),0) -> 6 | AN39: =+IFERROR(VLOOKUP($AN$17,Sheet1!AD3:AG3,3,0),0) -> 0 | AO39: =+IFERROR(VLOOKUP($AO$17,Sheet1!AD3:AG3,3,0),0) -> 0 | AP39: =+IFERROR(VLOOKUP($AP$17,Sheet1!AD3:AG3,3,0),0) -> 0 | AQ39: =+IFERROR(VLOOKUP($AQ$17,Sheet1!AD3:AG3,3,0),0) -> 0 | AR39: =+IFERROR(VLOOKUP($AR$17,Sheet1!AD3:AG3,3,0),0) -> 0 | AS39: 44 | AT39: =+IFERROR(VLOOKUP($AT$17,Sheet1!AD3:AG3,3,0),0) -> 0 | AU39: =+IFERROR(VLOOKUP($AU$17,Sheet1!AH3:AK3,3,0),0) -> 0 | AV39: =+IFERROR(VLOOKUP($AV$17,Sheet1!AH3:AK3,3,0),0) -> 0 | AW39: =+IFERROR(VLOOKUP($AW$17,Sheet1!AH3:AK3,3,0),0) -> 0 | AX39: =+IFERROR(VLOOKUP($AX$17,Sheet1!AH3:AK3,3,0),0) -> 0 | AY39: =+IFERROR(VLOOKUP($AY$17,Sheet1!AH3:AK3,3,0),0) -> 0 | AZ39: =+IFERROR(VLOOKUP($AZ$17,Sheet1!AH3:AK3,3,0),0) -> 0 | BA39: =+IFERROR(VLOOKUP($BA$17,Sheet1!AH3:AK3,3,0),0) -> 0 | BB39: =+IFERROR(VLOOKUP($BB$17,Sheet1!AH3:AK3,3,0),0) -> 0 | BC39: 526 | BD39: =+IFERROR(VLOOKUP($BD$17,Sheet1!AH3:AK3,3,0),0) -> 0 | BE39: =+IFERROR(VLOOKUP($BE$17,Sheet1!AL3:AO3,3,0),0) -> 0 | BF39: =+IFERROR(VLOOKUP($BF$17,Sheet1!AL3:AO3,3,0),0) -> 0 | BG39: =+IFERROR(VLOOKUP($BG$17,Sheet1!AL3:AO3,3,0),0) -> 0 | BH39: 178 | BI39: =+IFERROR(VLOOKUP($BI$17,Sheet1!AL3:AO3,3,0),0) -> 0 | BJ39: =+IFERROR(VLOOKUP($BJ$17,Sheet1!AL3:AO3,3,0),0) -> 0 | BK39: =+IFERROR(VLOOKUP($BK$17,Sheet1!AL3:AO3,3,0),0) -> 0 | BL39: =+IFERROR(VLOOKUP($BL$17,Sheet1!AL3:AO3,3,0),0) -> 0 | BM39: =+IFERROR(VLOOKUP($BM$17,Sheet1!AL3:AO3,3,0),0) -> 0 | BN39: =+IFERROR(VLOOKUP($BN$17,Sheet1!AL3:AO3,3,0),0) -> 0 | BO39: =+IFERROR(VLOOKUP($BO$17,Sheet1!AP3:AS3,3,0),0) -> 0 | BP39: =+IFERROR(VLOOKUP($BP$17,Sheet1!AT3:AW3,3,0),0) -> 0 | BQ39: =+IFERROR(VLOOKUP($BQ$17,Sheet1!AX3:BA3,3,0),0) -> 0 | BR39: =+IFERROR(VLOOKUP($BR$17,Sheet1!BB3:BE3,3,0),0) -> 0 | BS39: =+IFERROR(VLOOKUP($BS$17,Sheet1!BF3:BI3,3,0),0) -> 0 | BT39: =+IFERROR(VLOOKUP($BT$17,Sheet1!BJ3:BM3,3,0),0) -> 0 | BU39: =+IFERROR(VLOOKUP($BU$17,Sheet1!BN3:BQ3,3,0),0) -> 0 | BV39: =+IFERROR(VLOOKUP($BV$17,Sheet1!BR3:BU3,3,0),0) -> 0 | BW39: =+IFERROR(VLOOKUP($BW$17,Sheet1!BV3:BY3,3,0),0) -> 0 | BX39: =Sheet1!E3 -> WOOD | BY39: =Sheet1!CV3 -> MD0100066 | BZ39: =Sheet1!CW3 -> DRUM - 40 X 15 X 23 X 2 | CA39: =Sheet1!CX3 -> 500 | CB39: =Sheet1!BZ3 -> 5100 | CC39: =SUMPRODUCT($P$18:$BW$18,P39:BW39)+CB39 -> 306950 | CD39: 0.01 | CE39: =CC39*CD39 -> 3069.5 | CF39: 0.15 | CG39: =CC39*CF39 -> 46042.5 | CH39: 0 | CI39: =CC39*CH39 -> 0 | CJ39: =CC39+CE39+CG39+CI39 -> 356062 | CK39: 0.02 | CL39: =CJ39*CK39 -> 7121.24 | CM39: 0.01 | CN39: =CJ39*CM39 -> 3560.62
B40: 22 | C40: =Sheet1!A4 -> ENQ-15115-22-23 | D40: 45658 | E40: =Sheet1!C4 -> FA0200005 | F40: =Sheet1!D4 -> 16 CORE X 2.5 SQ. MM. CU/ARD - WIRE (PVC) | G40: =CJ40+CL40+CN40 -> 472972.33 | H40: =ROUNDUP(O70,0) -> 3750 | I40: =G40+H40 -> 476722.33 | J40: =Sheet1!CP4 -> 0.18 | K40: =I40*J40 -> 85810.02 | L40: =I40+K40 -> 562532.35 | M40: 28 | N40: =Sheet1!CT4 -> KMS | O40: =L40*M40 -> 15750906 | P40: =+IFERROR(VLOOKUP($P$17,Sheet1!J4:L4,3,0),0) -> 0 | Q40: =+IFERROR(VLOOKUP($Q$17,Sheet1!J4:L4,3,0),0) -> 0 | R40: =+IFERROR(VLOOKUP($R$17,Sheet1!J4:M4,3,0),0) -> 355 | S40: =+IFERROR(VLOOKUP($S$17,Sheet1!J4:M4,3,0),0) -> 0 | T40: =+IFERROR(VLOOKUP($T$17,Sheet1!J4:M4,3,0),0) -> 0 | U40: =+IFERROR(VLOOKUP($U$17,Sheet1!N4:Q4,3,0),0) -> 0 | V40: =+IFERROR(VLOOKUP($V$17,Sheet1!N4:Q4,3,0),0) -> 0 | W40: =+IFERROR(VLOOKUP($W$17,Sheet1!F4:I4,3,0),0) -> 0 | X40: =+IFERROR(VLOOKUP($X$17,Sheet1!F4:I4,3,0),0) -> 0 | Y40: =+IFERROR(VLOOKUP($Y$17,Sheet1!F4:I4,3,0),0) -> 0 | Z40: =+IFERROR(VLOOKUP($Z$17,Sheet1!F4:I4,3,0),0) -> 0 | AA40: =+IFERROR(VLOOKUP($AA$17,Sheet1!F4:I4,3,0),0) -> 0 | AB40: =+IFERROR(VLOOKUP($AB$17,Sheet1!F4:I4,3,0),0) -> 0 | AC40: =+IFERROR(VLOOKUP($AC$17,Sheet1!F4:I4,3,0),0) -> 0 | AD40: =+IFERROR(VLOOKUP($AD$17,Sheet1!F4:I4,3,0),0) -> 0 | AE40: =+IFERROR(VLOOKUP($AE$17,Sheet1!R4:U4,3,0),0) -> 0 | AF40: =+IFERROR(VLOOKUP($AF$17,Sheet1!R4:U4,2,0),0) -> 0 | AG40: =+IFERROR(VLOOKUP($AG$17,Sheet1!V4:Y4,3,0),0) -> 0 | AH40: =+IFERROR(VLOOKUP($AH$17,Sheet1!V4:Y4,3,0),0) -> 0 | AI40: =+IFERROR(VLOOKUP($AI$17,Sheet1!V4:Y4,3,0),0) -> 0 | AJ40: =+IFERROR(VLOOKUP($AJ$17,Sheet1!V4:Y4,3,0),0) -> 0 | AK40: 214 | AL40: =+IFERROR(VLOOKUP($AL$17,Sheet1!V4:Y4,3,0),0) -> 0 | AM40: =+IFERROR(VLOOKUP($AM$17,Sheet1!Z4:AB4,3,0),0) -> 6 | AN40: =+IFERROR(VLOOKUP($AN$17,Sheet1!AD4:AG4,3,0),0) -> 0 | AO40: =+IFERROR(VLOOKUP($AO$17,Sheet1!AD4:AG4,3,0),0) -> 0 | AP40: =+IFERROR(VLOOKUP($AP$17,Sheet1!AD4:AG4,3,0),0) -> 0 | AQ40: =+IFERROR(VLOOKUP($AQ$17,Sheet1!AD4:AG4,3,0),0) -> 0 | AR40: =+IFERROR(VLOOKUP($AR$17,Sheet1!AD4:AG4,3,0),0) -> 0 | AS40: 58 | AT40: =+IFERROR(VLOOKUP($AT$17,Sheet1!AD4:AG4,3,0),0) -> 0 | AU40: =+IFERROR(VLOOKUP($AU$17,Sheet1!AH4:AK4,3,0),0) -> 0 | AV40: =+IFERROR(VLOOKUP($AV$17,Sheet1!AH4:AK4,3,0),0) -> 0 | AW40: =+IFERROR(VLOOKUP($AW$17,Sheet1!AH4:AK4,3,0),0) -> 0 | AX40: =+IFERROR(VLOOKUP($AX$17,Sheet1!AH4:AK4,3,0),0) -> 0 | AY40: =+IFERROR(VLOOKUP($AY$17,Sheet1!AH4:AK4,3,0),0) -> 0 | AZ40: =+IFERROR(VLOOKUP($AZ$17,Sheet1!AH4:AK4,3,0),0) -> 0 | BA40: =+IFERROR(VLOOKUP($BA$17,Sheet1!AH4:AK4,3,0),0) -> 0 | BB40: =+IFERROR(VLOOKUP($BB$17,Sheet1!AH4:AK4,3,0),0) -> 0 | BC40: =+IFERROR(VLOOKUP($BC$17,Sheet1!AH4:AK4,3,0),0) -> 574 | BD40: =+IFERROR(VLOOKUP($BD$17,Sheet1!AH4:AK4,3,0),0) -> 0 | BE40: =+IFERROR(VLOOKUP($BE$17,Sheet1!AL4:AO4,3,0),0) -> 0 | BF40: =+IFERROR(VLOOKUP($BF$17,Sheet1!AL4:AO4,3,0),0) -> 0 | BG40: =+IFERROR(VLOOKUP($BG$17,Sheet1!AL4:AO4,3,0),0) -> 0 | BH40: 193 | BI40: =+IFERROR(VLOOKUP($BI$17,Sheet1!AL4:AO4,3,0),0) -> 0 | BJ40: =+IFERROR(VLOOKUP($BJ$17,Sheet1!AL4:AO4,3,0),0) -> 0 | BK40: =+IFERROR(VLOOKUP($BK$17,Sheet1!AL4:AO4,3,0),0) -> 0 | BL40: =+IFERROR(VLOOKUP($BL$17,Sheet1!AL4:AO4,3,0),0) -> 0 | BM40: =+IFERROR(VLOOKUP($BM$17,Sheet1!AL4:AO4,3,0),0) -> 0 | BN40: =+IFERROR(VLOOKUP($BN$17,Sheet1!AL4:AO4,3,0),0) -> 0 | BO40: =+IFERROR(VLOOKUP($BO$17,Sheet1!AP4:AS4,3,0),0) -> 0 | BP40: =+IFERROR(VLOOKUP($BP$17,Sheet1!AT4:AW4,3,0),0) -> 0 | BQ40: =+IFERROR(VLOOKUP($BQ$17,Sheet1!AX4:BA4,3,0),0) -> 0 | BR40: =+IFERROR(VLOOKUP($BR$17,Sheet1!BB4:BE4,3,0),0) -> 0 | BS40: =+IFERROR(VLOOKUP($BS$17,Sheet1!BF4:BI4,3,0),0) -> 0 | BT40: =+IFERROR(VLOOKUP($BT$17,Sheet1!BJ4:BM4,3,0),0) -> 0 | BU40: =+IFERROR(VLOOKUP($BU$17,Sheet1!BN4:BQ4,3,0),0) -> 0 | BV40: =+IFERROR(VLOOKUP($BV$17,Sheet1!BR4:BU4,3,0),0) -> 0 | BW40: =+IFERROR(VLOOKUP($BW$17,Sheet1!BV4:BY4,3,0),0) -> 0 | BX40: =Sheet1!E4 -> WOOD | BY40: =Sheet1!CV4 -> MD0100075 | BZ40: =Sheet1!CW4 -> DRUM - 42 X 15 X 23 X 2 | CA40: =Sheet1!CX4 -> 500 | CB40: =Sheet1!BZ4 -> 7984 | CC40: =SUMPRODUCT($P$18:$BW$18,P40:BW40)+CB40 -> 395859 | CD40: 0.01 | CE40: =CC40*CD40 -> 3958.59 | CF40: 0.15 | CG40: =CC40*CF40 -> 59378.85 | CH40: 0 | CI40: =CC40*CH40 -> 0 | CJ40: =CC40+CE40+CG40+CI40 -> 459196.44 | CK40: 0.02 | CL40: =CJ40*CK40 -> 9183.9288 | CM40: 0.01 | CN40: =CJ40*CM40 -> 4591.9644
B41: 23 | C41: =Sheet1!A15 -> ENQ-15115-22-23 | D41: 45658 | E41: =Sheet1!C15 -> FA0900024 | F41: =Sheet1!D15 -> 4 CORE X 4 SQ. MM. CU/ARD - WIRE (PVC) | G41: =CJ41+CL41+CN41 -> 210455.66 | H41: =ROUNDUP(O71,0) -> 35000 | I41: =G41+H41 -> 245455.66 | J41: =Sheet1!CP15 -> 0.18 | K41: =I41*J41 -> 44182.018 | L41: =I41+K41 -> 289637.67 | M41: =Sheet1!CS15 -> 1 | N41: =Sheet1!CT15 -> KMS | O41: =L41*M41 -> 289637.67 | P41: =+IFERROR(VLOOKUP($P$17,Sheet1!J15:L15,3,0),0) -> 0 | Q41: =+IFERROR(VLOOKUP($Q$17,Sheet1!J15:L15,3,0),0) -> 0 | R41: =+IFERROR(VLOOKUP($R$17,Sheet1!J15:M15,3,0),0) -> 144 | S41: =+IFERROR(VLOOKUP($S$17,Sheet1!J15:M15,3,0),0) -> 0 | T41: =+IFERROR(VLOOKUP($T$17,Sheet1!J15:M15,3,0),0) -> 0 | U41: =+IFERROR(VLOOKUP($U$17,Sheet1!N15:Q15,3,0),0) -> 0 | V41: =+IFERROR(VLOOKUP($V$17,Sheet1!N15:Q15,3,0),0) -> 0 | W41: =+IFERROR(VLOOKUP($W$17,Sheet1!F15:I15,3,0),0) -> 0 | X41: =+IFERROR(VLOOKUP($X$17,Sheet1!F15:I15,3,0),0) -> 0 | Y41: =+IFERROR(VLOOKUP($Y$17,Sheet1!F15:I15,3,0),0) -> 0 | Z41: =+IFERROR(VLOOKUP($Z$17,Sheet1!F15:I15,3,0),0) -> 0 | AA41: =+IFERROR(VLOOKUP($AA$17,Sheet1!F15:I15,3,0),0) -> 0 | AB41: =+IFERROR(VLOOKUP($AB$17,Sheet1!F15:I15,3,0),0) -> 0 | AC41: =+IFERROR(VLOOKUP($AC$17,Sheet1!F15:I15,3,0),0) -> 0 | AD41: =+IFERROR(VLOOKUP($AD$17,Sheet1!F15:I15,3,0),0) -> 0 | AE41: =+IFERROR(VLOOKUP($AE$17,Sheet1!R15:U15,3,0),0) -> 0 | AF41: =+IFERROR(VLOOKUP($AF$17,Sheet1!R15:U15,2,0),0) -> 0 | AG41: =+IFERROR(VLOOKUP($AG$17,Sheet1!V15:Y15,3,0),0) -> 0 | AH41: =+IFERROR(VLOOKUP($AH$17,Sheet1!V15:Y15,3,0),0) -> 0 | AI41: =+IFERROR(VLOOKUP($AI$17,Sheet1!V15:Y15,3,0),0) -> 0 | AJ41: =+IFERROR(VLOOKUP($AJ$17,Sheet1!V15:Y15,3,0),0) -> 0 | AK41: =+IFERROR(VLOOKUP($AK$17,Sheet1!V15:Y15,3,0),0) -> 76 | AL41: =+IFERROR(VLOOKUP($AL$17,Sheet1!V15:Y15,3,0),0) -> 0 | AM41: =+IFERROR(VLOOKUP($AM$17,Sheet1!Z15:AB15,3,0),0) -> 4 | AN41: =+IFERROR(VLOOKUP($AN$17,Sheet1!AD15:AG15,3,0),0) -> 0 | AO41: =+IFERROR(VLOOKUP($AO$17,Sheet1!AD15:AG15,3,0),0) -> 0 | AP41: =+IFERROR(VLOOKUP($AP$17,Sheet1!AD15:AG15,3,0),0) -> 0 | AQ41: =+IFERROR(VLOOKUP($AQ$17,Sheet1!AD15:AG15,3,0),0) -> 0 | AR41: =+IFERROR(VLOOKUP($AR$17,Sheet1!AD15:AG15,3,0),0) -> 0 | AS41: =+IFERROR(VLOOKUP($AS$17,Sheet1!AD15:AG15,3,0),0) -> 34 | AT41: =+IFERROR(VLOOKUP($AT$17,Sheet1!AD15:AG15,3,0),0) -> 0 | AU41: =+IFERROR(VLOOKUP($AU$17,Sheet1!AH15:AK15,3,0),0) -> 0 | AV41: =+IFERROR(VLOOKUP($AV$17,Sheet1!AH15:AK15,3,0),0) -> 0 | AW41: =+IFERROR(VLOOKUP($AW$17,Sheet1!AH15:AK15,3,0),0) -> 0 | AX41: =+IFERROR(VLOOKUP($AX$17,Sheet1!AH15:AK15,3,0),0) -> 0 | AY41: =+IFERROR(VLOOKUP($AY$17,Sheet1!AH15:AK15,3,0),0) -> 0 | AZ41: =+IFERROR(VLOOKUP($AZ$17,Sheet1!AH15:AK15,3,0),0) -> 0 | BA41: =+IFERROR(VLOOKUP($BA$17,Sheet1!AH15:AK15,3,0),0) -> 0 | BB41: =+IFERROR(VLOOKUP($BB$17,Sheet1!AH15:AK15,3,0),0) -> 0 | BC41: =+IFERROR(VLOOKUP($BC$17,Sheet1!AH15:AK15,3,0),0) -> 352 | BD41: =+IFERROR(VLOOKUP($BD$17,Sheet1!AH15:AK15,3,0),0) -> 0 | BE41: =+IFERROR(VLOOKUP($BE$17,Sheet1!AL15:AO15,3,0),0) -> 0 | BF41: =+IFERROR(VLOOKUP($BF$17,Sheet1!AL15:AO15,3,0),0) -> 0 | BG41: =+IFERROR(VLOOKUP($BG$17,Sheet1!AL15:AO15,3,0),0) -> 0 | BH41: =+IFERROR(VLOOKUP($BH$17,Sheet1!AL15:AO15,3,0),0) -> 119 | BI41: =+IFERROR(VLOOKUP($BI$17,Sheet1!AL15:AO15,3,0),0) -> 0 | BJ41: =+IFERROR(VLOOKUP($BJ$17,Sheet1!AL15:AO15,3,0),0) -> 0 | BK41: =+IFERROR(VLOOKUP($BK$17,Sheet1!AL15:AO15,3,0),0) -> 0 | BL41: =+IFERROR(VLOOKUP($BL$17,Sheet1!AL15:AO15,3,0),0) -> 0 | BM41: =+IFERROR(VLOOKUP($BM$17,Sheet1!AL15:AO15,3,0),0) -> 0 | BN41: =+IFERROR(VLOOKUP($BN$17,Sheet1!AL15:AO15,3,0),0) -> 0 | BO41: =+IFERROR(VLOOKUP($BO$17,Sheet1!AP15:AS15,3,0),0) -> 0 | BP41: =+IFERROR(VLOOKUP($BP$17,Sheet1!AT15:AW15,3,0),0) -> 0 | BQ41: =+IFERROR(VLOOKUP($BQ$17,Sheet1!AX15:BA15,3,0),0) -> 0 | BR41: =+IFERROR(VLOOKUP($BR$17,Sheet1!BB15:BE15,3,0),0) -> 0 | BS41: =+IFERROR(VLOOKUP($BS$17,Sheet1!BF15:BI15,3,0),0) -> 0 | BT41: =+IFERROR(VLOOKUP($BT$17,Sheet1!BJ15:BM15,3,0),0) -> 0 | BU41: =+IFERROR(VLOOKUP($BU$17,Sheet1!BN15:BQ15,3,0),0) -> 0 | BV41: =+IFERROR(VLOOKUP($BV$17,Sheet1!BR15:BU15,3,0),0) -> 0 | BW41: =+IFERROR(VLOOKUP($BW$17,Sheet1!BV15:BY15,3,0),0) -> 0 | BX41: =Sheet1!E15 -> WOOD | BY41: MD0100005 | BZ41: DRUM - 36 X 14 X 23 X 2 | CA41: 500 | CB41: 4858 | CC41: =SUMPRODUCT($P$18:$BW$18,P41:BW41)+CB41 -> 176143 | CD41: 0.01 | CE41: =CC41*CD41 -> 1761.43 | CF41: 0.15 | CG41: =CC41*CF41 -> 26421.45 | CH41: 0 | CI41: =CC41*CH41 -> 0 | CJ41: =CC41+CE41+CG41+CI41 -> 204325.88 | CK41: 0.02 | CL41: =CJ41*CK41 -> 4086.5176 | CM41: 0.01 | CN41: =CJ41*CM41 -> 2043.2588
A42: 9150 | B42: 24 | C42: =Sheet1!A22 -> ENQ-15115-22-23 | D42: 45658 | E42: =Sheet1!C22 -> FA0900132 | F42: =Sheet1!D22 -> 4 CORE X 16 SQ. MM. AL/ARD - WIRE (XLPE) | G42: =CJ42+CL42+CN42 -> 142452.42 | H42: =ROUNDUP(O72,0) -> 23334 | I42: =G42+H42 -> 165786.42 | J42: =Sheet1!CP22 -> 0.18 | K42: =I42*J42 -> 29841.556 | L42: =I42+K42 -> 195627.98 | M42: =Sheet1!CS22 -> 1.5 | N42: =Sheet1!CT22 -> KMS | O42: =L42*M42 -> 293441.96 | P42: =+IFERROR(VLOOKUP($P$17,Sheet1!J22:L22,3,0),0) -> 173 | Q42: =+IFERROR(VLOOKUP($Q$17,Sheet1!J22:L22,3,0),0) -> 0 | R42: =+IFERROR(VLOOKUP($R$17,Sheet1!J22:M22,3,0),0) -> 0 | S42: =+IFERROR(VLOOKUP($S$17,Sheet1!J22:M22,3,0),0) -> 0 | T42: =+IFERROR(VLOOKUP($T$17,Sheet1!J22:M22,3,0),0) -> 0 | U42: =+IFERROR(VLOOKUP($U$17,Sheet1!N22:Q22,3,0),0) -> 0 | V42: =+IFERROR(VLOOKUP($V$17,Sheet1!N22:Q22,3,0),0) -> 0 | W42: =+IFERROR(VLOOKUP($W$17,Sheet1!F22:I22,3,0),0) -> 0 | X42: =+IFERROR(VLOOKUP($X$17,Sheet1!F22:I22,3,0),0) -> 0 | Y42: =+IFERROR(VLOOKUP($Y$17,Sheet1!F22:I22,3,0),0) -> 0 | Z42: =+IFERROR(VLOOKUP($Z$17,Sheet1!F22:I22,3,0),0) -> 0 | AA42: =+IFERROR(VLOOKUP($AA$17,Sheet1!F22:I22,3,0),0) -> 0 | AB42: =+IFERROR(VLOOKUP($AB$17,Sheet1!F22:I22,3,0),0) -> 0 | AC42: =+IFERROR(VLOOKUP($AC$17,Sheet1!F22:I22,3,0),0) -> 0 | AD42: =+IFERROR(VLOOKUP($AD$17,Sheet1!F22:I22,3,0),0) -> 0 | AE42: =+IFERROR(VLOOKUP($AE$17,Sheet1!R22:U22,3,0),0) -> 0 | AF42: =+IFERROR(VLOOKUP($AF$17,Sheet1!R22:U22,2,0),0) -> 0 | AG42: =+IFERROR(VLOOKUP($AG$17,Sheet1!V22:Y22,3,0),0) -> 0 | AH42: 64 | AI42: =+IFERROR(VLOOKUP($AI$17,Sheet1!V22:Y22,3,0),0) -> 0 | AJ42: =+IFERROR(VLOOKUP($AJ$17,Sheet1!V22:Y22,3,0),0) -> 0 | AK42: =+IFERROR(VLOOKUP($AK$17,Sheet1!V22:Y22,3,0),0) -> 0 | AL42: =+IFERROR(VLOOKUP($AL$17,Sheet1!V22:Y22,3,0),0) -> 0 | AM42: =+IFERROR(VLOOKUP($AM$17,Sheet1!Z22:AB22,3,0),0) -> 0 | AN42: =+IFERROR(VLOOKUP($AN$17,Sheet1!AD22:AG22,3,0),0) -> 0 | AO42: =+IFERROR(VLOOKUP($AO$17,Sheet1!AD22:AG22,3,0),0) -> 0 | AP42: =+IFERROR(VLOOKUP($AP$17,Sheet1!AD22:AG22,3,0),0) -> 0 | AQ42: =+IFERROR(VLOOKUP($AQ$17,Sheet1!AD22:AG22,3,0),0) -> 0 | AR42: =+IFERROR(VLOOKUP($AR$17,Sheet1!AD22:AG22,3,0),0) -> 0 | AS42: =+IFERROR(VLOOKUP($AS$17,Sheet1!AD22:AG22,3,0),0) -> 40 | AT42: =+IFERROR(VLOOKUP($AT$17,Sheet1!AD22:AG22,3,0),0) -> 0 | AU42: =+IFERROR(VLOOKUP($AU$17,Sheet1!AH22:AK22,3,0),0) -> 0 | AV42: =+IFERROR(VLOOKUP($AV$17,Sheet1!AH22:AK22,3,0),0) -> 0 | AW42: =+IFERROR(VLOOKUP($AW$17,Sheet1!AH22:AK22,3,0),0) -> 0 | AX42: =+IFERROR(VLOOKUP($AX$17,Sheet1!AH22:AK22,3,0),0) -> 0 | AY42: =+IFERROR(VLOOKUP($AY$17,Sheet1!AH22:AK22,3,0),0) -> 0 | AZ42: =+IFERROR(VLOOKUP($AZ$17,Sheet1!AH22:AK22,3,0),0) -> 0 | BA42: =+IFERROR(VLOOKUP($BA$17,Sheet1!AH22:AK22,3,0),0) -> 0 | BB42: =+IFERROR(VLOOKUP($BB$17,Sheet1!AH22:AK22,3,0),0) -> 0 | BC42: 460 | BD42: =+IFERROR(VLOOKUP($BD$17,Sheet1!AH22:AK22,3,0),0) -> 0 | BE42: =+IFERROR(VLOOKUP($BE$17,Sheet1!AL22:AO22,3,0),0) -> 0 | BF42: =+IFERROR(VLOOKUP($BF$17,Sheet1!AL22:AO22,3,0),0) -> 0 | BG42: =+IFERROR(VLOOKUP($BG$17,Sheet1!AL22:AO22,3,0),0) -> 0 | BH42: 158 | BI42: =+IFERROR(VLOOKUP($BI$17,Sheet1!AL22:AO22,3,0),0) -> 0 | BJ42: =+IFERROR(VLOOKUP($BJ$17,Sheet1!AL22:AO22,3,0),0) -> 0 | BK42: =+IFERROR(VLOOKUP($BK$17,Sheet1!AL22:AO22,3,0),0) -> 0 | BL42: =+IFERROR(VLOOKUP($BL$17,Sheet1!AL22:AO22,3,0),0) -> 0 | BM42: =+IFERROR(VLOOKUP($BM$17,Sheet1!AL22:AO22,3,0),0) -> 0 | BN42: =+IFERROR(VLOOKUP($BN$17,Sheet1!AL22:AO22,3,0),0) -> 0 | BO42: =+IFERROR(VLOOKUP($BO$17,Sheet1!AP22:AS22,3,0),0) -> 0 | BP42: =+IFERROR(VLOOKUP($BP$17,Sheet1!AT22:AW22,3,0),0) -> 0 | BQ42: =+IFERROR(VLOOKUP($BQ$17,Sheet1!AX22:BA22,3,0),0) -> 0 | BR42: =+IFERROR(VLOOKUP($BR$17,Sheet1!BB22:BE22,3,0),0) -> 0 | BS42: =+IFERROR(VLOOKUP($BS$17,Sheet1!BF22:BI22,3,0),0) -> 0 | BT42: =+IFERROR(VLOOKUP($BT$17,Sheet1!BJ22:BM22,3,0),0) -> 0 | BU42: =+IFERROR(VLOOKUP($BU$17,Sheet1!BN22:BQ22,3,0),0) -> 0 | BV42: 14 | BW42: =+IFERROR(VLOOKUP($BW$17,Sheet1!BV22:BY22,3,0),0) -> 0 | BX42: =Sheet1!E22 -> WOOD | BY42: =Sheet1!CV22 -> MD0100090 | BZ42: =Sheet1!CW22 -> DRUM - 43 X 15 X 36 X 2.5 | CA42: =Sheet1!CX22 -> 1000 | CB42: =Sheet1!BZ22 -> 3881 | CC42: =SUMPRODUCT($P$18:$BW$18,P42:BW42)+CB42 -> 119227 | CD42: 0.01 | CE42: =CC42*CD42 -> 1192.27 | CF42: 0.15 | CG42: =CC42*CF42 -> 17884.05 | CH42: 0 | CI42: =CC42*CH42 -> 0 | CJ42: =CC42+CE42+CG42+CI42 -> 138303.32 | CK42: 0.02 | CL42: =CJ42*CK42 -> 2766.0664 | CM42: 0.01 | CN42: =CJ42*CM42 -> 1383.0332
B43: 25 | C43: =Sheet1!A13 -> ENQ-15115-22-23 | D43: 45658 | E43: =Sheet1!C13 -> FA0800001 | F43: =Sheet1!D13 -> 1 CORE X 16 SQ. MM. AL/ARD. (XLPE) | G43: =CJ43+CL43+CN43 -> 39479.776 | H43: =ROUNDUP(O73,0) -> 70000 | I43: =G43+H43 -> 109479.78 | J43: =Sheet1!CP13 -> 0.18 | K43: =I43*J43 -> 19706.36 | L43: =I43+K43 -> 129186.14 | M43: =Sheet1!CS13 -> 0.5 | N43: =Sheet1!CT13 -> KMS | O43: =L43*M43 -> 64593.068 | P43: 44 | Q43: =+IFERROR(VLOOKUP($Q$17,Sheet1!J13:L13,3,0),0) -> 0 | R43: =+IFERROR(VLOOKUP($R$17,Sheet1!J13:M13,3,0),0) -> 0 | S43: =+IFERROR(VLOOKUP($S$17,Sheet1!J13:M13,3,0),0) -> 0 | T43: =+IFERROR(VLOOKUP($T$17,Sheet1!J13:M13,3,0),0) -> 0 | U43: =+IFERROR(VLOOKUP($U$17,Sheet1!N13:Q13,3,0),0) -> 0 | V43: =+IFERROR(VLOOKUP($V$17,Sheet1!N13:Q13,3,0),0) -> 0 | W43: =+IFERROR(VLOOKUP($W$17,Sheet1!F13:I13,3,0),0) -> 0 | X43: =+IFERROR(VLOOKUP($X$17,Sheet1!F13:I13,3,0),0) -> 0 | Y43: =+IFERROR(VLOOKUP($Y$17,Sheet1!F13:I13,3,0),0) -> 0 | Z43: =+IFERROR(VLOOKUP($Z$17,Sheet1!F13:I13,3,0),0) -> 0 | AA43: =+IFERROR(VLOOKUP($AA$17,Sheet1!F13:I13,3,0),0) -> 0 | AB43: =+IFERROR(VLOOKUP($AB$17,Sheet1!F13:I13,3,0),0) -> 0 | AC43: =+IFERROR(VLOOKUP($AC$17,Sheet1!F13:I13,3,0),0) -> 0 | AD43: =+IFERROR(VLOOKUP($AD$17,Sheet1!F13:I13,3,0),0) -> 0 | AE43: =+IFERROR(VLOOKUP($AE$17,Sheet1!R13:U13,3,0),0) -> 0 | AF43: =+IFERROR(VLOOKUP($AF$17,Sheet1!R13:U13,2,0),0) -> 0 | AG43: =+IFERROR(VLOOKUP($AG$17,Sheet1!V13:Y13,3,0),0) -> 0 | AH43: 22 | AI43: =+IFERROR(VLOOKUP($AI$17,Sheet1!V13:Y13,3,0),0) -> 0 | AJ43: =+IFERROR(VLOOKUP($AJ$17,Sheet1!V13:Y13,3,0),0) -> 0 | AK43: =+IFERROR(VLOOKUP($AK$17,Sheet1!V13:Y13,3,0),0) -> 0 | AL43: =+IFERROR(VLOOKUP($AL$17,Sheet1!V13:Y13,3,0),0) -> 0 | AM43: =+IFERROR(VLOOKUP($AM$17,Sheet1!Z13:AB13,3,0),0) -> 0 | AN43: =+IFERROR(VLOOKUP($AN$17,Sheet1!AD13:AG13,3,0),0) -> 0 | AO43: =+IFERROR(VLOOKUP($AO$17,Sheet1!AD13:AG13,3,0),0) -> 0 | AP43: =+IFERROR(VLOOKUP($AP$17,Sheet1!AD13:AG13,3,0),0) -> 0 | AQ43: =+IFERROR(VLOOKUP($AQ$17,Sheet1!AD13:AG13,3,0),0) -> 0 | AR43: =+IFERROR(VLOOKUP($AR$17,Sheet1!AD13:AG13,3,0),0) -> 0 | AS43: =+IFERROR(VLOOKUP($AS$17,Sheet1!AD13:AG13,3,0),0) -> 0 | AT43: =+IFERROR(VLOOKUP($AT$17,Sheet1!AD13:AG13,3,0),0) -> 0 | AU43: =+IFERROR(VLOOKUP($AU$17,Sheet1!AH13:AK13,3,0),0) -> 0 | AV43: =+IFERROR(VLOOKUP($AV$17,Sheet1!AH13:AK13,3,0),0) -> 0 | AW43: =+IFERROR(VLOOKUP($AW$17,Sheet1!AH13:AK13,3,0),0) -> 0 | AX43: =+IFERROR(VLOOKUP($AX$17,Sheet1!AH13:AK13,3,0),0) -> 0 | AY43: =+IFERROR(VLOOKUP($AY$17,Sheet1!AH13:AK13,3,0),0) -> 0 | AZ43: =+IFERROR(VLOOKUP($AZ$17,Sheet1!AH13:AK13,3,0),0) -> 0 | BA43: =+IFERROR(VLOOKUP($BA$17,Sheet1!AH13:AK13,3,0),0) -> 0 | BB43: =+IFERROR(VLOOKUP($BB$17,Sheet1!AH13:AK13,3,0),0) -> 0 | BC43: 62 | BD43: =+IFERROR(VLOOKUP($BD$17,Sheet1!AH13:AK13,3,0),0) -> 0 | BE43: =+IFERROR(VLOOKUP($BE$17,Sheet1!AL13:AO13,3,0),0) -> 0 | BF43: =+IFERROR(VLOOKUP($BF$17,Sheet1!AL13:AO13,3,0),0) -> 0 | BG43: =+IFERROR(VLOOKUP($BG$17,Sheet1!AL13:AO13,3,0),0) -> 0 | BH43: 88 | BI43: =+IFERROR(VLOOKUP($BI$17,Sheet1!AL13:AO13,3,0),0) -> 0 | BJ43: =+IFERROR(VLOOKUP($BJ$17,Sheet1!AL13:AO13,3,0),0) -> 0 | BK43: =+IFERROR(VLOOKUP($BK$17,Sheet1!AL13:AO13,3,0),0) -> 0 | BL43: =+IFERROR(VLOOKUP($BL$17,Sheet1!AL13:AO13,3,0),0) -> 0 | BM43: =+IFERROR(VLOOKUP($BM$17,Sheet1!AL13:AO13,3,0),0) -> 0 | BN43: =+IFERROR(VLOOKUP($BN$17,Sheet1!AL13:AO13,3,0),0) -> 0 | BO43: =+IFERROR(VLOOKUP($BO$17,Sheet1!AP13:AS13,3,0),0) -> 0 | BP43: =+IFERROR(VLOOKUP($BP$17,Sheet1!AT13:AW13,3,0),0) -> 0 | BQ43: =+IFERROR(VLOOKUP($BQ$17,Sheet1!AX13:BA13,3,0),0) -> 0 | BR43: =+IFERROR(VLOOKUP($BR$17,Sheet1!BB13:BE13,3,0),0) -> 0 | BS43: =+IFERROR(VLOOKUP($BS$17,Sheet1!BF13:BI13,3,0),0) -> 0 | BT43: =+IFERROR(VLOOKUP($BT$17,Sheet1!BJ13:BM13,3,0),0) -> 0 | BU43: =+IFERROR(VLOOKUP($BU$17,Sheet1!BN13:BQ13,3,0),0) -> 0 | BV43: 8 | BW43: =+IFERROR(VLOOKUP($BW$17,Sheet1!BV13:BY13,3,0),0) -> 0 | BX43: WOOD | BY43: MD0100005 | BZ43: DRUM - 36 X 14 X 23 X 2 | CA43: =Sheet1!CX13 -> 1000 | CB43: 2429 | CC43: =SUMPRODUCT($P$18:$BW$18,P43:BW43)+CB43 -> 33043 | CD43: 0.01 | CE43: =CC43*CD43 -> 330.43 | CF43: 0.15 | CG43: =CC43*CF43 -> 4956.45 | CH43: 0 | CI43: =CC43*CH43 -> 0 | CJ43: =CC43+CE43+CG43+CI43 -> 38329.88 | CK43: 0.02 | CL43: =CJ43*CK43 -> 766.5976 | CM43: 0.01 | CN43: =CJ43*CM43 -> 383.2988
A44: 9150 | B44: 26 | C44: =Sheet1!A23 -> ENQ-15115-22-23 | D44: 45658 | E44: =Sheet1!C23 -> FA0900133 | F44: =Sheet1!D23 -> 2 CORE X 16 SQ. MM. AL/ARD - WIRE (XLPE) | G44: =CJ44+CL44+CN44 -> 118456.06 | H44: =ROUNDUP(O74,0) -> 70000 | I44: =G44+H44 -> 188456.06 | J44: =Sheet1!CP23 -> 0.18 | K44: =I44*J44 -> 33922.09 | L44: =I44+K44 -> 222378.15 | M44: =Sheet1!CS23 -> 0.5 | N44: =Sheet1!CT23 -> KMS | O44: =L44*M44 -> 111189.07 | P44: =+IFERROR(VLOOKUP($P$17,Sheet1!J23:L23,3,0),0) -> 86 | Q44: =+IFERROR(VLOOKUP($Q$17,Sheet1!J23:L23,3,0),0) -> 0 | R44: =+IFERROR(VLOOKUP($R$17,Sheet1!J23:M23,3,0),0) -> 0 | S44: =+IFERROR(VLOOKUP($S$17,Sheet1!J23:M23,3,0),0) -> 0 | T44: =+IFERROR(VLOOKUP($T$17,Sheet1!J23:M23,3,0),0) -> 0 | U44: =+IFERROR(VLOOKUP($U$17,Sheet1!N23:Q23,3,0),0) -> 0 | V44: =+IFERROR(VLOOKUP($V$17,Sheet1!N23:Q23,3,0),0) -> 0 | W44: =+IFERROR(VLOOKUP($W$17,Sheet1!F23:I23,3,0),0) -> 0 | X44: =+IFERROR(VLOOKUP($X$17,Sheet1!F23:I23,3,0),0) -> 0 | Y44: =+IFERROR(VLOOKUP($Y$17,Sheet1!F23:I23,3,0),0) -> 0 | Z44: =+IFERROR(VLOOKUP($Z$17,Sheet1!F23:I23,3,0),0) -> 0 | AA44: =+IFERROR(VLOOKUP($AA$17,Sheet1!F23:I23,3,0),0) -> 0 | AB44: =+IFERROR(VLOOKUP($AB$17,Sheet1!F23:I23,3,0),0) -> 0 | AC44: =+IFERROR(VLOOKUP($AC$17,Sheet1!F23:I23,3,0),0) -> 0 | AD44: =+IFERROR(VLOOKUP($AD$17,Sheet1!F23:I23,3,0),0) -> 0 | AE44: =+IFERROR(VLOOKUP($AE$17,Sheet1!R23:U23,3,0),0) -> 0 | AF44: =+IFERROR(VLOOKUP($AF$17,Sheet1!R23:U23,2,0),0) -> 0 | AG44: =+IFERROR(VLOOKUP($AG$17,Sheet1!V23:Y23,3,0),0) -> 0 | AH44: 32 | AI44: =+IFERROR(VLOOKUP($AI$17,Sheet1!V23:Y23,3,0),0) -> 0 | AJ44: =+IFERROR(VLOOKUP($AJ$17,Sheet1!V23:Y23,3,0),0) -> 0 | AK44: =+IFERROR(VLOOKUP($AK$17,Sheet1!V23:Y23,3,0),0) -> 0 | AL44: =+IFERROR(VLOOKUP($AL$17,Sheet1!V23:Y23,3,0),0) -> 0 | AM44: =+IFERROR(VLOOKUP($AM$17,Sheet1!Z23:AB23,3,0),0) -> 0 | AN44: =+IFERROR(VLOOKUP($AN$17,Sheet1!AD23:AG23,3,0),0) -> 0 | AO44: =+IFERROR(VLOOKUP($AO$17,Sheet1!AD23:AG23,3,0),0) -> 0 | AP44: =+IFERROR(VLOOKUP($AP$17,Sheet1!AD23:AG23,3,0),0) -> 0 | AQ44: =+IFERROR(VLOOKUP($AQ$17,Sheet1!AD23:AG23,3,0),0) -> 0 | AR44: =+IFERROR(VLOOKUP($AR$17,Sheet1!AD23:AG23,3,0),0) -> 0 | AS44: 104 | AT44: 0 | AU44: =+IFERROR(VLOOKUP($AU$17,Sheet1!AH23:AK23,3,0),0) -> 0 | AV44: =+IFERROR(VLOOKUP($AV$17,Sheet1!AH23:AK23,3,0),0) -> 0 | AW44: =+IFERROR(VLOOKUP($AW$17,Sheet1!AH23:AK23,3,0),0) -> 0 | AX44: =+IFERROR(VLOOKUP($AX$17,Sheet1!AH23:AK23,3,0),0) -> 0 | AY44: =+IFERROR(VLOOKUP($AY$17,Sheet1!AH23:AK23,3,0),0) -> 0 | AZ44: =+IFERROR(VLOOKUP($AZ$17,Sheet1!AH23:AK23,3,0),0) -> 0 | BA44: =+IFERROR(VLOOKUP($BA$17,Sheet1!AH23:AK23,3,0),0) -> 0 | BB44: =+IFERROR(VLOOKUP($BB$17,Sheet1!AH23:AK23,3,0),0) -> 0 | BC44: 487 | BD44: =+IFERROR(VLOOKUP($BD$17,Sheet1!AH23:AK23,3,0),0) -> 0 | BE44: =+IFERROR(VLOOKUP($BE$17,Sheet1!AL23:AO23,3,0),0) -> 0 | BF44: =+IFERROR(VLOOKUP($BF$17,Sheet1!AL23:AO23,3,0),0) -> 0 | BG44: =+IFERROR(VLOOKUP($BG$17,Sheet1!AL23:AO23,3,0),0) -> 0 | BH44: 150 | BI44: =+IFERROR(VLOOKUP($BI$17,Sheet1!AL23:AO23,3,0),0) -> 0 | BJ44: =+IFERROR(VLOOKUP($BJ$17,Sheet1!AL23:AO23,3,0),0) -> 0 | BK44: =+IFERROR(VLOOKUP($BK$17,Sheet1!AL23:AO23,3,0),0) -> 0 | BL44: =+IFERROR(VLOOKUP($BL$17,Sheet1!AL23:AO23,3,0),0) -> 0 | BM44: =+IFERROR(VLOOKUP($BM$17,Sheet1!AL23:AO23,3,0),0) -> 0 | BN44: =+IFERROR(VLOOKUP($BN$17,Sheet1!AL23:AO23,3,0),0) -> 0 | BO44: =+IFERROR(VLOOKUP($BO$17,Sheet1!AP23:AS23,3,0),0) -> 0 | BP44: =+IFERROR(VLOOKUP($BP$17,Sheet1!AT23:AW23,3,0),0) -> 0 | BQ44: =+IFERROR(VLOOKUP($BQ$17,Sheet1!AX23:BA23,3,0),0) -> 0 | BR44: =+IFERROR(VLOOKUP($BR$17,Sheet1!BB23:BE23,3,0),0) -> 0 | BS44: =+IFERROR(VLOOKUP($BS$17,Sheet1!BF23:BI23,3,0),0) -> 0 | BT44: =+IFERROR(VLOOKUP($BT$17,Sheet1!BJ23:BM23,3,0),0) -> 0 | BU44: =+IFERROR(VLOOKUP($BU$17,Sheet1!BN23:BQ23,3,0),0) -> 0 | BV44: 13 | BW44: =+IFERROR(VLOOKUP($BW$17,Sheet1!BV23:BY23,3,0),0) -> 0 | BX44: =Sheet1!E23 -> WOOD | BY44: =Sheet1!CV23 -> MD0100064 | BZ44: =Sheet1!CW23 -> DRUM - 42 X 15 X 32 X 2 (LOMBU) | CA44: =Sheet1!CX23 -> 1000 | CB44: =Sheet1!BZ23 -> 4593 | CC44: =SUMPRODUCT($P$18:$BW$18,P44:BW44)+CB44 -> 99143 | CD44: 0.01 | CE44: =CC44*CD44 -> 991.43 | CF44: 0.15 | CG44: =CC44*CF44 -> 14871.45 | CH44: 0 | CI44: =CC44*CH44 -> 0 | CJ44: =CC44+CE44+CG44+CI44 -> 115005.88 | CK44: 0.02 | CL44: =CJ44*CK44 -> 2300.1176 | CM44: 0.01 | CN44: =CJ44*CM44 -> 1150.0588
A45: 10761 | B45: 27 | C45: =Sheet1!A24 -> ENQ-15115-22-23 | D45: 45658 | E45: =Sheet1!C24 -> FA0900160 | F45: =Sheet1!D24 -> 2 CORE X 50 SQ. MM. AL/ARD - WIRE (XLPE) | G45: =CJ45+CL45+CN45 -> 240884.82 | H45: =ROUNDUP(O75,0) -> 70000 | I45: =G45+H45 -> 310884.82 | J45: =Sheet1!CP24 -> 0.18 | K45: =I45*J45 -> 55959.268 | L45: =I45+K45 -> 366844.09 | M45: =Sheet1!CS24 -> 0.5 | N45: =Sheet1!CT24 -> KMS | O45: =L45*M45 -> 183422.05 | P45: =+IFERROR(VLOOKUP($P$17,Sheet1!J24:L24,3,0),0) -> 270 | Q45: =+IFERROR(VLOOKUP($Q$17,Sheet1!J24:L24,3,0),0) -> 0 | R45: =+IFERROR(VLOOKUP($R$17,Sheet1!J24:M24,3,0),0) -> 0 | S45: =+IFERROR(VLOOKUP($S$17,Sheet1!J24:M24,3,0),0) -> 0 | T45: =+IFERROR(VLOOKUP($T$17,Sheet1!J24:M24,3,0),0) -> 0 | U45: =+IFERROR(VLOOKUP($U$17,Sheet1!N24:Q24,3,0),0) -> 0 | V45: =+IFERROR(VLOOKUP($V$17,Sheet1!N24:Q24,3,0),0) -> 0 | W45: =+IFERROR(VLOOKUP($W$17,Sheet1!F24:I24,3,0),0) -> 0 | X45: =+IFERROR(VLOOKUP($X$17,Sheet1!F24:I24,3,0),0) -> 0 | Y45: =+IFERROR(VLOOKUP($Y$17,Sheet1!F24:I24,3,0),0) -> 0 | Z45: =+IFERROR(VLOOKUP($Z$17,Sheet1!F24:I24,3,0),0) -> 0 | AA45: =+IFERROR(VLOOKUP($AA$17,Sheet1!F24:I24,3,0),0) -> 0 | AB45: =+IFERROR(VLOOKUP($AB$17,Sheet1!F24:I24,3,0),0) -> 0 | AC45: =+IFERROR(VLOOKUP($AC$17,Sheet1!F24:I24,3,0),0) -> 0 | AD45: =+IFERROR(VLOOKUP($AD$17,Sheet1!F24:I24,3,0),0) -> 0 | AE45: =+IFERROR(VLOOKUP($AE$17,Sheet1!R24:U24,3,0),0) -> 0 | AF45: =+IFERROR(VLOOKUP($AF$17,Sheet1!R24:U24,2,0),0) -> 0 | AG45: =+IFERROR(VLOOKUP($AG$17,Sheet1!V24:Y24,3,0),0) -> 0 | AH45: 64 | AI45: =+IFERROR(VLOOKUP($AI$17,Sheet1!V24:Y24,3,0),0) -> 0 | AJ45: =+IFERROR(VLOOKUP($AJ$17,Sheet1!V24:Y24,3,0),0) -> 0 | AK45: =+IFERROR(VLOOKUP($AK$17,Sheet1!V24:Y24,3,0),0) -> 0 | AL45: =+IFERROR(VLOOKUP($AL$17,Sheet1!V24:Y24,3,0),0) -> 0 | AM45: =+IFERROR(VLOOKUP($AM$17,Sheet1!Z24:AB24,3,0),0) -> 0 | AN45: =+IFERROR(VLOOKUP($AN$17,Sheet1!AD24:AG24,3,0),0) -> 0 | AO45: =+IFERROR(VLOOKUP($AO$17,Sheet1!AD24:AG24,3,0),0) -> 0 | AP45: =+IFERROR(VLOOKUP($AP$17,Sheet1!AD24:AG24,3,0),0) -> 0 | AQ45: =+IFERROR(VLOOKUP($AQ$17,Sheet1!AD24:AG24,3,0),0) -> 0 | AR45: =+IFERROR(VLOOKUP($AR$17,Sheet1!AD24:AG24,3,0),0) -> 0 | AS45: 80 | AT45: 0 | AU45: =+IFERROR(VLOOKUP($AU$17,Sheet1!AH24:AK24,3,0),0) -> 0 | AV45: =+IFERROR(VLOOKUP($AV$17,Sheet1!AH24:AK24,3,0),0) -> 0 | AW45: =+IFERROR(VLOOKUP($AW$17,Sheet1!AH24:AK24,3,0),0) -> 0 | AX45: =+IFERROR(VLOOKUP($AX$17,Sheet1!AH24:AK24,3,0),0) -> 0 | AY45: =+IFERROR(VLOOKUP($AY$17,Sheet1!AH24:AK24,3,0),0) -> 0 | AZ45: =+IFERROR(VLOOKUP($AZ$17,Sheet1!AH24:AK24,3,0),0) -> 0 | BA45: =+IFERROR(VLOOKUP($BA$17,Sheet1!AH24:AK24,3,0),0) -> 0 | BB45: =+IFERROR(VLOOKUP($BB$17,Sheet1!AH24:AK24,3,0),0) -> 0 | BC45: 1018 | BD45: =+IFERROR(VLOOKUP($BD$17,Sheet1!AH24:AK24,3,0),0) -> 0 | BE45: =+IFERROR(VLOOKUP($BE$17,Sheet1!AL24:AO24,3,0),0) -> 0 | BF45: =+IFERROR(VLOOKUP($BF$17,Sheet1!AL24:AO24,3,0),0) -> 0 | BG45: =+IFERROR(VLOOKUP($BG$17,Sheet1!AL24:AO24,3,0),0) -> 0 | BH45: 200 | BI45: =+IFERROR(VLOOKUP($BI$17,Sheet1!AL24:AO24,3,0),0) -> 0 | BJ45: =+IFERROR(VLOOKUP($BJ$17,Sheet1!AL24:AO24,3,0),0) -> 0 | BK45: =+IFERROR(VLOOKUP($BK$17,Sheet1!AL24:AO24,3,0),0) -> 0 | BL45: =+IFERROR(VLOOKUP($BL$17,Sheet1!AL24:AO24,3,0),0) -> 0 | BM45: =+IFERROR(VLOOKUP($BM$17,Sheet1!AL24:AO24,3,0),0) -> 0 | BN45: =+IFERROR(VLOOKUP($BN$17,Sheet1!AL24:AO24,3,0),0) -> 0 | BO45: =+IFERROR(VLOOKUP($BO$17,Sheet1!AP24:AS24,3,0),0) -> 0 | BP45: =+IFERROR(VLOOKUP($BP$17,Sheet1!AT24:AW24,3,0),0) -> 0 | BQ45: =+IFERROR(VLOOKUP($BQ$17,Sheet1!AX24:BA24,3,0),0) -> 0 | BR45: =+IFERROR(VLOOKUP($BR$17,Sheet1!BB24:BE24,3,0),0) -> 0 | BS45: =+IFERROR(VLOOKUP($BS$17,Sheet1!BF24:BI24,3,0),0) -> 0 | BT45: =+IFERROR(VLOOKUP($BT$17,Sheet1!BJ24:BM24,3,0),0) -> 0 | BU45: =+IFERROR(VLOOKUP($BU$17,Sheet1!BN24:BQ24,3,0),0) -> 0 | BV45: 18 | BW45: =+IFERROR(VLOOKUP($BW$17,Sheet1!BV24:BY24,3,0),0) -> 0 | BX45: =Sheet1!E24 -> WOOD | BY45: =Sheet1!CV24 -> MD0100013 | BZ45: =Sheet1!CW24 -> DRUM - 48 X 14 X 36 X 2.25 | CA45: =Sheet1!CX24 -> 1000 | CB45: =Sheet1!BZ24 -> 4139 | CC45: =SUMPRODUCT($P$18:$BW$18,P45:BW45)+CB45 -> 201611 | CD45: 0.01 | CE45: =CC45*CD45 -> 2016.11 | CF45: 0.15 | CG45: =CC45*CF45 -> 30241.65 | CH45: 0 | CI45: =CC45*CH45 -> 0 | CJ45: =CC45+CE45+CG45+CI45 -> 233868.76 | CK45: 0.02 | CL45: =CJ45*CK45 -> 4677.3752 | CM45: 0.01 | CN45: =CJ45*CM45 -> 2338.6876
O46: =SUM(O19:O45) -> 9.8945496e+08 | CH46: 0
G48: Order Quantity | H48: Stnd Length | I48: Truck type | J48: Fare of one truck | K48: No of Drum in one truck | L48: Total length in one Truck | M48: No of Truck | N48: Total Freight | O48: Freight per KM | R48: CABLE WEIGHT KG/KM | AH48: DRUM WEIGHT | AK48: CABLE+DRUM WEIGHT | AM48: WEIGHT OF TRUCK
D49: =BY19 -> MD0100066 | E49: =E19 -> FA0600013 | F49: =F19 -> 1 CORE X 95 SQ. MM. AL/UNARD(XLPE ) | G49: =M19 -> 79.532 | H49: =CA19/1000 -> 1 | I49: 16 MT | J49: 35000 | K49: 31 | L49: =H49*K49 -> 31 | M49: =ROUNDUP((G49/L49),0) -> 3 | N49: =O49*G49 -> 105000 | O49: =(J49*M49)/G49 -> 1320.2233 | P49: =BY19 -> MD0100066 | R49: =SUM(P19:BV19) -> 440 | AH49: 75 | AK49: =((R49*H49)+AH49) -> 515 | AM49: =AK49*K49 -> 15965
D50: =BY20 -> MD0100085 | E50: =E20 -> FA0600019 | F50: =F20 -> 1 CORE X 150 SQ. MM. AL/UNARD. (XLPE) | G50: =M20 -> 57.308 | H50: =CA20/1000 -> 1 | I50: 16 MT | J50: 35000 | K50: 20 | L50: =H50*K50 -> 20 | M50: =ROUNDUP((G50/L50),0) -> 3 | N50: =O50*G50 -> 105000 | O50: =(J50*M50)/G50 -> 1832.2049 | P50: =BY20 -> MD0100085 | R50: =SUM(P20:BV20) -> 686 | AH50: 100 | AK50: =((R50*H50)+AH50) -> 786 | AM50: =AK50*K50 -> 15720
D51: =BY21 -> MD0100090 | E51: =E21 -> FA0600021 | F51: =F21 -> 1 CORE X 185 SQ. MM. AL/UNARD. (XLPE) | G51: =M21 -> 35.75 | H51: =CA21/1000 -> 1 | I51: 16 MT | J51: 35000 | K51: 17 | L51: =H51*K51 -> 17 | M51: =ROUNDUP((G51/L51),0) -> 3 | N51: =O51*G51 -> 105000 | O51: =(J51*M51)/G51 -> 2937.0629 | P51: =BY21 -> MD0100090 | R51: =SUM(P21:BV21) -> 828 | AH51: 100 | AK51: =((R51*H51)+AH51) -> 928 | AM51: =AK51*K51 -> 15776
D52: =BY22 -> MD0100017 | E52: =E22 -> FA0600020 | F52: =F22 -> 1 CORE X 300 SQ. MM. AL/UNARD. (XLPE) | G52: =M22 -> 81.552 | H52: =CA22/1000 -> 1 | I52: 16 MT | J52: 35000 | K52: 8 | L52: =H52*K52 -> 8 | M52: =ROUNDUP((G52/L52),0) -> 11 | N52: =O52*G52 -> 385000 | O52: =(J52*M52)/G52 -> 4720.9143 | P52: =BY22 -> MD0100017 | R52: =SUM(P22:BV22) -> 1225 | AH52: 150 | AK52: =((R52*H52)+AH52) -> 1375 | AM52: =AK52*K52 -> 11000
C53: FREIGHT CHARGES | D53: =BY23 -> MD0100062 | E53: =E23 -> FA0600032 | F53: =F23 -> 1 CORE X 630 SQ. MM. ALU/UNARD (XLPE) | G53: =M23 -> 38.704 | H53: =CA23/1000 -> 1 | I53: 16 MT | J53: 35000 | K53: 5 | L53: =H53*K53 -> 5 | M53: =ROUNDUP((G53/L53),0) -> 8 | N53: =O53*G53 -> 280000 | O53: =(J53*M53)/G53 -> 7234.3944 | P53: =BY23 -> MD0100062 | R53: =SUM(P23:BV23) -> 2391 | AH53: 365 | AK53: =((R53*H53)+AH53) -> 2756 | AM53: =AK53*K53 -> 13780
C54: 25 MT TRAILER | D54: =BY24 -> MD0100068 | E54: =E24 -> FA0900116 | F54: =F24 -> 4 CORE X 50 SQ. MM. AL/ARD - WIRE (XLPE) | G54: =M24 -> 26.605 | H54: =CA24/1000 -> 1 | I54: 16 MT | J54: 35000 | K54: 7 | L54: =H54*K54 -> 7 | M54: =ROUNDUP((G54/L54),0) -> 4 | N54: =O54*G54 -> 140000 | O54: =(J54*M54)/G54 -> 5262.1688 | P54: =BY24 -> MD0100068 | R54: =SUM(P24:BV24) -> 2038 | AH54: 180 | AK54: =((R54*H54)+AH54) -> 2218 | AM54: =AK54*K54 -> 15526
B55: BHUBANESWAR | C55: 24000 | D55: =BY25 -> MD0100061 | E55: =E25 -> FA1100094 | F55: =F25 -> 4 CORE X 95 SQ. MM. ALU/ARD - WIRE (XLPE) | G55: =M25 -> 17.586 | H55: =CA25/1000 -> 0.5 | I55: 16 MT | J55: 35000 | K55: 9 | L55: =H55*K55 -> 4.5 | M55: =ROUNDUP((G55/L55),0) -> 4 | N55: =O55*G55 -> 140000 | O55: =(J55*M55)/G55 -> 7960.878 | P55: =BY25 -> MD0100061 | R55: =SUM(P25:BV25) -> 3033 | AH55: 190 | AK55: =((R55*H55)+AH55) -> 1706.5 | AM55: =AK55*K55 -> 15358.5
B56: BALIA | C56: 55000 | D56: =BY26 -> MD0100024 | E56: =E26 -> FA1100177 | F56: =F26 -> 4 CORE X 150 SQ. MM. AL/ARD - WIRE (XLPE) | G56: =M26 -> 21.866 | H56: =CA26/1000 -> 0.5 | I56: 16 MT | J56: 35000 | K56: 5 | L56: =H56*K56 -> 2.5 | M56: =ROUNDUP((G56/L56),0) -> 9 | N56: =O56*G56 -> 315000 | O56: =(J56*M56)/G56 -> 14405.927 | P56: =BY26 -> MD0100024 | R56: =SUM(P26:BV26) -> 4939 | AH56: 315 | AK56: =((R56*H56)+AH56) -> 2784.5 | AM56: =AK56*K56 -> 13922.5
B57: BERHAMPUR | C57: 28000 | D57: =BY27 -> SP0400123 | E57: =E27 -> FA1100091 | F57: =F27 -> 4 CORE X 240 SQ. MM. AL/ARD - WIRE (XLPE) | G57: =M27 -> 7 | H57: =CA27/1000 -> 0.5 | I57: 16 MT | J57: 35000 | K57: 3 | L57: =H57*K57 -> 1.5 | M57: =ROUNDUP((G57/L57),0) -> 5 | N57: =O57*G57 -> 175000 | O57: =(J57*M57)/G57 -> 25000 | P57: =BY27 -> SP0400123 | R57: =SUM(P27:BV27) -> 6837 | AH57: 280 | AK57: =((R57*H57)+AH57) -> 3698.5 | AM57: =AK57*K57 -> 11095.5
B58: BURLA | C58: 30000 | D58: =BY28 -> SP0400139 | E58: =E28 -> FA1100176 | F58: =F28 -> 4 CORE X 300 SQ. MM. AL/ARD - WIRE (XLPE) | G58: =M28 -> 34.5 | H58: =CA28/1000 -> 0.5 | I58: 16 MT | J58: 35000 | K58: 3 | L58: =H58*K58 -> 1.5 | M58: =ROUNDUP((G58/L58),0) -> 23 | N58: =O58*G58 -> 805000 | O58: =(J58*M58)/G58 -> 23333.333 | P58: =BY28 -> SP0400139 | R58: =SUM(P28:BV28) -> 8134 | AH58: 320 | AK58: =((R58*H58)+AH58) -> 4387 | AM58: =AK58*K58 -> 13161
B59: AVERAGE = | C59: =AVERAGE(C55:C58) -> 34250 | D59: =BY29 -> MD0100005 | E59: =E29 -> FA0500017 | F59: =F29 -> 1 CORE X 50 SQ. MM. AL/UNARD. (XLPE) | G59: =M29 -> 24.06 | H59: =CA29/1000 -> 1 | I59: 16 MT | J59: 35000 | K59: 40 | L59: =H59*K59 -> 40 | M59: =ROUNDUP((G59/L59),0) -> 1 | N59: =O59*G59 -> 35000 | O59: =(J59*M59)/G59 -> 1454.6966 | P59: =BY29 -> MD0100005 | R59: =SUM(P29:BV29) -> 282 | AH59: 65 | AK59: =((R59*H59)+AH59) -> 347 | AM59: =AK59*K59 -> 13880
D60: =BY30 -> MD0100090 | E60: =E30 -> FA0900111 | F60: =F30 -> 4 CORE X 25 SQ. MM. ALU/ARD - WIRE (XLPE) | G60: =M30 -> 146.208 | H60: =CA30/1000 -> 1 | I60: 16 MT | J60: 35000 | K60: 11 | L60: =H60*K60 -> 11 | M60: =ROUNDUP((G60/L60),0) -> 14 | N60: =O60*G60 -> 490000 | O60: =(J60*M60)/G60 -> 3351.3898 | P60: =BY30 -> MD0100090 | R60: =SUM(P30:BV30) -> 1251 | AH60: 100 | AK60: =((R60*H60)+AH60) -> 1351 | AM60: =AK60*K60 -> 14861
D61: =BY31 -> MD0100013 | E61: =E31 -> FA0900117 | F61: =F31 -> 4 CORE X 35 SQ. MM. AL/ARD - WIRE (XLPE) | G61: =M31 -> 88.208 | H61: =CA31/1000 -> 1 | I61: 16 MT | J61: 35000 | K61: 9 | L61: =H61*K61 -> 9 | M61: =ROUNDUP((G61/L61),0) -> 10 | N61: =O61*G61 -> 350000 | O61: =(J61*M61)/G61 -> 3967.8941 | P61: =BY31 -> MD0100013 | R61: =SUM(P31:BV31) -> 1525 | AH61: 125 | AK61: =((R61*H61)+AH61) -> 1650 | AM61: =AK61*K61 -> 14850
D62: =BY32 -> MD0100066 | E62: =E32 -> FA0900041 | F62: =F32 -> 2 CORE X 4 SQ. MM. AL/ARD - WIRE (XLPE) | G62: =M32 -> 2077.047 | H62: =CA32/1000 -> 1 | I62: 16 MT | J62: 35000 | K62: 28 | L62: =H62*K62 -> 28 | M62: =ROUNDUP((G62/L62),0) -> 75 | N62: =O62*G62 -> 2625000 | O62: =(J62*M62)/G62 -> 1263.8135 | P62: =BY32 -> MD0100066 | R62: =SUM(P32:BV32) -> 477 | AH62: 75 | AK62: =((R62*H62)+AH62) -> 552 | AM62: =AK62*K62 -> 15456
D63: =BY33 -> MD0100066 | E63: =E33 -> FA0900020 | F63: =F33 -> 2 CORE X 6 SQ. MM. AL/ARD - WIRE (XLPE) | G63: =M33 -> 5000 | H63: =CA33/1000 -> 1 | I63: 16 MT | J63: 35000 | K63: 26 | L63: =H63*K63 -> 26 | M63: =ROUNDUP((G63/L63),0) -> 193 | N63: =O63*G63 -> 6755000 | O63: =(J63*M63)/G63 -> 1351 | P63: =BY33 -> MD0100066 | R63: =SUM(P33:BV33) -> 528 | AH63: 75 | AK63: =((R63*H63)+AH63) -> 603 | AM63: =AK63*K63 -> 15678
D64: =BY34 -> MD0100075 | E64: =E34 -> FA0900042 | F64: =F34 -> 2 CORE X 10 SQ. MM. ALU/ARD - WIRE (XLPE) | G64: =M34 -> 130.04 | H64: =CA34/1000 -> 1 | I64: 16 MT | J64: 35000 | K64: 21 | L64: =H64*K64 -> 21 | M64: =ROUNDUP((G64/L64),0) -> 7 | N64: =O64*G64 -> 245000 | O64: =(J64*M64)/G64 -> 1884.0357 | P64: =BY34 -> MD0100075 | R64: =SUM(P34:BV34) -> 674 | AH64: 75 | AK64: =((R64*H64)+AH64) -> 749 | AM64: =AK64*K64 -> 15729
D65: =BY35 -> MD0100064 | E65: =E35 -> FA0900112 | F65: =F35 -> 4 CORE X 10 SQ. MM. AL/ARD - WIRE (XLPE) | G65: =M35 -> 151.832 | H65: =CA35/1000 -> 1 | I65: 16 MT | J65: 35000 | K65: 18 | L65: =H65*K65 -> 18 | M65: =ROUNDUP((G65/L65),0) -> 9 | N65: =O65*G65 -> 315000 | O65: =(J65*M65)/G65 -> 2074.6615 | P65: =BY35 -> MD0100064 | R65: =SUM(P35:BV35) -> 734.5 | AH65: 75 | AK65: =((R65*H65)+AH65) -> 809.5 | AM65: =AK65*K65 -> 14571
D66: =BY36 -> MD0100005 | E66: =E36 -> FA0200011 | F66: =F36 -> 4 CORE X 2.5 SQ. MM. CU/ARD - WIRE (PVC) | G66: =M36 -> 61.67 | H66: =CA36/1000 -> 0.5 | I66: 16 MT | J66: 35000 | K66: 36 | L66: =H66*K66 -> 18 | M66: =ROUNDUP((G66/L66),0) -> 4 | N66: =O66*G66 -> 140000 | O66: =(J66*M66)/G66 -> 2270.1476 | P66: =BY36 -> MD0100005 | R66: =SUM(P36:BV36) -> 564 | AH66: 65 | AK66: =((R66*H66)+AH66) -> 347 | AM66: =AK66*K66 -> 12492
D67: =BY37 -> MD0100005 | E67: =E37 -> FA0200018 | F67: =F37 -> 7 CORE X 2.5 SQ. MM. CU/ARD - WIRE (PVC) | G67: =M37 -> 98.845 | H67: =CA37/1000 -> 0.5 | I67: 16 MT | J67: 35000 | K67: 36 | L67: =H67*K67 -> 18 | M67: =ROUNDUP((G67/L67),0) -> 6 | N67: =O67*G67 -> 210000 | O67: =(J67*M67)/G67 -> 2124.5384 | P67: =BY37 -> MD0100005 | R67: =SUM(P37:BV37) -> 755 | AH67: 65 | AK67: =((R67*H67)+AH67) -> 442.5 | AM67: =AK67*K67 -> 15930
D68: =BY38 -> MD0100066 | E68: =E38 -> FA0200002 | F68: =F38 -> 10 CORE X 2.5 SQ. MM. CU/ARD - WIRE (PVC) | G68: =M38 -> 78.965 | H68: =CA38/1000 -> 0.5 | I68: 16 MT | J68: 35000 | K68: 26 | L68: =H68*K68 -> 13 | M68: =ROUNDUP((G68/L68),0) -> 7 | N68: =O68*G68 -> 245000 | O68: =(J68*M68)/G68 -> 3102.6404 | P68: =BY38 -> MD0100066 | R68: =SUM(P38:BV38) -> 1080 | AH68: 75 | AK68: =((R68*H68)+AH68) -> 615 | AM68: =AK68*K68 -> 15990
D69: =BY39 -> MD0100066 | E69: =E39 -> FA0200003 | F69: =F39 -> 12 CORE X 2.5 SQ. MM. CU/ARD - WIRE (PVC) | G69: =M39 -> 39 | H69: =CA39/1000 -> 0.5 | I69: 16 MT | J69: 35000 | K69: 24 | L69: =H69*K69 -> 12 | M69: =ROUNDUP((G69/L69),0) -> 4 | N69: =O69*G69 -> 140000 | O69: =(J69*M69)/G69 -> 3589.7436 | P69: =BY39 -> MD0100066 | R69: =SUM(P39:BV39) -> 1176 | AH69: 75 | AK69: =((R69*H69)+AH69) -> 663 | AM69: =AK69*K69 -> 15912
D70: =BY40 -> MD0100075 | E70: =E40 -> FA0200005 | F70: =F40 -> 16 CORE X 2.5 SQ. MM. CU/ARD - WIRE (PVC) | G70: =M40 -> 28 | H70: =CA40/1000 -> 0.5 | I70: 16 MT | J70: 35000 | K70: 19 | L70: =H70*K70 -> 9.5 | M70: =ROUNDUP((G70/L70),0) -> 3 | N70: =O70*G70 -> 105000 | O70: =(J70*M70)/G70 -> 3750 | P70: =BY40 -> MD0100075 | R70: =SUM(P40:BV40) -> 1400 | AH70: 100 | AK70: =((R70*H70)+AH70) -> 800 | AM70: =AK70*K70 -> 15200
D71: =BY41 -> MD0100005 | E71: =E41 -> FA0900024 | F71: =F41 -> 4 CORE X 4 SQ. MM. CU/ARD - WIRE (PVC) | G71: =M41 -> 1 | H71: =CA41/1000 -> 0.5 | I71: 16 MT | J71: 35000 | K71: 36 | L71: =H71*K71 -> 18 | M71: =ROUNDUP((G71/L71),0) -> 1 | N71: =O71*G71 -> 35000 | O71: =(J71*M71)/G71 -> 35000 | P71: =BY41 -> MD0100005 | R71: =SUM(P41:BV41) -> 729 | AH71: 65 | AK71: =((R71*H71)+AH71) -> 429.5 | AM71: =AK71*K71 -> 15462
... D75: =BY45 -> MD0100013 | E75: =E45 -> FA0900160 | F75: =F45 -> 2 CORE X 50 SQ. MM. AL/ARD - WIRE (XLPE) | G75: =M45 -> 0.5 | H75: =CA45/1000 -> 1 | I75: 16 MT | J75: 35000 | K75: 8 | L75: =H75*K75 -> 8 | M75: =ROUNDUP((G75/L75),0) -> 1 | N75: =O75*G75 -> 35000 | O75: =(J75*M75)/G75 -> 70000 | P75: =BY45 -> MD0100013 | R75: =SUM(P45:BV45) -> 1650 | AH75: 150 | AK75: =((R75*H75)+AH75) -> 1800 | AM75: =AK75*K75 -> 14400
C78: DOCKET NO. | D78: Base Date | E78: ITEM CODE | F78: PROPOSE ERP ITEM NAME | G78: EX-WORKS (PER MTR) | H78: FREIGHT PER MTR | I78: PRICE INCLUDING FREIGHT (PER MTR) | J78: GST % | K78: GST VALUE | L78: PRICE INCLUDING GST & FREIGHT (PER MTR) | M78: QTY | N78: Unit | O78: TOTAL PRICE OF FULL QTY (INCLUDING FRIGHT & GST)
C80: =C19 -> ENQ-15115-22-23 | D80: =D19 -> 45658 | E80: =E19 -> FA0600013 | F80: =F19 -> 1 CORE X 95 SQ. MM. AL/UNARD(XLPE ) | G80: =ROUNDUP(G19/1000,2) -> 104.74 | H80: =ROUNDUP(H19/1000,2) -> 1.33 | I80: =G80+H80 -> 106.07 | J80: =J19 -> 0.18 | K80: =ROUND(I80*J80,2) -> 19.09 | L80: =ROUND(I80+K80,2) -> 125.16 | M80: =M19*1000 -> 79532 | N80: MTR | O80: =L80*M80 -> 9954225.1
C81: =C20 -> ENQ-15115-22-23 | D81: =D20 -> 45658 | E81: =E20 -> FA0600019 | F81: =F20 -> 1 CORE X 150 SQ. MM. AL/UNARD. (XLPE) | G81: =ROUNDUP(G20/1000,2) -> 168.26 | H81: =ROUNDUP(H20/1000,2) -> 1.84 | I81: =G81+H81 -> 170.1 | J81: =J20 -> 0.18 | K81: =ROUND(I81*J81,2) -> 30.62 | L81: =ROUND(I81+K81,2) -> 200.72 | M81: =M20*1000 -> 57308 | N81: MTR | O81: =L81*M81 -> 11502862
C82: =C21 -> ENQ-15115-22-23 | D82: =D21 -> 45658 | E82: =E21 -> FA0600021 | F82: =F21 -> 1 CORE X 185 SQ. MM. AL/UNARD. (XLPE) | G82: =ROUNDUP(G21/1000,2) -> 206.36 | H82: =ROUNDUP(H21/1000,2) -> 2.94 | I82: =G82+H82 -> 209.3 | J82: =J21 -> 0.18 | K82: =ROUND(I82*J82,2) -> 37.67 | L82: =ROUND(I82+K82,2) -> 246.97 | M82: =M21*1000 -> 35750 | N82: MTR | O82: =L82*M82 -> 8829177.5
C83: =C22 -> ENQ-15115-22-23 | D83: =D22 -> 45658 | E83: =E22 -> FA0600020 | F83: =F22 -> 1 CORE X 300 SQ. MM. AL/UNARD. (XLPE) | G83: =ROUNDUP(G22/1000,2) -> 318.75 | H83: =ROUNDUP(H22/1000,2) -> 4.73 | I83: =G83+H83 -> 323.48 | J83: =J22 -> 0.18 | K83: =ROUND(I83*J83,2) -> 58.23 | L83: =ROUND(I83+K83,2) -> 381.71 | M83: =M22*1000 -> 81552 | N83: MTR | O83: =L83*M83 -> 31129214
C84: =C23 -> ENQ-15115-22-23 | D84: =D23 -> 45658 | E84: =E23 -> FA0600032 | F84: =F23 -> 1 CORE X 630 SQ. MM. ALU/UNARD (XLPE) | G84: =ROUNDUP(G23/1000,2) -> 643.54 | H84: =ROUNDUP(H23/1000,2) -> 7.24 | I84: =G84+H84 -> 650.78 | J84: =J23 -> 0.18 | K84: =ROUND(I84*J84,2) -> 117.14 | L84: =ROUND(I84+K84,2) -> 767.92 | M84: =M23*1000 -> 38704 | N84: MTR | O84: =L84*M84 -> 29721576
C85: =C24 -> ENQ-15115-22-23 | D85: =D24 -> 45658 | E85: =E24 -> FA0900116 | F85: =F24 -> 4 CORE X 50 SQ. MM. AL/ARD - WIRE (XLPE) | G85: =ROUNDUP(G24/1000,2) -> 343.82 | H85: =ROUNDUP(H24/1000,2) -> 5.27 | I85: =G85+H85 -> 349.09 | J85: =J24 -> 0.18 | K85: =ROUND(I85*J85,2) -> 62.84 | L85: =ROUND(I85+K85,2) -> 411.93 | M85: =M24*1000 -> 26605 | N85: MTR | O85: =L85*M85 -> 10959398
C86: =C25 -> ENQ-15115-22-23 | D86: =D25 -> 45658 | E86: =E25 -> FA1100094 | F86: =F25 -> 4 CORE X 95 SQ. MM. ALU/ARD - WIRE (XLPE) | G86: =ROUNDUP(G25/1000,2) -> 562.65 | H86: =ROUNDUP(H25/1000,2) -> 7.97 | I86: =G86+H86 -> 570.62 | J86: =J25 -> 0.18 | K86: =ROUND(I86*J86,2) -> 102.71 | L86: =ROUND(I86+K86,2) -> 673.33 | M86: =M25*1000 -> 17586 | N86: MTR | O86: =L86*M86 -> 11841181
C87: =C26 -> ENQ-15115-22-23 | D87: =D26 -> 45658 | E87: =E26 -> FA1100177 | F87: =F26 -> 4 CORE X 150 SQ. MM. AL/ARD - WIRE (XLPE) | G87: =ROUNDUP(G26/1000,2) -> 915.21 | H87: =ROUNDUP(H26/1000,2) -> 14.41 | I87: =G87+H87 -> 929.62 | J87: =J26 -> 0.18 | K87: =ROUND(I87*J87,2) -> 167.33 | L87: =ROUND(I87+K87,2) -> 1096.95 | M87: =M26*1000 -> 21866 | N87: MTR | O87: =L87*M87 -> 23985909
C88: =C27 -> ENQ-15115-22-23 | D88: =D27 -> 45658 | E88: =E27 -> FA1100091 | F88: =F27 -> 4 CORE X 240 SQ. MM. AL/ARD - WIRE (XLPE) | G88: =ROUNDUP(G27/1000,2) -> 1367.57 | H88: =ROUNDUP(H27/1000,2) -> 25 | I88: =G88+H88 -> 1392.57 | J88: =J27 -> 0.18 | K88: =ROUND(I88*J88,2) -> 250.66 | L88: =ROUND(I88+K88,2) -> 1643.23 | M88: =M27*1000 -> 7000 | N88: MTR | O88: =L88*M88 -> 11502610
C89: =C28 -> ENQ-15115-22-23 | D89: =D28 -> 45658 | E89: =E28 -> FA1100176 | F89: =F28 -> 4 CORE X 300 SQ. MM. AL/ARD - WIRE (XLPE) | G89: =ROUNDUP(G28/1000,2) -> 1683.37 | H89: =ROUNDUP(H28/1000,2) -> 23.34 | I89: =G89+H89 -> 1706.71 | J89: =J28 -> 0.18 | K89: =ROUND(I89*J89,2) -> 307.21 | L89: =ROUND(I89+K89,2) -> 2013.92 | M89: =M28*1000 -> 34500 | N89: MTR | O89: =L89*M89 -> 69480240
C90: =C29 -> ENQ-15115-22-23 | D90: =D29 -> 45658 | E90: =E29 -> FA0500017 | F90: =F29 -> 1 CORE X 50 SQ. MM. AL/UNARD. (XLPE) | G90: =ROUNDUP(G29/1000,2) -> 62.43 | H90: =ROUNDUP(H29/1000,2) -> 1.46 | I90: =G90+H90 -> 63.89 | J90: =J29 -> 0.18 | K90: =ROUND(I90*J90,2) -> 11.5 | L90: =ROUND(I90+K90,2) -> 75.39 | M90: =M29*1000 -> 24060 | N90: MTR | O90: =L90*M90 -> 1813883.4
C91: =C30 -> ENQ-15115-22-23 | D91: =D30 -> 45658 | E91: =E30 -> FA0900111 | F91: =F30 -> 4 CORE X 25 SQ. MM. ALU/ARD - WIRE (XLPE) | G91: =ROUNDUP(G30/1000,2) -> 199.96 | H91: =ROUNDUP(H30/1000,2) -> 3.36 | I91: =G91+H91 -> 203.32 | J91: =J30 -> 0.18 | K91: =ROUND(I91*J91,2) -> 36.6 | L91: =ROUND(I91+K91,2) -> 239.92 | M91: =M30*1000 -> 146208 | N91: MTR | O91: =L91*M91 -> 35078223
... C106: =C45 -> ENQ-15115-22-23 | D106: =D45 -> 45658 | E106: =E45 -> FA0900160 | F106: =F45 -> 2 CORE X 50 SQ. MM. AL/ARD - WIRE (XLPE) | G106: =ROUNDUP(G45/1000,2) -> 240.89 | H106: =ROUNDUP(H45/1000,2) -> 70 | I106: =G106+H106 -> 310.89 | J106: =J45 -> 0.18 | K106: =ROUND(I106*J106,2) -> 55.96 | L106: =ROUND(I106+K106,2) -> 366.85 | M106: =M45*1000 -> 500 | N106: MTR | O106: =L106*M106 -> 183425
O107: =SUM(O80:O106) -> 9.896233e+08
O108: =O107-O46 -> 168334.87

Sheet PV
B1: Base Date | C1: 45658
B2: PV FORMULA HT POWRE CABLE
B3: IEEMA formulae and factors governing the price variation shall be as follows: The prices shall be subject to IEEMA Price Variation Clause with following conditions: P = Po + AIF (Al-Alo) + XLFAL (Cc-Cco) + CCFAl(PVCc-PVCco) + FeF (Fe-Feo)
B5: PV | C5: Base circular shall be January 2025 circular issued in february 2025. Base month for Bid Price shall remain same throughout the negotiation process till Outline Agreement / Rate Contract is finalized.Base month circular has to be attached in the price bid.
B8: Item | C8: Calculation part | D8: Date of Inspection | E8: Applicable Date | K8: BASE DATE | Q8: FACTORS | V8: Ex-Work Po | W8: PVC of al | X8: PVC of Cu Tape | Y8: PVC of XLPE | Z8: PVC OF PVC | AA8: PVC OF FE | AB8: PV/PKM | AC8: Billing Price/PKM | AD8: ='AUTO CALCULATION SHEET (2)'!P17 -> Alumimium | AE8: ='AUTO CALCULATION SHEET (2)'!R17 -> Copper | AF8: ='AUTO CALCULATION SHEET (2)'!AH17 -> LT-XLPE | AG8: ='AUTO CALCULATION SHEET (2)'!AK17 -> Type C PVC (HR) | AH8: ='AUTO CALCULATION SHEET (2)'!AM17 -> POLY TAPE | AI8: ='AUTO CALCULATION SHEET (2)'!AS17 -> PVC Type ST-2 | AJ8: ='AUTO CALCULATION SHEET (2)'!AT17 -> PVC Type ST-2-PRESSURE EXTRUDED | AK8: ='AUTO CALCULATION SHEET (2)'!BC17 -> Galvanised Steel Round Wire | AL8: ='AUTO CALCULATION SHEET (2)'!BH17 -> FRLSH PVC Type ST-2 | AM8: ='AUTO CALCULATION SHEET (2)'!BQ17 -> NCWBT | AN8: ='AUTO CALCULATION SHEET (2)'!BV17 -> RUBBERIZED COTTON TAPE | AO8: RMC | AP8: Drum | AQ8: RMC+Drum | AR8: VA | AS8: Groos VA% | AT8: Mfg % | AU8: Int % | AV8: Ins% | AW8: Net VA
E9: Date | F9: Al | G9: Cu | H9: Cc | I9: PVCc | J9: Fe | K9: Date | L9: Alo | M9: Cuo | N9: Cco | O9: PVCco | P9: Feo | AD9: 273 | AE9: 866 | AF9: 108 | AG9: 104 | AH9: 120 | AI9: 68 | AJ9: 87 | AK9: 82 | AL9: =86+5 -> 91 | AM9: 340 | AN9: 370
Q10: AlF | R10: CuF | S10: XLFAL | T10: CCFAI | U10: FeF | AD10: Kg/Km | AE10: Kg/Km | AF10: Kg/Km | AG10: Kg/Km | AH10: Kg/Km | AI10: Kg/Km | AJ10: Kg/Km | AK10: Kg/Km | AL10: Kg/Km | AM10: Kg/Km | AN10: Kg/Km
B11: ='AUTO CALCULATION SHEET (2)'!F19 -> 1 CORE X 95 SQ. MM. AL/UNARD(XLPE ) | D11: PROVISIONAL | E11: 45706 | F11: 265753.41 | H11: 154134 | I11: 159825 | K11: =$C$1 -> 45658 | L11: 264189 | N11: 154134 | O11: 159825 | Q11: 0.274 | S11: 0.048 | T11: 0.163 | V11: ='AUTO CALCULATION SHEET (2)'!G19 -> 104733.78 | W11: =Q11*(F11-L11) -> 428.64834 | X11: =R11*(G11-M11) -> 0 | Y11: =S11*(H11-N11) -> 0 | Z11: =T11*(I11-O11) -> 0 | AA11: =U11*(J11-P11) -> 0 | AB11: =W11+X11+Y11+Z11+AA11 -> 428.64834 | AC11: =V11+AB11 -> 105162.43 | AD11: ='AUTO CALCULATION SHEET (2)'!P19 -> 256 | AE11: ='AUTO CALCULATION SHEET (2)'!R19 -> 0 | AF11: ='AUTO CALCULATION SHEET (2)'!AH19 -> 44 | AG11: ='AUTO CALCULATION SHEET (2)'!AK19 -> 0 | AH11: ='AUTO CALCULATION SHEET (2)'!AM19 -> 0 | AI11: ='AUTO CALCULATION SHEET (2)'!AS19 -> 0 | AJ11: ='AUTO CALCULATION SHEET (2)'!AT19 -> 0 | AK11: ='AUTO CALCULATION SHEET (2)'!BC19 -> 0 | AL11: ='AUTO CALCULATION SHEET (2)'!BH19 -> 140 | AM11: ='AUTO CALCULATION SHEET (2)'!BQ19 -> 0 | AN11: ='AUTO CALCULATION SHEET (2)'!BV19 -> 0 | AO11: =SUMPRODUCT(AD11:AN11,$AD$9:$AN$9) -> 87380 | AP11: ='AUTO CALCULATION SHEET (2)'!CB19 -> 2550 | AQ11: =AO11+AP11 -> 89930 | AR11: =AC11-AQ11 -> 15232.427 | AS11: =ROUND((AR11/AQ11)*100,2) -> 16.94 | AT11: 0 | AU11: 2 | AV11: 1 | AW11: =AS11-AT11-AU11-AV11 -> 13.94
B12: ='AUTO CALCULATION SHEET (2)'!F20 -> 1 CORE X 150 SQ. MM. AL/UNARD. (XLPE) | D12: PROVISIONAL | E12: 45706 | F12: 265753.41 | H12: 154134 | I12: 159825 | K12: =$C$1 -> 45658 | L12: 264189 | N12: 154134 | O12: 159825 | Q12: 0.425 | S12: 0.078 | T12: 0.217 | V12: ='AUTO CALCULATION SHEET (2)'!G20 -> 168250.54 | W12: =Q12*(F12-L12) -> 664.87425 | X12: =R12*(G12-M12) -> 0 | Y12: =S12*(H12-N12) -> 0 | Z12: =T12*(I12-O12) -> 0 | AA12: =U12*(J12-P12) -> 0 | AB12: =W12+X12+Y12+Z12+AA12 -> 664.87425 | AC12: =V12+AB12 -> 168915.42 | AD12: ='AUTO CALCULATION SHEET (2)'!P20 -> 405 | AE12: ='AUTO CALCULATION SHEET (2)'!R20 -> 0 | AF12: ='AUTO CALCULATION SHEET (2)'!AH20 -> 72 | AG12: ='AUTO CALCULATION SHEET (2)'!AK20 -> 0 | AH12: ='AUTO CALCULATION SHEET (2)'!AM20 -> 0 | AI12: ='AUTO CALCULATION SHEET (2)'!AS20 -> 0 | AJ12: ='AUTO CALCULATION SHEET (2)'!AT20 -> 0 | AK12: ='AUTO CALCULATION SHEET (2)'!BC20 -> 0 | AL12: ='AUTO CALCULATION SHEET (2)'!BH20 -> 195 | AM12: ='AUTO CALCULATION SHEET (2)'!BQ20 -> 14 | AN12: ='AUTO CALCULATION SHEET (2)'!BV20 -> 0 | AO12: =SUMPRODUCT(AD12:AN12,$AD$9:$AN$9) -> 140846 | AP12: ='AUTO CALCULATION SHEET (2)'!CB20 -> 3606 | AQ12: =AO12+AP12 -> 144452 | AR12: =AC12-AQ12 -> 24463.415 | AS12: =ROUND((AR12/AQ12)*100,2) -> 16.94 | AT12: 0 | AU12: 2 | AV12: 1 | AW12: =AS12-AT12-AU12-AV12 -> 13.94
B13: ='AUTO CALCULATION SHEET (2)'!F21 -> 1 CORE X 185 SQ. MM. AL/UNARD. (XLPE) | D13: PROVISIONAL | E13: 45706 | F13: 265753.41 | H13: 154134 | I13: 159825 | K13: =$C$1 -> 45658 | L13: 264189 | N13: 154134 | O13: 159825 | Q13: 0.533 | S13: 0.097 | T13: 0.236 | V13: ='AUTO CALCULATION SHEET (2)'!G21 -> 206352.71 | W13: =Q13*(F13-L13) -> 833.83053 | X13: =R13*(G13-M13) -> 0 | Y13: =S13*(H13-N13) -> 0 | Z13: =T13*(I13-O13) -> 0 | AA13: =U13*(J13-P13) -> 0 | AB13: =W13+X13+Y13+Z13+AA13 -> 833.83053 | AC13: =V13+AB13 -> 207186.54 | AD13: ='AUTO CALCULATION SHEET (2)'!P21 -> 500 | AE13: ='AUTO CALCULATION SHEET (2)'!R21 -> 0 | AF13: ='AUTO CALCULATION SHEET (2)'!AH21 -> 90 | AG13: ='AUTO CALCULATION SHEET (2)'!AK21 -> 0 | AH13: ='AUTO CALCULATION SHEET (2)'!AM21 -> 0 | AI13: ='AUTO CALCULATION SHEET (2)'!AS21 -> 0 | AJ13: ='AUTO CALCULATION SHEET (2)'!AT21 -> 0 | AK13: ='AUTO CALCULATION SHEET (2)'!BC21 -> 0 | AL13: ='AUTO CALCULATION SHEET (2)'!BH21 -> 216 | AM13: ='AUTO CALCULATION SHEET (2)'!BQ21 -> 22 | AN13: ='AUTO CALCULATION SHEET (2)'!BV21 -> 0 | AO13: =SUMPRODUCT(AD13:AN13,$AD$9:$AN$9) -> 173356 | AP13: ='AUTO CALCULATION SHEET (2)'!CB21 -> 3881 | AQ13: =AO13+AP13 -> 177237 | AR13: =AC13-AQ13 -> 29949.544 | AS13: =ROUND((AR13/AQ13)*100,2) -> 16.9 | AT13: 0 | AU13: 2 | AV13: 1 | AW13: =AS13-AT13-AU13-AV13 -> 13.9
B14: ='AUTO CALCULATION SHEET (2)'!F22 -> 1 CORE X 300 SQ. MM. AL/UNARD. (XLPE) | D14: PROVISIONAL | E14: 45706 | F14: 265753.41 | H14: 154134 | I14: 159825 | K14: =$C$1 -> 45658 | L14: 264189 | N14: 154134 | O14: 159825 | Q14: 0.879 | S14: 0.138 | T14: 0.303 | V14: ='AUTO CALCULATION SHEET (2)'!G22 -> 318747.55 | W14: =Q14*(F14-L14) -> 1375.1164 | X14: =R14*(G14-M14) -> 0 | Y14: =S14*(H14-N14) -> 0 | Z14: =T14*(I14-O14) -> 0 | AA14: =U14*(J14-P14) -> 0 | AB14: =W14+X14+Y14+Z14+AA14 -> 1375.1164 | AC14: =V14+AB14 -> 320122.67 | AD14: ='AUTO CALCULATION SHEET (2)'!P22 -> 810 | AE14: ='AUTO CALCULATION SHEET (2)'!R22 -> 0 | AF14: ='AUTO CALCULATION SHEET (2)'!AH22 -> 132 | AG14: ='AUTO CALCULATION SHEET (2)'!AK22 -> 0 | AH14: ='AUTO CALCULATION SHEET (2)'!AM22 -> 0 | AI14: ='AUTO CALCULATION SHEET (2)'!AS22 -> 0 | AJ14: ='AUTO CALCULATION SHEET (2)'!AT22 -> 0 | AK14: ='AUTO CALCULATION SHEET (2)'!BC22 -> 0 | AL14: ='AUTO CALCULATION SHEET (2)'!BH22 -> 255 | AM14: ='AUTO CALCULATION SHEET (2)'!BQ22 -> 28 | AN14: ='AUTO CALCULATION SHEET (2)'!BV22 -> 0 | AO14: =SUMPRODUCT(AD14:AN14,$AD$9:$AN$9) -> 268111 | AP14: ='AUTO CALCULATION SHEET (2)'!CB22 -> 6276 | AQ14: =AO14+AP14 -> 274387 | AR14: =AC14-AQ14 -> 45735.666 | AS14: =ROUND((AR14/AQ14)*100,2) -> 16.67 | AT14: 0 | AU14: 2 | AV14: 1 | AW14: =AS14-AT14-AU14-AV14 -> 13.67
B15: ='AUTO CALCULATION SHEET (2)'!F23 -> 1 CORE X 630 SQ. MM. ALU/UNARD (XLPE) | D15: PROVISIONAL | E15: 45706 | F15: 265753.41 | H15: 154134 | I15: 159825 | K15: =$C$1 -> 45658 | L15: 264189 | N15: 154134 | O15: 159825 | Q15: 1.828 | S15: 0.265 | T15: 0.469 | V15: ='AUTO CALCULATION SHEET (2)'!G23 -> 643530.03 | W15: =Q15*(F15-L15) -> 2859.7415 | X15: =R15*(G15-M15) -> 0 | Y15: =S15*(H15-N15) -> 0 | Z15: =T15*(I15-O15) -> 0 | AA15: =U15*(J15-P15) -> 0 | AB15: =W15+X15+Y15+Z15+AA15 -> 2859.7415 | AC15: =V15+AB15 -> 646389.77 | AD15: ='AUTO CALCULATION SHEET (2)'!P23 -> 1701 | AE15: ='AUTO CALCULATION SHEET (2)'!R23 -> 0 | AF15: ='AUTO CALCULATION SHEET (2)'!AH23 -> 242 | AG15: ='AUTO CALCULATION SHEET (2)'!AK23 -> 0 | AH15: ='AUTO CALCULATION SHEET (2)'!AM23 -> 0 | AI15: ='AUTO CALCULATION SHEET (2)'!AS23 -> 0 | AJ15: ='AUTO CALCULATION SHEET (2)'!AT23 -> 0 | AK15: ='AUTO CALCULATION SHEET (2)'!BC23 -> 0 | AL15: ='AUTO CALCULATION SHEET (2)'!BH23 -> 408 | AM15: ='AUTO CALCULATION SHEET (2)'!BQ23 -> 40 | AN15: ='AUTO CALCULATION SHEET (2)'!BV23 -> 0 | AO15: =SUMPRODUCT(AD15:AN15,$AD$9:$AN$9) -> 541237 | AP15: ='AUTO CALCULATION SHEET (2)'!CB23 -> 13815 | AQ15: =AO15+AP15 -> 555052 | AR15: =AC15-AQ15 -> 91337.775 | AS15: =ROUND((AR15/AQ15)*100,2) -> 16.46 | AT15: 0 | AU15: 2 | AV15: 1 | AW15: =AS15-AT15-AU15-AV15 -> 13.46
B16: ='AUTO CALCULATION SHEET (2)'!F24 -> 4 CORE X 50 SQ. MM. AL/ARD - WIRE (XLPE) | D16: PROVISIONAL | E16: 45706 | F16: 265753.41 | H16: 154134 | I16: 159825 | J16: 74750 | K16: =$C$1 -> 45658 | L16: 264189 | N16: 154134 | O16: 159825 | P16: 74750 | Q16: 0.547 | S16: 0.144 | T16: 0.394 | U16: 1.108 | V16: ='AUTO CALCULATION SHEET (2)'!G24 -> 343815.65 | W16: =Q16*(F16-L16) -> 855.73227 | X16: =R16*(G16-M16) -> 0 | Y16: =S16*(H16-N16) -> 0 | Z16: =T16*(I16-O16) -> 0 | AA16: =U16*(J16-P16) -> 0 | AB16: =W16+X16+Y16+Z16+AA16 -> 855.73227 | AC16: =V16+AB16 -> 344671.38 | AD16: ='AUTO CALCULATION SHEET (2)'!P24 -> 541 | AE16: ='AUTO CALCULATION SHEET (2)'!R24 -> 0 | AF16: ='AUTO CALCULATION SHEET (2)'!AH24 -> 119 | AG16: ='AUTO CALCULATION SHEET (2)'!AK24 -> 0 | AH16: ='AUTO CALCULATION SHEET (2)'!AM24 -> 0 | AI16: ='AUTO CALCULATION SHEET (2)'!AS24 -> 56 | AJ16: ='AUTO CALCULATION SHEET (2)'!AT24 -> 0 | AK16: ='AUTO CALCULATION SHEET (2)'!BC24 -> 1042 | AL16: ='AUTO CALCULATION SHEET (2)'!BH24 -> 260 | AM16: ='AUTO CALCULATION SHEET (2)'!BQ24 -> 0 | AN16: ='AUTO CALCULATION SHEET (2)'!BV24 -> 20 | AO16: =SUMPRODUCT(AD16:AN16,$AD$9:$AN$9) -> 280857 | AP16: ='AUTO CALCULATION SHEET (2)'!CB24 -> 6254 | AQ16: =AO16+AP16 -> 287111 | AR16: =AC16-AQ16 -> 57560.38 | AS16: =ROUND((AR16/AQ16)*100,2) -> 20.05 | AT16: 0 | AU16: 2 | AV16: 1 | AW16: =AS16-AT16-AU16-AV16 -> 17.05
B17: ='AUTO CALCULATION SHEET (2)'!F25 -> 4 CORE X 95 SQ. MM. ALU/ARD - WIRE (XLPE) | D17: PROVISIONAL | E17: 45706 | F17: 265753.41 | H17: 154134 | I17: 159825 | J17: 74750 | K17: =$C$1 -> 45658 | L17: 264189 | N17: 154134 | O17: 159825 | P17: 74750 | Q17: 1.095 | S17: 0.211 | T17: 0.523 | U17: 1.443 | V17: ='AUTO CALCULATION SHEET (2)'!G25 -> 562648.05 | W17: =Q17*(F17-L17) -> 1713.0289 | X17: =R17*(G17-M17) -> 0 | Y17: =S17*(H17-N17) -> 0 | Z17: =T17*(I17-O17) -> 0 | AA17: =U17*(J17-P17) -> 0 | AB17: =W17+X17+Y17+Z17+AA17 -> 1713.0289 | AC17: =V17+AB17 -> 564361.08 | AD17: ='AUTO CALCULATION SHEET (2)'!P25 -> 1027 | AE17: ='AUTO CALCULATION SHEET (2)'!R25 -> 0 | AF17: ='AUTO CALCULATION SHEET (2)'!AH25 -> 172 | AG17: ='AUTO CALCULATION SHEET (2)'!AK25 -> 0 | AH17: ='AUTO CALCULATION SHEET (2)'!AM25 -> 0 | AI17: ='AUTO CALCULATION SHEET (2)'!AS25 -> 89 | AJ17: ='AUTO CALCULATION SHEET (2)'!AT25 -> 0 | AK17: ='AUTO CALCULATION SHEET (2)'!BC25 -> 1362 | AL17: ='AUTO CALCULATION SHEET (2)'!BH25 -> 358 | AM17: ='AUTO CALCULATION SHEET (2)'!BQ25 -> 0 | AN17: ='AUTO CALCULATION SHEET (2)'!BV25 -> 25 | AO17: =SUMPRODUCT(AD17:AN17,$AD$9:$AN$9) -> 458511 | AP17: ='AUTO CALCULATION SHEET (2)'!CB25 -> 14928 | AQ17: =AO17+AP17 -> 473439 | AR17: =AC17-AQ17 -> 90922.076 | AS17: =ROUND((AR17/AQ17)*100,2) -> 19.2 | AT17: 0 | AU17: 2 | AV17: 1 | AW17: =AS17-AT17-AU17-AV17 -> 16.2
B18: ='AUTO CALCULATION SHEET (2)'!F26 -> 4 CORE X 150 SQ. MM. AL/ARD - WIRE (XLPE) | D18: PROVISIONAL | E18: 45706 | F18: 265753.41 | H18: 154134 | I18: 159825 | J18: 74750 | K18: =$C$1 -> 45658 | L18: 264189 | N18: 154134 | O18: 159825 | P18: 74750 | Q18: 1.706 | S18: 0.344 | T18: 0.762 | U18: 0.79 | V18: ='AUTO CALCULATION SHEET (2)'!G26 -> 915207.24 | W18: =Q18*(F18-L18) -> 2668.8835 | X18: =R18*(G18-M18) -> 0 | Y18: =S18*(H18-N18) -> 0 | Z18: =T18*(I18-O18) -> 0 | AA18: =U18*(J18-P18) -> 0 | AB18: =W18+X18+Y18+Z18+AA18 -> 2668.8835 | AC18: =V18+AB18 -> 917876.13 | AD18: ='AUTO CALCULATION SHEET (2)'!P26 -> 1620 | AE18: ='AUTO CALCULATION SHEET (2)'!R26 -> 0 | AF18: ='AUTO CALCULATION SHEET (2)'!AH26 -> 276 | AG18: ='AUTO CALCULATION SHEET (2)'!AK26 -> 0 | AH18: ='AUTO CALCULATION SHEET (2)'!AM26 -> 0 | AI18: ='AUTO CALCULATION SHEET (2)'!AS26 -> 135 | AJ18: ='AUTO CALCULATION SHEET (2)'!AT26 -> 0 | AK18: ='AUTO CALCULATION SHEET (2)'!BC26 -> 2290 | AL18: ='AUTO CALCULATION SHEET (2)'!BH26 -> 530 | AM18: ='AUTO CALCULATION SHEET (2)'!BQ26 -> 55 | AN18: ='AUTO CALCULATION SHEET (2)'!BV26 -> 33 | AO18: =SUMPRODUCT(AD18:AN18,$AD$9:$AN$9) -> 748168 | AP18: ='AUTO CALCULATION SHEET (2)'!CB26 -> 21178 | AQ18: =AO18+AP18 -> 769346 | AR18: =AC18-AQ18 -> 148530.13 | AS18: =ROUND((AR18/AQ18)*100,2) -> 19.31 | AT18: 0 | AU18: 2 | AV18: 1 | AW18: =AS18-AT18-AU18-AV18 -> 16.31
B19: ='AUTO CALCULATION SHEET (2)'!F27 -> 4 CORE X 240 SQ. MM. AL/ARD - WIRE (XLPE) | D19: PROVISIONAL | E19: 45706 | F19: 265753.41 | H19: 154134 | I19: 159825 | J19: 74750 | K19: =$C$1 -> 45658 | L19: 264189 | N19: 154134 | O19: 159825 | P19: 74750 | Q19: 2.799 | S19: 0.518 | T19: 1.119 | U19: 2.722 | V19: ='AUTO CALCULATION SHEET (2)'!G27 -> 1367560.9 | W19: =Q19*(F19-L19) -> 4378.7836 | X19: =R19*(G19-M19) -> 0 | Y19: =S19*(H19-N19) -> 0 | Z19: =T19*(I19-O19) -> 0 | AA19: =U19*(J19-P19) -> 0 | AB19: =W19+X19+Y19+Z19+AA19 -> 4378.7836 | AC19: =V19+AB19 -> 1371939.7 | AD19: ='AUTO CALCULATION SHEET (2)'!P27 -> 2595 | AE19: ='AUTO CALCULATION SHEET (2)'!R27 -> 0 | AF19: ='AUTO CALCULATION SHEET (2)'!AH27 -> 415 | AG19: ='AUTO CALCULATION SHEET (2)'!AK27 -> 0 | AH19: ='AUTO CALCULATION SHEET (2)'!AM27 -> 0 | AI19: ='AUTO CALCULATION SHEET (2)'!AS27 -> 185 | AJ19: ='AUTO CALCULATION SHEET (2)'!AT27 -> 0 | AK19: ='AUTO CALCULATION SHEET (2)'!BC27 -> 2800 | AL19: ='AUTO CALCULATION SHEET (2)'!BH27 -> 728 | AM19: ='AUTO CALCULATION SHEET (2)'!BQ27 -> 75 | AN19: ='AUTO CALCULATION SHEET (2)'!BV27 -> 39 | AO19: =SUMPRODUCT(AD19:AN19,$AD$9:$AN$9) -> 1101613 | AP19: ='AUTO CALCULATION SHEET (2)'!CB27 -> 53200 | AQ19: =AO19+AP19 -> 1154813 | AR19: =AC19-AQ19 -> 217126.69 | AS19: =ROUND((AR19/AQ19)*100,2) -> 18.8 | AT19: 0 | AU19: 2 | AV19: 1 | AW19: =AS19-AT19-AU19-AV19 -> 15.8
B20: ='AUTO CALCULATION SHEET (2)'!F28 -> 4 CORE X 300 SQ. MM. AL/ARD - WIRE (XLPE) | D20: PROVISIONAL | E20: 45706 | F20: 265753.41 | H20: 154134 | I20: 159825 | J20: 74750 | K20: =$C$1 -> 45658 | L20: 264189 | N20: 154134 | O20: 159825 | P20: 74750 | Q20: 3.514 | S20: 0.62 | T20: 1.414 | U20: 3.842 | V20: ='AUTO CALCULATION SHEET (2)'!G28 -> 1683360.9 | W20: =Q20*(F20-L20) -> 5497.3367 | X20: =R20*(G20-M20) -> 0 | Y20: =S20*(H20-N20) -> 0 | Z20: =T20*(I20-O20) -> 0 | AA20: =U20*(J20-P20) -> 0 | AB20: =W20+X20+Y20+Z20+AA20 -> 5497.3367 | AC20: =V20+AB20 -> 1688858.2 | AD20: ='AUTO CALCULATION SHEET (2)'!P28 -> 3240 | AE20: ='AUTO CALCULATION SHEET (2)'!R28 -> 0 | AF20: ='AUTO CALCULATION SHEET (2)'!AH28 -> 500 | AG20: ='AUTO CALCULATION SHEET (2)'!AK28 -> 0 | AH20: ='AUTO CALCULATION SHEET (2)'!AM28 -> 0 | AI20: ='AUTO CALCULATION SHEET (2)'!AS28 -> 240 | AJ20: ='AUTO CALCULATION SHEET (2)'!AT28 -> 0 | AK20: ='AUTO CALCULATION SHEET (2)'!BC28 -> 3118 | AL20: ='AUTO CALCULATION SHEET (2)'!BH28 -> 880 | AM20: ='AUTO CALCULATION SHEET (2)'!BQ28 -> 112 | AN20: ='AUTO CALCULATION SHEET (2)'!BV28 -> 44 | AO20: =SUMPRODUCT(AD20:AN20,$AD$9:$AN$9) -> 1344956 | AP20: ='AUTO CALCULATION SHEET (2)'!CB28 -> 78780 | AQ20: =AO20+AP20 -> 1423736 | AR20: =AC20-AQ20 -> 265122.23 | AS20: =ROUND((AR20/AQ20)*100,2) -> 18.62 | AT20: 0 | AU20: 2 | AV20: 1 | AW20: =AS20-AT20-AU20-AV20 -> 15.62
B21: ='AUTO CALCULATION SHEET (2)'!F29 -> 1 CORE X 50 SQ. MM. AL/UNARD. (XLPE) | D21: PROVISIONAL | E21: 45706 | F21: 265753.41 | H21: 154134 | I21: 159825 | K21: =$C$1 -> 45658 | L21: 264189 | N21: 154134 | O21: 159825 | Q21: 0.137 | S21: 0.033 | T21: 0.124 | V21: ='AUTO CALCULATION SHEET (2)'!G29 -> 62424.716 | W21: =Q21*(F21-L21) -> 214.32417 | X21: =R21*(G21-M21) -> 0 | Y21: =S21*(H21-N21) -> 0 | Z21: =T21*(I21-O21) -> 0 | AA21: =U21*(J21-P21) -> 0 | AB21: =W21+X21+Y21+Z21+AA21 -> 214.32417 | AC21: =V21+AB21 -> 62639.04 | AD21: ='AUTO CALCULATION SHEET (2)'!P29 -> 135 | AE21: ='AUTO CALCULATION SHEET (2)'!R29 -> 0 | AF21: ='AUTO CALCULATION SHEET (2)'!AH29 -> 37 | AG21: ='AUTO CALCULATION SHEET (2)'!AK29 -> 0 | AH21: ='AUTO CALCULATION SHEET (2)'!AM29 -> 0 | AI21: ='AUTO CALCULATION SHEET (2)'!AS29 -> 0 | AJ21: ='AUTO CALCULATION SHEET (2)'!AT29 -> 0 | AK21: ='AUTO CALCULATION SHEET (2)'!BC29 -> 0 | AL21: ='AUTO CALCULATION SHEET (2)'!BH29 -> 110 | AM21: ='AUTO CALCULATION SHEET (2)'!BQ29 -> 0 | AN21: ='AUTO CALCULATION SHEET (2)'!BV29 -> 0 | AO21: =SUMPRODUCT(AD21:AN21,$AD$9:$AN$9) -> 50861 | AP21: ='AUTO CALCULATION SHEET (2)'!CB29 -> 2429 | AQ21: =AO21+AP21 -> 53290 | AR21: =AC21-AQ21 -> 9349.0398 | AS21: =ROUND((AR21/AQ21)*100,2) -> 17.54 | AT21: 0 | AU21: 2 | AV21: 1 | AW21: =AS21-AT21-AU21-AV21 -> 14.54
B22: ='AUTO CALCULATION SHEET (2)'!F30 -> 4 CORE X 25 SQ. MM. ALU/ARD - WIRE (XLPE) | D22: PROVISIONAL | E22: 45706 | F22: 265753.41 | H22: 154134 | I22: 159825 | J22: 74750 | K22: =$C$1 -> 45658 | L22: 264189 | N22: 154134 | O22: 159825 | P22: 74750 | Q22: 0.292 | S22: 0.093 | T22: 0.29 | U22: 0.685 | V22: ='AUTO CALCULATION SHEET (2)'!G30 -> 199954.56 | W22: =Q22*(F22-L22) -> 456.80772 | X22: =R22*(G22-M22) -> 0 | Y22: =S22*(H22-N22) -> 0 | Z22: =T22*(I22-O22) -> 0 | AA22: =U22*(J22-P22) -> 0 | AB22: =W22+X22+Y22+Z22+AA22 -> 456.80772 | AC22: =V22+AB22 -> 200411.37 | AD22: ='AUTO CALCULATION SHEET (2)'!P30 -> 270 | AE22: ='AUTO CALCULATION SHEET (2)'!R30 -> 0 | AF22: ='AUTO CALCULATION SHEET (2)'!AH30 -> 90 | AG22: ='AUTO CALCULATION SHEET (2)'!AK30 -> 0 | AH22: ='AUTO CALCULATION SHEET (2)'!AM30 -> 0 | AI22: ='AUTO CALCULATION SHEET (2)'!AS30 -> 44 | AJ22: ='AUTO CALCULATION SHEET (2)'!AT30 -> 0 | AK22: ='AUTO CALCULATION SHEET (2)'!BC30 -> 641 | AL22: ='AUTO CALCULATION SHEET (2)'!BH30 -> 190 | AM22: ='AUTO CALCULATION SHEET (2)'!BQ30 -> 0 | AN22: ='AUTO CALCULATION SHEET (2)'!BV30 -> 16 | AO22: =SUMPRODUCT(AD22:AN22,$AD$9:$AN$9) -> 162194 | AP22: ='AUTO CALCULATION SHEET (2)'!CB30 -> 3881 | AQ22: =AO22+AP22 -> 166075 | AR22: =AC22-AQ22 -> 34336.367 | AS22: =ROUND((AR22/AQ22)*100,2) -> 20.68 | AT22: 0 | AU22: 2 | AV22: 1 | AW22: =AS22-AT22-AU22-AV22 -> 17.68
B23: ='AUTO CALCULATION SHEET (2)'!F31 -> 4 CORE X 35 SQ. MM. AL/ARD - WIRE (XLPE) | D23: PROVISIONAL | E23: 45706 | F23: 265753.41 | H23: 154134 | I23: 159825 | J23: 74750 | K23: =$C$1 -> 45658 | L23: 264189 | N23: 154134 | O23: 159825 | P23: 74750 | Q23: 0.404 | S23: 0.112 | T23: 0.319 | U23: 0.761 | V23: ='AUTO CALCULATION SHEET (2)'!G31 -> 252365.66 | W23: =Q23*(F23-L23) -> 632.02164 | X23: =R23*(G23-M23) -> 0 | Y23: =S23*(H23-N23) -> 0 | Z23: =T23*(I23-O23) -> 0 | AA23: =U23*(J23-P23) -> 0 | AB23: =W23+X23+Y23+Z23+AA23 -> 632.02164 | AC23: =V23+AB23 -> 252997.68 | AD23: ='AUTO CALCULATION SHEET (2)'!P31 -> 378 | AE23: ='AUTO CALCULATION SHEET (2)'!R31 -> 0 | AF23: ='AUTO CALCULATION SHEET (2)'!AH31 -> 102 | AG23: ='AUTO CALCULATION SHEET (2)'!AK31 -> 0 | AH23: ='AUTO CALCULATION SHEET (2)'!AM31 -> 0 | AI23: ='AUTO CALCULATION SHEET (2)'!AS31 -> 51 | AJ23: ='AUTO CALCULATION SHEET (2)'!AT31 -> 0 | AK23: ='AUTO CALCULATION SHEET (2)'!BC31 -> 770 | AL23: ='AUTO CALCULATION SHEET (2)'!BH31 -> 206 | AM23: ='AUTO CALCULATION SHEET (2)'!BQ31 -> 0 | AN23: ='AUTO CALCULATION SHEET (2)'!BV31 -> 18 | AO23: =SUMPRODUCT(AD23:AN23,$AD$9:$AN$9) -> 206224 | AP23: ='AUTO CALCULATION SHEET (2)'!CB31 -> 4139 | AQ23: =AO23+AP23 -> 210363 | AR23: =AC23-AQ23 -> 42634.678 | AS23: =ROUND((AR23/AQ23)*100,2) -> 20.27 | AT23: 0 | AU23: 2 | AV23: 1 | AW23: =AS23-AT23-AU23-AV23 -> 17.27
B24: ='AUTO CALCULATION SHEET (2)'!F32 -> 2 CORE X 4 SQ. MM. AL/ARD - WIRE (XLPE) | D24: PROVISIONAL | E24: 45706 | F24: 265753.41 | H24: 154134 | I24: 159825 | J24: 74750 | K24: =$C$1 -> 45658 | L24: 264189 | N24: 154134 | O24: 159825 | P24: 74750 | Q24: 0.023 | S24: 0.018 | T24: 0.204 | U24: 0.305 | V24: ='AUTO CALCULATION SHEET (2)'!G32 -> 60548.88 | W24: =Q24*(F24-L24) -> 35.98143 | X24: =R24*(G24-M24) -> 0 | Y24: =S24*(H24-N24) -> 0 | Z24: =T24*(I24-O24) -> 0 | AA24: =U24*(J24-P24) -> 0 | AB24: =W24+X24+Y24+Z24+AA24 -> 35.98143 | AC24: =V24+AB24 -> 60584.861 | AD24: ='AUTO CALCULATION SHEET (2)'!P32 -> 22 | AE24: ='AUTO CALCULATION SHEET (2)'!R32 -> 0 | AF24: ='AUTO CALCULATION SHEET (2)'!AH32 -> 20 | AG24: ='AUTO CALCULATION SHEET (2)'!AK32 -> 0 | AH24: ='AUTO CALCULATION SHEET (2)'!AM32 -> 0 | AI24: ='AUTO CALCULATION SHEET (2)'!AS32 -> 70 | AJ24: ='AUTO CALCULATION SHEET (2)'!AT32 -> 0 | AK24: ='AUTO CALCULATION SHEET (2)'!BC32 -> 252 | AL24: ='AUTO CALCULATION SHEET (2)'!BH32 -> 103 | AM24: ='AUTO CALCULATION SHEET (2)'!BQ32 -> 0 | AN24: ='AUTO CALCULATION SHEET (2)'!BV32 -> 10 | AO24: =SUMPRODUCT(AD24:AN24,$AD$9:$AN$9) -> 46663 | AP24: ='AUTO CALCULATION SHEET (2)'!CB32 -> 2550 | AQ24: =AO24+AP24 -> 49213 | AR24: =AC24-AQ24 -> 11371.861 | AS24: =ROUND((AR24/AQ24)*100,2) -> 23.11 | AT24: 0 | AU24: 2 | AV24: 1 | AW24: =AS24-AT24-AU24-AV24 -> 20.11
B25: ='AUTO CALCULATION SHEET (2)'!F33 -> 2 CORE X 6 SQ. MM. AL/ARD - WIRE (XLPE) | D25: PROVISIONAL | E25: 45706 | F25: 265753.41 | H25: 154134 | I25: 159825 | J25: 74750 | K25: =$C$1 -> 45658 | L25: 264189 | N25: 154134 | O25: 159825 | P25: 74750 | Q25: 0.034 | S25: 0.022 | T25: 0.234 | U25: 0.348 | V25: ='AUTO CALCULATION SHEET (2)'!G33 -> 69881.462 | W25: =Q25*(F25-L25) -> 53.18994 | X25: =R25*(G25-M25) -> 0 | Y25: =S25*(H25-N25) -> 0 | Z25: =T25*(I25-O25) -> 0 | AA25: =U25*(J25-P25) -> 0 | AB25: =W25+X25+Y25+Z25+AA25 -> 53.18994 | AC25: =V25+AB25 -> 69934.652 | AD25: ='AUTO CALCULATION SHEET (2)'!P33 -> 33 | AE25: ='AUTO CALCULATION SHEET (2)'!R33 -> 0 | AF25: ='AUTO CALCULATION SHEET (2)'!AH33 -> 23 | AG25: ='AUTO CALCULATION SHEET (2)'!AK33 -> 0 | AH25: ='AUTO CALCULATION SHEET (2)'!AM33 -> 0 | AI25: ='AUTO CALCULATION SHEET (2)'!AS33 -> 0 | AJ25: ='AUTO CALCULATION SHEET (2)'!AT33 -> 78 | AK25: ='AUTO CALCULATION SHEET (2)'!BC33 -> 276 | AL25: ='AUTO CALCULATION SHEET (2)'!BH33 -> 108 | AM25: ='AUTO CALCULATION SHEET (2)'!BQ33 -> 0 | AN25: ='AUTO CALCULATION SHEET (2)'!BV33 -> 10 | AO25: =SUMPRODUCT(AD25:AN25,$AD$9:$AN$9) -> 54439 | AP25: ='AUTO CALCULATION SHEET (2)'!CB33 -> 2550 | AQ25: =AO25+AP25 -> 56989 | AR25: =AC25-AQ25 -> 12945.652 | AS25: =ROUND((AR25/AQ25)*100,2) -> 22.72 | AT25: 0 | AU25: 2 | AV25: 1 | AW25: =AS25-AT25-AU25-AV25 -> 19.72
B26: ='AUTO CALCULATION SHEET (2)'!F34 -> 2 CORE X 10 SQ. MM. ALU/ARD - WIRE (XLPE) | D26: PROVISIONAL | E26: 45706 | F26: 265753.41 | H26: 154134 | I26: 159825 | J26: 74750 | K26: =$C$1 -> 45658 | L26: 264189 | N26: 154134 | O26: 159825 | P26: 74750 | Q26: 0.053 | S26: 0.025 | T26: 0.28 | U26: 0.392 | V26: ='AUTO CALCULATION SHEET (2)'!G34 -> 92040.223 | W26: =Q26*(F26-L26) -> 82.91373 | X26: =R26*(G26-M26) -> 0 | Y26: =S26*(H26-N26) -> 0 | Z26: =T26*(I26-O26) -> 0 | AA26: =U26*(J26-P26) -> 0 | AB26: =W26+X26+Y26+Z26+AA26 -> 82.91373 | AC26: =V26+AB26 -> 92123.137 | AD26: ='AUTO CALCULATION SHEET (2)'!P34 -> 54 | AE26: ='AUTO CALCULATION SHEET (2)'!R34 -> 0 | AF26: ='AUTO CALCULATION SHEET (2)'!AH34 -> 25 | AG26: ='AUTO CALCULATION SHEET (2)'!AK34 -> 0 | AH26: ='AUTO CALCULATION SHEET (2)'!AM34 -> 0 | AI26: ='AUTO CALCULATION SHEET (2)'!AS34 -> 0 | AJ26: ='AUTO CALCULATION SHEET (2)'!AT34 -> 103 | AK26: ='AUTO CALCULATION SHEET (2)'!BC34 -> 360 | AL26: ='AUTO CALCULATION SHEET (2)'!BH34 -> 120 | AM26: ='AUTO CALCULATION SHEET (2)'!BQ34 -> 0 | AN26: ='AUTO CALCULATION SHEET (2)'!BV34 -> 12 | AO26: =SUMPRODUCT(AD26:AN26,$AD$9:$AN$9) -> 71283 | AP26: ='AUTO CALCULATION SHEET (2)'!CB34 -> 3992 | AQ26: =AO26+AP26 -> 75275 | AR26: =AC26-AQ26 -> 16848.137 | AS26: =ROUND((AR26/AQ26)*100,2) -> 22.38 | AT26: 0 | AU26: 2 | AV26: 1 | AW26: =AS26-AT26-AU26-AV26 -> 19.38
B27: ='AUTO CALCULATION SHEET (2)'!F35 -> 4 CORE X 10 SQ. MM. AL/ARD - WIRE (XLPE) | D27: PROVISIONAL | E27: 45706 | F27: 265753.41 | H27: 154134 | I27: 159825 | J27: 74750 | K27: =$C$1 -> 45658 | L27: 264189 | N27: 154134 | O27: 159825 | P27: 74750 | Q27: 0.116 | S27: 0.053 | T27: 0.298 | U27: 0.533 | V27: ='AUTO CALCULATION SHEET (2)'!G35 -> 111007.08 | W27: =Q27*(F27-L27) -> 181.47156 | X27: =R27*(G27-M27) -> 0 | Y27: =S27*(H27-N27) -> 0 | Z27: =T27*(I27-O27) -> 0 | AA27: =U27*(J27-P27) -> 0 | AB27: =W27+X27+Y27+Z27+AA27 -> 181.47156 | AC27: =V27+AB27 -> 111188.55 | AD27: ='AUTO CALCULATION SHEET (2)'!P35 -> 108 | AE27: ='AUTO CALCULATION SHEET (2)'!R35 -> 0 | AF27: ='AUTO CALCULATION SHEET (2)'!AH35 -> 50 | AG27: ='AUTO CALCULATION SHEET (2)'!AK35 -> 0 | AH27: ='AUTO CALCULATION SHEET (2)'!AM35 -> 0 | AI27: ='AUTO CALCULATION SHEET (2)'!AS35 -> 35 | AJ27: ='AUTO CALCULATION SHEET (2)'!AT35 -> 0 | AK27: ='AUTO CALCULATION SHEET (2)'!BC35 -> 377 | AL27: ='AUTO CALCULATION SHEET (2)'!BH35 -> 151 | AM27: ='AUTO CALCULATION SHEET (2)'!BQ35 -> 0 | AN27: ='AUTO CALCULATION SHEET (2)'!BV35 -> 13.5 | AO27: =SUMPRODUCT(AD27:AN27,$AD$9:$AN$9) -> 86914 | AP27: ='AUTO CALCULATION SHEET (2)'!CB35 -> 4593 | AQ27: =AO27+AP27 -> 91507 | AR27: =AC27-AQ27 -> 19681.547 | AS27: =ROUND((AR27/AQ27)*100,2) -> 21.51 | AT27: 0 | AU27: 2 | AV27: 1 | AW27: =AS27-AT27-AU27-AV27 -> 18.51
B28: ='AUTO CALCULATION SHEET (2)'!F36 -> 4 CORE X 2.5 SQ. MM. CU/ARD - WIRE (PVC) | D28: PROVISIONAL | E28: 45706 | G28: 870134.53 | I28: 159825 | J28: 75250 | K28: =$C$1 -> 45658 | M28: 837521 | O28: 159825 | P28: 75250 | R28: 0.094 | T28: 0.179 | U28: 0.314 | V28: ='AUTO CALCULATION SHEET (2)'!G36 -> 144287.63 | W28: =Q28*(F28-L28) -> 0 | X28: =R28*(G28-M28) -> 3065.6718 | Y28: =S28*(H28-N28) -> 0 | Z28: =T28*(I28-O28) -> 0 | AA28: =U28*(J28-P28) -> 0 | AB28: =W28+X28+Y28+Z28+AA28 -> 3065.6718 | AC28: =V28+AB28 -> 147353.3 | AD28: ='AUTO CALCULATION SHEET (2)'!P36 -> 0 | AE28: ='AUTO CALCULATION SHEET (2)'!R36 -> 89 | AF28: ='AUTO CALCULATION SHEET (2)'!AH36 -> 0 | AG28: ='AUTO CALCULATION SHEET (2)'!AK36 -> 52 | AH28: ='AUTO CALCULATION SHEET (2)'!AM36 -> 3 | AI28: ='AUTO CALCULATION SHEET (2)'!AS36 -> 27 | AJ28: ='AUTO CALCULATION SHEET (2)'!AT36 -> 0 | AK28: ='AUTO CALCULATION SHEET (2)'!BC36 -> 289 | AL28: ='AUTO CALCULATION SHEET (2)'!BH36 -> 104 | AM28: ='AUTO CALCULATION SHEET (2)'!BQ36 -> 0 | AN28: ='AUTO CALCULATION SHEET (2)'!BV36 -> 0 | AO28: =SUMPRODUCT(AD28:AN28,$AD$9:$AN$9) -> 117840 | AP28: ='AUTO CALCULATION SHEET (2)'!CB36 -> 4858 | AQ28: =AO28+AP28 -> 122698 | AR28: =AC28-AQ28 -> 24655.304 | AS28: =ROUND((AR28/AQ28)*100,2) -> 20.09 | AT28: 0 | AU28: 2 | AV28: 1 | AW28: =AS28-AT28-AU28-AV28 -> 17.09
B29: ='AUTO CALCULATION SHEET (2)'!F37 -> 7 CORE X 2.5 SQ. MM. CU/ARD - WIRE (PVC) | D29: PROVISIONAL | E29: 45706 | G29: 870134.53 | I29: 159825 | J29: 75250 | K29: =$C$1 -> 45658 | M29: 837521 | O29: 159825 | P29: 75250 | R29: 0.164 | T29: 0.26 | U29: 0.379 | V29: ='AUTO CALCULATION SHEET (2)'!G37 -> 223186.25 | W29: =Q29*(F29-L29) -> 0 | X29: =R29*(G29-M29) -> 5348.6189 | Y29: =S29*(H29-N29) -> 0 | Z29: =T29*(I29-O29) -> 0 | AA29: =U29*(J29-P29) -> 0 | AB29: =W29+X29+Y29+Z29+AA29 -> 5348.6189 | AC29: =V29+AB29 -> 228534.87 | AD29: ='AUTO CALCULATION SHEET (2)'!P37 -> 0 | AE29: ='AUTO CALCULATION SHEET (2)'!R37 -> 155 | AF29: ='AUTO CALCULATION SHEET (2)'!AH37 -> 0 | AG29: ='AUTO CALCULATION SHEET (2)'!AK37 -> 91 | AH29: ='AUTO CALCULATION SHEET (2)'!AM37 -> 4 | AI29: ='AUTO CALCULATION SHEET (2)'!AS37 -> 33 | AJ29: ='AUTO CALCULATION SHEET (2)'!AT37 -> 0 | AK29: ='AUTO CALCULATION SHEET (2)'!BC37 -> 352 | AL29: ='AUTO CALCULATION SHEET (2)'!BH37 -> 120 | AM29: ='AUTO CALCULATION SHEET (2)'!BQ37 -> 0 | AN29: ='AUTO CALCULATION SHEET (2)'!BV37 -> 0 | AO29: =SUMPRODUCT(AD29:AN29,$AD$9:$AN$9) -> 186202 | AP29: ='AUTO CALCULATION SHEET (2)'!CB37 -> 4858 | AQ29: =AO29+AP29 -> 191060 | AR29: =AC29-AQ29 -> 37474.869 | AS29: =ROUND((AR29/AQ29)*100,2) -> 19.61 | AT29: 0 | AU29: 2 | AV29: 1 | AW29: =AS29-AT29-AU29-AV29 -> 16.61
B30: ='AUTO CALCULATION SHEET (2)'!F38 -> 10 CORE X 2.5 SQ. MM. CU/ARD - WIRE (PVC) | D30: PROVISIONAL | E30: 45706 | G30: 870134.53 | I30: 159825 | J30: 75250 | K30: =$C$1 -> 45658 | M30: 837521 | O30: 159825 | P30: 75250 | R30: 0.235 | T30: 0.337 | U30: 0.535 | V30: ='AUTO CALCULATION SHEET (2)'!G38 -> 317379.5 | W30: =Q30*(F30-L30) -> 0 | X30: =R30*(G30-M30) -> 7664.1796 | Y30: =S30*(H30-N30) -> 0 | Z30: =T30*(I30-O30) -> 0 | AA30: =U30*(J30-P30) -> 0 | AB30: =W30+X30+Y30+Z30+AA30 -> 7664.1796 | AC30: =V30+AB30 -> 325043.68 | AD30: ='AUTO CALCULATION SHEET (2)'!P38 -> 0 | AE30: ='AUTO CALCULATION SHEET (2)'!R38 -> 222 | AF30: ='AUTO CALCULATION SHEET (2)'!AH38 -> 0 | AG30: ='AUTO CALCULATION SHEET (2)'!AK38 -> 130 | AH30: ='AUTO CALCULATION SHEET (2)'!AM38 -> 5 | AI30: ='AUTO CALCULATION SHEET (2)'!AS38 -> 42 | AJ30: ='AUTO CALCULATION SHEET (2)'!AT38 -> 0 | AK30: ='AUTO CALCULATION SHEET (2)'!BC38 -> 509 | AL30: ='AUTO CALCULATION SHEET (2)'!BH38 -> 172 | AM30: ='AUTO CALCULATION SHEET (2)'!BQ38 -> 0 | AN30: ='AUTO CALCULATION SHEET (2)'!BV38 -> 0 | AO30: =SUMPRODUCT(AD30:AN30,$AD$9:$AN$9) -> 266618 | AP30: ='AUTO CALCULATION SHEET (2)'!CB38 -> 5100 | AQ30: =AO30+AP30 -> 271718 | AR30: =AC30-AQ30 -> 53325.683 | AS30: =ROUND((AR30/AQ30)*100,2) -> 19.63 | AT30: 0 | AU30: 2 | AV30: 1 | AW30: =AS30-AT30-AU30-AV30 -> 16.63
B31: ='AUTO CALCULATION SHEET (2)'!F39 -> 12 CORE X 2.5 SQ. MM. CU/ARD - WIRE (PVC) | D31: PROVISIONAL | E31: 45706 | G31: 870134.53 | I31: 159825 | J31: 75250 | K31: =$C$1 -> 45658 | M31: 837521 | O31: 159825 | P31: 75250 | R31: 0.282 | T31: 0.371 | U31: 0.572 | V31: ='AUTO CALCULATION SHEET (2)'!G39 -> 366743.86 | W31: =Q31*(F31-L31) -> 0 | X31: =R31*(G31-M31) -> 9197.0155 | Y31: =S31*(H31-N31) -> 0 | Z31: =T31*(I31-O31) -> 0 | AA31: =U31*(J31-P31) -> 0 | AB31: =W31+X31+Y31+Z31+AA31 -> 9197.0155 | AC31: =V31+AB31 -> 375940.88 | AD31: ='AUTO CALCULATION SHEET (2)'!P39 -> 0 | AE31: ='AUTO CALCULATION SHEET (2)'!R39 -> 266 | AF31: ='AUTO CALCULATION SHEET (2)'!AH39 -> 0 | AG31: ='AUTO CALCULATION SHEET (2)'!AK39 -> 156 | AH31: ='AUTO CALCULATION SHEET (2)'!AM39 -> 6 | AI31: ='AUTO CALCULATION SHEET (2)'!AS39 -> 44 | AJ31: ='AUTO CALCULATION SHEET (2)'!AT39 -> 0 | AK31: ='AUTO CALCULATION SHEET (2)'!BC39 -> 526 | AL31: ='AUTO CALCULATION SHEET (2)'!BH39 -> 178 | AM31: ='AUTO CALCULATION SHEET (2)'!BQ39 -> 0 | AN31: ='AUTO CALCULATION SHEET (2)'!BV39 -> 0 | AO31: =SUMPRODUCT(AD31:AN31,$AD$9:$AN$9) -> 309622 | AP31: ='AUTO CALCULATION SHEET (2)'!CB39 -> 5100 | AQ31: =AO31+AP31 -> 314722 | AR31: =AC31-AQ31 -> 61218.875 | AS31: =ROUND((AR31/AQ31)*100,2) -> 19.45 | AT31: 0 | AU31: 2 | AV31: 1 | AW31: =AS31-AT31-AU31-AV31 -> 16.45
B32: ='AUTO CALCULATION SHEET (2)'!F40 -> 16 CORE X 2.5 SQ. MM. CU/ARD - WIRE (PVC) | D32: PROVISIONAL | E32: 45706 | G32: 870134.53 | I32: 159825 | J32: 75250 | K32: =$C$1 -> 45658 | M32: 837521 | O32: 159825 | P32: 75250 | R32: 0.376 | T32: 0.458 | U32: 0.66 | V32: ='AUTO CALCULATION SHEET (2)'!G40 -> 472972.33 | W32: =Q32*(F32-L32) -> 0 | X32: =R32*(G32-M32) -> 12262.687 | Y32: =S32*(H32-N32) -> 0 | Z32: =T32*(I32-O32) -> 0 | AA32: =U32*(J32-P32) -> 0 | AB32: =W32+X32+Y32+Z32+AA32 -> 12262.687 | AC32: =V32+AB32 -> 485235.02 | AD32: ='AUTO CALCULATION SHEET (2)'!P40 -> 0 | AE32: ='AUTO CALCULATION SHEET (2)'!R40 -> 355 | AF32: ='AUTO CALCULATION SHEET (2)'!AH40 -> 0 | AG32: ='AUTO CALCULATION SHEET (2)'!AK40 -> 214 | AH32: ='AUTO CALCULATION SHEET (2)'!AM40 -> 6 | AI32: ='AUTO CALCULATION SHEET (2)'!AS40 -> 58 | AJ32: ='AUTO CALCULATION SHEET (2)'!AT40 -> 0 | AK32: ='AUTO CALCULATION SHEET (2)'!BC40 -> 574 | AL32: ='AUTO CALCULATION SHEET (2)'!BH40 -> 193 | AM32: ='AUTO CALCULATION SHEET (2)'!BQ40 -> 0 | AN32: ='AUTO CALCULATION SHEET (2)'!BV40 -> 0 | AO32: =SUMPRODUCT(AD32:AN32,$AD$9:$AN$9) -> 398981 | AP32: ='AUTO CALCULATION SHEET (2)'!CB40 -> 7984 | AQ32: =AO32+AP32 -> 406965 | AR32: =AC32-AQ32 -> 78270.02 | AS32: =ROUND((AR32/AQ32)*100,2) -> 19.23 | AT32: 0 | AU32: 2 | AV32: 1 | AW32: =AS32-AT32-AU32-AV32 -> 16.23
B33: ='AUTO CALCULATION SHEET (2)'!F41 -> 4 CORE X 4 SQ. MM. CU/ARD - WIRE (PVC) | D33: PROVISIONAL | E33: 45706 | G33: 870134.53 | I33: 159825 | J33: 74750 | K33: =$C$1 -> 45658 | M33: 837521 | O33: 159825 | P33: 74750 | R33: 0.151 | T33: 0.209 | U33: 0.363 | V33: ='AUTO CALCULATION SHEET (2)'!G41 -> 210455.66 | W33: =Q33*(F33-L33) -> 0 | X33: =R33*(G33-M33) -> 4924.643 | Y33: =S33*(H33-N33) -> 0 | Z33: =T33*(I33-O33) -> 0 | AA33: =U33*(J33-P33) -> 0 | AB33: =W33+X33+Y33+Z33+AA33 -> 4924.643 | AC33: =V33+AB33 -> 215380.3 | AD33: ='AUTO CALCULATION SHEET (2)'!P41 -> 0 | AE33: ='AUTO CALCULATION SHEET (2)'!R41 -> 144 | AF33: ='AUTO CALCULATION SHEET (2)'!AH41 -> 0 | AG33: ='AUTO CALCULATION SHEET (2)'!AK41 -> 76 | AH33: ='AUTO CALCULATION SHEET (2)'!AM41 -> 4 | AI33: ='AUTO CALCULATION SHEET (2)'!AS41 -> 34 | AJ33: ='AUTO CALCULATION SHEET (2)'!AT41 -> 0 | AK33: ='AUTO CALCULATION SHEET (2)'!BC41 -> 352 | AL33: ='AUTO CALCULATION SHEET (2)'!BH41 -> 119 | AM33: ='AUTO CALCULATION SHEET (2)'!BQ41 -> 0 | AN33: ='AUTO CALCULATION SHEET (2)'!BV41 -> 0 | AO33: =SUMPRODUCT(AD33:AN33,$AD$9:$AN$9) -> 175093 | AP33: ='AUTO CALCULATION SHEET (2)'!CB41 -> 4858 | AQ33: =AO33+AP33 -> 179951 | AR33: =AC33-AQ33 -> 35429.299 | AS33: =ROUND((AR33/AQ33)*100,2) -> 19.69 | AT33: 0 | AU33: 2 | AV33: 1 | AW33: =AS33-AT33-AU33-AV33 -> 16.69
B34: ='AUTO CALCULATION SHEET (2)'!F42 -> 4 CORE X 16 SQ. MM. AL/ARD - WIRE (XLPE) | D34: PROVISIONAL | E34: 45706 | F34: 265753.41 | H34: 154134 | I34: 159825 | J34: 74750 | K34: =$C$1 -> 45658 | L34: 264189 | N34: 154134 | O34: 159825 | P34: 74750 | R34: 0.183 | S34: 0.065 | T34: 0.279 | U34: 0.573 | V34: ='AUTO CALCULATION SHEET (2)'!G42 -> 142452.42 | W34: =Q34*(F34-L34) -> 0 | X34: =R34*(G34-M34) -> 0 | Y34: =S34*(H34-N34) -> 0 | Z34: =T34*(I34-O34) -> 0 | AA34: =U34*(J34-P34) -> 0 | AB34: =W34+X34+Y34+Z34+AA34 -> 0 | AC34: =V34+AB34 -> 142452.42 | AD34: ='AUTO CALCULATION SHEET (2)'!P42 -> 173 | AE34: ='AUTO CALCULATION SHEET (2)'!R42 -> 0 | AF34: ='AUTO CALCULATION SHEET (2)'!AH42 -> 64 | AG34: ='AUTO CALCULATION SHEET (2)'!AK42 -> 0 | AH34: ='AUTO CALCULATION SHEET (2)'!AM42 -> 0 | AI34: ='AUTO CALCULATION SHEET (2)'!AS42 -> 40 | AJ34: ='AUTO CALCULATION SHEET (2)'!AT42 -> 0 | AK34: ='AUTO CALCULATION SHEET (2)'!BC42 -> 460 | AL34: ='AUTO CALCULATION SHEET (2)'!BH42 -> 158 | AM34: ='AUTO CALCULATION SHEET (2)'!BQ42 -> 0 | AN34: ='AUTO CALCULATION SHEET (2)'!BV42 -> 14 | AO34: =SUMPRODUCT(AD34:AN34,$AD$9:$AN$9) -> 114139 | AP34: ='AUTO CALCULATION SHEET (2)'!CB42 -> 3881 | AQ34: =AO34+AP34 -> 118020 | AR34: =AC34-AQ34 -> 24432.42 | AS34: =ROUND((AR34/AQ34)*100,2) -> 20.7 | AT34: 0 | AU34: 2 | AV34: 1 | AW34: =AS34-AT34-AU34-AV34 -> 17.7
