Workbook

Sheet Sheet1
A1: DOCKET NO. | B1: Base Date | C1: ITEM CODE | D1: PROPOSE ERP ITEM NAME | E1: Propose Drum Type | F1: Insulation Screening(Metallic) | G1: RM Rate(Insulation Screening(Metallic)) | H1: Weight (Insulation Screening (Metallic)) | I1: Cost Insulation Screening(Metallic) | J1: Conductor | K1: RM Rate(Conductor) | L1: Weight(Conductor) | M1: Cost(Conductor) | N1: AL ALLOY | O1: RM Rate(AL Alloy) | P1: Weight(Al Alloy) | Q1: Cost(AL Alloy) | R1: Insulation Screening(Non-Metallic) | S1: RM Rate(Insulation Screening(Non-Metallic)) | T1: Weight(Insulation Screening(Non-Metallic) | U1: Cost(Insulation Screening(Non-Metallic) | V1: Insulation | W1: RM Rate(Insulation) | X1: Weight(Insulation) | Y1: Cost(Insulation) | Z1: Poly Tape | AA1: RM Rate(Poly Tape) | AB1: Weight(Poly Tape) | AC1: Cost(Poly Tape) | AD1: Inner Sheath | AE1: RM Rate(Inner Sheath) | AF1: Weight(Inner Sheath) | AG1: Cost(Inner Sheath) | AH1: Armouring | AI1: RM Rate(Armouring) | AJ1: Weight(Armouring) | AK1: Cost(Armouring) | AL1: Outer Sheath | AM1: RM Rate(Outer Sheath) | AN1: Weight(Outer Sheath) | AO1: Cost(Outer Sheath) | AP1: Filler | AQ1: RM Rate(Filler) | AR1: Weight(Filler) | AS1: Cost(Filler) | AT1: Grease | AU1: RM Rate(Grease) | AV1: Weight(Grease) | AW1: Cost(Grease) | AX1: Water Swellable Tape | AY1: RM Rate(Water Swellable Tape) | AZ1: Weight(Water Swellable Tape) | BA1: Cost(Water Swellable Tape) | BB1: Semi Conducting Water Swellable Tape | BC1: RM Rate(Semi Conducting Water Swellable Tape) | BD1: Weight(Semi Conducting Water Swellable Tape) | BE1: Cost(Semi Conducting Water Swellable Tape) | BF1: Semicon Tape | BG1: RM Rate(Semicon Tape) | BH1: Weight(Semicon Tape) | BI1: Cost(Semicon Tape) | BJ1: Glass Fiber Tape | BK1: RM Rate(Glass Fiber Tape) | BL1: Weight(Glass Fiber Tape) | BM1: Cost(Glass Fiber Tape) | BN1: Copper Wire 0.8MM | BO1: RM Rate(Copper Wire 0.8MM) | BP1: Weight(Copper Wire 0.8MM) | BQ1: Cost(Copper Wire 0.8MM) | BR1: Rubberized Cotton Tape | BS1: RM Rate(Rubberized Cotton Tape) | BT1: Weight(Rubberized Cotton Tape) | BU1: Cost(Rubberized Cotton Tape) | BV1: Water Tight Compound | BW1: RM Rate(Water Tight Compound) | BX1: Weight(Water Tight Compound) | BY1: Cost(Water Tight Compound) | BZ1: Drum Cost Per KM | CA1: Total RM Cost | CB1: FIRM % | CC1: Firm Value | CD1: MFG% | CE1: MFG Value | CF1: PROF% | CG1: Profit Value | CH1: 1st EX-Works | CI1: Intt % | CJ1: Intt Value | CK1: insp% | CL1: Insp Value | CM1: EX-Works Per KM | CN1: Freight Per KM | CO1: Price Including Freight Per KM | CP1: GST % | CQ1: GST Value | CR1: Price Including GST & Freight Per KM | CS1: QTY | CT1: Unit | CU1: Total Price Of Full QTY(Including Freight&GST) | CV1: DRUM CODE | CW1: DRUM SIZE (FxbXtx Ft) | CX1: Party Standard Length(MTR)
A2: ENQ-15138-22-23 | B2: 45627 | C2: FA1300079 | D2: 3 CORE X 185 SQ. MM AL/ARM - WIRE (XLPE) - 33 KV | E2: STEEL | F2: Copper Tape - 0.045 mm | G2: 873.4 | H2: 149 | I2: 130136.6 | J2: Alumimium | K2: 257 | L2: 1499 | M2: 385243 | P2: 0 | R2: Extruded Semiconductive | S2: 180 | T2: 326 | U2: 58680 | V2: HT-XLPE | W2: 140 | X2: 2040 | Y2: 285600 | AB2: 0 | AD2: PVC Type ST-2-PRESSURE EXTRUDED | AE2: 87 | AF2: 335 | AG2: 29145 | AH2: Galvanised Steel Round Wire | AI2: 90.2 | AJ2: 5745 | AK2: 518199 | AL2: FRLSH PVC Type ST-2 | AM2: 89 | AN2: 1411 | AO2: 125579 | AP2: Polypropylene Filler | AR2: 1838 | AV2: 0 | AX2: Water swellable Tape | AY2: 420 | AZ2: 0 | BA2: 0 | BB2: Semi conducting Water Swellable tape | BC2: 400 | BD2: 0 | BE2: 0 | BH2: 0 | BL2: 0 | BP2: 0 | BR2: RUBBERIZED COTTON TAPE | BS2: 375 | BT2: 0 | BU2: 0 | BX2: 0 | BZ2: 171000 | CA2: 1703582.6 | CH2: 1703582.6 | CM2: 1703582.6 | CO2: 1703582.6 | CP2: 0.18 | CQ2: 306644.87 | CR2: 2010227.5 | CS2: 12.5 | CT2: KMS | CU2: 25127843 | CV2: SP0400081 | CW2: CORRUGATED DISPATCH STEEL DRUM 2500 X 1400 X 1250 MM | CX2: 250
A3: ENQ-15138-22-23 | B3: 45627 | C3: FA1300083 | D3: 3 CORE X 400 SQ. MM. AL/ARM - WIRE (XLPE) - 11 KV | E3: STEEL | F3: Copper Tape - 0.045 mm | G3: 873.4 | H3: 136 | I3: 118782.4 | J3: Alumimium | K3: 257 | L3: 3240 | M3: 832680 | P3: 0 | R3: Extruded Semiconductive | S3: 180 | T3: 366 | U3: 65880 | V3: HT-XLPE | W3: 140 | X3: 908 | Y3: 127120 | AB3: 0 | AD3: PVC Type ST-2-PRESSURE EXTRUDED | AE3: 87 | AF3: 305 | AG3: 26535 | AH3: Galvanised Steel Round Wire | AI3: 90.2 | AJ3: 5335 | AK3: 481217 | AL3: FRLSH PVC Type ST-2 | AM3: 89 | AN3: 1308 | AO3: 116412 | AP3: Polypropylene Filler | AR3: 1535 | AV3: 0 | AX3: Water swellable Tape | AY3: 420 | AZ3: 0 | BA3: 0 | BB3: Semi conducting Water Swellable tape | BC3: 400 | BD3: 64 | BE3: 25600 | BH3: 0 | BL3: 0 | BP3: 0 | BR3: RUBBERIZED COTTON TAPE | BS3: 375 | BT3: 0 | BU3: 0 | BX3: 0 | BZ3: 182400 | CA3: 1976626.4 | CH3: 1976626.4 | CM3: 1976626.4 | CO3: 1976626.4 | CP3: 0.18 | CQ3: 355792.75 | CR3: 2332419.1 | CS3: 314 | CT3: KMS | CU3: 732379614 | CV3: SP0400105 | CW3: CORRUGATED DISPATCH STEEL DRUM 2500 X 1500 X 1400 | CX3: 250
A4: ENQ-15138-22-23 | B4: 45627 | C4: FA1300120 | D4: 3 CORE X 70 SQ. MM. AL/ARM - WIRE (XLPE) - 33 KV | E4: STEEL | F4: Copper Tape - 0.045 mm | G4: 873.4 | H4: 134 | I4: 117035.6 | J4: Alumimium | K4: 257 | L4: 567 | M4: 145719 | P4: 0 | R4: Extruded Semiconductive | S4: 180 | T4: 245 | U4: 44100 | V4: HT-XLPE | W4: 140 | X4: 1561 | Y4: 218540 | AB4: 0 | AD4: PVC Type ST-2-PRESSURE EXTRUDED | AE4: 87 | AF4: 280 | AG4: 24360 | AH4: Galvanised Steel Round Wire | AI4: 90.2 | AJ4: 3818 | AK4: 344383.6 | AL4: FRLSH PVC Type ST-2 | AM4: 89 | AN4: 1124 | AO4: 100036 | AP4: Polypropylene Filler | AR4: 1267 | AV4: 0 | AX4: Water swellable Tape | AY4: 420 | AZ4: 0 | BA4: 0 | BB4: Semi conducting Water Swellable tape | BC4: 400 | BD4: 0 | BE4: 0 | BH4: 0 | BL4: 0 | BP4: 0 | BR4: RUBBERIZED COTTON TAPE | BS4: 375 | BT4: 0 | BU4: 0 | BX4: 0 | BZ4: 171000 | CA4: 1165174.2 | CH4: 1165174.2 | CM4: 1165174.2 | CO4: 1165174.2 | CP4: 0.18 | CQ4: 209731.36 | CR4: 1374905.6 | CS4: 3 | CT4: KMS | CU4: 4124717 | CV4: SP0400136 | CW4: CORRUGATED DISPATCH STEEL DRUM 2200 X 1300 X 1200 MM | CX4: 250
A5: ENQ-15138-22-23 | B5: 45627 | C5: FA1300200 | D5: 3 CORE X 95 SQ. MM. AL/ARM WIRE (XLPE) - 33 KV | E5: STEEL | F5: Copper Tape - 0.045 mm | G5: 873.4 | H5: 129 | I5: 112668.6 | J5: Alumimium | K5: 257 | L5: 770 | M5: 197890 | P5: 0 | R5: Extruded Semiconductive | S5: 180 | T5: 265 | U5: 47700 | V5: HT-XLPE | W5: 140 | X5: 1670 | Y5: 233800 | AB5: 0 | AD5: PVC Type ST-2-PRESSURE EXTRUDED | AE5: 87 | AF5: 292 | AG5: 25404 | AH5: Galvanised Steel Round Wire | AI5: 90.2 | AJ5: 3945 | AK5: 355839 | AL5: FRLSH PVC Type ST-2 | AM5: 89 | AN5: 1228 | AO5: 109292 | AP5: Polypropylene Filler | AR5: 1389 | AV5: 0 | AX5: Water swellable Tape | AY5: 420 | AZ5: 0 | BA5: 0 | BB5: Semi conducting Water Swellable tape | BC5: 400 | BD5: 0 | BE5: 0 | BH5: 0 | BL5: 0 | BP5: 0 | BR5: RUBBERIZED COTTON TAPE | BS5: 375 | BT5: 0 | BU5: 0 | BX5: 0 | BZ5: 147200 | CA5: 1229793.6 | CH5: 1229793.6 | CM5: 1229793.6 | CO5: 1229793.6 | CP5: 0.18 | CQ5: 221362.85 | CR5: 1451156.4 | CS5: 4 | CT5: KMS | CU5: 5804626 | CV5: SP0400136 | CW5: CORRUGATED DISPATCH STEEL DRUM 2200 X 1300 X 1200 MM | CX5: 250
A6: ENQ-15138-22-23 | B6: 45627 | C6: FA1300091 | D6: 3 CORE X 300 SQ. MM. AL/ARM - WIRE (XLPE) - 11 KV | E6: STEEL | F6: Copper Tape - 0.045 mm | G6: 873.4 | H6: 122 | I6: 106554.8 | J6: Alumimium | K6: 257 | L6: 2430 | M6: 624510 | P6: 0 | R6: Extruded Semiconductive | S6: 180 | T6: 337 | U6: 60660 | V6: HT-XLPE | W6: 140 | X6: 802 | Y6: 112280 | AB6: 0 | AD6: PVC Type ST-2-PRESSURE EXTRUDED | AE6: 87 | AF6: 277 | AG6: 24099 | AH6: Galvanised Steel Round Wire | AI6: 90.2 | AJ6: 3753 | AK6: 338520.6 | AL6: FRLSH PVC Type ST-2 | AM6: 89 | AN6: 1120 | AO6: 99680 | AP6: Polypropylene Filler | AR6: 1258 | AV6: 0 | AX6: Water swellable Tape | AY6: 420 | AZ6: 0 | BA6: 0 | BB6: Semi conducting Water Swellable tape | BC6: 400 | BD6: 115 | BE6: 46000 | BH6: 34 | BL6: 0 | BP6: 0 | BR6: RUBBERIZED COTTON TAPE | BS6: 375 | BT6: 0 | BU6: 0 | BX6: 0 | BZ6: 171000 | CA6: 1583304.4 | CH6: 1583304.4 | CM6: 1583304.4 | CO6: 1583304.4 | CP6: 0.18 | CQ6: 284994.79 | CR6: 1868299.2 | CS6: 43 | CT6: KMS | CU6: 80336865 | CV6: SP0400136 | CW6: CORRUGATED DISPATCH STEEL DRUM 2200 X 1300 X 1200 MM | CX6: 250
A7: ENQ-15138-22-23 | B7: 45627 | C7: FA1300090 | D7: 3 CORE X 185 SQ. MM AL/ARM - WIRE (XLPE) - 11 KV | E7: STEEL | F7: Copper Tape - 0.045 mm | G7: 873.4 | H7: 105 | I7: 91707 | J7: Alumimium | K7: 257 | L7: 1499 | M7: 385243 | P7: 0 | R7: Extruded Semiconductive | S7: 180 | T7: 276 | U7: 49680 | V7: HT-XLPE | W7: 140 | X7: 663 | Y7: 92820 | AB7: 0 | AD7: PVC Type ST-2-PRESSURE EXTRUDED | AE7: 87 | AF7: 237 | AG7: 20619 | AH7: Galvanised Steel Round Wire | AI7: 90.2 | AJ7: 3244 | AK7: 292608.8 | AL7: FRLSH PVC Type ST-2 | AM7: 89 | AN7: 862 | AO7: 76718 | AP7: Polypropylene Filler | AR7: 914 | AV7: 0 | AX7: Water swellable Tape | AY7: 420 | AZ7: 0 | BA7: 0 | BB7: Semi conducting Water Swellable tape | BC7: 400 | BD7: 0 | BE7: 0 | BH7: 0 | BL7: 0 | BP7: 0 | BR7: RUBBERIZED COTTON TAPE | BS7: 375 | BT7: 0 | BU7: 0 | BX7: 0 | BZ7: 76000 | CA7: 1085395.8 | CH7: 1085395.8 | CM7: 1085395.8 | CO7: 1085395.8 | CP7: 0.18 | CQ7: 195371.24 | CR7: 1280767 | CS7: 2 | CT7: KMS | CU7: 2561534 | CV7: SP0400111 | CW7: CORRUGATED DISPATCH STEEL DRUM 1900 X 1000 X 1000 MM | CX7: 250
A8: ENQ-15138-22-23 | B8: 45627 | C8: FA1300176 | D8: 3 CORE X 150 SQ. MM. AL/ARM - WIRE (XLPE) - 11 KV | E8: STEEL | F8: Copper Tape - 0.045 mm | G8: 873.4 | H8: 99 | I8: 86466.6 | J8: Alumimium | K8: 257 | L8: 1215 | M8: 312255 | P8: 0 | R8: Extruded Semiconductive | S8: 180 | T8: 246 | U8: 44280 | V8: HT-XLPE | W8: 140 | X8: 620 | Y8: 86800 | AB8: 0 | AD8: PVC Type ST-2-PRESSURE EXTRUDED | AE8: 87 | AF8: 200 | AG8: 17400 | AH8: Galvanised Steel Round Wire | AI8: 90.2 | AJ8: 2404 | AK8: 216840.8 | AL8: FRLSH PVC Type ST-2 | AM8: 89 | AN8: 755 | AO8: 67195 | AP8: Polypropylene Filler | AR8: 809 | AV8: 0 | AX8: Water swellable Tape | AY8: 420 | AZ8: 0 | BA8: 0 | BB8: Semi conducting Water Swellable tape | BC8: 400 | BD8: 162 | BE8: 64800 | BH8: 0 | BL8: 0 | BP8: 0 | BR8: RUBBERIZED COTTON TAPE | BS8: 375 | BT8: 0 | BU8: 0 | BX8: 0 | BZ8: 108300 | CA8: 1004337.4 | CH8: 1004337.4 | CM8: 1004337.4 | CO8: 1004337.4 | CP8: 0.18 | CQ8: 180780.73 | CR8: 1185118.1 | CS8: 4 | CT8: KMS | CU8: 4740473 | CV8: SP0400111 | CW8: CORRUGATED DISPATCH STEEL DRUM 1900 X 1000 X 1000 MM | CX8: 250
A9: ENQ-15138-22-23 | B9: 45627 | C9: FA1300197 | D9: 3 CORE X 120 SQ. MM. AL/ARM - WIRE (XLPE) - 11 KV | E9: STEEL | F9: Copper Tape - 0.045 mm | G9: 873.4 | H9: 93 | I9: 81226.2 | J9: Alumimium | K9: 257 | L9: 972 | M9: 249804 | P9: 0 | R9: Extruded Semiconductive | S9: 180 | T9: 232 | U9: 41760 | V9: HT-XLPE | W9: 140 | X9: 567 | Y9: 79380 | AB9: 0 | AD9: PVC Type ST-2-PRESSURE EXTRUDED | AE9: 87 | AF9: 185 | AG9: 16095 | AH9: Galvanised Steel Round Wire | AI9: 90.2 | AJ9: 2244 | AK9: 202408.8 | AL9: FRLSH PVC Type ST-2 | AM9: 89 | AN9: 669 | AO9: 59541 | AP9: Polypropylene Filler | AR9: 704 | AV9: 0 | AX9: Water swellable Tape | AY9: 420 | AZ9: 0 | BA9: 0 | BB9: Semi conducting Water Swellable tape | BC9: 400 | BD9: 59 | BE9: 23600 | BH9: 0 | BL9: 0 | BP9: 0 | BR9: RUBBERIZED COTTON TAPE | BS9: 375 | BT9: 0 | BU9: 0 | BX9: 0 | BZ9: 95000 | CA9: 848815 | CH9: 848815 | CM9: 848815 | CO9: 848815 | CP9: 0.18 | CQ9: 152786.7 | CR9: 1001601.7 | CS9: 10 | CT9: KMS | CU9: 10016017 | CV9: SP0400118 | CW9: CORRUGATED DISPATCH STEEL DRUM 1700 X 1000 X 1200 | CX9: 250
A10: ENQ-15138-22-23 | B10: 45627 | C10: FA1300088 | D10: 3 CORE X 95 SQ. MM. AL/ARM - WIRE (XLPE) - 11 KV (E) | E10: STEEL | F10: Copper Tape - 0.045 mm | G10: 873.4 | H10: 86 | I10: 75112.4 | J10: Alumimium | K10: 257 | L10: 770 | M10: 197890 | P10: 0 | R10: Extruded Semiconductive | S10: 180 | T10: 173 | U10: 31140 | V10: HT-XLPE | W10: 140 | X10: 525 | Y10: 73500 | AB10: 0 | AD10: PVC Type ST-2-PRESSURE EXTRUDED | AE10: 87 | AF10: 129 | AG10: 11223 | AH10: Galvanised Steel Round Wire | AI10: 90.2 | AJ10: 2001 | AK10: 180490.2 | AL10: FRLSH PVC Type ST-2 | AM10: 89 | AN10: 605 | AO10: 53845 | AP10: FILLER | AQ10: 28 | AR10: 573 | AS10: 16044 | AV10: 0 | AX10: Water swellable Tape | AY10: 420 | AZ10: 0 | BA10: 0 | BB10: Semi conducting Water Swellable tape | BC10: 400 | BD10: 52 | BE10: 20800 | BH10: 0 | BL10: 0 | BP10: 0 | BT10: 0 | BX10: 0 | BZ10: 72000 | CA10: 732044.6 | CH10: 732044.6 | CM10: 732044.6 | CO10: 732044.6 | CP10: 0.18 | CQ10: 131768.03 | CR10: 863812.63 | CS10: 23 | CT10: KMS | CU10: 19867690 | CV10: SP0400110 | CW10: CORRUGATED DISPATCH STEEL DRUM 1600 X 900 X 1000 MM | CX10: 250
A11: ENQ-15138-22-23 | B11: 45627 | C11: FA1300027 | D11: 1 CORE X 630 SQ. MM. AL/ARM (XLPE) - 33 KV | E11: STEEL | F11: Copper Tape - 0.045 mm | G11: 873.4 | H11: 69 | I11: 60264.6 | J11: Alumimium | K11: 257 | L11: 1701 | M11: 437157 | P11: 0 | R11: Extruded Semiconductive | S11: 180 | T11: 172 | U11: 30960 | V11: HT-XLPE | W11: 140 | X11: 1040 | Y11: 145600 | Z11: POLY TAPE | AA11: 123.8 | AB11: 0 | AC11: 0 | AD11: PVC Type ST-2 | AE11: 62 | AF11: 193 | AG11: 11966 | AH11: Aluminium Round Wire | AI11: 262 | AJ11: 800 | AK11: 209600 | AL11: FRLSH PVC Type ST-2 | AM11: 89 | AN11: 738 | AO11: 65682 | AR11: 0 | AV11: 0 | AX11: Water swellable Tape | AY11: 420 | AZ11: 0 | BA11: 0 | BB11: Semi conducting Water Swellable tape | BC11: 400 | BD11: 0 | BE11: 0 | BH11: 0 | BL11: 0 | BP11: 0 | BR11: RUBBERIZED COTTON TAPE | BS11: 375 | BT11: 0 | BU11: 0 | BX11: 0 | BZ11: 53200 | CA11: 1014429.6 | CH11: 1014429.6 | CM11: 1014429.6 | CO11: 1014429.6 | CP11: 0.18 | CQ11: 182597.33 | CR11: 1197026.9 | CS11: 547.5 | CT11: KMS | CU11: 655372243 | CV11: SP0400123 | CW11: CORRUGATED DISPATCH STEEL DRUM 2000 X 1000 X 1200 MM | CX11: 500
A12: ENQ-15138-22-23 | B12: 45627 | C12: FA1300066 | D12: 1 CORE X 1000 SQ. MM. AL/ARM (XLPE) - 11 KV | E12: STEEL | F12: Copper Tape - 0.045 mm | G12: 873.4 | H12: 66 | I12: 57644.4 | J12: Alumimium | K12: 257 | L12: 2732 | M12: 702124 | P12: 0 | R12: Extruded Semiconductive | S12: 180 | T12: 200 | U12: 36000 | V12: HT-XLPE | W12: 140 | X12: 465 | Y12: 65100 | Z12: POLY TAPE | AA12: 123.8 | AB12: 0 | AC12: 0 | AD12: PVC Type ST-2 | AE12: 62 | AF12: 185 | AG12: 11470 | AH12: Aluminium Round Wire | AI12: 262 | AJ12: 773 | AK12: 202526 | AL12: FRLSH PVC Type ST-2 | AM12: 89 | AN12: 655 | AO12: 58295 | AR12: 0 | AV12: 0 | AX12: Water swellable Tape | AY12: 420 | AZ12: 0 | BA12: 0 | BB12: Semi conducting Water Swellable tape | BC12: 400 | BD12: 99 | BE12: 39600 | BH12: 59 | BL12: 0 | BP12: 0 | BR12: RUBBERIZED COTTON TAPE | BS12: 375 | BT12: 52 | BU12: 19500 | BX12: 0 | BZ12: 66500 | CA12: 1258759.4 | CH12: 1258759.4 | CM12: 1258759.4 | CO12: 1258759.4 | CP12: 0.18 | CQ12: 226576.69 | CR12: 1485336.1 | CS12: 1 | CT12: KMS | CU12: 1485336 | CV12: SP0400107 | CW12: CORRUGATED DISPATCH STEEL DRUM 2150 X 1080 X 1240 MM | CX12: 500
A13: ENQ-15138-22-23 | B13: 45627 | C13: FA1300018 | D13: 1 CORE X 400 SQ. MM. AL/ARM (XLPE) - 33 KV | E13: STEEL | F13: Copper Tape - 0.045 mm | G13: 873.4 | H13: 60 | I13: 52404 | J13: Alumimium | K13: 257 | L13: 1080 | M13: 277560 | P13: 0 | R13: Extruded Semiconductive | S13: 180 | T13: 141 | U13: 25380 | V13: HT-XLPE | W13: 140 | X13: 870 | Y13: 121800 | Z13: POLY TAPE | AA13: 123.8 | AB13: 0 | AC13: 0 | AD13: PVC Type ST-2 | AE13: 62 | AF13: 147 | AG13: 9114 | AH13: Aluminium Round Wire | AI13: 262 | AJ13: 702 | AK13: 183924 | AL13: FRLSH PVC Type ST-2 | AM13: 89 | AN13: 575 | AO13: 51175 | AR13: 0 | AV13: 0 | AX13: Water swellable Tape | AY13: 420 | AZ13: 54 | BA13: 22680 | BB13: Semi conducting Water Swellable tape | BC13: 400 | BD13: 0 | BE13: 0 | BH13: 52 | BL13: 0 | BP13: 0 | BR13: RUBBERIZED COTTON TAPE | BS13: 375 | BT13: 0 | BU13: 0 | BX13: 0 | BZ13: 53200 | CA13: 797237 | CH13: 797237 | CM13: 797237 | CO13: 797237 | CP13: 0.18 | CQ13: 143502.66 | CR13: 940739.66 | CS13: 17.5 | CT13: KMS | CU13: 16462944 | CV13: SP0400112 | CW13: CORRUGATED DISPATCH STEEL DRUM 2000 X 1000 X 1000 MM | CX13: 500
A14: ENQ-15138-22-23 | B14: 45627 | C14: FA1300019 | D14: 1 CORE X 300 SQ. MM. AL/ARM (XLPE) - 33 KV | E14: STEEL | F14: Copper Tape - 0.045 mm | G14: 873.4 | H14: 55 | I14: 48037 | J14: Alumimium | K14: 257 | L14: 810 | M14: 208170 | P14: 0 | R14: Extruded Semiconductive | S14: 180 | T14: 128 | U14: 23040 | V14: HT-XLPE | W14: 140 | X14: 792 | Y14: 110880 | Z14: POLY TAPE | AA14: 123.8 | AB14: 0 | AC14: 0 | AD14: PVC Type ST-2 | AE14: 62 | AF14: 138 | AG14: 8556 | AH14: Aluminium Round Wire | AI14: 262 | AJ14: 648 | AK14: 169776 | AL14: FRLSH PVC Type ST-2 | AM14: 89 | AN14: 542 | AO14: 48238 | AR14: 0 | AV14: 0 | AX14: Water swellable Tape | AY14: 420 | AZ14: 0 | BA14: 0 | BB14: Semi conducting Water Swellable tape | BC14: 400 | BD14: 0 | BE14: 0 | BH14: 0 | BL14: 0 | BP14: 0 | BR14: RUBBERIZED COTTON TAPE | BS14: 375 | BT14: 0 | BU14: 0 | BX14: 0 | BZ14: 47500 | CA14: 664197 | CH14: 664197 | CM14: 664197 | CO14: 664197 | CP14: 0.18 | CQ14: 119555.46 | CR14: 783752.46 | CS14: 7 | CT14: KMS | CU14: 5486267 | CV14: SP0400110 | CW14: CORRUGATED DISPATCH STEEL DRUM 1600 X 900 X 1000 MM | CX14: 500
A15: ENQ-15138-22-23 | B15: 45627 | C15: FA1300016 | D15: 1 CORE X 630 SQ. MM. AL/ARM (XLPE) - 11 KV | E15: STEEL | F15: Copper Tape - 0.045 mm | G15: 873.4 | H15: 54 | I15: 47163.6 | J15: Alumimium | K15: 257 | L15: 1701 | M15: 437157 | P15: 0 | R15: Extruded Semiconductive | S15: 180 | T15: 150 | U15: 27000 | V15: HT-XLPE | W15: 140 | X15: 374 | Y15: 52360 | Z15: POLY TAPE | AA15: 123.8 | AB15: 0 | AC15: 0 | AD15: PVC Type ST-2 | AE15: 62 | AF15: 134 | AG15: 8308 | AH15: Aluminium Round Wire | AI15: 262 | AJ15: 511 | AK15: 133882 | AL15: FRLSH PVC Type ST-2 | AM15: 89 | AN15: 472 | AO15: 42008 | AR15: 0 | AV15: 0 | AX15: Water swellable Tape | AY15: 420 | AZ15: 0 | BA15: 0 | BB15: Semi conducting Water Swellable tape | BC15: 400 | BD15: 70 | BE15: 28000 | BH15: 0 | BL15: 0 | BP15: 0 | BR15: RUBBERIZED COTTON TAPE | BS15: 375 | BT15: 0 | BU15: 0 | BX15: 0 | BZ15: 48450 | CA15: 824328.6 | CH15: 824328.6 | CM15: 824328.6 | CO15: 824328.6 | CP15: 0.18 | CQ15: 148379.15 | CR15: 972707.75 | CS15: 11 | CT15: KMS | CU15: 10699785 | CV15: SP0400091 | CW15: CORRUGATED DISPATCH STEEL DRUM 1800 X 900 X 1000 | CX15: 500
A16: ENQ-15138-22-23 | B16: 45627 | C16: FA1300047 | D16: 1 CORE X 400 SQ. MM. AL/ARM (XLPE) - 11 KV | E16: STEEL | F16: Copper Tape - 0.045 mm | G16: 873.4 | H16: 45 | I16: 39303 | J16: Alumimium | K16: 257 | L16: 1080 | M16: 277560 | P16: 0 | R16: Extruded Semiconductive | S16: 180 | T16: 122 | U16: 21960 | V16: HT-XLPE | W16: 140 | X16: 305 | Y16: 42700 | AB16: 0 | AD16: PVC Type ST-2 | AE16: 62 | AF16: 96 | AG16: 5952 | AH16: Aluminium Round Wire | AI16: 262 | AJ16: 423 | AK16: 110826 | AL16: FRLSH PVC Type ST-2 | AM16: 89 | AN16: 376 | AO16: 33464 | AR16: 0 | AV16: 0 | AX16: Water swellable Tape | AY16: 420 | AZ16: 0 | BA16: 0 | BB16: Semi conducting Water Swellable tape | BC16: 400 | BD16: 54 | BE16: 21600 | BH16: 0 | BL16: 0 | BP16: 0 | BT16: 0 | BX16: 0 | BZ16: 34200 | CA16: 587565 | CH16: 587565 | CM16: 587565 | CO16: 587565 | CP16: 0.18 | CQ16: 105761.7 | CR16: 693326.7 | CS16: 4 | CT16: KMS | CU16: 2773307 | CV16: SP0400125 | CW16: CORRUGATED DISPATCH STEEL DRUM 1600 X 700 X 915 MM | CX16: 500
A17: ENQ-15138-22-23 | B17: 45627 | C17: FA1300022 | D17: 3 CORE X 50 SQ. MM. AL/ARD - WIRE (XLPE) - 33 KV (E) | E17: STEEL | F17: Copper Tape - 0.045 mm | G17: 873.4 | J17: Alumimium | K17: 257 | R17: Extruded Semiconductive | S17: 180 | V17: HT-XLPE | W17: 140 | AD17: PVC Type ST-2-PRESSURE EXTRUDED | AE17: 87 | AH17: Galvanised Steel Round Wire | AI17: 90.2 | AL17: FRLSH PVC Type ST-2 | AM17: 89 | AP17: Polypropylene Filler | AX17: Water swellable Tape | AY17: 420 | BB17: Semi conducting Water Swellable tape | BC17: 400 | BR17: RUBBERIZED COTTON TAPE | BS17: 375 | BZ17: 106400 | CA17: 106400 | CH17: 106400 | CM17: 106400 | CO17: 106400 | CP17: 0.18 | CQ17: 19152 | CR17: 125552 | CS17: 5 | CT17: KMS | CU17: 627760 | CV17: SP0400112 | CW17: CORRUGATED DISPATCH STEEL DRUM 2000 X 1000 X 1000 MM | CX17: 250
A18: ENQ-15138-22-23 | B18: 45627 | C18: FA1300297 | D18: 3 CORE X 35 SQ. MM. AL/ARM - WIRE (XLPE) - 33 KV (E) | E18: STEEL | F18: Copper Tape - 0.045 mm | G18: 873.4 | J18: Alumimium | K18: 257 | R18: Extruded Semiconductive | S18: 180 | V18: HT-XLPE | W18: 140 | AD18: PVC Type ST-2-PRESSURE EXTRUDED | AE18: 87 | AH18: Galvanised Steel Round Wire | AI18: 90.2 | AL18: FRLSH PVC Type ST-2 | AM18: 89 | AP18: Polypropylene Filler | AX18: Water swellable Tape | AY18: 420 | BB18: Semi conducting Water Swellable tape | BC18: 400 | BR18: RUBBERIZED COTTON TAPE | BS18: 375 | BZ18: 80000 | CA18: 80000 | CH18: 80000 | CM18: 80000 | CO18: 80000 | CP18: 0.18 | CQ18: 14400 | CR18: 94400 | CS18: 4 | CT18: KMS | CU18: 377600 | CV18: SP0400112 | CW18: CORRUGATED DISPATCH STEEL DRUM 2000 X 1000 X 1000 MM | CX18: 250
A19: ENQ-15138-22-23 | B19: 45627 | C19: FA1300313 | D19: 3 CORE X 50 SQ. MM. AL/ARD - WIRE (XLPE) - 11 KV | H19: 0 | L19: 405 | P19: 0 | T19: 165 | X19: 423 | AB19: 0 | AF19: 130 | AJ19: 1804 | AN19: 520 | AR19: 448 | AV19: 0 | AZ19: 0 | BD19: 0 | BH19: 0 | BL19: 0 | BP19: 0 | BT19: 0 | BX19: 0 | CP19: 0.18 | CS19: 7.5 | CT19: KMS | CX19: 250
A20: ENQ-15138-22-23 | B20: 45627 | C20: FA1300081 | D20: 3 CORE X 300 SQ. MM. AL/ARM - WIRE (XLPE) - 33 KV | E20: STEEL | F20: Copper Tape - 0.045 mm | G20: 873.4 | H20: 165 | I20: 144111 | J20: Alumimium | K20: 257 | L20: 2430 | M20: 624510 | P20: 0 | R20: Extruded Semiconductive | S20: 180 | T20: 386 | U20: 69480 | V20: HT-XLPE | W20: 140 | X20: 2385 | Y20: 333900 | AB20: 0 | AD20: PVC Type ST-2-PRESSURE EXTRUDED | AE20: 87 | AF20: 378 | AG20: 32886 | AH20: Galvanised Steel Round Wire | AI20: 90.2 | AJ20: 6463 | AK20: 582962.6 | AL20: FRLSH PVC Type ST-2 | AM20: 89 | AN20: 1558 | AO20: 138662 | AP20: Polypropylene Filler | AR20: 2315 | AV20: 0 | AX20: Water swellable Tape | AY20: 420 | AZ20: 0 | BA20: 0 | BB20: Semi conducting Water Swellable tape | BC20: 400 | BD20: 0 | BE20: 0 | BH20: 0 | BL20: 0 | BP20: 0 | BR20: RUBBERIZED COTTON TAPE | BS20: 375 | BT20: 0 | BU20: 0 | BX20: 0 | BZ20: 190000 | CA20: 2116511.6 | CH20: 2116511.6 | CM20: 2116511.6 | CO20: 2116511.6 | CP20: 0.18 | CQ20: 380972.09 | CR20: 2497483.7 | CS20: 17.5 | CT20: KMS | CU20: 43705965 | CV20: SP0400137 | CW20: CORRUGATED DISPATCH STEEL DRUM 2600 X 1600 X 1600 | CX20: 250
A21: ENQ-15138-22-23 | B21: 45627 | C21: FA1300080 | D21: 3 CORE X 400 SQ. MM AL/ARM - WIRE (XLPE) - 33 KV | E21: STEEL | F21: Copper Tape - 0.045 mm | G21: 873.4 | H21: 179 | I21: 156338.6 | J21: Alumimium | K21: 257 | L21: 3240 | M21: 832680 | P21: 0 | R21: Extruded Semiconductive | S21: 180 | T21: 427 | U21: 76860 | V21: HT-XLPE | W21: 140 | X21: 2621 | Y21: 366940 | AB21: 0 | AD21: PVC Type ST-2-PRESSURE EXTRUDED | AE21: 87 | AF21: 405 | AG21: 35235 | AH21: Galvanised Steel Round Wire | AI21: 90.2 | AJ21: 6975 | AK21: 629145 | AL21: FRLSH PVC Type ST-2 | AM21: 89 | AN21: 1660 | AO21: 147740 | AP21: Polypropylene Filler | AR21: 2672 | AV21: 0 | AX21: Water swellable Tape | AY21: 420 | AZ21: 120 | BA21: 50400 | BB21: Semi conducting Water Swellable tape | BC21: 400 | BD21: 0 | BE21: 0 | BH21: 144 | BL21: 0 | BP21: 0 | BR21: RUBBERIZED COTTON TAPE | BS21: 375 | BT21: 0 | BU21: 0 | BX21: 0 | BZ21: 190000 | CA21: 2485338.6 | CH21: 2485338.6 | CM21: 2485338.6 | CO21: 2485338.6 | CP21: 0.18 | CQ21: 447360.95 | CR21: 2932699.5 | CS21: 222.75 | CT21: KMS | CU21: 653258824 | CV21: SP0400137 | CW21: CORRUGATED DISPATCH STEEL DRUM 2600 X 1600 X 1600 MM | CX21: 250
A22: DOCKET NO. | B22: Base Date | C22: ITEM CODE | D22: PROPOSE ERP ITEM NAME | E22: Propose Drum Type | F22: Insulation Screening(Metallic) | G22: RM Rate(Insulation Screening(Metallic)) | H22: Weight (Insulation Screening (Metallic)) | I22: Cost Insulation Screening(Metallic) | J22: Conductor | K22: RM Rate(Conductor) | L22: Weight(Conductor) | M22: Cost(Conductor) | N22: AL ALLOY | O22: RM Rate(AL Alloy) | P22: Weight(Al Alloy) | Q22: Cost(AL Alloy) | R22: Insulation Screening(Non-Metallic) | S22: RM Rate(Insulation Screening(Non-Metallic)) | T22: Weight(Insulation Screening(Non-Metallic) | U22: Cost(Insulation Screening(Non-Metallic) | V22: Insulation | W22: RM Rate(Insulation) | X22: Weight(Insulation) | Y22: Cost(Insulation) | Z22: Poly Tape | AA22: RM Rate(Poly Tape) | AB22: Weight(Poly Tape) | AC22: Cost(Poly Tape) | AD22: Inner Sheath | AE22: RM Rate(Inner Sheath) | AF22: Weight(Inner Sheath) | AG22: Cost(Inner Sheath) | AH22: Armouring | AI22: RM Rate(Armouring) | AJ22: Weight(Armouring) | AK22: Cost(Armouring) | AL22: Outer Sheath | AM22: RM Rate(Outer Sheath) | AN22: Weight(Outer Sheath) | AO22: Cost(Outer Sheath) | AP22: Filler | AQ22: RM Rate(Filler) | AR22: Weight(Filler) | AS22: Cost(Filler) | AT22: Grease | AU22: RM Rate(Grease) | AV22: Weight(Grease) | AW22: Cost(Grease) | AX22: Water Swellable Tape | AY22: RM Rate(Water Swellable Tape) | AZ22: Weight(Water Swellable Tape) | BA22: Cost(Water Swellable Tape) | BB22: Semi Conducting Water Swellable Tape | BC22: RM Rate(Semi Conducting Water Swellable Tape) | BD22: Weight(Semi Conducting Water Swellable Tape) | BE22: Cost(Semi Conducting Water Swellable Tape) | BF22: Semicon Tape | BG22: RM Rate(Semicon Tape) | BH22: Weight(Semicon Tape) | BI22: Cost(Semicon Tape) | BJ22: Glass Fiber Tape | BK22: RM Rate(Glass Fiber Tape) | BL22: Weight(Glass Fiber Tape) | BM22: Cost(Glass Fiber Tape) | BN22: Copper Wire 0.8MM | BO22: RM Rate(Copper Wire 0.8MM) | BP22: Weight(Copper Wire 0.8MM) | BQ22: Cost(Copper Wire 0.8MM) | BR22: Rubberized Cotton Tape | BS22: RM Rate(Rubberized Cotton Tape) | BT22: Weight(Rubberized Cotton Tape) | BU22: Cost(Rubberized Cotton Tape) | BV22: Water Tight Compound | BW22: RM Rate(Water Tight Compound) | BX22: Weight(Water Tight Compound) | BY22: Cost(Water Tight Compound) | BZ22: Drum Cost Per KM | CA22: Total RM Cost | CB22: FIRM % | CC22: Firm Value | CD22: MFG% | CE22: MFG Value | CF22: PROF% | CG22: Profit Value | CH22: 1st EX-Works | CI22: Intt % | CJ22: Intt Value | CK22: insp% | CL22: Insp Value | CM22: EX-Works Per KM | CN22: Freight Per KM | CO22: Price Including Freight Per KM | CP22: GST % | CQ22: GST Value | CR22: Price Including GST & Freight Per KM | CS22: QTY | CT22: Unit | CU22: Total Price Of Full QTY(Including Freight&GST) | CV22: DRUM CODE | CW22: DRUM SIZE (FxbXtx Ft) | CX22: Party Standard Length(MTR)
A23: ENQ-15138-22-23 | B23: 45627 | C23: FA1300009 | D23: 1 CORE X 300 SQ. MM. AL./ARM (XLPE) - 11 KV | E23: STEEL | F23: Copper Tape - 0.045 mm | G23: 873.4 | H23: 41 | I23: 35809.4 | J23: Alumimium | K23: 257 | L23: 810 | M23: 208170 | P23: 0 | R23: Extruded Semiconductive | S23: 180 | T23: 112 | U23: 20160 | V23: HT-XLPE | W23: 140 | X23: 267 | Y23: 37380 | Z23: POLY TAPE | AA23: 123.8 | AB23: 0 | AC23: 0 | AD23: PVC Type ST-2 | AE23: 62 | AF23: 87 | AG23: 5394 | AH23: Aluminium Round Wire | AI23: 262 | AJ23: 388 | AK23: 101656 | AL23: FRLSH PVC Type ST-2 | AM23: 89 | AN23: 318 | AO23: 28302 | AR23: 0 | AV23: 0 | AX23: Water swellable Tape | AY23: 420 | AZ23: 0 | BA23: 0 | BB23: Semi conducting Water Swellable tape | BC23: 400 | BD23: 38 | BE23: 15200 | BH23: 0 | BL23: 0 | BP23: 0 | BR23: RUBBERIZED COTTON TAPE | BS23: 375 | BT23: 0 | BU23: 0 | BX23: 0 | BZ23: 27000 | CA23: 479071.4 | CH23: 479071.4 | CM23: 479071.4 | CO23: 479071.4 | CP23: 0.18 | CQ23: 86232.85 | CR23: 565304.25 | CS23: 6.5 | CT23: KMS | CU23: 3674478 | CV23: SP0400152 | CW23: CORRUGATED DISPATCH STEEL DRUM 1500 X 800 X 915 | CX23: 500

Sheet AUTO CALCULATION SHEET (2)
A2: TP Odisha DISCOMs
A4: TENDER SPECIFICATION NO () | B4: TPCODL / CCG / FY 24-25 / 1000001767
A5: TENDER DESCRIPTION () | B5: One Year Rate Contract for supply of HT Cables at TPCODL, TPNODL, TPSODL & TPWODL
A6: Last Date & Time of Submission () | B6: 17.02.2025 [16:00 Hrs]
A7: REVERSE AUCTION | B7: No of bidders allowed to participate in RA process shall be: Total No of bidders on whom tender would be split PLUS 2 more bidders. Illustrative example: Total no of qualified bidders is 10 & tender needs to split amongst 4 bidders.
A8: Price () | B8: The line-item prices shall be subject to Price Variation clause as per latest IEEMA Circular. (Base Date of IEEMA for price consideration shall be Dec-24).
A9: Validity () | B9: Bids shall remain valid for 180 days from the due date of submission of the bid. Notwithstanding clause above, CCG may solicit the Bidder’s consent to an extension of the Period of Bid Validity. The request and responses thereto shall be made in writing.
A10: Delivery Period () | B10: The delivery period for a quantity of up to 40 KM shall be 90 days from the date of issuance of the RO or GTP drawing approval, whichever is later.
A11: Payment Terms () | B11: 100% payment will be made within 60 days of submission of error-free certified invoice complete in all respects. For MSME payment cycle shall be within 45 days.
A12: Standard length () | B12: Cable length on one drum shall be 250 meters for 3 core cables & 500 meters for 1 core cables max. +/- 5%. (As per PO Terms.)
A13: Packing () | B13: Steel drums shall be provided. Drum shall be free from sharp edges and visual defect. Stencil plate on one flange side of the drum and laminated paper sheet on other side flange of drum.
A14: Technical Specification
N16: =Sheet1!J1 -> Conductor | S16: AL ALLOY | U16: Insulation Screening (Metallic) | AC16: Insulation Screening (Non-Metallic) | AE16: Insulation | AK16: POLY TAPE | AL16: Inner Sheath | AS16: Armouring | BC16: Outer Sheath | BF16: Rs. 15/kg extra | BM16: FILLER | BN16: GREASE | BO16: Water swellable Tape | BP16: Semi conducting Water Swellable tape | BQ16: SEMICON TAPE | BR16: GLASS FIBER TAPE | BS16: COPPER WIRE 0.8 MM | BT16: RUBBERIZED COTTON TAPE | BU16: Water Tight Compound | BZ16: DRUM COST PER KM | CA16: TOTAL RM COST | CB16: EXTRA CONSUMPTION | CC16: EXTRA CONSUMPTION VALUE
A17: DOCKET NO. | B17: =Sheet1!B1 -> Base Date | C17: ITEM CODE | D17: PROPOSE ERP ITEM NAME | E17: EX-WORKS (PER KM) | F17: FREIGHT PER KM | G17: PRICE INCLUDING FREIGHT (PER KM) | H17: GST % | I17: GST VALUE | J17: PRICE INCLUDING GST & FREIGHT (PER KM) | K17: QTY | L17: Unit | M17: TOTAL PRICE OF FULL QTY (INCLUDING FRIGHT & GST) | N17: Alumimium | O17: Alumimium ALLOY | P17: Copper | Q17: Flexible Copper | R17: Galvanized steel wire | S17: Alumimium | T17: Alumimium ALLOY | U17: Coper tape - 0.1 mm | V17: Copper Tape - 0.03 mm | W17: Copper Tape - 0.035 mm | X17: Copper Tape - 0.04 mm | Y17: Copper Tape - 0.045 mm | Z17: Copper Tape - 0.050 mm | AA17: Copper Tape - 0.060 mm | AB17: Copper Tape - 0.075 mm(DOUBLE) | AC17: Extruded semiconductive | AD17: Extruded Semiconductive(Stripable) | AE17: HT-XLPE | AF17: LT-XLPE | AG17: TR XLPE | AH17: Type A PVC | AI17: Type C PVC (HR) | AJ17: XLPE | AK17: POLY TAPE | AL17: FR PVC Type ST-1 | AM17: FR PVC Type ST-2 | AN17: FRLSH PVC Type ST-2 | AO17: PVC Type ST-1 | AP17: PVC Type ST-1-PRESSURE EXTRUDED | AQ17: PVC Type ST-2 | AR17: PVC Type ST-2-PRESSURE EXTRUDED | AS17: ACSR CORE WIRE | AT17: ACSR DOG STEEL WIRE | AU17: Aluminium Flat Strip | AV17: Aluminium Round Wire | AW17: Double Steel Tape | AX17: Galvanised Steel Flat Strip | AY17: Galvanised Steel Flat Strip (Double) | AZ17: Galvanised Steel Flat Strip-B | BA17: Galvanised Steel Round Wire | BB17: Galvanised Steel Round Wire (Double) | BC17: FR PVC Type ST-1 | BD17: FR PVC Type ST-2 | BE17: FRLSH PVC Type ST-1 | BF17: FRLSH PVC Type ST-2 | BG17: PE, ST-3 | BH17: PE, ST-7 | BI17: PVC Type ST-1 | BJ17: PVC Type ST-2 | BK17: PVC Type ST-2-PRESSURE EXTRUDED | BL17: PP FILLER | BM17: FILLER | BN17: NCWBT | BO17: Water swellable Tape | BP17: Semi conducting Water Swellable tape | BQ17: SEMICON TAPE | BR17: GLASS FIBER TAPE | BS17: COPPER WIRE 0.8 MM | BT17: RUBBERIZED COTTON TAPE | BU17: Water Tight Compound | BV17: =Sheet1!E1 -> Propose Drum Type | BW17: =Sheet1!CV1 -> DRUM CODE | BX17: =Sheet1!CW1 -> DRUM SIZE (FxbXtx Ft) | BY17: =Sheet1!CX1 -> Party Standard Length(MTR) | CB17: Consider 1% extra cost for complete cable . | CD17: MFG% | CE17: MFG VALUE | CF17: PROF% | CG17: PROFIT VALUE | CH17: 1ST EX-WORKS | CI17: Intt % | CJ17: INTT VALUE | CK17: insp% | CL17: INSP VALUE
N18: 256 | O18: =+IFERROR(VLOOKUP($O$17,Sheet1!J:L,2,0),0) -> 0 | P18: =+IFERROR(VLOOKUP($P$17,Sheet1!J:M,2,0),0) -> 0 | Q18: =+IFERROR(VLOOKUP($Q$17,Sheet1!J:M,2,0),0) -> 0 | R18: =+IFERROR(VLOOKUP($R$17,Sheet1!J:M,2,0),0) -> 0 | S18: =+IFERROR(VLOOKUP($S$17,Sheet1!N:Q,2,0),0) -> 0 | T18: =+IFERROR(VLOOKUP($T$17,Sheet1!N:O,2,0),0) -> 0 | U18: =+IFERROR(VLOOKUP($U$17,Sheet1!F:I,2,0),0) -> 0 | V18: =+IFERROR(VLOOKUP($V$17,Sheet1!F:I,2,0),0) -> 0 | W18: =+IFERROR(VLOOKUP($W$17,Sheet1!F:I,2,0),0) -> 0 | X18: =+IFERROR(VLOOKUP($X$17,Sheet1!F:I,2,0),0) -> 0 | Y18: 924 | Z18: =+IFERROR(VLOOKUP($Z$17,Sheet1!F:I,2,0),0) -> 0 | AA18: =+IFERROR(VLOOKUP($AA$17,Sheet1!F:I,2,0),0) -> 0 | AB18: =+IFERROR(VLOOKUP($AB$17,Sheet1!F:I,2,0),0) -> 0 | AC18: =+IFERROR(VLOOKUP($AC$17,Sheet1!R:U,2,0),0) -> 180 | AD18: =+IFERROR(VLOOKUP($AD$17,Sheet1!R:U,2,0),0) -> 0 | AE18: =+IFERROR(VLOOKUP($AE$17,Sheet1!V:Y,2,0),0) -> 140 | AF18: =+IFERROR(VLOOKUP($AF$17,Sheet1!V:Y,2,0),0) -> 0 | AG18: =+IFERROR(VLOOKUP($AG$17,Sheet1!V:Y,2,0),0) -> 0 | AH18: =+IFERROR(VLOOKUP($AH$17,Sheet1!V:Y,2,0),0) -> 0 | AI18: =+IFERROR(VLOOKUP($AI$17,Sheet1!V:Y,2,0),0) -> 0 | AJ18: =+IFERROR(VLOOKUP($AJ$17,Sheet1!V:Y,2,0),0) -> 0 | AK18: 124 | AL18: =+IFERROR(VLOOKUP($AL$17,Sheet1!AD2:AG840,2,0),0) -> 0 | AM18: =+IFERROR(VLOOKUP($AM$17,Sheet1!AD2:AG840,2,0),0) -> 0 | AN18: =+IFERROR(VLOOKUP($AN$17,Sheet1!AD2:AG840,2,0),0) -> 0 | AO18: =+IFERROR(VLOOKUP($AO$17,Sheet1!AD2:AG840,2,0),0) -> 0 | AP18: =+IFERROR(VLOOKUP($AP$17,Sheet1!AD2:AG840,2,0),0) -> 0 | AQ18: 69 | AS18: =+IFERROR(VLOOKUP($AS$17,Sheet1!AH2:AK840,2,0),0) -> 0 | AT18: =+IFERROR(VLOOKUP($AT$17,Sheet1!AH2:AK840,2,0),0) -> 0 | AU18: =+IFERROR(VLOOKUP($AU$17,Sheet1!AH2:AK840,2,0),0) -> 0 | AV18: 261 | AW18: =+IFERROR(VLOOKUP($AW$17,Sheet1!AH2:AK840,2,0),0) -> 0 | AX18: =+IFERROR(VLOOKUP($AX$17,Sheet1!AH2:AK840,2,0),0) -> 0 | AY18: =+IFERROR(VLOOKUP($AY$17,Sheet1!AH2:AK840,2,0),0) -> 0 | AZ18: =+IFERROR(VLOOKUP($AZ$17,Sheet1!AH2:AK840,2,0),0) -> 0 | BA18: 89 | BB18: =+IFERROR(VLOOKUP($BB$17,Sheet1!AH2:AK840,2,0),0) -> 0 | BC18: =+IFERROR(VLOOKUP($BC$17,Sheet1!AL2:AO840,2,0),0) -> 0 | BD18: =+IFERROR(VLOOKUP($BD$17,Sheet1!AL2:AO840,2,0),0) -> 0 | BE18: =+IFERROR(VLOOKUP($BE$17,Sheet1!AL2:AO840,2,0),0) -> 0 | BF18: =90+15 -> 105 | BG18: =+IFERROR(VLOOKUP($BG$17,Sheet1!AL2:AO840,2,0),0) -> 0 | BH18: =+IFERROR(VLOOKUP($BH$17,Sheet1!AL2:AO840,2,0),0) -> 0 | BI18: =+IFERROR(VLOOKUP($BI$17,Sheet1!AL2:AO840,2,0),0) -> 0 | BJ18: =+IFERROR(VLOOKUP($BJ$17,Sheet1!AL2:AO840,2,0),0) -> 0 | BK18: =+IFERROR(VLOOKUP($BK$17,Sheet1!AL2:AO840,2,0),0) -> 0 | BL18: 85 | BN18: 340 | BP18: =+IFERROR(VLOOKUP($BP$17,Sheet1!BB2:BE840,2,0),0) -> 400 | BQ18: =+IFERROR(VLOOKUP($BQ$17,Sheet1!BF2:BI840,2,0),0) -> RM Rate(Semicon Tape) | BR18: =+IFERROR(VLOOKUP($BR$17,Sheet1!BJ2:BM840,2,0),0) -> RM Rate(Glass Fiber Tape) | BS18: =+IFERROR(VLOOKUP($BS$17,Sheet1!BN2:BQ840,2,0),0) -> 0 | BT18: =+IFERROR(VLOOKUP($BT$17,Sheet1!BR2:BU840,2,0),0) -> 375 | BU18: =+IFERROR(VLOOKUP($BU$17,Sheet1!BV2:BY840,2,0),0) -> RM Rate(Water Tight Compound) | BX18: Non Returnable Steel Drum
A19: =Sheet1!A3 -> ENQ-15138-22-23 | B19: =Sheet1!B3 -> 45627 | C19: =Sheet1!C3 -> FA1300083 | D19: =Sheet1!D3 -> 3 CORE X 400 SQ. MM. AL/ARM - WIRE (XLPE) - 11 KV | E19: =CH19+CJ19+CL19 -> 2890355 | F19: =ROUNDUP(M43,0) -> 52166 | G19: =E19+F19 -> 2942521 | H19: =Sheet1!CP3 -> 0.18 | I19: =G19*H19 -> 529653.79 | J19: =G19+I19 -> 3472174.8 | K19: =Sheet1!CS3 -> 314 | L19: =Sheet1!CT3 -> KMS | M19: =J19*K19 -> 1.0902629e+09 | N19: =+IFERROR(VLOOKUP($N$17,Sheet1!J3:L3,3,0),0) -> 3240 | O19: =+IFERROR(VLOOKUP($O$17,Sheet1!J3:L3,3,0),0) -> 0 | P19: =+IFERROR(VLOOKUP($P$17,Sheet1!J3:M3,3,0),0) -> 0 | Q19: =+IFERROR(VLOOKUP($Q$17,Sheet1!J3:M3,3,0),0) -> 0 | R19: =+IFERROR(VLOOKUP($R$17,Sheet1!J3:M3,3,0),0) -> 0 | S19: =+IFERROR(VLOOKUP($S$17,Sheet1!N3:Q3,3,0),0) -> 0 | T19: =+IFERROR(VLOOKUP($T$17,Sheet1!N3:Q3,3,0),0) -> 0 | U19: =+IFERROR(VLOOKUP($U$17,Sheet1!F3:I3,3,0),0) -> 0 | V19: =+IFERROR(VLOOKUP($V$17,Sheet1!F3:I3,3,0),0) -> 0 | W19: =+IFERROR(VLOOKUP($W$17,Sheet1!F3:I3,3,0),0) -> 0 | X19: =+IFERROR(VLOOKUP($X$17,Sheet1!F3:I3,3,0),0) -> 0 | Y19: 176 | Z19: =+IFERROR(VLOOKUP($Z$17,Sheet1!F3:I3,3,0),0) -> 0 | AA19: =+IFERROR(VLOOKUP($AA$17,Sheet1!F3:I3,3,0),0) -> 0 | AB19: =+IFERROR(VLOOKUP($AB$17,Sheet1!F3:I3,3,0),0) -> 0 | AC19: 518 | AD19: =+IFERROR(VLOOKUP($AD$17,Sheet1!R3:U3,2,0),0) -> 0 | AE19: 930 | AF19: =+IFERROR(VLOOKUP($AF$17,Sheet1!V3:Y3,3,0),0) -> 0 | AG19: =+IFERROR(VLOOKUP($AG$17,Sheet1!V3:Y3,3,0),0) -> 0 | AH19: =+IFERROR(VLOOKUP($AH$17,Sheet1!V3:Y3,3,0),0) -> 0 | AI19: =+IFERROR(VLOOKUP($AI$17,Sheet1!V3:Y3,3,0),0) -> 0 | AJ19: =+IFERROR(VLOOKUP($AJ$17,Sheet1!V3:Y3,3,0),0) -> 0 | AK19: =+IFERROR(VLOOKUP($AK$17,Sheet1!Z3:AB3,3,0),0) -> 0 | AL19: =+IFERROR(VLOOKUP($AL$17,Sheet1!AD3:AG3,3,0),0) -> 0 | AM19: =+IFERROR(VLOOKUP($AM$17,Sheet1!AD3:AG3,3,0),0) -> 0 | AN19: =+IFERROR(VLOOKUP($AN$17,Sheet1!AD3:AG3,3,0),0) -> 0 | AO19: =+IFERROR(VLOOKUP($AO$17,Sheet1!AD3:AG3,3,0),0) -> 0 | AP19: =+IFERROR(VLOOKUP($AP$17,Sheet1!AD3:AG3,3,0),0) -> 0 | AQ19: 1027 | AS19: =+IFERROR(VLOOKUP($AS$17,Sheet1!AH3:AK3,3,0),0) -> 0 | AT19: =+IFERROR(VLOOKUP($AT$17,Sheet1!AH3:AK3,3,0),0) -> 0 | AU19: =+IFERROR(VLOOKUP($AU$17,Sheet1!AH3:AK3,3,0),0) -> 0 | AV19: =+IFERROR(VLOOKUP($AV$17,Sheet1!AH3:AK3,3,0),0) -> 0 | AW19: =+IFERROR(VLOOKUP($AW$17,Sheet1!AH3:AK3,3,0),0) -> 0 | AX19: =+IFERROR(VLOOKUP($AX$17,Sheet1!AH3:AK3,3,0),0) -> 0 | AY19: =+IFERROR(VLOOKUP($AY$17,Sheet1!AH3:AK3,3,0),0) -> 0 | AZ19: =+IFERROR(VLOOKUP($AZ$17,Sheet1!AH3:AK3,3,0),0) -> 0 | BA19: 5643 | BB19: =+IFERROR(VLOOKUP($BB$17,Sheet1!AH3:AK3,3,0),0) -> 0 | BC19: =+IFERROR(VLOOKUP($BC$17,Sheet1!AL3:AO3,3,0),0) -> 0 | BD19: =+IFERROR(VLOOKUP($BD$17,Sheet1!AL3:AO3,3,0),0) -> 0 | BE19: =+IFERROR(VLOOKUP($BE$17,Sheet1!AL3:AO3,3,0),0) -> 0 | BF19: 1377 | BG19: =+IFERROR(VLOOKUP($BG$17,Sheet1!AL3:AO3,3,0),0) -> 0 | BH19: =+IFERROR(VLOOKUP($BH$17,Sheet1!AL3:AO3,3,0),0) -> 0 | BI19: =+IFERROR(VLOOKUP($BI$17,Sheet1!AL3:AO3,3,0),0) -> 0 | BJ19: =+IFERROR(VLOOKUP($BJ$17,Sheet1!AL3:AO3,3,0),0) -> 0 | BK19: =+IFERROR(VLOOKUP($BK$17,Sheet1!AL3:AO3,3,0),0) -> 0 | BL19: 1032 | BM19: =+IFERROR(VLOOKUP($BM$17,Sheet1!AP3:AS3,3,0),0) -> 0 | BN19: 58 | BO19: =+IFERROR(VLOOKUP($BO$17,Sheet1!AX3:BA3,3,0),0) -> 0 | BP19: 95 | BQ19: =+IFERROR(VLOOKUP($BQ$17,Sheet1!BF3:BI3,3,0),0) -> 0 | BR19: =+IFERROR(VLOOKUP($BR$17,Sheet1!BJ3:BM3,3,0),0) -> 0 | BS19: =+IFERROR(VLOOKUP($BS$17,Sheet1!BN3:BQ3,3,0),0) -> 0 | BT19: 60 | BU19: =+IFERROR(VLOOKUP($BU$17,Sheet1!BV3:BY3,3,0),0) -> 0 | BV19: =Sheet1!E3 -> STEEL | BW19: SP0400136 | BX19: CORRUGATED DISPATCH STEEL DRUM 2200 X 1300 X 1200 MM | BY19: =Sheet1!CX3 -> 250 | BZ19: =31500/0.25 -> 126000 | CA19: =SUMPRODUCT($N$18:$BU$18,N19:BU19)+BZ19 -> 2227119 | CB19: 0.01 | CC19: =CA19*CB19 -> 22271.19 | CD19: 0.25 | CE19: =CA19*CD19 -> 556779.75 | CF19: =Sheet1!CF3 -> 0 | CG19: =CA19*CF19 -> 0 | CH19: =CA19+CC19+CE19+CG19 -> 2806169.9 | CI19: 0.02 | CJ19: =CH19*CI19 -> 56123.399 | CK19: 0.01 | CL19: =CH19*CK19 -> 28061.699
A20: =Sheet1!A6 -> ENQ-15138-22-23 | B20: =Sheet1!B6 -> 45627 | C20: =Sheet1!C6 -> FA1300091 | D20: =Sheet1!D6 -> 3 CORE X 300 SQ. MM. AL/ARM - WIRE (XLPE) - 11 KV | E20: =CH20+CJ20+CL20 -> 2318788.3 | F20: =ROUNDUP(M44,0) -> 52907 | G20: =E20+F20 -> 2371695.3 | H20: =Sheet1!CP6 -> 0.18 | I20: =G20*H20 -> 426905.16 | J20: =G20+I20 -> 2798600.5 | K20: =Sheet1!CS6 -> 43 | L20: =Sheet1!CT6 -> KMS | M20: =J20*K20 -> 1.2033982e+08 | N20: =+IFERROR(VLOOKUP($N$17,Sheet1!J6:L6,3,0),0) -> 2430 | O20: =+IFERROR(VLOOKUP($O$17,Sheet1!J6:L6,3,0),0) -> 0 | P20: =+IFERROR(VLOOKUP($P$17,Sheet1!J6:M6,3,0),0) -> 0 | Q20: =+IFERROR(VLOOKUP($Q$17,Sheet1!J6:M6,3,0),0) -> 0 | R20: =+IFERROR(VLOOKUP($R$17,Sheet1!J6:M6,3,0),0) -> 0 | S20: =+IFERROR(VLOOKUP($S$17,Sheet1!N6:Q6,3,0),0) -> 0 | T20: =+IFERROR(VLOOKUP($T$17,Sheet1!N6:Q6,3,0),0) -> 0 | U20: =+IFERROR(VLOOKUP($U$17,Sheet1!F6:I6,3,0),0) -> 0 | V20: =+IFERROR(VLOOKUP($V$17,Sheet1!F6:I6,3,0),0) -> 0 | W20: =+IFERROR(VLOOKUP($W$17,Sheet1!F6:I6,3,0),0) -> 0 | X20: =+IFERROR(VLOOKUP($X$17,Sheet1!F6:I6,3,0),0) -> 0 | Y20: 161 | Z20: =+IFERROR(VLOOKUP($Z$17,Sheet1!F6:I6,3,0),0) -> 0 | AA20: =+IFERROR(VLOOKUP($AA$17,Sheet1!F6:I6,3,0),0) -> 0 | AB20: =+IFERROR(VLOOKUP($AB$17,Sheet1!F6:I6,3,0),0) -> 0 | AC20: 465 | AD20: =+IFERROR(VLOOKUP($AD$17,Sheet1!R6:U6,2,0),0) -> 0 | AE20: 835 | AF20: =+IFERROR(VLOOKUP($AF$17,Sheet1!V6:Y6,3,0),0) -> 0 | AG20: =+IFERROR(VLOOKUP($AG$17,Sheet1!V6:Y6,3,0),0) -> 0 | AH20: =+IFERROR(VLOOKUP($AH$17,Sheet1!V6:Y6,3,0),0) -> 0 | AI20: =+IFERROR(VLOOKUP($AI$17,Sheet1!V6:Y6,3,0),0) -> 0 | AJ20: =+IFERROR(VLOOKUP($AJ$17,Sheet1!V6:Y6,3,0),0) -> 0 | AK20: =+IFERROR(VLOOKUP($AK$17,Sheet1!Z6:AB6,3,0),0) -> 0 | AL20: =+IFERROR(VLOOKUP($AL$17,Sheet1!AD6:AG6,3,0),0) -> 0 | AM20: =+IFERROR(VLOOKUP($AM$17,Sheet1!AD6:AG6,3,0),0) -> 0 | AN20: =+IFERROR(VLOOKUP($AN$17,Sheet1!AD6:AG6,3,0),0) -> 0 | AO20: =+IFERROR(VLOOKUP($AO$17,Sheet1!AD6:AG6,3,0),0) -> 0 | AP20: =+IFERROR(VLOOKUP($AP$17,Sheet1!AD6:AG6,3,0),0) -> 0 | AQ20: 885 | AS20: =+IFERROR(VLOOKUP($AS$17,Sheet1!AH6:AK6,3,0),0) -> 0 | AT20: =+IFERROR(VLOOKUP($AT$17,Sheet1!AH6:AK6,3,0),0) -> 0 | AU20: =+IFERROR(VLOOKUP($AU$17,Sheet1!AH6:AK6,3,0),0) -> 0 | AV20: =+IFERROR(VLOOKUP($AV$17,Sheet1!AH6:AK6,3,0),0) -> 0 | AW20: =+IFERROR(VLOOKUP($AW$17,Sheet1!AH6:AK6,3,0),0) -> 0 | AX20: =+IFERROR(VLOOKUP($AX$17,Sheet1!AH6:AK6,3,0),0) -> 0 | AY20: =+IFERROR(VLOOKUP($AY$17,Sheet1!AH6:AK6,3,0),0) -> 0 | AZ20: =+IFERROR(VLOOKUP($AZ$17,Sheet1!AH6:AK6,3,0),0) -> 0 | BA20: 4072 | BB20: =+IFERROR(VLOOKUP($BB$17,Sheet1!AH6:AK6,3,0),0) -> 0 | BC20: =+IFERROR(VLOOKUP($BC$17,Sheet1!AL6:AO6,3,0),0) -> 0 | BD20: =+IFERROR(VLOOKUP($BD$17,Sheet1!AL6:AO6,3,0),0) -> 0 | BE20: =+IFERROR(VLOOKUP($BE$17,Sheet1!AL6:AO6,3,0),0) -> 0 | BF20: 1190 | BG20: =+IFERROR(VLOOKUP($BG$17,Sheet1!AL6:AO6,3,0),0) -> 0 | BH20: =+IFERROR(VLOOKUP($BH$17,Sheet1!AL6:AO6,3,0),0) -> 0 | BI20: =+IFERROR(VLOOKUP($BI$17,Sheet1!AL6:AO6,3,0),0) -> 0 | BJ20: =+IFERROR(VLOOKUP($BJ$17,Sheet1!AL6:AO6,3,0),0) -> 0 | BK20: =+IFERROR(VLOOKUP($BK$17,Sheet1!AL6:AO6,3,0),0) -> 0 | BL20: 862 | BM20: =+IFERROR(VLOOKUP($BM$17,Sheet1!AP6:AS6,3,0),0) -> 0 | BN20: 38 | BO20: =+IFERROR(VLOOKUP($BO$17,Sheet1!AX6:BA6,3,0),0) -> 0 | BP20: 86 | BQ20: =+IFERROR(VLOOKUP($BQ$17,Sheet1!BF6:BI6,3,0),0) -> 0 | BR20: =+IFERROR(VLOOKUP($BR$17,Sheet1!BJ6:BM6,3,0),0) -> 0 | BS20: =+IFERROR(VLOOKUP($BS$17,Sheet1!BN6:BQ6,3,0),0) -> 0 | BT20: 54 | BU20: =+IFERROR(VLOOKUP($BU$17,Sheet1!BV6:BY6,3,0),0) -> 0 | BV20: =Sheet1!E6 -> STEEL | BW20: =Sheet1!CV6 -> SP0400136 | BX20: =Sheet1!CW6 -> CORRUGATED DISPATCH STEEL DRUM 2200 X 1300 X 1200 MM | BY20: =Sheet1!CX6 -> 250 | BZ20: =31500/0.25 -> 126000 | CA20: =SUMPRODUCT($N$18:$BU$18,N20:BU20)+BZ20 -> 1786707 | CB20: 0.01 | CC20: =CA20*CB20 -> 17867.07 | CD20: 0.25 | CE20: =CA20*CD20 -> 446676.75 | CF20: =Sheet1!CF6 -> 0 | CG20: =CA20*CF20 -> 0 | CH20: =CA20+CC20+CE20+CG20 -> 2251250.8 | CI20: 0.02 | CJ20: =CH20*CI20 -> 45025.016 | CK20: 0.01 | CL20: =CH20*CK20 -> 22512.508
A21: =Sheet1!A7 -> ENQ-15138-22-23 | B21: =Sheet1!B7 -> 45627 | C21: =Sheet1!C7 -> FA1300090 | D21: =Sheet1!D7 -> 3 CORE X 185 SQ. MM AL/ARM - WIRE (XLPE) - 11 KV | E21: =CH21+CJ21+CL21 -> 1723155.2 | F21: =ROUNDUP(M45,0) -> 65000 | G21: =E21+F21 -> 1788155.2 | H21: =Sheet1!CP7 -> 0.18 | I21: =G21*H21 -> 321867.94 | J21: =G21+I21 -> 2110023.2 | K21: =Sheet1!CS7 -> 2 | L21: =Sheet1!CT7 -> KMS | M21: =J21*K21 -> 4220046.4 | N21: =+IFERROR(VLOOKUP($N$17,Sheet1!J7:L7,3,0),0) -> 1499 | O21: =+IFERROR(VLOOKUP($O$17,Sheet1!J7:L7,3,0),0) -> 0 | P21: =+IFERROR(VLOOKUP($P$17,Sheet1!J7:M7,3,0),0) -> 0 | Q21: =+IFERROR(VLOOKUP($Q$17,Sheet1!J7:M7,3,0),0) -> 0 | R21: =+IFERROR(VLOOKUP($R$17,Sheet1!J7:M7,3,0),0) -> 0 | S21: =+IFERROR(VLOOKUP($S$17,Sheet1!N7:Q7,3,0),0) -> 0 | T21: =+IFERROR(VLOOKUP($T$17,Sheet1!N7:Q7,3,0),0) -> 0 | U21: =+IFERROR(VLOOKUP($U$17,Sheet1!F7:I7,3,0),0) -> 0 | V21: =+IFERROR(VLOOKUP($V$17,Sheet1!F7:I7,3,0),0) -> 0 | W21: =+IFERROR(VLOOKUP($W$17,Sheet1!F7:I7,3,0),0) -> 0 | X21: =+IFERROR(VLOOKUP($X$17,Sheet1!F7:I7,3,0),0) -> 0 | Y21: 138 | Z21: =+IFERROR(VLOOKUP($Z$17,Sheet1!F7:I7,3,0),0) -> 0 | AA21: =+IFERROR(VLOOKUP($AA$17,Sheet1!F7:I7,3,0),0) -> 0 | AB21: =+IFERROR(VLOOKUP($AB$17,Sheet1!F7:I7,3,0),0) -> 0 | AC21: 387 | AD21: =+IFERROR(VLOOKUP($AD$17,Sheet1!R7:U7,2,0),0) -> 0 | AE21: 693 | AF21: =+IFERROR(VLOOKUP($AF$17,Sheet1!V7:Y7,3,0),0) -> 0 | AG21: =+IFERROR(VLOOKUP($AG$17,Sheet1!V7:Y7,3,0),0) -> 0 | AH21: =+IFERROR(VLOOKUP($AH$17,Sheet1!V7:Y7,3,0),0) -> 0 | AI21: =+IFERROR(VLOOKUP($AI$17,Sheet1!V7:Y7,3,0),0) -> 0 | AJ21: =+IFERROR(VLOOKUP($AJ$17,Sheet1!V7:Y7,3,0),0) -> 0 | AK21: =+IFERROR(VLOOKUP($AK$17,Sheet1!Z7:AB7,3,0),0) -> 0 | AL21: =+IFERROR(VLOOKUP($AL$17,Sheet1!AD7:AG7,3,0),0) -> 0 | AM21: =+IFERROR(VLOOKUP($AM$17,Sheet1!AD7:AG7,3,0),0) -> 0 | AN21: =+IFERROR(VLOOKUP($AN$17,Sheet1!AD7:AG7,3,0),0) -> 0 | AO21: =+IFERROR(VLOOKUP($AO$17,Sheet1!AD7:AG7,3,0),0) -> 0 | AP21: =+IFERROR(VLOOKUP($AP$17,Sheet1!AD7:AG7,3,0),0) -> 0 | AQ21: 735 | AS21: =+IFERROR(VLOOKUP($AS$17,Sheet1!AH7:AK7,3,0),0) -> 0 | AT21: =+IFERROR(VLOOKUP($AT$17,Sheet1!AH7:AK7,3,0),0) -> 0 | AU21: =+IFERROR(VLOOKUP($AU$17,Sheet1!AH7:AK7,3,0),0) -> 0 | AV21: =+IFERROR(VLOOKUP($AV$17,Sheet1!AH7:AK7,3,0),0) -> 0 | AW21: =+IFERROR(VLOOKUP($AW$17,Sheet1!AH7:AK7,3,0),0) -> 0 | AX21: =+IFERROR(VLOOKUP($AX$17,Sheet1!AH7:AK7,3,0),0) -> 0 | AY21: =+IFERROR(VLOOKUP($AY$17,Sheet1!AH7:AK7,3,0),0) -> 0 | AZ21: =+IFERROR(VLOOKUP($AZ$17,Sheet1!AH7:AK7,3,0),0) -> 0 | BA21: 3500 | BB21: =+IFERROR(VLOOKUP($BB$17,Sheet1!AH7:AK7,3,0),0) -> 0 | BC21: =+IFERROR(VLOOKUP($BC$17,Sheet1!AL7:AO7,3,0),0) -> 0 | BD21: =+IFERROR(VLOOKUP($BD$17,Sheet1!AL7:AO7,3,0),0) -> 0 | BE21: =+IFERROR(VLOOKUP($BE$17,Sheet1!AL7:AO7,3,0),0) -> 0 | BF21: 945 | BG21: =+IFERROR(VLOOKUP($BG$17,Sheet1!AL7:AO7,3,0),0) -> 0 | BH21: =+IFERROR(VLOOKUP($BH$17,Sheet1!AL7:AO7,3,0),0) -> 0 | BI21: =+IFERROR(VLOOKUP($BI$17,Sheet1!AL7:AO7,3,0),0) -> 0 | BJ21: =+IFERROR(VLOOKUP($BJ$17,Sheet1!AL7:AO7,3,0),0) -> 0 | BK21: =+IFERROR(VLOOKUP($BK$17,Sheet1!AL7:AO7,3,0),0) -> 0 | BL21: 615 | BM21: =+IFERROR(VLOOKUP($BM$17,Sheet1!AP7:AS7,3,0),0) -> 0 | BN21: 35 | BO21: =+IFERROR(VLOOKUP($BO$17,Sheet1!AX7:BA7,3,0),0) -> 0 | BP21: 72 | BQ21: =+IFERROR(VLOOKUP($BQ$17,Sheet1!BF7:BI7,3,0),0) -> 0 | BR21: =+IFERROR(VLOOKUP($BR$17,Sheet1!BJ7:BM7,3,0),0) -> 0 | BS21: =+IFERROR(VLOOKUP($BS$17,Sheet1!BN7:BQ7,3,0),0) -> 0 | BT21: 48 | BU21: =+IFERROR(VLOOKUP($BU$17,Sheet1!BV7:BY7,3,0),0) -> 0 | BV21: =Sheet1!E7 -> STEEL | BW21: =Sheet1!CV7 -> SP0400111 | BX21: =Sheet1!CW7 -> CORRUGATED DISPATCH STEEL DRUM 1900 X 1000 X 1000 MM | BY21: =Sheet1!CX7 -> 250 | BZ21: =19350/0.25 -> 77400 | CA21: =SUMPRODUCT($N$18:$BU$18,N21:BU21)+BZ21 -> 1327751 | CB21: 0.01 | CC21: =CA21*CB21 -> 13277.51 | CD21: 0.25 | CE21: =CA21*CD21 -> 331937.75 | CF21: =Sheet1!CF7 -> 0 | CG21: =CA21*CF21 -> 0 | CH21: =CA21+CC21+CE21+CG21 -> 1672966.3 | CI21: 0.02 | CJ21: =CH21*CI21 -> 33459.325 | CK21: 0.01 | CL21: =CH21*CK21 -> 16729.663
A22: =Sheet1!A8 -> ENQ-15138-22-23 | B22: =Sheet1!B8 -> 45627 | C22: =Sheet1!C8 -> FA1300176 | D22: =Sheet1!D8 -> 3 CORE X 150 SQ. MM. AL/ARM - WIRE (XLPE) - 11 KV | E22: =CH22+CJ22+CL22 -> 1443834.9 | F22: =ROUNDUP(M46,0) -> 32500 | G22: =E22+F22 -> 1476334.9 | H22: =Sheet1!CP8 -> 0.18 | I22: =G22*H22 -> 265740.29 | J22: =G22+I22 -> 1742075.2 | K22: =Sheet1!CS8 -> 4 | L22: =Sheet1!CT8 -> KMS | M22: =J22*K22 -> 6968300.9 | N22: =+IFERROR(VLOOKUP($N$17,Sheet1!J8:L8,3,0),0) -> 1215 | O22: =+IFERROR(VLOOKUP($O$17,Sheet1!J8:L8,3,0),0) -> 0 | P22: =+IFERROR(VLOOKUP($P$17,Sheet1!J8:M8,3,0),0) -> 0 | Q22: =+IFERROR(VLOOKUP($Q$17,Sheet1!J8:M8,3,0),0) -> 0 | R22: =+IFERROR(VLOOKUP($R$17,Sheet1!J8:M8,3,0),0) -> 0 | S22: =+IFERROR(VLOOKUP($S$17,Sheet1!N8:Q8,3,0),0) -> 0 | T22: =+IFERROR(VLOOKUP($T$17,Sheet1!N8:Q8,3,0),0) -> 0 | U22: =+IFERROR(VLOOKUP($U$17,Sheet1!F8:I8,3,0),0) -> 0 | V22: =+IFERROR(VLOOKUP($V$17,Sheet1!F8:I8,3,0),0) -> 0 | W22: =+IFERROR(VLOOKUP($W$17,Sheet1!F8:I8,3,0),0) -> 0 | X22: =+IFERROR(VLOOKUP($X$17,Sheet1!F8:I8,3,0),0) -> 0 | Y22: 130 | Z22: =+IFERROR(VLOOKUP($Z$17,Sheet1!F8:I8,3,0),0) -> 0 | AA22: =+IFERROR(VLOOKUP($AA$17,Sheet1!F8:I8,3,0),0) -> 0 | AB22: =+IFERROR(VLOOKUP($AB$17,Sheet1!F8:I8,3,0),0) -> 0 | AC22: 359 | AD22: =+IFERROR(VLOOKUP($AD$17,Sheet1!R8:U8,2,0),0) -> 0 | AE22: 642 | AF22: =+IFERROR(VLOOKUP($AF$17,Sheet1!V8:Y8,3,0),0) -> 0 | AG22: =+IFERROR(VLOOKUP($AG$17,Sheet1!V8:Y8,3,0),0) -> 0 | AH22: =+IFERROR(VLOOKUP($AH$17,Sheet1!V8:Y8,3,0),0) -> 0 | AI22: =+IFERROR(VLOOKUP($AI$17,Sheet1!V8:Y8,3,0),0) -> 0 | AJ22: =+IFERROR(VLOOKUP($AJ$17,Sheet1!V8:Y8,3,0),0) -> 0 | AK22: =+IFERROR(VLOOKUP($AK$17,Sheet1!Z8:AB8,3,0),0) -> 0 | AL22: =+IFERROR(VLOOKUP($AL$17,Sheet1!AD8:AG8,3,0),0) -> 0 | AM22: =+IFERROR(VLOOKUP($AM$17,Sheet1!AD8:AG8,3,0),0) -> 0 | AN22: =+IFERROR(VLOOKUP($AN$17,Sheet1!AD8:AG8,3,0),0) -> 0 | AO22: =+IFERROR(VLOOKUP($AO$17,Sheet1!AD8:AG8,3,0),0) -> 0 | AP22: =+IFERROR(VLOOKUP($AP$17,Sheet1!AD8:AG8,3,0),0) -> 0 | AQ22: 605 | AS22: =+IFERROR(VLOOKUP($AS$17,Sheet1!AH8:AK8,3,0),0) -> 0 | AT22: =+IFERROR(VLOOKUP($AT$17,Sheet1!AH8:AK8,3,0),0) -> 0 | AU22: =+IFERROR(VLOOKUP($AU$17,Sheet1!AH8:AK8,3,0),0) -> 0 | AV22: =+IFERROR(VLOOKUP($AV$17,Sheet1!AH8:AK8,3,0),0) -> 0 | AW22: =+IFERROR(VLOOKUP($AW$17,Sheet1!AH8:AK8,3,0),0) -> 0 | AX22: =+IFERROR(VLOOKUP($AX$17,Sheet1!AH8:AK8,3,0),0) -> 0 | AY22: =+IFERROR(VLOOKUP($AY$17,Sheet1!AH8:AK8,3,0),0) -> 0 | AZ22: =+IFERROR(VLOOKUP($AZ$17,Sheet1!AH8:AK8,3,0),0) -> 0 | BA22: 2605 | BB22: =+IFERROR(VLOOKUP($BB$17,Sheet1!AH8:AK8,3,0),0) -> 0 | BC22: =+IFERROR(VLOOKUP($BC$17,Sheet1!AL8:AO8,3,0),0) -> 0 | BD22: =+IFERROR(VLOOKUP($BD$17,Sheet1!AL8:AO8,3,0),0) -> 0 | BE22: =+IFERROR(VLOOKUP($BE$17,Sheet1!AL8:AO8,3,0),0) -> 0 | BF22: 812 | BG22: =+IFERROR(VLOOKUP($BG$17,Sheet1!AL8:AO8,3,0),0) -> 0 | BH22: =+IFERROR(VLOOKUP($BH$17,Sheet1!AL8:AO8,3,0),0) -> 0 | BI22: =+IFERROR(VLOOKUP($BI$17,Sheet1!AL8:AO8,3,0),0) -> 0 | BJ22: =+IFERROR(VLOOKUP($BJ$17,Sheet1!AL8:AO8,3,0),0) -> 0 | BK22: =+IFERROR(VLOOKUP($BK$17,Sheet1!AL8:AO8,3,0),0) -> 0 | BL22: 567 | BM22: =+IFERROR(VLOOKUP($BM$17,Sheet1!AP8:AS8,3,0),0) -> 0 | BN22: 18 | BO22: =+IFERROR(VLOOKUP($BO$17,Sheet1!AX8:BA8,3,0),0) -> 0 | BP22: 67 | BQ22: =+IFERROR(VLOOKUP($BQ$17,Sheet1!BF8:BI8,3,0),0) -> 0 | BR22: =+IFERROR(VLOOKUP($BR$17,Sheet1!BJ8:BM8,3,0),0) -> 0 | BS22: =+IFERROR(VLOOKUP($BS$17,Sheet1!BN8:BQ8,3,0),0) -> 0 | BT22: 44 | BU22: =+IFERROR(VLOOKUP($BU$17,Sheet1!BV8:BY8,3,0),0) -> 0 | BV22: =Sheet1!E8 -> STEEL | BW22: SP0400118 | BX22: CORRUGATED DISPATCH STEEL DRUM 1700 X 1000 X 1200 | BY22: =Sheet1!CX8 -> 250 | BZ22: =17600/0.25 -> 70400 | CA22: =SUMPRODUCT($N$18:$BU$18,N22:BU22)+BZ22 -> 1112525 | CB22: 0.01 | CC22: =CA22*CB22 -> 11125.25 | CD22: 0.25 | CE22: =CA22*CD22 -> 278131.25 | CF22: =Sheet1!CF8 -> 0 | CG22: =CA22*CF22 -> 0 | CH22: =CA22+CC22+CE22+CG22 -> 1401781.5 | CI22: 0.02 | CJ22: =CH22*CI22 -> 28035.63 | CK22: 0.01 | CL22: =CH22*CK22 -> 14017.815
A23: =Sheet1!A9 -> ENQ-15138-22-23 | B23: =Sheet1!B9 -> 45627 | C23: =Sheet1!C9 -> FA1300197 | D23: =Sheet1!D9 -> 3 CORE X 120 SQ. MM. AL/ARM - WIRE (XLPE) - 11 KV | E23: =CH23+CJ23+CL23 -> 1297922 | F23: =ROUNDUP(M47,0) -> 32500 | G23: =E23+F23 -> 1330422 | H23: =Sheet1!CP9 -> 0.18 | I23: =G23*H23 -> 239475.96 | J23: =G23+I23 -> 1569898 | K23: =Sheet1!CS9 -> 10 | L23: =Sheet1!CT9 -> KMS | M23: =J23*K23 -> 15698980 | N23: =+IFERROR(VLOOKUP($N$17,Sheet1!J9:L9,3,0),0) -> 972 | O23: =+IFERROR(VLOOKUP($O$17,Sheet1!J9:L9,3,0),0) -> 0 | P23: =+IFERROR(VLOOKUP($P$17,Sheet1!J9:M9,3,0),0) -> 0 | Q23: =+IFERROR(VLOOKUP($Q$17,Sheet1!J9:M9,3,0),0) -> 0 | R23: =+IFERROR(VLOOKUP($R$17,Sheet1!J9:M9,3,0),0) -> 0 | S23: =+IFERROR(VLOOKUP($S$17,Sheet1!N9:Q9,3,0),0) -> 0 | T23: =+IFERROR(VLOOKUP($T$17,Sheet1!N9:Q9,3,0),0) -> 0 | U23: =+IFERROR(VLOOKUP($U$17,Sheet1!F9:I9,3,0),0) -> 0 | V23: =+IFERROR(VLOOKUP($V$17,Sheet1!F9:I9,3,0),0) -> 0 | W23: =+IFERROR(VLOOKUP($W$17,Sheet1!F9:I9,3,0),0) -> 0 | X23: =+IFERROR(VLOOKUP($X$17,Sheet1!F9:I9,3,0),0) -> 0 | Y23: 123 | Z23: =+IFERROR(VLOOKUP($Z$17,Sheet1!F9:I9,3,0),0) -> 0 | AA23: =+IFERROR(VLOOKUP($AA$17,Sheet1!F9:I9,3,0),0) -> 0 | AB23: =+IFERROR(VLOOKUP($AB$17,Sheet1!F9:I9,3,0),0) -> 0 | AC23: 332 | AD23: =+IFERROR(VLOOKUP($AD$17,Sheet1!R9:U9,2,0),0) -> 0 | AE23: 593 | AF23: =+IFERROR(VLOOKUP($AF$17,Sheet1!V9:Y9,3,0),0) -> 0 | AG23: =+IFERROR(VLOOKUP($AG$17,Sheet1!V9:Y9,3,0),0) -> 0 | AH23: =+IFERROR(VLOOKUP($AH$17,Sheet1!V9:Y9,3,0),0) -> 0 | AI23: =+IFERROR(VLOOKUP($AI$17,Sheet1!V9:Y9,3,0),0) -> 0 | AJ23: =+IFERROR(VLOOKUP($AJ$17,Sheet1!V9:Y9,3,0),0) -> 0 | AK23: =+IFERROR(VLOOKUP($AK$17,Sheet1!Z9:AB9,3,0),0) -> 0 | AL23: =+IFERROR(VLOOKUP($AL$17,Sheet1!AD9:AG9,3,0),0) -> 0 | AM23: =+IFERROR(VLOOKUP($AM$17,Sheet1!AD9:AG9,3,0),0) -> 0 | AN23: =+IFERROR(VLOOKUP($AN$17,Sheet1!AD9:AG9,3,0),0) -> 0 | AO23: =+IFERROR(VLOOKUP($AO$17,Sheet1!AD9:AG9,3,0),0) -> 0 | AP23: =+IFERROR(VLOOKUP($AP$17,Sheet1!AD9:AG9,3,0),0) -> 0 | AQ23: 550 | AS23: =+IFERROR(VLOOKUP($AS$17,Sheet1!AH9:AK9,3,0),0) -> 0 | AT23: =+IFERROR(VLOOKUP($AT$17,Sheet1!AH9:AK9,3,0),0) -> 0 | AU23: =+IFERROR(VLOOKUP($AU$17,Sheet1!AH9:AK9,3,0),0) -> 0 | AV23: =+IFERROR(VLOOKUP($AV$17,Sheet1!AH9:AK9,3,0),0) -> 0 | AW23: =+IFERROR(VLOOKUP($AW$17,Sheet1!AH9:AK9,3,0),0) -> 0 | AX23: =+IFERROR(VLOOKUP($AX$17,Sheet1!AH9:AK9,3,0),0) -> 0 | AY23: =+IFERROR(VLOOKUP($AY$17,Sheet1!AH9:AK9,3,0),0) -> 0 | AZ23: =+IFERROR(VLOOKUP($AZ$17,Sheet1!AH9:AK9,3,0),0) -> 0 | BA23: 2485 | BB23: =+IFERROR(VLOOKUP($BB$17,Sheet1!AH9:AK9,3,0),0) -> 0 | BC23: =+IFERROR(VLOOKUP($BC$17,Sheet1!AL9:AO9,3,0),0) -> 0 | BD23: =+IFERROR(VLOOKUP($BD$17,Sheet1!AL9:AO9,3,0),0) -> 0 | BE23: =+IFERROR(VLOOKUP($BE$17,Sheet1!AL9:AO9,3,0),0) -> 0 | BF23: 726 | BG23: =+IFERROR(VLOOKUP($BG$17,Sheet1!AL9:AO9,3,0),0) -> 0 | BH23: =+IFERROR(VLOOKUP($BH$17,Sheet1!AL9:AO9,3,0),0) -> 0 | BI23: =+IFERROR(VLOOKUP($BI$17,Sheet1!AL9:AO9,3,0),0) -> 0 | BJ23: =+IFERROR(VLOOKUP($BJ$17,Sheet1!AL9:AO9,3,0),0) -> 0 | BK23: =+IFERROR(VLOOKUP($BK$17,Sheet1!AL9:AO9,3,0),0) -> 0 | BL23: 503 | BM23: =+IFERROR(VLOOKUP($BM$17,Sheet1!AP9:AS9,3,0),0) -> 0 | BN23: 17 | BO23: =+IFERROR(VLOOKUP($BO$17,Sheet1!AX9:BA9,3,0),0) -> 0 | BP23: 62 | BQ23: =+IFERROR(VLOOKUP($BQ$17,Sheet1!BF9:BI9,3,0),0) -> 0 | BR23: =+IFERROR(VLOOKUP($BR$17,Sheet1!BJ9:BM9,3,0),0) -> 0 | BS23: =+IFERROR(VLOOKUP($BS$17,Sheet1!BN9:BQ9,3,0),0) -> 0 | BT23: 42 | BU23: =+IFERROR(VLOOKUP($BU$17,Sheet1!BV9:BY9,3,0),0) -> 0 | BV23: =Sheet1!E9 -> STEEL | BW23: =Sheet1!CV9 -> SP0400118 | BX23: =Sheet1!CW9 -> CORRUGATED DISPATCH STEEL DRUM 1700 X 1000 X 1200 | BY23: =Sheet1!CX9 -> 250 | BZ23: =17600/0.25 -> 70400 | CA23: =SUMPRODUCT($N$18:$BU$18,N23:BU23)+BZ23 -> 1000094 | CB23: 0.01 | CC23: =CA23*CB23 -> 10000.94 | CD23: 0.25 | CE23: =CA23*CD23 -> 250023.5 | CF23: =Sheet1!CF9 -> 0 | CG23: =CA23*CF23 -> 0 | CH23: =CA23+CC23+CE23+CG23 -> 1260118.4 | CI23: 0.02 | CJ23: =CH23*CI23 -> 25202.369 | CK23: 0.01 | CL23: =CH23*CK23 -> 12601.184
A24: =Sheet1!A10 -> ENQ-15138-22-23 | B24: =Sheet1!B10 -> 45627 | C24: =Sheet1!C10 -> FA1300088 | D24: =Sheet1!D10 -> 3 CORE X 95 SQ. MM. AL/ARM - WIRE (XLPE) - 11 KV (E) | E24: =CH24+CJ24+CL24 -> 1162904.1 | F24: =ROUNDUP(M48,0) -> 33914 | G24: =E24+F24 -> 1196818.1 | H24: =Sheet1!CP10 -> 0.18 | I24: =G24*H24 -> 215427.25 | J24: =G24+I24 -> 1412245.3 | K24: =Sheet1!CS10 -> 23 | L24: =Sheet1!CT10 -> KMS | M24: =J24*K24 -> 32481642 | N24: =+IFERROR(VLOOKUP($N$17,Sheet1!J10:L10,3,0),0) -> 770 | O24: =+IFERROR(VLOOKUP($O$17,Sheet1!J10:L10,3,0),0) -> 0 | P24: =+IFERROR(VLOOKUP($P$17,Sheet1!J10:M10,3,0),0) -> 0 | Q24: =+IFERROR(VLOOKUP($Q$17,Sheet1!J10:M10,3,0),0) -> 0 | R24: =+IFERROR(VLOOKUP($R$17,Sheet1!J10:M10,3,0),0) -> 0 | S24: =+IFERROR(VLOOKUP($S$17,Sheet1!N10:Q10,3,0),0) -> 0 | T24: =+IFERROR(VLOOKUP($T$17,Sheet1!N10:Q10,3,0),0) -> 0 | U24: =+IFERROR(VLOOKUP($U$17,Sheet1!F10:I10,3,0),0) -> 0 | V24: =+IFERROR(VLOOKUP($V$17,Sheet1!F10:I10,3,0),0) -> 0 | W24: =+IFERROR(VLOOKUP($W$17,Sheet1!F10:I10,3,0),0) -> 0 | X24: =+IFERROR(VLOOKUP($X$17,Sheet1!F10:I10,3,0),0) -> 0 | Y24: 115 | Z24: =+IFERROR(VLOOKUP($Z$17,Sheet1!F10:I10,3,0),0) -> 0 | AA24: =+IFERROR(VLOOKUP($AA$17,Sheet1!F10:I10,3,0),0) -> 0 | AB24: =+IFERROR(VLOOKUP($AB$17,Sheet1!F10:I10,3,0),0) -> 0 | AC24: 304 | AD24: =+IFERROR(VLOOKUP($AD$17,Sheet1!R10:U10,2,0),0) -> 0 | AE24: 542 | AF24: =+IFERROR(VLOOKUP($AF$17,Sheet1!V10:Y10,3,0),0) -> 0 | AG24: =+IFERROR(VLOOKUP($AG$17,Sheet1!V10:Y10,3,0),0) -> 0 | AH24: =+IFERROR(VLOOKUP($AH$17,Sheet1!V10:Y10,3,0),0) -> 0 | AI24: =+IFERROR(VLOOKUP($AI$17,Sheet1!V10:Y10,3,0),0) -> 0 | AJ24: =+IFERROR(VLOOKUP($AJ$17,Sheet1!V10:Y10,3,0),0) -> 0 | AK24: =+IFERROR(VLOOKUP($AK$17,Sheet1!Z10:AB10,3,0),0) -> 0 | AL24: =+IFERROR(VLOOKUP($AL$17,Sheet1!AD10:AG10,3,0),0) -> 0 | AM24: =+IFERROR(VLOOKUP($AM$17,Sheet1!AD10:AG10,3,0),0) -> 0 | AN24: =+IFERROR(VLOOKUP($AN$17,Sheet1!AD10:AG10,3,0),0) -> 0 | AO24: =+IFERROR(VLOOKUP($AO$17,Sheet1!AD10:AG10,3,0),0) -> 0 | AP24: =+IFERROR(VLOOKUP($AP$17,Sheet1!AD10:AG10,3,0),0) -> 0 | AQ24: 523 | AR24: 0 | AS24: =+IFERROR(VLOOKUP($AS$17,Sheet1!AH10:AK10,3,0),0) -> 0 | AT24: =+IFERROR(VLOOKUP($AT$17,Sheet1!AH10:AK10,3,0),0) -> 0 | AU24: =+IFERROR(VLOOKUP($AU$17,Sheet1!AH10:AK10,3,0),0) -> 0 | AV24: =+IFERROR(VLOOKUP($AV$17,Sheet1!AH10:AK10,3,0),0) -> 0 | AW24: =+IFERROR(VLOOKUP($AW$17,Sheet1!AH10:AK10,3,0),0) -> 0 | AX24: =+IFERROR(VLOOKUP($AX$17,Sheet1!AH10:AK10,3,0),0) -> 0 | AY24: =+IFERROR(VLOOKUP($AY$17,Sheet1!AH10:AK10,3,0),0) -> 0 | AZ24: =+IFERROR(VLOOKUP($AZ$17,Sheet1!AH10:AK10,3,0),0) -> 0 | BA24: 2324 | BB24: =+IFERROR(VLOOKUP($BB$17,Sheet1!AH10:AK10,3,0),0) -> 0 | BC24: =+IFERROR(VLOOKUP($BC$17,Sheet1!AL10:AO10,3,0),0) -> 0 | BD24: =+IFERROR(VLOOKUP($BD$17,Sheet1!AL10:AO10,3,0),0) -> 0 | BE24: =+IFERROR(VLOOKUP($BE$17,Sheet1!AL10:AO10,3,0),0) -> 0 | BF24: 685 | BG24: =+IFERROR(VLOOKUP($BG$17,Sheet1!AL10:AO10,3,0),0) -> 0 | BH24: =+IFERROR(VLOOKUP($BH$17,Sheet1!AL10:AO10,3,0),0) -> 0 | BI24: =+IFERROR(VLOOKUP($BI$17,Sheet1!AL10:AO10,3,0),0) -> 0 | BJ24: =+IFERROR(VLOOKUP($BJ$17,Sheet1!AL10:AO10,3,0),0) -> 0 | BK24: =+IFERROR(VLOOKUP($BK$17,Sheet1!AL10:AO10,3,0),0) -> 0 | BL24: 418 | BM24: 0 | BN24: 15 | BO24: =+IFERROR(VLOOKUP($BO$17,Sheet1!AX10:BA10,3,0),0) -> 0 | BP24: 57 | BQ24: =+IFERROR(VLOOKUP($BQ$17,Sheet1!BF10:BI10,3,0),0) -> 0 | BR24: =+IFERROR(VLOOKUP($BR$17,Sheet1!BJ10:BM10,3,0),0) -> 0 | BS24: =+IFERROR(VLOOKUP($BS$17,Sheet1!BN10:BQ10,3,0),0) -> 0 | BT24: 40 | BU24: =+IFERROR(VLOOKUP($BU$17,Sheet1!BV10:BY10,3,0),0) -> 0 | BV24: =Sheet1!E10 -> STEEL | BW24: =Sheet1!CV10 -> SP0400110 | BX24: =Sheet1!CW10 -> CORRUGATED DISPATCH STEEL DRUM 1600 X 900 X 1000 MM | BY24: =Sheet1!CX10 -> 250 | BZ24: =17200/0.25 -> 68800 | CA24: =SUMPRODUCT($N$18:$BU$18,N24:BU24)+BZ24 -> 896058 | CB24: 0.01 | CC24: =CA24*CB24 -> 8960.58 | CD24: 0.25 | CE24: =CA24*CD24 -> 224014.5 | CF24: =Sheet1!CF10 -> 0 | CG24: =CA24*CF24 -> 0 | CH24: =CA24+CC24+CE24+CG24 -> 1129033.1 | CI24: 0.02 | CJ24: =CH24*CI24 -> 22580.662 | CK24: 0.01 | CL24: =CH24*CK24 -> 11290.331
A25: =Sheet1!A19 -> ENQ-15138-22-23 | B25: =Sheet1!B19 -> 45627 | C25: =Sheet1!C19 -> FA1300313 | D25: =Sheet1!D19 -> 3 CORE X 50 SQ. MM. AL/ARD - WIRE (XLPE) - 11 KV | E25: =CH25+CJ25+CL25 -> 892612.56 | F25: =ROUNDUP(M49,0) -> 26000 | G25: =E25+F25 -> 918612.56 | H25: =Sheet1!CP19 -> 0.18 | I25: =G25*H25 -> 165350.26 | J25: =G25+I25 -> 1083962.8 | K25: =Sheet1!CS19 -> 7.5 | L25: =Sheet1!CT19 -> KMS | M25: =J25*K25 -> 8129721.2 | N25: 405 | O25: =+IFERROR(VLOOKUP($O$17,Sheet1!J19:L19,3,0),0) -> 0 | P25: =+IFERROR(VLOOKUP($P$17,Sheet1!J19:M19,3,0),0) -> 0 | Q25: =+IFERROR(VLOOKUP($Q$17,Sheet1!J19:M19,3,0),0) -> 0 | R25: =+IFERROR(VLOOKUP($R$17,Sheet1!J19:M19,3,0),0) -> 0 | S25: =+IFERROR(VLOOKUP($S$17,Sheet1!N19:Q19,3,0),0) -> 0 | T25: =+IFERROR(VLOOKUP($T$17,Sheet1!N19:Q19,3,0),0) -> 0 | U25: =+IFERROR(VLOOKUP($U$17,Sheet1!F19:I19,3,0),0) -> 0 | V25: =+IFERROR(VLOOKUP($V$17,Sheet1!F19:I19,3,0),0) -> 0 | W25: =+IFERROR(VLOOKUP($W$17,Sheet1!F19:I19,3,0),0) -> 0 | X25: =+IFERROR(VLOOKUP($X$17,Sheet1!F19:I19,3,0),0) -> 0 | Y25: 90 | Z25: =+IFERROR(VLOOKUP($Z$17,Sheet1!F19:I19,3,0),0) -> 0 | AA25: =+IFERROR(VLOOKUP($AA$17,Sheet1!F19:I19,3,0),0) -> 0 | AB25: =+IFERROR(VLOOKUP($AB$17,Sheet1!F19:I19,3,0),0) -> 0 | AC25: 181 | AD25: =+IFERROR(VLOOKUP($AD$17,Sheet1!R19:U19,2,0),0) -> 0 | AE25: 445 | AF25: =+IFERROR(VLOOKUP($AF$17,Sheet1!V19:Y19,3,0),0) -> 0 | AG25: =+IFERROR(VLOOKUP($AG$17,Sheet1!V19:Y19,3,0),0) -> 0 | AH25: =+IFERROR(VLOOKUP($AH$17,Sheet1!V19:Y19,3,0),0) -> 0 | AI25: =+IFERROR(VLOOKUP($AI$17,Sheet1!V19:Y19,3,0),0) -> 0 | AJ25: =+IFERROR(VLOOKUP($AJ$17,Sheet1!V19:Y19,3,0),0) -> 0 | AK25: =+IFERROR(VLOOKUP($AK$17,Sheet1!Z19:AB19,3,0),0) -> 0 | AL25: =+IFERROR(VLOOKUP($AL$17,Sheet1!AD19:AG19,3,0),0) -> 0 | AM25: =+IFERROR(VLOOKUP($AM$17,Sheet1!AD19:AG19,3,0),0) -> 0 | AN25: =+IFERROR(VLOOKUP($AN$17,Sheet1!AD19:AG19,3,0),0) -> 0 | AO25: =+IFERROR(VLOOKUP($AO$17,Sheet1!AD19:AG19,3,0),0) -> 0 | AP25: =+IFERROR(VLOOKUP($AP$17,Sheet1!AD19:AG19,3,0),0) -> 0 | AQ25: 352 | AR25: =+IFERROR(VLOOKUP($AR$17,Sheet1!AD19:AG19,3,0),0) -> 0 | AS25: =+IFERROR(VLOOKUP($AS$17,Sheet1!AH19:AK19,3,0),0) -> 0 | AT25: =+IFERROR(VLOOKUP($AT$17,Sheet1!AH19:AK19,3,0),0) -> 0 | AU25: =+IFERROR(VLOOKUP($AU$17,Sheet1!AH19:AK19,3,0),0) -> 0 | AV25: =+IFERROR(VLOOKUP($AV$17,Sheet1!AH19:AK19,3,0),0) -> 0 | AW25: =+IFERROR(VLOOKUP($AW$17,Sheet1!AH19:AK19,3,0),0) -> 0 | AX25: =+IFERROR(VLOOKUP($AX$17,Sheet1!AH19:AK19,3,0),0) -> 0 | AY25: =+IFERROR(VLOOKUP($AY$17,Sheet1!AH19:AK19,3,0),0) -> 0 | AZ25: =+IFERROR(VLOOKUP($AZ$17,Sheet1!AH19:AK19,3,0),0) -> 0 | BA25: 1964 | BB25: =+IFERROR(VLOOKUP($BB$17,Sheet1!AH19:AK19,3,0),0) -> 0 | BC25: =+IFERROR(VLOOKUP($BC$17,Sheet1!AL19:AO19,3,0),0) -> 0 | BD25: =+IFERROR(VLOOKUP($BD$17,Sheet1!AL19:AO19,3,0),0) -> 0 | BE25: =+IFERROR(VLOOKUP($BE$17,Sheet1!AL19:AO19,3,0),0) -> 0 | BF25: 551 | BG25: =+IFERROR(VLOOKUP($BG$17,Sheet1!AL19:AO19,3,0),0) -> 0 | BH25: =+IFERROR(VLOOKUP($BH$17,Sheet1!AL19:AO19,3,0),0) -> 0 | BI25: =+IFERROR(VLOOKUP($BI$17,Sheet1!AL19:AO19,3,0),0) -> 0 | BJ25: =+IFERROR(VLOOKUP($BJ$17,Sheet1!AL19:AO19,3,0),0) -> 0 | BK25: =+IFERROR(VLOOKUP($BK$17,Sheet1!AL19:AO19,3,0),0) -> 0 | BL25: 308 | BM25: =+IFERROR(VLOOKUP($BM$17,Sheet1!AP19:AS19,3,0),0) -> 0 | BN25: 10 | BO25: =+IFERROR(VLOOKUP($BO$17,Sheet1!AX19:BA19,3,0),0) -> 0 | BP25: 42 | BQ25: =+IFERROR(VLOOKUP($BQ$17,Sheet1!BF19:BI19,3,0),0) -> 0 | BR25: =+IFERROR(VLOOKUP($BR$17,Sheet1!BJ19:BM19,3,0),0) -> 0 | BS25: =+IFERROR(VLOOKUP($BS$17,Sheet1!BN19:BQ19,3,0),0) -> 0 | BT25: 34 | BU25: =+IFERROR(VLOOKUP($BU$17,Sheet1!BV19:BY19,3,0),0) -> 0 | BV25: STEEL | BW25: SP0400152 | BX25: CORRUGATED DISPATCH STEEL DRUM 1500 X 800 X 915 | BY25: =Sheet1!CX19 -> 250 | BZ25: =22500/0.25 -> 90000 | CA25: =SUMPRODUCT($N$18:$BU$18,N25:BU25)+BZ25 -> 687789 | CB25: 0.01 | CC25: =CA25*CB25 -> 6877.89 | CD25: 0.25 | CE25: =CA25*CD25 -> 171947.25 | CF25: =Sheet1!CF19 -> 0 | CG25: =CA25*CF25 -> 0 | CH25: =CA25+CC25+CE25+CG25 -> 866614.14 | CI25: 0.02 | CJ25: =CH25*CI25 -> 17332.283 | CK25: 0.01 | CL25: =CH25*CK25 -> 8666.1414
A26: =Sheet1!A12 -> ENQ-15138-22-23 | B26: =Sheet1!B12 -> 45627 | C26: =Sheet1!C12 -> FA1300066 | D26: =Sheet1!D12 -> 1 CORE X 1000 SQ. MM. AL/ARM (XLPE) - 11 KV | E26: =CH26+CJ26+CL26 -> 1700227 | F26: =ROUNDUP(M50,0) -> 65000 | G26: =E26+F26 -> 1765227 | H26: =Sheet1!CP12 -> 0.18 | I26: =G26*H26 -> 317740.86 | J26: =G26+I26 -> 2082967.9 | K26: =Sheet1!CS12 -> 1 | L26: =Sheet1!CT12 -> KMS | M26: =J26*K26 -> 2082967.9 | N26: =+IFERROR(VLOOKUP($N$17,Sheet1!J12:L12,3,0),0) -> 2732 | O26: =+IFERROR(VLOOKUP($O$17,Sheet1!J12:L12,3,0),0) -> 0 | P26: =+IFERROR(VLOOKUP($P$17,Sheet1!J12:M12,3,0),0) -> 0 | Q26: =+IFERROR(VLOOKUP($Q$17,Sheet1!J12:M12,3,0),0) -> 0 | R26: =+IFERROR(VLOOKUP($R$17,Sheet1!J12:M12,3,0),0) -> 0 | S26: =+IFERROR(VLOOKUP($S$17,Sheet1!N12:Q12,3,0),0) -> 0 | T26: =+IFERROR(VLOOKUP($T$17,Sheet1!N12:Q12,3,0),0) -> 0 | U26: =+IFERROR(VLOOKUP($U$17,Sheet1!F12:I12,3,0),0) -> 0 | V26: =+IFERROR(VLOOKUP($V$17,Sheet1!F12:I12,3,0),0) -> 0 | W26: =+IFERROR(VLOOKUP($W$17,Sheet1!F12:I12,3,0),0) -> 0 | X26: =+IFERROR(VLOOKUP($X$17,Sheet1!F12:I12,3,0),0) -> 0 | Y26: 84 | Z26: =+IFERROR(VLOOKUP($Z$17,Sheet1!F12:I12,3,0),0) -> 0 | AA26: =+IFERROR(VLOOKUP($AA$17,Sheet1!F12:I12,3,0),0) -> 0 | AB26: =+IFERROR(VLOOKUP($AB$17,Sheet1!F12:I12,3,0),0) -> 0 | AC26: 276 | AD26: =+IFERROR(VLOOKUP($AD$17,Sheet1!R12:U12,2,0),0) -> 0 | AE26: 480 | AF26: =+IFERROR(VLOOKUP($AF$17,Sheet1!V12:Y12,3,0),0) -> 0 | AG26: =+IFERROR(VLOOKUP($AG$17,Sheet1!V12:Y12,3,0),0) -> 0 | AH26: =+IFERROR(VLOOKUP($AH$17,Sheet1!V12:Y12,3,0),0) -> 0 | AI26: =+IFERROR(VLOOKUP($AI$17,Sheet1!V12:Y12,3,0),0) -> 0 | AJ26: =+IFERROR(VLOOKUP($AJ$17,Sheet1!V12:Y12,3,0),0) -> 0 | AK26: 35 | AL26: =+IFERROR(VLOOKUP($AL$17,Sheet1!AD12:AG12,3,0),0) -> 0 | AM26: =+IFERROR(VLOOKUP($AM$17,Sheet1!AD12:AG12,3,0),0) -> 0 | AN26: =+IFERROR(VLOOKUP($AN$17,Sheet1!AD12:AG12,3,0),0) -> 0 | AO26: =+IFERROR(VLOOKUP($AO$17,Sheet1!AD12:AG12,3,0),0) -> 0 | AP26: =+IFERROR(VLOOKUP($AP$17,Sheet1!AD12:AG12,3,0),0) -> 0 | AQ26: 198 | AR26: =+IFERROR(VLOOKUP($AR$17,Sheet1!AD12:AG12,3,0),0) -> 0 | AS26: =+IFERROR(VLOOKUP($AS$17,Sheet1!AH12:AK12,3,0),0) -> 0 | AT26: =+IFERROR(VLOOKUP($AT$17,Sheet1!AH12:AK12,3,0),0) -> 0 | AU26: =+IFERROR(VLOOKUP($AU$17,Sheet1!AH12:AK12,3,0),0) -> 0 | AV26: 814 | AW26: =+IFERROR(VLOOKUP($AW$17,Sheet1!AH12:AK12,3,0),0) -> 0 | AX26: =+IFERROR(VLOOKUP($AX$17,Sheet1!AH12:AK12,3,0),0) -> 0 | AY26: =+IFERROR(VLOOKUP($AY$17,Sheet1!AH12:AK12,3,0),0) -> 0 | AZ26: =+IFERROR(VLOOKUP($AZ$17,Sheet1!AH12:AK12,3,0),0) -> 0 | BA26: =+IFERROR(VLOOKUP($BA$17,Sheet1!AH12:AK12,3,0),0) -> 0 | BB26: =+IFERROR(VLOOKUP($BB$17,Sheet1!AH12:AK12,3,0),0) -> 0 | BC26: =+IFERROR(VLOOKUP($BC$17,Sheet1!AL12:AO12,3,0),0) -> 0 | BD26: =+IFERROR(VLOOKUP($BD$17,Sheet1!AL12:AO12,3,0),0) -> 0 | BE26: =+IFERROR(VLOOKUP($BE$17,Sheet1!AL12:AO12,3,0),0) -> 0 | BF26: 706 | BG26: =+IFERROR(VLOOKUP($BG$17,Sheet1!AL12:AO12,3,0),0) -> 0 | BH26: =+IFERROR(VLOOKUP($BH$17,Sheet1!AL12:AO12,3,0),0) -> 0 | BI26: =+IFERROR(VLOOKUP($BI$17,Sheet1!AL12:AO12,3,0),0) -> 0 | BJ26: =+IFERROR(VLOOKUP($BJ$17,Sheet1!AL12:AO12,3,0),0) -> 0 | BK26: =+IFERROR(VLOOKUP($BK$17,Sheet1!AL12:AO12,3,0),0) -> 0 | BL26: =+IFERROR(VLOOKUP($BL$17,Sheet1!AL12:AO12,3,0),0) -> 0 | BM26: =+IFERROR(VLOOKUP($BM$17,Sheet1!AP12:AS12,3,0),0) -> 0 | BN26: 39 | BO26: =+IFERROR(VLOOKUP($BO$17,Sheet1!AX12:BA12,3,0),0) -> 0 | BP26: 49 | BQ26: =+IFERROR(VLOOKUP($BQ$17,Sheet1!BF12:BI12,3,0),0) -> 0 | BR26: =+IFERROR(VLOOKUP($BR$17,Sheet1!BJ12:BM12,3,0),0) -> 0 | BS26: =+IFERROR(VLOOKUP($BS$17,Sheet1!BN12:BQ12,3,0),0) -> 0 | BT26: 42 | BU26: =+IFERROR(VLOOKUP($BU$17,Sheet1!BV12:BY12,3,0),0) -> 0 | BV26: =Sheet1!E12 -> STEEL | BW26: SP0400123 | BX26: CORRUGATED DISPATCH STEEL DRUM 2000 X 1000 X 1200 MM | BY26: =Sheet1!CX12 -> 500 | BZ26: =31500/0.5 -> 63000 | CA26: =SUMPRODUCT($N$18:$BU$18,N26:BU26)+BZ26 -> 1310084 | CB26: 0.01 | CC26: =CA26*CB26 -> 13100.84 | CD26: 0.25 | CE26: =CA26*CD26 -> 327521 | CF26: =Sheet1!CF12 -> 0 | CG26: =CA26*CF26 -> 0 | CH26: =CA26+CC26+CE26+CG26 -> 1650705.8 | CI26: 0.02 | CJ26: =CH26*CI26 -> 33014.117 | CK26: 0.01 | CL26: =CH26*CK26 -> 16507.058
A27: =Sheet1!A15 -> ENQ-15138-22-23 | B27: =Sheet1!B15 -> 45627 | C27: =Sheet1!C15 -> FA1300016 | D27: =Sheet1!D15 -> 1 CORE X 630 SQ. MM. AL/ARM (XLPE) - 11 KV | E27: =CH27+CJ27+CL27 -> 1140867.4 | F27: =ROUNDUP(M51,0) -> 17728 | G27: =E27+F27 -> 1158595.4 | H27: =Sheet1!CP15 -> 0.18 | I27: =G27*H27 -> 208547.18 | J27: =G27+I27 -> 1367142.6 | K27: =Sheet1!CS15 -> 11 | L27: =Sheet1!CT15 -> KMS | M27: =J27*K27 -> 15038569 | N27: =+IFERROR(VLOOKUP($N$17,Sheet1!J15:L15,3,0),0) -> 1701 | O27: =+IFERROR(VLOOKUP($O$17,Sheet1!J15:L15,3,0),0) -> 0 | P27: =+IFERROR(VLOOKUP($P$17,Sheet1!J15:M15,3,0),0) -> 0 | Q27: =+IFERROR(VLOOKUP($Q$17,Sheet1!J15:M15,3,0),0) -> 0 | R27: =+IFERROR(VLOOKUP($R$17,Sheet1!J15:M15,3,0),0) -> 0 | S27: =+IFERROR(VLOOKUP($S$17,Sheet1!N15:Q15,3,0),0) -> 0 | T27: =+IFERROR(VLOOKUP($T$17,Sheet1!N15:Q15,3,0),0) -> 0 | U27: =+IFERROR(VLOOKUP($U$17,Sheet1!F15:I15,3,0),0) -> 0 | V27: =+IFERROR(VLOOKUP($V$17,Sheet1!F15:I15,3,0),0) -> 0 | W27: =+IFERROR(VLOOKUP($W$17,Sheet1!F15:I15,3,0),0) -> 0 | X27: =+IFERROR(VLOOKUP($X$17,Sheet1!F15:I15,3,0),0) -> 0 | Y27: 69 | Z27: =+IFERROR(VLOOKUP($Z$17,Sheet1!F15:I15,3,0),0) -> 0 | AA27: =+IFERROR(VLOOKUP($AA$17,Sheet1!F15:I15,3,0),0) -> 0 | AB27: =+IFERROR(VLOOKUP($AB$17,Sheet1!F15:I15,3,0),0) -> 0 | AC27: 213 | AD27: =+IFERROR(VLOOKUP($AD$17,Sheet1!R15:U15,2,0),0) -> 0 | AE27: 380 | AF27: =+IFERROR(VLOOKUP($AF$17,Sheet1!V15:Y15,3,0),0) -> 0 | AG27: =+IFERROR(VLOOKUP($AG$17,Sheet1!V15:Y15,3,0),0) -> 0 | AH27: =+IFERROR(VLOOKUP($AH$17,Sheet1!V15:Y15,3,0),0) -> 0 | AI27: =+IFERROR(VLOOKUP($AI$17,Sheet1!V15:Y15,3,0),0) -> 0 | AJ27: =+IFERROR(VLOOKUP($AJ$17,Sheet1!V15:Y15,3,0),0) -> 0 | AK27: 29 | AL27: =+IFERROR(VLOOKUP($AL$17,Sheet1!AD15:AG15,3,0),0) -> 0 | AM27: =+IFERROR(VLOOKUP($AM$17,Sheet1!AD15:AG15,3,0),0) -> 0 | AN27: =+IFERROR(VLOOKUP($AN$17,Sheet1!AD15:AG15,3,0),0) -> 0 | AO27: =+IFERROR(VLOOKUP($AO$17,Sheet1!AD15:AG15,3,0),0) -> 0 | AP27: =+IFERROR(VLOOKUP($AP$17,Sheet1!AD15:AG15,3,0),0) -> 0 | AQ27: 144 | AR27: =+IFERROR(VLOOKUP($AR$17,Sheet1!AD15:AG15,3,0),0) -> 0 | AS27: =+IFERROR(VLOOKUP($AS$17,Sheet1!AH15:AK15,3,0),0) -> 0 | AT27: =+IFERROR(VLOOKUP($AT$17,Sheet1!AH15:AK15,3,0),0) -> 0 | AU27: =+IFERROR(VLOOKUP($AU$17,Sheet1!AH15:AK15,3,0),0) -> 0 | AV27: 539 | AW27: =+IFERROR(VLOOKUP($AW$17,Sheet1!AH15:AK15,3,0),0) -> 0 | AX27: =+IFERROR(VLOOKUP($AX$17,Sheet1!AH15:AK15,3,0),0) -> 0 | AY27: =+IFERROR(VLOOKUP($AY$17,Sheet1!AH15:AK15,3,0),0) -> 0 | AZ27: =+IFERROR(VLOOKUP($AZ$17,Sheet1!AH15:AK15,3,0),0) -> 0 | BA27: =+IFERROR(VLOOKUP($BA$17,Sheet1!AH15:AK15,3,0),0) -> 0 | BB27: =+IFERROR(VLOOKUP($BB$17,Sheet1!AH15:AK15,3,0),0) -> 0 | BC27: =+IFERROR(VLOOKUP($BC$17,Sheet1!AL15:AO15,3,0),0) -> 0 | BD27: =+IFERROR(VLOOKUP($BD$17,Sheet1!AL15:AO15,3,0),0) -> 0 | BE27: =+IFERROR(VLOOKUP($BE$17,Sheet1!AL15:AO15,3,0),0) -> 0 | BF27: 500 | BG27: =+IFERROR(VLOOKUP($BG$17,Sheet1!AL15:AO15,3,0),0) -> 0 | BH27: =+IFERROR(VLOOKUP($BH$17,Sheet1!AL15:AO15,3,0),0) -> 0 | BI27: =+IFERROR(VLOOKUP($BI$17,Sheet1!AL15:AO15,3,0),0) -> 0 | BJ27: =+IFERROR(VLOOKUP($BJ$17,Sheet1!AL15:AO15,3,0),0) -> 0 | BK27: =+IFERROR(VLOOKUP($BK$17,Sheet1!AL15:AO15,3,0),0) -> 0 | BL27: =+IFERROR(VLOOKUP($BL$17,Sheet1!AL15:AO15,3,0),0) -> 0 | BM27: =+IFERROR(VLOOKUP($BM$17,Sheet1!AP15:AS15,3,0),0) -> 0 | BN27: 26 | BO27: =+IFERROR(VLOOKUP($BO$17,Sheet1!AX15:BA15,3,0),0) -> 0 | BP27: 39 | BQ27: =+IFERROR(VLOOKUP($BQ$17,Sheet1!BF15:BI15,3,0),0) -> 0 | BR27: =+IFERROR(VLOOKUP($BR$17,Sheet1!BJ15:BM15,3,0),0) -> 0 | BS27: =+IFERROR(VLOOKUP($BS$17,Sheet1!BN15:BQ15,3,0),0) -> 0 | BT27: 33 | BU27: =+IFERROR(VLOOKUP($BU$17,Sheet1!BV15:BY15,3,0),0) -> 0 | BV27: =Sheet1!E15 -> STEEL | BW27: =Sheet1!CV15 -> SP0400091 | BX27: =Sheet1!CW15 -> CORRUGATED DISPATCH STEEL DRUM 1800 X 900 X 1000 | BY27: =Sheet1!CX15 -> 500 | BZ27: =22400/0.5 -> 44800 | CA27: =SUMPRODUCT($N$18:$BU$18,N27:BU27)+BZ27 -> 879078 | CB27: 0.01 | CC27: =CA27*CB27 -> 8790.78 | CD27: 0.25 | CE27: =CA27*CD27 -> 219769.5 | CF27: =Sheet1!CF15 -> 0 | CG27: =CA27*CF27 -> 0 | CH27: =CA27+CC27+CE27+CG27 -> 1107638.3 | CI27: 0.02 | CJ27: =CH27*CI27 -> 22152.766 | CK27: 0.01 | CL27: =CH27*CK27 -> 11076.383
A28: =Sheet1!A16 -> ENQ-15138-22-23 | B28: =Sheet1!B16 -> 45627 | C28: =Sheet1!C16 -> FA1300047 | D28: =Sheet1!D16 -> 1 CORE X 400 SQ. MM. AL/ARM (XLPE) - 11 KV | E28: =CH28+CJ28+CL28 -> 831134.48 | F28: =ROUNDUP(M52,0) -> 16250 | G28: =E28+F28 -> 847384.48 | H28: =Sheet1!CP16 -> 0.18 | I28: =G28*H28 -> 152529.21 | J28: =G28+I28 -> 999913.69 | K28: =Sheet1!CS16 -> 4 | L28: =Sheet1!CT16 -> KMS | M28: =J28*K28 -> 3999654.7 | N28: =+IFERROR(VLOOKUP($N$17,Sheet1!J16:L16,3,0),0) -> 1080 | O28: =+IFERROR(VLOOKUP($O$17,Sheet1!J16:L16,3,0),0) -> 0 | P28: =+IFERROR(VLOOKUP($P$17,Sheet1!J16:M16,3,0),0) -> 0 | Q28: =+IFERROR(VLOOKUP($Q$17,Sheet1!J16:M16,3,0),0) -> 0 | R28: =+IFERROR(VLOOKUP($R$17,Sheet1!J16:M16,3,0),0) -> 0 | S28: =+IFERROR(VLOOKUP($S$17,Sheet1!N16:Q16,3,0),0) -> 0 | T28: =+IFERROR(VLOOKUP($T$17,Sheet1!N16:Q16,3,0),0) -> 0 | U28: =+IFERROR(VLOOKUP($U$17,Sheet1!F16:I16,3,0),0) -> 0 | V28: =+IFERROR(VLOOKUP($V$17,Sheet1!F16:I16,3,0),0) -> 0 | W28: =+IFERROR(VLOOKUP($W$17,Sheet1!F16:I16,3,0),0) -> 0 | X28: =+IFERROR(VLOOKUP($X$17,Sheet1!F16:I16,3,0),0) -> 0 | Y28: 59 | Z28: =+IFERROR(VLOOKUP($Z$17,Sheet1!F16:I16,3,0),0) -> 0 | AA28: =+IFERROR(VLOOKUP($AA$17,Sheet1!F16:I16,3,0),0) -> 0 | AB28: =+IFERROR(VLOOKUP($AB$17,Sheet1!F16:I16,3,0),0) -> 0 | AC28: 172 | AD28: =+IFERROR(VLOOKUP($AD$17,Sheet1!R16:U16,2,0),0) -> 0 | AE28: 310 | AF28: =+IFERROR(VLOOKUP($AF$17,Sheet1!V16:Y16,3,0),0) -> 0 | AG28: =+IFERROR(VLOOKUP($AG$17,Sheet1!V16:Y16,3,0),0) -> 0 | AH28: =+IFERROR(VLOOKUP($AH$17,Sheet1!V16:Y16,3,0),0) -> 0 | AI28: =+IFERROR(VLOOKUP($AI$17,Sheet1!V16:Y16,3,0),0) -> 0 | AJ28: =+IFERROR(VLOOKUP($AJ$17,Sheet1!V16:Y16,3,0),0) -> 0 | AK28: 24 | AL28: =+IFERROR(VLOOKUP($AL$17,Sheet1!AD16:AG16,3,0),0) -> 0 | AM28: =+IFERROR(VLOOKUP($AM$17,Sheet1!AD16:AG16,3,0),0) -> 0 | AN28: =+IFERROR(VLOOKUP($AN$17,Sheet1!AD16:AG16,3,0),0) -> 0 | AO28: =+IFERROR(VLOOKUP($AO$17,Sheet1!AD16:AG16,3,0),0) -> 0 | AP28: =+IFERROR(VLOOKUP($AP$17,Sheet1!AD16:AG16,3,0),0) -> 0 | AQ28: 104 | AR28: =+IFERROR(VLOOKUP($AR$17,Sheet1!AD16:AG16,3,0),0) -> 0 | AS28: =+IFERROR(VLOOKUP($AS$17,Sheet1!AH16:AK16,3,0),0) -> 0 | AT28: =+IFERROR(VLOOKUP($AT$17,Sheet1!AH16:AK16,3,0),0) -> 0 | AU28: =+IFERROR(VLOOKUP($AU$17,Sheet1!AH16:AK16,3,0),0) -> 0 | AV28: 460 | AW28: =+IFERROR(VLOOKUP($AW$17,Sheet1!AH16:AK16,3,0),0) -> 0 | AX28: =+IFERROR(VLOOKUP($AX$17,Sheet1!AH16:AK16,3,0),0) -> 0 | AY28: =+IFERROR(VLOOKUP($AY$17,Sheet1!AH16:AK16,3,0),0) -> 0 | AZ28: =+IFERROR(VLOOKUP($AZ$17,Sheet1!AH16:AK16,3,0),0) -> 0 | BA28: =+IFERROR(VLOOKUP($BA$17,Sheet1!AH16:AK16,3,0),0) -> 0 | BB28: =+IFERROR(VLOOKUP($BB$17,Sheet1!AH16:AK16,3,0),0) -> 0 | BC28: =+IFERROR(VLOOKUP($BC$17,Sheet1!AL16:AO16,3,0),0) -> 0 | BD28: =+IFERROR(VLOOKUP($BD$17,Sheet1!AL16:AO16,3,0),0) -> 0 | BE28: =+IFERROR(VLOOKUP($BE$17,Sheet1!AL16:AO16,3,0),0) -> 0 | BF28: 400 | BG28: =+IFERROR(VLOOKUP($BG$17,Sheet1!AL16:AO16,3,0),0) -> 0 | BH28: =+IFERROR(VLOOKUP($BH$17,Sheet1!AL16:AO16,3,0),0) -> 0 | BI28: =+IFERROR(VLOOKUP($BI$17,Sheet1!AL16:AO16,3,0),0) -> 0 | BJ28: =+IFERROR(VLOOKUP($BJ$17,Sheet1!AL16:AO16,3,0),0) -> 0 | BK28: =+IFERROR(VLOOKUP($BK$17,Sheet1!AL16:AO16,3,0),0) -> 0 | BL28: =+IFERROR(VLOOKUP($BL$17,Sheet1!AL16:AO16,3,0),0) -> 0 | BM28: =+IFERROR(VLOOKUP($BM$17,Sheet1!AP16:AS16,3,0),0) -> 0 | BN28: 20 | BO28: =+IFERROR(VLOOKUP($BO$17,Sheet1!AX16:BA16,3,0),0) -> 0 | BP28: 32 | BQ28: =+IFERROR(VLOOKUP($BQ$17,Sheet1!BF16:BI16,3,0),0) -> 0 | BR28: =+IFERROR(VLOOKUP($BR$17,Sheet1!BJ16:BM16,3,0),0) -> 0 | BS28: =+IFERROR(VLOOKUP($BS$17,Sheet1!BN16:BQ16,3,0),0) -> 0 | BT28: 30 | BU28: =+IFERROR(VLOOKUP($BU$17,Sheet1!BV16:BY16,3,0),0) -> 0 | BV28: =Sheet1!E16 -> STEEL | BW28: =Sheet1!CV16 -> SP0400125 | BX28: =Sheet1!CW16 -> CORRUGATED DISPATCH STEEL DRUM 1600 X 700 X 915 MM | BY28: =Sheet1!CX16 -> 500 | BZ28: =16000/0.5 -> 32000 | CA28: =SUMPRODUCT($N$18:$BU$18,N28:BU28)+BZ28 -> 640418 | CB28: 0.01 | CC28: =CA28*CB28 -> 6404.18 | CD28: 0.25 | CE28: =CA28*CD28 -> 160104.5 | CF28: =Sheet1!CF16 -> 0 | CG28: =CA28*CF28 -> 0 | CH28: =CA28+CC28+CE28+CG28 -> 806926.68 | CI28: 0.02 | CJ28: =CH28*CI28 -> 16138.534 | CK28: 0.01 | CL28: =CH28*CK28 -> 8069.2668
A29: =Sheet1!A23 -> ENQ-15138-22-23 | B29: =Sheet1!B23 -> 45627 | C29: =Sheet1!C23 -> FA1300009 | D29: =Sheet1!D23 -> 1 CORE X 300 SQ. MM. AL./ARM (XLPE) - 11 KV | E29: =CH29+CJ29+CL29 -> 694300.94 | F29: =ROUNDUP(M53,0) -> 20000 | G29: =E29+F29 -> 714300.94 | H29: =Sheet1!CP23 -> 0.18 | I29: =G29*H29 -> 128574.17 | J29: =G29+I29 -> 842875.11 | K29: =Sheet1!CS23 -> 6.5 | L29: =Sheet1!CT23 -> KMS | M29: =J29*K29 -> 5478688.2 | N29: =+IFERROR(VLOOKUP($N$17,Sheet1!J23:L23,3,0),0) -> 810 | O29: =+IFERROR(VLOOKUP($O$17,Sheet1!J23:L23,3,0),0) -> 0 | P29: =+IFERROR(VLOOKUP($P$17,Sheet1!J23:M23,3,0),0) -> 0 | Q29: =+IFERROR(VLOOKUP($Q$17,Sheet1!J23:M23,3,0),0) -> 0 | R29: =+IFERROR(VLOOKUP($R$17,Sheet1!J23:M23,3,0),0) -> 0 | S29: =+IFERROR(VLOOKUP($S$17,Sheet1!N23:Q23,3,0),0) -> 0 | T29: =+IFERROR(VLOOKUP($T$17,Sheet1!N23:Q23,3,0),0) -> 0 | U29: =+IFERROR(VLOOKUP($U$17,Sheet1!F23:I23,3,0),0) -> 0 | V29: =+IFERROR(VLOOKUP($V$17,Sheet1!F23:I23,3,0),0) -> 0 | W29: =+IFERROR(VLOOKUP($W$17,Sheet1!F23:I23,3,0),0) -> 0 | X29: =+IFERROR(VLOOKUP($X$17,Sheet1!F23:I23,3,0),0) -> 0 | Y29: 54 | Z29: =+IFERROR(VLOOKUP($Z$17,Sheet1!F23:I23,3,0),0) -> 0 | AA29: =+IFERROR(VLOOKUP($AA$17,Sheet1!F23:I23,3,0),0) -> 0 | AB29: =+IFERROR(VLOOKUP($AB$17,Sheet1!F23:I23,3,0),0) -> 0 | AC29: 155 | AD29: =+IFERROR(VLOOKUP($AD$17,Sheet1!R23:U23,2,0),0) -> 0 | AE29: 278 | AF29: =+IFERROR(VLOOKUP($AF$17,Sheet1!V23:Y23,3,0),0) -> 0 | AG29: =+IFERROR(VLOOKUP($AG$17,Sheet1!V23:Y23,3,0),0) -> 0 | AH29: =+IFERROR(VLOOKUP($AH$17,Sheet1!V23:Y23,3,0),0) -> 0 | AI29: =+IFERROR(VLOOKUP($AI$17,Sheet1!V23:Y23,3,0),0) -> 0 | AJ29: =+IFERROR(VLOOKUP($AJ$17,Sheet1!V23:Y23,3,0),0) -> 0 | AK29: 22 | AL29: =+IFERROR(VLOOKUP($AL$17,Sheet1!AD23:AG23,3,0),0) -> 0 | AM29: =+IFERROR(VLOOKUP($AM$17,Sheet1!AD23:AG23,3,0),0) -> 0 | AN29: =+IFERROR(VLOOKUP($AN$17,Sheet1!AD23:AG23,3,0),0) -> 0 | AO29: =+IFERROR(VLOOKUP($AO$17,Sheet1!AD23:AG23,3,0),0) -> 0 | AP29: =+IFERROR(VLOOKUP($AP$17,Sheet1!AD23:AG23,3,0),0) -> 0 | AQ29: 95 | AR29: =+IFERROR(VLOOKUP($AR$17,Sheet1!AD23:AG23,3,0),0) -> 0 | AS29: =+IFERROR(VLOOKUP($AS$17,Sheet1!AH23:AK23,3,0),0) -> 0 | AT29: =+IFERROR(VLOOKUP($AT$17,Sheet1!AH23:AK23,3,0),0) -> 0 | AU29: =+IFERROR(VLOOKUP($AU$17,Sheet1!AH23:AK23,3,0),0) -> 0 | AV29: 424 | AW29: =+IFERROR(VLOOKUP($AW$17,Sheet1!AH23:AK23,3,0),0) -> 0 | AX29: =+IFERROR(VLOOKUP($AX$17,Sheet1!AH23:AK23,3,0),0) -> 0 | AY29: =+IFERROR(VLOOKUP($AY$17,Sheet1!AH23:AK23,3,0),0) -> 0 | AZ29: =+IFERROR(VLOOKUP($AZ$17,Sheet1!AH23:AK23,3,0),0) -> 0 | BA29: =+IFERROR(VLOOKUP($BA$17,Sheet1!AH23:AK23,3,0),0) -> 0 | BB29: =+IFERROR(VLOOKUP($BB$17,Sheet1!AH23:AK23,3,0),0) -> 0 | BC29: =+IFERROR(VLOOKUP($BC$17,Sheet1!AL23:AO23,3,0),0) -> 0 | BD29: =+IFERROR(VLOOKUP($BD$17,Sheet1!AL23:AO23,3,0),0) -> 0 | BE29: =+IFERROR(VLOOKUP($BE$17,Sheet1!AL23:AO23,3,0),0) -> 0 | BF29: 343 | BG29: =+IFERROR(VLOOKUP($BG$17,Sheet1!AL23:AO23,3,0),0) -> 0 | BH29: =+IFERROR(VLOOKUP($BH$17,Sheet1!AL23:AO23,3,0),0) -> 0 | BI29: =+IFERROR(VLOOKUP($BI$17,Sheet1!AL23:AO23,3,0),0) -> 0 | BJ29: =+IFERROR(VLOOKUP($BJ$17,Sheet1!AL23:AO23,3,0),0) -> 0 | BK29: =+IFERROR(VLOOKUP($BK$17,Sheet1!AL23:AO23,3,0),0) -> 0 | BL29: =+IFERROR(VLOOKUP($BL$17,Sheet1!AL23:AO23,3,0),0) -> 0 | BM29: =+IFERROR(VLOOKUP($BM$17,Sheet1!AP23:AS23,3,0),0) -> 0 | BN29: 13 | BO29: =+IFERROR(VLOOKUP($BO$17,Sheet1!AX23:BA23,3,0),0) -> 0 | BP29: 29 | BQ29: =+IFERROR(VLOOKUP($BQ$17,Sheet1!BF23:BI23,3,0),0) -> 0 | BR29: =+IFERROR(VLOOKUP($BR$17,Sheet1!BJ23:BM23,3,0),0) -> 0 | BS29: =+IFERROR(VLOOKUP($BS$17,Sheet1!BN23:BQ23,3,0),0) -> 0 | BT29: 27 | BU29: =+IFERROR(VLOOKUP($BU$17,Sheet1!BV23:BY23,3,0),0) -> 0 | BV29: =Sheet1!E23 -> STEEL | BW29: =Sheet1!CV23 -> SP0400152 | BX29: =Sheet1!CW23 -> CORRUGATED DISPATCH STEEL DRUM 1500 X 800 X 915 | BY29: =Sheet1!CX23 -> 500 | BZ29: =14400/0.5 -> 28800 | CA29: =SUMPRODUCT($N$18:$BU$18,N29:BU29)+BZ29 -> 534983 | CB29: 0.01 | CC29: =CA29*CB29 -> 5349.83 | CD29: 0.25 | CE29: =CA29*CD29 -> 133745.75 | CF29: =Sheet1!CF23 -> 0 | CG29: =CA29*CF29 -> 0 | CH29: =CA29+CC29+CE29+CG29 -> 674078.58 | CI29: 0.02 | CJ29: =CH29*CI29 -> 13481.572 | CK29: 0.01 | CL29: =CH29*CK29 -> 6740.7858
A30: =Sheet1!A21 -> ENQ-15138-22-23 | B30: =Sheet1!B21 -> 45627 | C30: =Sheet1!C21 -> FA1300080 | D30: =Sheet1!D21 -> 3 CORE X 400 SQ. MM AL/ARM - WIRE (XLPE) - 33 KV | E30: =CH30+CJ30+CL30 -> 3751528.4 | F30: =ROUNDUP(M54,0) -> 65073 | G30: =E30+F30 -> 3816601.4 | H30: =Sheet1!CP21 -> 0.18 | I30: =G30*H30 -> 686988.25 | J30: =G30+I30 -> 4503589.6 | K30: =Sheet1!CS21 -> 222.75 | L30: =Sheet1!CT21 -> KMS | M30: =J30*K30 -> 1.0031746e+09 | N30: =+IFERROR(VLOOKUP($N$17,Sheet1!J21:L21,3,0),0) -> 3240 | O30: =+IFERROR(VLOOKUP($O$17,Sheet1!J21:L21,3,0),0) -> 0 | P30: =+IFERROR(VLOOKUP($P$17,Sheet1!J21:M21,3,0),0) -> 0 | Q30: =+IFERROR(VLOOKUP($Q$17,Sheet1!J21:M21,3,0),0) -> 0 | R30: =+IFERROR(VLOOKUP($R$17,Sheet1!J21:M21,3,0),0) -> 0 | S30: =+IFERROR(VLOOKUP($S$17,Sheet1!N21:Q21,3,0),0) -> 0 | T30: =+IFERROR(VLOOKUP($T$17,Sheet1!N21:Q21,3,0),0) -> 0 | U30: =+IFERROR(VLOOKUP($U$17,Sheet1!F21:I21,3,0),0) -> 0 | V30: =+IFERROR(VLOOKUP($V$17,Sheet1!F21:I21,3,0),0) -> 0 | W30: =+IFERROR(VLOOKUP($W$17,Sheet1!F21:I21,3,0),0) -> 0 | X30: =+IFERROR(VLOOKUP($X$17,Sheet1!F21:I21,3,0),0) -> 0 | Y30: 229 | Z30: =+IFERROR(VLOOKUP($Z$17,Sheet1!F21:I21,3,0),0) -> 0 | AA30: =+IFERROR(VLOOKUP($AA$17,Sheet1!F21:I21,3,0),0) -> 0 | AB30: =+IFERROR(VLOOKUP($AB$17,Sheet1!F21:I21,3,0),0) -> 0 | AC30: 618 | AD30: =+IFERROR(VLOOKUP($AD$17,Sheet1!R21:U21,2,0),0) -> 0 | AE30: 2674 | AF30: =+IFERROR(VLOOKUP($AF$17,Sheet1!V21:Y21,3,0),0) -> 0 | AG30: =+IFERROR(VLOOKUP($AG$17,Sheet1!V21:Y21,3,0),0) -> 0 | AH30: =+IFERROR(VLOOKUP($AH$17,Sheet1!V21:Y21,3,0),0) -> 0 | AI30: =+IFERROR(VLOOKUP($AI$17,Sheet1!V21:Y21,3,0),0) -> 0 | AJ30: =+IFERROR(VLOOKUP($AJ$17,Sheet1!V21:Y21,3,0),0) -> 0 | AK30: =+IFERROR(VLOOKUP($AK$17,Sheet1!Z21:AB21,3,0),0) -> 0 | AL30: =+IFERROR(VLOOKUP($AL$17,Sheet1!AD21:AG21,3,0),0) -> 0 | AM30: =+IFERROR(VLOOKUP($AM$17,Sheet1!AD21:AG21,3,0),0) -> 0 | AN30: =+IFERROR(VLOOKUP($AN$17,Sheet1!AD21:AG21,3,0),0) -> 0 | AO30: =+IFERROR(VLOOKUP($AO$17,Sheet1!AD21:AG21,3,0),0) -> 0 | AP30: =+IFERROR(VLOOKUP($AP$17,Sheet1!AD21:AG21,3,0),0) -> 0 | AQ30: 1629 | AS30: =+IFERROR(VLOOKUP($AS$17,Sheet1!AH21:AK21,3,0),0) -> 0 | AT30: =+IFERROR(VLOOKUP($AT$17,Sheet1!AH21:AK21,3,0),0) -> 0 | AU30: =+IFERROR(VLOOKUP($AU$17,Sheet1!AH21:AK21,3,0),0) -> 0 | AV30: =+IFERROR(VLOOKUP($AV$17,Sheet1!AH21:AK21,3,0),0) -> 0 | AW30: =+IFERROR(VLOOKUP($AW$17,Sheet1!AH21:AK21,3,0),0) -> 0 | AX30: =+IFERROR(VLOOKUP($AX$17,Sheet1!AH21:AK21,3,0),0) -> 0 | AY30: =+IFERROR(VLOOKUP($AY$17,Sheet1!AH21:AK21,3,0),0) -> 0 | AZ30: =+IFERROR(VLOOKUP($AZ$17,Sheet1!AH21:AK21,3,0),0) -> 0 | BA30: 7284 | BB30: =+IFERROR(VLOOKUP($BB$17,Sheet1!AH21:AK21,3,0),0) -> 0 | BC30: =+IFERROR(VLOOKUP($BC$17,Sheet1!AL21:AO21,3,0),0) -> 0 | BD30: =+IFERROR(VLOOKUP($BD$17,Sheet1!AL21:AO21,3,0),0) -> 0 | BE30: =+IFERROR(VLOOKUP($BE$17,Sheet1!AL21:AO21,3,0),0) -> 0 | BF30: 1760 | BG30: =+IFERROR(VLOOKUP($BG$17,Sheet1!AL21:AO21,3,0),0) -> 0 | BH30: =+IFERROR(VLOOKUP($BH$17,Sheet1!AL21:AO21,3,0),0) -> 0 | BI30: =+IFERROR(VLOOKUP($BI$17,Sheet1!AL21:AO21,3,0),0) -> 0 | BJ30: =+IFERROR(VLOOKUP($BJ$17,Sheet1!AL21:AO21,3,0),0) -> 0 | BK30: =+IFERROR(VLOOKUP($BK$17,Sheet1!AL21:AO21,3,0),0) -> 0 | BL30: 1750 | BM30: =+IFERROR(VLOOKUP($BM$17,Sheet1!AP21:AS21,3,0),0) -> 0 | BN30: 58 | BP30: 114 | BQ30: =+IFERROR(VLOOKUP($BQ$17,Sheet1!BF21:BI21,3,0),0) -> 0 | BR30: =+IFERROR(VLOOKUP($BR$17,Sheet1!BJ21:BM21,3,0),0) -> 0 | BS30: =+IFERROR(VLOOKUP($BS$17,Sheet1!BN21:BQ21,3,0),0) -> 0 | BT30: 76 | BU30: =+IFERROR(VLOOKUP($BU$17,Sheet1!BV21:BY21,3,0),0) -> 0 | BV30: =Sheet1!E21 -> STEEL | BW30: =Sheet1!CV21 -> SP0400137 | BX30: =Sheet1!CW21 -> CORRUGATED DISPATCH STEEL DRUM 2600 X 1600 X 1600 MM | BY30: =Sheet1!CX21 -> 250 | BZ30: =44000/0.25 -> 176000 | CA30: =SUMPRODUCT($N$18:$BU$18,N30:BU30)+BZ30 -> 2890683 | CB30: 0.01 | CC30: =CA30*CB30 -> 28906.83 | CD30: 0.25 | CE30: =CA30*CD30 -> 722670.75 | CF30: =Sheet1!CF21 -> 0 | CG30: =CA30*CF30 -> 0 | CH30: =CA30+CC30+CE30+CG30 -> 3642260.6 | CI30: 0.02 | CJ30: =CH30*CI30 -> 72845.212 | CK30: 0.01 | CL30: =CH30*CK30 -> 36422.606
A31: =Sheet1!A20 -> ENQ-15138-22-23 | B31: =Sheet1!B20 -> 45627 | C31: =Sheet1!C20 -> FA1300081 | D31: =Sheet1!D20 -> 3 CORE X 300 SQ. MM. AL/ARM - WIRE (XLPE) - 33 KV | E31: =CH31+CJ31+CL31 -> 3269603.3 | F31: =ROUNDUP(M55,0) -> 66858 | G31: =E31+F31 -> 3336461.3 | H31: =Sheet1!CP20 -> 0.18 | I31: =G31*H31 -> 600563.04 | J31: =G31+I31 -> 3937024.4 | K31: =Sheet1!CS20 -> 17.5 | L31: =Sheet1!CT20 -> KMS | M31: =J31*K31 -> 68897927 | N31: =+IFERROR(VLOOKUP($N$17,Sheet1!J20:L20,3,0),0) -> 2430 | O31: =+IFERROR(VLOOKUP($O$17,Sheet1!J20:L20,3,0),0) -> 0 | P31: =+IFERROR(VLOOKUP($P$17,Sheet1!J20:M20,3,0),0) -> 0 | Q31: =+IFERROR(VLOOKUP($Q$17,Sheet1!J20:M20,3,0),0) -> 0 | R31: =+IFERROR(VLOOKUP($R$17,Sheet1!J20:M20,3,0),0) -> 0 | S31: =+IFERROR(VLOOKUP($S$17,Sheet1!N20:Q20,3,0),0) -> 0 | T31: =+IFERROR(VLOOKUP($T$17,Sheet1!N20:Q20,3,0),0) -> 0 | U31: =+IFERROR(VLOOKUP($U$17,Sheet1!F20:I20,3,0),0) -> 0 | V31: =+IFERROR(VLOOKUP($V$17,Sheet1!F20:I20,3,0),0) -> 0 | W31: =+IFERROR(VLOOKUP($W$17,Sheet1!F20:I20,3,0),0) -> 0 | X31: =+IFERROR(VLOOKUP($X$17,Sheet1!F20:I20,3,0),0) -> 0 | Y31: 214 | Z31: =+IFERROR(VLOOKUP($Z$17,Sheet1!F20:I20,3,0),0) -> 0 | AA31: =+IFERROR(VLOOKUP($AA$17,Sheet1!F20:I20,3,0),0) -> 0 | AB31: =+IFERROR(VLOOKUP($AB$17,Sheet1!F20:I20,3,0),0) -> 0 | AC31: 564 | AD31: =+IFERROR(VLOOKUP($AD$17,Sheet1!R20:U20,2,0),0) -> 0 | AE31: 2438 | AF31: =+IFERROR(VLOOKUP($AF$17,Sheet1!V20:Y20,3,0),0) -> 0 | AG31: =+IFERROR(VLOOKUP($AG$17,Sheet1!V20:Y20,3,0),0) -> 0 | AH31: =+IFERROR(VLOOKUP($AH$17,Sheet1!V20:Y20,3,0),0) -> 0 | AI31: =+IFERROR(VLOOKUP($AI$17,Sheet1!V20:Y20,3,0),0) -> 0 | AJ31: =+IFERROR(VLOOKUP($AJ$17,Sheet1!V20:Y20,3,0),0) -> 0 | AK31: =+IFERROR(VLOOKUP($AK$17,Sheet1!Z20:AB20,3,0),0) -> 0 | AL31: =+IFERROR(VLOOKUP($AL$17,Sheet1!AD20:AG20,3,0),0) -> 0 | AM31: =+IFERROR(VLOOKUP($AM$17,Sheet1!AD20:AG20,3,0),0) -> 0 | AN31: =+IFERROR(VLOOKUP($AN$17,Sheet1!AD20:AG20,3,0),0) -> 0 | AO31: =+IFERROR(VLOOKUP($AO$17,Sheet1!AD20:AG20,3,0),0) -> 0 | AP31: =+IFERROR(VLOOKUP($AP$17,Sheet1!AD20:AG20,3,0),0) -> 0 | AQ31: 1449 | AS31: =+IFERROR(VLOOKUP($AS$17,Sheet1!AH20:AK20,3,0),0) -> 0 | AT31: =+IFERROR(VLOOKUP($AT$17,Sheet1!AH20:AK20,3,0),0) -> 0 | AU31: =+IFERROR(VLOOKUP($AU$17,Sheet1!AH20:AK20,3,0),0) -> 0 | AV31: =+IFERROR(VLOOKUP($AV$17,Sheet1!AH20:AK20,3,0),0) -> 0 | AW31: =+IFERROR(VLOOKUP($AW$17,Sheet1!AH20:AK20,3,0),0) -> 0 | AX31: =+IFERROR(VLOOKUP($AX$17,Sheet1!AH20:AK20,3,0),0) -> 0 | AY31: =+IFERROR(VLOOKUP($AY$17,Sheet1!AH20:AK20,3,0),0) -> 0 | AZ31: =+IFERROR(VLOOKUP($AZ$17,Sheet1!AH20:AK20,3,0),0) -> 0 | BA31: 6874 | BB31: =+IFERROR(VLOOKUP($BB$17,Sheet1!AH20:AK20,3,0),0) -> 0 | BC31: =+IFERROR(VLOOKUP($BC$17,Sheet1!AL20:AO20,3,0),0) -> 0 | BD31: =+IFERROR(VLOOKUP($BD$17,Sheet1!AL20:AO20,3,0),0) -> 0 | BE31: =+IFERROR(VLOOKUP($BE$17,Sheet1!AL20:AO20,3,0),0) -> 0 | BF31: 1655 | BG31: =+IFERROR(VLOOKUP($BG$17,Sheet1!AL20:AO20,3,0),0) -> 0 | BH31: =+IFERROR(VLOOKUP($BH$17,Sheet1!AL20:AO20,3,0),0) -> 0 | BI31: =+IFERROR(VLOOKUP($BI$17,Sheet1!AL20:AO20,3,0),0) -> 0 | BJ31: =+IFERROR(VLOOKUP($BJ$17,Sheet1!AL20:AO20,3,0),0) -> 0 | BK31: =+IFERROR(VLOOKUP($BK$17,Sheet1!AL20:AO20,3,0),0) -> 0 | BL31: 1525 | BM31: =+IFERROR(VLOOKUP($BM$17,Sheet1!AP20:AS20,3,0),0) -> 0 | BN31: 38 | BO31: =+IFERROR(VLOOKUP($BO$17,Sheet1!AX20:BA20,3,0),0) -> 0 | BP31: 104 | BQ31: =+IFERROR(VLOOKUP($BQ$17,Sheet1!BF20:BI20,3,0),0) -> 0 | BR31: =+IFERROR(VLOOKUP($BR$17,Sheet1!BJ20:BM20,3,0),0) -> 0 | BS31: =+IFERROR(VLOOKUP($BS$17,Sheet1!BN20:BQ20,3,0),0) -> 0 | BT31: 72 | BU31: =+IFERROR(VLOOKUP($BU$17,Sheet1!BV20:BY20,3,0),0) -> 0 | BV31: =Sheet1!E20 -> STEEL | BW31: SP0400105 | BX31: CORRUGATED DISPATCH STEEL DRUM 2500 X 1500 X 1400 | BY31: =Sheet1!CX20 -> 250 | BZ31: =40000/0.25 -> 160000 | CA31: =SUMPRODUCT($N$18:$BU$18,N31:BU31)+BZ31 -> 2519343 | CB31: 0.01 | CC31: =CA31*CB31 -> 25193.43 | CD31: 0.25 | CE31: =CA31*CD31 -> 629835.75 | CF31: =Sheet1!CF20 -> 0 | CG31: =CA31*CF31 -> 0 | CH31: =CA31+CC31+CE31+CG31 -> 3174372.2 | CI31: 0.02 | CJ31: =CH31*CI31 -> 63487.444 | CK31: 0.01 | CL31: =CH31*CK31 -> 31743.722
A32: =Sheet1!A2 -> ENQ-15138-22-23 | B32: =Sheet1!B2 -> 45627 | C32: =Sheet1!C2 -> FA1300079 | D32: =Sheet1!D2 -> 3 CORE X 185 SQ. MM AL/ARM - WIRE (XLPE) - 33 KV | E32: =CH32+CJ32+CL32 -> 2659700.9 | F32: =ROUNDUP(M56,0) -> 46800 | G32: =E32+F32 -> 2706500.9 | H32: =Sheet1!CP2 -> 0.18 | I32: =G32*H32 -> 487170.17 | J32: =G32+I32 -> 3193671.1 | K32: =Sheet1!CS2 -> 12.5 | L32: =Sheet1!CT2 -> KMS | M32: =J32*K32 -> 39920889 | N32: =+IFERROR(VLOOKUP($N$17,Sheet1!J2:L2,3,0),0) -> 1499 | O32: =+IFERROR(VLOOKUP($O$17,Sheet1!J2:L2,3,0),0) -> 0 | P32: =+IFERROR(VLOOKUP($P$17,Sheet1!J2:M2,3,0),0) -> 0 | Q32: =+IFERROR(VLOOKUP($Q$17,Sheet1!J2:M2,3,0),0) -> 0 | R32: =+IFERROR(VLOOKUP($R$17,Sheet1!J2:M2,3,0),0) -> 0 | S32: =+IFERROR(VLOOKUP($S$17,Sheet1!N2:Q2,3,0),0) -> 0 | T32: =+IFERROR(VLOOKUP($T$17,Sheet1!N2:Q2,3,0),0) -> 0 | U32: =+IFERROR(VLOOKUP($U$17,Sheet1!F2:I2,3,0),0) -> 0 | V32: =+IFERROR(VLOOKUP($V$17,Sheet1!F2:I2,3,0),0) -> 0 | W32: =+IFERROR(VLOOKUP($W$17,Sheet1!F2:I2,3,0),0) -> 0 | X32: =+IFERROR(VLOOKUP($X$17,Sheet1!F2:I2,3,0),0) -> 0 | Y32: 191 | Z32: =+IFERROR(VLOOKUP($Z$17,Sheet1!F2:I2,3,0),0) -> 0 | AA32: =+IFERROR(VLOOKUP($AA$17,Sheet1!F2:I2,3,0),0) -> 0 | AB32: =+IFERROR(VLOOKUP($AB$17,Sheet1!F2:I2,3,0),0) -> 0 | AC32: 486 | AD32: =+IFERROR(VLOOKUP($AD$17,Sheet1!R2:U2,2,0),0) -> 0 | AE32: 2091 | AF32: =+IFERROR(VLOOKUP($AF$17,Sheet1!V2:Y2,3,0),0) -> 0 | AG32: =+IFERROR(VLOOKUP($AG$17,Sheet1!V2:Y2,3,0),0) -> 0 | AH32: =+IFERROR(VLOOKUP($AH$17,Sheet1!V2:Y2,3,0),0) -> 0 | AI32: =+IFERROR(VLOOKUP($AI$17,Sheet1!V2:Y2,3,0),0) -> 0 | AJ32: =+IFERROR(VLOOKUP($AJ$17,Sheet1!V2:Y2,3,0),0) -> 0 | AK32: =+IFERROR(VLOOKUP($AK$17,Sheet1!Z2:AB2,3,0),0) -> 0 | AL32: =+IFERROR(VLOOKUP($AL$17,Sheet1!AD2:AG2,3,0),0) -> 0 | AM32: =+IFERROR(VLOOKUP($AM$17,Sheet1!AD2:AG2,3,0),0) -> 0 | AN32: =+IFERROR(VLOOKUP($AN$17,Sheet1!AD2:AG2,3,0),0) -> 0 | AO32: =+IFERROR(VLOOKUP($AO$17,Sheet1!AD2:AG2,3,0),0) -> 0 | AP32: =+IFERROR(VLOOKUP($AP$17,Sheet1!AD2:AG2,3,0),0) -> 0 | AQ32: 1186 | AS32: =+IFERROR(VLOOKUP($AS$17,Sheet1!AH2:AK2,3,0),0) -> 0 | AT32: =+IFERROR(VLOOKUP($AT$17,Sheet1!AH2:AK2,3,0),0) -> 0 | AU32: =+IFERROR(VLOOKUP($AU$17,Sheet1!AH2:AK2,3,0),0) -> 0 | AV32: =+IFERROR(VLOOKUP($AV$17,Sheet1!AH2:AK2,3,0),0) -> 0 | AW32: =+IFERROR(VLOOKUP($AW$17,Sheet1!AH2:AK2,3,0),0) -> 0 | AX32: =+IFERROR(VLOOKUP($AX$17,Sheet1!AH2:AK2,3,0),0) -> 0 | AY32: =+IFERROR(VLOOKUP($AY$17,Sheet1!AH2:AK2,3,0),0) -> 0 | AZ32: =+IFERROR(VLOOKUP($AZ$17,Sheet1!AH2:AK2,3,0),0) -> 0 | BA32: 6155 | BB32: =+IFERROR(VLOOKUP($BB$17,Sheet1!AH2:AK2,3,0),0) -> 0 | BC32: =+IFERROR(VLOOKUP($BC$17,Sheet1!AL2:AO2,3,0),0) -> 0 | BD32: =+IFERROR(VLOOKUP($BD$17,Sheet1!AL2:AO2,3,0),0) -> 0 | BE32: =+IFERROR(VLOOKUP($BE$17,Sheet1!AL2:AO2,3,0),0) -> 0 | BF32: 1480 | BG32: =+IFERROR(VLOOKUP($BG$17,Sheet1!AL2:AO2,3,0),0) -> 0 | BH32: =+IFERROR(VLOOKUP($BH$17,Sheet1!AL2:AO2,3,0),0) -> 0 | BI32: =+IFERROR(VLOOKUP($BI$17,Sheet1!AL2:AO2,3,0),0) -> 0 | BJ32: =+IFERROR(VLOOKUP($BJ$17,Sheet1!AL2:AO2,3,0),0) -> 0 | BK32: =+IFERROR(VLOOKUP($BK$17,Sheet1!AL2:AO2,3,0),0) -> 0 | BL32: 1224 | BM32: =+IFERROR(VLOOKUP($BM$17,Sheet1!AP2:AS2,3,0),0) -> 0 | BN32: 35 | BO32: =+IFERROR(VLOOKUP($BO$17,Sheet1!AX2:BA2,3,0),0) -> 0 | BP32: 90 | BQ32: =+IFERROR(VLOOKUP($BQ$17,Sheet1!BF2:BI2,3,0),0) -> 0 | BR32: =+IFERROR(VLOOKUP($BR$17,Sheet1!BJ2:BM2,3,0),0) -> 0 | BS32: =+IFERROR(VLOOKUP($BS$17,Sheet1!BN2:BQ2,3,0),0) -> 0 | BT32: 65 | BU32: =+IFERROR(VLOOKUP($BU$17,Sheet1!BV2:BY2,3,0),0) -> 0 | BV32: =Sheet1!E2 -> STEEL | BW32: SP0400108 | BX32: CORRUGATED DISPATCH STEEL DRUM 2250 X 1200 X 1400 MM | BY32: =Sheet1!CX2 -> 250 | BZ32: =36900/0.25 -> 147600 | CA32: =SUMPRODUCT($N$18:$BU$18,N32:BU32)+BZ32 -> 2049392 | CB32: 0.01 | CC32: =CA32*CB32 -> 20493.92 | CD32: 0.25 | CE32: =CA32*CD32 -> 512348 | CF32: =Sheet1!CF2 -> 0 | CG32: =CA32*CF32 -> 0 | CH32: =CA32+CC32+CE32+CG32 -> 2582233.9 | CI32: 0.02 | CJ32: =CH32*CI32 -> 51644.678 | CK32: 0.01 | CL32: =CH32*CK32 -> 25822.339
A33: =Sheet1!A5 -> ENQ-15138-22-23 | B33: =Sheet1!B5 -> 45627 | C33: =Sheet1!C5 -> FA1300200 | D33: =Sheet1!D5 -> 3 CORE X 95 SQ. MM. AL/ARM WIRE (XLPE) - 33 KV | E33: =CH33+CJ33+CL33 -> 1960522.9 | F33: =ROUNDUP(M57,0) -> 32500 | G33: =E33+F33 -> 1993022.9 | H33: =Sheet1!CP5 -> 0.18 | I33: =G33*H33 -> 358744.12 | J33: =G33+I33 -> 2351767 | K33: =Sheet1!CS5 -> 4 | L33: =Sheet1!CT5 -> KMS | M33: =J33*K33 -> 9407067.9 | N33: =+IFERROR(VLOOKUP($N$17,Sheet1!J5:L5,3,0),0) -> 770 | O33: =+IFERROR(VLOOKUP($O$17,Sheet1!J5:L5,3,0),0) -> 0 | P33: =+IFERROR(VLOOKUP($P$17,Sheet1!J5:M5,3,0),0) -> 0 | Q33: =+IFERROR(VLOOKUP($Q$17,Sheet1!J5:M5,3,0),0) -> 0 | R33: =+IFERROR(VLOOKUP($R$17,Sheet1!J5:M5,3,0),0) -> 0 | S33: =+IFERROR(VLOOKUP($S$17,Sheet1!N5:Q5,3,0),0) -> 0 | T33: =+IFERROR(VLOOKUP($T$17,Sheet1!N5:Q5,3,0),0) -> 0 | U33: =+IFERROR(VLOOKUP($U$17,Sheet1!F5:I5,3,0),0) -> 0 | V33: =+IFERROR(VLOOKUP($V$17,Sheet1!F5:I5,3,0),0) -> 0 | W33: =+IFERROR(VLOOKUP($W$17,Sheet1!F5:I5,3,0),0) -> 0 | X33: =+IFERROR(VLOOKUP($X$17,Sheet1!F5:I5,3,0),0) -> 0 | Y33: 167 | Z33: =+IFERROR(VLOOKUP($Z$17,Sheet1!F5:I5,3,0),0) -> 0 | AA33: =+IFERROR(VLOOKUP($AA$17,Sheet1!F5:I5,3,0),0) -> 0 | AB33: =+IFERROR(VLOOKUP($AB$17,Sheet1!F5:I5,3,0),0) -> 0 | AC33: 403 | AD33: =+IFERROR(VLOOKUP($AD$17,Sheet1!R5:U5,2,0),0) -> 0 | AE33: 1724 | AF33: =+IFERROR(VLOOKUP($AF$17,Sheet1!V5:Y5,3,0),0) -> 0 | AG33: =+IFERROR(VLOOKUP($AG$17,Sheet1!V5:Y5,3,0),0) -> 0 | AH33: =+IFERROR(VLOOKUP($AH$17,Sheet1!V5:Y5,3,0),0) -> 0 | AI33: =+IFERROR(VLOOKUP($AI$17,Sheet1!V5:Y5,3,0),0) -> 0 | AJ33: =+IFERROR(VLOOKUP($AJ$17,Sheet1!V5:Y5,3,0),0) -> 0 | AK33: =+IFERROR(VLOOKUP($AK$17,Sheet1!Z5:AB5,3,0),0) -> 0 | AL33: =+IFERROR(VLOOKUP($AL$17,Sheet1!AD5:AG5,3,0),0) -> 0 | AM33: =+IFERROR(VLOOKUP($AM$17,Sheet1!AD5:AG5,3,0),0) -> 0 | AN33: =+IFERROR(VLOOKUP($AN$17,Sheet1!AD5:AG5,3,0),0) -> 0 | AO33: =+IFERROR(VLOOKUP($AO$17,Sheet1!AD5:AG5,3,0),0) -> 0 | AP33: =+IFERROR(VLOOKUP($AP$17,Sheet1!AD5:AG5,3,0),0) -> 0 | AQ33: 950 | AS33: =+IFERROR(VLOOKUP($AS$17,Sheet1!AH5:AK5,3,0),0) -> 0 | AT33: =+IFERROR(VLOOKUP($AT$17,Sheet1!AH5:AK5,3,0),0) -> 0 | AU33: =+IFERROR(VLOOKUP($AU$17,Sheet1!AH5:AK5,3,0),0) -> 0 | AV33: =+IFERROR(VLOOKUP($AV$17,Sheet1!AH5:AK5,3,0),0) -> 0 | AW33: =+IFERROR(VLOOKUP($AW$17,Sheet1!AH5:AK5,3,0),0) -> 0 | AX33: =+IFERROR(VLOOKUP($AX$17,Sheet1!AH5:AK5,3,0),0) -> 0 | AY33: =+IFERROR(VLOOKUP($AY$17,Sheet1!AH5:AK5,3,0),0) -> 0 | AZ33: =+IFERROR(VLOOKUP($AZ$17,Sheet1!AH5:AK5,3,0),0) -> 0 | BA33: 4262 | BB33: =+IFERROR(VLOOKUP($BB$17,Sheet1!AH5:AK5,3,0),0) -> 0 | BC33: =+IFERROR(VLOOKUP($BC$17,Sheet1!AL5:AO5,3,0),0) -> 0 | BD33: =+IFERROR(VLOOKUP($BD$17,Sheet1!AL5:AO5,3,0),0) -> 0 | BE33: =+IFERROR(VLOOKUP($BE$17,Sheet1!AL5:AO5,3,0),0) -> 0 | BF33: 1296 | BG33: =+IFERROR(VLOOKUP($BG$17,Sheet1!AL5:AO5,3,0),0) -> 0 | BH33: =+IFERROR(VLOOKUP($BH$17,Sheet1!AL5:AO5,3,0),0) -> 0 | BI33: =+IFERROR(VLOOKUP($BI$17,Sheet1!AL5:AO5,3,0),0) -> 0 | BJ33: =+IFERROR(VLOOKUP($BJ$17,Sheet1!AL5:AO5,3,0),0) -> 0 | BK33: =+IFERROR(VLOOKUP($BK$17,Sheet1!AL5:AO5,3,0),0) -> 0 | BL33: 940 | BM33: =+IFERROR(VLOOKUP($BM$17,Sheet1!AP5:AS5,3,0),0) -> 0 | BN33: 15 | BO33: =+IFERROR(VLOOKUP($BO$17,Sheet1!AX5:BA5,3,0),0) -> 0 | BP33: 75 | BQ33: =+IFERROR(VLOOKUP($BQ$17,Sheet1!BF5:BI5,3,0),0) -> 0 | BR33: =+IFERROR(VLOOKUP($BR$17,Sheet1!BJ5:BM5,3,0),0) -> 0 | BS33: =+IFERROR(VLOOKUP($BS$17,Sheet1!BN5:BQ5,3,0),0) -> 0 | BT33: 57 | BU33: =+IFERROR(VLOOKUP($BU$17,Sheet1!BV5:BY5,3,0),0) -> 0 | BV33: =Sheet1!E5 -> STEEL | BW33: =Sheet1!CV5 -> SP0400136 | BX33: =Sheet1!CW5 -> CORRUGATED DISPATCH STEEL DRUM 2200 X 1300 X 1200 MM | BY33: =Sheet1!CX5 -> 250 | BZ33: =32000/0.25 -> 128000 | CA33: =SUMPRODUCT($N$18:$BU$18,N33:BU33)+BZ33 -> 1510651 | CB33: 0.01 | CC33: =CA33*CB33 -> 15106.51 | CD33: 0.25 | CE33: =CA33*CD33 -> 377662.75 | CF33: =Sheet1!CF5 -> 0 | CG33: =CA33*CF33 -> 0 | CH33: =CA33+CC33+CE33+CG33 -> 1903420.3 | CI33: 0.02 | CJ33: =CH33*CI33 -> 38068.405 | CK33: 0.01 | CL33: =CH33*CK33 -> 19034.203
A34: =Sheet1!A4 -> ENQ-15138-22-23 | B34: =Sheet1!B4 -> 45627 | C34: =Sheet1!C4 -> FA1300120 | D34: =Sheet1!D4 -> 3 CORE X 70 SQ. MM. AL/ARM - WIRE (XLPE) - 33 KV | E34: =CH34+CJ34+CL34 -> 1826652.2 | F34: =ROUNDUP(M58,0) -> 43334 | G34: =E34+F34 -> 1869986.2 | H34: =Sheet1!CP4 -> 0.18 | I34: =G34*H34 -> 336597.52 | J34: =G34+I34 -> 2206583.7 | K34: =Sheet1!CS4 -> 3 | L34: =Sheet1!CT4 -> KMS | M34: =J34*K34 -> 6619751.2 | N34: =+IFERROR(VLOOKUP($N$17,Sheet1!J4:L4,3,0),0) -> 567 | O34: =+IFERROR(VLOOKUP($O$17,Sheet1!J4:L4,3,0),0) -> 0 | P34: =+IFERROR(VLOOKUP($P$17,Sheet1!J4:M4,3,0),0) -> 0 | Q34: =+IFERROR(VLOOKUP($Q$17,Sheet1!J4:M4,3,0),0) -> 0 | R34: =+IFERROR(VLOOKUP($R$17,Sheet1!J4:M4,3,0),0) -> 0 | S34: =+IFERROR(VLOOKUP($S$17,Sheet1!N4:Q4,3,0),0) -> 0 | T34: =+IFERROR(VLOOKUP($T$17,Sheet1!N4:Q4,3,0),0) -> 0 | U34: =+IFERROR(VLOOKUP($U$17,Sheet1!F4:I4,3,0),0) -> 0 | V34: =+IFERROR(VLOOKUP($V$17,Sheet1!F4:I4,3,0),0) -> 0 | W34: =+IFERROR(VLOOKUP($W$17,Sheet1!F4:I4,3,0),0) -> 0 | X34: =+IFERROR(VLOOKUP($X$17,Sheet1!F4:I4,3,0),0) -> 0 | Y34: 161 | Z34: =+IFERROR(VLOOKUP($Z$17,Sheet1!F4:I4,3,0),0) -> 0 | AA34: =+IFERROR(VLOOKUP($AA$17,Sheet1!F4:I4,3,0),0) -> 0 | AB34: =+IFERROR(VLOOKUP($AB$17,Sheet1!F4:I4,3,0),0) -> 0 | AC34: 378 | AD34: =+IFERROR(VLOOKUP($AD$17,Sheet1!R4:U4,2,0),0) -> 0 | AE34: 1615 | AF34: =+IFERROR(VLOOKUP($AF$17,Sheet1!V4:Y4,3,0),0) -> 0 | AG34: =+IFERROR(VLOOKUP($AG$17,Sheet1!V4:Y4,3,0),0) -> 0 | AH34: =+IFERROR(VLOOKUP($AH$17,Sheet1!V4:Y4,3,0),0) -> 0 | AI34: =+IFERROR(VLOOKUP($AI$17,Sheet1!V4:Y4,3,0),0) -> 0 | AJ34: =+IFERROR(VLOOKUP($AJ$17,Sheet1!V4:Y4,3,0),0) -> 0 | AK34: =+IFERROR(VLOOKUP($AK$17,Sheet1!Z4:AB4,3,0),0) -> 0 | AL34: =+IFERROR(VLOOKUP($AL$17,Sheet1!AD4:AG4,3,0),0) -> 0 | AM34: =+IFERROR(VLOOKUP($AM$17,Sheet1!AD4:AG4,3,0),0) -> 0 | AN34: =+IFERROR(VLOOKUP($AN$17,Sheet1!AD4:AG4,3,0),0) -> 0 | AO34: =+IFERROR(VLOOKUP($AO$17,Sheet1!AD4:AG4,3,0),0) -> 0 | AP34: =+IFERROR(VLOOKUP($AP$17,Sheet1!AD4:AG4,3,0),0) -> 0 | AQ34: 885 | AS34: =+IFERROR(VLOOKUP($AS$17,Sheet1!AH4:AK4,3,0),0) -> 0 | AT34: =+IFERROR(VLOOKUP($AT$17,Sheet1!AH4:AK4,3,0),0) -> 0 | AU34: =+IFERROR(VLOOKUP($AU$17,Sheet1!AH4:AK4,3,0),0) -> 0 | AV34: =+IFERROR(VLOOKUP($AV$17,Sheet1!AH4:AK4,3,0),0) -> 0 | AW34: =+IFERROR(VLOOKUP($AW$17,Sheet1!AH4:AK4,3,0),0) -> 0 | AX34: =+IFERROR(VLOOKUP($AX$17,Sheet1!AH4:AK4,3,0),0) -> 0 | AY34: =+IFERROR(VLOOKUP($AY$17,Sheet1!AH4:AK4,3,0),0) -> 0 | AZ34: =+IFERROR(VLOOKUP($AZ$17,Sheet1!AH4:AK4,3,0),0) -> 0 | BA34: 4072 | BB34: =+IFERROR(VLOOKUP($BB$17,Sheet1!AH4:AK4,3,0),0) -> 0 | BC34: =+IFERROR(VLOOKUP($BC$17,Sheet1!AL4:AO4,3,0),0) -> 0 | BD34: =+IFERROR(VLOOKUP($BD$17,Sheet1!AL4:AO4,3,0),0) -> 0 | BE34: =+IFERROR(VLOOKUP($BE$17,Sheet1!AL4:AO4,3,0),0) -> 0 | BF34: 1190 | BG34: =+IFERROR(VLOOKUP($BG$17,Sheet1!AL4:AO4,3,0),0) -> 0 | BH34: =+IFERROR(VLOOKUP($BH$17,Sheet1!AL4:AO4,3,0),0) -> 0 | BI34: =+IFERROR(VLOOKUP($BI$17,Sheet1!AL4:AO4,3,0),0) -> 0 | BJ34: =+IFERROR(VLOOKUP($BJ$17,Sheet1!AL4:AO4,3,0),0) -> 0 | BK34: =+IFERROR(VLOOKUP($BK$17,Sheet1!AL4:AO4,3,0),0) -> 0 | BL34: 862 | BM34: =+IFERROR(VLOOKUP($BM$17,Sheet1!AP4:AS4,3,0),0) -> 0 | BN34: 15 | BO34: =+IFERROR(VLOOKUP($BO$17,Sheet1!AX4:BA4,3,0),0) -> 0 | BP34: 71 | BQ34: =+IFERROR(VLOOKUP($BQ$17,Sheet1!BF4:BI4,3,0),0) -> 0 | BR34: =+IFERROR(VLOOKUP($BR$17,Sheet1!BJ4:BM4,3,0),0) -> 0 | BS34: =+IFERROR(VLOOKUP($BS$17,Sheet1!BN4:BQ4,3,0),0) -> 0 | BT34: 54 | BU34: =+IFERROR(VLOOKUP($BU$17,Sheet1!BV4:BY4,3,0),0) -> 0 | BV34: =Sheet1!E4 -> STEEL | BW34: =Sheet1!CV4 -> SP0400136 | BX34: =Sheet1!CW4 -> CORRUGATED DISPATCH STEEL DRUM 2200 X 1300 X 1200 MM | BY34: =Sheet1!CX4 -> 250 | BZ34: =36000/0.25 -> 144000 | CA34: =SUMPRODUCT($N$18:$BU$18,N34:BU34)+BZ34 -> 1407499 | CB34: 0.01 | CC34: =CA34*CB34 -> 14074.99 | CD34: 0.25 | CE34: =CA34*CD34 -> 351874.75 | CF34: =Sheet1!CF4 -> 0 | CG34: =CA34*CF34 -> 0 | CH34: =CA34+CC34+CE34+CG34 -> 1773448.7 | CI34: 0.02 | CJ34: =CH34*CI34 -> 35468.975 | CK34: 0.01 | CL34: =CH34*CK34 -> 17734.487
A35: =Sheet1!A17 -> ENQ-15138-22-23 | B35: =Sheet1!B17 -> 45627 | C35: =Sheet1!C17 -> FA1300022 | D35: =Sheet1!D17 -> 3 CORE X 50 SQ. MM. AL/ARD - WIRE (XLPE) - 33 KV (E) | E35: =CH35+CJ35+CL35 -> 1591041.8 | F35: =ROUNDUP(M59,0) -> 39000 | G35: =E35+F35 -> 1630041.8 | H35: =Sheet1!CP17 -> 0.18 | I35: =G35*H35 -> 293407.52 | J35: =G35+I35 -> 1923449.3 | K35: =Sheet1!CS17 -> 5 | L35: =Sheet1!CT17 -> KMS | M35: =J35*K35 -> 9617246.6 | N35: 405 | O35: =+IFERROR(VLOOKUP($O$17,Sheet1!J17:L17,3,0),0) -> 0 | P35: =+IFERROR(VLOOKUP($P$17,Sheet1!J17:M17,3,0),0) -> 0 | Q35: =+IFERROR(VLOOKUP($Q$17,Sheet1!J17:M17,3,0),0) -> 0 | R35: =+IFERROR(VLOOKUP($R$17,Sheet1!J17:M17,3,0),0) -> 0 | S35: =+IFERROR(VLOOKUP($S$17,Sheet1!N17:Q17,3,0),0) -> 0 | T35: =+IFERROR(VLOOKUP($T$17,Sheet1!N17:Q17,3,0),0) -> 0 | U35: =+IFERROR(VLOOKUP($U$17,Sheet1!F17:I17,3,0),0) -> 0 | V35: =+IFERROR(VLOOKUP($V$17,Sheet1!F17:I17,3,0),0) -> 0 | W35: =+IFERROR(VLOOKUP($W$17,Sheet1!F17:I17,3,0),0) -> 0 | X35: =+IFERROR(VLOOKUP($X$17,Sheet1!F17:I17,3,0),0) -> 0 | Y35: 153 | Z35: =+IFERROR(VLOOKUP($Z$17,Sheet1!F17:I17,3,0),0) -> 0 | AA35: =+IFERROR(VLOOKUP($AA$17,Sheet1!F17:I17,3,0),0) -> 0 | AB35: =+IFERROR(VLOOKUP($AB$17,Sheet1!F17:I17,3,0),0) -> 0 | AC35: 350 | AD35: =+IFERROR(VLOOKUP($AD$17,Sheet1!R17:U17,2,0),0) -> 0 | AE35: 1490 | AF35: =+IFERROR(VLOOKUP($AF$17,Sheet1!V17:Y17,3,0),0) -> 0 | AG35: =+IFERROR(VLOOKUP($AG$17,Sheet1!V17:Y17,3,0),0) -> 0 | AH35: =+IFERROR(VLOOKUP($AH$17,Sheet1!V17:Y17,3,0),0) -> 0 | AI35: =+IFERROR(VLOOKUP($AI$17,Sheet1!V17:Y17,3,0),0) -> 0 | AJ35: =+IFERROR(VLOOKUP($AJ$17,Sheet1!V17:Y17,3,0),0) -> 0 | AK35: =+IFERROR(VLOOKUP($AK$17,Sheet1!Z17:AB17,3,0),0) -> 0 | AL35: =+IFERROR(VLOOKUP($AL$17,Sheet1!AD17:AG17,3,0),0) -> 0 | AM35: =+IFERROR(VLOOKUP($AM$17,Sheet1!AD17:AG17,3,0),0) -> 0 | AN35: =+IFERROR(VLOOKUP($AN$17,Sheet1!AD17:AG17,3,0),0) -> 0 | AO35: =+IFERROR(VLOOKUP($AO$17,Sheet1!AD17:AG17,3,0),0) -> 0 | AP35: =+IFERROR(VLOOKUP($AP$17,Sheet1!AD17:AG17,3,0),0) -> 0 | AQ35: 798 | AR35: =+IFERROR(VLOOKUP($AR$17,Sheet1!AD17:AG17,3,0),0) -> 0 | AS35: =+IFERROR(VLOOKUP($AS$17,Sheet1!AH17:AK17,3,0),0) -> 0 | AT35: =+IFERROR(VLOOKUP($AT$17,Sheet1!AH17:AK17,3,0),0) -> 0 | AU35: =+IFERROR(VLOOKUP($AU$17,Sheet1!AH17:AK17,3,0),0) -> 0 | AV35: =+IFERROR(VLOOKUP($AV$17,Sheet1!AH17:AK17,3,0),0) -> 0 | AW35: =+IFERROR(VLOOKUP($AW$17,Sheet1!AH17:AK17,3,0),0) -> 0 | AX35: =+IFERROR(VLOOKUP($AX$17,Sheet1!AH17:AK17,3,0),0) -> 0 | AY35: =+IFERROR(VLOOKUP($AY$17,Sheet1!AH17:AK17,3,0),0) -> 0 | AZ35: =+IFERROR(VLOOKUP($AZ$17,Sheet1!AH17:AK17,3,0),0) -> 0 | BA35: 3881 | BB35: =+IFERROR(VLOOKUP($BB$17,Sheet1!AH17:AK17,3,0),0) -> 0 | BC35: =+IFERROR(VLOOKUP($BC$17,Sheet1!AL17:AO17,3,0),0) -> 0 | BD35: =+IFERROR(VLOOKUP($BD$17,Sheet1!AL17:AO17,3,0),0) -> 0 | BE35: =+IFERROR(VLOOKUP($BE$17,Sheet1!AL17:AO17,3,0),0) -> 0 | BF35: 1080 | BG35: =+IFERROR(VLOOKUP($BG$17,Sheet1!AL17:AO17,3,0),0) -> 0 | BH35: =+IFERROR(VLOOKUP($BH$17,Sheet1!AL17:AO17,3,0),0) -> 0 | BI35: =+IFERROR(VLOOKUP($BI$17,Sheet1!AL17:AO17,3,0),0) -> 0 | BJ35: =+IFERROR(VLOOKUP($BJ$17,Sheet1!AL17:AO17,3,0),0) -> 0 | BK35: =+IFERROR(VLOOKUP($BK$17,Sheet1!AL17:AO17,3,0),0) -> 0 | BL35: 778 | BM35: =+IFERROR(VLOOKUP($BM$17,Sheet1!AP17:AS17,3,0),0) -> 0 | BN35: 10 | BO35: =+IFERROR(VLOOKUP($BO$17,Sheet1!AX17:BA17,3,0),0) -> 0 | BP35: 66 | BQ35: =+IFERROR(VLOOKUP($BQ$17,Sheet1!BF17:BI17,3,0),0) -> 0 | BR35: =+IFERROR(VLOOKUP($BR$17,Sheet1!BJ17:BM17,3,0),0) -> 0 | BS35: =+IFERROR(VLOOKUP($BS$17,Sheet1!BN17:BQ17,3,0),0) -> 0 | BT35: 52 | BU35: =+IFERROR(VLOOKUP($BU$17,Sheet1!BV17:BY17,3,0),0) -> 0 | BV35: =Sheet1!E17 -> STEEL | BW35: =Sheet1!CV17 -> SP0400112 | BX35: =Sheet1!CW17 -> CORRUGATED DISPATCH STEEL DRUM 2000 X 1000 X 1000 MM | BY35: =Sheet1!CX17 -> 250 | BZ35: =20000/0.25 -> 80000 | CA35: =SUMPRODUCT($N$18:$BU$18,N35:BU35)+BZ35 -> 1225953 | CB35: 0.01 | CC35: =CA35*CB35 -> 12259.53 | CD35: 0.25 | CE35: =CA35*CD35 -> 306488.25 | CF35: =Sheet1!CF17 -> 0 | CG35: =CA35*CF35 -> 0 | CH35: =CA35+CC35+CE35+CG35 -> 1544700.8 | CI35: 0.02 | CJ35: =CH35*CI35 -> 30894.016 | CK35: 0.01 | CL35: =CH35*CK35 -> 15447.008
A36: =Sheet1!A18 -> ENQ-15138-22-23 | B36: =Sheet1!B18 -> 45627 | C36: =Sheet1!C18 -> FA1300297 | D36: =Sheet1!D18 -> 3 CORE X 35 SQ. MM. AL/ARM - WIRE (XLPE) - 33 KV (E) | E36: =CH36+CJ36+CL36 -> 1591041.8 | F36: =ROUNDUP(M60,0) -> 32500 | G36: =E36+F36 -> 1623541.8 | H36: =Sheet1!CP18 -> 0.18 | I36: =G36*H36 -> 292237.52 | J36: =G36+I36 -> 1915779.3 | K36: =Sheet1!CS18 -> 4 | L36: =Sheet1!CT18 -> KMS | M36: =J36*K36 -> 7663117.3 | N36: 405 | O36: =+IFERROR(VLOOKUP($O$17,Sheet1!J18:L18,3,0),0) -> 0 | P36: =+IFERROR(VLOOKUP($P$17,Sheet1!J18:M18,3,0),0) -> 0 | Q36: =+IFERROR(VLOOKUP($Q$17,Sheet1!J18:M18,3,0),0) -> 0 | R36: =+IFERROR(VLOOKUP($R$17,Sheet1!J18:M18,3,0),0) -> 0 | S36: =+IFERROR(VLOOKUP($S$17,Sheet1!N18:Q18,3,0),0) -> 0 | T36: =+IFERROR(VLOOKUP($T$17,Sheet1!N18:Q18,3,0),0) -> 0 | U36: =+IFERROR(VLOOKUP($U$17,Sheet1!F18:I18,3,0),0) -> 0 | V36: =+IFERROR(VLOOKUP($V$17,Sheet1!F18:I18,3,0),0) -> 0 | W36: =+IFERROR(VLOOKUP($W$17,Sheet1!F18:I18,3,0),0) -> 0 | X36: =+IFERROR(VLOOKUP($X$17,Sheet1!F18:I18,3,0),0) -> 0 | Y36: 153 | Z36: =+IFERROR(VLOOKUP($Z$17,Sheet1!F18:I18,3,0),0) -> 0 | AA36: =+IFERROR(VLOOKUP($AA$17,Sheet1!F18:I18,3,0),0) -> 0 | AB36: =+IFERROR(VLOOKUP($AB$17,Sheet1!F18:I18,3,0),0) -> 0 | AC36: 350 | AD36: =+IFERROR(VLOOKUP($AD$17,Sheet1!R18:U18,2,0),0) -> 0 | AE36: 1490 | AF36: =+IFERROR(VLOOKUP($AF$17,Sheet1!V18:Y18,3,0),0) -> 0 | AG36: =+IFERROR(VLOOKUP($AG$17,Sheet1!V18:Y18,3,0),0) -> 0 | AH36: =+IFERROR(VLOOKUP($AH$17,Sheet1!V18:Y18,3,0),0) -> 0 | AI36: =+IFERROR(VLOOKUP($AI$17,Sheet1!V18:Y18,3,0),0) -> 0 | AJ36: =+IFERROR(VLOOKUP($AJ$17,Sheet1!V18:Y18,3,0),0) -> 0 | AK36: =+IFERROR(VLOOKUP($AK$17,Sheet1!Z18:AB18,3,0),0) -> 0 | AL36: =+IFERROR(VLOOKUP($AL$17,Sheet1!AD18:AG18,3,0),0) -> 0 | AM36: =+IFERROR(VLOOKUP($AM$17,Sheet1!AD18:AG18,3,0),0) -> 0 | AN36: =+IFERROR(VLOOKUP($AN$17,Sheet1!AD18:AG18,3,0),0) -> 0 | AO36: =+IFERROR(VLOOKUP($AO$17,Sheet1!AD18:AG18,3,0),0) -> 0 | AP36: =+IFERROR(VLOOKUP($AP$17,Sheet1!AD18:AG18,3,0),0) -> 0 | AQ36: 798 | AR36: =+IFERROR(VLOOKUP($AR$17,Sheet1!AD18:AG18,3,0),0) -> 0 | AS36: =+IFERROR(VLOOKUP($AS$17,Sheet1!AH18:AK18,3,0),0) -> 0 | AT36: =+IFERROR(VLOOKUP($AT$17,Sheet1!AH18:AK18,3,0),0) -> 0 | AU36: =+IFERROR(VLOOKUP($AU$17,Sheet1!AH18:AK18,3,0),0) -> 0 | AV36: =+IFERROR(VLOOKUP($AV$17,Sheet1!AH18:AK18,3,0),0) -> 0 | AW36: =+IFERROR(VLOOKUP($AW$17,Sheet1!AH18:AK18,3,0),0) -> 0 | AX36: =+IFERROR(VLOOKUP($AX$17,Sheet1!AH18:AK18,3,0),0) -> 0 | AY36: =+IFERROR(VLOOKUP($AY$17,Sheet1!AH18:AK18,3,0),0) -> 0 | AZ36: =+IFERROR(VLOOKUP($AZ$17,Sheet1!AH18:AK18,3,0),0) -> 0 | BA36: 3881 | BB36: =+IFERROR(VLOOKUP($BB$17,Sheet1!AH18:AK18,3,0),0) -> 0 | BC36: =+IFERROR(VLOOKUP($BC$17,Sheet1!AL18:AO18,3,0),0) -> 0 | BD36: =+IFERROR(VLOOKUP($BD$17,Sheet1!AL18:AO18,3,0),0) -> 0 | BE36: =+IFERROR(VLOOKUP($BE$17,Sheet1!AL18:AO18,3,0),0) -> 0 | BF36: 1080 | BG36: =+IFERROR(VLOOKUP($BG$17,Sheet1!AL18:AO18,3,0),0) -> 0 | BH36: =+IFERROR(VLOOKUP($BH$17,Sheet1!AL18:AO18,3,0),0) -> 0 | BI36: =+IFERROR(VLOOKUP($BI$17,Sheet1!AL18:AO18,3,0),0) -> 0 | BJ36: =+IFERROR(VLOOKUP($BJ$17,Sheet1!AL18:AO18,3,0),0) -> 0 | BK36: =+IFERROR(VLOOKUP($BK$17,Sheet1!AL18:AO18,3,0),0) -> 0 | BL36: 778 | BM36: =+IFERROR(VLOOKUP($BM$17,Sheet1!AP18:AS18,3,0),0) -> 0 | BN36: 10 | BO36: =+IFERROR(VLOOKUP($BO$17,Sheet1!AX18:BA18,3,0),0) -> 0 | BP36: 66 | BQ36: =+IFERROR(VLOOKUP($BQ$17,Sheet1!BF18:BI18,3,0),0) -> 0 | BR36: =+IFERROR(VLOOKUP($BR$17,Sheet1!BJ18:BM18,3,0),0) -> 0 | BS36: =+IFERROR(VLOOKUP($BS$17,Sheet1!BN18:BQ18,3,0),0) -> 0 | BT36: 52 | BU36: =+IFERROR(VLOOKUP($BU$17,Sheet1!BV18:BY18,3,0),0) -> 0 | BV36: =Sheet1!E18 -> STEEL | BW36: =Sheet1!CV18 -> SP0400112 | BX36: =Sheet1!CW18 -> CORRUGATED DISPATCH STEEL DRUM 2000 X 1000 X 1000 MM | BY36: =Sheet1!CX18 -> 250 | BZ36: =20000/0.25 -> 80000 | CA36: =SUMPRODUCT($N$18:$BU$18,N36:BU36)+BZ36 -> 1225953 | CB36: 0.01 | CC36: =CA36*CB36 -> 12259.53 | CD36: 0.25 | CE36: =CA36*CD36 -> 306488.25 | CF36: =Sheet1!CF18 -> 0 | CG36: =CA36*CF36 -> 0 | CH36: =CA36+CC36+CE36+CG36 -> 1544700.8 | CI36: 0.02 | CJ36: =CH36*CI36 -> 30894.016 | CK36: 0.01 | CL36: =CH36*CK36 -> 15447.008
A37: =Sheet1!A11 -> ENQ-15138-22-23 | B37: =Sheet1!B11 -> 45627 | C37: =Sheet1!C11 -> FA1300027 | D37: =Sheet1!D11 -> 1 CORE X 630 SQ. MM. AL/ARM (XLPE) - 33 KV | E37: =CH37+CJ37+CL37 -> 1439768.9 | F37: =ROUNDUP(M61,0) -> 16265 | G37: =E37+F37 -> 1456033.9 | H37: =Sheet1!CP11 -> 0.18 | I37: =G37*H37 -> 262086.11 | J37: =G37+I37 -> 1718120 | K37: =Sheet1!CS11 -> 547.5 | L37: =Sheet1!CT11 -> KMS | M37: =J37*K37 -> 9.4067073e+08 | N37: =+IFERROR(VLOOKUP($N$17,Sheet1!J11:L11,3,0),0) -> 1701 | O37: =+IFERROR(VLOOKUP($O$17,Sheet1!J11:L11,3,0),0) -> 0 | P37: =+IFERROR(VLOOKUP($P$17,Sheet1!J11:M11,3,0),0) -> 0 | Q37: =+IFERROR(VLOOKUP($Q$17,Sheet1!J11:M11,3,0),0) -> 0 | R37: =+IFERROR(VLOOKUP($R$17,Sheet1!J11:M11,3,0),0) -> 0 | S37: =+IFERROR(VLOOKUP($S$17,Sheet1!N11:Q11,3,0),0) -> 0 | T37: =+IFERROR(VLOOKUP($T$17,Sheet1!N11:Q11,3,0),0) -> 0 | U37: =+IFERROR(VLOOKUP($U$17,Sheet1!F11:I11,3,0),0) -> 0 | V37: =+IFERROR(VLOOKUP($V$17,Sheet1!F11:I11,3,0),0) -> 0 | W37: =+IFERROR(VLOOKUP($W$17,Sheet1!F11:I11,3,0),0) -> 0 | X37: =+IFERROR(VLOOKUP($X$17,Sheet1!F11:I11,3,0),0) -> 0 | Y37: 87 | Z37: =+IFERROR(VLOOKUP($Z$17,Sheet1!F11:I11,3,0),0) -> 0 | AA37: =+IFERROR(VLOOKUP($AA$17,Sheet1!F11:I11,3,0),0) -> 0 | AB37: =+IFERROR(VLOOKUP($AB$17,Sheet1!F11:I11,3,0),0) -> 0 | AC37: 243 | AD37: =+IFERROR(VLOOKUP($AD$17,Sheet1!R11:U11,2,0),0) -> 0 | AE37: 1056 | AF37: =+IFERROR(VLOOKUP($AF$17,Sheet1!V11:Y11,3,0),0) -> 0 | AG37: =+IFERROR(VLOOKUP($AG$17,Sheet1!V11:Y11,3,0),0) -> 0 | AH37: =+IFERROR(VLOOKUP($AH$17,Sheet1!V11:Y11,3,0),0) -> 0 | AI37: =+IFERROR(VLOOKUP($AI$17,Sheet1!V11:Y11,3,0),0) -> 0 | AJ37: =+IFERROR(VLOOKUP($AJ$17,Sheet1!V11:Y11,3,0),0) -> 0 | AK37: 36 | AL37: =+IFERROR(VLOOKUP($AL$17,Sheet1!AD11:AG11,3,0),0) -> 0 | AM37: =+IFERROR(VLOOKUP($AM$17,Sheet1!AD11:AG11,3,0),0) -> 0 | AN37: =+IFERROR(VLOOKUP($AN$17,Sheet1!AD11:AG11,3,0),0) -> 0 | AO37: =+IFERROR(VLOOKUP($AO$17,Sheet1!AD11:AG11,3,0),0) -> 0 | AP37: =+IFERROR(VLOOKUP($AP$17,Sheet1!AD11:AG11,3,0),0) -> 0 | AQ37: 203 | AR37: =+IFERROR(VLOOKUP($AR$17,Sheet1!AD11:AG11,3,0),0) -> 0 | AS37: =+IFERROR(VLOOKUP($AS$17,Sheet1!AH11:AK11,3,0),0) -> 0 | AT37: =+IFERROR(VLOOKUP($AT$17,Sheet1!AH11:AK11,3,0),0) -> 0 | AU37: =+IFERROR(VLOOKUP($AU$17,Sheet1!AH11:AK11,3,0),0) -> 0 | AV37: 842 | AW37: =+IFERROR(VLOOKUP($AW$17,Sheet1!AH11:AK11,3,0),0) -> 0 | AX37: =+IFERROR(VLOOKUP($AX$17,Sheet1!AH11:AK11,3,0),0) -> 0 | AY37: =+IFERROR(VLOOKUP($AY$17,Sheet1!AH11:AK11,3,0),0) -> 0 | AZ37: =+IFERROR(VLOOKUP($AZ$17,Sheet1!AH11:AK11,3,0),0) -> 0 | BA37: =+IFERROR(VLOOKUP($BA$17,Sheet1!AH11:AK11,3,0),0) -> 0 | BB37: =+IFERROR(VLOOKUP($BB$17,Sheet1!AH11:AK11,3,0),0) -> 0 | BC37: =+IFERROR(VLOOKUP($BC$17,Sheet1!AL11:AO11,3,0),0) -> 0 | BD37: =+IFERROR(VLOOKUP($BD$17,Sheet1!AL11:AO11,3,0),0) -> 0 | BE37: =+IFERROR(VLOOKUP($BE$17,Sheet1!AL11:AO11,3,0),0) -> 0 | BF37: 769 | BG37: =+IFERROR(VLOOKUP($BG$17,Sheet1!AL11:AO11,3,0),0) -> 0 | BH37: =+IFERROR(VLOOKUP($BH$17,Sheet1!AL11:AO11,3,0),0) -> 0 | BI37: =+IFERROR(VLOOKUP($BI$17,Sheet1!AL11:AO11,3,0),0) -> 0 | BJ37: =+IFERROR(VLOOKUP($BJ$17,Sheet1!AL11:AO11,3,0),0) -> 0 | BK37: =+IFERROR(VLOOKUP($BK$17,Sheet1!AL11:AO11,3,0),0) -> 0 | BL37: =+IFERROR(VLOOKUP($BL$17,Sheet1!AL11:AO11,3,0),0) -> 0 | BM37: =+IFERROR(VLOOKUP($BM$17,Sheet1!AP11:AS11,3,0),0) -> 0 | BN37: 26 | BO37: =+IFERROR(VLOOKUP($BO$17,Sheet1!AX11:BA11,3,0),0) -> 0 | BP37: 46 | BQ37: =+IFERROR(VLOOKUP($BQ$17,Sheet1!BF11:BI11,3,0),0) -> 0 | BR37: =+IFERROR(VLOOKUP($BR$17,Sheet1!BJ11:BM11,3,0),0) -> 0 | BS37: =+IFERROR(VLOOKUP($BS$17,Sheet1!BN11:BQ11,3,0),0) -> 0 | BT37: 42 | BU37: =+IFERROR(VLOOKUP($BU$17,Sheet1!BV11:BY11,3,0),0) -> 0 | BV37: =Sheet1!E11 -> STEEL | BW37: SP0400118 | BX37: CORRUGATED DISPATCH STEEL DRUM 1700 X 1000 X 1200 | BY37: =Sheet1!CX11 -> 500 | BZ37: =20000/0.5 -> 40000 | CA37: =SUMPRODUCT($N$18:$BU$18,N37:BU37)+BZ37 -> 1109392 | CB37: 0.01 | CC37: =CA37*CB37 -> 11093.92 | CD37: 0.25 | CE37: =CA37*CD37 -> 277348 | CF37: =Sheet1!CF11 -> 0 | CG37: =CA37*CF37 -> 0 | CH37: =CA37+CC37+CE37+CG37 -> 1397833.9 | CI37: 0.02 | CJ37: =CH37*CI37 -> 27956.678 | CK37: 0.01 | CL37: =CH37*CK37 -> 13978.339
A38: =Sheet1!A13 -> ENQ-15138-22-23 | B38: =Sheet1!B13 -> 45627 | C38: =Sheet1!C13 -> FA1300018 | D38: =Sheet1!D13 -> 1 CORE X 400 SQ. MM. AL/ARM (XLPE) - 33 KV | E38: =CH38+CJ38+CL38 -> 1096461.9 | F38: =ROUNDUP(M62,0) -> 18572 | G38: =E38+F38 -> 1115033.9 | H38: =Sheet1!CP13 -> 0.18 | I38: =G38*H38 -> 200706.1 | J38: =G38+I38 -> 1315740 | K38: =Sheet1!CS13 -> 17.5 | L38: =Sheet1!CT13 -> KMS | M38: =J38*K38 -> 23025450 | N38: =+IFERROR(VLOOKUP($N$17,Sheet1!J13:L13,3,0),0) -> 1080 | O38: =+IFERROR(VLOOKUP($O$17,Sheet1!J13:L13,3,0),0) -> 0 | P38: =+IFERROR(VLOOKUP($P$17,Sheet1!J13:M13,3,0),0) -> 0 | Q38: =+IFERROR(VLOOKUP($Q$17,Sheet1!J13:M13,3,0),0) -> 0 | R38: =+IFERROR(VLOOKUP($R$17,Sheet1!J13:M13,3,0),0) -> 0 | S38: =+IFERROR(VLOOKUP($S$17,Sheet1!N13:Q13,3,0),0) -> 0 | T38: =+IFERROR(VLOOKUP($T$17,Sheet1!N13:Q13,3,0),0) -> 0 | U38: =+IFERROR(VLOOKUP($U$17,Sheet1!F13:I13,3,0),0) -> 0 | V38: =+IFERROR(VLOOKUP($V$17,Sheet1!F13:I13,3,0),0) -> 0 | W38: =+IFERROR(VLOOKUP($W$17,Sheet1!F13:I13,3,0),0) -> 0 | X38: =+IFERROR(VLOOKUP($X$17,Sheet1!F13:I13,3,0),0) -> 0 | Y38: 76 | Z38: =+IFERROR(VLOOKUP($Z$17,Sheet1!F13:I13,3,0),0) -> 0 | AA38: =+IFERROR(VLOOKUP($AA$17,Sheet1!F13:I13,3,0),0) -> 0 | AB38: =+IFERROR(VLOOKUP($AB$17,Sheet1!F13:I13,3,0),0) -> 0 | AC38: 206 | AD38: =+IFERROR(VLOOKUP($AD$17,Sheet1!R13:U13,2,0),0) -> 0 | AE38: 890 | AF38: =+IFERROR(VLOOKUP($AF$17,Sheet1!V13:Y13,3,0),0) -> 0 | AG38: =+IFERROR(VLOOKUP($AG$17,Sheet1!V13:Y13,3,0),0) -> 0 | AH38: =+IFERROR(VLOOKUP($AH$17,Sheet1!V13:Y13,3,0),0) -> 0 | AI38: =+IFERROR(VLOOKUP($AI$17,Sheet1!V13:Y13,3,0),0) -> 0 | AJ38: =+IFERROR(VLOOKUP($AJ$17,Sheet1!V13:Y13,3,0),0) -> 0 | AK38: 32 | AL38: =+IFERROR(VLOOKUP($AL$17,Sheet1!AD13:AG13,3,0),0) -> 0 | AM38: =+IFERROR(VLOOKUP($AM$17,Sheet1!AD13:AG13,3,0),0) -> 0 | AN38: =+IFERROR(VLOOKUP($AN$17,Sheet1!AD13:AG13,3,0),0) -> 0 | AO38: =+IFERROR(VLOOKUP($AO$17,Sheet1!AD13:AG13,3,0),0) -> 0 | AP38: =+IFERROR(VLOOKUP($AP$17,Sheet1!AD13:AG13,3,0),0) -> 0 | AQ38: 156 | AR38: =+IFERROR(VLOOKUP($AR$17,Sheet1!AD13:AG13,3,0),0) -> 0 | AS38: =+IFERROR(VLOOKUP($AS$17,Sheet1!AH13:AK13,3,0),0) -> 0 | AT38: =+IFERROR(VLOOKUP($AT$17,Sheet1!AH13:AK13,3,0),0) -> 0 | AU38: =+IFERROR(VLOOKUP($AU$17,Sheet1!AH13:AK13,3,0),0) -> 0 | AV38: 731 | AW38: =+IFERROR(VLOOKUP($AW$17,Sheet1!AH13:AK13,3,0),0) -> 0 | AX38: =+IFERROR(VLOOKUP($AX$17,Sheet1!AH13:AK13,3,0),0) -> 0 | AY38: =+IFERROR(VLOOKUP($AY$17,Sheet1!AH13:AK13,3,0),0) -> 0 | AZ38: =+IFERROR(VLOOKUP($AZ$17,Sheet1!AH13:AK13,3,0),0) -> 0 | BA38: =+IFERROR(VLOOKUP($BA$17,Sheet1!AH13:AK13,3,0),0) -> 0 | BB38: =+IFERROR(VLOOKUP($BB$17,Sheet1!AH13:AK13,3,0),0) -> 0 | BC38: =+IFERROR(VLOOKUP($BC$17,Sheet1!AL13:AO13,3,0),0) -> 0 | BD38: =+IFERROR(VLOOKUP($BD$17,Sheet1!AL13:AO13,3,0),0) -> 0 | BE38: =+IFERROR(VLOOKUP($BE$17,Sheet1!AL13:AO13,3,0),0) -> 0 | BF38: 604 | BG38: =+IFERROR(VLOOKUP($BG$17,Sheet1!AL13:AO13,3,0),0) -> 0 | BH38: =+IFERROR(VLOOKUP($BH$17,Sheet1!AL13:AO13,3,0),0) -> 0 | BI38: =+IFERROR(VLOOKUP($BI$17,Sheet1!AL13:AO13,3,0),0) -> 0 | BJ38: =+IFERROR(VLOOKUP($BJ$17,Sheet1!AL13:AO13,3,0),0) -> 0 | BK38: =+IFERROR(VLOOKUP($BK$17,Sheet1!AL13:AO13,3,0),0) -> 0 | BL38: =+IFERROR(VLOOKUP($BL$17,Sheet1!AL13:AO13,3,0),0) -> 0 | BM38: =+IFERROR(VLOOKUP($BM$17,Sheet1!AP13:AS13,3,0),0) -> 0 | BN38: 19 | BP38: 38 | BQ38: =+IFERROR(VLOOKUP($BQ$17,Sheet1!BF13:BI13,3,0),0) -> 0 | BR38: =+IFERROR(VLOOKUP($BR$17,Sheet1!BJ13:BM13,3,0),0) -> 0 | BS38: =+IFERROR(VLOOKUP($BS$17,Sheet1!BN13:BQ13,3,0),0) -> 0 | BT38: 37 | BU38: =+IFERROR(VLOOKUP($BU$17,Sheet1!BV13:BY13,3,0),0) -> 0 | BV38: =Sheet1!E13 -> STEEL | BW38: SP0400126 | BX38: CORRUGATED DISPATCH STEEL DRUM 1900 X 830 X 915 MM | BY38: =Sheet1!CX13 -> 500 | BZ38: =16000/0.5 -> 32000 | CA38: =SUMPRODUCT($N$18:$BU$18,N38:BU38)+BZ38 -> 844862 | CB38: 0.01 | CC38: =CA38*CB38 -> 8448.62 | CD38: 0.25 | CE38: =CA38*CD38 -> 211215.5 | CF38: =Sheet1!CF13 -> 0 | CG38: =CA38*CF38 -> 0 | CH38: =CA38+CC38+CE38+CG38 -> 1064526.1 | CI38: 0.02 | CJ38: =CH38*CI38 -> 21290.522 | CK38: 0.01 | CL38: =CH38*CK38 -> 10645.261
A39: =Sheet1!A14 -> ENQ-15138-22-23 | B39: =Sheet1!B14 -> 45627 | C39: =Sheet1!C14 -> FA1300019 | D39: =Sheet1!D14 -> 1 CORE X 300 SQ. MM. AL/ARM (XLPE) - 33 KV | E39: =CH39+CJ39+CL39 -> 956871.83 | F39: =ROUNDUP(M63,0) -> 18572 | G39: =E39+F39 -> 975443.83 | H39: =Sheet1!CP14 -> 0.18 | I39: =G39*H39 -> 175579.89 | J39: =G39+I39 -> 1151023.7 | K39: =Sheet1!CS14 -> 7 | L39: =Sheet1!CT14 -> KMS | M39: =J39*K39 -> 8057166.1 | N39: =+IFERROR(VLOOKUP($N$17,Sheet1!J14:L14,3,0),0) -> 810 | O39: =+IFERROR(VLOOKUP($O$17,Sheet1!J14:L14,3,0),0) -> 0 | P39: =+IFERROR(VLOOKUP($P$17,Sheet1!J14:M14,3,0),0) -> 0 | Q39: =+IFERROR(VLOOKUP($Q$17,Sheet1!J14:M14,3,0),0) -> 0 | R39: =+IFERROR(VLOOKUP($R$17,Sheet1!J14:M14,3,0),0) -> 0 | S39: =+IFERROR(VLOOKUP($S$17,Sheet1!N14:Q14,3,0),0) -> 0 | T39: =+IFERROR(VLOOKUP($T$17,Sheet1!N14:Q14,3,0),0) -> 0 | U39: =+IFERROR(VLOOKUP($U$17,Sheet1!F14:I14,3,0),0) -> 0 | V39: =+IFERROR(VLOOKUP($V$17,Sheet1!F14:I14,3,0),0) -> 0 | W39: =+IFERROR(VLOOKUP($W$17,Sheet1!F14:I14,3,0),0) -> 0 | X39: =+IFERROR(VLOOKUP($X$17,Sheet1!F14:I14,3,0),0) -> 0 | Y39: 71 | Z39: =+IFERROR(VLOOKUP($Z$17,Sheet1!F14:I14,3,0),0) -> 0 | AA39: =+IFERROR(VLOOKUP($AA$17,Sheet1!F14:I14,3,0),0) -> 0 | AB39: =+IFERROR(VLOOKUP($AB$17,Sheet1!F14:I14,3,0),0) -> 0 | AC39: 187 | AD39: =+IFERROR(VLOOKUP($AD$17,Sheet1!R14:U14,2,0),0) -> 0 | AE39: 810 | AF39: =+IFERROR(VLOOKUP($AF$17,Sheet1!V14:Y14,3,0),0) -> 0 | AG39: =+IFERROR(VLOOKUP($AG$17,Sheet1!V14:Y14,3,0),0) -> 0 | AH39: =+IFERROR(VLOOKUP($AH$17,Sheet1!V14:Y14,3,0),0) -> 0 | AI39: =+IFERROR(VLOOKUP($AI$17,Sheet1!V14:Y14,3,0),0) -> 0 | AJ39: =+IFERROR(VLOOKUP($AJ$17,Sheet1!V14:Y14,3,0),0) -> 0 | AK39: 30 | AL39: =+IFERROR(VLOOKUP($AL$17,Sheet1!AD14:AG14,3,0),0) -> 0 | AM39: =+IFERROR(VLOOKUP($AM$17,Sheet1!AD14:AG14,3,0),0) -> 0 | AN39: =+IFERROR(VLOOKUP($AN$17,Sheet1!AD14:AG14,3,0),0) -> 0 | AO39: =+IFERROR(VLOOKUP($AO$17,Sheet1!AD14:AG14,3,0),0) -> 0 | AP39: =+IFERROR(VLOOKUP($AP$17,Sheet1!AD14:AG14,3,0),0) -> 0 | AQ39: 146 | AR39: =+IFERROR(VLOOKUP($AR$17,Sheet1!AD14:AG14,3,0),0) -> 0 | AS39: =+IFERROR(VLOOKUP($AS$17,Sheet1!AH14:AK14,3,0),0) -> 0 | AT39: =+IFERROR(VLOOKUP($AT$17,Sheet1!AH14:AK14,3,0),0) -> 0 | AU39: =+IFERROR(VLOOKUP($AU$17,Sheet1!AH14:AK14,3,0),0) -> 0 | AV39: 690 | AW39: =+IFERROR(VLOOKUP($AW$17,Sheet1!AH14:AK14,3,0),0) -> 0 | AX39: =+IFERROR(VLOOKUP($AX$17,Sheet1!AH14:AK14,3,0),0) -> 0 | AY39: =+IFERROR(VLOOKUP($AY$17,Sheet1!AH14:AK14,3,0),0) -> 0 | AZ39: =+IFERROR(VLOOKUP($AZ$17,Sheet1!AH14:AK14,3,0),0) -> 0 | BA39: =+IFERROR(VLOOKUP($BA$17,Sheet1!AH14:AK14,3,0),0) -> 0 | BB39: =+IFERROR(VLOOKUP($BB$17,Sheet1!AH14:AK14,3,0),0) -> 0 | BC39: =+IFERROR(VLOOKUP($BC$17,Sheet1!AL14:AO14,3,0),0) -> 0 | BD39: =+IFERROR(VLOOKUP($BD$17,Sheet1!AL14:AO14,3,0),0) -> 0 | BE39: =+IFERROR(VLOOKUP($BE$17,Sheet1!AL14:AO14,3,0),0) -> 0 | BF39: 570 | BG39: =+IFERROR(VLOOKUP($BG$17,Sheet1!AL14:AO14,3,0),0) -> 0 | BH39: =+IFERROR(VLOOKUP($BH$17,Sheet1!AL14:AO14,3,0),0) -> 0 | BI39: =+IFERROR(VLOOKUP($BI$17,Sheet1!AL14:AO14,3,0),0) -> 0 | BJ39: =+IFERROR(VLOOKUP($BJ$17,Sheet1!AL14:AO14,3,0),0) -> 0 | BK39: =+IFERROR(VLOOKUP($BK$17,Sheet1!AL14:AO14,3,0),0) -> 0 | BL39: =+IFERROR(VLOOKUP($BL$17,Sheet1!AL14:AO14,3,0),0) -> 0 | BM39: =+IFERROR(VLOOKUP($BM$17,Sheet1!AP14:AS14,3,0),0) -> 0 | BN39: 13 | BO39: =+IFERROR(VLOOKUP($BO$17,Sheet1!AX14:BA14,3,0),0) -> 0 | BP39: 35 | BQ39: =+IFERROR(VLOOKUP($BQ$17,Sheet1!BF14:BI14,3,0),0) -> 0 | BR39: =+IFERROR(VLOOKUP($BR$17,Sheet1!BJ14:BM14,3,0),0) -> 0 | BS39: =+IFERROR(VLOOKUP($BS$17,Sheet1!BN14:BQ14,3,0),0) -> 0 | BT39: 35 | BU39: =+IFERROR(VLOOKUP($BU$17,Sheet1!BV14:BY14,3,0),0) -> 0 | BV39: =Sheet1!E14 -> STEEL | BW39: SP0400126 | BX39: CORRUGATED DISPATCH STEEL DRUM 1900 X 830 X 915 MM | BY39: =Sheet1!CX14 -> 500 | BZ39: =16000/0.5 -> 32000 | CA39: =SUMPRODUCT($N$18:$BU$18,N39:BU39)+BZ39 -> 737303 | CB39: 0.01 | CC39: =CA39*CB39 -> 7373.03 | CD39: 0.25 | CE39: =CA39*CD39 -> 184325.75 | CF39: =Sheet1!CF14 -> 0 | CG39: =CA39*CF39 -> 0 | CH39: =CA39+CC39+CE39+CG39 -> 929001.78 | CI39: 0.02 | CJ39: =CH39*CI39 -> 18580.036 | CK39: 0.01 | CL39: =CH39*CK39 -> 9290.0178
M40: =SUM(M19:M39) -> 3.4217552e+09
E42: Order Quantity | F42: Stnd Length | G42: Truck type | H42: Fare of one truck | I42: No of Drum in one truck | J42: Total length in one Truck | K42: No of Truck | L42: Total Freight | M42: Freight per KM | Y42: CABLE WEIGHT KG/KM | AC42: DRUM WEIGHT | AE42: CABLE+DRUM WEIGHT | AK42: TRAILOR WEIGHT
D43: =D19 -> 3 CORE X 400 SQ. MM. AL/ARM - WIRE (XLPE) - 11 KV | E43: =K19 -> 314 | F43: =BY19/1000 -> 0.25 | G43: 25 MT TRAILER | H43: 65000 | I43: 5 | J43: =F43*I43 -> 1.25 | K43: =ROUNDUP((E43/J43),0) -> 252 | L43: =M43*E43 -> 16380000 | M43: =(H43*K43)/E43 -> 52165.605 | Y43: =SUM(N19:BT19) -> 14156 | AC43: =(BZ19*F43)/80 -> 393.75 | AE43: =((Y43*F43)+AC43) -> 3932.75 | AK43: =I43*AE43 -> 19663.75
D44: =D20 -> 3 CORE X 300 SQ. MM. AL/ARM - WIRE (XLPE) - 11 KV | E44: =K20 -> 43 | F44: =BY20/1000 -> 0.25 | G44: 25 MT TRAILER | H44: 65000 | I44: 5 | J44: =F44*I44 -> 1.25 | K44: =ROUNDUP((E44/J44),0) -> 35 | L44: =M44*E44 -> 2275000 | M44: =(H44*K44)/E44 -> 52906.977 | Y44: =SUM(N20:BT20) -> 11078 | AC44: =(BZ20*F44)/80 -> 393.75 | AE44: =((Y44*F44)+AC44) -> 3163.25 | AK44: =I44*AE44 -> 15816.25
D45: =D21 -> 3 CORE X 185 SQ. MM AL/ARM - WIRE (XLPE) - 11 KV | E45: =K21 -> 2 | F45: =BY21/1000 -> 0.25 | G45: 25 MT TRAILER | H45: 65000 | I45: 6 | J45: =F45*I45 -> 1.5 | K45: =ROUNDUP((E45/J45),0) -> 2 | L45: =M45*E45 -> 130000 | M45: =(H45*K45)/E45 -> 65000 | Y45: =SUM(N21:BT21) -> 8667 | AC45: =(BZ21*F45)/80 -> 241.875 | AE45: =((Y45*F45)+AC45) -> 2408.625 | AK45: =I45*AE45 -> 14451.75
B46: FREIGHT CHARGES | D46: =D22 -> 3 CORE X 150 SQ. MM. AL/ARM - WIRE (XLPE) - 11 KV | E46: =K22 -> 4 | F46: =BY22/1000 -> 0.25 | G46: 25 MT TRAILER | H46: 65000 | I46: 8 | J46: =F46*I46 -> 2 | K46: =ROUNDUP((E46/J46),0) -> 2 | L46: =M46*E46 -> 130000 | M46: =(H46*K46)/E46 -> 32500 | Y46: =SUM(N22:BT22) -> 7064 | AC46: =(BZ22*F46)/80 -> 220 | AE46: =((Y46*F46)+AC46) -> 1986 | AK46: =I46*AE46 -> 15888
B47: 25 MT TRAILER | D47: =D23 -> 3 CORE X 120 SQ. MM. AL/ARM - WIRE (XLPE) - 11 KV | E47: =K23 -> 10 | F47: =BY23/1000 -> 0.25 | G47: 25 MT TRAILER | H47: 65000 | I47: 8 | J47: =F47*I47 -> 2 | K47: =ROUNDUP((E47/J47),0) -> 5 | L47: =M47*E47 -> 325000 | M47: =(H47*K47)/E47 -> 32500 | Y47: =SUM(N23:BT23) -> 6405 | AC47: =(BZ23*F47)/80 -> 220 | AE47: =((Y47*F47)+AC47) -> 1821.25 | AK47: =I47*AE47 -> 14570
A48: BHUBANESWAR | B48: 45000 | D48: =D24 -> 3 CORE X 95 SQ. MM. AL/ARM - WIRE (XLPE) - 11 KV (E) | E48: =K24 -> 23 | F48: =BY24/1000 -> 0.25 | G48: 25 MT TRAILER | H48: 65000 | I48: 8 | J48: =F48*I48 -> 2 | K48: =ROUNDUP((E48/J48),0) -> 12 | L48: =M48*E48 -> 780000 | M48: =(H48*K48)/E48 -> 33913.043 | Y48: =SUM(N24:BT24) -> 5793 | AC48: =(BZ24*F48)/80 -> 215 | AE48: =((Y48*F48)+AC48) -> 1663.25 | AK48: =I48*AE48 -> 13306
A49: BALIA | B49: 80000 | D49: =D25 -> 3 CORE X 50 SQ. MM. AL/ARD - WIRE (XLPE) - 11 KV | E49: =K25 -> 7.5 | F49: =BY25/1000 -> 0.25 | G49: 25 MT TRAILER | H49: 65000 | I49: 14 | J49: =F49*I49 -> 3.5 | K49: =ROUNDUP((E49/J49),0) -> 3 | L49: =M49*E49 -> 195000 | M49: =(H49*K49)/E49 -> 26000 | Y49: =SUM(N25:BT25) -> 4382 | AC49: =(BZ25*F49)/80 -> 281.25 | AE49: =((Y49*F49)+AC49) -> 1376.75 | AK49: =I49*AE49 -> 19274.5
A50: BERHAMPUR | B50: 75000 | D50: =D26 -> 1 CORE X 1000 SQ. MM. AL/ARM (XLPE) - 11 KV | E50: =K26 -> 1 | F50: =BY26/1000 -> 0.5 | G50: 25 MT TRAILER | H50: 65000 | I50: 6 | J50: =F50*I50 -> 3 | K50: =ROUNDUP((E50/J50),0) -> 1 | L50: =M50*E50 -> 65000 | M50: =(H50*K50)/E50 -> 65000 | Y50: =SUM(N26:BT26) -> 5455 | AC50: =(BZ26*F50)/80 -> 393.75 | AE50: =((Y50*F50)+AC50) -> 3121.25 | AK50: =I50*AE50 -> 18727.5
A51: BURLA | B51: 55000 | D51: =D27 -> 1 CORE X 630 SQ. MM. AL/ARM (XLPE) - 11 KV | E51: =K27 -> 11 | F51: =BY27/1000 -> 0.5 | G51: 25 MT TRAILER | H51: 65000 | I51: 8 | J51: =F51*I51 -> 4 | K51: =ROUNDUP((E51/J51),0) -> 3 | L51: =M51*E51 -> 195000 | M51: =(H51*K51)/E51 -> 17727.273 | Y51: =SUM(N27:BT27) -> 3673 | AC51: =(BZ27*F51)/80 -> 280 | AE51: =((Y51*F51)+AC51) -> 2116.5 | AK51: =I51*AE51 -> 16932
A52: AVERAGE = | B52: =AVERAGE(B48:B51) -> 63750 | D52: =D28 -> 1 CORE X 400 SQ. MM. AL/ARM (XLPE) - 11 KV | E52: =K28 -> 4 | F52: =BY28/1000 -> 0.5 | G52: 25 MT TRAILER | H52: 65000 | I52: 8 | J52: =F52*I52 -> 4 | K52: =ROUNDUP((E52/J52),0) -> 1 | L52: =M52*E52 -> 65000 | M52: =(H52*K52)/E52 -> 16250 | Y52: =SUM(N28:BT28) -> 2691 | AC52: =(BZ28*F52)/80 -> 200 | AE52: =((Y52*F52)+AC52) -> 1545.5 | AK52: =I52*AE52 -> 12364
D53: =D29 -> 1 CORE X 300 SQ. MM. AL./ARM (XLPE) - 11 KV | E53: =K29 -> 6.5 | F53: =BY29/1000 -> 0.5 | G53: 25 MT TRAILER | H53: 65000 | I53: 8 | J53: =F53*I53 -> 4 | K53: =ROUNDUP((E53/J53),0) -> 2 | L53: =M53*E53 -> 130000 | M53: =(H53*K53)/E53 -> 20000 | Y53: =SUM(N29:BT29) -> 2250 | AC53: =(BZ29*F53)/80 -> 180 | AE53: =((Y53*F53)+AC53) -> 1305 | AK53: =I53*AE53 -> 10440
D54: =D30 -> 3 CORE X 400 SQ. MM AL/ARM - WIRE (XLPE) - 33 KV | E54: =K30 -> 222.75 | F54: =BY30/1000 -> 0.25 | G54: 25 MT TRAILER | H54: 65000 | I54: 4 | J54: =F54*I54 -> 1 | K54: =ROUNDUP((E54/J54),0) -> 223 | L54: =M54*E54 -> 14495000 | M54: =(H54*K54)/E54 -> 65072.952 | Y54: =SUM(N30:BT30) -> 19432 | AC54: =(BZ30*F54)/80 -> 550 | AE54: =((Y54*F54)+AC54) -> 5408 | AK54: =I54*AE54 -> 21632
D55: =D31 -> 3 CORE X 300 SQ. MM. AL/ARM - WIRE (XLPE) - 33 KV | E55: =K31 -> 17.5 | F55: =BY31/1000 -> 0.25 | G55: 25 MT TRAILER | H55: 65000 | I55: 4 | J55: =F55*I55 -> 1 | K55: =ROUNDUP((E55/J55),0) -> 18 | L55: =M55*E55 -> 1170000 | M55: =(H55*K55)/E55 -> 66857.143 | Y55: =SUM(N31:BT31) -> 17363 | AC55: =(BZ31*F55)/80 -> 500 | AE55: =((Y55*F55)+AC55) -> 4840.75 | AK55: =I55*AE55 -> 19363
D56: =D32 -> 3 CORE X 185 SQ. MM AL/ARM - WIRE (XLPE) - 33 KV | E56: =K32 -> 12.5 | F56: =BY32/1000 -> 0.25 | G56: 25 MT TRAILER | H56: 65000 | I56: 6 | J56: =F56*I56 -> 1.5 | K56: =ROUNDUP((E56/J56),0) -> 9 | L56: =M56*E56 -> 585000 | M56: =(H56*K56)/E56 -> 46800 | Y56: =SUM(N32:BT32) -> 14502 | AC56: =(BZ32*F56)/80 -> 461.25 | AE56: =((Y56*F56)+AC56) -> 4086.75 | AK56: =I56*AE56 -> 24520.5
D57: =D33 -> 3 CORE X 95 SQ. MM. AL/ARM WIRE (XLPE) - 33 KV | E57: =K33 -> 4 | F57: =BY33/1000 -> 0.25 | G57: 25 MT TRAILER | H57: 65000 | I57: 8 | J57: =F57*I57 -> 2 | K57: =ROUNDUP((E57/J57),0) -> 2 | L57: =M57*E57 -> 130000 | M57: =(H57*K57)/E57 -> 32500 | Y57: =SUM(N33:BT33) -> 10659 | AC57: =(BZ33*F57)/80 -> 400 | AE57: =((Y57*F57)+AC57) -> 3064.75 | AK57: =I57*AE57 -> 24518
D58: =D34 -> 3 CORE X 70 SQ. MM. AL/ARM - WIRE (XLPE) - 33 KV | E58: =K34 -> 3 | F58: =BY34/1000 -> 0.25 | G58: 25 MT TRAILER | H58: 65000 | I58: 8 | J58: =F58*I58 -> 2 | K58: =ROUNDUP((E58/J58),0) -> 2 | L58: =M58*E58 -> 130000 | M58: =(H58*K58)/E58 -> 43333.333 | Y58: =SUM(N34:BT34) -> 9870 | AC58: =(BZ34*F58)/80 -> 450 | AE58: =((Y58*F58)+AC58) -> 2917.5 | AK58: =I58*AE58 -> 23340
D59: =D35 -> 3 CORE X 50 SQ. MM. AL/ARD - WIRE (XLPE) - 33 KV (E) | E59: =K35 -> 5 | F59: =BY35/1000 -> 0.25 | G59: 25 MT TRAILER | H59: 65000 | I59: 9 | J59: =F59*I59 -> 2.25 | K59: =ROUNDUP((E59/J59),0) -> 3 | L59: =M59*E59 -> 195000 | M59: =(H59*K59)/E59 -> 39000 | Y59: =SUM(N35:BT35) -> 9063 | AC59: =(BZ35*F59)/80 -> 250 | AE59: =((Y59*F59)+AC59) -> 2515.75 | AK59: =I59*AE59 -> 22641.75
D60: =D36 -> 3 CORE X 35 SQ. MM. AL/ARM - WIRE (XLPE) - 33 KV (E) | E60: =K36 -> 4 | F60: =BY36/1000 -> 0.25 | G60: 25 MT TRAILER | H60: 65000 | I60: 9 | J60: =F60*I60 -> 2.25 | K60: =ROUNDUP((E60/J60),0) -> 2 | L60: =M60*E60 -> 130000 | M60: =(H60*K60)/E60 -> 32500 | Y60: =SUM(N36:BT36) -> 9063 | AC60: =(BZ36*F60)/80 -> 250 | AE60: =((Y60*F60)+AC60) -> 2515.75 | AK60: =I60*AE60 -> 22641.75
D61: =D37 -> 1 CORE X 630 SQ. MM. AL/ARM (XLPE) - 33 KV | E61: =K37 -> 547.5 | F61: =BY37/1000 -> 0.5 | G61: 25 MT TRAILER | H61: 65000 | I61: 8 | J61: =F61*I61 -> 4 | K61: =ROUNDUP((E61/J61),0) -> 137 | L61: =M61*E61 -> 8905000 | M61: =(H61*K61)/E61 -> 16264.84 | Y61: =SUM(N37:BT37) -> 5051 | AC61: =(BZ37*F61)/80 -> 250 | AE61: =((Y61*F61)+AC61) -> 2775.5 | AK61: =I61*AE61 -> 22204
D62: =D38 -> 1 CORE X 400 SQ. MM. AL/ARM (XLPE) - 33 KV | E62: =K38 -> 17.5 | F62: =BY38/1000 -> 0.5 | G62: 25 MT TRAILER | H62: 65000 | I62: 8 | J62: =F62*I62 -> 4 | K62: =ROUNDUP((E62/J62),0) -> 5 | L62: =M62*E62 -> 325000 | M62: =(H62*K62)/E62 -> 18571.429 | Y62: =SUM(N38:BT38) -> 3869 | AC62: =(BZ38*F62)/80 -> 200 | AE62: =((Y62*F62)+AC62) -> 2134.5 | AK62: =I62*AE62 -> 17076
D63: =D39 -> 1 CORE X 300 SQ. MM. AL/ARM (XLPE) - 33 KV | E63: =K39 -> 7 | F63: =BY39/1000 -> 0.5 | G63: 25 MT TRAILER | H63: 65000 | I63: 8 | J63: =F63*I63 -> 4 | K63: =ROUNDUP((E63/J63),0) -> 2 | L63: =M63*E63 -> 130000 | M63: =(H63*K63)/E63 -> 18571.429 | Y63: =SUM(N39:BT39) -> 3397 | AC63: =(BZ39*F63)/80 -> 200 | AE63: =((Y63*F63)+AC63) -> 1898.5 | AK63: =I63*AE63 -> 15188
I64: sombhu sir confirmed overphone IN LAST TENDER DOCKET 12171 & 12172
A67: DOCKET NO. | B67: Base Date | C67: ITEM CODE | D67: PROPOSE ERP ITEM NAME | E67: EX-WORKS (PER MTR) | F67: FREIGHT PER MTR | G67: PRICE INCLUDING FREIGHT (PER MTR) | H67: GST % | I67: GST VALUE | J67: PRICE INCLUDING GST & FREIGHT (PER MTR) | K67: QTY | L67: Unit | M67: TOTAL PRICE OF FULL QTY (INCLUDING FRIGHT & GST)
A69: =A19 -> ENQ-15138-22-23 | B69: =B19 -> 45627 | C69: =C19 -> FA1300083 | D69: =D19 -> 3 CORE X 400 SQ. MM. AL/ARM - WIRE (XLPE) - 11 KV | E69: =ROUNDUP(E19/1000,2) -> 2890.36 | F69: =ROUNDUP(F19/1000,2) -> 52.17 | G69: =E69+F69 -> 2942.53 | H69: =H19 -> 0.18 | I69: =ROUND(G69*H69,2) -> 529.66 | J69: =ROUND(G69+I69,2) -> 3472.19 | K69: =K19*1000 -> 314000 | L69: MTR | M69: =J69*K69 -> 1090267660
A70: =A20 -> ENQ-15138-22-23 | B70: =B20 -> 45627 | C70: =C20 -> FA1300091 | D70: =D20 -> 3 CORE X 300 SQ. MM. AL/ARM - WIRE (XLPE) - 11 KV | E70: =ROUNDUP(E20/1000,2) -> 2318.79 | F70: =ROUNDUP(F20/1000,2) -> 52.91 | G70: =E70+F70 -> 2371.7 | H70: =H20 -> 0.18 | I70: =ROUND(G70*H70,2) -> 426.91 | J70: =ROUND(G70+I70,2) -> 2798.61 | K70: =K20*1000 -> 43000 | L70: MTR | M70: =J70*K70 -> 120340230
A71: =A21 -> ENQ-15138-22-23 | B71: =B21 -> 45627 | C71: =C21 -> FA1300090 | D71: =D21 -> 3 CORE X 185 SQ. MM AL/ARM - WIRE (XLPE) - 11 KV | E71: =ROUNDUP(E21/1000,2) -> 1723.16 | F71: =ROUNDUP(F21/1000,2) -> 65 | G71: =E71+F71 -> 1788.16 | H71: =H21 -> 0.18 | I71: =ROUND(G71*H71,2) -> 321.87 | J71: =ROUND(G71+I71,2) -> 2110.03 | K71: =K21*1000 -> 2000 | L71: MTR | M71: =J71*K71 -> 4220060
A72: =A22 -> ENQ-15138-22-23 | B72: =B22 -> 45627 | C72: =C22 -> FA1300176 | D72: =D22 -> 3 CORE X 150 SQ. MM. AL/ARM - WIRE (XLPE) - 11 KV | E72: =ROUNDUP(E22/1000,2) -> 1443.84 | F72: =ROUNDUP(F22/1000,2) -> 32.5 | G72: =E72+F72 -> 1476.34 | H72: =H22 -> 0.18 | I72: =ROUND(G72*H72,2) -> 265.74 | J72: =ROUND(G72+I72,2) -> 1742.08 | K72: =K22*1000 -> 4000 | L72: MTR | M72: =J72*K72 -> 6968320
A73: =A23 -> ENQ-15138-22-23 | B73: =B23 -> 45627 | C73: =C23 -> FA1300197 | D73: =D23 -> 3 CORE X 120 SQ. MM. AL/ARM - WIRE (XLPE) - 11 KV | E73: =ROUNDUP(E23/1000,2) -> 1297.93 | F73: =ROUNDUP(F23/1000,2) -> 32.5 | G73: =E73+F73 -> 1330.43 | H73: =H23 -> 0.18 | I73: =ROUND(G73*H73,2) -> 239.48 | J73: =ROUND(G73+I73,2) -> 1569.91 | K73: =K23*1000 -> 10000 | L73: MTR | M73: =J73*K73 -> 15699100
A74: =A24 -> ENQ-15138-22-23 | B74: =B24 -> 45627 | C74: =C24 -> FA1300088 | D74: =D24 -> 3 CORE X 95 SQ. MM. AL/ARM - WIRE (XLPE) - 11 KV (E) | E74: =ROUNDUP(E24/1000,2) -> 1162.91 | F74: =ROUNDUP(F24/1000,2) -> 33.92 | G74: =E74+F74 -> 1196.83 | H74: =H24 -> 0.18 | I74: =ROUND(G74*H74,2) -> 215.43 | J74: =ROUND(G74+I74,2) -> 1412.26 | K74: =K24*1000 -> 23000 | L74: MTR | M74: =J74*K74 -> 32481980
A75: =A25 -> ENQ-15138-22-23 | B75: =B25 -> 45627 | C75: =C25 -> FA1300313 | D75: =D25 -> 3 CORE X 50 SQ. MM. AL/ARD - WIRE (XLPE) - 11 KV | E75: =ROUNDUP(E25/1000,2) -> 892.62 | F75: =ROUNDUP(F25/1000,2) -> 26 | G75: =E75+F75 -> 918.62 | H75: =H25 -> 0.18 | I75: =ROUND(G75*H75,2) -> 165.35 | J75: =ROUND(G75+I75,2) -> 1083.97 | K75: =K25*1000 -> 7500 | L75: MTR | M75: =J75*K75 -> 8129775
A76: =A26 -> ENQ-15138-22-23 | B76: =B26 -> 45627 | C76: =C26 -> FA1300066 | D76: =D26 -> 1 CORE X 1000 SQ. MM. AL/ARM (XLPE) - 11 KV | E76: =ROUNDUP(E26/1000,2) -> 1700.23 | F76: =ROUNDUP(F26/1000,2) -> 65 | G76: =E76+F76 -> 1765.23 | H76: =H26 -> 0.18 | I76: =ROUND(G76*H76,2) -> 317.74 | J76: =ROUND(G76+I76,2) -> 2082.97 | K76: =K26*1000 -> 1000 | L76: MTR | M76: =J76*K76 -> 2082970
A77: =A27 -> ENQ-15138-22-23 | B77: =B27 -> 45627 | C77: =C27 -> FA1300016 | D77: =D27 -> 1 CORE X 630 SQ. MM. AL/ARM (XLPE) - 11 KV | E77: =ROUNDUP(E27/1000,2) -> 1140.87 | F77: =ROUNDUP(F27/1000,2) -> 17.73 | G77: =E77+F77 -> 1158.6 | H77: =H27 -> 0.18 | I77: =ROUND(G77*H77,2) -> 208.55 | J77: =ROUND(G77+I77,2) -> 1367.15 | K77: =K27*1000 -> 11000 | L77: MTR | M77: =J77*K77 -> 15038650
A78: =A28 -> ENQ-15138-22-23 | B78: =B28 -> 45627 | C78: =C28 -> FA1300047 | D78: =D28 -> 1 CORE X 400 SQ. MM. AL/ARM (XLPE) - 11 KV | E78: =ROUNDUP(E28/1000,2) -> 831.14 | F78: =ROUNDUP(F28/1000,2) -> 16.25 | G78: =E78+F78 -> 847.39 | H78: =H28 -> 0.18 | I78: =ROUND(G78*H78,2) -> 152.53 | J78: =ROUND(G78+I78,2) -> 999.92 | K78: =K28*1000 -> 4000 | L78: MTR | M78: =J78*K78 -> 3999680
A79: =A29 -> ENQ-15138-22-23 | B79: =B29 -> 45627 | C79: =C29 -> FA1300009 | D79: =D29 -> 1 CORE X 300 SQ. MM. AL./ARM (XLPE) - 11 KV | E79: =ROUNDUP(E29/1000,2) -> 694.31 | F79: =ROUNDUP(F29/1000,2) -> 20 | G79: =E79+F79 -> 714.31 | H79: =H29 -> 0.18 | I79: =ROUND(G79*H79,2) -> 128.58 | J79: =ROUND(G79+I79,2) -> 842.89 | K79: =K29*1000 -> 6500 | L79: MTR | M79: =J79*K79 -> 5478785
A80: =A30 -> ENQ-15138-22-23 | B80: =B30 -> 45627 | C80: =C30 -> FA1300080 | D80: =D30 -> 3 CORE X 400 SQ. MM AL/ARM - WIRE (XLPE) - 33 KV | E80: =ROUNDUP(E30/1000,2) -> 3751.53 | F80: =ROUNDUP(F30/1000,2) -> 65.08 | G80: =E80+F80 -> 3816.61 | H80: =H30 -> 0.18 | I80: =ROUND(G80*H80,2) -> 686.99 | J80: =ROUND(G80+I80,2) -> 4503.6 | K80: =K30*1000 -> 222750 | L80: MTR | M80: =J80*K80 -> 1.0031769e+09
... A89: =A39 -> ENQ-15138-22-23 | B89: =B39 -> 45627 | C89: =C39 -> FA1300019 | D89: =D39 -> 1 CORE X 300 SQ. MM. AL/ARM (XLPE) - 33 KV | E89: =ROUNDUP(E39/1000,2) -> 956.88 | F89: =ROUNDUP(F39/1000,2) -> 18.58 | G89: =E89+F89 -> 975.46 | H89: =H39 -> 0.18 | I89: =ROUND(G89*H89,2) -> 175.58 | J89: =ROUND(G89+I89,2) -> 1151.04 | K89: =K39*1000 -> 7000 | L89: MTR | M89: =J89*K89 -> 8057280
M90: =SUM(M69:M89) -> 3421769770
M91: =M90-M40 -> 14548.627

Sheet PV IS
A1: Base Date | B1: 45627
A2: PV Terms(Price Variation Formula) | B2: The line-item prices shall be subject to Price Variation clause as per latest IEEMA Circular. (Base Date of IEEMA for price consideration shall be Dec-24).
A3: PV FORMULA
A4: P=Po+Alf (Al-Alo)+XLFAL(CC-Cco)+CCFAI(PVCc-PVCco)+FeF (Fe-Feo)
A7: Alf | B7: Variation factor for aluminum.
A8: CCFAI | B8: Variation factor for PVC compound/Polymer for aluminum conductor cable.
A9: XLFAL | B9: Variation Factor For XLPE
A10: Fef | B10: Variation factor for steel
A13: Item | B13: Ex-Work
AC14: VALUE ADDITION CALCULATION
A15: Item | B15: Calculation part | C15: Date of Inspection | D15: Applicable Date | J15: BASE DATE | P15: FACTORS | U15: Ex-Work Po | V15: PVC of al | W15: PVC of XLPE | X15: PVC OF PVC | Y15: PVC OF FE | Z15: PVC OF CU TAPE | AA15: PV/PKM | AB15: Billing Price/PKM
D16: Date | E16: Al | F16: Cu | G16: Cc | H16: PVCc | I16: Fe | J16: Date | K16: Alo | L16: Cuo | M16: Cco | N16: PVCco | O16: Feo | AC16: ='AUTO CALCULATION SHEET (2)'!N17 -> Alumimium | AD16: ='AUTO CALCULATION SHEET (2)'!Y17 -> Copper Tape - 0.045 mm | AE16: ='AUTO CALCULATION SHEET (2)'!AC17 -> Extruded semiconductive | AF16: ='AUTO CALCULATION SHEET (2)'!AE17 -> HT-XLPE | AG16: ='AUTO CALCULATION SHEET (2)'!AK17 -> POLY TAPE | AH16: ='AUTO CALCULATION SHEET (2)'!AQ17 -> PVC Type ST-2 | AI16: ='AUTO CALCULATION SHEET (2)'!AV17 -> Aluminium Round Wire | AJ16: ='AUTO CALCULATION SHEET (2)'!BA17 -> Galvanised Steel Round Wire | AK16: ='AUTO CALCULATION SHEET (2)'!BF17 -> FRLSH PVC Type ST-2 | AL16: ='AUTO CALCULATION SHEET (2)'!BL17 -> PP FILLER | AM16: ='AUTO CALCULATION SHEET (2)'!BN17 -> NCWBT | AN16: ='AUTO CALCULATION SHEET (2)'!BP17 -> Semi conducting Water Swellable tape | AO16: ='AUTO CALCULATION SHEET (2)'!BT17 -> RUBBERIZED COTTON TAPE | AP16: RMC | AQ16: Drum | AR16: RMC+Drum | AS16: VA | AT16: Groos VA% | AU16: Mfg % | AV16: Int % | AW16: Ins% | AX16: Net VA
P17: Alf | Q17: XLFAL | R17: CCFAI | S17: FeF | T17: Smif | AC17: 272 | AD17: 968 | AE17: 178 | AF17: 151 | AG17: 120 | AH17: 68 | AI17: =AC17+5 -> 277 | AJ17: 82 | AK17: =86+15 -> 101 | AL17: 85 | AM17: 340 | AN17: 430 | AO17: 370
B18: ARM WIRE DIA | AC18: Kg/Km | AD18: Kg/Km | AE18: Kg/Km | AF18: Kg/Km | AG18: Kg/Km | AH18: Kg/Km | AI18: Kg/Km | AJ18: Kg/Km | AK18: Kg/Km | AL18: Kg/Km | AM18: Kg/Km | AN18: Kg/Km | AO18: Kg/Km
A19: ='AUTO CALCULATION SHEET (2)'!D19 -> 3 CORE X 400 SQ. MM. AL/ARM - WIRE (XLPE) - 11 KV | B19: 4 | C19: PROVISIONAL | D19: 45705 | E19: 265753.41 | F19: 870134.53 | G19: 176136 | H19: 160825 | I19: 70250 | J19: =$B$1 -> 45627 | K19: 252941 | L19: 820039 | M19: 173241 | N19: 160825 | O19: 72250 | P19: 3.374 | Q19: 1.314 | R19: 3.664 | S19: 6.658 | T19: 0.124 | U19: ='AUTO CALCULATION SHEET (2)'!E19 -> 2890355 | V19: =(P19*(E19-K19)) -> 43229.071 | W19: =(Q19*(G19-M19)) -> 3804.03 | X19: =(R19*(H19-N19)) -> 0 | Y19: =(S19*(I19-O19)) -> -13316 | Z19: =T19*(F19-L19) -> 6211.8457 | AA19: =V19+W19+X19+Y19+Z19 -> 39928.947 | AB19: =+U19+AA19 -> 2930284 | AC19: ='AUTO CALCULATION SHEET (2)'!N19 -> 3240 | AD19: ='AUTO CALCULATION SHEET (2)'!Y19 -> 176 | AE19: ='AUTO CALCULATION SHEET (2)'!AC19 -> 518 | AF19: ='AUTO CALCULATION SHEET (2)'!AE19 -> 930 | AG19: ='AUTO CALCULATION SHEET (2)'!AK19 -> 0 | AH19: ='AUTO CALCULATION SHEET (2)'!AQ19 -> 1027 | AI19: ='AUTO CALCULATION SHEET (2)'!AV19 -> 0 | AJ19: ='AUTO CALCULATION SHEET (2)'!BA19 -> 5643 | AK19: ='AUTO CALCULATION SHEET (2)'!BF19 -> 1377 | AL19: ='AUTO CALCULATION SHEET (2)'!BL19 -> 1032 | AM19: ='AUTO CALCULATION SHEET (2)'!BN19 -> 58 | AN19: ='AUTO CALCULATION SHEET (2)'!BP19 -> 95 | AO19: ='AUTO CALCULATION SHEET (2)'!BT19 -> 60 | AP19: =SUMPRODUCT(AC19:AO19,$AC$17:$AO$17) -> 2126411 | AQ19: ='AUTO CALCULATION SHEET (2)'!BZ19 -> 126000 | AR19: =AP19+AQ19 -> 2252411 | AS19: =AB19-AR19 -> 677872.99 | AT19: =ROUND((AS19/AB19)*100,2) -> 23.13 | AU19: 0 | AV19: 2 | AW19: 1 | AX19: =AT19-AU19-AV19-AW19 -> 20.13
A20: ='AUTO CALCULATION SHEET (2)'!D20 -> 3 CORE X 300 SQ. MM. AL/ARM - WIRE (XLPE) - 11 KV | B20: 3.15 | C20: PROVISIONAL | D20: 45705 | E20: 265753.41 | F20: 870134.53 | G20: 176136 | H20: 160825 | I20: 70250 | J20: =$B$1 -> 45627 | K20: 252941 | L20: 820039 | M20: 173241 | N20: 160825 | O20: 72250 | P20: 2.635 | Q20: 1.167 | R20: 3.161 | S20: 5.182 | T20: 0.11 | U20: ='AUTO CALCULATION SHEET (2)'!E20 -> 2318788.3 | V20: =(P20*(E20-K20)) -> 33760.7 | W20: =(Q20*(G20-M20)) -> 3378.465 | X20: =(R20*(H20-N20)) -> 0 | Y20: =(S20*(I20-O20)) -> -10364 | Z20: =T20*(F20-L20) -> 5510.5083 | AA20: =V20+W20+X20+Y20+Z20 -> 32285.674 | AB20: =+U20+AA20 -> 2351074 | AC20: ='AUTO CALCULATION SHEET (2)'!N20 -> 2430 | AD20: ='AUTO CALCULATION SHEET (2)'!Y20 -> 161 | AE20: ='AUTO CALCULATION SHEET (2)'!AC20 -> 465 | AF20: ='AUTO CALCULATION SHEET (2)'!AE20 -> 835 | AG20: ='AUTO CALCULATION SHEET (2)'!AK20 -> 0 | AH20: ='AUTO CALCULATION SHEET (2)'!AQ20 -> 885 | AI20: ='AUTO CALCULATION SHEET (2)'!AV20 -> 0 | AJ20: ='AUTO CALCULATION SHEET (2)'!BA20 -> 4072 | AK20: ='AUTO CALCULATION SHEET (2)'!BF20 -> 1190 | AL20: ='AUTO CALCULATION SHEET (2)'!BL20 -> 862 | AM20: ='AUTO CALCULATION SHEET (2)'!BN20 -> 38 | AN20: ='AUTO CALCULATION SHEET (2)'!BP20 -> 86 | AO20: ='AUTO CALCULATION SHEET (2)'!BT20 -> 54 | AP20: =SUMPRODUCT(AC20:AO20,$AC$17:$AO$17) -> 1683087 | AQ20: ='AUTO CALCULATION SHEET (2)'!BZ20 -> 126000 | AR20: =AP20+AQ20 -> 1809087 | AS20: =AB20-AR20 -> 541987.02 | AT20: =ROUND((AS20/AB20)*100,2) -> 23.05 | AU20: 0 | AV20: 2 | AW20: 1 | AX20: =AT20-AU20-AV20-AW20 -> 20.05
A21: ='AUTO CALCULATION SHEET (2)'!D21 -> 3 CORE X 185 SQ. MM AL/ARM - WIRE (XLPE) - 11 KV | B21: 3.15 | C21: PROVISIONAL | D21: 45705 | E21: 265753.41 | F21: 870134.53 | G21: 176136 | H21: 160825 | I21: 70250 | J21: =$B$1 -> 45627 | K21: 252941 | L21: 820039 | M21: 173241 | N21: 160825 | O21: 72250 | P21: 1.605 | Q21: 0.968 | R21: 2.406 | S21: 4.148 | T21: 0.094 | U21: ='AUTO CALCULATION SHEET (2)'!E21 -> 1723155.2 | V21: =(P21*(E21-K21)) -> 20563.918 | W21: =(Q21*(G21-M21)) -> 2802.36 | X21: =(R21*(H21-N21)) -> 0 | Y21: =(S21*(I21-O21)) -> -8296 | Z21: =T21*(F21-L21) -> 4708.9798 | AA21: =V21+W21+X21+Y21+Z21 -> 19779.258 | AB21: =+U21+AA21 -> 1742934.5 | AC21: ='AUTO CALCULATION SHEET (2)'!N21 -> 1499 | AD21: ='AUTO CALCULATION SHEET (2)'!Y21 -> 138 | AE21: ='AUTO CALCULATION SHEET (2)'!AC21 -> 387 | AF21: ='AUTO CALCULATION SHEET (2)'!AE21 -> 693 | AG21: ='AUTO CALCULATION SHEET (2)'!AK21 -> 0 | AH21: ='AUTO CALCULATION SHEET (2)'!AQ21 -> 735 | AI21: ='AUTO CALCULATION SHEET (2)'!AV21 -> 0 | AJ21: ='AUTO CALCULATION SHEET (2)'!BA21 -> 3500 | AK21: ='AUTO CALCULATION SHEET (2)'!BF21 -> 945 | AL21: ='AUTO CALCULATION SHEET (2)'!BL21 -> 615 | AM21: ='AUTO CALCULATION SHEET (2)'!BN21 -> 35 | AN21: ='AUTO CALCULATION SHEET (2)'!BP21 -> 72 | AO21: ='AUTO CALCULATION SHEET (2)'!BT21 -> 48 | AP21: =SUMPRODUCT(AC21:AO21,$AC$17:$AO$17) -> 1260161 | AQ21: ='AUTO CALCULATION SHEET (2)'!BZ21 -> 77400 | AR21: =AP21+AQ21 -> 1337561 | AS21: =AB21-AR21 -> 405373.51 | AT21: =ROUND((AS21/AB21)*100,2) -> 23.26 | AU21: 0 | AV21: 2 | AW21: 1 | AX21: =AT21-AU21-AV21-AW21 -> 20.26
A22: ='AUTO CALCULATION SHEET (2)'!D22 -> 3 CORE X 150 SQ. MM. AL/ARM - WIRE (XLPE) - 11 KV | B22: 2.5 | C22: PROVISIONAL | D22: 45705 | E22: 265753.41 | F22: 870134.53 | G22: 176136 | H22: 160825 | I22: 71250 | J22: =$B$1 -> 45627 | K22: 252941 | L22: 820039 | M22: 173241 | N22: 160825 | O22: 73250 | P22: 1.279 | Q22: 0.89 | R22: 2.061 | S22: 3.265 | T22: 0.088 | U22: ='AUTO CALCULATION SHEET (2)'!E22 -> 1443834.9 | V22: =(P22*(E22-K22)) -> 16387.072 | W22: =(Q22*(G22-M22)) -> 2576.55 | X22: =(R22*(H22-N22)) -> 0 | Y22: =(S22*(I22-O22)) -> -6530 | Z22: =T22*(F22-L22) -> 4408.4066 | AA22: =V22+W22+X22+Y22+Z22 -> 16842.029 | AB22: =+U22+AA22 -> 1460677 | AC22: ='AUTO CALCULATION SHEET (2)'!N22 -> 1215 | AD22: ='AUTO CALCULATION SHEET (2)'!Y22 -> 130 | AE22: ='AUTO CALCULATION SHEET (2)'!AC22 -> 359 | AF22: ='AUTO CALCULATION SHEET (2)'!AE22 -> 642 | AG22: ='AUTO CALCULATION SHEET (2)'!AK22 -> 0 | AH22: ='AUTO CALCULATION SHEET (2)'!AQ22 -> 605 | AI22: ='AUTO CALCULATION SHEET (2)'!AV22 -> 0 | AJ22: ='AUTO CALCULATION SHEET (2)'!BA22 -> 2605 | AK22: ='AUTO CALCULATION SHEET (2)'!BF22 -> 812 | AL22: ='AUTO CALCULATION SHEET (2)'!BL22 -> 567 | AM22: ='AUTO CALCULATION SHEET (2)'!BN22 -> 18 | AN22: ='AUTO CALCULATION SHEET (2)'!BP22 -> 67 | AO22: ='AUTO CALCULATION SHEET (2)'!BT22 -> 44 | AP22: =SUMPRODUCT(AC22:AO22,$AC$17:$AO$17) -> 1053331 | AQ22: ='AUTO CALCULATION SHEET (2)'!BZ22 -> 70400 | AR22: =AP22+AQ22 -> 1123731 | AS22: =AB22-AR22 -> 336945.97 | AT22: =ROUND((AS22/AB22)*100,2) -> 23.07 | AU22: 0 | AV22: 2 | AW22: 1 | AX22: =AT22-AU22-AV22-AW22 -> 20.07
A23: ='AUTO CALCULATION SHEET (2)'!D23 -> 3 CORE X 120 SQ. MM. AL/ARM - WIRE (XLPE) - 11 KV | B23: 2.5 | C23: PROVISIONAL | D23: 45705 | E23: 265753.41 | F23: 870134.53 | G23: 176136 | H23: 160825 | I23: 71250 | J23: =$B$1 -> 45627 | K23: 252941 | L23: 820039 | M23: 173241 | N23: 160825 | O23: 73250 | P23: 1.036 | Q23: 0.822 | R23: 1.877 | S23: 2.882 | T23: 0.083 | U23: ='AUTO CALCULATION SHEET (2)'!E23 -> 1297922 | V23: =(P23*(E23-K23)) -> 13273.657 | W23: =(Q23*(G23-M23)) -> 2379.69 | X23: =(R23*(H23-N23)) -> 0 | Y23: =(S23*(I23-O23)) -> -5764 | Z23: =T23*(F23-L23) -> 4157.929 | AA23: =V23+W23+X23+Y23+Z23 -> 14047.276 | AB23: =+U23+AA23 -> 1311969.3 | AC23: ='AUTO CALCULATION SHEET (2)'!N23 -> 972 | AD23: ='AUTO CALCULATION SHEET (2)'!Y23 -> 123 | AE23: ='AUTO CALCULATION SHEET (2)'!AC23 -> 332 | AF23: ='AUTO CALCULATION SHEET (2)'!AE23 -> 593 | AG23: ='AUTO CALCULATION SHEET (2)'!AK23 -> 0 | AH23: ='AUTO CALCULATION SHEET (2)'!AQ23 -> 550 | AI23: ='AUTO CALCULATION SHEET (2)'!AV23 -> 0 | AJ23: ='AUTO CALCULATION SHEET (2)'!BA23 -> 2485 | AK23: ='AUTO CALCULATION SHEET (2)'!BF23 -> 726 | AL23: ='AUTO CALCULATION SHEET (2)'!BL23 -> 503 | AM23: ='AUTO CALCULATION SHEET (2)'!BN23 -> 17 | AN23: ='AUTO CALCULATION SHEET (2)'!BP23 -> 62 | AO23: ='AUTO CALCULATION SHEET (2)'!BT23 -> 42 | AP23: =SUMPRODUCT(AC23:AO23,$AC$17:$AO$17) -> 937318 | AQ23: ='AUTO CALCULATION SHEET (2)'!BZ23 -> 70400 | AR23: =AP23+AQ23 -> 1007718 | AS23: =AB23-AR23 -> 304251.27 | AT23: =ROUND((AS23/AB23)*100,2) -> 23.19 | AU23: 0 | AV23: 2 | AW23: 1 | AX23: =AT23-AU23-AV23-AW23 -> 20.19
A24: ='AUTO CALCULATION SHEET (2)'!D24 -> 3 CORE X 95 SQ. MM. AL/ARM - WIRE (XLPE) - 11 KV (E) | B24: 2.5 | C24: PROVISIONAL | D24: 45705 | E24: 265753.41 | F24: 870134.53 | G24: 176136 | H24: 160825 | I24: 71250 | J24: =$B$1 -> 45627 | K24: 252941 | L24: 820039 | M24: 173241 | N24: 160825 | O24: 73250 | P24: 0.821 | Q24: 0.755 | R24: 1.647 | S24: 2.718 | T24: 0.077 | U24: ='AUTO CALCULATION SHEET (2)'!E24 -> 1162904.1 | V24: =(P24*(E24-K24)) -> 10518.989 | W24: =(Q24*(G24-M24)) -> 2185.725 | X24: =(R24*(H24-N24)) -> 0 | Y24: =(S24*(I24-O24)) -> -5436 | Z24: =T24*(F24-L24) -> 3857.3558 | AA24: =V24+W24+X24+Y24+Z24 -> 11126.069 | AB24: =+U24+AA24 -> 1174030.1 | AC24: ='AUTO CALCULATION SHEET (2)'!N24 -> 770 | AD24: ='AUTO CALCULATION SHEET (2)'!Y24 -> 115 | AE24: ='AUTO CALCULATION SHEET (2)'!AC24 -> 304 | AF24: ='AUTO CALCULATION SHEET (2)'!AE24 -> 542 | AG24: ='AUTO CALCULATION SHEET (2)'!AK24 -> 0 | AH24: ='AUTO CALCULATION SHEET (2)'!AQ24 -> 523 | AI24: ='AUTO CALCULATION SHEET (2)'!AV24 -> 0 | AJ24: ='AUTO CALCULATION SHEET (2)'!BA24 -> 2324 | AK24: ='AUTO CALCULATION SHEET (2)'!BF24 -> 685 | AL24: ='AUTO CALCULATION SHEET (2)'!BL24 -> 418 | AM24: ='AUTO CALCULATION SHEET (2)'!BN24 -> 15 | AN24: ='AUTO CALCULATION SHEET (2)'!BP24 -> 57 | AO24: ='AUTO CALCULATION SHEET (2)'!BT24 -> 40 | AP24: =SUMPRODUCT(AC24:AO24,$AC$17:$AO$17) -> 831971 | AQ24: ='AUTO CALCULATION SHEET (2)'!BZ24 -> 68800 | AR24: =AP24+AQ24 -> 900771 | AS24: =AB24-AR24 -> 273259.14 | AT24: =ROUND((AS24/AB24)*100,2) -> 23.28 | AU24: 0 | AV24: 2 | AW24: 1 | AX24: =AT24-AU24-AV24-AW24 -> 20.28
A25: ='AUTO CALCULATION SHEET (2)'!D25 -> 3 CORE X 50 SQ. MM. AL/ARD - WIRE (XLPE) - 11 KV | B25: 2.5 | C25: PROVISIONAL | D25: 45705 | E25: 265753.41 | F25: 870134.53 | G25: 176136 | H25: 160825 | I25: 71250 | J25: =$B$1 -> 45627 | K25: 252941 | L25: 820039 | M25: 173241 | N25: 160825 | O25: 73250 | P25: 0.41 | Q25: 0.6 | R25: 1.26 | S25: 2.321 | T25: 0.065 | U25: ='AUTO CALCULATION SHEET (2)'!E25 -> 892612.56 | V25: =(P25*(E25-K25)) -> 5253.0881 | W25: =(Q25*(G25-M25)) -> 1737 | X25: =(R25*(H25-N25)) -> 0 | Y25: =(S25*(I25-O25)) -> -4642 | Z25: =T25*(F25-L25) -> 3256.2095 | AA25: =V25+W25+X25+Y25+Z25 -> 5604.2975 | AB25: =+U25+AA25 -> 898216.86 | AC25: ='AUTO CALCULATION SHEET (2)'!N25 -> 405 | AD25: ='AUTO CALCULATION SHEET (2)'!Y25 -> 90 | AE25: ='AUTO CALCULATION SHEET (2)'!AC25 -> 181 | AF25: ='AUTO CALCULATION SHEET (2)'!AE25 -> 445 | AG25: ='AUTO CALCULATION SHEET (2)'!AK25 -> 0 | AH25: ='AUTO CALCULATION SHEET (2)'!AQ25 -> 352 | AI25: ='AUTO CALCULATION SHEET (2)'!AV25 -> 0 | AJ25: ='AUTO CALCULATION SHEET (2)'!BA25 -> 1964 | AK25: ='AUTO CALCULATION SHEET (2)'!BF25 -> 551 | AL25: ='AUTO CALCULATION SHEET (2)'!BL25 -> 308 | AM25: ='AUTO CALCULATION SHEET (2)'!BN25 -> 10 | AN25: ='AUTO CALCULATION SHEET (2)'!BP25 -> 42 | AO25: ='AUTO CALCULATION SHEET (2)'!BT25 -> 34 | AP25: =SUMPRODUCT(AC25:AO25,$AC$17:$AO$17) -> 597548 | AQ25: ='AUTO CALCULATION SHEET (2)'!BZ25 -> 90000 | AR25: =AP25+AQ25 -> 687548 | AS25: =AB25-AR25 -> 210668.86 | AT25: =ROUND((AS25/AB25)*100,2) -> 23.45 | AU25: 0 | AV25: 2 | AW25: 1 | AX25: =AT25-AU25-AV25-AW25 -> 20.45
A26: ='AUTO CALCULATION SHEET (2)'!D26 -> 1 CORE X 1000 SQ. MM. AL/ARM (XLPE) - 11 KV | B26: 2.5 | C26: PROVISIONAL | D26: 45705 | E26: 265753.41 | F26: 870134.53 | G26: 176136 | H26: 160825 | J26: =$B$1 -> 45627 | K26: 252941 | L26: 820039 | M26: 173241 | N26: 160825 | P26: 3.749 | Q26: 0.66 | R26: 1.035 | T26: 0.058 | U26: ='AUTO CALCULATION SHEET (2)'!E26 -> 1700227 | V26: =(P26*(E26-K26)) -> 48033.725 | W26: =(Q26*(G26-M26)) -> 1910.7 | X26: =(R26*(H26-N26)) -> 0 | Y26: =(S26*(I26-O26)) -> 0 | Z26: =T26*(F26-L26) -> 2905.5407 | AA26: =V26+W26+X26+Y26+Z26 -> 52849.966 | AB26: =+U26+AA26 -> 1753077 | AC26: ='AUTO CALCULATION SHEET (2)'!N26 -> 2732 | AD26: ='AUTO CALCULATION SHEET (2)'!Y26 -> 84 | AE26: ='AUTO CALCULATION SHEET (2)'!AC26 -> 276 | AF26: ='AUTO CALCULATION SHEET (2)'!AE26 -> 480 | AG26: ='AUTO CALCULATION SHEET (2)'!AK26 -> 35 | AH26: ='AUTO CALCULATION SHEET (2)'!AQ26 -> 198 | AI26: ='AUTO CALCULATION SHEET (2)'!AV26 -> 814 | AJ26: ='AUTO CALCULATION SHEET (2)'!BA26 -> 0 | AK26: ='AUTO CALCULATION SHEET (2)'!BF26 -> 706 | AL26: ='AUTO CALCULATION SHEET (2)'!BL26 -> 0 | AM26: ='AUTO CALCULATION SHEET (2)'!BN26 -> 39 | AN26: ='AUTO CALCULATION SHEET (2)'!BP26 -> 49 | AO26: ='AUTO CALCULATION SHEET (2)'!BT26 -> 42 | AP26: =SUMPRODUCT(AC26:AO26,$AC$17:$AO$17) -> 1310342 | AQ26: ='AUTO CALCULATION SHEET (2)'!BZ26 -> 63000 | AR26: =AP26+AQ26 -> 1373342 | AS26: =AB26-AR26 -> 379734.98 | AT26: =ROUND((AS26/AB26)*100,2) -> 21.66 | AU26: 0 | AV26: 2 | AW26: 1 | AX26: =AT26-AU26-AV26-AW26 -> 18.66
A27: ='AUTO CALCULATION SHEET (2)'!D27 -> 1 CORE X 630 SQ. MM. AL/ARM (XLPE) - 11 KV | B27: 2 | C27: PROVISIONAL | D27: 45705 | E27: 265753.41 | F27: 870134.53 | G27: 176136 | H27: 160825 | J27: =$B$1 -> 45627 | K27: 252941 | L27: 820039 | M27: 173241 | N27: 160825 | P27: 2.369 | Q27: 0.529 | R27: 0.739 | T27: 0.05 | U27: ='AUTO CALCULATION SHEET (2)'!E27 -> 1140867.4 | V27: =(P27*(E27-K27)) -> 30352.599 | W27: =(Q27*(G27-M27)) -> 1531.455 | X27: =(R27*(H27-N27)) -> 0 | Y27: =(S27*(I27-O27)) -> 0 | Z27: =T27*(F27-L27) -> 2504.7765 | AA27: =V27+W27+X27+Y27+Z27 -> 34388.831 | AB27: =+U27+AA27 -> 1175256.3 | AC27: ='AUTO CALCULATION SHEET (2)'!N27 -> 1701 | AD27: ='AUTO CALCULATION SHEET (2)'!Y27 -> 69 | AE27: ='AUTO CALCULATION SHEET (2)'!AC27 -> 213 | AF27: ='AUTO CALCULATION SHEET (2)'!AE27 -> 380 | AG27: ='AUTO CALCULATION SHEET (2)'!AK27 -> 29 | AH27: ='AUTO CALCULATION SHEET (2)'!AQ27 -> 144 | AI27: ='AUTO CALCULATION SHEET (2)'!AV27 -> 539 | AJ27: ='AUTO CALCULATION SHEET (2)'!BA27 -> 0 | AK27: ='AUTO CALCULATION SHEET (2)'!BF27 -> 500 | AL27: ='AUTO CALCULATION SHEET (2)'!BL27 -> 0 | AM27: ='AUTO CALCULATION SHEET (2)'!BN27 -> 26 | AN27: ='AUTO CALCULATION SHEET (2)'!BP27 -> 39 | AO27: ='AUTO CALCULATION SHEET (2)'!BT27 -> 33 | AP27: =SUMPRODUCT(AC27:AO27,$AC$17:$AO$17) -> 875653 | AQ27: ='AUTO CALCULATION SHEET (2)'!BZ27 -> 44800 | AR27: =AP27+AQ27 -> 920453 | AS27: =AB27-AR27 -> 254803.26 | AT27: =ROUND((AS27/AB27)*100,2) -> 21.68 | AU27: 0 | AV27: 2 | AW27: 1 | AX27: =AT27-AU27-AV27-AW27 -> 18.68
A28: ='AUTO CALCULATION SHEET (2)'!D28 -> 1 CORE X 400 SQ. MM. AL/ARM (XLPE) - 11 KV | B28: 2 | C28: PROVISIONAL | D28: 45705 | E28: 265753.41 | F28: 870134.53 | G28: 176136 | H28: 160825 | J28: =$B$1 -> 45627 | K28: 252941 | L28: 820039 | M28: 173241 | N28: 160825 | P28: 1.565 | Q28: 0.42 | R28: 0.578 | T28: 0.041 | U28: ='AUTO CALCULATION SHEET (2)'!E28 -> 831134.48 | V28: =(P28*(E28-K28)) -> 20051.422 | W28: =(Q28*(G28-M28)) -> 1215.9 | X28: =(R28*(H28-N28)) -> 0 | Y28: =(S28*(I28-O28)) -> 0 | Z28: =T28*(F28-L28) -> 2053.9167 | AA28: =V28+W28+X28+Y28+Z28 -> 23321.238 | AB28: =+U28+AA28 -> 854455.72 | AC28: ='AUTO CALCULATION SHEET (2)'!N28 -> 1080 | AD28: ='AUTO CALCULATION SHEET (2)'!Y28 -> 59 | AE28: ='AUTO CALCULATION SHEET (2)'!AC28 -> 172 | AF28: ='AUTO CALCULATION SHEET (2)'!AE28 -> 310 | AG28: ='AUTO CALCULATION SHEET (2)'!AK28 -> 24 | AH28: ='AUTO CALCULATION SHEET (2)'!AQ28 -> 104 | AI28: ='AUTO CALCULATION SHEET (2)'!AV28 -> 460 | AJ28: ='AUTO CALCULATION SHEET (2)'!BA28 -> 0 | AK28: ='AUTO CALCULATION SHEET (2)'!BF28 -> 400 | AL28: ='AUTO CALCULATION SHEET (2)'!BL28 -> 0 | AM28: ='AUTO CALCULATION SHEET (2)'!BN28 -> 20 | AN28: ='AUTO CALCULATION SHEET (2)'!BP28 -> 32 | AO28: ='AUTO CALCULATION SHEET (2)'!BT28 -> 30 | AP28: =SUMPRODUCT(AC28:AO28,$AC$17:$AO$17) -> 637730 | AQ28: ='AUTO CALCULATION SHEET (2)'!BZ28 -> 32000 | AR28: =AP28+AQ28 -> 669730 | AS28: =AB28-AR28 -> 184725.72 | AT28: =ROUND((AS28/AB28)*100,2) -> 21.62 | AU28: 0 | AV28: 2 | AW28: 1 | AX28: =AT28-AU28-AV28-AW28 -> 18.62
A29: ='AUTO CALCULATION SHEET (2)'!D29 -> 1 CORE X 300 SQ. MM. AL./ARM (XLPE) - 11 KV | B29: 2 | C29: PROVISIONAL | D29: 45705 | E29: 265753.41 | F29: 870134.53 | G29: 176136 | H29: 160825 | J29: =$B$1 -> 45627 | K29: 252941 | L29: 820039 | M29: 173241 | N29: 160825 | P29: 1.283 | Q29: 0.372 | R29: 0.506 | T29: 0.036 | U29: ='AUTO CALCULATION SHEET (2)'!E29 -> 694300.94 | V29: =(P29*(E29-K29)) -> 16438.322 | W29: =(Q29*(G29-M29)) -> 1076.94 | X29: =(R29*(H29-N29)) -> 0 | Y29: =(S29*(I29-O29)) -> 0 | Z29: =T29*(F29-L29) -> 1803.4391 | AA29: =V29+W29+X29+Y29+Z29 -> 19318.701 | AB29: =+U29+AA29 -> 713619.64 | AC29: ='AUTO CALCULATION SHEET (2)'!N29 -> 810 | AD29: ='AUTO CALCULATION SHEET (2)'!Y29 -> 54 | AE29: ='AUTO CALCULATION SHEET (2)'!AC29 -> 155 | AF29: ='AUTO CALCULATION SHEET (2)'!AE29 -> 278 | AG29: ='AUTO CALCULATION SHEET (2)'!AK29 -> 22 | AH29: ='AUTO CALCULATION SHEET (2)'!AQ29 -> 95 | AI29: ='AUTO CALCULATION SHEET (2)'!AV29 -> 424 | AJ29: ='AUTO CALCULATION SHEET (2)'!BA29 -> 0 | AK29: ='AUTO CALCULATION SHEET (2)'!BF29 -> 343 | AL29: ='AUTO CALCULATION SHEET (2)'!BL29 -> 0 | AM29: ='AUTO CALCULATION SHEET (2)'!BN29 -> 13 | AN29: ='AUTO CALCULATION SHEET (2)'!BP29 -> 29 | AO29: ='AUTO CALCULATION SHEET (2)'!BT29 -> 27 | AP29: =SUMPRODUCT(AC29:AO29,$AC$17:$AO$17) -> 530231 | AQ29: ='AUTO CALCULATION SHEET (2)'!BZ29 -> 28800 | AR29: =AP29+AQ29 -> 559031 | AS29: =AB29-AR29 -> 154588.64 | AT29: =ROUND((AS29/AB29)*100,2) -> 21.66 | AU29: 0 | AV29: 2 | AW29: 1 | AX29: =AT29-AU29-AV29-AW29 -> 18.66
A30: ='AUTO CALCULATION SHEET (2)'!D30 -> 3 CORE X 400 SQ. MM AL/ARM - WIRE (XLPE) - 33 KV | B30: 4 | C30: PROVISIONAL | D30: 45705 | E30: 265753.41 | F30: 870134.53 | G30: 176136 | H30: 160825 | I30: 70250 | J30: =$B$1 -> 45627 | K30: 252941 | L30: 820039 | M30: 173241 | N30: 160825 | O30: 72250 | P30: 3.374 | Q30: 3.229 | R30: 5.736 | S30: 8.76 | T30: 0.164 | U30: ='AUTO CALCULATION SHEET (2)'!E30 -> 3751528.4 | V30: =(P30*(E30-K30)) -> 43229.071 | W30: =(Q30*(G30-M30)) -> 9347.955 | X30: =(R30*(H30-N30)) -> 0 | Y30: =(S30*(I30-O30)) -> -17520 | Z30: =T30*(F30-L30) -> 8215.6669 | AA30: =V30+W30+X30+Y30+Z30 -> 43272.693 | AB30: =+U30+AA30 -> 3794801.1 | AC30: ='AUTO CALCULATION SHEET (2)'!N30 -> 3240 | AD30: ='AUTO CALCULATION SHEET (2)'!Y30 -> 229 | AE30: ='AUTO CALCULATION SHEET (2)'!AC30 -> 618 | AF30: ='AUTO CALCULATION SHEET (2)'!AE30 -> 2674 | AG30: ='AUTO CALCULATION SHEET (2)'!AK30 -> 0 | AH30: ='AUTO CALCULATION SHEET (2)'!AQ30 -> 1629 | AI30: ='AUTO CALCULATION SHEET (2)'!AV30 -> 0 | AJ30: ='AUTO CALCULATION SHEET (2)'!BA30 -> 7284 | AK30: ='AUTO CALCULATION SHEET (2)'!BF30 -> 1760 | AL30: ='AUTO CALCULATION SHEET (2)'!BL30 -> 1750 | AM30: ='AUTO CALCULATION SHEET (2)'!BN30 -> 58 | AN30: ='AUTO CALCULATION SHEET (2)'!BP30 -> 114 | AO30: ='AUTO CALCULATION SHEET (2)'!BT30 -> 76 | AP30: =SUMPRODUCT(AC30:AO30,$AC$17:$AO$17) -> 2748160 | AQ30: ='AUTO CALCULATION SHEET (2)'!BZ30 -> 176000 | AR30: =AP30+AQ30 -> 2924160 | AS30: =AB30-AR30 -> 870641.09 | AT30: =ROUND((AS30/AB30)*100,2) -> 22.94 | AU30: 0 | AV30: 2 | AW30: 1 | AX30: =AT30-AU30-AV30-AW30 -> 19.94
A31: ='AUTO CALCULATION SHEET (2)'!D31 -> 3 CORE X 300 SQ. MM. AL/ARM - WIRE (XLPE) - 33 KV | B31: 4 | C31: PROVISIONAL | D31: 45705 | E31: 265753.41 | F31: 870134.53 | G31: 176136 | H31: 160825 | I31: 70250 | J31: =$B$1 -> 45627 | K31: 252941 | L31: 820039 | M31: 173241 | N31: 160825 | O31: 72250 | P31: 2.635 | Q31: 2.919 | R31: 5.029 | S31: 8.187 | T31: 0.15 | U31: ='AUTO CALCULATION SHEET (2)'!E31 -> 3269603.3 | V31: =(P31*(E31-K31)) -> 33760.7 | W31: =(Q31*(G31-M31)) -> 8450.505 | X31: =(R31*(H31-N31)) -> 0 | Y31: =(S31*(I31-O31)) -> -16374 | Z31: =T31*(F31-L31) -> 7514.3295 | AA31: =V31+W31+X31+Y31+Z31 -> 33351.535 | AB31: =+U31+AA31 -> 3302954.9 | AC31: ='AUTO CALCULATION SHEET (2)'!N31 -> 2430 | AD31: ='AUTO CALCULATION SHEET (2)'!Y31 -> 214 | AE31: ='AUTO CALCULATION SHEET (2)'!AC31 -> 564 | AF31: ='AUTO CALCULATION SHEET (2)'!AE31 -> 2438 | AG31: ='AUTO CALCULATION SHEET (2)'!AK31 -> 0 | AH31: ='AUTO CALCULATION SHEET (2)'!AQ31 -> 1449 | AI31: ='AUTO CALCULATION SHEET (2)'!AV31 -> 0 | AJ31: ='AUTO CALCULATION SHEET (2)'!BA31 -> 6874 | AK31: ='AUTO CALCULATION SHEET (2)'!BF31 -> 1655 | AL31: ='AUTO CALCULATION SHEET (2)'!BL31 -> 1525 | AM31: ='AUTO CALCULATION SHEET (2)'!BN31 -> 38 | AN31: ='AUTO CALCULATION SHEET (2)'!BP31 -> 104 | AO31: ='AUTO CALCULATION SHEET (2)'!BT31 -> 72 | AP31: =SUMPRODUCT(AC31:AO31,$AC$17:$AO$17) -> 2379902 | AQ31: ='AUTO CALCULATION SHEET (2)'!BZ31 -> 160000 | AR31: =AP31+AQ31 -> 2539902 | AS31: =AB31-AR31 -> 763052.88 | AT31: =ROUND((AS31/AB31)*100,2) -> 23.1 | AU31: 0 | AV31: 2 | AW31: 1 | AX31: =AT31-AU31-AV31-AW31 -> 20.1
A32: ='AUTO CALCULATION SHEET (2)'!D32 -> 3 CORE X 185 SQ. MM AL/ARM - WIRE (XLPE) - 33 KV | B32: 4 | C32: PROVISIONAL | D32: 45705 | E32: 265753.41 | F32: 870134.53 | G32: 176136 | H32: 160825 | I32: 70250 | J32: =$B$1 -> 45627 | K32: 252941 | L32: 820039 | M32: 173241 | N32: 160825 | O32: 72250 | P32: 1.605 | Q32: 2.513 | R32: 4.166 | S32: 7.356 | T32: 0.134 | U32: ='AUTO CALCULATION SHEET (2)'!E32 -> 2659700.9 | V32: =(P32*(E32-K32)) -> 20563.918 | W32: =(Q32*(G32-M32)) -> 7275.135 | X32: =(R32*(H32-N32)) -> 0 | Y32: =(S32*(I32-O32)) -> -14712 | Z32: =T32*(F32-L32) -> 6712.801 | AA32: =V32+W32+X32+Y32+Z32 -> 19839.854 | AB32: =+U32+AA32 -> 2679540.8 | AC32: ='AUTO CALCULATION SHEET (2)'!N32 -> 1499 | AD32: ='AUTO CALCULATION SHEET (2)'!Y32 -> 191 | AE32: ='AUTO CALCULATION SHEET (2)'!AC32 -> 486 | AF32: ='AUTO CALCULATION SHEET (2)'!AE32 -> 2091 | AG32: ='AUTO CALCULATION SHEET (2)'!AK32 -> 0 | AH32: ='AUTO CALCULATION SHEET (2)'!AQ32 -> 1186 | AI32: ='AUTO CALCULATION SHEET (2)'!AV32 -> 0 | AJ32: ='AUTO CALCULATION SHEET (2)'!BA32 -> 6155 | AK32: ='AUTO CALCULATION SHEET (2)'!BF32 -> 1480 | AL32: ='AUTO CALCULATION SHEET (2)'!BL32 -> 1224 | AM32: ='AUTO CALCULATION SHEET (2)'!BN32 -> 35 | AN32: ='AUTO CALCULATION SHEET (2)'!BP32 -> 90 | AO32: ='AUTO CALCULATION SHEET (2)'!BT32 -> 65 | AP32: =SUMPRODUCT(AC32:AO32,$AC$17:$AO$17) -> 1908393 | AQ32: ='AUTO CALCULATION SHEET (2)'!BZ32 -> 147600 | AR32: =AP32+AQ32 -> 2055993 | AS32: =AB32-AR32 -> 623547.79 | AT32: =ROUND((AS32/AB32)*100,2) -> 23.27 | AU32: 0 | AV32: 2 | AW32: 1 | AX32: =AT32-AU32-AV32-AW32 -> 20.27
A33: ='AUTO CALCULATION SHEET (2)'!D33 -> 3 CORE X 95 SQ. MM. AL/ARM WIRE (XLPE) - 33 KV | B33: 3.15 | C33: PROVISIONAL | D33: 45705 | E33: 265753.41 | F33: 870134.53 | G33: 176136 | H33: 160825 | I33: 70250 | J33: =$B$1 -> 45627 | K33: 252941 | L33: 820039 | M33: 173241 | N33: 160825 | O33: 72250 | P33: 0.821 | Q33: 2.071 | R33: 3.367 | S33: 5.437 | T33: 0.117 | U33: ='AUTO CALCULATION SHEET (2)'!E33 -> 1960522.9 | V33: =(P33*(E33-K33)) -> 10518.989 | W33: =(Q33*(G33-M33)) -> 5995.545 | X33: =(R33*(H33-N33)) -> 0 | Y33: =(S33*(I33-O33)) -> -10874 | Z33: =T33*(F33-L33) -> 5861.177 | AA33: =V33+W33+X33+Y33+Z33 -> 11501.711 | AB33: =+U33+AA33 -> 1972024.6 | AC33: ='AUTO CALCULATION SHEET (2)'!N33 -> 770 | AD33: ='AUTO CALCULATION SHEET (2)'!Y33 -> 167 | AE33: ='AUTO CALCULATION SHEET (2)'!AC33 -> 403 | AF33: ='AUTO CALCULATION SHEET (2)'!AE33 -> 1724 | AG33: ='AUTO CALCULATION SHEET (2)'!AK33 -> 0 | AH33: ='AUTO CALCULATION SHEET (2)'!AQ33 -> 950 | AI33: ='AUTO CALCULATION SHEET (2)'!AV33 -> 0 | AJ33: ='AUTO CALCULATION SHEET (2)'!BA33 -> 4262 | AK33: ='AUTO CALCULATION SHEET (2)'!BF33 -> 1296 | AL33: ='AUTO CALCULATION SHEET (2)'!BL33 -> 940 | AM33: ='AUTO CALCULATION SHEET (2)'!BN33 -> 15 | AN33: ='AUTO CALCULATION SHEET (2)'!BP33 -> 75 | AO33: ='AUTO CALCULATION SHEET (2)'!BT33 -> 57 | AP33: =SUMPRODUCT(AC33:AO33,$AC$17:$AO$17) -> 1386474 | AQ33: ='AUTO CALCULATION SHEET (2)'!BZ33 -> 128000 | AR33: =AP33+AQ33 -> 1514474 | AS33: =AB33-AR33 -> 457550.58 | AT33: =ROUND((AS33/AB33)*100,2) -> 23.2 | AU33: 0 | AV33: 2 | AW33: 1 | AX33: =AT33-AU33-AV33-AW33 -> 20.2
A34: ='AUTO CALCULATION SHEET (2)'!D34 -> 3 CORE X 70 SQ. MM. AL/ARM - WIRE (XLPE) - 33 KV | B34: 3.15 | C34: PROVISIONAL | D34: 45705 | E34: 265753.41 | F34: 870134.53 | G34: 176136 | H34: 160825 | I34: 70250 | J34: =$B$1 -> 45627 | K34: 252941 | L34: 820039 | M34: 173241 | N34: 160825 | O34: 72250 | P34: 0.593 | Q34: 1.916 | R34: 3.219 | S34: 4.809 | T34: 0.111 | U34: ='AUTO CALCULATION SHEET (2)'!E34 -> 1826652.2 | V34: =(P34*(E34-K34)) -> 7597.7591 | W34: =(Q34*(G34-M34)) -> 5546.82 | X34: =(R34*(H34-N34)) -> 0 | Y34: =(S34*(I34-O34)) -> -9618 | Z34: =T34*(F34-L34) -> 5560.6038 | AA34: =V34+W34+X34+Y34+Z34 -> 9087.183 | AB34: =+U34+AA34 -> 1835739.4 | AC34: ='AUTO CALCULATION SHEET (2)'!N34 -> 567 | AD34: ='AUTO CALCULATION SHEET (2)'!Y34 -> 161 | AE34: ='AUTO CALCULATION SHEET (2)'!AC34 -> 378 | AF34: ='AUTO CALCULATION SHEET (2)'!AE34 -> 1615 | AG34: ='AUTO CALCULATION SHEET (2)'!AK34 -> 0 | AH34: ='AUTO CALCULATION SHEET (2)'!AQ34 -> 885 | AI34: ='AUTO CALCULATION SHEET (2)'!AV34 -> 0 | AJ34: ='AUTO CALCULATION SHEET (2)'!BA34 -> 4072 | AK34: ='AUTO CALCULATION SHEET (2)'!BF34 -> 1190 | AL34: ='AUTO CALCULATION SHEET (2)'!BL34 -> 862 | AM34: ='AUTO CALCULATION SHEET (2)'!BN34 -> 15 | AN34: ='AUTO CALCULATION SHEET (2)'!BP34 -> 71 | AO34: ='AUTO CALCULATION SHEET (2)'!BT34 -> 54 | AP34: =SUMPRODUCT(AC34:AO34,$AC$17:$AO$17) -> 1264375 | AQ34: ='AUTO CALCULATION SHEET (2)'!BZ34 -> 144000 | AR34: =AP34+AQ34 -> 1408375 | AS34: =AB34-AR34 -> 427364.39 | AT34: =ROUND((AS34/AB34)*100,2) -> 23.28 | AU34: 0 | AV34: 2 | AW34: 1 | AX34: =AT34-AU34-AV34-AW34 -> 20.28
A35: ='AUTO CALCULATION SHEET (2)'!D35 -> 3 CORE X 50 SQ. MM. AL/ARD - WIRE (XLPE) - 33 KV (E) | B35: 3.15 | C35: PROVISIONAL | D35: 45705 | E35: 265753.41 | F35: 870134.53 | G35: 176136 | H35: 160825 | I35: 70250 | J35: =$B$1 -> 45627 | K35: 252941 | L35: 820039 | M35: 173241 | N35: 160825 | O35: 72250 | P35: 0.41 | Q35: 1.751 | R35: 2.864 | S35: 4.569 | T35: 0.104 | U35: ='AUTO CALCULATION SHEET (2)'!E35 -> 1591041.8 | V35: =(P35*(E35-K35)) -> 5253.0881 | W35: =(Q35*(G35-M35)) -> 5069.145 | X35: =(R35*(H35-N35)) -> 0 | Y35: =(S35*(I35-O35)) -> -9138 | Z35: =T35*(F35-L35) -> 5209.9351 | AA35: =V35+W35+X35+Y35+Z35 -> 6394.1682 | AB35: =+U35+AA35 -> 1597436 | AC35: ='AUTO CALCULATION SHEET (2)'!N35 -> 405 | AD35: ='AUTO CALCULATION SHEET (2)'!Y35 -> 153 | AE35: ='AUTO CALCULATION SHEET (2)'!AC35 -> 350 | AF35: ='AUTO CALCULATION SHEET (2)'!AE35 -> 1490 | AG35: ='AUTO CALCULATION SHEET (2)'!AK35 -> 0 | AH35: ='AUTO CALCULATION SHEET (2)'!AQ35 -> 798 | AI35: ='AUTO CALCULATION SHEET (2)'!AV35 -> 0 | AJ35: ='AUTO CALCULATION SHEET (2)'!BA35 -> 3881 | AK35: ='AUTO CALCULATION SHEET (2)'!BF35 -> 1080 | AL35: ='AUTO CALCULATION SHEET (2)'!BL35 -> 778 | AM35: ='AUTO CALCULATION SHEET (2)'!BN35 -> 10 | AN35: ='AUTO CALCULATION SHEET (2)'!BP35 -> 66 | AO35: ='AUTO CALCULATION SHEET (2)'!BT35 -> 52 | AP35: =SUMPRODUCT(AC35:AO35,$AC$17:$AO$17) -> 1144290 | AQ35: ='AUTO CALCULATION SHEET (2)'!BZ35 -> 80000 | AR35: =AP35+AQ35 -> 1224290 | AS35: =AB35-AR35 -> 373145.97 | AT35: =ROUND((AS35/AB35)*100,2) -> 23.36 | AU35: 0 | AV35: 2 | AW35: 1 | AX35: =AT35-AU35-AV35-AW35 -> 20.36
A36: ='AUTO CALCULATION SHEET (2)'!D36 -> 3 CORE X 35 SQ. MM. AL/ARM - WIRE (XLPE) - 33 KV (E) | B36: 3.15 | C36: PROVISIONAL | D36: 45705 | E36: 265753.41 | F36: 870134.53 | G36: 176136 | H36: 160825 | I36: 70250 | J36: =$B$1 -> 45627 | K36: 252941 | L36: 820039 | M36: 173241 | N36: 160825 | O36: 72250 | P36: 0.302 | Q36: 1.638 | R36: 2.864 | S36: 2.517 | T36: 0.104 | U36: ='AUTO CALCULATION SHEET (2)'!E36 -> 1591041.8 | V36: =(P36*(E36-K36)) -> 3869.3478 | W36: =(Q36*(G36-M36)) -> 4742.01 | X36: =(R36*(H36-N36)) -> 0 | Y36: =(S36*(I36-O36)) -> -5034 | Z36: =T36*(F36-L36) -> 5209.9351 | AA36: =V36+W36+X36+Y36+Z36 -> 8787.2929 | AB36: =+U36+AA36 -> 1599829.1 | AC36: ='AUTO CALCULATION SHEET (2)'!N36 -> 405 | AD36: ='AUTO CALCULATION SHEET (2)'!Y36 -> 153 | AE36: ='AUTO CALCULATION SHEET (2)'!AC36 -> 350 | AF36: ='AUTO CALCULATION SHEET (2)'!AE36 -> 1490 | AG36: ='AUTO CALCULATION SHEET (2)'!AK36 -> 0 | AH36: ='AUTO CALCULATION SHEET (2)'!AQ36 -> 798 | AI36: ='AUTO CALCULATION SHEET (2)'!AV36 -> 0 | AJ36: ='AUTO CALCULATION SHEET (2)'!BA36 -> 3881 | AK36: ='AUTO CALCULATION SHEET (2)'!BF36 -> 1080 | AL36: ='AUTO CALCULATION SHEET (2)'!BL36 -> 778 | AM36: ='AUTO CALCULATION SHEET (2)'!BN36 -> 10 | AN36: ='AUTO CALCULATION SHEET (2)'!BP36 -> 66 | AO36: ='AUTO CALCULATION SHEET (2)'!BT36 -> 52 | AP36: =SUMPRODUCT(AC36:AO36,$AC$17:$AO$17) -> 1144290 | AQ36: ='AUTO CALCULATION SHEET (2)'!BZ36 -> 80000 | AR36: =AP36+AQ36 -> 1224290 | AS36: =AB36-AR36 -> 375539.1 | AT36: =ROUND((AS36/AB36)*100,2) -> 23.47 | AU36: 0 | AV36: 2 | AW36: 1 | AX36: =AT36-AU36-AV36-AW36 -> 20.47
A37: ='AUTO CALCULATION SHEET (2)'!D37 -> 1 CORE X 630 SQ. MM. AL/ARM (XLPE) - 33 KV | B37: 2.5 | C37: PROVISIONAL | D37: 45705 | E37: 265753.41 | F37: 870134.53 | G37: 176136 | H37: 160825 | J37: =$B$1 -> 45627 | K37: 252941 | L37: 820039 | M37: 173241 | N37: 160825 | P37: 2.978 | Q37: 1.265 | R37: 1.168 | T37: 0.063 | U37: ='AUTO CALCULATION SHEET (2)'!E37 -> 1439768.9 | V37: =(P37*(E37-K37)) -> 38155.357 | W37: =(Q37*(G37-M37)) -> 3662.175 | X37: =(R37*(H37-N37)) -> 0 | Y37: =(S37*(I37-O37)) -> 0 | Z37: =T37*(F37-L37) -> 3156.0184 | AA37: =V37+W37+X37+Y37+Z37 -> 44973.55 | AB37: =+U37+AA37 -> 1484742.5 | AC37: ='AUTO CALCULATION SHEET (2)'!N37 -> 1701 | AD37: ='AUTO CALCULATION SHEET (2)'!Y37 -> 87 | AE37: ='AUTO CALCULATION SHEET (2)'!AC37 -> 243 | AF37: ='AUTO CALCULATION SHEET (2)'!AE37 -> 1056 | AG37: ='AUTO CALCULATION SHEET (2)'!AK37 -> 36 | AH37: ='AUTO CALCULATION SHEET (2)'!AQ37 -> 203 | AI37: ='AUTO CALCULATION SHEET (2)'!AV37 -> 842 | AJ37: ='AUTO CALCULATION SHEET (2)'!BA37 -> 0 | AK37: ='AUTO CALCULATION SHEET (2)'!BF37 -> 769 | AL37: ='AUTO CALCULATION SHEET (2)'!BL37 -> 0 | AM37: ='AUTO CALCULATION SHEET (2)'!BN37 -> 26 | AN37: ='AUTO CALCULATION SHEET (2)'!BP37 -> 46 | AO37: ='AUTO CALCULATION SHEET (2)'!BT37 -> 42 | AP37: =SUMPRODUCT(AC37:AO37,$AC$17:$AO$17) -> 1122785 | AQ37: ='AUTO CALCULATION SHEET (2)'!BZ37 -> 40000 | AR37: =AP37+AQ37 -> 1162785 | AS37: =AB37-AR37 -> 321957.49 | AT37: =ROUND((AS37/AB37)*100,2) -> 21.68 | AU37: 0 | AV37: 2 | AW37: 1 | AX37: =AT37-AU37-AV37-AW37 -> 18.68
A38: ='AUTO CALCULATION SHEET (2)'!D38 -> 1 CORE X 400 SQ. MM. AL/ARM (XLPE) - 33 KV | B38: 2.5 | C38: PROVISIONAL | D38: 45705 | E38: 265753.41 | F38: 870134.53 | G38: 176136 | H38: 160825 | J38: =$B$1 -> 45627 | K38: 252941 | L38: 820039 | M38: 173241 | N38: 160825 | P38: 2.046 | Q38: 1.041 | R38: 0.866 | T38: 0.054 | U38: ='AUTO CALCULATION SHEET (2)'!E38 -> 1096461.9 | V38: =(P38*(E38-K38)) -> 26214.191 | W38: =(Q38*(G38-M38)) -> 3013.695 | X38: =(R38*(H38-N38)) -> 0 | Y38: =(S38*(I38-O38)) -> 0 | Z38: =T38*(F38-L38) -> 2705.1586 | AA38: =V38+W38+X38+Y38+Z38 -> 31933.044 | AB38: =+U38+AA38 -> 1128394.9 | AC38: ='AUTO CALCULATION SHEET (2)'!N38 -> 1080 | AD38: ='AUTO CALCULATION SHEET (2)'!Y38 -> 76 | AE38: ='AUTO CALCULATION SHEET (2)'!AC38 -> 206 | AF38: ='AUTO CALCULATION SHEET (2)'!AE38 -> 890 | AG38: ='AUTO CALCULATION SHEET (2)'!AK38 -> 32 | AH38: ='AUTO CALCULATION SHEET (2)'!AQ38 -> 156 | AI38: ='AUTO CALCULATION SHEET (2)'!AV38 -> 731 | AJ38: ='AUTO CALCULATION SHEET (2)'!BA38 -> 0 | AK38: ='AUTO CALCULATION SHEET (2)'!BF38 -> 604 | AL38: ='AUTO CALCULATION SHEET (2)'!BL38 -> 0 | AM38: ='AUTO CALCULATION SHEET (2)'!BN38 -> 19 | AN38: ='AUTO CALCULATION SHEET (2)'!BP38 -> 38 | AO38: ='AUTO CALCULATION SHEET (2)'!BT38 -> 37 | AP38: =SUMPRODUCT(AC38:AO38,$AC$17:$AO$17) -> 852815 | AQ38: ='AUTO CALCULATION SHEET (2)'!BZ38 -> 32000 | AR38: =AP38+AQ38 -> 884815 | AS38: =AB38-AR38 -> 243579.95 | AT38: =ROUND((AS38/AB38)*100,2) -> 21.59 | AU38: 0 | AV38: 2 | AW38: 1 | AX38: =AT38-AU38-AV38-AW38 -> 18.59
A39: ='AUTO CALCULATION SHEET (2)'!D39 -> 1 CORE X 300 SQ. MM. AL/ARM (XLPE) - 33 KV | B39: 2.5 | C39: PROVISIONAL | D39: 45705 | E39: 265753.41 | F39: 870134.53 | G39: 176136 | H39: 160825 | J39: =$B$1 -> 45627 | K39: 252941 | L39: 820039 | M39: 173241 | N39: 160825 | P39: 1.753 | Q39: 0.943 | R39: 0.811 | T39: 0.05 | U39: ='AUTO CALCULATION SHEET (2)'!E39 -> 956871.83 | V39: =(P39*(E39-K39)) -> 22460.155 | W39: =(Q39*(G39-M39)) -> 2729.985 | X39: =(R39*(H39-N39)) -> 0 | Y39: =(S39*(I39-O39)) -> 0 | Z39: =T39*(F39-L39) -> 2504.7765 | AA39: =V39+W39+X39+Y39+Z39 -> 27694.916 | AB39: =+U39+AA39 -> 984566.75 | AC39: ='AUTO CALCULATION SHEET (2)'!N39 -> 810 | AD39: ='AUTO CALCULATION SHEET (2)'!Y39 -> 71 | AE39: ='AUTO CALCULATION SHEET (2)'!AC39 -> 187 | AF39: ='AUTO CALCULATION SHEET (2)'!AE39 -> 810 | AG39: ='AUTO CALCULATION SHEET (2)'!AK39 -> 30 | AH39: ='AUTO CALCULATION SHEET (2)'!AQ39 -> 146 | AI39: ='AUTO CALCULATION SHEET (2)'!AV39 -> 690 | AJ39: ='AUTO CALCULATION SHEET (2)'!BA39 -> 0 | AK39: ='AUTO CALCULATION SHEET (2)'!BF39 -> 570 | AL39: ='AUTO CALCULATION SHEET (2)'!BL39 -> 0 | AM39: ='AUTO CALCULATION SHEET (2)'!BN39 -> 13 | AN39: ='AUTO CALCULATION SHEET (2)'!BP39 -> 35 | AO39: ='AUTO CALCULATION SHEET (2)'!BT39 -> 35 | AP39: =SUMPRODUCT(AC39:AO39,$AC$17:$AO$17) -> 739292 | AQ39: ='AUTO CALCULATION SHEET (2)'!BZ39 -> 32000 | AR39: =AP39+AQ39 -> 771292 | AS39: =AB39-AR39 -> 213274.75 | AT39: =ROUND((AS39/AB39)*100,2) -> 21.66 | AU39: 0 | AV39: 2 | AW39: 1 | AX39: =AT39-AU39-AV39-AW39 -> 18.66
