Workbook

Sheet Sheet1
A1: DOCKET NO. | B1: Base Date | C1: ITEM CODE | D1: PROPOSE ERP ITEM NAME | E1: PROPOSE DRUM TYPE | F1: Insulation Screening (Metallic) | G1: RM RATE (Insulation Screening (Metallic)) | H1: Weight (Insulation Screening (Metallic)) | I1: COST(Insulation Screening (Metallic)) | J1: Conductor | K1: RM RATE(Conductor) | L1: WEIGHT(Conductor) | M1: COST(Conductor) | N1: AL ALLOY | O1: RM RATE(Alu Alloy) | P1: WEIGHT(Alu Alloy) | Q1: COST(Alu Alloy) | R1: Insulation Screening (Non-Metallic) | S1: RM RATE(Insulation Screening (Non-Metallic)) | T1: WEIGHT(Insulation Screening (Non-Metallic)) | U1: COST(Insulation Screening (Non-Metallic)) | V1: Insulation | W1: RM RATE(Insulation) | X1: WEIGHT(Insulation) | Y1: COST(Insulation) | Z1: POLY TAPE | AA1: RM RATE (Poly Tape) | AB1: WEIGHT (Poly Tape) | AC1: COST(Poly Tape) | AD1: Inner Sheath | AE1: RM RATE(Inner Sheath) | AF1: WEIGHT(Inner Sheath) | AG1: COST(Inner Sheath) | AH1: Armouring | AI1: RM RATE(Armouring) | AJ1: WEIGHT(Armouring) | AK1: COST(Armouring) | AL1: Outer Sheath | AM1: RM RATE(Outer Sheath) | AN1: WEIGHT(Outer Sheath) | AO1: COST(Outer Sheath) | AP1: FILLER | AQ1: RM RATE(Filler) | AR1: WEIGHT(Filler) | AS1: COST(Filler) | AT1: GREASE | AU1: RM RATE(Grease) | AV1: WEIGHT(Grease) | AW1: COST(Grease) | AX1: Water swellable Tape | AY1: RM RATE(Water swellable Tape) | AZ1: WEIGHT(Water swellable Tape) | BA1: COST(Water swellable Tape) | BB1: Semi conducting Water Swellable tape | BC1: RM RATE(Semi conducting Water Swellable tape) | BD1: WEIGHT(Semi conducting Water Swellable tape) | BE1: COST(Semi conducting Water Swellable tape) | BF1: SEMICON TAPE | BG1: RM RATE(SEMICON TAPE) | BH1: WEIGHT(SEMICON TAPE) | BI1: COST(SEMICON TAPE) | BJ1: GLASS FIBER TAPE | BK1: RM RATE(GLASS FIBER TAPE) | BL1: WEIGHT(GLASS FIBER TAPE) | BM1: COST(GLASS FIBER TAPE) | BN1: COPPER WIRE 0.8 MM | BO1: RM RATE(COPPER WIRE 0.8 MM) | BP1: WEIGHT(COPPER WIRE 0.8 MM) | BQ1: COST(COPPER WIRE 0.8 MM) | BR1: RUBBERIZED COTTON TAPE | BS1: RM RATE(RUBBERIZED COTTON TAPE) | BT1: WEIGHT(RUBBERIZED COTTON TAPE) | BU1: COST(RUBBERIZED COTTON TAPE) | BV1: Water Tight Compound | BW1: RM RATE(Water Tight Compound) | BX1: WEIGHT(Water Tight Compound) | BY1: COST(Water Tight Compound) | BZ1: DRUM COST PER KM | CA1: TOTAL RM COST | CB1: FIRM % | CC1: FIRM VALUE | CD1: MFG% | CE1: MFG VALUE | CF1: PROF% | CG1: PROFIT VALUE | CH1: 1ST EX-WORKS | CI1: Intt % | CJ1: INTT VALUE | CK1: insp% | CL1: INSP VALUE | CM1: EX-WORKS (PER KM) | CN1: FREIGHT PER KM | CO1: PRICE INCLUDING FREIGHT (PER KM) | CP1: GST % | CQ1: GST VALUE | CR1: PRICE INCLUDING GST & FREIGHT (PER KM) | CS1: QTY | CT1: Unit | CU1: TOTAL PRICE OF FULL QTY (INCLUDING FRIGHT & GST) | CV1: DRUM CODE | CW1: DRUM SIZE (FxbXtx Ft) | CX1: PARTY STANDARD LENGTH (MTR)
A2: ENQ-11788-22-23 | B2: 45231 | C2: FC6200002 | D2: ACSR : DOG CONDUCTOR - 100 SQ. MM. (6/4.72/7/1.57) | E2: WOOD | J2: Alumimium | K2: 214 | L2: 288.3 | M2: 61696.2 | P2: 0 | T2: 0 | X2: 0 | AB2: 0 | AF2: 0 | AH2: ACSR DOG STEEL WIRE | AI2: 83.36 | AJ2: 106 | AK2: 8836.16 | AN2: 0 | AR2: 0 | AV2: 0 | AZ2: 0 | BD2: 0 | BH2: 0 | BL2: 0 | BP2: 0 | BT2: 0 | BX2: 0 | BZ2: 1463.42 | CA2: 71995.78 | CH2: 71995.78 | CM2: 71995.78 | CN2: 1454.55 | CO2: 73450.33 | CP2: 0.18 | CQ2: 13221.06 | CR2: 86671.38 | CS2: 165 | CT2: KMS | CU2: 14300778 | CV2: MD0100015 | CW2: DRUM - 48 X 20 X 28 X 2.25 - RDSO | CX2: 2500

Sheet AUTO CALCULATION SHEET (3)
A2: KANPUR ELECTRICITY SUPPLY COMPANY LIMITED
A4: TENDER SPECIFICATION NO () | B4: 96/23-24
A5: TENDER DESCRIPTION () | B5: Supply of ACSR Dog Conductor
A6: Last Date & Time of Submission () | B6: 11.12.2023 & 12:00 PM.
A7: REVERSE AUCTION | B7: Not Mention.
A8: Price () | B8: The prices will be variable and as per CACMAI Date 01.11.2023.
A9: Validity () | B9: The bidder’s proposal must remain valid for acceptance for a period of 180 days from the date of opening of bid (Envelope-1) or any other extended date for their receipt or any other extended period consented upon by the bidders. KESCO may ask the bidder to extend the validity period of their bid) and during this period no bidder shall be allowed to withdraw their bid. Any such withdrawal during the said period will entail forfeiture of EMD deposited by the bidder with their bid. The bidders who agree to such extension shall confirm that they maintain the availability of the professional staff nominated in the proposal or in their confirmation of extension of validity of the proposal.
A10: Payment Terms () | B10: Ninety percent of the f.o.r. contract value of the plant in rupees on receipt by the purchaser of the contractor's invoice giving the number and date of railway receipt covering the dispatch of the plant from the Indian port and of the advice note giving case number and contents, together with a certificate by the contractor to the effect that the plant detailed in the said advice note has actually been dispatched under the says railway receipt and that the contract value of the said plant so dispatched is not less than the amount entered in the invoice. Ten percent of the f.o.r. contract value on presentation of the contractor's invoice when each commercially useable section of the plant is completed and the last portion of such section has been dispatched and the whole material has been delivered at the place fixed for delivery and checked at the site of the work within one month of such delivery, whichever is earlier.
A11: Standard length () | B11: The standard length for each type of ACSR Dog Conductor shall be as given below Item Standard length Non standard length ACSR Dog 2.50 KM. 1.00 K.M. (Minimum for Last drum)
A12: Packing () | B12: The conductor shall be supplied on strong non-returnable wooden drum so that it is not damaged during, during transit and can withstand all the transit and weather hazards. The Supplier/manufacturer shall be responsible for any damage in the material during transit due to improper/inadequate packing. The drum shall be painted on the inside and outside with Aluminum paints and fitted with strong cast iron bushings. All drums shall have layer of a water proof paper under the lagging. The conductor drums shall conform to IS: 1778/1980. The drums shall be strapped with steel wire. Each drum shall have the following information marked on it with indelible ink alongwith other essential data.
A13: Technical Specification
N15: =Sheet1!J1 -> Conductor | S15: AL ALLOY | U15: Insulation Screening (Metallic) | AC15: Insulation Screening (Non-Metallic) | AE15: Insulation | AK15: POLY TAPE | AL15: Inner Sheath | AS15: Armouring | BC15: Outer Sheath | BM15: FILLER | BN15: GREASE | BO15: Water swellable Tape | BP15: Semi conducting Water Swellable tape | BQ15: SEMICON TAPE | BR15: GLASS FIBER TAPE | BS15: COPPER WIRE 0.8 MM | BT15: RUBBERIZED COTTON TAPE | BU15: Water Tight Compound | BZ15: DRUM COST PER KM | CA15: TOTAL RM COST | CB15: EXTRA CONSUMPTION | CC15: EXTRA CONSUMPTION VALUE
A16: DOCKET NO. | B16: =Sheet1!B1 -> Base Date | C16: ITEM CODE | D16: PROPOSE ERP ITEM NAME | E16: EX-WORKS (PER KM) | F16: FREIGHT PER KM | G16: PRICE INCLUDING FREIGHT (PER KM) | H16: GST % | I16: GST VALUE | J16: PRICE INCLUDING GST & FREIGHT (PER KM) | K16: QTY | L16: Unit | M16: TOTAL PRICE OF FULL QTY (INCLUDING FRIGHT & GST) | N16: Alumimium | O16: Alumimium ALLOY | P16: Copper | Q16: Flexible Copper | R16: Galvanized steel wire | S16: Alumimium | T16: Alumimium ALLOY | U16: Coper tape - 0.1 mm | V16: Copper Tape - 0.03 mm | W16: Copper Tape - 0.035 mm | X16: Copper Tape - 0.04 mm | Y16: Copper Tape - 0.045 mm | Z16: Copper Tape - 0.050 mm | AA16: Copper Tape - 0.060 mm | AB16: Copper Tape - 0.075 mm(DOUBLE) | AC16: Extruded semiconductive | AD16: Extruded Semiconductive(Stripable) | AE16: HT-XLPE | AF16: LT-XLPE | AG16: TR XLPE | AH16: Type A PVC | AI16: Type C PVC (HR) | AJ16: XLPE | AK16: POLY TAPE | AL16: FR PVC Type ST-1 | AM16: FR PVC Type ST-2 | AN16: FRLSH PVC Type ST-2 | AO16: PVC Type ST-1 | AP16: PVC Type ST-1-PRESSURE EXTRUDED | AQ16: PVC Type ST-2 | AR16: PVC Type ST-2-PRESSURE EXTRUDED | AS16: ACSR CORE WIRE | AT16: ACSR DOG STEEL WIRE | AU16: Aluminium Flat Strip | AV16: Aluminium Round Wire | AW16: Double Steel Tape | AX16: Galvanised Steel Flat Strip | AY16: Galvanised Steel Flat Strip (Double) | AZ16: Galvanised Steel Flat Strip-B | BA16: Galvanised Steel Round Wire | BB16: Galvanised Steel Round Wire (Double) | BC16: FR PVC Type ST-1 | BD16: FR PVC Type ST-2 | BE16: FRLSH PVC Type ST-1 | BF16: FRLSH PVC Type ST-2 | BG16: PE, ST-3 | BH16: PE, ST-7 | BI16: PVC Type ST-1 | BJ16: PVC Type ST-2 | BK16: PVC Type ST-2-PRESSURE EXTRUDED | BL16: UV & Track Resistant XLPE | BM16: FILLER | BN16: Grease | BO16: Water swellable Tape | BP16: Semi conducting Water Swellable tape | BQ16: SEMICON TAPE | BR16: GLASS FIBER TAPE | BS16: COPPER WIRE 0.8 MM | BT16: RUBBERIZED COTTON TAPE | BU16: Water Tight Compound | BV16: =Sheet1!E1 -> PROPOSE DRUM TYPE | BW16: =Sheet1!CV1 -> DRUM CODE | BX16: =Sheet1!CW1 -> DRUM SIZE (FxbXtx Ft) | BY16: =Sheet1!CX1 -> PARTY STANDARD LENGTH (MTR) | CD16: MFG% | CE16: MFG VALUE | CF16: PROF% | CG16: PROFIT VALUE | CH16: 1ST EX-WORKS | CI16: Intt % | CJ16: INTT VALUE | CK16: insp% | CL16: INSP VALUE
N17: 218 | O17: =+IFERROR(VLOOKUP($O$16,Sheet1!J:L,2,0),0) -> 0 | P17: =+IFERROR(VLOOKUP($P$16,Sheet1!J:M,2,0),0) -> 0 | Q17: =+IFERROR(VLOOKUP($Q$16,Sheet1!J:M,2,0),0) -> 0 | R17: =+IFERROR(VLOOKUP($R$16,Sheet1!J:M,2,0),0) -> 0 | S17: =+IFERROR(VLOOKUP($S$16,Sheet1!N:Q,2,0),0) -> 0 | T17: =+IFERROR(VLOOKUP($T$16,Sheet1!N:O,2,0),0) -> 0 | U17: =+IFERROR(VLOOKUP($U$16,Sheet1!F:I,2,0),0) -> 0 | V17: =+IFERROR(VLOOKUP($V$16,Sheet1!F:I,2,0),0) -> 0 | W17: =+IFERROR(VLOOKUP($W$16,Sheet1!F:I,2,0),0) -> 0 | X17: =+IFERROR(VLOOKUP($X$16,Sheet1!F:I,2,0),0) -> 0 | Y17: =+IFERROR(VLOOKUP($Y$16,Sheet1!F:I,2,0),0) -> 0 | Z17: =+IFERROR(VLOOKUP($Z$16,Sheet1!F:I,2,0),0) -> 0 | AA17: =+IFERROR(VLOOKUP($AA$16,Sheet1!F:I,2,0),0) -> 0 | AB17: =+IFERROR(VLOOKUP($AB$16,Sheet1!F:I,2,0),0) -> 0 | AC17: =+IFERROR(VLOOKUP($AC$16,Sheet1!R:U,2,0),0) -> 0 | AD17: =+IFERROR(VLOOKUP($AD$16,Sheet1!R:U,2,0),0) -> 0 | AE17: =+IFERROR(VLOOKUP($AE$16,Sheet1!V:Y,2,0),0) -> 0 | AF17: =+IFERROR(VLOOKUP($AF$16,Sheet1!V:Y,2,0),0) -> 0 | AG17: =+IFERROR(VLOOKUP($AG$16,Sheet1!V:Y,2,0),0) -> 0 | AH17: =+IFERROR(VLOOKUP($AH$16,Sheet1!V:Y,2,0),0) -> 0 | AI17: =+IFERROR(VLOOKUP($AI$16,Sheet1!V:Y,2,0),0) -> 0 | AJ17: =+IFERROR(VLOOKUP($AJ$16,Sheet1!V:Y,2,0),0) -> 0 | AK17: =+IFERROR(VLOOKUP($AK$16,Sheet1!Z2:AA840,2,0),0) -> 0 | AL17: =+IFERROR(VLOOKUP($AL$16,Sheet1!AD2:AG840,2,0),0) -> 0 | AM17: =+IFERROR(VLOOKUP($AM$16,Sheet1!AD2:AG840,2,0),0) -> 0 | AN17: =+IFERROR(VLOOKUP($AN$16,Sheet1!AD2:AG840,2,0),0) -> 0 | AO17: =+IFERROR(VLOOKUP($AO$16,Sheet1!AD2:AG840,2,0),0) -> 0 | AP17: =+IFERROR(VLOOKUP($AP$16,Sheet1!AD2:AG840,2,0),0) -> 0 | AQ17: =+IFERROR(VLOOKUP($AQ$16,Sheet1!AD2:AG840,2,0),0) -> 0 | AR17: =+IFERROR(VLOOKUP($AR$16,Sheet1!AD2:AG840,2,0),0) -> 0 | AS17: =+IFERROR(VLOOKUP($AS$16,Sheet1!AH2:AK840,2,0),0) -> 0 | AT17: 89 | AU17: =+IFERROR(VLOOKUP($AU$16,Sheet1!AH2:AK840,2,0),0) -> 0 | AV17: =+IFERROR(VLOOKUP($AV$16,Sheet1!AH2:AK840,2,0),0) -> 0 | AW17: =+IFERROR(VLOOKUP($AW$16,Sheet1!AH2:AK840,2,0),0) -> 0 | AX17: =+IFERROR(VLOOKUP($AX$16,Sheet1!AH2:AK840,2,0),0) -> 0 | AY17: =+IFERROR(VLOOKUP($AY$16,Sheet1!AH2:AK840,2,0),0) -> 0 | AZ17: =+IFERROR(VLOOKUP($AZ$16,Sheet1!AH2:AK840,2,0),0) -> 0 | BA17: =+IFERROR(VLOOKUP($BA$16,Sheet1!AH2:AK840,2,0),0) -> 0 | BB17: =+IFERROR(VLOOKUP($BB$16,Sheet1!AH2:AK840,2,0),0) -> 0 | BC17: =+IFERROR(VLOOKUP($BC$16,Sheet1!AL2:AO840,2,0),0) -> 0 | BD17: =+IFERROR(VLOOKUP($BD$16,Sheet1!AL2:AO840,2,0),0) -> 0 | BE17: =+IFERROR(VLOOKUP($BE$16,Sheet1!AL2:AO840,2,0),0) -> 0 | BF17: =+IFERROR(VLOOKUP($BF$16,Sheet1!AL2:AO840,2,0),0) -> 0 | BG17: =+IFERROR(VLOOKUP($BG$16,Sheet1!AL2:AO840,2,0),0) -> 0 | BH17: =+IFERROR(VLOOKUP($BH$16,Sheet1!AL2:AO840,2,0),0) -> 0 | BI17: =+IFERROR(VLOOKUP($BI$16,Sheet1!AL2:AO840,2,0),0) -> 0 | BJ17: =+IFERROR(VLOOKUP($BJ$16,Sheet1!AL2:AO840,2,0),0) -> 0 | BK17: =+IFERROR(VLOOKUP($BK$16,Sheet1!AL2:AO840,2,0),0) -> 0 | BL17: =+IFERROR(VLOOKUP($BL$16,Sheet1!AL2:AO840,2,0),0) -> 0 | BM17: =+IFERROR(VLOOKUP($BM$16,Sheet1!AP2:AS840,2,0),0) -> 0 | BN17: =+IFERROR(VLOOKUP($BN$16,Sheet1!AT2:AW840,2,0),0) -> 0 | BO17: =+IFERROR(VLOOKUP($BO$16,Sheet1!AX2:BA840,2,0),0) -> 0 | BP17: =+IFERROR(VLOOKUP($BP$16,Sheet1!BB2:BE840,2,0),0) -> 0 | BQ17: =+IFERROR(VLOOKUP($BQ$16,Sheet1!BF2:BI840,2,0),0) -> 0 | BR17: =+IFERROR(VLOOKUP($BR$16,Sheet1!BJ2:BM840,2,0),0) -> 0 | BS17: =+IFERROR(VLOOKUP($BS$16,Sheet1!BN2:BQ840,2,0),0) -> 0 | BT17: =+IFERROR(VLOOKUP($BT$16,Sheet1!BR2:BU840,2,0),0) -> 0 | BU17: =+IFERROR(VLOOKUP($BU$16,Sheet1!BV2:BY840,2,0),0) -> 0
A18: =Sheet1!A2 -> ENQ-11788-22-23 | B18: =Sheet1!B2 -> 45231 | C18: =Sheet1!C2 -> FC6200002 | D18: =Sheet1!D2 -> ACSR : DOG CONDUCTOR - 100 SQ. MM. (6/4.72/7/1.57) | E18: =CH18+CJ18+CL18 -> 88424.107 | F18: =ROUNDUP(M21,0) -> 1470 | G18: =E18+F18 -> 89894.107 | H18: =Sheet1!CP2 -> 0.18 | I18: =G18*H18 -> 16180.939 | J18: =G18+I18 -> 106075.05 | K18: 100 | L18: =Sheet1!CT2 -> KMS | M18: =J18*K18 -> 10607505 | N18: 289 | O18: =+IFERROR(VLOOKUP($O$16,Sheet1!J2:L2,3,0),0) -> 0 | P18: =+IFERROR(VLOOKUP($P$16,Sheet1!J2:M2,3,0),0) -> 0 | Q18: =+IFERROR(VLOOKUP($Q$16,Sheet1!J2:M2,3,0),0) -> 0 | R18: =+IFERROR(VLOOKUP($R$16,Sheet1!J2:M2,3,0),0) -> 0 | S18: =+IFERROR(VLOOKUP($S$16,Sheet1!N2:Q2,3,0),0) -> 0 | T18: =+IFERROR(VLOOKUP($T$16,Sheet1!N2:Q2,3,0),0) -> 0 | U18: =+IFERROR(VLOOKUP($U$16,Sheet1!F2:I2,3,0),0) -> 0 | V18: =+IFERROR(VLOOKUP($V$16,Sheet1!F2:I2,3,0),0) -> 0 | W18: =+IFERROR(VLOOKUP($W$16,Sheet1!F2:I2,3,0),0) -> 0 | X18: =+IFERROR(VLOOKUP($X$16,Sheet1!F2:I2,3,0),0) -> 0 | Y18: =+IFERROR(VLOOKUP($Y$16,Sheet1!F2:I2,3,0),0) -> 0 | Z18: =+IFERROR(VLOOKUP($Z$16,Sheet1!F2:I2,3,0),0) -> 0 | AA18: =+IFERROR(VLOOKUP($AA$16,Sheet1!F2:I2,3,0),0) -> 0 | AB18: =+IFERROR(VLOOKUP($AB$16,Sheet1!F2:I2,3,0),0) -> 0 | AC18: =+IFERROR(VLOOKUP($AC$16,Sheet1!R2:U2,3,0),0) -> 0 | AD18: =+IFERROR(VLOOKUP($AD$16,Sheet1!R2:U2,2,0),0) -> 0 | AE18: =+IFERROR(VLOOKUP($AE$16,Sheet1!V2:Y2,3,0),0) -> 0 | AF18: =+IFERROR(VLOOKUP($AF$16,Sheet1!V2:Y2,3,0),0) -> 0 | AG18: =+IFERROR(VLOOKUP($AG$16,Sheet1!V2:Y2,3,0),0) -> 0 | AH18: =+IFERROR(VLOOKUP($AH$16,Sheet1!V2:Y2,3,0),0) -> 0 | AI18: =+IFERROR(VLOOKUP($AI$16,Sheet1!V2:Y2,3,0),0) -> 0 | AJ18: =+IFERROR(VLOOKUP($AJ$16,Sheet1!V2:Y2,3,0),0) -> 0 | AK18: =+IFERROR(VLOOKUP($AK$16,Sheet1!Z2:AB2,3,0),0) -> 0 | AL18: =+IFERROR(VLOOKUP($AL$16,Sheet1!AD2:AG2,3,0),0) -> 0 | AM18: =+IFERROR(VLOOKUP($AM$16,Sheet1!AD2:AG2,3,0),0) -> 0 | AN18: =+IFERROR(VLOOKUP($AN$16,Sheet1!AD2:AG2,3,0),0) -> 0 | AO18: =+IFERROR(VLOOKUP($AO$16,Sheet1!AD2:AG2,3,0),0) -> 0 | AP18: =+IFERROR(VLOOKUP($AP$16,Sheet1!AD2:AG2,3,0),0) -> 0 | AQ18: =+IFERROR(VLOOKUP($AQ$16,Sheet1!AD2:AG2,3,0),0) -> 0 | AR18: =+IFERROR(VLOOKUP($AR$16,Sheet1!AD2:AG2,3,0),0) -> 0 | AS18: =+IFERROR(VLOOKUP($AS$16,Sheet1!AH2:AK2,3,0),0) -> 0 | AT18: =+IFERROR(VLOOKUP($AT$16,Sheet1!AH2:AK2,3,0),0) -> 106 | AU18: =+IFERROR(VLOOKUP($AU$16,Sheet1!AH2:AK2,3,0),0) -> 0 | AV18: =+IFERROR(VLOOKUP($AV$16,Sheet1!AH2:AK2,3,0),0) -> 0 | AW18: =+IFERROR(VLOOKUP($AW$16,Sheet1!AH2:AK2,3,0),0) -> 0 | AX18: =+IFERROR(VLOOKUP($AX$16,Sheet1!AH2:AK2,3,0),0) -> 0 | AY18: =+IFERROR(VLOOKUP($AY$16,Sheet1!AH2:AK2,3,0),0) -> 0 | AZ18: =+IFERROR(VLOOKUP($AZ$16,Sheet1!AH2:AK2,3,0),0) -> 0 | BA18: =+IFERROR(VLOOKUP($BA$16,Sheet1!AH2:AK2,3,0),0) -> 0 | BB18: =+IFERROR(VLOOKUP($BB$16,Sheet1!AH2:AK2,3,0),0) -> 0 | BC18: =+IFERROR(VLOOKUP($BC$16,Sheet1!AL2:AO2,3,0),0) -> 0 | BD18: =+IFERROR(VLOOKUP($BD$16,Sheet1!AL2:AO2,3,0),0) -> 0 | BE18: =+IFERROR(VLOOKUP($BE$16,Sheet1!AL2:AO2,3,0),0) -> 0 | BF18: =+IFERROR(VLOOKUP($BF$16,Sheet1!AL2:AO2,3,0),0) -> 0 | BG18: =+IFERROR(VLOOKUP($BG$16,Sheet1!AL2:AO2,3,0),0) -> 0 | BH18: =+IFERROR(VLOOKUP($BH$16,Sheet1!AL2:AO2,3,0),0) -> 0 | BI18: =+IFERROR(VLOOKUP($BI$16,Sheet1!AL2:AO2,3,0),0) -> 0 | BJ18: =+IFERROR(VLOOKUP($BJ$16,Sheet1!AL2:AO2,3,0),0) -> 0 | BK18: =+IFERROR(VLOOKUP($BK$16,Sheet1!AL2:AO2,3,0),0) -> 0 | BL18: =+IFERROR(VLOOKUP($BL$16,Sheet1!AL2:AO2,3,0),0) -> 0 | BM18: =+IFERROR(VLOOKUP($BM$16,Sheet1!AP2:AS2,3,0),0) -> 0 | BN18: =+IFERROR(VLOOKUP($BN$16,Sheet1!AT2:AW2,3,0),0) -> 0 | BO18: =+IFERROR(VLOOKUP($BO$16,Sheet1!AX2:BA2,3,0),0) -> 0 | BP18: =+IFERROR(VLOOKUP($BP$16,Sheet1!BB2:BE2,3,0),0) -> 0 | BQ18: =+IFERROR(VLOOKUP($BQ$16,Sheet1!BF2:BI2,3,0),0) -> 0 | BR18: =+IFERROR(VLOOKUP($BR$16,Sheet1!BJ2:BM2,3,0),0) -> 0 | BS18: =+IFERROR(VLOOKUP($BS$16,Sheet1!BN2:BQ2,3,0),0) -> 0 | BT18: =+IFERROR(VLOOKUP($BT$16,Sheet1!BR2:BU2,3,0),0) -> 0 | BU18: =+IFERROR(VLOOKUP($BU$16,Sheet1!BV2:BY2,3,0),0) -> 0 | BV18: =Sheet1!E2 -> WOOD | BW18: MD0100013 | BX18: 1220 X 600 X 710 | BY18: =Sheet1!CX2 -> 2500 | BZ18: =3743/2.5 -> 1497.2 | CA18: =SUMPRODUCT($N$17:$BU$17,N18:BU18)+BZ18 -> 73933.2 | CB18: =Sheet1!CB2 -> 0 | CC18: =CA18*CB18 -> 0 | CD18: 0.15 | CE18: =CA18*CD18 -> 11089.98 | CF18: 0 | CG18: =CA18*CF18 -> 0 | CH18: =CA18+CC18+CE18+CG18 -> 85023.18 | CI18: 0.02 | CJ18: =CH18*CI18 -> 1700.4636 | CK18: 0.02 | CL18: =CH18*CK18 -> 1700.4636
E20: Order Quantity | F20: Stnd Length | G20: Truck type | H20: Fare of one truck | I20: No of Drum in one truck | J20: Total length in one Truck | K20: No of Truck | L20: Total Freight | M20: Freight per KM
E21: =K18 -> 100 | F21: 2.5 | G21: 16 MT | H21: 49000 | I21: 14 | J21: =F21*I21 -> 35 | K21: =ROUNDUP((E21/J21),0) -> 3 | L21: =M21*E21 -> 147000 | M21: =(H21*K21)/E21 -> 1470

Sheet CONDUCTOR
A1: Base Date | B1: 01.11.2023
A2: PV Terms | B2: The prices will be variable and as per CACMAI Based dated 01.11.2023
A3: PV FORMULA
A4: P=Po + W (Al - Alo) + Fe (fe-feo)
A7: W | B7: Aluminium Conductor factor
A8: Fe | B8: galvanized steel wire factor
A9: Item | B9: Ex-Work
A10: ='AUTO CALCULATION SHEET (3)'!D18 -> ACSR : DOG CONDUCTOR - 100 SQ. MM. (6/4.72/7/1.57) | B10: ='AUTO CALCULATION SHEET (3)'!E18 -> 88424.107
A13: Item | B13: Calculation part | C13: Date of Inspection | D13: Applicable Date | G13: BASE DATE | J13: FACTORS | L13: Ex-Work Po | M13: PVC of Al | N13: PVC of Fe | O13: PVC per KM | P13: Billing Price/PKM | Q13: VALUE ADDITION CALCULATION
D14: Date | E14: Al | F14: fe | G14: Date | H14: Alo | I14: feo
J15: W | K15: Fe | Q15: ='AUTO CALCULATION SHEET (3)'!N16 -> Alumimium | R15: ='AUTO CALCULATION SHEET (3)'!AT16 -> ACSR DOG STEEL WIRE | S15: RMC | T15: Drum | U15: RMC+DRUM | V15: VA | W15: Groos VA% | X15: Mfg % | Y15: Int % | Z15: Ins% | AA15: Net VA
Q16: 210 | R16: 84
A17: =A10 -> ACSR : DOG CONDUCTOR - 100 SQ. MM. (6/4.72/7/1.57) | C17: PROVISIONAL | D17: 45267 | E17: 244763 | F17: 165500 | G17: =$B$1 -> 01.11.2023 | H17: 253250 | I17: 165500 | J17: 0.288 | K17: 0.106 | L17: =B10 -> 88424.107 | M17: =J17*(E17-H17) -> -2444.256 | N17: =K17*(F17-I17) -> 0 | O17: =M17+N17 -> -2444.256 | P17: =L17+O17 -> 85979.851 | Q17: ='AUTO CALCULATION SHEET (3)'!N18 -> 289 | R17: ='AUTO CALCULATION SHEET (3)'!AT18 -> 106 | S17: =SUMPRODUCT(Q17:R17,$Q$16:$R$16) -> 69594 | T17: ='AUTO CALCULATION SHEET (3)'!BZ18 -> 1497.2 | U17: =S17+T17 -> 71091.2 | V17: =+P17-U17 -> 14888.651 | W17: =V17/U17*100% -> 0.2094303 | Y17: 0.02 | Z17: 0.02 | AA17: =W17-SUM(X17:Z17) -> 0.1694303
