Workbook

Sheet Sheet1
A1: DOCKET NO. | B1: Base Date | C1: ITEM CODE | D1: PROPOSE ERP ITEM NAME | E1: PROPOSE DRUM TYPE | F1: Insulation Screening (Metallic) | G1: RM RATE (Insulation Screening (Metallic)) | H1: Weight (Insulation Screening (Metallic)) | I1: COST(Insulation Screening (Metallic)) | J1: Conductor | K1: RM RATE(Conductor) | L1: WEIGHT(Conductor) | M1: COST(Conductor) | N1: AL ALLOY | O1: RM RATE(Alu Alloy) | P1: WEIGHT(Alu Alloy) | Q1: COST(Alu Alloy) | R1: Insulation Screening (Non-Metallic) | S1: RM RATE(Insulation Screening (Non-Metallic)) | T1: WEIGHT(Insulation Screening (Non-Metallic)) | U1: COST(Insulation Screening (Non-Metallic)) | V1: Insulation | W1: RM RATE(Insulation) | X1: WEIGHT(Insulation) | Y1: COST(Insulation) | Z1: POLY TAPE | AA1: RM RATE (Poly Tape) | AB1: WEIGHT (Poly Tape) | AC1: COST(Poly Tape) | AD1: Inner Sheath | AE1: RM RATE(Inner Sheath) | AF1: WEIGHT(Inner Sheath) | AG1: COST(Inner Sheath) | AH1: Armouring | AI1: RM RATE(Armouring) | AJ1: WEIGHT(Armouring) | AK1: COST(Armouring) | AL1: Outer Sheath | AM1: RM RATE(Outer Sheath) | AN1: WEIGHT(Outer Sheath) | AO1: COST(Outer Sheath) | AP1: FILLER | AQ1: RM RATE(Filler) | AR1: WEIGHT(Filler) | AS1: COST(Filler) | AT1: GREASE | AU1: RM RATE(Grease) | AV1: WEIGHT(Grease) | AW1: COST(Grease) | AX1: Water swellable Tape | AY1: RM RATE(Water swellable Tape) | AZ1: WEIGHT(Water swellable Tape) | BA1: COST(Water swellable Tape) | BB1: Semi conducting Water Swellable tape | BC1: RM RATE(Semi conducting Water Swellable tape) | BD1: WEIGHT(Semi conducting Water Swellable tape) | BE1: COST(Semi conducting Water Swellable tape) | BF1: SEMICON TAPE | BG1: RM RATE(SEMICON TAPE) | BH1: WEIGHT(SEMICON TAPE) | BI1: COST(SEMICON TAPE) | BJ1: GLASS FIBER TAPE | BK1: RM RATE(GLASS FIBER TAPE) | BL1: WEIGHT(GLASS FIBER TAPE) | BM1: COST(GLASS FIBER TAPE) | BN1: COPPER WIRE 0.8 MM | BO1: RM RATE(COPPER WIRE 0.8 MM) | BP1: WEIGHT(COPPER WIRE 0.8 MM) | BQ1: COST(COPPER WIRE 0.8 MM) | BR1: RUBBERIZED COTTON TAPE | BS1: RM RATE(RUBBERIZED COTTON TAPE) | BT1: WEIGHT(RUBBERIZED COTTON TAPE) | BU1: COST(RUBBERIZED COTTON TAPE) | BV1: Water Tight Compound | BW1: RM RATE(Water Tight Compound) | BX1: WEIGHT(Water Tight Compound) | BY1: COST(Water Tight Compound) | BZ1: DRUM COST PER KM | CA1: TOTAL RM COST | CB1: FIRM % | CC1: FIRM VALUE | CD1: MFG% | CE1: MFG VALUE | CF1: PROF% | CG1: PROFIT VALUE | CH1: 1ST EX-WORKS | CI1: Intt % | CJ1: INTT VALUE | CK1: insp% | CL1: INSP VALUE | CM1: EX-WORKS (PER KM) | CN1: FREIGHT PER KM | CO1: PRICE INCLUDING FREIGHT (PER KM) | CP1: GST % | CQ1: GST VALUE | CR1: PRICE INCLUDING GST & FREIGHT (PER KM) | CS1: QTY | CT1: Unit | CU1: TOTAL PRICE OF FULL QTY (INCLUDING FRIGHT & GST) | CV1: DRUM CODE | CW1: DRUM SIZE (FxbXtx Ft) | CX1: PARTY STANDARD LENGTH (MTR)
A2: ENQ-11285-22-23 | B2: 45170 | C2: FA0600021 | D2: 1 CORE X 185 SQ. MM. AL/UNARD. (XLPE) | E2: Hybrid | J2: Alumimium | K2: 212 | L2: 499.5 | M2: 105894 | P2: 0 | T2: 0 | V2: LT-XLPE | W2: 116 | X2: 90 | Y2: 10440 | AB2: 0 | AF2: 0 | AJ2: 0 | AL2: FRLSH PVC Type ST-2 | AM2: 94 | AN2: 207 | AO2: 19458 | AR2: 0 | AV2: 0 | AX2: Water swellable Tape | AY2: 455 | AZ2: 0 | BA2: 0 | BD2: 0 | BH2: 0 | BL2: 0 | BP2: 0 | BT2: 0 | BX2: 0 | BZ2: 7976.12 | CA2: 143768.12 | CH2: 143768.12 | CM2: 143768.12 | CO2: 143768.12 | CR2: 143768.12 | CS2: 6.7 | CT2: KMS | CU2: 963246 | CV2: MD0100107 | CW2: DRUM - 42 X 15 X 38 X 2 (LOMBU-HYBRID) | CX2: 1000
A3: ENQ-11285-22-23 | B3: 45170 | C3: FA1000114 | D3: 1 CORE X 4 SQ. MM. AL/UNARD (XLPE) | E3: Hybrid | J3: Alumimium | K3: 212 | L3: 11 | M3: 2332 | P3: 0 | T3: 0 | V3: LT-XLPE | W3: 116 | X3: 11 | Y3: 1276 | AB3: 0 | AF3: 0 | AJ3: 0 | AL3: FRLSH PVC Type ST-2 | AM3: 94 | AN3: 56 | AO3: 5264 | AR3: 0 | AV3: 0 | AZ3: 0 | BD3: 0 | BH3: 0 | BL3: 0 | BP3: 0 | BT3: 0 | BX3: 0 | BZ3: 1875.84 | CA3: 10747.84 | CH3: 10747.84 | CM3: 10747.84 | CO3: 10747.84 | CR3: 10747.84 | CS3: 12.5 | CT3: KMS | CU3: 134348 | CV3: MD0100004 | CW3: DRUM - 28 X 10 X 23 X 2 | CX3: 1000
A4: ENQ-11285-22-23 | B4: 45170 | C4: FA0600032 | D4: 1 CORE X 630 SQ. MM. ALU/UNARD (XLPE) | E4: STEEL | J4: Alumimium | K4: 212 | L4: 1701 | M4: 360612 | P4: 0 | T4: 0 | V4: LT-XLPE | W4: 116 | X4: 253 | Y4: 29348 | AB4: 0 | AF4: 0 | AJ4: 0 | AL4: FRLSH PVC Type ST-2 | AM4: 94 | AN4: 429 | AO4: 40326 | AR4: 0 | AV4: 0 | AX4: Water swellable Tape | AY4: 455 | AZ4: 0 | BA4: 0 | BD4: 0 | BH4: 0 | BL4: 0 | BP4: 0 | BT4: 0 | BX4: 0 | BZ4: 26600 | CA4: 456886 | CH4: 456886 | CM4: 456886 | CO4: 456886 | CR4: 456886 | CS4: 18 | CT4: KMS | CU4: 8223948 | CV4: SP0400126 | CW4: CORRUGATED DISPATCH STEEL DRUM 1900 X 830 X 915 MM | CX4: 1000
A5: ENQ-11285-22-23 | B5: 45170 | C5: FA0600013 | D5: 1 CORE X 95 SQ. MM. AL/UNARD(XLPE ) | E5: Hybrid | J5: Alumimium | K5: 212 | L5: 256.5 | M5: 54378 | P5: 0 | T5: 0 | V5: LT-XLPE | W5: 116 | X5: 53 | Y5: 6148 | AB5: 0 | AF5: 0 | AJ5: 0 | AL5: FRLSH PVC Type ST-2 | AM5: 94 | AN5: 139 | AO5: 13066 | AR5: 0 | AV5: 0 | AZ5: 0 | BD5: 0 | BH5: 0 | BL5: 0 | BP5: 0 | BT5: 0 | BX5: 0 | BZ5: 7244.19 | CA5: 80836.19 | CH5: 80836.19 | CM5: 80836.19 | CO5: 80836.19 | CR5: 80836.19 | CS5: 18.5 | CT5: KMS | CU5: 1495470 | CV5: MD0100106 | CW5: DRUM - 42 X 15 X 23 X 2 (LOMBU-HYBRID) | CX5: 1000
A6: ENQ-11285-22-23 | B6: 45170 | C6: FA0600020 | D6: 1 CORE X 300 SQ. MM. AL/UNARD. (XLPE) | E6: STEEL | J6: Alumimium | K6: 212 | L6: 810 | M6: 171720 | P6: 0 | T6: 0 | V6: LT-XLPE | W6: 116 | X6: 132 | Y6: 15312 | AB6: 0 | AF6: 0 | AJ6: 0 | AL6: FRLSH PVC Type ST-2 | AM6: 94 | AN6: 251 | AO6: 23594 | AR6: 0 | AV6: 0 | AX6: Water swellable Tape | AY6: 455 | AZ6: 0 | BA6: 0 | BD6: 0 | BH6: 0 | BL6: 0 | BP6: 0 | BT6: 0 | BX6: 0 | CA6: 210626 | CH6: 210626 | CM6: 210626 | CO6: 210626 | CR6: 210626 | CS6: 20.7 | CT6: KMS | CU6: 4359958 | CX6: 1000
A7: ENQ-11285-22-23 | B7: 45170 | C7: FA0500020 | D7: 1 CORE X 25 SQ. MM. ALU/UNARD (XLPE ) | E7: Hybrid | J7: Alumimium | K7: 212 | L7: 67.5 | M7: 14310 | P7: 0 | T7: 0 | V7: LT-XLPE | W7: 116 | X7: 26 | Y7: 3016 | AB7: 0 | AF7: 0 | AJ7: 0 | AL7: FRLSH PVC Type ST-2 | AM7: 94 | AN7: 89 | AO7: 8366 | AR7: 0 | AV7: 0 | AZ7: 0 | BD7: 0 | BH7: 0 | BL7: 0 | BP7: 0 | BT7: 0 | BX7: 0 | BZ7: 1875.84 | CA7: 27567.84 | CH7: 27567.84 | CM7: 27567.84 | CO7: 27567.84 | CR7: 27567.84 | CS7: 39 | CT7: KMS | CU7: 1075146 | CV7: MD0100004 | CW7: DRUM - 28 X 10 X 23 X 2 | CX7: 1000
A8: ENQ-11285-22-23 | B8: 45170 | C8: FA1500045 | D8: 2 CORE X 25 SQ MM + 1 CORE X 25 SQ MM (AB CABLES) (BARE) | E8: STEEL | J8: Alumimium | K8: 212 | L8: 135 | M8: 28620 | N8: Alumimium Alloy | O8: 219 | P8: 67.5 | Q8: 14782.5 | T8: 0 | V8: LT-XLPE | W8: 116 | X8: 56 | Y8: 6496 | AB8: 0 | AF8: 0 | AJ8: 0 | AN8: 0 | AR8: 0 | AV8: 0 | AZ8: 0 | BD8: 0 | BH8: 0 | BL8: 0 | BP8: 0 | BT8: 0 | BX8: 0 | CA8: 49898.5 | CH8: 49898.5 | CM8: 49898.5 | CO8: 49898.5 | CR8: 49898.5 | CS8: 40 | CT8: KMS | CU8: 1995940 | CX8: 1000
A9: ENQ-11285-22-23 | B9: 45170 | C9: FA1100262 | D9: 4 CORE X 150 SQ. MM. AL/ARD - STRIP/TYPE - B (XLPE) | E9: STEEL | J9: Alumimium | K9: 212 | L9: 1620 | M9: 343440 | P9: 0 | T9: 0 | V9: LT-XLPE | W9: 116 | X9: 275 | Y9: 31900 | AB9: 0 | AD9: PVC Type ST-2 | AE9: 61.6 | AF9: 135 | AG9: 8316 | AH9: Galvanised Steel Flat Strip-B | AI9: 87.87 | AJ9: 1212 | AK9: 106498.44 | AL9: FRLSH PVC Type ST-2 | AM9: 94 | AN9: 445 | AO9: 41830 | AR9: 0 | AV9: 0 | AX9: Water swellable Tape | AY9: 455 | AZ9: 0 | BA9: 0 | BD9: 0 | BH9: 0 | BL9: 0 | BP9: 0 | BR9: RUBBERIZED COTTON TAPE | BS9: 450 | BT9: 0 | BU9: 0 | BX9: 0 | CA9: 531984.44 | CH9: 531984.44 | CM9: 531984.44 | CO9: 531984.44 | CR9: 531984.44 | CS9: 45 | CT9: KMS | CU9: 23939300 | CX9: 500
A10: ENQ-11285-22-23 | B10: 45170 | C10: FA0500035 | D10: 1 CORE X 2.5 SQ. MM. ALU/UNARD (XLPE) | E10: Hybrid | J10: Alumimium | K10: 212 | L10: 6.75 | M10: 1431 | P10: 0 | T10: 0 | V10: LT-XLPE | W10: 116 | X10: 10 | Y10: 1160 | AB10: 0 | AF10: 0 | AJ10: 0 | AL10: FRLSH PVC Type ST-2 | AM10: 94 | AN10: 53 | AO10: 4982 | AR10: 0 | AV10: 0 | AZ10: 0 | BD10: 0 | BH10: 0 | BL10: 0 | BP10: 0 | BT10: 0 | BX10: 0 | BZ10: 1875.84 | CA10: 9448.84 | CH10: 9448.84 | CM10: 9448.84 | CO10: 9448.84 | CR10: 9448.84 | CS10: 46 | CT10: KMS | CU10: 434647 | CV10: MD0100004 | CW10: DRUM - 28 X 10 X 23 X 2 | CX10: 1000
A11: ENQ-11285-22-23 | B11: 45170 | C11: FA1100176 | D11: 4 CORE X 300 SQ. MM. AL/ARD - WIRE (XLPE) | E11: STEEL | J11: Alumimium | K11: 212 | L11: 3240 | M11: 686880 | P11: 0 | T11: 0 | V11: LT-XLPE | W11: 116 | X11: 488 | Y11: 56608 | AB11: 0 | AD11: PVC Type ST-2 | AE11: 61.6 | AF11: 255 | AG11: 15708 | AH11: Galvanised Steel Round Wire | AI11: 86.13 | AJ11: 3436 | AK11: 295942.68 | AL11: FRLSH PVC Type ST-2 | AM11: 94 | AN11: 888 | AO11: 83472 | AR11: 0 | AV11: 0 | AX11: Water swellable Tape | AY11: 455 | AZ11: 0 | BA11: 0 | BD11: 90 | BH11: 0 | BL11: 0 | BP11: 0 | BR11: RUBBERIZED COTTON TAPE | BS11: 450 | BT11: 36 | BU11: 16200 | BX11: 0 | BZ11: 78780 | CA11: 1233590.7 | CH11: 1233590.7 | CM11: 1233590.7 | CO11: 1233590.7 | CR11: 1233590.7 | CS11: 72 | CT11: KMS | CU11: 88818529 | CV11: SP0400139 | CW11: CORRUGATED DISPATCH STEEL DRUM 2130 X 890 X 965 | CX11: 500
A12: ENQ-11285-22-23 | B12: 45170 | C12: FA1100012 | D12: 4 CORE X 95 SQ. MM. AL/ARD - STRIP (XLPE) | E12: STEEL | J12: Alumimium | K12: 212 | L12: 1026 | M12: 217512 | P12: 0 | T12: 0 | V12: LT-XLPE | W12: 116 | X12: 187 | Y12: 21692 | AB12: 0 | AD12: PVC Type ST-2 | AE12: 61.6 | AF12: 93 | AG12: 5728.8 | AH12: Galvanised Steel Flat Strip | AI12: 77.87 | AJ12: 611 | AK12: 47578.57 | AL12: FRLSH PVC Type ST-2 | AM12: 94 | AN12: 348 | AO12: 32712 | AR12: 0 | AV12: 0 | AZ12: 0 | BD12: 0 | BH12: 0 | BL12: 0 | BP12: 0 | BR12: RUBBERIZED COTTON TAPE | BS12: 450 | BT12: 0 | BU12: 0 | BX12: 0 | CA12: 325223.37 | CH12: 325223.37 | CM12: 325223.37 | CO12: 325223.37 | CR12: 325223.37 | CS12: 82 | CT12: KMS | CU12: 26668316 | CX12: 500
A13: ENQ-11285-22-23 | B13: 45170 | C13: FA0900036 | D13: 4 CORE X 50 SQ. MM. ALU/ARD - STRIP (XLPE) | E13: STEEL | J13: Alumimium | K13: 212 | L13: 540 | M13: 114480 | P13: 0 | T13: 0 | V13: LT-XLPE | W13: 116 | X13: 124 | Y13: 14384 | AB13: 0 | AD13: PVC Type ST-2 | AE13: 61.6 | AF13: 69 | AG13: 4250.4 | AH13: Galvanised Steel Flat Strip | AI13: 77.87 | AJ13: 457 | AK13: 35586.59 | AL13: FRLSH PVC Type ST-2 | AM13: 94 | AN13: 240 | AO13: 22560 | AR13: 0 | AV13: 0 | AZ13: 0 | BD13: 0 | BH13: 0 | BL13: 0 | BP13: 0 | BR13: RUBBERIZED COTTON TAPE | BS13: 450 | BT13: 0 | BU13: 0 | BX13: 0 | CA13: 191260.99 | CH13: 191260.99 | CM13: 191260.99 | CO13: 191260.99 | CR13: 191260.99 | CS13: 97 | CT13: KMS | CU13: 18552316 | CX13: 1000
A14: ENQ-11285-22-23 | B14: 45170 | C14: FA0900038 | D14: 2 CORE X 25 SQ. MM. AL/ARD - STRIP (XLPE) | E14: Hybrid | J14: Alumimium | K14: 212 | L14: 135 | M14: 28620 | P14: 0 | T14: 0 | V14: LT-XLPE | W14: 116 | X14: 38 | Y14: 4408 | AB14: 0 | AD14: PVC Type ST-2-PRESSURE EXTRUDED | AE14: 88 | AF14: 38 | AG14: 3344 | AH14: Galvanised Steel Flat Strip | AI14: 77.87 | AJ14: 256 | AK14: 19934.72 | AL14: FRLSH PVC Type ST-2 | AM14: 94 | AN14: 129 | AO14: 12126 | AR14: 0 | AV14: 0 | AZ14: 0 | BD14: 0 | BH14: 0 | BL14: 0 | BP14: 0 | BR14: RUBBERIZED COTTON TAPE | BS14: 450 | BT14: 0 | BU14: 0 | BX14: 0 | BZ14: 7976.12 | CA14: 76408.84 | CH14: 76408.84 | CM14: 76408.84 | CO14: 76408.84 | CR14: 76408.84 | CS14: 125 | CT14: KMS | CU14: 9551105 | CV14: MD0100105 | CW14: DRUM - 42 X 24 X 38 X 2 (LOMBU-HYBRID) | CX14: 1000
A15: ENQ-11285-22-23 | B15: 45170 | C15: FA0100086 | D15: 4 CORE X 150 SQ MM + 1 CORE X 16 SQ MM + 1 CORE X 150 SQ MM (AB CABLES) (BARE) | E15: WOOD | J15: Alumimium | K15: 212 | L15: 1664 | M15: 352768 | N15: Alumimium Alloy | O15: 219 | P15: 416 | Q15: 91104 | T15: 0 | V15: LT-XLPE | W15: 116 | X15: 360 | Y15: 41760 | AB15: 0 | AF15: 0 | AJ15: 0 | AN15: 0 | AR15: 0 | AV15: 0 | AZ15: 0 | BD15: 0 | BH15: 0 | BL15: 0 | BP15: 0 | BT15: 0 | BX15: 0 | BZ15: 17878.84 | CA15: 503510.84 | CH15: 503510.84 | CM15: 503510.84 | CO15: 503510.84 | CR15: 503510.84 | CS15: 170 | CT15: KMS | CU15: 85596843 | CV15: MD0100070 | CW15: DRUM - 68 X 24 X 32 X 3 | CX15: 500
A16: ENQ-11285-22-23 | B16: 45170 | C16: FA0900015 | D16: 4 CORE X 25 SQ. MM. ALU/ARD - STRIP (XLPE) | E16: Hybrid | J16: Alumimium | K16: 212 | L16: 270 | M16: 57240 | P16: 0 | T16: 0 | V16: LT-XLPE | W16: 116 | X16: 95 | Y16: 11020 | AB16: 0 | AD16: PVC Type ST-2 | AE16: 61.6 | AF16: 46 | AG16: 2833.6 | AH16: Galvanised Steel Flat Strip | AI16: 77.87 | AJ16: 364 | AK16: 28344.68 | AL16: FRLSH PVC Type ST-2 | AM16: 94 | AN16: 173 | AO16: 16262 | AR16: 0 | AV16: 0 | AZ16: 0 | BD16: 0 | BH16: 0 | BL16: 0 | BP16: 0 | BR16: RUBBERIZED COTTON TAPE | BS16: 450 | BT16: 0 | BU16: 0 | BX16: 0 | BZ16: 4493.28 | CA16: 120193.56 | CH16: 120193.56 | CM16: 120193.56 | CO16: 120193.56 | CR16: 120193.56 | CS16: 357 | CT16: KMS | CU16: 42909101 | CV16: MD0100092 | CW16: DRUM - 42 X 18 X 36 X 2 (LOMBU) | CX16: 1000
A17: ENQ-11285-22-23 | B17: 45170 | C17: FA0900133 | D17: 2 CORE X 16 SQ. MM. AL/ARD - WIRE (XLPE) | E17: Hybrid | J17: Alumimium | K17: 212 | L17: 86.4 | M17: 18316.8 | P17: 0 | T17: 0 | V17: LT-XLPE | W17: 116 | X17: 37 | Y17: 4292 | AB17: 0 | AD17: PVC Type ST-2-PRESSURE EXTRUDED | AE17: 88 | AF17: 33 | AG17: 2904 | AH17: Galvanised Steel Round Wire | AI17: 86.13 | AJ17: 416 | AK17: 35830.08 | AL17: FRLSH PVC Type ST-2 | AM17: 94 | AN17: 144 | AO17: 13536 | AR17: 0 | AV17: 0 | AZ17: 0 | BD17: 0 | BH17: 0 | BL17: 0 | BP17: 0 | BR17: RUBBERIZED COTTON TAPE | BS17: 450 | BT17: 0 | BU17: 0 | BX17: 0 | BZ17: 7244.19 | CA17: 82123.07 | CH17: 82123.07 | CM17: 82123.07 | CO17: 82123.07 | CR17: 82123.07 | CS17: 1511 | CT17: KMS | CU17: 124087959 | CV17: MD0100106 | CW17: DRUM - 42 X 15 X 23 X 2 (LOMBU-HYBRID) | CX17: 1000

Sheet AUTO CALCULATION SHEET (2)
A2: Tata Power Delhi Distribution Limited
A4: TENDER SPECIFICATION NO () | B4: TPDDL/ENGG/ENQ/200001584/23-24
A5: TENDER DESCRIPTION () | B5: Rate Contract for supply of LT XLPE Power and AB Cables at Tata Power-DDL Site/Store.
A6: Last Date & Time of Submission () | B6: 06.10.2023 up to 1500 Hours
A7: REVERSE AUCTION | B7: Tata Power-DDL reserves the right to conduct the reverse auction (instead of public opening of price bids) for the products/ services being asked for in the tender. The terms and conditions for such reverse auction events shall be as per the Acceptance Form attached as Annexure VI of this document. The bidders along with the tender document shall mandatorily submit a duly signed copy of the Acceptance Form attached as Annexure VI as a token of acceptance for the same.
A8: Price () | B8: LME Average Settlement Price in Kg including Premium for Ingot as per IEEMA. This price is applicable as of 1st working day of the month, 1 month prior to the due date of submission of tender.
A9: Validity () | B9: Bids shall remain valid for 180 days from the due date of submission of the bid. Notwithstanding clause above, the Tata Power-DDL may solicit the Bidder’s consent to an extension of the Period of Bid Validity. The request and responses thereto shall be made in writing.
A10: Delivery Period () | B10: The total time for completion of delivery at Tata Power-DDL Stores shall be within 60 days from the date of issue of RO to BA or manufacturing clearance whichever is later.
A11: Payment Terms () | B11: Tata Power-DDL will make 100% payment within 45 days (MSME) / 60 days (Non MSME) of submission of the Bill/Invoice complete in all respects and along with all the requisite documents at Bill Inward Receipt Desk (BIRD) located at Civil Lines II Office, Tata Power-DDL Near Delhi Vidhan Sabha; subject to condition that associate has furnished the requisite Security-cumPerformance Guarantee as stipulated in the contract.
A12: Technical Specification
BF13: Consider Rs. 1 extra for colour of o/sh for all cables
N14: =Sheet1!J1 -> Conductor | S14: AL ALLOY | U14: Insulation Screening (Metallic) | AC14: Insulation Screening (Non-Metallic) | AE14: Insulation | AK14: POLY TAPE | AL14: Inner Sheath | AS14: Armouring | BC14: Consider 5 rs/kg extra on outer sheath for UV protection for all cables | BM14: FILLER | BN14: GREASE | BO14: Water swellable Tape | BP14: Semi conducting Water Swellable tape | BQ14: SEMICON TAPE | BR14: GLASS FIBER TAPE | BS14: COPPER WIRE 0.8 MM | BT14: RUBBERIZED COTTON TAPE | BU14: Water Tight Compound | BZ14: DRUM COST PER KM | CA14: TOTAL RM COST | CB14: EXTRA CONSUMPTION | CC14: EXTRA CONSUMPTION VALUE
A15: DOCKET NO. | B15: =Sheet1!B1 -> Base Date | C15: ITEM CODE | D15: PROPOSE ERP ITEM NAME | E15: EX-WORKS (PER KM) | F15: FREIGHT PER KM | G15: PRICE INCLUDING FREIGHT (PER KM) | H15: GST % | I15: GST VALUE | J15: PRICE INCLUDING GST & FREIGHT (PER KM) | K15: QTY | L15: Unit | M15: TOTAL PRICE OF FULL QTY (INCLUDING FRIGHT & GST) | N15: Alumimium | O15: Alumimium ALLOY | P15: Copper | Q15: Flexible Copper | R15: Galvanized steel wire | S15: Alumimium | T15: Alumimium ALLOY | U15: Coper tape - 0.1 mm | V15: Copper Tape - 0.03 mm | W15: Copper Tape - 0.035 mm | X15: Copper Tape - 0.04 mm | Y15: Copper Tape - 0.045 mm | Z15: Copper Tape - 0.050 mm | AA15: Copper Tape - 0.060 mm | AB15: Copper Tape - 0.075 mm(DOUBLE) | AC15: Extruded semiconductive | AD15: Extruded Semiconductive(Stripable) | AE15: HT-XLPE | AF15: LT-XLPE | AG15: TR XLPE | AH15: Type A PVC | AI15: Type C PVC (HR) | AJ15: XLPE | AK15: POLY TAPE | AL15: FR PVC Type ST-1 | AM15: FR PVC Type ST-2 | AN15: FRLSH PVC Type ST-2 | AO15: PVC Type ST-1 | AP15: PVC Type ST-1-PRESSURE EXTRUDED | AQ15: PVC Type ST-2 | AR15: PVC Type ST-2-PRESSURE EXTRUDED | AS15: ACSR CORE WIRE | AT15: ACSR DOG STEEL WIRE | AU15: Aluminium Flat Strip | AV15: Aluminium Round Wire | AW15: Double Steel Tape | AX15: Galvanised Steel Flat Strip | AY15: Galvanised Steel Flat Strip (Double) | AZ15: Galvanised Steel Flat Strip-B | BA15: Galvanised Steel Round Wire | BB15: Galvanised Steel Round Wire (Double) | BC15: FR PVC Type ST-1 | BD15: FR PVC Type ST-2 | BE15: FRLSH PVC Type ST-1 | BF15: FRLSH PVC Type ST-2 | BG15: PE, ST-3 | BH15: PE, ST-7 | BI15: PVC Type ST-1 | BJ15: PVC Type ST-2 | BK15: PVC Type ST-2-PRESSURE EXTRUDED | BL15: UV & Track Resistant XLPE | BM15: FILLER | BN15: Grease | BO15: NCWBT | BP15: Semi conducting Water Swellable tape | BQ15: SEMICON TAPE | BR15: GLASS FIBER TAPE | BS15: COPPER WIRE 0.8 MM | BT15: RUBBERIZED COTTON TAPE | BU15: Water Tight Compound | BV15: =Sheet1!E1 -> PROPOSE DRUM TYPE | BW15: =Sheet1!CV1 -> DRUM CODE | BX15: =Sheet1!CW1 -> DRUM SIZE (FxbXtx Ft) | BY15: =Sheet1!CX1 -> PARTY STANDARD LENGTH (MTR) | CD15: MFG% | CE15: MFG VALUE | CF15: PROF% | CG15: PROFIT VALUE | CH15: 1ST EX-WORKS | CI15: Intt % | CJ15: INTT VALUE | CK15: insp% | CL15: INSP VALUE
N16: 213 | O16: =+IFERROR(VLOOKUP($O$15,Sheet1!J:L,2,0),0) -> 0 | P16: =+IFERROR(VLOOKUP($P$15,Sheet1!J:M,2,0),0) -> 0 | Q16: =+IFERROR(VLOOKUP($Q$15,Sheet1!J:M,2,0),0) -> 0 | R16: =+IFERROR(VLOOKUP($R$15,Sheet1!J:M,2,0),0) -> 0 | S16: =+IFERROR(VLOOKUP($S$15,Sheet1!N:Q,2,0),0) -> 0 | T16: =N16+7 -> 220 | U16: =+IFERROR(VLOOKUP($U$15,Sheet1!F:I,2,0),0) -> 0 | V16: =+IFERROR(VLOOKUP($V$15,Sheet1!F:I,2,0),0) -> 0 | W16: =+IFERROR(VLOOKUP($W$15,Sheet1!F:I,2,0),0) -> 0 | X16: =+IFERROR(VLOOKUP($X$15,Sheet1!F:I,2,0),0) -> 0 | Y16: =+IFERROR(VLOOKUP($Y$15,Sheet1!F:I,2,0),0) -> 0 | Z16: =+IFERROR(VLOOKUP($Z$15,Sheet1!F:I,2,0),0) -> 0 | AA16: =+IFERROR(VLOOKUP($AA$15,Sheet1!F:I,2,0),0) -> 0 | AB16: =+IFERROR(VLOOKUP($AB$15,Sheet1!F:I,2,0),0) -> 0 | AC16: =+IFERROR(VLOOKUP($AC$15,Sheet1!R:U,2,0),0) -> 0 | AD16: =+IFERROR(VLOOKUP($AD$15,Sheet1!R:U,2,0),0) -> 0 | AE16: =+IFERROR(VLOOKUP($AE$15,Sheet1!V:Y,2,0),0) -> 0 | AF16: =+IFERROR(VLOOKUP($AF$15,Sheet1!V:Y,2,0),0) -> 116 | AG16: =+IFERROR(VLOOKUP($AG$15,Sheet1!V:Y,2,0),0) -> 0 | AH16: =+IFERROR(VLOOKUP($AH$15,Sheet1!V:Y,2,0),0) -> 0 | AI16: =+IFERROR(VLOOKUP($AI$15,Sheet1!V:Y,2,0),0) -> 0 | AJ16: =+IFERROR(VLOOKUP($AJ$15,Sheet1!V:Y,2,0),0) -> 0 | AK16: =+IFERROR(VLOOKUP($AK$15,Sheet1!Z2:AA840,2,0),0) -> 0 | AL16: =+IFERROR(VLOOKUP($AL$15,Sheet1!AD2:AG840,2,0),0) -> 0 | AM16: =+IFERROR(VLOOKUP($AM$15,Sheet1!AD2:AG840,2,0),0) -> 0 | AN16: =+IFERROR(VLOOKUP($AN$15,Sheet1!AD2:AG840,2,0),0) -> 0 | AO16: =+IFERROR(VLOOKUP($AO$15,Sheet1!AD2:AG840,2,0),0) -> 0 | AP16: =+IFERROR(VLOOKUP($AP$15,Sheet1!AD2:AG840,2,0),0) -> 0 | AQ16: 62 | AR16: 88 | AX16: 76 | AZ16: 86 | BA16: 88 | BF16: =94+5+1 -> 100 | BO16: 420 | BT16: 450 | BU16: =+IFERROR(VLOOKUP($BU$15,Sheet1!BV2:BY840,2,0),0) -> 0
A17: =Sheet1!A10 -> ENQ-11285-22-23 | B17: =Sheet1!B10 -> 45170 | C17: =Sheet1!C10 -> FA0500035 | D17: =Sheet1!D10 -> 1 CORE X 2.5 SQ. MM. ALU/UNARD (XLPE) | E17: =CH17+CJ17+CL17 -> 16844.625 | F17: =ROUNDUP(M36,0) -> 1848 | G17: =E17+F17 -> 18692.625 | H17: 0.18 | I17: =G17*H17 -> 3364.6725 | J17: =G17+I17 -> 22057.298 | K17: =Sheet1!CS10 -> 46 | L17: =Sheet1!CT10 -> KMS | M17: =J17*K17 -> 1014635.7 | N17: 7 | O17: =+IFERROR(VLOOKUP($O$15,Sheet1!J10:L10,3,0),0) -> 0 | P17: =+IFERROR(VLOOKUP($P$15,Sheet1!J10:M10,3,0),0) -> 0 | Q17: =+IFERROR(VLOOKUP($Q$15,Sheet1!J10:M10,3,0),0) -> 0 | R17: =+IFERROR(VLOOKUP($R$15,Sheet1!J10:M10,3,0),0) -> 0 | S17: =+IFERROR(VLOOKUP($S$15,Sheet1!N10:Q10,3,0),0) -> 0 | T17: =+IFERROR(VLOOKUP($T$15,Sheet1!N10:Q10,3,0),0) -> 0 | U17: =+IFERROR(VLOOKUP($U$15,Sheet1!F10:I10,3,0),0) -> 0 | V17: =+IFERROR(VLOOKUP($V$15,Sheet1!F10:I10,3,0),0) -> 0 | W17: =+IFERROR(VLOOKUP($W$15,Sheet1!F10:I10,3,0),0) -> 0 | X17: =+IFERROR(VLOOKUP($X$15,Sheet1!F10:I10,3,0),0) -> 0 | Y17: =+IFERROR(VLOOKUP($Y$15,Sheet1!F10:I10,3,0),0) -> 0 | Z17: =+IFERROR(VLOOKUP($Z$15,Sheet1!F10:I10,3,0),0) -> 0 | AA17: =+IFERROR(VLOOKUP($AA$15,Sheet1!F10:I10,3,0),0) -> 0 | AB17: =+IFERROR(VLOOKUP($AB$15,Sheet1!F10:I10,3,0),0) -> 0 | AC17: =+IFERROR(VLOOKUP($AC$15,Sheet1!R10:U10,3,0),0) -> 0 | AD17: =+IFERROR(VLOOKUP($AD$15,Sheet1!R10:U10,2,0),0) -> 0 | AE17: =+IFERROR(VLOOKUP($AE$15,Sheet1!V10:Y10,3,0),0) -> 0 | AF17: 9 | AG17: =+IFERROR(VLOOKUP($AG$15,Sheet1!V10:Y10,3,0),0) -> 0 | AH17: =+IFERROR(VLOOKUP($AH$15,Sheet1!V10:Y10,3,0),0) -> 0 | AI17: =+IFERROR(VLOOKUP($AI$15,Sheet1!V10:Y10,3,0),0) -> 0 | AJ17: =+IFERROR(VLOOKUP($AJ$15,Sheet1!V10:Y10,3,0),0) -> 0 | AK17: =+IFERROR(VLOOKUP($AK$15,Sheet1!Z10:AB10,3,0),0) -> 0 | AL17: =+IFERROR(VLOOKUP($AL$15,Sheet1!AD10:AG10,3,0),0) -> 0 | AM17: =+IFERROR(VLOOKUP($AM$15,Sheet1!AD10:AG10,3,0),0) -> 0 | AN17: =+IFERROR(VLOOKUP($AN$15,Sheet1!AD10:AG10,3,0),0) -> 0 | AO17: =+IFERROR(VLOOKUP($AO$15,Sheet1!AD10:AG10,3,0),0) -> 0 | AP17: =+IFERROR(VLOOKUP($AP$15,Sheet1!AD10:AG10,3,0),0) -> 0 | AQ17: =+IFERROR(VLOOKUP($AQ$15,Sheet1!AD10:AG10,3,0),0) -> 0 | AR17: =+IFERROR(VLOOKUP($AR$15,Sheet1!AD10:AG10,3,0),0) -> 0 | AS17: =+IFERROR(VLOOKUP($AS$15,Sheet1!AH10:AK10,3,0),0) -> 0 | AT17: =+IFERROR(VLOOKUP($AT$15,Sheet1!AH10:AK10,3,0),0) -> 0 | AU17: =+IFERROR(VLOOKUP($AU$15,Sheet1!AH10:AK10,3,0),0) -> 0 | AV17: =+IFERROR(VLOOKUP($AV$15,Sheet1!AH10:AK10,3,0),0) -> 0 | AW17: =+IFERROR(VLOOKUP($AW$15,Sheet1!AH10:AK10,3,0),0) -> 0 | AX17: =+IFERROR(VLOOKUP($AX$15,Sheet1!AH10:AK10,3,0),0) -> 0 | AY17: =+IFERROR(VLOOKUP($AY$15,Sheet1!AH10:AK10,3,0),0) -> 0 | AZ17: =+IFERROR(VLOOKUP($AZ$15,Sheet1!AH10:AK10,3,0),0) -> 0 | BA17: =+IFERROR(VLOOKUP($BA$15,Sheet1!AH10:AK10,3,0),0) -> 0 | BB17: =+IFERROR(VLOOKUP($BB$15,Sheet1!AH10:AK10,3,0),0) -> 0 | BC17: =+IFERROR(VLOOKUP($BC$15,Sheet1!AL10:AO10,3,0),0) -> 0 | BD17: =+IFERROR(VLOOKUP($BD$15,Sheet1!AL10:AO10,3,0),0) -> 0 | BE17: =+IFERROR(VLOOKUP($BE$15,Sheet1!AL10:AO10,3,0),0) -> 0 | BF17: 52 | BG17: =+IFERROR(VLOOKUP($BG$15,Sheet1!AL10:AO10,3,0),0) -> 0 | BH17: =+IFERROR(VLOOKUP($BH$15,Sheet1!AL10:AO10,3,0),0) -> 0 | BI17: =+IFERROR(VLOOKUP($BI$15,Sheet1!AL10:AO10,3,0),0) -> 0 | BJ17: =+IFERROR(VLOOKUP($BJ$15,Sheet1!AL10:AO10,3,0),0) -> 0 | BK17: =+IFERROR(VLOOKUP($BK$15,Sheet1!AL10:AO10,3,0),0) -> 0 | BL17: =+IFERROR(VLOOKUP($BL$15,Sheet1!AL10:AO10,3,0),0) -> 0 | BM17: =+IFERROR(VLOOKUP($BM$15,Sheet1!AP10:AS10,3,0),0) -> 0 | BN17: =+IFERROR(VLOOKUP($BN$15,Sheet1!AT10:AW10,3,0),0) -> 0 | BO17: =+IFERROR(VLOOKUP($BO$15,Sheet1!AX10:BA10,3,0),0) -> 0 | BP17: =+IFERROR(VLOOKUP($BP$15,Sheet1!BB10:BE10,3,0),0) -> 0 | BQ17: =+IFERROR(VLOOKUP($BQ$15,Sheet1!BF10:BI10,3,0),0) -> 0 | BR17: =+IFERROR(VLOOKUP($BR$15,Sheet1!BJ10:BM10,3,0),0) -> 0 | BS17: =+IFERROR(VLOOKUP($BS$15,Sheet1!BN10:BQ10,3,0),0) -> 0 | BT17: =+IFERROR(VLOOKUP($BT$15,Sheet1!BR10:BU10,3,0),0) -> 0 | BU17: =+IFERROR(VLOOKUP($BU$15,Sheet1!BV10:BY10,3,0),0) -> 0 | BV17: =Sheet1!E10 -> Hybrid | BW17: =Sheet1!CV10 -> MD0100004 | BX17: =Sheet1!CW10 -> DRUM - 28 X 10 X 23 X 2 | BY17: =VLOOKUP(C17,Sheet1!$C$1:$CX$17,100,0) -> 1000 | BZ17: 2960 | CA17: =SUMPRODUCT($N$16:$BU$16,N17:BU17)+BZ17 -> 10695 | CB17: =Sheet1!CB10 -> 0 | CC17: =CA17*CB17 -> 0 | CD17: 0.5 | CE17: =CA17*CD17 -> 5347.5 | CF17: 0 | CG17: =CA17*CF17 -> 0 | CH17: =CA17+CC17+CE17+CG17 -> 16042.5 | CI17: 0.03 | CJ17: =CH17*CI17 -> 481.275 | CK17: 0.02 | CL17: =CH17*CK17 -> 320.85
A18: =Sheet1!A3 -> ENQ-11285-22-23 | B18: =Sheet1!B3 -> 45170 | C18: =Sheet1!C3 -> FA1000114 | D18: =Sheet1!D3 -> 1 CORE X 4 SQ. MM. AL/UNARD (XLPE) | E18: =CH18+CJ18+CL18 -> 19181.925 | F18: =ROUNDUP(M37,0) -> 6800 | G18: =E18+F18 -> 25981.925 | H18: 0.18 | I18: =G18*H18 -> 4676.7465 | J18: =G18+I18 -> 30658.671 | K18: =Sheet1!CS3 -> 12.5 | L18: =Sheet1!CT3 -> KMS | M18: =J18*K18 -> 383233.39 | N18: =+IFERROR(VLOOKUP($N$15,Sheet1!J3:L3,3,0),0) -> 11 | O18: =+IFERROR(VLOOKUP($O$15,Sheet1!J3:L3,3,0),0) -> 0 | P18: =+IFERROR(VLOOKUP($P$15,Sheet1!J3:M3,3,0),0) -> 0 | Q18: =+IFERROR(VLOOKUP($Q$15,Sheet1!J3:M3,3,0),0) -> 0 | R18: =+IFERROR(VLOOKUP($R$15,Sheet1!J3:M3,3,0),0) -> 0 | S18: =+IFERROR(VLOOKUP($S$15,Sheet1!N3:Q3,3,0),0) -> 0 | T18: =+IFERROR(VLOOKUP($T$15,Sheet1!N3:Q3,3,0),0) -> 0 | U18: =+IFERROR(VLOOKUP($U$15,Sheet1!F3:I3,3,0),0) -> 0 | V18: =+IFERROR(VLOOKUP($V$15,Sheet1!F3:I3,3,0),0) -> 0 | W18: =+IFERROR(VLOOKUP($W$15,Sheet1!F3:I3,3,0),0) -> 0 | X18: =+IFERROR(VLOOKUP($X$15,Sheet1!F3:I3,3,0),0) -> 0 | Y18: =+IFERROR(VLOOKUP($Y$15,Sheet1!F3:I3,3,0),0) -> 0 | Z18: =+IFERROR(VLOOKUP($Z$15,Sheet1!F3:I3,3,0),0) -> 0 | AA18: =+IFERROR(VLOOKUP($AA$15,Sheet1!F3:I3,3,0),0) -> 0 | AB18: =+IFERROR(VLOOKUP($AB$15,Sheet1!F3:I3,3,0),0) -> 0 | AC18: =+IFERROR(VLOOKUP($AC$15,Sheet1!R3:U3,3,0),0) -> 0 | AD18: =+IFERROR(VLOOKUP($AD$15,Sheet1!R3:U3,2,0),0) -> 0 | AE18: =+IFERROR(VLOOKUP($AE$15,Sheet1!V3:Y3,3,0),0) -> 0 | AF18: =+IFERROR(VLOOKUP($AF$15,Sheet1!V3:Y3,3,0),0) -> 11 | AG18: =+IFERROR(VLOOKUP($AG$15,Sheet1!V3:Y3,3,0),0) -> 0 | AH18: =+IFERROR(VLOOKUP($AH$15,Sheet1!V3:Y3,3,0),0) -> 0 | AI18: =+IFERROR(VLOOKUP($AI$15,Sheet1!V3:Y3,3,0),0) -> 0 | AJ18: =+IFERROR(VLOOKUP($AJ$15,Sheet1!V3:Y3,3,0),0) -> 0 | AK18: =+IFERROR(VLOOKUP($AK$15,Sheet1!Z3:AB3,3,0),0) -> 0 | AL18: =+IFERROR(VLOOKUP($AL$15,Sheet1!AD3:AG3,3,0),0) -> 0 | AM18: =+IFERROR(VLOOKUP($AM$15,Sheet1!AD3:AG3,3,0),0) -> 0 | AN18: =+IFERROR(VLOOKUP($AN$15,Sheet1!AD3:AG3,3,0),0) -> 0 | AO18: =+IFERROR(VLOOKUP($AO$15,Sheet1!AD3:AG3,3,0),0) -> 0 | AP18: =+IFERROR(VLOOKUP($AP$15,Sheet1!AD3:AG3,3,0),0) -> 0 | AQ18: =+IFERROR(VLOOKUP($AQ$15,Sheet1!AD3:AG3,3,0),0) -> 0 | AR18: =+IFERROR(VLOOKUP($AR$15,Sheet1!AD3:AG3,3,0),0) -> 0 | AS18: =+IFERROR(VLOOKUP($AS$15,Sheet1!AH3:AK3,3,0),0) -> 0 | AT18: =+IFERROR(VLOOKUP($AT$15,Sheet1!AH3:AK3,3,0),0) -> 0 | AU18: =+IFERROR(VLOOKUP($AU$15,Sheet1!AH3:AK3,3,0),0) -> 0 | AV18: =+IFERROR(VLOOKUP($AV$15,Sheet1!AH3:AK3,3,0),0) -> 0 | AW18: =+IFERROR(VLOOKUP($AW$15,Sheet1!AH3:AK3,3,0),0) -> 0 | AX18: =+IFERROR(VLOOKUP($AX$15,Sheet1!AH3:AK3,3,0),0) -> 0 | AY18: =+IFERROR(VLOOKUP($AY$15,Sheet1!AH3:AK3,3,0),0) -> 0 | AZ18: =+IFERROR(VLOOKUP($AZ$15,Sheet1!AH3:AK3,3,0),0) -> 0 | BA18: =+IFERROR(VLOOKUP($BA$15,Sheet1!AH3:AK3,3,0),0) -> 0 | BB18: =+IFERROR(VLOOKUP($BB$15,Sheet1!AH3:AK3,3,0),0) -> 0 | BC18: =+IFERROR(VLOOKUP($BC$15,Sheet1!AL3:AO3,3,0),0) -> 0 | BD18: =+IFERROR(VLOOKUP($BD$15,Sheet1!AL3:AO3,3,0),0) -> 0 | BE18: =+IFERROR(VLOOKUP($BE$15,Sheet1!AL3:AO3,3,0),0) -> 0 | BF18: =+IFERROR(VLOOKUP($BF$15,Sheet1!AL3:AO3,3,0),0) -> 56 | BG18: =+IFERROR(VLOOKUP($BG$15,Sheet1!AL3:AO3,3,0),0) -> 0 | BH18: =+IFERROR(VLOOKUP($BH$15,Sheet1!AL3:AO3,3,0),0) -> 0 | BI18: =+IFERROR(VLOOKUP($BI$15,Sheet1!AL3:AO3,3,0),0) -> 0 | BJ18: =+IFERROR(VLOOKUP($BJ$15,Sheet1!AL3:AO3,3,0),0) -> 0 | BK18: =+IFERROR(VLOOKUP($BK$15,Sheet1!AL3:AO3,3,0),0) -> 0 | BL18: =+IFERROR(VLOOKUP($BL$15,Sheet1!AL3:AO3,3,0),0) -> 0 | BM18: =+IFERROR(VLOOKUP($BM$15,Sheet1!AP3:AS3,3,0),0) -> 0 | BN18: =+IFERROR(VLOOKUP($BN$15,Sheet1!AT3:AW3,3,0),0) -> 0 | BO18: =+IFERROR(VLOOKUP($BO$15,Sheet1!AX3:BA3,3,0),0) -> 0 | BP18: =+IFERROR(VLOOKUP($BP$15,Sheet1!BB3:BE3,3,0),0) -> 0 | BQ18: =+IFERROR(VLOOKUP($BQ$15,Sheet1!BF3:BI3,3,0),0) -> 0 | BR18: =+IFERROR(VLOOKUP($BR$15,Sheet1!BJ3:BM3,3,0),0) -> 0 | BS18: =+IFERROR(VLOOKUP($BS$15,Sheet1!BN3:BQ3,3,0),0) -> 0 | BT18: =+IFERROR(VLOOKUP($BT$15,Sheet1!BR3:BU3,3,0),0) -> 0 | BU18: =+IFERROR(VLOOKUP($BU$15,Sheet1!BV3:BY3,3,0),0) -> 0 | BV18: =Sheet1!E3 -> Hybrid | BW18: =Sheet1!CV3 -> MD0100004 | BX18: =Sheet1!CW3 -> DRUM - 28 X 10 X 23 X 2 | BY18: =VLOOKUP(C18,Sheet1!$C$1:$CX$17,100,0) -> 1000 | BZ18: 2960 | CA18: =SUMPRODUCT($N$16:$BU$16,N18:BU18)+BZ18 -> 12179 | CB18: =Sheet1!CB3 -> 0 | CC18: =CA18*CB18 -> 0 | CD18: 0.5 | CE18: =CA18*CD18 -> 6089.5 | CF18: =Sheet1!CF3 -> 0 | CG18: =CA18*CF18 -> 0 | CH18: =CA18+CC18+CE18+CG18 -> 18268.5 | CI18: 0.03 | CJ18: =CH18*CI18 -> 548.055 | CK18: 0.02 | CL18: =CH18*CK18 -> 365.37
A19: =Sheet1!A7 -> ENQ-11285-22-23 | B19: =Sheet1!B7 -> 45170 | C19: =Sheet1!C7 -> FA0500020 | D19: =Sheet1!D7 -> 1 CORE X 25 SQ. MM. ALU/UNARD (XLPE ) | E19: =CH19+CJ19+CL19 -> 46242 | F19: =ROUNDUP(M38,0) -> 2180 | G19: =E19+F19 -> 48422 | H19: 0.18 | I19: =G19*H19 -> 8715.96 | J19: =G19+I19 -> 57137.96 | K19: =Sheet1!CS7 -> 39 | L19: =Sheet1!CT7 -> KMS | M19: =J19*K19 -> 2228380.4 | N19: 68 | O19: =+IFERROR(VLOOKUP($O$15,Sheet1!J7:L7,3,0),0) -> 0 | P19: =+IFERROR(VLOOKUP($P$15,Sheet1!J7:M7,3,0),0) -> 0 | Q19: =+IFERROR(VLOOKUP($Q$15,Sheet1!J7:M7,3,0),0) -> 0 | R19: =+IFERROR(VLOOKUP($R$15,Sheet1!J7:M7,3,0),0) -> 0 | S19: =+IFERROR(VLOOKUP($S$15,Sheet1!N7:Q7,3,0),0) -> 0 | T19: =+IFERROR(VLOOKUP($T$15,Sheet1!N7:Q7,3,0),0) -> 0 | U19: =+IFERROR(VLOOKUP($U$15,Sheet1!F7:I7,3,0),0) -> 0 | V19: =+IFERROR(VLOOKUP($V$15,Sheet1!F7:I7,3,0),0) -> 0 | W19: =+IFERROR(VLOOKUP($W$15,Sheet1!F7:I7,3,0),0) -> 0 | X19: =+IFERROR(VLOOKUP($X$15,Sheet1!F7:I7,3,0),0) -> 0 | Y19: =+IFERROR(VLOOKUP($Y$15,Sheet1!F7:I7,3,0),0) -> 0 | Z19: =+IFERROR(VLOOKUP($Z$15,Sheet1!F7:I7,3,0),0) -> 0 | AA19: =+IFERROR(VLOOKUP($AA$15,Sheet1!F7:I7,3,0),0) -> 0 | AB19: =+IFERROR(VLOOKUP($AB$15,Sheet1!F7:I7,3,0),0) -> 0 | AC19: =+IFERROR(VLOOKUP($AC$15,Sheet1!R7:U7,3,0),0) -> 0 | AD19: =+IFERROR(VLOOKUP($AD$15,Sheet1!R7:U7,2,0),0) -> 0 | AE19: =+IFERROR(VLOOKUP($AE$15,Sheet1!V7:Y7,3,0),0) -> 0 | AF19: =+IFERROR(VLOOKUP($AF$15,Sheet1!V7:Y7,3,0),0) -> 26 | AG19: =+IFERROR(VLOOKUP($AG$15,Sheet1!V7:Y7,3,0),0) -> 0 | AH19: =+IFERROR(VLOOKUP($AH$15,Sheet1!V7:Y7,3,0),0) -> 0 | AI19: =+IFERROR(VLOOKUP($AI$15,Sheet1!V7:Y7,3,0),0) -> 0 | AJ19: =+IFERROR(VLOOKUP($AJ$15,Sheet1!V7:Y7,3,0),0) -> 0 | AK19: =+IFERROR(VLOOKUP($AK$15,Sheet1!Z7:AB7,3,0),0) -> 0 | AL19: =+IFERROR(VLOOKUP($AL$15,Sheet1!AD7:AG7,3,0),0) -> 0 | AM19: =+IFERROR(VLOOKUP($AM$15,Sheet1!AD7:AG7,3,0),0) -> 0 | AN19: =+IFERROR(VLOOKUP($AN$15,Sheet1!AD7:AG7,3,0),0) -> 0 | AO19: =+IFERROR(VLOOKUP($AO$15,Sheet1!AD7:AG7,3,0),0) -> 0 | AP19: =+IFERROR(VLOOKUP($AP$15,Sheet1!AD7:AG7,3,0),0) -> 0 | AQ19: =+IFERROR(VLOOKUP($AQ$15,Sheet1!AD7:AG7,3,0),0) -> 0 | AR19: =+IFERROR(VLOOKUP($AR$15,Sheet1!AD7:AG7,3,0),0) -> 0 | AS19: =+IFERROR(VLOOKUP($AS$15,Sheet1!AH7:AK7,3,0),0) -> 0 | AT19: =+IFERROR(VLOOKUP($AT$15,Sheet1!AH7:AK7,3,0),0) -> 0 | AU19: =+IFERROR(VLOOKUP($AU$15,Sheet1!AH7:AK7,3,0),0) -> 0 | AV19: =+IFERROR(VLOOKUP($AV$15,Sheet1!AH7:AK7,3,0),0) -> 0 | AW19: =+IFERROR(VLOOKUP($AW$15,Sheet1!AH7:AK7,3,0),0) -> 0 | AX19: =+IFERROR(VLOOKUP($AX$15,Sheet1!AH7:AK7,3,0),0) -> 0 | AY19: =+IFERROR(VLOOKUP($AY$15,Sheet1!AH7:AK7,3,0),0) -> 0 | AZ19: =+IFERROR(VLOOKUP($AZ$15,Sheet1!AH7:AK7,3,0),0) -> 0 | BA19: =+IFERROR(VLOOKUP($BA$15,Sheet1!AH7:AK7,3,0),0) -> 0 | BB19: =+IFERROR(VLOOKUP($BB$15,Sheet1!AH7:AK7,3,0),0) -> 0 | BC19: =+IFERROR(VLOOKUP($BC$15,Sheet1!AL7:AO7,3,0),0) -> 0 | BD19: =+IFERROR(VLOOKUP($BD$15,Sheet1!AL7:AO7,3,0),0) -> 0 | BE19: =+IFERROR(VLOOKUP($BE$15,Sheet1!AL7:AO7,3,0),0) -> 0 | BF19: =+IFERROR(VLOOKUP($BF$15,Sheet1!AL7:AO7,3,0),0) -> 89 | BG19: =+IFERROR(VLOOKUP($BG$15,Sheet1!AL7:AO7,3,0),0) -> 0 | BH19: =+IFERROR(VLOOKUP($BH$15,Sheet1!AL7:AO7,3,0),0) -> 0 | BI19: =+IFERROR(VLOOKUP($BI$15,Sheet1!AL7:AO7,3,0),0) -> 0 | BJ19: =+IFERROR(VLOOKUP($BJ$15,Sheet1!AL7:AO7,3,0),0) -> 0 | BK19: =+IFERROR(VLOOKUP($BK$15,Sheet1!AL7:AO7,3,0),0) -> 0 | BL19: =+IFERROR(VLOOKUP($BL$15,Sheet1!AL7:AO7,3,0),0) -> 0 | BM19: =+IFERROR(VLOOKUP($BM$15,Sheet1!AP7:AS7,3,0),0) -> 0 | BN19: =+IFERROR(VLOOKUP($BN$15,Sheet1!AT7:AW7,3,0),0) -> 0 | BO19: =+IFERROR(VLOOKUP($BO$15,Sheet1!AX7:BA7,3,0),0) -> 0 | BP19: =+IFERROR(VLOOKUP($BP$15,Sheet1!BB7:BE7,3,0),0) -> 0 | BQ19: =+IFERROR(VLOOKUP($BQ$15,Sheet1!BF7:BI7,3,0),0) -> 0 | BR19: =+IFERROR(VLOOKUP($BR$15,Sheet1!BJ7:BM7,3,0),0) -> 0 | BS19: =+IFERROR(VLOOKUP($BS$15,Sheet1!BN7:BQ7,3,0),0) -> 0 | BT19: =+IFERROR(VLOOKUP($BT$15,Sheet1!BR7:BU7,3,0),0) -> 0 | BU19: =+IFERROR(VLOOKUP($BU$15,Sheet1!BV7:BY7,3,0),0) -> 0 | BV19: =Sheet1!E7 -> Hybrid | BW19: =Sheet1!CV7 -> MD0100004 | BX19: =Sheet1!CW7 -> DRUM - 28 X 10 X 23 X 2 | BY19: =VLOOKUP(C19,Sheet1!$C$1:$CX$17,100,0) -> 1000 | BZ19: 2960 | CA19: =SUMPRODUCT($N$16:$BU$16,N19:BU19)+BZ19 -> 29360 | CB19: =Sheet1!CB7 -> 0 | CC19: =CA19*CB19 -> 0 | CD19: 0.5 | CE19: =CA19*CD19 -> 14680 | CF19: =Sheet1!CF7 -> 0 | CG19: =CA19*CF19 -> 0 | CH19: =CA19+CC19+CE19+CG19 -> 44040 | CI19: 0.03 | CJ19: =CH19*CI19 -> 1321.2 | CK19: 0.02 | CL19: =CH19*CK19 -> 880.8
A20: =Sheet1!A5 -> ENQ-11285-22-23 | B20: =Sheet1!B5 -> 45170 | C20: =Sheet1!C5 -> FA0600013 | D20: =Sheet1!D5 -> 1 CORE X 95 SQ. MM. AL/UNARD(XLPE ) | E20: =CH20+CJ20+CL20 -> 128866.8 | F20: =ROUNDUP(M39,0) -> 4595 | G20: =E20+F20 -> 133461.8 | H20: 0.18 | I20: =G20*H20 -> 24023.124 | J20: =G20+I20 -> 157484.92 | K20: =Sheet1!CS5 -> 18.5 | L20: =Sheet1!CT5 -> KMS | M20: =J20*K20 -> 2913471.1 | N20: 256 | O20: =+IFERROR(VLOOKUP($O$15,Sheet1!J5:L5,3,0),0) -> 0 | P20: =+IFERROR(VLOOKUP($P$15,Sheet1!J5:M5,3,0),0) -> 0 | Q20: =+IFERROR(VLOOKUP($Q$15,Sheet1!J5:M5,3,0),0) -> 0 | R20: =+IFERROR(VLOOKUP($R$15,Sheet1!J5:M5,3,0),0) -> 0 | S20: =+IFERROR(VLOOKUP($S$15,Sheet1!N5:Q5,3,0),0) -> 0 | T20: =+IFERROR(VLOOKUP($T$15,Sheet1!N5:Q5,3,0),0) -> 0 | U20: =+IFERROR(VLOOKUP($U$15,Sheet1!F5:I5,3,0),0) -> 0 | V20: =+IFERROR(VLOOKUP($V$15,Sheet1!F5:I5,3,0),0) -> 0 | W20: =+IFERROR(VLOOKUP($W$15,Sheet1!F5:I5,3,0),0) -> 0 | X20: =+IFERROR(VLOOKUP($X$15,Sheet1!F5:I5,3,0),0) -> 0 | Y20: =+IFERROR(VLOOKUP($Y$15,Sheet1!F5:I5,3,0),0) -> 0 | Z20: =+IFERROR(VLOOKUP($Z$15,Sheet1!F5:I5,3,0),0) -> 0 | AA20: =+IFERROR(VLOOKUP($AA$15,Sheet1!F5:I5,3,0),0) -> 0 | AB20: =+IFERROR(VLOOKUP($AB$15,Sheet1!F5:I5,3,0),0) -> 0 | AC20: =+IFERROR(VLOOKUP($AC$15,Sheet1!R5:U5,3,0),0) -> 0 | AD20: =+IFERROR(VLOOKUP($AD$15,Sheet1!R5:U5,2,0),0) -> 0 | AE20: =+IFERROR(VLOOKUP($AE$15,Sheet1!V5:Y5,3,0),0) -> 0 | AF20: =+IFERROR(VLOOKUP($AF$15,Sheet1!V5:Y5,3,0),0) -> 53 | AG20: =+IFERROR(VLOOKUP($AG$15,Sheet1!V5:Y5,3,0),0) -> 0 | AH20: =+IFERROR(VLOOKUP($AH$15,Sheet1!V5:Y5,3,0),0) -> 0 | AI20: =+IFERROR(VLOOKUP($AI$15,Sheet1!V5:Y5,3,0),0) -> 0 | AJ20: =+IFERROR(VLOOKUP($AJ$15,Sheet1!V5:Y5,3,0),0) -> 0 | AK20: =+IFERROR(VLOOKUP($AK$15,Sheet1!Z5:AB5,3,0),0) -> 0 | AL20: =+IFERROR(VLOOKUP($AL$15,Sheet1!AD5:AG5,3,0),0) -> 0 | AM20: =+IFERROR(VLOOKUP($AM$15,Sheet1!AD5:AG5,3,0),0) -> 0 | AN20: =+IFERROR(VLOOKUP($AN$15,Sheet1!AD5:AG5,3,0),0) -> 0 | AO20: =+IFERROR(VLOOKUP($AO$15,Sheet1!AD5:AG5,3,0),0) -> 0 | AP20: =+IFERROR(VLOOKUP($AP$15,Sheet1!AD5:AG5,3,0),0) -> 0 | AQ20: =+IFERROR(VLOOKUP($AQ$15,Sheet1!AD5:AG5,3,0),0) -> 0 | AR20: =+IFERROR(VLOOKUP($AR$15,Sheet1!AD5:AG5,3,0),0) -> 0 | AS20: =+IFERROR(VLOOKUP($AS$15,Sheet1!AH5:AK5,3,0),0) -> 0 | AT20: =+IFERROR(VLOOKUP($AT$15,Sheet1!AH5:AK5,3,0),0) -> 0 | AU20: =+IFERROR(VLOOKUP($AU$15,Sheet1!AH5:AK5,3,0),0) -> 0 | AV20: =+IFERROR(VLOOKUP($AV$15,Sheet1!AH5:AK5,3,0),0) -> 0 | AW20: =+IFERROR(VLOOKUP($AW$15,Sheet1!AH5:AK5,3,0),0) -> 0 | AX20: =+IFERROR(VLOOKUP($AX$15,Sheet1!AH5:AK5,3,0),0) -> 0 | AY20: =+IFERROR(VLOOKUP($AY$15,Sheet1!AH5:AK5,3,0),0) -> 0 | AZ20: =+IFERROR(VLOOKUP($AZ$15,Sheet1!AH5:AK5,3,0),0) -> 0 | BA20: =+IFERROR(VLOOKUP($BA$15,Sheet1!AH5:AK5,3,0),0) -> 0 | BB20: =+IFERROR(VLOOKUP($BB$15,Sheet1!AH5:AK5,3,0),0) -> 0 | BC20: =+IFERROR(VLOOKUP($BC$15,Sheet1!AL5:AO5,3,0),0) -> 0 | BD20: =+IFERROR(VLOOKUP($BD$15,Sheet1!AL5:AO5,3,0),0) -> 0 | BE20: =+IFERROR(VLOOKUP($BE$15,Sheet1!AL5:AO5,3,0),0) -> 0 | BF20: =+IFERROR(VLOOKUP($BF$15,Sheet1!AL5:AO5,3,0),0) -> 139 | BG20: =+IFERROR(VLOOKUP($BG$15,Sheet1!AL5:AO5,3,0),0) -> 0 | BH20: =+IFERROR(VLOOKUP($BH$15,Sheet1!AL5:AO5,3,0),0) -> 0 | BI20: =+IFERROR(VLOOKUP($BI$15,Sheet1!AL5:AO5,3,0),0) -> 0 | BJ20: =+IFERROR(VLOOKUP($BJ$15,Sheet1!AL5:AO5,3,0),0) -> 0 | BK20: =+IFERROR(VLOOKUP($BK$15,Sheet1!AL5:AO5,3,0),0) -> 0 | BL20: =+IFERROR(VLOOKUP($BL$15,Sheet1!AL5:AO5,3,0),0) -> 0 | BM20: =+IFERROR(VLOOKUP($BM$15,Sheet1!AP5:AS5,3,0),0) -> 0 | BN20: =+IFERROR(VLOOKUP($BN$15,Sheet1!AT5:AW5,3,0),0) -> 0 | BO20: =+IFERROR(VLOOKUP($BO$15,Sheet1!AX5:BA5,3,0),0) -> 0 | BP20: =+IFERROR(VLOOKUP($BP$15,Sheet1!BB5:BE5,3,0),0) -> 0 | BQ20: =+IFERROR(VLOOKUP($BQ$15,Sheet1!BF5:BI5,3,0),0) -> 0 | BR20: =+IFERROR(VLOOKUP($BR$15,Sheet1!BJ5:BM5,3,0),0) -> 0 | BS20: =+IFERROR(VLOOKUP($BS$15,Sheet1!BN5:BQ5,3,0),0) -> 0 | BT20: =+IFERROR(VLOOKUP($BT$15,Sheet1!BR5:BU5,3,0),0) -> 0 | BU20: =+IFERROR(VLOOKUP($BU$15,Sheet1!BV5:BY5,3,0),0) -> 0 | BV20: =Sheet1!E5 -> Hybrid | BW20: =Sheet1!CV5 -> MD0100106 | BX20: =Sheet1!CW5 -> DRUM - 42 X 15 X 23 X 2 (LOMBU-HYBRID) | BY20: =VLOOKUP(C20,Sheet1!$C$1:$CX$17,100,0) -> 1000 | BZ20: =Sheet1!BZ5 -> 7244.19 | CA20: =SUMPRODUCT($N$16:$BU$16,N20:BU20)+BZ20 -> 81820.19 | CB20: =Sheet1!CB5 -> 0 | CC20: =CA20*CB20 -> 0 | CD20: 0.5 | CE20: =CA20*CD20 -> 40910.095 | CF20: =Sheet1!CF5 -> 0 | CG20: =CA20*CF20 -> 0 | CH20: =CA20+CC20+CE20+CG20 -> 122730.29 | CI20: 0.03 | CJ20: =CH20*CI20 -> 3681.9086 | CK20: 0.02 | CL20: =CH20*CK20 -> 2454.6057
A21: =Sheet1!A2 -> ENQ-11285-22-23 | B21: =Sheet1!B2 -> 45170 | C21: =Sheet1!C2 -> FA0600021 | D21: =Sheet1!D2 -> 1 CORE X 185 SQ. MM. AL/UNARD. (XLPE) | E21: =CH21+CJ21+CL21 -> 244370.89 | F21: =ROUNDUP(M40,0) -> 12687 | G21: =E21+F21 -> 257057.89 | H21: 0.18 | I21: =G21*H21 -> 46270.42 | J21: =G21+I21 -> 303328.31 | K21: =Sheet1!CS2 -> 6.7 | L21: =Sheet1!CT2 -> KMS | M21: =J21*K21 -> 2032299.7 | N21: 500 | O21: =+IFERROR(VLOOKUP($O$15,Sheet1!J2:L2,3,0),0) -> 0 | P21: =+IFERROR(VLOOKUP($P$15,Sheet1!J2:M2,3,0),0) -> 0 | Q21: =+IFERROR(VLOOKUP($Q$15,Sheet1!J2:M2,3,0),0) -> 0 | R21: =+IFERROR(VLOOKUP($R$15,Sheet1!J2:M2,3,0),0) -> 0 | S21: =+IFERROR(VLOOKUP($S$15,Sheet1!N2:Q2,3,0),0) -> 0 | T21: =+IFERROR(VLOOKUP($T$15,Sheet1!N2:Q2,3,0),0) -> 0 | U21: =+IFERROR(VLOOKUP($U$15,Sheet1!F2:I2,3,0),0) -> 0 | V21: =+IFERROR(VLOOKUP($V$15,Sheet1!F2:I2,3,0),0) -> 0 | W21: =+IFERROR(VLOOKUP($W$15,Sheet1!F2:I2,3,0),0) -> 0 | X21: =+IFERROR(VLOOKUP($X$15,Sheet1!F2:I2,3,0),0) -> 0 | Y21: =+IFERROR(VLOOKUP($Y$15,Sheet1!F2:I2,3,0),0) -> 0 | Z21: =+IFERROR(VLOOKUP($Z$15,Sheet1!F2:I2,3,0),0) -> 0 | AA21: =+IFERROR(VLOOKUP($AA$15,Sheet1!F2:I2,3,0),0) -> 0 | AB21: =+IFERROR(VLOOKUP($AB$15,Sheet1!F2:I2,3,0),0) -> 0 | AC21: =+IFERROR(VLOOKUP($AC$15,Sheet1!R2:U2,3,0),0) -> 0 | AD21: =+IFERROR(VLOOKUP($AD$15,Sheet1!R2:U2,2,0),0) -> 0 | AE21: =+IFERROR(VLOOKUP($AE$15,Sheet1!V2:Y2,3,0),0) -> 0 | AF21: =+IFERROR(VLOOKUP($AF$15,Sheet1!V2:Y2,3,0),0) -> 90 | AG21: =+IFERROR(VLOOKUP($AG$15,Sheet1!V2:Y2,3,0),0) -> 0 | AH21: =+IFERROR(VLOOKUP($AH$15,Sheet1!V2:Y2,3,0),0) -> 0 | AI21: =+IFERROR(VLOOKUP($AI$15,Sheet1!V2:Y2,3,0),0) -> 0 | AJ21: =+IFERROR(VLOOKUP($AJ$15,Sheet1!V2:Y2,3,0),0) -> 0 | AK21: =+IFERROR(VLOOKUP($AK$15,Sheet1!Z2:AB2,3,0),0) -> 0 | AL21: =+IFERROR(VLOOKUP($AL$15,Sheet1!AD2:AG2,3,0),0) -> 0 | AM21: =+IFERROR(VLOOKUP($AM$15,Sheet1!AD2:AG2,3,0),0) -> 0 | AN21: =+IFERROR(VLOOKUP($AN$15,Sheet1!AD2:AG2,3,0),0) -> 0 | AO21: =+IFERROR(VLOOKUP($AO$15,Sheet1!AD2:AG2,3,0),0) -> 0 | AP21: =+IFERROR(VLOOKUP($AP$15,Sheet1!AD2:AG2,3,0),0) -> 0 | AQ21: =+IFERROR(VLOOKUP($AQ$15,Sheet1!AD2:AG2,3,0),0) -> 0 | AR21: =+IFERROR(VLOOKUP($AR$15,Sheet1!AD2:AG2,3,0),0) -> 0 | AS21: =+IFERROR(VLOOKUP($AS$15,Sheet1!AH2:AK2,3,0),0) -> 0 | AT21: =+IFERROR(VLOOKUP($AT$15,Sheet1!AH2:AK2,3,0),0) -> 0 | AU21: =+IFERROR(VLOOKUP($AU$15,Sheet1!AH2:AK2,3,0),0) -> 0 | AV21: =+IFERROR(VLOOKUP($AV$15,Sheet1!AH2:AK2,3,0),0) -> 0 | AW21: =+IFERROR(VLOOKUP($AW$15,Sheet1!AH2:AK2,3,0),0) -> 0 | AX21: =+IFERROR(VLOOKUP($AX$15,Sheet1!AH2:AK2,3,0),0) -> 0 | AY21: =+IFERROR(VLOOKUP($AY$15,Sheet1!AH2:AK2,3,0),0) -> 0 | AZ21: =+IFERROR(VLOOKUP($AZ$15,Sheet1!AH2:AK2,3,0),0) -> 0 | BA21: =+IFERROR(VLOOKUP($BA$15,Sheet1!AH2:AK2,3,0),0) -> 0 | BB21: =+IFERROR(VLOOKUP($BB$15,Sheet1!AH2:AK2,3,0),0) -> 0 | BC21: =+IFERROR(VLOOKUP($BC$15,Sheet1!AL2:AO2,3,0),0) -> 0 | BD21: =+IFERROR(VLOOKUP($BD$15,Sheet1!AL2:AO2,3,0),0) -> 0 | BE21: =+IFERROR(VLOOKUP($BE$15,Sheet1!AL2:AO2,3,0),0) -> 0 | BF21: 210 | BG21: =+IFERROR(VLOOKUP($BG$15,Sheet1!AL2:AO2,3,0),0) -> 0 | BH21: =+IFERROR(VLOOKUP($BH$15,Sheet1!AL2:AO2,3,0),0) -> 0 | BI21: =+IFERROR(VLOOKUP($BI$15,Sheet1!AL2:AO2,3,0),0) -> 0 | BJ21: =+IFERROR(VLOOKUP($BJ$15,Sheet1!AL2:AO2,3,0),0) -> 0 | BK21: =+IFERROR(VLOOKUP($BK$15,Sheet1!AL2:AO2,3,0),0) -> 0 | BL21: =+IFERROR(VLOOKUP($BL$15,Sheet1!AL2:AO2,3,0),0) -> 0 | BM21: =+IFERROR(VLOOKUP($BM$15,Sheet1!AP2:AS2,3,0),0) -> 0 | BN21: =+IFERROR(VLOOKUP($BN$15,Sheet1!AT2:AW2,3,0),0) -> 0 | BO21: 22 | BP21: =+IFERROR(VLOOKUP($BP$15,Sheet1!BB2:BE2,3,0),0) -> 0 | BQ21: =+IFERROR(VLOOKUP($BQ$15,Sheet1!BF2:BI2,3,0),0) -> 0 | BR21: =+IFERROR(VLOOKUP($BR$15,Sheet1!BJ2:BM2,3,0),0) -> 0 | BS21: =+IFERROR(VLOOKUP($BS$15,Sheet1!BN2:BQ2,3,0),0) -> 0 | BU21: =+IFERROR(VLOOKUP($BU$15,Sheet1!BV2:BY2,3,0),0) -> 0 | BV21: =Sheet1!E2 -> Hybrid | BW21: =Sheet1!CV2 -> MD0100107 | BX21: =Sheet1!CW2 -> DRUM - 42 X 15 X 38 X 2 (LOMBU-HYBRID) | BY21: =VLOOKUP(C21,Sheet1!$C$1:$CX$17,100,0) -> 1000 | BZ21: =Sheet1!BZ2 -> 7976.12 | CA21: =SUMPRODUCT($N$16:$BU$16,N21:BU21)+BZ21 -> 155156.12 | CB21: =Sheet1!CB2 -> 0 | CC21: =CA21*CB21 -> 0 | CD21: 0.5 | CE21: =CA21*CD21 -> 77578.06 | CF21: =Sheet1!CF2 -> 0 | CG21: =CA21*CF21 -> 0 | CH21: =CA21+CC21+CE21+CG21 -> 232734.18 | CI21: 0.03 | CJ21: =CH21*CI21 -> 6982.0254 | CK21: 0.02 | CL21: =CH21*CK21 -> 4654.6836
A22: =Sheet1!A6 -> ENQ-11285-22-23 | B22: =Sheet1!B6 -> 45170 | C22: =Sheet1!C6 -> FA0600020 | D22: =Sheet1!D6 -> 1 CORE X 300 SQ. MM. AL/UNARD. (XLPE) | E22: =CH22+CJ22+CL22 -> 387453.15 | F22: =ROUNDUP(M41,0) -> 12319 | G22: =E22+F22 -> 399772.15 | H22: 0.18 | I22: =G22*H22 -> 71958.987 | J22: =G22+I22 -> 471731.14 | K22: =Sheet1!CS6 -> 20.7 | L22: =Sheet1!CT6 -> KMS | M22: =J22*K22 -> 9764834.5 | N22: =+IFERROR(VLOOKUP($N$15,Sheet1!J6:L6,3,0),0) -> 810 | O22: =+IFERROR(VLOOKUP($O$15,Sheet1!J6:L6,3,0),0) -> 0 | P22: =+IFERROR(VLOOKUP($P$15,Sheet1!J6:M6,3,0),0) -> 0 | Q22: =+IFERROR(VLOOKUP($Q$15,Sheet1!J6:M6,3,0),0) -> 0 | R22: =+IFERROR(VLOOKUP($R$15,Sheet1!J6:M6,3,0),0) -> 0 | S22: =+IFERROR(VLOOKUP($S$15,Sheet1!N6:Q6,3,0),0) -> 0 | T22: =+IFERROR(VLOOKUP($T$15,Sheet1!N6:Q6,3,0),0) -> 0 | U22: =+IFERROR(VLOOKUP($U$15,Sheet1!F6:I6,3,0),0) -> 0 | V22: =+IFERROR(VLOOKUP($V$15,Sheet1!F6:I6,3,0),0) -> 0 | W22: =+IFERROR(VLOOKUP($W$15,Sheet1!F6:I6,3,0),0) -> 0 | X22: =+IFERROR(VLOOKUP($X$15,Sheet1!F6:I6,3,0),0) -> 0 | Y22: =+IFERROR(VLOOKUP($Y$15,Sheet1!F6:I6,3,0),0) -> 0 | Z22: =+IFERROR(VLOOKUP($Z$15,Sheet1!F6:I6,3,0),0) -> 0 | AA22: =+IFERROR(VLOOKUP($AA$15,Sheet1!F6:I6,3,0),0) -> 0 | AB22: =+IFERROR(VLOOKUP($AB$15,Sheet1!F6:I6,3,0),0) -> 0 | AC22: =+IFERROR(VLOOKUP($AC$15,Sheet1!R6:U6,3,0),0) -> 0 | AD22: =+IFERROR(VLOOKUP($AD$15,Sheet1!R6:U6,2,0),0) -> 0 | AE22: =+IFERROR(VLOOKUP($AE$15,Sheet1!V6:Y6,3,0),0) -> 0 | AF22: =+IFERROR(VLOOKUP($AF$15,Sheet1!V6:Y6,3,0),0) -> 132 | AG22: =+IFERROR(VLOOKUP($AG$15,Sheet1!V6:Y6,3,0),0) -> 0 | AH22: =+IFERROR(VLOOKUP($AH$15,Sheet1!V6:Y6,3,0),0) -> 0 | AI22: =+IFERROR(VLOOKUP($AI$15,Sheet1!V6:Y6,3,0),0) -> 0 | AJ22: =+IFERROR(VLOOKUP($AJ$15,Sheet1!V6:Y6,3,0),0) -> 0 | AK22: =+IFERROR(VLOOKUP($AK$15,Sheet1!Z6:AB6,3,0),0) -> 0 | AL22: =+IFERROR(VLOOKUP($AL$15,Sheet1!AD6:AG6,3,0),0) -> 0 | AM22: =+IFERROR(VLOOKUP($AM$15,Sheet1!AD6:AG6,3,0),0) -> 0 | AN22: =+IFERROR(VLOOKUP($AN$15,Sheet1!AD6:AG6,3,0),0) -> 0 | AO22: =+IFERROR(VLOOKUP($AO$15,Sheet1!AD6:AG6,3,0),0) -> 0 | AP22: =+IFERROR(VLOOKUP($AP$15,Sheet1!AD6:AG6,3,0),0) -> 0 | AQ22: =+IFERROR(VLOOKUP($AQ$15,Sheet1!AD6:AG6,3,0),0) -> 0 | AR22: =+IFERROR(VLOOKUP($AR$15,Sheet1!AD6:AG6,3,0),0) -> 0 | AS22: =+IFERROR(VLOOKUP($AS$15,Sheet1!AH6:AK6,3,0),0) -> 0 | AT22: =+IFERROR(VLOOKUP($AT$15,Sheet1!AH6:AK6,3,0),0) -> 0 | AU22: =+IFERROR(VLOOKUP($AU$15,Sheet1!AH6:AK6,3,0),0) -> 0 | AV22: =+IFERROR(VLOOKUP($AV$15,Sheet1!AH6:AK6,3,0),0) -> 0 | AW22: =+IFERROR(VLOOKUP($AW$15,Sheet1!AH6:AK6,3,0),0) -> 0 | AX22: =+IFERROR(VLOOKUP($AX$15,Sheet1!AH6:AK6,3,0),0) -> 0 | AY22: =+IFERROR(VLOOKUP($AY$15,Sheet1!AH6:AK6,3,0),0) -> 0 | AZ22: =+IFERROR(VLOOKUP($AZ$15,Sheet1!AH6:AK6,3,0),0) -> 0 | BA22: =+IFERROR(VLOOKUP($BA$15,Sheet1!AH6:AK6,3,0),0) -> 0 | BB22: =+IFERROR(VLOOKUP($BB$15,Sheet1!AH6:AK6,3,0),0) -> 0 | BC22: =+IFERROR(VLOOKUP($BC$15,Sheet1!AL6:AO6,3,0),0) -> 0 | BD22: =+IFERROR(VLOOKUP($BD$15,Sheet1!AL6:AO6,3,0),0) -> 0 | BE22: =+IFERROR(VLOOKUP($BE$15,Sheet1!AL6:AO6,3,0),0) -> 0 | BF22: 255 | BG22: =+IFERROR(VLOOKUP($BG$15,Sheet1!AL6:AO6,3,0),0) -> 0 | BH22: =+IFERROR(VLOOKUP($BH$15,Sheet1!AL6:AO6,3,0),0) -> 0 | BI22: =+IFERROR(VLOOKUP($BI$15,Sheet1!AL6:AO6,3,0),0) -> 0 | BJ22: =+IFERROR(VLOOKUP($BJ$15,Sheet1!AL6:AO6,3,0),0) -> 0 | BK22: =+IFERROR(VLOOKUP($BK$15,Sheet1!AL6:AO6,3,0),0) -> 0 | BL22: =+IFERROR(VLOOKUP($BL$15,Sheet1!AL6:AO6,3,0),0) -> 0 | BM22: =+IFERROR(VLOOKUP($BM$15,Sheet1!AP6:AS6,3,0),0) -> 0 | BN22: =+IFERROR(VLOOKUP($BN$15,Sheet1!AT6:AW6,3,0),0) -> 0 | BO22: 28 | BP22: =+IFERROR(VLOOKUP($BP$15,Sheet1!BB6:BE6,3,0),0) -> 0 | BQ22: =+IFERROR(VLOOKUP($BQ$15,Sheet1!BF6:BI6,3,0),0) -> 0 | BR22: =+IFERROR(VLOOKUP($BR$15,Sheet1!BJ6:BM6,3,0),0) -> 0 | BS22: =+IFERROR(VLOOKUP($BS$15,Sheet1!BN6:BQ6,3,0),0) -> 0 | BT22: =+IFERROR(VLOOKUP($BT$15,Sheet1!BR6:BU6,3,0),0) -> 0 | BU22: =+IFERROR(VLOOKUP($BU$15,Sheet1!BV6:BY6,3,0),0) -> 0 | BV22: =Sheet1!E6 -> STEEL | BW22: SP0400125 | BX22: CORRUGATED DISPATCH STEEL DRUM 1600 X 700 X 915 MM | BY22: =VLOOKUP(C22,Sheet1!$C$1:$CX$17,100,0) -> 1000 | BZ22: 20900 | CA22: =SUMPRODUCT($N$16:$BU$16,N22:BU22)+BZ22 -> 246002 | CB22: =Sheet1!CB6 -> 0 | CC22: =CA22*CB22 -> 0 | CD22: 0.5 | CE22: =CA22*CD22 -> 123001 | CF22: =Sheet1!CF6 -> 0 | CG22: =CA22*CF22 -> 0 | CH22: =CA22+CC22+CE22+CG22 -> 369003 | CI22: 0.03 | CJ22: =CH22*CI22 -> 11070.09 | CK22: 0.02 | CL22: =CH22*CK22 -> 7380.06
A23: =Sheet1!A4 -> ENQ-11285-22-23 | B23: =Sheet1!B4 -> 45170 | C23: =Sheet1!C4 -> FA0600032 | D23: =Sheet1!D4 -> 1 CORE X 630 SQ. MM. ALU/UNARD (XLPE) | E23: =CH23+CJ23+CL23 -> 747471.38 | F23: =ROUNDUP(M42,0) -> 28334 | G23: =E23+F23 -> 775805.38 | H23: 0.18 | I23: =G23*H23 -> 139644.97 | J23: =G23+I23 -> 915450.34 | K23: =Sheet1!CS4 -> 18 | L23: =Sheet1!CT4 -> KMS | M23: =J23*K23 -> 16478106 | N23: =+IFERROR(VLOOKUP($N$15,Sheet1!J4:L4,3,0),0) -> 1701 | O23: =+IFERROR(VLOOKUP($O$15,Sheet1!J4:L4,3,0),0) -> 0 | P23: =+IFERROR(VLOOKUP($P$15,Sheet1!J4:M4,3,0),0) -> 0 | Q23: =+IFERROR(VLOOKUP($Q$15,Sheet1!J4:M4,3,0),0) -> 0 | R23: =+IFERROR(VLOOKUP($R$15,Sheet1!J4:M4,3,0),0) -> 0 | S23: =+IFERROR(VLOOKUP($S$15,Sheet1!N4:Q4,3,0),0) -> 0 | T23: =+IFERROR(VLOOKUP($T$15,Sheet1!N4:Q4,3,0),0) -> 0 | U23: =+IFERROR(VLOOKUP($U$15,Sheet1!F4:I4,3,0),0) -> 0 | V23: =+IFERROR(VLOOKUP($V$15,Sheet1!F4:I4,3,0),0) -> 0 | W23: =+IFERROR(VLOOKUP($W$15,Sheet1!F4:I4,3,0),0) -> 0 | X23: =+IFERROR(VLOOKUP($X$15,Sheet1!F4:I4,3,0),0) -> 0 | Y23: =+IFERROR(VLOOKUP($Y$15,Sheet1!F4:I4,3,0),0) -> 0 | Z23: =+IFERROR(VLOOKUP($Z$15,Sheet1!F4:I4,3,0),0) -> 0 | AA23: =+IFERROR(VLOOKUP($AA$15,Sheet1!F4:I4,3,0),0) -> 0 | AB23: =+IFERROR(VLOOKUP($AB$15,Sheet1!F4:I4,3,0),0) -> 0 | AC23: =+IFERROR(VLOOKUP($AC$15,Sheet1!R4:U4,3,0),0) -> 0 | AD23: =+IFERROR(VLOOKUP($AD$15,Sheet1!R4:U4,2,0),0) -> 0 | AE23: =+IFERROR(VLOOKUP($AE$15,Sheet1!V4:Y4,3,0),0) -> 0 | AF23: 242 | AG23: =+IFERROR(VLOOKUP($AG$15,Sheet1!V4:Y4,3,0),0) -> 0 | AH23: =+IFERROR(VLOOKUP($AH$15,Sheet1!V4:Y4,3,0),0) -> 0 | AI23: =+IFERROR(VLOOKUP($AI$15,Sheet1!V4:Y4,3,0),0) -> 0 | AJ23: =+IFERROR(VLOOKUP($AJ$15,Sheet1!V4:Y4,3,0),0) -> 0 | AK23: =+IFERROR(VLOOKUP($AK$15,Sheet1!Z4:AB4,3,0),0) -> 0 | AL23: =+IFERROR(VLOOKUP($AL$15,Sheet1!AD4:AG4,3,0),0) -> 0 | AM23: =+IFERROR(VLOOKUP($AM$15,Sheet1!AD4:AG4,3,0),0) -> 0 | AN23: =+IFERROR(VLOOKUP($AN$15,Sheet1!AD4:AG4,3,0),0) -> 0 | AO23: =+IFERROR(VLOOKUP($AO$15,Sheet1!AD4:AG4,3,0),0) -> 0 | AP23: =+IFERROR(VLOOKUP($AP$15,Sheet1!AD4:AG4,3,0),0) -> 0 | AQ23: =+IFERROR(VLOOKUP($AQ$15,Sheet1!AD4:AG4,3,0),0) -> 0 | AR23: =+IFERROR(VLOOKUP($AR$15,Sheet1!AD4:AG4,3,0),0) -> 0 | AS23: =+IFERROR(VLOOKUP($AS$15,Sheet1!AH4:AK4,3,0),0) -> 0 | AT23: =+IFERROR(VLOOKUP($AT$15,Sheet1!AH4:AK4,3,0),0) -> 0 | AU23: =+IFERROR(VLOOKUP($AU$15,Sheet1!AH4:AK4,3,0),0) -> 0 | AV23: =+IFERROR(VLOOKUP($AV$15,Sheet1!AH4:AK4,3,0),0) -> 0 | AW23: =+IFERROR(VLOOKUP($AW$15,Sheet1!AH4:AK4,3,0),0) -> 0 | AX23: =+IFERROR(VLOOKUP($AX$15,Sheet1!AH4:AK4,3,0),0) -> 0 | AY23: =+IFERROR(VLOOKUP($AY$15,Sheet1!AH4:AK4,3,0),0) -> 0 | AZ23: =+IFERROR(VLOOKUP($AZ$15,Sheet1!AH4:AK4,3,0),0) -> 0 | BA23: =+IFERROR(VLOOKUP($BA$15,Sheet1!AH4:AK4,3,0),0) -> 0 | BB23: =+IFERROR(VLOOKUP($BB$15,Sheet1!AH4:AK4,3,0),0) -> 0 | BC23: =+IFERROR(VLOOKUP($BC$15,Sheet1!AL4:AO4,3,0),0) -> 0 | BD23: =+IFERROR(VLOOKUP($BD$15,Sheet1!AL4:AO4,3,0),0) -> 0 | BE23: =+IFERROR(VLOOKUP($BE$15,Sheet1!AL4:AO4,3,0),0) -> 0 | BF23: 408 | BG23: =+IFERROR(VLOOKUP($BG$15,Sheet1!AL4:AO4,3,0),0) -> 0 | BH23: =+IFERROR(VLOOKUP($BH$15,Sheet1!AL4:AO4,3,0),0) -> 0 | BI23: =+IFERROR(VLOOKUP($BI$15,Sheet1!AL4:AO4,3,0),0) -> 0 | BJ23: =+IFERROR(VLOOKUP($BJ$15,Sheet1!AL4:AO4,3,0),0) -> 0 | BK23: =+IFERROR(VLOOKUP($BK$15,Sheet1!AL4:AO4,3,0),0) -> 0 | BL23: =+IFERROR(VLOOKUP($BL$15,Sheet1!AL4:AO4,3,0),0) -> 0 | BM23: =+IFERROR(VLOOKUP($BM$15,Sheet1!AP4:AS4,3,0),0) -> 0 | BN23: =+IFERROR(VLOOKUP($BN$15,Sheet1!AT4:AW4,3,0),0) -> 0 | BO23: 40 | BP23: =+IFERROR(VLOOKUP($BP$15,Sheet1!BB4:BE4,3,0),0) -> 0 | BQ23: =+IFERROR(VLOOKUP($BQ$15,Sheet1!BF4:BI4,3,0),0) -> 0 | BR23: =+IFERROR(VLOOKUP($BR$15,Sheet1!BJ4:BM4,3,0),0) -> 0 | BS23: =+IFERROR(VLOOKUP($BS$15,Sheet1!BN4:BQ4,3,0),0) -> 0 | BT23: =+IFERROR(VLOOKUP($BT$15,Sheet1!BR4:BU4,3,0),0) -> 0 | BU23: =+IFERROR(VLOOKUP($BU$15,Sheet1!BV4:BY4,3,0),0) -> 0 | BV23: =Sheet1!E4 -> STEEL | BW23: =Sheet1!CV4 -> SP0400126 | BX23: =Sheet1!CW4 -> CORRUGATED DISPATCH STEEL DRUM 1900 X 830 X 915 MM | BY23: =VLOOKUP(C23,Sheet1!$C$1:$CX$17,100,0) -> 1000 | BZ23: =Sheet1!BZ4 -> 26600 | CA23: =SUMPRODUCT($N$16:$BU$16,N23:BU23)+BZ23 -> 474585 | CB23: =Sheet1!CB4 -> 0 | CC23: =CA23*CB23 -> 0 | CD23: 0.5 | CE23: =CA23*CD23 -> 237292.5 | CF23: =Sheet1!CF4 -> 0 | CG23: =CA23*CF23 -> 0 | CH23: =CA23+CC23+CE23+CG23 -> 711877.5 | CI23: 0.03 | CJ23: =CH23*CI23 -> 21356.325 | CK23: 0.02 | CL23: =CH23*CK23 -> 14237.55
A24: =Sheet1!A17 -> ENQ-11285-22-23 | B24: =Sheet1!B17 -> 45170 | C24: =Sheet1!C17 -> FA0900133 | D24: =Sheet1!D17 -> 2 CORE X 16 SQ. MM. AL/ARD - WIRE (XLPE) | E24: =CH24+CJ24+CL24 -> 114603.6 | F24: =ROUNDUP(M43,0) -> 4276 | G24: =E24+F24 -> 118879.6 | H24: 0.18 | I24: =G24*H24 -> 21398.328 | J24: =G24+I24 -> 140277.93 | K24: =Sheet1!CS17 -> 1511 | L24: =Sheet1!CT17 -> KMS | M24: =J24*K24 -> 2.1195995e+08 | N24: 86 | O24: =+IFERROR(VLOOKUP($O$15,Sheet1!J17:L17,3,0),0) -> 0 | P24: =+IFERROR(VLOOKUP($P$15,Sheet1!J17:M17,3,0),0) -> 0 | Q24: =+IFERROR(VLOOKUP($Q$15,Sheet1!J17:M17,3,0),0) -> 0 | R24: =+IFERROR(VLOOKUP($R$15,Sheet1!J17:M17,3,0),0) -> 0 | S24: =+IFERROR(VLOOKUP($S$15,Sheet1!N17:Q17,3,0),0) -> 0 | T24: =+IFERROR(VLOOKUP($T$15,Sheet1!N17:Q17,3,0),0) -> 0 | U24: =+IFERROR(VLOOKUP($U$15,Sheet1!F17:I17,3,0),0) -> 0 | V24: =+IFERROR(VLOOKUP($V$15,Sheet1!F17:I17,3,0),0) -> 0 | W24: =+IFERROR(VLOOKUP($W$15,Sheet1!F17:I17,3,0),0) -> 0 | X24: =+IFERROR(VLOOKUP($X$15,Sheet1!F17:I17,3,0),0) -> 0 | Y24: =+IFERROR(VLOOKUP($Y$15,Sheet1!F17:I17,3,0),0) -> 0 | Z24: =+IFERROR(VLOOKUP($Z$15,Sheet1!F17:I17,3,0),0) -> 0 | AA24: =+IFERROR(VLOOKUP($AA$15,Sheet1!F17:I17,3,0),0) -> 0 | AB24: =+IFERROR(VLOOKUP($AB$15,Sheet1!F17:I17,3,0),0) -> 0 | AC24: =+IFERROR(VLOOKUP($AC$15,Sheet1!R17:U17,3,0),0) -> 0 | AD24: =+IFERROR(VLOOKUP($AD$15,Sheet1!R17:U17,2,0),0) -> 0 | AE24: =+IFERROR(VLOOKUP($AE$15,Sheet1!V17:Y17,3,0),0) -> 0 | AF24: =+IFERROR(VLOOKUP($AF$15,Sheet1!V17:Y17,3,0),0) -> 37 | AG24: =+IFERROR(VLOOKUP($AG$15,Sheet1!V17:Y17,3,0),0) -> 0 | AH24: =+IFERROR(VLOOKUP($AH$15,Sheet1!V17:Y17,3,0),0) -> 0 | AI24: =+IFERROR(VLOOKUP($AI$15,Sheet1!V17:Y17,3,0),0) -> 0 | AJ24: =+IFERROR(VLOOKUP($AJ$15,Sheet1!V17:Y17,3,0),0) -> 0 | AK24: =+IFERROR(VLOOKUP($AK$15,Sheet1!Z17:AB17,3,0),0) -> 0 | AL24: =+IFERROR(VLOOKUP($AL$15,Sheet1!AD17:AG17,3,0),0) -> 0 | AM24: =+IFERROR(VLOOKUP($AM$15,Sheet1!AD17:AG17,3,0),0) -> 0 | AN24: =+IFERROR(VLOOKUP($AN$15,Sheet1!AD17:AG17,3,0),0) -> 0 | AO24: =+IFERROR(VLOOKUP($AO$15,Sheet1!AD17:AG17,3,0),0) -> 0 | AP24: =+IFERROR(VLOOKUP($AP$15,Sheet1!AD17:AG17,3,0),0) -> 0 | AQ24: =+IFERROR(VLOOKUP($AQ$15,Sheet1!AD17:AG17,3,0),0) -> 0 | AR24: 45 | AS24: =+IFERROR(VLOOKUP($AS$15,Sheet1!AH17:AK17,3,0),0) -> 0 | AT24: =+IFERROR(VLOOKUP($AT$15,Sheet1!AH17:AK17,3,0),0) -> 0 | AU24: =+IFERROR(VLOOKUP($AU$15,Sheet1!AH17:AK17,3,0),0) -> 0 | AV24: =+IFERROR(VLOOKUP($AV$15,Sheet1!AH17:AK17,3,0),0) -> 0 | AW24: =+IFERROR(VLOOKUP($AW$15,Sheet1!AH17:AK17,3,0),0) -> 0 | AX24: =+IFERROR(VLOOKUP($AX$15,Sheet1!AH17:AK17,3,0),0) -> 0 | AY24: =+IFERROR(VLOOKUP($AY$15,Sheet1!AH17:AK17,3,0),0) -> 0 | AZ24: =+IFERROR(VLOOKUP($AZ$15,Sheet1!AH17:AK17,3,0),0) -> 0 | BA24: 250 | BB24: =+IFERROR(VLOOKUP($BB$15,Sheet1!AH17:AK17,3,0),0) -> 0 | BC24: =+IFERROR(VLOOKUP($BC$15,Sheet1!AL17:AO17,3,0),0) -> 0 | BD24: =+IFERROR(VLOOKUP($BD$15,Sheet1!AL17:AO17,3,0),0) -> 0 | BE24: =+IFERROR(VLOOKUP($BE$15,Sheet1!AL17:AO17,3,0),0) -> 0 | BF24: 120 | BG24: =+IFERROR(VLOOKUP($BG$15,Sheet1!AL17:AO17,3,0),0) -> 0 | BH24: =+IFERROR(VLOOKUP($BH$15,Sheet1!AL17:AO17,3,0),0) -> 0 | BI24: =+IFERROR(VLOOKUP($BI$15,Sheet1!AL17:AO17,3,0),0) -> 0 | BJ24: =+IFERROR(VLOOKUP($BJ$15,Sheet1!AL17:AO17,3,0),0) -> 0 | BK24: =+IFERROR(VLOOKUP($BK$15,Sheet1!AL17:AO17,3,0),0) -> 0 | BL24: =+IFERROR(VLOOKUP($BL$15,Sheet1!AL17:AO17,3,0),0) -> 0 | BM24: =+IFERROR(VLOOKUP($BM$15,Sheet1!AP17:AS17,3,0),0) -> 0 | BN24: =+IFERROR(VLOOKUP($BN$15,Sheet1!AT17:AW17,3,0),0) -> 0 | BO24: =+IFERROR(VLOOKUP($BO$15,Sheet1!AX17:BA17,3,0),0) -> 0 | BP24: =+IFERROR(VLOOKUP($BP$15,Sheet1!BB17:BE17,3,0),0) -> 0 | BQ24: =+IFERROR(VLOOKUP($BQ$15,Sheet1!BF17:BI17,3,0),0) -> 0 | BR24: =+IFERROR(VLOOKUP($BR$15,Sheet1!BJ17:BM17,3,0),0) -> 0 | BS24: =+IFERROR(VLOOKUP($BS$15,Sheet1!BN17:BQ17,3,0),0) -> 0 | BT24: 11 | BU24: =+IFERROR(VLOOKUP($BU$15,Sheet1!BV17:BY17,3,0),0) -> 0 | BV24: =Sheet1!E17 -> Hybrid | BW24: =Sheet1!CV17 -> MD0100106 | BX24: =Sheet1!CW17 -> DRUM - 42 X 15 X 23 X 2 (LOMBU-HYBRID) | BY24: =VLOOKUP(C24,Sheet1!$C$1:$CX$17,100,0) -> 1000 | BZ24: =Sheet1!BZ17 -> 7244.19 | CA24: =SUMPRODUCT($N$16:$BU$16,N24:BU24)+BZ24 -> 72764.19 | CB24: =Sheet1!CB17 -> 0 | CC24: =CA24*CB24 -> 0 | CD24: 0.5 | CE24: =CA24*CD24 -> 36382.095 | CF24: =Sheet1!CF17 -> 0 | CG24: =CA24*CF24 -> 0 | CH24: =CA24+CC24+CE24+CG24 -> 109146.29 | CI24: 0.03 | CJ24: =CH24*CI24 -> 3274.3886 | CK24: 0.02 | CL24: =CH24*CK24 -> 2182.9257
A25: =Sheet1!A14 -> ENQ-11285-22-23 | B25: =Sheet1!B14 -> 45170 | C25: =Sheet1!C14 -> FA0900038 | D25: =Sheet1!D14 -> 2 CORE X 25 SQ. MM. AL/ARD - STRIP (XLPE) | E25: =CH25+CJ25+CL25 -> 137789.06 | F25: =ROUNDUP(M44,0) -> 4080 | G25: =E25+F25 -> 141869.06 | H25: 0.18 | I25: =G25*H25 -> 25536.432 | J25: =G25+I25 -> 167405.5 | K25: =Sheet1!CS14 -> 125 | L25: =Sheet1!CT14 -> KMS | M25: =J25*K25 -> 20925687 | N25: =+IFERROR(VLOOKUP($N$15,Sheet1!J14:L14,3,0),0) -> 135 | O25: =+IFERROR(VLOOKUP($O$15,Sheet1!J14:L14,3,0),0) -> 0 | P25: =+IFERROR(VLOOKUP($P$15,Sheet1!J14:M14,3,0),0) -> 0 | Q25: =+IFERROR(VLOOKUP($Q$15,Sheet1!J14:M14,3,0),0) -> 0 | R25: =+IFERROR(VLOOKUP($R$15,Sheet1!J14:M14,3,0),0) -> 0 | S25: =+IFERROR(VLOOKUP($S$15,Sheet1!N14:Q14,3,0),0) -> 0 | T25: =+IFERROR(VLOOKUP($T$15,Sheet1!N14:Q14,3,0),0) -> 0 | U25: =+IFERROR(VLOOKUP($U$15,Sheet1!F14:I14,3,0),0) -> 0 | V25: =+IFERROR(VLOOKUP($V$15,Sheet1!F14:I14,3,0),0) -> 0 | W25: =+IFERROR(VLOOKUP($W$15,Sheet1!F14:I14,3,0),0) -> 0 | X25: =+IFERROR(VLOOKUP($X$15,Sheet1!F14:I14,3,0),0) -> 0 | Y25: =+IFERROR(VLOOKUP($Y$15,Sheet1!F14:I14,3,0),0) -> 0 | Z25: =+IFERROR(VLOOKUP($Z$15,Sheet1!F14:I14,3,0),0) -> 0 | AA25: =+IFERROR(VLOOKUP($AA$15,Sheet1!F14:I14,3,0),0) -> 0 | AB25: =+IFERROR(VLOOKUP($AB$15,Sheet1!F14:I14,3,0),0) -> 0 | AC25: =+IFERROR(VLOOKUP($AC$15,Sheet1!R14:U14,3,0),0) -> 0 | AD25: =+IFERROR(VLOOKUP($AD$15,Sheet1!R14:U14,2,0),0) -> 0 | AE25: =+IFERROR(VLOOKUP($AE$15,Sheet1!V14:Y14,3,0),0) -> 0 | AF25: 44 | AG25: =+IFERROR(VLOOKUP($AG$15,Sheet1!V14:Y14,3,0),0) -> 0 | AH25: =+IFERROR(VLOOKUP($AH$15,Sheet1!V14:Y14,3,0),0) -> 0 | AI25: =+IFERROR(VLOOKUP($AI$15,Sheet1!V14:Y14,3,0),0) -> 0 | AJ25: =+IFERROR(VLOOKUP($AJ$15,Sheet1!V14:Y14,3,0),0) -> 0 | AK25: =+IFERROR(VLOOKUP($AK$15,Sheet1!Z14:AB14,3,0),0) -> 0 | AL25: =+IFERROR(VLOOKUP($AL$15,Sheet1!AD14:AG14,3,0),0) -> 0 | AM25: =+IFERROR(VLOOKUP($AM$15,Sheet1!AD14:AG14,3,0),0) -> 0 | AN25: =+IFERROR(VLOOKUP($AN$15,Sheet1!AD14:AG14,3,0),0) -> 0 | AO25: =+IFERROR(VLOOKUP($AO$15,Sheet1!AD14:AG14,3,0),0) -> 0 | AP25: =+IFERROR(VLOOKUP($AP$15,Sheet1!AD14:AG14,3,0),0) -> 0 | AQ25: =+IFERROR(VLOOKUP($AQ$15,Sheet1!AD14:AG14,3,0),0) -> 0 | AR25: 50 | AS25: =+IFERROR(VLOOKUP($AS$15,Sheet1!AH14:AK14,3,0),0) -> 0 | AT25: =+IFERROR(VLOOKUP($AT$15,Sheet1!AH14:AK14,3,0),0) -> 0 | AU25: =+IFERROR(VLOOKUP($AU$15,Sheet1!AH14:AK14,3,0),0) -> 0 | AV25: =+IFERROR(VLOOKUP($AV$15,Sheet1!AH14:AK14,3,0),0) -> 0 | AW25: =+IFERROR(VLOOKUP($AW$15,Sheet1!AH14:AK14,3,0),0) -> 0 | AX25: 275 | AY25: =+IFERROR(VLOOKUP($AY$15,Sheet1!AH14:AK14,3,0),0) -> 0 | AZ25: =+IFERROR(VLOOKUP($AZ$15,Sheet1!AH14:AK14,3,0),0) -> 0 | BA25: =+IFERROR(VLOOKUP($BA$15,Sheet1!AH14:AK14,3,0),0) -> 0 | BB25: =+IFERROR(VLOOKUP($BB$15,Sheet1!AH14:AK14,3,0),0) -> 0 | BC25: =+IFERROR(VLOOKUP($BC$15,Sheet1!AL14:AO14,3,0),0) -> 0 | BD25: =+IFERROR(VLOOKUP($BD$15,Sheet1!AL14:AO14,3,0),0) -> 0 | BE25: =+IFERROR(VLOOKUP($BE$15,Sheet1!AL14:AO14,3,0),0) -> 0 | BF25: 145 | BG25: =+IFERROR(VLOOKUP($BG$15,Sheet1!AL14:AO14,3,0),0) -> 0 | BH25: =+IFERROR(VLOOKUP($BH$15,Sheet1!AL14:AO14,3,0),0) -> 0 | BI25: =+IFERROR(VLOOKUP($BI$15,Sheet1!AL14:AO14,3,0),0) -> 0 | BJ25: =+IFERROR(VLOOKUP($BJ$15,Sheet1!AL14:AO14,3,0),0) -> 0 | BK25: =+IFERROR(VLOOKUP($BK$15,Sheet1!AL14:AO14,3,0),0) -> 0 | BL25: =+IFERROR(VLOOKUP($BL$15,Sheet1!AL14:AO14,3,0),0) -> 0 | BM25: =+IFERROR(VLOOKUP($BM$15,Sheet1!AP14:AS14,3,0),0) -> 0 | BN25: =+IFERROR(VLOOKUP($BN$15,Sheet1!AT14:AW14,3,0),0) -> 0 | BO25: =+IFERROR(VLOOKUP($BO$15,Sheet1!AX14:BA14,3,0),0) -> 0 | BP25: =+IFERROR(VLOOKUP($BP$15,Sheet1!BB14:BE14,3,0),0) -> 0 | BQ25: =+IFERROR(VLOOKUP($BQ$15,Sheet1!BF14:BI14,3,0),0) -> 0 | BR25: =+IFERROR(VLOOKUP($BR$15,Sheet1!BJ14:BM14,3,0),0) -> 0 | BS25: =+IFERROR(VLOOKUP($BS$15,Sheet1!BN14:BQ14,3,0),0) -> 0 | BT25: 13 | BU25: =+IFERROR(VLOOKUP($BU$15,Sheet1!BV14:BY14,3,0),0) -> 0 | BV25: =Sheet1!E14 -> Hybrid | BW25: =Sheet1!CV14 -> MD0100105 | BX25: =Sheet1!CW14 -> DRUM - 42 X 24 X 38 X 2 (LOMBU-HYBRID) | BY25: =VLOOKUP(C25,Sheet1!$C$1:$CX$17,100,0) -> 1000 | BZ25: =Sheet1!BZ14 -> 7976.12 | CA25: =SUMPRODUCT($N$16:$BU$16,N25:BU25)+BZ25 -> 87485.12 | CB25: =Sheet1!CB14 -> 0 | CC25: =CA25*CB25 -> 0 | CD25: 0.5 | CE25: =CA25*CD25 -> 43742.56 | CF25: =Sheet1!CF14 -> 0 | CG25: =CA25*CF25 -> 0 | CH25: =CA25+CC25+CE25+CG25 -> 131227.68 | CI25: 0.03 | CJ25: =CH25*CI25 -> 3936.8304 | CK25: 0.02 | CL25: =CH25*CK25 -> 2624.5536
A26: =Sheet1!A16 -> ENQ-11285-22-23 | B26: =Sheet1!B16 -> 45170 | C26: =Sheet1!C16 -> FA0900015 | D26: =Sheet1!D16 -> 4 CORE X 25 SQ. MM. ALU/ARD - STRIP (XLPE) | E26: =CH26+CJ26+CL26 -> 204072.75 | F26: =ROUNDUP(M45,0) -> 5715 | G26: =E26+F26 -> 209787.75 | H26: 0.18 | I26: =G26*H26 -> 37761.795 | J26: =G26+I26 -> 247549.54 | K26: =Sheet1!CS16 -> 357 | L26: =Sheet1!CT16 -> KMS | M26: =J26*K26 -> 88375188 | N26: =+IFERROR(VLOOKUP($N$15,Sheet1!J16:L16,3,0),0) -> 270 | O26: =+IFERROR(VLOOKUP($O$15,Sheet1!J16:L16,3,0),0) -> 0 | P26: =+IFERROR(VLOOKUP($P$15,Sheet1!J16:M16,3,0),0) -> 0 | Q26: =+IFERROR(VLOOKUP($Q$15,Sheet1!J16:M16,3,0),0) -> 0 | R26: =+IFERROR(VLOOKUP($R$15,Sheet1!J16:M16,3,0),0) -> 0 | S26: =+IFERROR(VLOOKUP($S$15,Sheet1!N16:Q16,3,0),0) -> 0 | T26: =+IFERROR(VLOOKUP($T$15,Sheet1!N16:Q16,3,0),0) -> 0 | U26: =+IFERROR(VLOOKUP($U$15,Sheet1!F16:I16,3,0),0) -> 0 | V26: =+IFERROR(VLOOKUP($V$15,Sheet1!F16:I16,3,0),0) -> 0 | W26: =+IFERROR(VLOOKUP($W$15,Sheet1!F16:I16,3,0),0) -> 0 | X26: =+IFERROR(VLOOKUP($X$15,Sheet1!F16:I16,3,0),0) -> 0 | Y26: =+IFERROR(VLOOKUP($Y$15,Sheet1!F16:I16,3,0),0) -> 0 | Z26: =+IFERROR(VLOOKUP($Z$15,Sheet1!F16:I16,3,0),0) -> 0 | AA26: =+IFERROR(VLOOKUP($AA$15,Sheet1!F16:I16,3,0),0) -> 0 | AB26: =+IFERROR(VLOOKUP($AB$15,Sheet1!F16:I16,3,0),0) -> 0 | AC26: =+IFERROR(VLOOKUP($AC$15,Sheet1!R16:U16,3,0),0) -> 0 | AD26: =+IFERROR(VLOOKUP($AD$15,Sheet1!R16:U16,2,0),0) -> 0 | AE26: =+IFERROR(VLOOKUP($AE$15,Sheet1!V16:Y16,3,0),0) -> 0 | AF26: =+IFERROR(VLOOKUP($AF$15,Sheet1!V16:Y16,3,0),0) -> 95 | AG26: =+IFERROR(VLOOKUP($AG$15,Sheet1!V16:Y16,3,0),0) -> 0 | AH26: =+IFERROR(VLOOKUP($AH$15,Sheet1!V16:Y16,3,0),0) -> 0 | AI26: =+IFERROR(VLOOKUP($AI$15,Sheet1!V16:Y16,3,0),0) -> 0 | AJ26: =+IFERROR(VLOOKUP($AJ$15,Sheet1!V16:Y16,3,0),0) -> 0 | AK26: =+IFERROR(VLOOKUP($AK$15,Sheet1!Z16:AB16,3,0),0) -> 0 | AL26: =+IFERROR(VLOOKUP($AL$15,Sheet1!AD16:AG16,3,0),0) -> 0 | AM26: =+IFERROR(VLOOKUP($AM$15,Sheet1!AD16:AG16,3,0),0) -> 0 | AN26: =+IFERROR(VLOOKUP($AN$15,Sheet1!AD16:AG16,3,0),0) -> 0 | AO26: =+IFERROR(VLOOKUP($AO$15,Sheet1!AD16:AG16,3,0),0) -> 0 | AP26: =+IFERROR(VLOOKUP($AP$15,Sheet1!AD16:AG16,3,0),0) -> 0 | AQ26: =+IFERROR(VLOOKUP($AQ$15,Sheet1!AD16:AG16,3,0),0) -> 46 | AR26: =+IFERROR(VLOOKUP($AR$15,Sheet1!AD16:AG16,3,0),0) -> 0 | AS26: =+IFERROR(VLOOKUP($AS$15,Sheet1!AH16:AK16,3,0),0) -> 0 | AT26: =+IFERROR(VLOOKUP($AT$15,Sheet1!AH16:AK16,3,0),0) -> 0 | AU26: =+IFERROR(VLOOKUP($AU$15,Sheet1!AH16:AK16,3,0),0) -> 0 | AV26: =+IFERROR(VLOOKUP($AV$15,Sheet1!AH16:AK16,3,0),0) -> 0 | AW26: =+IFERROR(VLOOKUP($AW$15,Sheet1!AH16:AK16,3,0),0) -> 0 | AX26: =+IFERROR(VLOOKUP($AX$15,Sheet1!AH16:AK16,3,0),0) -> 364 | AY26: =+IFERROR(VLOOKUP($AY$15,Sheet1!AH16:AK16,3,0),0) -> 0 | AZ26: =+IFERROR(VLOOKUP($AZ$15,Sheet1!AH16:AK16,3,0),0) -> 0 | BA26: =+IFERROR(VLOOKUP($BA$15,Sheet1!AH16:AK16,3,0),0) -> 0 | BB26: =+IFERROR(VLOOKUP($BB$15,Sheet1!AH16:AK16,3,0),0) -> 0 | BC26: =+IFERROR(VLOOKUP($BC$15,Sheet1!AL16:AO16,3,0),0) -> 0 | BD26: =+IFERROR(VLOOKUP($BD$15,Sheet1!AL16:AO16,3,0),0) -> 0 | BE26: =+IFERROR(VLOOKUP($BE$15,Sheet1!AL16:AO16,3,0),0) -> 0 | BF26: =+IFERROR(VLOOKUP($BF$15,Sheet1!AL16:AO16,3,0),0) -> 173 | BG26: =+IFERROR(VLOOKUP($BG$15,Sheet1!AL16:AO16,3,0),0) -> 0 | BH26: =+IFERROR(VLOOKUP($BH$15,Sheet1!AL16:AO16,3,0),0) -> 0 | BI26: =+IFERROR(VLOOKUP($BI$15,Sheet1!AL16:AO16,3,0),0) -> 0 | BJ26: =+IFERROR(VLOOKUP($BJ$15,Sheet1!AL16:AO16,3,0),0) -> 0 | BK26: =+IFERROR(VLOOKUP($BK$15,Sheet1!AL16:AO16,3,0),0) -> 0 | BL26: =+IFERROR(VLOOKUP($BL$15,Sheet1!AL16:AO16,3,0),0) -> 0 | BM26: =+IFERROR(VLOOKUP($BM$15,Sheet1!AP16:AS16,3,0),0) -> 0 | BN26: =+IFERROR(VLOOKUP($BN$15,Sheet1!AT16:AW16,3,0),0) -> 0 | BO26: =+IFERROR(VLOOKUP($BO$15,Sheet1!AX16:BA16,3,0),0) -> 0 | BP26: =+IFERROR(VLOOKUP($BP$15,Sheet1!BB16:BE16,3,0),0) -> 0 | BQ26: =+IFERROR(VLOOKUP($BQ$15,Sheet1!BF16:BI16,3,0),0) -> 0 | BR26: =+IFERROR(VLOOKUP($BR$15,Sheet1!BJ16:BM16,3,0),0) -> 0 | BS26: =+IFERROR(VLOOKUP($BS$15,Sheet1!BN16:BQ16,3,0),0) -> 0 | BT26: 13 | BU26: =+IFERROR(VLOOKUP($BU$15,Sheet1!BV16:BY16,3,0),0) -> 0 | BV26: =Sheet1!E16 -> Hybrid | BW26: =Sheet1!CV16 -> MD0100092 | BX26: =Sheet1!CW16 -> DRUM - 42 X 18 X 36 X 2 (LOMBU) | BY26: =VLOOKUP(C26,Sheet1!$C$1:$CX$17,100,0) -> 1000 | BZ26: 7374 | CA26: =SUMPRODUCT($N$16:$BU$16,N26:BU26)+BZ26 -> 129570 | CB26: =Sheet1!CB16 -> 0 | CC26: =CA26*CB26 -> 0 | CD26: 0.5 | CE26: =CA26*CD26 -> 64785 | CF26: =Sheet1!CF16 -> 0 | CG26: =CA26*CF26 -> 0 | CH26: =CA26+CC26+CE26+CG26 -> 194355 | CI26: 0.03 | CJ26: =CH26*CI26 -> 5830.65 | CK26: 0.02 | CL26: =CH26*CK26 -> 3887.1
A27: =Sheet1!A13 -> ENQ-11285-22-23 | B27: =Sheet1!B13 -> 45170 | C27: =Sheet1!C13 -> FA0900036 | D27: =Sheet1!D13 -> 4 CORE X 50 SQ. MM. ALU/ARD - STRIP (XLPE) | E27: =CH27+CJ27+CL27 -> 348018.3 | F27: =ROUNDUP(M46,0) -> 7887 | G27: =E27+F27 -> 355905.3 | H27: 0.18 | I27: =G27*H27 -> 64062.954 | J27: =G27+I27 -> 419968.25 | K27: =Sheet1!CS13 -> 97 | L27: =Sheet1!CT13 -> KMS | M27: =J27*K27 -> 40736921 | N27: =+IFERROR(VLOOKUP($N$15,Sheet1!J13:L13,3,0),0) -> 540 | O27: =+IFERROR(VLOOKUP($O$15,Sheet1!J13:L13,3,0),0) -> 0 | P27: =+IFERROR(VLOOKUP($P$15,Sheet1!J13:M13,3,0),0) -> 0 | Q27: =+IFERROR(VLOOKUP($Q$15,Sheet1!J13:M13,3,0),0) -> 0 | R27: =+IFERROR(VLOOKUP($R$15,Sheet1!J13:M13,3,0),0) -> 0 | S27: =+IFERROR(VLOOKUP($S$15,Sheet1!N13:Q13,3,0),0) -> 0 | T27: =+IFERROR(VLOOKUP($T$15,Sheet1!N13:Q13,3,0),0) -> 0 | U27: =+IFERROR(VLOOKUP($U$15,Sheet1!F13:I13,3,0),0) -> 0 | V27: =+IFERROR(VLOOKUP($V$15,Sheet1!F13:I13,3,0),0) -> 0 | W27: =+IFERROR(VLOOKUP($W$15,Sheet1!F13:I13,3,0),0) -> 0 | X27: =+IFERROR(VLOOKUP($X$15,Sheet1!F13:I13,3,0),0) -> 0 | Y27: =+IFERROR(VLOOKUP($Y$15,Sheet1!F13:I13,3,0),0) -> 0 | Z27: =+IFERROR(VLOOKUP($Z$15,Sheet1!F13:I13,3,0),0) -> 0 | AA27: =+IFERROR(VLOOKUP($AA$15,Sheet1!F13:I13,3,0),0) -> 0 | AB27: =+IFERROR(VLOOKUP($AB$15,Sheet1!F13:I13,3,0),0) -> 0 | AC27: =+IFERROR(VLOOKUP($AC$15,Sheet1!R13:U13,3,0),0) -> 0 | AD27: =+IFERROR(VLOOKUP($AD$15,Sheet1!R13:U13,2,0),0) -> 0 | AE27: =+IFERROR(VLOOKUP($AE$15,Sheet1!V13:Y13,3,0),0) -> 0 | AF27: =+IFERROR(VLOOKUP($AF$15,Sheet1!V13:Y13,3,0),0) -> 124 | AG27: =+IFERROR(VLOOKUP($AG$15,Sheet1!V13:Y13,3,0),0) -> 0 | AH27: =+IFERROR(VLOOKUP($AH$15,Sheet1!V13:Y13,3,0),0) -> 0 | AI27: =+IFERROR(VLOOKUP($AI$15,Sheet1!V13:Y13,3,0),0) -> 0 | AJ27: =+IFERROR(VLOOKUP($AJ$15,Sheet1!V13:Y13,3,0),0) -> 0 | AK27: =+IFERROR(VLOOKUP($AK$15,Sheet1!Z13:AB13,3,0),0) -> 0 | AL27: =+IFERROR(VLOOKUP($AL$15,Sheet1!AD13:AG13,3,0),0) -> 0 | AM27: =+IFERROR(VLOOKUP($AM$15,Sheet1!AD13:AG13,3,0),0) -> 0 | AN27: =+IFERROR(VLOOKUP($AN$15,Sheet1!AD13:AG13,3,0),0) -> 0 | AO27: =+IFERROR(VLOOKUP($AO$15,Sheet1!AD13:AG13,3,0),0) -> 0 | AP27: =+IFERROR(VLOOKUP($AP$15,Sheet1!AD13:AG13,3,0),0) -> 0 | AQ27: =+IFERROR(VLOOKUP($AQ$15,Sheet1!AD13:AG13,3,0),0) -> 69 | AR27: =+IFERROR(VLOOKUP($AR$15,Sheet1!AD13:AG13,3,0),0) -> 0 | AS27: =+IFERROR(VLOOKUP($AS$15,Sheet1!AH13:AK13,3,0),0) -> 0 | AT27: =+IFERROR(VLOOKUP($AT$15,Sheet1!AH13:AK13,3,0),0) -> 0 | AU27: =+IFERROR(VLOOKUP($AU$15,Sheet1!AH13:AK13,3,0),0) -> 0 | AV27: =+IFERROR(VLOOKUP($AV$15,Sheet1!AH13:AK13,3,0),0) -> 0 | AW27: =+IFERROR(VLOOKUP($AW$15,Sheet1!AH13:AK13,3,0),0) -> 0 | AX27: =+IFERROR(VLOOKUP($AX$15,Sheet1!AH13:AK13,3,0),0) -> 457 | AY27: =+IFERROR(VLOOKUP($AY$15,Sheet1!AH13:AK13,3,0),0) -> 0 | AZ27: =+IFERROR(VLOOKUP($AZ$15,Sheet1!AH13:AK13,3,0),0) -> 0 | BA27: =+IFERROR(VLOOKUP($BA$15,Sheet1!AH13:AK13,3,0),0) -> 0 | BB27: =+IFERROR(VLOOKUP($BB$15,Sheet1!AH13:AK13,3,0),0) -> 0 | BC27: =+IFERROR(VLOOKUP($BC$15,Sheet1!AL13:AO13,3,0),0) -> 0 | BD27: =+IFERROR(VLOOKUP($BD$15,Sheet1!AL13:AO13,3,0),0) -> 0 | BE27: =+IFERROR(VLOOKUP($BE$15,Sheet1!AL13:AO13,3,0),0) -> 0 | BF27: =+IFERROR(VLOOKUP($BF$15,Sheet1!AL13:AO13,3,0),0) -> 240 | BG27: =+IFERROR(VLOOKUP($BG$15,Sheet1!AL13:AO13,3,0),0) -> 0 | BH27: =+IFERROR(VLOOKUP($BH$15,Sheet1!AL13:AO13,3,0),0) -> 0 | BI27: =+IFERROR(VLOOKUP($BI$15,Sheet1!AL13:AO13,3,0),0) -> 0 | BJ27: =+IFERROR(VLOOKUP($BJ$15,Sheet1!AL13:AO13,3,0),0) -> 0 | BK27: =+IFERROR(VLOOKUP($BK$15,Sheet1!AL13:AO13,3,0),0) -> 0 | BL27: =+IFERROR(VLOOKUP($BL$15,Sheet1!AL13:AO13,3,0),0) -> 0 | BM27: =+IFERROR(VLOOKUP($BM$15,Sheet1!AP13:AS13,3,0),0) -> 0 | BN27: =+IFERROR(VLOOKUP($BN$15,Sheet1!AT13:AW13,3,0),0) -> 0 | BO27: =+IFERROR(VLOOKUP($BO$15,Sheet1!AX13:BA13,3,0),0) -> 0 | BP27: =+IFERROR(VLOOKUP($BP$15,Sheet1!BB13:BE13,3,0),0) -> 0 | BQ27: =+IFERROR(VLOOKUP($BQ$15,Sheet1!BF13:BI13,3,0),0) -> 0 | BR27: =+IFERROR(VLOOKUP($BR$15,Sheet1!BJ13:BM13,3,0),0) -> 0 | BS27: =+IFERROR(VLOOKUP($BS$15,Sheet1!BN13:BQ13,3,0),0) -> 0 | BT27: 17 | BU27: =+IFERROR(VLOOKUP($BU$15,Sheet1!BV13:BY13,3,0),0) -> 0 | BV27: =Sheet1!E13 -> STEEL | BW27: SP0400125 | BX27: CORRUGATED DISPATCH STEEL DRUM 1600 X 700 X 915 MM | BY27: =VLOOKUP(C27,Sheet1!$C$1:$CX$17,100,0) -> 1000 | BZ27: 20900 | CA27: =SUMPRODUCT($N$16:$BU$16,N27:BU27)+BZ27 -> 220964 | CB27: =Sheet1!CB13 -> 0 | CC27: =CA27*CB27 -> 0 | CD27: 0.5 | CE27: =CA27*CD27 -> 110482 | CF27: =Sheet1!CF13 -> 0 | CG27: =CA27*CF27 -> 0 | CH27: =CA27+CC27+CE27+CG27 -> 331446 | CI27: 0.03 | CJ27: =CH27*CI27 -> 9943.38 | CK27: 0.02 | CL27: =CH27*CK27 -> 6628.92
A28: =Sheet1!A12 -> ENQ-11285-22-23 | B28: =Sheet1!B12 -> 45170 | C28: =Sheet1!C12 -> FA1100012 | D28: =Sheet1!D12 -> 4 CORE X 95 SQ. MM. AL/ARD - STRIP (XLPE) | E28: =CH28+CJ28+CL28 -> 564254.77 | F28: =ROUNDUP(M47,0) -> 15549 | G28: =E28+F28 -> 579803.77 | H28: 0.18 | I28: =G28*H28 -> 104364.68 | J28: =G28+I28 -> 684168.45 | K28: =Sheet1!CS12 -> 82 | L28: =Sheet1!CT12 -> KMS | M28: =J28*K28 -> 56101813 | N28: =+IFERROR(VLOOKUP($N$15,Sheet1!J12:L12,3,0),0) -> 1026 | O28: =+IFERROR(VLOOKUP($O$15,Sheet1!J12:L12,3,0),0) -> 0 | P28: =+IFERROR(VLOOKUP($P$15,Sheet1!J12:M12,3,0),0) -> 0 | Q28: =+IFERROR(VLOOKUP($Q$15,Sheet1!J12:M12,3,0),0) -> 0 | R28: =+IFERROR(VLOOKUP($R$15,Sheet1!J12:M12,3,0),0) -> 0 | S28: =+IFERROR(VLOOKUP($S$15,Sheet1!N12:Q12,3,0),0) -> 0 | T28: =+IFERROR(VLOOKUP($T$15,Sheet1!N12:Q12,3,0),0) -> 0 | U28: =+IFERROR(VLOOKUP($U$15,Sheet1!F12:I12,3,0),0) -> 0 | V28: =+IFERROR(VLOOKUP($V$15,Sheet1!F12:I12,3,0),0) -> 0 | W28: =+IFERROR(VLOOKUP($W$15,Sheet1!F12:I12,3,0),0) -> 0 | X28: =+IFERROR(VLOOKUP($X$15,Sheet1!F12:I12,3,0),0) -> 0 | Y28: =+IFERROR(VLOOKUP($Y$15,Sheet1!F12:I12,3,0),0) -> 0 | Z28: =+IFERROR(VLOOKUP($Z$15,Sheet1!F12:I12,3,0),0) -> 0 | AA28: =+IFERROR(VLOOKUP($AA$15,Sheet1!F12:I12,3,0),0) -> 0 | AB28: =+IFERROR(VLOOKUP($AB$15,Sheet1!F12:I12,3,0),0) -> 0 | AC28: =+IFERROR(VLOOKUP($AC$15,Sheet1!R12:U12,3,0),0) -> 0 | AD28: =+IFERROR(VLOOKUP($AD$15,Sheet1!R12:U12,2,0),0) -> 0 | AE28: =+IFERROR(VLOOKUP($AE$15,Sheet1!V12:Y12,3,0),0) -> 0 | AF28: =+IFERROR(VLOOKUP($AF$15,Sheet1!V12:Y12,3,0),0) -> 187 | AG28: =+IFERROR(VLOOKUP($AG$15,Sheet1!V12:Y12,3,0),0) -> 0 | AH28: =+IFERROR(VLOOKUP($AH$15,Sheet1!V12:Y12,3,0),0) -> 0 | AI28: =+IFERROR(VLOOKUP($AI$15,Sheet1!V12:Y12,3,0),0) -> 0 | AJ28: =+IFERROR(VLOOKUP($AJ$15,Sheet1!V12:Y12,3,0),0) -> 0 | AK28: =+IFERROR(VLOOKUP($AK$15,Sheet1!Z12:AB12,3,0),0) -> 0 | AL28: =+IFERROR(VLOOKUP($AL$15,Sheet1!AD12:AG12,3,0),0) -> 0 | AM28: =+IFERROR(VLOOKUP($AM$15,Sheet1!AD12:AG12,3,0),0) -> 0 | AN28: =+IFERROR(VLOOKUP($AN$15,Sheet1!AD12:AG12,3,0),0) -> 0 | AO28: =+IFERROR(VLOOKUP($AO$15,Sheet1!AD12:AG12,3,0),0) -> 0 | AP28: =+IFERROR(VLOOKUP($AP$15,Sheet1!AD12:AG12,3,0),0) -> 0 | AQ28: =+IFERROR(VLOOKUP($AQ$15,Sheet1!AD12:AG12,3,0),0) -> 93 | AR28: =+IFERROR(VLOOKUP($AR$15,Sheet1!AD12:AG12,3,0),0) -> 0 | AS28: =+IFERROR(VLOOKUP($AS$15,Sheet1!AH12:AK12,3,0),0) -> 0 | AT28: =+IFERROR(VLOOKUP($AT$15,Sheet1!AH12:AK12,3,0),0) -> 0 | AU28: =+IFERROR(VLOOKUP($AU$15,Sheet1!AH12:AK12,3,0),0) -> 0 | AV28: =+IFERROR(VLOOKUP($AV$15,Sheet1!AH12:AK12,3,0),0) -> 0 | AW28: =+IFERROR(VLOOKUP($AW$15,Sheet1!AH12:AK12,3,0),0) -> 0 | AX28: =+IFERROR(VLOOKUP($AX$15,Sheet1!AH12:AK12,3,0),0) -> 611 | AY28: =+IFERROR(VLOOKUP($AY$15,Sheet1!AH12:AK12,3,0),0) -> 0 | AZ28: =+IFERROR(VLOOKUP($AZ$15,Sheet1!AH12:AK12,3,0),0) -> 0 | BA28: =+IFERROR(VLOOKUP($BA$15,Sheet1!AH12:AK12,3,0),0) -> 0 | BB28: =+IFERROR(VLOOKUP($BB$15,Sheet1!AH12:AK12,3,0),0) -> 0 | BC28: =+IFERROR(VLOOKUP($BC$15,Sheet1!AL12:AO12,3,0),0) -> 0 | BD28: =+IFERROR(VLOOKUP($BD$15,Sheet1!AL12:AO12,3,0),0) -> 0 | BE28: =+IFERROR(VLOOKUP($BE$15,Sheet1!AL12:AO12,3,0),0) -> 0 | BF28: =+IFERROR(VLOOKUP($BF$15,Sheet1!AL12:AO12,3,0),0) -> 348 | BG28: =+IFERROR(VLOOKUP($BG$15,Sheet1!AL12:AO12,3,0),0) -> 0 | BH28: =+IFERROR(VLOOKUP($BH$15,Sheet1!AL12:AO12,3,0),0) -> 0 | BI28: =+IFERROR(VLOOKUP($BI$15,Sheet1!AL12:AO12,3,0),0) -> 0 | BJ28: =+IFERROR(VLOOKUP($BJ$15,Sheet1!AL12:AO12,3,0),0) -> 0 | BK28: =+IFERROR(VLOOKUP($BK$15,Sheet1!AL12:AO12,3,0),0) -> 0 | BL28: =+IFERROR(VLOOKUP($BL$15,Sheet1!AL12:AO12,3,0),0) -> 0 | BM28: =+IFERROR(VLOOKUP($BM$15,Sheet1!AP12:AS12,3,0),0) -> 0 | BN28: =+IFERROR(VLOOKUP($BN$15,Sheet1!AT12:AW12,3,0),0) -> 0 | BO28: =+IFERROR(VLOOKUP($BO$15,Sheet1!AX12:BA12,3,0),0) -> 0 | BP28: =+IFERROR(VLOOKUP($BP$15,Sheet1!BB12:BE12,3,0),0) -> 0 | BQ28: =+IFERROR(VLOOKUP($BQ$15,Sheet1!BF12:BI12,3,0),0) -> 0 | BR28: =+IFERROR(VLOOKUP($BR$15,Sheet1!BJ12:BM12,3,0),0) -> 0 | BS28: =+IFERROR(VLOOKUP($BS$15,Sheet1!BN12:BQ12,3,0),0) -> 0 | BT28: 22.5 | BU28: =+IFERROR(VLOOKUP($BU$15,Sheet1!BV12:BY12,3,0),0) -> 0 | BV28: =Sheet1!E12 -> STEEL | BW28: SP0400124 | BX28: CORRUGATED DISPATCH STEEL DRUM 1220 X 550 X 915 MM | BY28: =VLOOKUP(C28,Sheet1!$C$1:$CX$17,100,0) -> 500 | BZ28: =10450*2 -> 20900 | CA28: =SUMPRODUCT($N$16:$BU$16,N28:BU28)+BZ28 -> 358257 | CB28: =Sheet1!CB12 -> 0 | CC28: =CA28*CB28 -> 0 | CD28: 0.5 | CE28: =CA28*CD28 -> 179128.5 | CF28: =Sheet1!CF12 -> 0 | CG28: =CA28*CF28 -> 0 | CH28: =CA28+CC28+CE28+CG28 -> 537385.5 | CI28: 0.03 | CJ28: =CH28*CI28 -> 16121.565 | CK28: 0.02 | CL28: =CH28*CK28 -> 10747.71
A29: =Sheet1!A9 -> ENQ-11285-22-23 | B29: =Sheet1!B9 -> 45170 | C29: =Sheet1!C9 -> FA1100262 | D29: =Sheet1!D9 -> 4 CORE X 150 SQ. MM. AL/ARD - STRIP/TYPE - B (XLPE) | E29: =CH29+CJ29+CL29 -> 977476.5 | F29: =ROUNDUP(M48,0) -> 22667 | G29: =E29+F29 -> 1000143.5 | H29: 0.18 | I29: =G29*H29 -> 180025.83 | J29: =G29+I29 -> 1180169.3 | K29: =Sheet1!CS9 -> 45 | L29: =Sheet1!CT9 -> KMS | M29: =J29*K29 -> 53107620 | N29: =+IFERROR(VLOOKUP($N$15,Sheet1!J9:L9,3,0),0) -> 1620 | O29: =+IFERROR(VLOOKUP($O$15,Sheet1!J9:L9,3,0),0) -> 0 | P29: =+IFERROR(VLOOKUP($P$15,Sheet1!J9:M9,3,0),0) -> 0 | Q29: =+IFERROR(VLOOKUP($Q$15,Sheet1!J9:M9,3,0),0) -> 0 | R29: =+IFERROR(VLOOKUP($R$15,Sheet1!J9:M9,3,0),0) -> 0 | S29: =+IFERROR(VLOOKUP($S$15,Sheet1!N9:Q9,3,0),0) -> 0 | T29: =+IFERROR(VLOOKUP($T$15,Sheet1!N9:Q9,3,0),0) -> 0 | U29: =+IFERROR(VLOOKUP($U$15,Sheet1!F9:I9,3,0),0) -> 0 | V29: =+IFERROR(VLOOKUP($V$15,Sheet1!F9:I9,3,0),0) -> 0 | W29: =+IFERROR(VLOOKUP($W$15,Sheet1!F9:I9,3,0),0) -> 0 | X29: =+IFERROR(VLOOKUP($X$15,Sheet1!F9:I9,3,0),0) -> 0 | Y29: =+IFERROR(VLOOKUP($Y$15,Sheet1!F9:I9,3,0),0) -> 0 | Z29: =+IFERROR(VLOOKUP($Z$15,Sheet1!F9:I9,3,0),0) -> 0 | AA29: =+IFERROR(VLOOKUP($AA$15,Sheet1!F9:I9,3,0),0) -> 0 | AB29: =+IFERROR(VLOOKUP($AB$15,Sheet1!F9:I9,3,0),0) -> 0 | AC29: =+IFERROR(VLOOKUP($AC$15,Sheet1!R9:U9,3,0),0) -> 0 | AD29: =+IFERROR(VLOOKUP($AD$15,Sheet1!R9:U9,2,0),0) -> 0 | AE29: =+IFERROR(VLOOKUP($AE$15,Sheet1!V9:Y9,3,0),0) -> 0 | AF29: 285 | AG29: =+IFERROR(VLOOKUP($AG$15,Sheet1!V9:Y9,3,0),0) -> 0 | AH29: =+IFERROR(VLOOKUP($AH$15,Sheet1!V9:Y9,3,0),0) -> 0 | AI29: =+IFERROR(VLOOKUP($AI$15,Sheet1!V9:Y9,3,0),0) -> 0 | AJ29: =+IFERROR(VLOOKUP($AJ$15,Sheet1!V9:Y9,3,0),0) -> 0 | AK29: =+IFERROR(VLOOKUP($AK$15,Sheet1!Z9:AB9,3,0),0) -> 0 | AL29: =+IFERROR(VLOOKUP($AL$15,Sheet1!AD9:AG9,3,0),0) -> 0 | AM29: =+IFERROR(VLOOKUP($AM$15,Sheet1!AD9:AG9,3,0),0) -> 0 | AN29: =+IFERROR(VLOOKUP($AN$15,Sheet1!AD9:AG9,3,0),0) -> 0 | AO29: =+IFERROR(VLOOKUP($AO$15,Sheet1!AD9:AG9,3,0),0) -> 0 | AP29: =+IFERROR(VLOOKUP($AP$15,Sheet1!AD9:AG9,3,0),0) -> 0 | AQ29: 138 | AR29: =+IFERROR(VLOOKUP($AR$15,Sheet1!AD9:AG9,3,0),0) -> 0 | AS29: =+IFERROR(VLOOKUP($AS$15,Sheet1!AH9:AK9,3,0),0) -> 0 | AT29: =+IFERROR(VLOOKUP($AT$15,Sheet1!AH9:AK9,3,0),0) -> 0 | AU29: =+IFERROR(VLOOKUP($AU$15,Sheet1!AH9:AK9,3,0),0) -> 0 | AV29: =+IFERROR(VLOOKUP($AV$15,Sheet1!AH9:AK9,3,0),0) -> 0 | AW29: =+IFERROR(VLOOKUP($AW$15,Sheet1!AH9:AK9,3,0),0) -> 0 | AX29: =+IFERROR(VLOOKUP($AX$15,Sheet1!AH9:AK9,3,0),0) -> 0 | AY29: =+IFERROR(VLOOKUP($AY$15,Sheet1!AH9:AK9,3,0),0) -> 0 | AZ29: 1279 | BA29: =+IFERROR(VLOOKUP($BA$15,Sheet1!AH9:AK9,3,0),0) -> 0 | BB29: =+IFERROR(VLOOKUP($BB$15,Sheet1!AH9:AK9,3,0),0) -> 0 | BC29: =+IFERROR(VLOOKUP($BC$15,Sheet1!AL9:AO9,3,0),0) -> 0 | BD29: =+IFERROR(VLOOKUP($BD$15,Sheet1!AL9:AO9,3,0),0) -> 0 | BE29: =+IFERROR(VLOOKUP($BE$15,Sheet1!AL9:AO9,3,0),0) -> 0 | BF29: 460 | BG29: =+IFERROR(VLOOKUP($BG$15,Sheet1!AL9:AO9,3,0),0) -> 0 | BH29: =+IFERROR(VLOOKUP($BH$15,Sheet1!AL9:AO9,3,0),0) -> 0 | BI29: =+IFERROR(VLOOKUP($BI$15,Sheet1!AL9:AO9,3,0),0) -> 0 | BJ29: =+IFERROR(VLOOKUP($BJ$15,Sheet1!AL9:AO9,3,0),0) -> 0 | BK29: =+IFERROR(VLOOKUP($BK$15,Sheet1!AL9:AO9,3,0),0) -> 0 | BL29: =+IFERROR(VLOOKUP($BL$15,Sheet1!AL9:AO9,3,0),0) -> 0 | BM29: =+IFERROR(VLOOKUP($BM$15,Sheet1!AP9:AS9,3,0),0) -> 0 | BN29: =+IFERROR(VLOOKUP($BN$15,Sheet1!AT9:AW9,3,0),0) -> 0 | BO29: 55 | BP29: =+IFERROR(VLOOKUP($BP$15,Sheet1!BB9:BE9,3,0),0) -> 0 | BQ29: =+IFERROR(VLOOKUP($BQ$15,Sheet1!BF9:BI9,3,0),0) -> 0 | BR29: =+IFERROR(VLOOKUP($BR$15,Sheet1!BJ9:BM9,3,0),0) -> 0 | BS29: =+IFERROR(VLOOKUP($BS$15,Sheet1!BN9:BQ9,3,0),0) -> 0 | BT29: 29 | BU29: =+IFERROR(VLOOKUP($BU$15,Sheet1!BV9:BY9,3,0),0) -> 0 | BV29: =Sheet1!E9 -> STEEL | BW29: SP0400125 | BX29: CORRUGATED DISPATCH STEEL DRUM 1600 X 700 X 915 MM | BY29: =VLOOKUP(C29,Sheet1!$C$1:$CX$17,100,0) -> 500 | BZ29: =20900*2 -> 41800 | CA29: =SUMPRODUCT($N$16:$BU$16,N29:BU29)+BZ29 -> 620620 | CB29: =Sheet1!CB9 -> 0 | CC29: =CA29*CB29 -> 0 | CD29: 0.5 | CE29: =CA29*CD29 -> 310310 | CF29: =Sheet1!CF9 -> 0 | CG29: =CA29*CF29 -> 0 | CH29: =CA29+CC29+CE29+CG29 -> 930930 | CI29: 0.03 | CJ29: =CH29*CI29 -> 27927.9 | CK29: 0.02 | CL29: =CH29*CK29 -> 18618.6
A30: =Sheet1!A11 -> ENQ-11285-22-23 | B30: =Sheet1!B11 -> 45170 | C30: =Sheet1!C11 -> FA1100176 | D30: =Sheet1!D11 -> 4 CORE X 300 SQ. MM. AL/ARD - WIRE (XLPE) | E30: =CH30+CJ30+CL30 -> 1901327.4 | F30: =ROUNDUP(M49,0) -> 56667 | G30: =E30+F30 -> 1957994.4 | H30: 0.18 | I30: =G30*H30 -> 352438.99 | J30: =G30+I30 -> 2310433.4 | K30: =Sheet1!CS11 -> 72 | L30: =Sheet1!CT11 -> KMS | M30: =J30*K30 -> 1.663512e+08 | N30: =+IFERROR(VLOOKUP($N$15,Sheet1!J11:L11,3,0),0) -> 3240 | O30: =+IFERROR(VLOOKUP($O$15,Sheet1!J11:L11,3,0),0) -> 0 | P30: =+IFERROR(VLOOKUP($P$15,Sheet1!J11:M11,3,0),0) -> 0 | Q30: =+IFERROR(VLOOKUP($Q$15,Sheet1!J11:M11,3,0),0) -> 0 | R30: =+IFERROR(VLOOKUP($R$15,Sheet1!J11:M11,3,0),0) -> 0 | S30: =+IFERROR(VLOOKUP($S$15,Sheet1!N11:Q11,3,0),0) -> 0 | T30: =+IFERROR(VLOOKUP($T$15,Sheet1!N11:Q11,3,0),0) -> 0 | U30: =+IFERROR(VLOOKUP($U$15,Sheet1!F11:I11,3,0),0) -> 0 | V30: =+IFERROR(VLOOKUP($V$15,Sheet1!F11:I11,3,0),0) -> 0 | W30: =+IFERROR(VLOOKUP($W$15,Sheet1!F11:I11,3,0),0) -> 0 | X30: =+IFERROR(VLOOKUP($X$15,Sheet1!F11:I11,3,0),0) -> 0 | Y30: =+IFERROR(VLOOKUP($Y$15,Sheet1!F11:I11,3,0),0) -> 0 | Z30: =+IFERROR(VLOOKUP($Z$15,Sheet1!F11:I11,3,0),0) -> 0 | AA30: =+IFERROR(VLOOKUP($AA$15,Sheet1!F11:I11,3,0),0) -> 0 | AB30: =+IFERROR(VLOOKUP($AB$15,Sheet1!F11:I11,3,0),0) -> 0 | AC30: =+IFERROR(VLOOKUP($AC$15,Sheet1!R11:U11,3,0),0) -> 0 | AD30: =+IFERROR(VLOOKUP($AD$15,Sheet1!R11:U11,2,0),0) -> 0 | AE30: =+IFERROR(VLOOKUP($AE$15,Sheet1!V11:Y11,3,0),0) -> 0 | AF30: 500 | AG30: =+IFERROR(VLOOKUP($AG$15,Sheet1!V11:Y11,3,0),0) -> 0 | AH30: =+IFERROR(VLOOKUP($AH$15,Sheet1!V11:Y11,3,0),0) -> 0 | AI30: =+IFERROR(VLOOKUP($AI$15,Sheet1!V11:Y11,3,0),0) -> 0 | AJ30: =+IFERROR(VLOOKUP($AJ$15,Sheet1!V11:Y11,3,0),0) -> 0 | AK30: =+IFERROR(VLOOKUP($AK$15,Sheet1!Z11:AB11,3,0),0) -> 0 | AL30: =+IFERROR(VLOOKUP($AL$15,Sheet1!AD11:AG11,3,0),0) -> 0 | AM30: =+IFERROR(VLOOKUP($AM$15,Sheet1!AD11:AG11,3,0),0) -> 0 | AN30: =+IFERROR(VLOOKUP($AN$15,Sheet1!AD11:AG11,3,0),0) -> 0 | AO30: =+IFERROR(VLOOKUP($AO$15,Sheet1!AD11:AG11,3,0),0) -> 0 | AP30: =+IFERROR(VLOOKUP($AP$15,Sheet1!AD11:AG11,3,0),0) -> 0 | AQ30: 240 | AR30: =+IFERROR(VLOOKUP($AR$15,Sheet1!AD11:AG11,3,0),0) -> 0 | AS30: =+IFERROR(VLOOKUP($AS$15,Sheet1!AH11:AK11,3,0),0) -> 0 | AT30: =+IFERROR(VLOOKUP($AT$15,Sheet1!AH11:AK11,3,0),0) -> 0 | AU30: =+IFERROR(VLOOKUP($AU$15,Sheet1!AH11:AK11,3,0),0) -> 0 | AV30: =+IFERROR(VLOOKUP($AV$15,Sheet1!AH11:AK11,3,0),0) -> 0 | AW30: =+IFERROR(VLOOKUP($AW$15,Sheet1!AH11:AK11,3,0),0) -> 0 | AX30: =+IFERROR(VLOOKUP($AX$15,Sheet1!AH11:AK11,3,0),0) -> 0 | AY30: =+IFERROR(VLOOKUP($AY$15,Sheet1!AH11:AK11,3,0),0) -> 0 | AZ30: =+IFERROR(VLOOKUP($AZ$15,Sheet1!AH11:AK11,3,0),0) -> 0 | BA30: 2444 | BB30: =+IFERROR(VLOOKUP($BB$15,Sheet1!AH11:AK11,3,0),0) -> 0 | BC30: =+IFERROR(VLOOKUP($BC$15,Sheet1!AL11:AO11,3,0),0) -> 0 | BD30: =+IFERROR(VLOOKUP($BD$15,Sheet1!AL11:AO11,3,0),0) -> 0 | BE30: =+IFERROR(VLOOKUP($BE$15,Sheet1!AL11:AO11,3,0),0) -> 0 | BF30: 835 | BG30: =+IFERROR(VLOOKUP($BG$15,Sheet1!AL11:AO11,3,0),0) -> 0 | BH30: =+IFERROR(VLOOKUP($BH$15,Sheet1!AL11:AO11,3,0),0) -> 0 | BI30: =+IFERROR(VLOOKUP($BI$15,Sheet1!AL11:AO11,3,0),0) -> 0 | BJ30: =+IFERROR(VLOOKUP($BJ$15,Sheet1!AL11:AO11,3,0),0) -> 0 | BK30: =+IFERROR(VLOOKUP($BK$15,Sheet1!AL11:AO11,3,0),0) -> 0 | BL30: =+IFERROR(VLOOKUP($BL$15,Sheet1!AL11:AO11,3,0),0) -> 0 | BM30: =+IFERROR(VLOOKUP($BM$15,Sheet1!AP11:AS11,3,0),0) -> 0 | BN30: =+IFERROR(VLOOKUP($BN$15,Sheet1!AT11:AW11,3,0),0) -> 0 | BO30: 112 | BP30: =+IFERROR(VLOOKUP($BP$15,Sheet1!BB11:BE11,3,0),0) -> 0 | BQ30: =+IFERROR(VLOOKUP($BQ$15,Sheet1!BF11:BI11,3,0),0) -> 0 | BR30: =+IFERROR(VLOOKUP($BR$15,Sheet1!BJ11:BM11,3,0),0) -> 0 | BS30: =+IFERROR(VLOOKUP($BS$15,Sheet1!BN11:BQ11,3,0),0) -> 0 | BT30: 44 | BU30: =+IFERROR(VLOOKUP($BU$15,Sheet1!BV11:BY11,3,0),0) -> 0 | BV30: =Sheet1!E11 -> STEEL | BW30: =Sheet1!CV11 -> SP0400139 | BX30: =Sheet1!CW11 -> CORRUGATED DISPATCH STEEL DRUM 2130 X 890 X 965 | BY30: =VLOOKUP(C30,Sheet1!$C$1:$CX$17,100,0) -> 500 | BZ30: =Sheet1!BZ11 -> 78780 | CA30: =SUMPRODUCT($N$16:$BU$16,N30:BU30)+BZ30 -> 1207192 | CB30: =Sheet1!CB11 -> 0 | CC30: =CA30*CB30 -> 0 | CD30: 0.5 | CE30: =CA30*CD30 -> 603596 | CF30: =Sheet1!CF11 -> 0 | CG30: =CA30*CF30 -> 0 | CH30: =CA30+CC30+CE30+CG30 -> 1810788 | CI30: 0.03 | CJ30: =CH30*CI30 -> 54323.64 | CK30: 0.02 | CL30: =CH30*CK30 -> 36215.76
A31: =Sheet1!A8 -> ENQ-11285-22-23 | B31: =Sheet1!B8 -> 45170 | C31: =Sheet1!C8 -> FA1500045 | D31: =Sheet1!D8 -> 2 CORE X 25 SQ MM + 1 CORE X 25 SQ MM (AB CABLES) (BARE) | E31: =CH31+CJ31+CL31 -> 84853.17 | F31: =ROUNDUP(M50,0) -> 4250 | G31: =E31+F31 -> 89103.17 | H31: 0.18 | I31: =G31*H31 -> 16038.571 | J31: =G31+I31 -> 105141.74 | K31: =Sheet1!CS8 -> 40 | L31: =Sheet1!CT8 -> KMS | M31: =J31*K31 -> 4205669.6 | N31: =+IFERROR(VLOOKUP($N$15,Sheet1!J8:L8,3,0),0) -> 135 | O31: =+IFERROR(VLOOKUP($O$15,Sheet1!J8:L8,3,0),0) -> 0 | P31: =+IFERROR(VLOOKUP($P$15,Sheet1!J8:M8,3,0),0) -> 0 | Q31: =+IFERROR(VLOOKUP($Q$15,Sheet1!J8:M8,3,0),0) -> 0 | R31: =+IFERROR(VLOOKUP($R$15,Sheet1!J8:M8,3,0),0) -> 0 | S31: =+IFERROR(VLOOKUP($S$15,Sheet1!N8:Q8,3,0),0) -> 0 | T31: =+IFERROR(VLOOKUP($T$15,Sheet1!N8:Q8,3,0),0) -> 67.5 | U31: =+IFERROR(VLOOKUP($U$15,Sheet1!F8:I8,3,0),0) -> 0 | V31: =+IFERROR(VLOOKUP($V$15,Sheet1!F8:I8,3,0),0) -> 0 | W31: =+IFERROR(VLOOKUP($W$15,Sheet1!F8:I8,3,0),0) -> 0 | X31: =+IFERROR(VLOOKUP($X$15,Sheet1!F8:I8,3,0),0) -> 0 | Y31: =+IFERROR(VLOOKUP($Y$15,Sheet1!F8:I8,3,0),0) -> 0 | Z31: =+IFERROR(VLOOKUP($Z$15,Sheet1!F8:I8,3,0),0) -> 0 | AA31: =+IFERROR(VLOOKUP($AA$15,Sheet1!F8:I8,3,0),0) -> 0 | AB31: =+IFERROR(VLOOKUP($AB$15,Sheet1!F8:I8,3,0),0) -> 0 | AC31: =+IFERROR(VLOOKUP($AC$15,Sheet1!R8:U8,3,0),0) -> 0 | AD31: =+IFERROR(VLOOKUP($AD$15,Sheet1!R8:U8,2,0),0) -> 0 | AE31: =+IFERROR(VLOOKUP($AE$15,Sheet1!V8:Y8,3,0),0) -> 0 | AF31: 58 | AG31: =+IFERROR(VLOOKUP($AG$15,Sheet1!V8:Y8,3,0),0) -> 0 | AH31: =+IFERROR(VLOOKUP($AH$15,Sheet1!V8:Y8,3,0),0) -> 0 | AI31: =+IFERROR(VLOOKUP($AI$15,Sheet1!V8:Y8,3,0),0) -> 0 | AJ31: =+IFERROR(VLOOKUP($AJ$15,Sheet1!V8:Y8,3,0),0) -> 0 | AK31: =+IFERROR(VLOOKUP($AK$15,Sheet1!Z8:AB8,3,0),0) -> 0 | AL31: =+IFERROR(VLOOKUP($AL$15,Sheet1!AD8:AG8,3,0),0) -> 0 | AM31: =+IFERROR(VLOOKUP($AM$15,Sheet1!AD8:AG8,3,0),0) -> 0 | AN31: =+IFERROR(VLOOKUP($AN$15,Sheet1!AD8:AG8,3,0),0) -> 0 | AO31: =+IFERROR(VLOOKUP($AO$15,Sheet1!AD8:AG8,3,0),0) -> 0 | AP31: =+IFERROR(VLOOKUP($AP$15,Sheet1!AD8:AG8,3,0),0) -> 0 | AQ31: =+IFERROR(VLOOKUP($AQ$15,Sheet1!AD8:AG8,3,0),0) -> 0 | AR31: =+IFERROR(VLOOKUP($AR$15,Sheet1!AD8:AG8,3,0),0) -> 0 | AS31: =+IFERROR(VLOOKUP($AS$15,Sheet1!AH8:AK8,3,0),0) -> 0 | AT31: =+IFERROR(VLOOKUP($AT$15,Sheet1!AH8:AK8,3,0),0) -> 0 | AU31: =+IFERROR(VLOOKUP($AU$15,Sheet1!AH8:AK8,3,0),0) -> 0 | AV31: =+IFERROR(VLOOKUP($AV$15,Sheet1!AH8:AK8,3,0),0) -> 0 | AW31: =+IFERROR(VLOOKUP($AW$15,Sheet1!AH8:AK8,3,0),0) -> 0 | AX31: =+IFERROR(VLOOKUP($AX$15,Sheet1!AH8:AK8,3,0),0) -> 0 | AY31: =+IFERROR(VLOOKUP($AY$15,Sheet1!AH8:AK8,3,0),0) -> 0 | AZ31: =+IFERROR(VLOOKUP($AZ$15,Sheet1!AH8:AK8,3,0),0) -> 0 | BA31: =+IFERROR(VLOOKUP($BA$15,Sheet1!AH8:AK8,3,0),0) -> 0 | BB31: =+IFERROR(VLOOKUP($BB$15,Sheet1!AH8:AK8,3,0),0) -> 0 | BC31: =+IFERROR(VLOOKUP($BC$15,Sheet1!AL8:AO8,3,0),0) -> 0 | BD31: =+IFERROR(VLOOKUP($BD$15,Sheet1!AL8:AO8,3,0),0) -> 0 | BE31: =+IFERROR(VLOOKUP($BE$15,Sheet1!AL8:AO8,3,0),0) -> 0 | BF31: =+IFERROR(VLOOKUP($BF$15,Sheet1!AL8:AO8,3,0),0) -> 0 | BG31: =+IFERROR(VLOOKUP($BG$15,Sheet1!AL8:AO8,3,0),0) -> 0 | BH31: =+IFERROR(VLOOKUP($BH$15,Sheet1!AL8:AO8,3,0),0) -> 0 | BI31: =+IFERROR(VLOOKUP($BI$15,Sheet1!AL8:AO8,3,0),0) -> 0 | BJ31: =+IFERROR(VLOOKUP($BJ$15,Sheet1!AL8:AO8,3,0),0) -> 0 | BK31: =+IFERROR(VLOOKUP($BK$15,Sheet1!AL8:AO8,3,0),0) -> 0 | BL31: =+IFERROR(VLOOKUP($BL$15,Sheet1!AL8:AO8,3,0),0) -> 0 | BM31: =+IFERROR(VLOOKUP($BM$15,Sheet1!AP8:AS8,3,0),0) -> 0 | BN31: =+IFERROR(VLOOKUP($BN$15,Sheet1!AT8:AW8,3,0),0) -> 0 | BO31: =+IFERROR(VLOOKUP($BO$15,Sheet1!AX8:BA8,3,0),0) -> 0 | BP31: =+IFERROR(VLOOKUP($BP$15,Sheet1!BB8:BE8,3,0),0) -> 0 | BQ31: =+IFERROR(VLOOKUP($BQ$15,Sheet1!BF8:BI8,3,0),0) -> 0 | BR31: =+IFERROR(VLOOKUP($BR$15,Sheet1!BJ8:BM8,3,0),0) -> 0 | BS31: =+IFERROR(VLOOKUP($BS$15,Sheet1!BN8:BQ8,3,0),0) -> 0 | BT31: =+IFERROR(VLOOKUP($BT$15,Sheet1!BR8:BU8,3,0),0) -> 0 | BU31: =+IFERROR(VLOOKUP($BU$15,Sheet1!BV8:BY8,3,0),0) -> 0 | BV31: WOOD | BW31: MD0100075 | BX31: DRUM - 42 X 15 X 23 X 2 | BY31: =VLOOKUP(C31,Sheet1!$C$1:$CX$17,100,0) -> 1000 | BZ31: 3542.0286 | CA31: =SUMPRODUCT($N$16:$BU$16,N31:BU31)+BZ31 -> 53875.029 | CB31: =Sheet1!CB8 -> 0 | CC31: =CA31*CB31 -> 0 | CD31: 0.5 | CE31: =CA31*CD31 -> 26937.514 | CF31: =Sheet1!CF8 -> 0 | CG31: =CA31*CF31 -> 0 | CH31: =CA31+CC31+CE31+CG31 -> 80812.543 | CI31: 0.03 | CJ31: =CH31*CI31 -> 2424.3763 | CK31: 0.02 | CL31: =CH31*CK31 -> 1616.2509
A32: =Sheet1!A15 -> ENQ-11285-22-23 | B32: =Sheet1!B15 -> 45170 | C32: =Sheet1!C15 -> FA0100086 | D32: =Sheet1!D15 -> 4 CORE X 150 SQ MM + 1 CORE X 16 SQ MM + 1 CORE X 150 SQ MM (AB CABLES) (BARE) | E32: =CH32+CJ32+CL32 -> 797786.07 | F32: =ROUNDUP(M51,0) -> 19000 | G32: =E32+F32 -> 816786.07 | H32: 0.18 | I32: =G32*H32 -> 147021.49 | J32: =G32+I32 -> 963807.57 | K32: =Sheet1!CS15 -> 170 | L32: =Sheet1!CT15 -> KMS | M32: =J32*K32 -> 1.6384729e+08 | N32: =+IFERROR(VLOOKUP($N$15,Sheet1!J15:L15,3,0),0) -> 1664 | O32: =+IFERROR(VLOOKUP($O$15,Sheet1!J15:L15,3,0),0) -> 0 | P32: =+IFERROR(VLOOKUP($P$15,Sheet1!J15:M15,3,0),0) -> 0 | Q32: =+IFERROR(VLOOKUP($Q$15,Sheet1!J15:M15,3,0),0) -> 0 | R32: =+IFERROR(VLOOKUP($R$15,Sheet1!J15:M15,3,0),0) -> 0 | S32: =+IFERROR(VLOOKUP($S$15,Sheet1!N15:Q15,3,0),0) -> 0 | T32: 415 | U32: =+IFERROR(VLOOKUP($U$15,Sheet1!F15:I15,3,0),0) -> 0 | V32: =+IFERROR(VLOOKUP($V$15,Sheet1!F15:I15,3,0),0) -> 0 | W32: =+IFERROR(VLOOKUP($W$15,Sheet1!F15:I15,3,0),0) -> 0 | X32: =+IFERROR(VLOOKUP($X$15,Sheet1!F15:I15,3,0),0) -> 0 | Y32: =+IFERROR(VLOOKUP($Y$15,Sheet1!F15:I15,3,0),0) -> 0 | Z32: =+IFERROR(VLOOKUP($Z$15,Sheet1!F15:I15,3,0),0) -> 0 | AA32: =+IFERROR(VLOOKUP($AA$15,Sheet1!F15:I15,3,0),0) -> 0 | AB32: =+IFERROR(VLOOKUP($AB$15,Sheet1!F15:I15,3,0),0) -> 0 | AC32: =+IFERROR(VLOOKUP($AC$15,Sheet1!R15:U15,3,0),0) -> 0 | AD32: =+IFERROR(VLOOKUP($AD$15,Sheet1!R15:U15,2,0),0) -> 0 | AE32: =+IFERROR(VLOOKUP($AE$15,Sheet1!V15:Y15,3,0),0) -> 0 | AF32: 370 | AG32: =+IFERROR(VLOOKUP($AG$15,Sheet1!V15:Y15,3,0),0) -> 0 | AH32: =+IFERROR(VLOOKUP($AH$15,Sheet1!V15:Y15,3,0),0) -> 0 | AI32: =+IFERROR(VLOOKUP($AI$15,Sheet1!V15:Y15,3,0),0) -> 0 | AJ32: =+IFERROR(VLOOKUP($AJ$15,Sheet1!V15:Y15,3,0),0) -> 0 | AK32: =+IFERROR(VLOOKUP($AK$15,Sheet1!Z15:AB15,3,0),0) -> 0 | AL32: =+IFERROR(VLOOKUP($AL$15,Sheet1!AD15:AG15,3,0),0) -> 0 | AM32: =+IFERROR(VLOOKUP($AM$15,Sheet1!AD15:AG15,3,0),0) -> 0 | AN32: =+IFERROR(VLOOKUP($AN$15,Sheet1!AD15:AG15,3,0),0) -> 0 | AO32: =+IFERROR(VLOOKUP($AO$15,Sheet1!AD15:AG15,3,0),0) -> 0 | AP32: =+IFERROR(VLOOKUP($AP$15,Sheet1!AD15:AG15,3,0),0) -> 0 | AQ32: =+IFERROR(VLOOKUP($AQ$15,Sheet1!AD15:AG15,3,0),0) -> 0 | AR32: =+IFERROR(VLOOKUP($AR$15,Sheet1!AD15:AG15,3,0),0) -> 0 | AS32: =+IFERROR(VLOOKUP($AS$15,Sheet1!AH15:AK15,3,0),0) -> 0 | AT32: =+IFERROR(VLOOKUP($AT$15,Sheet1!AH15:AK15,3,0),0) -> 0 | AU32: =+IFERROR(VLOOKUP($AU$15,Sheet1!AH15:AK15,3,0),0) -> 0 | AV32: =+IFERROR(VLOOKUP($AV$15,Sheet1!AH15:AK15,3,0),0) -> 0 | AW32: =+IFERROR(VLOOKUP($AW$15,Sheet1!AH15:AK15,3,0),0) -> 0 | AX32: =+IFERROR(VLOOKUP($AX$15,Sheet1!AH15:AK15,3,0),0) -> 0 | AY32: =+IFERROR(VLOOKUP($AY$15,Sheet1!AH15:AK15,3,0),0) -> 0 | AZ32: =+IFERROR(VLOOKUP($AZ$15,Sheet1!AH15:AK15,3,0),0) -> 0 | BA32: =+IFERROR(VLOOKUP($BA$15,Sheet1!AH15:AK15,3,0),0) -> 0 | BB32: =+IFERROR(VLOOKUP($BB$15,Sheet1!AH15:AK15,3,0),0) -> 0 | BC32: =+IFERROR(VLOOKUP($BC$15,Sheet1!AL15:AO15,3,0),0) -> 0 | BD32: =+IFERROR(VLOOKUP($BD$15,Sheet1!AL15:AO15,3,0),0) -> 0 | BE32: =+IFERROR(VLOOKUP($BE$15,Sheet1!AL15:AO15,3,0),0) -> 0 | BF32: =+IFERROR(VLOOKUP($BF$15,Sheet1!AL15:AO15,3,0),0) -> 0 | BG32: =+IFERROR(VLOOKUP($BG$15,Sheet1!AL15:AO15,3,0),0) -> 0 | BH32: =+IFERROR(VLOOKUP($BH$15,Sheet1!AL15:AO15,3,0),0) -> 0 | BI32: =+IFERROR(VLOOKUP($BI$15,Sheet1!AL15:AO15,3,0),0) -> 0 | BJ32: =+IFERROR(VLOOKUP($BJ$15,Sheet1!AL15:AO15,3,0),0) -> 0 | BK32: =+IFERROR(VLOOKUP($BK$15,Sheet1!AL15:AO15,3,0),0) -> 0 | BL32: =+IFERROR(VLOOKUP($BL$15,Sheet1!AL15:AO15,3,0),0) -> 0 | BM32: =+IFERROR(VLOOKUP($BM$15,Sheet1!AP15:AS15,3,0),0) -> 0 | BN32: =+IFERROR(VLOOKUP($BN$15,Sheet1!AT15:AW15,3,0),0) -> 0 | BO32: =+IFERROR(VLOOKUP($BO$15,Sheet1!AX15:BA15,3,0),0) -> 0 | BP32: =+IFERROR(VLOOKUP($BP$15,Sheet1!BB15:BE15,3,0),0) -> 0 | BQ32: =+IFERROR(VLOOKUP($BQ$15,Sheet1!BF15:BI15,3,0),0) -> 0 | BR32: =+IFERROR(VLOOKUP($BR$15,Sheet1!BJ15:BM15,3,0),0) -> 0 | BS32: =+IFERROR(VLOOKUP($BS$15,Sheet1!BN15:BQ15,3,0),0) -> 0 | BT32: =+IFERROR(VLOOKUP($BT$15,Sheet1!BR15:BU15,3,0),0) -> 0 | BU32: =+IFERROR(VLOOKUP($BU$15,Sheet1!BV15:BY15,3,0),0) -> 0 | BV32: =Sheet1!E15 -> WOOD | BW32: =Sheet1!CV15 -> MD0100070 | BX32: =Sheet1!CW15 -> DRUM - 68 X 24 X 32 X 3 | BY32: =VLOOKUP(C32,Sheet1!$C$1:$CX$17,100,0) -> 500 | BZ32: =Sheet1!BZ15 -> 17878.84 | CA32: =SUMPRODUCT($N$16:$BU$16,N32:BU32)+BZ32 -> 506530.84 | CB32: =Sheet1!CB15 -> 0 | CC32: =CA32*CB32 -> 0 | CD32: 0.5 | CE32: =CA32*CD32 -> 253265.42 | CF32: =Sheet1!CF15 -> 0 | CG32: =CA32*CF32 -> 0 | CH32: =CA32+CC32+CE32+CG32 -> 759796.26 | CI32: 0.03 | CJ32: =CH32*CI32 -> 22793.888 | CK32: 0.02 | CL32: =CH32*CK32 -> 15195.925
M33: =SUM(M17:M32) -> 8.404263e+08
B35: WEIGHT OF CABLE | E35: Order Quantity | F35: Stnd Length | G35: Truck type | H35: Fare of one truck | I35: No of Drum in one truck | J35: Total length in one Truck | K35: No of Truck | L35: Total Freight | M35: Freight per KM
B36: =SUM(N17:BT17) -> 68 | C36: =BV17 -> Hybrid | D36: =D17 -> 1 CORE X 2.5 SQ. MM. ALU/UNARD (XLPE) | E36: =K17 -> 46 | F36: =(BY17/1000) -> 1 | G36: 16 MT | H36: 85000 | I36: 88 | J36: =F36*I36 -> 88 | K36: =ROUNDUP((E36/J36),0) -> 1 | L36: =M36*E36 -> 85000 | M36: =(H36*K36)/E36 -> 1847.8261
B37: =SUM(N18:BT18) -> 78 | C37: =BV18 -> Hybrid | D37: =D18 -> 1 CORE X 4 SQ. MM. AL/UNARD (XLPE) | E37: =K18 -> 12.5 | F37: =(BY18/1000) -> 1 | G37: 16 MT | H37: 85000 | I37: 88 | J37: =F37*I37 -> 88 | K37: =ROUNDUP((E37/J37),0) -> 1 | L37: =M37*E37 -> 85000 | M37: =(H37*K37)/E37 -> 6800
B38: =SUM(N19:BT19) -> 183 | C38: =BV19 -> Hybrid | D38: =D19 -> 1 CORE X 25 SQ. MM. ALU/UNARD (XLPE ) | E38: =K19 -> 39 | F38: =(BY19/1000) -> 1 | G38: 16 MT | H38: 85000 | I38: 66 | J38: =F38*I38 -> 66 | K38: =ROUNDUP((E38/J38),0) -> 1 | L38: =M38*E38 -> 85000 | M38: =(H38*K38)/E38 -> 2179.4872
B39: =SUM(N20:BT20) -> 448 | C39: =BV20 -> Hybrid | D39: =D20 -> 1 CORE X 95 SQ. MM. AL/UNARD(XLPE ) | E39: =K20 -> 18.5 | F39: =(BY20/1000) -> 1 | G39: 16 MT | H39: 85000 | I39: 31 | J39: =F39*I39 -> 31 | K39: =ROUNDUP((E39/J39),0) -> 1 | L39: =M39*E39 -> 85000 | M39: =(H39*K39)/E39 -> 4594.5946
B40: =SUM(N21:BT21) -> 822 | C40: =BV21 -> Hybrid | D40: =D21 -> 1 CORE X 185 SQ. MM. AL/UNARD. (XLPE) | E40: =K21 -> 6.7 | F40: =(BY21/1000) -> 1 | G40: 16 MT | H40: 85000 | I40: 18 | J40: =F40*I40 -> 18 | K40: =ROUNDUP((E40/J40),0) -> 1 | L40: =M40*E40 -> 85000 | M40: =(H40*K40)/E40 -> 12686.567
B41: =SUM(N22:BT22) -> 1225 | C41: =BV22 -> STEEL | D41: =D22 -> 1 CORE X 300 SQ. MM. AL/UNARD. (XLPE) | E41: =K22 -> 20.7 | F41: =(BY22/1000) -> 1 | G41: 16 MT | H41: 85000 | I41: 10 | J41: =F41*I41 -> 10 | K41: =ROUNDUP((E41/J41),0) -> 3 | L41: =M41*E41 -> 255000 | M41: =(H41*K41)/E41 -> 12318.841
B42: =SUM(N23:BT23) -> 2391 | C42: =BV23 -> STEEL | D42: =D23 -> 1 CORE X 630 SQ. MM. ALU/UNARD (XLPE) | E42: =K23 -> 18 | F42: =(BY23/1000) -> 1 | G42: 16 MT | H42: 85000 | I42: 3 | J42: =F42*I42 -> 3 | K42: =ROUNDUP((E42/J42),0) -> 6 | L42: =M42*E42 -> 510000 | M42: =(H42*K42)/E42 -> 28333.333
B43: =SUM(N24:BT24) -> 549 | C43: =BV24 -> Hybrid | D43: =D24 -> 2 CORE X 16 SQ. MM. AL/ARD - WIRE (XLPE) | E43: =K24 -> 1511 | F43: =(BY24/1000) -> 1 | G43: 16 MT | H43: 85000 | I43: 20 | J43: =F43*I43 -> 20 | K43: =ROUNDUP((E43/J43),0) -> 76 | L43: =M43*E43 -> 6460000 | M43: =(H43*K43)/E43 -> 4275.3144
B44: =SUM(N25:BT25) -> 662 | C44: =BV25 -> Hybrid | D44: =D25 -> 2 CORE X 25 SQ. MM. AL/ARD - STRIP (XLPE) | E44: =K25 -> 125 | F44: =(BY25/1000) -> 1 | G44: 16 MT | H44: 85000 | I44: 23 | J44: =F44*I44 -> 23 | K44: =ROUNDUP((E44/J44),0) -> 6 | L44: =M44*E44 -> 510000 | M44: =(H44*K44)/E44 -> 4080
B45: =SUM(N26:BT26) -> 961 | C45: =BV26 -> Hybrid | D45: =D26 -> 4 CORE X 25 SQ. MM. ALU/ARD - STRIP (XLPE) | E45: =K26 -> 357 | F45: =(BY26/1000) -> 1 | G45: 16 MT | H45: 85000 | I45: 15 | J45: =F45*I45 -> 15 | K45: =ROUNDUP((E45/J45),0) -> 24 | L45: =M45*E45 -> 2040000 | M45: =(H45*K45)/E45 -> 5714.2857
B46: =SUM(N27:BT27) -> 1447 | C46: =BV27 -> STEEL | D46: =D27 -> 4 CORE X 50 SQ. MM. ALU/ARD - STRIP (XLPE) | E46: =K27 -> 97 | F46: =(BY27/1000) -> 1 | G46: 16 MT | H46: 85000 | I46: 11 | J46: =F46*I46 -> 11 | K46: =ROUNDUP((E46/J46),0) -> 9 | L46: =M46*E46 -> 765000 | M46: =(H46*K46)/E46 -> 7886.5979
B47: =SUM(N28:BT28) -> 2287.5 | C47: =BV28 -> STEEL | D47: =D28 -> 4 CORE X 95 SQ. MM. AL/ARD - STRIP (XLPE) | E47: =K28 -> 82 | F47: =(BY28/1000) -> 0.5 | G47: 16 MT | H47: 85000 | I47: 11 | J47: =F47*I47 -> 5.5 | K47: =ROUNDUP((E47/J47),0) -> 15 | L47: =M47*E47 -> 1275000 | M47: =(H47*K47)/E47 -> 15548.78
... B51: =SUM(N32:BT32) -> 2449 | C51: =BV32 -> WOOD | D51: =D32 -> 4 CORE X 150 SQ MM + 1 CORE X 16 SQ MM + 1 CORE X 150 SQ MM (AB CABLES) (BARE) | E51: =K32 -> 170 | F51: =(BY32/1000) -> 0.5 | G51: 16 MT | H51: 85000 | I51: 9 | J51: =F51*I51 -> 4.5 | K51: =ROUNDUP((E51/J51),0) -> 38 | L51: =M51*E51 -> 3230000 | M51: =(H51*K51)/E51 -> 19000
A55: DOCKET NO. | B55: Base Date | C55: ITEM CODE | D55: PROPOSE ERP ITEM NAME | E55: EX-WORKS (PER MTR) | F55: FREIGHT PER MTR | G55: PRICE INCLUDING FREIGHT (PER MTR) | H55: GST % | I55: GST VALUE | J55: PRICE INCLUDING GST & FREIGHT (PER MTR) | K55: QTY | L55: Unit | M55: TOTAL PRICE OF FULL QTY (INCLUDING FRIGHT & GST)
A57: =A17 -> ENQ-11285-22-23 | B57: =B17 -> 45170 | C57: =C17 -> FA0500035 | D57: =D17 -> 1 CORE X 2.5 SQ. MM. ALU/UNARD (XLPE) | E57: =ROUNDUP(E17/1000,2) -> 16.85 | F57: =ROUNDUP(F17/1000,2) -> 1.85 | G57: =ROUND(E57+F57,2) -> 18.7 | H57: =H17 -> 0.18 | I57: =ROUND(G57*H57,2) -> 3.37 | J57: =ROUND(G57+I57,2) -> 22.07 | K57: =K17*1000 -> 46000 | L57: MTR | M57: =J57*K57 -> 1015220
A58: =A18 -> ENQ-11285-22-23 | B58: =B18 -> 45170 | C58: =C18 -> FA1000114 | D58: =D18 -> 1 CORE X 4 SQ. MM. AL/UNARD (XLPE) | E58: =ROUNDUP(E18/1000,2) -> 19.19 | F58: =ROUNDUP(F18/1000,2) -> 6.8 | G58: =ROUND(E58+F58,2) -> 25.99 | H58: =H18 -> 0.18 | I58: =ROUND(G58*H58,2) -> 4.68 | J58: =ROUND(G58+I58,2) -> 30.67 | K58: =K18*1000 -> 12500 | L58: MTR | M58: =J58*K58 -> 383375
A59: =A19 -> ENQ-11285-22-23 | B59: =B19 -> 45170 | C59: =C19 -> FA0500020 | D59: =D19 -> 1 CORE X 25 SQ. MM. ALU/UNARD (XLPE ) | E59: =ROUNDUP(E19/1000,2) -> 46.25 | F59: =ROUNDUP(F19/1000,2) -> 2.18 | G59: =ROUND(E59+F59,2) -> 48.43 | H59: =H19 -> 0.18 | I59: =ROUND(G59*H59,2) -> 8.72 | J59: =ROUND(G59+I59,2) -> 57.15 | K59: =K19*1000 -> 39000 | L59: MTR | M59: =J59*K59 -> 2228850
A60: =A20 -> ENQ-11285-22-23 | B60: =B20 -> 45170 | C60: =C20 -> FA0600013 | D60: =D20 -> 1 CORE X 95 SQ. MM. AL/UNARD(XLPE ) | E60: =ROUNDUP(E20/1000,2) -> 128.87 | F60: =ROUNDUP(F20/1000,2) -> 4.6 | G60: =ROUND(E60+F60,2) -> 133.47 | H60: =H20 -> 0.18 | I60: =ROUND(G60*H60,2) -> 24.02 | J60: =ROUND(G60+I60,2) -> 157.49 | K60: =K20*1000 -> 18500 | L60: MTR | M60: =J60*K60 -> 2913565
A61: =A21 -> ENQ-11285-22-23 | B61: =B21 -> 45170 | C61: =C21 -> FA0600021 | D61: =D21 -> 1 CORE X 185 SQ. MM. AL/UNARD. (XLPE) | E61: =ROUNDUP(E21/1000,2) -> 244.38 | F61: =ROUNDUP(F21/1000,2) -> 12.69 | G61: =ROUND(E61+F61,2) -> 257.07 | H61: =H21 -> 0.18 | I61: =ROUND(G61*H61,2) -> 46.27 | J61: =ROUND(G61+I61,2) -> 303.34 | K61: =K21*1000 -> 6700 | L61: MTR | M61: =J61*K61 -> 2032378
A62: =A22 -> ENQ-11285-22-23 | B62: =B22 -> 45170 | C62: =C22 -> FA0600020 | D62: =D22 -> 1 CORE X 300 SQ. MM. AL/UNARD. (XLPE) | E62: =ROUNDUP(E22/1000,2) -> 387.46 | F62: =ROUNDUP(F22/1000,2) -> 12.32 | G62: =ROUND(E62+F62,2) -> 399.78 | H62: =H22 -> 0.18 | I62: =ROUND(G62*H62,2) -> 71.96 | J62: =ROUND(G62+I62,2) -> 471.74 | K62: =K22*1000 -> 20700 | L62: MTR | M62: =J62*K62 -> 9765018
A63: =A23 -> ENQ-11285-22-23 | B63: =B23 -> 45170 | C63: =C23 -> FA0600032 | D63: =D23 -> 1 CORE X 630 SQ. MM. ALU/UNARD (XLPE) | E63: =ROUNDUP(E23/1000,2) -> 747.48 | F63: =ROUNDUP(F23/1000,2) -> 28.34 | G63: =ROUND(E63+F63,2) -> 775.82 | H63: =H23 -> 0.18 | I63: =ROUND(G63*H63,2) -> 139.65 | J63: =ROUND(G63+I63,2) -> 915.47 | K63: =K23*1000 -> 18000 | L63: MTR | M63: =J63*K63 -> 16478460
A64: =A24 -> ENQ-11285-22-23 | B64: =B24 -> 45170 | C64: =C24 -> FA0900133 | D64: =D24 -> 2 CORE X 16 SQ. MM. AL/ARD - WIRE (XLPE) | E64: =ROUNDUP(E24/1000,2) -> 114.61 | F64: =ROUNDUP(F24/1000,2) -> 4.28 | G64: =ROUND(E64+F64,2) -> 118.89 | H64: =H24 -> 0.18 | I64: =ROUND(G64*H64,2) -> 21.4 | J64: =ROUND(G64+I64,2) -> 140.29 | K64: =K24*1000 -> 1511000 | L64: MTR | M64: =J64*K64 -> 211978190
A65: =A25 -> ENQ-11285-22-23 | B65: =B25 -> 45170 | C65: =C25 -> FA0900038 | D65: =D25 -> 2 CORE X 25 SQ. MM. AL/ARD - STRIP (XLPE) | E65: =ROUNDUP(E25/1000,2) -> 137.79 | F65: =ROUNDUP(F25/1000,2) -> 4.08 | G65: =ROUND(E65+F65,2) -> 141.87 | H65: =H25 -> 0.18 | I65: =ROUND(G65*H65,2) -> 25.54 | J65: =ROUND(G65+I65,2) -> 167.41 | K65: =K25*1000 -> 125000 | L65: MTR | M65: =J65*K65 -> 20926250
A66: =A26 -> ENQ-11285-22-23 | B66: =B26 -> 45170 | C66: =C26 -> FA0900015 | D66: =D26 -> 4 CORE X 25 SQ. MM. ALU/ARD - STRIP (XLPE) | E66: =ROUNDUP(E26/1000,2) -> 204.08 | F66: =ROUNDUP(F26/1000,2) -> 5.72 | G66: =ROUND(E66+F66,2) -> 209.8 | H66: =H26 -> 0.18 | I66: =ROUND(G66*H66,2) -> 37.76 | J66: =ROUND(G66+I66,2) -> 247.56 | K66: =K26*1000 -> 357000 | L66: MTR | M66: =J66*K66 -> 88378920
A67: =A27 -> ENQ-11285-22-23 | B67: =B27 -> 45170 | C67: =C27 -> FA0900036 | D67: =D27 -> 4 CORE X 50 SQ. MM. ALU/ARD - STRIP (XLPE) | E67: =ROUNDUP(E27/1000,2) -> 348.02 | F67: =ROUNDUP(F27/1000,2) -> 7.89 | G67: =ROUND(E67+F67,2) -> 355.91 | H67: =H27 -> 0.18 | I67: =ROUND(G67*H67,2) -> 64.06 | J67: =ROUND(G67+I67,2) -> 419.97 | K67: =K27*1000 -> 97000 | L67: MTR | M67: =J67*K67 -> 40737090
A68: =A28 -> ENQ-11285-22-23 | B68: =B28 -> 45170 | C68: =C28 -> FA1100012 | D68: =D28 -> 4 CORE X 95 SQ. MM. AL/ARD - STRIP (XLPE) | E68: =ROUNDUP(E28/1000,2) -> 564.26 | F68: =ROUNDUP(F28/1000,2) -> 15.55 | G68: =ROUND(E68+F68,2) -> 579.81 | H68: =H28 -> 0.18 | I68: =ROUND(G68*H68,2) -> 104.37 | J68: =ROUND(G68+I68,2) -> 684.18 | K68: =K28*1000 -> 82000 | L68: MTR | M68: =J68*K68 -> 56102760
... A72: =A32 -> ENQ-11285-22-23 | B72: =B32 -> 45170 | C72: =C32 -> FA0100086 | D72: =D32 -> 4 CORE X 150 SQ MM + 1 CORE X 16 SQ MM + 1 CORE X 150 SQ MM (AB CABLES) (BARE) | E72: =ROUNDUP(E32/1000,2) -> 797.79 | F72: =ROUNDUP(F32/1000,2) -> 19 | G72: =ROUND(E72+F72,2) -> 816.79 | H72: =H32 -> 0.18 | I72: =ROUND(G72*H72,2) -> 147.02 | J72: =ROUND(G72+I72,2) -> 963.81 | K72: =K32*1000 -> 170000 | L72: MTR | M72: =J72*K72 -> 163847700
M73: =SUM(M57:M72) -> 840453556

Sheet PV-CALCULATION
A1: Base Date | B1: 45170
A2: PV Terms(Price Variation Formula) | B2: BASE DATE : This price is applicable as of 1st working day of the month, 1 month prior to the due date of submission of tender.
A3: PV FORMULA
A4: P=Po+{Wt. of Al conductor in Kg/Mtr * (Al - Alo) } +{Wt. of Armor (GI wire) in Kg/Mtr * (Fe - Feo)}
A7: Alf | B7: Variation factor for aluminum.
A8: Fef | B8: Variation factor for steel
T11: VALUE ADDITION CALCULATION
A12: Item | B12: Calculation part | C12: Date of Inspection | D12: Applicable Date | G12: BASE DATE | J12: FACTORS | O12: Ex-Work Po | P12: PVC of al | Q12: PVC OF FE | R12: PV/PKM | S12: Billing Price/PKM
D13: Date | E13: Al | F13: Fe | G13: Date | H13: Alo | I13: Feo | T13: ='AUTO CALCULATION SHEET (2)'!N15 -> Alumimium | U13: ='AUTO CALCULATION SHEET (2)'!T15 -> Alumimium ALLOY | V13: ='AUTO CALCULATION SHEET (2)'!AF15 -> LT-XLPE | W13: ='AUTO CALCULATION SHEET (2)'!AQ15 -> PVC Type ST-2 | X13: ='AUTO CALCULATION SHEET (2)'!AR15 -> PVC Type ST-2-PRESSURE EXTRUDED | Y13: ='AUTO CALCULATION SHEET (2)'!AX15 -> Galvanised Steel Flat Strip | Z13: ='AUTO CALCULATION SHEET (2)'!AZ15 -> Galvanised Steel Flat Strip-B | AA13: ='AUTO CALCULATION SHEET (2)'!BA15 -> Galvanised Steel Round Wire | AB13: ='AUTO CALCULATION SHEET (2)'!BF15 -> FRLSH PVC Type ST-2 | AC13: ='AUTO CALCULATION SHEET (2)'!BO15 -> NCWBT | AD13: ='AUTO CALCULATION SHEET (2)'!BT15 -> RUBBERIZED COTTON TAPE | AE13: RMC | AF13: Drum | AG13: RMC+Drum | AH13: VA | AI13: Groos VA% | AJ13: Mfg % | AK13: Int % | AL13: Ins% | AM13: Net VA
J14: Alf | K14: XLFAL | L14: CCFAI | M14: FeF | N14: SMIF | T14: 224 | U14: 231 | V14: 116 | W14: 63 | X14: 89 | Y14: 76 | Z14: 86 | AA14: 87 | AB14: =95+5+1 -> 101 | AC14: 420 | AD14: 450
T15: Kg/Km | U15: Kg/Km | V15: Kg/Km | W15: Kg/Km | X15: Kg/Km | Y15: Kg/Km | Z15: Kg/Km | AA15: Kg/Km | AB15: Kg/Km | AC15: Kg/Km | AD15: Kg/Km
A16: 1 CORE X 2.5 SQ. MM. ALU/UNARD (XLPE) | C16: PROVISIONAL | D16: 45201 | E16: 218785.75 | G16: =$B$1 -> 45170 | H16: 208424.45 | J16: =6.5/1000 -> 0.0065 | O16: ='AUTO CALCULATION SHEET (2)'!E17 -> 16844.625 | P16: =(J16*(E16-H16)) -> 67.34845 | Q16: =(M16*(F16-I16)) -> 0 | R16: =P16+Q16 -> 67.34845 | S16: =+O16+R16 -> 16911.973 | T16: ='AUTO CALCULATION SHEET (2)'!N17 -> 7 | U16: ='AUTO CALCULATION SHEET (2)'!T17 -> 0 | V16: ='AUTO CALCULATION SHEET (2)'!AF17 -> 9 | W16: ='AUTO CALCULATION SHEET (2)'!AQ17 -> 0 | X16: ='AUTO CALCULATION SHEET (2)'!AR17 -> 0 | Y16: ='AUTO CALCULATION SHEET (2)'!AX17 -> 0 | Z16: ='AUTO CALCULATION SHEET (2)'!AZ17 -> 0 | AA16: ='AUTO CALCULATION SHEET (2)'!BA17 -> 0 | AB16: ='AUTO CALCULATION SHEET (2)'!BF17 -> 52 | AC16: ='AUTO CALCULATION SHEET (2)'!BO17 -> 0 | AD16: ='AUTO CALCULATION SHEET (2)'!BT17 -> 0 | AE16: =SUMPRODUCT($T$14:$AD$14,T16:AD16) -> 7864 | AF16: ='AUTO CALCULATION SHEET (2)'!BZ17 -> 2960 | AG16: =AE16+AF16 -> 10824 | AH16: =S16-AG16 -> 6087.9735 | AI16: =ROUND((AH16/AG16)*100,2) -> 56.25 | AK16: 2 | AL16: 1 | AM16: =AI16-AJ16-AK16-AL16 -> 53.25
A17: 1 CORE X 4 SQ. MM. ALU/UNARD (XLPE) | C17: PROVISIONAL | D17: 45201 | E17: 218785.75 | G17: =$B$1 -> 45170 | H17: 208424.45 | J17: =10.4/1000 -> 0.0104 | O17: ='AUTO CALCULATION SHEET (2)'!E18 -> 19181.925 | P17: =(J17*(E17-H17)) -> 107.75752 | Q17: =(M17*(F17-I17)) -> 0 | R17: =P17+Q17 -> 107.75752 | S17: =+O17+R17 -> 19289.683 | T17: ='AUTO CALCULATION SHEET (2)'!N18 -> 11 | U17: ='AUTO CALCULATION SHEET (2)'!T18 -> 0 | V17: ='AUTO CALCULATION SHEET (2)'!AF18 -> 11 | W17: ='AUTO CALCULATION SHEET (2)'!AQ18 -> 0 | X17: ='AUTO CALCULATION SHEET (2)'!AR18 -> 0 | Y17: ='AUTO CALCULATION SHEET (2)'!AX18 -> 0 | Z17: ='AUTO CALCULATION SHEET (2)'!AZ18 -> 0 | AA17: ='AUTO CALCULATION SHEET (2)'!BA18 -> 0 | AB17: ='AUTO CALCULATION SHEET (2)'!BF18 -> 56 | AC17: ='AUTO CALCULATION SHEET (2)'!BO18 -> 0 | AD17: ='AUTO CALCULATION SHEET (2)'!BT18 -> 0 | AE17: =SUMPRODUCT($T$14:$AD$14,T17:AD17) -> 9396 | AF17: ='AUTO CALCULATION SHEET (2)'!BZ18 -> 2960 | AG17: =AE17+AF17 -> 12356 | AH17: =S17-AG17 -> 6933.6825 | AI17: =ROUND((AH17/AG17)*100,2) -> 56.12 | AK17: 2 | AL17: 1 | AM17: =AI17-AJ17-AK17-AL17 -> 53.12
A18: 1 CORE X 25 SQ. MM. ALU/UNARD (XLPE ) | C18: PROVISIONAL | D18: 45201 | E18: 218785.75 | G18: =$B$1 -> 45170 | H18: 208424.45 | J18: =65/1000 -> 0.065 | O18: ='AUTO CALCULATION SHEET (2)'!E19 -> 46242 | P18: =(J18*(E18-H18)) -> 673.4845 | Q18: =(M18*(F18-I18)) -> 0 | R18: =P18+Q18 -> 673.4845 | S18: =+O18+R18 -> 46915.484 | T18: ='AUTO CALCULATION SHEET (2)'!N19 -> 68 | U18: ='AUTO CALCULATION SHEET (2)'!T19 -> 0 | V18: ='AUTO CALCULATION SHEET (2)'!AF19 -> 26 | W18: ='AUTO CALCULATION SHEET (2)'!AQ19 -> 0 | X18: ='AUTO CALCULATION SHEET (2)'!AR19 -> 0 | Y18: ='AUTO CALCULATION SHEET (2)'!AX19 -> 0 | Z18: ='AUTO CALCULATION SHEET (2)'!AZ19 -> 0 | AA18: ='AUTO CALCULATION SHEET (2)'!BA19 -> 0 | AB18: ='AUTO CALCULATION SHEET (2)'!BF19 -> 89 | AC18: ='AUTO CALCULATION SHEET (2)'!BO19 -> 0 | AD18: ='AUTO CALCULATION SHEET (2)'!BT19 -> 0 | AE18: =SUMPRODUCT($T$14:$AD$14,T18:AD18) -> 27237 | AF18: ='AUTO CALCULATION SHEET (2)'!BZ19 -> 2960 | AG18: =AE18+AF18 -> 30197 | AH18: =S18-AG18 -> 16718.484 | AI18: =ROUND((AH18/AG18)*100,2) -> 55.36 | AK18: 2 | AL18: 1 | AM18: =AI18-AJ18-AK18-AL18 -> 52.36
A19: 1 CORE X 95 SQ. MM. AL/UNARD(XLPE ) | C19: PROVISIONAL | D19: 45201 | E19: 218785.75 | G19: =$B$1 -> 45170 | H19: 208424.45 | J19: 0.247 | O19: ='AUTO CALCULATION SHEET (2)'!E20 -> 128866.8 | P19: =(J19*(E19-H19)) -> 2559.2411 | Q19: =(M19*(F19-I19)) -> 0 | R19: =P19+Q19 -> 2559.2411 | S19: =+O19+R19 -> 131426.04 | T19: ='AUTO CALCULATION SHEET (2)'!N20 -> 256 | U19: ='AUTO CALCULATION SHEET (2)'!T20 -> 0 | V19: ='AUTO CALCULATION SHEET (2)'!AF20 -> 53 | W19: ='AUTO CALCULATION SHEET (2)'!AQ20 -> 0 | X19: ='AUTO CALCULATION SHEET (2)'!AR20 -> 0 | Y19: ='AUTO CALCULATION SHEET (2)'!AX20 -> 0 | Z19: ='AUTO CALCULATION SHEET (2)'!AZ20 -> 0 | AA19: ='AUTO CALCULATION SHEET (2)'!BA20 -> 0 | AB19: ='AUTO CALCULATION SHEET (2)'!BF20 -> 139 | AC19: ='AUTO CALCULATION SHEET (2)'!BO20 -> 0 | AD19: ='AUTO CALCULATION SHEET (2)'!BT20 -> 0 | AE19: =SUMPRODUCT($T$14:$AD$14,T19:AD19) -> 77531 | AF19: ='AUTO CALCULATION SHEET (2)'!BZ20 -> 7244.19 | AG19: =AE19+AF19 -> 84775.19 | AH19: =S19-AG19 -> 46650.85 | AI19: =ROUND((AH19/AG19)*100,2) -> 55.03 | AK19: 2 | AL19: 1 | AM19: =AI19-AJ19-AK19-AL19 -> 52.03
A20: 1 CORE X 185 SQ. MM. AL/UNARD. (XLPE) | C20: PROVISIONAL | D20: 45201 | E20: 218785.75 | G20: =$B$1 -> 45170 | H20: 208424.45 | J20: =482/1000 -> 0.482 | O20: ='AUTO CALCULATION SHEET (2)'!E21 -> 244370.89 | P20: =(J20*(E20-H20)) -> 4994.1466 | Q20: =(M20*(F20-I20)) -> 0 | R20: =P20+Q20 -> 4994.1466 | S20: =+O20+R20 -> 249365.04 | T20: ='AUTO CALCULATION SHEET (2)'!N21 -> 500 | U20: ='AUTO CALCULATION SHEET (2)'!T21 -> 0 | V20: ='AUTO CALCULATION SHEET (2)'!AF21 -> 90 | W20: ='AUTO CALCULATION SHEET (2)'!AQ21 -> 0 | X20: ='AUTO CALCULATION SHEET (2)'!AR21 -> 0 | Y20: ='AUTO CALCULATION SHEET (2)'!AX21 -> 0 | Z20: ='AUTO CALCULATION SHEET (2)'!AZ21 -> 0 | AA20: ='AUTO CALCULATION SHEET (2)'!BA21 -> 0 | AB20: ='AUTO CALCULATION SHEET (2)'!BF21 -> 210 | AC20: ='AUTO CALCULATION SHEET (2)'!BO21 -> 22 | AD20: ='AUTO CALCULATION SHEET (2)'!BT21 -> 0 | AE20: =SUMPRODUCT($T$14:$AD$14,T20:AD20) -> 152890 | AF20: ='AUTO CALCULATION SHEET (2)'!BZ21 -> 7976.12 | AG20: =AE20+AF20 -> 160866.12 | AH20: =S20-AG20 -> 88498.916 | AI20: =ROUND((AH20/AG20)*100,2) -> 55.01 | AK20: 2 | AL20: 1 | AM20: =AI20-AJ20-AK20-AL20 -> 52.01
A21: 1 CORE X 300 SQ. MM. AL/UNARD. (XLPE) | C21: PROVISIONAL | D21: 45201 | E21: 218785.75 | G21: =$B$1 -> 45170 | H21: 208424.45 | J21: =780/1000 -> 0.78 | O21: ='AUTO CALCULATION SHEET (2)'!E22 -> 387453.15 | P21: =(J21*(E21-H21)) -> 8081.814 | Q21: =(M21*(F21-I21)) -> 0 | R21: =P21+Q21 -> 8081.814 | S21: =+O21+R21 -> 395534.96 | T21: ='AUTO CALCULATION SHEET (2)'!N22 -> 810 | U21: ='AUTO CALCULATION SHEET (2)'!T22 -> 0 | V21: ='AUTO CALCULATION SHEET (2)'!AF22 -> 132 | W21: ='AUTO CALCULATION SHEET (2)'!AQ22 -> 0 | X21: ='AUTO CALCULATION SHEET (2)'!AR22 -> 0 | Y21: ='AUTO CALCULATION SHEET (2)'!AX22 -> 0 | Z21: ='AUTO CALCULATION SHEET (2)'!AZ22 -> 0 | AA21: ='AUTO CALCULATION SHEET (2)'!BA22 -> 0 | AB21: ='AUTO CALCULATION SHEET (2)'!BF22 -> 255 | AC21: ='AUTO CALCULATION SHEET (2)'!BO22 -> 28 | AD21: ='AUTO CALCULATION SHEET (2)'!BT22 -> 0 | AE21: =SUMPRODUCT($T$14:$AD$14,T21:AD21) -> 234267 | AF21: ='AUTO CALCULATION SHEET (2)'!BZ22 -> 20900 | AG21: =AE21+AF21 -> 255167 | AH21: =S21-AG21 -> 140367.96 | AI21: =ROUND((AH21/AG21)*100,2) -> 55.01 | AK21: 2 | AL21: 1 | AM21: =AI21-AJ21-AK21-AL21 -> 52.01
A22: 1 CORE X 630 SQ. MM. ALU/UNARD (XLPE) | C22: PROVISIONAL | D22: 45201 | E22: 218785.75 | G22: =$B$1 -> 45170 | H22: 208424.45 | J22: 1.64 | O22: ='AUTO CALCULATION SHEET (2)'!E23 -> 747471.38 | P22: =(J22*(E22-H22)) -> 16992.532 | Q22: =(M22*(F22-I22)) -> 0 | R22: =P22+Q22 -> 16992.532 | S22: =+O22+R22 -> 764463.91 | T22: ='AUTO CALCULATION SHEET (2)'!N23 -> 1701 | U22: ='AUTO CALCULATION SHEET (2)'!T23 -> 0 | V22: ='AUTO CALCULATION SHEET (2)'!AF23 -> 242 | W22: ='AUTO CALCULATION SHEET (2)'!AQ23 -> 0 | X22: ='AUTO CALCULATION SHEET (2)'!AR23 -> 0 | Y22: ='AUTO CALCULATION SHEET (2)'!AX23 -> 0 | Z22: ='AUTO CALCULATION SHEET (2)'!AZ23 -> 0 | AA22: ='AUTO CALCULATION SHEET (2)'!BA23 -> 0 | AB22: ='AUTO CALCULATION SHEET (2)'!BF23 -> 408 | AC22: ='AUTO CALCULATION SHEET (2)'!BO23 -> 40 | AD22: ='AUTO CALCULATION SHEET (2)'!BT23 -> 0 | AE22: =SUMPRODUCT($T$14:$AD$14,T22:AD22) -> 467104 | AF22: ='AUTO CALCULATION SHEET (2)'!BZ23 -> 26600 | AG22: =AE22+AF22 -> 493704 | AH22: =S22-AG22 -> 270759.91 | AI22: =ROUND((AH22/AG22)*100,2) -> 54.84 | AK22: 2 | AL22: 1 | AM22: =AI22-AJ22-AK22-AL22 -> 51.84
A23: 2 CORE X 16 SQ. MM. AL/ARD - WIRE (XLPE) | C23: PROVISIONAL | D23: 45201 | E23: 218785.75 | F23: 78250 | G23: =$B$1 -> 45170 | H23: 208424.45 | I23: 78250 | J23: =84/1000 -> 0.084 | M23: =202/1000 -> 0.202 | O23: ='AUTO CALCULATION SHEET (2)'!E24 -> 114603.6 | P23: =(J23*(E23-H23)) -> 870.3492 | Q23: =(M23*(F23-I23)) -> 0 | R23: =P23+Q23 -> 870.3492 | S23: =+O23+R23 -> 115473.95 | T23: ='AUTO CALCULATION SHEET (2)'!N24 -> 86 | U23: ='AUTO CALCULATION SHEET (2)'!T24 -> 0 | V23: ='AUTO CALCULATION SHEET (2)'!AF24 -> 37 | W23: ='AUTO CALCULATION SHEET (2)'!AQ24 -> 0 | X23: ='AUTO CALCULATION SHEET (2)'!AR24 -> 45 | Y23: ='AUTO CALCULATION SHEET (2)'!AX24 -> 0 | Z23: ='AUTO CALCULATION SHEET (2)'!AZ24 -> 0 | AA23: ='AUTO CALCULATION SHEET (2)'!BA24 -> 250 | AB23: ='AUTO CALCULATION SHEET (2)'!BF24 -> 120 | AC23: ='AUTO CALCULATION SHEET (2)'!BO24 -> 0 | AD23: ='AUTO CALCULATION SHEET (2)'!BT24 -> 11 | AE23: =SUMPRODUCT($T$14:$AD$14,T23:AD23) -> 66381 | AF23: ='AUTO CALCULATION SHEET (2)'!BZ24 -> 7244.19 | AG23: =AE23+AF23 -> 73625.19 | AH23: =S23-AG23 -> 41848.758 | AI23: =ROUND((AH23/AG23)*100,2) -> 56.84 | AK23: 2 | AL23: 1 | AM23: =AI23-AJ23-AK23-AL23 -> 53.84
A24: 2 CORE X 25 SQ. MM. AL/ARD - STRIP (XLPE) | C24: PROVISIONAL | D24: 45201 | E24: 218785.75 | F24: 79250 | G24: =$B$1 -> 45170 | H24: 208424.45 | I24: 79250 | J24: 0.13 | M24: 0.227 | O24: ='AUTO CALCULATION SHEET (2)'!E25 -> 137789.06 | P24: =(J24*(E24-H24)) -> 1346.969 | Q24: =(M24*(F24-I24)) -> 0 | R24: =P24+Q24 -> 1346.969 | S24: =+O24+R24 -> 139136.03 | T24: ='AUTO CALCULATION SHEET (2)'!N25 -> 135 | U24: ='AUTO CALCULATION SHEET (2)'!T25 -> 0 | V24: ='AUTO CALCULATION SHEET (2)'!AF25 -> 44 | W24: ='AUTO CALCULATION SHEET (2)'!AQ25 -> 0 | X24: ='AUTO CALCULATION SHEET (2)'!AR25 -> 50 | Y24: ='AUTO CALCULATION SHEET (2)'!AX25 -> 275 | Z24: ='AUTO CALCULATION SHEET (2)'!AZ25 -> 0 | AA24: ='AUTO CALCULATION SHEET (2)'!BA25 -> 0 | AB24: ='AUTO CALCULATION SHEET (2)'!BF25 -> 145 | AC24: ='AUTO CALCULATION SHEET (2)'!BO25 -> 0 | AD24: ='AUTO CALCULATION SHEET (2)'!BT25 -> 13 | AE24: =SUMPRODUCT($T$14:$AD$14,T24:AD24) -> 81189 | AF24: ='AUTO CALCULATION SHEET (2)'!BZ25 -> 7976.12 | AG24: =AE24+AF24 -> 89165.12 | AH24: =S24-AG24 -> 49970.913 | AI24: =ROUND((AH24/AG24)*100,2) -> 56.04 | AK24: 2 | AL24: 1 | AM24: =AI24-AJ24-AK24-AL24 -> 53.04
A25: 4 CORE X 25 SQ. MM. ALU/ARD - STRIP (XLPE) | C25: PROVISIONAL | D25: 45201 | E25: 218785.75 | F25: 79250 | G25: =$B$1 -> 45170 | H25: 208424.45 | I25: 79250 | J25: 0.26 | M25: 0.303 | O25: ='AUTO CALCULATION SHEET (2)'!E26 -> 204072.75 | P25: =(J25*(E25-H25)) -> 2693.938 | Q25: =(M25*(F25-I25)) -> 0 | R25: =P25+Q25 -> 2693.938 | S25: =+O25+R25 -> 206766.69 | T25: ='AUTO CALCULATION SHEET (2)'!N26 -> 270 | U25: ='AUTO CALCULATION SHEET (2)'!T26 -> 0 | V25: ='AUTO CALCULATION SHEET (2)'!AF26 -> 95 | W25: ='AUTO CALCULATION SHEET (2)'!AQ26 -> 46 | X25: ='AUTO CALCULATION SHEET (2)'!AR26 -> 0 | Y25: ='AUTO CALCULATION SHEET (2)'!AX26 -> 364 | Z25: ='AUTO CALCULATION SHEET (2)'!AZ26 -> 0 | AA25: ='AUTO CALCULATION SHEET (2)'!BA26 -> 0 | AB25: ='AUTO CALCULATION SHEET (2)'!BF26 -> 173 | AC25: ='AUTO CALCULATION SHEET (2)'!BO26 -> 0 | AD25: ='AUTO CALCULATION SHEET (2)'!BT26 -> 13 | AE25: =SUMPRODUCT($T$14:$AD$14,T25:AD25) -> 125385 | AF25: ='AUTO CALCULATION SHEET (2)'!BZ26 -> 7374 | AG25: =AE25+AF25 -> 132759 | AH25: =S25-AG25 -> 74007.688 | AI25: =ROUND((AH25/AG25)*100,2) -> 55.75 | AK25: 2 | AL25: 1 | AM25: =AI25-AJ25-AK25-AL25 -> 52.75
A26: 4 CORE X 50 SQ. MM. ALU/ARD - STRIP (XLPE) | C26: PROVISIONAL | D26: 45201 | E26: 218785.75 | F26: 79250 | G26: =$B$1 -> 45170 | H26: 208424.45 | I26: 79250 | J26: 0.52 | M26: 0.379 | O26: ='AUTO CALCULATION SHEET (2)'!E27 -> 348018.3 | P26: =(J26*(E26-H26)) -> 5387.876 | Q26: =(M26*(F26-I26)) -> 0 | R26: =P26+Q26 -> 5387.876 | S26: =+O26+R26 -> 353406.18 | T26: ='AUTO CALCULATION SHEET (2)'!N27 -> 540 | U26: ='AUTO CALCULATION SHEET (2)'!T27 -> 0 | V26: ='AUTO CALCULATION SHEET (2)'!AF27 -> 124 | W26: ='AUTO CALCULATION SHEET (2)'!AQ27 -> 69 | X26: ='AUTO CALCULATION SHEET (2)'!AR27 -> 0 | Y26: ='AUTO CALCULATION SHEET (2)'!AX27 -> 457 | Z26: ='AUTO CALCULATION SHEET (2)'!AZ27 -> 0 | AA26: ='AUTO CALCULATION SHEET (2)'!BA27 -> 0 | AB26: ='AUTO CALCULATION SHEET (2)'!BF27 -> 240 | AC26: ='AUTO CALCULATION SHEET (2)'!BO27 -> 0 | AD26: ='AUTO CALCULATION SHEET (2)'!BT27 -> 17 | AE26: =SUMPRODUCT($T$14:$AD$14,T26:AD26) -> 206313 | AF26: ='AUTO CALCULATION SHEET (2)'!BZ27 -> 20900 | AG26: =AE26+AF26 -> 227213 | AH26: =S26-AG26 -> 126193.18 | AI26: =ROUND((AH26/AG26)*100,2) -> 55.54 | AK26: 2 | AL26: 1 | AM26: =AI26-AJ26-AK26-AL26 -> 52.54
A27: 4 CORE X 95 SQ. MM. AL/ARD - STRIP (XLPE) | C27: PROVISIONAL | D27: 45201 | E27: 218785.75 | F27: 79250 | G27: =$B$1 -> 45170 | H27: 208424.45 | I27: 79250 | J27: 0.988 | M27: 0.505 | O27: ='AUTO CALCULATION SHEET (2)'!E28 -> 564254.77 | P27: =(J27*(E27-H27)) -> 10236.964 | Q27: =(M27*(F27-I27)) -> 0 | R27: =P27+Q27 -> 10236.964 | S27: =+O27+R27 -> 574491.74 | T27: ='AUTO CALCULATION SHEET (2)'!N28 -> 1026 | U27: ='AUTO CALCULATION SHEET (2)'!T28 -> 0 | V27: ='AUTO CALCULATION SHEET (2)'!AF28 -> 187 | W27: ='AUTO CALCULATION SHEET (2)'!AQ28 -> 93 | X27: ='AUTO CALCULATION SHEET (2)'!AR28 -> 0 | Y27: ='AUTO CALCULATION SHEET (2)'!AX28 -> 611 | Z27: ='AUTO CALCULATION SHEET (2)'!AZ28 -> 0 | AA27: ='AUTO CALCULATION SHEET (2)'!BA28 -> 0 | AB27: ='AUTO CALCULATION SHEET (2)'!BF28 -> 348 | AC27: ='AUTO CALCULATION SHEET (2)'!BO28 -> 0 | AD27: ='AUTO CALCULATION SHEET (2)'!BT28 -> 22.5 | AE27: =SUMPRODUCT($T$14:$AD$14,T27:AD27) -> 349084 | AF27: ='AUTO CALCULATION SHEET (2)'!BZ28 -> 20900 | AG27: =AE27+AF27 -> 369984 | AH27: =S27-AG27 -> 204507.74 | AI27: =ROUND((AH27/AG27)*100,2) -> 55.27 | AK27: 2 | AL27: 1 | AM27: =AI27-AJ27-AK27-AL27 -> 52.27
A28: 4 CORE X 150 SQ. MM. AL/ARD - STRIP/TYPE - B (XLPE) | C28: PROVISIONAL | D28: 45201 | E28: 218785.75 | F28: 79250 | G28: =$B$1 -> 45170 | H28: 208424.45 | I28: 79250 | J28: 1.56 | M28: 1.145 | O28: ='AUTO CALCULATION SHEET (2)'!E29 -> 977476.5 | P28: =(J28*(E28-H28)) -> 16163.628 | Q28: =(M28*(F28-I28)) -> 0 | R28: =P28+Q28 -> 16163.628 | S28: =+O28+R28 -> 993640.13 | T28: ='AUTO CALCULATION SHEET (2)'!N29 -> 1620 | U28: ='AUTO CALCULATION SHEET (2)'!T29 -> 0 | V28: ='AUTO CALCULATION SHEET (2)'!AF29 -> 285 | W28: ='AUTO CALCULATION SHEET (2)'!AQ29 -> 138 | X28: ='AUTO CALCULATION SHEET (2)'!AR29 -> 0 | Y28: ='AUTO CALCULATION SHEET (2)'!AX29 -> 0 | Z28: ='AUTO CALCULATION SHEET (2)'!AZ29 -> 1279 | AA28: ='AUTO CALCULATION SHEET (2)'!BA29 -> 0 | AB28: ='AUTO CALCULATION SHEET (2)'!BF29 -> 460 | AC28: ='AUTO CALCULATION SHEET (2)'!BO29 -> 55 | AD28: ='AUTO CALCULATION SHEET (2)'!BT29 -> 29 | AE28: =SUMPRODUCT($T$14:$AD$14,T28:AD28) -> 597238 | AF28: ='AUTO CALCULATION SHEET (2)'!BZ29 -> 41800 | AG28: =AE28+AF28 -> 639038 | AH28: =S28-AG28 -> 354602.13 | AI28: =ROUND((AH28/AG28)*100,2) -> 55.49 | AK28: 2 | AL28: 1 | AM28: =AI28-AJ28-AK28-AL28 -> 52.49
A29: 4 CORE X 300 SQ. MM. AL/ARD - WIRE (XLPE) | C29: PROVISIONAL | D29: 45201 | E29: 218785.75 | F29: 74250 | G29: =$B$1 -> 45170 | H29: 208424.45 | I29: 74250 | J29: 3.12 | M29: 2.323 | O29: ='AUTO CALCULATION SHEET (2)'!E30 -> 1901327.4 | P29: =(J29*(E29-H29)) -> 32327.256 | Q29: =(M29*(F29-I29)) -> 0 | R29: =P29+Q29 -> 32327.256 | S29: =+O29+R29 -> 1933654.7 | T29: ='AUTO CALCULATION SHEET (2)'!N30 -> 3240 | U29: ='AUTO CALCULATION SHEET (2)'!T30 -> 0 | V29: ='AUTO CALCULATION SHEET (2)'!AF30 -> 500 | W29: ='AUTO CALCULATION SHEET (2)'!AQ30 -> 240 | X29: ='AUTO CALCULATION SHEET (2)'!AR30 -> 0 | Y29: ='AUTO CALCULATION SHEET (2)'!AX30 -> 0 | Z29: ='AUTO CALCULATION SHEET (2)'!AZ30 -> 0 | AA29: ='AUTO CALCULATION SHEET (2)'!BA30 -> 2444 | AB29: ='AUTO CALCULATION SHEET (2)'!BF30 -> 835 | AC29: ='AUTO CALCULATION SHEET (2)'!BO30 -> 112 | AD29: ='AUTO CALCULATION SHEET (2)'!BT30 -> 44 | AE29: =SUMPRODUCT($T$14:$AD$14,T29:AD29) -> 1162683 | AF29: ='AUTO CALCULATION SHEET (2)'!BZ30 -> 78780 | AG29: =AE29+AF29 -> 1241463 | AH29: =S29-AG29 -> 692191.66 | AI29: =ROUND((AH29/AG29)*100,2) -> 55.76 | AK29: 2 | AL29: 1 | AM29: =AI29-AJ29-AK29-AL29 -> 52.76
A30: ='AUTO CALCULATION SHEET (2)'!D31 -> 2 CORE X 25 SQ MM + 1 CORE X 25 SQ MM (AB CABLES) (BARE) | C30: PROVISIONAL | D30: 45201 | E30: 218785.75 | G30: =$B$1 -> 45170 | H30: 208424.45 | J30: 0.197 | O30: ='AUTO CALCULATION SHEET (2)'!E31 -> 84853.17 | P30: =(J30*(E30-H30)) -> 2041.1761 | R30: =P30+Q30 -> 2041.1761 | S30: =+O30+R30 -> 86894.346 | T30: ='AUTO CALCULATION SHEET (2)'!N31 -> 135 | U30: ='AUTO CALCULATION SHEET (2)'!T31 -> 67.5 | V30: ='AUTO CALCULATION SHEET (2)'!AF31 -> 58 | W30: ='AUTO CALCULATION SHEET (2)'!AQ31 -> 0 | X30: ='AUTO CALCULATION SHEET (2)'!AR31 -> 0 | Y30: ='AUTO CALCULATION SHEET (2)'!AX31 -> 0 | Z30: ='AUTO CALCULATION SHEET (2)'!AZ31 -> 0 | AA30: ='AUTO CALCULATION SHEET (2)'!BA31 -> 0 | AB30: ='AUTO CALCULATION SHEET (2)'!BF31 -> 0 | AC30: ='AUTO CALCULATION SHEET (2)'!BO31 -> 0 | AD30: ='AUTO CALCULATION SHEET (2)'!BT31 -> 0 | AE30: =SUMPRODUCT($T$14:$AD$14,T30:AD30) -> 52560.5 | AF30: ='AUTO CALCULATION SHEET (2)'!BZ31 -> 3542.0286 | AG30: =AE30+AF30 -> 56102.529 | AH30: =S30-AG30 -> 30791.818 | AI30: =ROUND((AH30/AG30)*100,2) -> 54.88 | AK30: 2 | AL30: 1 | AM30: =AI30-AJ30-AK30-AL30 -> 51.88
A31: ='AUTO CALCULATION SHEET (2)'!D32 -> 4 CORE X 150 SQ MM + 1 CORE X 16 SQ MM + 1 CORE X 150 SQ MM (AB CABLES) (BARE) | C31: PROVISIONAL | D31: 45201 | E31: 218785.75 | G31: =$B$1 -> 45170 | H31: 208424.45 | J31: 2.032 | O31: ='AUTO CALCULATION SHEET (2)'!E32 -> 797786.07 | P31: =(J31*(E31-H31)) -> 21054.162 | R31: =P31+Q31 -> 21054.162 | S31: =+O31+R31 -> 818840.23 | T31: ='AUTO CALCULATION SHEET (2)'!N32 -> 1664 | U31: ='AUTO CALCULATION SHEET (2)'!T32 -> 415 | V31: ='AUTO CALCULATION SHEET (2)'!AF32 -> 370 | W31: ='AUTO CALCULATION SHEET (2)'!AQ32 -> 0 | X31: ='AUTO CALCULATION SHEET (2)'!AR32 -> 0 | Y31: ='AUTO CALCULATION SHEET (2)'!AX32 -> 0 | Z31: ='AUTO CALCULATION SHEET (2)'!AZ32 -> 0 | AA31: ='AUTO CALCULATION SHEET (2)'!BA32 -> 0 | AB31: ='AUTO CALCULATION SHEET (2)'!BF32 -> 0 | AC31: ='AUTO CALCULATION SHEET (2)'!BO32 -> 0 | AD31: ='AUTO CALCULATION SHEET (2)'!BT32 -> 0 | AE31: =SUMPRODUCT($T$14:$AD$14,T31:AD31) -> 511521 | AF31: ='AUTO CALCULATION SHEET (2)'!BZ32 -> 17878.84 | AG31: =AE31+AF31 -> 529399.84 | AH31: =S31-AG31 -> 289440.39 | AI31: =ROUND((AH31/AG31)*100,2) -> 54.67 | AK31: 2 | AL31: 1 | AM31: =AI31-AJ31-AK31-AL31 -> 51.67
