Workbook

Sheet Sheet1
A1: DOCKET NO. | B1: Base Date | C1: ITEM CODE | D1: PROPOSE ERP ITEM NAME | E1: PROPOSE DRUM TYPE | F1: Insulation Screening (Metallic) | G1: Sum of RM RATE (Insulation Screening (Metallic)) | H1: Weight (Insulation Screening (Metallic)) | I1: COST(Insulation Screening (Metallic)) | J1: Conductor | K1: Sum of RM RATE(Conductor) | L1: WEIGHT(Conductor) | M1: COST(Conductor) | N1: AL ALLOY | O1: Sum of RM RATE(Alu Alloy) | P1: WEIGHT(Alu Alloy) | Q1: COST(Alu Alloy) | R1: Insulation Screening (Non-Metallic) | S1: Sum of RM RATE(Insulation Screening (Non-Metallic)) | T1: WEIGHT(Insulation Screening (Non-Metallic)) | U1: COST(Insulation Screening (Non-Metallic)) | V1: Insulation | W1: Sum of RM RATE(Insulation) | X1: WEIGHT(Insulation) | Y1: COST(Insulation) | Z1: POLY TAPE | AA1: Sum of RM RATE (Poly Tape) | AB1: WEIGHT (Poly Tape) | AC1: COST(Poly Tape) | AD1: Inner Sheath | AE1: Sum of RM RATE(Inner Sheath) | AF1: WEIGHT(Inner Sheath) | AG1: COST(Inner Sheath) | AH1: Armouring | AI1: Sum of RM RATE(Armouring) | AJ1: WEIGHT(Armouring) | AK1: COST(Armouring) | AL1: Outer Sheath | AM1: Sum of RM RATE(Outer Sheath) | AN1: WEIGHT(Outer Sheath) | AO1: COST(Outer Sheath) | AP1: FILLER | AQ1: Sum of RM RATE(Filler) | AR1: WEIGHT(Filler) | AS1: COST(Filler) | AT1: GREASE | AU1: Sum of RM RATE(Grease) | AV1: WEIGHT(Grease) | AW1: COST(Grease) | AX1: Water swellable Tape | AY1: Sum of RM RATE(Water swellable Tape) | AZ1: WEIGHT(Water swellable Tape) | BA1: COST(Water swellable Tape) | BB1: Semi conducting Water Swellable tape | BC1: Sum of RM RATE(Semi conducting Water Swellable tape) | BD1: WEIGHT(Semi conducting Water Swellable tape) | BE1: COST(Semi conducting Water Swellable tape) | BF1: SEMICON TAPE | BG1: Sum of RM RATE(SEMICON TAPE) | BH1: WEIGHT(SEMICON TAPE) | BI1: COST(SEMICON TAPE) | BJ1: GLASS FIBER TAPE | BK1: Sum of RM RATE(GLASS FIBER TAPE) | BL1: WEIGHT(GLASS FIBER TAPE) | BM1: COST(GLASS FIBER TAPE) | BN1: COPPER WIRE 0.8 MM | BO1: Sum of RM RATE(COPPER WIRE 0.8 MM) | BP1: WEIGHT(COPPER WIRE 0.8 MM) | BQ1: COST(COPPER WIRE 0.8 MM) | BR1: RUBBERIZED COTTON TAPE | BS1: Sum of RM RATE(RUBBERIZED COTTON TAPE) | BT1: WEIGHT(RUBBERIZED COTTON TAPE) | BU1: COST(RUBBERIZED COTTON TAPE) | BV1: Water Tight Compound | BW1: Sum of RM RATE(Water Tight Compound) | BX1: WEIGHT(Water Tight Compound) | BY1: COST(Water Tight Compound) | BZ1: DRUM COST PER KM | CA1: TOTAL RM COST | CB1: FIRM % | CC1: FIRM VALUE | CD1: MFG% | CE1: MFG VALUE | CF1: PROF% | CG1: PROFIT VALUE | CH1: 1ST EX-WORKS | CI1: Intt % | CJ1: INTT VALUE | CK1: insp% | CL1: INSP VALUE | CM1: EX-WORKS (PER KM) | CN1: FREIGHT PER KM | CO1: PRICE INCLUDING FREIGHT (PER KM) | CP1: GST % | CQ1: GST VALUE | CR1: PRICE INCLUDING GST & FREIGHT (PER KM) | CS1: QTY | CT1: Unit | CU1: TOTAL PRICE OF FULL QTY (INCLUDING FRIGHT & GST) | CV1: DRUM CODE | CW1: DRUM SIZE (FxbXtx Ft) | CX1: PARTY STANDARD LENGTH (MTR)
A2: ENQ-10773-22-23 | B2: 45135 | C2: FA1300200 | D2: 3 CORE X 95 SQ. MM. AL/ARM WIRE (XLPE) - 33 KV | E2: STEEL | F2: Copper Tape - 0.045 mm | G2: 872.6 | H2: 129.106 | I2: 112657.9 | J2: Alumimium | K2: 212 | L2: 769.5 | M2: 163134 | P2: 0 | R2: Extruded Semiconductive | S2: 194 | T2: 268 | U2: 51992 | V2: HT-XLPE | W2: 150.5 | X2: 1650 | Y2: 248325 | AB2: 0 | AD2: PVC Type ST-2-PRESSURE EXTRUDED | AE2: 85 | AF2: 288 | AG2: 24480 | AH2: Galvanised Steel Round Wire | AI2: 86.87 | AJ2: 3945 | AK2: 342702.15 | AL2: FRLSH PVC Type ST-2 | AM2: 91 | AN2: 1217 | AO2: 110747 | AP2: Polypropylene Filler | AR2: 1370 | AV2: 0 | AX2: Water swellable Tape | AY2: 460 | AZ2: 0 | BA2: 0 | BB2: Semi conducting Water Swellable tape | BC2: 510 | BD2: 0 | BE2: 0 | BH2: 0 | BL2: 0 | BP2: 0 | BR2: RUBBERIZED COTTON TAPE | BS2: 440 | BT2: 0 | BU2: 0 | BX2: 0 | BZ2: 147200 | CA2: 1201238.1 | CH2: 1201238.1 | CM2: 1201238.1 | CO2: 1201238.1 | CP2: 0.18 | CQ2: 216222.85 | CR2: 1417460.9 | CS2: 0.5 | CT2: KMS | CU2: 708730 | CV2: SP0400136 | CW2: CORRUGATED DISPATCH STEEL DRUM 2200 X 1300 X 1200 MM | CX2: 250
A3: ENQ-10773-22-23 | B3: 45135 | C3: FA1300176 | D3: 3 CORE X 150 SQ. MM. AL/ARM - WIRE (XLPE) - 11 KV | E3: STEEL | F3: Copper Tape - 0.045 mm | G3: 872.6 | H3: 98.846 | I3: 86253.02 | J3: Alumimium | K3: 212 | L3: 1215 | M3: 257580 | P3: 0 | R3: Extruded Semiconductive | S3: 194 | T3: 208 | U3: 40352 | V3: HT-XLPE | W3: 150.5 | X3: 625 | Y3: 94062.5 | AB3: 0 | AD3: PVC Type ST-2-PRESSURE EXTRUDED | AE3: 85 | AF3: 173 | AG3: 14705 | AH3: Galvanised Steel Round Wire | AI3: 86.87 | AJ3: 2300 | AK3: 199801 | AL3: FRLSH PVC Type ST-2 | AM3: 91 | AN3: 713 | AO3: 64883 | AP3: Polypropylene Filler | AR3: 757 | AV3: 0 | AX3: Water swellable Tape | AY3: 460 | AZ3: 0 | BA3: 0 | BB3: Semi conducting Water Swellable tape | BC3: 510 | BD3: 162 | BE3: 82620 | BH3: 0 | BL3: 0 | BP3: 0 | BR3: RUBBERIZED COTTON TAPE | BS3: 440 | BT3: 0 | BU3: 0 | BX3: 0 | BZ3: 108300 | CA3: 948556.52 | CH3: 948556.52 | CM3: 948556.52 | CO3: 948556.52 | CP3: 0.18 | CQ3: 170740.17 | CR3: 1119296.7 | CS3: 1 | CT3: KMS | CU3: 1119297 | CV3: SP0400111 | CW3: CORRUGATED DISPATCH STEEL DRUM 1900 X 1000 X 1000 MM | CX3: 250
A4: ENQ-10773-22-23 | B4: 45135 | C4: FA1300088 | D4: 3 CORE X 95 SQ. MM. AL/ARM - WIRE (XLPE) - 11 KV (E) | E4: STEEL | F4: Copper Tape - 0.045 mm | G4: 872.6 | H4: 85.995 | I4: 75039.24 | J4: Alumimium | K4: 212 | L4: 769.5 | M4: 163134 | P4: 0 | R4: Extruded Semiconductive | S4: 194 | T4: 173 | U4: 33562 | V4: HT-XLPE | W4: 150.5 | X4: 525 | Y4: 79012.5 | AB4: 0 | AD4: PVC Type ST-2-PRESSURE EXTRUDED | AE4: 85 | AF4: 129 | AG4: 10965 | AH4: Galvanised Steel Round Wire | AI4: 86.87 | AJ4: 2001 | AK4: 173826.87 | AL4: FRLSH PVC Type ST-2 | AM4: 91 | AN4: 605 | AO4: 55055 | AP4: FILLER | AQ4: 31 | AR4: 573 | AS4: 17763 | AV4: 0 | AX4: Water swellable Tape | AY4: 460 | AZ4: 0 | BA4: 0 | BB4: Semi conducting Water Swellable tape | BC4: 510 | BD4: 52 | BE4: 26520 | BH4: 0 | BL4: 0 | BP4: 0 | BT4: 0 | BX4: 0 | CA4: 634877.61 | CH4: 634877.61 | CM4: 634877.61 | CO4: 634877.61 | CP4: 0.18 | CQ4: 114277.97 | CR4: 749155.58 | CS4: 2.5 | CT4: KMS | CU4: 1872889 | CX4: 250
A5: ENQ-10773-22-23 | B5: 45135 | C5: FA1300016 | D5: 1 CORE X 630 SQ. MM. AL/ARM (XLPE) - 11 KV | E5: STEEL | F5: Copper Tape - 0.045 mm | G5: 872.6 | H5: 54.366 | I5: 47439.78 | J5: Alumimium | K5: 212 | L5: 1701 | M5: 360612 | P5: 0 | R5: Extruded Semiconductive | S5: 194 | T5: 128 | U5: 24832 | V5: HT-XLPE | W5: 150.5 | X5: 375 | Y5: 56437.5 | Z5: POLY TAPE | AA5: 120 | AB5: 0 | AC5: 0 | AD5: PVC Type ST-2 | AE5: 60.7 | AF5: 171 | AG5: 10379.7 | AH5: Aluminium Round Wire | AI5: 217 | AJ5: 494 | AK5: 107198 | AL5: FRLSH PVC Type ST-2 | AM5: 91 | AN5: 407 | AO5: 37037 | AR5: 0 | AV5: 0 | AX5: Water swellable Tape | AY5: 460 | AZ5: 0 | BA5: 0 | BB5: Semi conducting Water Swellable tape | BC5: 510 | BD5: 70 | BE5: 35700 | BH5: 0 | BL5: 0 | BP5: 0 | BR5: RUBBERIZED COTTON TAPE | BS5: 440 | BT5: 0 | BU5: 0 | BX5: 0 | BZ5: 48450 | CA5: 728085.98 | CH5: 728085.98 | CM5: 728085.98 | CO5: 728085.98 | CP5: 0.18 | CQ5: 131055.48 | CR5: 859141.46 | CS5: 5 | CT5: KMS | CU5: 4295707 | CV5: SP0400091 | CW5: CORRUGATED DISPATCH STEEL DRUM 1800 X 900 X 1000 | CX5: 500
A6: ENQ-10773-22-23 | B6: 45135 | C6: FA1300197 | D6: 3 CORE X 120 SQ. MM. AL/ARM - WIRE (XLPE) - 11 KV | E6: STEEL | F6: Copper Tape - 0.045 mm | G6: 872.6 | H6: 92.628 | I6: 80827.2 | J6: Alumimium | K6: 212 | L6: 972 | M6: 206064 | P6: 0 | R6: Extruded Semiconductive | S6: 194 | T6: 232 | U6: 45008 | V6: HT-XLPE | W6: 150.5 | X6: 567 | Y6: 85333.5 | AB6: 0 | AD6: PVC Type ST-2-PRESSURE EXTRUDED | AE6: 85 | AF6: 185 | AG6: 15725 | AH6: Galvanised Steel Round Wire | AI6: 86.87 | AJ6: 2244 | AK6: 194936.28 | AL6: FRLSH PVC Type ST-2 | AM6: 91 | AN6: 669 | AO6: 60879 | AP6: Polypropylene Filler | AR6: 704 | AV6: 0 | AX6: Water swellable Tape | AY6: 460 | AZ6: 0 | BA6: 0 | BB6: Semi conducting Water Swellable tape | BC6: 510 | BD6: 59 | BE6: 30090 | BH6: 0 | BL6: 0 | BP6: 0 | BR6: RUBBERIZED COTTON TAPE | BS6: 440 | BT6: 0 | BU6: 0 | BX6: 0 | BZ6: 95000 | CA6: 813862.98 | CH6: 813862.98 | CM6: 813862.98 | CO6: 813862.98 | CP6: 0.18 | CQ6: 146495.34 | CR6: 960358.32 | CS6: 6.5 | CT6: KMS | CU6: 6242329 | CV6: SP0400118 | CW6: CORRUGATED DISPATCH STEEL DRUM 1700 X 1000 X 1200 | CX6: 250
A7: ENQ-10773-22-23 | B7: 45135 | C7: FA1300019 | D7: 1 CORE X 300 SQ. MM. AL/ARM (XLPE) - 33 KV | E7: STEEL | F7: Copper Tape - 0.045 mm | G7: 872.6 | H7: 54.919 | I7: 47922.32 | J7: Alumimium | K7: 212 | L7: 810 | M7: 171720 | P7: 0 | R7: Extruded Semiconductive | S7: 194 | T7: 105 | U7: 20370 | V7: HT-XLPE | W7: 150.5 | X7: 790 | Y7: 118895 | Z7: POLY TAPE | AA7: 120 | AB7: 0 | AC7: 0 | AD7: PVC Type ST-2 | AE7: 60.7 | AF7: 173 | AG7: 10501.1 | AH7: Aluminium Round Wire | AI7: 217 | AJ7: 623 | AK7: 135191 | AL7: FRLSH PVC Type ST-2 | AM7: 91 | AN7: 454 | AO7: 41314 | AR7: 0 | AV7: 0 | AX7: Water swellable Tape | AY7: 460 | AZ7: 0 | BA7: 0 | BB7: Semi conducting Water Swellable tape | BC7: 510 | BD7: 0 | BE7: 0 | BH7: 0 | BL7: 0 | BP7: 0 | BR7: RUBBERIZED COTTON TAPE | BS7: 440 | BT7: 0 | BU7: 0 | BX7: 0 | BZ7: 47500 | CA7: 593413.42 | CH7: 593413.42 | CM7: 593413.42 | CO7: 593413.42 | CP7: 0.18 | CQ7: 106814.42 | CR7: 700227.84 | CS7: 13 | CT7: KMS | CU7: 9102962 | CV7: SP0400110 | CW7: CORRUGATED DISPATCH STEEL DRUM 1600 X 900 X 1000 MM | CX7: 500
A8: ENQ-10773-22-23 | B8: 45135 | C8: FA1300066 | D8: 1 CORE X 1000 SQ. MM. AL/ARM (XLPE) - 11 KV | E8: STEEL | F8: Copper Tape - 0.045 mm | G8: 872.6 | H8: 66.388 | I8: 57930.17 | J8: Alumimium | K8: 212 | L8: 2700 | M8: 572400 | P8: 0 | R8: Extruded Semiconductive | S8: 194 | T8: 161 | U8: 31234 | V8: HT-XLPE | W8: 150.5 | X8: 468 | Y8: 70434 | Z8: POLY TAPE | AA8: 120 | AB8: 0 | AC8: 0 | AD8: PVC Type ST-2 | AE8: 60.7 | AF8: 231 | AG8: 14021.7 | AH8: Aluminium Round Wire | AI8: 217 | AJ8: 750 | AK8: 162750 | AL8: FRLSH PVC Type ST-2 | AM8: 91 | AN8: 542 | AO8: 49322 | AR8: 0 | AV8: 0 | AX8: Water swellable Tape | AY8: 460 | AZ8: 0 | BA8: 0 | BB8: Semi conducting Water Swellable tape | BC8: 510 | BD8: 99 | BE8: 50490 | BH8: 59 | BL8: 0 | BP8: 0 | BR8: RUBBERIZED COTTON TAPE | BS8: 440 | BT8: 52 | BU8: 22880 | BX8: 0 | BZ8: 66500 | CA8: 1097961.9 | CH8: 1097961.9 | CM8: 1097961.9 | CO8: 1097961.9 | CP8: 0.18 | CQ8: 197633.14 | CR8: 1295595 | CS8: 15 | CT8: KMS | CU8: 19433925 | CV8: SP0400107 | CW8: CORRUGATED DISPATCH STEEL DRUM 2150 X 1080 X 1240 MM | CX8: 500
A9: ENQ-10773-22-23 | B9: 45135 | C9: FA1300081 | D9: 3 CORE X 300 SQ. MM. AL/ARM - WIRE (XLPE) - 33 KV | E9: STEEL | F9: Copper Tape - 0.045 mm | G9: 872.6 | H9: 164.756 | I9: 143766.09 | J9: Alumimium | K9: 212 | L9: 2430 | M9: 515160 | P9: 0 | R9: Extruded Semiconductive | S9: 194 | T9: 394 | U9: 76436 | V9: HT-XLPE | W9: 150.5 | X9: 2355 | Y9: 354427.5 | AB9: 0 | AD9: PVC Type ST-2-PRESSURE EXTRUDED | AE9: 85 | AF9: 393 | AG9: 33405 | AH9: Galvanised Steel Round Wire | AI9: 86.87 | AJ9: 6463 | AK9: 561440.81 | AL9: FRLSH PVC Type ST-2 | AM9: 91 | AN9: 1550 | AO9: 141050 | AP9: Polypropylene Filler | AR9: 2292 | AV9: 0 | AX9: Water swellable Tape | AY9: 460 | AZ9: 0 | BA9: 0 | BB9: Semi conducting Water Swellable tape | BC9: 510 | BD9: 0 | BE9: 0 | BH9: 0 | BL9: 0 | BP9: 0 | BR9: RUBBERIZED COTTON TAPE | BS9: 440 | BT9: 0 | BU9: 0 | BX9: 0 | BZ9: 190000 | CA9: 2015685.4 | CH9: 2015685.4 | CM9: 2015685.4 | CO9: 2015685.4 | CP9: 0.18 | CQ9: 362823.37 | CR9: 2378508.8 | CS9: 15.09 | CT9: KMS | CU9: 35891697 | CV9: SP0400137 | CW9: CORRUGATED DISPATCH STEEL DRUM 2600 X 1600 X 1600 | CX9: 250
A10: ENQ-10773-22-23 | B10: 45135 | C10: FA1300018 | D10: 1 CORE X 400 SQ. MM. AL/ARM (XLPE) - 33 KV | E10: STEEL | F10: Copper Tape - 0.045 mm | G10: 872.6 | H10: 59.755 | I10: 52142.22 | J10: Alumimium | K10: 212 | L10: 1080 | M10: 228960 | P10: 0 | R10: Extruded Semiconductive | S10: 194 | T10: 119 | U10: 23086 | V10: HT-XLPE | W10: 150.5 | X10: 882 | Y10: 132741 | Z10: POLY TAPE | AA10: 120 | AB10: 0 | AC10: 0 | AD10: PVC Type ST-2 | AE10: 60.7 | AF10: 187 | AG10: 11350.9 | AH10: Aluminium Round Wire | AI10: 217 | AJ10: 675 | AK10: 146475 | AL10: FRLSH PVC Type ST-2 | AM10: 91 | AN10: 490 | AO10: 44590 | AR10: 0 | AV10: 0 | AX10: Water swellable Tape | AY10: 460 | AZ10: 54 | BA10: 24840 | BB10: Semi conducting Water Swellable tape | BC10: 510 | BD10: 0 | BE10: 0 | BH10: 52 | BL10: 0 | BP10: 0 | BR10: RUBBERIZED COTTON TAPE | BS10: 440 | BT10: 0 | BU10: 0 | BX10: 0 | BZ10: 53200 | CA10: 717385.12 | CH10: 717385.12 | CM10: 717385.12 | CO10: 717385.12 | CP10: 0.18 | CQ10: 129129.32 | CR10: 846514.44 | CS10: 25.5 | CT10: KMS | CU10: 21586118 | CV10: SP0400112 | CW10: CORRUGATED DISPATCH STEEL DRUM 2000 X 1000 X 1000 MM | CX10: 500
A11: ENQ-10773-22-23 | B11: 45135 | C11: FA1300047 | D11: 1 CORE X 400 SQ. MM. AL/ARM (XLPE) - 11 KV | E11: STEEL | F11: Copper Tape - 0.045 mm | G11: 872.6 | H11: 45.385 | I11: 39602.96 | J11: Alumimium | K11: 212 | L11: 1080 | M11: 228960 | P11: 0 | R11: Extruded Semiconductive | S11: 194 | T11: 103 | U11: 19982 | V11: HT-XLPE | W11: 150.5 | X11: 305 | Y11: 45902.5 | AB11: 0 | AD11: PVC Type ST-2 | AE11: 60.7 | AF11: 127 | AG11: 7708.9 | AH11: Aluminium Round Wire | AI11: 217 | AJ11: 413 | AK11: 89621 | AL11: FRLSH PVC Type ST-2 | AM11: 91 | AN11: 308 | AO11: 28028 | AR11: 0 | AV11: 0 | AX11: Water swellable Tape | AY11: 460 | AZ11: 0 | BA11: 0 | BB11: Semi conducting Water Swellable tape | BC11: 510 | BD11: 54 | BE11: 27540 | BH11: 0 | BL11: 0 | BP11: 0 | BT11: 0 | BX11: 0 | BZ11: 34200 | CA11: 521545.36 | CH11: 521545.36 | CM11: 521545.36 | CO11: 521545.36 | CP11: 0.18 | CQ11: 93878.16 | CR11: 615423.52 | CS11: 40 | CT11: KMS | CU11: 24616941 | CV11: SP0400125 | CW11: CORRUGATED DISPATCH STEEL DRUM 1600 X 700 X 915 MM | CX11: 500
A12: ENQ-10773-22-23 | B12: 45135 | C12: FA1300027 | D12: 1 CORE X 630 SQ. MM. AL/ARM (XLPE) - 33 KV | E12: STEEL | F12: Copper Tape - 0.045 mm | G12: 872.6 | H12: 68.737 | I12: 59979.91 | J12: Alumimium | K12: 212 | L12: 1701 | M12: 360612 | P12: 0 | R12: Extruded Semiconductive | S12: 194 | T12: 143 | U12: 27742 | V12: HT-XLPE | W12: 150.5 | X12: 1053 | Y12: 158476.5 | Z12: POLY TAPE | AA12: 120 | AB12: 0 | AC12: 0 | AD12: PVC Type ST-2 | AE12: 60.7 | AF12: 239 | AG12: 14507.3 | AH12: Aluminium Round Wire | AI12: 217 | AJ12: 776 | AK12: 168392 | AL12: FRLSH PVC Type ST-2 | AM12: 91 | AN12: 639 | AO12: 58149 | AR12: 0 | AV12: 0 | AX12: Water swellable Tape | AY12: 460 | AZ12: 0 | BA12: 0 | BB12: Semi conducting Water Swellable tape | BC12: 510 | BD12: 0 | BE12: 0 | BH12: 0 | BL12: 0 | BP12: 0 | BR12: RUBBERIZED COTTON TAPE | BS12: 440 | BT12: 0 | BU12: 0 | BX12: 0 | BZ12: 53200 | CA12: 901058.71 | CH12: 901058.71 | CM12: 901058.71 | CO12: 901058.71 | CP12: 0.18 | CQ12: 162190.57 | CR12: 1063249.3 | CS12: 33 | CT12: KMS | CU12: 35087226 | CV12: SP0400123 | CW12: CORRUGATED DISPATCH STEEL DRUM 2000 X 1000 X 1200 MM | CX12: 500
A13: ENQ-10773-22-23 | B13: 45135 | C13: FA1300083 | D13: 3 CORE X 400 SQ. MM. AL/ARM - WIRE (XLPE) - 11 KV | E13: STEEL | F13: Copper Tape - 0.045 mm | G13: 872.6 | H13: 136.153 | I13: 118807.11 | J13: Alumimium | K13: 212 | L13: 3240 | M13: 686880 | P13: 0 | R13: Extruded Semiconductive | S13: 194 | T13: 378 | U13: 73332 | V13: HT-XLPE | W13: 150.5 | X13: 897 | Y13: 134998.5 | AB13: 0 | AD13: PVC Type ST-2-PRESSURE EXTRUDED | AE13: 85 | AF13: 321 | AG13: 27285 | AH13: Galvanised Steel Round Wire | AI13: 86.87 | AJ13: 5335 | AK13: 463451.45 | AL13: FRLSH PVC Type ST-2 | AM13: 91 | AN13: 1303 | AO13: 118573 | AP13: Polypropylene Filler | AR13: 1525 | AV13: 0 | AX13: Water swellable Tape | AY13: 460 | AZ13: 0 | BA13: 0 | BB13: Semi conducting Water Swellable tape | BC13: 510 | BD13: 64 | BE13: 32640 | BH13: 0 | BL13: 0 | BP13: 0 | BR13: RUBBERIZED COTTON TAPE | BS13: 440 | BT13: 0 | BU13: 0 | BX13: 0 | BZ13: 182400 | CA13: 1838367.1 | CH13: 1838367.1 | CM13: 1838367.1 | CO13: 1838367.1 | CP13: 0.18 | CQ13: 330906.07 | CR13: 2169273.1 | CS13: 41.1 | CT13: KMS | CU13: 89157126 | CV13: SP0400105 | CW13: CORRUGATED DISPATCH STEEL DRUM 2500 X 1500 X 1400 | CX13: 250
A14: ENQ-10773-22-23 | B14: 45135 | C14: FA1300080 | D14: 3 CORE X 400 SQ. MM AL/ARM - WIRE (XLPE) - 33 KV | E14: STEEL | F14: Copper Tape - 0.045 mm | G14: 872.6 | H14: 179.265 | I14: 156426.64 | J14: Alumimium | K14: 212 | L14: 3240 | M14: 686880 | P14: 0 | R14: Extruded Semiconductive | S14: 194 | T14: 356 | U14: 69064 | V14: HT-XLPE | W14: 150.5 | X14: 2646 | Y14: 398223 | AB14: 0 | AD14: PVC Type ST-2-PRESSURE EXTRUDED | AE14: 85 | AF14: 414 | AG14: 35190 | AH14: Galvanised Steel Round Wire | AI14: 86.87 | AJ14: 6615 | AK14: 574645.05 | AL14: FRLSH PVC Type ST-2 | AM14: 91 | AN14: 1552 | AO14: 141232 | AP14: Polypropylene Filler | AR14: 2484 | AV14: 0 | AX14: Water swellable Tape | AY14: 460 | AZ14: 120 | BA14: 55200 | BB14: Semi conducting Water Swellable tape | BC14: 510 | BD14: 0 | BE14: 0 | BH14: 144 | BL14: 0 | BP14: 0 | BR14: RUBBERIZED COTTON TAPE | BS14: 440 | BT14: 0 | BU14: 0 | BX14: 0 | BZ14: 190000 | CA14: 2306860.7 | CH14: 2306860.7 | CM14: 2306860.7 | CO14: 2306860.7 | CP14: 0.18 | CQ14: 415234.92 | CR14: 2722095.6 | CS14: 103.5 | CT14: KMS | CU14: 281736896 | CV14: SP0400137 | CW14: CORRUGATED DISPATCH STEEL DRUM 2600 X 1600 X 1600 MM | CX14: 250
A15: ENQ-10773-22-23 | B15: 45135 | C15: FA1300091 | D15: 3 CORE X 300 SQ. MM. AL/ARM - WIRE (XLPE) - 11 KV | E15: STEEL | F15: Copper Tape - 0.045 mm | G15: 872.6 | H15: 121.645 | I15: 106147.43 | J15: Alumimium | K15: 212 | L15: 2430 | M15: 515160 | P15: 0 | R15: Extruded Semiconductive | S15: 194 | T15: 338 | U15: 65572 | V15: HT-XLPE | W15: 150.5 | X15: 802 | Y15: 120701 | AB15: 0 | AD15: PVC Type ST-2-PRESSURE EXTRUDED | AE15: 85 | AF15: 292 | AG15: 24820 | AH15: Galvanised Steel Round Wire | AI15: 86.87 | AJ15: 3817 | AK15: 331582.79 | AL15: FRLSH PVC Type ST-2 | AM15: 91 | AN15: 1125 | AO15: 102375 | AP15: Polypropylene Filler | AR15: 1305 | AV15: 0 | AX15: Water swellable Tape | AY15: 460 | AZ15: 0 | BA15: 0 | BB15: Semi conducting Water Swellable tape | BC15: 510 | BD15: 115 | BE15: 58650 | BH15: 34 | BL15: 0 | BP15: 0 | BR15: RUBBERIZED COTTON TAPE | BS15: 440 | BT15: 0 | BU15: 0 | BX15: 0 | BZ15: 171000 | CA15: 1496008.2 | CH15: 1496008.2 | CM15: 1496008.2 | CO15: 1496008.2 | CP15: 0.18 | CQ15: 269281.48 | CR15: 1765289.7 | CS15: 169.9 | CT15: KMS | CU15: 299922720 | CV15: SP0400136 | CW15: CORRUGATED DISPATCH STEEL DRUM 2200 X 1300 X 1200 MM | CX15: 250

Sheet AUTO CALCULATION SHEET (2)
A2: TP Central Odisha Distribution Limited
A4: TENDER SPECIFICATION NO () | B4: TPCODL/CCG/23-24/013.
A5: TENDER DESCRIPTION () | B5: Rate Contract for Supply of 11 KV & 33 KV HT XLPE Cable of various sizes for TPCODL, TPWODL & TPNODL.
A6: Last Date & Time of Submission () | B6: 31st July 2023 [17:00 Hrs.]
A7: REVERSE AUCTION | B7: CCG reserves the right to conduct the reverse auction (instead of public opening of price bids) for the products/ services being asked for in the tender. The terms and conditions for such reverse auction events shall be as per the Acceptance Form attached as Annexure VI of this document. The bidders along with the tender document shall mandatorily submit a duly signed copy of the Acceptance Form attached as Annexure VI as a token of acceptance for the same.
A8: Price () | B8: Price will be fixed and firm during the contractual period.
A9: Validity () | B9: Bids shall remain valid for 180 days from the due date of submission of the bid. Notwithstanding clause above, the Odisha DISCOMs may solicit the Bidder’s consent to an extension of the Period of Bid Validity. The request and responses thereto shall be made in writing.
A10: Delivery Period () | B10: Delivery period shall be 60 days from date of receipt of release order / CAT-A issuance, whichever is later.
A11: Payment Terms () | B11: TPCODL will make 100% payment within 30 days of submission of the Bill/Invoice complete in all respects and along with all the requisite documents mentioned above, subject to condition that Associate has furnished the requisite Security-cum-Performance Guarantee as stipulated in the contract.
A12: Standard length () | B12: The cable shall be supplied in continuous standard length of 250 (3 cores) & 500 (Single core) running meters with +/- 5% tolerance.
A13: Packing () | B13: Steel drums shall be provided. Drum shall be free from sharp edges and visual defect. Stencil plate on one flange side of the drum and laminated paper sheet on other side flange of drum.
A14: Technical Specification
N16: =Sheet1!J1 -> Conductor | S16: AL ALLOY | U16: Insulation Screening (Metallic) | AC16: Insulation Screening (Non-Metallic) | AE16: Insulation | AK16: POLY TAPE | AL16: Inner Sheath | AS16: Armouring | BC16: Outer Sheath | BF16: Consider Rs. 1 extra for colour of o/sh-FRLSH | BM16: FILLER | BN16: GREASE | BO16: Water swellable Tape | BP16: Semi conducting Water Swellable tape | BQ16: SEMICON TAPE | BR16: GLASS FIBER TAPE | BS16: COPPER WIRE 0.8 MM | BT16: RUBBERIZED COTTON TAPE | BU16: Water Tight Compound | BZ16: DRUM COST PER KM | CA16: TOTAL RM COST | CB16: EXTRA CONSUMPTION | CC16: EXTRA CONSUMPTION VALUE
A17: DOCKET NO. | B17: =Sheet1!B1 -> Base Date | C17: ITEM CODE | D17: PROPOSE ERP ITEM NAME | E17: EX-WORKS (PER KM) | F17: FREIGHT PER KM | G17: PRICE INCLUDING FREIGHT (PER KM) | H17: GST % | I17: GST VALUE | J17: PRICE INCLUDING GST & FREIGHT (PER KM) | K17: QTY | L17: Unit | M17: TOTAL PRICE OF FULL QTY (INCLUDING FRIGHT & GST) | N17: Alumimium | O17: Alumimium ALLOY | P17: Copper | Q17: Flexible Copper | R17: Galvanized steel wire | S17: Alumimium | T17: Alumimium ALLOY | U17: Coper tape - 0.1 mm | V17: Copper Tape - 0.03 mm | W17: Copper Tape - 0.035 mm | X17: Copper Tape - 0.04 mm | Y17: Copper Tape - 0.045 mm | Z17: Copper Tape - 0.050 mm | AA17: Copper Tape - 0.060 mm | AB17: Copper Tape - 0.075 mm(DOUBLE) | AC17: Extruded semiconductive | AD17: Extruded Semiconductive(Stripable) | AE17: HT-XLPE | AF17: LT-XLPE | AG17: TR XLPE | AH17: Type A PVC | AI17: Type C PVC (HR) | AJ17: XLPE | AK17: POLY TAPE | AL17: FR PVC Type ST-1 | AM17: FR PVC Type ST-2 | AN17: FRLSH PVC Type ST-2 | AO17: PVC Type ST-1 | AP17: PVC Type ST-1-PRESSURE EXTRUDED | AQ17: PVC Type ST-2 | AR17: PVC Type ST-2-PRESSURE EXTRUDED | AS17: ACSR CORE WIRE | AT17: ACSR DOG STEEL WIRE | AU17: Aluminium Flat Strip | AV17: Aluminium Round Wire | AW17: Double Steel Tape | AX17: Galvanised Steel Flat Strip | AY17: Galvanised Steel Flat Strip (Double) | AZ17: Galvanised Steel Flat Strip-B | BA17: Galvanised Steel Round Wire | BB17: Galvanised Steel Round Wire (Double) | BC17: FR PVC Type ST-1 | BD17: FR PVC Type ST-2 | BE17: FRLSH PVC Type ST-1 | BF17: FRLSH PVC Type ST-2 | BG17: Polypropylene Filler | BH17: PE, ST-7 | BI17: PVC Type ST-1 | BJ17: PVC Type ST-2 | BK17: PVC Type ST-2-PRESSURE EXTRUDED | BL17: UV & Track Resistant XLPE | BM17: FILLER | BN17: Grease | BO17: NCWBT | BP17: Semi conducting Water Swellable tape | BQ17: SEMICON TAPE | BR17: GLASS FIBER TAPE | BS17: COPPER WIRE 0.8 MM | BT17: RUBBERIZED COTTON TAPE | BU17: Water Tight Compound | BV17: =Sheet1!E1 -> PROPOSE DRUM TYPE | BW17: =Sheet1!CV1 -> DRUM CODE | BX17: =Sheet1!CW1 -> DRUM SIZE (FxbXtx Ft) | BY17: =Sheet1!CX1 -> PARTY STANDARD LENGTH (MTR) | CD17: MFG% | CE17: MFG VALUE | CF17: PROF% | CG17: PROFIT VALUE | CH17: 1ST EX-WORKS | CI17: Intt % | CJ17: INTT VALUE | CK17: insp% | CL17: INSP VALUE
N18: 216 | O18: =+IFERROR(VLOOKUP($O$17,Sheet1!J:L,2,0),0) -> 0 | P18: =+IFERROR(VLOOKUP($P$17,Sheet1!J:M,2,0),0) -> 0 | Q18: =+IFERROR(VLOOKUP($Q$17,Sheet1!J:M,2,0),0) -> 0 | R18: =+IFERROR(VLOOKUP($R$17,Sheet1!J:M,2,0),0) -> 0 | S18: =+IFERROR(VLOOKUP($S$17,Sheet1!N:Q,2,0),0) -> 0 | T18: =+IFERROR(VLOOKUP($T$17,Sheet1!N:O,2,0),0) -> 0 | U18: =+IFERROR(VLOOKUP($U$17,Sheet1!F:I,2,0),0) -> 0 | V18: =+IFERROR(VLOOKUP($V$17,Sheet1!F:I,2,0),0) -> 0 | W18: =+IFERROR(VLOOKUP($W$17,Sheet1!F:I,2,0),0) -> 0 | X18: =+IFERROR(VLOOKUP($X$17,Sheet1!F:I,2,0),0) -> 0 | Y18: 878 | Z18: =+IFERROR(VLOOKUP($Z$17,Sheet1!F:I,2,0),0) -> 0 | AA18: =+IFERROR(VLOOKUP($AA$17,Sheet1!F:I,2,0),0) -> 0 | AB18: =+IFERROR(VLOOKUP($AB$17,Sheet1!F:I,2,0),0) -> 0 | AC18: 195 | AD18: =+IFERROR(VLOOKUP($AD$17,Sheet1!R:U,2,0),0) -> 0 | AE18: 155 | AF18: =+IFERROR(VLOOKUP($AF$17,Sheet1!V:Y,2,0),0) -> 0 | AG18: =+IFERROR(VLOOKUP($AG$17,Sheet1!V:Y,2,0),0) -> 0 | AH18: =+IFERROR(VLOOKUP($AH$17,Sheet1!V:Y,2,0),0) -> 0 | AI18: =+IFERROR(VLOOKUP($AI$17,Sheet1!V:Y,2,0),0) -> 0 | AJ18: =+IFERROR(VLOOKUP($AJ$17,Sheet1!V:Y,2,0),0) -> 0 | AK18: 123 | AL18: =+IFERROR(VLOOKUP($AL$17,Sheet1!AD2:AG840,2,0),0) -> 0 | AM18: =+IFERROR(VLOOKUP($AM$17,Sheet1!AD2:AG840,2,0),0) -> 0 | AN18: =+IFERROR(VLOOKUP($AN$17,Sheet1!AD2:AG840,2,0),0) -> 0 | AO18: =+IFERROR(VLOOKUP($AO$17,Sheet1!AD2:AG840,2,0),0) -> 0 | AP18: =+IFERROR(VLOOKUP($AP$17,Sheet1!AD2:AG840,2,0),0) -> 0 | AQ18: 61 | AR18: 88 | AS18: =+IFERROR(VLOOKUP($AS$17,Sheet1!AH2:AK840,2,0),0) -> 0 | AT18: =+IFERROR(VLOOKUP($AT$17,Sheet1!AH2:AK840,2,0),0) -> 0 | AU18: =+IFERROR(VLOOKUP($AU$17,Sheet1!AH2:AK840,2,0),0) -> 0 | AV18: 219 | AW18: =+IFERROR(VLOOKUP($AW$17,Sheet1!AH2:AK840,2,0),0) -> 0 | AX18: =+IFERROR(VLOOKUP($AX$17,Sheet1!AH2:AK840,2,0),0) -> 0 | AY18: =+IFERROR(VLOOKUP($AY$17,Sheet1!AH2:AK840,2,0),0) -> 0 | AZ18: =+IFERROR(VLOOKUP($AZ$17,Sheet1!AH2:AK840,2,0),0) -> 0 | BA18: 87 | BB18: =+IFERROR(VLOOKUP($BB$17,Sheet1!AH2:AK840,2,0),0) -> 0 | BC18: =+IFERROR(VLOOKUP($BC$17,Sheet1!AL2:AO840,2,0),0) -> 0 | BD18: =+IFERROR(VLOOKUP($BD$17,Sheet1!AL2:AO840,2,0),0) -> 0 | BE18: =+IFERROR(VLOOKUP($BE$17,Sheet1!AL2:AO840,2,0),0) -> 0 | BF18: 94 | BG18: 65 | BH18: =+IFERROR(VLOOKUP($BH$17,Sheet1!AL2:AO840,2,0),0) -> 0 | BI18: =+IFERROR(VLOOKUP($BI$17,Sheet1!AL2:AO840,2,0),0) -> 0 | BJ18: =+IFERROR(VLOOKUP($BJ$17,Sheet1!AL2:AO840,2,0),0) -> 0 | BK18: =+IFERROR(VLOOKUP($BK$17,Sheet1!AL2:AO840,2,0),0) -> 0 | BL18: =+IFERROR(VLOOKUP($BL$17,Sheet1!AL2:AO840,2,0),0) -> 0 | BN18: =+IFERROR(VLOOKUP($BN$17,Sheet1!AT2:AW840,2,0),0) -> 0 | BO18: 350 | BP18: =+IFERROR(VLOOKUP($BP$17,Sheet1!BB2:BE840,2,0),0) -> 510 | BQ18: =+IFERROR(VLOOKUP($BQ$17,Sheet1!BF2:BI840,2,0),0) -> 0 | BR18: =+IFERROR(VLOOKUP($BR$17,Sheet1!BJ2:BM840,2,0),0) -> 0 | BS18: =+IFERROR(VLOOKUP($BS$17,Sheet1!BN2:BQ840,2,0),0) -> 0 | BT18: =+IFERROR(VLOOKUP($BT$17,Sheet1!BR2:BU840,2,0),0) -> 440 | BU18: =+IFERROR(VLOOKUP($BU$17,Sheet1!BV2:BY840,2,0),0) -> 0
A19: =Sheet1!A13 -> ENQ-10773-22-23 | B19: =Sheet1!B13 -> 45135 | C19: =Sheet1!C13 -> FA1300083 | D19: =Sheet1!D13 -> 3 CORE X 400 SQ. MM. AL/ARM - WIRE (XLPE) - 11 KV | E19: =CH19+CJ19+CL19 -> 3241791.6 | F19: =ROUNDUP(M35,0) -> 90998 | G19: =E19+F19 -> 3332789.6 | H19: =Sheet1!CP13 -> 0.18 | I19: =G19*H19 -> 599902.13 | J19: =G19+I19 -> 3932691.7 | K19: =12.6+28.5 -> 41.1 | L19: =Sheet1!CT13 -> KMS | M19: =J19*K19 -> 1.6163363e+08 | N19: 3243 | O19: =+IFERROR(VLOOKUP($O$17,Sheet1!J13:L13,3,0),0) -> 0 | P19: =+IFERROR(VLOOKUP($P$17,Sheet1!J13:M13,3,0),0) -> 0 | Q19: =+IFERROR(VLOOKUP($Q$17,Sheet1!J13:M13,3,0),0) -> 0 | R19: =+IFERROR(VLOOKUP($R$17,Sheet1!J13:M13,3,0),0) -> 0 | S19: =+IFERROR(VLOOKUP($S$17,Sheet1!N13:Q13,3,0),0) -> 0 | T19: =+IFERROR(VLOOKUP($T$17,Sheet1!N13:Q13,3,0),0) -> 0 | U19: =+IFERROR(VLOOKUP($U$17,Sheet1!F13:I13,3,0),0) -> 0 | V19: =+IFERROR(VLOOKUP($V$17,Sheet1!F13:I13,3,0),0) -> 0 | W19: =+IFERROR(VLOOKUP($W$17,Sheet1!F13:I13,3,0),0) -> 0 | X19: =+IFERROR(VLOOKUP($X$17,Sheet1!F13:I13,3,0),0) -> 0 | Y19: 158 | Z19: =+IFERROR(VLOOKUP($Z$17,Sheet1!F13:I13,3,0),0) -> 0 | AA19: =+IFERROR(VLOOKUP($AA$17,Sheet1!F13:I13,3,0),0) -> 0 | AB19: =+IFERROR(VLOOKUP($AB$17,Sheet1!F13:I13,3,0),0) -> 0 | AC19: 414 | AD19: =+IFERROR(VLOOKUP($AD$17,Sheet1!R13:U13,2,0),0) -> 0 | AE19: 938 | AF19: =+IFERROR(VLOOKUP($AF$17,Sheet1!V13:Y13,3,0),0) -> 0 | AG19: =+IFERROR(VLOOKUP($AG$17,Sheet1!V13:Y13,3,0),0) -> 0 | AH19: =+IFERROR(VLOOKUP($AH$17,Sheet1!V13:Y13,3,0),0) -> 0 | AI19: =+IFERROR(VLOOKUP($AI$17,Sheet1!V13:Y13,3,0),0) -> 0 | AJ19: =+IFERROR(VLOOKUP($AJ$17,Sheet1!V13:Y13,3,0),0) -> 0 | AK19: =+IFERROR(VLOOKUP($AK$17,Sheet1!Z13:AB13,3,0),0) -> 0 | AL19: =+IFERROR(VLOOKUP($AL$17,Sheet1!AD13:AG13,3,0),0) -> 0 | AM19: =+IFERROR(VLOOKUP($AM$17,Sheet1!AD13:AG13,3,0),0) -> 0 | AN19: =+IFERROR(VLOOKUP($AN$17,Sheet1!AD13:AG13,3,0),0) -> 0 | AO19: =+IFERROR(VLOOKUP($AO$17,Sheet1!AD13:AG13,3,0),0) -> 0 | AP19: =+IFERROR(VLOOKUP($AP$17,Sheet1!AD13:AG13,3,0),0) -> 0 | AQ19: =+IFERROR(VLOOKUP($AQ$17,Sheet1!AD13:AG13,3,0),0) -> 0 | AR19: 980 | AS19: =+IFERROR(VLOOKUP($AS$17,Sheet1!AH13:AK13,3,0),0) -> 0 | AT19: =+IFERROR(VLOOKUP($AT$17,Sheet1!AH13:AK13,3,0),0) -> 0 | AU19: =+IFERROR(VLOOKUP($AU$17,Sheet1!AH13:AK13,3,0),0) -> 0 | AV19: =+IFERROR(VLOOKUP($AV$17,Sheet1!AH13:AK13,3,0),0) -> 0 | AW19: =+IFERROR(VLOOKUP($AW$17,Sheet1!AH13:AK13,3,0),0) -> 0 | AX19: =+IFERROR(VLOOKUP($AX$17,Sheet1!AH13:AK13,3,0),0) -> 0 | AY19: =+IFERROR(VLOOKUP($AY$17,Sheet1!AH13:AK13,3,0),0) -> 0 | AZ19: =+IFERROR(VLOOKUP($AZ$17,Sheet1!AH13:AK13,3,0),0) -> 0 | BA19: 5540 | BB19: =+IFERROR(VLOOKUP($BB$17,Sheet1!AH13:AK13,3,0),0) -> 0 | BC19: =+IFERROR(VLOOKUP($BC$17,Sheet1!AL13:AO13,3,0),0) -> 0 | BD19: =+IFERROR(VLOOKUP($BD$17,Sheet1!AL13:AO13,3,0),0) -> 0 | BE19: =+IFERROR(VLOOKUP($BE$17,Sheet1!AL13:AO13,3,0),0) -> 0 | BF19: 1355 | BG19: 997 | BH19: =+IFERROR(VLOOKUP($BH$17,Sheet1!AL13:AO13,3,0),0) -> 0 | BI19: =+IFERROR(VLOOKUP($BI$17,Sheet1!AL13:AO13,3,0),0) -> 0 | BJ19: =+IFERROR(VLOOKUP($BJ$17,Sheet1!AL13:AO13,3,0),0) -> 0 | BK19: =+IFERROR(VLOOKUP($BK$17,Sheet1!AL13:AO13,3,0),0) -> 0 | BL19: =+IFERROR(VLOOKUP($BL$17,Sheet1!AL13:AO13,3,0),0) -> 0 | BM19: =+IFERROR(VLOOKUP($BM$17,Sheet1!AP13:AS13,3,0),0) -> 0 | BN19: =+IFERROR(VLOOKUP($BN$17,Sheet1!AT13:AW13,3,0),0) -> 0 | BO19: 58 | BP19: 86 | BQ19: =+IFERROR(VLOOKUP($BQ$17,Sheet1!BF13:BI13,3,0),0) -> 0 | BR19: =+IFERROR(VLOOKUP($BR$17,Sheet1!BJ13:BM13,3,0),0) -> 0 | BS19: =+IFERROR(VLOOKUP($BS$17,Sheet1!BN13:BQ13,3,0),0) -> 0 | BT19: 59 | BU19: =+IFERROR(VLOOKUP($BU$17,Sheet1!BV13:BY13,3,0),0) -> 0 | BV19: =Sheet1!E13 -> STEEL | BW19: =Sheet1!CV13 -> SP0400105 | BX19: =Sheet1!CW13 -> CORRUGATED DISPATCH STEEL DRUM 2500 X 1500 X 1400 | BY19: =Sheet1!CX13 -> 250 | BZ19: =Sheet1!BZ13 -> 182400 | CA19: =SUMPRODUCT($N$18:$BU$18,N19:BU19)+BZ19 -> 2098247 | CB19: =Sheet1!CB13 -> 0 | CC19: =CA19*CB19 -> 0 | CD19: 0.5 | CE19: =CA19*CD19 -> 1049123.5 | CF19: 0 | CG19: =CA19*CF19 -> 0 | CH19: =CA19+CC19+CE19+CG19 -> 3147370.5 | CI19: 0.02 | CJ19: =CH19*CI19 -> 62947.41 | CK19: 0.01 | CL19: =CH19*CK19 -> 31473.705
A20: =Sheet1!A15 -> ENQ-10773-22-23 | B20: =Sheet1!B15 -> 45135 | C20: =Sheet1!C15 -> FA1300091 | D20: =Sheet1!D15 -> 3 CORE X 300 SQ. MM. AL/ARM - WIRE (XLPE) - 11 KV | E20: =CH20+CJ20+CL20 -> 2598299.1 | F20: =ROUNDUP(M36,0) -> 68375 | G20: =E20+F20 -> 2666674.1 | H20: =Sheet1!CP15 -> 0.18 | I20: =G20*H20 -> 480001.34 | J20: =G20+I20 -> 3146675.5 | K20: =38.4+114+1.75 -> 154.15 | L20: =Sheet1!CT15 -> KMS | M20: =J20*K20 -> 4.8506002e+08 | N20: =+IFERROR(VLOOKUP($N$17,Sheet1!J15:L15,3,0),0) -> 2430 | O20: =+IFERROR(VLOOKUP($O$17,Sheet1!J15:L15,3,0),0) -> 0 | P20: =+IFERROR(VLOOKUP($P$17,Sheet1!J15:M15,3,0),0) -> 0 | Q20: =+IFERROR(VLOOKUP($Q$17,Sheet1!J15:M15,3,0),0) -> 0 | R20: =+IFERROR(VLOOKUP($R$17,Sheet1!J15:M15,3,0),0) -> 0 | S20: =+IFERROR(VLOOKUP($S$17,Sheet1!N15:Q15,3,0),0) -> 0 | T20: =+IFERROR(VLOOKUP($T$17,Sheet1!N15:Q15,3,0),0) -> 0 | U20: =+IFERROR(VLOOKUP($U$17,Sheet1!F15:I15,3,0),0) -> 0 | V20: =+IFERROR(VLOOKUP($V$17,Sheet1!F15:I15,3,0),0) -> 0 | W20: =+IFERROR(VLOOKUP($W$17,Sheet1!F15:I15,3,0),0) -> 0 | X20: =+IFERROR(VLOOKUP($X$17,Sheet1!F15:I15,3,0),0) -> 0 | Y20: 144 | Z20: =+IFERROR(VLOOKUP($Z$17,Sheet1!F15:I15,3,0),0) -> 0 | AA20: =+IFERROR(VLOOKUP($AA$17,Sheet1!F15:I15,3,0),0) -> 0 | AB20: =+IFERROR(VLOOKUP($AB$17,Sheet1!F15:I15,3,0),0) -> 0 | AC20: 370 | AD20: =+IFERROR(VLOOKUP($AD$17,Sheet1!R15:U15,2,0),0) -> 0 | AE20: 838 | AF20: =+IFERROR(VLOOKUP($AF$17,Sheet1!V15:Y15,3,0),0) -> 0 | AG20: =+IFERROR(VLOOKUP($AG$17,Sheet1!V15:Y15,3,0),0) -> 0 | AH20: =+IFERROR(VLOOKUP($AH$17,Sheet1!V15:Y15,3,0),0) -> 0 | AI20: =+IFERROR(VLOOKUP($AI$17,Sheet1!V15:Y15,3,0),0) -> 0 | AJ20: =+IFERROR(VLOOKUP($AJ$17,Sheet1!V15:Y15,3,0),0) -> 0 | AK20: =+IFERROR(VLOOKUP($AK$17,Sheet1!Z15:AB15,3,0),0) -> 0 | AL20: =+IFERROR(VLOOKUP($AL$17,Sheet1!AD15:AG15,3,0),0) -> 0 | AM20: =+IFERROR(VLOOKUP($AM$17,Sheet1!AD15:AG15,3,0),0) -> 0 | AN20: =+IFERROR(VLOOKUP($AN$17,Sheet1!AD15:AG15,3,0),0) -> 0 | AO20: =+IFERROR(VLOOKUP($AO$17,Sheet1!AD15:AG15,3,0),0) -> 0 | AP20: =+IFERROR(VLOOKUP($AP$17,Sheet1!AD15:AG15,3,0),0) -> 0 | AQ20: =+IFERROR(VLOOKUP($AQ$17,Sheet1!AD15:AG15,3,0),0) -> 0 | AR20: 840 | AS20: =+IFERROR(VLOOKUP($AS$17,Sheet1!AH15:AK15,3,0),0) -> 0 | AT20: =+IFERROR(VLOOKUP($AT$17,Sheet1!AH15:AK15,3,0),0) -> 0 | AU20: =+IFERROR(VLOOKUP($AU$17,Sheet1!AH15:AK15,3,0),0) -> 0 | AV20: =+IFERROR(VLOOKUP($AV$17,Sheet1!AH15:AK15,3,0),0) -> 0 | AW20: =+IFERROR(VLOOKUP($AW$17,Sheet1!AH15:AK15,3,0),0) -> 0 | AX20: =+IFERROR(VLOOKUP($AX$17,Sheet1!AH15:AK15,3,0),0) -> 0 | AY20: =+IFERROR(VLOOKUP($AY$17,Sheet1!AH15:AK15,3,0),0) -> 0 | AZ20: =+IFERROR(VLOOKUP($AZ$17,Sheet1!AH15:AK15,3,0),0) -> 0 | BA20: 3945 | BB20: =+IFERROR(VLOOKUP($BB$17,Sheet1!AH15:AK15,3,0),0) -> 0 | BC20: =+IFERROR(VLOOKUP($BC$17,Sheet1!AL15:AO15,3,0),0) -> 0 | BD20: =+IFERROR(VLOOKUP($BD$17,Sheet1!AL15:AO15,3,0),0) -> 0 | BE20: =+IFERROR(VLOOKUP($BE$17,Sheet1!AL15:AO15,3,0),0) -> 0 | BF20: 1170 | BG20: 830 | BH20: =+IFERROR(VLOOKUP($BH$17,Sheet1!AL15:AO15,3,0),0) -> 0 | BI20: =+IFERROR(VLOOKUP($BI$17,Sheet1!AL15:AO15,3,0),0) -> 0 | BJ20: =+IFERROR(VLOOKUP($BJ$17,Sheet1!AL15:AO15,3,0),0) -> 0 | BK20: =+IFERROR(VLOOKUP($BK$17,Sheet1!AL15:AO15,3,0),0) -> 0 | BL20: =+IFERROR(VLOOKUP($BL$17,Sheet1!AL15:AO15,3,0),0) -> 0 | BM20: =+IFERROR(VLOOKUP($BM$17,Sheet1!AP15:AS15,3,0),0) -> 0 | BN20: =+IFERROR(VLOOKUP($BN$17,Sheet1!AT15:AW15,3,0),0) -> 0 | BO20: 38 | BP20: 77 | BQ20: =+IFERROR(VLOOKUP($BQ$17,Sheet1!BF15:BI15,3,0),0) -> 0 | BR20: =+IFERROR(VLOOKUP($BR$17,Sheet1!BJ15:BM15,3,0),0) -> 0 | BS20: =+IFERROR(VLOOKUP($BS$17,Sheet1!BN15:BQ15,3,0),0) -> 0 | BT20: 54 | BU20: =+IFERROR(VLOOKUP($BU$17,Sheet1!BV15:BY15,3,0),0) -> 0 | BV20: =Sheet1!E15 -> STEEL | BW20: =Sheet1!CV15 -> SP0400136 | BX20: =Sheet1!CW15 -> CORRUGATED DISPATCH STEEL DRUM 2200 X 1300 X 1200 MM | BY20: =Sheet1!CX15 -> 250 | BZ20: =Sheet1!BZ15 -> 171000 | CA20: =SUMPRODUCT($N$18:$BU$18,N20:BU20)+BZ20 -> 1681747 | CB20: =Sheet1!CB15 -> 0 | CC20: =CA20*CB20 -> 0 | CD20: 0.5 | CE20: =CA20*CD20 -> 840873.5 | CF20: 0 | CG20: =CA20*CF20 -> 0 | CH20: =CA20+CC20+CE20+CG20 -> 2522620.5 | CI20: 0.02 | CJ20: =CH20*CI20 -> 50452.41 | CK20: 0.01 | CL20: =CH20*CK20 -> 25226.205
A21: =Sheet1!A3 -> ENQ-10773-22-23 | B21: =Sheet1!B3 -> 45135 | C21: =Sheet1!C3 -> FA1300176 | D21: =Sheet1!D3 -> 3 CORE X 150 SQ. MM. AL/ARM - WIRE (XLPE) - 11 KV | E21: =CH21+CJ21+CL21 -> 1671588 | F21: =ROUNDUP(M37,0) -> 68000 | G21: =E21+F21 -> 1739588 | H21: =Sheet1!CP3 -> 0.18 | I21: =G21*H21 -> 313125.85 | J21: =G21+I21 -> 2052713.9 | K21: =1 -> 1 | L21: =Sheet1!CT3 -> KMS | M21: =J21*K21 -> 2052713.9 | N21: =+IFERROR(VLOOKUP($N$17,Sheet1!J3:L3,3,0),0) -> 1215 | O21: =+IFERROR(VLOOKUP($O$17,Sheet1!J3:L3,3,0),0) -> 0 | P21: =+IFERROR(VLOOKUP($P$17,Sheet1!J3:M3,3,0),0) -> 0 | Q21: =+IFERROR(VLOOKUP($Q$17,Sheet1!J3:M3,3,0),0) -> 0 | R21: =+IFERROR(VLOOKUP($R$17,Sheet1!J3:M3,3,0),0) -> 0 | S21: =+IFERROR(VLOOKUP($S$17,Sheet1!N3:Q3,3,0),0) -> 0 | T21: =+IFERROR(VLOOKUP($T$17,Sheet1!N3:Q3,3,0),0) -> 0 | U21: =+IFERROR(VLOOKUP($U$17,Sheet1!F3:I3,3,0),0) -> 0 | V21: =+IFERROR(VLOOKUP($V$17,Sheet1!F3:I3,3,0),0) -> 0 | W21: =+IFERROR(VLOOKUP($W$17,Sheet1!F3:I3,3,0),0) -> 0 | X21: =+IFERROR(VLOOKUP($X$17,Sheet1!F3:I3,3,0),0) -> 0 | Y21: 117 | Z21: =+IFERROR(VLOOKUP($Z$17,Sheet1!F3:I3,3,0),0) -> 0 | AA21: =+IFERROR(VLOOKUP($AA$17,Sheet1!F3:I3,3,0),0) -> 0 | AB21: =+IFERROR(VLOOKUP($AB$17,Sheet1!F3:I3,3,0),0) -> 0 | AC21: 280 | AD21: =+IFERROR(VLOOKUP($AD$17,Sheet1!R3:U3,2,0),0) -> 0 | AE21: 642 | AF21: =+IFERROR(VLOOKUP($AF$17,Sheet1!V3:Y3,3,0),0) -> 0 | AG21: =+IFERROR(VLOOKUP($AG$17,Sheet1!V3:Y3,3,0),0) -> 0 | AH21: =+IFERROR(VLOOKUP($AH$17,Sheet1!V3:Y3,3,0),0) -> 0 | AI21: =+IFERROR(VLOOKUP($AI$17,Sheet1!V3:Y3,3,0),0) -> 0 | AJ21: =+IFERROR(VLOOKUP($AJ$17,Sheet1!V3:Y3,3,0),0) -> 0 | AK21: =+IFERROR(VLOOKUP($AK$17,Sheet1!Z3:AB3,3,0),0) -> 0 | AL21: =+IFERROR(VLOOKUP($AL$17,Sheet1!AD3:AG3,3,0),0) -> 0 | AM21: =+IFERROR(VLOOKUP($AM$17,Sheet1!AD3:AG3,3,0),0) -> 0 | AN21: =+IFERROR(VLOOKUP($AN$17,Sheet1!AD3:AG3,3,0),0) -> 0 | AO21: =+IFERROR(VLOOKUP($AO$17,Sheet1!AD3:AG3,3,0),0) -> 0 | AP21: =+IFERROR(VLOOKUP($AP$17,Sheet1!AD3:AG3,3,0),0) -> 0 | AQ21: =+IFERROR(VLOOKUP($AQ$17,Sheet1!AD3:AG3,3,0),0) -> 0 | AR21: 621 | AS21: =+IFERROR(VLOOKUP($AS$17,Sheet1!AH3:AK3,3,0),0) -> 0 | AT21: =+IFERROR(VLOOKUP($AT$17,Sheet1!AH3:AK3,3,0),0) -> 0 | AU21: =+IFERROR(VLOOKUP($AU$17,Sheet1!AH3:AK3,3,0),0) -> 0 | AV21: =+IFERROR(VLOOKUP($AV$17,Sheet1!AH3:AK3,3,0),0) -> 0 | AW21: =+IFERROR(VLOOKUP($AW$17,Sheet1!AH3:AK3,3,0),0) -> 0 | AX21: =+IFERROR(VLOOKUP($AX$17,Sheet1!AH3:AK3,3,0),0) -> 0 | AY21: =+IFERROR(VLOOKUP($AY$17,Sheet1!AH3:AK3,3,0),0) -> 0 | AZ21: =+IFERROR(VLOOKUP($AZ$17,Sheet1!AH3:AK3,3,0),0) -> 0 | BA21: 2685 | BB21: =+IFERROR(VLOOKUP($BB$17,Sheet1!AH3:AK3,3,0),0) -> 0 | BC21: =+IFERROR(VLOOKUP($BC$17,Sheet1!AL3:AO3,3,0),0) -> 0 | BD21: =+IFERROR(VLOOKUP($BD$17,Sheet1!AL3:AO3,3,0),0) -> 0 | BE21: =+IFERROR(VLOOKUP($BE$17,Sheet1!AL3:AO3,3,0),0) -> 0 | BF21: 800 | BG21: 541 | BH21: =+IFERROR(VLOOKUP($BH$17,Sheet1!AL3:AO3,3,0),0) -> 0 | BI21: =+IFERROR(VLOOKUP($BI$17,Sheet1!AL3:AO3,3,0),0) -> 0 | BJ21: =+IFERROR(VLOOKUP($BJ$17,Sheet1!AL3:AO3,3,0),0) -> 0 | BK21: =+IFERROR(VLOOKUP($BK$17,Sheet1!AL3:AO3,3,0),0) -> 0 | BL21: =+IFERROR(VLOOKUP($BL$17,Sheet1!AL3:AO3,3,0),0) -> 0 | BM21: =+IFERROR(VLOOKUP($BM$17,Sheet1!AP3:AS3,3,0),0) -> 0 | BN21: =+IFERROR(VLOOKUP($BN$17,Sheet1!AT3:AW3,3,0),0) -> 0 | BO21: 18 | BP21: 59 | BQ21: =+IFERROR(VLOOKUP($BQ$17,Sheet1!BF3:BI3,3,0),0) -> 0 | BR21: =+IFERROR(VLOOKUP($BR$17,Sheet1!BJ3:BM3,3,0),0) -> 0 | BS21: =+IFERROR(VLOOKUP($BS$17,Sheet1!BN3:BQ3,3,0),0) -> 0 | BT21: 44 | BU21: =+IFERROR(VLOOKUP($BU$17,Sheet1!BV3:BY3,3,0),0) -> 0 | BV21: =Sheet1!E3 -> STEEL | BW21: =Sheet1!CV3 -> SP0400111 | BX21: =Sheet1!CW3 -> CORRUGATED DISPATCH STEEL DRUM 1900 X 1000 X 1000 MM | BY21: =Sheet1!CX3 -> 250 | BZ21: =Sheet1!BZ3 -> 108300 | CA21: =SUMPRODUCT($N$18:$BU$18,N21:BU21)+BZ21 -> 1081934 | CB21: =Sheet1!CB3 -> 0 | CC21: =CA21*CB21 -> 0 | CD21: 0.5 | CE21: =CA21*CD21 -> 540967 | CF21: 0 | CG21: =CA21*CF21 -> 0 | CH21: =CA21+CC21+CE21+CG21 -> 1622901 | CI21: 0.02 | CJ21: =CH21*CI21 -> 32458.02 | CK21: 0.01 | CL21: =CH21*CK21 -> 16229.01
A22: =Sheet1!A6 -> ENQ-10773-22-23 | B22: =Sheet1!B6 -> 45135 | C22: =Sheet1!C6 -> FA1300197 | D22: =Sheet1!D6 -> 3 CORE X 120 SQ. MM. AL/ARM - WIRE (XLPE) - 11 KV | E22: =CH22+CJ22+CL22 -> 1462048.9 | F22: =ROUNDUP(M38,0) -> 54400 | G22: =E22+F22 -> 1516448.9 | H22: =Sheet1!CP6 -> 0.18 | I22: =G22*H22 -> 272960.81 | J22: =G22+I22 -> 1789409.8 | K22: =1+6.5 -> 7.5 | L22: =Sheet1!CT6 -> KMS | M22: =J22*K22 -> 13420573 | N22: =+IFERROR(VLOOKUP($N$17,Sheet1!J6:L6,3,0),0) -> 972 | O22: =+IFERROR(VLOOKUP($O$17,Sheet1!J6:L6,3,0),0) -> 0 | P22: =+IFERROR(VLOOKUP($P$17,Sheet1!J6:M6,3,0),0) -> 0 | Q22: =+IFERROR(VLOOKUP($Q$17,Sheet1!J6:M6,3,0),0) -> 0 | R22: =+IFERROR(VLOOKUP($R$17,Sheet1!J6:M6,3,0),0) -> 0 | S22: =+IFERROR(VLOOKUP($S$17,Sheet1!N6:Q6,3,0),0) -> 0 | T22: =+IFERROR(VLOOKUP($T$17,Sheet1!N6:Q6,3,0),0) -> 0 | U22: =+IFERROR(VLOOKUP($U$17,Sheet1!F6:I6,3,0),0) -> 0 | V22: =+IFERROR(VLOOKUP($V$17,Sheet1!F6:I6,3,0),0) -> 0 | W22: =+IFERROR(VLOOKUP($W$17,Sheet1!F6:I6,3,0),0) -> 0 | X22: =+IFERROR(VLOOKUP($X$17,Sheet1!F6:I6,3,0),0) -> 0 | Y22: 110 | Z22: =+IFERROR(VLOOKUP($Z$17,Sheet1!F6:I6,3,0),0) -> 0 | AA22: =+IFERROR(VLOOKUP($AA$17,Sheet1!F6:I6,3,0),0) -> 0 | AB22: =+IFERROR(VLOOKUP($AB$17,Sheet1!F6:I6,3,0),0) -> 0 | AC22: 258 | AD22: =+IFERROR(VLOOKUP($AD$17,Sheet1!R6:U6,2,0),0) -> 0 | AE22: 596 | AF22: =+IFERROR(VLOOKUP($AF$17,Sheet1!V6:Y6,3,0),0) -> 0 | AG22: =+IFERROR(VLOOKUP($AG$17,Sheet1!V6:Y6,3,0),0) -> 0 | AH22: =+IFERROR(VLOOKUP($AH$17,Sheet1!V6:Y6,3,0),0) -> 0 | AI22: =+IFERROR(VLOOKUP($AI$17,Sheet1!V6:Y6,3,0),0) -> 0 | AJ22: =+IFERROR(VLOOKUP($AJ$17,Sheet1!V6:Y6,3,0),0) -> 0 | AK22: =+IFERROR(VLOOKUP($AK$17,Sheet1!Z6:AB6,3,0),0) -> 0 | AL22: =+IFERROR(VLOOKUP($AL$17,Sheet1!AD6:AG6,3,0),0) -> 0 | AM22: =+IFERROR(VLOOKUP($AM$17,Sheet1!AD6:AG6,3,0),0) -> 0 | AN22: =+IFERROR(VLOOKUP($AN$17,Sheet1!AD6:AG6,3,0),0) -> 0 | AO22: =+IFERROR(VLOOKUP($AO$17,Sheet1!AD6:AG6,3,0),0) -> 0 | AP22: =+IFERROR(VLOOKUP($AP$17,Sheet1!AD6:AG6,3,0),0) -> 0 | AQ22: =+IFERROR(VLOOKUP($AQ$17,Sheet1!AD6:AG6,3,0),0) -> 0 | AR22: 513 | AS22: =+IFERROR(VLOOKUP($AS$17,Sheet1!AH6:AK6,3,0),0) -> 0 | AT22: =+IFERROR(VLOOKUP($AT$17,Sheet1!AH6:AK6,3,0),0) -> 0 | AU22: =+IFERROR(VLOOKUP($AU$17,Sheet1!AH6:AK6,3,0),0) -> 0 | AV22: =+IFERROR(VLOOKUP($AV$17,Sheet1!AH6:AK6,3,0),0) -> 0 | AW22: =+IFERROR(VLOOKUP($AW$17,Sheet1!AH6:AK6,3,0),0) -> 0 | AX22: =+IFERROR(VLOOKUP($AX$17,Sheet1!AH6:AK6,3,0),0) -> 0 | AY22: =+IFERROR(VLOOKUP($AY$17,Sheet1!AH6:AK6,3,0),0) -> 0 | AZ22: =+IFERROR(VLOOKUP($AZ$17,Sheet1!AH6:AK6,3,0),0) -> 0 | BA22: 2404 | BB22: =+IFERROR(VLOOKUP($BB$17,Sheet1!AH6:AK6,3,0),0) -> 0 | BC22: =+IFERROR(VLOOKUP($BC$17,Sheet1!AL6:AO6,3,0),0) -> 0 | BD22: =+IFERROR(VLOOKUP($BD$17,Sheet1!AL6:AO6,3,0),0) -> 0 | BE22: =+IFERROR(VLOOKUP($BE$17,Sheet1!AL6:AO6,3,0),0) -> 0 | BF22: 694 | BG22: 479 | BH22: =+IFERROR(VLOOKUP($BH$17,Sheet1!AL6:AO6,3,0),0) -> 0 | BI22: =+IFERROR(VLOOKUP($BI$17,Sheet1!AL6:AO6,3,0),0) -> 0 | BJ22: =+IFERROR(VLOOKUP($BJ$17,Sheet1!AL6:AO6,3,0),0) -> 0 | BK22: =+IFERROR(VLOOKUP($BK$17,Sheet1!AL6:AO6,3,0),0) -> 0 | BL22: =+IFERROR(VLOOKUP($BL$17,Sheet1!AL6:AO6,3,0),0) -> 0 | BM22: =+IFERROR(VLOOKUP($BM$17,Sheet1!AP6:AS6,3,0),0) -> 0 | BN22: =+IFERROR(VLOOKUP($BN$17,Sheet1!AT6:AW6,3,0),0) -> 0 | BO22: 16.5 | BP22: 55 | BQ22: =+IFERROR(VLOOKUP($BQ$17,Sheet1!BF6:BI6,3,0),0) -> 0 | BR22: =+IFERROR(VLOOKUP($BR$17,Sheet1!BJ6:BM6,3,0),0) -> 0 | BS22: =+IFERROR(VLOOKUP($BS$17,Sheet1!BN6:BQ6,3,0),0) -> 0 | BT22: 40 | BU22: =+IFERROR(VLOOKUP($BU$17,Sheet1!BV6:BY6,3,0),0) -> 0 | BV22: =Sheet1!E6 -> STEEL | BW22: =Sheet1!CV6 -> SP0400118 | BX22: =Sheet1!CW6 -> CORRUGATED DISPATCH STEEL DRUM 1700 X 1000 X 1200 | BY22: =Sheet1!CX6 -> 250 | BZ22: =Sheet1!BZ6 -> 95000 | CA22: =SUMPRODUCT($N$18:$BU$18,N22:BU22)+BZ22 -> 946310 | CB22: =Sheet1!CB6 -> 0 | CC22: =CA22*CB22 -> 0 | CD22: 0.5 | CE22: =CA22*CD22 -> 473155 | CF22: 0 | CG22: =CA22*CF22 -> 0 | CH22: =CA22+CC22+CE22+CG22 -> 1419465 | CI22: 0.02 | CJ22: =CH22*CI22 -> 28389.3 | CK22: 0.01 | CL22: =CH22*CK22 -> 14194.65
A23: =Sheet1!A4 -> ENQ-10773-22-23 | B23: =Sheet1!B4 -> 45135 | C23: FA1300098 | D23: 3 CORE X 95 SQ. MM. AL/ARM - WIRE (XLPE) - 11 KV | E23: =CH23+CJ23+CL23 -> 1316664.4 | F23: =ROUNDUP(M39,0) -> 54400 | G23: =E23+F23 -> 1371064.4 | H23: =Sheet1!CP4 -> 0.18 | I23: =G23*H23 -> 246791.6 | J23: =G23+I23 -> 1617856.1 | K23: =Sheet1!CS4 -> 2.5 | L23: =Sheet1!CT4 -> KMS | M23: =J23*K23 -> 4044640.1 | N23: =+IFERROR(VLOOKUP($N$17,Sheet1!J4:L4,3,0),0) -> 769.5 | O23: =+IFERROR(VLOOKUP($O$17,Sheet1!J4:L4,3,0),0) -> 0 | P23: =+IFERROR(VLOOKUP($P$17,Sheet1!J4:M4,3,0),0) -> 0 | Q23: =+IFERROR(VLOOKUP($Q$17,Sheet1!J4:M4,3,0),0) -> 0 | R23: =+IFERROR(VLOOKUP($R$17,Sheet1!J4:M4,3,0),0) -> 0 | S23: =+IFERROR(VLOOKUP($S$17,Sheet1!N4:Q4,3,0),0) -> 0 | T23: =+IFERROR(VLOOKUP($T$17,Sheet1!N4:Q4,3,0),0) -> 0 | U23: =+IFERROR(VLOOKUP($U$17,Sheet1!F4:I4,3,0),0) -> 0 | V23: =+IFERROR(VLOOKUP($V$17,Sheet1!F4:I4,3,0),0) -> 0 | W23: =+IFERROR(VLOOKUP($W$17,Sheet1!F4:I4,3,0),0) -> 0 | X23: =+IFERROR(VLOOKUP($X$17,Sheet1!F4:I4,3,0),0) -> 0 | Y23: 102 | Z23: =+IFERROR(VLOOKUP($Z$17,Sheet1!F4:I4,3,0),0) -> 0 | AA23: =+IFERROR(VLOOKUP($AA$17,Sheet1!F4:I4,3,0),0) -> 0 | AB23: =+IFERROR(VLOOKUP($AB$17,Sheet1!F4:I4,3,0),0) -> 0 | AC23: 232 | AD23: =+IFERROR(VLOOKUP($AD$17,Sheet1!R4:U4,2,0),0) -> 0 | AE23: 544 | AF23: =+IFERROR(VLOOKUP($AF$17,Sheet1!V4:Y4,3,0),0) -> 0 | AG23: =+IFERROR(VLOOKUP($AG$17,Sheet1!V4:Y4,3,0),0) -> 0 | AH23: =+IFERROR(VLOOKUP($AH$17,Sheet1!V4:Y4,3,0),0) -> 0 | AI23: =+IFERROR(VLOOKUP($AI$17,Sheet1!V4:Y4,3,0),0) -> 0 | AJ23: =+IFERROR(VLOOKUP($AJ$17,Sheet1!V4:Y4,3,0),0) -> 0 | AK23: =+IFERROR(VLOOKUP($AK$17,Sheet1!Z4:AB4,3,0),0) -> 0 | AL23: =+IFERROR(VLOOKUP($AL$17,Sheet1!AD4:AG4,3,0),0) -> 0 | AM23: =+IFERROR(VLOOKUP($AM$17,Sheet1!AD4:AG4,3,0),0) -> 0 | AN23: =+IFERROR(VLOOKUP($AN$17,Sheet1!AD4:AG4,3,0),0) -> 0 | AO23: =+IFERROR(VLOOKUP($AO$17,Sheet1!AD4:AG4,3,0),0) -> 0 | AP23: =+IFERROR(VLOOKUP($AP$17,Sheet1!AD4:AG4,3,0),0) -> 0 | AQ23: =+IFERROR(VLOOKUP($AQ$17,Sheet1!AD4:AG4,3,0),0) -> 0 | AR23: 460 | AS23: =+IFERROR(VLOOKUP($AS$17,Sheet1!AH4:AK4,3,0),0) -> 0 | AT23: =+IFERROR(VLOOKUP($AT$17,Sheet1!AH4:AK4,3,0),0) -> 0 | AU23: =+IFERROR(VLOOKUP($AU$17,Sheet1!AH4:AK4,3,0),0) -> 0 | AV23: =+IFERROR(VLOOKUP($AV$17,Sheet1!AH4:AK4,3,0),0) -> 0 | AW23: =+IFERROR(VLOOKUP($AW$17,Sheet1!AH4:AK4,3,0),0) -> 0 | AX23: =+IFERROR(VLOOKUP($AX$17,Sheet1!AH4:AK4,3,0),0) -> 0 | AY23: =+IFERROR(VLOOKUP($AY$17,Sheet1!AH4:AK4,3,0),0) -> 0 | AZ23: =+IFERROR(VLOOKUP($AZ$17,Sheet1!AH4:AK4,3,0),0) -> 0 | BA23: 2244 | BB23: =+IFERROR(VLOOKUP($BB$17,Sheet1!AH4:AK4,3,0),0) -> 0 | BC23: =+IFERROR(VLOOKUP($BC$17,Sheet1!AL4:AO4,3,0),0) -> 0 | BD23: =+IFERROR(VLOOKUP($BD$17,Sheet1!AL4:AO4,3,0),0) -> 0 | BE23: =+IFERROR(VLOOKUP($BE$17,Sheet1!AL4:AO4,3,0),0) -> 0 | BF23: 656 | BG23: 416 | BH23: =+IFERROR(VLOOKUP($BH$17,Sheet1!AL4:AO4,3,0),0) -> 0 | BI23: =+IFERROR(VLOOKUP($BI$17,Sheet1!AL4:AO4,3,0),0) -> 0 | BJ23: =+IFERROR(VLOOKUP($BJ$17,Sheet1!AL4:AO4,3,0),0) -> 0 | BK23: =+IFERROR(VLOOKUP($BK$17,Sheet1!AL4:AO4,3,0),0) -> 0 | BL23: =+IFERROR(VLOOKUP($BL$17,Sheet1!AL4:AO4,3,0),0) -> 0 | BN23: =+IFERROR(VLOOKUP($BN$17,Sheet1!AT4:AW4,3,0),0) -> 0 | BO23: 15 | BP23: 50 | BQ23: =+IFERROR(VLOOKUP($BQ$17,Sheet1!BF4:BI4,3,0),0) -> 0 | BR23: =+IFERROR(VLOOKUP($BR$17,Sheet1!BJ4:BM4,3,0),0) -> 0 | BS23: =+IFERROR(VLOOKUP($BS$17,Sheet1!BN4:BQ4,3,0),0) -> 0 | BT23: 38 | BU23: =+IFERROR(VLOOKUP($BU$17,Sheet1!BV4:BY4,3,0),0) -> 0 | BV23: =Sheet1!E4 -> STEEL | BW23: SP0400118 | BX23: CORRUGATED DISPATCH STEEL DRUM 1700 X 1000 X 1200 | BY23: =Sheet1!CX4 -> 250 | BZ23: 95000 | CA23: =SUMPRODUCT($N$18:$BU$18,N23:BU23)+BZ23 -> 852210 | CB23: =Sheet1!CB4 -> 0 | CC23: =CA23*CB23 -> 0 | CD23: 0.5 | CE23: =CA23*CD23 -> 426105 | CF23: 0 | CG23: =CA23*CF23 -> 0 | CH23: =CA23+CC23+CE23+CG23 -> 1278315 | CI23: 0.02 | CJ23: =CH23*CI23 -> 25566.3 | CK23: 0.01 | CL23: =CH23*CK23 -> 12783.15
A24: =Sheet1!A8 -> ENQ-10773-22-23 | B24: =Sheet1!B8 -> 45135 | C24: =Sheet1!C8 -> FA1300066 | D24: =Sheet1!D8 -> 1 CORE X 1000 SQ. MM. AL/ARM (XLPE) - 11 KV | E24: =CH24+CJ24+CL24 -> 1852703.7 | F24: =ROUNDUP(M40,0) -> 36267 | G24: =E24+F24 -> 1888970.7 | H24: =Sheet1!CP8 -> 0.18 | I24: =G24*H24 -> 340014.73 | J24: =G24+I24 -> 2228985.5 | K24: =Sheet1!CS8 -> 15 | L24: =Sheet1!CT8 -> KMS | M24: =J24*K24 -> 33434782 | N24: 2732 | O24: =+IFERROR(VLOOKUP($O$17,Sheet1!J8:L8,3,0),0) -> 0 | P24: =+IFERROR(VLOOKUP($P$17,Sheet1!J8:M8,3,0),0) -> 0 | Q24: =+IFERROR(VLOOKUP($Q$17,Sheet1!J8:M8,3,0),0) -> 0 | R24: =+IFERROR(VLOOKUP($R$17,Sheet1!J8:M8,3,0),0) -> 0 | S24: =+IFERROR(VLOOKUP($S$17,Sheet1!N8:Q8,3,0),0) -> 0 | T24: =+IFERROR(VLOOKUP($T$17,Sheet1!N8:Q8,3,0),0) -> 0 | U24: =+IFERROR(VLOOKUP($U$17,Sheet1!F8:I8,3,0),0) -> 0 | V24: =+IFERROR(VLOOKUP($V$17,Sheet1!F8:I8,3,0),0) -> 0 | W24: =+IFERROR(VLOOKUP($W$17,Sheet1!F8:I8,3,0),0) -> 0 | X24: =+IFERROR(VLOOKUP($X$17,Sheet1!F8:I8,3,0),0) -> 0 | Y24: 77 | Z24: =+IFERROR(VLOOKUP($Z$17,Sheet1!F8:I8,3,0),0) -> 0 | AA24: =+IFERROR(VLOOKUP($AA$17,Sheet1!F8:I8,3,0),0) -> 0 | AB24: =+IFERROR(VLOOKUP($AB$17,Sheet1!F8:I8,3,0),0) -> 0 | AC24: 230 | AD24: =+IFERROR(VLOOKUP($AD$17,Sheet1!R8:U8,2,0),0) -> 0 | AE24: 476 | AF24: =+IFERROR(VLOOKUP($AF$17,Sheet1!V8:Y8,3,0),0) -> 0 | AG24: =+IFERROR(VLOOKUP($AG$17,Sheet1!V8:Y8,3,0),0) -> 0 | AH24: =+IFERROR(VLOOKUP($AH$17,Sheet1!V8:Y8,3,0),0) -> 0 | AI24: =+IFERROR(VLOOKUP($AI$17,Sheet1!V8:Y8,3,0),0) -> 0 | AJ24: =+IFERROR(VLOOKUP($AJ$17,Sheet1!V8:Y8,3,0),0) -> 0 | AK24: 19 | AL24: =+IFERROR(VLOOKUP($AL$17,Sheet1!AD8:AG8,3,0),0) -> 0 | AM24: =+IFERROR(VLOOKUP($AM$17,Sheet1!AD8:AG8,3,0),0) -> 0 | AN24: =+IFERROR(VLOOKUP($AN$17,Sheet1!AD8:AG8,3,0),0) -> 0 | AO24: =+IFERROR(VLOOKUP($AO$17,Sheet1!AD8:AG8,3,0),0) -> 0 | AP24: =+IFERROR(VLOOKUP($AP$17,Sheet1!AD8:AG8,3,0),0) -> 0 | AQ24: 194 | AR24: =+IFERROR(VLOOKUP($AR$17,Sheet1!AD8:AG8,3,0),0) -> 0 | AS24: =+IFERROR(VLOOKUP($AS$17,Sheet1!AH8:AK8,3,0),0) -> 0 | AT24: =+IFERROR(VLOOKUP($AT$17,Sheet1!AH8:AK8,3,0),0) -> 0 | AU24: =+IFERROR(VLOOKUP($AU$17,Sheet1!AH8:AK8,3,0),0) -> 0 | AV24: 1008 | AW24: =+IFERROR(VLOOKUP($AW$17,Sheet1!AH8:AK8,3,0),0) -> 0 | AX24: =+IFERROR(VLOOKUP($AX$17,Sheet1!AH8:AK8,3,0),0) -> 0 | AY24: =+IFERROR(VLOOKUP($AY$17,Sheet1!AH8:AK8,3,0),0) -> 0 | AZ24: =+IFERROR(VLOOKUP($AZ$17,Sheet1!AH8:AK8,3,0),0) -> 0 | BA24: =+IFERROR(VLOOKUP($BA$17,Sheet1!AH8:AK8,3,0),0) -> 0 | BB24: =+IFERROR(VLOOKUP($BB$17,Sheet1!AH8:AK8,3,0),0) -> 0 | BC24: =+IFERROR(VLOOKUP($BC$17,Sheet1!AL8:AO8,3,0),0) -> 0 | BD24: =+IFERROR(VLOOKUP($BD$17,Sheet1!AL8:AO8,3,0),0) -> 0 | BE24: =+IFERROR(VLOOKUP($BE$17,Sheet1!AL8:AO8,3,0),0) -> 0 | BF24: 700 | BG24: =+IFERROR(VLOOKUP($BG$17,Sheet1!AL8:AO8,3,0),0) -> 0 | BH24: =+IFERROR(VLOOKUP($BH$17,Sheet1!AL8:AO8,3,0),0) -> 0 | BI24: =+IFERROR(VLOOKUP($BI$17,Sheet1!AL8:AO8,3,0),0) -> 0 | BJ24: =+IFERROR(VLOOKUP($BJ$17,Sheet1!AL8:AO8,3,0),0) -> 0 | BK24: =+IFERROR(VLOOKUP($BK$17,Sheet1!AL8:AO8,3,0),0) -> 0 | BL24: =+IFERROR(VLOOKUP($BL$17,Sheet1!AL8:AO8,3,0),0) -> 0 | BM24: =+IFERROR(VLOOKUP($BM$17,Sheet1!AP8:AS8,3,0),0) -> 0 | BN24: =+IFERROR(VLOOKUP($BN$17,Sheet1!AT8:AW8,3,0),0) -> 0 | BO24: 39 | BP24: 46 | BQ24: =+IFERROR(VLOOKUP($BQ$17,Sheet1!BF8:BI8,3,0),0) -> 0 | BR24: =+IFERROR(VLOOKUP($BR$17,Sheet1!BJ8:BM8,3,0),0) -> 0 | BS24: =+IFERROR(VLOOKUP($BS$17,Sheet1!BN8:BQ8,3,0),0) -> 0 | BT24: 42 | BU24: =+IFERROR(VLOOKUP($BU$17,Sheet1!BV8:BY8,3,0),0) -> 0 | BV24: =Sheet1!E8 -> STEEL | BW24: =Sheet1!CV8 -> SP0400107 | BX24: =Sheet1!CW8 -> CORRUGATED DISPATCH STEEL DRUM 2150 X 1080 X 1240 MM | BY24: =Sheet1!CX8 -> 500 | BZ24: =Sheet1!BZ8 -> 66500 | CA24: =SUMPRODUCT($N$18:$BU$18,N24:BU24)+BZ24 -> 1199161 | CB24: =Sheet1!CB8 -> 0 | CC24: =CA24*CB24 -> 0 | CD24: 0.5 | CE24: =CA24*CD24 -> 599580.5 | CF24: 0 | CG24: =CA24*CF24 -> 0 | CH24: =CA24+CC24+CE24+CG24 -> 1798741.5 | CI24: 0.02 | CJ24: =CH24*CI24 -> 35974.83 | CK24: 0.01 | CL24: =CH24*CK24 -> 17987.415
A25: =Sheet1!A5 -> ENQ-10773-22-23 | B25: =Sheet1!B5 -> 45135 | C25: =Sheet1!C5 -> FA1300016 | D25: =Sheet1!D5 -> 1 CORE X 630 SQ. MM. AL/ARM (XLPE) - 11 KV | E25: =CH25+CJ25+CL25 -> 1201875.6 | F25: =ROUNDUP(M41,0) -> 27200 | G25: =E25+F25 -> 1229075.6 | H25: =Sheet1!CP5 -> 0.18 | I25: =G25*H25 -> 221233.61 | J25: =G25+I25 -> 1450309.2 | K25: =Sheet1!CS5 -> 5 | L25: =Sheet1!CT5 -> KMS | M25: =J25*K25 -> 7251546 | N25: =+IFERROR(VLOOKUP($N$17,Sheet1!J5:L5,3,0),0) -> 1701 | O25: =+IFERROR(VLOOKUP($O$17,Sheet1!J5:L5,3,0),0) -> 0 | P25: =+IFERROR(VLOOKUP($P$17,Sheet1!J5:M5,3,0),0) -> 0 | Q25: =+IFERROR(VLOOKUP($Q$17,Sheet1!J5:M5,3,0),0) -> 0 | R25: =+IFERROR(VLOOKUP($R$17,Sheet1!J5:M5,3,0),0) -> 0 | S25: =+IFERROR(VLOOKUP($S$17,Sheet1!N5:Q5,3,0),0) -> 0 | T25: =+IFERROR(VLOOKUP($T$17,Sheet1!N5:Q5,3,0),0) -> 0 | U25: =+IFERROR(VLOOKUP($U$17,Sheet1!F5:I5,3,0),0) -> 0 | V25: =+IFERROR(VLOOKUP($V$17,Sheet1!F5:I5,3,0),0) -> 0 | W25: =+IFERROR(VLOOKUP($W$17,Sheet1!F5:I5,3,0),0) -> 0 | X25: =+IFERROR(VLOOKUP($X$17,Sheet1!F5:I5,3,0),0) -> 0 | Y25: 63 | Z25: =+IFERROR(VLOOKUP($Z$17,Sheet1!F5:I5,3,0),0) -> 0 | AA25: =+IFERROR(VLOOKUP($AA$17,Sheet1!F5:I5,3,0),0) -> 0 | AB25: =+IFERROR(VLOOKUP($AB$17,Sheet1!F5:I5,3,0),0) -> 0 | AC25: 170 | AD25: =+IFERROR(VLOOKUP($AD$17,Sheet1!R5:U5,2,0),0) -> 0 | AE25: 380 | AF25: =+IFERROR(VLOOKUP($AF$17,Sheet1!V5:Y5,3,0),0) -> 0 | AG25: =+IFERROR(VLOOKUP($AG$17,Sheet1!V5:Y5,3,0),0) -> 0 | AH25: =+IFERROR(VLOOKUP($AH$17,Sheet1!V5:Y5,3,0),0) -> 0 | AI25: =+IFERROR(VLOOKUP($AI$17,Sheet1!V5:Y5,3,0),0) -> 0 | AJ25: =+IFERROR(VLOOKUP($AJ$17,Sheet1!V5:Y5,3,0),0) -> 0 | AK25: 15 | AL25: =+IFERROR(VLOOKUP($AL$17,Sheet1!AD5:AG5,3,0),0) -> 0 | AM25: =+IFERROR(VLOOKUP($AM$17,Sheet1!AD5:AG5,3,0),0) -> 0 | AN25: =+IFERROR(VLOOKUP($AN$17,Sheet1!AD5:AG5,3,0),0) -> 0 | AO25: =+IFERROR(VLOOKUP($AO$17,Sheet1!AD5:AG5,3,0),0) -> 0 | AP25: =+IFERROR(VLOOKUP($AP$17,Sheet1!AD5:AG5,3,0),0) -> 0 | AQ25: 140 | AR25: =+IFERROR(VLOOKUP($AR$17,Sheet1!AD5:AG5,3,0),0) -> 0 | AS25: =+IFERROR(VLOOKUP($AS$17,Sheet1!AH5:AK5,3,0),0) -> 0 | AT25: =+IFERROR(VLOOKUP($AT$17,Sheet1!AH5:AK5,3,0),0) -> 0 | AU25: =+IFERROR(VLOOKUP($AU$17,Sheet1!AH5:AK5,3,0),0) -> 0 | AV25: 530 | AW25: =+IFERROR(VLOOKUP($AW$17,Sheet1!AH5:AK5,3,0),0) -> 0 | AX25: =+IFERROR(VLOOKUP($AX$17,Sheet1!AH5:AK5,3,0),0) -> 0 | AY25: =+IFERROR(VLOOKUP($AY$17,Sheet1!AH5:AK5,3,0),0) -> 0 | AZ25: =+IFERROR(VLOOKUP($AZ$17,Sheet1!AH5:AK5,3,0),0) -> 0 | BA25: =+IFERROR(VLOOKUP($BA$17,Sheet1!AH5:AK5,3,0),0) -> 0 | BB25: =+IFERROR(VLOOKUP($BB$17,Sheet1!AH5:AK5,3,0),0) -> 0 | BC25: =+IFERROR(VLOOKUP($BC$17,Sheet1!AL5:AO5,3,0),0) -> 0 | BD25: =+IFERROR(VLOOKUP($BD$17,Sheet1!AL5:AO5,3,0),0) -> 0 | BE25: =+IFERROR(VLOOKUP($BE$17,Sheet1!AL5:AO5,3,0),0) -> 0 | BF25: 492 | BG25: =+IFERROR(VLOOKUP($BG$17,Sheet1!AL5:AO5,3,0),0) -> 0 | BH25: =+IFERROR(VLOOKUP($BH$17,Sheet1!AL5:AO5,3,0),0) -> 0 | BI25: =+IFERROR(VLOOKUP($BI$17,Sheet1!AL5:AO5,3,0),0) -> 0 | BJ25: =+IFERROR(VLOOKUP($BJ$17,Sheet1!AL5:AO5,3,0),0) -> 0 | BK25: =+IFERROR(VLOOKUP($BK$17,Sheet1!AL5:AO5,3,0),0) -> 0 | BL25: =+IFERROR(VLOOKUP($BL$17,Sheet1!AL5:AO5,3,0),0) -> 0 | BM25: =+IFERROR(VLOOKUP($BM$17,Sheet1!AP5:AS5,3,0),0) -> 0 | BN25: =+IFERROR(VLOOKUP($BN$17,Sheet1!AT5:AW5,3,0),0) -> 0 | BO25: 26 | BP25: 36 | BQ25: =+IFERROR(VLOOKUP($BQ$17,Sheet1!BF5:BI5,3,0),0) -> 0 | BR25: =+IFERROR(VLOOKUP($BR$17,Sheet1!BJ5:BM5,3,0),0) -> 0 | BS25: =+IFERROR(VLOOKUP($BS$17,Sheet1!BN5:BQ5,3,0),0) -> 0 | BT25: 33 | BU25: =+IFERROR(VLOOKUP($BU$17,Sheet1!BV5:BY5,3,0),0) -> 0 | BV25: =Sheet1!E5 -> STEEL | BW25: =Sheet1!CV5 -> SP0400091 | BX25: =Sheet1!CW5 -> CORRUGATED DISPATCH STEEL DRUM 1800 X 900 X 1000 | BY25: =Sheet1!CX5 -> 500 | BZ25: =Sheet1!BZ5 -> 48450 | CA25: =SUMPRODUCT($N$18:$BU$18,N25:BU25)+BZ25 -> 777913 | CB25: =Sheet1!CB5 -> 0 | CC25: =CA25*CB25 -> 0 | CD25: 0.5 | CE25: =CA25*CD25 -> 388956.5 | CF25: 0 | CG25: =CA25*CF25 -> 0 | CH25: =CA25+CC25+CE25+CG25 -> 1166869.5 | CI25: 0.02 | CJ25: =CH25*CI25 -> 23337.39 | CK25: 0.01 | CL25: =CH25*CK25 -> 11668.695
A26: =Sheet1!A11 -> ENQ-10773-22-23 | B26: =Sheet1!B11 -> 45135 | C26: =Sheet1!C11 -> FA1300047 | D26: =Sheet1!D11 -> 1 CORE X 400 SQ. MM. AL/ARM (XLPE) - 11 KV | E26: =CH26+CJ26+CL26 -> 911866.72 | F26: =ROUNDUP(M42,0) -> 23800 | G26: =E26+F26 -> 935666.72 | H26: =Sheet1!CP11 -> 0.18 | I26: =G26*H26 -> 168420.01 | J26: =G26+I26 -> 1104086.7 | K26: =Sheet1!CS11 -> 40 | L26: =Sheet1!CT11 -> KMS | M26: =J26*K26 -> 44163469 | N26: =+IFERROR(VLOOKUP($N$17,Sheet1!J11:L11,3,0),0) -> 1080 | O26: =+IFERROR(VLOOKUP($O$17,Sheet1!J11:L11,3,0),0) -> 0 | P26: =+IFERROR(VLOOKUP($P$17,Sheet1!J11:M11,3,0),0) -> 0 | Q26: =+IFERROR(VLOOKUP($Q$17,Sheet1!J11:M11,3,0),0) -> 0 | R26: =+IFERROR(VLOOKUP($R$17,Sheet1!J11:M11,3,0),0) -> 0 | S26: =+IFERROR(VLOOKUP($S$17,Sheet1!N11:Q11,3,0),0) -> 0 | T26: =+IFERROR(VLOOKUP($T$17,Sheet1!N11:Q11,3,0),0) -> 0 | U26: =+IFERROR(VLOOKUP($U$17,Sheet1!F11:I11,3,0),0) -> 0 | V26: =+IFERROR(VLOOKUP($V$17,Sheet1!F11:I11,3,0),0) -> 0 | W26: =+IFERROR(VLOOKUP($W$17,Sheet1!F11:I11,3,0),0) -> 0 | X26: =+IFERROR(VLOOKUP($X$17,Sheet1!F11:I11,3,0),0) -> 0 | Y26: 53 | Z26: =+IFERROR(VLOOKUP($Z$17,Sheet1!F11:I11,3,0),0) -> 0 | AA26: =+IFERROR(VLOOKUP($AA$17,Sheet1!F11:I11,3,0),0) -> 0 | AB26: =+IFERROR(VLOOKUP($AB$17,Sheet1!F11:I11,3,0),0) -> 0 | AC26: 138 | AD26: =+IFERROR(VLOOKUP($AD$17,Sheet1!R11:U11,2,0),0) -> 0 | AE26: 310 | AF26: =+IFERROR(VLOOKUP($AF$17,Sheet1!V11:Y11,3,0),0) -> 0 | AG26: =+IFERROR(VLOOKUP($AG$17,Sheet1!V11:Y11,3,0),0) -> 0 | AH26: =+IFERROR(VLOOKUP($AH$17,Sheet1!V11:Y11,3,0),0) -> 0 | AI26: =+IFERROR(VLOOKUP($AI$17,Sheet1!V11:Y11,3,0),0) -> 0 | AJ26: =+IFERROR(VLOOKUP($AJ$17,Sheet1!V11:Y11,3,0),0) -> 0 | AK26: 13 | AL26: =+IFERROR(VLOOKUP($AL$17,Sheet1!AD11:AG11,3,0),0) -> 0 | AM26: =+IFERROR(VLOOKUP($AM$17,Sheet1!AD11:AG11,3,0),0) -> 0 | AN26: =+IFERROR(VLOOKUP($AN$17,Sheet1!AD11:AG11,3,0),0) -> 0 | AO26: =+IFERROR(VLOOKUP($AO$17,Sheet1!AD11:AG11,3,0),0) -> 0 | AP26: =+IFERROR(VLOOKUP($AP$17,Sheet1!AD11:AG11,3,0),0) -> 0 | AQ26: 102 | AR26: =+IFERROR(VLOOKUP($AR$17,Sheet1!AD11:AG11,3,0),0) -> 0 | AS26: =+IFERROR(VLOOKUP($AS$17,Sheet1!AH11:AK11,3,0),0) -> 0 | AT26: =+IFERROR(VLOOKUP($AT$17,Sheet1!AH11:AK11,3,0),0) -> 0 | AU26: =+IFERROR(VLOOKUP($AU$17,Sheet1!AH11:AK11,3,0),0) -> 0 | AV26: 552 | AW26: =+IFERROR(VLOOKUP($AW$17,Sheet1!AH11:AK11,3,0),0) -> 0 | AX26: =+IFERROR(VLOOKUP($AX$17,Sheet1!AH11:AK11,3,0),0) -> 0 | AY26: =+IFERROR(VLOOKUP($AY$17,Sheet1!AH11:AK11,3,0),0) -> 0 | AZ26: =+IFERROR(VLOOKUP($AZ$17,Sheet1!AH11:AK11,3,0),0) -> 0 | BA26: =+IFERROR(VLOOKUP($BA$17,Sheet1!AH11:AK11,3,0),0) -> 0 | BB26: =+IFERROR(VLOOKUP($BB$17,Sheet1!AH11:AK11,3,0),0) -> 0 | BC26: =+IFERROR(VLOOKUP($BC$17,Sheet1!AL11:AO11,3,0),0) -> 0 | BD26: =+IFERROR(VLOOKUP($BD$17,Sheet1!AL11:AO11,3,0),0) -> 0 | BE26: =+IFERROR(VLOOKUP($BE$17,Sheet1!AL11:AO11,3,0),0) -> 0 | BF26: 403 | BG26: =+IFERROR(VLOOKUP($BG$17,Sheet1!AL11:AO11,3,0),0) -> 0 | BH26: =+IFERROR(VLOOKUP($BH$17,Sheet1!AL11:AO11,3,0),0) -> 0 | BI26: =+IFERROR(VLOOKUP($BI$17,Sheet1!AL11:AO11,3,0),0) -> 0 | BJ26: =+IFERROR(VLOOKUP($BJ$17,Sheet1!AL11:AO11,3,0),0) -> 0 | BK26: =+IFERROR(VLOOKUP($BK$17,Sheet1!AL11:AO11,3,0),0) -> 0 | BL26: =+IFERROR(VLOOKUP($BL$17,Sheet1!AL11:AO11,3,0),0) -> 0 | BM26: =+IFERROR(VLOOKUP($BM$17,Sheet1!AP11:AS11,3,0),0) -> 0 | BN26: =+IFERROR(VLOOKUP($BN$17,Sheet1!AT11:AW11,3,0),0) -> 0 | BO26: 19 | BP26: 29 | BQ26: =+IFERROR(VLOOKUP($BQ$17,Sheet1!BF11:BI11,3,0),0) -> 0 | BR26: =+IFERROR(VLOOKUP($BR$17,Sheet1!BJ11:BM11,3,0),0) -> 0 | BS26: =+IFERROR(VLOOKUP($BS$17,Sheet1!BN11:BQ11,3,0),0) -> 0 | BT26: 30 | BU26: =+IFERROR(VLOOKUP($BU$17,Sheet1!BV11:BY11,3,0),0) -> 0 | BV26: =Sheet1!E11 -> STEEL | BW26: =Sheet1!CV11 -> SP0400125 | BX26: =Sheet1!CW11 -> CORRUGATED DISPATCH STEEL DRUM 1600 X 700 X 915 MM | BY26: =Sheet1!CX11 -> 500 | BZ26: =Sheet1!BZ11 -> 34200 | CA26: =SUMPRODUCT($N$18:$BU$18,N26:BU26)+BZ26 -> 590205 | CB26: =Sheet1!CB11 -> 0 | CC26: =CA26*CB26 -> 0 | CD26: 0.5 | CE26: =CA26*CD26 -> 295102.5 | CF26: 0 | CG26: =CA26*CF26 -> 0 | CH26: =CA26+CC26+CE26+CG26 -> 885307.5 | CI26: 0.02 | CJ26: =CH26*CI26 -> 17706.15 | CK26: 0.01 | CL26: =CH26*CK26 -> 8853.075
A27: =Sheet1!A14 -> ENQ-10773-22-23 | B27: =Sheet1!B14 -> 45135 | C27: =Sheet1!C14 -> FA1300080 | D27: =Sheet1!D14 -> 3 CORE X 400 SQ. MM AL/ARM - WIRE (XLPE) - 33 KV | E27: =CH27+CJ27+CL27 -> 4221435.9 | F27: =ROUNDUP(M43,0) -> 136000 | G27: =E27+F27 -> 4357435.9 | H27: =Sheet1!CP14 -> 0.18 | I27: =G27*H27 -> 784338.47 | J27: =G27+I27 -> 5141774.4 | K27: =36+60+7.5 -> 103.5 | L27: =Sheet1!CT14 -> KMS | M27: =J27*K27 -> 5.3217365e+08 | N27: 3243 | O27: =+IFERROR(VLOOKUP($O$17,Sheet1!J14:L14,3,0),0) -> 0 | P27: =+IFERROR(VLOOKUP($P$17,Sheet1!J14:M14,3,0),0) -> 0 | Q27: =+IFERROR(VLOOKUP($Q$17,Sheet1!J14:M14,3,0),0) -> 0 | R27: =+IFERROR(VLOOKUP($R$17,Sheet1!J14:M14,3,0),0) -> 0 | S27: =+IFERROR(VLOOKUP($S$17,Sheet1!N14:Q14,3,0),0) -> 0 | T27: =+IFERROR(VLOOKUP($T$17,Sheet1!N14:Q14,3,0),0) -> 0 | U27: =+IFERROR(VLOOKUP($U$17,Sheet1!F14:I14,3,0),0) -> 0 | V27: =+IFERROR(VLOOKUP($V$17,Sheet1!F14:I14,3,0),0) -> 0 | W27: =+IFERROR(VLOOKUP($W$17,Sheet1!F14:I14,3,0),0) -> 0 | X27: =+IFERROR(VLOOKUP($X$17,Sheet1!F14:I14,3,0),0) -> 0 | Y27: 212 | Z27: =+IFERROR(VLOOKUP($Z$17,Sheet1!F14:I14,3,0),0) -> 0 | AA27: =+IFERROR(VLOOKUP($AA$17,Sheet1!F14:I14,3,0),0) -> 0 | AB27: =+IFERROR(VLOOKUP($AB$17,Sheet1!F14:I14,3,0),0) -> 0 | AC27: 515 | AD27: =+IFERROR(VLOOKUP($AD$17,Sheet1!R14:U14,2,0),0) -> 0 | AE27: 2670 | AF27: =+IFERROR(VLOOKUP($AF$17,Sheet1!V14:Y14,3,0),0) -> 0 | AG27: =+IFERROR(VLOOKUP($AG$17,Sheet1!V14:Y14,3,0),0) -> 0 | AH27: =+IFERROR(VLOOKUP($AH$17,Sheet1!V14:Y14,3,0),0) -> 0 | AI27: =+IFERROR(VLOOKUP($AI$17,Sheet1!V14:Y14,3,0),0) -> 0 | AJ27: =+IFERROR(VLOOKUP($AJ$17,Sheet1!V14:Y14,3,0),0) -> 0 | AK27: =+IFERROR(VLOOKUP($AK$17,Sheet1!Z14:AB14,3,0),0) -> 0 | AL27: =+IFERROR(VLOOKUP($AL$17,Sheet1!AD14:AG14,3,0),0) -> 0 | AM27: =+IFERROR(VLOOKUP($AM$17,Sheet1!AD14:AG14,3,0),0) -> 0 | AN27: =+IFERROR(VLOOKUP($AN$17,Sheet1!AD14:AG14,3,0),0) -> 0 | AO27: =+IFERROR(VLOOKUP($AO$17,Sheet1!AD14:AG14,3,0),0) -> 0 | AP27: =+IFERROR(VLOOKUP($AP$17,Sheet1!AD14:AG14,3,0),0) -> 0 | AQ27: =+IFERROR(VLOOKUP($AQ$17,Sheet1!AD14:AG14,3,0),0) -> 0 | AR27: 1561 | AS27: =+IFERROR(VLOOKUP($AS$17,Sheet1!AH14:AK14,3,0),0) -> 0 | AT27: =+IFERROR(VLOOKUP($AT$17,Sheet1!AH14:AK14,3,0),0) -> 0 | AU27: =+IFERROR(VLOOKUP($AU$17,Sheet1!AH14:AK14,3,0),0) -> 0 | AV27: =+IFERROR(VLOOKUP($AV$17,Sheet1!AH14:AK14,3,0),0) -> 0 | AW27: =+IFERROR(VLOOKUP($AW$17,Sheet1!AH14:AK14,3,0),0) -> 0 | AX27: =+IFERROR(VLOOKUP($AX$17,Sheet1!AH14:AK14,3,0),0) -> 0 | AY27: =+IFERROR(VLOOKUP($AY$17,Sheet1!AH14:AK14,3,0),0) -> 0 | AZ27: =+IFERROR(VLOOKUP($AZ$17,Sheet1!AH14:AK14,3,0),0) -> 0 | BA27: 7182 | BB27: =+IFERROR(VLOOKUP($BB$17,Sheet1!AH14:AK14,3,0),0) -> 0 | BC27: =+IFERROR(VLOOKUP($BC$17,Sheet1!AL14:AO14,3,0),0) -> 0 | BD27: =+IFERROR(VLOOKUP($BD$17,Sheet1!AL14:AO14,3,0),0) -> 0 | BE27: =+IFERROR(VLOOKUP($BE$17,Sheet1!AL14:AO14,3,0),0) -> 0 | BF27: 1715 | BG27: 1718 | BH27: =+IFERROR(VLOOKUP($BH$17,Sheet1!AL14:AO14,3,0),0) -> 0 | BI27: =+IFERROR(VLOOKUP($BI$17,Sheet1!AL14:AO14,3,0),0) -> 0 | BJ27: =+IFERROR(VLOOKUP($BJ$17,Sheet1!AL14:AO14,3,0),0) -> 0 | BK27: =+IFERROR(VLOOKUP($BK$17,Sheet1!AL14:AO14,3,0),0) -> 0 | BL27: =+IFERROR(VLOOKUP($BL$17,Sheet1!AL14:AO14,3,0),0) -> 0 | BM27: =+IFERROR(VLOOKUP($BM$17,Sheet1!AP14:AS14,3,0),0) -> 0 | BN27: =+IFERROR(VLOOKUP($BN$17,Sheet1!AT14:AW14,3,0),0) -> 0 | BO27: 58 | BP27: 104 | BQ27: =+IFERROR(VLOOKUP($BQ$17,Sheet1!BF14:BI14,3,0),0) -> 0 | BR27: =+IFERROR(VLOOKUP($BR$17,Sheet1!BJ14:BM14,3,0),0) -> 0 | BS27: =+IFERROR(VLOOKUP($BS$17,Sheet1!BN14:BQ14,3,0),0) -> 0 | BT27: 75 | BU27: =+IFERROR(VLOOKUP($BU$17,Sheet1!BV14:BY14,3,0),0) -> 0 | BV27: =Sheet1!E14 -> STEEL | BW27: =Sheet1!CV14 -> SP0400137 | BX27: =Sheet1!CW14 -> CORRUGATED DISPATCH STEEL DRUM 2600 X 1600 X 1600 MM | BY27: =Sheet1!CX14 -> 250 | BZ27: =Sheet1!BZ14 -> 190000 | CA27: =SUMPRODUCT($N$18:$BU$18,N27:BU27)+BZ27 -> 2732321 | CB27: =Sheet1!CB14 -> 0 | CC27: =CA27*CB27 -> 0 | CD27: 0.5 | CE27: =CA27*CD27 -> 1366160.5 | CF27: 0 | CG27: =CA27*CF27 -> 0 | CH27: =CA27+CC27+CE27+CG27 -> 4098481.5 | CI27: 0.02 | CJ27: =CH27*CI27 -> 81969.63 | CK27: 0.01 | CL27: =CH27*CK27 -> 40984.815
A28: =Sheet1!A9 -> ENQ-10773-22-23 | B28: =Sheet1!B9 -> 45135 | C28: =Sheet1!C9 -> FA1300081 | D28: =Sheet1!D9 -> 3 CORE X 300 SQ. MM. AL/ARM - WIRE (XLPE) - 33 KV | E28: =CH28+CJ28+CL28 -> 3709171.1 | F28: =ROUNDUP(M44,0) -> 137403 | G28: =E28+F28 -> 3846574.1 | H28: =Sheet1!CP9 -> 0.18 | I28: =G28*H28 -> 692383.34 | J28: =G28+I28 -> 4538957.4 | K28: =10+13+1.25 -> 24.25 | L28: =Sheet1!CT9 -> KMS | M28: =J28*K28 -> 1.1006972e+08 | N28: =+IFERROR(VLOOKUP($N$17,Sheet1!J9:L9,3,0),0) -> 2430 | O28: =+IFERROR(VLOOKUP($O$17,Sheet1!J9:L9,3,0),0) -> 0 | P28: =+IFERROR(VLOOKUP($P$17,Sheet1!J9:M9,3,0),0) -> 0 | Q28: =+IFERROR(VLOOKUP($Q$17,Sheet1!J9:M9,3,0),0) -> 0 | R28: =+IFERROR(VLOOKUP($R$17,Sheet1!J9:M9,3,0),0) -> 0 | S28: =+IFERROR(VLOOKUP($S$17,Sheet1!N9:Q9,3,0),0) -> 0 | T28: =+IFERROR(VLOOKUP($T$17,Sheet1!N9:Q9,3,0),0) -> 0 | U28: =+IFERROR(VLOOKUP($U$17,Sheet1!F9:I9,3,0),0) -> 0 | V28: =+IFERROR(VLOOKUP($V$17,Sheet1!F9:I9,3,0),0) -> 0 | W28: =+IFERROR(VLOOKUP($W$17,Sheet1!F9:I9,3,0),0) -> 0 | X28: =+IFERROR(VLOOKUP($X$17,Sheet1!F9:I9,3,0),0) -> 0 | Y28: 193 | Z28: =+IFERROR(VLOOKUP($Z$17,Sheet1!F9:I9,3,0),0) -> 0 | AA28: =+IFERROR(VLOOKUP($AA$17,Sheet1!F9:I9,3,0),0) -> 0 | AB28: =+IFERROR(VLOOKUP($AB$17,Sheet1!F9:I9,3,0),0) -> 0 | AC28: 495 | AD28: =+IFERROR(VLOOKUP($AD$17,Sheet1!R9:U9,2,0),0) -> 0 | AE28: 2434 | AF28: =+IFERROR(VLOOKUP($AF$17,Sheet1!V9:Y9,3,0),0) -> 0 | AG28: =+IFERROR(VLOOKUP($AG$17,Sheet1!V9:Y9,3,0),0) -> 0 | AH28: =+IFERROR(VLOOKUP($AH$17,Sheet1!V9:Y9,3,0),0) -> 0 | AI28: =+IFERROR(VLOOKUP($AI$17,Sheet1!V9:Y9,3,0),0) -> 0 | AJ28: =+IFERROR(VLOOKUP($AJ$17,Sheet1!V9:Y9,3,0),0) -> 0 | AK28: =+IFERROR(VLOOKUP($AK$17,Sheet1!Z9:AB9,3,0),0) -> 0 | AL28: =+IFERROR(VLOOKUP($AL$17,Sheet1!AD9:AG9,3,0),0) -> 0 | AM28: =+IFERROR(VLOOKUP($AM$17,Sheet1!AD9:AG9,3,0),0) -> 0 | AN28: =+IFERROR(VLOOKUP($AN$17,Sheet1!AD9:AG9,3,0),0) -> 0 | AO28: =+IFERROR(VLOOKUP($AO$17,Sheet1!AD9:AG9,3,0),0) -> 0 | AP28: =+IFERROR(VLOOKUP($AP$17,Sheet1!AD9:AG9,3,0),0) -> 0 | AQ28: =+IFERROR(VLOOKUP($AQ$17,Sheet1!AD9:AG9,3,0),0) -> 0 | AR28: 1382 | AS28: =+IFERROR(VLOOKUP($AS$17,Sheet1!AH9:AK9,3,0),0) -> 0 | AT28: =+IFERROR(VLOOKUP($AT$17,Sheet1!AH9:AK9,3,0),0) -> 0 | AU28: =+IFERROR(VLOOKUP($AU$17,Sheet1!AH9:AK9,3,0),0) -> 0 | AV28: =+IFERROR(VLOOKUP($AV$17,Sheet1!AH9:AK9,3,0),0) -> 0 | AW28: =+IFERROR(VLOOKUP($AW$17,Sheet1!AH9:AK9,3,0),0) -> 0 | AX28: =+IFERROR(VLOOKUP($AX$17,Sheet1!AH9:AK9,3,0),0) -> 0 | AY28: =+IFERROR(VLOOKUP($AY$17,Sheet1!AH9:AK9,3,0),0) -> 0 | AZ28: =+IFERROR(VLOOKUP($AZ$17,Sheet1!AH9:AK9,3,0),0) -> 0 | BA28: 6668 | BB28: =+IFERROR(VLOOKUP($BB$17,Sheet1!AH9:AK9,3,0),0) -> 0 | BC28: =+IFERROR(VLOOKUP($BC$17,Sheet1!AL9:AO9,3,0),0) -> 0 | BD28: =+IFERROR(VLOOKUP($BD$17,Sheet1!AL9:AO9,3,0),0) -> 0 | BE28: =+IFERROR(VLOOKUP($BE$17,Sheet1!AL9:AO9,3,0),0) -> 0 | BF28: 1613 | BG28: 1497 | BH28: =+IFERROR(VLOOKUP($BH$17,Sheet1!AL9:AO9,3,0),0) -> 0 | BI28: =+IFERROR(VLOOKUP($BI$17,Sheet1!AL9:AO9,3,0),0) -> 0 | BJ28: =+IFERROR(VLOOKUP($BJ$17,Sheet1!AL9:AO9,3,0),0) -> 0 | BK28: =+IFERROR(VLOOKUP($BK$17,Sheet1!AL9:AO9,3,0),0) -> 0 | BL28: =+IFERROR(VLOOKUP($BL$17,Sheet1!AL9:AO9,3,0),0) -> 0 | BM28: =+IFERROR(VLOOKUP($BM$17,Sheet1!AP9:AS9,3,0),0) -> 0 | BN28: =+IFERROR(VLOOKUP($BN$17,Sheet1!AT9:AW9,3,0),0) -> 0 | BO28: 38 | BP28: 93 | BQ28: =+IFERROR(VLOOKUP($BQ$17,Sheet1!BF9:BI9,3,0),0) -> 0 | BR28: =+IFERROR(VLOOKUP($BR$17,Sheet1!BJ9:BM9,3,0),0) -> 0 | BS28: =+IFERROR(VLOOKUP($BS$17,Sheet1!BN9:BQ9,3,0),0) -> 0 | BT28: 71 | BU28: =+IFERROR(VLOOKUP($BU$17,Sheet1!BV9:BY9,3,0),0) -> 0 | BV28: =Sheet1!E9 -> STEEL | BW28: =Sheet1!CV9 -> SP0400137 | BX28: =Sheet1!CW9 -> CORRUGATED DISPATCH STEEL DRUM 2600 X 1600 X 1600 | BY28: =Sheet1!CX9 -> 250 | BZ28: =Sheet1!BZ9 -> 190000 | CA28: =SUMPRODUCT($N$18:$BU$18,N28:BU28)+BZ28 -> 2400758 | CB28: =Sheet1!CB9 -> 0 | CC28: =CA28*CB28 -> 0 | CD28: 0.5 | CE28: =CA28*CD28 -> 1200379 | CF28: 0 | CG28: =CA28*CF28 -> 0 | CH28: =CA28+CC28+CE28+CG28 -> 3601137 | CI28: 0.02 | CJ28: =CH28*CI28 -> 72022.74 | CK28: 0.01 | CL28: =CH28*CK28 -> 36011.37
A29: =Sheet1!A2 -> ENQ-10773-22-23 | B29: =Sheet1!B2 -> 45135 | C29: =Sheet1!C2 -> FA1300200 | D29: =Sheet1!D2 -> 3 CORE X 95 SQ. MM. AL/ARM WIRE (XLPE) - 33 KV | E29: =CH29+CJ29+CL29 -> 2262621.6 | F29: =ROUNDUP(M45,0) -> 136000 | G29: =E29+F29 -> 2398621.6 | H29: =Sheet1!CP2 -> 0.18 | I29: =G29*H29 -> 431751.89 | J29: =G29+I29 -> 2830373.5 | K29: =Sheet1!CS2 -> 0.5 | L29: =Sheet1!CT2 -> KMS | M29: =J29*K29 -> 1415186.7 | N29: =+IFERROR(VLOOKUP($N$17,Sheet1!J2:L2,3,0),0) -> 769.5 | O29: =+IFERROR(VLOOKUP($O$17,Sheet1!J2:L2,3,0),0) -> 0 | P29: =+IFERROR(VLOOKUP($P$17,Sheet1!J2:M2,3,0),0) -> 0 | Q29: =+IFERROR(VLOOKUP($Q$17,Sheet1!J2:M2,3,0),0) -> 0 | R29: =+IFERROR(VLOOKUP($R$17,Sheet1!J2:M2,3,0),0) -> 0 | S29: =+IFERROR(VLOOKUP($S$17,Sheet1!N2:Q2,3,0),0) -> 0 | T29: =+IFERROR(VLOOKUP($T$17,Sheet1!N2:Q2,3,0),0) -> 0 | U29: =+IFERROR(VLOOKUP($U$17,Sheet1!F2:I2,3,0),0) -> 0 | V29: =+IFERROR(VLOOKUP($V$17,Sheet1!F2:I2,3,0),0) -> 0 | W29: =+IFERROR(VLOOKUP($W$17,Sheet1!F2:I2,3,0),0) -> 0 | X29: =+IFERROR(VLOOKUP($X$17,Sheet1!F2:I2,3,0),0) -> 0 | Y29: 151 | Z29: =+IFERROR(VLOOKUP($Z$17,Sheet1!F2:I2,3,0),0) -> 0 | AA29: =+IFERROR(VLOOKUP($AA$17,Sheet1!F2:I2,3,0),0) -> 0 | AB29: =+IFERROR(VLOOKUP($AB$17,Sheet1!F2:I2,3,0),0) -> 0 | AC29: 345 | AD29: =+IFERROR(VLOOKUP($AD$17,Sheet1!R2:U2,2,0),0) -> 0 | AE29: 1725 | AF29: =+IFERROR(VLOOKUP($AF$17,Sheet1!V2:Y2,3,0),0) -> 0 | AG29: =+IFERROR(VLOOKUP($AG$17,Sheet1!V2:Y2,3,0),0) -> 0 | AH29: =+IFERROR(VLOOKUP($AH$17,Sheet1!V2:Y2,3,0),0) -> 0 | AI29: =+IFERROR(VLOOKUP($AI$17,Sheet1!V2:Y2,3,0),0) -> 0 | AJ29: =+IFERROR(VLOOKUP($AJ$17,Sheet1!V2:Y2,3,0),0) -> 0 | AK29: =+IFERROR(VLOOKUP($AK$17,Sheet1!Z2:AB2,3,0),0) -> 0 | AL29: =+IFERROR(VLOOKUP($AL$17,Sheet1!AD2:AG2,3,0),0) -> 0 | AM29: =+IFERROR(VLOOKUP($AM$17,Sheet1!AD2:AG2,3,0),0) -> 0 | AN29: =+IFERROR(VLOOKUP($AN$17,Sheet1!AD2:AG2,3,0),0) -> 0 | AO29: =+IFERROR(VLOOKUP($AO$17,Sheet1!AD2:AG2,3,0),0) -> 0 | AP29: =+IFERROR(VLOOKUP($AP$17,Sheet1!AD2:AG2,3,0),0) -> 0 | AQ29: =+IFERROR(VLOOKUP($AQ$17,Sheet1!AD2:AG2,3,0),0) -> 0 | AR29: 914 | AS29: =+IFERROR(VLOOKUP($AS$17,Sheet1!AH2:AK2,3,0),0) -> 0 | AT29: =+IFERROR(VLOOKUP($AT$17,Sheet1!AH2:AK2,3,0),0) -> 0 | AU29: =+IFERROR(VLOOKUP($AU$17,Sheet1!AH2:AK2,3,0),0) -> 0 | AV29: =+IFERROR(VLOOKUP($AV$17,Sheet1!AH2:AK2,3,0),0) -> 0 | AW29: =+IFERROR(VLOOKUP($AW$17,Sheet1!AH2:AK2,3,0),0) -> 0 | AX29: =+IFERROR(VLOOKUP($AX$17,Sheet1!AH2:AK2,3,0),0) -> 0 | AY29: =+IFERROR(VLOOKUP($AY$17,Sheet1!AH2:AK2,3,0),0) -> 0 | AZ29: =+IFERROR(VLOOKUP($AZ$17,Sheet1!AH2:AK2,3,0),0) -> 0 | BA29: 4135 | BB29: =+IFERROR(VLOOKUP($BB$17,Sheet1!AH2:AK2,3,0),0) -> 0 | BC29: =+IFERROR(VLOOKUP($BC$17,Sheet1!AL2:AO2,3,0),0) -> 0 | BD29: =+IFERROR(VLOOKUP($BD$17,Sheet1!AL2:AO2,3,0),0) -> 0 | BE29: =+IFERROR(VLOOKUP($BE$17,Sheet1!AL2:AO2,3,0),0) -> 0 | BF29: 1282 | BG29: 917 | BH29: =+IFERROR(VLOOKUP($BH$17,Sheet1!AL2:AO2,3,0),0) -> 0 | BI29: =+IFERROR(VLOOKUP($BI$17,Sheet1!AL2:AO2,3,0),0) -> 0 | BJ29: =+IFERROR(VLOOKUP($BJ$17,Sheet1!AL2:AO2,3,0),0) -> 0 | BK29: =+IFERROR(VLOOKUP($BK$17,Sheet1!AL2:AO2,3,0),0) -> 0 | BL29: =+IFERROR(VLOOKUP($BL$17,Sheet1!AL2:AO2,3,0),0) -> 0 | BM29: =+IFERROR(VLOOKUP($BM$17,Sheet1!AP2:AS2,3,0),0) -> 0 | BN29: =+IFERROR(VLOOKUP($BN$17,Sheet1!AT2:AW2,3,0),0) -> 0 | BO29: 15 | BP29: 66 | BQ29: =+IFERROR(VLOOKUP($BQ$17,Sheet1!BF2:BI2,3,0),0) -> 0 | BR29: =+IFERROR(VLOOKUP($BR$17,Sheet1!BJ2:BM2,3,0),0) -> 0 | BS29: =+IFERROR(VLOOKUP($BS$17,Sheet1!BN2:BQ2,3,0),0) -> 0 | BT29: 56 | BU29: =+IFERROR(VLOOKUP($BU$17,Sheet1!BV2:BY2,3,0),0) -> 0 | BV29: =Sheet1!E2 -> STEEL | BW29: =Sheet1!CV2 -> SP0400136 | BX29: =Sheet1!CW2 -> CORRUGATED DISPATCH STEEL DRUM 2200 X 1300 X 1200 MM | BY29: =Sheet1!CX2 -> 250 | BZ29: =Sheet1!BZ2 -> 147200 | CA29: =SUMPRODUCT($N$18:$BU$18,N29:BU29)+BZ29 -> 1464480 | CB29: =Sheet1!CB2 -> 0 | CC29: =CA29*CB29 -> 0 | CD29: 0.5 | CE29: =CA29*CD29 -> 732240 | CF29: 0 | CG29: =CA29*CF29 -> 0 | CH29: =CA29+CC29+CE29+CG29 -> 2196720 | CI29: 0.02 | CJ29: =CH29*CI29 -> 43934.4 | CK29: 0.01 | CL29: =CH29*CK29 -> 21967.2
A30: =Sheet1!A12 -> ENQ-10773-22-23 | B30: =Sheet1!B12 -> 45135 | C30: =Sheet1!C12 -> FA1300027 | D30: =Sheet1!D12 -> 1 CORE X 630 SQ. MM. AL/ARM (XLPE) - 33 KV | E30: =CH30+CJ30+CL30 -> 1563059.5 | F30: =ROUNDUP(M46,0) -> 35031 | G30: =E30+F30 -> 1598090.5 | H30: =Sheet1!CP12 -> 0.18 | I30: =G30*H30 -> 287656.29 | J30: =G30+I30 -> 1885746.8 | K30: =Sheet1!CS12 -> 33 | L30: =Sheet1!CT12 -> KMS | M30: =J30*K30 -> 62229644 | N30: =+IFERROR(VLOOKUP($N$17,Sheet1!J12:L12,3,0),0) -> 1701 | O30: =+IFERROR(VLOOKUP($O$17,Sheet1!J12:L12,3,0),0) -> 0 | P30: =+IFERROR(VLOOKUP($P$17,Sheet1!J12:M12,3,0),0) -> 0 | Q30: =+IFERROR(VLOOKUP($Q$17,Sheet1!J12:M12,3,0),0) -> 0 | R30: =+IFERROR(VLOOKUP($R$17,Sheet1!J12:M12,3,0),0) -> 0 | S30: =+IFERROR(VLOOKUP($S$17,Sheet1!N12:Q12,3,0),0) -> 0 | T30: =+IFERROR(VLOOKUP($T$17,Sheet1!N12:Q12,3,0),0) -> 0 | U30: =+IFERROR(VLOOKUP($U$17,Sheet1!F12:I12,3,0),0) -> 0 | V30: =+IFERROR(VLOOKUP($V$17,Sheet1!F12:I12,3,0),0) -> 0 | W30: =+IFERROR(VLOOKUP($W$17,Sheet1!F12:I12,3,0),0) -> 0 | X30: =+IFERROR(VLOOKUP($X$17,Sheet1!F12:I12,3,0),0) -> 0 | Y30: 79 | Z30: =+IFERROR(VLOOKUP($Z$17,Sheet1!F12:I12,3,0),0) -> 0 | AA30: =+IFERROR(VLOOKUP($AA$17,Sheet1!F12:I12,3,0),0) -> 0 | AB30: =+IFERROR(VLOOKUP($AB$17,Sheet1!F12:I12,3,0),0) -> 0 | AC30: 218 | AD30: =+IFERROR(VLOOKUP($AD$17,Sheet1!R12:U12,2,0),0) -> 0 | AE30: 1055 | AF30: =+IFERROR(VLOOKUP($AF$17,Sheet1!V12:Y12,3,0),0) -> 0 | AG30: =+IFERROR(VLOOKUP($AG$17,Sheet1!V12:Y12,3,0),0) -> 0 | AH30: =+IFERROR(VLOOKUP($AH$17,Sheet1!V12:Y12,3,0),0) -> 0 | AI30: =+IFERROR(VLOOKUP($AI$17,Sheet1!V12:Y12,3,0),0) -> 0 | AJ30: =+IFERROR(VLOOKUP($AJ$17,Sheet1!V12:Y12,3,0),0) -> 0 | AK30: 18 | AL30: =+IFERROR(VLOOKUP($AL$17,Sheet1!AD12:AG12,3,0),0) -> 0 | AM30: =+IFERROR(VLOOKUP($AM$17,Sheet1!AD12:AG12,3,0),0) -> 0 | AN30: =+IFERROR(VLOOKUP($AN$17,Sheet1!AD12:AG12,3,0),0) -> 0 | AO30: =+IFERROR(VLOOKUP($AO$17,Sheet1!AD12:AG12,3,0),0) -> 0 | AP30: =+IFERROR(VLOOKUP($AP$17,Sheet1!AD12:AG12,3,0),0) -> 0 | AQ30: 200 | AR30: =+IFERROR(VLOOKUP($AR$17,Sheet1!AD12:AG12,3,0),0) -> 0 | AS30: =+IFERROR(VLOOKUP($AS$17,Sheet1!AH12:AK12,3,0),0) -> 0 | AT30: =+IFERROR(VLOOKUP($AT$17,Sheet1!AH12:AK12,3,0),0) -> 0 | AU30: =+IFERROR(VLOOKUP($AU$17,Sheet1!AH12:AK12,3,0),0) -> 0 | AV30: 828 | AW30: =+IFERROR(VLOOKUP($AW$17,Sheet1!AH12:AK12,3,0),0) -> 0 | AX30: =+IFERROR(VLOOKUP($AX$17,Sheet1!AH12:AK12,3,0),0) -> 0 | AY30: =+IFERROR(VLOOKUP($AY$17,Sheet1!AH12:AK12,3,0),0) -> 0 | AZ30: =+IFERROR(VLOOKUP($AZ$17,Sheet1!AH12:AK12,3,0),0) -> 0 | BA30: =+IFERROR(VLOOKUP($BA$17,Sheet1!AH12:AK12,3,0),0) -> 0 | BB30: =+IFERROR(VLOOKUP($BB$17,Sheet1!AH12:AK12,3,0),0) -> 0 | BC30: =+IFERROR(VLOOKUP($BC$17,Sheet1!AL12:AO12,3,0),0) -> 0 | BD30: =+IFERROR(VLOOKUP($BD$17,Sheet1!AL12:AO12,3,0),0) -> 0 | BE30: =+IFERROR(VLOOKUP($BE$17,Sheet1!AL12:AO12,3,0),0) -> 0 | BF30: 760 | BG30: =+IFERROR(VLOOKUP($BG$17,Sheet1!AL12:AO12,3,0),0) -> 0 | BH30: =+IFERROR(VLOOKUP($BH$17,Sheet1!AL12:AO12,3,0),0) -> 0 | BI30: =+IFERROR(VLOOKUP($BI$17,Sheet1!AL12:AO12,3,0),0) -> 0 | BJ30: =+IFERROR(VLOOKUP($BJ$17,Sheet1!AL12:AO12,3,0),0) -> 0 | BK30: =+IFERROR(VLOOKUP($BK$17,Sheet1!AL12:AO12,3,0),0) -> 0 | BL30: =+IFERROR(VLOOKUP($BL$17,Sheet1!AL12:AO12,3,0),0) -> 0 | BM30: =+IFERROR(VLOOKUP($BM$17,Sheet1!AP12:AS12,3,0),0) -> 0 | BN30: =+IFERROR(VLOOKUP($BN$17,Sheet1!AT12:AW12,3,0),0) -> 0 | BO30: 26 | BP30: 41 | BQ30: =+IFERROR(VLOOKUP($BQ$17,Sheet1!BF12:BI12,3,0),0) -> 0 | BR30: =+IFERROR(VLOOKUP($BR$17,Sheet1!BJ12:BM12,3,0),0) -> 0 | BS30: =+IFERROR(VLOOKUP($BS$17,Sheet1!BN12:BQ12,3,0),0) -> 0 | BT30: 42 | BU30: =+IFERROR(VLOOKUP($BU$17,Sheet1!BV12:BY12,3,0),0) -> 0 | BV30: =Sheet1!E12 -> STEEL | BW30: =Sheet1!CV12 -> SP0400123 | BX30: =Sheet1!CW12 -> CORRUGATED DISPATCH STEEL DRUM 2000 X 1000 X 1200 MM | BY30: =Sheet1!CX12 -> 500 | BZ30: =Sheet1!BZ12 -> 53200 | CA30: =SUMPRODUCT($N$18:$BU$18,N30:BU30)+BZ30 -> 1011689 | CB30: =Sheet1!CB12 -> 0 | CC30: =CA30*CB30 -> 0 | CD30: 0.5 | CE30: =CA30*CD30 -> 505844.5 | CF30: 0 | CG30: =CA30*CF30 -> 0 | CH30: =CA30+CC30+CE30+CG30 -> 1517533.5 | CI30: 0.02 | CJ30: =CH30*CI30 -> 30350.67 | CK30: 0.01 | CL30: =CH30*CK30 -> 15175.335
A31: =Sheet1!A10 -> ENQ-10773-22-23 | B31: =Sheet1!B10 -> 45135 | C31: =Sheet1!C10 -> FA1300018 | D31: =Sheet1!D10 -> 1 CORE X 400 SQ. MM. AL/ARM (XLPE) - 33 KV | E31: =CH31+CJ31+CL31 -> 1212522.2 | F31: =ROUNDUP(M47,0) -> 29334 | G31: =E31+F31 -> 1241856.2 | H31: =Sheet1!CP10 -> 0.18 | I31: =G31*H31 -> 223534.11 | J31: =G31+I31 -> 1465390.3 | K31: =13+12.5 -> 25.5 | L31: =Sheet1!CT10 -> KMS | M31: =J31*K31 -> 37367452 | N31: 1081 | O31: =+IFERROR(VLOOKUP($O$17,Sheet1!J10:L10,3,0),0) -> 0 | P31: =+IFERROR(VLOOKUP($P$17,Sheet1!J10:M10,3,0),0) -> 0 | Q31: =+IFERROR(VLOOKUP($Q$17,Sheet1!J10:M10,3,0),0) -> 0 | R31: =+IFERROR(VLOOKUP($R$17,Sheet1!J10:M10,3,0),0) -> 0 | S31: =+IFERROR(VLOOKUP($S$17,Sheet1!N10:Q10,3,0),0) -> 0 | T31: =+IFERROR(VLOOKUP($T$17,Sheet1!N10:Q10,3,0),0) -> 0 | U31: =+IFERROR(VLOOKUP($U$17,Sheet1!F10:I10,3,0),0) -> 0 | V31: =+IFERROR(VLOOKUP($V$17,Sheet1!F10:I10,3,0),0) -> 0 | W31: =+IFERROR(VLOOKUP($W$17,Sheet1!F10:I10,3,0),0) -> 0 | X31: =+IFERROR(VLOOKUP($X$17,Sheet1!F10:I10,3,0),0) -> 0 | Y31: 70 | Z31: =+IFERROR(VLOOKUP($Z$17,Sheet1!F10:I10,3,0),0) -> 0 | AA31: =+IFERROR(VLOOKUP($AA$17,Sheet1!F10:I10,3,0),0) -> 0 | AB31: =+IFERROR(VLOOKUP($AB$17,Sheet1!F10:I10,3,0),0) -> 0 | AC31: 171 | AD31: =+IFERROR(VLOOKUP($AD$17,Sheet1!R10:U10,2,0),0) -> 0 | AE31: 885 | AF31: =+IFERROR(VLOOKUP($AF$17,Sheet1!V10:Y10,3,0),0) -> 0 | AG31: =+IFERROR(VLOOKUP($AG$17,Sheet1!V10:Y10,3,0),0) -> 0 | AH31: =+IFERROR(VLOOKUP($AH$17,Sheet1!V10:Y10,3,0),0) -> 0 | AI31: =+IFERROR(VLOOKUP($AI$17,Sheet1!V10:Y10,3,0),0) -> 0 | AJ31: =+IFERROR(VLOOKUP($AJ$17,Sheet1!V10:Y10,3,0),0) -> 0 | AK31: 16 | AL31: =+IFERROR(VLOOKUP($AL$17,Sheet1!AD10:AG10,3,0),0) -> 0 | AM31: =+IFERROR(VLOOKUP($AM$17,Sheet1!AD10:AG10,3,0),0) -> 0 | AN31: =+IFERROR(VLOOKUP($AN$17,Sheet1!AD10:AG10,3,0),0) -> 0 | AO31: =+IFERROR(VLOOKUP($AO$17,Sheet1!AD10:AG10,3,0),0) -> 0 | AP31: =+IFERROR(VLOOKUP($AP$17,Sheet1!AD10:AG10,3,0),0) -> 0 | AQ31: 151 | AR31: =+IFERROR(VLOOKUP($AR$17,Sheet1!AD10:AG10,3,0),0) -> 0 | AS31: =+IFERROR(VLOOKUP($AS$17,Sheet1!AH10:AK10,3,0),0) -> 0 | AT31: =+IFERROR(VLOOKUP($AT$17,Sheet1!AH10:AK10,3,0),0) -> 0 | AU31: =+IFERROR(VLOOKUP($AU$17,Sheet1!AH10:AK10,3,0),0) -> 0 | AV31: 731 | AW31: =+IFERROR(VLOOKUP($AW$17,Sheet1!AH10:AK10,3,0),0) -> 0 | AX31: =+IFERROR(VLOOKUP($AX$17,Sheet1!AH10:AK10,3,0),0) -> 0 | AY31: =+IFERROR(VLOOKUP($AY$17,Sheet1!AH10:AK10,3,0),0) -> 0 | AZ31: =+IFERROR(VLOOKUP($AZ$17,Sheet1!AH10:AK10,3,0),0) -> 0 | BA31: =+IFERROR(VLOOKUP($BA$17,Sheet1!AH10:AK10,3,0),0) -> 0 | BB31: =+IFERROR(VLOOKUP($BB$17,Sheet1!AH10:AK10,3,0),0) -> 0 | BC31: =+IFERROR(VLOOKUP($BC$17,Sheet1!AL10:AO10,3,0),0) -> 0 | BD31: =+IFERROR(VLOOKUP($BD$17,Sheet1!AL10:AO10,3,0),0) -> 0 | BE31: =+IFERROR(VLOOKUP($BE$17,Sheet1!AL10:AO10,3,0),0) -> 0 | BF31: 580 | BG31: =+IFERROR(VLOOKUP($BG$17,Sheet1!AL10:AO10,3,0),0) -> 0 | BH31: =+IFERROR(VLOOKUP($BH$17,Sheet1!AL10:AO10,3,0),0) -> 0 | BI31: =+IFERROR(VLOOKUP($BI$17,Sheet1!AL10:AO10,3,0),0) -> 0 | BJ31: =+IFERROR(VLOOKUP($BJ$17,Sheet1!AL10:AO10,3,0),0) -> 0 | BK31: =+IFERROR(VLOOKUP($BK$17,Sheet1!AL10:AO10,3,0),0) -> 0 | BL31: =+IFERROR(VLOOKUP($BL$17,Sheet1!AL10:AO10,3,0),0) -> 0 | BM31: =+IFERROR(VLOOKUP($BM$17,Sheet1!AP10:AS10,3,0),0) -> 0 | BN31: =+IFERROR(VLOOKUP($BN$17,Sheet1!AT10:AW10,3,0),0) -> 0 | BO31: 19 | BP31: 35 | BQ31: =+IFERROR(VLOOKUP($BQ$17,Sheet1!BF10:BI10,3,0),0) -> 0 | BR31: =+IFERROR(VLOOKUP($BR$17,Sheet1!BJ10:BM10,3,0),0) -> 0 | BS31: =+IFERROR(VLOOKUP($BS$17,Sheet1!BN10:BQ10,3,0),0) -> 0 | BT31: 36 | BU31: =+IFERROR(VLOOKUP($BU$17,Sheet1!BV10:BY10,3,0),0) -> 0 | BV31: =Sheet1!E10 -> STEEL | BW31: =Sheet1!CV10 -> SP0400112 | BX31: =Sheet1!CW10 -> CORRUGATED DISPATCH STEEL DRUM 2000 X 1000 X 1000 MM | BY31: =Sheet1!CX10 -> 500 | BZ31: =Sheet1!BZ10 -> 53200 | CA31: =SUMPRODUCT($N$18:$BU$18,N31:BU31)+BZ31 -> 784804 | CB31: =Sheet1!CB10 -> 0 | CC31: =CA31*CB31 -> 0 | CD31: 0.5 | CE31: =CA31*CD31 -> 392402 | CF31: 0 | CG31: =CA31*CF31 -> 0 | CH31: =CA31+CC31+CE31+CG31 -> 1177206 | CI31: 0.02 | CJ31: =CH31*CI31 -> 23544.12 | CK31: 0.01 | CL31: =CH31*CK31 -> 11772.06
A32: =Sheet1!A7 -> ENQ-10773-22-23 | B32: =Sheet1!B7 -> 45135 | C32: =Sheet1!C7 -> FA1300019 | D32: =Sheet1!D7 -> 1 CORE X 300 SQ. MM. AL/ARM (XLPE) - 33 KV | E32: =CH32+CJ32+CL32 -> 1056143.5 | F32: =ROUNDUP(M48,0) -> 26154 | G32: =E32+F32 -> 1082297.5 | H32: =Sheet1!CP7 -> 0.18 | I32: =G32*H32 -> 194813.54 | J32: =G32+I32 -> 1277111 | K32: =Sheet1!CS7 -> 13 | L32: =Sheet1!CT7 -> KMS | M32: =J32*K32 -> 16602443 | N32: =+IFERROR(VLOOKUP($N$17,Sheet1!J7:L7,3,0),0) -> 810 | O32: =+IFERROR(VLOOKUP($O$17,Sheet1!J7:L7,3,0),0) -> 0 | P32: =+IFERROR(VLOOKUP($P$17,Sheet1!J7:M7,3,0),0) -> 0 | Q32: =+IFERROR(VLOOKUP($Q$17,Sheet1!J7:M7,3,0),0) -> 0 | R32: =+IFERROR(VLOOKUP($R$17,Sheet1!J7:M7,3,0),0) -> 0 | S32: =+IFERROR(VLOOKUP($S$17,Sheet1!N7:Q7,3,0),0) -> 0 | T32: =+IFERROR(VLOOKUP($T$17,Sheet1!N7:Q7,3,0),0) -> 0 | U32: =+IFERROR(VLOOKUP($U$17,Sheet1!F7:I7,3,0),0) -> 0 | V32: =+IFERROR(VLOOKUP($V$17,Sheet1!F7:I7,3,0),0) -> 0 | W32: =+IFERROR(VLOOKUP($W$17,Sheet1!F7:I7,3,0),0) -> 0 | X32: =+IFERROR(VLOOKUP($X$17,Sheet1!F7:I7,3,0),0) -> 0 | Y32: 65 | Z32: =+IFERROR(VLOOKUP($Z$17,Sheet1!F7:I7,3,0),0) -> 0 | AA32: =+IFERROR(VLOOKUP($AA$17,Sheet1!F7:I7,3,0),0) -> 0 | AB32: =+IFERROR(VLOOKUP($AB$17,Sheet1!F7:I7,3,0),0) -> 0 | AC32: 164 | AD32: =+IFERROR(VLOOKUP($AD$17,Sheet1!R7:U7,2,0),0) -> 0 | AE32: 808 | AF32: =+IFERROR(VLOOKUP($AF$17,Sheet1!V7:Y7,3,0),0) -> 0 | AG32: =+IFERROR(VLOOKUP($AG$17,Sheet1!V7:Y7,3,0),0) -> 0 | AH32: =+IFERROR(VLOOKUP($AH$17,Sheet1!V7:Y7,3,0),0) -> 0 | AI32: =+IFERROR(VLOOKUP($AI$17,Sheet1!V7:Y7,3,0),0) -> 0 | AJ32: =+IFERROR(VLOOKUP($AJ$17,Sheet1!V7:Y7,3,0),0) -> 0 | AK32: 12 | AL32: =+IFERROR(VLOOKUP($AL$17,Sheet1!AD7:AG7,3,0),0) -> 0 | AM32: =+IFERROR(VLOOKUP($AM$17,Sheet1!AD7:AG7,3,0),0) -> 0 | AN32: =+IFERROR(VLOOKUP($AN$17,Sheet1!AD7:AG7,3,0),0) -> 0 | AO32: =+IFERROR(VLOOKUP($AO$17,Sheet1!AD7:AG7,3,0),0) -> 0 | AP32: =+IFERROR(VLOOKUP($AP$17,Sheet1!AD7:AG7,3,0),0) -> 0 | AQ32: 144 | AR32: =+IFERROR(VLOOKUP($AR$17,Sheet1!AD7:AG7,3,0),0) -> 0 | AS32: =+IFERROR(VLOOKUP($AS$17,Sheet1!AH7:AK7,3,0),0) -> 0 | AT32: =+IFERROR(VLOOKUP($AT$17,Sheet1!AH7:AK7,3,0),0) -> 0 | AU32: =+IFERROR(VLOOKUP($AU$17,Sheet1!AH7:AK7,3,0),0) -> 0 | AV32: 676 | AW32: =+IFERROR(VLOOKUP($AW$17,Sheet1!AH7:AK7,3,0),0) -> 0 | AX32: =+IFERROR(VLOOKUP($AX$17,Sheet1!AH7:AK7,3,0),0) -> 0 | AY32: =+IFERROR(VLOOKUP($AY$17,Sheet1!AH7:AK7,3,0),0) -> 0 | AZ32: =+IFERROR(VLOOKUP($AZ$17,Sheet1!AH7:AK7,3,0),0) -> 0 | BA32: =+IFERROR(VLOOKUP($BA$17,Sheet1!AH7:AK7,3,0),0) -> 0 | BB32: =+IFERROR(VLOOKUP($BB$17,Sheet1!AH7:AK7,3,0),0) -> 0 | BC32: =+IFERROR(VLOOKUP($BC$17,Sheet1!AL7:AO7,3,0),0) -> 0 | BD32: =+IFERROR(VLOOKUP($BD$17,Sheet1!AL7:AO7,3,0),0) -> 0 | BE32: =+IFERROR(VLOOKUP($BE$17,Sheet1!AL7:AO7,3,0),0) -> 0 | BF32: 556 | BG32: =+IFERROR(VLOOKUP($BG$17,Sheet1!AL7:AO7,3,0),0) -> 0 | BH32: =+IFERROR(VLOOKUP($BH$17,Sheet1!AL7:AO7,3,0),0) -> 0 | BI32: =+IFERROR(VLOOKUP($BI$17,Sheet1!AL7:AO7,3,0),0) -> 0 | BJ32: =+IFERROR(VLOOKUP($BJ$17,Sheet1!AL7:AO7,3,0),0) -> 0 | BK32: =+IFERROR(VLOOKUP($BK$17,Sheet1!AL7:AO7,3,0),0) -> 0 | BL32: =+IFERROR(VLOOKUP($BL$17,Sheet1!AL7:AO7,3,0),0) -> 0 | BM32: =+IFERROR(VLOOKUP($BM$17,Sheet1!AP7:AS7,3,0),0) -> 0 | BN32: =+IFERROR(VLOOKUP($BN$17,Sheet1!AT7:AW7,3,0),0) -> 0 | BO32: 13 | BP32: 32 | BQ32: =+IFERROR(VLOOKUP($BQ$17,Sheet1!BF7:BI7,3,0),0) -> 0 | BR32: =+IFERROR(VLOOKUP($BR$17,Sheet1!BJ7:BM7,3,0),0) -> 0 | BS32: =+IFERROR(VLOOKUP($BS$17,Sheet1!BN7:BQ7,3,0),0) -> 0 | BT32: 35 | BU32: =+IFERROR(VLOOKUP($BU$17,Sheet1!BV7:BY7,3,0),0) -> 0 | BV32: =Sheet1!E7 -> STEEL | BW32: =Sheet1!CV7 -> SP0400110 | BX32: =Sheet1!CW7 -> CORRUGATED DISPATCH STEEL DRUM 1600 X 900 X 1000 MM | BY32: =Sheet1!CX7 -> 500 | BZ32: =Sheet1!BZ7 -> 47500 | CA32: =SUMPRODUCT($N$18:$BU$18,N32:BU32)+BZ32 -> 683588 | CB32: =Sheet1!CB7 -> 0 | CC32: =CA32*CB32 -> 0 | CD32: 0.5 | CE32: =CA32*CD32 -> 341794 | CF32: 0 | CG32: =CA32*CF32 -> 0 | CH32: =CA32+CC32+CE32+CG32 -> 1025382 | CI32: 0.02 | CJ32: =CH32*CI32 -> 20507.64 | CK32: 0.01 | CL32: =CH32*CK32 -> 10253.82
E34: Order Quantity | F34: Stnd Length | G34: Truck type | H34: Fare of one truck | I34: No of Drum in one truck | J34: Total length in one Truck | K34: No of Truck | L34: Total Freight | M34: Freight per KM
D35: =D19 -> 3 CORE X 400 SQ. MM. AL/ARM - WIRE (XLPE) - 11 KV | E35: =K19 -> 41.1 | F35: =BY19/1000 -> 0.25 | G35: TRAILER 28 MT | H35: 68000 | I35: 3 | J35: =F35*I35 -> 0.75 | K35: =ROUNDUP((E35/J35),0) -> 55 | L35: =M35*E35 -> 3740000 | M35: =(H35*K35)/E35 -> 90997.567
D36: =D20 -> 3 CORE X 300 SQ. MM. AL/ARM - WIRE (XLPE) - 11 KV | E36: =K20 -> 154.15 | F36: =BY20/1000 -> 0.25 | G36: TRAILER 28 MT | H36: 68000 | I36: 4 | J36: =F36*I36 -> 1 | K36: =ROUNDUP((E36/J36),0) -> 155 | L36: =M36*E36 -> 10540000 | M36: =(H36*K36)/E36 -> 68374.959
D37: =D21 -> 3 CORE X 150 SQ. MM. AL/ARM - WIRE (XLPE) - 11 KV | E37: =K21 -> 1 | F37: =BY21/1000 -> 0.25 | G37: TRAILER 28 MT | H37: 68000 | I37: 5 | J37: =F37*I37 -> 1.25 | K37: =ROUNDUP((E37/J37),0) -> 1 | L37: =M37*E37 -> 68000 | M37: =(H37*K37)/E37 -> 68000
D38: =D22 -> 3 CORE X 120 SQ. MM. AL/ARM - WIRE (XLPE) - 11 KV | E38: =K22 -> 7.5 | F38: =BY22/1000 -> 0.25 | G38: TRAILER 28 MT | H38: 68000 | I38: 5 | J38: =F38*I38 -> 1.25 | K38: =ROUNDUP((E38/J38),0) -> 6 | L38: =M38*E38 -> 408000 | M38: =(H38*K38)/E38 -> 54400
D39: =D23 -> 3 CORE X 95 SQ. MM. AL/ARM - WIRE (XLPE) - 11 KV | E39: =K23 -> 2.5 | F39: =BY23/1000 -> 0.25 | G39: TRAILER 28 MT | H39: 68000 | I39: 5 | J39: =F39*I39 -> 1.25 | K39: =ROUNDUP((E39/J39),0) -> 2 | L39: =M39*E39 -> 136000 | M39: =(H39*K39)/E39 -> 54400
D40: =D24 -> 1 CORE X 1000 SQ. MM. AL/ARM (XLPE) - 11 KV | E40: =K24 -> 15 | F40: =BY24/1000 -> 0.5 | G40: TRAILER 28 MT | H40: 68000 | I40: 4 | J40: =F40*I40 -> 2 | K40: =ROUNDUP((E40/J40),0) -> 8 | L40: =M40*E40 -> 544000 | M40: =(H40*K40)/E40 -> 36266.667
D41: =D25 -> 1 CORE X 630 SQ. MM. AL/ARM (XLPE) - 11 KV | E41: =K25 -> 5 | F41: =BY25/1000 -> 0.5 | G41: TRAILER 28 MT | H41: 68000 | I41: 5 | J41: =F41*I41 -> 2.5 | K41: =ROUNDUP((E41/J41),0) -> 2 | L41: =M41*E41 -> 136000 | M41: =(H41*K41)/E41 -> 27200
D42: =D26 -> 1 CORE X 400 SQ. MM. AL/ARM (XLPE) - 11 KV | E42: =K26 -> 40 | F42: =BY26/1000 -> 0.5 | G42: TRAILER 28 MT | H42: 68000 | I42: 6 | J42: =F42*I42 -> 3 | K42: =ROUNDUP((E42/J42),0) -> 14 | L42: =M42*E42 -> 952000 | M42: =(H42*K42)/E42 -> 23800
D43: =D27 -> 3 CORE X 400 SQ. MM AL/ARM - WIRE (XLPE) - 33 KV | E43: =K27 -> 103.5 | F43: =BY27/1000 -> 0.25 | G43: TRAILER 28 MT | H43: 68000 | I43: 2 | J43: =F43*I43 -> 0.5 | K43: =ROUNDUP((E43/J43),0) -> 207 | L43: =M43*E43 -> 14076000 | M43: =(H43*K43)/E43 -> 136000
D44: =D28 -> 3 CORE X 300 SQ. MM. AL/ARM - WIRE (XLPE) - 33 KV | E44: =K28 -> 24.25 | F44: =BY28/1000 -> 0.25 | G44: TRAILER 28 MT | H44: 68000 | I44: 2 | J44: =F44*I44 -> 0.5 | K44: =ROUNDUP((E44/J44),0) -> 49 | L44: =M44*E44 -> 3332000 | M44: =(H44*K44)/E44 -> 137402.06
D45: =D29 -> 3 CORE X 95 SQ. MM. AL/ARM WIRE (XLPE) - 33 KV | E45: =K29 -> 0.5 | F45: =BY29/1000 -> 0.25 | G45: TRAILER 28 MT | H45: 68000 | I45: 4 | J45: =F45*I45 -> 1 | K45: =ROUNDUP((E45/J45),0) -> 1 | L45: =M45*E45 -> 68000 | M45: =(H45*K45)/E45 -> 136000
D46: =D30 -> 1 CORE X 630 SQ. MM. AL/ARM (XLPE) - 33 KV | E46: =K30 -> 33 | F46: =BY30/1000 -> 0.5 | G46: TRAILER 28 MT | H46: 68000 | I46: 4 | J46: =F46*I46 -> 2 | K46: =ROUNDUP((E46/J46),0) -> 17 | L46: =M46*E46 -> 1156000 | M46: =(H46*K46)/E46 -> 35030.303
... D48: =D32 -> 1 CORE X 300 SQ. MM. AL/ARM (XLPE) - 33 KV | E48: =K32 -> 13 | F48: =BY32/1000 -> 0.5 | G48: TRAILER 28 MT | H48: 68000 | I48: 6 | J48: =F48*I48 -> 3 | K48: =ROUNDUP((E48/J48),0) -> 5 | L48: =M48*E48 -> 340000 | M48: =(H48*K48)/E48 -> 26153.846
A51: DOCKET NO. | B51: Base Date | C51: ITEM CODE | D51: PROPOSE ERP ITEM NAME | E51: EX-WORKS (PER MTR) | F51: FREIGHT PER MTR | G51: PRICE INCLUDING FREIGHT (PER MTR) | H51: GST % | I51: GST VALUE | J51: PRICE INCLUDING GST & FREIGHT (PER MTR) | K51: QTY | L51: Unit | M51: TOTAL PRICE OF FULL QTY (INCLUDING FRIGHT & GST)
A53: =A19 -> ENQ-10773-22-23 | B53: =B19 -> 45135 | C53: =C19 -> FA1300083 | D53: =D19 -> 3 CORE X 400 SQ. MM. AL/ARM - WIRE (XLPE) - 11 KV | E53: =ROUNDUP(E19/1000,2) -> 3241.8 | F53: =ROUNDUP(F19/1000,2) -> 91 | G53: =E53+F53 -> 3332.8 | H53: =H19 -> 0.18 | I53: =ROUND(G53*H53,2) -> 599.9 | J53: =ROUND(G53+I53,2) -> 3932.7 | K53: =K19*1000 -> 41100 | L53: =Sheet1!CT47 -> 0 | M53: =J53*K53 -> 161633970
A54: =A20 -> ENQ-10773-22-23 | B54: =B20 -> 45135 | C54: =C20 -> FA1300091 | D54: =D20 -> 3 CORE X 300 SQ. MM. AL/ARM - WIRE (XLPE) - 11 KV | E54: =ROUNDUP(E20/1000,2) -> 2598.3 | F54: =ROUNDUP(F20/1000,2) -> 68.38 | G54: =E54+F54 -> 2666.68 | H54: =H20 -> 0.18 | I54: =ROUND(G54*H54,2) -> 480 | J54: =ROUND(G54+I54,2) -> 3146.68 | K54: =K20*1000 -> 154150 | L54: MTR | M54: =J54*K54 -> 485060722
A55: =A21 -> ENQ-10773-22-23 | B55: =B21 -> 45135 | C55: =C21 -> FA1300176 | D55: =D21 -> 3 CORE X 150 SQ. MM. AL/ARM - WIRE (XLPE) - 11 KV | E55: =ROUNDUP(E21/1000,2) -> 1671.59 | F55: =ROUNDUP(F21/1000,2) -> 68 | G55: =E55+F55 -> 1739.59 | H55: =H21 -> 0.18 | I55: =ROUND(G55*H55,2) -> 313.13 | J55: =ROUND(G55+I55,2) -> 2052.72 | K55: =K21*1000 -> 1000 | L55: MTR | M55: =J55*K55 -> 2052720
A56: =A22 -> ENQ-10773-22-23 | B56: =B22 -> 45135 | C56: =C22 -> FA1300197 | D56: =D22 -> 3 CORE X 120 SQ. MM. AL/ARM - WIRE (XLPE) - 11 KV | E56: =ROUNDUP(E22/1000,2) -> 1462.05 | F56: =ROUNDUP(F22/1000,2) -> 54.4 | G56: =E56+F56 -> 1516.45 | H56: =H22 -> 0.18 | I56: =ROUND(G56*H56,2) -> 272.96 | J56: =ROUND(G56+I56,2) -> 1789.41 | K56: =K22*1000 -> 7500 | L56: MTR | M56: =J56*K56 -> 13420575
A57: =A23 -> ENQ-10773-22-23 | B57: =B23 -> 45135 | C57: =C23 -> FA1300098 | D57: =D23 -> 3 CORE X 95 SQ. MM. AL/ARM - WIRE (XLPE) - 11 KV | E57: =ROUNDUP(E23/1000,2) -> 1316.67 | F57: =ROUNDUP(F23/1000,2) -> 54.4 | G57: =E57+F57 -> 1371.07 | H57: =H23 -> 0.18 | I57: =ROUND(G57*H57,2) -> 246.79 | J57: =ROUND(G57+I57,2) -> 1617.86 | K57: =K23*1000 -> 2500 | L57: MTR | M57: =J57*K57 -> 4044650
A58: =A24 -> ENQ-10773-22-23 | B58: =B24 -> 45135 | C58: =C24 -> FA1300066 | D58: =D24 -> 1 CORE X 1000 SQ. MM. AL/ARM (XLPE) - 11 KV | E58: =ROUNDUP(E24/1000,2) -> 1852.71 | F58: =ROUNDUP(F24/1000,2) -> 36.27 | G58: =E58+F58 -> 1888.98 | H58: =H24 -> 0.18 | I58: =ROUND(G58*H58,2) -> 340.02 | J58: =ROUND(G58+I58,2) -> 2229 | K58: =K24*1000 -> 15000 | L58: MTR | M58: =J58*K58 -> 33435000
A59: =A25 -> ENQ-10773-22-23 | B59: =B25 -> 45135 | C59: =C25 -> FA1300016 | D59: =D25 -> 1 CORE X 630 SQ. MM. AL/ARM (XLPE) - 11 KV | E59: =ROUNDUP(E25/1000,2) -> 1201.88 | F59: =ROUNDUP(F25/1000,2) -> 27.2 | G59: =E59+F59 -> 1229.08 | H59: =H25 -> 0.18 | I59: =ROUND(G59*H59,2) -> 221.23 | J59: =ROUND(G59+I59,2) -> 1450.31 | K59: =K25*1000 -> 5000 | L59: MTR | M59: =J59*K59 -> 7251550
A60: =A26 -> ENQ-10773-22-23 | B60: =B26 -> 45135 | C60: =C26 -> FA1300047 | D60: =D26 -> 1 CORE X 400 SQ. MM. AL/ARM (XLPE) - 11 KV | E60: =ROUNDUP(E26/1000,2) -> 911.87 | F60: =ROUNDUP(F26/1000,2) -> 23.8 | G60: =E60+F60 -> 935.67 | H60: =H26 -> 0.18 | I60: =ROUND(G60*H60,2) -> 168.42 | J60: =ROUND(G60+I60,2) -> 1104.09 | K60: =K26*1000 -> 40000 | L60: MTR | M60: =J60*K60 -> 44163600
A61: =A27 -> ENQ-10773-22-23 | B61: =B27 -> 45135 | C61: =C27 -> FA1300080 | D61: =D27 -> 3 CORE X 400 SQ. MM AL/ARM - WIRE (XLPE) - 33 KV | E61: =ROUNDUP(E27/1000,2) -> 4221.44 | F61: =ROUNDUP(F27/1000,2) -> 136 | G61: =E61+F61 -> 4357.44 | H61: =H27 -> 0.18 | I61: =ROUND(G61*H61,2) -> 784.34 | J61: =ROUND(G61+I61,2) -> 5141.78 | K61: =K27*1000 -> 103500 | L61: MTR | M61: =J61*K61 -> 532174230
A62: =A28 -> ENQ-10773-22-23 | B62: =B28 -> 45135 | C62: =C28 -> FA1300081 | D62: =D28 -> 3 CORE X 300 SQ. MM. AL/ARM - WIRE (XLPE) - 33 KV | E62: =ROUNDUP(E28/1000,2) -> 3709.18 | F62: =ROUNDUP(F28/1000,2) -> 137.41 | G62: =E62+F62 -> 3846.59 | H62: =H28 -> 0.18 | I62: =ROUND(G62*H62,2) -> 692.39 | J62: =ROUND(G62+I62,2) -> 4538.98 | K62: =K28*1000 -> 24250 | L62: MTR | M62: =J62*K62 -> 1.1007026e+08
A63: =A29 -> ENQ-10773-22-23 | B63: =B29 -> 45135 | C63: =C29 -> FA1300200 | D63: =D29 -> 3 CORE X 95 SQ. MM. AL/ARM WIRE (XLPE) - 33 KV | E63: =ROUNDUP(E29/1000,2) -> 2262.63 | F63: =ROUNDUP(F29/1000,2) -> 136 | G63: =E63+F63 -> 2398.63 | H63: =H29 -> 0.18 | I63: =ROUND(G63*H63,2) -> 431.75 | J63: =ROUND(G63+I63,2) -> 2830.38 | K63: =K29*1000 -> 500 | L63: MTR | M63: =J63*K63 -> 1415190
A64: =A30 -> ENQ-10773-22-23 | B64: =B30 -> 45135 | C64: =C30 -> FA1300027 | D64: =D30 -> 1 CORE X 630 SQ. MM. AL/ARM (XLPE) - 33 KV | E64: =ROUNDUP(E30/1000,2) -> 1563.06 | F64: =ROUNDUP(F30/1000,2) -> 35.04 | G64: =E64+F64 -> 1598.1 | H64: =H30 -> 0.18 | I64: =ROUND(G64*H64,2) -> 287.66 | J64: =ROUND(G64+I64,2) -> 1885.76 | K64: =K30*1000 -> 33000 | L64: MTR | M64: =J64*K64 -> 62230080
A65: =A31 -> ENQ-10773-22-23 | B65: =B31 -> 45135 | C65: =C31 -> FA1300018 | D65: =D31 -> 1 CORE X 400 SQ. MM. AL/ARM (XLPE) - 33 KV | E65: =ROUNDUP(E31/1000,2) -> 1212.53 | F65: =ROUNDUP(F31/1000,2) -> 29.34 | G65: =E65+F65 -> 1241.87 | H65: =H31 -> 0.18 | I65: =ROUND(G65*H65,2) -> 223.54 | J65: =ROUND(G65+I65,2) -> 1465.41 | K65: =K31*1000 -> 25500 | L65: MTR | M65: =J65*K65 -> 37367955
A66: =A32 -> ENQ-10773-22-23 | B66: =B32 -> 45135 | C66: =C32 -> FA1300019 | D66: =D32 -> 1 CORE X 300 SQ. MM. AL/ARM (XLPE) - 33 KV | E66: =ROUNDUP(E32/1000,2) -> 1056.15 | F66: =ROUNDUP(F32/1000,2) -> 26.16 | G66: =E66+F66 -> 1082.31 | H66: =H32 -> 0.18 | I66: =ROUND(G66*H66,2) -> 194.82 | J66: =ROUND(G66+I66,2) -> 1277.13 | K66: =K32*1000 -> 13000 | L66: MTR | M66: =J66*K66 -> 16602690

Sheet TPNODL
A2: TP Central Odisha Distribution Limited
A4: TENDER SPECIFICATION NO () | B4: TPCODL/CCG/23-24/013.
A5: TENDER DESCRIPTION () | B5: Rate Contract for Supply of 11 KV & 33 KV HT XLPE Cable of various sizes for TPCODL, TPWODL & TPNODL.
A6: Last Date & Time of Submission () | B6: 31st July 2023 [17:00 Hrs.]
A7: REVERSE AUCTION | B7: CCG reserves the right to conduct the reverse auction (instead of public opening of price bids) for the products/ services being asked for in the tender. The terms and conditions for such reverse auction events shall be as per the Acceptance Form attached as Annexure VI of this document. The bidders along with the tender document shall mandatorily submit a duly signed copy of the Acceptance Form attached as Annexure VI as a token of acceptance for the same.
A8: Price () | B8: Price will be fixed and firm during the contractual period.
A9: Validity () | B9: Bids shall remain valid for 180 days from the due date of submission of the bid. Notwithstanding clause above, the Odisha DISCOMs may solicit the Bidder’s consent to an extension of the Period of Bid Validity. The request and responses thereto shall be made in writing.
A10: Delivery Period () | B10: Delivery period shall be 60 days from date of receipt of release order / CAT-A issuance, whichever is later.
A11: Payment Terms () | B11: TPCODL will make 100% payment within 30 days of submission of the Bill/Invoice complete in all respects and along with all the requisite documents mentioned above, subject to condition that Associate has furnished the requisite Security-cum-Performance Guarantee as stipulated in the contract.
A12: Standard length () | B12: The cable shall be supplied in continuous standard length of 250 (3 cores) & 500 (Single core) running meters with +/- 5% tolerance.
A13: Packing () | B13: Steel drums shall be provided. Drum shall be free from sharp edges and visual defect. Stencil plate on one flange side of the drum and laminated paper sheet on other side flange of drum.
A14: Technical Specification
N16: =Sheet1!J1 -> Conductor | S16: AL ALLOY | U16: Insulation Screening (Metallic) | AC16: Insulation Screening (Non-Metallic) | AE16: Insulation | AK16: POLY TAPE | AL16: Inner Sheath | AS16: Armouring | BC16: Outer Sheath | BF16: Consider Rs. 1 extra for colour of o/sh-FRLSH | BM16: FILLER | BN16: GREASE | BO16: Water swellable Tape | BP16: Semi conducting Water Swellable tape | BQ16: SEMICON TAPE | BR16: GLASS FIBER TAPE | BS16: COPPER WIRE 0.8 MM | BT16: RUBBERIZED COTTON TAPE | BU16: Water Tight Compound | BZ16: DRUM COST PER KM | CA16: TOTAL RM COST | CB16: EXTRA CONSUMPTION | CC16: EXTRA CONSUMPTION VALUE
A17: DOCKET NO. | B17: =Sheet1!B1 -> Base Date | C17: ITEM CODE | D17: PROPOSE ERP ITEM NAME | E17: EX-WORKS (PER KM) | F17: FREIGHT PER KM | G17: PRICE INCLUDING FREIGHT (PER KM) | H17: GST % | I17: GST VALUE | J17: PRICE INCLUDING GST & FREIGHT (PER KM) | K17: QTY | L17: Unit | M17: TOTAL PRICE OF FULL QTY (INCLUDING FRIGHT & GST) | N17: Alumimium | O17: Alumimium ALLOY | P17: Copper | Q17: Flexible Copper | R17: Galvanized steel wire | S17: Alumimium | T17: Alumimium ALLOY | U17: Coper tape - 0.1 mm | V17: Copper Tape - 0.03 mm | W17: Copper Tape - 0.035 mm | X17: Copper Tape - 0.04 mm | Y17: Copper Tape - 0.045 mm | Z17: Copper Tape - 0.050 mm | AA17: Copper Tape - 0.060 mm | AB17: Copper Tape - 0.075 mm(DOUBLE) | AC17: Extruded semiconductive | AD17: Extruded Semiconductive(Stripable) | AE17: HT-XLPE | AF17: LT-XLPE | AG17: TR XLPE | AH17: Type A PVC | AI17: Type C PVC (HR) | AJ17: XLPE | AK17: POLY TAPE | AL17: FR PVC Type ST-1 | AM17: FR PVC Type ST-2 | AN17: FRLSH PVC Type ST-2 | AO17: PVC Type ST-1 | AP17: PVC Type ST-1-PRESSURE EXTRUDED | AQ17: PVC Type ST-2 | AR17: PVC Type ST-2-PRESSURE EXTRUDED | AS17: ACSR CORE WIRE | AT17: ACSR DOG STEEL WIRE | AU17: Aluminium Flat Strip | AV17: Aluminium Round Wire | AW17: Double Steel Tape | AX17: Galvanised Steel Flat Strip | AY17: Galvanised Steel Flat Strip (Double) | AZ17: Galvanised Steel Flat Strip-B | BA17: Galvanised Steel Round Wire | BB17: Galvanised Steel Round Wire (Double) | BC17: FR PVC Type ST-1 | BD17: FR PVC Type ST-2 | BE17: FRLSH PVC Type ST-1 | BF17: FRLSH PVC Type ST-2 | BG17: Polypropylene Filler | BH17: PE, ST-7 | BI17: PVC Type ST-1 | BJ17: PVC Type ST-2 | BK17: PVC Type ST-2-PRESSURE EXTRUDED | BL17: UV & Track Resistant XLPE | BM17: FILLER | BN17: Grease | BO17: NCWBT | BP17: Semi conducting Water Swellable tape | BQ17: SEMICON TAPE | BR17: GLASS FIBER TAPE | BS17: COPPER WIRE 0.8 MM | BT17: RUBBERIZED COTTON TAPE | BU17: Water Tight Compound | BV17: =Sheet1!E1 -> PROPOSE DRUM TYPE | BW17: =Sheet1!CV1 -> DRUM CODE | BX17: =Sheet1!CW1 -> DRUM SIZE (FxbXtx Ft) | BY17: =Sheet1!CX1 -> PARTY STANDARD LENGTH (MTR) | CD17: MFG% | CE17: MFG VALUE | CF17: PROF% | CG17: PROFIT VALUE | CH17: 1ST EX-WORKS | CI17: Intt % | CJ17: INTT VALUE | CK17: insp% | CL17: INSP VALUE
N18: 216 | O18: =+IFERROR(VLOOKUP($O$17,Sheet1!J:L,2,0),0) -> 0 | P18: =+IFERROR(VLOOKUP($P$17,Sheet1!J:M,2,0),0) -> 0 | Q18: =+IFERROR(VLOOKUP($Q$17,Sheet1!J:M,2,0),0) -> 0 | R18: =+IFERROR(VLOOKUP($R$17,Sheet1!J:M,2,0),0) -> 0 | S18: =+IFERROR(VLOOKUP($S$17,Sheet1!N:Q,2,0),0) -> 0 | T18: =+IFERROR(VLOOKUP($T$17,Sheet1!N:O,2,0),0) -> 0 | U18: =+IFERROR(VLOOKUP($U$17,Sheet1!F:I,2,0),0) -> 0 | V18: =+IFERROR(VLOOKUP($V$17,Sheet1!F:I,2,0),0) -> 0 | W18: =+IFERROR(VLOOKUP($W$17,Sheet1!F:I,2,0),0) -> 0 | X18: =+IFERROR(VLOOKUP($X$17,Sheet1!F:I,2,0),0) -> 0 | Y18: 878 | Z18: =+IFERROR(VLOOKUP($Z$17,Sheet1!F:I,2,0),0) -> 0 | AA18: =+IFERROR(VLOOKUP($AA$17,Sheet1!F:I,2,0),0) -> 0 | AB18: =+IFERROR(VLOOKUP($AB$17,Sheet1!F:I,2,0),0) -> 0 | AC18: 195 | AD18: =+IFERROR(VLOOKUP($AD$17,Sheet1!R:U,2,0),0) -> 0 | AE18: 155 | AF18: =+IFERROR(VLOOKUP($AF$17,Sheet1!V:Y,2,0),0) -> 0 | AG18: =+IFERROR(VLOOKUP($AG$17,Sheet1!V:Y,2,0),0) -> 0 | AH18: =+IFERROR(VLOOKUP($AH$17,Sheet1!V:Y,2,0),0) -> 0 | AI18: =+IFERROR(VLOOKUP($AI$17,Sheet1!V:Y,2,0),0) -> 0 | AJ18: =+IFERROR(VLOOKUP($AJ$17,Sheet1!V:Y,2,0),0) -> 0 | AK18: 123 | AL18: =+IFERROR(VLOOKUP($AL$17,Sheet1!AD2:AG840,2,0),0) -> 0 | AM18: =+IFERROR(VLOOKUP($AM$17,Sheet1!AD2:AG840,2,0),0) -> 0 | AN18: =+IFERROR(VLOOKUP($AN$17,Sheet1!AD2:AG840,2,0),0) -> 0 | AO18: =+IFERROR(VLOOKUP($AO$17,Sheet1!AD2:AG840,2,0),0) -> 0 | AP18: =+IFERROR(VLOOKUP($AP$17,Sheet1!AD2:AG840,2,0),0) -> 0 | AQ18: 61 | AR18: 88 | AS18: =+IFERROR(VLOOKUP($AS$17,Sheet1!AH2:AK840,2,0),0) -> 0 | AT18: =+IFERROR(VLOOKUP($AT$17,Sheet1!AH2:AK840,2,0),0) -> 0 | AU18: =+IFERROR(VLOOKUP($AU$17,Sheet1!AH2:AK840,2,0),0) -> 0 | AV18: 219 | AW18: =+IFERROR(VLOOKUP($AW$17,Sheet1!AH2:AK840,2,0),0) -> 0 | AX18: =+IFERROR(VLOOKUP($AX$17,Sheet1!AH2:AK840,2,0),0) -> 0 | AY18: =+IFERROR(VLOOKUP($AY$17,Sheet1!AH2:AK840,2,0),0) -> 0 | AZ18: =+IFERROR(VLOOKUP($AZ$17,Sheet1!AH2:AK840,2,0),0) -> 0 | BA18: 87 | BB18: =+IFERROR(VLOOKUP($BB$17,Sheet1!AH2:AK840,2,0),0) -> 0 | BC18: =+IFERROR(VLOOKUP($BC$17,Sheet1!AL2:AO840,2,0),0) -> 0 | BD18: =+IFERROR(VLOOKUP($BD$17,Sheet1!AL2:AO840,2,0),0) -> 0 | BE18: =+IFERROR(VLOOKUP($BE$17,Sheet1!AL2:AO840,2,0),0) -> 0 | BF18: 94 | BG18: 65 | BH18: =+IFERROR(VLOOKUP($BH$17,Sheet1!AL2:AO840,2,0),0) -> 0 | BI18: =+IFERROR(VLOOKUP($BI$17,Sheet1!AL2:AO840,2,0),0) -> 0 | BJ18: =+IFERROR(VLOOKUP($BJ$17,Sheet1!AL2:AO840,2,0),0) -> 0 | BK18: =+IFERROR(VLOOKUP($BK$17,Sheet1!AL2:AO840,2,0),0) -> 0 | BL18: =+IFERROR(VLOOKUP($BL$17,Sheet1!AL2:AO840,2,0),0) -> 0 | BN18: =+IFERROR(VLOOKUP($BN$17,Sheet1!AT2:AW840,2,0),0) -> 0 | BO18: 350 | BP18: =+IFERROR(VLOOKUP($BP$17,Sheet1!BB2:BE840,2,0),0) -> 510 | BQ18: =+IFERROR(VLOOKUP($BQ$17,Sheet1!BF2:BI840,2,0),0) -> 0 | BR18: =+IFERROR(VLOOKUP($BR$17,Sheet1!BJ2:BM840,2,0),0) -> 0 | BS18: =+IFERROR(VLOOKUP($BS$17,Sheet1!BN2:BQ840,2,0),0) -> 0 | BT18: =+IFERROR(VLOOKUP($BT$17,Sheet1!BR2:BU840,2,0),0) -> 440 | BU18: =+IFERROR(VLOOKUP($BU$17,Sheet1!BV2:BY840,2,0),0) -> 0
A19: =Sheet1!A13 -> ENQ-10773-22-23 | B19: =Sheet1!B13 -> 45135 | C19: =Sheet1!C13 -> FA1300083 | D19: =Sheet1!D13 -> 3 CORE X 400 SQ. MM. AL/ARM - WIRE (XLPE) - 11 KV | E19: =CH19+CJ19+CL19 -> 3241791.6 | F19: =ROUNDUP(M35,0) -> 94445 | G19: =E19+F19 -> 3336236.6 | H19: =Sheet1!CP13 -> 0.18 | I19: =G19*H19 -> 600522.59 | J19: =G19+I19 -> 3936759.2 | K19: 12.6 | L19: =Sheet1!CT13 -> KMS | M19: =J19*K19 -> 49603166 | N19: 3243 | O19: =+IFERROR(VLOOKUP($O$17,Sheet1!J13:L13,3,0),0) -> 0 | P19: =+IFERROR(VLOOKUP($P$17,Sheet1!J13:M13,3,0),0) -> 0 | Q19: =+IFERROR(VLOOKUP($Q$17,Sheet1!J13:M13,3,0),0) -> 0 | R19: =+IFERROR(VLOOKUP($R$17,Sheet1!J13:M13,3,0),0) -> 0 | S19: =+IFERROR(VLOOKUP($S$17,Sheet1!N13:Q13,3,0),0) -> 0 | T19: =+IFERROR(VLOOKUP($T$17,Sheet1!N13:Q13,3,0),0) -> 0 | U19: =+IFERROR(VLOOKUP($U$17,Sheet1!F13:I13,3,0),0) -> 0 | V19: =+IFERROR(VLOOKUP($V$17,Sheet1!F13:I13,3,0),0) -> 0 | W19: =+IFERROR(VLOOKUP($W$17,Sheet1!F13:I13,3,0),0) -> 0 | X19: =+IFERROR(VLOOKUP($X$17,Sheet1!F13:I13,3,0),0) -> 0 | Y19: 158 | Z19: =+IFERROR(VLOOKUP($Z$17,Sheet1!F13:I13,3,0),0) -> 0 | AA19: =+IFERROR(VLOOKUP($AA$17,Sheet1!F13:I13,3,0),0) -> 0 | AB19: =+IFERROR(VLOOKUP($AB$17,Sheet1!F13:I13,3,0),0) -> 0 | AC19: 414 | AD19: =+IFERROR(VLOOKUP($AD$17,Sheet1!R13:U13,2,0),0) -> 0 | AE19: 938 | AF19: =+IFERROR(VLOOKUP($AF$17,Sheet1!V13:Y13,3,0),0) -> 0 | AG19: =+IFERROR(VLOOKUP($AG$17,Sheet1!V13:Y13,3,0),0) -> 0 | AH19: =+IFERROR(VLOOKUP($AH$17,Sheet1!V13:Y13,3,0),0) -> 0 | AI19: =+IFERROR(VLOOKUP($AI$17,Sheet1!V13:Y13,3,0),0) -> 0 | AJ19: =+IFERROR(VLOOKUP($AJ$17,Sheet1!V13:Y13,3,0),0) -> 0 | AK19: =+IFERROR(VLOOKUP($AK$17,Sheet1!Z13:AB13,3,0),0) -> 0 | AL19: =+IFERROR(VLOOKUP($AL$17,Sheet1!AD13:AG13,3,0),0) -> 0 | AM19: =+IFERROR(VLOOKUP($AM$17,Sheet1!AD13:AG13,3,0),0) -> 0 | AN19: =+IFERROR(VLOOKUP($AN$17,Sheet1!AD13:AG13,3,0),0) -> 0 | AO19: =+IFERROR(VLOOKUP($AO$17,Sheet1!AD13:AG13,3,0),0) -> 0 | AP19: =+IFERROR(VLOOKUP($AP$17,Sheet1!AD13:AG13,3,0),0) -> 0 | AQ19: =+IFERROR(VLOOKUP($AQ$17,Sheet1!AD13:AG13,3,0),0) -> 0 | AR19: 980 | AS19: =+IFERROR(VLOOKUP($AS$17,Sheet1!AH13:AK13,3,0),0) -> 0 | AT19: =+IFERROR(VLOOKUP($AT$17,Sheet1!AH13:AK13,3,0),0) -> 0 | AU19: =+IFERROR(VLOOKUP($AU$17,Sheet1!AH13:AK13,3,0),0) -> 0 | AV19: =+IFERROR(VLOOKUP($AV$17,Sheet1!AH13:AK13,3,0),0) -> 0 | AW19: =+IFERROR(VLOOKUP($AW$17,Sheet1!AH13:AK13,3,0),0) -> 0 | AX19: =+IFERROR(VLOOKUP($AX$17,Sheet1!AH13:AK13,3,0),0) -> 0 | AY19: =+IFERROR(VLOOKUP($AY$17,Sheet1!AH13:AK13,3,0),0) -> 0 | AZ19: =+IFERROR(VLOOKUP($AZ$17,Sheet1!AH13:AK13,3,0),0) -> 0 | BA19: 5540 | BB19: =+IFERROR(VLOOKUP($BB$17,Sheet1!AH13:AK13,3,0),0) -> 0 | BC19: =+IFERROR(VLOOKUP($BC$17,Sheet1!AL13:AO13,3,0),0) -> 0 | BD19: =+IFERROR(VLOOKUP($BD$17,Sheet1!AL13:AO13,3,0),0) -> 0 | BE19: =+IFERROR(VLOOKUP($BE$17,Sheet1!AL13:AO13,3,0),0) -> 0 | BF19: 1355 | BG19: 997 | BH19: =+IFERROR(VLOOKUP($BH$17,Sheet1!AL13:AO13,3,0),0) -> 0 | BI19: =+IFERROR(VLOOKUP($BI$17,Sheet1!AL13:AO13,3,0),0) -> 0 | BJ19: =+IFERROR(VLOOKUP($BJ$17,Sheet1!AL13:AO13,3,0),0) -> 0 | BK19: =+IFERROR(VLOOKUP($BK$17,Sheet1!AL13:AO13,3,0),0) -> 0 | BL19: =+IFERROR(VLOOKUP($BL$17,Sheet1!AL13:AO13,3,0),0) -> 0 | BM19: =+IFERROR(VLOOKUP($BM$17,Sheet1!AP13:AS13,3,0),0) -> 0 | BN19: =+IFERROR(VLOOKUP($BN$17,Sheet1!AT13:AW13,3,0),0) -> 0 | BO19: 58 | BP19: 86 | BQ19: =+IFERROR(VLOOKUP($BQ$17,Sheet1!BF13:BI13,3,0),0) -> 0 | BR19: =+IFERROR(VLOOKUP($BR$17,Sheet1!BJ13:BM13,3,0),0) -> 0 | BS19: =+IFERROR(VLOOKUP($BS$17,Sheet1!BN13:BQ13,3,0),0) -> 0 | BT19: 59 | BU19: =+IFERROR(VLOOKUP($BU$17,Sheet1!BV13:BY13,3,0),0) -> 0 | BV19: =Sheet1!E13 -> STEEL | BW19: =Sheet1!CV13 -> SP0400105 | BX19: =Sheet1!CW13 -> CORRUGATED DISPATCH STEEL DRUM 2500 X 1500 X 1400 | BY19: =Sheet1!CX13 -> 250 | BZ19: =Sheet1!BZ13 -> 182400 | CA19: =SUMPRODUCT($N$18:$BU$18,N19:BU19)+BZ19 -> 2098247 | CB19: =Sheet1!CB13 -> 0 | CC19: =CA19*CB19 -> 0 | CD19: 0.5 | CE19: =CA19*CD19 -> 1049123.5 | CF19: 0 | CG19: =CA19*CF19 -> 0 | CH19: =CA19+CC19+CE19+CG19 -> 3147370.5 | CI19: 0.02 | CJ19: =CH19*CI19 -> 62947.41 | CK19: 0.01 | CL19: =CH19*CK19 -> 31473.705
A20: =Sheet1!A15 -> ENQ-10773-22-23 | B20: =Sheet1!B15 -> 45135 | C20: =Sheet1!C15 -> FA1300091 | D20: =Sheet1!D15 -> 3 CORE X 300 SQ. MM. AL/ARM - WIRE (XLPE) - 11 KV | E20: =CH20+CJ20+CL20 -> 2598299.1 | F20: =ROUNDUP(M36,0) -> 71094 | G20: =E20+F20 -> 2669393.1 | H20: =Sheet1!CP15 -> 0.18 | I20: =G20*H20 -> 480490.76 | J20: =G20+I20 -> 3149883.9 | K20: 38.4 | L20: =Sheet1!CT15 -> KMS | M20: =J20*K20 -> 1.2095554e+08 | N20: =+IFERROR(VLOOKUP($N$17,Sheet1!J15:L15,3,0),0) -> 2430 | O20: =+IFERROR(VLOOKUP($O$17,Sheet1!J15:L15,3,0),0) -> 0 | P20: =+IFERROR(VLOOKUP($P$17,Sheet1!J15:M15,3,0),0) -> 0 | Q20: =+IFERROR(VLOOKUP($Q$17,Sheet1!J15:M15,3,0),0) -> 0 | R20: =+IFERROR(VLOOKUP($R$17,Sheet1!J15:M15,3,0),0) -> 0 | S20: =+IFERROR(VLOOKUP($S$17,Sheet1!N15:Q15,3,0),0) -> 0 | T20: =+IFERROR(VLOOKUP($T$17,Sheet1!N15:Q15,3,0),0) -> 0 | U20: =+IFERROR(VLOOKUP($U$17,Sheet1!F15:I15,3,0),0) -> 0 | V20: =+IFERROR(VLOOKUP($V$17,Sheet1!F15:I15,3,0),0) -> 0 | W20: =+IFERROR(VLOOKUP($W$17,Sheet1!F15:I15,3,0),0) -> 0 | X20: =+IFERROR(VLOOKUP($X$17,Sheet1!F15:I15,3,0),0) -> 0 | Y20: 144 | Z20: =+IFERROR(VLOOKUP($Z$17,Sheet1!F15:I15,3,0),0) -> 0 | AA20: =+IFERROR(VLOOKUP($AA$17,Sheet1!F15:I15,3,0),0) -> 0 | AB20: =+IFERROR(VLOOKUP($AB$17,Sheet1!F15:I15,3,0),0) -> 0 | AC20: 370 | AD20: =+IFERROR(VLOOKUP($AD$17,Sheet1!R15:U15,2,0),0) -> 0 | AE20: 838 | AF20: =+IFERROR(VLOOKUP($AF$17,Sheet1!V15:Y15,3,0),0) -> 0 | AG20: =+IFERROR(VLOOKUP($AG$17,Sheet1!V15:Y15,3,0),0) -> 0 | AH20: =+IFERROR(VLOOKUP($AH$17,Sheet1!V15:Y15,3,0),0) -> 0 | AI20: =+IFERROR(VLOOKUP($AI$17,Sheet1!V15:Y15,3,0),0) -> 0 | AJ20: =+IFERROR(VLOOKUP($AJ$17,Sheet1!V15:Y15,3,0),0) -> 0 | AK20: =+IFERROR(VLOOKUP($AK$17,Sheet1!Z15:AB15,3,0),0) -> 0 | AL20: =+IFERROR(VLOOKUP($AL$17,Sheet1!AD15:AG15,3,0),0) -> 0 | AM20: =+IFERROR(VLOOKUP($AM$17,Sheet1!AD15:AG15,3,0),0) -> 0 | AN20: =+IFERROR(VLOOKUP($AN$17,Sheet1!AD15:AG15,3,0),0) -> 0 | AO20: =+IFERROR(VLOOKUP($AO$17,Sheet1!AD15:AG15,3,0),0) -> 0 | AP20: =+IFERROR(VLOOKUP($AP$17,Sheet1!AD15:AG15,3,0),0) -> 0 | AQ20: =+IFERROR(VLOOKUP($AQ$17,Sheet1!AD15:AG15,3,0),0) -> 0 | AR20: 840 | AS20: =+IFERROR(VLOOKUP($AS$17,Sheet1!AH15:AK15,3,0),0) -> 0 | AT20: =+IFERROR(VLOOKUP($AT$17,Sheet1!AH15:AK15,3,0),0) -> 0 | AU20: =+IFERROR(VLOOKUP($AU$17,Sheet1!AH15:AK15,3,0),0) -> 0 | AV20: =+IFERROR(VLOOKUP($AV$17,Sheet1!AH15:AK15,3,0),0) -> 0 | AW20: =+IFERROR(VLOOKUP($AW$17,Sheet1!AH15:AK15,3,0),0) -> 0 | AX20: =+IFERROR(VLOOKUP($AX$17,Sheet1!AH15:AK15,3,0),0) -> 0 | AY20: =+IFERROR(VLOOKUP($AY$17,Sheet1!AH15:AK15,3,0),0) -> 0 | AZ20: =+IFERROR(VLOOKUP($AZ$17,Sheet1!AH15:AK15,3,0),0) -> 0 | BA20: 3945 | BB20: =+IFERROR(VLOOKUP($BB$17,Sheet1!AH15:AK15,3,0),0) -> 0 | BC20: =+IFERROR(VLOOKUP($BC$17,Sheet1!AL15:AO15,3,0),0) -> 0 | BD20: =+IFERROR(VLOOKUP($BD$17,Sheet1!AL15:AO15,3,0),0) -> 0 | BE20: =+IFERROR(VLOOKUP($BE$17,Sheet1!AL15:AO15,3,0),0) -> 0 | BF20: 1170 | BG20: 830 | BH20: =+IFERROR(VLOOKUP($BH$17,Sheet1!AL15:AO15,3,0),0) -> 0 | BI20: =+IFERROR(VLOOKUP($BI$17,Sheet1!AL15:AO15,3,0),0) -> 0 | BJ20: =+IFERROR(VLOOKUP($BJ$17,Sheet1!AL15:AO15,3,0),0) -> 0 | BK20: =+IFERROR(VLOOKUP($BK$17,Sheet1!AL15:AO15,3,0),0) -> 0 | BL20: =+IFERROR(VLOOKUP($BL$17,Sheet1!AL15:AO15,3,0),0) -> 0 | BM20: =+IFERROR(VLOOKUP($BM$17,Sheet1!AP15:AS15,3,0),0) -> 0 | BN20: =+IFERROR(VLOOKUP($BN$17,Sheet1!AT15:AW15,3,0),0) -> 0 | BO20: 38 | BP20: 77 | BQ20: =+IFERROR(VLOOKUP($BQ$17,Sheet1!BF15:BI15,3,0),0) -> 0 | BR20: =+IFERROR(VLOOKUP($BR$17,Sheet1!BJ15:BM15,3,0),0) -> 0 | BS20: =+IFERROR(VLOOKUP($BS$17,Sheet1!BN15:BQ15,3,0),0) -> 0 | BT20: 54 | BU20: =+IFERROR(VLOOKUP($BU$17,Sheet1!BV15:BY15,3,0),0) -> 0 | BV20: =Sheet1!E15 -> STEEL | BW20: =Sheet1!CV15 -> SP0400136 | BX20: =Sheet1!CW15 -> CORRUGATED DISPATCH STEEL DRUM 2200 X 1300 X 1200 MM | BY20: =Sheet1!CX15 -> 250 | BZ20: =Sheet1!BZ15 -> 171000 | CA20: =SUMPRODUCT($N$18:$BU$18,N20:BU20)+BZ20 -> 1681747 | CB20: =Sheet1!CB15 -> 0 | CC20: =CA20*CB20 -> 0 | CD20: 0.5 | CE20: =CA20*CD20 -> 840873.5 | CF20: 0 | CG20: =CA20*CF20 -> 0 | CH20: =CA20+CC20+CE20+CG20 -> 2522620.5 | CI20: 0.02 | CJ20: =CH20*CI20 -> 50452.41 | CK20: 0.01 | CL20: =CH20*CK20 -> 25226.205
A21: =Sheet1!A3 -> ENQ-10773-22-23 | B21: =Sheet1!B3 -> 45135 | C21: =Sheet1!C3 -> FA1300176 | D21: =Sheet1!D3 -> 3 CORE X 150 SQ. MM. AL/ARM - WIRE (XLPE) - 11 KV | E21: =CH21+CJ21+CL21 -> 1671588 | F21: =ROUNDUP(M37,0) -> #DIV/0! | G21: =E21+F21 -> #DIV/0! | H21: =Sheet1!CP3 -> 0.18 | I21: =G21*H21 -> #DIV/0! | J21: =G21+I21 -> #DIV/0! | K21: 0 | L21: =Sheet1!CT3 -> KMS | M21: =J21*K21 -> #DIV/0! | N21: =+IFERROR(VLOOKUP($N$17,Sheet1!J3:L3,3,0),0) -> 1215 | O21: =+IFERROR(VLOOKUP($O$17,Sheet1!J3:L3,3,0),0) -> 0 | P21: =+IFERROR(VLOOKUP($P$17,Sheet1!J3:M3,3,0),0) -> 0 | Q21: =+IFERROR(VLOOKUP($Q$17,Sheet1!J3:M3,3,0),0) -> 0 | R21: =+IFERROR(VLOOKUP($R$17,Sheet1!J3:M3,3,0),0) -> 0 | S21: =+IFERROR(VLOOKUP($S$17,Sheet1!N3:Q3,3,0),0) -> 0 | T21: =+IFERROR(VLOOKUP($T$17,Sheet1!N3:Q3,3,0),0) -> 0 | U21: =+IFERROR(VLOOKUP($U$17,Sheet1!F3:I3,3,0),0) -> 0 | V21: =+IFERROR(VLOOKUP($V$17,Sheet1!F3:I3,3,0),0) -> 0 | W21: =+IFERROR(VLOOKUP($W$17,Sheet1!F3:I3,3,0),0) -> 0 | X21: =+IFERROR(VLOOKUP($X$17,Sheet1!F3:I3,3,0),0) -> 0 | Y21: 117 | Z21: =+IFERROR(VLOOKUP($Z$17,Sheet1!F3:I3,3,0),0) -> 0 | AA21: =+IFERROR(VLOOKUP($AA$17,Sheet1!F3:I3,3,0),0) -> 0 | AB21: =+IFERROR(VLOOKUP($AB$17,Sheet1!F3:I3,3,0),0) -> 0 | AC21: 280 | AD21: =+IFERROR(VLOOKUP($AD$17,Sheet1!R3:U3,2,0),0) -> 0 | AE21: 642 | AF21: =+IFERROR(VLOOKUP($AF$17,Sheet1!V3:Y3,3,0),0) -> 0 | AG21: =+IFERROR(VLOOKUP($AG$17,Sheet1!V3:Y3,3,0),0) -> 0 | AH21: =+IFERROR(VLOOKUP($AH$17,Sheet1!V3:Y3,3,0),0) -> 0 | AI21: =+IFERROR(VLOOKUP($AI$17,Sheet1!V3:Y3,3,0),0) -> 0 | AJ21: =+IFERROR(VLOOKUP($AJ$17,Sheet1!V3:Y3,3,0),0) -> 0 | AK21: =+IFERROR(VLOOKUP($AK$17,Sheet1!Z3:AB3,3,0),0) -> 0 | AL21: =+IFERROR(VLOOKUP($AL$17,Sheet1!AD3:AG3,3,0),0) -> 0 | AM21: =+IFERROR(VLOOKUP($AM$17,Sheet1!AD3:AG3,3,0),0) -> 0 | AN21: =+IFERROR(VLOOKUP($AN$17,Sheet1!AD3:AG3,3,0),0) -> 0 | AO21: =+IFERROR(VLOOKUP($AO$17,Sheet1!AD3:AG3,3,0),0) -> 0 | AP21: =+IFERROR(VLOOKUP($AP$17,Sheet1!AD3:AG3,3,0),0) -> 0 | AQ21: =+IFERROR(VLOOKUP($AQ$17,Sheet1!AD3:AG3,3,0),0) -> 0 | AR21: 621 | AS21: =+IFERROR(VLOOKUP($AS$17,Sheet1!AH3:AK3,3,0),0) -> 0 | AT21: =+IFERROR(VLOOKUP($AT$17,Sheet1!AH3:AK3,3,0),0) -> 0 | AU21: =+IFERROR(VLOOKUP($AU$17,Sheet1!AH3:AK3,3,0),0) -> 0 | AV21: =+IFERROR(VLOOKUP($AV$17,Sheet1!AH3:AK3,3,0),0) -> 0 | AW21: =+IFERROR(VLOOKUP($AW$17,Sheet1!AH3:AK3,3,0),0) -> 0 | AX21: =+IFERROR(VLOOKUP($AX$17,Sheet1!AH3:AK3,3,0),0) -> 0 | AY21: =+IFERROR(VLOOKUP($AY$17,Sheet1!AH3:AK3,3,0),0) -> 0 | AZ21: =+IFERROR(VLOOKUP($AZ$17,Sheet1!AH3:AK3,3,0),0) -> 0 | BA21: 2685 | BB21: =+IFERROR(VLOOKUP($BB$17,Sheet1!AH3:AK3,3,0),0) -> 0 | BC21: =+IFERROR(VLOOKUP($BC$17,Sheet1!AL3:AO3,3,0),0) -> 0 | BD21: =+IFERROR(VLOOKUP($BD$17,Sheet1!AL3:AO3,3,0),0) -> 0 | BE21: =+IFERROR(VLOOKUP($BE$17,Sheet1!AL3:AO3,3,0),0) -> 0 | BF21: 800 | BG21: 541 | BH21: =+IFERROR(VLOOKUP($BH$17,Sheet1!AL3:AO3,3,0),0) -> 0 | BI21: =+IFERROR(VLOOKUP($BI$17,Sheet1!AL3:AO3,3,0),0) -> 0 | BJ21: =+IFERROR(VLOOKUP($BJ$17,Sheet1!AL3:AO3,3,0),0) -> 0 | BK21: =+IFERROR(VLOOKUP($BK$17,Sheet1!AL3:AO3,3,0),0) -> 0 | BL21: =+IFERROR(VLOOKUP($BL$17,Sheet1!AL3:AO3,3,0),0) -> 0 | BM21: =+IFERROR(VLOOKUP($BM$17,Sheet1!AP3:AS3,3,0),0) -> 0 | BN21: =+IFERROR(VLOOKUP($BN$17,Sheet1!AT3:AW3,3,0),0) -> 0 | BO21: 18 | BP21: 59 | BQ21: =+IFERROR(VLOOKUP($BQ$17,Sheet1!BF3:BI3,3,0),0) -> 0 | BR21: =+IFERROR(VLOOKUP($BR$17,Sheet1!BJ3:BM3,3,0),0) -> 0 | BS21: =+IFERROR(VLOOKUP($BS$17,Sheet1!BN3:BQ3,3,0),0) -> 0 | BT21: 44 | BU21: =+IFERROR(VLOOKUP($BU$17,Sheet1!BV3:BY3,3,0),0) -> 0 | BV21: =Sheet1!E3 -> STEEL | BW21: =Sheet1!CV3 -> SP0400111 | BX21: =Sheet1!CW3 -> CORRUGATED DISPATCH STEEL DRUM 1900 X 1000 X 1000 MM | BY21: =Sheet1!CX3 -> 250 | BZ21: =Sheet1!BZ3 -> 108300 | CA21: =SUMPRODUCT($N$18:$BU$18,N21:BU21)+BZ21 -> 1081934 | CB21: =Sheet1!CB3 -> 0 | CC21: =CA21*CB21 -> 0 | CD21: 0.5 | CE21: =CA21*CD21 -> 540967 | CF21: 0 | CG21: =CA21*CF21 -> 0 | CH21: =CA21+CC21+CE21+CG21 -> 1622901 | CI21: 0.02 | CJ21: =CH21*CI21 -> 32458.02 | CK21: 0.01 | CL21: =CH21*CK21 -> 16229.01
A22: =Sheet1!A6 -> ENQ-10773-22-23 | B22: =Sheet1!B6 -> 45135 | C22: =Sheet1!C6 -> FA1300197 | D22: =Sheet1!D6 -> 3 CORE X 120 SQ. MM. AL/ARM - WIRE (XLPE) - 11 KV | E22: =CH22+CJ22+CL22 -> 1462048.9 | F22: =ROUNDUP(M38,0) -> 70000 | G22: =E22+F22 -> 1532048.9 | H22: =Sheet1!CP6 -> 0.18 | I22: =G22*H22 -> 275768.81 | J22: =G22+I22 -> 1807817.8 | K22: 1 | L22: =Sheet1!CT6 -> KMS | M22: =J22*K22 -> 1807817.8 | N22: =+IFERROR(VLOOKUP($N$17,Sheet1!J6:L6,3,0),0) -> 972 | O22: =+IFERROR(VLOOKUP($O$17,Sheet1!J6:L6,3,0),0) -> 0 | P22: =+IFERROR(VLOOKUP($P$17,Sheet1!J6:M6,3,0),0) -> 0 | Q22: =+IFERROR(VLOOKUP($Q$17,Sheet1!J6:M6,3,0),0) -> 0 | R22: =+IFERROR(VLOOKUP($R$17,Sheet1!J6:M6,3,0),0) -> 0 | S22: =+IFERROR(VLOOKUP($S$17,Sheet1!N6:Q6,3,0),0) -> 0 | T22: =+IFERROR(VLOOKUP($T$17,Sheet1!N6:Q6,3,0),0) -> 0 | U22: =+IFERROR(VLOOKUP($U$17,Sheet1!F6:I6,3,0),0) -> 0 | V22: =+IFERROR(VLOOKUP($V$17,Sheet1!F6:I6,3,0),0) -> 0 | W22: =+IFERROR(VLOOKUP($W$17,Sheet1!F6:I6,3,0),0) -> 0 | X22: =+IFERROR(VLOOKUP($X$17,Sheet1!F6:I6,3,0),0) -> 0 | Y22: 110 | Z22: =+IFERROR(VLOOKUP($Z$17,Sheet1!F6:I6,3,0),0) -> 0 | AA22: =+IFERROR(VLOOKUP($AA$17,Sheet1!F6:I6,3,0),0) -> 0 | AB22: =+IFERROR(VLOOKUP($AB$17,Sheet1!F6:I6,3,0),0) -> 0 | AC22: 258 | AD22: =+IFERROR(VLOOKUP($AD$17,Sheet1!R6:U6,2,0),0) -> 0 | AE22: 596 | AF22: =+IFERROR(VLOOKUP($AF$17,Sheet1!V6:Y6,3,0),0) -> 0 | AG22: =+IFERROR(VLOOKUP($AG$17,Sheet1!V6:Y6,3,0),0) -> 0 | AH22: =+IFERROR(VLOOKUP($AH$17,Sheet1!V6:Y6,3,0),0) -> 0 | AI22: =+IFERROR(VLOOKUP($AI$17,Sheet1!V6:Y6,3,0),0) -> 0 | AJ22: =+IFERROR(VLOOKUP($AJ$17,Sheet1!V6:Y6,3,0),0) -> 0 | AK22: =+IFERROR(VLOOKUP($AK$17,Sheet1!Z6:AB6,3,0),0) -> 0 | AL22: =+IFERROR(VLOOKUP($AL$17,Sheet1!AD6:AG6,3,0),0) -> 0 | AM22: =+IFERROR(VLOOKUP($AM$17,Sheet1!AD6:AG6,3,0),0) -> 0 | AN22: =+IFERROR(VLOOKUP($AN$17,Sheet1!AD6:AG6,3,0),0) -> 0 | AO22: =+IFERROR(VLOOKUP($AO$17,Sheet1!AD6:AG6,3,0),0) -> 0 | AP22: =+IFERROR(VLOOKUP($AP$17,Sheet1!AD6:AG6,3,0),0) -> 0 | AQ22: =+IFERROR(VLOOKUP($AQ$17,Sheet1!AD6:AG6,3,0),0) -> 0 | AR22: 513 | AS22: =+IFERROR(VLOOKUP($AS$17,Sheet1!AH6:AK6,3,0),0) -> 0 | AT22: =+IFERROR(VLOOKUP($AT$17,Sheet1!AH6:AK6,3,0),0) -> 0 | AU22: =+IFERROR(VLOOKUP($AU$17,Sheet1!AH6:AK6,3,0),0) -> 0 | AV22: =+IFERROR(VLOOKUP($AV$17,Sheet1!AH6:AK6,3,0),0) -> 0 | AW22: =+IFERROR(VLOOKUP($AW$17,Sheet1!AH6:AK6,3,0),0) -> 0 | AX22: =+IFERROR(VLOOKUP($AX$17,Sheet1!AH6:AK6,3,0),0) -> 0 | AY22: =+IFERROR(VLOOKUP($AY$17,Sheet1!AH6:AK6,3,0),0) -> 0 | AZ22: =+IFERROR(VLOOKUP($AZ$17,Sheet1!AH6:AK6,3,0),0) -> 0 | BA22: 2404 | BB22: =+IFERROR(VLOOKUP($BB$17,Sheet1!AH6:AK6,3,0),0) -> 0 | BC22: =+IFERROR(VLOOKUP($BC$17,Sheet1!AL6:AO6,3,0),0) -> 0 | BD22: =+IFERROR(VLOOKUP($BD$17,Sheet1!AL6:AO6,3,0),0) -> 0 | BE22: =+IFERROR(VLOOKUP($BE$17,Sheet1!AL6:AO6,3,0),0) -> 0 | BF22: 694 | BG22: 479 | BH22: =+IFERROR(VLOOKUP($BH$17,Sheet1!AL6:AO6,3,0),0) -> 0 | BI22: =+IFERROR(VLOOKUP($BI$17,Sheet1!AL6:AO6,3,0),0) -> 0 | BJ22: =+IFERROR(VLOOKUP($BJ$17,Sheet1!AL6:AO6,3,0),0) -> 0 | BK22: =+IFERROR(VLOOKUP($BK$17,Sheet1!AL6:AO6,3,0),0) -> 0 | BL22: =+IFERROR(VLOOKUP($BL$17,Sheet1!AL6:AO6,3,0),0) -> 0 | BM22: =+IFERROR(VLOOKUP($BM$17,Sheet1!AP6:AS6,3,0),0) -> 0 | BN22: =+IFERROR(VLOOKUP($BN$17,Sheet1!AT6:AW6,3,0),0) -> 0 | BO22: 16.5 | BP22: 55 | BQ22: =+IFERROR(VLOOKUP($BQ$17,Sheet1!BF6:BI6,3,0),0) -> 0 | BR22: =+IFERROR(VLOOKUP($BR$17,Sheet1!BJ6:BM6,3,0),0) -> 0 | BS22: =+IFERROR(VLOOKUP($BS$17,Sheet1!BN6:BQ6,3,0),0) -> 0 | BT22: 40 | BU22: =+IFERROR(VLOOKUP($BU$17,Sheet1!BV6:BY6,3,0),0) -> 0 | BV22: =Sheet1!E6 -> STEEL | BW22: =Sheet1!CV6 -> SP0400118 | BX22: =Sheet1!CW6 -> CORRUGATED DISPATCH STEEL DRUM 1700 X 1000 X 1200 | BY22: =Sheet1!CX6 -> 250 | BZ22: =Sheet1!BZ6 -> 95000 | CA22: =SUMPRODUCT($N$18:$BU$18,N22:BU22)+BZ22 -> 946310 | CB22: =Sheet1!CB6 -> 0 | CC22: =CA22*CB22 -> 0 | CD22: 0.5 | CE22: =CA22*CD22 -> 473155 | CF22: 0 | CG22: =CA22*CF22 -> 0 | CH22: =CA22+CC22+CE22+CG22 -> 1419465 | CI22: 0.02 | CJ22: =CH22*CI22 -> 28389.3 | CK22: 0.01 | CL22: =CH22*CK22 -> 14194.65
A23: =Sheet1!A4 -> ENQ-10773-22-23 | B23: =Sheet1!B4 -> 45135 | C23: FA1300098 | D23: 3 CORE X 95 SQ. MM. AL/ARM - WIRE (XLPE) - 11 KV | E23: =CH23+CJ23+CL23 -> 1316664.4 | F23: =ROUNDUP(M39,0) -> #DIV/0! | G23: =E23+F23 -> #DIV/0! | H23: =Sheet1!CP4 -> 0.18 | I23: =G23*H23 -> #DIV/0! | J23: =G23+I23 -> #DIV/0! | K23: 0 | L23: =Sheet1!CT4 -> KMS | M23: =J23*K23 -> #DIV/0! | N23: =+IFERROR(VLOOKUP($N$17,Sheet1!J4:L4,3,0),0) -> 769.5 | O23: =+IFERROR(VLOOKUP($O$17,Sheet1!J4:L4,3,0),0) -> 0 | P23: =+IFERROR(VLOOKUP($P$17,Sheet1!J4:M4,3,0),0) -> 0 | Q23: =+IFERROR(VLOOKUP($Q$17,Sheet1!J4:M4,3,0),0) -> 0 | R23: =+IFERROR(VLOOKUP($R$17,Sheet1!J4:M4,3,0),0) -> 0 | S23: =+IFERROR(VLOOKUP($S$17,Sheet1!N4:Q4,3,0),0) -> 0 | T23: =+IFERROR(VLOOKUP($T$17,Sheet1!N4:Q4,3,0),0) -> 0 | U23: =+IFERROR(VLOOKUP($U$17,Sheet1!F4:I4,3,0),0) -> 0 | V23: =+IFERROR(VLOOKUP($V$17,Sheet1!F4:I4,3,0),0) -> 0 | W23: =+IFERROR(VLOOKUP($W$17,Sheet1!F4:I4,3,0),0) -> 0 | X23: =+IFERROR(VLOOKUP($X$17,Sheet1!F4:I4,3,0),0) -> 0 | Y23: 102 | Z23: =+IFERROR(VLOOKUP($Z$17,Sheet1!F4:I4,3,0),0) -> 0 | AA23: =+IFERROR(VLOOKUP($AA$17,Sheet1!F4:I4,3,0),0) -> 0 | AB23: =+IFERROR(VLOOKUP($AB$17,Sheet1!F4:I4,3,0),0) -> 0 | AC23: 232 | AD23: =+IFERROR(VLOOKUP($AD$17,Sheet1!R4:U4,2,0),0) -> 0 | AE23: 544 | AF23: =+IFERROR(VLOOKUP($AF$17,Sheet1!V4:Y4,3,0),0) -> 0 | AG23: =+IFERROR(VLOOKUP($AG$17,Sheet1!V4:Y4,3,0),0) -> 0 | AH23: =+IFERROR(VLOOKUP($AH$17,Sheet1!V4:Y4,3,0),0) -> 0 | AI23: =+IFERROR(VLOOKUP($AI$17,Sheet1!V4:Y4,3,0),0) -> 0 | AJ23: =+IFERROR(VLOOKUP($AJ$17,Sheet1!V4:Y4,3,0),0) -> 0 | AK23: =+IFERROR(VLOOKUP($AK$17,Sheet1!Z4:AB4,3,0),0) -> 0 | AL23: =+IFERROR(VLOOKUP($AL$17,Sheet1!AD4:AG4,3,0),0) -> 0 | AM23: =+IFERROR(VLOOKUP($AM$17,Sheet1!AD4:AG4,3,0),0) -> 0 | AN23: =+IFERROR(VLOOKUP($AN$17,Sheet1!AD4:AG4,3,0),0) -> 0 | AO23: =+IFERROR(VLOOKUP($AO$17,Sheet1!AD4:AG4,3,0),0) -> 0 | AP23: =+IFERROR(VLOOKUP($AP$17,Sheet1!AD4:AG4,3,0),0) -> 0 | AQ23: =+IFERROR(VLOOKUP($AQ$17,Sheet1!AD4:AG4,3,0),0) -> 0 | AR23: 460 | AS23: =+IFERROR(VLOOKUP($AS$17,Sheet1!AH4:AK4,3,0),0) -> 0 | AT23: =+IFERROR(VLOOKUP($AT$17,Sheet1!AH4:AK4,3,0),0) -> 0 | AU23: =+IFERROR(VLOOKUP($AU$17,Sheet1!AH4:AK4,3,0),0) -> 0 | AV23: =+IFERROR(VLOOKUP($AV$17,Sheet1!AH4:AK4,3,0),0) -> 0 | AW23: =+IFERROR(VLOOKUP($AW$17,Sheet1!AH4:AK4,3,0),0) -> 0 | AX23: =+IFERROR(VLOOKUP($AX$17,Sheet1!AH4:AK4,3,0),0) -> 0 | AY23: =+IFERROR(VLOOKUP($AY$17,Sheet1!AH4:AK4,3,0),0) -> 0 | AZ23: =+IFERROR(VLOOKUP($AZ$17,Sheet1!AH4:AK4,3,0),0) -> 0 | BA23: 2244 | BB23: =+IFERROR(VLOOKUP($BB$17,Sheet1!AH4:AK4,3,0),0) -> 0 | BC23: =+IFERROR(VLOOKUP($BC$17,Sheet1!AL4:AO4,3,0),0) -> 0 | BD23: =+IFERROR(VLOOKUP($BD$17,Sheet1!AL4:AO4,3,0),0) -> 0 | BE23: =+IFERROR(VLOOKUP($BE$17,Sheet1!AL4:AO4,3,0),0) -> 0 | BF23: 656 | BG23: 416 | BH23: =+IFERROR(VLOOKUP($BH$17,Sheet1!AL4:AO4,3,0),0) -> 0 | BI23: =+IFERROR(VLOOKUP($BI$17,Sheet1!AL4:AO4,3,0),0) -> 0 | BJ23: =+IFERROR(VLOOKUP($BJ$17,Sheet1!AL4:AO4,3,0),0) -> 0 | BK23: =+IFERROR(VLOOKUP($BK$17,Sheet1!AL4:AO4,3,0),0) -> 0 | BL23: =+IFERROR(VLOOKUP($BL$17,Sheet1!AL4:AO4,3,0),0) -> 0 | BN23: =+IFERROR(VLOOKUP($BN$17,Sheet1!AT4:AW4,3,0),0) -> 0 | BO23: 15 | BP23: 50 | BQ23: =+IFERROR(VLOOKUP($BQ$17,Sheet1!BF4:BI4,3,0),0) -> 0 | BR23: =+IFERROR(VLOOKUP($BR$17,Sheet1!BJ4:BM4,3,0),0) -> 0 | BS23: =+IFERROR(VLOOKUP($BS$17,Sheet1!BN4:BQ4,3,0),0) -> 0 | BT23: 38 | BU23: =+IFERROR(VLOOKUP($BU$17,Sheet1!BV4:BY4,3,0),0) -> 0 | BV23: =Sheet1!E4 -> STEEL | BW23: SP0400118 | BX23: CORRUGATED DISPATCH STEEL DRUM 1700 X 1000 X 1200 | BY23: =Sheet1!CX4 -> 250 | BZ23: 95000 | CA23: =SUMPRODUCT($N$18:$BU$18,N23:BU23)+BZ23 -> 852210 | CB23: =Sheet1!CB4 -> 0 | CC23: =CA23*CB23 -> 0 | CD23: 0.5 | CE23: =CA23*CD23 -> 426105 | CF23: 0 | CG23: =CA23*CF23 -> 0 | CH23: =CA23+CC23+CE23+CG23 -> 1278315 | CI23: 0.02 | CJ23: =CH23*CI23 -> 25566.3 | CK23: 0.01 | CL23: =CH23*CK23 -> 12783.15
A24: =Sheet1!A8 -> ENQ-10773-22-23 | B24: =Sheet1!B8 -> 45135 | C24: =Sheet1!C8 -> FA1300066 | D24: =Sheet1!D8 -> 1 CORE X 1000 SQ. MM. AL/ARM (XLPE) - 11 KV | E24: =CH24+CJ24+CL24 -> 1852703.7 | F24: =ROUNDUP(M40,0) -> #DIV/0! | G24: =E24+F24 -> #DIV/0! | H24: =Sheet1!CP8 -> 0.18 | I24: =G24*H24 -> #DIV/0! | J24: =G24+I24 -> #DIV/0! | K24: 0 | L24: =Sheet1!CT8 -> KMS | M24: =J24*K24 -> #DIV/0! | N24: 2732 | O24: =+IFERROR(VLOOKUP($O$17,Sheet1!J8:L8,3,0),0) -> 0 | P24: =+IFERROR(VLOOKUP($P$17,Sheet1!J8:M8,3,0),0) -> 0 | Q24: =+IFERROR(VLOOKUP($Q$17,Sheet1!J8:M8,3,0),0) -> 0 | R24: =+IFERROR(VLOOKUP($R$17,Sheet1!J8:M8,3,0),0) -> 0 | S24: =+IFERROR(VLOOKUP($S$17,Sheet1!N8:Q8,3,0),0) -> 0 | T24: =+IFERROR(VLOOKUP($T$17,Sheet1!N8:Q8,3,0),0) -> 0 | U24: =+IFERROR(VLOOKUP($U$17,Sheet1!F8:I8,3,0),0) -> 0 | V24: =+IFERROR(VLOOKUP($V$17,Sheet1!F8:I8,3,0),0) -> 0 | W24: =+IFERROR(VLOOKUP($W$17,Sheet1!F8:I8,3,0),0) -> 0 | X24: =+IFERROR(VLOOKUP($X$17,Sheet1!F8:I8,3,0),0) -> 0 | Y24: 77 | Z24: =+IFERROR(VLOOKUP($Z$17,Sheet1!F8:I8,3,0),0) -> 0 | AA24: =+IFERROR(VLOOKUP($AA$17,Sheet1!F8:I8,3,0),0) -> 0 | AB24: =+IFERROR(VLOOKUP($AB$17,Sheet1!F8:I8,3,0),0) -> 0 | AC24: 230 | AD24: =+IFERROR(VLOOKUP($AD$17,Sheet1!R8:U8,2,0),0) -> 0 | AE24: 476 | AF24: =+IFERROR(VLOOKUP($AF$17,Sheet1!V8:Y8,3,0),0) -> 0 | AG24: =+IFERROR(VLOOKUP($AG$17,Sheet1!V8:Y8,3,0),0) -> 0 | AH24: =+IFERROR(VLOOKUP($AH$17,Sheet1!V8:Y8,3,0),0) -> 0 | AI24: =+IFERROR(VLOOKUP($AI$17,Sheet1!V8:Y8,3,0),0) -> 0 | AJ24: =+IFERROR(VLOOKUP($AJ$17,Sheet1!V8:Y8,3,0),0) -> 0 | AK24: 19 | AL24: =+IFERROR(VLOOKUP($AL$17,Sheet1!AD8:AG8,3,0),0) -> 0 | AM24: =+IFERROR(VLOOKUP($AM$17,Sheet1!AD8:AG8,3,0),0) -> 0 | AN24: =+IFERROR(VLOOKUP($AN$17,Sheet1!AD8:AG8,3,0),0) -> 0 | AO24: =+IFERROR(VLOOKUP($AO$17,Sheet1!AD8:AG8,3,0),0) -> 0 | AP24: =+IFERROR(VLOOKUP($AP$17,Sheet1!AD8:AG8,3,0),0) -> 0 | AQ24: 194 | AR24: =+IFERROR(VLOOKUP($AR$17,Sheet1!AD8:AG8,3,0),0) -> 0 | AS24: =+IFERROR(VLOOKUP($AS$17,Sheet1!AH8:AK8,3,0),0) -> 0 | AT24: =+IFERROR(VLOOKUP($AT$17,Sheet1!AH8:AK8,3,0),0) -> 0 | AU24: =+IFERROR(VLOOKUP($AU$17,Sheet1!AH8:AK8,3,0),0) -> 0 | AV24: 1008 | AW24: =+IFERROR(VLOOKUP($AW$17,Sheet1!AH8:AK8,3,0),0) -> 0 | AX24: =+IFERROR(VLOOKUP($AX$17,Sheet1!AH8:AK8,3,0),0) -> 0 | AY24: =+IFERROR(VLOOKUP($AY$17,Sheet1!AH8:AK8,3,0),0) -> 0 | AZ24: =+IFERROR(VLOOKUP($AZ$17,Sheet1!AH8:AK8,3,0),0) -> 0 | BA24: =+IFERROR(VLOOKUP($BA$17,Sheet1!AH8:AK8,3,0),0) -> 0 | BB24: =+IFERROR(VLOOKUP($BB$17,Sheet1!AH8:AK8,3,0),0) -> 0 | BC24: =+IFERROR(VLOOKUP($BC$17,Sheet1!AL8:AO8,3,0),0) -> 0 | BD24: =+IFERROR(VLOOKUP($BD$17,Sheet1!AL8:AO8,3,0),0) -> 0 | BE24: =+IFERROR(VLOOKUP($BE$17,Sheet1!AL8:AO8,3,0),0) -> 0 | BF24: 700 | BG24: =+IFERROR(VLOOKUP($BG$17,Sheet1!AL8:AO8,3,0),0) -> 0 | BH24: =+IFERROR(VLOOKUP($BH$17,Sheet1!AL8:AO8,3,0),0) -> 0 | BI24: =+IFERROR(VLOOKUP($BI$17,Sheet1!AL8:AO8,3,0),0) -> 0 | BJ24: =+IFERROR(VLOOKUP($BJ$17,Sheet1!AL8:AO8,3,0),0) -> 0 | BK24: =+IFERROR(VLOOKUP($BK$17,Sheet1!AL8:AO8,3,0),0) -> 0 | BL24: =+IFERROR(VLOOKUP($BL$17,Sheet1!AL8:AO8,3,0),0) -> 0 | BM24: =+IFERROR(VLOOKUP($BM$17,Sheet1!AP8:AS8,3,0),0) -> 0 | BN24: =+IFERROR(VLOOKUP($BN$17,Sheet1!AT8:AW8,3,0),0) -> 0 | BO24: 39 | BP24: 46 | BQ24: =+IFERROR(VLOOKUP($BQ$17,Sheet1!BF8:BI8,3,0),0) -> 0 | BR24: =+IFERROR(VLOOKUP($BR$17,Sheet1!BJ8:BM8,3,0),0) -> 0 | BS24: =+IFERROR(VLOOKUP($BS$17,Sheet1!BN8:BQ8,3,0),0) -> 0 | BT24: 42 | BU24: =+IFERROR(VLOOKUP($BU$17,Sheet1!BV8:BY8,3,0),0) -> 0 | BV24: =Sheet1!E8 -> STEEL | BW24: =Sheet1!CV8 -> SP0400107 | BX24: =Sheet1!CW8 -> CORRUGATED DISPATCH STEEL DRUM 2150 X 1080 X 1240 MM | BY24: =Sheet1!CX8 -> 500 | BZ24: =Sheet1!BZ8 -> 66500 | CA24: =SUMPRODUCT($N$18:$BU$18,N24:BU24)+BZ24 -> 1199161 | CB24: =Sheet1!CB8 -> 0 | CC24: =CA24*CB24 -> 0 | CD24: 0.5 | CE24: =CA24*CD24 -> 599580.5 | CF24: 0 | CG24: =CA24*CF24 -> 0 | CH24: =CA24+CC24+CE24+CG24 -> 1798741.5 | CI24: 0.02 | CJ24: =CH24*CI24 -> 35974.83 | CK24: 0.01 | CL24: =CH24*CK24 -> 17987.415
A25: =Sheet1!A5 -> ENQ-10773-22-23 | B25: =Sheet1!B5 -> 45135 | C25: =Sheet1!C5 -> FA1300016 | D25: =Sheet1!D5 -> 1 CORE X 630 SQ. MM. AL/ARM (XLPE) - 11 KV | E25: =CH25+CJ25+CL25 -> 1201875.6 | F25: =ROUNDUP(M41,0) -> #DIV/0! | G25: =E25+F25 -> #DIV/0! | H25: =Sheet1!CP5 -> 0.18 | I25: =G25*H25 -> #DIV/0! | J25: =G25+I25 -> #DIV/0! | K25: 0 | L25: =Sheet1!CT5 -> KMS | M25: =J25*K25 -> #DIV/0! | N25: =+IFERROR(VLOOKUP($N$17,Sheet1!J5:L5,3,0),0) -> 1701 | O25: =+IFERROR(VLOOKUP($O$17,Sheet1!J5:L5,3,0),0) -> 0 | P25: =+IFERROR(VLOOKUP($P$17,Sheet1!J5:M5,3,0),0) -> 0 | Q25: =+IFERROR(VLOOKUP($Q$17,Sheet1!J5:M5,3,0),0) -> 0 | R25: =+IFERROR(VLOOKUP($R$17,Sheet1!J5:M5,3,0),0) -> 0 | S25: =+IFERROR(VLOOKUP($S$17,Sheet1!N5:Q5,3,0),0) -> 0 | T25: =+IFERROR(VLOOKUP($T$17,Sheet1!N5:Q5,3,0),0) -> 0 | U25: =+IFERROR(VLOOKUP($U$17,Sheet1!F5:I5,3,0),0) -> 0 | V25: =+IFERROR(VLOOKUP($V$17,Sheet1!F5:I5,3,0),0) -> 0 | W25: =+IFERROR(VLOOKUP($W$17,Sheet1!F5:I5,3,0),0) -> 0 | X25: =+IFERROR(VLOOKUP($X$17,Sheet1!F5:I5,3,0),0) -> 0 | Y25: 63 | Z25: =+IFERROR(VLOOKUP($Z$17,Sheet1!F5:I5,3,0),0) -> 0 | AA25: =+IFERROR(VLOOKUP($AA$17,Sheet1!F5:I5,3,0),0) -> 0 | AB25: =+IFERROR(VLOOKUP($AB$17,Sheet1!F5:I5,3,0),0) -> 0 | AC25: 170 | AD25: =+IFERROR(VLOOKUP($AD$17,Sheet1!R5:U5,2,0),0) -> 0 | AE25: 380 | AF25: =+IFERROR(VLOOKUP($AF$17,Sheet1!V5:Y5,3,0),0) -> 0 | AG25: =+IFERROR(VLOOKUP($AG$17,Sheet1!V5:Y5,3,0),0) -> 0 | AH25: =+IFERROR(VLOOKUP($AH$17,Sheet1!V5:Y5,3,0),0) -> 0 | AI25: =+IFERROR(VLOOKUP($AI$17,Sheet1!V5:Y5,3,0),0) -> 0 | AJ25: =+IFERROR(VLOOKUP($AJ$17,Sheet1!V5:Y5,3,0),0) -> 0 | AK25: 15 | AL25: =+IFERROR(VLOOKUP($AL$17,Sheet1!AD5:AG5,3,0),0) -> 0 | AM25: =+IFERROR(VLOOKUP($AM$17,Sheet1!AD5:AG5,3,0),0) -> 0 | AN25: =+IFERROR(VLOOKUP($AN$17,Sheet1!AD5:AG5,3,0),0) -> 0 | AO25: =+IFERROR(VLOOKUP($AO$17,Sheet1!AD5:AG5,3,0),0) -> 0 | AP25: =+IFERROR(VLOOKUP($AP$17,Sheet1!AD5:AG5,3,0),0) -> 0 | AQ25: 140 | AR25: =+IFERROR(VLOOKUP($AR$17,Sheet1!AD5:AG5,3,0),0) -> 0 | AS25: =+IFERROR(VLOOKUP($AS$17,Sheet1!AH5:AK5,3,0),0) -> 0 | AT25: =+IFERROR(VLOOKUP($AT$17,Sheet1!AH5:AK5,3,0),0) -> 0 | AU25: =+IFERROR(VLOOKUP($AU$17,Sheet1!AH5:AK5,3,0),0) -> 0 | AV25: 530 | AW25: =+IFERROR(VLOOKUP($AW$17,Sheet1!AH5:AK5,3,0),0) -> 0 | AX25: =+IFERROR(VLOOKUP($AX$17,Sheet1!AH5:AK5,3,0),0) -> 0 | AY25: =+IFERROR(VLOOKUP($AY$17,Sheet1!AH5:AK5,3,0),0) -> 0 | AZ25: =+IFERROR(VLOOKUP($AZ$17,Sheet1!AH5:AK5,3,0),0) -> 0 | BA25: =+IFERROR(VLOOKUP($BA$17,Sheet1!AH5:AK5,3,0),0) -> 0 | BB25: =+IFERROR(VLOOKUP($BB$17,Sheet1!AH5:AK5,3,0),0) -> 0 | BC25: =+IFERROR(VLOOKUP($BC$17,Sheet1!AL5:AO5,3,0),0) -> 0 | BD25: =+IFERROR(VLOOKUP($BD$17,Sheet1!AL5:AO5,3,0),0) -> 0 | BE25: =+IFERROR(VLOOKUP($BE$17,Sheet1!AL5:AO5,3,0),0) -> 0 | BF25: 492 | BG25: =+IFERROR(VLOOKUP($BG$17,Sheet1!AL5:AO5,3,0),0) -> 0 | BH25: =+IFERROR(VLOOKUP($BH$17,Sheet1!AL5:AO5,3,0),0) -> 0 | BI25: =+IFERROR(VLOOKUP($BI$17,Sheet1!AL5:AO5,3,0),0) -> 0 | BJ25: =+IFERROR(VLOOKUP($BJ$17,Sheet1!AL5:AO5,3,0),0) -> 0 | BK25: =+IFERROR(VLOOKUP($BK$17,Sheet1!AL5:AO5,3,0),0) -> 0 | BL25: =+IFERROR(VLOOKUP($BL$17,Sheet1!AL5:AO5,3,0),0) -> 0 | BM25: =+IFERROR(VLOOKUP($BM$17,Sheet1!AP5:AS5,3,0),0) -> 0 | BN25: =+IFERROR(VLOOKUP($BN$17,Sheet1!AT5:AW5,3,0),0) -> 0 | BO25: 26 | BP25: 36 | BQ25: =+IFERROR(VLOOKUP($BQ$17,Sheet1!BF5:BI5,3,0),0) -> 0 | BR25: =+IFERROR(VLOOKUP($BR$17,Sheet1!BJ5:BM5,3,0),0) -> 0 | BS25: =+IFERROR(VLOOKUP($BS$17,Sheet1!BN5:BQ5,3,0),0) -> 0 | BT25: 33 | BU25: =+IFERROR(VLOOKUP($BU$17,Sheet1!BV5:BY5,3,0),0) -> 0 | BV25: =Sheet1!E5 -> STEEL | BW25: =Sheet1!CV5 -> SP0400091 | BX25: =Sheet1!CW5 -> CORRUGATED DISPATCH STEEL DRUM 1800 X 900 X 1000 | BY25: =Sheet1!CX5 -> 500 | BZ25: =Sheet1!BZ5 -> 48450 | CA25: =SUMPRODUCT($N$18:$BU$18,N25:BU25)+BZ25 -> 777913 | CB25: =Sheet1!CB5 -> 0 | CC25: =CA25*CB25 -> 0 | CD25: 0.5 | CE25: =CA25*CD25 -> 388956.5 | CF25: 0 | CG25: =CA25*CF25 -> 0 | CH25: =CA25+CC25+CE25+CG25 -> 1166869.5 | CI25: 0.02 | CJ25: =CH25*CI25 -> 23337.39 | CK25: 0.01 | CL25: =CH25*CK25 -> 11668.695
A26: =Sheet1!A11 -> ENQ-10773-22-23 | B26: =Sheet1!B11 -> 45135 | C26: =Sheet1!C11 -> FA1300047 | D26: =Sheet1!D11 -> 1 CORE X 400 SQ. MM. AL/ARM (XLPE) - 11 KV | E26: =CH26+CJ26+CL26 -> 911866.72 | F26: =ROUNDUP(M42,0) -> #DIV/0! | G26: =E26+F26 -> #DIV/0! | H26: =Sheet1!CP11 -> 0.18 | I26: =G26*H26 -> #DIV/0! | J26: =G26+I26 -> #DIV/0! | K26: 0 | L26: =Sheet1!CT11 -> KMS | M26: =J26*K26 -> #DIV/0! | N26: =+IFERROR(VLOOKUP($N$17,Sheet1!J11:L11,3,0),0) -> 1080 | O26: =+IFERROR(VLOOKUP($O$17,Sheet1!J11:L11,3,0),0) -> 0 | P26: =+IFERROR(VLOOKUP($P$17,Sheet1!J11:M11,3,0),0) -> 0 | Q26: =+IFERROR(VLOOKUP($Q$17,Sheet1!J11:M11,3,0),0) -> 0 | R26: =+IFERROR(VLOOKUP($R$17,Sheet1!J11:M11,3,0),0) -> 0 | S26: =+IFERROR(VLOOKUP($S$17,Sheet1!N11:Q11,3,0),0) -> 0 | T26: =+IFERROR(VLOOKUP($T$17,Sheet1!N11:Q11,3,0),0) -> 0 | U26: =+IFERROR(VLOOKUP($U$17,Sheet1!F11:I11,3,0),0) -> 0 | V26: =+IFERROR(VLOOKUP($V$17,Sheet1!F11:I11,3,0),0) -> 0 | W26: =+IFERROR(VLOOKUP($W$17,Sheet1!F11:I11,3,0),0) -> 0 | X26: =+IFERROR(VLOOKUP($X$17,Sheet1!F11:I11,3,0),0) -> 0 | Y26: 53 | Z26: =+IFERROR(VLOOKUP($Z$17,Sheet1!F11:I11,3,0),0) -> 0 | AA26: =+IFERROR(VLOOKUP($AA$17,Sheet1!F11:I11,3,0),0) -> 0 | AB26: =+IFERROR(VLOOKUP($AB$17,Sheet1!F11:I11,3,0),0) -> 0 | AC26: 138 | AD26: =+IFERROR(VLOOKUP($AD$17,Sheet1!R11:U11,2,0),0) -> 0 | AE26: 310 | AF26: =+IFERROR(VLOOKUP($AF$17,Sheet1!V11:Y11,3,0),0) -> 0 | AG26: =+IFERROR(VLOOKUP($AG$17,Sheet1!V11:Y11,3,0),0) -> 0 | AH26: =+IFERROR(VLOOKUP($AH$17,Sheet1!V11:Y11,3,0),0) -> 0 | AI26: =+IFERROR(VLOOKUP($AI$17,Sheet1!V11:Y11,3,0),0) -> 0 | AJ26: =+IFERROR(VLOOKUP($AJ$17,Sheet1!V11:Y11,3,0),0) -> 0 | AK26: 13 | AL26: =+IFERROR(VLOOKUP($AL$17,Sheet1!AD11:AG11,3,0),0) -> 0 | AM26: =+IFERROR(VLOOKUP($AM$17,Sheet1!AD11:AG11,3,0),0) -> 0 | AN26: =+IFERROR(VLOOKUP($AN$17,Sheet1!AD11:AG11,3,0),0) -> 0 | AO26: =+IFERROR(VLOOKUP($AO$17,Sheet1!AD11:AG11,3,0),0) -> 0 | AP26: =+IFERROR(VLOOKUP($AP$17,Sheet1!AD11:AG11,3,0),0) -> 0 | AQ26: 102 | AR26: =+IFERROR(VLOOKUP($AR$17,Sheet1!AD11:AG11,3,0),0) -> 0 | AS26: =+IFERROR(VLOOKUP($AS$17,Sheet1!AH11:AK11,3,0),0) -> 0 | AT26: =+IFERROR(VLOOKUP($AT$17,Sheet1!AH11:AK11,3,0),0) -> 0 | AU26: =+IFERROR(VLOOKUP($AU$17,Sheet1!AH11:AK11,3,0),0) -> 0 | AV26: 552 | AW26: =+IFERROR(VLOOKUP($AW$17,Sheet1!AH11:AK11,3,0),0) -> 0 | AX26: =+IFERROR(VLOOKUP($AX$17,Sheet1!AH11:AK11,3,0),0) -> 0 | AY26: =+IFERROR(VLOOKUP($AY$17,Sheet1!AH11:AK11,3,0),0) -> 0 | AZ26: =+IFERROR(VLOOKUP($AZ$17,Sheet1!AH11:AK11,3,0),0) -> 0 | BA26: =+IFERROR(VLOOKUP($BA$17,Sheet1!AH11:AK11,3,0),0) -> 0 | BB26: =+IFERROR(VLOOKUP($BB$17,Sheet1!AH11:AK11,3,0),0) -> 0 | BC26: =+IFERROR(VLOOKUP($BC$17,Sheet1!AL11:AO11,3,0),0) -> 0 | BD26: =+IFERROR(VLOOKUP($BD$17,Sheet1!AL11:AO11,3,0),0) -> 0 | BE26: =+IFERROR(VLOOKUP($BE$17,Sheet1!AL11:AO11,3,0),0) -> 0 | BF26: 403 | BG26: =+IFERROR(VLOOKUP($BG$17,Sheet1!AL11:AO11,3,0),0) -> 0 | BH26: =+IFERROR(VLOOKUP($BH$17,Sheet1!AL11:AO11,3,0),0) -> 0 | BI26: =+IFERROR(VLOOKUP($BI$17,Sheet1!AL11:AO11,3,0),0) -> 0 | BJ26: =+IFERROR(VLOOKUP($BJ$17,Sheet1!AL11:AO11,3,0),0) -> 0 | BK26: =+IFERROR(VLOOKUP($BK$17,Sheet1!AL11:AO11,3,0),0) -> 0 | BL26: =+IFERROR(VLOOKUP($BL$17,Sheet1!AL11:AO11,3,0),0) -> 0 | BM26: =+IFERROR(VLOOKUP($BM$17,Sheet1!AP11:AS11,3,0),0) -> 0 | BN26: =+IFERROR(VLOOKUP($BN$17,Sheet1!AT11:AW11,3,0),0) -> 0 | BO26: 19 | BP26: 29 | BQ26: =+IFERROR(VLOOKUP($BQ$17,Sheet1!BF11:BI11,3,0),0) -> 0 | BR26: =+IFERROR(VLOOKUP($BR$17,Sheet1!BJ11:BM11,3,0),0) -> 0 | BS26: =+IFERROR(VLOOKUP($BS$17,Sheet1!BN11:BQ11,3,0),0) -> 0 | BT26: 30 | BU26: =+IFERROR(VLOOKUP($BU$17,Sheet1!BV11:BY11,3,0),0) -> 0 | BV26: =Sheet1!E11 -> STEEL | BW26: =Sheet1!CV11 -> SP0400125 | BX26: =Sheet1!CW11 -> CORRUGATED DISPATCH STEEL DRUM 1600 X 700 X 915 MM | BY26: =Sheet1!CX11 -> 500 | BZ26: =Sheet1!BZ11 -> 34200 | CA26: =SUMPRODUCT($N$18:$BU$18,N26:BU26)+BZ26 -> 590205 | CB26: =Sheet1!CB11 -> 0 | CC26: =CA26*CB26 -> 0 | CD26: 0.5 | CE26: =CA26*CD26 -> 295102.5 | CF26: 0 | CG26: =CA26*CF26 -> 0 | CH26: =CA26+CC26+CE26+CG26 -> 885307.5 | CI26: 0.02 | CJ26: =CH26*CI26 -> 17706.15 | CK26: 0.01 | CL26: =CH26*CK26 -> 8853.075
A27: =Sheet1!A14 -> ENQ-10773-22-23 | B27: =Sheet1!B14 -> 45135 | C27: =Sheet1!C14 -> FA1300080 | D27: =Sheet1!D14 -> 3 CORE X 400 SQ. MM AL/ARM - WIRE (XLPE) - 33 KV | E27: =CH27+CJ27+CL27 -> 4221435.9 | F27: =ROUNDUP(M43,0) -> 140000 | G27: =E27+F27 -> 4361435.9 | H27: =Sheet1!CP14 -> 0.18 | I27: =G27*H27 -> 785058.47 | J27: =G27+I27 -> 5146494.4 | K27: 36 | L27: =Sheet1!CT14 -> KMS | M27: =J27*K27 -> 1.852738e+08 | N27: 3243 | O27: =+IFERROR(VLOOKUP($O$17,Sheet1!J14:L14,3,0),0) -> 0 | P27: =+IFERROR(VLOOKUP($P$17,Sheet1!J14:M14,3,0),0) -> 0 | Q27: =+IFERROR(VLOOKUP($Q$17,Sheet1!J14:M14,3,0),0) -> 0 | R27: =+IFERROR(VLOOKUP($R$17,Sheet1!J14:M14,3,0),0) -> 0 | S27: =+IFERROR(VLOOKUP($S$17,Sheet1!N14:Q14,3,0),0) -> 0 | T27: =+IFERROR(VLOOKUP($T$17,Sheet1!N14:Q14,3,0),0) -> 0 | U27: =+IFERROR(VLOOKUP($U$17,Sheet1!F14:I14,3,0),0) -> 0 | V27: =+IFERROR(VLOOKUP($V$17,Sheet1!F14:I14,3,0),0) -> 0 | W27: =+IFERROR(VLOOKUP($W$17,Sheet1!F14:I14,3,0),0) -> 0 | X27: =+IFERROR(VLOOKUP($X$17,Sheet1!F14:I14,3,0),0) -> 0 | Y27: 212 | Z27: =+IFERROR(VLOOKUP($Z$17,Sheet1!F14:I14,3,0),0) -> 0 | AA27: =+IFERROR(VLOOKUP($AA$17,Sheet1!F14:I14,3,0),0) -> 0 | AB27: =+IFERROR(VLOOKUP($AB$17,Sheet1!F14:I14,3,0),0) -> 0 | AC27: 515 | AD27: =+IFERROR(VLOOKUP($AD$17,Sheet1!R14:U14,2,0),0) -> 0 | AE27: 2670 | AF27: =+IFERROR(VLOOKUP($AF$17,Sheet1!V14:Y14,3,0),0) -> 0 | AG27: =+IFERROR(VLOOKUP($AG$17,Sheet1!V14:Y14,3,0),0) -> 0 | AH27: =+IFERROR(VLOOKUP($AH$17,Sheet1!V14:Y14,3,0),0) -> 0 | AI27: =+IFERROR(VLOOKUP($AI$17,Sheet1!V14:Y14,3,0),0) -> 0 | AJ27: =+IFERROR(VLOOKUP($AJ$17,Sheet1!V14:Y14,3,0),0) -> 0 | AK27: =+IFERROR(VLOOKUP($AK$17,Sheet1!Z14:AB14,3,0),0) -> 0 | AL27: =+IFERROR(VLOOKUP($AL$17,Sheet1!AD14:AG14,3,0),0) -> 0 | AM27: =+IFERROR(VLOOKUP($AM$17,Sheet1!AD14:AG14,3,0),0) -> 0 | AN27: =+IFERROR(VLOOKUP($AN$17,Sheet1!AD14:AG14,3,0),0) -> 0 | AO27: =+IFERROR(VLOOKUP($AO$17,Sheet1!AD14:AG14,3,0),0) -> 0 | AP27: =+IFERROR(VLOOKUP($AP$17,Sheet1!AD14:AG14,3,0),0) -> 0 | AQ27: =+IFERROR(VLOOKUP($AQ$17,Sheet1!AD14:AG14,3,0),0) -> 0 | AR27: 1561 | AS27: =+IFERROR(VLOOKUP($AS$17,Sheet1!AH14:AK14,3,0),0) -> 0 | AT27: =+IFERROR(VLOOKUP($AT$17,Sheet1!AH14:AK14,3,0),0) -> 0 | AU27: =+IFERROR(VLOOKUP($AU$17,Sheet1!AH14:AK14,3,0),0) -> 0 | AV27: =+IFERROR(VLOOKUP($AV$17,Sheet1!AH14:AK14,3,0),0) -> 0 | AW27: =+IFERROR(VLOOKUP($AW$17,Sheet1!AH14:AK14,3,0),0) -> 0 | AX27: =+IFERROR(VLOOKUP($AX$17,Sheet1!AH14:AK14,3,0),0) -> 0 | AY27: =+IFERROR(VLOOKUP($AY$17,Sheet1!AH14:AK14,3,0),0) -> 0 | AZ27: =+IFERROR(VLOOKUP($AZ$17,Sheet1!AH14:AK14,3,0),0) -> 0 | BA27: 7182 | BB27: =+IFERROR(VLOOKUP($BB$17,Sheet1!AH14:AK14,3,0),0) -> 0 | BC27: =+IFERROR(VLOOKUP($BC$17,Sheet1!AL14:AO14,3,0),0) -> 0 | BD27: =+IFERROR(VLOOKUP($BD$17,Sheet1!AL14:AO14,3,0),0) -> 0 | BE27: =+IFERROR(VLOOKUP($BE$17,Sheet1!AL14:AO14,3,0),0) -> 0 | BF27: 1715 | BG27: 1718 | BH27: =+IFERROR(VLOOKUP($BH$17,Sheet1!AL14:AO14,3,0),0) -> 0 | BI27: =+IFERROR(VLOOKUP($BI$17,Sheet1!AL14:AO14,3,0),0) -> 0 | BJ27: =+IFERROR(VLOOKUP($BJ$17,Sheet1!AL14:AO14,3,0),0) -> 0 | BK27: =+IFERROR(VLOOKUP($BK$17,Sheet1!AL14:AO14,3,0),0) -> 0 | BL27: =+IFERROR(VLOOKUP($BL$17,Sheet1!AL14:AO14,3,0),0) -> 0 | BM27: =+IFERROR(VLOOKUP($BM$17,Sheet1!AP14:AS14,3,0),0) -> 0 | BN27: =+IFERROR(VLOOKUP($BN$17,Sheet1!AT14:AW14,3,0),0) -> 0 | BO27: 58 | BP27: 104 | BQ27: =+IFERROR(VLOOKUP($BQ$17,Sheet1!BF14:BI14,3,0),0) -> 0 | BR27: =+IFERROR(VLOOKUP($BR$17,Sheet1!BJ14:BM14,3,0),0) -> 0 | BS27: =+IFERROR(VLOOKUP($BS$17,Sheet1!BN14:BQ14,3,0),0) -> 0 | BT27: 75 | BU27: =+IFERROR(VLOOKUP($BU$17,Sheet1!BV14:BY14,3,0),0) -> 0 | BV27: =Sheet1!E14 -> STEEL | BW27: =Sheet1!CV14 -> SP0400137 | BX27: =Sheet1!CW14 -> CORRUGATED DISPATCH STEEL DRUM 2600 X 1600 X 1600 MM | BY27: =Sheet1!CX14 -> 250 | BZ27: =Sheet1!BZ14 -> 190000 | CA27: =SUMPRODUCT($N$18:$BU$18,N27:BU27)+BZ27 -> 2732321 | CB27: =Sheet1!CB14 -> 0 | CC27: =CA27*CB27 -> 0 | CD27: 0.5 | CE27: =CA27*CD27 -> 1366160.5 | CF27: 0 | CG27: =CA27*CF27 -> 0 | CH27: =CA27+CC27+CE27+CG27 -> 4098481.5 | CI27: 0.02 | CJ27: =CH27*CI27 -> 81969.63 | CK27: 0.01 | CL27: =CH27*CK27 -> 40984.815
A28: =Sheet1!A9 -> ENQ-10773-22-23 | B28: =Sheet1!B9 -> 45135 | C28: =Sheet1!C9 -> FA1300081 | D28: =Sheet1!D9 -> 3 CORE X 300 SQ. MM. AL/ARM - WIRE (XLPE) - 33 KV | E28: =CH28+CJ28+CL28 -> 3709171.1 | F28: =ROUNDUP(M44,0) -> 140000 | G28: =E28+F28 -> 3849171.1 | H28: =Sheet1!CP9 -> 0.18 | I28: =G28*H28 -> 692850.8 | J28: =G28+I28 -> 4542021.9 | K28: 10 | L28: =Sheet1!CT9 -> KMS | M28: =J28*K28 -> 45420219 | N28: =+IFERROR(VLOOKUP($N$17,Sheet1!J9:L9,3,0),0) -> 2430 | O28: =+IFERROR(VLOOKUP($O$17,Sheet1!J9:L9,3,0),0) -> 0 | P28: =+IFERROR(VLOOKUP($P$17,Sheet1!J9:M9,3,0),0) -> 0 | Q28: =+IFERROR(VLOOKUP($Q$17,Sheet1!J9:M9,3,0),0) -> 0 | R28: =+IFERROR(VLOOKUP($R$17,Sheet1!J9:M9,3,0),0) -> 0 | S28: =+IFERROR(VLOOKUP($S$17,Sheet1!N9:Q9,3,0),0) -> 0 | T28: =+IFERROR(VLOOKUP($T$17,Sheet1!N9:Q9,3,0),0) -> 0 | U28: =+IFERROR(VLOOKUP($U$17,Sheet1!F9:I9,3,0),0) -> 0 | V28: =+IFERROR(VLOOKUP($V$17,Sheet1!F9:I9,3,0),0) -> 0 | W28: =+IFERROR(VLOOKUP($W$17,Sheet1!F9:I9,3,0),0) -> 0 | X28: =+IFERROR(VLOOKUP($X$17,Sheet1!F9:I9,3,0),0) -> 0 | Y28: 193 | Z28: =+IFERROR(VLOOKUP($Z$17,Sheet1!F9:I9,3,0),0) -> 0 | AA28: =+IFERROR(VLOOKUP($AA$17,Sheet1!F9:I9,3,0),0) -> 0 | AB28: =+IFERROR(VLOOKUP($AB$17,Sheet1!F9:I9,3,0),0) -> 0 | AC28: 495 | AD28: =+IFERROR(VLOOKUP($AD$17,Sheet1!R9:U9,2,0),0) -> 0 | AE28: 2434 | AF28: =+IFERROR(VLOOKUP($AF$17,Sheet1!V9:Y9,3,0),0) -> 0 | AG28: =+IFERROR(VLOOKUP($AG$17,Sheet1!V9:Y9,3,0),0) -> 0 | AH28: =+IFERROR(VLOOKUP($AH$17,Sheet1!V9:Y9,3,0),0) -> 0 | AI28: =+IFERROR(VLOOKUP($AI$17,Sheet1!V9:Y9,3,0),0) -> 0 | AJ28: =+IFERROR(VLOOKUP($AJ$17,Sheet1!V9:Y9,3,0),0) -> 0 | AK28: =+IFERROR(VLOOKUP($AK$17,Sheet1!Z9:AB9,3,0),0) -> 0 | AL28: =+IFERROR(VLOOKUP($AL$17,Sheet1!AD9:AG9,3,0),0) -> 0 | AM28: =+IFERROR(VLOOKUP($AM$17,Sheet1!AD9:AG9,3,0),0) -> 0 | AN28: =+IFERROR(VLOOKUP($AN$17,Sheet1!AD9:AG9,3,0),0) -> 0 | AO28: =+IFERROR(VLOOKUP($AO$17,Sheet1!AD9:AG9,3,0),0) -> 0 | AP28: =+IFERROR(VLOOKUP($AP$17,Sheet1!AD9:AG9,3,0),0) -> 0 | AQ28: =+IFERROR(VLOOKUP($AQ$17,Sheet1!AD9:AG9,3,0),0) -> 0 | AR28: 1382 | AS28: =+IFERROR(VLOOKUP($AS$17,Sheet1!AH9:AK9,3,0),0) -> 0 | AT28: =+IFERROR(VLOOKUP($AT$17,Sheet1!AH9:AK9,3,0),0) -> 0 | AU28: =+IFERROR(VLOOKUP($AU$17,Sheet1!AH9:AK9,3,0),0) -> 0 | AV28: =+IFERROR(VLOOKUP($AV$17,Sheet1!AH9:AK9,3,0),0) -> 0 | AW28: =+IFERROR(VLOOKUP($AW$17,Sheet1!AH9:AK9,3,0),0) -> 0 | AX28: =+IFERROR(VLOOKUP($AX$17,Sheet1!AH9:AK9,3,0),0) -> 0 | AY28: =+IFERROR(VLOOKUP($AY$17,Sheet1!AH9:AK9,3,0),0) -> 0 | AZ28: =+IFERROR(VLOOKUP($AZ$17,Sheet1!AH9:AK9,3,0),0) -> 0 | BA28: 6668 | BB28: =+IFERROR(VLOOKUP($BB$17,Sheet1!AH9:AK9,3,0),0) -> 0 | BC28: =+IFERROR(VLOOKUP($BC$17,Sheet1!AL9:AO9,3,0),0) -> 0 | BD28: =+IFERROR(VLOOKUP($BD$17,Sheet1!AL9:AO9,3,0),0) -> 0 | BE28: =+IFERROR(VLOOKUP($BE$17,Sheet1!AL9:AO9,3,0),0) -> 0 | BF28: 1613 | BG28: 1497 | BH28: =+IFERROR(VLOOKUP($BH$17,Sheet1!AL9:AO9,3,0),0) -> 0 | BI28: =+IFERROR(VLOOKUP($BI$17,Sheet1!AL9:AO9,3,0),0) -> 0 | BJ28: =+IFERROR(VLOOKUP($BJ$17,Sheet1!AL9:AO9,3,0),0) -> 0 | BK28: =+IFERROR(VLOOKUP($BK$17,Sheet1!AL9:AO9,3,0),0) -> 0 | BL28: =+IFERROR(VLOOKUP($BL$17,Sheet1!AL9:AO9,3,0),0) -> 0 | BM28: =+IFERROR(VLOOKUP($BM$17,Sheet1!AP9:AS9,3,0),0) -> 0 | BN28: =+IFERROR(VLOOKUP($BN$17,Sheet1!AT9:AW9,3,0),0) -> 0 | BO28: 38 | BP28: 93 | BQ28: =+IFERROR(VLOOKUP($BQ$17,Sheet1!BF9:BI9,3,0),0) -> 0 | BR28: =+IFERROR(VLOOKUP($BR$17,Sheet1!BJ9:BM9,3,0),0) -> 0 | BS28: =+IFERROR(VLOOKUP($BS$17,Sheet1!BN9:BQ9,3,0),0) -> 0 | BT28: 71 | BU28: =+IFERROR(VLOOKUP($BU$17,Sheet1!BV9:BY9,3,0),0) -> 0 | BV28: =Sheet1!E9 -> STEEL | BW28: =Sheet1!CV9 -> SP0400137 | BX28: =Sheet1!CW9 -> CORRUGATED DISPATCH STEEL DRUM 2600 X 1600 X 1600 | BY28: =Sheet1!CX9 -> 250 | BZ28: =Sheet1!BZ9 -> 190000 | CA28: =SUMPRODUCT($N$18:$BU$18,N28:BU28)+BZ28 -> 2400758 | CB28: =Sheet1!CB9 -> 0 | CC28: =CA28*CB28 -> 0 | CD28: 0.5 | CE28: =CA28*CD28 -> 1200379 | CF28: 0 | CG28: =CA28*CF28 -> 0 | CH28: =CA28+CC28+CE28+CG28 -> 3601137 | CI28: 0.02 | CJ28: =CH28*CI28 -> 72022.74 | CK28: 0.01 | CL28: =CH28*CK28 -> 36011.37
A29: =Sheet1!A2 -> ENQ-10773-22-23 | B29: =Sheet1!B2 -> 45135 | C29: =Sheet1!C2 -> FA1300200 | D29: =Sheet1!D2 -> 3 CORE X 95 SQ. MM. AL/ARM WIRE (XLPE) - 33 KV | E29: =CH29+CJ29+CL29 -> 2262621.6 | F29: =ROUNDUP(M45,0) -> #DIV/0! | G29: =E29+F29 -> #DIV/0! | H29: =Sheet1!CP2 -> 0.18 | I29: =G29*H29 -> #DIV/0! | J29: =G29+I29 -> #DIV/0! | K29: 0 | L29: =Sheet1!CT2 -> KMS | M29: =J29*K29 -> #DIV/0! | N29: =+IFERROR(VLOOKUP($N$17,Sheet1!J2:L2,3,0),0) -> 769.5 | O29: =+IFERROR(VLOOKUP($O$17,Sheet1!J2:L2,3,0),0) -> 0 | P29: =+IFERROR(VLOOKUP($P$17,Sheet1!J2:M2,3,0),0) -> 0 | Q29: =+IFERROR(VLOOKUP($Q$17,Sheet1!J2:M2,3,0),0) -> 0 | R29: =+IFERROR(VLOOKUP($R$17,Sheet1!J2:M2,3,0),0) -> 0 | S29: =+IFERROR(VLOOKUP($S$17,Sheet1!N2:Q2,3,0),0) -> 0 | T29: =+IFERROR(VLOOKUP($T$17,Sheet1!N2:Q2,3,0),0) -> 0 | U29: =+IFERROR(VLOOKUP($U$17,Sheet1!F2:I2,3,0),0) -> 0 | V29: =+IFERROR(VLOOKUP($V$17,Sheet1!F2:I2,3,0),0) -> 0 | W29: =+IFERROR(VLOOKUP($W$17,Sheet1!F2:I2,3,0),0) -> 0 | X29: =+IFERROR(VLOOKUP($X$17,Sheet1!F2:I2,3,0),0) -> 0 | Y29: 151 | Z29: =+IFERROR(VLOOKUP($Z$17,Sheet1!F2:I2,3,0),0) -> 0 | AA29: =+IFERROR(VLOOKUP($AA$17,Sheet1!F2:I2,3,0),0) -> 0 | AB29: =+IFERROR(VLOOKUP($AB$17,Sheet1!F2:I2,3,0),0) -> 0 | AC29: 345 | AD29: =+IFERROR(VLOOKUP($AD$17,Sheet1!R2:U2,2,0),0) -> 0 | AE29: 1725 | AF29: =+IFERROR(VLOOKUP($AF$17,Sheet1!V2:Y2,3,0),0) -> 0 | AG29: =+IFERROR(VLOOKUP($AG$17,Sheet1!V2:Y2,3,0),0) -> 0 | AH29: =+IFERROR(VLOOKUP($AH$17,Sheet1!V2:Y2,3,0),0) -> 0 | AI29: =+IFERROR(VLOOKUP($AI$17,Sheet1!V2:Y2,3,0),0) -> 0 | AJ29: =+IFERROR(VLOOKUP($AJ$17,Sheet1!V2:Y2,3,0),0) -> 0 | AK29: =+IFERROR(VLOOKUP($AK$17,Sheet1!Z2:AB2,3,0),0) -> 0 | AL29: =+IFERROR(VLOOKUP($AL$17,Sheet1!AD2:AG2,3,0),0) -> 0 | AM29: =+IFERROR(VLOOKUP($AM$17,Sheet1!AD2:AG2,3,0),0) -> 0 | AN29: =+IFERROR(VLOOKUP($AN$17,Sheet1!AD2:AG2,3,0),0) -> 0 | AO29: =+IFERROR(VLOOKUP($AO$17,Sheet1!AD2:AG2,3,0),0) -> 0 | AP29: =+IFERROR(VLOOKUP($AP$17,Sheet1!AD2:AG2,3,0),0) -> 0 | AQ29: =+IFERROR(VLOOKUP($AQ$17,Sheet1!AD2:AG2,3,0),0) -> 0 | AR29: 914 | AS29: =+IFERROR(VLOOKUP($AS$17,Sheet1!AH2:AK2,3,0),0) -> 0 | AT29: =+IFERROR(VLOOKUP($AT$17,Sheet1!AH2:AK2,3,0),0) -> 0 | AU29: =+IFERROR(VLOOKUP($AU$17,Sheet1!AH2:AK2,3,0),0) -> 0 | AV29: =+IFERROR(VLOOKUP($AV$17,Sheet1!AH2:AK2,3,0),0) -> 0 | AW29: =+IFERROR(VLOOKUP($AW$17,Sheet1!AH2:AK2,3,0),0) -> 0 | AX29: =+IFERROR(VLOOKUP($AX$17,Sheet1!AH2:AK2,3,0),0) -> 0 | AY29: =+IFERROR(VLOOKUP($AY$17,Sheet1!AH2:AK2,3,0),0) -> 0 | AZ29: =+IFERROR(VLOOKUP($AZ$17,Sheet1!AH2:AK2,3,0),0) -> 0 | BA29: 4135 | BB29: =+IFERROR(VLOOKUP($BB$17,Sheet1!AH2:AK2,3,0),0) -> 0 | BC29: =+IFERROR(VLOOKUP($BC$17,Sheet1!AL2:AO2,3,0),0) -> 0 | BD29: =+IFERROR(VLOOKUP($BD$17,Sheet1!AL2:AO2,3,0),0) -> 0 | BE29: =+IFERROR(VLOOKUP($BE$17,Sheet1!AL2:AO2,3,0),0) -> 0 | BF29: 1282 | BG29: 917 | BH29: =+IFERROR(VLOOKUP($BH$17,Sheet1!AL2:AO2,3,0),0) -> 0 | BI29: =+IFERROR(VLOOKUP($BI$17,Sheet1!AL2:AO2,3,0),0) -> 0 | BJ29: =+IFERROR(VLOOKUP($BJ$17,Sheet1!AL2:AO2,3,0),0) -> 0 | BK29: =+IFERROR(VLOOKUP($BK$17,Sheet1!AL2:AO2,3,0),0) -> 0 | BL29: =+IFERROR(VLOOKUP($BL$17,Sheet1!AL2:AO2,3,0),0) -> 0 | BM29: =+IFERROR(VLOOKUP($BM$17,Sheet1!AP2:AS2,3,0),0) -> 0 | BN29: =+IFERROR(VLOOKUP($BN$17,Sheet1!AT2:AW2,3,0),0) -> 0 | BO29: 15 | BP29: 66 | BQ29: =+IFERROR(VLOOKUP($BQ$17,Sheet1!BF2:BI2,3,0),0) -> 0 | BR29: =+IFERROR(VLOOKUP($BR$17,Sheet1!BJ2:BM2,3,0),0) -> 0 | BS29: =+IFERROR(VLOOKUP($BS$17,Sheet1!BN2:BQ2,3,0),0) -> 0 | BT29: 56 | BU29: =+IFERROR(VLOOKUP($BU$17,Sheet1!BV2:BY2,3,0),0) -> 0 | BV29: =Sheet1!E2 -> STEEL | BW29: =Sheet1!CV2 -> SP0400136 | BX29: =Sheet1!CW2 -> CORRUGATED DISPATCH STEEL DRUM 2200 X 1300 X 1200 MM | BY29: =Sheet1!CX2 -> 250 | BZ29: =Sheet1!BZ2 -> 147200 | CA29: =SUMPRODUCT($N$18:$BU$18,N29:BU29)+BZ29 -> 1464480 | CB29: =Sheet1!CB2 -> 0 | CC29: =CA29*CB29 -> 0 | CD29: 0.5 | CE29: =CA29*CD29 -> 732240 | CF29: 0 | CG29: =CA29*CF29 -> 0 | CH29: =CA29+CC29+CE29+CG29 -> 2196720 | CI29: 0.02 | CJ29: =CH29*CI29 -> 43934.4 | CK29: 0.01 | CL29: =CH29*CK29 -> 21967.2
A30: =Sheet1!A12 -> ENQ-10773-22-23 | B30: =Sheet1!B12 -> 45135 | C30: =Sheet1!C12 -> FA1300027 | D30: =Sheet1!D12 -> 1 CORE X 630 SQ. MM. AL/ARM (XLPE) - 33 KV | E30: =CH30+CJ30+CL30 -> 1563059.5 | F30: =ROUNDUP(M46,0) -> #DIV/0! | G30: =E30+F30 -> #DIV/0! | H30: =Sheet1!CP12 -> 0.18 | I30: =G30*H30 -> #DIV/0! | J30: =G30+I30 -> #DIV/0! | K30: 0 | L30: =Sheet1!CT12 -> KMS | M30: =J30*K30 -> #DIV/0! | N30: =+IFERROR(VLOOKUP($N$17,Sheet1!J12:L12,3,0),0) -> 1701 | O30: =+IFERROR(VLOOKUP($O$17,Sheet1!J12:L12,3,0),0) -> 0 | P30: =+IFERROR(VLOOKUP($P$17,Sheet1!J12:M12,3,0),0) -> 0 | Q30: =+IFERROR(VLOOKUP($Q$17,Sheet1!J12:M12,3,0),0) -> 0 | R30: =+IFERROR(VLOOKUP($R$17,Sheet1!J12:M12,3,0),0) -> 0 | S30: =+IFERROR(VLOOKUP($S$17,Sheet1!N12:Q12,3,0),0) -> 0 | T30: =+IFERROR(VLOOKUP($T$17,Sheet1!N12:Q12,3,0),0) -> 0 | U30: =+IFERROR(VLOOKUP($U$17,Sheet1!F12:I12,3,0),0) -> 0 | V30: =+IFERROR(VLOOKUP($V$17,Sheet1!F12:I12,3,0),0) -> 0 | W30: =+IFERROR(VLOOKUP($W$17,Sheet1!F12:I12,3,0),0) -> 0 | X30: =+IFERROR(VLOOKUP($X$17,Sheet1!F12:I12,3,0),0) -> 0 | Y30: 79 | Z30: =+IFERROR(VLOOKUP($Z$17,Sheet1!F12:I12,3,0),0) -> 0 | AA30: =+IFERROR(VLOOKUP($AA$17,Sheet1!F12:I12,3,0),0) -> 0 | AB30: =+IFERROR(VLOOKUP($AB$17,Sheet1!F12:I12,3,0),0) -> 0 | AC30: 218 | AD30: =+IFERROR(VLOOKUP($AD$17,Sheet1!R12:U12,2,0),0) -> 0 | AE30: 1055 | AF30: =+IFERROR(VLOOKUP($AF$17,Sheet1!V12:Y12,3,0),0) -> 0 | AG30: =+IFERROR(VLOOKUP($AG$17,Sheet1!V12:Y12,3,0),0) -> 0 | AH30: =+IFERROR(VLOOKUP($AH$17,Sheet1!V12:Y12,3,0),0) -> 0 | AI30: =+IFERROR(VLOOKUP($AI$17,Sheet1!V12:Y12,3,0),0) -> 0 | AJ30: =+IFERROR(VLOOKUP($AJ$17,Sheet1!V12:Y12,3,0),0) -> 0 | AK30: 18 | AL30: =+IFERROR(VLOOKUP($AL$17,Sheet1!AD12:AG12,3,0),0) -> 0 | AM30: =+IFERROR(VLOOKUP($AM$17,Sheet1!AD12:AG12,3,0),0) -> 0 | AN30: =+IFERROR(VLOOKUP($AN$17,Sheet1!AD12:AG12,3,0),0) -> 0 | AO30: =+IFERROR(VLOOKUP($AO$17,Sheet1!AD12:AG12,3,0),0) -> 0 | AP30: =+IFERROR(VLOOKUP($AP$17,Sheet1!AD12:AG12,3,0),0) -> 0 | AQ30: 200 | AR30: =+IFERROR(VLOOKUP($AR$17,Sheet1!AD12:AG12,3,0),0) -> 0 | AS30: =+IFERROR(VLOOKUP($AS$17,Sheet1!AH12:AK12,3,0),0) -> 0 | AT30: =+IFERROR(VLOOKUP($AT$17,Sheet1!AH12:AK12,3,0),0) -> 0 | AU30: =+IFERROR(VLOOKUP($AU$17,Sheet1!AH12:AK12,3,0),0) -> 0 | AV30: 828 | AW30: =+IFERROR(VLOOKUP($AW$17,Sheet1!AH12:AK12,3,0),0) -> 0 | AX30: =+IFERROR(VLOOKUP($AX$17,Sheet1!AH12:AK12,3,0),0) -> 0 | AY30: =+IFERROR(VLOOKUP($AY$17,Sheet1!AH12:AK12,3,0),0) -> 0 | AZ30: =+IFERROR(VLOOKUP($AZ$17,Sheet1!AH12:AK12,3,0),0) -> 0 | BA30: =+IFERROR(VLOOKUP($BA$17,Sheet1!AH12:AK12,3,0),0) -> 0 | BB30: =+IFERROR(VLOOKUP($BB$17,Sheet1!AH12:AK12,3,0),0) -> 0 | BC30: =+IFERROR(VLOOKUP($BC$17,Sheet1!AL12:AO12,3,0),0) -> 0 | BD30: =+IFERROR(VLOOKUP($BD$17,Sheet1!AL12:AO12,3,0),0) -> 0 | BE30: =+IFERROR(VLOOKUP($BE$17,Sheet1!AL12:AO12,3,0),0) -> 0 | BF30: 760 | BG30: =+IFERROR(VLOOKUP($BG$17,Sheet1!AL12:AO12,3,0),0) -> 0 | BH30: =+IFERROR(VLOOKUP($BH$17,Sheet1!AL12:AO12,3,0),0) -> 0 | BI30: =+IFERROR(VLOOKUP($BI$17,Sheet1!AL12:AO12,3,0),0) -> 0 | BJ30: =+IFERROR(VLOOKUP($BJ$17,Sheet1!AL12:AO12,3,0),0) -> 0 | BK30: =+IFERROR(VLOOKUP($BK$17,Sheet1!AL12:AO12,3,0),0) -> 0 | BL30: =+IFERROR(VLOOKUP($BL$17,Sheet1!AL12:AO12,3,0),0) -> 0 | BM30: =+IFERROR(VLOOKUP($BM$17,Sheet1!AP12:AS12,3,0),0) -> 0 | BN30: =+IFERROR(VLOOKUP($BN$17,Sheet1!AT12:AW12,3,0),0) -> 0 | BO30: 26 | BP30: 41 | BQ30: =+IFERROR(VLOOKUP($BQ$17,Sheet1!BF12:BI12,3,0),0) -> 0 | BR30: =+IFERROR(VLOOKUP($BR$17,Sheet1!BJ12:BM12,3,0),0) -> 0 | BS30: =+IFERROR(VLOOKUP($BS$17,Sheet1!BN12:BQ12,3,0),0) -> 0 | BT30: 42 | BU30: =+IFERROR(VLOOKUP($BU$17,Sheet1!BV12:BY12,3,0),0) -> 0 | BV30: =Sheet1!E12 -> STEEL | BW30: =Sheet1!CV12 -> SP0400123 | BX30: =Sheet1!CW12 -> CORRUGATED DISPATCH STEEL DRUM 2000 X 1000 X 1200 MM | BY30: =Sheet1!CX12 -> 500 | BZ30: =Sheet1!BZ12 -> 53200 | CA30: =SUMPRODUCT($N$18:$BU$18,N30:BU30)+BZ30 -> 1011689 | CB30: =Sheet1!CB12 -> 0 | CC30: =CA30*CB30 -> 0 | CD30: 0.5 | CE30: =CA30*CD30 -> 505844.5 | CF30: 0 | CG30: =CA30*CF30 -> 0 | CH30: =CA30+CC30+CE30+CG30 -> 1517533.5 | CI30: 0.02 | CJ30: =CH30*CI30 -> 30350.67 | CK30: 0.01 | CL30: =CH30*CK30 -> 15175.335
A31: =Sheet1!A10 -> ENQ-10773-22-23 | B31: =Sheet1!B10 -> 45135 | C31: =Sheet1!C10 -> FA1300018 | D31: =Sheet1!D10 -> 1 CORE X 400 SQ. MM. AL/ARM (XLPE) - 33 KV | E31: =CH31+CJ31+CL31 -> 1212522.2 | F31: =ROUNDUP(M47,0) -> #DIV/0! | G31: =E31+F31 -> #DIV/0! | H31: =Sheet1!CP10 -> 0.18 | I31: =G31*H31 -> #DIV/0! | J31: =G31+I31 -> #DIV/0! | K31: 0 | L31: =Sheet1!CT10 -> KMS | M31: =J31*K31 -> #DIV/0! | N31: 1081 | O31: =+IFERROR(VLOOKUP($O$17,Sheet1!J10:L10,3,0),0) -> 0 | P31: =+IFERROR(VLOOKUP($P$17,Sheet1!J10:M10,3,0),0) -> 0 | Q31: =+IFERROR(VLOOKUP($Q$17,Sheet1!J10:M10,3,0),0) -> 0 | R31: =+IFERROR(VLOOKUP($R$17,Sheet1!J10:M10,3,0),0) -> 0 | S31: =+IFERROR(VLOOKUP($S$17,Sheet1!N10:Q10,3,0),0) -> 0 | T31: =+IFERROR(VLOOKUP($T$17,Sheet1!N10:Q10,3,0),0) -> 0 | U31: =+IFERROR(VLOOKUP($U$17,Sheet1!F10:I10,3,0),0) -> 0 | V31: =+IFERROR(VLOOKUP($V$17,Sheet1!F10:I10,3,0),0) -> 0 | W31: =+IFERROR(VLOOKUP($W$17,Sheet1!F10:I10,3,0),0) -> 0 | X31: =+IFERROR(VLOOKUP($X$17,Sheet1!F10:I10,3,0),0) -> 0 | Y31: 70 | Z31: =+IFERROR(VLOOKUP($Z$17,Sheet1!F10:I10,3,0),0) -> 0 | AA31: =+IFERROR(VLOOKUP($AA$17,Sheet1!F10:I10,3,0),0) -> 0 | AB31: =+IFERROR(VLOOKUP($AB$17,Sheet1!F10:I10,3,0),0) -> 0 | AC31: 171 | AD31: =+IFERROR(VLOOKUP($AD$17,Sheet1!R10:U10,2,0),0) -> 0 | AE31: 885 | AF31: =+IFERROR(VLOOKUP($AF$17,Sheet1!V10:Y10,3,0),0) -> 0 | AG31: =+IFERROR(VLOOKUP($AG$17,Sheet1!V10:Y10,3,0),0) -> 0 | AH31: =+IFERROR(VLOOKUP($AH$17,Sheet1!V10:Y10,3,0),0) -> 0 | AI31: =+IFERROR(VLOOKUP($AI$17,Sheet1!V10:Y10,3,0),0) -> 0 | AJ31: =+IFERROR(VLOOKUP($AJ$17,Sheet1!V10:Y10,3,0),0) -> 0 | AK31: 16 | AL31: =+IFERROR(VLOOKUP($AL$17,Sheet1!AD10:AG10,3,0),0) -> 0 | AM31: =+IFERROR(VLOOKUP($AM$17,Sheet1!AD10:AG10,3,0),0) -> 0 | AN31: =+IFERROR(VLOOKUP($AN$17,Sheet1!AD10:AG10,3,0),0) -> 0 | AO31: =+IFERROR(VLOOKUP($AO$17,Sheet1!AD10:AG10,3,0),0) -> 0 | AP31: =+IFERROR(VLOOKUP($AP$17,Sheet1!AD10:AG10,3,0),0) -> 0 | AQ31: 151 | AR31: =+IFERROR(VLOOKUP($AR$17,Sheet1!AD10:AG10,3,0),0) -> 0 | AS31: =+IFERROR(VLOOKUP($AS$17,Sheet1!AH10:AK10,3,0),0) -> 0 | AT31: =+IFERROR(VLOOKUP($AT$17,Sheet1!AH10:AK10,3,0),0) -> 0 | AU31: =+IFERROR(VLOOKUP($AU$17,Sheet1!AH10:AK10,3,0),0) -> 0 | AV31: 731 | AW31: =+IFERROR(VLOOKUP($AW$17,Sheet1!AH10:AK10,3,0),0) -> 0 | AX31: =+IFERROR(VLOOKUP($AX$17,Sheet1!AH10:AK10,3,0),0) -> 0 | AY31: =+IFERROR(VLOOKUP($AY$17,Sheet1!AH10:AK10,3,0),0) -> 0 | AZ31: =+IFERROR(VLOOKUP($AZ$17,Sheet1!AH10:AK10,3,0),0) -> 0 | BA31: =+IFERROR(VLOOKUP($BA$17,Sheet1!AH10:AK10,3,0),0) -> 0 | BB31: =+IFERROR(VLOOKUP($BB$17,Sheet1!AH10:AK10,3,0),0) -> 0 | BC31: =+IFERROR(VLOOKUP($BC$17,Sheet1!AL10:AO10,3,0),0) -> 0 | BD31: =+IFERROR(VLOOKUP($BD$17,Sheet1!AL10:AO10,3,0),0) -> 0 | BE31: =+IFERROR(VLOOKUP($BE$17,Sheet1!AL10:AO10,3,0),0) -> 0 | BF31: 580 | BG31: =+IFERROR(VLOOKUP($BG$17,Sheet1!AL10:AO10,3,0),0) -> 0 | BH31: =+IFERROR(VLOOKUP($BH$17,Sheet1!AL10:AO10,3,0),0) -> 0 | BI31: =+IFERROR(VLOOKUP($BI$17,Sheet1!AL10:AO10,3,0),0) -> 0 | BJ31: =+IFERROR(VLOOKUP($BJ$17,Sheet1!AL10:AO10,3,0),0) -> 0 | BK31: =+IFERROR(VLOOKUP($BK$17,Sheet1!AL10:AO10,3,0),0) -> 0 | BL31: =+IFERROR(VLOOKUP($BL$17,Sheet1!AL10:AO10,3,0),0) -> 0 | BM31: =+IFERROR(VLOOKUP($BM$17,Sheet1!AP10:AS10,3,0),0) -> 0 | BN31: =+IFERROR(VLOOKUP($BN$17,Sheet1!AT10:AW10,3,0),0) -> 0 | BO31: 19 | BP31: 35 | BQ31: =+IFERROR(VLOOKUP($BQ$17,Sheet1!BF10:BI10,3,0),0) -> 0 | BR31: =+IFERROR(VLOOKUP($BR$17,Sheet1!BJ10:BM10,3,0),0) -> 0 | BS31: =+IFERROR(VLOOKUP($BS$17,Sheet1!BN10:BQ10,3,0),0) -> 0 | BT31: 36 | BU31: =+IFERROR(VLOOKUP($BU$17,Sheet1!BV10:BY10,3,0),0) -> 0 | BV31: =Sheet1!E10 -> STEEL | BW31: =Sheet1!CV10 -> SP0400112 | BX31: =Sheet1!CW10 -> CORRUGATED DISPATCH STEEL DRUM 2000 X 1000 X 1000 MM | BY31: =Sheet1!CX10 -> 500 | BZ31: =Sheet1!BZ10 -> 53200 | CA31: =SUMPRODUCT($N$18:$BU$18,N31:BU31)+BZ31 -> 784804 | CB31: =Sheet1!CB10 -> 0 | CC31: =CA31*CB31 -> 0 | CD31: 0.5 | CE31: =CA31*CD31 -> 392402 | CF31: 0 | CG31: =CA31*CF31 -> 0 | CH31: =CA31+CC31+CE31+CG31 -> 1177206 | CI31: 0.02 | CJ31: =CH31*CI31 -> 23544.12 | CK31: 0.01 | CL31: =CH31*CK31 -> 11772.06
A32: =Sheet1!A7 -> ENQ-10773-22-23 | B32: =Sheet1!B7 -> 45135 | C32: =Sheet1!C7 -> FA1300019 | D32: =Sheet1!D7 -> 1 CORE X 300 SQ. MM. AL/ARM (XLPE) - 33 KV | E32: =CH32+CJ32+CL32 -> 1056143.5 | F32: =ROUNDUP(M48,0) -> #DIV/0! | G32: =E32+F32 -> #DIV/0! | H32: =Sheet1!CP7 -> 0.18 | I32: =G32*H32 -> #DIV/0! | J32: =G32+I32 -> #DIV/0! | K32: 0 | L32: =Sheet1!CT7 -> KMS | M32: =J32*K32 -> #DIV/0! | N32: =+IFERROR(VLOOKUP($N$17,Sheet1!J7:L7,3,0),0) -> 810 | O32: =+IFERROR(VLOOKUP($O$17,Sheet1!J7:L7,3,0),0) -> 0 | P32: =+IFERROR(VLOOKUP($P$17,Sheet1!J7:M7,3,0),0) -> 0 | Q32: =+IFERROR(VLOOKUP($Q$17,Sheet1!J7:M7,3,0),0) -> 0 | R32: =+IFERROR(VLOOKUP($R$17,Sheet1!J7:M7,3,0),0) -> 0 | S32: =+IFERROR(VLOOKUP($S$17,Sheet1!N7:Q7,3,0),0) -> 0 | T32: =+IFERROR(VLOOKUP($T$17,Sheet1!N7:Q7,3,0),0) -> 0 | U32: =+IFERROR(VLOOKUP($U$17,Sheet1!F7:I7,3,0),0) -> 0 | V32: =+IFERROR(VLOOKUP($V$17,Sheet1!F7:I7,3,0),0) -> 0 | W32: =+IFERROR(VLOOKUP($W$17,Sheet1!F7:I7,3,0),0) -> 0 | X32: =+IFERROR(VLOOKUP($X$17,Sheet1!F7:I7,3,0),0) -> 0 | Y32: 65 | Z32: =+IFERROR(VLOOKUP($Z$17,Sheet1!F7:I7,3,0),0) -> 0 | AA32: =+IFERROR(VLOOKUP($AA$17,Sheet1!F7:I7,3,0),0) -> 0 | AB32: =+IFERROR(VLOOKUP($AB$17,Sheet1!F7:I7,3,0),0) -> 0 | AC32: 164 | AD32: =+IFERROR(VLOOKUP($AD$17,Sheet1!R7:U7,2,0),0) -> 0 | AE32: 808 | AF32: =+IFERROR(VLOOKUP($AF$17,Sheet1!V7:Y7,3,0),0) -> 0 | AG32: =+IFERROR(VLOOKUP($AG$17,Sheet1!V7:Y7,3,0),0) -> 0 | AH32: =+IFERROR(VLOOKUP($AH$17,Sheet1!V7:Y7,3,0),0) -> 0 | AI32: =+IFERROR(VLOOKUP($AI$17,Sheet1!V7:Y7,3,0),0) -> 0 | AJ32: =+IFERROR(VLOOKUP($AJ$17,Sheet1!V7:Y7,3,0),0) -> 0 | AK32: 12 | AL32: =+IFERROR(VLOOKUP($AL$17,Sheet1!AD7:AG7,3,0),0) -> 0 | AM32: =+IFERROR(VLOOKUP($AM$17,Sheet1!AD7:AG7,3,0),0) -> 0 | AN32: =+IFERROR(VLOOKUP($AN$17,Sheet1!AD7:AG7,3,0),0) -> 0 | AO32: =+IFERROR(VLOOKUP($AO$17,Sheet1!AD7:AG7,3,0),0) -> 0 | AP32: =+IFERROR(VLOOKUP($AP$17,Sheet1!AD7:AG7,3,0),0) -> 0 | AQ32: 144 | AR32: =+IFERROR(VLOOKUP($AR$17,Sheet1!AD7:AG7,3,0),0) -> 0 | AS32: =+IFERROR(VLOOKUP($AS$17,Sheet1!AH7:AK7,3,0),0) -> 0 | AT32: =+IFERROR(VLOOKUP($AT$17,Sheet1!AH7:AK7,3,0),0) -> 0 | AU32: =+IFERROR(VLOOKUP($AU$17,Sheet1!AH7:AK7,3,0),0) -> 0 | AV32: 676 | AW32: =+IFERROR(VLOOKUP($AW$17,Sheet1!AH7:AK7,3,0),0) -> 0 | AX32: =+IFERROR(VLOOKUP($AX$17,Sheet1!AH7:AK7,3,0),0) -> 0 | AY32: =+IFERROR(VLOOKUP($AY$17,Sheet1!AH7:AK7,3,0),0) -> 0 | AZ32: =+IFERROR(VLOOKUP($AZ$17,Sheet1!AH7:AK7,3,0),0) -> 0 | BA32: =+IFERROR(VLOOKUP($BA$17,Sheet1!AH7:AK7,3,0),0) -> 0 | BB32: =+IFERROR(VLOOKUP($BB$17,Sheet1!AH7:AK7,3,0),0) -> 0 | BC32: =+IFERROR(VLOOKUP($BC$17,Sheet1!AL7:AO7,3,0),0) -> 0 | BD32: =+IFERROR(VLOOKUP($BD$17,Sheet1!AL7:AO7,3,0),0) -> 0 | BE32: =+IFERROR(VLOOKUP($BE$17,Sheet1!AL7:AO7,3,0),0) -> 0 | BF32: 556 | BG32: =+IFERROR(VLOOKUP($BG$17,Sheet1!AL7:AO7,3,0),0) -> 0 | BH32: =+IFERROR(VLOOKUP($BH$17,Sheet1!AL7:AO7,3,0),0) -> 0 | BI32: =+IFERROR(VLOOKUP($BI$17,Sheet1!AL7:AO7,3,0),0) -> 0 | BJ32: =+IFERROR(VLOOKUP($BJ$17,Sheet1!AL7:AO7,3,0),0) -> 0 | BK32: =+IFERROR(VLOOKUP($BK$17,Sheet1!AL7:AO7,3,0),0) -> 0 | BL32: =+IFERROR(VLOOKUP($BL$17,Sheet1!AL7:AO7,3,0),0) -> 0 | BM32: =+IFERROR(VLOOKUP($BM$17,Sheet1!AP7:AS7,3,0),0) -> 0 | BN32: =+IFERROR(VLOOKUP($BN$17,Sheet1!AT7:AW7,3,0),0) -> 0 | BO32: 13 | BP32: 32 | BQ32: =+IFERROR(VLOOKUP($BQ$17,Sheet1!BF7:BI7,3,0),0) -> 0 | BR32: =+IFERROR(VLOOKUP($BR$17,Sheet1!BJ7:BM7,3,0),0) -> 0 | BS32: =+IFERROR(VLOOKUP($BS$17,Sheet1!BN7:BQ7,3,0),0) -> 0 | BT32: 35 | BU32: =+IFERROR(VLOOKUP($BU$17,Sheet1!BV7:BY7,3,0),0) -> 0 | BV32: =Sheet1!E7 -> STEEL | BW32: =Sheet1!CV7 -> SP0400110 | BX32: =Sheet1!CW7 -> CORRUGATED DISPATCH STEEL DRUM 1600 X 900 X 1000 MM | BY32: =Sheet1!CX7 -> 500 | BZ32: =Sheet1!BZ7 -> 47500 | CA32: =SUMPRODUCT($N$18:$BU$18,N32:BU32)+BZ32 -> 683588 | CB32: =Sheet1!CB7 -> 0 | CC32: =CA32*CB32 -> 0 | CD32: 0.5 | CE32: =CA32*CD32 -> 341794 | CF32: 0 | CG32: =CA32*CF32 -> 0 | CH32: =CA32+CC32+CE32+CG32 -> 1025382 | CI32: 0.02 | CJ32: =CH32*CI32 -> 20507.64 | CK32: 0.01 | CL32: =CH32*CK32 -> 10253.82
E34: Order Quantity | F34: Stnd Length | G34: Truck type | H34: Fare of one truck | I34: No of Drum in one truck | J34: Total length in one Truck | K34: No of Truck | L34: Total Freight | M34: Freight per KM
D35: =D19 -> 3 CORE X 400 SQ. MM. AL/ARM - WIRE (XLPE) - 11 KV | E35: =K19 -> 12.6 | F35: =BY19/1000 -> 0.25 | G35: TRAILER 28 MT | H35: 70000 | I35: 3 | J35: =F35*I35 -> 0.75 | K35: =ROUNDUP((E35/J35),0) -> 17 | L35: =M35*E35 -> 1190000 | M35: =(H35*K35)/E35 -> 94444.444
D36: =D20 -> 3 CORE X 300 SQ. MM. AL/ARM - WIRE (XLPE) - 11 KV | E36: =K20 -> 38.4 | F36: =BY20/1000 -> 0.25 | G36: TRAILER 28 MT | H36: 70000 | I36: 4 | J36: =F36*I36 -> 1 | K36: =ROUNDUP((E36/J36),0) -> 39 | L36: =M36*E36 -> 2730000 | M36: =(H36*K36)/E36 -> 71093.75
D37: =D21 -> 3 CORE X 150 SQ. MM. AL/ARM - WIRE (XLPE) - 11 KV | E37: =K21 -> 0 | F37: =BY21/1000 -> 0.25 | G37: TRAILER 28 MT | H37: 70000 | I37: 5 | J37: =F37*I37 -> 1.25 | K37: =ROUNDUP((E37/J37),0) -> 0 | L37: =M37*E37 -> #DIV/0! | M37: =(H37*K37)/E37 -> #DIV/0!
D38: =D22 -> 3 CORE X 120 SQ. MM. AL/ARM - WIRE (XLPE) - 11 KV | E38: =K22 -> 1 | F38: =BY22/1000 -> 0.25 | G38: TRAILER 28 MT | H38: 70000 | I38: 5 | J38: =F38*I38 -> 1.25 | K38: =ROUNDUP((E38/J38),0) -> 1 | L38: =M38*E38 -> 70000 | M38: =(H38*K38)/E38 -> 70000
D39: =D23 -> 3 CORE X 95 SQ. MM. AL/ARM - WIRE (XLPE) - 11 KV | E39: =K23 -> 0 | F39: =BY23/1000 -> 0.25 | G39: TRAILER 28 MT | H39: 70000 | I39: 5 | J39: =F39*I39 -> 1.25 | K39: =ROUNDUP((E39/J39),0) -> 0 | L39: =M39*E39 -> #DIV/0! | M39: =(H39*K39)/E39 -> #DIV/0!
D40: =D24 -> 1 CORE X 1000 SQ. MM. AL/ARM (XLPE) - 11 KV | E40: =K24 -> 0 | F40: =BY24/1000 -> 0.5 | G40: TRAILER 28 MT | H40: 70000 | I40: 4 | J40: =F40*I40 -> 2 | K40: =ROUNDUP((E40/J40),0) -> 0 | L40: =M40*E40 -> #DIV/0! | M40: =(H40*K40)/E40 -> #DIV/0!
D41: =D25 -> 1 CORE X 630 SQ. MM. AL/ARM (XLPE) - 11 KV | E41: =K25 -> 0 | F41: =BY25/1000 -> 0.5 | G41: TRAILER 28 MT | H41: 70000 | I41: 5 | J41: =F41*I41 -> 2.5 | K41: =ROUNDUP((E41/J41),0) -> 0 | L41: =M41*E41 -> #DIV/0! | M41: =(H41*K41)/E41 -> #DIV/0!
D42: =D26 -> 1 CORE X 400 SQ. MM. AL/ARM (XLPE) - 11 KV | E42: =K26 -> 0 | F42: =BY26/1000 -> 0.5 | G42: TRAILER 28 MT | H42: 70000 | I42: 6 | J42: =F42*I42 -> 3 | K42: =ROUNDUP((E42/J42),0) -> 0 | L42: =M42*E42 -> #DIV/0! | M42: =(H42*K42)/E42 -> #DIV/0!
D43: =D27 -> 3 CORE X 400 SQ. MM AL/ARM - WIRE (XLPE) - 33 KV | E43: =K27 -> 36 | F43: =BY27/1000 -> 0.25 | G43: TRAILER 28 MT | H43: 70000 | I43: 2 | J43: =F43*I43 -> 0.5 | K43: =ROUNDUP((E43/J43),0) -> 72 | L43: =M43*E43 -> 5040000 | M43: =(H43*K43)/E43 -> 140000
D44: =D28 -> 3 CORE X 300 SQ. MM. AL/ARM - WIRE (XLPE) - 33 KV | E44: =K28 -> 10 | F44: =BY28/1000 -> 0.25 | G44: TRAILER 28 MT | H44: 70000 | I44: 2 | J44: =F44*I44 -> 0.5 | K44: =ROUNDUP((E44/J44),0) -> 20 | L44: =M44*E44 -> 1400000 | M44: =(H44*K44)/E44 -> 140000
D45: =D29 -> 3 CORE X 95 SQ. MM. AL/ARM WIRE (XLPE) - 33 KV | E45: =K29 -> 0 | F45: =BY29/1000 -> 0.25 | G45: TRAILER 28 MT | H45: 70000 | I45: 4 | J45: =F45*I45 -> 1 | K45: =ROUNDUP((E45/J45),0) -> 0 | L45: =M45*E45 -> #DIV/0! | M45: =(H45*K45)/E45 -> #DIV/0!
D46: =D30 -> 1 CORE X 630 SQ. MM. AL/ARM (XLPE) - 33 KV | E46: =K30 -> 0 | F46: =BY30/1000 -> 0.5 | G46: TRAILER 28 MT | H46: 70000 | I46: 4 | J46: =F46*I46 -> 2 | K46: =ROUNDUP((E46/J46),0) -> 0 | L46: =M46*E46 -> #DIV/0! | M46: =(H46*K46)/E46 -> #DIV/0!
... D48: =D32 -> 1 CORE X 300 SQ. MM. AL/ARM (XLPE) - 33 KV | E48: =K32 -> 0 | F48: =BY32/1000 -> 0.5 | G48: TRAILER 28 MT | H48: 70000 | I48: 6 | J48: =F48*I48 -> 3 | K48: =ROUNDUP((E48/J48),0) -> 0 | L48: =M48*E48 -> #DIV/0! | M48: =(H48*K48)/E48 -> #DIV/0!
A51: DOCKET NO. | B51: Base Date | C51: ITEM CODE | D51: PROPOSE ERP ITEM NAME | E51: EX-WORKS (PER MTR) | F51: FREIGHT PER MTR | G51: PRICE INCLUDING FREIGHT (PER MTR) | H51: GST % | I51: GST VALUE | J51: PRICE INCLUDING GST & FREIGHT (PER MTR) | K51: QTY | L51: Unit | M51: TOTAL PRICE OF FULL QTY (INCLUDING FRIGHT & GST)
A53: =A19 -> ENQ-10773-22-23 | B53: =B19 -> 45135 | C53: =C19 -> FA1300083 | D53: =D19 -> 3 CORE X 400 SQ. MM. AL/ARM - WIRE (XLPE) - 11 KV | E53: =ROUNDUP(E19/1000,2) -> 3241.8 | F53: =ROUNDUP(F19/1000,2) -> 94.45 | G53: =E53+F53 -> 3336.25 | H53: =H19 -> 0.18 | I53: =ROUND(G53*H53,2) -> 600.53 | J53: =ROUND(G53+I53,2) -> 3936.78 | K53: =K19*1000 -> 12600 | L53: MTR | M53: =J53*K53 -> 49603428
A54: =A20 -> ENQ-10773-22-23 | B54: =B20 -> 45135 | C54: =C20 -> FA1300091 | D54: =D20 -> 3 CORE X 300 SQ. MM. AL/ARM - WIRE (XLPE) - 11 KV | E54: =ROUNDUP(E20/1000,2) -> 2598.3 | F54: =ROUNDUP(F20/1000,2) -> 71.1 | G54: =E54+F54 -> 2669.4 | H54: =H20 -> 0.18 | I54: =ROUND(G54*H54,2) -> 480.49 | J54: =ROUND(G54+I54,2) -> 3149.89 | K54: =K20*1000 -> 38400 | L54: MTR | M54: =J54*K54 -> 120955776
A55: =A21 -> ENQ-10773-22-23 | B55: =B21 -> 45135 | C55: =C21 -> FA1300176 | D55: =D21 -> 3 CORE X 150 SQ. MM. AL/ARM - WIRE (XLPE) - 11 KV | E55: =ROUNDUP(E21/1000,2) -> 1671.59 | F55: =ROUNDUP(F21/1000,2) -> #DIV/0! | G55: =E55+F55 -> #DIV/0! | H55: =H21 -> 0.18 | I55: =ROUND(G55*H55,2) -> #DIV/0! | J55: =ROUND(G55+I55,2) -> #DIV/0! | K55: =K21*1000 -> 0 | L55: MTR | M55: =J55*K55 -> #DIV/0!
A56: =A22 -> ENQ-10773-22-23 | B56: =B22 -> 45135 | C56: =C22 -> FA1300197 | D56: =D22 -> 3 CORE X 120 SQ. MM. AL/ARM - WIRE (XLPE) - 11 KV | E56: =ROUNDUP(E22/1000,2) -> 1462.05 | F56: =ROUNDUP(F22/1000,2) -> 70 | G56: =E56+F56 -> 1532.05 | H56: =H22 -> 0.18 | I56: =ROUND(G56*H56,2) -> 275.77 | J56: =ROUND(G56+I56,2) -> 1807.82 | K56: =K22*1000 -> 1000 | L56: MTR | M56: =J56*K56 -> 1807820
A57: =A23 -> ENQ-10773-22-23 | B57: =B23 -> 45135 | C57: =C23 -> FA1300098 | D57: =D23 -> 3 CORE X 95 SQ. MM. AL/ARM - WIRE (XLPE) - 11 KV | E57: =ROUNDUP(E23/1000,2) -> 1316.67 | F57: =ROUNDUP(F23/1000,2) -> #DIV/0! | G57: =E57+F57 -> #DIV/0! | H57: =H23 -> 0.18 | I57: =ROUND(G57*H57,2) -> #DIV/0! | J57: =ROUND(G57+I57,2) -> #DIV/0! | K57: =K23*1000 -> 0 | L57: MTR | M57: =J57*K57 -> #DIV/0!
A58: =A24 -> ENQ-10773-22-23 | B58: =B24 -> 45135 | C58: =C24 -> FA1300066 | D58: =D24 -> 1 CORE X 1000 SQ. MM. AL/ARM (XLPE) - 11 KV | E58: =ROUNDUP(E24/1000,2) -> 1852.71 | F58: =ROUNDUP(F24/1000,2) -> #DIV/0! | G58: =E58+F58 -> #DIV/0! | H58: =H24 -> 0.18 | I58: =ROUND(G58*H58,2) -> #DIV/0! | J58: =ROUND(G58+I58,2) -> #DIV/0! | K58: =K24*1000 -> 0 | L58: MTR | M58: =J58*K58 -> #DIV/0!
A59: =A25 -> ENQ-10773-22-23 | B59: =B25 -> 45135 | C59: =C25 -> FA1300016 | D59: =D25 -> 1 CORE X 630 SQ. MM. AL/ARM (XLPE) - 11 KV | E59: =ROUNDUP(E25/1000,2) -> 1201.88 | F59: =ROUNDUP(F25/1000,2) -> #DIV/0! | G59: =E59+F59 -> #DIV/0! | H59: =H25 -> 0.18 | I59: =ROUND(G59*H59,2) -> #DIV/0! | J59: =ROUND(G59+I59,2) -> #DIV/0! | K59: =K25*1000 -> 0 | L59: MTR | M59: =J59*K59 -> #DIV/0!
A60: =A26 -> ENQ-10773-22-23 | B60: =B26 -> 45135 | C60: =C26 -> FA1300047 | D60: =D26 -> 1 CORE X 400 SQ. MM. AL/ARM (XLPE) - 11 KV | E60: =ROUNDUP(E26/1000,2) -> 911.87 | F60: =ROUNDUP(F26/1000,2) -> #DIV/0! | G60: =E60+F60 -> #DIV/0! | H60: =H26 -> 0.18 | I60: =ROUND(G60*H60,2) -> #DIV/0! | J60: =ROUND(G60+I60,2) -> #DIV/0! | K60: =K26*1000 -> 0 | L60: MTR | M60: =J60*K60 -> #DIV/0!
A61: =A27 -> ENQ-10773-22-23 | B61: =B27 -> 45135 | C61: =C27 -> FA1300080 | D61: =D27 -> 3 CORE X 400 SQ. MM AL/ARM - WIRE (XLPE) - 33 KV | E61: =ROUNDUP(E27/1000,2) -> 4221.44 | F61: =ROUNDUP(F27/1000,2) -> 140 | G61: =E61+F61 -> 4361.44 | H61: =H27 -> 0.18 | I61: =ROUND(G61*H61,2) -> 785.06 | J61: =ROUND(G61+I61,2) -> 5146.5 | K61: =K27*1000 -> 36000 | L61: MTR | M61: =J61*K61 -> 185274000
A62: =A28 -> ENQ-10773-22-23 | B62: =B28 -> 45135 | C62: =C28 -> FA1300081 | D62: =D28 -> 3 CORE X 300 SQ. MM. AL/ARM - WIRE (XLPE) - 33 KV | E62: =ROUNDUP(E28/1000,2) -> 3709.18 | F62: =ROUNDUP(F28/1000,2) -> 140 | G62: =E62+F62 -> 3849.18 | H62: =H28 -> 0.18 | I62: =ROUND(G62*H62,2) -> 692.85 | J62: =ROUND(G62+I62,2) -> 4542.03 | K62: =K28*1000 -> 10000 | L62: MTR | M62: =J62*K62 -> 45420300
A63: =A29 -> ENQ-10773-22-23 | B63: =B29 -> 45135 | C63: =C29 -> FA1300200 | D63: =D29 -> 3 CORE X 95 SQ. MM. AL/ARM WIRE (XLPE) - 33 KV | E63: =ROUNDUP(E29/1000,2) -> 2262.63 | F63: =ROUNDUP(F29/1000,2) -> #DIV/0! | G63: =E63+F63 -> #DIV/0! | H63: =H29 -> 0.18 | I63: =ROUND(G63*H63,2) -> #DIV/0! | J63: =ROUND(G63+I63,2) -> #DIV/0! | K63: =K29*1000 -> 0 | L63: MTR | M63: =J63*K63 -> #DIV/0!
A64: =A30 -> ENQ-10773-22-23 | B64: =B30 -> 45135 | C64: =C30 -> FA1300027 | D64: =D30 -> 1 CORE X 630 SQ. MM. AL/ARM (XLPE) - 33 KV | E64: =ROUNDUP(E30/1000,2) -> 1563.06 | F64: =ROUNDUP(F30/1000,2) -> #DIV/0! | G64: =E64+F64 -> #DIV/0! | H64: =H30 -> 0.18 | I64: =ROUND(G64*H64,2) -> #DIV/0! | J64: =ROUND(G64+I64,2) -> #DIV/0! | K64: =K30*1000 -> 0 | L64: MTR | M64: =J64*K64 -> #DIV/0!
... A66: =A32 -> ENQ-10773-22-23 | B66: =B32 -> 45135 | C66: =C32 -> FA1300019 | D66: =D32 -> 1 CORE X 300 SQ. MM. AL/ARM (XLPE) - 33 KV | E66: =ROUNDUP(E32/1000,2) -> 1056.15 | F66: =ROUNDUP(F32/1000,2) -> #DIV/0! | G66: =E66+F66 -> #DIV/0! | H66: =H32 -> 0.18 | I66: =ROUND(G66*H66,2) -> #DIV/0! | J66: =ROUND(G66+I66,2) -> #DIV/0! | K66: =K32*1000 -> 0 | L66: MTR | M66: =J66*K66 -> #DIV/0!

Sheet TPWODL
A2: TP Central Odisha Distribution Limited
A4: TENDER SPECIFICATION NO () | B4: TPCODL/CCG/23-24/013.
A5: TENDER DESCRIPTION () | B5: Rate Contract for Supply of 11 KV & 33 KV HT XLPE Cable of various sizes for TPCODL, TPWODL & TPNODL.
A6: Last Date & Time of Submission () | B6: 31st July 2023 [17:00 Hrs.]
A7: REVERSE AUCTION | B7: CCG reserves the right to conduct the reverse auction (instead of public opening of price bids) for the products/ services being asked for in the tender. The terms and conditions for such reverse auction events shall be as per the Acceptance Form attached as Annexure VI of this document. The bidders along with the tender document shall mandatorily submit a duly signed copy of the Acceptance Form attached as Annexure VI as a token of acceptance for the same.
A8: Price () | B8: Price will be fixed and firm during the contractual period.
A9: Validity () | B9: Bids shall remain valid for 180 days from the due date of submission of the bid. Notwithstanding clause above, the Odisha DISCOMs may solicit the Bidder’s consent to an extension of the Period of Bid Validity. The request and responses thereto shall be made in writing.
A10: Delivery Period () | B10: Delivery period shall be 60 days from date of receipt of release order / CAT-A issuance, whichever is later.
A11: Payment Terms () | B11: TPCODL will make 100% payment within 30 days of submission of the Bill/Invoice complete in all respects and along with all the requisite documents mentioned above, subject to condition that Associate has furnished the requisite Security-cum-Performance Guarantee as stipulated in the contract.
A12: Standard length () | B12: The cable shall be supplied in continuous standard length of 250 (3 cores) & 500 (Single core) running meters with +/- 5% tolerance.
A13: Packing () | B13: Steel drums shall be provided. Drum shall be free from sharp edges and visual defect. Stencil plate on one flange side of the drum and laminated paper sheet on other side flange of drum.
A14: Technical Specification
N16: =Sheet1!J1 -> Conductor | S16: AL ALLOY | U16: Insulation Screening (Metallic) | AC16: Insulation Screening (Non-Metallic) | AE16: Insulation | AK16: POLY TAPE | AL16: Inner Sheath | AS16: Armouring | BC16: Outer Sheath | BF16: Consider Rs. 1 extra for colour of o/sh-FRLSH | BM16: FILLER | BN16: GREASE | BO16: Water swellable Tape | BP16: Semi conducting Water Swellable tape | BQ16: SEMICON TAPE | BR16: GLASS FIBER TAPE | BS16: COPPER WIRE 0.8 MM | BT16: RUBBERIZED COTTON TAPE | BU16: Water Tight Compound | BZ16: DRUM COST PER KM | CA16: TOTAL RM COST | CB16: EXTRA CONSUMPTION | CC16: EXTRA CONSUMPTION VALUE
A17: DOCKET NO. | B17: =Sheet1!B1 -> Base Date | C17: ITEM CODE | D17: PROPOSE ERP ITEM NAME | E17: EX-WORKS (PER KM) | F17: FREIGHT PER KM | G17: PRICE INCLUDING FREIGHT (PER KM) | H17: GST % | I17: GST VALUE | J17: PRICE INCLUDING GST & FREIGHT (PER KM) | K17: QTY | L17: Unit | M17: TOTAL PRICE OF FULL QTY (INCLUDING FRIGHT & GST) | N17: Alumimium | O17: Alumimium ALLOY | P17: Copper | Q17: Flexible Copper | R17: Galvanized steel wire | S17: Alumimium | T17: Alumimium ALLOY | U17: Coper tape - 0.1 mm | V17: Copper Tape - 0.03 mm | W17: Copper Tape - 0.035 mm | X17: Copper Tape - 0.04 mm | Y17: Copper Tape - 0.045 mm | Z17: Copper Tape - 0.050 mm | AA17: Copper Tape - 0.060 mm | AB17: Copper Tape - 0.075 mm(DOUBLE) | AC17: Extruded semiconductive | AD17: Extruded Semiconductive(Stripable) | AE17: HT-XLPE | AF17: LT-XLPE | AG17: TR XLPE | AH17: Type A PVC | AI17: Type C PVC (HR) | AJ17: XLPE | AK17: POLY TAPE | AL17: FR PVC Type ST-1 | AM17: FR PVC Type ST-2 | AN17: FRLSH PVC Type ST-2 | AO17: PVC Type ST-1 | AP17: PVC Type ST-1-PRESSURE EXTRUDED | AQ17: PVC Type ST-2 | AR17: PVC Type ST-2-PRESSURE EXTRUDED | AS17: ACSR CORE WIRE | AT17: ACSR DOG STEEL WIRE | AU17: Aluminium Flat Strip | AV17: Aluminium Round Wire | AW17: Double Steel Tape | AX17: Galvanised Steel Flat Strip | AY17: Galvanised Steel Flat Strip (Double) | AZ17: Galvanised Steel Flat Strip-B | BA17: Galvanised Steel Round Wire | BB17: Galvanised Steel Round Wire (Double) | BC17: FR PVC Type ST-1 | BD17: FR PVC Type ST-2 | BE17: FRLSH PVC Type ST-1 | BF17: FRLSH PVC Type ST-2 | BG17: Polypropylene Filler | BH17: PE, ST-7 | BI17: PVC Type ST-1 | BJ17: PVC Type ST-2 | BK17: PVC Type ST-2-PRESSURE EXTRUDED | BL17: UV & Track Resistant XLPE | BM17: FILLER | BN17: Grease | BO17: NCWBT | BP17: Semi conducting Water Swellable tape | BQ17: SEMICON TAPE | BR17: GLASS FIBER TAPE | BS17: COPPER WIRE 0.8 MM | BT17: RUBBERIZED COTTON TAPE | BU17: Water Tight Compound | BV17: =Sheet1!E1 -> PROPOSE DRUM TYPE | BW17: =Sheet1!CV1 -> DRUM CODE | BX17: =Sheet1!CW1 -> DRUM SIZE (FxbXtx Ft) | BY17: =Sheet1!CX1 -> PARTY STANDARD LENGTH (MTR) | CD17: MFG% | CE17: MFG VALUE | CF17: PROF% | CG17: PROFIT VALUE | CH17: 1ST EX-WORKS | CI17: Intt % | CJ17: INTT VALUE | CK17: insp% | CL17: INSP VALUE
N18: 216 | O18: =+IFERROR(VLOOKUP($O$17,Sheet1!J:L,2,0),0) -> 0 | P18: =+IFERROR(VLOOKUP($P$17,Sheet1!J:M,2,0),0) -> 0 | Q18: =+IFERROR(VLOOKUP($Q$17,Sheet1!J:M,2,0),0) -> 0 | R18: =+IFERROR(VLOOKUP($R$17,Sheet1!J:M,2,0),0) -> 0 | S18: =+IFERROR(VLOOKUP($S$17,Sheet1!N:Q,2,0),0) -> 0 | T18: =+IFERROR(VLOOKUP($T$17,Sheet1!N:O,2,0),0) -> 0 | U18: =+IFERROR(VLOOKUP($U$17,Sheet1!F:I,2,0),0) -> 0 | V18: =+IFERROR(VLOOKUP($V$17,Sheet1!F:I,2,0),0) -> 0 | W18: =+IFERROR(VLOOKUP($W$17,Sheet1!F:I,2,0),0) -> 0 | X18: =+IFERROR(VLOOKUP($X$17,Sheet1!F:I,2,0),0) -> 0 | Y18: 878 | Z18: =+IFERROR(VLOOKUP($Z$17,Sheet1!F:I,2,0),0) -> 0 | AA18: =+IFERROR(VLOOKUP($AA$17,Sheet1!F:I,2,0),0) -> 0 | AB18: =+IFERROR(VLOOKUP($AB$17,Sheet1!F:I,2,0),0) -> 0 | AC18: 195 | AD18: =+IFERROR(VLOOKUP($AD$17,Sheet1!R:U,2,0),0) -> 0 | AE18: 155 | AF18: =+IFERROR(VLOOKUP($AF$17,Sheet1!V:Y,2,0),0) -> 0 | AG18: =+IFERROR(VLOOKUP($AG$17,Sheet1!V:Y,2,0),0) -> 0 | AH18: =+IFERROR(VLOOKUP($AH$17,Sheet1!V:Y,2,0),0) -> 0 | AI18: =+IFERROR(VLOOKUP($AI$17,Sheet1!V:Y,2,0),0) -> 0 | AJ18: =+IFERROR(VLOOKUP($AJ$17,Sheet1!V:Y,2,0),0) -> 0 | AK18: 123 | AL18: =+IFERROR(VLOOKUP($AL$17,Sheet1!AD2:AG840,2,0),0) -> 0 | AM18: =+IFERROR(VLOOKUP($AM$17,Sheet1!AD2:AG840,2,0),0) -> 0 | AN18: =+IFERROR(VLOOKUP($AN$17,Sheet1!AD2:AG840,2,0),0) -> 0 | AO18: =+IFERROR(VLOOKUP($AO$17,Sheet1!AD2:AG840,2,0),0) -> 0 | AP18: =+IFERROR(VLOOKUP($AP$17,Sheet1!AD2:AG840,2,0),0) -> 0 | AQ18: 61 | AR18: 88 | AS18: =+IFERROR(VLOOKUP($AS$17,Sheet1!AH2:AK840,2,0),0) -> 0 | AT18: =+IFERROR(VLOOKUP($AT$17,Sheet1!AH2:AK840,2,0),0) -> 0 | AU18: =+IFERROR(VLOOKUP($AU$17,Sheet1!AH2:AK840,2,0),0) -> 0 | AV18: 219 | AW18: =+IFERROR(VLOOKUP($AW$17,Sheet1!AH2:AK840,2,0),0) -> 0 | AX18: =+IFERROR(VLOOKUP($AX$17,Sheet1!AH2:AK840,2,0),0) -> 0 | AY18: =+IFERROR(VLOOKUP($AY$17,Sheet1!AH2:AK840,2,0),0) -> 0 | AZ18: =+IFERROR(VLOOKUP($AZ$17,Sheet1!AH2:AK840,2,0),0) -> 0 | BA18: 87 | BB18: =+IFERROR(VLOOKUP($BB$17,Sheet1!AH2:AK840,2,0),0) -> 0 | BC18: =+IFERROR(VLOOKUP($BC$17,Sheet1!AL2:AO840,2,0),0) -> 0 | BD18: =+IFERROR(VLOOKUP($BD$17,Sheet1!AL2:AO840,2,0),0) -> 0 | BE18: =+IFERROR(VLOOKUP($BE$17,Sheet1!AL2:AO840,2,0),0) -> 0 | BF18: 94 | BG18: 65 | BH18: =+IFERROR(VLOOKUP($BH$17,Sheet1!AL2:AO840,2,0),0) -> 0 | BI18: =+IFERROR(VLOOKUP($BI$17,Sheet1!AL2:AO840,2,0),0) -> 0 | BJ18: =+IFERROR(VLOOKUP($BJ$17,Sheet1!AL2:AO840,2,0),0) -> 0 | BK18: =+IFERROR(VLOOKUP($BK$17,Sheet1!AL2:AO840,2,0),0) -> 0 | BL18: =+IFERROR(VLOOKUP($BL$17,Sheet1!AL2:AO840,2,0),0) -> 0 | BN18: =+IFERROR(VLOOKUP($BN$17,Sheet1!AT2:AW840,2,0),0) -> 0 | BO18: 350 | BP18: =+IFERROR(VLOOKUP($BP$17,Sheet1!BB2:BE840,2,0),0) -> 510 | BQ18: =+IFERROR(VLOOKUP($BQ$17,Sheet1!BF2:BI840,2,0),0) -> 0 | BR18: =+IFERROR(VLOOKUP($BR$17,Sheet1!BJ2:BM840,2,0),0) -> 0 | BS18: =+IFERROR(VLOOKUP($BS$17,Sheet1!BN2:BQ840,2,0),0) -> 0 | BT18: =+IFERROR(VLOOKUP($BT$17,Sheet1!BR2:BU840,2,0),0) -> 440 | BU18: =+IFERROR(VLOOKUP($BU$17,Sheet1!BV2:BY840,2,0),0) -> 0
A19: =Sheet1!A13 -> ENQ-10773-22-23 | B19: =Sheet1!B13 -> 45135 | C19: =Sheet1!C13 -> FA1300083 | D19: =Sheet1!D13 -> 3 CORE X 400 SQ. MM. AL/ARM - WIRE (XLPE) - 11 KV | E19: =CH19+CJ19+CL19 -> 3241791.6 | F19: =ROUNDUP(M35,0) -> #DIV/0! | G19: =E19+F19 -> #DIV/0! | H19: =Sheet1!CP13 -> 0.18 | I19: =G19*H19 -> #DIV/0! | J19: =G19+I19 -> #DIV/0! | K19: 0 | L19: =Sheet1!CT13 -> KMS | M19: =J19*K19 -> #DIV/0! | N19: 3243 | O19: =+IFERROR(VLOOKUP($O$17,Sheet1!J13:L13,3,0),0) -> 0 | P19: =+IFERROR(VLOOKUP($P$17,Sheet1!J13:M13,3,0),0) -> 0 | Q19: =+IFERROR(VLOOKUP($Q$17,Sheet1!J13:M13,3,0),0) -> 0 | R19: =+IFERROR(VLOOKUP($R$17,Sheet1!J13:M13,3,0),0) -> 0 | S19: =+IFERROR(VLOOKUP($S$17,Sheet1!N13:Q13,3,0),0) -> 0 | T19: =+IFERROR(VLOOKUP($T$17,Sheet1!N13:Q13,3,0),0) -> 0 | U19: =+IFERROR(VLOOKUP($U$17,Sheet1!F13:I13,3,0),0) -> 0 | V19: =+IFERROR(VLOOKUP($V$17,Sheet1!F13:I13,3,0),0) -> 0 | W19: =+IFERROR(VLOOKUP($W$17,Sheet1!F13:I13,3,0),0) -> 0 | X19: =+IFERROR(VLOOKUP($X$17,Sheet1!F13:I13,3,0),0) -> 0 | Y19: 158 | Z19: =+IFERROR(VLOOKUP($Z$17,Sheet1!F13:I13,3,0),0) -> 0 | AA19: =+IFERROR(VLOOKUP($AA$17,Sheet1!F13:I13,3,0),0) -> 0 | AB19: =+IFERROR(VLOOKUP($AB$17,Sheet1!F13:I13,3,0),0) -> 0 | AC19: 414 | AD19: =+IFERROR(VLOOKUP($AD$17,Sheet1!R13:U13,2,0),0) -> 0 | AE19: 938 | AF19: =+IFERROR(VLOOKUP($AF$17,Sheet1!V13:Y13,3,0),0) -> 0 | AG19: =+IFERROR(VLOOKUP($AG$17,Sheet1!V13:Y13,3,0),0) -> 0 | AH19: =+IFERROR(VLOOKUP($AH$17,Sheet1!V13:Y13,3,0),0) -> 0 | AI19: =+IFERROR(VLOOKUP($AI$17,Sheet1!V13:Y13,3,0),0) -> 0 | AJ19: =+IFERROR(VLOOKUP($AJ$17,Sheet1!V13:Y13,3,0),0) -> 0 | AK19: =+IFERROR(VLOOKUP($AK$17,Sheet1!Z13:AB13,3,0),0) -> 0 | AL19: =+IFERROR(VLOOKUP($AL$17,Sheet1!AD13:AG13,3,0),0) -> 0 | AM19: =+IFERROR(VLOOKUP($AM$17,Sheet1!AD13:AG13,3,0),0) -> 0 | AN19: =+IFERROR(VLOOKUP($AN$17,Sheet1!AD13:AG13,3,0),0) -> 0 | AO19: =+IFERROR(VLOOKUP($AO$17,Sheet1!AD13:AG13,3,0),0) -> 0 | AP19: =+IFERROR(VLOOKUP($AP$17,Sheet1!AD13:AG13,3,0),0) -> 0 | AQ19: =+IFERROR(VLOOKUP($AQ$17,Sheet1!AD13:AG13,3,0),0) -> 0 | AR19: 980 | AS19: =+IFERROR(VLOOKUP($AS$17,Sheet1!AH13:AK13,3,0),0) -> 0 | AT19: =+IFERROR(VLOOKUP($AT$17,Sheet1!AH13:AK13,3,0),0) -> 0 | AU19: =+IFERROR(VLOOKUP($AU$17,Sheet1!AH13:AK13,3,0),0) -> 0 | AV19: =+IFERROR(VLOOKUP($AV$17,Sheet1!AH13:AK13,3,0),0) -> 0 | AW19: =+IFERROR(VLOOKUP($AW$17,Sheet1!AH13:AK13,3,0),0) -> 0 | AX19: =+IFERROR(VLOOKUP($AX$17,Sheet1!AH13:AK13,3,0),0) -> 0 | AY19: =+IFERROR(VLOOKUP($AY$17,Sheet1!AH13:AK13,3,0),0) -> 0 | AZ19: =+IFERROR(VLOOKUP($AZ$17,Sheet1!AH13:AK13,3,0),0) -> 0 | BA19: 5540 | BB19: =+IFERROR(VLOOKUP($BB$17,Sheet1!AH13:AK13,3,0),0) -> 0 | BC19: =+IFERROR(VLOOKUP($BC$17,Sheet1!AL13:AO13,3,0),0) -> 0 | BD19: =+IFERROR(VLOOKUP($BD$17,Sheet1!AL13:AO13,3,0),0) -> 0 | BE19: =+IFERROR(VLOOKUP($BE$17,Sheet1!AL13:AO13,3,0),0) -> 0 | BF19: 1355 | BG19: 997 | BH19: =+IFERROR(VLOOKUP($BH$17,Sheet1!AL13:AO13,3,0),0) -> 0 | BI19: =+IFERROR(VLOOKUP($BI$17,Sheet1!AL13:AO13,3,0),0) -> 0 | BJ19: =+IFERROR(VLOOKUP($BJ$17,Sheet1!AL13:AO13,3,0),0) -> 0 | BK19: =+IFERROR(VLOOKUP($BK$17,Sheet1!AL13:AO13,3,0),0) -> 0 | BL19: =+IFERROR(VLOOKUP($BL$17,Sheet1!AL13:AO13,3,0),0) -> 0 | BM19: =+IFERROR(VLOOKUP($BM$17,Sheet1!AP13:AS13,3,0),0) -> 0 | BN19: =+IFERROR(VLOOKUP($BN$17,Sheet1!AT13:AW13,3,0),0) -> 0 | BO19: 58 | BP19: 86 | BQ19: =+IFERROR(VLOOKUP($BQ$17,Sheet1!BF13:BI13,3,0),0) -> 0 | BR19: =+IFERROR(VLOOKUP($BR$17,Sheet1!BJ13:BM13,3,0),0) -> 0 | BS19: =+IFERROR(VLOOKUP($BS$17,Sheet1!BN13:BQ13,3,0),0) -> 0 | BT19: 59 | BU19: =+IFERROR(VLOOKUP($BU$17,Sheet1!BV13:BY13,3,0),0) -> 0 | BV19: =Sheet1!E13 -> STEEL | BW19: =Sheet1!CV13 -> SP0400105 | BX19: =Sheet1!CW13 -> CORRUGATED DISPATCH STEEL DRUM 2500 X 1500 X 1400 | BY19: =Sheet1!CX13 -> 250 | BZ19: =Sheet1!BZ13 -> 182400 | CA19: =SUMPRODUCT($N$18:$BU$18,N19:BU19)+BZ19 -> 2098247 | CB19: =Sheet1!CB13 -> 0 | CC19: =CA19*CB19 -> 0 | CD19: 0.5 | CE19: =CA19*CD19 -> 1049123.5 | CF19: 0 | CG19: =CA19*CF19 -> 0 | CH19: =CA19+CC19+CE19+CG19 -> 3147370.5 | CI19: 0.02 | CJ19: =CH19*CI19 -> 62947.41 | CK19: 0.01 | CL19: =CH19*CK19 -> 31473.705
A20: =Sheet1!A15 -> ENQ-10773-22-23 | B20: =Sheet1!B15 -> 45135 | C20: =Sheet1!C15 -> FA1300091 | D20: =Sheet1!D15 -> 3 CORE X 300 SQ. MM. AL/ARM - WIRE (XLPE) - 11 KV | E20: =CH20+CJ20+CL20 -> 2598299.1 | F20: =ROUNDUP(M36,0) -> 65000 | G20: =E20+F20 -> 2663299.1 | H20: =Sheet1!CP15 -> 0.18 | I20: =G20*H20 -> 479393.84 | J20: =G20+I20 -> 3142693 | K20: 114 | L20: =Sheet1!CT15 -> KMS | M20: =J20*K20 -> 3.58267e+08 | N20: =+IFERROR(VLOOKUP($N$17,Sheet1!J15:L15,3,0),0) -> 2430 | O20: =+IFERROR(VLOOKUP($O$17,Sheet1!J15:L15,3,0),0) -> 0 | P20: =+IFERROR(VLOOKUP($P$17,Sheet1!J15:M15,3,0),0) -> 0 | Q20: =+IFERROR(VLOOKUP($Q$17,Sheet1!J15:M15,3,0),0) -> 0 | R20: =+IFERROR(VLOOKUP($R$17,Sheet1!J15:M15,3,0),0) -> 0 | S20: =+IFERROR(VLOOKUP($S$17,Sheet1!N15:Q15,3,0),0) -> 0 | T20: =+IFERROR(VLOOKUP($T$17,Sheet1!N15:Q15,3,0),0) -> 0 | U20: =+IFERROR(VLOOKUP($U$17,Sheet1!F15:I15,3,0),0) -> 0 | V20: =+IFERROR(VLOOKUP($V$17,Sheet1!F15:I15,3,0),0) -> 0 | W20: =+IFERROR(VLOOKUP($W$17,Sheet1!F15:I15,3,0),0) -> 0 | X20: =+IFERROR(VLOOKUP($X$17,Sheet1!F15:I15,3,0),0) -> 0 | Y20: 144 | Z20: =+IFERROR(VLOOKUP($Z$17,Sheet1!F15:I15,3,0),0) -> 0 | AA20: =+IFERROR(VLOOKUP($AA$17,Sheet1!F15:I15,3,0),0) -> 0 | AB20: =+IFERROR(VLOOKUP($AB$17,Sheet1!F15:I15,3,0),0) -> 0 | AC20: 370 | AD20: =+IFERROR(VLOOKUP($AD$17,Sheet1!R15:U15,2,0),0) -> 0 | AE20: 838 | AF20: =+IFERROR(VLOOKUP($AF$17,Sheet1!V15:Y15,3,0),0) -> 0 | AG20: =+IFERROR(VLOOKUP($AG$17,Sheet1!V15:Y15,3,0),0) -> 0 | AH20: =+IFERROR(VLOOKUP($AH$17,Sheet1!V15:Y15,3,0),0) -> 0 | AI20: =+IFERROR(VLOOKUP($AI$17,Sheet1!V15:Y15,3,0),0) -> 0 | AJ20: =+IFERROR(VLOOKUP($AJ$17,Sheet1!V15:Y15,3,0),0) -> 0 | AK20: =+IFERROR(VLOOKUP($AK$17,Sheet1!Z15:AB15,3,0),0) -> 0 | AL20: =+IFERROR(VLOOKUP($AL$17,Sheet1!AD15:AG15,3,0),0) -> 0 | AM20: =+IFERROR(VLOOKUP($AM$17,Sheet1!AD15:AG15,3,0),0) -> 0 | AN20: =+IFERROR(VLOOKUP($AN$17,Sheet1!AD15:AG15,3,0),0) -> 0 | AO20: =+IFERROR(VLOOKUP($AO$17,Sheet1!AD15:AG15,3,0),0) -> 0 | AP20: =+IFERROR(VLOOKUP($AP$17,Sheet1!AD15:AG15,3,0),0) -> 0 | AQ20: =+IFERROR(VLOOKUP($AQ$17,Sheet1!AD15:AG15,3,0),0) -> 0 | AR20: 840 | AS20: =+IFERROR(VLOOKUP($AS$17,Sheet1!AH15:AK15,3,0),0) -> 0 | AT20: =+IFERROR(VLOOKUP($AT$17,Sheet1!AH15:AK15,3,0),0) -> 0 | AU20: =+IFERROR(VLOOKUP($AU$17,Sheet1!AH15:AK15,3,0),0) -> 0 | AV20: =+IFERROR(VLOOKUP($AV$17,Sheet1!AH15:AK15,3,0),0) -> 0 | AW20: =+IFERROR(VLOOKUP($AW$17,Sheet1!AH15:AK15,3,0),0) -> 0 | AX20: =+IFERROR(VLOOKUP($AX$17,Sheet1!AH15:AK15,3,0),0) -> 0 | AY20: =+IFERROR(VLOOKUP($AY$17,Sheet1!AH15:AK15,3,0),0) -> 0 | AZ20: =+IFERROR(VLOOKUP($AZ$17,Sheet1!AH15:AK15,3,0),0) -> 0 | BA20: 3945 | BB20: =+IFERROR(VLOOKUP($BB$17,Sheet1!AH15:AK15,3,0),0) -> 0 | BC20: =+IFERROR(VLOOKUP($BC$17,Sheet1!AL15:AO15,3,0),0) -> 0 | BD20: =+IFERROR(VLOOKUP($BD$17,Sheet1!AL15:AO15,3,0),0) -> 0 | BE20: =+IFERROR(VLOOKUP($BE$17,Sheet1!AL15:AO15,3,0),0) -> 0 | BF20: 1170 | BG20: 830 | BH20: =+IFERROR(VLOOKUP($BH$17,Sheet1!AL15:AO15,3,0),0) -> 0 | BI20: =+IFERROR(VLOOKUP($BI$17,Sheet1!AL15:AO15,3,0),0) -> 0 | BJ20: =+IFERROR(VLOOKUP($BJ$17,Sheet1!AL15:AO15,3,0),0) -> 0 | BK20: =+IFERROR(VLOOKUP($BK$17,Sheet1!AL15:AO15,3,0),0) -> 0 | BL20: =+IFERROR(VLOOKUP($BL$17,Sheet1!AL15:AO15,3,0),0) -> 0 | BM20: =+IFERROR(VLOOKUP($BM$17,Sheet1!AP15:AS15,3,0),0) -> 0 | BN20: =+IFERROR(VLOOKUP($BN$17,Sheet1!AT15:AW15,3,0),0) -> 0 | BO20: 38 | BP20: 77 | BQ20: =+IFERROR(VLOOKUP($BQ$17,Sheet1!BF15:BI15,3,0),0) -> 0 | BR20: =+IFERROR(VLOOKUP($BR$17,Sheet1!BJ15:BM15,3,0),0) -> 0 | BS20: =+IFERROR(VLOOKUP($BS$17,Sheet1!BN15:BQ15,3,0),0) -> 0 | BT20: 54 | BU20: =+IFERROR(VLOOKUP($BU$17,Sheet1!BV15:BY15,3,0),0) -> 0 | BV20: =Sheet1!E15 -> STEEL | BW20: =Sheet1!CV15 -> SP0400136 | BX20: =Sheet1!CW15 -> CORRUGATED DISPATCH STEEL DRUM 2200 X 1300 X 1200 MM | BY20: =Sheet1!CX15 -> 250 | BZ20: =Sheet1!BZ15 -> 171000 | CA20: =SUMPRODUCT($N$18:$BU$18,N20:BU20)+BZ20 -> 1681747 | CB20: =Sheet1!CB15 -> 0 | CC20: =CA20*CB20 -> 0 | CD20: 0.5 | CE20: =CA20*CD20 -> 840873.5 | CF20: 0 | CG20: =CA20*CF20 -> 0 | CH20: =CA20+CC20+CE20+CG20 -> 2522620.5 | CI20: 0.02 | CJ20: =CH20*CI20 -> 50452.41 | CK20: 0.01 | CL20: =CH20*CK20 -> 25226.205
A21: =Sheet1!A3 -> ENQ-10773-22-23 | B21: =Sheet1!B3 -> 45135 | C21: =Sheet1!C3 -> FA1300176 | D21: =Sheet1!D3 -> 3 CORE X 150 SQ. MM. AL/ARM - WIRE (XLPE) - 11 KV | E21: =CH21+CJ21+CL21 -> 1671588 | F21: =ROUNDUP(M37,0) -> #DIV/0! | G21: =E21+F21 -> #DIV/0! | H21: =Sheet1!CP3 -> 0.18 | I21: =G21*H21 -> #DIV/0! | J21: =G21+I21 -> #DIV/0! | K21: 0 | L21: =Sheet1!CT3 -> KMS | M21: =J21*K21 -> #DIV/0! | N21: =+IFERROR(VLOOKUP($N$17,Sheet1!J3:L3,3,0),0) -> 1215 | O21: =+IFERROR(VLOOKUP($O$17,Sheet1!J3:L3,3,0),0) -> 0 | P21: =+IFERROR(VLOOKUP($P$17,Sheet1!J3:M3,3,0),0) -> 0 | Q21: =+IFERROR(VLOOKUP($Q$17,Sheet1!J3:M3,3,0),0) -> 0 | R21: =+IFERROR(VLOOKUP($R$17,Sheet1!J3:M3,3,0),0) -> 0 | S21: =+IFERROR(VLOOKUP($S$17,Sheet1!N3:Q3,3,0),0) -> 0 | T21: =+IFERROR(VLOOKUP($T$17,Sheet1!N3:Q3,3,0),0) -> 0 | U21: =+IFERROR(VLOOKUP($U$17,Sheet1!F3:I3,3,0),0) -> 0 | V21: =+IFERROR(VLOOKUP($V$17,Sheet1!F3:I3,3,0),0) -> 0 | W21: =+IFERROR(VLOOKUP($W$17,Sheet1!F3:I3,3,0),0) -> 0 | X21: =+IFERROR(VLOOKUP($X$17,Sheet1!F3:I3,3,0),0) -> 0 | Y21: 117 | Z21: =+IFERROR(VLOOKUP($Z$17,Sheet1!F3:I3,3,0),0) -> 0 | AA21: =+IFERROR(VLOOKUP($AA$17,Sheet1!F3:I3,3,0),0) -> 0 | AB21: =+IFERROR(VLOOKUP($AB$17,Sheet1!F3:I3,3,0),0) -> 0 | AC21: 280 | AD21: =+IFERROR(VLOOKUP($AD$17,Sheet1!R3:U3,2,0),0) -> 0 | AE21: 642 | AF21: =+IFERROR(VLOOKUP($AF$17,Sheet1!V3:Y3,3,0),0) -> 0 | AG21: =+IFERROR(VLOOKUP($AG$17,Sheet1!V3:Y3,3,0),0) -> 0 | AH21: =+IFERROR(VLOOKUP($AH$17,Sheet1!V3:Y3,3,0),0) -> 0 | AI21: =+IFERROR(VLOOKUP($AI$17,Sheet1!V3:Y3,3,0),0) -> 0 | AJ21: =+IFERROR(VLOOKUP($AJ$17,Sheet1!V3:Y3,3,0),0) -> 0 | AK21: =+IFERROR(VLOOKUP($AK$17,Sheet1!Z3:AB3,3,0),0) -> 0 | AL21: =+IFERROR(VLOOKUP($AL$17,Sheet1!AD3:AG3,3,0),0) -> 0 | AM21: =+IFERROR(VLOOKUP($AM$17,Sheet1!AD3:AG3,3,0),0) -> 0 | AN21: =+IFERROR(VLOOKUP($AN$17,Sheet1!AD3:AG3,3,0),0) -> 0 | AO21: =+IFERROR(VLOOKUP($AO$17,Sheet1!AD3:AG3,3,0),0) -> 0 | AP21: =+IFERROR(VLOOKUP($AP$17,Sheet1!AD3:AG3,3,0),0) -> 0 | AQ21: =+IFERROR(VLOOKUP($AQ$17,Sheet1!AD3:AG3,3,0),0) -> 0 | AR21: 621 | AS21: =+IFERROR(VLOOKUP($AS$17,Sheet1!AH3:AK3,3,0),0) -> 0 | AT21: =+IFERROR(VLOOKUP($AT$17,Sheet1!AH3:AK3,3,0),0) -> 0 | AU21: =+IFERROR(VLOOKUP($AU$17,Sheet1!AH3:AK3,3,0),0) -> 0 | AV21: =+IFERROR(VLOOKUP($AV$17,Sheet1!AH3:AK3,3,0),0) -> 0 | AW21: =+IFERROR(VLOOKUP($AW$17,Sheet1!AH3:AK3,3,0),0) -> 0 | AX21: =+IFERROR(VLOOKUP($AX$17,Sheet1!AH3:AK3,3,0),0) -> 0 | AY21: =+IFERROR(VLOOKUP($AY$17,Sheet1!AH3:AK3,3,0),0) -> 0 | AZ21: =+IFERROR(VLOOKUP($AZ$17,Sheet1!AH3:AK3,3,0),0) -> 0 | BA21: 2685 | BB21: =+IFERROR(VLOOKUP($BB$17,Sheet1!AH3:AK3,3,0),0) -> 0 | BC21: =+IFERROR(VLOOKUP($BC$17,Sheet1!AL3:AO3,3,0),0) -> 0 | BD21: =+IFERROR(VLOOKUP($BD$17,Sheet1!AL3:AO3,3,0),0) -> 0 | BE21: =+IFERROR(VLOOKUP($BE$17,Sheet1!AL3:AO3,3,0),0) -> 0 | BF21: 800 | BG21: 541 | BH21: =+IFERROR(VLOOKUP($BH$17,Sheet1!AL3:AO3,3,0),0) -> 0 | BI21: =+IFERROR(VLOOKUP($BI$17,Sheet1!AL3:AO3,3,0),0) -> 0 | BJ21: =+IFERROR(VLOOKUP($BJ$17,Sheet1!AL3:AO3,3,0),0) -> 0 | BK21: =+IFERROR(VLOOKUP($BK$17,Sheet1!AL3:AO3,3,0),0) -> 0 | BL21: =+IFERROR(VLOOKUP($BL$17,Sheet1!AL3:AO3,3,0),0) -> 0 | BM21: =+IFERROR(VLOOKUP($BM$17,Sheet1!AP3:AS3,3,0),0) -> 0 | BN21: =+IFERROR(VLOOKUP($BN$17,Sheet1!AT3:AW3,3,0),0) -> 0 | BO21: 18 | BP21: 59 | BQ21: =+IFERROR(VLOOKUP($BQ$17,Sheet1!BF3:BI3,3,0),0) -> 0 | BR21: =+IFERROR(VLOOKUP($BR$17,Sheet1!BJ3:BM3,3,0),0) -> 0 | BS21: =+IFERROR(VLOOKUP($BS$17,Sheet1!BN3:BQ3,3,0),0) -> 0 | BT21: 44 | BU21: =+IFERROR(VLOOKUP($BU$17,Sheet1!BV3:BY3,3,0),0) -> 0 | BV21: =Sheet1!E3 -> STEEL | BW21: =Sheet1!CV3 -> SP0400111 | BX21: =Sheet1!CW3 -> CORRUGATED DISPATCH STEEL DRUM 1900 X 1000 X 1000 MM | BY21: =Sheet1!CX3 -> 250 | BZ21: =Sheet1!BZ3 -> 108300 | CA21: =SUMPRODUCT($N$18:$BU$18,N21:BU21)+BZ21 -> 1081934 | CB21: =Sheet1!CB3 -> 0 | CC21: =CA21*CB21 -> 0 | CD21: 0.5 | CE21: =CA21*CD21 -> 540967 | CF21: 0 | CG21: =CA21*CF21 -> 0 | CH21: =CA21+CC21+CE21+CG21 -> 1622901 | CI21: 0.02 | CJ21: =CH21*CI21 -> 32458.02 | CK21: 0.01 | CL21: =CH21*CK21 -> 16229.01
A22: =Sheet1!A6 -> ENQ-10773-22-23 | B22: =Sheet1!B6 -> 45135 | C22: =Sheet1!C6 -> FA1300197 | D22: =Sheet1!D6 -> 3 CORE X 120 SQ. MM. AL/ARM - WIRE (XLPE) - 11 KV | E22: =CH22+CJ22+CL22 -> 1462048.9 | F22: =ROUNDUP(M38,0) -> #DIV/0! | G22: =E22+F22 -> #DIV/0! | H22: =Sheet1!CP6 -> 0.18 | I22: =G22*H22 -> #DIV/0! | J22: =G22+I22 -> #DIV/0! | K22: 0 | L22: =Sheet1!CT6 -> KMS | M22: =J22*K22 -> #DIV/0! | N22: =+IFERROR(VLOOKUP($N$17,Sheet1!J6:L6,3,0),0) -> 972 | O22: =+IFERROR(VLOOKUP($O$17,Sheet1!J6:L6,3,0),0) -> 0 | P22: =+IFERROR(VLOOKUP($P$17,Sheet1!J6:M6,3,0),0) -> 0 | Q22: =+IFERROR(VLOOKUP($Q$17,Sheet1!J6:M6,3,0),0) -> 0 | R22: =+IFERROR(VLOOKUP($R$17,Sheet1!J6:M6,3,0),0) -> 0 | S22: =+IFERROR(VLOOKUP($S$17,Sheet1!N6:Q6,3,0),0) -> 0 | T22: =+IFERROR(VLOOKUP($T$17,Sheet1!N6:Q6,3,0),0) -> 0 | U22: =+IFERROR(VLOOKUP($U$17,Sheet1!F6:I6,3,0),0) -> 0 | V22: =+IFERROR(VLOOKUP($V$17,Sheet1!F6:I6,3,0),0) -> 0 | W22: =+IFERROR(VLOOKUP($W$17,Sheet1!F6:I6,3,0),0) -> 0 | X22: =+IFERROR(VLOOKUP($X$17,Sheet1!F6:I6,3,0),0) -> 0 | Y22: 110 | Z22: =+IFERROR(VLOOKUP($Z$17,Sheet1!F6:I6,3,0),0) -> 0 | AA22: =+IFERROR(VLOOKUP($AA$17,Sheet1!F6:I6,3,0),0) -> 0 | AB22: =+IFERROR(VLOOKUP($AB$17,Sheet1!F6:I6,3,0),0) -> 0 | AC22: 258 | AD22: =+IFERROR(VLOOKUP($AD$17,Sheet1!R6:U6,2,0),0) -> 0 | AE22: 596 | AF22: =+IFERROR(VLOOKUP($AF$17,Sheet1!V6:Y6,3,0),0) -> 0 | AG22: =+IFERROR(VLOOKUP($AG$17,Sheet1!V6:Y6,3,0),0) -> 0 | AH22: =+IFERROR(VLOOKUP($AH$17,Sheet1!V6:Y6,3,0),0) -> 0 | AI22: =+IFERROR(VLOOKUP($AI$17,Sheet1!V6:Y6,3,0),0) -> 0 | AJ22: =+IFERROR(VLOOKUP($AJ$17,Sheet1!V6:Y6,3,0),0) -> 0 | AK22: =+IFERROR(VLOOKUP($AK$17,Sheet1!Z6:AB6,3,0),0) -> 0 | AL22: =+IFERROR(VLOOKUP($AL$17,Sheet1!AD6:AG6,3,0),0) -> 0 | AM22: =+IFERROR(VLOOKUP($AM$17,Sheet1!AD6:AG6,3,0),0) -> 0 | AN22: =+IFERROR(VLOOKUP($AN$17,Sheet1!AD6:AG6,3,0),0) -> 0 | AO22: =+IFERROR(VLOOKUP($AO$17,Sheet1!AD6:AG6,3,0),0) -> 0 | AP22: =+IFERROR(VLOOKUP($AP$17,Sheet1!AD6:AG6,3,0),0) -> 0 | AQ22: =+IFERROR(VLOOKUP($AQ$17,Sheet1!AD6:AG6,3,0),0) -> 0 | AR22: 513 | AS22: =+IFERROR(VLOOKUP($AS$17,Sheet1!AH6:AK6,3,0),0) -> 0 | AT22: =+IFERROR(VLOOKUP($AT$17,Sheet1!AH6:AK6,3,0),0) -> 0 | AU22: =+IFERROR(VLOOKUP($AU$17,Sheet1!AH6:AK6,3,0),0) -> 0 | AV22: =+IFERROR(VLOOKUP($AV$17,Sheet1!AH6:AK6,3,0),0) -> 0 | AW22: =+IFERROR(VLOOKUP($AW$17,Sheet1!AH6:AK6,3,0),0) -> 0 | AX22: =+IFERROR(VLOOKUP($AX$17,Sheet1!AH6:AK6,3,0),0) -> 0 | AY22: =+IFERROR(VLOOKUP($AY$17,Sheet1!AH6:AK6,3,0),0) -> 0 | AZ22: =+IFERROR(VLOOKUP($AZ$17,Sheet1!AH6:AK6,3,0),0) -> 0 | BA22: 2404 | BB22: =+IFERROR(VLOOKUP($BB$17,Sheet1!AH6:AK6,3,0),0) -> 0 | BC22: =+IFERROR(VLOOKUP($BC$17,Sheet1!AL6:AO6,3,0),0) -> 0 | BD22: =+IFERROR(VLOOKUP($BD$17,Sheet1!AL6:AO6,3,0),0) -> 0 | BE22: =+IFERROR(VLOOKUP($BE$17,Sheet1!AL6:AO6,3,0),0) -> 0 | BF22: 694 | BG22: 479 | BH22: =+IFERROR(VLOOKUP($BH$17,Sheet1!AL6:AO6,3,0),0) -> 0 | BI22: =+IFERROR(VLOOKUP($BI$17,Sheet1!AL6:AO6,3,0),0) -> 0 | BJ22: =+IFERROR(VLOOKUP($BJ$17,Sheet1!AL6:AO6,3,0),0) -> 0 | BK22: =+IFERROR(VLOOKUP($BK$17,Sheet1!AL6:AO6,3,0),0) -> 0 | BL22: =+IFERROR(VLOOKUP($BL$17,Sheet1!AL6:AO6,3,0),0) -> 0 | BM22: =+IFERROR(VLOOKUP($BM$17,Sheet1!AP6:AS6,3,0),0) -> 0 | BN22: =+IFERROR(VLOOKUP($BN$17,Sheet1!AT6:AW6,3,0),0) -> 0 | BO22: 16.5 | BP22: 55 | BQ22: =+IFERROR(VLOOKUP($BQ$17,Sheet1!BF6:BI6,3,0),0) -> 0 | BR22: =+IFERROR(VLOOKUP($BR$17,Sheet1!BJ6:BM6,3,0),0) -> 0 | BS22: =+IFERROR(VLOOKUP($BS$17,Sheet1!BN6:BQ6,3,0),0) -> 0 | BT22: 40 | BU22: =+IFERROR(VLOOKUP($BU$17,Sheet1!BV6:BY6,3,0),0) -> 0 | BV22: =Sheet1!E6 -> STEEL | BW22: =Sheet1!CV6 -> SP0400118 | BX22: =Sheet1!CW6 -> CORRUGATED DISPATCH STEEL DRUM 1700 X 1000 X 1200 | BY22: =Sheet1!CX6 -> 250 | BZ22: =Sheet1!BZ6 -> 95000 | CA22: =SUMPRODUCT($N$18:$BU$18,N22:BU22)+BZ22 -> 946310 | CB22: =Sheet1!CB6 -> 0 | CC22: =CA22*CB22 -> 0 | CD22: 0.5 | CE22: =CA22*CD22 -> 473155 | CF22: 0 | CG22: =CA22*CF22 -> 0 | CH22: =CA22+CC22+CE22+CG22 -> 1419465 | CI22: 0.02 | CJ22: =CH22*CI22 -> 28389.3 | CK22: 0.01 | CL22: =CH22*CK22 -> 14194.65
A23: =Sheet1!A4 -> ENQ-10773-22-23 | B23: =Sheet1!B4 -> 45135 | C23: FA1300098 | D23: 3 CORE X 95 SQ. MM. AL/ARM - WIRE (XLPE) - 11 KV | E23: =CH23+CJ23+CL23 -> 1316664.4 | F23: =ROUNDUP(M39,0) -> #DIV/0! | G23: =E23+F23 -> #DIV/0! | H23: =Sheet1!CP4 -> 0.18 | I23: =G23*H23 -> #DIV/0! | J23: =G23+I23 -> #DIV/0! | K23: 0 | L23: =Sheet1!CT4 -> KMS | M23: =J23*K23 -> #DIV/0! | N23: =+IFERROR(VLOOKUP($N$17,Sheet1!J4:L4,3,0),0) -> 769.5 | O23: =+IFERROR(VLOOKUP($O$17,Sheet1!J4:L4,3,0),0) -> 0 | P23: =+IFERROR(VLOOKUP($P$17,Sheet1!J4:M4,3,0),0) -> 0 | Q23: =+IFERROR(VLOOKUP($Q$17,Sheet1!J4:M4,3,0),0) -> 0 | R23: =+IFERROR(VLOOKUP($R$17,Sheet1!J4:M4,3,0),0) -> 0 | S23: =+IFERROR(VLOOKUP($S$17,Sheet1!N4:Q4,3,0),0) -> 0 | T23: =+IFERROR(VLOOKUP($T$17,Sheet1!N4:Q4,3,0),0) -> 0 | U23: =+IFERROR(VLOOKUP($U$17,Sheet1!F4:I4,3,0),0) -> 0 | V23: =+IFERROR(VLOOKUP($V$17,Sheet1!F4:I4,3,0),0) -> 0 | W23: =+IFERROR(VLOOKUP($W$17,Sheet1!F4:I4,3,0),0) -> 0 | X23: =+IFERROR(VLOOKUP($X$17,Sheet1!F4:I4,3,0),0) -> 0 | Y23: 102 | Z23: =+IFERROR(VLOOKUP($Z$17,Sheet1!F4:I4,3,0),0) -> 0 | AA23: =+IFERROR(VLOOKUP($AA$17,Sheet1!F4:I4,3,0),0) -> 0 | AB23: =+IFERROR(VLOOKUP($AB$17,Sheet1!F4:I4,3,0),0) -> 0 | AC23: 232 | AD23: =+IFERROR(VLOOKUP($AD$17,Sheet1!R4:U4,2,0),0) -> 0 | AE23: 544 | AF23: =+IFERROR(VLOOKUP($AF$17,Sheet1!V4:Y4,3,0),0) -> 0 | AG23: =+IFERROR(VLOOKUP($AG$17,Sheet1!V4:Y4,3,0),0) -> 0 | AH23: =+IFERROR(VLOOKUP($AH$17,Sheet1!V4:Y4,3,0),0) -> 0 | AI23: =+IFERROR(VLOOKUP($AI$17,Sheet1!V4:Y4,3,0),0) -> 0 | AJ23: =+IFERROR(VLOOKUP($AJ$17,Sheet1!V4:Y4,3,0),0) -> 0 | AK23: =+IFERROR(VLOOKUP($AK$17,Sheet1!Z4:AB4,3,0),0) -> 0 | AL23: =+IFERROR(VLOOKUP($AL$17,Sheet1!AD4:AG4,3,0),0) -> 0 | AM23: =+IFERROR(VLOOKUP($AM$17,Sheet1!AD4:AG4,3,0),0) -> 0 | AN23: =+IFERROR(VLOOKUP($AN$17,Sheet1!AD4:AG4,3,0),0) -> 0 | AO23: =+IFERROR(VLOOKUP($AO$17,Sheet1!AD4:AG4,3,0),0) -> 0 | AP23: =+IFERROR(VLOOKUP($AP$17,Sheet1!AD4:AG4,3,0),0) -> 0 | AQ23: =+IFERROR(VLOOKUP($AQ$17,Sheet1!AD4:AG4,3,0),0) -> 0 | AR23: 460 | AS23: =+IFERROR(VLOOKUP($AS$17,Sheet1!AH4:AK4,3,0),0) -> 0 | AT23: =+IFERROR(VLOOKUP($AT$17,Sheet1!AH4:AK4,3,0),0) -> 0 | AU23: =+IFERROR(VLOOKUP($AU$17,Sheet1!AH4:AK4,3,0),0) -> 0 | AV23: =+IFERROR(VLOOKUP($AV$17,Sheet1!AH4:AK4,3,0),0) -> 0 | AW23: =+IFERROR(VLOOKUP($AW$17,Sheet1!AH4:AK4,3,0),0) -> 0 | AX23: =+IFERROR(VLOOKUP($AX$17,Sheet1!AH4:AK4,3,0),0) -> 0 | AY23: =+IFERROR(VLOOKUP($AY$17,Sheet1!AH4:AK4,3,0),0) -> 0 | AZ23: =+IFERROR(VLOOKUP($AZ$17,Sheet1!AH4:AK4,3,0),0) -> 0 | BA23: 2244 | BB23: =+IFERROR(VLOOKUP($BB$17,Sheet1!AH4:AK4,3,0),0) -> 0 | BC23: =+IFERROR(VLOOKUP($BC$17,Sheet1!AL4:AO4,3,0),0) -> 0 | BD23: =+IFERROR(VLOOKUP($BD$17,Sheet1!AL4:AO4,3,0),0) -> 0 | BE23: =+IFERROR(VLOOKUP($BE$17,Sheet1!AL4:AO4,3,0),0) -> 0 | BF23: 656 | BG23: 416 | BH23: =+IFERROR(VLOOKUP($BH$17,Sheet1!AL4:AO4,3,0),0) -> 0 | BI23: =+IFERROR(VLOOKUP($BI$17,Sheet1!AL4:AO4,3,0),0) -> 0 | BJ23: =+IFERROR(VLOOKUP($BJ$17,Sheet1!AL4:AO4,3,0),0) -> 0 | BK23: =+IFERROR(VLOOKUP($BK$17,Sheet1!AL4:AO4,3,0),0) -> 0 | BL23: =+IFERROR(VLOOKUP($BL$17,Sheet1!AL4:AO4,3,0),0) -> 0 | BN23: =+IFERROR(VLOOKUP($BN$17,Sheet1!AT4:AW4,3,0),0) -> 0 | BO23: 15 | BP23: 50 | BQ23: =+IFERROR(VLOOKUP($BQ$17,Sheet1!BF4:BI4,3,0),0) -> 0 | BR23: =+IFERROR(VLOOKUP($BR$17,Sheet1!BJ4:BM4,3,0),0) -> 0 | BS23: =+IFERROR(VLOOKUP($BS$17,Sheet1!BN4:BQ4,3,0),0) -> 0 | BT23: 38 | BU23: =+IFERROR(VLOOKUP($BU$17,Sheet1!BV4:BY4,3,0),0) -> 0 | BV23: =Sheet1!E4 -> STEEL | BW23: SP0400118 | BX23: CORRUGATED DISPATCH STEEL DRUM 1700 X 1000 X 1200 | BY23: =Sheet1!CX4 -> 250 | BZ23: 95000 | CA23: =SUMPRODUCT($N$18:$BU$18,N23:BU23)+BZ23 -> 852210 | CB23: =Sheet1!CB4 -> 0 | CC23: =CA23*CB23 -> 0 | CD23: 0.5 | CE23: =CA23*CD23 -> 426105 | CF23: 0 | CG23: =CA23*CF23 -> 0 | CH23: =CA23+CC23+CE23+CG23 -> 1278315 | CI23: 0.02 | CJ23: =CH23*CI23 -> 25566.3 | CK23: 0.01 | CL23: =CH23*CK23 -> 12783.15
A24: =Sheet1!A8 -> ENQ-10773-22-23 | B24: =Sheet1!B8 -> 45135 | C24: =Sheet1!C8 -> FA1300066 | D24: =Sheet1!D8 -> 1 CORE X 1000 SQ. MM. AL/ARM (XLPE) - 11 KV | E24: =CH24+CJ24+CL24 -> 1852703.7 | F24: =ROUNDUP(M40,0) -> 34667 | G24: =E24+F24 -> 1887370.7 | H24: =Sheet1!CP8 -> 0.18 | I24: =G24*H24 -> 339726.73 | J24: =G24+I24 -> 2227097.5 | K24: 15 | L24: =Sheet1!CT8 -> KMS | M24: =J24*K24 -> 33406462 | N24: 2732 | O24: =+IFERROR(VLOOKUP($O$17,Sheet1!J8:L8,3,0),0) -> 0 | P24: =+IFERROR(VLOOKUP($P$17,Sheet1!J8:M8,3,0),0) -> 0 | Q24: =+IFERROR(VLOOKUP($Q$17,Sheet1!J8:M8,3,0),0) -> 0 | R24: =+IFERROR(VLOOKUP($R$17,Sheet1!J8:M8,3,0),0) -> 0 | S24: =+IFERROR(VLOOKUP($S$17,Sheet1!N8:Q8,3,0),0) -> 0 | T24: =+IFERROR(VLOOKUP($T$17,Sheet1!N8:Q8,3,0),0) -> 0 | U24: =+IFERROR(VLOOKUP($U$17,Sheet1!F8:I8,3,0),0) -> 0 | V24: =+IFERROR(VLOOKUP($V$17,Sheet1!F8:I8,3,0),0) -> 0 | W24: =+IFERROR(VLOOKUP($W$17,Sheet1!F8:I8,3,0),0) -> 0 | X24: =+IFERROR(VLOOKUP($X$17,Sheet1!F8:I8,3,0),0) -> 0 | Y24: 77 | Z24: =+IFERROR(VLOOKUP($Z$17,Sheet1!F8:I8,3,0),0) -> 0 | AA24: =+IFERROR(VLOOKUP($AA$17,Sheet1!F8:I8,3,0),0) -> 0 | AB24: =+IFERROR(VLOOKUP($AB$17,Sheet1!F8:I8,3,0),0) -> 0 | AC24: 230 | AD24: =+IFERROR(VLOOKUP($AD$17,Sheet1!R8:U8,2,0),0) -> 0 | AE24: 476 | AF24: =+IFERROR(VLOOKUP($AF$17,Sheet1!V8:Y8,3,0),0) -> 0 | AG24: =+IFERROR(VLOOKUP($AG$17,Sheet1!V8:Y8,3,0),0) -> 0 | AH24: =+IFERROR(VLOOKUP($AH$17,Sheet1!V8:Y8,3,0),0) -> 0 | AI24: =+IFERROR(VLOOKUP($AI$17,Sheet1!V8:Y8,3,0),0) -> 0 | AJ24: =+IFERROR(VLOOKUP($AJ$17,Sheet1!V8:Y8,3,0),0) -> 0 | AK24: 19 | AL24: =+IFERROR(VLOOKUP($AL$17,Sheet1!AD8:AG8,3,0),0) -> 0 | AM24: =+IFERROR(VLOOKUP($AM$17,Sheet1!AD8:AG8,3,0),0) -> 0 | AN24: =+IFERROR(VLOOKUP($AN$17,Sheet1!AD8:AG8,3,0),0) -> 0 | AO24: =+IFERROR(VLOOKUP($AO$17,Sheet1!AD8:AG8,3,0),0) -> 0 | AP24: =+IFERROR(VLOOKUP($AP$17,Sheet1!AD8:AG8,3,0),0) -> 0 | AQ24: 194 | AR24: =+IFERROR(VLOOKUP($AR$17,Sheet1!AD8:AG8,3,0),0) -> 0 | AS24: =+IFERROR(VLOOKUP($AS$17,Sheet1!AH8:AK8,3,0),0) -> 0 | AT24: =+IFERROR(VLOOKUP($AT$17,Sheet1!AH8:AK8,3,0),0) -> 0 | AU24: =+IFERROR(VLOOKUP($AU$17,Sheet1!AH8:AK8,3,0),0) -> 0 | AV24: 1008 | AW24: =+IFERROR(VLOOKUP($AW$17,Sheet1!AH8:AK8,3,0),0) -> 0 | AX24: =+IFERROR(VLOOKUP($AX$17,Sheet1!AH8:AK8,3,0),0) -> 0 | AY24: =+IFERROR(VLOOKUP($AY$17,Sheet1!AH8:AK8,3,0),0) -> 0 | AZ24: =+IFERROR(VLOOKUP($AZ$17,Sheet1!AH8:AK8,3,0),0) -> 0 | BA24: =+IFERROR(VLOOKUP($BA$17,Sheet1!AH8:AK8,3,0),0) -> 0 | BB24: =+IFERROR(VLOOKUP($BB$17,Sheet1!AH8:AK8,3,0),0) -> 0 | BC24: =+IFERROR(VLOOKUP($BC$17,Sheet1!AL8:AO8,3,0),0) -> 0 | BD24: =+IFERROR(VLOOKUP($BD$17,Sheet1!AL8:AO8,3,0),0) -> 0 | BE24: =+IFERROR(VLOOKUP($BE$17,Sheet1!AL8:AO8,3,0),0) -> 0 | BF24: 700 | BG24: =+IFERROR(VLOOKUP($BG$17,Sheet1!AL8:AO8,3,0),0) -> 0 | BH24: =+IFERROR(VLOOKUP($BH$17,Sheet1!AL8:AO8,3,0),0) -> 0 | BI24: =+IFERROR(VLOOKUP($BI$17,Sheet1!AL8:AO8,3,0),0) -> 0 | BJ24: =+IFERROR(VLOOKUP($BJ$17,Sheet1!AL8:AO8,3,0),0) -> 0 | BK24: =+IFERROR(VLOOKUP($BK$17,Sheet1!AL8:AO8,3,0),0) -> 0 | BL24: =+IFERROR(VLOOKUP($BL$17,Sheet1!AL8:AO8,3,0),0) -> 0 | BM24: =+IFERROR(VLOOKUP($BM$17,Sheet1!AP8:AS8,3,0),0) -> 0 | BN24: =+IFERROR(VLOOKUP($BN$17,Sheet1!AT8:AW8,3,0),0) -> 0 | BO24: 39 | BP24: 46 | BQ24: =+IFERROR(VLOOKUP($BQ$17,Sheet1!BF8:BI8,3,0),0) -> 0 | BR24: =+IFERROR(VLOOKUP($BR$17,Sheet1!BJ8:BM8,3,0),0) -> 0 | BS24: =+IFERROR(VLOOKUP($BS$17,Sheet1!BN8:BQ8,3,0),0) -> 0 | BT24: 42 | BU24: =+IFERROR(VLOOKUP($BU$17,Sheet1!BV8:BY8,3,0),0) -> 0 | BV24: =Sheet1!E8 -> STEEL | BW24: =Sheet1!CV8 -> SP0400107 | BX24: =Sheet1!CW8 -> CORRUGATED DISPATCH STEEL DRUM 2150 X 1080 X 1240 MM | BY24: =Sheet1!CX8 -> 500 | BZ24: =Sheet1!BZ8 -> 66500 | CA24: =SUMPRODUCT($N$18:$BU$18,N24:BU24)+BZ24 -> 1199161 | CB24: =Sheet1!CB8 -> 0 | CC24: =CA24*CB24 -> 0 | CD24: 0.5 | CE24: =CA24*CD24 -> 599580.5 | CF24: 0 | CG24: =CA24*CF24 -> 0 | CH24: =CA24+CC24+CE24+CG24 -> 1798741.5 | CI24: 0.02 | CJ24: =CH24*CI24 -> 35974.83 | CK24: 0.01 | CL24: =CH24*CK24 -> 17987.415
