Workbook

Sheet Sheet1
A1: DOCKET NO. | B1: Base Date | C1: ITEM CODE | D1: PROPOSE ERP ITEM NAME | E1: PROPOSE DRUM TYPE | F1: Insulation Screening (Metallic) | G1: Sum of RM RATE (Insulation Screening (Metallic)) | H1: Weight (Insulation Screening (Metallic)) | I1: COST(Insulation Screening (Metallic)) | J1: Conductor | K1: Sum of RM RATE(Conductor) | L1: WEIGHT(Conductor) | M1: COST(Conductor) | N1: AL ALLOY | O1: Sum of RM RATE(Alu Alloy) | P1: WEIGHT(Alu Alloy) | Q1: COST(Alu Alloy) | R1: Insulation Screening (Non-Metallic) | S1: Sum of RM RATE(Insulation Screening (Non-Metallic)) | T1: WEIGHT(Insulation Screening (Non-Metallic)) | U1: COST(Insulation Screening (Non-Metallic)) | V1: Insulation | W1: Sum of RM RATE(Insulation) | X1: WEIGHT(Insulation) | Y1: COST(Insulation) | Z1: POLY TAPE | AA1: Sum of RM RATE (Poly Tape) | AB1: WEIGHT (Poly Tape) | AC1: COST(Poly Tape) | AD1: Inner Sheath | AE1: Sum of RM RATE(Inner Sheath) | AF1: WEIGHT(Inner Sheath) | AG1: COST(Inner Sheath) | AH1: Armouring | AI1: Sum of RM RATE(Armouring) | AJ1: WEIGHT(Armouring) | AK1: COST(Armouring) | AL1: Outer Sheath | AM1: Sum of RM RATE(Outer Sheath) | AN1: WEIGHT(Outer Sheath) | AO1: COST(Outer Sheath) | AP1: FILLER | AQ1: Sum of RM RATE(Filler) | AR1: WEIGHT(Filler) | AS1: COST(Filler) | AT1: GREASE | AU1: Sum of RM RATE(Grease) | AV1: WEIGHT(Grease) | AW1: COST(Grease) | AX1: Water swellable Tape | AY1: Sum of RM RATE(Water swellable Tape) | AZ1: WEIGHT(Water swellable Tape) | BA1: COST(Water swellable Tape) | BB1: Semi conducting Water Swellable tape | BC1: Sum of RM RATE(Semi conducting Water Swellable tape) | BD1: WEIGHT(Semi conducting Water Swellable tape) | BE1: COST(Semi conducting Water Swellable tape) | BF1: SEMICON TAPE | BG1: Sum of RM RATE(SEMICON TAPE) | BH1: WEIGHT(SEMICON TAPE) | BI1: COST(SEMICON TAPE) | BJ1: GLASS FIBER TAPE | BK1: Sum of RM RATE(GLASS FIBER TAPE) | BL1: WEIGHT(GLASS FIBER TAPE) | BM1: COST(GLASS FIBER TAPE) | BN1: COPPER WIRE 0.8 MM | BO1: Sum of RM RATE(COPPER WIRE 0.8 MM) | BP1: WEIGHT(COPPER WIRE 0.8 MM) | BQ1: COST(COPPER WIRE 0.8 MM) | BR1: RUBBERIZED COTTON TAPE | BS1: Sum of RM RATE(RUBBERIZED COTTON TAPE) | BT1: WEIGHT(RUBBERIZED COTTON TAPE) | BU1: COST(RUBBERIZED COTTON TAPE) | BV1: Water Tight Compound | BW1: Sum of RM RATE(Water Tight Compound) | BX1: WEIGHT(Water Tight Compound) | BY1: COST(Water Tight Compound) | BZ1: DRUM COST PER KM | CA1: TOTAL RM COST | CB1: FIRM % | CC1: FIRM VALUE | CD1: MFG% | CE1: MFG VALUE | CF1: PROF% | CG1: PROFIT VALUE | CH1: 1ST EX-WORKS | CI1: Intt % | CJ1: INTT VALUE | CK1: insp% | CL1: INSP VALUE | CM1: EX-WORKS (PER KM) | CN1: FREIGHT PER KM | CO1: PRICE INCLUDING FREIGHT (PER KM) | CP1: GST % | CQ1: GST VALUE | CR1: PRICE INCLUDING GST & FREIGHT (PER KM) | CS1: QTY | CT1: Unit | CU1: TOTAL PRICE OF FULL QTY (INCLUDING FRIGHT & GST) | CV1: DRUM CODE | CW1: DRUM SIZE (FxbXtx Ft) | CX1: PARTY STANDARD LENGTH (MTR)
A2: ENQ-10176-22-23 | B2: 45019 | C2: FC0700007 | D2: ACSR : RABBIT CONDUCTOR - 50 SQ. MM. (6/1/3.35) | E2: WOOD | J2: Alumimium | K2: 215 | L2: 145 | M2: 31175 | P2: 0 | T2: 0 | X2: 0 | AB2: 0 | AF2: 0 | AH2: ACSR CORE WIRE | AI2: 80.67 | AJ2: 69 | AK2: 5566.23 | AN2: 0 | AR2: 0 | AV2: 0 | AZ2: 0 | BD2: 0 | BH2: 0 | BL2: 0 | BP2: 0 | BT2: 0 | BX2: 0 | BZ2: 636.27 | CA2: 37377.5 | CH2: 37377.5 | CM2: 37377.5 | CN2: 26000 | CO2: 63377.5 | CR2: 63377.5 | CS2: 1 | CT2: KMS | CU2: 63378 | CV2: MD0100015 | CW2: DRUM - 48 X 20 X 28 X 2.25 - RDSO | CX2: 5000

Sheet AUTO CALCULATION SHEET (2)
A2: JHARKHAND BIJLI VITRAN NIGAM LIMITED
A4: TENDER SPECIFICATION NO () | B4: 15/PR/JBVNL/2023-24.
A5: TENDER DESCRIPTION () | B5: Rate contract for supply of Manufacturing, testing & supply of ISI marked ACSR Rabbit Conductor
A6: Last Date & Time of Submission () | B6: 22.05.2023 upto 18:00 Hrs.
A7: REVERSE AUCTION | B7: Not Mention.
A8: Price () | B8: Rate contract shall be done on L-1 rate with successful bidder against NIT for the period of 02(two) years [ 1st year on FIRM Price + 2nd year on Variable Price] which may be further extended for 01 year on variable Price on mutual agreement and satisfactory performance.
A9: Validity () | B9: Tenderer should specify the validity period of their offer which should not be less than 180 (One Hundred Eighty) days from the date of opening of tender, which may be extended on discretion of the NIGAM. The offers with lesser validity period may be out- rightly rejected.
A10: Delivery Period () | B10: The materials shall be delivered as per delivery schedule mentioned in purchase order. Early delivery may be preferred. The commencement of delivery period shall be reckoned from the date of issue of PO.
A11: Payment Terms () | B11: 100% payment will be made by Sr. Manager, JBVNL, Headquarter, Ranchi on submission of 5% Bank Guarantee from any Nationalised/Scheduled Bank of ordered value on non-judicial stamp Rs. 100/- (Rupees hundred) only valid for Guarantee period as per cl-38 and on receipt of SRV duly signed by the concerned consignee after receipt of the materials in good condition along with approved routine test certificate and duly filled check list for payment from Stores & Purchase wing.
A12: Standard length () | B12: Normal wire length of conductor is 1.25 Km. Longer length will be acceptable (short length not less than 1 KM shall be acceptable to the maximum extent of 10% of the quantity ordered.) (viii) No. of length in each drum ---- 2 to 4
A13: Packing () | B13: The conductors shall be would in non-returnable reels of drums confirming to ISS: 1778 / 1961 Specification for reels/drums for Bare wire and shall be marked with the following.
A14: Technical Specification
N16: =Sheet1!J1 -> Conductor | S16: AL ALLOY | U16: Insulation Screening (Metallic) | AC16: Insulation Screening (Non-Metallic) | AE16: Insulation | AK16: POLY TAPE | AL16: Inner Sheath | AS16: Armouring | BC16: Outer Sheath | BM16: FILLER | BN16: GREASE | BO16: Water swellable Tape | BP16: Semi conducting Water Swellable tape | BQ16: SEMICON TAPE | BR16: GLASS FIBER TAPE | BS16: COPPER WIRE 0.8 MM | BT16: RUBBERIZED COTTON TAPE | BU16: Water Tight Compound | BZ16: DRUM COST PER KM | CA16: TOTAL RM COST | CB16: EXTRA CONSUMPTION | CC16: EXTRA CONSUMPTION VALUE
A17: DOCKET NO. | B17: =Sheet1!B1 -> Base Date | C17: ITEM CODE | D17: PROPOSE ERP ITEM NAME | E17: EX-WORKS (PER KM) | F17: FREIGHT PER KM | G17: PRICE INCLUDING FREIGHT (PER KM) | H17: GST % | I17: GST VALUE | J17: PRICE INCLUDING GST & FREIGHT (PER KM) | K17: QTY | L17: Unit | M17: TOTAL PRICE OF FULL QTY (INCLUDING FRIGHT & GST) | N17: Alumimium | O17: Alumimium ALLOY | P17: Copper | Q17: Flexible Copper | R17: Galvanized steel wire | S17: Alumimium | T17: Alumimium ALLOY | U17: Coper tape - 0.1 mm | V17: Copper Tape - 0.03 mm | W17: Copper Tape - 0.035 mm | X17: Copper Tape - 0.04 mm | Y17: Copper Tape - 0.045 mm | Z17: Copper Tape - 0.050 mm | AA17: Copper Tape - 0.060 mm | AB17: Copper Tape - 0.075 mm(DOUBLE) | AC17: Extruded semiconductive | AD17: Extruded Semiconductive(Stripable) | AE17: HT-XLPE | AF17: LT-XLPE | AG17: TR XLPE | AH17: Type A PVC | AI17: Type C PVC (HR) | AJ17: XLPE | AK17: POLY TAPE | AL17: FR PVC Type ST-1 | AM17: FR PVC Type ST-2 | AN17: FRLSH PVC Type ST-2 | AO17: PVC Type ST-1 | AP17: PVC Type ST-1-PRESSURE EXTRUDED | AQ17: PVC Type ST-2 | AR17: PVC Type ST-2-PRESSURE EXTRUDED | AS17: ACSR CORE WIRE | AT17: ACSR DOG STEEL WIRE | AU17: Aluminium Flat Strip | AV17: Aluminium Round Wire | AW17: Double Steel Tape | AX17: Galvanised Steel Flat Strip | AY17: Galvanised Steel Flat Strip (Double) | AZ17: Galvanised Steel Flat Strip-B | BA17: Galvanised Steel Round Wire | BB17: Galvanised Steel Round Wire (Double) | BC17: FR PVC Type ST-1 | BD17: FR PVC Type ST-2 | BE17: FRLSH PVC Type ST-1 | BF17: FRLSH PVC Type ST-2 | BG17: PE, ST-3 | BH17: PE, ST-7 | BI17: PVC Type ST-1 | BJ17: PVC Type ST-2 | BK17: PVC Type ST-2-PRESSURE EXTRUDED | BL17: UV & Track Resistant XLPE | BM17: FILLER | BN17: Grease | BO17: Water swellable Tape | BP17: Semi conducting Water Swellable tape | BQ17: SEMICON TAPE | BR17: GLASS FIBER TAPE | BS17: COPPER WIRE 0.8 MM | BT17: RUBBERIZED COTTON TAPE | BU17: Water Tight Compound | BV17: =Sheet1!E1 -> PROPOSE DRUM TYPE | BW17: =Sheet1!CV1 -> DRUM CODE | BX17: =Sheet1!CW1 -> DRUM SIZE (FxbXtx Ft) | BY17: =Sheet1!CX1 -> PARTY STANDARD LENGTH (MTR) | CD17: MFG% | CE17: MFG VALUE | CF17: PROF% | CG17: PROFIT VALUE | CH17: 1ST EX-WORKS | CI17: Intt % | CJ17: INTT VALUE | CK17: insp% | CL17: INSP VALUE
N18: 232 | AS18: 79 | AT18: =+IFERROR(VLOOKUP($AT$17,Sheet1!AH2:AK840,2,0),0) -> 0 | AU18: =+IFERROR(VLOOKUP($AU$17,Sheet1!AH2:AK840,2,0),0) -> 0 | AV18: =+IFERROR(VLOOKUP($AV$17,Sheet1!AH2:AK840,2,0),0) -> 0 | AW18: =+IFERROR(VLOOKUP($AW$17,Sheet1!AH2:AK840,2,0),0) -> 0 | AX18: =+IFERROR(VLOOKUP($AX$17,Sheet1!AH2:AK840,2,0),0) -> 0 | AY18: =+IFERROR(VLOOKUP($AY$17,Sheet1!AH2:AK840,2,0),0) -> 0 | AZ18: =+IFERROR(VLOOKUP($AZ$17,Sheet1!AH2:AK840,2,0),0) -> 0 | BA18: =+IFERROR(VLOOKUP($BA$17,Sheet1!AH2:AK840,2,0),0) -> 0 | BB18: =+IFERROR(VLOOKUP($BB$17,Sheet1!AH2:AK840,2,0),0) -> 0 | BC18: =+IFERROR(VLOOKUP($BC$17,Sheet1!AL2:AO840,2,0),0) -> 0 | BD18: =+IFERROR(VLOOKUP($BD$17,Sheet1!AL2:AO840,2,0),0) -> 0 | BE18: =+IFERROR(VLOOKUP($BE$17,Sheet1!AL2:AO840,2,0),0) -> 0 | BF18: =+IFERROR(VLOOKUP($BF$17,Sheet1!AL2:AO840,2,0),0) -> 0 | BG18: =+IFERROR(VLOOKUP($BG$17,Sheet1!AL2:AO840,2,0),0) -> 0 | BH18: =+IFERROR(VLOOKUP($BH$17,Sheet1!AL2:AO840,2,0),0) -> 0 | BI18: =+IFERROR(VLOOKUP($BI$17,Sheet1!AL2:AO840,2,0),0) -> 0 | BJ18: =+IFERROR(VLOOKUP($BJ$17,Sheet1!AL2:AO840,2,0),0) -> 0 | BK18: =+IFERROR(VLOOKUP($BK$17,Sheet1!AL2:AO840,2,0),0) -> 0 | BL18: =+IFERROR(VLOOKUP($BL$17,Sheet1!AL2:AO840,2,0),0) -> 0 | BM18: =+IFERROR(VLOOKUP($BM$17,Sheet1!AP2:AS840,2,0),0) -> 0 | BN18: =+IFERROR(VLOOKUP($BN$17,Sheet1!AT2:AW840,2,0),0) -> 0 | BO18: =+IFERROR(VLOOKUP($BO$17,Sheet1!AX2:BA840,2,0),0) -> 0 | BP18: =+IFERROR(VLOOKUP($BP$17,Sheet1!BB2:BE840,2,0),0) -> 0 | BQ18: =+IFERROR(VLOOKUP($BQ$17,Sheet1!BF2:BI840,2,0),0) -> 0 | BR18: =+IFERROR(VLOOKUP($BR$17,Sheet1!BJ2:BM840,2,0),0) -> 0 | BS18: =+IFERROR(VLOOKUP($BS$17,Sheet1!BN2:BQ840,2,0),0) -> 0 | BT18: =+IFERROR(VLOOKUP($BT$17,Sheet1!BR2:BU840,2,0),0) -> 0 | BU18: =+IFERROR(VLOOKUP($BU$17,Sheet1!BV2:BY840,2,0),0) -> 0
A19: =Sheet1!A2 -> ENQ-10176-22-23 | B19: 45038 | C19: =Sheet1!C2 -> FC0700007 | D19: =Sheet1!D2 -> ACSR : RABBIT CONDUCTOR - 50 SQ. MM. (6/1/3.35) | E19: =CH19+CJ19+CL19 -> 44483.067 | F19: =ROUNDUP(M22,0) -> 408 | G19: =E19+F19 -> 44891.067 | H19: 0.18 | I19: =G19*H19 -> 8080.3921 | J19: =G19+I19 -> 52971.459 | K19: 3000 | L19: =Sheet1!CT2 -> KMS | M19: =J19*K19 -> 1.5891438e+08 | N19: 146 | O19: =+IFERROR(VLOOKUP($O$17,Sheet1!J2:L2,3,0),0) -> 0 | P19: =+IFERROR(VLOOKUP($P$17,Sheet1!J2:M2,3,0),0) -> 0 | Q19: =+IFERROR(VLOOKUP($Q$17,Sheet1!J2:M2,3,0),0) -> 0 | R19: =+IFERROR(VLOOKUP($R$17,Sheet1!J2:M2,3,0),0) -> 0 | S19: =+IFERROR(VLOOKUP($S$17,Sheet1!N2:Q2,3,0),0) -> 0 | T19: =+IFERROR(VLOOKUP($T$17,Sheet1!N2:Q2,3,0),0) -> 0 | U19: =+IFERROR(VLOOKUP($U$17,Sheet1!F2:I2,3,0),0) -> 0 | V19: =+IFERROR(VLOOKUP($V$17,Sheet1!F2:I2,3,0),0) -> 0 | W19: =+IFERROR(VLOOKUP($W$17,Sheet1!F2:I2,3,0),0) -> 0 | X19: =+IFERROR(VLOOKUP($X$17,Sheet1!F2:I2,3,0),0) -> 0 | Y19: =+IFERROR(VLOOKUP($Y$17,Sheet1!F2:I2,3,0),0) -> 0 | Z19: =+IFERROR(VLOOKUP($Z$17,Sheet1!F2:I2,3,0),0) -> 0 | AA19: =+IFERROR(VLOOKUP($AA$17,Sheet1!F2:I2,3,0),0) -> 0 | AB19: =+IFERROR(VLOOKUP($AB$17,Sheet1!F2:I2,3,0),0) -> 0 | AC19: =+IFERROR(VLOOKUP($AC$17,Sheet1!R2:U2,3,0),0) -> 0 | AD19: =+IFERROR(VLOOKUP($AD$17,Sheet1!R2:U2,2,0),0) -> 0 | AE19: =+IFERROR(VLOOKUP($AE$17,Sheet1!V2:Y2,3,0),0) -> 0 | AF19: =+IFERROR(VLOOKUP($AF$17,Sheet1!V2:Y2,3,0),0) -> 0 | AG19: =+IFERROR(VLOOKUP($AG$17,Sheet1!V2:Y2,3,0),0) -> 0 | AH19: =+IFERROR(VLOOKUP($AH$17,Sheet1!V2:Y2,3,0),0) -> 0 | AI19: =+IFERROR(VLOOKUP($AI$17,Sheet1!V2:Y2,3,0),0) -> 0 | AJ19: =+IFERROR(VLOOKUP($AJ$17,Sheet1!V2:Y2,3,0),0) -> 0 | AK19: =+IFERROR(VLOOKUP($AK$17,Sheet1!Z2:AB2,3,0),0) -> 0 | AL19: =+IFERROR(VLOOKUP($AL$17,Sheet1!AD2:AG2,3,0),0) -> 0 | AM19: =+IFERROR(VLOOKUP($AM$17,Sheet1!AD2:AG2,3,0),0) -> 0 | AN19: =+IFERROR(VLOOKUP($AN$17,Sheet1!AD2:AG2,3,0),0) -> 0 | AO19: =+IFERROR(VLOOKUP($AO$17,Sheet1!AD2:AG2,3,0),0) -> 0 | AP19: =+IFERROR(VLOOKUP($AP$17,Sheet1!AD2:AG2,3,0),0) -> 0 | AQ19: =+IFERROR(VLOOKUP($AQ$17,Sheet1!AD2:AG2,3,0),0) -> 0 | AR19: =+IFERROR(VLOOKUP($AR$17,Sheet1!AD2:AG2,3,0),0) -> 0 | AS19: =+IFERROR(VLOOKUP($AS$17,Sheet1!AH2:AK2,3,0),0) -> 69 | AT19: =+IFERROR(VLOOKUP($AT$17,Sheet1!AH2:AK2,3,0),0) -> 0 | AU19: =+IFERROR(VLOOKUP($AU$17,Sheet1!AH2:AK2,3,0),0) -> 0 | AV19: =+IFERROR(VLOOKUP($AV$17,Sheet1!AH2:AK2,3,0),0) -> 0 | AW19: =+IFERROR(VLOOKUP($AW$17,Sheet1!AH2:AK2,3,0),0) -> 0 | AX19: =+IFERROR(VLOOKUP($AX$17,Sheet1!AH2:AK2,3,0),0) -> 0 | AY19: =+IFERROR(VLOOKUP($AY$17,Sheet1!AH2:AK2,3,0),0) -> 0 | AZ19: =+IFERROR(VLOOKUP($AZ$17,Sheet1!AH2:AK2,3,0),0) -> 0 | BA19: =+IFERROR(VLOOKUP($BA$17,Sheet1!AH2:AK2,3,0),0) -> 0 | BB19: =+IFERROR(VLOOKUP($BB$17,Sheet1!AH2:AK2,3,0),0) -> 0 | BC19: =+IFERROR(VLOOKUP($BC$17,Sheet1!AL2:AO2,3,0),0) -> 0 | BD19: =+IFERROR(VLOOKUP($BD$17,Sheet1!AL2:AO2,3,0),0) -> 0 | BE19: =+IFERROR(VLOOKUP($BE$17,Sheet1!AL2:AO2,3,0),0) -> 0 | BF19: =+IFERROR(VLOOKUP($BF$17,Sheet1!AL2:AO2,3,0),0) -> 0 | BG19: =+IFERROR(VLOOKUP($BG$17,Sheet1!AL2:AO2,3,0),0) -> 0 | BH19: =+IFERROR(VLOOKUP($BH$17,Sheet1!AL2:AO2,3,0),0) -> 0 | BI19: =+IFERROR(VLOOKUP($BI$17,Sheet1!AL2:AO2,3,0),0) -> 0 | BJ19: =+IFERROR(VLOOKUP($BJ$17,Sheet1!AL2:AO2,3,0),0) -> 0 | BK19: =+IFERROR(VLOOKUP($BK$17,Sheet1!AL2:AO2,3,0),0) -> 0 | BL19: =+IFERROR(VLOOKUP($BL$17,Sheet1!AL2:AO2,3,0),0) -> 0 | BM19: =+IFERROR(VLOOKUP($BM$17,Sheet1!AP2:AS2,3,0),0) -> 0 | BN19: =+IFERROR(VLOOKUP($BN$17,Sheet1!AT2:AW2,3,0),0) -> 0 | BO19: =+IFERROR(VLOOKUP($BO$17,Sheet1!AX2:BA2,3,0),0) -> 0 | BP19: =+IFERROR(VLOOKUP($BP$17,Sheet1!BB2:BE2,3,0),0) -> 0 | BQ19: =+IFERROR(VLOOKUP($BQ$17,Sheet1!BF2:BI2,3,0),0) -> 0 | BR19: =+IFERROR(VLOOKUP($BR$17,Sheet1!BJ2:BM2,3,0),0) -> 0 | BS19: =+IFERROR(VLOOKUP($BS$17,Sheet1!BN2:BQ2,3,0),0) -> 0 | BT19: =+IFERROR(VLOOKUP($BT$17,Sheet1!BR2:BU2,3,0),0) -> 0 | BU19: =+IFERROR(VLOOKUP($BU$17,Sheet1!BV2:BY2,3,0),0) -> 0 | BV19: =Sheet1!E2 -> WOOD | BW19: MD0100013 | BX19: 1220 X 600 X 710 | BY19: =Sheet1!CX2 -> 5000 | BZ19: =3255/5 -> 651 | CA19: =SUMPRODUCT($N$18:$BU$18,N19:BU19)+BZ19 -> 39974 | CB19: =Sheet1!CB2 -> 0 | CC19: =CA19*CB19 -> 0 | CD19: 0.07 | CE19: =CA19*CD19 -> 2798.18 | CF19: 0 | CG19: =CA19*CF19 -> 0 | CH19: =CA19+CC19+CE19+CG19 -> 42772.18 | CI19: 0.02 | CJ19: =CH19*CI19 -> 855.4436 | CK19: 0.02 | CL19: =CH19*CK19 -> 855.4436
E21: Order Quantity | F21: Stnd Length | G21: Truck type | H21: Fare of one truck | I21: No of Drum in one truck | J21: Total length in one Truck | K21: No of Truck | L21: Total Freight | M21: Freight per KM
D22: =D19 -> ACSR : RABBIT CONDUCTOR - 50 SQ. MM. (6/1/3.35) | E22: =K19 -> 3000 | F22: 5 | G22: 16 MT | H22: 26000 | I22: 13 | J22: =F22*I22 -> 65 | K22: =ROUNDUP((E22/J22),0) -> 47 | L22: =M22*E22 -> 1222000 | M22: =(H22*K22)/E22 -> 407.33333
I24: =SUM(N19:AS19)*5 -> 1075
I25: =I24+125 -> 1200
I26: =16000/I25 -> 13.333333

Sheet CONDUCTOR
A1: ='AUTO CALCULATION SHEET (2)'!A2:R2 -> JHARKHAND BIJLI VITRAN NIGAM LIMITED
A2: Base Date | B2: 45038
A3: PV Terms | B3: It is one month prior to the last date of submission of bid against the NIT i.e price is applicable on 1st working day of month, one month prior to date of tendering (due date of tender) i.e if due date of tender is in month sept’2022 then price indices shall be taken of 1st August’2022. Similarly for date of delivery price is applicable on 1st working day of month, one month prior to date of delivery if date of delivery is in month DEC’2022 then price indices shall be taken of 1st NOV’2022.
A4: PV FORMULA (IEEMA)
A5: P = Po + WA(AL – ALo) + WF(FE – FEo) / WA = 0.145, WF = 0.069
A7: Item | B7: Ex-Work
A8: ='AUTO CALCULATION SHEET (2)'!D19 -> ACSR : RABBIT CONDUCTOR - 50 SQ. MM. (6/1/3.35) | B8: ='AUTO CALCULATION SHEET (2)'!E19 -> 44483.067
A11: Item | B11: Calculation part | C11: Date of Inspection | D11: Applicable Date | G11: BASE DATE | J11: FACTORS | L11: Ex-Work Po | M11: PVC of Al | N11: PVC of Fe | O11: PVC per KM | P11: Billing Price/PKM | Q11: VALUE ADDITION CALCULATION
D12: Date | E12: Al | F12: fe | G12: Date | H12: Alo | I12: feo
J13: W | K13: Fe | Q13: Al @ | R13: ST @ | S13: RMC | T13: Drum | U13: RMC+DRUM | V13: VA | W13: Groos VA% | X13: Mfg % | Y13: Int % | Z13: Ins% | AA13: Net VA
Q14: 221 | R14: 76
A15: =A8 -> ACSR : RABBIT CONDUCTOR - 50 SQ. MM. (6/1/3.35) | C15: provisional | D15: 19.05.2023 | E15: 213277.76 | F15: 85063 | G15: =$B$2 -> 45038 | H15: 225250 | I15: 85063 | J15: 0.145 | K15: 0.069 | L15: =B8 -> 44483.067 | M15: =J15*(E15-H15) -> -1735.9744 | N15: =K15*(F15-I15) -> 0 | O15: =M15+N15 -> -1735.9744 | P15: =L15+O15 -> 42747.093 | Q15: ='AUTO CALCULATION SHEET (2)'!N19 -> 146 | R15: ='AUTO CALCULATION SHEET (2)'!AS19 -> 69 | S15: =SUMPRODUCT($Q$14:$R$14,Q15:R15) -> 37510 | T15: ='AUTO CALCULATION SHEET (2)'!BZ19 -> 651 | U15: =S15+T15 -> 38161 | V15: =+P15-U15 -> 4586.0928 | W15: =V15/P15*100% -> 0.10728432 | Y15: 0.02 | Z15: 0.02 | AA15: =W15-SUM(X15:Z15) -> 0.06728432
