Workbook

Sheet Sheet1
A1: DOCKET NO. | B1: Base Date | C1: ITEM CODE | D1: PROPOSE ERP ITEM NAME | E1: Propose Drum Type | F1: Insulation Screening(Metallic) | G1: RM Rate(Insulation Screening(Metallic)) | H1: Weight (Insulation Screening (Metallic)) | I1: Cost Insulation Screening(Metallic) | J1: Conductor | K1: RM Rate(Conductor) | L1: Weight(Conductor) | M1: Cost(Conductor) | N1: AL ALLOY | O1: RM Rate(AL Alloy) | P1: Weight(Al Alloy) | Q1: Cost(AL Alloy) | R1: Insulation Screening(Non-Metallic) | S1: RM Rate(Insulation Screening(Non-Metallic)) | T1: Weight(Insulation Screening(Non-Metallic) | U1: Cost(Insulation Screening(Non-Metallic) | V1: Insulation | W1: RM Rate(Insulation) | X1: Weight(Insulation) | Y1: Cost(Insulation) | Z1: Poly Tape | AA1: RM Rate(Poly Tape) | AB1: Weight(Poly Tape) | AC1: Cost(Poly Tape) | AD1: Inner Sheath | AE1: RM Rate(Inner Sheath) | AF1: Weight(Inner Sheath) | AG1: Cost(Inner Sheath) | AH1: Armouring | AI1: RM Rate(Armouring) | AJ1: Weight(Armouring) | AK1: Cost(Armouring) | AL1: Outer Sheath | AM1: RM Rate(Outer Sheath) | AN1: Weight(Outer Sheath) | AO1: Cost(Outer Sheath) | AP1: Filler | AQ1: RM Rate(Filler) | AR1: Weight(Filler) | AS1: Cost(Filler) | AT1: Grease | AU1: RM Rate(Grease) | AV1: Weight(Grease) | AW1: Cost(Grease) | AX1: Water Swellable Tape | AY1: RM Rate(Water Swellable Tape) | AZ1: Weight(Water Swellable Tape) | BA1: Cost(Water Swellable Tape) | BB1: Semi Conducting Water Swellable Tape | BC1: RM Rate(Semi Conducting Water Swellable Tape) | BD1: Weight(Semi Conducting Water Swellable Tape) | BE1: Cost(Semi Conducting Water Swellable Tape) | BF1: Semicon Tape | BG1: RM Rate(Semicon Tape) | BH1: Weight(Semicon Tape) | BI1: Cost(Semicon Tape) | BJ1: Glass Fiber Tape | BK1: RM Rate(Glass Fiber Tape) | BL1: Weight(Glass Fiber Tape) | BM1: Cost(Glass Fiber Tape) | BN1: Copper Wire 0.8MM | BO1: RM Rate(Copper Wire 0.8MM) | BP1: Weight(Copper Wire 0.8MM) | BQ1: Cost(Copper Wire 0.8MM) | BR1: Rubberized Cotton Tape | BS1: RM Rate(Rubberized Cotton Tape) | BT1: Weight(Rubberized Cotton Tape) | BU1: Cost(Rubberized Cotton Tape) | BV1: Water Tight Compound | BW1: RM Rate(Water Tight Compound) | BX1: Weight(Water Tight Compound) | BY1: Cost(Water Tight Compound) | BZ1: Drum Cost Per KM | CA1: Total RM Cost | CB1: FIRM % | CC1: Firm Value | CD1: MFG% | CE1: MFG Value | CF1: PROF% | CG1: Profit Value | CH1: 1st EX-Works | CI1: Intt % | CJ1: Intt Value | CK1: insp% | CL1: Insp Value | CM1: EX-Works Per KM | CN1: Freight Per KM | CO1: Price Including Freight Per KM | CP1: GST % | CQ1: GST Value | CR1: Price Including GST & Freight Per KM | CS1: QTY | CT1: Unit | CU1: Total Price Of Full QTY(Including Freight&GST) | CV1: DRUM CODE | CW1: DRUM SIZE (FxbXtx Ft) | CX1: Party Standard Length(MTR)
A2: ENQ-15214-22-23 | B2: 45714 | C2: FA2900004 | D2: COVERED CONDUCTOR - 1 CORE x 100 SQ. MM. (AAAC) - 11KV | E2: WOOD | J2: Alumimium Alloy | K2: 281 | N2: Alumimium Alloy | O2: 281 | R2: Extruded Semiconductive | S2: 178 | V2: HT-XLPE | W2: 151 | AL2: UV & Track Resistant XLPE | AM2: 237 | BV2: Water Tight Compound | BW2: 210 | BZ2: 3992 | CA2: 3992 | CH2: 3992 | CM2: 3992 | CO2: 3992 | CP2: 0.18 | CQ2: 718.56 | CR2: 4710.56 | CS2: 1220.919 | CT2: KMS | CU2: 5751212 | CV2: MD0100075 | CW2: DRUM - 42 X 15 X 23 X 2 (LOMBU)
A3: ENQ-15214-22-23 | B3: 45714 | C3: FA2900008 | D3: COVERED CONDUCTOR - 1 CORE X 99 SQ. MM. (AAAC) - 33 KV | E3: WOOD | J3: Alumimium Alloy | K3: 281 | R3: Extruded Semiconductive | S3: 178 | V3: HT-XLPE | W3: 151 | AL3: UV & Track Resistant XLPE | AM3: 237 | BV3: Water Tight Compound | BW3: 210 | BZ3: 4110 | CA3: 4110 | CH3: 4110 | CM3: 4110 | CO3: 4110 | CP3: 0.18 | CQ3: 739.8 | CR3: 4849.8 | CS3: 65 | CT3: KMS | CU3: 315237 | CV3: MD0100015 | CW3: DRUM - 48 X 20 X 28 X 2.25
A4: ENQ-15214-22-23 | B4: 45714 | C4: FA2900029 | D4: COVERED CONDUCTOR - 1 CORE X 55 SQ. MM. (AAAC) - 11 KV | E4: WOOD | J4: Alumimium Alloy | K4: 281 | R4: Extruded Semiconductive | S4: 178 | V4: HT-XLPE | W4: 151 | AL4: UV & Track Resistant XLPE | AM4: 237 | BV4: Water Tight Compound | BW4: 210 | BZ4: 2429 | CA4: 2429 | CH4: 2429 | CM4: 2429 | CO4: 2429 | CP4: 0.18 | CQ4: 437.22 | CR4: 2866.22 | CS4: 23 | CT4: KMS | CU4: 65923 | CV4: MD0100005 | CW4: DRUM - 36 X 14 X 23 X 2
A5: ENQ-15214-22-23 | B5: 45714 | C5: FA2900032 | D5: COVERED CONDUCTOR - 1 CORE X 232 SQ. MM. (AAAC) - 33 KV | E5: WOOD | J5: Alumimium Alloy | K5: 281 | R5: Extruded Semiconductive | S5: 178 | V5: HT-XLPE | W5: 151 | AL5: UV & Track Resistant XLPE | AM5: 237 | BV5: Water Tight Compound | BW5: 210 | BZ5: 7013 | CA5: 7013 | CH5: 7013 | CM5: 7013 | CO5: 7013 | CP5: 0.18 | CQ5: 1262.34 | CR5: 8275.34 | CS5: 127 | CT5: KMS | CU5: 1050968 | CV5: MD0100019 | CW5: DRUM - 54 X 24 X 32 X 3
A6: ENQ-15214-22-23 | B6: 45714 | C6: FA2900034 | D6: COVERED CONDUCTOR - 1 CORE X 80 SQ. MM. (AAAC) - 11 KV | E6: WOOD | J6: Alumimium Alloy | K6: 281 | R6: Extruded Semiconductive | S6: 178 | V6: HT-XLPE | W6: 151 | AL6: UV & Track Resistant XLPE | AM6: 237 | BV6: Water Tight Compound | BW6: 210 | BZ6: 3606 | CA6: 3606 | CH6: 3606 | CM6: 3606 | CO6: 3606 | CP6: 0.18 | CQ6: 649.08 | CR6: 4255.08 | CS6: 48.085 | CT6: KMS | CU6: 204606 | CV6: MD0100085 | CW6: DRUM - 43 X 15 X 28 X 2.25
A7: ENQ-15214-22-23 | B7: 45714 | C7: FA2900014 | D7: COVERED CONDUCTOR - 1 CORE x 150 SQ. MM. (XLPE) (AAAC) - 33 KV | E7: WOOD | J7: Alumimium Alloy | K7: 281 | R7: Extruded Semiconductive | S7: 178 | V7: HT-XLPE | W7: 151 | AL7: UV & Track Resistant XLPE | AM7: 237 | BV7: Water Tight Compound | BW7: 210 | BZ7: 4629 | CA7: 4629 | CH7: 4629 | CM7: 4629 | CO7: 4629 | CP7: 0.18 | CQ7: 833.22 | CR7: 5462.22 | CS7: 253.175 | CT7: KMS | CU7: 1382898 | CV7: MD0100099 | CW7: DRUM - 48 X 14 X 36 X 2.25 (LOMBU)

Sheet AUTO CALCULATION SHEET (2)
A2: Tata Power Odisha DISCOMs
A4: TENDER SPECIFICATION NO () | B4: TPCODL / CCG / 23-24 / 1000001765
A5: TENDER DESCRIPTION () | B5: Rate Contract for Supply Covered Conductor for TPCODL, TPNODL, TPSODL & TPWODL.
A6: Last Date & Time of Submission () | B6: 28-02-2025; 17:00 Hrs.
A7: REVERSE AUCTION | B7: No. of bidders allowed to participate in RA process shall be: Total No. of bidders on whom tender would be split PLUS 2 more bidders. Illustrative example: Total no. of qualified bidders is 10 & tender needs to split amongst 4 bidders. PLUS 2 means (04 + 02 = 06) means lowest 6 bidders i.e., L1 to L6 bidders would be allowed in the RA process. Balance, H1 to H4 bidders would not be allowed in the RA process.
A8: Price () | B8: The line-item prices shall be subject to Price variation clause as per latest IEEMA circular for Medium Voltage Covered Conductors.
A9: Validity () | B9: Bids shall remain valid for 180 days from the due date of submission of the bid. Notwithstanding clause above, CCG may solicit the Bidder’s consent to an extension of the Period of Bid Validity. The request and responses thereto shall be made in writing.
A10: Delivery Period () | B10: Delivery Period shall be 60 Days from date of receipt of release order / CAT-A GTP approval, whichever is later.
A11: Payment Terms ()
A12: Standard length () | B12: Standard Packing length - 1000 (+/- 5%) as per PO terms
A13: Packing () | B13: The Conductor shall be wound on wooden/STEEL drums and packed in line with requirements of IS 10418- 1982. The ends of the Conductor shall be sealed by means of non-hygroscopic sealing material. Heat or cold Shrinkable end caps with sealant shall be used for effectively sealing the end terminals of the covered conductor. The inner diameter range of cap shall be such that it shall tightly fit to the covered conductors to prevent moisture ingress.
A14: Technical Specification
N16: =Sheet1!J1 -> Conductor | S16: AL ALLOY | U16: Insulation Screening (Metallic) | AC16: Insulation Screening (Non-Metallic) | AE16: Insulation | AK16: POLY TAPE | AL16: Inner Sheath | AS16: Armouring | BC16: Outer Sheath | BM16: FILLER | BN16: GREASE | BO16: Water swellable Tape | BP16: Semi conducting Water Swellable tape | BQ16: SEMICON TAPE | BR16: GLASS FIBER TAPE | BS16: COPPER WIRE 0.8 MM | BT16: RUBBERIZED COTTON TAPE | BU16: Water Tight Compound | BZ16: DRUM COST PER KM | CA16: TOTAL RM COST | CB16: EXTRA CONSUMPTION | CC16: EXTRA CONSUMPTION VALUE
A17: DOCKET NO. | B17: =Sheet1!B1 -> Base Date | C17: ITEM CODE | D17: PROPOSE ERP ITEM NAME | E17: EX-WORKS (PER KM) | F17: FREIGHT PER KM | G17: PRICE INCLUDING FREIGHT (PER KM) | H17: GST % | I17: GST VALUE | J17: PRICE INCLUDING GST & FREIGHT (PER KM) | K17: QTY | L17: Unit | M17: TOTAL PRICE OF FULL QTY (INCLUDING FRIGHT & GST) | N17: Alumimium | O17: AL 59 | P17: Copper | Q17: Flexible Copper | R17: Galvanized steel wire | S17: Alumimium | U17: Coper tape - 0.1 mm | V17: Copper Tape - 0.03 mm | W17: Copper Tape - 0.035 mm | X17: Copper Tape - 0.04 mm | Y17: Copper Tape - 0.045 mm | Z17: Copper Tape - 0.050 mm | AA17: Copper Tape - 0.060 mm | AB17: Copper Tape - 0.075 mm(DOUBLE) | AC17: Extruded semiconductive | AD17: Extruded Semiconductive(Stripable) | AE17: HT-XLPE | AF17: LT-XLPE | AG17: TR XLPE | AH17: Type A PVC | AI17: Type C PVC (HR) | AJ17: XLPE | AK17: POLY TAPE | AL17: FR PVC Type ST-1 | AM17: FR PVC Type ST-2 | AN17: FRLSH PVC Type ST-2 | AO17: PVC Type ST-1 | AP17: PVC Type ST-1-PRESSURE EXTRUDED | AQ17: PVC Type ST-2 | AR17: PVC Type ST-2-PRESSURE EXTRUDED | AS17: ACSR CORE WIRE | AT17: ACSR DOG STEEL WIRE | AU17: Aluminium Flat Strip | AV17: Aluminium Round Wire | AW17: Double Steel Tape | AX17: Galvanised Steel Flat Strip | AY17: Galvanised Steel Flat Strip (Double) | AZ17: Galvanised Steel Flat Strip-B | BA17: Galvanised Steel Round Wire | BB17: Galvanised Steel Round Wire (Double) | BC17: FR PVC Type ST-1 | BD17: FR PVC Type ST-2 | BE17: FRLSH PVC Type ST-1 | BF17: FRLSH PVC Type ST-2 | BG17: PE, ST-3 | BH17: PE, ST-7 | BI17: PVC Type ST-1 | BJ17: PVC Type ST-2 | BK17: PVC Type ST-2-PRESSURE EXTRUDED | BL17: UV & Track Resistant XLPE | BM17: FILLER | BN17: Grease | BO17: Water swellable Tape | BP17: Semi conducting Water Swellable tape | BQ17: SEMICON TAPE | BR17: GLASS FIBER TAPE | BS17: COPPER WIRE 0.8 MM | BT17: RUBBERIZED COTTON TAPE | BU17: Water Tight Compound | BV17: =Sheet1!E1 -> Propose Drum Type | BW17: =Sheet1!CV1 -> DRUM CODE | BX17: =Sheet1!CW1 -> DRUM SIZE (FxbXtx Ft) | BY17: =Sheet1!CX1 -> Party Standard Length(MTR) | CD17: MFG% | CE17: MFG VALUE | CF17: PROF% | CG17: PROFIT VALUE | CH17: 1ST EX-WORKS | CI17: Intt % | CJ17: INTT VALUE | CK17: insp% | CL17: INSP VALUE
N18: =+IFERROR(VLOOKUP($N$17,Sheet1!J:L,2,0),0) -> 0 | O18: 284 | AC18: 175 | AE18: 160 | BL18: 235 | BU18: 210
A19: =Sheet1!A4 -> ENQ-15214-22-23 | B19: 45658 | C19: =Sheet1!C4 -> FA2900029 | D19: =Sheet1!D4 -> COVERED CONDUCTOR - 1 CORE X 55 SQ. MM. (AAAC) - 11 KV | E19: =CH19+CJ19+CL19 -> 107898.94 | F19: =ROUNDUP(M28,0) -> 1522 | G19: =E19+F19 -> 109420.94 | H19: =Sheet1!CP4 -> 0.18 | I19: =G19*H19 -> 19695.769 | J19: =G19+I19 -> 129116.71 | K19: =Sheet1!CS4 -> 23 | L19: =Sheet1!CT4 -> KMS | M19: =J19*K19 -> 2969684.2 | N19: =+IFERROR(VLOOKUP($N$17,Sheet1!J4:L4,3,0),0) -> 0 | O19: 150 | P19: =+IFERROR(VLOOKUP($P$17,Sheet1!J4:M4,3,0),0) -> 0 | Q19: =+IFERROR(VLOOKUP($Q$17,Sheet1!J4:M4,3,0),0) -> 0 | R19: =+IFERROR(VLOOKUP($R$17,Sheet1!J4:M4,3,0),0) -> 0 | S19: =+IFERROR(VLOOKUP($S$17,Sheet1!N4:Q4,3,0),0) -> 0 | T19: =+IFERROR(VLOOKUP($T$17,Sheet1!N4:Q4,3,0),0) -> 0 | U19: =+IFERROR(VLOOKUP($U$17,Sheet1!F4:I4,3,0),0) -> 0 | V19: =+IFERROR(VLOOKUP($V$17,Sheet1!F4:I4,3,0),0) -> 0 | W19: =+IFERROR(VLOOKUP($W$17,Sheet1!F4:I4,3,0),0) -> 0 | X19: =+IFERROR(VLOOKUP($X$17,Sheet1!F4:I4,3,0),0) -> 0 | Y19: =+IFERROR(VLOOKUP($Y$17,Sheet1!F4:I4,3,0),0) -> 0 | Z19: =+IFERROR(VLOOKUP($Z$17,Sheet1!F4:I4,3,0),0) -> 0 | AA19: =+IFERROR(VLOOKUP($AA$17,Sheet1!F4:I4,3,0),0) -> 0 | AB19: =+IFERROR(VLOOKUP($AB$17,Sheet1!F4:I4,3,0),0) -> 0 | AC19: 40 | AD19: =+IFERROR(VLOOKUP($AD$17,Sheet1!R4:U4,2,0),0) -> 0 | AE19: 48 | AF19: =+IFERROR(VLOOKUP($AF$17,Sheet1!V4:Y4,3,0),0) -> 0 | AG19: =+IFERROR(VLOOKUP($AG$17,Sheet1!V4:Y4,3,0),0) -> 0 | AH19: =+IFERROR(VLOOKUP($AH$17,Sheet1!V4:Y4,3,0),0) -> 0 | AI19: =+IFERROR(VLOOKUP($AI$17,Sheet1!V4:Y4,3,0),0) -> 0 | AJ19: =+IFERROR(VLOOKUP($AJ$17,Sheet1!V4:Y4,3,0),0) -> 0 | AK19: =+IFERROR(VLOOKUP($AK$17,Sheet1!Z4:AB4,3,0),0) -> 0 | AL19: =+IFERROR(VLOOKUP($AL$17,Sheet1!AD4:AG4,3,0),0) -> 0 | AM19: =+IFERROR(VLOOKUP($AM$17,Sheet1!AD4:AG4,3,0),0) -> 0 | AN19: =+IFERROR(VLOOKUP($AN$17,Sheet1!AD4:AG4,3,0),0) -> 0 | AO19: =+IFERROR(VLOOKUP($AO$17,Sheet1!AD4:AG4,3,0),0) -> 0 | AP19: =+IFERROR(VLOOKUP($AP$17,Sheet1!AD4:AG4,3,0),0) -> 0 | AQ19: =+IFERROR(VLOOKUP($AQ$17,Sheet1!AD4:AG4,3,0),0) -> 0 | AR19: =+IFERROR(VLOOKUP($AR$17,Sheet1!AD4:AG4,3,0),0) -> 0 | AS19: =+IFERROR(VLOOKUP($AS$17,Sheet1!AH4:AK4,3,0),0) -> 0 | AT19: =+IFERROR(VLOOKUP($AT$17,Sheet1!AH4:AK4,3,0),0) -> 0 | AU19: =+IFERROR(VLOOKUP($AU$17,Sheet1!AH4:AK4,3,0),0) -> 0 | AV19: =+IFERROR(VLOOKUP($AV$17,Sheet1!AH4:AK4,3,0),0) -> 0 | AW19: =+IFERROR(VLOOKUP($AW$17,Sheet1!AH4:AK4,3,0),0) -> 0 | AX19: =+IFERROR(VLOOKUP($AX$17,Sheet1!AH4:AK4,3,0),0) -> 0 | AY19: =+IFERROR(VLOOKUP($AY$17,Sheet1!AH4:AK4,3,0),0) -> 0 | AZ19: =+IFERROR(VLOOKUP($AZ$17,Sheet1!AH4:AK4,3,0),0) -> 0 | BA19: =+IFERROR(VLOOKUP($BA$17,Sheet1!AH4:AK4,3,0),0) -> 0 | BB19: =+IFERROR(VLOOKUP($BB$17,Sheet1!AH4:AK4,3,0),0) -> 0 | BC19: =+IFERROR(VLOOKUP($BC$17,Sheet1!AL4:AO4,3,0),0) -> 0 | BD19: =+IFERROR(VLOOKUP($BD$17,Sheet1!AL4:AO4,3,0),0) -> 0 | BE19: =+IFERROR(VLOOKUP($BE$17,Sheet1!AL4:AO4,3,0),0) -> 0 | BF19: =+IFERROR(VLOOKUP($BF$17,Sheet1!AL4:AO4,3,0),0) -> 0 | BG19: =+IFERROR(VLOOKUP($BG$17,Sheet1!AL4:AO4,3,0),0) -> 0 | BH19: =+IFERROR(VLOOKUP($BH$17,Sheet1!AL4:AO4,3,0),0) -> 0 | BI19: =+IFERROR(VLOOKUP($BI$17,Sheet1!AL4:AO4,3,0),0) -> 0 | BJ19: =+IFERROR(VLOOKUP($BJ$17,Sheet1!AL4:AO4,3,0),0) -> 0 | BK19: =+IFERROR(VLOOKUP($BK$17,Sheet1!AL4:AO4,3,0),0) -> 0 | BL19: 65 | BM19: =+IFERROR(VLOOKUP($BM$17,Sheet1!AP4:AS4,3,0),0) -> 0 | BN19: =+IFERROR(VLOOKUP($BN$17,Sheet1!AT4:AW4,3,0),0) -> 0 | BO19: =+IFERROR(VLOOKUP($BO$17,Sheet1!AX4:BA4,3,0),0) -> 0 | BP19: =+IFERROR(VLOOKUP($BP$17,Sheet1!BB4:BE4,3,0),0) -> 0 | BQ19: =+IFERROR(VLOOKUP($BQ$17,Sheet1!BF4:BI4,3,0),0) -> 0 | BR19: =+IFERROR(VLOOKUP($BR$17,Sheet1!BJ4:BM4,3,0),0) -> 0 | BS19: =+IFERROR(VLOOKUP($BS$17,Sheet1!BN4:BQ4,3,0),0) -> 0 | BT19: =+IFERROR(VLOOKUP($BT$17,Sheet1!BR4:BU4,3,0),0) -> 0 | BU19: 15 | BV19: STEEL | BW19: SP0400144 | BX19: CORRUGATED DISPATCH STEEL DRUM 1060 X 600 X 965 MM | BY19: 1000 | BZ19: 8100 | CA19: =SUMPRODUCT($N$18:$BU$18,N19:BU19)+BZ19 -> 83805 | CB19: =Sheet1!CB4 -> 0 | CC19: =CA19*CB19 -> 0 | CD19: 0.25 | CE19: =CA19*CD19 -> 20951.25 | CF19: 0 | CG19: =CA19*CF19 -> 0 | CH19: =CA19+CC19+CE19+CG19 -> 104756.25 | CI19: 0.02 | CJ19: =CH19*CI19 -> 2095.125 | CK19: 0.01 | CL19: =CH19*CK19 -> 1047.5625
A20: =Sheet1!A6 -> ENQ-15214-22-23 | B20: 45658 | C20: =Sheet1!C6 -> FA2900034 | D20: =Sheet1!D6 -> COVERED CONDUCTOR - 1 CORE X 80 SQ. MM. (AAAC) - 11 KV | E20: =CH20+CJ20+CL20 -> 139366.73 | F20: =ROUNDUP(M29,0) -> 2184 | G20: =E20+F20 -> 141550.73 | H20: =Sheet1!CP6 -> 0.18 | I20: =G20*H20 -> 25479.13 | J20: =G20+I20 -> 167029.86 | K20: =Sheet1!CS6 -> 48.085 | L20: =Sheet1!CT6 -> KMS | M20: =J20*K20 -> 8031630.6 | N20: =+IFERROR(VLOOKUP($N$17,Sheet1!J6:L6,3,0),0) -> 0 | O20: 219 | P20: =+IFERROR(VLOOKUP($P$17,Sheet1!J6:M6,3,0),0) -> 0 | Q20: =+IFERROR(VLOOKUP($Q$17,Sheet1!J6:M6,3,0),0) -> 0 | R20: =+IFERROR(VLOOKUP($R$17,Sheet1!J6:M6,3,0),0) -> 0 | S20: =+IFERROR(VLOOKUP($S$17,Sheet1!N6:Q6,3,0),0) -> 0 | T20: =+IFERROR(VLOOKUP($T$17,Sheet1!N6:Q6,3,0),0) -> 0 | U20: =+IFERROR(VLOOKUP($U$17,Sheet1!F6:I6,3,0),0) -> 0 | V20: =+IFERROR(VLOOKUP($V$17,Sheet1!F6:I6,3,0),0) -> 0 | W20: =+IFERROR(VLOOKUP($W$17,Sheet1!F6:I6,3,0),0) -> 0 | X20: =+IFERROR(VLOOKUP($X$17,Sheet1!F6:I6,3,0),0) -> 0 | Y20: =+IFERROR(VLOOKUP($Y$17,Sheet1!F6:I6,3,0),0) -> 0 | Z20: =+IFERROR(VLOOKUP($Z$17,Sheet1!F6:I6,3,0),0) -> 0 | AA20: =+IFERROR(VLOOKUP($AA$17,Sheet1!F6:I6,3,0),0) -> 0 | AB20: =+IFERROR(VLOOKUP($AB$17,Sheet1!F6:I6,3,0),0) -> 0 | AC20: 48 | AD20: =+IFERROR(VLOOKUP($AD$17,Sheet1!R6:U6,2,0),0) -> 0 | AE20: 55 | AF20: =+IFERROR(VLOOKUP($AF$17,Sheet1!V6:Y6,3,0),0) -> 0 | AG20: =+IFERROR(VLOOKUP($AG$17,Sheet1!V6:Y6,3,0),0) -> 0 | AH20: =+IFERROR(VLOOKUP($AH$17,Sheet1!V6:Y6,3,0),0) -> 0 | AI20: =+IFERROR(VLOOKUP($AI$17,Sheet1!V6:Y6,3,0),0) -> 0 | AJ20: =+IFERROR(VLOOKUP($AJ$17,Sheet1!V6:Y6,3,0),0) -> 0 | AK20: =+IFERROR(VLOOKUP($AK$17,Sheet1!Z6:AB6,3,0),0) -> 0 | AL20: =+IFERROR(VLOOKUP($AL$17,Sheet1!AD6:AG6,3,0),0) -> 0 | AM20: =+IFERROR(VLOOKUP($AM$17,Sheet1!AD6:AG6,3,0),0) -> 0 | AN20: =+IFERROR(VLOOKUP($AN$17,Sheet1!AD6:AG6,3,0),0) -> 0 | AO20: =+IFERROR(VLOOKUP($AO$17,Sheet1!AD6:AG6,3,0),0) -> 0 | AP20: =+IFERROR(VLOOKUP($AP$17,Sheet1!AD6:AG6,3,0),0) -> 0 | AQ20: =+IFERROR(VLOOKUP($AQ$17,Sheet1!AD6:AG6,3,0),0) -> 0 | AR20: =+IFERROR(VLOOKUP($AR$17,Sheet1!AD6:AG6,3,0),0) -> 0 | AS20: =+IFERROR(VLOOKUP($AS$17,Sheet1!AH6:AK6,3,0),0) -> 0 | AT20: =+IFERROR(VLOOKUP($AT$17,Sheet1!AH6:AK6,3,0),0) -> 0 | AU20: =+IFERROR(VLOOKUP($AU$17,Sheet1!AH6:AK6,3,0),0) -> 0 | AV20: =+IFERROR(VLOOKUP($AV$17,Sheet1!AH6:AK6,3,0),0) -> 0 | AW20: =+IFERROR(VLOOKUP($AW$17,Sheet1!AH6:AK6,3,0),0) -> 0 | AX20: =+IFERROR(VLOOKUP($AX$17,Sheet1!AH6:AK6,3,0),0) -> 0 | AY20: =+IFERROR(VLOOKUP($AY$17,Sheet1!AH6:AK6,3,0),0) -> 0 | AZ20: =+IFERROR(VLOOKUP($AZ$17,Sheet1!AH6:AK6,3,0),0) -> 0 | BA20: =+IFERROR(VLOOKUP($BA$17,Sheet1!AH6:AK6,3,0),0) -> 0 | BB20: =+IFERROR(VLOOKUP($BB$17,Sheet1!AH6:AK6,3,0),0) -> 0 | BC20: =+IFERROR(VLOOKUP($BC$17,Sheet1!AL6:AO6,3,0),0) -> 0 | BD20: =+IFERROR(VLOOKUP($BD$17,Sheet1!AL6:AO6,3,0),0) -> 0 | BE20: =+IFERROR(VLOOKUP($BE$17,Sheet1!AL6:AO6,3,0),0) -> 0 | BF20: =+IFERROR(VLOOKUP($BF$17,Sheet1!AL6:AO6,3,0),0) -> 0 | BG20: =+IFERROR(VLOOKUP($BG$17,Sheet1!AL6:AO6,3,0),0) -> 0 | BH20: =+IFERROR(VLOOKUP($BH$17,Sheet1!AL6:AO6,3,0),0) -> 0 | BI20: =+IFERROR(VLOOKUP($BI$17,Sheet1!AL6:AO6,3,0),0) -> 0 | BJ20: =+IFERROR(VLOOKUP($BJ$17,Sheet1!AL6:AO6,3,0),0) -> 0 | BK20: =+IFERROR(VLOOKUP($BK$17,Sheet1!AL6:AO6,3,0),0) -> 0 | BL20: 74 | BM20: =+IFERROR(VLOOKUP($BM$17,Sheet1!AP6:AS6,3,0),0) -> 0 | BN20: =+IFERROR(VLOOKUP($BN$17,Sheet1!AT6:AW6,3,0),0) -> 0 | BO20: =+IFERROR(VLOOKUP($BO$17,Sheet1!AX6:BA6,3,0),0) -> 0 | BP20: =+IFERROR(VLOOKUP($BP$17,Sheet1!BB6:BE6,3,0),0) -> 0 | BQ20: =+IFERROR(VLOOKUP($BQ$17,Sheet1!BF6:BI6,3,0),0) -> 0 | BR20: =+IFERROR(VLOOKUP($BR$17,Sheet1!BJ6:BM6,3,0),0) -> 0 | BS20: =+IFERROR(VLOOKUP($BS$17,Sheet1!BN6:BQ6,3,0),0) -> 0 | BT20: =+IFERROR(VLOOKUP($BT$17,Sheet1!BR6:BU6,3,0),0) -> 0 | BU20: 16 | BV20: STEEL | BW20: SP0400144 | BX20: CORRUGATED DISPATCH STEEL DRUM 1060 X 600 X 965 MM | BY20: 1000 | BZ20: 8100 | CA20: =SUMPRODUCT($N$18:$BU$18,N20:BU20)+BZ20 -> 108246 | CB20: =Sheet1!CB6 -> 0 | CC20: =CA20*CB20 -> 0 | CD20: 0.25 | CE20: =CA20*CD20 -> 27061.5 | CF20: 0 | CG20: =CA20*CF20 -> 0 | CH20: =CA20+CC20+CE20+CG20 -> 135307.5 | CI20: 0.02 | CJ20: =CH20*CI20 -> 2706.15 | CK20: 0.01 | CL20: =CH20*CK20 -> 1353.075
A21: =Sheet1!A2 -> ENQ-15214-22-23 | B21: 45658 | C21: =Sheet1!C2 -> FA2900004 | D21: =Sheet1!D2 -> COVERED CONDUCTOR - 1 CORE x 100 SQ. MM. (AAAC) - 11KV | E21: =CH21+CJ21+CL21 -> 163309.07 | F21: =ROUNDUP(M30,0) -> 1463 | G21: =E21+F21 -> 164772.07 | H21: =Sheet1!CP2 -> 0.18 | I21: =G21*H21 -> 29658.973 | J21: =G21+I21 -> 194431.05 | K21: =Sheet1!CS2 -> 1220.919 | L21: =Sheet1!CT2 -> KMS | M21: =J21*K21 -> 2.3738456e+08 | N21: =+IFERROR(VLOOKUP($N$17,Sheet1!J2:L2,3,0),0) -> 0 | O21: 273 | P21: =+IFERROR(VLOOKUP($P$17,Sheet1!J2:M2,3,0),0) -> 0 | Q21: =+IFERROR(VLOOKUP($Q$17,Sheet1!J2:M2,3,0),0) -> 0 | R21: =+IFERROR(VLOOKUP($R$17,Sheet1!J2:M2,3,0),0) -> 0 | S21: =+IFERROR(VLOOKUP($S$17,Sheet1!N2:Q2,3,0),0) -> 0 | T21: =+IFERROR(VLOOKUP($T$17,Sheet1!N2:Q2,3,0),0) -> 0 | U21: =+IFERROR(VLOOKUP($U$17,Sheet1!F2:I2,3,0),0) -> 0 | V21: =+IFERROR(VLOOKUP($V$17,Sheet1!F2:I2,3,0),0) -> 0 | W21: =+IFERROR(VLOOKUP($W$17,Sheet1!F2:I2,3,0),0) -> 0 | X21: =+IFERROR(VLOOKUP($X$17,Sheet1!F2:I2,3,0),0) -> 0 | Y21: =+IFERROR(VLOOKUP($Y$17,Sheet1!F2:I2,3,0),0) -> 0 | Z21: =+IFERROR(VLOOKUP($Z$17,Sheet1!F2:I2,3,0),0) -> 0 | AA21: =+IFERROR(VLOOKUP($AA$17,Sheet1!F2:I2,3,0),0) -> 0 | AB21: =+IFERROR(VLOOKUP($AB$17,Sheet1!F2:I2,3,0),0) -> 0 | AC21: 54 | AD21: =+IFERROR(VLOOKUP($AD$17,Sheet1!R2:U2,2,0),0) -> 0 | AE21: 60 | AF21: =+IFERROR(VLOOKUP($AF$17,Sheet1!V2:Y2,3,0),0) -> 0 | AG21: =+IFERROR(VLOOKUP($AG$17,Sheet1!V2:Y2,3,0),0) -> 0 | AH21: =+IFERROR(VLOOKUP($AH$17,Sheet1!V2:Y2,3,0),0) -> 0 | AI21: =+IFERROR(VLOOKUP($AI$17,Sheet1!V2:Y2,3,0),0) -> 0 | AJ21: =+IFERROR(VLOOKUP($AJ$17,Sheet1!V2:Y2,3,0),0) -> 0 | AK21: =+IFERROR(VLOOKUP($AK$17,Sheet1!Z2:AB2,3,0),0) -> 0 | AL21: =+IFERROR(VLOOKUP($AL$17,Sheet1!AD2:AG2,3,0),0) -> 0 | AM21: =+IFERROR(VLOOKUP($AM$17,Sheet1!AD2:AG2,3,0),0) -> 0 | AN21: =+IFERROR(VLOOKUP($AN$17,Sheet1!AD2:AG2,3,0),0) -> 0 | AO21: =+IFERROR(VLOOKUP($AO$17,Sheet1!AD2:AG2,3,0),0) -> 0 | AP21: =+IFERROR(VLOOKUP($AP$17,Sheet1!AD2:AG2,3,0),0) -> 0 | AQ21: =+IFERROR(VLOOKUP($AQ$17,Sheet1!AD2:AG2,3,0),0) -> 0 | AR21: =+IFERROR(VLOOKUP($AR$17,Sheet1!AD2:AG2,3,0),0) -> 0 | AS21: =+IFERROR(VLOOKUP($AS$17,Sheet1!AH2:AK2,3,0),0) -> 0 | AT21: =+IFERROR(VLOOKUP($AT$17,Sheet1!AH2:AK2,3,0),0) -> 0 | AU21: =+IFERROR(VLOOKUP($AU$17,Sheet1!AH2:AK2,3,0),0) -> 0 | AV21: =+IFERROR(VLOOKUP($AV$17,Sheet1!AH2:AK2,3,0),0) -> 0 | AW21: =+IFERROR(VLOOKUP($AW$17,Sheet1!AH2:AK2,3,0),0) -> 0 | AX21: =+IFERROR(VLOOKUP($AX$17,Sheet1!AH2:AK2,3,0),0) -> 0 | AY21: =+IFERROR(VLOOKUP($AY$17,Sheet1!AH2:AK2,3,0),0) -> 0 | AZ21: =+IFERROR(VLOOKUP($AZ$17,Sheet1!AH2:AK2,3,0),0) -> 0 | BA21: =+IFERROR(VLOOKUP($BA$17,Sheet1!AH2:AK2,3,0),0) -> 0 | BB21: =+IFERROR(VLOOKUP($BB$17,Sheet1!AH2:AK2,3,0),0) -> 0 | BC21: =+IFERROR(VLOOKUP($BC$17,Sheet1!AL2:AO2,3,0),0) -> 0 | BD21: =+IFERROR(VLOOKUP($BD$17,Sheet1!AL2:AO2,3,0),0) -> 0 | BE21: =+IFERROR(VLOOKUP($BE$17,Sheet1!AL2:AO2,3,0),0) -> 0 | BF21: =+IFERROR(VLOOKUP($BF$17,Sheet1!AL2:AO2,3,0),0) -> 0 | BG21: =+IFERROR(VLOOKUP($BG$17,Sheet1!AL2:AO2,3,0),0) -> 0 | BH21: =+IFERROR(VLOOKUP($BH$17,Sheet1!AL2:AO2,3,0),0) -> 0 | BI21: =+IFERROR(VLOOKUP($BI$17,Sheet1!AL2:AO2,3,0),0) -> 0 | BJ21: =+IFERROR(VLOOKUP($BJ$17,Sheet1!AL2:AO2,3,0),0) -> 0 | BK21: =+IFERROR(VLOOKUP($BK$17,Sheet1!AL2:AO2,3,0),0) -> 0 | BL21: 80 | BM21: =+IFERROR(VLOOKUP($BM$17,Sheet1!AP2:AS2,3,0),0) -> 0 | BN21: =+IFERROR(VLOOKUP($BN$17,Sheet1!AT2:AW2,3,0),0) -> 0 | BO21: =+IFERROR(VLOOKUP($BO$17,Sheet1!AX2:BA2,3,0),0) -> 0 | BP21: =+IFERROR(VLOOKUP($BP$17,Sheet1!BB2:BE2,3,0),0) -> 0 | BQ21: =+IFERROR(VLOOKUP($BQ$17,Sheet1!BF2:BI2,3,0),0) -> 0 | BR21: =+IFERROR(VLOOKUP($BR$17,Sheet1!BJ2:BM2,3,0),0) -> 0 | BS21: =+IFERROR(VLOOKUP($BS$17,Sheet1!BN2:BQ2,3,0),0) -> 0 | BT21: =+IFERROR(VLOOKUP($BT$17,Sheet1!BR2:BU2,3,0),0) -> 0 | BU21: 16 | BV21: STEEL | BW21: SP0400144 | BX21: CORRUGATED DISPATCH STEEL DRUM 1060 X 600 X 965 MM | BY21: 1000 | BZ21: 8100 | CA21: =SUMPRODUCT($N$18:$BU$18,N21:BU21)+BZ21 -> 126842 | CB21: =Sheet1!CB2 -> 0 | CC21: =CA21*CB21 -> 0 | CD21: 0.25 | CE21: =CA21*CD21 -> 31710.5 | CF21: 0 | CG21: =CA21*CF21 -> 0 | CH21: =CA21+CC21+CE21+CG21 -> 158552.5 | CI21: 0.02 | CJ21: =CH21*CI21 -> 3171.05 | CK21: 0.01 | CL21: =CH21*CK21 -> 1585.525
A22: =Sheet1!A3 -> ENQ-15214-22-23 | B22: 45658 | C22: =Sheet1!C3 -> FA2900008 | D22: =Sheet1!D3 -> COVERED CONDUCTOR - 1 CORE X 99 SQ. MM. (AAAC) - 33 KV | E22: =CH22+CJ22+CL22 -> 186033.45 | F22: =ROUNDUP(M31,0) -> 2059 | G22: =E22+F22 -> 188092.45 | H22: =Sheet1!CP3 -> 0.18 | I22: =G22*H22 -> 33856.641 | J22: =G22+I22 -> 221949.09 | K22: 85 | L22: =Sheet1!CT3 -> KMS | M22: =J22*K22 -> 18865673 | N22: =+IFERROR(VLOOKUP($N$17,Sheet1!J3:L3,3,0),0) -> 0 | O22: 273 | P22: =+IFERROR(VLOOKUP($P$17,Sheet1!J3:M3,3,0),0) -> 0 | Q22: =+IFERROR(VLOOKUP($Q$17,Sheet1!J3:M3,3,0),0) -> 0 | R22: =+IFERROR(VLOOKUP($R$17,Sheet1!J3:M3,3,0),0) -> 0 | S22: =+IFERROR(VLOOKUP($S$17,Sheet1!N3:Q3,3,0),0) -> 0 | T22: =+IFERROR(VLOOKUP($T$17,Sheet1!N3:Q3,3,0),0) -> 0 | U22: =+IFERROR(VLOOKUP($U$17,Sheet1!F3:I3,3,0),0) -> 0 | V22: =+IFERROR(VLOOKUP($V$17,Sheet1!F3:I3,3,0),0) -> 0 | W22: =+IFERROR(VLOOKUP($W$17,Sheet1!F3:I3,3,0),0) -> 0 | X22: =+IFERROR(VLOOKUP($X$17,Sheet1!F3:I3,3,0),0) -> 0 | Y22: =+IFERROR(VLOOKUP($Y$17,Sheet1!F3:I3,3,0),0) -> 0 | Z22: =+IFERROR(VLOOKUP($Z$17,Sheet1!F3:I3,3,0),0) -> 0 | AA22: =+IFERROR(VLOOKUP($AA$17,Sheet1!F3:I3,3,0),0) -> 0 | AB22: =+IFERROR(VLOOKUP($AB$17,Sheet1!F3:I3,3,0),0) -> 0 | AC22: 54 | AD22: =+IFERROR(VLOOKUP($AD$17,Sheet1!R3:U3,2,0),0) -> 0 | AE22: 127 | AF22: =+IFERROR(VLOOKUP($AF$17,Sheet1!V3:Y3,3,0),0) -> 0 | AG22: =+IFERROR(VLOOKUP($AG$17,Sheet1!V3:Y3,3,0),0) -> 0 | AH22: =+IFERROR(VLOOKUP($AH$17,Sheet1!V3:Y3,3,0),0) -> 0 | AI22: =+IFERROR(VLOOKUP($AI$17,Sheet1!V3:Y3,3,0),0) -> 0 | AJ22: =+IFERROR(VLOOKUP($AJ$17,Sheet1!V3:Y3,3,0),0) -> 0 | AK22: =+IFERROR(VLOOKUP($AK$17,Sheet1!Z3:AB3,3,0),0) -> 0 | AL22: =+IFERROR(VLOOKUP($AL$17,Sheet1!AD3:AG3,3,0),0) -> 0 | AM22: =+IFERROR(VLOOKUP($AM$17,Sheet1!AD3:AG3,3,0),0) -> 0 | AN22: =+IFERROR(VLOOKUP($AN$17,Sheet1!AD3:AG3,3,0),0) -> 0 | AO22: =+IFERROR(VLOOKUP($AO$17,Sheet1!AD3:AG3,3,0),0) -> 0 | AP22: =+IFERROR(VLOOKUP($AP$17,Sheet1!AD3:AG3,3,0),0) -> 0 | AQ22: =+IFERROR(VLOOKUP($AQ$17,Sheet1!AD3:AG3,3,0),0) -> 0 | AR22: =+IFERROR(VLOOKUP($AR$17,Sheet1!AD3:AG3,3,0),0) -> 0 | AS22: =+IFERROR(VLOOKUP($AS$17,Sheet1!AH3:AK3,3,0),0) -> 0 | AT22: =+IFERROR(VLOOKUP($AT$17,Sheet1!AH3:AK3,3,0),0) -> 0 | AU22: =+IFERROR(VLOOKUP($AU$17,Sheet1!AH3:AK3,3,0),0) -> 0 | AV22: =+IFERROR(VLOOKUP($AV$17,Sheet1!AH3:AK3,3,0),0) -> 0 | AW22: =+IFERROR(VLOOKUP($AW$17,Sheet1!AH3:AK3,3,0),0) -> 0 | AX22: =+IFERROR(VLOOKUP($AX$17,Sheet1!AH3:AK3,3,0),0) -> 0 | AY22: =+IFERROR(VLOOKUP($AY$17,Sheet1!AH3:AK3,3,0),0) -> 0 | AZ22: =+IFERROR(VLOOKUP($AZ$17,Sheet1!AH3:AK3,3,0),0) -> 0 | BA22: =+IFERROR(VLOOKUP($BA$17,Sheet1!AH3:AK3,3,0),0) -> 0 | BB22: =+IFERROR(VLOOKUP($BB$17,Sheet1!AH3:AK3,3,0),0) -> 0 | BC22: =+IFERROR(VLOOKUP($BC$17,Sheet1!AL3:AO3,3,0),0) -> 0 | BD22: =+IFERROR(VLOOKUP($BD$17,Sheet1!AL3:AO3,3,0),0) -> 0 | BE22: =+IFERROR(VLOOKUP($BE$17,Sheet1!AL3:AO3,3,0),0) -> 0 | BF22: =+IFERROR(VLOOKUP($BF$17,Sheet1!AL3:AO3,3,0),0) -> 0 | BG22: =+IFERROR(VLOOKUP($BG$17,Sheet1!AL3:AO3,3,0),0) -> 0 | BH22: =+IFERROR(VLOOKUP($BH$17,Sheet1!AL3:AO3,3,0),0) -> 0 | BI22: =+IFERROR(VLOOKUP($BI$17,Sheet1!AL3:AO3,3,0),0) -> 0 | BJ22: =+IFERROR(VLOOKUP($BJ$17,Sheet1!AL3:AO3,3,0),0) -> 0 | BK22: =+IFERROR(VLOOKUP($BK$17,Sheet1!AL3:AO3,3,0),0) -> 0 | BL22: 98 | BM22: =+IFERROR(VLOOKUP($BM$17,Sheet1!AP3:AS3,3,0),0) -> 0 | BN22: =+IFERROR(VLOOKUP($BN$17,Sheet1!AT3:AW3,3,0),0) -> 0 | BO22: =+IFERROR(VLOOKUP($BO$17,Sheet1!AX3:BA3,3,0),0) -> 0 | BP22: =+IFERROR(VLOOKUP($BP$17,Sheet1!BB3:BE3,3,0),0) -> 0 | BQ22: =+IFERROR(VLOOKUP($BQ$17,Sheet1!BF3:BI3,3,0),0) -> 0 | BR22: =+IFERROR(VLOOKUP($BR$17,Sheet1!BJ3:BM3,3,0),0) -> 0 | BS22: =+IFERROR(VLOOKUP($BS$17,Sheet1!BN3:BQ3,3,0),0) -> 0 | BT22: =+IFERROR(VLOOKUP($BT$17,Sheet1!BR3:BU3,3,0),0) -> 0 | BU22: 16 | BV22: STEEL | BW22: SP0400124 | BX22: CORRUGATED DISPATCH STEEL DRUM 1220 X 550 X 915 MM | BY22: 1000 | BZ22: 10800 | CA22: =SUMPRODUCT($N$18:$BU$18,N22:BU22)+BZ22 -> 144492 | CB22: =Sheet1!CB3 -> 0 | CC22: =CA22*CB22 -> 0 | CD22: 0.25 | CE22: =CA22*CD22 -> 36123 | CF22: 0 | CG22: =CA22*CF22 -> 0 | CH22: =CA22+CC22+CE22+CG22 -> 180615 | CI22: 0.02 | CJ22: =CH22*CI22 -> 3612.3 | CK22: 0.01 | CL22: =CH22*CK22 -> 1806.15
A23: =Sheet1!A7 -> ENQ-15214-22-23 | B23: 45658 | C23: =Sheet1!C7 -> FA2900014 | D23: =Sheet1!D7 -> COVERED CONDUCTOR - 1 CORE x 150 SQ. MM. (XLPE) (AAAC) - 33 KV | E23: =CH23+CJ23+CL23 -> 249650.11 | F23: =ROUNDUP(M32,0) -> 2261 | G23: =E23+F23 -> 251911.11 | H23: =Sheet1!CP7 -> 0.18 | I23: =G23*H23 -> 45344 | J23: =G23+I23 -> 297255.11 | K23: 263.175 | L23: =Sheet1!CT7 -> KMS | M23: =J23*K23 -> 78230114 | N23: =+IFERROR(VLOOKUP($N$17,Sheet1!J7:L7,3,0),0) -> 0 | O23: 407 | P23: =+IFERROR(VLOOKUP($P$17,Sheet1!J7:M7,3,0),0) -> 0 | Q23: =+IFERROR(VLOOKUP($Q$17,Sheet1!J7:M7,3,0),0) -> 0 | R23: =+IFERROR(VLOOKUP($R$17,Sheet1!J7:M7,3,0),0) -> 0 | S23: =+IFERROR(VLOOKUP($S$17,Sheet1!N7:Q7,3,0),0) -> 0 | T23: =+IFERROR(VLOOKUP($T$17,Sheet1!N7:Q7,3,0),0) -> 0 | U23: =+IFERROR(VLOOKUP($U$17,Sheet1!F7:I7,3,0),0) -> 0 | V23: =+IFERROR(VLOOKUP($V$17,Sheet1!F7:I7,3,0),0) -> 0 | W23: =+IFERROR(VLOOKUP($W$17,Sheet1!F7:I7,3,0),0) -> 0 | X23: =+IFERROR(VLOOKUP($X$17,Sheet1!F7:I7,3,0),0) -> 0 | Y23: =+IFERROR(VLOOKUP($Y$17,Sheet1!F7:I7,3,0),0) -> 0 | Z23: =+IFERROR(VLOOKUP($Z$17,Sheet1!F7:I7,3,0),0) -> 0 | AA23: =+IFERROR(VLOOKUP($AA$17,Sheet1!F7:I7,3,0),0) -> 0 | AB23: =+IFERROR(VLOOKUP($AB$17,Sheet1!F7:I7,3,0),0) -> 0 | AC23: 66 | AD23: =+IFERROR(VLOOKUP($AD$17,Sheet1!R7:U7,2,0),0) -> 0 | AE23: 150 | AF23: =+IFERROR(VLOOKUP($AF$17,Sheet1!V7:Y7,3,0),0) -> 0 | AG23: =+IFERROR(VLOOKUP($AG$17,Sheet1!V7:Y7,3,0),0) -> 0 | AH23: =+IFERROR(VLOOKUP($AH$17,Sheet1!V7:Y7,3,0),0) -> 0 | AI23: =+IFERROR(VLOOKUP($AI$17,Sheet1!V7:Y7,3,0),0) -> 0 | AJ23: =+IFERROR(VLOOKUP($AJ$17,Sheet1!V7:Y7,3,0),0) -> 0 | AK23: =+IFERROR(VLOOKUP($AK$17,Sheet1!Z7:AB7,3,0),0) -> 0 | AL23: =+IFERROR(VLOOKUP($AL$17,Sheet1!AD7:AG7,3,0),0) -> 0 | AM23: =+IFERROR(VLOOKUP($AM$17,Sheet1!AD7:AG7,3,0),0) -> 0 | AN23: =+IFERROR(VLOOKUP($AN$17,Sheet1!AD7:AG7,3,0),0) -> 0 | AO23: =+IFERROR(VLOOKUP($AO$17,Sheet1!AD7:AG7,3,0),0) -> 0 | AP23: =+IFERROR(VLOOKUP($AP$17,Sheet1!AD7:AG7,3,0),0) -> 0 | AQ23: =+IFERROR(VLOOKUP($AQ$17,Sheet1!AD7:AG7,3,0),0) -> 0 | AR23: =+IFERROR(VLOOKUP($AR$17,Sheet1!AD7:AG7,3,0),0) -> 0 | AS23: =+IFERROR(VLOOKUP($AS$17,Sheet1!AH7:AK7,3,0),0) -> 0 | AT23: =+IFERROR(VLOOKUP($AT$17,Sheet1!AH7:AK7,3,0),0) -> 0 | AU23: =+IFERROR(VLOOKUP($AU$17,Sheet1!AH7:AK7,3,0),0) -> 0 | AV23: =+IFERROR(VLOOKUP($AV$17,Sheet1!AH7:AK7,3,0),0) -> 0 | AW23: =+IFERROR(VLOOKUP($AW$17,Sheet1!AH7:AK7,3,0),0) -> 0 | AX23: =+IFERROR(VLOOKUP($AX$17,Sheet1!AH7:AK7,3,0),0) -> 0 | AY23: =+IFERROR(VLOOKUP($AY$17,Sheet1!AH7:AK7,3,0),0) -> 0 | AZ23: =+IFERROR(VLOOKUP($AZ$17,Sheet1!AH7:AK7,3,0),0) -> 0 | BA23: =+IFERROR(VLOOKUP($BA$17,Sheet1!AH7:AK7,3,0),0) -> 0 | BB23: =+IFERROR(VLOOKUP($BB$17,Sheet1!AH7:AK7,3,0),0) -> 0 | BC23: =+IFERROR(VLOOKUP($BC$17,Sheet1!AL7:AO7,3,0),0) -> 0 | BD23: =+IFERROR(VLOOKUP($BD$17,Sheet1!AL7:AO7,3,0),0) -> 0 | BE23: =+IFERROR(VLOOKUP($BE$17,Sheet1!AL7:AO7,3,0),0) -> 0 | BF23: =+IFERROR(VLOOKUP($BF$17,Sheet1!AL7:AO7,3,0),0) -> 0 | BG23: =+IFERROR(VLOOKUP($BG$17,Sheet1!AL7:AO7,3,0),0) -> 0 | BH23: =+IFERROR(VLOOKUP($BH$17,Sheet1!AL7:AO7,3,0),0) -> 0 | BI23: =+IFERROR(VLOOKUP($BI$17,Sheet1!AL7:AO7,3,0),0) -> 0 | BJ23: =+IFERROR(VLOOKUP($BJ$17,Sheet1!AL7:AO7,3,0),0) -> 0 | BK23: =+IFERROR(VLOOKUP($BK$17,Sheet1!AL7:AO7,3,0),0) -> 0 | BL23: 111 | BM23: =+IFERROR(VLOOKUP($BM$17,Sheet1!AP7:AS7,3,0),0) -> 0 | BN23: =+IFERROR(VLOOKUP($BN$17,Sheet1!AT7:AW7,3,0),0) -> 0 | BO23: =+IFERROR(VLOOKUP($BO$17,Sheet1!AX7:BA7,3,0),0) -> 0 | BP23: =+IFERROR(VLOOKUP($BP$17,Sheet1!BB7:BE7,3,0),0) -> 0 | BQ23: =+IFERROR(VLOOKUP($BQ$17,Sheet1!BF7:BI7,3,0),0) -> 0 | BR23: =+IFERROR(VLOOKUP($BR$17,Sheet1!BJ7:BM7,3,0),0) -> 0 | BS23: =+IFERROR(VLOOKUP($BS$17,Sheet1!BN7:BQ7,3,0),0) -> 0 | BT23: =+IFERROR(VLOOKUP($BT$17,Sheet1!BR7:BU7,3,0),0) -> 0 | BU23: 28 | BV23: STEEL | BW23: SP0400124 | BX23: CORRUGATED DISPATCH STEEL DRUM 1220 X 550 X 915 MM | BY23: 1000 | BZ23: 10800 | CA23: =SUMPRODUCT($N$18:$BU$18,N23:BU23)+BZ23 -> 193903 | CB23: =Sheet1!CB7 -> 0 | CC23: =CA23*CB23 -> 0 | CD23: 0.25 | CE23: =CA23*CD23 -> 48475.75 | CF23: 0 | CG23: =CA23*CF23 -> 0 | CH23: =CA23+CC23+CE23+CG23 -> 242378.75 | CI23: 0.02 | CJ23: =CH23*CI23 -> 4847.575 | CK23: 0.01 | CL23: =CH23*CK23 -> 2423.7875
A24: =Sheet1!A5 -> ENQ-15214-22-23 | B24: 45658 | C24: =Sheet1!C5 -> FA2900032 | D24: =Sheet1!D5 -> COVERED CONDUCTOR - 1 CORE X 232 SQ. MM. (AAAC) - 33 KV | E24: =CH24+CJ24+CL24 -> 352283.17 | F24: =ROUNDUP(M33,0) -> 4104 | G24: =E24+F24 -> 356387.17 | H24: =Sheet1!CP5 -> 0.18 | I24: =G24*H24 -> 64149.691 | J24: =G24+I24 -> 420536.87 | K24: 145 | L24: =Sheet1!CT5 -> KMS | M24: =J24*K24 -> 60977846 | N24: =+IFERROR(VLOOKUP($N$17,Sheet1!J5:L5,3,0),0) -> 0 | O24: 637 | P24: =+IFERROR(VLOOKUP($P$17,Sheet1!J5:M5,3,0),0) -> 0 | Q24: =+IFERROR(VLOOKUP($Q$17,Sheet1!J5:M5,3,0),0) -> 0 | R24: =+IFERROR(VLOOKUP($R$17,Sheet1!J5:M5,3,0),0) -> 0 | S24: =+IFERROR(VLOOKUP($S$17,Sheet1!N5:Q5,3,0),0) -> 0 | T24: =+IFERROR(VLOOKUP($T$17,Sheet1!N5:Q5,3,0),0) -> 0 | U24: =+IFERROR(VLOOKUP($U$17,Sheet1!F5:I5,3,0),0) -> 0 | V24: =+IFERROR(VLOOKUP($V$17,Sheet1!F5:I5,3,0),0) -> 0 | W24: =+IFERROR(VLOOKUP($W$17,Sheet1!F5:I5,3,0),0) -> 0 | X24: =+IFERROR(VLOOKUP($X$17,Sheet1!F5:I5,3,0),0) -> 0 | Y24: =+IFERROR(VLOOKUP($Y$17,Sheet1!F5:I5,3,0),0) -> 0 | Z24: =+IFERROR(VLOOKUP($Z$17,Sheet1!F5:I5,3,0),0) -> 0 | AA24: =+IFERROR(VLOOKUP($AA$17,Sheet1!F5:I5,3,0),0) -> 0 | AB24: =+IFERROR(VLOOKUP($AB$17,Sheet1!F5:I5,3,0),0) -> 0 | AC24: 80 | AD24: =+IFERROR(VLOOKUP($AD$17,Sheet1!R5:U5,2,0),0) -> 0 | AE24: 178 | AF24: =+IFERROR(VLOOKUP($AF$17,Sheet1!V5:Y5,3,0),0) -> 0 | AG24: =+IFERROR(VLOOKUP($AG$17,Sheet1!V5:Y5,3,0),0) -> 0 | AH24: =+IFERROR(VLOOKUP($AH$17,Sheet1!V5:Y5,3,0),0) -> 0 | AI24: =+IFERROR(VLOOKUP($AI$17,Sheet1!V5:Y5,3,0),0) -> 0 | AJ24: =+IFERROR(VLOOKUP($AJ$17,Sheet1!V5:Y5,3,0),0) -> 0 | AK24: =+IFERROR(VLOOKUP($AK$17,Sheet1!Z5:AB5,3,0),0) -> 0 | AL24: =+IFERROR(VLOOKUP($AL$17,Sheet1!AD5:AG5,3,0),0) -> 0 | AM24: =+IFERROR(VLOOKUP($AM$17,Sheet1!AD5:AG5,3,0),0) -> 0 | AN24: =+IFERROR(VLOOKUP($AN$17,Sheet1!AD5:AG5,3,0),0) -> 0 | AO24: =+IFERROR(VLOOKUP($AO$17,Sheet1!AD5:AG5,3,0),0) -> 0 | AP24: =+IFERROR(VLOOKUP($AP$17,Sheet1!AD5:AG5,3,0),0) -> 0 | AQ24: =+IFERROR(VLOOKUP($AQ$17,Sheet1!AD5:AG5,3,0),0) -> 0 | AR24: =+IFERROR(VLOOKUP($AR$17,Sheet1!AD5:AG5,3,0),0) -> 0 | AS24: =+IFERROR(VLOOKUP($AS$17,Sheet1!AH5:AK5,3,0),0) -> 0 | AT24: =+IFERROR(VLOOKUP($AT$17,Sheet1!AH5:AK5,3,0),0) -> 0 | AU24: =+IFERROR(VLOOKUP($AU$17,Sheet1!AH5:AK5,3,0),0) -> 0 | AV24: =+IFERROR(VLOOKUP($AV$17,Sheet1!AH5:AK5,3,0),0) -> 0 | AW24: =+IFERROR(VLOOKUP($AW$17,Sheet1!AH5:AK5,3,0),0) -> 0 | AX24: =+IFERROR(VLOOKUP($AX$17,Sheet1!AH5:AK5,3,0),0) -> 0 | AY24: =+IFERROR(VLOOKUP($AY$17,Sheet1!AH5:AK5,3,0),0) -> 0 | AZ24: =+IFERROR(VLOOKUP($AZ$17,Sheet1!AH5:AK5,3,0),0) -> 0 | BA24: =+IFERROR(VLOOKUP($BA$17,Sheet1!AH5:AK5,3,0),0) -> 0 | BB24: =+IFERROR(VLOOKUP($BB$17,Sheet1!AH5:AK5,3,0),0) -> 0 | BC24: =+IFERROR(VLOOKUP($BC$17,Sheet1!AL5:AO5,3,0),0) -> 0 | BD24: =+IFERROR(VLOOKUP($BD$17,Sheet1!AL5:AO5,3,0),0) -> 0 | BE24: =+IFERROR(VLOOKUP($BE$17,Sheet1!AL5:AO5,3,0),0) -> 0 | BF24: =+IFERROR(VLOOKUP($BF$17,Sheet1!AL5:AO5,3,0),0) -> 0 | BG24: =+IFERROR(VLOOKUP($BG$17,Sheet1!AL5:AO5,3,0),0) -> 0 | BH24: =+IFERROR(VLOOKUP($BH$17,Sheet1!AL5:AO5,3,0),0) -> 0 | BI24: =+IFERROR(VLOOKUP($BI$17,Sheet1!AL5:AO5,3,0),0) -> 0 | BJ24: =+IFERROR(VLOOKUP($BJ$17,Sheet1!AL5:AO5,3,0),0) -> 0 | BK24: =+IFERROR(VLOOKUP($BK$17,Sheet1!AL5:AO5,3,0),0) -> 0 | BL24: 130 | BM24: =+IFERROR(VLOOKUP($BM$17,Sheet1!AP5:AS5,3,0),0) -> 0 | BN24: =+IFERROR(VLOOKUP($BN$17,Sheet1!AT5:AW5,3,0),0) -> 0 | BO24: =+IFERROR(VLOOKUP($BO$17,Sheet1!AX5:BA5,3,0),0) -> 0 | BP24: =+IFERROR(VLOOKUP($BP$17,Sheet1!BB5:BE5,3,0),0) -> 0 | BQ24: =+IFERROR(VLOOKUP($BQ$17,Sheet1!BF5:BI5,3,0),0) -> 0 | BR24: =+IFERROR(VLOOKUP($BR$17,Sheet1!BJ5:BM5,3,0),0) -> 0 | BS24: =+IFERROR(VLOOKUP($BS$17,Sheet1!BN5:BQ5,3,0),0) -> 0 | BT24: =+IFERROR(VLOOKUP($BT$17,Sheet1!BR5:BU5,3,0),0) -> 0 | BU24: 38 | BV24: STEEL | BW24: SP0400152 | BX24: CORRUGATED DISPATCH STEEL DRUM 1500 X 800 X 915 | BY24: 1000 | BZ24: 11700 | CA24: =SUMPRODUCT($N$18:$BU$18,N24:BU24)+BZ24 -> 273618 | CB24: =Sheet1!CB5 -> 0 | CC24: =CA24*CB24 -> 0 | CD24: 0.25 | CE24: =CA24*CD24 -> 68404.5 | CF24: 0 | CG24: =CA24*CF24 -> 0 | CH24: =CA24+CC24+CE24+CG24 -> 342022.5 | CI24: 0.02 | CJ24: =CH24*CI24 -> 6840.45 | CK24: 0.01 | CL24: =CH24*CK24 -> 3420.225
M25: =SUM(M19:M24) -> 4.0645951e+08
C27: 16MT Truck fare | E27: Order Quantity | F27: Stnd Length | G27: Truck type | H27: Fare of one truck | I27: No of Drum in one truck | J27: Total length in one Truck | K27: No of Truck | L27: Total Freight | M27: Freight per KM | AC27: CABLE WEIGHT KG/KM | AE27: DRUM WEIGHT | BL27: CABLE+DRUM WEIGHT | BU27: TRUCK WEIGHT
B28: Bhubaneswar | C28: 24000 | D28: =D19 -> COVERED CONDUCTOR - 1 CORE X 55 SQ. MM. (AAAC) - 11 KV | E28: =K19 -> 23 | F28: =BY19/1000 -> 1 | G28: 16 MT | H28: 35000 | I28: 24 | J28: =F28*I28 -> 24 | K28: =ROUNDUP((E28/J28),0) -> 1 | L28: =M28*E28 -> 35000 | M28: =(H28*K28)/E28 -> 1521.7391 | AC28: =SUM(O19:BU19) -> 318 | AE28: =BZ19/90 -> 90 | BL28: =((AC28*F28)+AE28) -> 408 | BU28: =BL28*I28 -> 9792
B29: Balia | C29: 55000 | D29: =D20 -> COVERED CONDUCTOR - 1 CORE X 80 SQ. MM. (AAAC) - 11 KV | E29: =K20 -> 48.085 | F29: =BY20/1000 -> 1 | G29: 16 MT | H29: 35000 | I29: 24 | J29: =F29*I29 -> 24 | K29: =ROUNDUP((E29/J29),0) -> 3 | L29: =M29*E29 -> 105000 | M29: =(H29*K29)/E29 -> 2183.6331 | AC29: =SUM(O20:BU20) -> 412 | AE29: =BZ20/90 -> 90 | BL29: =((AC29*F29)+AE29) -> 502 | BU29: =BL29*I29 -> 12048
B30: Berhampur | C30: 28000 | D30: =D21 -> COVERED CONDUCTOR - 1 CORE x 100 SQ. MM. (AAAC) - 11KV | E30: =K21 -> 1220.919 | F30: =BY21/1000 -> 1 | G30: 16 MT | H30: 35000 | I30: 24 | J30: =F30*I30 -> 24 | K30: =ROUNDUP((E30/J30),0) -> 51 | L30: =M30*E30 -> 1785000 | M30: =(H30*K30)/E30 -> 1462.0135 | AC30: =SUM(O21:BU21) -> 483 | AE30: =BZ21/90 -> 90 | BL30: =((AC30*F30)+AE30) -> 573 | BU30: =BL30*I30 -> 13752
B31: Burla | C31: 30000 | D31: =D22 -> COVERED CONDUCTOR - 1 CORE X 99 SQ. MM. (AAAC) - 33 KV | E31: =K22 -> 85 | F31: =BY22/1000 -> 1 | G31: 16 MT | H31: 35000 | I31: 18 | J31: =F31*I31 -> 18 | K31: =ROUNDUP((E31/J31),0) -> 5 | L31: =M31*E31 -> 175000 | M31: =(H31*K31)/E31 -> 2058.8235 | AC31: =SUM(O22:BU22) -> 568 | AE31: =BZ22/90 -> 120 | BL31: =((AC31*F31)+AE31) -> 688 | BU31: =BL31*I31 -> 12384
B32: Average = | C32: =AVERAGE(C28:C31) -> 34250 | D32: =D23 -> COVERED CONDUCTOR - 1 CORE x 150 SQ. MM. (XLPE) (AAAC) - 33 KV | E32: =K23 -> 263.175 | F32: =BY23/1000 -> 1 | G32: 16 MT | H32: 35000 | I32: 16 | J32: =F32*I32 -> 16 | K32: =ROUNDUP((E32/J32),0) -> 17 | L32: =M32*E32 -> 595000 | M32: =(H32*K32)/E32 -> 2260.853 | AC32: =SUM(O23:BU23) -> 762 | AE32: =BZ23/90 -> 120 | BL32: =((AC32*F32)+AE32) -> 882 | BU32: =BL32*I32 -> 14112
D33: =D24 -> COVERED CONDUCTOR - 1 CORE X 232 SQ. MM. (AAAC) - 33 KV | E33: =K24 -> 145 | F33: =BY24/1000 -> 1 | G33: 16 MT | H33: 35000 | I33: 9 | J33: =F33*I33 -> 9 | K33: =ROUNDUP((E33/J33),0) -> 17 | L33: =M33*E33 -> 595000 | M33: =(H33*K33)/E33 -> 4103.4483 | AC33: =SUM(O24:BU24) -> 1063 | AE33: =BZ24/90 -> 130 | BL33: =((AC33*F33)+AE33) -> 1193 | BU33: =BL33*I33 -> 10737
I34: SOMBHU SIR CONFIRMED OVER PHONE
A37: DOCKET NO. | B37: Base Date | C37: ITEM CODE | D37: PROPOSE ERP ITEM NAME | E37: EX-WORKS (PER MTR) | F37: FREIGHT PER MTR | G37: PRICE INCLUDING FREIGHT (PER MTR) | H37: GST % | I37: GST VALUE | J37: PRICE INCLUDING GST & FREIGHT (PER KM) | K37: QTY | L37: Unit | M37: TOTAL PRICE OF FULL QTY (INCLUDING FRIGHT & GST)
A39: =A19 -> ENQ-15214-22-23 | B39: =B19 -> 45658 | C39: =C19 -> FA2900029 | D39: =D19 -> COVERED CONDUCTOR - 1 CORE X 55 SQ. MM. (AAAC) - 11 KV | E39: =ROUNDUP(E19/1000,2) -> 107.9 | F39: =ROUNDUP(F19/1000,2) -> 1.53 | G39: =E39+F39 -> 109.43 | H39: =H19 -> 0.18 | I39: =ROUND(G39*H39,2) -> 19.7 | J39: =ROUND(G39+I39,2) -> 129.13 | K39: =K19*1000 -> 23000 | L39: MTR | M39: =J39*K39 -> 2969990
A40: =A20 -> ENQ-15214-22-23 | B40: =B20 -> 45658 | C40: =C20 -> FA2900034 | D40: =D20 -> COVERED CONDUCTOR - 1 CORE X 80 SQ. MM. (AAAC) - 11 KV | E40: =ROUNDUP(E20/1000,2) -> 139.37 | F40: =ROUNDUP(F20/1000,2) -> 2.19 | G40: =E40+F40 -> 141.56 | H40: =H20 -> 0.18 | I40: =ROUND(G40*H40,2) -> 25.48 | J40: =ROUND(G40+I40,2) -> 167.04 | K40: =K20*1000 -> 48085 | L40: MTR | M40: =J40*K40 -> 8032118.4
A41: =A21 -> ENQ-15214-22-23 | B41: =B21 -> 45658 | C41: =C21 -> FA2900004 | D41: =D21 -> COVERED CONDUCTOR - 1 CORE x 100 SQ. MM. (AAAC) - 11KV | E41: =ROUNDUP(E21/1000,2) -> 163.31 | F41: =ROUNDUP(F21/1000,2) -> 1.47 | G41: =E41+F41 -> 164.78 | H41: =H21 -> 0.18 | I41: =ROUND(G41*H41,2) -> 29.66 | J41: =ROUND(G41+I41,2) -> 194.44 | K41: =K21*1000 -> 1220919 | L41: MTR | M41: =J41*K41 -> 2.3739549e+08
A42: =A22 -> ENQ-15214-22-23 | B42: =B22 -> 45658 | C42: =C22 -> FA2900008 | D42: =D22 -> COVERED CONDUCTOR - 1 CORE X 99 SQ. MM. (AAAC) - 33 KV | E42: =ROUNDUP(E22/1000,2) -> 186.04 | F42: =ROUNDUP(F22/1000,2) -> 2.06 | G42: =E42+F42 -> 188.1 | H42: =H22 -> 0.18 | I42: =ROUND(G42*H42,2) -> 33.86 | J42: =ROUND(G42+I42,2) -> 221.96 | K42: =K22*1000 -> 85000 | L42: MTR | M42: =J42*K42 -> 18866600
A43: =A23 -> ENQ-15214-22-23 | B43: =B23 -> 45658 | C43: =C23 -> FA2900014 | D43: =D23 -> COVERED CONDUCTOR - 1 CORE x 150 SQ. MM. (XLPE) (AAAC) - 33 KV | E43: =ROUNDUP(E23/1000,2) -> 249.66 | F43: =ROUNDUP(F23/1000,2) -> 2.27 | G43: =E43+F43 -> 251.93 | H43: =H23 -> 0.18 | I43: =ROUND(G43*H43,2) -> 45.35 | J43: =ROUND(G43+I43,2) -> 297.28 | K43: =K23*1000 -> 263175 | L43: MTR | M43: =J43*K43 -> 78236664
A44: =A24 -> ENQ-15214-22-23 | B44: =B24 -> 45658 | C44: =C24 -> FA2900032 | D44: =D24 -> COVERED CONDUCTOR - 1 CORE X 232 SQ. MM. (AAAC) - 33 KV | E44: =ROUNDUP(E24/1000,2) -> 352.29 | F44: =ROUNDUP(F24/1000,2) -> 4.11 | G44: =E44+F44 -> 356.4 | H44: =H24 -> 0.18 | I44: =ROUND(G44*H44,2) -> 64.15 | J44: =ROUND(G44+I44,2) -> 420.55 | K44: =K24*1000 -> 145000 | L44: MTR | M44: =J44*K44 -> 60979750
M45: =SUM(M39:M44) -> 4.0648061e+08
M46: =M45-M25 -> 21103.935

Sheet PV ON IS
A1: Base Date | B1: 45658
A2: PV Terms
A3: PV FORMULA
A4: P=Po + WAL(AL-Alo)+WA(AL-Alo)+WF(FE-Feo)+WSc(SC-Sco)+WI(IN-Ino)+WO(IN-Ino)
A7: P = Ex-works price payable in Rs. per km as adjusted in accordance with the price variation clause
A8: Po = Ex-works price quoted/confirmed in Rs. per km.
A10: WA = Variation factor of Aluminium in MV Covered Conductor as per the type of MVC conductor
A11: WAL = Variation factor of AL-59 in MV Covered Conductor as per the type of MVC conductor
A12: ALo = Price of LME CSP Average of Aluminium. This price is as applicable for the month, ONE month prior to the date of tender opening.
A13: AL = Price of LME CSP Average of Aluminium. This price is as applicable for the month, ONE month prior to the date of delivery.
A15: WF = Variation factor of Steel Content in ACSR and AL-59 ACS MVC Conductor as per the type of MVC conductor
A16: FEo = Price of High Tensile Galvanized Steel Wire in Rs./MT of appropriate size. This price is as applicable for the month, ONE month prior to the date of tender opening.
A17: FE = Price of High Tensile Galvanized Steel Wire in Rs./MT of appropriate size. This price is as applicable for the month, ONE month prior to the date of delivery.
... A27: IN = Price of XLPE Compound/ Polymeric Compound (HDPE) as used for inner/outer insulation in Rs./MT. This price is as applicable for the month, ONE month prior to the date of delivery.
A31: Item | B31: Calculation part | C31: Date of Inspection | D31: Applicable Date | I31: BASE DATE | N31: FACTORS | T31: Ex-Work Po | U31: PVC of WAL | V31: PVC of WA | W31: PVC of WF | X31: PVC of WSC | Y31: PVC of WI | Z31: PVC of WO | AA31: PVC per KM | AB31: Billing Price/PKM | AC31: VALUE ADDITION CALCULATION
D32: Date | E32: Al | F32: FE | G32: SC | H32: IN | I32: Date | J32: Alo | K32: FEo | L32: SCo | M32: INo
N33: WAL | O33: WA | P33: WF | Q33: WSC | R33: WI | S33: WO | AC33: ='AUTO CALCULATION SHEET (2)'!O17 -> AL 59 | AD33: ='AUTO CALCULATION SHEET (2)'!AC17 -> Extruded semiconductive | AE33: ='AUTO CALCULATION SHEET (2)'!AE17 -> HT-XLPE | AF33: ='AUTO CALCULATION SHEET (2)'!BL17 -> UV & Track Resistant XLPE | AG33: ='AUTO CALCULATION SHEET (2)'!BU17 -> Water Tight Compound | AH33: RMC | AI33: Drum | AJ33: RMC+DRUM | AK33: VA | AL33: Groos VA% | AM33: Mfg % | AN33: Int % | AO33: Ins% | AP33: Net VA
AC34: 296 | AD34: 178 | AE34: 151 | AF34: 237 | AG34: 210
A35: ='AUTO CALCULATION SHEET (2)'!D19 -> COVERED CONDUCTOR - 1 CORE X 55 SQ. MM. (AAAC) - 11 KV | C35: PROVISIONAL | D35: 45685 | E35: 267933.34 | G35: 293182 | H35: 176136 | I35: =$B$1 -> 45658 | J35: 264189 | L35: 293182 | M35: 176136 | O35: 0.1528 | Q35: 0.0449 | R35: 0.0486 | S35: 0.0555 | T35: ='AUTO CALCULATION SHEET (2)'!E39*1000 -> 107900 | U35: =(E35-J35)*N35 -> 0 | V35: =(E35-J35)*O35 -> 572.13515 | W35: =(F35-K35)*P35 -> 0 | X35: =(G35-L35)*Q35 -> 0 | Y35: =(H35-M35)*R35 -> 0 | Z35: =(H35-M35)*S35 -> 0 | AA35: =U35+V35+W35+X35+Y35+Z35 -> 572.13515 | AB35: =T35+AA35 -> 108472.14 | AC35: ='AUTO CALCULATION SHEET (2)'!O19 -> 150 | AD35: ='AUTO CALCULATION SHEET (2)'!AC19 -> 40 | AE35: ='AUTO CALCULATION SHEET (2)'!AE19 -> 48 | AF35: ='AUTO CALCULATION SHEET (2)'!BL19 -> 65 | AG35: ='AUTO CALCULATION SHEET (2)'!BU19 -> 15 | AH35: =SUMPRODUCT($AC$34:$AG$34,AC35:AG35) -> 77323 | AI35: ='AUTO CALCULATION SHEET (2)'!BZ19 -> 8100 | AJ35: =AH35+AI35 -> 85423 | AK35: =+AB35-AJ35 -> 23049.135 | AL35: =AK35/AB35*100% -> 0.212489 | AN35: 0.02 | AO35: 0.01 | AP35: =AL35-SUM(AM35:AO35) -> 0.182489
A36: ='AUTO CALCULATION SHEET (2)'!D20 -> COVERED CONDUCTOR - 1 CORE X 80 SQ. MM. (AAAC) - 11 KV | C36: PROVISIONAL | D36: 45685 | E36: 267933.34 | G36: 293182 | H36: 176136 | I36: =$B$1 -> 45658 | J36: 264189 | L36: 293182 | M36: 176136 | O36: 0.2225 | Q36: 0.0568 | R36: 0.0576 | S36: 0.0666 | T36: ='AUTO CALCULATION SHEET (2)'!E40*1000 -> 139370 | U36: =(E36-J36)*N36 -> 0 | V36: =(E36-J36)*O36 -> 833.11565 | W36: =(F36-K36)*P36 -> 0 | X36: =(G36-L36)*Q36 -> 0 | Y36: =(H36-M36)*R36 -> 0 | Z36: =(H36-M36)*S36 -> 0 | AA36: =U36+V36+W36+X36+Y36+Z36 -> 833.11565 | AB36: =T36+AA36 -> 140203.12 | AC36: ='AUTO CALCULATION SHEET (2)'!O20 -> 219 | AD36: ='AUTO CALCULATION SHEET (2)'!AC20 -> 48 | AE36: ='AUTO CALCULATION SHEET (2)'!AE20 -> 55 | AF36: ='AUTO CALCULATION SHEET (2)'!BL20 -> 74 | AG36: ='AUTO CALCULATION SHEET (2)'!BU20 -> 16 | AH36: =SUMPRODUCT($AC$34:$AG$34,AC36:AG36) -> 102571 | AI36: ='AUTO CALCULATION SHEET (2)'!BZ20 -> 8100 | AJ36: =AH36+AI36 -> 110671 | AK36: =+AB36-AJ36 -> 29532.116 | AL36: =AK36/AB36*100% -> 0.21063808 | AN36: 0.02 | AO36: 0.01 | AP36: =AL36-SUM(AM36:AO36) -> 0.18063808
A37: ='AUTO CALCULATION SHEET (2)'!D21 -> COVERED CONDUCTOR - 1 CORE x 100 SQ. MM. (AAAC) - 11KV | C37: PROVISIONAL | D37: 45685 | E37: 267933.34 | G37: 293182 | H37: 176136 | I37: =$B$1 -> 45658 | J37: 264189 | L37: 293182 | M37: 176136 | O37: 0.2796 | Q37: 0.0634 | R37: 0.0622 | S37: 0.0688 | T37: ='AUTO CALCULATION SHEET (2)'!E41*1000 -> 163310 | U37: =(E37-J37)*N37 -> 0 | V37: =(E37-J37)*O37 -> 1046.9175 | W37: =(F37-K37)*P37 -> 0 | X37: =(G37-L37)*Q37 -> 0 | Y37: =(H37-M37)*R37 -> 0 | Z37: =(H37-M37)*S37 -> 0 | AA37: =U37+V37+W37+X37+Y37+Z37 -> 1046.9175 | AB37: =T37+AA37 -> 164356.92 | AC37: ='AUTO CALCULATION SHEET (2)'!O21 -> 273 | AD37: ='AUTO CALCULATION SHEET (2)'!AC21 -> 54 | AE37: ='AUTO CALCULATION SHEET (2)'!AE21 -> 60 | AF37: ='AUTO CALCULATION SHEET (2)'!BL21 -> 80 | AG37: ='AUTO CALCULATION SHEET (2)'!BU21 -> 16 | AH37: =SUMPRODUCT($AC$34:$AG$34,AC37:AG37) -> 121800 | AI37: ='AUTO CALCULATION SHEET (2)'!BZ21 -> 8100 | AJ37: =AH37+AI37 -> 129900 | AK37: =+AB37-AJ37 -> 34456.917 | AL37: =AK37/AB37*100% -> 0.2096469 | AN37: 0.02 | AO37: 0.01 | AP37: =AL37-SUM(AM37:AO37) -> 0.1796469
A38: ='AUTO CALCULATION SHEET (2)'!D22 -> COVERED CONDUCTOR - 1 CORE X 99 SQ. MM. (AAAC) - 33 KV | C38: PROVISIONAL | D38: 45685 | E38: 267933.34 | G38: 293182 | H38: 176136 | I38: =$B$1 -> 45658 | J38: 264189 | L38: 293182 | M38: 176136 | O38: 0.2796 | Q38: 0.0719 | R38: 0.1337 | S38: 0.0898 | T38: ='AUTO CALCULATION SHEET (2)'!E42*1000 -> 186040 | U38: =(E38-J38)*N38 -> 0 | V38: =(E38-J38)*O38 -> 1046.9175 | W38: =(F38-K38)*P38 -> 0 | X38: =(G38-L38)*Q38 -> 0 | Y38: =(H38-M38)*R38 -> 0 | Z38: =(H38-M38)*S38 -> 0 | AA38: =U38+V38+W38+X38+Y38+Z38 -> 1046.9175 | AB38: =T38+AA38 -> 187086.92 | AC38: ='AUTO CALCULATION SHEET (2)'!O22 -> 273 | AD38: ='AUTO CALCULATION SHEET (2)'!AC22 -> 54 | AE38: ='AUTO CALCULATION SHEET (2)'!AE22 -> 127 | AF38: ='AUTO CALCULATION SHEET (2)'!BL22 -> 98 | AG38: ='AUTO CALCULATION SHEET (2)'!BU22 -> 16 | AH38: =SUMPRODUCT($AC$34:$AG$34,AC38:AG38) -> 136183 | AI38: ='AUTO CALCULATION SHEET (2)'!BZ22 -> 10800 | AJ38: =AH38+AI38 -> 146983 | AK38: =+AB38-AJ38 -> 40103.917 | AL38: =AK38/AB38*100% -> 0.21435982 | AN38: 0.02 | AO38: 0.01 | AP38: =AL38-SUM(AM38:AO38) -> 0.18435982
A39: ='AUTO CALCULATION SHEET (2)'!D23 -> COVERED CONDUCTOR - 1 CORE x 150 SQ. MM. (XLPE) (AAAC) - 33 KV | C39: PROVISIONAL | D39: 45685 | E39: 267933.34 | G39: 293182 | H39: 176136 | I39: =$B$1 -> 45658 | J39: 264189 | L39: 293182 | M39: 176136 | O39: 0.4142 | Q39: 0.0968 | R39: 0.1576 | S39: 0.1028 | T39: ='AUTO CALCULATION SHEET (2)'!E43*1000 -> 249660 | U39: =(E39-J39)*N39 -> 0 | V39: =(E39-J39)*O39 -> 1550.9056 | W39: =(F39-K39)*P39 -> 0 | X39: =(G39-L39)*Q39 -> 0 | Y39: =(H39-M39)*R39 -> 0 | Z39: =(H39-M39)*S39 -> 0 | AA39: =U39+V39+W39+X39+Y39+Z39 -> 1550.9056 | AB39: =T39+AA39 -> 251210.91 | AC39: ='AUTO CALCULATION SHEET (2)'!O23 -> 407 | AD39: ='AUTO CALCULATION SHEET (2)'!AC23 -> 66 | AE39: ='AUTO CALCULATION SHEET (2)'!AE23 -> 150 | AF39: ='AUTO CALCULATION SHEET (2)'!BL23 -> 111 | AG39: ='AUTO CALCULATION SHEET (2)'!BU23 -> 28 | AH39: =SUMPRODUCT($AC$34:$AG$34,AC39:AG39) -> 187057 | AI39: ='AUTO CALCULATION SHEET (2)'!BZ23 -> 10800 | AJ39: =AH39+AI39 -> 197857 | AK39: =+AB39-AJ39 -> 53353.906 | AL39: =AK39/AB39*100% -> 0.2123869 | AN39: 0.02 | AO39: 0.01 | AP39: =AL39-SUM(AM39:AO39) -> 0.1823869
A40: ='AUTO CALCULATION SHEET (2)'!D24 -> COVERED CONDUCTOR - 1 CORE X 232 SQ. MM. (AAAC) - 33 KV | C40: PROVISIONAL | D40: 45685 | E40: 267933.34 | G40: 293182 | H40: 176136 | I40: =$B$1 -> 45658 | J40: 264189 | L40: 293182 | M40: 176136 | O40: 0.648 | Q40: 0.1265 | R40: 0.1894 | S40: 0.1202 | T40: ='AUTO CALCULATION SHEET (2)'!E44*1000 -> 352290 | U40: =(E40-J40)*N40 -> 0 | V40: =(E40-J40)*O40 -> 2426.3323 | W40: =(F40-K40)*P40 -> 0 | X40: =(G40-L40)*Q40 -> 0 | Y40: =(H40-M40)*R40 -> 0 | Z40: =(H40-M40)*S40 -> 0 | AA40: =U40+V40+W40+X40+Y40+Z40 -> 2426.3323 | AB40: =T40+AA40 -> 354716.33 | AC40: ='AUTO CALCULATION SHEET (2)'!O24 -> 637 | AD40: ='AUTO CALCULATION SHEET (2)'!AC24 -> 80 | AE40: ='AUTO CALCULATION SHEET (2)'!AE24 -> 178 | AF40: ='AUTO CALCULATION SHEET (2)'!BL24 -> 130 | AG40: ='AUTO CALCULATION SHEET (2)'!BU24 -> 38 | AH40: =SUMPRODUCT($AC$34:$AG$34,AC40:AG40) -> 268460 | AI40: ='AUTO CALCULATION SHEET (2)'!BZ24 -> 11700 | AJ40: =AH40+AI40 -> 280160 | AK40: =+AB40-AJ40 -> 74556.332 | AL40: =AK40/AB40*100% -> 0.21018579 | AN40: 0.02 | AO40: 0.01 | AP40: =AL40-SUM(AM40:AO40) -> 0.18018579
