Workbook

Sheet Sheet1
A1: DOCKET NO. | B1: Base Date | C1: ITEM CODE | D1: PROPOSE ERP ITEM NAME | E1: PROPOSE DRUM TYPE | F1: Insulation Screening (Metallic) | G1: RM RATE (Insulation Screening (Metallic)) | H1: Weight (Insulation Screening (Metallic)) | I1: COST(Insulation Screening (Metallic)) | J1: Conductor | K1: RM RATE(Conductor) | L1: WEIGHT(Conductor) | M1: COST(Conductor) | N1: AL ALLOY | O1: RM RATE(Alu Alloy) | P1: WEIGHT(Alu Alloy) | Q1: COST(Alu Alloy) | R1: Insulation Screening (Non-Metallic) | S1: RM RATE(Insulation Screening (Non-Metallic)) | T1: WEIGHT(Insulation Screening (Non-Metallic)) | U1: COST(Insulation Screening (Non-Metallic)) | V1: Insulation | W1: RM RATE(Insulation) | X1: WEIGHT(Insulation) | Y1: COST(Insulation) | Z1: POLY TAPE | AA1: RM RATE (Poly Tape) | AB1: WEIGHT (Poly Tape) | AC1: COST(Poly Tape) | AD1: Inner Sheath | AE1: RM RATE(Inner Sheath) | AF1: WEIGHT(Inner Sheath) | AG1: COST(Inner Sheath) | AH1: Armouring | AI1: RM RATE(Armouring) | AJ1: WEIGHT(Armouring) | AK1: COST(Armouring) | AL1: Outer Sheath | AM1: RM RATE(Outer Sheath) | AN1: WEIGHT(Outer Sheath) | AO1: COST(Outer Sheath) | AP1: FILLER | AQ1: RM RATE(Filler) | AR1: WEIGHT(Filler) | AS1: COST(Filler) | AT1: GREASE | AU1: RM RATE(Grease) | AV1: WEIGHT(Grease) | AW1: COST(Grease) | AX1: Water swellable Tape | AY1: RM RATE(Water swellable Tape) | AZ1: WEIGHT(Water swellable Tape) | BA1: COST(Water swellable Tape) | BB1: Semi conducting Water Swellable tape | BC1: RM RATE(Semi conducting Water Swellable tape) | BD1: WEIGHT(Semi conducting Water Swellable tape) | BE1: COST(Semi conducting Water Swellable tape) | BF1: SEMICON TAPE | BG1: RM RATE(SEMICON TAPE) | BH1: WEIGHT(SEMICON TAPE) | BI1: COST(SEMICON TAPE) | BJ1: GLASS FIBER TAPE | BK1: RM RATE(GLASS FIBER TAPE) | BL1: WEIGHT(GLASS FIBER TAPE) | BM1: COST(GLASS FIBER TAPE) | BN1: COPPER WIRE 0.8 MM | BO1: RM RATE(COPPER WIRE 0.8 MM) | BP1: WEIGHT(COPPER WIRE 0.8 MM) | BQ1: COST(COPPER WIRE 0.8 MM) | BR1: RUBBERIZED COTTON TAPE | BS1: RM RATE(RUBBERIZED COTTON TAPE) | BT1: WEIGHT(RUBBERIZED COTTON TAPE) | BU1: COST(RUBBERIZED COTTON TAPE) | BV1: Water Tight Compound | BW1: RM RATE(Water Tight Compound) | BX1: WEIGHT(Water Tight Compound) | BY1: COST(Water Tight Compound) | BZ1: DRUM COST PER KM | CA1: TOTAL RM COST | CB1: FIRM % | CC1: FIRM VALUE | CD1: MFG% | CE1: MFG VALUE | CF1: PROF% | CG1: PROFIT VALUE | CH1: 1ST EX-WORKS | CI1: Intt % | CJ1: INTT VALUE | CK1: insp% | CL1: INSP VALUE | CM1: EX-WORKS (PER KM) | CN1: FREIGHT PER KM | CO1: PRICE INCLUDING FREIGHT (PER KM) | CP1: GST % | CQ1: GST VALUE | CR1: PRICE INCLUDING GST & FREIGHT (PER KM) | CS1: QTY | CT1: Unit | CU1: TOTAL PRICE OF FULL QTY (INCLUDING FRIGHT & GST) | CV1: DRUM CODE | CW1: DRUM SIZE (FxbXtx Ft) | CX1: PARTY STANDARD LENGTH (MTR)
A2: ENQ-13482-22-23 | B2: 45474 | C2: FA0400001 | D2: 3 CORE X 120 SQ MM + 1 CORE X 95 SQ MM (AB CABLES) (BARE) - 11 KV | E2: WOOD | F2: Copper Tape - 0.060 mm | G2: 998 | H2: 123.586 | I2: 123338.83 | J2: Alumimium | K2: 253 | L2: 977.135 | M2: 247215.16 | N2: Alumimium Alloy | O2: 260 | P2: 257.85 | Q2: 67041 | R2: Extruded Semiconductive | S2: 188 | T2: 191 | U2: 35908 | V2: HT-XLPE | W2: 147 | X2: 577 | Y2: 84819 | AB2: 31 | AF2: 0 | AJ2: 0 | AL2: PE-ST-7 | AM2: 128 | AN2: 706 | AO2: 90368 | AR2: 0 | AV2: 0 | AZ2: 0 | BD2: 0 | BH2: 0 | BL2: 0 | BP2: 0 | BT2: 0 | BX2: 0 | BZ2: 28794 | CA2: 677483.99 | CH2: 677483.99 | CM2: 677483.99 | CO2: 677483.99 | CP2: 0.18 | CQ2: 121947.12 | CR2: 799431.11 | CS2: 40 | CT2: KMS | CU2: 31977244 | CV2: MD0100027 | CW2: DRUM - 76 X 40 X 38 X 3

Sheet AUTO CALCULATION SHEET (2)
A2: NORTH BIHAR POWER DISTRIBUTION CO. LTD
A4: TENDER SPECIFICATION NO () | B4: NITNO-29/PR/NBPDCL/2024
A5: TENDER DESCRIPTION () | B5: 11 kV AB Cable [3CX120 Sq mm+1Cx95 Sq mm]
A6: Last Date & Time of Submission () | B6: 13.08.2024 up to 18:00 hrs.
A7: REVERSE AUCTION | B7: Not mention.
A8: Price () | B8: Price Variation for AB Cable shall be applicable as per current IEEMA circulars and indices for respective items as applicable on the final date of submission of bid.
A9: Validity () | B9: The tenderers should specify the validity period of their offer which should be for a minimum period of 180 days from the last date of submission of bid.
A10: Delivery Period () | B10: The material are required to be delivered within 04 (Four) months from the date of issue of Purchase Order as per the following delivery schedule. Within 2 (two) months - at least 30 % of the ordered quantity During 3rd(Third) month - at least 35 % of the ordered quantity During 4th(Fourth) month - at least 35 % of the ordered quantity Early delivery shall be preferred. The proforma for schedule of delivery is enclosed with the Tender; Tenderers are requested to fill up the proforma giving a clear schedule of month wise delivery capability.
A11: Payment Terms () | B11: i. 75% payment along with full amount of taxes, duties and freight keeping 10% retention money & 15% against type test report, on submission of triplicate copy of bills with all relevant documents (Sample check list) enclosed in annexure by the vendor after receipt of the material / equipment in good condition. After successful completion of delivery of entire order or modified quantity as decided during its delivery schedule, 10 % retention money may be released after deduction of penalty. ii. 15% of bill amount shall be keep back up to submission of type test report. This 15% keep back amount shall be released against the submission of equivalent amount of BG. iii. Payment will be released normally within 15 working days from the date of submission of bill along with all required relevant document(s) to Sr. Manager (Finance), NBPDCL/SBPDCL.
A12: Standard length () | B12: Material shall be delivered suitably packed in metallic drum (non-returnable basis as per ISS).The standard length of bunched cable in each drum should be 500 m (+/- 10%). It should be robust enough for rough handling during transportation by Rail/Road. Further it is to clarify here that all the charges towards packing, forwarding, loading, unloading etc shall be borne by the supplier.
A13: Technical Specification
N15: =Sheet1!J1 -> Conductor | S15: AL ALLOY | U15: Insulation Screening (Metallic) | AC15: Insulation Screening (Non-Metallic) | AE15: Insulation | AK15: POLY TAPE | AL15: Inner Sheath | AS15: Armouring | BC15: Outer Sheath | BM15: FILLER | BN15: GREASE | BO15: Water swellable Tape | BP15: Semi conducting Water Swellable tape | BQ15: SEMICON TAPE | BR15: GLASS FIBER TAPE | BS15: COPPER WIRE 0.8 MM | BT15: RUBBERIZED COTTON TAPE | BU15: Water Tight Compound | BZ15: DRUM COST PER KM | CA15: TOTAL RM COST | CB15: EXTRA CONSUMPTION | CC15: EXTRA CONSUMPTION VALUE
A16: DOCKET NO. | B16: =Sheet1!B1 -> Base Date | C16: ITEM CODE | D16: PROPOSE ERP ITEM NAME | E16: EX-WORKS (PER KM) | F16: FREIGHT PER KM | G16: PRICE INCLUDING FREIGHT (PER KM) | H16: GST % | I16: GST VALUE | J16: PRICE INCLUDING GST & FREIGHT (PER KM) | K16: QTY | L16: Unit | M16: TOTAL PRICE OF FULL QTY (INCLUDING FRIGHT & GST) | N16: Alumimium | O16: Alumimium ALLOY | P16: Copper | Q16: Flexible Copper | R16: Galvanized steel wire | S16: Alumimium | T16: Alumimium ALLOY | U16: Coper tape - 0.1 mm | V16: Copper Tape - 0.03 mm | W16: Copper Tape - 0.035 mm | X16: Copper Tape - 0.04 mm | Y16: Copper Tape - 0.045 mm | Z16: Copper Tape - 0.050 mm | AA16: Copper Tape - 0.060 mm | AB16: Copper Tape - 0.075 mm(DOUBLE) | AC16: Extruded semiconductive | AD16: Extruded Semiconductive(Stripable) | AE16: HT-XLPE | AF16: LT-XLPE | AG16: TR XLPE | AH16: Type A PVC | AI16: Type C PVC (HR) | AJ16: XLPE | AK16: POLY TAPE | AL16: FR PVC Type ST-1 | AM16: FR PVC Type ST-2 | AN16: FRLSH PVC Type ST-2 | AO16: PVC Type ST-1 | AP16: PVC Type ST-1-PRESSURE EXTRUDED | AQ16: PVC Type ST-2 | AR16: PVC Type ST-2-PRESSURE EXTRUDED | AS16: ACSR CORE WIRE | AT16: ACSR DOG STEEL WIRE | AU16: Aluminium Flat Strip | AV16: Aluminium Round Wire | AW16: Double Steel Tape | AX16: Galvanised Steel Flat Strip | AY16: Galvanised Steel Flat Strip (Double) | AZ16: Galvanised Steel Flat Strip-B | BA16: Galvanised Steel Round Wire | BB16: Galvanised Steel Round Wire (Double) | BC16: FR PVC Type ST-1 | BD16: FR PVC Type ST-2 | BE16: FRLSH PVC Type ST-1 | BF16: FRLSH PVC Type ST-2 | BG16: PE, ST-3 | BH16: PE-ST-7 | BI16: PVC Type ST-1 | BJ16: PVC Type ST-2 | BK16: PVC Type ST-2-PRESSURE EXTRUDED | BL16: UV & Track Resistant XLPE | BM16: FILLER | BN16: Grease | BO16: Water swellable Tape | BP16: Semi conducting Water Swellable tape | BQ16: SEMICON TAPE | BR16: GLASS FIBER TAPE | BS16: COPPER WIRE 0.8 MM | BT16: RUBBERIZED COTTON TAPE | BU16: Water Tight Compound | BV16: =Sheet1!E1 -> PROPOSE DRUM TYPE | BW16: =Sheet1!CV1 -> DRUM CODE | BX16: =Sheet1!CW1 -> DRUM SIZE (FxbXtx Ft) | BY16: =Sheet1!CX1 -> PARTY STANDARD LENGTH (MTR) | CD16: MFG% | CE16: MFG VALUE | CF16: PROF% | CG16: PROFIT VALUE | CH16: 1ST EX-WORKS | CI16: Intt % | CJ16: INTT VALUE | CK16: insp% | CL16: INSP VALUE
N17: 235 | O17: =+IFERROR(VLOOKUP($O$16,Sheet1!J:L,2,0),0) -> 0 | P17: =+IFERROR(VLOOKUP($P$16,Sheet1!J:M,2,0),0) -> 0 | Q17: =+IFERROR(VLOOKUP($Q$16,Sheet1!J:M,2,0),0) -> 0 | R17: =+IFERROR(VLOOKUP($R$16,Sheet1!J:M,2,0),0) -> 0 | S17: =+IFERROR(VLOOKUP($S$16,Sheet1!N:Q,2,0),0) -> 0 | T17: =N17+7 -> 242 | U17: =+IFERROR(VLOOKUP($U$16,Sheet1!F:I,2,0),0) -> 0 | V17: =+IFERROR(VLOOKUP($V$16,Sheet1!F:I,2,0),0) -> 0 | W17: =+IFERROR(VLOOKUP($W$16,Sheet1!F:I,2,0),0) -> 0 | X17: =+IFERROR(VLOOKUP($X$16,Sheet1!F:I,2,0),0) -> 0 | Y17: =+IFERROR(VLOOKUP($Y$16,Sheet1!F:I,2,0),0) -> 0 | Z17: =+IFERROR(VLOOKUP($Z$16,Sheet1!F:I,2,0),0) -> 0 | AA17: 972 | AB17: =+IFERROR(VLOOKUP($AB$16,Sheet1!F:I,2,0),0) -> 0 | AC17: 189 | AD17: =+IFERROR(VLOOKUP($AD$16,Sheet1!R:U,2,0),0) -> 0 | AE17: 145 | AF17: =+IFERROR(VLOOKUP($AF$16,Sheet1!V:Y,2,0),0) -> 0 | AG17: =+IFERROR(VLOOKUP($AG$16,Sheet1!V:Y,2,0),0) -> 0 | AH17: =+IFERROR(VLOOKUP($AH$16,Sheet1!V:Y,2,0),0) -> 0 | AI17: =+IFERROR(VLOOKUP($AI$16,Sheet1!V:Y,2,0),0) -> 0 | AJ17: =+IFERROR(VLOOKUP($AJ$16,Sheet1!V:Y,2,0),0) -> 0 | AK17: =+IFERROR(VLOOKUP($AK$16,Sheet1!Z2:AA840,2,0),0) -> 0 | AL17: =+IFERROR(VLOOKUP($AL$16,Sheet1!AD2:AG840,2,0),0) -> 0 | AM17: =+IFERROR(VLOOKUP($AM$16,Sheet1!AD2:AG840,2,0),0) -> 0 | AN17: =+IFERROR(VLOOKUP($AN$16,Sheet1!AD2:AG840,2,0),0) -> 0 | AO17: =+IFERROR(VLOOKUP($AO$16,Sheet1!AD2:AG840,2,0),0) -> 0 | AP17: =+IFERROR(VLOOKUP($AP$16,Sheet1!AD2:AG840,2,0),0) -> 0 | AQ17: =+IFERROR(VLOOKUP($AQ$16,Sheet1!AD2:AG840,2,0),0) -> 0 | AR17: =+IFERROR(VLOOKUP($AR$16,Sheet1!AD2:AG840,2,0),0) -> 0 | AS17: =+IFERROR(VLOOKUP($AS$16,Sheet1!AH2:AK840,2,0),0) -> 0 | AT17: =+IFERROR(VLOOKUP($AT$16,Sheet1!AH2:AK840,2,0),0) -> 0 | AU17: =+IFERROR(VLOOKUP($AU$16,Sheet1!AH2:AK840,2,0),0) -> 0 | AV17: =+IFERROR(VLOOKUP($AV$16,Sheet1!AH2:AK840,2,0),0) -> 0 | AW17: =+IFERROR(VLOOKUP($AW$16,Sheet1!AH2:AK840,2,0),0) -> 0 | AX17: =+IFERROR(VLOOKUP($AX$16,Sheet1!AH2:AK840,2,0),0) -> 0 | AY17: =+IFERROR(VLOOKUP($AY$16,Sheet1!AH2:AK840,2,0),0) -> 0 | AZ17: =+IFERROR(VLOOKUP($AZ$16,Sheet1!AH2:AK840,2,0),0) -> 0 | BA17: =+IFERROR(VLOOKUP($BA$16,Sheet1!AH2:AK840,2,0),0) -> 0 | BB17: =+IFERROR(VLOOKUP($BB$16,Sheet1!AH2:AK840,2,0),0) -> 0 | BC17: =+IFERROR(VLOOKUP($BC$16,Sheet1!AL2:AO840,2,0),0) -> 0 | BD17: =+IFERROR(VLOOKUP($BD$16,Sheet1!AL2:AO840,2,0),0) -> 0 | BE17: =+IFERROR(VLOOKUP($BE$16,Sheet1!AL2:AO840,2,0),0) -> 0 | BF17: =+IFERROR(VLOOKUP($BF$16,Sheet1!AL2:AO840,2,0),0) -> 0 | BG17: =+IFERROR(VLOOKUP($BG$16,Sheet1!AL2:AO840,2,0),0) -> 0 | BH17: 125 | BI17: =+IFERROR(VLOOKUP($BI$16,Sheet1!AL2:AO840,2,0),0) -> 0 | BJ17: =+IFERROR(VLOOKUP($BJ$16,Sheet1!AL2:AO840,2,0),0) -> 0 | BK17: =+IFERROR(VLOOKUP($BK$16,Sheet1!AL2:AO840,2,0),0) -> 0 | BL17: =+IFERROR(VLOOKUP($BL$16,Sheet1!AL2:AO840,2,0),0) -> 0 | BM17: =+IFERROR(VLOOKUP($BM$16,Sheet1!AP2:AS840,2,0),0) -> 0 | BN17: =+IFERROR(VLOOKUP($BN$16,Sheet1!AT2:AW840,2,0),0) -> 0 | BO17: =+IFERROR(VLOOKUP($BO$16,Sheet1!AX2:BA840,2,0),0) -> 0 | BP17: =+IFERROR(VLOOKUP($BP$16,Sheet1!BB2:BE840,2,0),0) -> 0 | BQ17: =+IFERROR(VLOOKUP($BQ$16,Sheet1!BF2:BI840,2,0),0) -> 0 | BR17: =+IFERROR(VLOOKUP($BR$16,Sheet1!BJ2:BM840,2,0),0) -> 0 | BS17: =+IFERROR(VLOOKUP($BS$16,Sheet1!BN2:BQ840,2,0),0) -> 0 | BT17: =+IFERROR(VLOOKUP($BT$16,Sheet1!BR2:BU840,2,0),0) -> 0 | BU17: =+IFERROR(VLOOKUP($BU$16,Sheet1!BV2:BY840,2,0),0) -> 0
A18: =Sheet1!A2 -> ENQ-13482-22-23 | B18: =Sheet1!B2 -> 45474 | C18: =Sheet1!C2 -> FA0400001 | D18: =Sheet1!D2 -> 3 CORE X 120 SQ MM + 1 CORE X 95 SQ MM (AB CABLES) (BARE) - 11 KV | E18: =CH18+CJ18+CL18 -> 1020018.3 | F18: =ROUNDUP(M21,0) -> 10500 | G18: =E18+F18 -> 1030518.3 | H18: =Sheet1!CP2 -> 0.18 | I18: =G18*H18 -> 185493.29 | J18: =G18+I18 -> 1216011.6 | K18: =Sheet1!CS2 -> 40 | L18: =Sheet1!CT2 -> KMS | M18: =J18*K18 -> 48640462 | N18: 972 | O18: =+IFERROR(VLOOKUP($O$16,Sheet1!J2:L2,3,0),0) -> 0 | P18: =+IFERROR(VLOOKUP($P$16,Sheet1!J2:M2,3,0),0) -> 0 | Q18: =+IFERROR(VLOOKUP($Q$16,Sheet1!J2:M2,3,0),0) -> 0 | R18: =+IFERROR(VLOOKUP($R$16,Sheet1!J2:M2,3,0),0) -> 0 | S18: =+IFERROR(VLOOKUP($S$16,Sheet1!N2:Q2,3,0),0) -> 0 | T18: 264 | U18: =+IFERROR(VLOOKUP($U$16,Sheet1!F2:I2,3,0),0) -> 0 | V18: =+IFERROR(VLOOKUP($V$16,Sheet1!F2:I2,3,0),0) -> 0 | W18: =+IFERROR(VLOOKUP($W$16,Sheet1!F2:I2,3,0),0) -> 0 | X18: =+IFERROR(VLOOKUP($X$16,Sheet1!F2:I2,3,0),0) -> 0 | Y18: =+IFERROR(VLOOKUP($Y$16,Sheet1!F2:I2,3,0),0) -> 0 | Z18: =+IFERROR(VLOOKUP($Z$16,Sheet1!F2:I2,3,0),0) -> 0 | AA18: 137 | AB18: =+IFERROR(VLOOKUP($AB$16,Sheet1!F2:I2,3,0),0) -> 0 | AC18: 310 | AD18: =+IFERROR(VLOOKUP($AD$16,Sheet1!R2:U2,2,0),0) -> 0 | AE18: 580 | AF18: =+IFERROR(VLOOKUP($AF$16,Sheet1!V2:Y2,3,0),0) -> 0 | AG18: =+IFERROR(VLOOKUP($AG$16,Sheet1!V2:Y2,3,0),0) -> 0 | AH18: =+IFERROR(VLOOKUP($AH$16,Sheet1!V2:Y2,3,0),0) -> 0 | AI18: =+IFERROR(VLOOKUP($AI$16,Sheet1!V2:Y2,3,0),0) -> 0 | AJ18: =+IFERROR(VLOOKUP($AJ$16,Sheet1!V2:Y2,3,0),0) -> 0 | AK18: =+IFERROR(VLOOKUP($AK$16,Sheet1!Z2:AB2,3,0),0) -> 0 | AL18: =+IFERROR(VLOOKUP($AL$16,Sheet1!AD2:AG2,3,0),0) -> 0 | AM18: =+IFERROR(VLOOKUP($AM$16,Sheet1!AD2:AG2,3,0),0) -> 0 | AN18: =+IFERROR(VLOOKUP($AN$16,Sheet1!AD2:AG2,3,0),0) -> 0 | AO18: =+IFERROR(VLOOKUP($AO$16,Sheet1!AD2:AG2,3,0),0) -> 0 | AP18: =+IFERROR(VLOOKUP($AP$16,Sheet1!AD2:AG2,3,0),0) -> 0 | AQ18: =+IFERROR(VLOOKUP($AQ$16,Sheet1!AD2:AG2,3,0),0) -> 0 | AR18: =+IFERROR(VLOOKUP($AR$16,Sheet1!AD2:AG2,3,0),0) -> 0 | AS18: =+IFERROR(VLOOKUP($AS$16,Sheet1!AH2:AK2,3,0),0) -> 0 | AT18: =+IFERROR(VLOOKUP($AT$16,Sheet1!AH2:AK2,3,0),0) -> 0 | AU18: =+IFERROR(VLOOKUP($AU$16,Sheet1!AH2:AK2,3,0),0) -> 0 | AV18: =+IFERROR(VLOOKUP($AV$16,Sheet1!AH2:AK2,3,0),0) -> 0 | AW18: =+IFERROR(VLOOKUP($AW$16,Sheet1!AH2:AK2,3,0),0) -> 0 | AX18: =+IFERROR(VLOOKUP($AX$16,Sheet1!AH2:AK2,3,0),0) -> 0 | AY18: =+IFERROR(VLOOKUP($AY$16,Sheet1!AH2:AK2,3,0),0) -> 0 | AZ18: =+IFERROR(VLOOKUP($AZ$16,Sheet1!AH2:AK2,3,0),0) -> 0 | BA18: =+IFERROR(VLOOKUP($BA$16,Sheet1!AH2:AK2,3,0),0) -> 0 | BB18: =+IFERROR(VLOOKUP($BB$16,Sheet1!AH2:AK2,3,0),0) -> 0 | BC18: =+IFERROR(VLOOKUP($BC$16,Sheet1!AL2:AO2,3,0),0) -> 0 | BD18: =+IFERROR(VLOOKUP($BD$16,Sheet1!AL2:AO2,3,0),0) -> 0 | BE18: =+IFERROR(VLOOKUP($BE$16,Sheet1!AL2:AO2,3,0),0) -> 0 | BF18: =+IFERROR(VLOOKUP($BF$16,Sheet1!AL2:AO2,3,0),0) -> 0 | BG18: =+IFERROR(VLOOKUP($BG$16,Sheet1!AL2:AO2,3,0),0) -> 0 | BH18: 506 | BI18: =+IFERROR(VLOOKUP($BI$16,Sheet1!AL2:AO2,3,0),0) -> 0 | BJ18: =+IFERROR(VLOOKUP($BJ$16,Sheet1!AL2:AO2,3,0),0) -> 0 | BK18: =+IFERROR(VLOOKUP($BK$16,Sheet1!AL2:AO2,3,0),0) -> 0 | BL18: =+IFERROR(VLOOKUP($BL$16,Sheet1!AL2:AO2,3,0),0) -> 0 | BM18: =+IFERROR(VLOOKUP($BM$16,Sheet1!AP2:AS2,3,0),0) -> 0 | BN18: =+IFERROR(VLOOKUP($BN$16,Sheet1!AT2:AW2,3,0),0) -> 0 | BO18: =+IFERROR(VLOOKUP($BO$16,Sheet1!AX2:BA2,3,0),0) -> 0 | BP18: =+IFERROR(VLOOKUP($BP$16,Sheet1!BB2:BE2,3,0),0) -> 0 | BQ18: =+IFERROR(VLOOKUP($BQ$16,Sheet1!BF2:BI2,3,0),0) -> 0 | BR18: =+IFERROR(VLOOKUP($BR$16,Sheet1!BJ2:BM2,3,0),0) -> 0 | BS18: =+IFERROR(VLOOKUP($BS$16,Sheet1!BN2:BQ2,3,0),0) -> 0 | BT18: =+IFERROR(VLOOKUP($BT$16,Sheet1!BR2:BU2,3,0),0) -> 0 | BU18: =+IFERROR(VLOOKUP($BU$16,Sheet1!BV2:BY2,3,0),0) -> 0 | BV18: =Sheet1!E2 -> WOOD | BW18: =Sheet1!CV2 -> MD0100027 | BX18: =Sheet1!CW2 -> DRUM - 76 X 40 X 38 X 3 | BY18: 500 | BZ18: =Sheet1!BZ2 -> 28794 | CA18: =SUMPRODUCT($N$17:$BU$17,N18:BU18)+BZ18 -> 660206 | CB18: =Sheet1!CB2 -> 0 | CC18: =CA18*CB18 -> 0 | CD18: 0.5 | CE18: =CA18*CD18 -> 330103 | CF18: 0 | CG18: =CA18*CF18 -> 0 | CH18: =CA18+CC18+CE18+CG18 -> 990309 | CI18: 0.02 | CJ18: =CH18*CI18 -> 19806.18 | CK18: 0.01 | CL18: =CH18*CK18 -> 9903.09
E20: Order Quantity | F20: Stnd Length | G20: Truck type | H20: Fare of one truck | I20: No of Drum in one truck | J20: Total length in one Truck | K20: No of Truck | L20: Total Freight | M20: Freight per KM | T20: CABLES WEIGHT KG/KM | AA20: DRUM WEIGHT | AC20: CABLE+DRUM WEIGHT | AE20: TRUCK WEIGHT
E21: =K18 -> 40 | F21: 0.5 | G21: 16 MT | H21: 35000 | I21: 7 | J21: =F21*I21 -> 3.5 | K21: =ROUNDUP((E21/J21),0) -> 12 | L21: =M21*E21 -> 420000 | M21: =(H21*K21)/E21 -> 10500 | T21: =N18+T18+AA18+AC18+AE18+BH18 -> 2769 | AA21: =350+70 -> 420 | AC21: =((T21*F21)+AA21) -> 1804.5 | AE21: =I21*AC21 -> 12631.5
E24: ESTIMATED COST (inclusive GST) | F24: AS PER COSTING SHEET | G24: %
D25: =D18 -> 3 CORE X 120 SQ MM + 1 CORE X 95 SQ MM (AB CABLES) (BARE) - 11 KV | E25: 47955693 | F25: =J18*K18 -> 48640462 | G25: =((F25-E25)/E25)*100 -> 1.4279209

Sheet HT ABC
A2: P = Po + AIph*n* (Al – Alo)+ AIm (Al – Alo)+ AIsl (Al – Alo)+CCFAIph*n*(CC-CCo)+CCFAIm(CC-CCo)+ CCFAIsl(CC-CCo) P = Po + AIph*n* (Al – Alo)+ AIm (Al – Alo)+ CUFtph*n*(Cu – Cuo)+CCF1AIph*n*(CC-CCo)+CCF2AIph*n*(PVCC-PVCCo)+ CCFAIm(CC-CCo)
A3: Base Date | B3: 45474
A4: PV Terms()
A5: PV FORMULA (IEEMA)
A6: P = Po + AIph*n* (Al – Alo)+ AIm (Al – Alo)+ AIsl (Al – Alo)+CCFAIph*n*(CC-CCo)+CCFAIm(CC-CCo)+ CCFAIsl(CC-CCo)
A9: n | B9: No. of Phase Conductor
A10: Alph | B10: Aluminium factor for phase conductor
A11: Alm | B11: Aluminium factor for messenger conductor
A12: CCFAIph | B12: XLPE factor for phase conductor
A13: CCFAIm | B13: XLPE factor for messenger conductor (For bare messenger,XLPE factor CCFAIm=0)
A15: Item | B15: Ex-Work
A16: ='AUTO CALCULATION SHEET (2)'!D18 -> 3 CORE X 120 SQ MM + 1 CORE X 95 SQ MM (AB CABLES) (BARE) - 11 KV | B16: ='AUTO CALCULATION SHEET (2)'!E18 -> 1020018.3
A18: Item | B18: Calculation part | C18: Date of Inspection | D18: Applicable Date | I18: BASE DATE | N18: FACTORS | W18: Ex-Work Po | X18: PVC of Al | Y18: PVC of AlM | Z18: PVC of Alsl | AA18: PVC of CUFtph | AB18: PVC of CCFAIph | AC18: PVC of CCFAIm | AD18: PVC of CCFAIsl | AE18: PVC of CCFAlph | AF18: PV/PKM | AG18: Billing Price/PKM | AH18: VALUE ADDITION CALCULATION WITH RESPECT TO PERCENTAGE
D19: Date | E19: Al | F19: Cu | G19: CC | H19: PEST7 | I19: Date | J19: Alo | K19: Cuo | L19: Cco | M19: PEST7o
N20: n | O20: Alph | P20: Alm | Q20: Alsl | R20: CUFtph | S20: CCFAIph | T20: CCFAIm | U20: CCFAIsl | V20: CCFAlph | AH20: ='AUTO CALCULATION SHEET (2)'!N16 -> Alumimium | AI20: ='AUTO CALCULATION SHEET (2)'!T16 -> Alumimium ALLOY | AJ20: ='AUTO CALCULATION SHEET (2)'!AA16 -> Copper Tape - 0.060 mm | AK20: ='AUTO CALCULATION SHEET (2)'!AC16 -> Extruded semiconductive | AL20: ='AUTO CALCULATION SHEET (2)'!AE16 -> HT-XLPE | AM20: ='AUTO CALCULATION SHEET (2)'!BH16 -> PE-ST-7 | AN20: RMC | AO20: Drum | AP20: RMC+Drum | AQ20: VA | AR20: Groos VA% | AS20: Mfg % | AT20: Int % | AU20: Ins% | AV20: Net VA %
AH21: 228 | AI21: =AH21+7 -> 235 | AJ21: 915 | AK21: 189 | AL21: 140 | AM21: 106
A22: =A16 -> 3 CORE X 120 SQ MM + 1 CORE X 95 SQ MM (AB CABLES) (BARE) - 11 KV | C22: Provisional | D22: 45505 | E22: 211378.47 | F22: 803165.19 | G22: 176484 | H22: 143250 | I22: =$B$3 -> 45474 | J22: 232711 | K22: 849090 | L22: 176484 | M22: 143250 | N22: 3 | O22: 0.346 | P22: 0.274 | R22: 0.036 | S22: 0.241 | V22: 0.172 | W22: =B16 -> 1020018.3 | X22: =(O22*N22*(E22-J22)) -> -22143.166 | Y22: =P22*(E22-J22) -> -5845.1132 | Z22: =Q22*(E22-J22) -> 0 | AA22: =N22*R22*(F22-K22) -> -4959.8795 | AB22: =(S22*N22*(G22-L22)) -> 0 | AC22: =T22*(G22-L22) -> 0 | AD22: =U22*(G22-L22) -> 0 | AE22: =N22*V22*(H22-M22) -> 0 | AF22: =X22+Y22+Z22+AA22+AB22+AC22+AD22+AE22 -> -32948.159 | AG22: =W22+AF22 -> 987070.11 | AH22: ='AUTO CALCULATION SHEET (2)'!N18 -> 972 | AI22: ='AUTO CALCULATION SHEET (2)'!T18 -> 264 | AJ22: ='AUTO CALCULATION SHEET (2)'!AA18 -> 137 | AK22: ='AUTO CALCULATION SHEET (2)'!AC18 -> 310 | AL22: ='AUTO CALCULATION SHEET (2)'!AE18 -> 580 | AM22: ='AUTO CALCULATION SHEET (2)'!BH18 -> 506 | AN22: =SUMPRODUCT($AH$21:$AM$21,AH22:AM22) -> 602437 | AO22: ='AUTO CALCULATION SHEET (2)'!BZ18 -> 28794 | AP22: =+AN22+AO22 -> 631231 | AQ22: =+AG22-AP22 -> 355839.11 | AR22: =+AQ22/AG22 -> 0.36050034 | AT22: 0.02 | AU22: 0.01 | AV22: =+AR22-(AS22+AT22+AU22) -> 0.33050034
