Workbook

Sheet Sheet1
A1: DOCKET NO. | B1: Base Date | C1: ITEM CODE | D1: PROPOSE ERP ITEM NAME | E1: PROPOSE DRUM TYPE | F1: Insulation Screening (Metallic) | G1: RM RATE (Insulation Screening (Metallic)) | H1: Weight (Insulation Screening (Metallic)) | I1: COST(Insulation Screening (Metallic)) | J1: Conductor | K1: RM RATE(Conductor) | L1: WEIGHT(Conductor) | M1: COST(Conductor) | N1: AL ALLOY | O1: RM RATE(Alu Alloy) | P1: WEIGHT(Alu Alloy) | Q1: COST(Alu Alloy) | R1: Insulation Screening (Non-Metallic) | S1: RM RATE(Insulation Screening (Non-Metallic)) | T1: WEIGHT(Insulation Screening (Non-Metallic)) | U1: COST(Insulation Screening (Non-Metallic)) | V1: Insulation | W1: RM RATE(Insulation) | X1: WEIGHT(Insulation) | Y1: COST(Insulation) | Z1: POLY TAPE | AA1: RM RATE (Poly Tape) | AB1: WEIGHT (Poly Tape) | AC1: COST(Poly Tape) | AD1: Inner Sheath | AE1: RM RATE(Inner Sheath) | AF1: WEIGHT(Inner Sheath) | AG1: COST(Inner Sheath) | AH1: Armouring | AI1: RM RATE(Armouring) | AJ1: WEIGHT(Armouring) | AK1: COST(Armouring) | AL1: Outer Sheath | AM1: RM RATE(Outer Sheath) | AN1: WEIGHT(Outer Sheath) | AO1: COST(Outer Sheath) | AP1: FILLER | AQ1: RM RATE(Filler) | AR1: WEIGHT(Filler) | AS1: COST(Filler) | AT1: GREASE | AU1: RM RATE(Grease) | AV1: WEIGHT(Grease) | AW1: COST(Grease) | AX1: Water swellable Tape | AY1: RM RATE(Water swellable Tape) | AZ1: WEIGHT(Water swellable Tape) | BA1: COST(Water swellable Tape) | BB1: Semi conducting Water Swellable tape | BC1: RM RATE(Semi conducting Water Swellable tape) | BD1: WEIGHT(Semi conducting Water Swellable tape) | BE1: COST(Semi conducting Water Swellable tape) | BF1: SEMICON TAPE | BG1: RM RATE(SEMICON TAPE) | BH1: WEIGHT(SEMICON TAPE) | BI1: COST(SEMICON TAPE) | BJ1: GLASS FIBER TAPE | BK1: RM RATE(GLASS FIBER TAPE) | BL1: WEIGHT(GLASS FIBER TAPE) | BM1: COST(GLASS FIBER TAPE) | BN1: COPPER WIRE 0.8 MM | BO1: RM RATE(COPPER WIRE 0.8 MM) | BP1: WEIGHT(COPPER WIRE 0.8 MM) | BQ1: COST(COPPER WIRE 0.8 MM) | BR1: RUBBERIZED COTTON TAPE | BS1: RM RATE(RUBBERIZED COTTON TAPE) | BT1: WEIGHT(RUBBERIZED COTTON TAPE) | BU1: COST(RUBBERIZED COTTON TAPE) | BV1: Water Tight Compound | BW1: RM RATE(Water Tight Compound) | BX1: WEIGHT(Water Tight Compound) | BY1: COST(Water Tight Compound) | BZ1: DRUM COST PER KM | CA1: TOTAL RM COST | CB1: FIRM % | CC1: FIRM VALUE | CD1: MFG% | CE1: MFG VALUE | CF1: PROF% | CG1: PROFIT VALUE | CH1: 1ST EX-WORKS | CI1: Intt % | CJ1: INTT VALUE | CK1: insp% | CL1: INSP VALUE | CM1: EX-WORKS (PER KM) | CN1: FREIGHT PER KM | CO1: PRICE INCLUDING FREIGHT (PER KM) | CP1: GST % | CQ1: GST VALUE | CR1: PRICE INCLUDING GST & FREIGHT (PER KM) | CS1: QTY | CT1: Unit | CU1: TOTAL PRICE OF FULL QTY (INCLUDING FRIGHT & GST) | CV1: DRUM CODE | CW1: DRUM SIZE (FxbXtx Ft) | CX1: PARTY STANDARD LENGTH (MTR)
A2: ENQ-12232-22-23 | B2: 45334 | C2: FA0800011 | D2: 1 CORE X 16 SQ. MM. CU/ARD (PVC) | E2: WOOD | J2: Copper | K2: 740 | L2: 142.24 | M2: 105257.6 | P2: 0 | T2: 0 | V2: Type C PVC (HR) | W2: 103.07 | X2: 40 | Y2: 4122.8 | AB2: 0 | AF2: 0 | AH2: Aluminium Round Wire | AI2: 221 | AJ2: 65 | AK2: 14365 | AL2: FRLSH PVC Type ST-2 | AM2: 92 | AN2: 88 | AO2: 8096 | AR2: 0 | AV2: 0 | AZ2: 0 | BD2: 0 | BH2: 0 | BL2: 15 | BP2: 0 | BT2: 0 | BX2: 0 | BZ2: 3751.68 | CA2: 135593.08 | CH2: 135593.08 | CM2: 135593.08 | CO2: 135593.08 | CP2: 0.18 | CQ2: 24406.75 | CR2: 159999.83 | CS2: 0.12 | CT2: KMS | CU2: 19200 | CV2: MD0100004 | CW2: DRUM - 28 X 10 X 23 X 2 | CX2: 500
A3: ENQ-12232-22-23 | B3: 45334 | C3: FA1100091 | D3: 4 CORE X 240 SQ. MM. AL/ARD - WIRE (XLPE) | E3: WOOD | J3: Alumimium | K3: 216 | L3: 2594.88 | M3: 560494.08 | P3: 0 | T3: 0 | V3: LT-XLPE | W3: 107 | X3: 438 | Y3: 46866 | AB3: 0 | AD3: PVC Type ST-2 | AE3: 60.05 | AF3: 244 | AG3: 14652.2 | AH3: Galvanised Steel Round Wire | AI3: 83.9 | AJ3: 2364 | AK3: 198339.6 | AL3: FRLSH PVC Type ST-2 | AM3: 92 | AN3: 735 | AO3: 67620 | AR3: 0 | AV3: 0 | AX3: Water swellable Tape | AY3: 445 | AZ3: 0 | BA3: 0 | BD3: 0 | BH3: 0 | BL3: 0 | BP3: 0 | BR3: RUBBERIZED COTTON TAPE | BS3: 445 | BT3: 0 | BU3: 0 | BX3: 0 | BZ3: 27302 | CA3: 915273.88 | CH3: 915273.88 | CM3: 915273.88 | CO3: 915273.88 | CP3: 0.18 | CQ3: 164749.3 | CR3: 1080023.2 | CS3: 1 | CT3: KMS | CU3: 1080023 | CV3: MD0100048 | CW3: DRUM - 74 X 35 X 39 X 3 | CX3: 500
A4: ENQ-12232-22-23 | B4: 45334 | C4: FA0900125 | D4: 4 CORE X 16 SQ. MM. CU/ARD - WIRE (PVC) | E4: WOOD | J4: Copper | K4: 740 | L4: 568.96 | M4: 421030.4 | P4: 0 | T4: 0 | V4: Type C PVC (HR) | W4: 103.07 | X4: 114 | Y4: 11749.98 | AB4: 0 | AD4: PVC Type ST-2 | AE4: 60.05 | AF4: 40 | AG4: 2402 | AH4: Galvanised Steel Round Wire | AI4: 83.9 | AJ4: 498 | AK4: 41782.2 | AL4: FRLSH PVC Type ST-2 | AM4: 92 | AN4: 166 | AO4: 15272 | AR4: 0 | AV4: 0 | AZ4: 0 | BD4: 0 | BH4: 0 | BL4: 0 | BP4: 0 | BT4: 0 | BX4: 0 | BZ4: 5151.48 | CA4: 497388.06 | CH4: 497388.06 | CM4: 497388.06 | CO4: 497388.06 | CP4: 0.18 | CQ4: 89529.85 | CR4: 586917.91 | CS4: 1.5 | CT4: KMS | CU4: 880377 | CV4: MD0100066 | CW4: DRUM - 40 X 15 X 23 X 2 | CX4: 500
A5: ENQ-12232-22-23 | B5: 45334 | C5: FA0900024 | D5: 4 CORE X 4 SQ. MM. CU/ARD - WIRE (PVC) | E5: WOOD | J5: Copper | K5: 740 | L5: 144 | M5: 106560 | P5: 0 | T5: 0 | V5: Type C PVC (HR) | W5: 103.07 | X5: 76 | Y5: 7833.32 | Z5: POLY TAPE | AA5: 119.6 | AB5: 4 | AC5: 478.4 | AD5: PVC Type ST-2 | AE5: 60.05 | AF5: 34 | AG5: 2041.7 | AH5: Galvanised Steel Round Wire | AI5: 83.9 | AJ5: 352 | AK5: 29532.8 | AL5: FRLSH PVC Type ST-2 | AM5: 92 | AN5: 119 | AO5: 10948 | AR5: 0 | AV5: 0 | AZ5: 0 | BD5: 0 | BH5: 0 | BL5: 0 | BP5: 0 | BT5: 0 | BX5: 0 | BZ5: 4610.79 | CA5: 162005.01 | CH5: 162005.01 | CM5: 162005.01 | CO5: 162005.01 | CP5: 0.18 | CQ5: 29160.9 | CR5: 191165.91 | CS5: 2 | CT5: KMS | CU5: 382332 | CV5: MD0100005 | CW5: DRUM - 36 X 14 X 23 X 2 | CX5: 500
A6: ENQ-12232-22-23 | B6: 45334 | C6: FA0900148 | D6: 2 CORE X 16 SQ. MM. CU/ARD - WIRE (PVC) | E6: WOOD | J6: Copper | K6: 740 | L6: 284.48 | M6: 210515.2 | P6: 0 | T6: 0 | V6: Type C PVC (HR) | W6: 103.07 | X6: 57 | Y6: 5874.99 | AB6: 0 | AD6: PVC Type ST-2 | AE6: 60.05 | AF6: 33 | AG6: 1981.65 | AH6: Galvanised Steel Round Wire | AI6: 83.9 | AJ6: 416 | AK6: 34902.4 | AL6: FRLSH PVC Type ST-2 | AM6: 92 | AN6: 144 | AO6: 13248 | AR6: 0 | AV6: 0 | AZ6: 0 | BD6: 0 | BH6: 0 | BL6: 0 | BP6: 0 | BT6: 0 | BX6: 0 | BZ6: 4610.79 | CA6: 271133.03 | CH6: 271133.03 | CM6: 271133.03 | CO6: 271133.03 | CP6: 0.18 | CQ6: 48803.95 | CR6: 319936.98 | CS6: 2.12 | CT6: KMS | CU6: 678266 | CV6: MD0100005 | CW6: DRUM - 36 X 14 X 23 X 2 | CX6: 500
A7: ENQ-12232-22-23 | B7: 45334 | C7: FA0900022 | D7: 4 CORE X 10 SQ. MM. CU/ARD - WIRE (PVC) | E7: WOOD | J7: Copper | K7: 740 | L7: 355.6 | M7: 263144 | P7: 0 | T7: 0 | V7: Type A PVC-1.45 | W7: 73.07 | X7: 98 | Y7: 7160.86 | AB7: 0 | AD7: PVC Type ST-1 | AE7: 58.05 | AF7: 35 | AG7: 2031.75 | AH7: Galvanised Steel Round Wire | AI7: 83.9 | AJ7: 441 | AK7: 36999.9 | AL7: PVC Type ST-1 | AM7: 58.05 | AN7: 151 | AO7: 8765.55 | AR7: 0 | AV7: 0 | AZ7: 0 | BD7: 0 | BH7: 0 | BL7: 0 | BP7: 0 | BT7: 0 | BX7: 0 | BZ7: 5151.48 | CA7: 323253.54 | CH7: 323253.54 | CM7: 323253.54 | CO7: 323253.54 | CP7: 0.18 | CQ7: 58185.64 | CR7: 381439.18 | CS7: 3 | CT7: KMS | CU7: 1144318 | CV7: MD0100066 | CW7: DRUM - 40 X 15 X 23 X 2 | CX7: 500
A8: ENQ-12232-22-23 | B8: 45334 | C8: FA0900165 | D8: 2 CORE X 50 SQ. MM. CU/ARD - WIRE (PVC) | E8: WOOD | J8: Copper | K8: 740 | L8: 860 | M8: 636400 | P8: 0 | T8: 0 | V8: Type C PVC (HR) | W8: 103.07 | X8: 132 | Y8: 13605.24 | AB8: 0 | AD8: PVC Type ST-2 | AE8: 60.05 | AF8: 50 | AG8: 3002.5 | AH8: Galvanised Steel Round Wire | AI8: 83.9 | AJ8: 575 | AK8: 48242.5 | AL8: FRLSH PVC Type ST-2 | AM8: 92 | AN8: 204 | AO8: 18768 | AR8: 0 | AV8: 0 | AZ8: 0 | BD8: 0 | BH8: 0 | BL8: 0 | BP8: 0 | BT8: 0 | BX8: 0 | BZ8: 7084.06 | CA8: 727102.3 | CH8: 727102.3 | CM8: 727102.3 | CO8: 727102.3 | CP8: 0.18 | CQ8: 130878.41 | CR8: 857980.71 | CS8: 3.65 | CT8: KMS | CU8: 3131630 | CV8: MD0100075 | CW8: DRUM - 42 X 15 X 23 X 2 | CX8: 500
A9: ENQ-12232-22-23 | B9: 45334 | C9: FA0500017 | D9: 1 CORE X 50 SQ. MM. AL/UNARD. (XLPE) | E9: WOOD | J9: Alumimium | K9: 216 | L9: 135 | M9: 29160 | P9: 0 | T9: 0 | V9: LT-XLPE | W9: 107 | X9: 37 | Y9: 3959 | AB9: 0 | AF9: 0 | AJ9: 0 | AL9: FRLSH PVC Type ST-2 | AM9: 92 | AN9: 110 | AO9: 10120 | AR9: 0 | AV9: 0 | AZ9: 0 | BD9: 0 | BH9: 0 | BL9: 0 | BP9: 0 | BT9: 0 | BX9: 0 | BZ9: 2305.4 | CA9: 45544.4 | CH9: 45544.4 | CM9: 45544.4 | CO9: 45544.4 | CP9: 0.18 | CQ9: 8197.99 | CR9: 53742.39 | CS9: 6.5 | CT9: KMS | CU9: 349326 | CV9: MD0100005 | CW9: DRUM - 36 X 14 X 23 X 2 | CX9: 1000
A10: ENQ-12232-22-23 | B10: 45334 | C10: FA1200026 | D10: 4 CORE X 150 SQ. MM. AL/UNARD (XLPE) | E10: WOOD | J10: Alumimium | K10: 216 | L10: 1620 | M10: 349920 | P10: 0 | T10: 0 | V10: LT-XLPE | W10: 107 | X10: 297 | Y10: 31779 | AB10: 0 | AD10: PVC Type ST-2 | AE10: 60.05 | AF10: 138 | AG10: 8286.9 | AJ10: 0 | AL10: FRLSH PVC Type ST-2 | AM10: 92 | AN10: 552 | AO10: 50784 | AR10: 0 | AV10: 0 | AX10: Water swellable Tape | AY10: 445 | AZ10: 0 | BA10: 0 | BD10: 0 | BH10: 0 | BL10: 0 | BP10: 0 | BT10: 0 | BX10: 0 | BZ10: 17878.84 | CA10: 458648.74 | CH10: 458648.74 | CM10: 458648.74 | CO10: 458648.74 | CP10: 0.18 | CQ10: 82556.77 | CR10: 541205.51 | CS10: 7.925 | CT10: KMS | CU10: 4289054 | CV10: MD0100070 | CW10: DRUM - 68 X 24 X 32 X 3 | CX10: 500
A11: ENQ-12232-22-23 | B11: 45334 | C11: FA0900117 | D11: 4 CORE X 35 SQ. MM. AL/ARD - WIRE (XLPE) | E11: WOOD | J11: Alumimium | K11: 216 | L11: 378.42 | M11: 81738.72 | P11: 0 | T11: 0 | V11: LT-XLPE | W11: 107 | X11: 109 | Y11: 11663 | AB11: 0 | AD11: PVC Type ST-2 | AE11: 60.05 | AF11: 51 | AG11: 3062.55 | AH11: Galvanised Steel Round Wire | AI11: 83.9 | AJ11: 639 | AK11: 53612.1 | AL11: FRLSH PVC Type ST-2 | AM11: 92 | AN11: 230 | AO11: 21160 | AR11: 0 | AV11: 0 | AZ11: 0 | BD11: 0 | BH11: 0 | BL11: 0 | BP11: 0 | BR11: RUBBERIZED COTTON TAPE | BS11: 445 | BT11: 0 | BU11: 0 | BX11: 0 | BZ11: 3743.02 | CA11: 174979.39 | CH11: 174979.39 | CM11: 174979.39 | CO11: 174979.39 | CP11: 0.18 | CQ11: 31496.29 | CR11: 206475.68 | CS11: 10.2 | CT11: KMS | CU11: 2106052 | CV11: MD0100013 | CW11: DRUM - 48 X 14 X 36 X 2.25 | CX11: 1000
A12: ENQ-12232-22-23 | B12: 45334 | C12: FA0900116 | D12: 4 CORE X 50 SQ. MM. AL/ARD - WIRE (XLPE) | E12: WOOD | J12: Alumimium | K12: 216 | L12: 540.6 | M12: 116769.6 | P12: 0 | T12: 0 | V12: LT-XLPE | W12: 107 | X12: 124 | Y12: 13268 | AB12: 0 | AD12: PVC Type ST-2 | AE12: 60.05 | AF12: 69 | AG12: 4143.45 | AH12: Galvanised Steel Round Wire | AI12: 83.9 | AJ12: 898 | AK12: 75342.2 | AL12: FRLSH PVC Type ST-2 | AM12: 92 | AN12: 260 | AO12: 23920 | AR12: 0 | AV12: 0 | AZ12: 0 | BD12: 0 | BH12: 0 | BL12: 0 | BP12: 0 | BR12: RUBBERIZED COTTON TAPE | BS12: 445 | BT12: 0 | BU12: 0 | BX12: 0 | BZ12: 5708.97 | CA12: 239152.22 | CH12: 239152.22 | CM12: 239152.22 | CO12: 239152.22 | CP12: 0.18 | CQ12: 43047.4 | CR12: 282199.62 | CS12: 13.67 | CT12: KMS | CU12: 3857669 | CV12: MD0100068 | CW12: DRUM - 54 X 20 X 36 X 2.5 | CX12: 1000
A13: ENQ-12232-22-23 | B13: 45334 | C13: FA0300006 | D13: 4 CORE X 2.5 SQ. MM. CU/UNARD.(PVC) | E13: WOOD | J13: Copper | K13: 740 | L13: 88.8 | M13: 65712 | P13: 0 | T13: 0 | V13: Type C PVC (HR) | W13: 103.07 | X13: 52 | Y13: 5359.64 | Z13: POLY TAPE | AA13: 119.6 | AB13: 4 | AC13: 478.4 | AD13: PVC Type ST-2 | AE13: 60.05 | AF13: 27 | AG13: 1621.35 | AJ13: 0 | AL13: FRLSH PVC Type ST-2 | AM13: 92 | AN13: 109 | AO13: 10028 | AR13: 0 | AV13: 0 | AZ13: 0 | BD13: 0 | BH13: 0 | BL13: 15 | BP13: 0 | BT13: 0 | BX13: 0 | BZ13: 3850.93 | CA13: 87050.32 | CH13: 87050.32 | CM13: 87050.32 | CO13: 87050.32 | CP13: 0.18 | CQ13: 15669.06 | CR13: 102719.38 | CS13: 16.3 | CT13: KMS | CU13: 1674326 | CV13: MD0100003 | CW13: DRUM - 28 X 14 X 23 X 2 | CX13: 500
A14: ENQ-12232-22-23 | B14: 45334 | C14: FA0300017 | D14: 16 CORE X 2.5 SQ. MM. CU/UNARD.(PVC) | E14: WOOD | J14: Copper | K14: 740 | L14: 355.2 | M14: 262848 | P14: 0 | T14: 0 | V14: Type C PVC (HR) | W14: 103.07 | X14: 208 | Y14: 21438.56 | Z14: POLY TAPE | AA14: 119.6 | AB14: 5 | AC14: 598 | AD14: PVC Type ST-2 | AE14: 60.05 | AF14: 42 | AG14: 2522.1 | AJ14: 0 | AL14: FRLSH PVC Type ST-2 | AM14: 92 | AN14: 191 | AO14: 17572 | AR14: 0 | AV14: 0 | AZ14: 0 | BD14: 0 | BH14: 0 | BL14: 0 | BP14: 0 | BT14: 0 | BX14: 0 | BZ14: 7084.06 | CA14: 312062.72 | CH14: 312062.72 | CM14: 312062.72 | CO14: 312062.72 | CP14: 0.18 | CQ14: 56171.29 | CR14: 368234.01 | CS14: 18.5 | CT14: KMS | CU14: 6812329 | CV14: MD0100075 | CW14: DRUM - 42 X 15 X 23 X 2 | CX14: 500
A15: ENQ-12232-22-23 | B15: 45334 | C15: FA0600021 | D15: 1 CORE X 185 SQ. MM. AL/UNARD. (XLPE) | E15: WOOD | J15: Alumimium | K15: 216 | L15: 499.5 | M15: 107892 | P15: 0 | T15: 0 | V15: LT-XLPE | W15: 107 | X15: 90 | Y15: 9630 | AB15: 0 | AF15: 0 | AJ15: 0 | AL15: FRLSH PVC Type ST-2 | AM15: 92 | AN15: 207 | AO15: 19044 | AR15: 0 | AV15: 0 | AX15: Water swellable Tape | AY15: 445 | AZ15: 0 | BA15: 0 | BD15: 0 | BH15: 0 | BL15: 0 | BP15: 0 | BT15: 0 | BX15: 0 | BZ15: 3505.61 | CA15: 140071.61 | CH15: 140071.61 | CM15: 140071.61 | CO15: 140071.61 | CP15: 0.18 | CQ15: 25212.89 | CR15: 165284.5 | CS15: 20 | CT15: KMS | CU15: 3305690 | CV15: MD0100090 | CW15: DRUM - 43 X 15 X 36 X 2.5 | CX15: 1000
A16: ENQ-12232-22-23 | B16: 45334 | C16: FA1100177 | D16: 4 CORE X 150 SQ. MM. AL/ARD - WIRE (XLPE) | E16: WOOD | J16: Alumimium | K16: 216 | L16: 1620 | M16: 349920 | P16: 0 | T16: 0 | V16: LT-XLPE | W16: 107 | X16: 276 | Y16: 29532 | AB16: 0 | AD16: PVC Type ST-2 | AE16: 60.05 | AF16: 148 | AG16: 8887.4 | AH16: Galvanised Steel Round Wire | AI16: 83.9 | AJ16: 1965 | AK16: 164863.5 | AL16: FRLSH PVC Type ST-2 | AM16: 92 | AN16: 543 | AO16: 49956 | AR16: 0 | AV16: 0 | AX16: Water swellable Tape | AY16: 445 | AZ16: 0 | BA16: 0 | BD16: 48 | BH16: 0 | BL16: 0 | BP16: 0 | BR16: RUBBERIZED COTTON TAPE | BS16: 445 | BT16: 26 | BU16: 11570 | BX16: 0 | BZ16: 18867.25 | CA16: 633596.15 | CH16: 633596.15 | CM16: 633596.15 | CO16: 633596.15 | CP16: 0.18 | CQ16: 114047.31 | CR16: 747643.46 | CS16: 22.17 | CT16: KMS | CU16: 16575255 | CV16: MD0100024 | CW16: DRUM - 70 X 30 X 36 X 3 | CX16: 500
A17: ENQ-12232-22-23 | B17: 45334 | C17: FA0300011 | D17: 10 CORE X 2.5 SQ. MM. CU/UNARD. (PVC) | E17: WOOD | J17: Copper | K17: 740 | L17: 222 | M17: 164280 | P17: 0 | T17: 0 | V17: Type C PVC (HR) | W17: 103.07 | X17: 130 | Y17: 13399.1 | Z17: POLY TAPE | AA17: 119.6 | AB17: 5 | AC17: 598 | AD17: PVC Type ST-2 | AE17: 60.05 | AF17: 36 | AG17: 2161.8 | AJ17: 0 | AL17: FRLSH PVC Type ST-2 | AM17: 92 | AN17: 165 | AO17: 15180 | AR17: 0 | AV17: 0 | AZ17: 0 | BD17: 0 | BH17: 0 | BL17: 0 | BP17: 0 | BT17: 0 | BX17: 0 | BZ17: 5151.48 | CA17: 200770.38 | CH17: 200770.38 | CM17: 200770.38 | CO17: 200770.38 | CP17: 0.18 | CQ17: 36138.67 | CR17: 236909.05 | CS17: 22.3 | CT17: KMS | CU17: 5283072 | CV17: MD0100066 | CW17: DRUM - 40 X 15 X 23 X 2 | CX17: 500
A18: ENQ-12232-22-23 | B18: 45334 | C18: FA1100176 | D18: 4 CORE X 300 SQ. MM. AL/ARD - WIRE (XLPE) | E18: WOOD | J18: Alumimium | K18: 216 | L18: 3240 | M18: 699840 | P18: 0 | T18: 0 | V18: LT-XLPE | W18: 107 | X18: 488 | Y18: 52216 | AB18: 0 | AD18: PVC Type ST-2 | AE18: 60.05 | AF18: 255 | AG18: 15312.75 | AH18: Galvanised Steel Round Wire | AI18: 83.9 | AJ18: 3436 | AK18: 288280.4 | AL18: FRLSH PVC Type ST-2 | AM18: 92 | AN18: 888 | AO18: 81696 | AR18: 0 | AV18: 0 | AX18: Water swellable Tape | AY18: 445 | AZ18: 0 | BA18: 0 | BD18: 90 | BH18: 0 | BL18: 0 | BP18: 0 | BR18: RUBBERIZED COTTON TAPE | BS18: 445 | BT18: 36 | BU18: 16020 | BX18: 0 | BZ18: 47086 | CA18: 1200451.1 | CH18: 1200451.1 | CM18: 1200451.1 | CO18: 1200451.1 | CP18: 0.18 | CQ18: 216081.21 | CR18: 1416532.4 | CS18: 34.32 | CT18: KMS | CU18: 48615390 | CV18: MD0100040 | CW18: DRUM - 86 X 38 X 46 X 4 | CX18: 500
A19: ENQ-12232-22-23 | B19: 45334 | C19: FA0600019 | D19: 1 CORE X 150 SQ. MM. AL/UNARD. (XLPE) | E19: WOOD | J19: Alumimium | K19: 216 | L19: 405 | M19: 87480 | P19: 0 | T19: 0 | V19: LT-XLPE | W19: 107 | X19: 72 | Y19: 7704 | AB19: 0 | AF19: 0 | AJ19: 0 | AL19: FRLSH PVC Type ST-2 | AM19: 92 | AN19: 187 | AO19: 17204 | AR19: 0 | AV19: 0 | AX19: Water swellable Tape | AY19: 445 | AZ19: 0 | BA19: 0 | BD19: 0 | BH19: 0 | BL19: 0 | BP19: 0 | BT19: 0 | BX19: 0 | BZ19: 3257.88 | CA19: 115645.88 | CH19: 115645.88 | CM19: 115645.88 | CO19: 115645.88 | CP19: 0.18 | CQ19: 20816.26 | CR19: 136462.14 | CS19: 47.838 | CT19: KMS | CU19: 6528076 | CV19: MD0100085 | CW19: DRUM - 43 X 15 X 28 X 2.25 | CX19: 1000
A20: ENQ-12232-22-23 | B20: 45334 | C20: FA0200003 | D20: 12 CORE X 2.5 SQ. MM. CU/ARD - WIRE (PVC) | E20: WOOD | J20: Copper | K20: 740 | L20: 266.4 | M20: 197136 | P20: 0 | T20: 0 | V20: Type C PVC (HR) | W20: 103.07 | X20: 156 | Y20: 16078.92 | Z20: POLY TAPE | AA20: 119.6 | AB20: 6 | AC20: 717.6 | AD20: PVC Type ST-2 | AE20: 60.05 | AF20: 40 | AG20: 2402 | AH20: Galvanised Steel Round Wire | AI20: 83.9 | AJ20: 508 | AK20: 42621.2 | AL20: FRLSH PVC Type ST-2 | AM20: 92 | AN20: 170 | AO20: 15640 | AR20: 0 | AV20: 0 | AZ20: 0 | BD20: 0 | BH20: 0 | BL20: 28 | BP20: 0 | BT20: 0 | BX20: 0 | BZ20: 5151.48 | CA20: 279747.2 | CH20: 279747.2 | CM20: 279747.2 | CO20: 279747.2 | CP20: 0.18 | CQ20: 50354.5 | CR20: 330101.7 | CS20: 62.667 | CT20: KMS | CU20: 20686483 | CV20: MD0100066 | CW20: DRUM - 40 X 15 X 23 X 2 | CX20: 500
A21: ENQ-12232-22-23 | B21: 45334 | C21: FA0600020 | D21: 1 CORE X 300 SQ. MM. AL/UNARD. (XLPE) | E21: WOOD | J21: Alumimium | K21: 216 | L21: 810 | M21: 174960 | P21: 0 | T21: 0 | V21: LT-XLPE | W21: 107 | X21: 132 | Y21: 14124 | AB21: 0 | AF21: 0 | AJ21: 0 | AL21: FRLSH PVC Type ST-2 | AM21: 92 | AN21: 251 | AO21: 23092 | AR21: 0 | AV21: 0 | AX21: Water swellable Tape | AY21: 445 | AZ21: 0 | BA21: 0 | BD21: 0 | BH21: 0 | BL21: 0 | BP21: 0 | BT21: 0 | BX21: 0 | BZ21: 4956.84 | CA21: 217132.84 | CH21: 217132.84 | CM21: 217132.84 | CO21: 217132.84 | CP21: 0.18 | CQ21: 39083.91 | CR21: 256216.75 | CS21: 63.368 | CT21: KMS | CU21: 16235943 | CV21: MD0100017 | CW21: DRUM - 52 X 18 X 36 X 2.5 | CX21: 1000
A22: ENQ-12232-22-23 | B22: 45334 | C22: FA0600032 | D22: 1 CORE X 630 SQ. MM. ALU/UNARD (XLPE) | E22: WOOD | J22: Alumimium | K22: 216 | L22: 1701 | M22: 367416 | P22: 0 | T22: 0 | V22: LT-XLPE | W22: 107 | X22: 253 | Y22: 27071 | AB22: 0 | AF22: 0 | AJ22: 0 | AL22: FRLSH PVC Type ST-2 | AM22: 92 | AN22: 429 | AO22: 39468 | AR22: 0 | AV22: 0 | AX22: Water swellable Tape | AY22: 445 | AZ22: 0 | BA22: 0 | BD22: 0 | BH22: 0 | BL22: 0 | BP22: 0 | BT22: 0 | BX22: 0 | BZ22: 17290 | CA22: 451245 | CH22: 451245 | CM22: 451245 | CO22: 451245 | CP22: 0.18 | CQ22: 81224.1 | CR22: 532469.1 | CS22: 81.688 | CT22: KMS | CU22: 43496336 | CV22: MD0100062 | CW22: DRUM - 74 X 24 X 32 X 3 | CX22: 1000
A23: ENQ-12232-22-23 | B23: 45334 | C23: FA0600013 | D23: 1 CORE X 95 SQ. MM. AL/UNARD(XLPE ) | E23: WOOD | J23: Alumimium | K23: 216 | L23: 256.5 | M23: 55404 | P23: 0 | T23: 0 | V23: LT-XLPE | W23: 107 | X23: 53 | Y23: 5671 | AB23: 0 | AF23: 0 | AJ23: 0 | AL23: FRLSH PVC Type ST-2 | AM23: 92 | AN23: 139 | AO23: 12788 | AR23: 0 | AV23: 0 | AZ23: 0 | BD23: 0 | BH23: 0 | BL23: 0 | BP23: 0 | BT23: 0 | BX23: 0 | BZ23: 2575.74 | CA23: 76438.74 | CH23: 76438.74 | CM23: 76438.74 | CO23: 76438.74 | CP23: 0.18 | CQ23: 13758.97 | CR23: 90197.71 | CS23: 82.208 | CT23: KMS | CU23: 7414974 | CV23: MD0100066 | CW23: DRUM - 40 X 15 X 23 X 2 | CX23: 1000
A24: ENQ-12232-22-23 | B24: 45334 | C24: FA0200002 | D24: 10 CORE X 2.5 SQ. MM. CU/ARD - WIRE (PVC) | E24: WOOD | J24: Copper | K24: 740 | L24: 222 | M24: 164280 | P24: 0 | T24: 0 | V24: Type C PVC (HR) | W24: 103.07 | X24: 130 | Y24: 13399.1 | Z24: POLY TAPE | AA24: 119.6 | AB24: 5 | AC24: 598 | AD24: PVC Type ST-2 | AE24: 60.05 | AF24: 38 | AG24: 2281.9 | AH24: Galvanised Steel Round Wire | AI24: 83.9 | AJ24: 492 | AK24: 41278.8 | AL24: FRLSH PVC Type ST-2 | AM24: 92 | AN24: 166 | AO24: 15272 | AR24: 0 | AV24: 0 | AZ24: 0 | BD24: 0 | BH24: 0 | BL24: 28 | BP24: 0 | BT24: 0 | BX24: 0 | BZ24: 5151.48 | CA24: 242261.28 | CH24: 242261.28 | CM24: 242261.28 | CO24: 242261.28 | CP24: 0.18 | CQ24: 43607.03 | CR24: 285868.31 | CS24: 83.006 | CT24: KMS | CU24: 23728785 | CV24: MD0100066 | CW24: DRUM - 40 X 15 X 23 X 2 | CX24: 500
A25: ENQ-12232-22-23 | B25: 45334 | C25: FA0200018 | D25: 7 CORE X 2.5 SQ. MM. CU/ARD - WIRE (PVC) | E25: WOOD | J25: Copper | K25: 740 | L25: 155.4 | M25: 114996 | P25: 0 | T25: 0 | V25: Type C PVC (HR) | W25: 103.07 | X25: 91 | Y25: 9379.37 | Z25: POLY TAPE | AA25: 119.6 | AB25: 4 | AC25: 478.4 | AD25: PVC Type ST-2 | AE25: 60.05 | AF25: 30 | AG25: 1801.5 | AH25: Galvanised Steel Round Wire | AI25: 83.9 | AJ25: 339 | AK25: 28442.1 | AL25: FRLSH PVC Type ST-2 | AM25: 92 | AN25: 120 | AO25: 11040 | AR25: 0 | AV25: 0 | AZ25: 0 | BD25: 0 | BH25: 0 | BL25: 22 | BP25: 0 | BT25: 0 | BX25: 0 | BZ25: 4610.79 | CA25: 170748.16 | CH25: 170748.16 | CM25: 170748.16 | CO25: 170748.16 | CP25: 0.18 | CQ25: 30734.67 | CR25: 201482.83 | CS25: 86.355 | CT25: KMS | CU25: 17399050 | CV25: MD0100005 | CW25: DRUM - 36 X 14 X 23 X 2 | CX25: 500
A26: ENQ-12232-22-23 | B26: 45334 | C26: FA0900042 | D26: 2 CORE X 10 SQ. MM. ALU/ARD - WIRE (XLPE) | E26: WOOD | J26: Alumimium | K26: 216 | L26: 54 | M26: 11664 | P26: 0 | T26: 0 | V26: LT-XLPE | W26: 107 | X26: 31 | Y26: 3317 | AB26: 0 | AD26: PVC Type ST-2-PRESSURE EXTRUDED | AE26: 88 | AF26: 112 | AG26: 9856 | AH26: Galvanised Steel Round Wire | AI26: 83.9 | AJ26: 360 | AK26: 30204 | AL26: FRLSH PVC Type ST-2 | AM26: 92 | AN26: 130 | AO26: 11960 | AR26: 0 | AV26: 0 | AZ26: 0 | BD26: 0 | BH26: 0 | BL26: 0 | BP26: 0 | BR26: RUBBERIZED COTTON TAPE | BS26: 445 | BT26: 0 | BU26: 0 | BX26: 0 | BZ26: 3542.03 | CA26: 70543.03 | CH26: 70543.03 | CM26: 70543.03 | CO26: 70543.03 | CP26: 0.18 | CQ26: 12697.75 | CR26: 83240.78 | CS26: 88.713 | CT26: KMS | CU26: 7384539 | CV26: MD0100075 | CW26: DRUM - 42 X 15 X 23 X 2 | CX26: 1000
A27: ENQ-12232-22-23 | B27: 45334 | C27: FA0200011 | D27: 4 CORE X 2.5 SQ. MM. CU/ARD - WIRE (PVC) | E27: WOOD | J27: Copper | K27: 740 | L27: 88.8 | M27: 65712 | P27: 0 | T27: 0 | V27: Type C PVC (HR) | W27: 103.07 | X27: 52 | Y27: 5359.64 | Z27: POLY TAPE | AA27: 119.6 | AB27: 3 | AC27: 358.8 | AD27: PVC Type ST-2 | AE27: 60.05 | AF27: 27 | AG27: 1621.35 | AH27: Galvanised Steel Round Wire | AI27: 83.9 | AJ27: 289 | AK27: 24247.1 | AL27: FRLSH PVC Type ST-2 | AM27: 92 | AN27: 104 | AO27: 9568 | AR27: 0 | AV27: 0 | AZ27: 0 | BD27: 0 | BH27: 0 | BL27: 19 | BP27: 0 | BT27: 0 | BX27: 0 | BZ27: 4610.79 | CA27: 111477.68 | CH27: 111477.68 | CM27: 111477.68 | CO27: 111477.68 | CP27: 0.18 | CQ27: 20065.98 | CR27: 131543.66 | CS27: 167.188 | CT27: KMS | CU27: 21992522 | CV27: MD0100005 | CW27: DRUM - 36 X 14 X 23 X 2 | CX27: 500
A28: ENQ-12232-22-23 | B28: 45334 | C28: FA0900111 | D28: 4 CORE X 25 SQ. MM. ALU/ARD - WIRE (XLPE) | E28: WOOD | J28: Alumimium | K28: 216 | L28: 270.3 | M28: 58384.8 | P28: 0 | T28: 0 | V28: LT-XLPE | W28: 107 | X28: 95 | Y28: 10165 | AB28: 0 | AD28: PVC Type ST-2 | AE28: 60.05 | AF28: 46 | AG28: 2762.3 | AH28: Galvanised Steel Round Wire | AI28: 83.9 | AJ28: 572 | AK28: 47990.8 | AL28: FRLSH PVC Type ST-2 | AM28: 92 | AN28: 185 | AO28: 17020 | AR28: 0 | AV28: 0 | AZ28: 0 | BD28: 0 | BH28: 0 | BL28: 0 | BP28: 0 | BT28: 0 | BX28: 0 | BZ28: 3505.61 | CA28: 139828.51 | CH28: 139828.51 | CM28: 139828.51 | CO28: 139828.51 | CP28: 0.18 | CQ28: 25169.13 | CR28: 164997.64 | CS28: 172.516 | CT28: KMS | CU28: 28464733 | CV28: MD0100090 | CW28: DRUM - 43 X 15 X 36 X 2.5 | CX28: 1000
A29: ENQ-12232-22-23 | B29: 45334 | C29: FA0900112 | D29: 4 CORE X 10 SQ. MM. AL/ARD - WIRE (XLPE) | E29: WOOD | J29: Alumimium | K29: 216 | L29: 108.12 | M29: 23353.92 | P29: 0 | T29: 0 | V29: LT-XLPE | W29: 107 | X29: 64 | Y29: 6848 | AB29: 0 | AD29: PVC Type ST-2 | AE29: 60.05 | AF29: 35 | AG29: 2101.75 | AH29: Galvanised Steel Round Wire | AI29: 83.9 | AJ29: 441 | AK29: 36999.9 | AL29: FRLSH PVC Type ST-2 | AM29: 92 | AN29: 151 | AO29: 13892 | AR29: 0 | AV29: 0 | AZ29: 0 | BD29: 0 | BH29: 0 | BL29: 0 | BP29: 0 | BT29: 0 | BX29: 0 | BZ29: 4155.88 | CA29: 87351.45 | CH29: 87351.45 | CM29: 87351.45 | CO29: 87351.45 | CP29: 0.18 | CQ29: 15723.26 | CR29: 103074.71 | CS29: 223.526 | CT29: KMS | CU29: 23039878 | CV29: MD0100064 | CW29: DRUM - 42 X 15 X 32 X 2 | CX29: 1000
A30: ENQ-12232-22-23 | B30: 45334 | C30: FA1100094 | D30: 4 CORE X 95 SQ. MM. ALU/ARD - WIRE (XLPE) | E30: WOOD | J30: Alumimium | K30: 216 | L30: 1027.14 | M30: 221862.24 | P30: 0 | T30: 0 | V30: LT-XLPE | W30: 107 | X30: 187 | Y30: 20009 | AB30: 0 | AD30: PVC Type ST-2 | AE30: 60.05 | AF30: 93 | AG30: 5584.65 | AH30: Galvanised Steel Round Wire | AI30: 83.9 | AJ30: 1200 | AK30: 100680 | AL30: FRLSH PVC Type ST-2 | AM30: 92 | AN30: 370 | AO30: 34040 | AR30: 0 | AV30: 0 | AZ30: 0 | BD30: 0 | BH30: 0 | BL30: 0 | BP30: 0 | BR30: RUBBERIZED COTTON TAPE | BS30: 445 | BT30: 0 | BU30: 0 | BX30: 0 | BZ30: 13713.74 | CA30: 395889.63 | CH30: 395889.63 | CM30: 395889.63 | CO30: 395889.63 | CP30: 0.18 | CQ30: 71260.13 | CR30: 467149.76 | CS30: 249.27 | CT30: KMS | CU30: 116446422 | CV30: MD0100061 | CW30: DRUM - 56 X 24 X 32 X 3 | CX30: 500
A31: ENQ-12232-22-23 | B31: 45334 | C31: FA0900020 | D31: 2 CORE X 6 SQ. MM. AL/ARD - WIRE (XLPE) | E31: WOOD | J31: Alumimium | K31: 216 | L31: 33.1 | M31: 7149.6 | P31: 0 | T31: 0 | V31: LT-XLPE | W31: 107 | X31: 26 | Y31: 2782 | AB31: 0 | AD31: PVC Type ST-2-PRESSURE EXTRUDED | AE31: 88 | AF31: 57 | AG31: 5016 | AH31: Galvanised Steel Round Wire | AI31: 83.9 | AJ31: 302 | AK31: 25337.8 | AL31: FRLSH PVC Type ST-2 | AM31: 92 | AN31: 108 | AO31: 9936 | AR31: 0 | AV31: 0 | AZ31: 0 | BD31: 0 | BH31: 0 | BL31: 0 | BP31: 0 | BR31: RUBBERIZED COTTON TAPE | BS31: 445 | BT31: 0 | BU31: 0 | BX31: 0 | BZ31: 2575.74 | CA31: 52797.14 | CH31: 52797.14 | CM31: 52797.14 | CO31: 52797.14 | CP31: 0.18 | CQ31: 9503.49 | CR31: 62300.63 | CS31: 900 | CT31: KMS | CU31: 56070563 | CV31: MD0100066 | CW31: DRUM - 40 X 15 X 23 X 2 | CX31: 1000
A32: ENQ-12232-22-23 | B32: 45334 | C32: FA0900041 | D32: 2 CORE X 4 SQ. MM. AL/ARD - WIRE (XLPE) | E32: WOOD | J32: Alumimium | K32: 216 | L32: 21.6 | M32: 4665.6 | P32: 0 | T32: 0 | V32: LT-XLPE | W32: 107 | X32: 23 | Y32: 2461 | AB32: 0 | AD32: PVC Type ST-2 | AE32: 60.05 | AF32: 47 | AG32: 2822.35 | AH32: Galvanised Steel Round Wire | AI32: 83.9 | AJ32: 250 | AK32: 20975 | AL32: FRLSH PVC Type ST-2 | AM32: 92 | AN32: 92 | AO32: 8464 | AR32: 0 | AV32: 0 | AZ32: 0 | BD32: 0 | BH32: 0 | BL32: 0 | BP32: 0 | BT32: 0 | BX32: 0 | BZ32: 2575.74 | CA32: 41963.69 | CH32: 41963.69 | CM32: 41963.69 | CO32: 41963.69 | CP32: 0.18 | CQ32: 7553.46 | CR32: 49517.15 | CS32: 3493.688 | CT32: KMS | CU32: 172997487 | CV32: MD0100066 | CW32: DRUM - 40 X 15 X 23 X 2 | CX32: 1000

Sheet AUTO CALCULATION SHEET (2)
A2: Tata Power Odisha DISCOMs
A4: TENDER SPECIFICATION NO () | B4: TPCODL / CCG / 23-24 / 1000000538
A5: TENDER DESCRIPTION () | B5: One Year Rate Contract for Supply of 1.1 kV Power and Control Cables at TPNODL, TPCODL & TPSODL.
A6: Last Date & Time of Submission () | B6: 20/Feb/2024 [17:00 Hrs.]
A7: REVERSE AUCTION | B7: Bidders shall be allowed to participate in Reverse auction as per following criteria hence bidders are advised to quote their most competitive rates while submitting the bids to avoid disqualification from participation in Reverse Auction. Reverse Auction shall be as per the below approach: No of bidders allowed to participate in RA process shall be: Total No of bidders on whom tender would be split PLUS 2 more bidders.
A8: Price () | B8: Price shall be fixed and firm during the contractual period.
A9: Validity () | B9: Bids shall remain valid for 180 days from the due date of submission of the bid. Notwithstanding clause above, CCG may solicit the Bidder’s consent to an extension of the Period of Bid Validity. The request and responses thereto shall be made in writing.
A10: Delivery Period () | B10: Delivery Period shall be 60 + 7 days (considering the approval of CAT-A / drawing / GTP) from date of receipt of release order for the first lot however for remaining lots the delivery period will be 60 days from RO date.
A11: Payment Terms () | B11: Payment Terms: On delivery of the materials in good condition and certification of acceptance by certified official, Associate shall submit the Bills/ Invoices in original in the name of respective Odisha discom to Invoice Desk. The payment shall be released within 30 days from the date of submission of error free certified bills/ invoices. Any change in statutory taxes, duties and levies during the contract period shall be borne by respective Odisha DISCOMs. However, in case of delay in work execution owing to reasons not attributable to Odisha Disom, any increase in total liability shall be passed on the Bidder, whereas any benefits arising owing to such statutory variation in taxes and duties shall be passed on TP Discom.
A12: Standard length () | B12: Cable length on one drum shall be: (a) 4 Core Cable – 95 sq.mm. to 300 sq.mm. – 500 meters with + 5% tolerance (b) 4 Core Cable – 16 sq.mm. to 50 sq.mm. – 1000 meters with + 5% tolerance (c) 2 Core & 1 Core Cables – 1000 meters with + 5% tolerance (as per PO terms and conditions)
A13: Packing () | B13: Wooden drums shall be free from sharp edges and visual defects.
A14: Technical Specification
N16: =Sheet1!J1 -> Conductor | S16: AL ALLOY | U16: Insulation Screening (Metallic) | AC16: Insulation Screening (Non-Metallic) | AE16: Insulation | AK16: POLY TAPE | AL16: Inner Sheath | AS16: Armouring | BC16: Outer Sheath | BF16: UV resistance RS-5/kg | BM16: FILLER | BN16: GREASE | BO16: Water swellable Tape | BP16: Semi conducting Water Swellable tape | BQ16: SEMICON TAPE | BR16: GLASS FIBER TAPE | BS16: COPPER WIRE 0.8 MM | BT16: RUBBERIZED COTTON TAPE | BU16: Water Tight Compound | BZ16: DRUM COST PER KM | CA16: TOTAL RM COST | CB16: EXTRA CONSUMPTION | CC16: EXTRA CONSUMPTION VALUE
A17: DOCKET NO. | B17: =Sheet1!B1 -> Base Date | C17: ITEM CODE | D17: PROPOSE ERP ITEM NAME | E17: EX-WORKS (PER KM) | F17: FREIGHT PER KM | G17: PRICE INCLUDING FREIGHT (PER KM) | H17: GST % | I17: GST VALUE | J17: PRICE INCLUDING GST & FREIGHT (PER KM) | K17: QTY | L17: Unit | M17: TOTAL PRICE OF FULL QTY (INCLUDING FRIGHT & GST) | N17: Alumimium | O17: Alumimium ALLOY | P17: Copper | Q17: Flexible Copper | R17: Galvanized steel wire | S17: Alumimium | T17: Alumimium ALLOY | U17: Coper tape - 0.1 mm | V17: Copper Tape - 0.03 mm | W17: Copper Tape - 0.035 mm | X17: Copper Tape - 0.04 mm | Y17: Copper Tape - 0.045 mm | Z17: Copper Tape - 0.050 mm | AA17: Copper Tape - 0.060 mm | AB17: Copper Tape - 0.075 mm(DOUBLE) | AC17: Extruded semiconductive | AD17: Extruded Semiconductive(Stripable) | AE17: HT-XLPE | AF17: LT-XLPE | AG17: TR XLPE | AH17: Type A PVC-1.45 | AI17: Type C PVC (HR) | AJ17: XLPE | AK17: POLY TAPE | AL17: FR PVC Type ST-1 | AM17: FR PVC Type ST-2 | AN17: FRLSH PVC Type ST-2 | AO17: PVC Type ST-1 | AP17: PVC Type ST-1-PRESSURE EXTRUDED | AQ17: PVC Type ST-2 | AR17: PVC Type ST-2-PRESSURE EXTRUDED | AS17: ACSR CORE WIRE | AT17: ACSR DOG STEEL WIRE | AU17: Aluminium Flat Strip | AV17: Aluminium Round Wire | AW17: Double Steel Tape | AX17: Galvanised Steel Flat Strip | AY17: Galvanised Steel Flat Strip (Double) | AZ17: Galvanised Steel Flat Strip-B | BA17: Galvanised Steel Round Wire | BB17: Galvanised Steel Round Wire (Double) | BC17: FR PVC Type ST-1 | BD17: FR PVC Type ST-2 | BE17: FRLSH PVC Type ST-1 | BF17: FRLSH PVC Type ST-2 | BG17: PE, ST-3 | BH17: PE, ST-7 | BI17: PVC Type ST-1 | BJ17: PVC Type ST-2 | BK17: PVC Type ST-2-PRESSURE EXTRUDED | BL17: UV & Track Resistant XLPE | BM17: FILLER | BN17: NCWBT | BO17: Water swellable Tape | BP17: Semi conducting Water Swellable tape | BQ17: SEMICON TAPE | BR17: GLASS FIBER TAPE | BS17: COPPER WIRE 0.8 MM | BT17: RUBBERIZED COTTON TAPE | BU17: Water Tight Compound | BV17: =Sheet1!E1 -> PROPOSE DRUM TYPE | BW17: =Sheet1!CV1 -> DRUM CODE | BX17: =Sheet1!CW1 -> DRUM SIZE (FxbXtx Ft) | BY17: =Sheet1!CX1 -> PARTY STANDARD LENGTH (MTR) | CD17: MFG% | CE17: MFG VALUE | CF17: PROF% | CG17: PROFIT VALUE | CH17: 1ST EX-WORKS | CI17: Intt % | CJ17: INTT VALUE | CK17: insp% | CL17: INSP VALUE
N18: 228 | O18: =+IFERROR(VLOOKUP($O$17,Sheet1!J:L,2,0),0) -> 0 | P18: 782 | Q18: =+IFERROR(VLOOKUP($Q$17,Sheet1!J:M,2,0),0) -> 0 | R18: =+IFERROR(VLOOKUP($R$17,Sheet1!J:M,2,0),0) -> 0 | S18: =+IFERROR(VLOOKUP($S$17,Sheet1!N:Q,2,0),0) -> 0 | T18: =+IFERROR(VLOOKUP($T$17,Sheet1!N:O,2,0),0) -> 0 | U18: =+IFERROR(VLOOKUP($U$17,Sheet1!F:I,2,0),0) -> 0 | V18: =+IFERROR(VLOOKUP($V$17,Sheet1!F:I,2,0),0) -> 0 | W18: =+IFERROR(VLOOKUP($W$17,Sheet1!F:I,2,0),0) -> 0 | X18: =+IFERROR(VLOOKUP($X$17,Sheet1!F:I,2,0),0) -> 0 | Y18: =+IFERROR(VLOOKUP($Y$17,Sheet1!F:I,2,0),0) -> 0 | Z18: =+IFERROR(VLOOKUP($Z$17,Sheet1!F:I,2,0),0) -> 0 | AA18: =+IFERROR(VLOOKUP($AA$17,Sheet1!F:I,2,0),0) -> 0 | AB18: =+IFERROR(VLOOKUP($AB$17,Sheet1!F:I,2,0),0) -> 0 | AC18: =+IFERROR(VLOOKUP($AC$17,Sheet1!R:U,2,0),0) -> 0 | AD18: =+IFERROR(VLOOKUP($AD$17,Sheet1!R:U,2,0),0) -> 0 | AE18: =+IFERROR(VLOOKUP($AE$17,Sheet1!V:Y,2,0),0) -> 0 | AF18: 100 | AG18: =+IFERROR(VLOOKUP($AG$17,Sheet1!V:Y,2,0),0) -> 0 | AH18: 75 | AI18: 105 | AJ18: =+IFERROR(VLOOKUP($AJ$17,Sheet1!V:Y,2,0),0) -> 0 | AK18: 114 | AL18: =+IFERROR(VLOOKUP($AL$17,Sheet1!AD2:AG840,2,0),0) -> 0 | AM18: =+IFERROR(VLOOKUP($AM$17,Sheet1!AD2:AG840,2,0),0) -> 0 | AN18: =+IFERROR(VLOOKUP($AN$17,Sheet1!AD2:AG840,2,0),0) -> 0 | AO18: 59 | AP18: =+IFERROR(VLOOKUP($AP$17,Sheet1!AD2:AG840,2,0),0) -> 0 | AQ18: 61 | AR18: 89 | AS18: =+IFERROR(VLOOKUP($AS$17,Sheet1!AH2:AK840,2,0),0) -> 0 | AT18: =+IFERROR(VLOOKUP($AT$17,Sheet1!AH2:AK840,2,0),0) -> 0 | AU18: =+IFERROR(VLOOKUP($AU$17,Sheet1!AH2:AK840,2,0),0) -> 0 | AV18: 233 | AW18: =+IFERROR(VLOOKUP($AW$17,Sheet1!AH2:AK840,2,0),0) -> 0 | AX18: =+IFERROR(VLOOKUP($AX$17,Sheet1!AH2:AK840,2,0),0) -> 0 | AY18: =+IFERROR(VLOOKUP($AY$17,Sheet1!AH2:AK840,2,0),0) -> 0 | AZ18: =+IFERROR(VLOOKUP($AZ$17,Sheet1!AH2:AK840,2,0),0) -> 0 | BA18: 82 | BB18: =+IFERROR(VLOOKUP($BB$17,Sheet1!AH2:AK840,2,0),0) -> 0 | BC18: =+IFERROR(VLOOKUP($BC$17,Sheet1!AL2:AO840,2,0),0) -> 0 | BD18: =+IFERROR(VLOOKUP($BD$17,Sheet1!AL2:AO840,2,0),0) -> 0 | BE18: =+IFERROR(VLOOKUP($BE$17,Sheet1!AL2:AO840,2,0),0) -> 0 | BF18: 105 | BG18: =+IFERROR(VLOOKUP($BG$17,Sheet1!AL2:AO840,2,0),0) -> 0 | BH18: =+IFERROR(VLOOKUP($BH$17,Sheet1!AL2:AO840,2,0),0) -> 0 | BI18: 59 | BJ18: =+IFERROR(VLOOKUP($BJ$17,Sheet1!AL2:AO840,2,0),0) -> 0 | BK18: =+IFERROR(VLOOKUP($BK$17,Sheet1!AL2:AO840,2,0),0) -> 0 | BL18: =+IFERROR(VLOOKUP($BL$17,Sheet1!AL2:AO840,2,0),0) -> 0 | BM18: =+IFERROR(VLOOKUP($BM$17,Sheet1!AP2:AS840,2,0),0) -> 0 | BN18: 340 | BP18: =+IFERROR(VLOOKUP($BP$17,Sheet1!BB2:BE840,2,0),0) -> 0 | BQ18: =+IFERROR(VLOOKUP($BQ$17,Sheet1!BF2:BI840,2,0),0) -> 0 | BR18: =+IFERROR(VLOOKUP($BR$17,Sheet1!BJ2:BM840,2,0),0) -> 0 | BS18: =+IFERROR(VLOOKUP($BS$17,Sheet1!BN2:BQ840,2,0),0) -> 0 | BT18: 450 | BU18: =+IFERROR(VLOOKUP($BU$17,Sheet1!BV2:BY840,2,0),0) -> 0
A19: =Sheet1!A23 -> ENQ-12232-22-23 | B19: 45380 | C19: =Sheet1!C23 -> FA0600013 | D19: =Sheet1!D23 -> 1 CORE X 95 SQ. MM. AL/UNARD(XLPE ) | E19: =CH19+CJ19+CL19 -> 97423.717 | F19: =ROUNDUP(M52,0) -> 986 | G19: =E19+F19 -> 98409.717 | H19: =Sheet1!CP23 -> 0.18 | I19: =G19*H19 -> 17713.749 | J19: =G19+I19 -> 116123.47 | K19: =Sheet1!CS23 -> 82.208 | L19: =Sheet1!CT23 -> KMS | M19: =J19*K19 -> 9546277.9 | N19: =+IFERROR(VLOOKUP($N$17,Sheet1!J23:L23,3,0),0) -> 256.5 | O19: =+IFERROR(VLOOKUP($O$17,Sheet1!J23:L23,3,0),0) -> 0 | P19: =+IFERROR(VLOOKUP($P$17,Sheet1!J23:M23,3,0),0) -> 0 | Q19: =+IFERROR(VLOOKUP($Q$17,Sheet1!J23:M23,3,0),0) -> 0 | R19: =+IFERROR(VLOOKUP($R$17,Sheet1!J23:M23,3,0),0) -> 0 | S19: =+IFERROR(VLOOKUP($S$17,Sheet1!N23:Q23,3,0),0) -> 0 | T19: =+IFERROR(VLOOKUP($T$17,Sheet1!N23:Q23,3,0),0) -> 0 | U19: =+IFERROR(VLOOKUP($U$17,Sheet1!F23:I23,3,0),0) -> 0 | V19: =+IFERROR(VLOOKUP($V$17,Sheet1!F23:I23,3,0),0) -> 0 | W19: =+IFERROR(VLOOKUP($W$17,Sheet1!F23:I23,3,0),0) -> 0 | X19: =+IFERROR(VLOOKUP($X$17,Sheet1!F23:I23,3,0),0) -> 0 | Y19: =+IFERROR(VLOOKUP($Y$17,Sheet1!F23:I23,3,0),0) -> 0 | Z19: =+IFERROR(VLOOKUP($Z$17,Sheet1!F23:I23,3,0),0) -> 0 | AA19: =+IFERROR(VLOOKUP($AA$17,Sheet1!F23:I23,3,0),0) -> 0 | AB19: =+IFERROR(VLOOKUP($AB$17,Sheet1!F23:I23,3,0),0) -> 0 | AC19: =+IFERROR(VLOOKUP($AC$17,Sheet1!R23:U23,3,0),0) -> 0 | AD19: =+IFERROR(VLOOKUP($AD$17,Sheet1!R23:U23,2,0),0) -> 0 | AE19: =+IFERROR(VLOOKUP($AE$17,Sheet1!V23:Y23,3,0),0) -> 0 | AF19: 44 | AG19: =+IFERROR(VLOOKUP($AG$17,Sheet1!V23:Y23,3,0),0) -> 0 | AH19: =+IFERROR(VLOOKUP($AH$17,Sheet1!V23:Y23,3,0),0) -> 0 | AI19: =+IFERROR(VLOOKUP($AI$17,Sheet1!V23:Y23,3,0),0) -> 0 | AJ19: =+IFERROR(VLOOKUP($AJ$17,Sheet1!V23:Y23,3,0),0) -> 0 | AK19: =+IFERROR(VLOOKUP($AK$17,Sheet1!Z23:AB23,3,0),0) -> 0 | AL19: =+IFERROR(VLOOKUP($AL$17,Sheet1!AD23:AG23,3,0),0) -> 0 | AM19: =+IFERROR(VLOOKUP($AM$17,Sheet1!AD23:AG23,3,0),0) -> 0 | AN19: =+IFERROR(VLOOKUP($AN$17,Sheet1!AD23:AG23,3,0),0) -> 0 | AO19: =+IFERROR(VLOOKUP($AO$17,Sheet1!AD23:AG23,3,0),0) -> 0 | AP19: =+IFERROR(VLOOKUP($AP$17,Sheet1!AD23:AG23,3,0),0) -> 0 | AQ19: =+IFERROR(VLOOKUP($AQ$17,Sheet1!AD23:AG23,3,0),0) -> 0 | AR19: =+IFERROR(VLOOKUP($AR$17,Sheet1!AD23:AG23,3,0),0) -> 0 | AS19: =+IFERROR(VLOOKUP($AS$17,Sheet1!AH23:AK23,3,0),0) -> 0 | AT19: =+IFERROR(VLOOKUP($AT$17,Sheet1!AH23:AK23,3,0),0) -> 0 | AU19: =+IFERROR(VLOOKUP($AU$17,Sheet1!AH23:AK23,3,0),0) -> 0 | AV19: =+IFERROR(VLOOKUP($AV$17,Sheet1!AH23:AK23,3,0),0) -> 0 | AW19: =+IFERROR(VLOOKUP($AW$17,Sheet1!AH23:AK23,3,0),0) -> 0 | AX19: =+IFERROR(VLOOKUP($AX$17,Sheet1!AH23:AK23,3,0),0) -> 0 | AY19: =+IFERROR(VLOOKUP($AY$17,Sheet1!AH23:AK23,3,0),0) -> 0 | AZ19: =+IFERROR(VLOOKUP($AZ$17,Sheet1!AH23:AK23,3,0),0) -> 0 | BA19: =+IFERROR(VLOOKUP($BA$17,Sheet1!AH23:AK23,3,0),0) -> 0 | BB19: =+IFERROR(VLOOKUP($BB$17,Sheet1!AH23:AK23,3,0),0) -> 0 | BC19: =+IFERROR(VLOOKUP($BC$17,Sheet1!AL23:AO23,3,0),0) -> 0 | BD19: =+IFERROR(VLOOKUP($BD$17,Sheet1!AL23:AO23,3,0),0) -> 0 | BE19: =+IFERROR(VLOOKUP($BE$17,Sheet1!AL23:AO23,3,0),0) -> 0 | BF19: 140 | BG19: =+IFERROR(VLOOKUP($BG$17,Sheet1!AL23:AO23,3,0),0) -> 0 | BH19: =+IFERROR(VLOOKUP($BH$17,Sheet1!AL23:AO23,3,0),0) -> 0 | BI19: =+IFERROR(VLOOKUP($BI$17,Sheet1!AL23:AO23,3,0),0) -> 0 | BJ19: =+IFERROR(VLOOKUP($BJ$17,Sheet1!AL23:AO23,3,0),0) -> 0 | BK19: =+IFERROR(VLOOKUP($BK$17,Sheet1!AL23:AO23,3,0),0) -> 0 | BL19: =+IFERROR(VLOOKUP($BL$17,Sheet1!AL23:AO23,3,0),0) -> 0 | BM19: =+IFERROR(VLOOKUP($BM$17,Sheet1!AP23:AS23,3,0),0) -> 0 | BN19: =+IFERROR(VLOOKUP($BN$17,Sheet1!AT23:AW23,3,0),0) -> 0 | BO19: =+IFERROR(VLOOKUP($BO$17,Sheet1!AX23:BA23,3,0),0) -> 0 | BP19: =+IFERROR(VLOOKUP($BP$17,Sheet1!BB23:BE23,3,0),0) -> 0 | BQ19: =+IFERROR(VLOOKUP($BQ$17,Sheet1!BF23:BI23,3,0),0) -> 0 | BR19: =+IFERROR(VLOOKUP($BR$17,Sheet1!BJ23:BM23,3,0),0) -> 0 | BS19: =+IFERROR(VLOOKUP($BS$17,Sheet1!BN23:BQ23,3,0),0) -> 0 | BT19: =+IFERROR(VLOOKUP($BT$17,Sheet1!BR23:BU23,3,0),0) -> 0 | BU19: =+IFERROR(VLOOKUP($BU$17,Sheet1!BV23:BY23,3,0),0) -> 0 | BV19: =Sheet1!E23 -> WOOD | BW19: =Sheet1!CV23 -> MD0100066 | BX19: =Sheet1!CW23 -> DRUM - 40 X 15 X 23 X 2 | BY19: =Sheet1!CX23 -> 1000 | BZ19: =Sheet1!BZ23 -> 2575.74 | CA19: =SUMPRODUCT($N$18:$BU$18,N19:BU19)+BZ19 -> 80157.74 | CB19: =Sheet1!CB23 -> 0 | CC19: =CA19*CB19 -> 0 | CD19: 0.18 | CE19: =CA19*CD19 -> 14428.393 | CF19: 0 | CG19: =CA19*CF19 -> 0 | CH19: =CA19+CC19+CE19+CG19 -> 94586.133 | CI19: 0.02 | CJ19: =CH19*CI19 -> 1891.7227 | CK19: 0.01 | CL19: =CH19*CK19 -> 945.86133 | CM19: 55 | CN19: 20
A20: =Sheet1!A19 -> ENQ-12232-22-23 | B20: 45380 | C20: =Sheet1!C19 -> FA0600019 | D20: =Sheet1!D19 -> 1 CORE X 150 SQ. MM. AL/UNARD. (XLPE) | E20: =CH20+CJ20+CL20 -> 155611.16 | F20: =ROUNDUP(M53,0) -> 1694 | G20: =E20+F20 -> 157305.16 | H20: =Sheet1!CP19 -> 0.18 | I20: =G20*H20 -> 28314.929 | J20: =G20+I20 -> 185620.09 | K20: =Sheet1!CS19 -> 47.838 | L20: =Sheet1!CT19 -> KMS | M20: =J20*K20 -> 8879693.9 | N20: =+IFERROR(VLOOKUP($N$17,Sheet1!J19:L19,3,0),0) -> 405 | O20: =+IFERROR(VLOOKUP($O$17,Sheet1!J19:L19,3,0),0) -> 0 | P20: =+IFERROR(VLOOKUP($P$17,Sheet1!J19:M19,3,0),0) -> 0 | Q20: =+IFERROR(VLOOKUP($Q$17,Sheet1!J19:M19,3,0),0) -> 0 | R20: =+IFERROR(VLOOKUP($R$17,Sheet1!J19:M19,3,0),0) -> 0 | S20: =+IFERROR(VLOOKUP($S$17,Sheet1!N19:Q19,3,0),0) -> 0 | T20: =+IFERROR(VLOOKUP($T$17,Sheet1!N19:Q19,3,0),0) -> 0 | U20: =+IFERROR(VLOOKUP($U$17,Sheet1!F19:I19,3,0),0) -> 0 | V20: =+IFERROR(VLOOKUP($V$17,Sheet1!F19:I19,3,0),0) -> 0 | W20: =+IFERROR(VLOOKUP($W$17,Sheet1!F19:I19,3,0),0) -> 0 | X20: =+IFERROR(VLOOKUP($X$17,Sheet1!F19:I19,3,0),0) -> 0 | Y20: =+IFERROR(VLOOKUP($Y$17,Sheet1!F19:I19,3,0),0) -> 0 | Z20: =+IFERROR(VLOOKUP($Z$17,Sheet1!F19:I19,3,0),0) -> 0 | AA20: =+IFERROR(VLOOKUP($AA$17,Sheet1!F19:I19,3,0),0) -> 0 | AB20: =+IFERROR(VLOOKUP($AB$17,Sheet1!F19:I19,3,0),0) -> 0 | AC20: =+IFERROR(VLOOKUP($AC$17,Sheet1!R19:U19,3,0),0) -> 0 | AD20: =+IFERROR(VLOOKUP($AD$17,Sheet1!R19:U19,2,0),0) -> 0 | AE20: =+IFERROR(VLOOKUP($AE$17,Sheet1!V19:Y19,3,0),0) -> 0 | AF20: =+IFERROR(VLOOKUP($AF$17,Sheet1!V19:Y19,3,0),0) -> 72 | AG20: =+IFERROR(VLOOKUP($AG$17,Sheet1!V19:Y19,3,0),0) -> 0 | AH20: =+IFERROR(VLOOKUP($AH$17,Sheet1!V19:Y19,3,0),0) -> 0 | AI20: =+IFERROR(VLOOKUP($AI$17,Sheet1!V19:Y19,3,0),0) -> 0 | AJ20: =+IFERROR(VLOOKUP($AJ$17,Sheet1!V19:Y19,3,0),0) -> 0 | AK20: =+IFERROR(VLOOKUP($AK$17,Sheet1!Z19:AB19,3,0),0) -> 0 | AL20: =+IFERROR(VLOOKUP($AL$17,Sheet1!AD19:AG19,3,0),0) -> 0 | AM20: =+IFERROR(VLOOKUP($AM$17,Sheet1!AD19:AG19,3,0),0) -> 0 | AN20: =+IFERROR(VLOOKUP($AN$17,Sheet1!AD19:AG19,3,0),0) -> 0 | AO20: =+IFERROR(VLOOKUP($AO$17,Sheet1!AD19:AG19,3,0),0) -> 0 | AP20: =+IFERROR(VLOOKUP($AP$17,Sheet1!AD19:AG19,3,0),0) -> 0 | AQ20: =+IFERROR(VLOOKUP($AQ$17,Sheet1!AD19:AG19,3,0),0) -> 0 | AR20: =+IFERROR(VLOOKUP($AR$17,Sheet1!AD19:AG19,3,0),0) -> 0 | AS20: =+IFERROR(VLOOKUP($AS$17,Sheet1!AH19:AK19,3,0),0) -> 0 | AT20: =+IFERROR(VLOOKUP($AT$17,Sheet1!AH19:AK19,3,0),0) -> 0 | AU20: =+IFERROR(VLOOKUP($AU$17,Sheet1!AH19:AK19,3,0),0) -> 0 | AV20: =+IFERROR(VLOOKUP($AV$17,Sheet1!AH19:AK19,3,0),0) -> 0 | AW20: =+IFERROR(VLOOKUP($AW$17,Sheet1!AH19:AK19,3,0),0) -> 0 | AX20: =+IFERROR(VLOOKUP($AX$17,Sheet1!AH19:AK19,3,0),0) -> 0 | AY20: =+IFERROR(VLOOKUP($AY$17,Sheet1!AH19:AK19,3,0),0) -> 0 | AZ20: =+IFERROR(VLOOKUP($AZ$17,Sheet1!AH19:AK19,3,0),0) -> 0 | BA20: =+IFERROR(VLOOKUP($BA$17,Sheet1!AH19:AK19,3,0),0) -> 0 | BB20: =+IFERROR(VLOOKUP($BB$17,Sheet1!AH19:AK19,3,0),0) -> 0 | BC20: =+IFERROR(VLOOKUP($BC$17,Sheet1!AL19:AO19,3,0),0) -> 0 | BD20: =+IFERROR(VLOOKUP($BD$17,Sheet1!AL19:AO19,3,0),0) -> 0 | BE20: =+IFERROR(VLOOKUP($BE$17,Sheet1!AL19:AO19,3,0),0) -> 0 | BF20: 195 | BG20: =+IFERROR(VLOOKUP($BG$17,Sheet1!AL19:AO19,3,0),0) -> 0 | BH20: =+IFERROR(VLOOKUP($BH$17,Sheet1!AL19:AO19,3,0),0) -> 0 | BI20: =+IFERROR(VLOOKUP($BI$17,Sheet1!AL19:AO19,3,0),0) -> 0 | BJ20: =+IFERROR(VLOOKUP($BJ$17,Sheet1!AL19:AO19,3,0),0) -> 0 | BK20: =+IFERROR(VLOOKUP($BK$17,Sheet1!AL19:AO19,3,0),0) -> 0 | BL20: =+IFERROR(VLOOKUP($BL$17,Sheet1!AL19:AO19,3,0),0) -> 0 | BM20: =+IFERROR(VLOOKUP($BM$17,Sheet1!AP19:AS19,3,0),0) -> 0 | BN20: 14 | BO20: =+IFERROR(VLOOKUP($BO$17,Sheet1!AX19:BA19,3,0),0) -> 0 | BP20: =+IFERROR(VLOOKUP($BP$17,Sheet1!BB19:BE19,3,0),0) -> 0 | BQ20: =+IFERROR(VLOOKUP($BQ$17,Sheet1!BF19:BI19,3,0),0) -> 0 | BR20: =+IFERROR(VLOOKUP($BR$17,Sheet1!BJ19:BM19,3,0),0) -> 0 | BS20: =+IFERROR(VLOOKUP($BS$17,Sheet1!BN19:BQ19,3,0),0) -> 0 | BT20: =+IFERROR(VLOOKUP($BT$17,Sheet1!BR19:BU19,3,0),0) -> 0 | BU20: =+IFERROR(VLOOKUP($BU$17,Sheet1!BV19:BY19,3,0),0) -> 0 | BV20: =Sheet1!E19 -> WOOD | BW20: =Sheet1!CV19 -> MD0100085 | BX20: =Sheet1!CW19 -> DRUM - 43 X 15 X 28 X 2.25 | BY20: =Sheet1!CX19 -> 1000 | BZ20: =Sheet1!BZ19 -> 3257.88 | CA20: =SUMPRODUCT($N$18:$BU$18,N20:BU20)+BZ20 -> 128032.88 | CB20: =Sheet1!CB19 -> 0 | CC20: =CA20*CB20 -> 0 | CD20: 0.18 | CE20: =CA20*CD20 -> 23045.918 | CF20: 0 | CG20: =CA20*CF20 -> 0 | CH20: =CA20+CC20+CE20+CG20 -> 151078.8 | CI20: 0.02 | CJ20: =CH20*CI20 -> 3021.576 | CK20: 0.01 | CL20: =CH20*CK20 -> 1510.788 | CM20: 75 | CN20: 25
A21: =Sheet1!A15 -> ENQ-12232-22-23 | B21: 45380 | C21: =Sheet1!C15 -> FA0600021 | D21: =Sheet1!D15 -> 1 CORE X 185 SQ. MM. AL/UNARD. (XLPE) | E21: =CH21+CJ21+CL21 -> 190411.38 | F21: =ROUNDUP(M54,0) -> 2700 | G21: =E21+F21 -> 193111.38 | H21: =Sheet1!CP15 -> 0.18 | I21: =G21*H21 -> 34760.049 | J21: =G21+I21 -> 227871.43 | K21: =Sheet1!CS15 -> 20 | L21: =Sheet1!CT15 -> KMS | M21: =J21*K21 -> 4557428.6 | N21: 500 | O21: =+IFERROR(VLOOKUP($O$17,Sheet1!J15:L15,3,0),0) -> 0 | P21: =+IFERROR(VLOOKUP($P$17,Sheet1!J15:M15,3,0),0) -> 0 | Q21: =+IFERROR(VLOOKUP($Q$17,Sheet1!J15:M15,3,0),0) -> 0 | R21: =+IFERROR(VLOOKUP($R$17,Sheet1!J15:M15,3,0),0) -> 0 | S21: =+IFERROR(VLOOKUP($S$17,Sheet1!N15:Q15,3,0),0) -> 0 | T21: =+IFERROR(VLOOKUP($T$17,Sheet1!N15:Q15,3,0),0) -> 0 | U21: =+IFERROR(VLOOKUP($U$17,Sheet1!F15:I15,3,0),0) -> 0 | V21: =+IFERROR(VLOOKUP($V$17,Sheet1!F15:I15,3,0),0) -> 0 | W21: =+IFERROR(VLOOKUP($W$17,Sheet1!F15:I15,3,0),0) -> 0 | X21: =+IFERROR(VLOOKUP($X$17,Sheet1!F15:I15,3,0),0) -> 0 | Y21: =+IFERROR(VLOOKUP($Y$17,Sheet1!F15:I15,3,0),0) -> 0 | Z21: =+IFERROR(VLOOKUP($Z$17,Sheet1!F15:I15,3,0),0) -> 0 | AA21: =+IFERROR(VLOOKUP($AA$17,Sheet1!F15:I15,3,0),0) -> 0 | AB21: =+IFERROR(VLOOKUP($AB$17,Sheet1!F15:I15,3,0),0) -> 0 | AC21: =+IFERROR(VLOOKUP($AC$17,Sheet1!R15:U15,3,0),0) -> 0 | AD21: =+IFERROR(VLOOKUP($AD$17,Sheet1!R15:U15,2,0),0) -> 0 | AE21: =+IFERROR(VLOOKUP($AE$17,Sheet1!V15:Y15,3,0),0) -> 0 | AF21: =+IFERROR(VLOOKUP($AF$17,Sheet1!V15:Y15,3,0),0) -> 90 | AG21: =+IFERROR(VLOOKUP($AG$17,Sheet1!V15:Y15,3,0),0) -> 0 | AH21: =+IFERROR(VLOOKUP($AH$17,Sheet1!V15:Y15,3,0),0) -> 0 | AI21: =+IFERROR(VLOOKUP($AI$17,Sheet1!V15:Y15,3,0),0) -> 0 | AJ21: =+IFERROR(VLOOKUP($AJ$17,Sheet1!V15:Y15,3,0),0) -> 0 | AK21: =+IFERROR(VLOOKUP($AK$17,Sheet1!Z15:AB15,3,0),0) -> 0 | AL21: =+IFERROR(VLOOKUP($AL$17,Sheet1!AD15:AG15,3,0),0) -> 0 | AM21: =+IFERROR(VLOOKUP($AM$17,Sheet1!AD15:AG15,3,0),0) -> 0 | AN21: =+IFERROR(VLOOKUP($AN$17,Sheet1!AD15:AG15,3,0),0) -> 0 | AO21: =+IFERROR(VLOOKUP($AO$17,Sheet1!AD15:AG15,3,0),0) -> 0 | AP21: =+IFERROR(VLOOKUP($AP$17,Sheet1!AD15:AG15,3,0),0) -> 0 | AQ21: =+IFERROR(VLOOKUP($AQ$17,Sheet1!AD15:AG15,3,0),0) -> 0 | AR21: =+IFERROR(VLOOKUP($AR$17,Sheet1!AD15:AG15,3,0),0) -> 0 | AS21: =+IFERROR(VLOOKUP($AS$17,Sheet1!AH15:AK15,3,0),0) -> 0 | AT21: =+IFERROR(VLOOKUP($AT$17,Sheet1!AH15:AK15,3,0),0) -> 0 | AU21: =+IFERROR(VLOOKUP($AU$17,Sheet1!AH15:AK15,3,0),0) -> 0 | AV21: =+IFERROR(VLOOKUP($AV$17,Sheet1!AH15:AK15,3,0),0) -> 0 | AW21: =+IFERROR(VLOOKUP($AW$17,Sheet1!AH15:AK15,3,0),0) -> 0 | AX21: =+IFERROR(VLOOKUP($AX$17,Sheet1!AH15:AK15,3,0),0) -> 0 | AY21: =+IFERROR(VLOOKUP($AY$17,Sheet1!AH15:AK15,3,0),0) -> 0 | AZ21: =+IFERROR(VLOOKUP($AZ$17,Sheet1!AH15:AK15,3,0),0) -> 0 | BA21: =+IFERROR(VLOOKUP($BA$17,Sheet1!AH15:AK15,3,0),0) -> 0 | BB21: =+IFERROR(VLOOKUP($BB$17,Sheet1!AH15:AK15,3,0),0) -> 0 | BC21: =+IFERROR(VLOOKUP($BC$17,Sheet1!AL15:AO15,3,0),0) -> 0 | BD21: =+IFERROR(VLOOKUP($BD$17,Sheet1!AL15:AO15,3,0),0) -> 0 | BE21: =+IFERROR(VLOOKUP($BE$17,Sheet1!AL15:AO15,3,0),0) -> 0 | BF21: 216 | BG21: =+IFERROR(VLOOKUP($BG$17,Sheet1!AL15:AO15,3,0),0) -> 0 | BH21: =+IFERROR(VLOOKUP($BH$17,Sheet1!AL15:AO15,3,0),0) -> 0 | BI21: =+IFERROR(VLOOKUP($BI$17,Sheet1!AL15:AO15,3,0),0) -> 0 | BJ21: =+IFERROR(VLOOKUP($BJ$17,Sheet1!AL15:AO15,3,0),0) -> 0 | BK21: =+IFERROR(VLOOKUP($BK$17,Sheet1!AL15:AO15,3,0),0) -> 0 | BL21: =+IFERROR(VLOOKUP($BL$17,Sheet1!AL15:AO15,3,0),0) -> 0 | BM21: =+IFERROR(VLOOKUP($BM$17,Sheet1!AP15:AS15,3,0),0) -> 0 | BN21: 22 | BO21: =+IFERROR(VLOOKUP($BO$17,Sheet1!AX15:BA15,3,0),0) -> 0 | BP21: =+IFERROR(VLOOKUP($BP$17,Sheet1!BB15:BE15,3,0),0) -> 0 | BQ21: =+IFERROR(VLOOKUP($BQ$17,Sheet1!BF15:BI15,3,0),0) -> 0 | BR21: =+IFERROR(VLOOKUP($BR$17,Sheet1!BJ15:BM15,3,0),0) -> 0 | BS21: =+IFERROR(VLOOKUP($BS$17,Sheet1!BN15:BQ15,3,0),0) -> 0 | BT21: =+IFERROR(VLOOKUP($BT$17,Sheet1!BR15:BU15,3,0),0) -> 0 | BU21: =+IFERROR(VLOOKUP($BU$17,Sheet1!BV15:BY15,3,0),0) -> 0 | BV21: =Sheet1!E15 -> WOOD | BW21: =Sheet1!CV15 -> MD0100090 | BX21: =Sheet1!CW15 -> DRUM - 43 X 15 X 36 X 2.5 | BY21: =Sheet1!CX15 -> 1000 | BZ21: =Sheet1!BZ15 -> 3505.61 | CA21: =SUMPRODUCT($N$18:$BU$18,N21:BU21)+BZ21 -> 156665.61 | CB21: =Sheet1!CB15 -> 0 | CC21: =CA21*CB21 -> 0 | CD21: 0.18 | CE21: =CA21*CD21 -> 28199.81 | CF21: 0 | CG21: =CA21*CF21 -> 0 | CH21: =CA21+CC21+CE21+CG21 -> 184865.42 | CI21: 0.02 | CJ21: =CH21*CI21 -> 3697.3084 | CK21: 0.01 | CL21: =CH21*CK21 -> 1848.6542 | CM21: 75 | CN21: 25
A22: =Sheet1!A21 -> ENQ-12232-22-23 | B22: 45380 | C22: =Sheet1!C21 -> FA0600020 | D22: =Sheet1!D21 -> 1 CORE X 300 SQ. MM. AL/UNARD. (XLPE) | E22: =CH22+CJ22+CL22 -> 290640.84 | F22: =ROUNDUP(M55,0) -> 2983 | G22: =E22+F22 -> 293623.84 | H22: =Sheet1!CP21 -> 0.18 | I22: =G22*H22 -> 52852.291 | J22: =G22+I22 -> 346476.13 | K22: =Sheet1!CS21 -> 63.368 | L22: =Sheet1!CT21 -> KMS | M22: =J22*K22 -> 21955499 | N22: =+IFERROR(VLOOKUP($N$17,Sheet1!J21:L21,3,0),0) -> 810 | O22: =+IFERROR(VLOOKUP($O$17,Sheet1!J21:L21,3,0),0) -> 0 | P22: =+IFERROR(VLOOKUP($P$17,Sheet1!J21:M21,3,0),0) -> 0 | Q22: =+IFERROR(VLOOKUP($Q$17,Sheet1!J21:M21,3,0),0) -> 0 | R22: =+IFERROR(VLOOKUP($R$17,Sheet1!J21:M21,3,0),0) -> 0 | S22: =+IFERROR(VLOOKUP($S$17,Sheet1!N21:Q21,3,0),0) -> 0 | T22: =+IFERROR(VLOOKUP($T$17,Sheet1!N21:Q21,3,0),0) -> 0 | U22: =+IFERROR(VLOOKUP($U$17,Sheet1!F21:I21,3,0),0) -> 0 | V22: =+IFERROR(VLOOKUP($V$17,Sheet1!F21:I21,3,0),0) -> 0 | W22: =+IFERROR(VLOOKUP($W$17,Sheet1!F21:I21,3,0),0) -> 0 | X22: =+IFERROR(VLOOKUP($X$17,Sheet1!F21:I21,3,0),0) -> 0 | Y22: =+IFERROR(VLOOKUP($Y$17,Sheet1!F21:I21,3,0),0) -> 0 | Z22: =+IFERROR(VLOOKUP($Z$17,Sheet1!F21:I21,3,0),0) -> 0 | AA22: =+IFERROR(VLOOKUP($AA$17,Sheet1!F21:I21,3,0),0) -> 0 | AB22: =+IFERROR(VLOOKUP($AB$17,Sheet1!F21:I21,3,0),0) -> 0 | AC22: =+IFERROR(VLOOKUP($AC$17,Sheet1!R21:U21,3,0),0) -> 0 | AD22: =+IFERROR(VLOOKUP($AD$17,Sheet1!R21:U21,2,0),0) -> 0 | AE22: =+IFERROR(VLOOKUP($AE$17,Sheet1!V21:Y21,3,0),0) -> 0 | AF22: =+IFERROR(VLOOKUP($AF$17,Sheet1!V21:Y21,3,0),0) -> 132 | AG22: =+IFERROR(VLOOKUP($AG$17,Sheet1!V21:Y21,3,0),0) -> 0 | AH22: =+IFERROR(VLOOKUP($AH$17,Sheet1!V21:Y21,3,0),0) -> 0 | AI22: =+IFERROR(VLOOKUP($AI$17,Sheet1!V21:Y21,3,0),0) -> 0 | AJ22: =+IFERROR(VLOOKUP($AJ$17,Sheet1!V21:Y21,3,0),0) -> 0 | AK22: =+IFERROR(VLOOKUP($AK$17,Sheet1!Z21:AB21,3,0),0) -> 0 | AL22: =+IFERROR(VLOOKUP($AL$17,Sheet1!AD21:AG21,3,0),0) -> 0 | AM22: =+IFERROR(VLOOKUP($AM$17,Sheet1!AD21:AG21,3,0),0) -> 0 | AN22: =+IFERROR(VLOOKUP($AN$17,Sheet1!AD21:AG21,3,0),0) -> 0 | AO22: =+IFERROR(VLOOKUP($AO$17,Sheet1!AD21:AG21,3,0),0) -> 0 | AP22: =+IFERROR(VLOOKUP($AP$17,Sheet1!AD21:AG21,3,0),0) -> 0 | AQ22: =+IFERROR(VLOOKUP($AQ$17,Sheet1!AD21:AG21,3,0),0) -> 0 | AR22: =+IFERROR(VLOOKUP($AR$17,Sheet1!AD21:AG21,3,0),0) -> 0 | AS22: =+IFERROR(VLOOKUP($AS$17,Sheet1!AH21:AK21,3,0),0) -> 0 | AT22: =+IFERROR(VLOOKUP($AT$17,Sheet1!AH21:AK21,3,0),0) -> 0 | AU22: =+IFERROR(VLOOKUP($AU$17,Sheet1!AH21:AK21,3,0),0) -> 0 | AV22: =+IFERROR(VLOOKUP($AV$17,Sheet1!AH21:AK21,3,0),0) -> 0 | AW22: =+IFERROR(VLOOKUP($AW$17,Sheet1!AH21:AK21,3,0),0) -> 0 | AX22: =+IFERROR(VLOOKUP($AX$17,Sheet1!AH21:AK21,3,0),0) -> 0 | AY22: =+IFERROR(VLOOKUP($AY$17,Sheet1!AH21:AK21,3,0),0) -> 0 | AZ22: =+IFERROR(VLOOKUP($AZ$17,Sheet1!AH21:AK21,3,0),0) -> 0 | BA22: =+IFERROR(VLOOKUP($BA$17,Sheet1!AH21:AK21,3,0),0) -> 0 | BB22: =+IFERROR(VLOOKUP($BB$17,Sheet1!AH21:AK21,3,0),0) -> 0 | BC22: =+IFERROR(VLOOKUP($BC$17,Sheet1!AL21:AO21,3,0),0) -> 0 | BD22: =+IFERROR(VLOOKUP($BD$17,Sheet1!AL21:AO21,3,0),0) -> 0 | BE22: =+IFERROR(VLOOKUP($BE$17,Sheet1!AL21:AO21,3,0),0) -> 0 | BF22: 255 | BG22: =+IFERROR(VLOOKUP($BG$17,Sheet1!AL21:AO21,3,0),0) -> 0 | BH22: =+IFERROR(VLOOKUP($BH$17,Sheet1!AL21:AO21,3,0),0) -> 0 | BI22: =+IFERROR(VLOOKUP($BI$17,Sheet1!AL21:AO21,3,0),0) -> 0 | BJ22: =+IFERROR(VLOOKUP($BJ$17,Sheet1!AL21:AO21,3,0),0) -> 0 | BK22: =+IFERROR(VLOOKUP($BK$17,Sheet1!AL21:AO21,3,0),0) -> 0 | BL22: =+IFERROR(VLOOKUP($BL$17,Sheet1!AL21:AO21,3,0),0) -> 0 | BM22: =+IFERROR(VLOOKUP($BM$17,Sheet1!AP21:AS21,3,0),0) -> 0 | BN22: 28 | BO22: =+IFERROR(VLOOKUP($BO$17,Sheet1!AX21:BA21,3,0),0) -> 0 | BP22: =+IFERROR(VLOOKUP($BP$17,Sheet1!BB21:BE21,3,0),0) -> 0 | BQ22: =+IFERROR(VLOOKUP($BQ$17,Sheet1!BF21:BI21,3,0),0) -> 0 | BR22: =+IFERROR(VLOOKUP($BR$17,Sheet1!BJ21:BM21,3,0),0) -> 0 | BS22: =+IFERROR(VLOOKUP($BS$17,Sheet1!BN21:BQ21,3,0),0) -> 0 | BT22: =+IFERROR(VLOOKUP($BT$17,Sheet1!BR21:BU21,3,0),0) -> 0 | BU22: =+IFERROR(VLOOKUP($BU$17,Sheet1!BV21:BY21,3,0),0) -> 0 | BV22: =Sheet1!E21 -> WOOD | BW22: =Sheet1!CV21 -> MD0100017 | BX22: =Sheet1!CW21 -> DRUM - 52 X 18 X 36 X 2.5 | BY22: =Sheet1!CX21 -> 1000 | BZ22: =Sheet1!BZ21 -> 4956.84 | CA22: =SUMPRODUCT($N$18:$BU$18,N22:BU22)+BZ22 -> 239131.84 | CB22: =Sheet1!CB21 -> 0 | CC22: =CA22*CB22 -> 0 | CD22: 0.18 | CE22: =CA22*CD22 -> 43043.731 | CF22: 0 | CG22: =CA22*CF22 -> 0 | CH22: =CA22+CC22+CE22+CG22 -> 282175.57 | CI22: 0.02 | CJ22: =CH22*CI22 -> 5643.5114 | CK22: 0.01 | CL22: =CH22*CK22 -> 2821.7557 | CM22: 120 | CN22: 30
A23: =Sheet1!A22 -> ENQ-12232-22-23 | B23: 45380 | C23: =Sheet1!C22 -> FA0600032 | D23: =Sheet1!D22 -> 1 CORE X 630 SQ. MM. ALU/UNARD (XLPE) | E23: =CH23+CJ23+CL23 -> 590390.27 | F23: =ROUNDUP(M56,0) -> 5619 | G23: =E23+F23 -> 596009.27 | H23: =Sheet1!CP22 -> 0.18 | I23: =G23*H23 -> 107281.67 | J23: =G23+I23 -> 703290.94 | K23: =Sheet1!CS22 -> 81.688 | L23: =Sheet1!CT22 -> KMS | M23: =J23*K23 -> 57450431 | N23: =+IFERROR(VLOOKUP($N$17,Sheet1!J22:L22,3,0),0) -> 1701 | O23: =+IFERROR(VLOOKUP($O$17,Sheet1!J22:L22,3,0),0) -> 0 | P23: =+IFERROR(VLOOKUP($P$17,Sheet1!J22:M22,3,0),0) -> 0 | Q23: =+IFERROR(VLOOKUP($Q$17,Sheet1!J22:M22,3,0),0) -> 0 | R23: =+IFERROR(VLOOKUP($R$17,Sheet1!J22:M22,3,0),0) -> 0 | S23: =+IFERROR(VLOOKUP($S$17,Sheet1!N22:Q22,3,0),0) -> 0 | T23: =+IFERROR(VLOOKUP($T$17,Sheet1!N22:Q22,3,0),0) -> 0 | U23: =+IFERROR(VLOOKUP($U$17,Sheet1!F22:I22,3,0),0) -> 0 | V23: =+IFERROR(VLOOKUP($V$17,Sheet1!F22:I22,3,0),0) -> 0 | W23: =+IFERROR(VLOOKUP($W$17,Sheet1!F22:I22,3,0),0) -> 0 | X23: =+IFERROR(VLOOKUP($X$17,Sheet1!F22:I22,3,0),0) -> 0 | Y23: =+IFERROR(VLOOKUP($Y$17,Sheet1!F22:I22,3,0),0) -> 0 | Z23: =+IFERROR(VLOOKUP($Z$17,Sheet1!F22:I22,3,0),0) -> 0 | AA23: =+IFERROR(VLOOKUP($AA$17,Sheet1!F22:I22,3,0),0) -> 0 | AB23: =+IFERROR(VLOOKUP($AB$17,Sheet1!F22:I22,3,0),0) -> 0 | AC23: =+IFERROR(VLOOKUP($AC$17,Sheet1!R22:U22,3,0),0) -> 0 | AD23: =+IFERROR(VLOOKUP($AD$17,Sheet1!R22:U22,2,0),0) -> 0 | AE23: =+IFERROR(VLOOKUP($AE$17,Sheet1!V22:Y22,3,0),0) -> 0 | AF23: 242 | AG23: =+IFERROR(VLOOKUP($AG$17,Sheet1!V22:Y22,3,0),0) -> 0 | AH23: =+IFERROR(VLOOKUP($AH$17,Sheet1!V22:Y22,3,0),0) -> 0 | AI23: =+IFERROR(VLOOKUP($AI$17,Sheet1!V22:Y22,3,0),0) -> 0 | AJ23: =+IFERROR(VLOOKUP($AJ$17,Sheet1!V22:Y22,3,0),0) -> 0 | AK23: =+IFERROR(VLOOKUP($AK$17,Sheet1!Z22:AB22,3,0),0) -> 0 | AL23: =+IFERROR(VLOOKUP($AL$17,Sheet1!AD22:AG22,3,0),0) -> 0 | AM23: =+IFERROR(VLOOKUP($AM$17,Sheet1!AD22:AG22,3,0),0) -> 0 | AN23: =+IFERROR(VLOOKUP($AN$17,Sheet1!AD22:AG22,3,0),0) -> 0 | AO23: =+IFERROR(VLOOKUP($AO$17,Sheet1!AD22:AG22,3,0),0) -> 0 | AP23: =+IFERROR(VLOOKUP($AP$17,Sheet1!AD22:AG22,3,0),0) -> 0 | AQ23: =+IFERROR(VLOOKUP($AQ$17,Sheet1!AD22:AG22,3,0),0) -> 0 | AR23: =+IFERROR(VLOOKUP($AR$17,Sheet1!AD22:AG22,3,0),0) -> 0 | AS23: =+IFERROR(VLOOKUP($AS$17,Sheet1!AH22:AK22,3,0),0) -> 0 | AT23: =+IFERROR(VLOOKUP($AT$17,Sheet1!AH22:AK22,3,0),0) -> 0 | AU23: =+IFERROR(VLOOKUP($AU$17,Sheet1!AH22:AK22,3,0),0) -> 0 | AV23: =+IFERROR(VLOOKUP($AV$17,Sheet1!AH22:AK22,3,0),0) -> 0 | AW23: =+IFERROR(VLOOKUP($AW$17,Sheet1!AH22:AK22,3,0),0) -> 0 | AX23: =+IFERROR(VLOOKUP($AX$17,Sheet1!AH22:AK22,3,0),0) -> 0 | AY23: =+IFERROR(VLOOKUP($AY$17,Sheet1!AH22:AK22,3,0),0) -> 0 | AZ23: =+IFERROR(VLOOKUP($AZ$17,Sheet1!AH22:AK22,3,0),0) -> 0 | BA23: =+IFERROR(VLOOKUP($BA$17,Sheet1!AH22:AK22,3,0),0) -> 0 | BB23: =+IFERROR(VLOOKUP($BB$17,Sheet1!AH22:AK22,3,0),0) -> 0 | BC23: =+IFERROR(VLOOKUP($BC$17,Sheet1!AL22:AO22,3,0),0) -> 0 | BD23: =+IFERROR(VLOOKUP($BD$17,Sheet1!AL22:AO22,3,0),0) -> 0 | BE23: =+IFERROR(VLOOKUP($BE$17,Sheet1!AL22:AO22,3,0),0) -> 0 | BF23: 408 | BG23: =+IFERROR(VLOOKUP($BG$17,Sheet1!AL22:AO22,3,0),0) -> 0 | BH23: =+IFERROR(VLOOKUP($BH$17,Sheet1!AL22:AO22,3,0),0) -> 0 | BI23: =+IFERROR(VLOOKUP($BI$17,Sheet1!AL22:AO22,3,0),0) -> 0 | BJ23: =+IFERROR(VLOOKUP($BJ$17,Sheet1!AL22:AO22,3,0),0) -> 0 | BK23: =+IFERROR(VLOOKUP($BK$17,Sheet1!AL22:AO22,3,0),0) -> 0 | BL23: =+IFERROR(VLOOKUP($BL$17,Sheet1!AL22:AO22,3,0),0) -> 0 | BM23: =+IFERROR(VLOOKUP($BM$17,Sheet1!AP22:AS22,3,0),0) -> 0 | BN23: 40 | BO23: =+IFERROR(VLOOKUP($BO$17,Sheet1!AX22:BA22,3,0),0) -> 0 | BP23: =+IFERROR(VLOOKUP($BP$17,Sheet1!BB22:BE22,3,0),0) -> 0 | BQ23: =+IFERROR(VLOOKUP($BQ$17,Sheet1!BF22:BI22,3,0),0) -> 0 | BR23: =+IFERROR(VLOOKUP($BR$17,Sheet1!BJ22:BM22,3,0),0) -> 0 | BS23: =+IFERROR(VLOOKUP($BS$17,Sheet1!BN22:BQ22,3,0),0) -> 0 | BT23: =+IFERROR(VLOOKUP($BT$17,Sheet1!BR22:BU22,3,0),0) -> 0 | BU23: =+IFERROR(VLOOKUP($BU$17,Sheet1!BV22:BY22,3,0),0) -> 0 | BV23: =Sheet1!E22 -> WOOD | BW23: =Sheet1!CV22 -> MD0100062 | BX23: =Sheet1!CW22 -> DRUM - 74 X 24 X 32 X 3 | BY23: =Sheet1!CX22 -> 1000 | BZ23: =Sheet1!BZ22 -> 17290 | CA23: =SUMPRODUCT($N$18:$BU$18,N23:BU23)+BZ23 -> 485758 | CB23: =Sheet1!CB22 -> 0 | CC23: =CA23*CB23 -> 0 | CD23: 0.18 | CE23: =CA23*CD23 -> 87436.44 | CF23: 0 | CG23: =CA23*CF23 -> 0 | CH23: =CA23+CC23+CE23+CG23 -> 573194.44 | CI23: 0.02 | CJ23: =CH23*CI23 -> 11463.889 | CK23: 0.01 | CL23: =CH23*CK23 -> 5731.9444 | CM23: 300 | CN23: 65
A24: =Sheet1!A10 -> ENQ-12232-22-23 | B24: 45380 | C24: =Sheet1!C10 -> FA1200026 | D24: =Sheet1!D10 -> 4 CORE X 150 SQ. MM. AL/UNARD (XLPE) | E24: =CH24+CJ24+CL24 -> 605334.64 | F24: =ROUNDUP(M57,0) -> #DIV/0! | G24: =E24+F24 -> #DIV/0! | H24: =Sheet1!CP10 -> 0.18 | I24: =G24*H24 -> #DIV/0! | J24: =G24+I24 -> #DIV/0! | L24: =Sheet1!CT10 -> KMS | M24: =J24*K24 -> #DIV/0! | N24: =+IFERROR(VLOOKUP($N$17,Sheet1!J10:L10,3,0),0) -> 1620 | O24: =+IFERROR(VLOOKUP($O$17,Sheet1!J10:L10,3,0),0) -> 0 | P24: =+IFERROR(VLOOKUP($P$17,Sheet1!J10:M10,3,0),0) -> 0 | Q24: =+IFERROR(VLOOKUP($Q$17,Sheet1!J10:M10,3,0),0) -> 0 | R24: =+IFERROR(VLOOKUP($R$17,Sheet1!J10:M10,3,0),0) -> 0 | S24: =+IFERROR(VLOOKUP($S$17,Sheet1!N10:Q10,3,0),0) -> 0 | T24: =+IFERROR(VLOOKUP($T$17,Sheet1!N10:Q10,3,0),0) -> 0 | U24: =+IFERROR(VLOOKUP($U$17,Sheet1!F10:I10,3,0),0) -> 0 | V24: =+IFERROR(VLOOKUP($V$17,Sheet1!F10:I10,3,0),0) -> 0 | W24: =+IFERROR(VLOOKUP($W$17,Sheet1!F10:I10,3,0),0) -> 0 | X24: =+IFERROR(VLOOKUP($X$17,Sheet1!F10:I10,3,0),0) -> 0 | Y24: =+IFERROR(VLOOKUP($Y$17,Sheet1!F10:I10,3,0),0) -> 0 | Z24: =+IFERROR(VLOOKUP($Z$17,Sheet1!F10:I10,3,0),0) -> 0 | AA24: =+IFERROR(VLOOKUP($AA$17,Sheet1!F10:I10,3,0),0) -> 0 | AB24: =+IFERROR(VLOOKUP($AB$17,Sheet1!F10:I10,3,0),0) -> 0 | AC24: =+IFERROR(VLOOKUP($AC$17,Sheet1!R10:U10,3,0),0) -> 0 | AD24: =+IFERROR(VLOOKUP($AD$17,Sheet1!R10:U10,2,0),0) -> 0 | AE24: =+IFERROR(VLOOKUP($AE$17,Sheet1!V10:Y10,3,0),0) -> 0 | AF24: 276 | AG24: =+IFERROR(VLOOKUP($AG$17,Sheet1!V10:Y10,3,0),0) -> 0 | AH24: =+IFERROR(VLOOKUP($AH$17,Sheet1!V10:Y10,3,0),0) -> 0 | AI24: =+IFERROR(VLOOKUP($AI$17,Sheet1!V10:Y10,3,0),0) -> 0 | AJ24: =+IFERROR(VLOOKUP($AJ$17,Sheet1!V10:Y10,3,0),0) -> 0 | AK24: =+IFERROR(VLOOKUP($AK$17,Sheet1!Z10:AB10,3,0),0) -> 0 | AL24: =+IFERROR(VLOOKUP($AL$17,Sheet1!AD10:AG10,3,0),0) -> 0 | AM24: =+IFERROR(VLOOKUP($AM$17,Sheet1!AD10:AG10,3,0),0) -> 0 | AN24: =+IFERROR(VLOOKUP($AN$17,Sheet1!AD10:AG10,3,0),0) -> 0 | AO24: =+IFERROR(VLOOKUP($AO$17,Sheet1!AD10:AG10,3,0),0) -> 0 | AP24: =+IFERROR(VLOOKUP($AP$17,Sheet1!AD10:AG10,3,0),0) -> 0 | AQ24: 135 | AR24: =+IFERROR(VLOOKUP($AR$17,Sheet1!AD10:AG10,3,0),0) -> 0 | AS24: =+IFERROR(VLOOKUP($AS$17,Sheet1!AH10:AK10,3,0),0) -> 0 | AT24: =+IFERROR(VLOOKUP($AT$17,Sheet1!AH10:AK10,3,0),0) -> 0 | AU24: =+IFERROR(VLOOKUP($AU$17,Sheet1!AH10:AK10,3,0),0) -> 0 | AV24: =+IFERROR(VLOOKUP($AV$17,Sheet1!AH10:AK10,3,0),0) -> 0 | AW24: =+IFERROR(VLOOKUP($AW$17,Sheet1!AH10:AK10,3,0),0) -> 0 | AX24: =+IFERROR(VLOOKUP($AX$17,Sheet1!AH10:AK10,3,0),0) -> 0 | AY24: =+IFERROR(VLOOKUP($AY$17,Sheet1!AH10:AK10,3,0),0) -> 0 | AZ24: =+IFERROR(VLOOKUP($AZ$17,Sheet1!AH10:AK10,3,0),0) -> 0 | BA24: =+IFERROR(VLOOKUP($BA$17,Sheet1!AH10:AK10,3,0),0) -> 0 | BB24: =+IFERROR(VLOOKUP($BB$17,Sheet1!AH10:AK10,3,0),0) -> 0 | BC24: =+IFERROR(VLOOKUP($BC$17,Sheet1!AL10:AO10,3,0),0) -> 0 | BD24: =+IFERROR(VLOOKUP($BD$17,Sheet1!AL10:AO10,3,0),0) -> 0 | BE24: =+IFERROR(VLOOKUP($BE$17,Sheet1!AL10:AO10,3,0),0) -> 0 | BF24: 536 | BG24: =+IFERROR(VLOOKUP($BG$17,Sheet1!AL10:AO10,3,0),0) -> 0 | BH24: =+IFERROR(VLOOKUP($BH$17,Sheet1!AL10:AO10,3,0),0) -> 0 | BI24: =+IFERROR(VLOOKUP($BI$17,Sheet1!AL10:AO10,3,0),0) -> 0 | BJ24: =+IFERROR(VLOOKUP($BJ$17,Sheet1!AL10:AO10,3,0),0) -> 0 | BK24: =+IFERROR(VLOOKUP($BK$17,Sheet1!AL10:AO10,3,0),0) -> 0 | BL24: =+IFERROR(VLOOKUP($BL$17,Sheet1!AL10:AO10,3,0),0) -> 0 | BM24: =+IFERROR(VLOOKUP($BM$17,Sheet1!AP10:AS10,3,0),0) -> 0 | BN24: 55 | BO24: =+IFERROR(VLOOKUP($BO$17,Sheet1!AX10:BA10,3,0),0) -> 0 | BP24: =+IFERROR(VLOOKUP($BP$17,Sheet1!BB10:BE10,3,0),0) -> 0 | BQ24: =+IFERROR(VLOOKUP($BQ$17,Sheet1!BF10:BI10,3,0),0) -> 0 | BR24: =+IFERROR(VLOOKUP($BR$17,Sheet1!BJ10:BM10,3,0),0) -> 0 | BS24: =+IFERROR(VLOOKUP($BS$17,Sheet1!BN10:BQ10,3,0),0) -> 0 | BT24: =+IFERROR(VLOOKUP($BT$17,Sheet1!BR10:BU10,3,0),0) -> 0 | BU24: =+IFERROR(VLOOKUP($BU$17,Sheet1!BV10:BY10,3,0),0) -> 0 | BV24: =Sheet1!E10 -> WOOD | BW24: =Sheet1!CV10 -> MD0100070 | BX24: =Sheet1!CW10 -> DRUM - 68 X 24 X 32 X 3 | BY24: =Sheet1!CX10 -> 500 | BZ24: =Sheet1!BZ10 -> 17878.84 | CA24: =SUMPRODUCT($N$18:$BU$18,N24:BU24)+BZ24 -> 498053.84 | CB24: =Sheet1!CB10 -> 0 | CC24: =CA24*CB24 -> 0 | CD24: 0.18 | CE24: =CA24*CD24 -> 89649.691 | CF24: 0 | CG24: =CA24*CF24 -> 0 | CH24: =CA24+CC24+CE24+CG24 -> 587703.53 | CI24: 0.02 | CJ24: =CH24*CI24 -> 11754.071 | CK24: 0.01 | CL24: =CH24*CK24 -> 5877.0353 | CM24: 250 | CN24: 50
A25: =Sheet1!A28 -> ENQ-12232-22-23 | B25: 45380 | C25: =Sheet1!C28 -> FA0900111 | D25: =Sheet1!D28 -> 4 CORE X 25 SQ. MM. ALU/ARD - WIRE (XLPE) | E25: =CH25+CJ25+CL25 -> 190246.57 | F25: =ROUNDUP(M58,0) -> 2464 | G25: =E25+F25 -> 192710.57 | H25: =Sheet1!CP28 -> 0.18 | I25: =G25*H25 -> 34687.903 | J25: =G25+I25 -> 227398.48 | K25: =48.74+166.6+25.776 -> 241.116 | L25: =Sheet1!CT28 -> KMS | M25: =J25*K25 -> 54829411 | N25: =+IFERROR(VLOOKUP($N$17,Sheet1!J28:L28,3,0),0) -> 270.3 | O25: =+IFERROR(VLOOKUP($O$17,Sheet1!J28:L28,3,0),0) -> 0 | P25: =+IFERROR(VLOOKUP($P$17,Sheet1!J28:M28,3,0),0) -> 0 | Q25: =+IFERROR(VLOOKUP($Q$17,Sheet1!J28:M28,3,0),0) -> 0 | R25: =+IFERROR(VLOOKUP($R$17,Sheet1!J28:M28,3,0),0) -> 0 | S25: =+IFERROR(VLOOKUP($S$17,Sheet1!N28:Q28,3,0),0) -> 0 | T25: =+IFERROR(VLOOKUP($T$17,Sheet1!N28:Q28,3,0),0) -> 0 | U25: =+IFERROR(VLOOKUP($U$17,Sheet1!F28:I28,3,0),0) -> 0 | V25: =+IFERROR(VLOOKUP($V$17,Sheet1!F28:I28,3,0),0) -> 0 | W25: =+IFERROR(VLOOKUP($W$17,Sheet1!F28:I28,3,0),0) -> 0 | X25: =+IFERROR(VLOOKUP($X$17,Sheet1!F28:I28,3,0),0) -> 0 | Y25: =+IFERROR(VLOOKUP($Y$17,Sheet1!F28:I28,3,0),0) -> 0 | Z25: =+IFERROR(VLOOKUP($Z$17,Sheet1!F28:I28,3,0),0) -> 0 | AA25: =+IFERROR(VLOOKUP($AA$17,Sheet1!F28:I28,3,0),0) -> 0 | AB25: =+IFERROR(VLOOKUP($AB$17,Sheet1!F28:I28,3,0),0) -> 0 | AC25: =+IFERROR(VLOOKUP($AC$17,Sheet1!R28:U28,3,0),0) -> 0 | AD25: =+IFERROR(VLOOKUP($AD$17,Sheet1!R28:U28,2,0),0) -> 0 | AE25: =+IFERROR(VLOOKUP($AE$17,Sheet1!V28:Y28,3,0),0) -> 0 | AF25: 90 | AG25: =+IFERROR(VLOOKUP($AG$17,Sheet1!V28:Y28,3,0),0) -> 0 | AH25: =+IFERROR(VLOOKUP($AH$17,Sheet1!V28:Y28,3,0),0) -> 0 | AI25: =+IFERROR(VLOOKUP($AI$17,Sheet1!V28:Y28,3,0),0) -> 0 | AJ25: =+IFERROR(VLOOKUP($AJ$17,Sheet1!V28:Y28,3,0),0) -> 0 | AK25: =+IFERROR(VLOOKUP($AK$17,Sheet1!Z28:AB28,3,0),0) -> 0 | AL25: =+IFERROR(VLOOKUP($AL$17,Sheet1!AD28:AG28,3,0),0) -> 0 | AM25: =+IFERROR(VLOOKUP($AM$17,Sheet1!AD28:AG28,3,0),0) -> 0 | AN25: =+IFERROR(VLOOKUP($AN$17,Sheet1!AD28:AG28,3,0),0) -> 0 | AO25: =+IFERROR(VLOOKUP($AO$17,Sheet1!AD28:AG28,3,0),0) -> 0 | AP25: =+IFERROR(VLOOKUP($AP$17,Sheet1!AD28:AG28,3,0),0) -> 0 | AQ25: 44 | AR25: =+IFERROR(VLOOKUP($AR$17,Sheet1!AD28:AG28,3,0),0) -> 0 | AS25: =+IFERROR(VLOOKUP($AS$17,Sheet1!AH28:AK28,3,0),0) -> 0 | AT25: =+IFERROR(VLOOKUP($AT$17,Sheet1!AH28:AK28,3,0),0) -> 0 | AU25: =+IFERROR(VLOOKUP($AU$17,Sheet1!AH28:AK28,3,0),0) -> 0 | AV25: =+IFERROR(VLOOKUP($AV$17,Sheet1!AH28:AK28,3,0),0) -> 0 | AW25: =+IFERROR(VLOOKUP($AW$17,Sheet1!AH28:AK28,3,0),0) -> 0 | AX25: =+IFERROR(VLOOKUP($AX$17,Sheet1!AH28:AK28,3,0),0) -> 0 | AY25: =+IFERROR(VLOOKUP($AY$17,Sheet1!AH28:AK28,3,0),0) -> 0 | AZ25: =+IFERROR(VLOOKUP($AZ$17,Sheet1!AH28:AK28,3,0),0) -> 0 | BA25: 641 | BB25: =+IFERROR(VLOOKUP($BB$17,Sheet1!AH28:AK28,3,0),0) -> 0 | BC25: =+IFERROR(VLOOKUP($BC$17,Sheet1!AL28:AO28,3,0),0) -> 0 | BD25: =+IFERROR(VLOOKUP($BD$17,Sheet1!AL28:AO28,3,0),0) -> 0 | BE25: =+IFERROR(VLOOKUP($BE$17,Sheet1!AL28:AO28,3,0),0) -> 0 | BF25: 190 | BG25: =+IFERROR(VLOOKUP($BG$17,Sheet1!AL28:AO28,3,0),0) -> 0 | BH25: =+IFERROR(VLOOKUP($BH$17,Sheet1!AL28:AO28,3,0),0) -> 0 | BI25: =+IFERROR(VLOOKUP($BI$17,Sheet1!AL28:AO28,3,0),0) -> 0 | BJ25: =+IFERROR(VLOOKUP($BJ$17,Sheet1!AL28:AO28,3,0),0) -> 0 | BK25: =+IFERROR(VLOOKUP($BK$17,Sheet1!AL28:AO28,3,0),0) -> 0 | BL25: =+IFERROR(VLOOKUP($BL$17,Sheet1!AL28:AO28,3,0),0) -> 0 | BM25: =+IFERROR(VLOOKUP($BM$17,Sheet1!AP28:AS28,3,0),0) -> 0 | BN25: =+IFERROR(VLOOKUP($BN$17,Sheet1!AT28:AW28,3,0),0) -> 0 | BO25: =+IFERROR(VLOOKUP($BO$17,Sheet1!AX28:BA28,3,0),0) -> 0 | BP25: =+IFERROR(VLOOKUP($BP$17,Sheet1!BB28:BE28,3,0),0) -> 0 | BQ25: =+IFERROR(VLOOKUP($BQ$17,Sheet1!BF28:BI28,3,0),0) -> 0 | BR25: =+IFERROR(VLOOKUP($BR$17,Sheet1!BJ28:BM28,3,0),0) -> 0 | BS25: =+IFERROR(VLOOKUP($BS$17,Sheet1!BN28:BQ28,3,0),0) -> 0 | BT25: 16 | BU25: =+IFERROR(VLOOKUP($BU$17,Sheet1!BV28:BY28,3,0),0) -> 0 | BV25: =Sheet1!E28 -> WOOD | BW25: =Sheet1!CV28 -> MD0100090 | BX25: =Sheet1!CW28 -> DRUM - 43 X 15 X 36 X 2.5 | BY25: =Sheet1!CX28 -> 1000 | BZ25: =Sheet1!BZ28 -> 3505.61 | CA25: =SUMPRODUCT($N$18:$BU$18,N25:BU25)+BZ25 -> 156530.01 | CB25: =Sheet1!CB28 -> 0 | CC25: =CA25*CB25 -> 0 | CD25: 0.18 | CE25: =CA25*CD25 -> 28175.402 | CF25: 0 | CG25: =CA25*CF25 -> 0 | CH25: =CA25+CC25+CE25+CG25 -> 184705.41 | CI25: 0.02 | CJ25: =CH25*CI25 -> 3694.1082 | CK25: 0.01 | CL25: =CH25*CK25 -> 1847.0541 | CM25: 75 | CN25: 25
A26: =Sheet1!A12 -> ENQ-12232-22-23 | B26: 45380 | C26: =Sheet1!C12 -> FA0900116 | D26: =Sheet1!D12 -> 4 CORE X 50 SQ. MM. AL/ARD - WIRE (XLPE) | E26: =CH26+CJ26+CL26 -> 323438.57 | F26: =ROUNDUP(M59,0) -> 3904 | G26: =E26+F26 -> 327342.57 | H26: =Sheet1!CP12 -> 0.18 | I26: =G26*H26 -> 58921.662 | J26: =G26+I26 -> 386264.23 | K26: =13.67+14 -> 27.67 | L26: =Sheet1!CT12 -> KMS | M26: =J26*K26 -> 10687931 | N26: 541 | O26: =+IFERROR(VLOOKUP($O$17,Sheet1!J12:L12,3,0),0) -> 0 | P26: =+IFERROR(VLOOKUP($P$17,Sheet1!J12:M12,3,0),0) -> 0 | Q26: =+IFERROR(VLOOKUP($Q$17,Sheet1!J12:M12,3,0),0) -> 0 | R26: =+IFERROR(VLOOKUP($R$17,Sheet1!J12:M12,3,0),0) -> 0 | S26: =+IFERROR(VLOOKUP($S$17,Sheet1!N12:Q12,3,0),0) -> 0 | T26: =+IFERROR(VLOOKUP($T$17,Sheet1!N12:Q12,3,0),0) -> 0 | U26: =+IFERROR(VLOOKUP($U$17,Sheet1!F12:I12,3,0),0) -> 0 | V26: =+IFERROR(VLOOKUP($V$17,Sheet1!F12:I12,3,0),0) -> 0 | W26: =+IFERROR(VLOOKUP($W$17,Sheet1!F12:I12,3,0),0) -> 0 | X26: =+IFERROR(VLOOKUP($X$17,Sheet1!F12:I12,3,0),0) -> 0 | Y26: =+IFERROR(VLOOKUP($Y$17,Sheet1!F12:I12,3,0),0) -> 0 | Z26: =+IFERROR(VLOOKUP($Z$17,Sheet1!F12:I12,3,0),0) -> 0 | AA26: =+IFERROR(VLOOKUP($AA$17,Sheet1!F12:I12,3,0),0) -> 0 | AB26: =+IFERROR(VLOOKUP($AB$17,Sheet1!F12:I12,3,0),0) -> 0 | AC26: =+IFERROR(VLOOKUP($AC$17,Sheet1!R12:U12,3,0),0) -> 0 | AD26: =+IFERROR(VLOOKUP($AD$17,Sheet1!R12:U12,2,0),0) -> 0 | AE26: =+IFERROR(VLOOKUP($AE$17,Sheet1!V12:Y12,3,0),0) -> 0 | AF26: 119 | AG26: =+IFERROR(VLOOKUP($AG$17,Sheet1!V12:Y12,3,0),0) -> 0 | AH26: =+IFERROR(VLOOKUP($AH$17,Sheet1!V12:Y12,3,0),0) -> 0 | AI26: =+IFERROR(VLOOKUP($AI$17,Sheet1!V12:Y12,3,0),0) -> 0 | AJ26: =+IFERROR(VLOOKUP($AJ$17,Sheet1!V12:Y12,3,0),0) -> 0 | AK26: =+IFERROR(VLOOKUP($AK$17,Sheet1!Z12:AB12,3,0),0) -> 0 | AL26: =+IFERROR(VLOOKUP($AL$17,Sheet1!AD12:AG12,3,0),0) -> 0 | AM26: =+IFERROR(VLOOKUP($AM$17,Sheet1!AD12:AG12,3,0),0) -> 0 | AN26: =+IFERROR(VLOOKUP($AN$17,Sheet1!AD12:AG12,3,0),0) -> 0 | AO26: =+IFERROR(VLOOKUP($AO$17,Sheet1!AD12:AG12,3,0),0) -> 0 | AP26: =+IFERROR(VLOOKUP($AP$17,Sheet1!AD12:AG12,3,0),0) -> 0 | AQ26: 56 | AR26: =+IFERROR(VLOOKUP($AR$17,Sheet1!AD12:AG12,3,0),0) -> 0 | AS26: =+IFERROR(VLOOKUP($AS$17,Sheet1!AH12:AK12,3,0),0) -> 0 | AT26: =+IFERROR(VLOOKUP($AT$17,Sheet1!AH12:AK12,3,0),0) -> 0 | AU26: =+IFERROR(VLOOKUP($AU$17,Sheet1!AH12:AK12,3,0),0) -> 0 | AV26: =+IFERROR(VLOOKUP($AV$17,Sheet1!AH12:AK12,3,0),0) -> 0 | AW26: =+IFERROR(VLOOKUP($AW$17,Sheet1!AH12:AK12,3,0),0) -> 0 | AX26: =+IFERROR(VLOOKUP($AX$17,Sheet1!AH12:AK12,3,0),0) -> 0 | AY26: =+IFERROR(VLOOKUP($AY$17,Sheet1!AH12:AK12,3,0),0) -> 0 | AZ26: =+IFERROR(VLOOKUP($AZ$17,Sheet1!AH12:AK12,3,0),0) -> 0 | BA26: 1042 | BB26: =+IFERROR(VLOOKUP($BB$17,Sheet1!AH12:AK12,3,0),0) -> 0 | BC26: =+IFERROR(VLOOKUP($BC$17,Sheet1!AL12:AO12,3,0),0) -> 0 | BD26: =+IFERROR(VLOOKUP($BD$17,Sheet1!AL12:AO12,3,0),0) -> 0 | BE26: =+IFERROR(VLOOKUP($BE$17,Sheet1!AL12:AO12,3,0),0) -> 0 | BF26: 260 | BG26: =+IFERROR(VLOOKUP($BG$17,Sheet1!AL12:AO12,3,0),0) -> 0 | BH26: =+IFERROR(VLOOKUP($BH$17,Sheet1!AL12:AO12,3,0),0) -> 0 | BI26: =+IFERROR(VLOOKUP($BI$17,Sheet1!AL12:AO12,3,0),0) -> 0 | BJ26: =+IFERROR(VLOOKUP($BJ$17,Sheet1!AL12:AO12,3,0),0) -> 0 | BK26: =+IFERROR(VLOOKUP($BK$17,Sheet1!AL12:AO12,3,0),0) -> 0 | BL26: =+IFERROR(VLOOKUP($BL$17,Sheet1!AL12:AO12,3,0),0) -> 0 | BM26: =+IFERROR(VLOOKUP($BM$17,Sheet1!AP12:AS12,3,0),0) -> 0 | BN26: =+IFERROR(VLOOKUP($BN$17,Sheet1!AT12:AW12,3,0),0) -> 0 | BO26: =+IFERROR(VLOOKUP($BO$17,Sheet1!AX12:BA12,3,0),0) -> 0 | BP26: =+IFERROR(VLOOKUP($BP$17,Sheet1!BB12:BE12,3,0),0) -> 0 | BQ26: =+IFERROR(VLOOKUP($BQ$17,Sheet1!BF12:BI12,3,0),0) -> 0 | BR26: =+IFERROR(VLOOKUP($BR$17,Sheet1!BJ12:BM12,3,0),0) -> 0 | BS26: =+IFERROR(VLOOKUP($BS$17,Sheet1!BN12:BQ12,3,0),0) -> 0 | BT26: 20 | BU26: =+IFERROR(VLOOKUP($BU$17,Sheet1!BV12:BY12,3,0),0) -> 0 | BV26: =Sheet1!E12 -> WOOD | BW26: =Sheet1!CV12 -> MD0100068 | BX26: =Sheet1!CW12 -> DRUM - 54 X 20 X 36 X 2.5 | BY26: =Sheet1!CX12 -> 1000 | BZ26: =Sheet1!BZ12 -> 5708.97 | CA26: =SUMPRODUCT($N$18:$BU$18,N26:BU26)+BZ26 -> 266116.97 | CB26: =Sheet1!CB12 -> 0 | CC26: =CA26*CB26 -> 0 | CD26: 0.18 | CE26: =CA26*CD26 -> 47901.055 | CF26: 0 | CG26: =CA26*CF26 -> 0 | CH26: =CA26+CC26+CE26+CG26 -> 314018.02 | CI26: 0.02 | CJ26: =CH26*CI26 -> 6280.3605 | CK26: 0.01 | CL26: =CH26*CK26 -> 3140.1802 | CM26: 150 | CN26: 30
A27: =Sheet1!A30 -> ENQ-12232-22-23 | B27: 45380 | C27: =Sheet1!C30 -> FA1100094 | D27: =Sheet1!D30 -> 4 CORE X 95 SQ. MM. ALU/ARD - WIRE (XLPE) | E27: =CH27+CJ27+CL27 -> 523865.04 | F27: =ROUNDUP(M60,0) -> 6130 | G27: =E27+F27 -> 529995.04 | H27: =Sheet1!CP30 -> 0.18 | I27: =G27*H27 -> 95399.107 | J27: =G27+I27 -> 625394.15 | K27: =6.27+143.5 -> 149.77 | L27: =Sheet1!CT30 -> KMS | M27: =J27*K27 -> 93665281 | N27: 1027 | O27: =+IFERROR(VLOOKUP($O$17,Sheet1!J30:L30,3,0),0) -> 0 | P27: =+IFERROR(VLOOKUP($P$17,Sheet1!J30:M30,3,0),0) -> 0 | Q27: =+IFERROR(VLOOKUP($Q$17,Sheet1!J30:M30,3,0),0) -> 0 | R27: =+IFERROR(VLOOKUP($R$17,Sheet1!J30:M30,3,0),0) -> 0 | S27: =+IFERROR(VLOOKUP($S$17,Sheet1!N30:Q30,3,0),0) -> 0 | T27: =+IFERROR(VLOOKUP($T$17,Sheet1!N30:Q30,3,0),0) -> 0 | U27: =+IFERROR(VLOOKUP($U$17,Sheet1!F30:I30,3,0),0) -> 0 | V27: =+IFERROR(VLOOKUP($V$17,Sheet1!F30:I30,3,0),0) -> 0 | W27: =+IFERROR(VLOOKUP($W$17,Sheet1!F30:I30,3,0),0) -> 0 | X27: =+IFERROR(VLOOKUP($X$17,Sheet1!F30:I30,3,0),0) -> 0 | Y27: =+IFERROR(VLOOKUP($Y$17,Sheet1!F30:I30,3,0),0) -> 0 | Z27: =+IFERROR(VLOOKUP($Z$17,Sheet1!F30:I30,3,0),0) -> 0 | AA27: =+IFERROR(VLOOKUP($AA$17,Sheet1!F30:I30,3,0),0) -> 0 | AB27: =+IFERROR(VLOOKUP($AB$17,Sheet1!F30:I30,3,0),0) -> 0 | AC27: =+IFERROR(VLOOKUP($AC$17,Sheet1!R30:U30,3,0),0) -> 0 | AD27: =+IFERROR(VLOOKUP($AD$17,Sheet1!R30:U30,2,0),0) -> 0 | AE27: =+IFERROR(VLOOKUP($AE$17,Sheet1!V30:Y30,3,0),0) -> 0 | AF27: 172 | AG27: =+IFERROR(VLOOKUP($AG$17,Sheet1!V30:Y30,3,0),0) -> 0 | AH27: =+IFERROR(VLOOKUP($AH$17,Sheet1!V30:Y30,3,0),0) -> 0 | AI27: =+IFERROR(VLOOKUP($AI$17,Sheet1!V30:Y30,3,0),0) -> 0 | AJ27: =+IFERROR(VLOOKUP($AJ$17,Sheet1!V30:Y30,3,0),0) -> 0 | AK27: =+IFERROR(VLOOKUP($AK$17,Sheet1!Z30:AB30,3,0),0) -> 0 | AL27: =+IFERROR(VLOOKUP($AL$17,Sheet1!AD30:AG30,3,0),0) -> 0 | AM27: =+IFERROR(VLOOKUP($AM$17,Sheet1!AD30:AG30,3,0),0) -> 0 | AN27: =+IFERROR(VLOOKUP($AN$17,Sheet1!AD30:AG30,3,0),0) -> 0 | AO27: =+IFERROR(VLOOKUP($AO$17,Sheet1!AD30:AG30,3,0),0) -> 0 | AP27: =+IFERROR(VLOOKUP($AP$17,Sheet1!AD30:AG30,3,0),0) -> 0 | AQ27: 89 | AR27: =+IFERROR(VLOOKUP($AR$17,Sheet1!AD30:AG30,3,0),0) -> 0 | AS27: =+IFERROR(VLOOKUP($AS$17,Sheet1!AH30:AK30,3,0),0) -> 0 | AT27: =+IFERROR(VLOOKUP($AT$17,Sheet1!AH30:AK30,3,0),0) -> 0 | AU27: =+IFERROR(VLOOKUP($AU$17,Sheet1!AH30:AK30,3,0),0) -> 0 | AV27: =+IFERROR(VLOOKUP($AV$17,Sheet1!AH30:AK30,3,0),0) -> 0 | AW27: =+IFERROR(VLOOKUP($AW$17,Sheet1!AH30:AK30,3,0),0) -> 0 | AX27: =+IFERROR(VLOOKUP($AX$17,Sheet1!AH30:AK30,3,0),0) -> 0 | AY27: =+IFERROR(VLOOKUP($AY$17,Sheet1!AH30:AK30,3,0),0) -> 0 | AZ27: =+IFERROR(VLOOKUP($AZ$17,Sheet1!AH30:AK30,3,0),0) -> 0 | BA27: 1362 | BB27: =+IFERROR(VLOOKUP($BB$17,Sheet1!AH30:AK30,3,0),0) -> 0 | BC27: =+IFERROR(VLOOKUP($BC$17,Sheet1!AL30:AO30,3,0),0) -> 0 | BD27: =+IFERROR(VLOOKUP($BD$17,Sheet1!AL30:AO30,3,0),0) -> 0 | BE27: =+IFERROR(VLOOKUP($BE$17,Sheet1!AL30:AO30,3,0),0) -> 0 | BF27: 358 | BG27: =+IFERROR(VLOOKUP($BG$17,Sheet1!AL30:AO30,3,0),0) -> 0 | BH27: =+IFERROR(VLOOKUP($BH$17,Sheet1!AL30:AO30,3,0),0) -> 0 | BI27: =+IFERROR(VLOOKUP($BI$17,Sheet1!AL30:AO30,3,0),0) -> 0 | BJ27: =+IFERROR(VLOOKUP($BJ$17,Sheet1!AL30:AO30,3,0),0) -> 0 | BK27: =+IFERROR(VLOOKUP($BK$17,Sheet1!AL30:AO30,3,0),0) -> 0 | BL27: =+IFERROR(VLOOKUP($BL$17,Sheet1!AL30:AO30,3,0),0) -> 0 | BM27: =+IFERROR(VLOOKUP($BM$17,Sheet1!AP30:AS30,3,0),0) -> 0 | BN27: =+IFERROR(VLOOKUP($BN$17,Sheet1!AT30:AW30,3,0),0) -> 0 | BO27: =+IFERROR(VLOOKUP($BO$17,Sheet1!AX30:BA30,3,0),0) -> 0 | BP27: =+IFERROR(VLOOKUP($BP$17,Sheet1!BB30:BE30,3,0),0) -> 0 | BQ27: =+IFERROR(VLOOKUP($BQ$17,Sheet1!BF30:BI30,3,0),0) -> 0 | BR27: =+IFERROR(VLOOKUP($BR$17,Sheet1!BJ30:BM30,3,0),0) -> 0 | BS27: =+IFERROR(VLOOKUP($BS$17,Sheet1!BN30:BQ30,3,0),0) -> 0 | BT27: 25 | BU27: =+IFERROR(VLOOKUP($BU$17,Sheet1!BV30:BY30,3,0),0) -> 0 | BV27: =Sheet1!E30 -> WOOD | BW27: =Sheet1!CV30 -> MD0100061 | BX27: =Sheet1!CW30 -> DRUM - 56 X 24 X 32 X 3 | BY27: =Sheet1!CX30 -> 500 | BZ27: =Sheet1!BZ30 -> 13713.74 | CA27: =SUMPRODUCT($N$18:$BU$18,N27:BU27)+BZ27 -> 431022.74 | CB27: =Sheet1!CB30 -> 0 | CC27: =CA27*CB27 -> 0 | CD27: 0.18 | CE27: =CA27*CD27 -> 77584.093 | CF27: 0 | CG27: =CA27*CF27 -> 0 | CH27: =CA27+CC27+CE27+CG27 -> 508606.83 | CI27: 0.02 | CJ27: =CH27*CI27 -> 10172.137 | CK27: 0.01 | CL27: =CH27*CK27 -> 5086.0683 | CM27: 160 | CN27: 30
A28: =Sheet1!A16 -> ENQ-12232-22-23 | B28: 45380 | C28: =Sheet1!C16 -> FA1100177 | D28: =Sheet1!D16 -> 4 CORE X 150 SQ. MM. AL/ARD - WIRE (XLPE) | E28: =CH28+CJ28+CL28 -> 852046.75 | F28: =ROUNDUP(M61,0) -> 11444 | G28: =E28+F28 -> 863490.75 | H28: =Sheet1!CP16 -> 0.18 | I28: =G28*H28 -> 155428.34 | J28: =G28+I28 -> 1018919.1 | K28: =1.6+3.5+18.495 -> 23.595 | L28: =Sheet1!CT16 -> KMS | M28: =J28*K28 -> 24041396 | N28: =+IFERROR(VLOOKUP($N$17,Sheet1!J16:L16,3,0),0) -> 1620 | O28: =+IFERROR(VLOOKUP($O$17,Sheet1!J16:L16,3,0),0) -> 0 | P28: =+IFERROR(VLOOKUP($P$17,Sheet1!J16:M16,3,0),0) -> 0 | Q28: =+IFERROR(VLOOKUP($Q$17,Sheet1!J16:M16,3,0),0) -> 0 | R28: =+IFERROR(VLOOKUP($R$17,Sheet1!J16:M16,3,0),0) -> 0 | S28: =+IFERROR(VLOOKUP($S$17,Sheet1!N16:Q16,3,0),0) -> 0 | T28: =+IFERROR(VLOOKUP($T$17,Sheet1!N16:Q16,3,0),0) -> 0 | U28: =+IFERROR(VLOOKUP($U$17,Sheet1!F16:I16,3,0),0) -> 0 | V28: =+IFERROR(VLOOKUP($V$17,Sheet1!F16:I16,3,0),0) -> 0 | W28: =+IFERROR(VLOOKUP($W$17,Sheet1!F16:I16,3,0),0) -> 0 | X28: =+IFERROR(VLOOKUP($X$17,Sheet1!F16:I16,3,0),0) -> 0 | Y28: =+IFERROR(VLOOKUP($Y$17,Sheet1!F16:I16,3,0),0) -> 0 | Z28: =+IFERROR(VLOOKUP($Z$17,Sheet1!F16:I16,3,0),0) -> 0 | AA28: =+IFERROR(VLOOKUP($AA$17,Sheet1!F16:I16,3,0),0) -> 0 | AB28: =+IFERROR(VLOOKUP($AB$17,Sheet1!F16:I16,3,0),0) -> 0 | AC28: =+IFERROR(VLOOKUP($AC$17,Sheet1!R16:U16,3,0),0) -> 0 | AD28: =+IFERROR(VLOOKUP($AD$17,Sheet1!R16:U16,2,0),0) -> 0 | AE28: =+IFERROR(VLOOKUP($AE$17,Sheet1!V16:Y16,3,0),0) -> 0 | AF28: =+IFERROR(VLOOKUP($AF$17,Sheet1!V16:Y16,3,0),0) -> 276 | AG28: =+IFERROR(VLOOKUP($AG$17,Sheet1!V16:Y16,3,0),0) -> 0 | AH28: =+IFERROR(VLOOKUP($AH$17,Sheet1!V16:Y16,3,0),0) -> 0 | AI28: =+IFERROR(VLOOKUP($AI$17,Sheet1!V16:Y16,3,0),0) -> 0 | AJ28: =+IFERROR(VLOOKUP($AJ$17,Sheet1!V16:Y16,3,0),0) -> 0 | AK28: =+IFERROR(VLOOKUP($AK$17,Sheet1!Z16:AB16,3,0),0) -> 0 | AL28: =+IFERROR(VLOOKUP($AL$17,Sheet1!AD16:AG16,3,0),0) -> 0 | AM28: =+IFERROR(VLOOKUP($AM$17,Sheet1!AD16:AG16,3,0),0) -> 0 | AN28: =+IFERROR(VLOOKUP($AN$17,Sheet1!AD16:AG16,3,0),0) -> 0 | AO28: =+IFERROR(VLOOKUP($AO$17,Sheet1!AD16:AG16,3,0),0) -> 0 | AP28: =+IFERROR(VLOOKUP($AP$17,Sheet1!AD16:AG16,3,0),0) -> 0 | AQ28: 135 | AR28: =+IFERROR(VLOOKUP($AR$17,Sheet1!AD16:AG16,3,0),0) -> 0 | AS28: =+IFERROR(VLOOKUP($AS$17,Sheet1!AH16:AK16,3,0),0) -> 0 | AT28: =+IFERROR(VLOOKUP($AT$17,Sheet1!AH16:AK16,3,0),0) -> 0 | AU28: =+IFERROR(VLOOKUP($AU$17,Sheet1!AH16:AK16,3,0),0) -> 0 | AV28: =+IFERROR(VLOOKUP($AV$17,Sheet1!AH16:AK16,3,0),0) -> 0 | AW28: =+IFERROR(VLOOKUP($AW$17,Sheet1!AH16:AK16,3,0),0) -> 0 | AX28: =+IFERROR(VLOOKUP($AX$17,Sheet1!AH16:AK16,3,0),0) -> 0 | AY28: =+IFERROR(VLOOKUP($AY$17,Sheet1!AH16:AK16,3,0),0) -> 0 | AZ28: =+IFERROR(VLOOKUP($AZ$17,Sheet1!AH16:AK16,3,0),0) -> 0 | BA28: 2290 | BB28: =+IFERROR(VLOOKUP($BB$17,Sheet1!AH16:AK16,3,0),0) -> 0 | BC28: =+IFERROR(VLOOKUP($BC$17,Sheet1!AL16:AO16,3,0),0) -> 0 | BD28: =+IFERROR(VLOOKUP($BD$17,Sheet1!AL16:AO16,3,0),0) -> 0 | BE28: =+IFERROR(VLOOKUP($BE$17,Sheet1!AL16:AO16,3,0),0) -> 0 | BF28: 530 | BG28: =+IFERROR(VLOOKUP($BG$17,Sheet1!AL16:AO16,3,0),0) -> 0 | BH28: =+IFERROR(VLOOKUP($BH$17,Sheet1!AL16:AO16,3,0),0) -> 0 | BI28: =+IFERROR(VLOOKUP($BI$17,Sheet1!AL16:AO16,3,0),0) -> 0 | BJ28: =+IFERROR(VLOOKUP($BJ$17,Sheet1!AL16:AO16,3,0),0) -> 0 | BK28: =+IFERROR(VLOOKUP($BK$17,Sheet1!AL16:AO16,3,0),0) -> 0 | BL28: =+IFERROR(VLOOKUP($BL$17,Sheet1!AL16:AO16,3,0),0) -> 0 | BM28: =+IFERROR(VLOOKUP($BM$17,Sheet1!AP16:AS16,3,0),0) -> 0 | BN28: 55 | BO28: =+IFERROR(VLOOKUP($BO$17,Sheet1!AX16:BA16,3,0),0) -> 0 | BP28: =+IFERROR(VLOOKUP($BP$17,Sheet1!BB16:BE16,3,0),0) -> 0 | BQ28: =+IFERROR(VLOOKUP($BQ$17,Sheet1!BF16:BI16,3,0),0) -> 0 | BR28: =+IFERROR(VLOOKUP($BR$17,Sheet1!BJ16:BM16,3,0),0) -> 0 | BS28: =+IFERROR(VLOOKUP($BS$17,Sheet1!BN16:BQ16,3,0),0) -> 0 | BT28: 33 | BU28: =+IFERROR(VLOOKUP($BU$17,Sheet1!BV16:BY16,3,0),0) -> 0 | BV28: =Sheet1!E16 -> WOOD | BW28: =Sheet1!CV16 -> MD0100024 | BX28: =Sheet1!CW16 -> DRUM - 70 X 30 X 36 X 3 | BY28: =Sheet1!CX16 -> 500 | BZ28: =Sheet1!BZ16 -> 18867.25 | CA28: =SUMPRODUCT($N$18:$BU$18,N28:BU28)+BZ28 -> 701042.25 | CB28: =Sheet1!CB16 -> 0 | CC28: =CA28*CB28 -> 0 | CD28: 0.18 | CE28: =CA28*CD28 -> 126187.6 | CF28: 0 | CG28: =CA28*CF28 -> 0 | CH28: =CA28+CC28+CE28+CG28 -> 827229.85 | CI28: 0.02 | CJ28: =CH28*CI28 -> 16544.597 | CK28: 0.01 | CL28: =CH28*CK28 -> 8272.2985 | CM28: 260 | CN28: 55
A29: =Sheet1!A3 -> ENQ-12232-22-23 | B29: 45380 | C29: =Sheet1!C3 -> FA1100091 | D29: =Sheet1!D3 -> 4 CORE X 240 SQ. MM. AL/ARD - WIRE (XLPE) | E29: =CH29+CJ29+CL29 -> 1240725.3 | F29: =ROUNDUP(M62,0) -> 27000 | G29: =E29+F29 -> 1267725.3 | H29: =Sheet1!CP3 -> 0.18 | I29: =G29*H29 -> 228190.55 | J29: =G29+I29 -> 1495915.8 | K29: =Sheet1!CS3 -> 1 | L29: =Sheet1!CT3 -> KMS | M29: =J29*K29 -> 1495915.8 | N29: 2595 | O29: =+IFERROR(VLOOKUP($O$17,Sheet1!J3:L3,3,0),0) -> 0 | P29: =+IFERROR(VLOOKUP($P$17,Sheet1!J3:M3,3,0),0) -> 0 | Q29: =+IFERROR(VLOOKUP($Q$17,Sheet1!J3:M3,3,0),0) -> 0 | R29: =+IFERROR(VLOOKUP($R$17,Sheet1!J3:M3,3,0),0) -> 0 | S29: =+IFERROR(VLOOKUP($S$17,Sheet1!N3:Q3,3,0),0) -> 0 | T29: =+IFERROR(VLOOKUP($T$17,Sheet1!N3:Q3,3,0),0) -> 0 | U29: =+IFERROR(VLOOKUP($U$17,Sheet1!F3:I3,3,0),0) -> 0 | V29: =+IFERROR(VLOOKUP($V$17,Sheet1!F3:I3,3,0),0) -> 0 | W29: =+IFERROR(VLOOKUP($W$17,Sheet1!F3:I3,3,0),0) -> 0 | X29: =+IFERROR(VLOOKUP($X$17,Sheet1!F3:I3,3,0),0) -> 0 | Y29: =+IFERROR(VLOOKUP($Y$17,Sheet1!F3:I3,3,0),0) -> 0 | Z29: =+IFERROR(VLOOKUP($Z$17,Sheet1!F3:I3,3,0),0) -> 0 | AA29: =+IFERROR(VLOOKUP($AA$17,Sheet1!F3:I3,3,0),0) -> 0 | AB29: =+IFERROR(VLOOKUP($AB$17,Sheet1!F3:I3,3,0),0) -> 0 | AC29: =+IFERROR(VLOOKUP($AC$17,Sheet1!R3:U3,3,0),0) -> 0 | AD29: =+IFERROR(VLOOKUP($AD$17,Sheet1!R3:U3,2,0),0) -> 0 | AE29: =+IFERROR(VLOOKUP($AE$17,Sheet1!V3:Y3,3,0),0) -> 0 | AF29: 415 | AG29: =+IFERROR(VLOOKUP($AG$17,Sheet1!V3:Y3,3,0),0) -> 0 | AH29: =+IFERROR(VLOOKUP($AH$17,Sheet1!V3:Y3,3,0),0) -> 0 | AI29: =+IFERROR(VLOOKUP($AI$17,Sheet1!V3:Y3,3,0),0) -> 0 | AJ29: =+IFERROR(VLOOKUP($AJ$17,Sheet1!V3:Y3,3,0),0) -> 0 | AK29: =+IFERROR(VLOOKUP($AK$17,Sheet1!Z3:AB3,3,0),0) -> 0 | AL29: =+IFERROR(VLOOKUP($AL$17,Sheet1!AD3:AG3,3,0),0) -> 0 | AM29: =+IFERROR(VLOOKUP($AM$17,Sheet1!AD3:AG3,3,0),0) -> 0 | AN29: =+IFERROR(VLOOKUP($AN$17,Sheet1!AD3:AG3,3,0),0) -> 0 | AO29: =+IFERROR(VLOOKUP($AO$17,Sheet1!AD3:AG3,3,0),0) -> 0 | AP29: =+IFERROR(VLOOKUP($AP$17,Sheet1!AD3:AG3,3,0),0) -> 0 | AQ29: 185 | AR29: =+IFERROR(VLOOKUP($AR$17,Sheet1!AD3:AG3,3,0),0) -> 0 | AS29: =+IFERROR(VLOOKUP($AS$17,Sheet1!AH3:AK3,3,0),0) -> 0 | AT29: =+IFERROR(VLOOKUP($AT$17,Sheet1!AH3:AK3,3,0),0) -> 0 | AU29: =+IFERROR(VLOOKUP($AU$17,Sheet1!AH3:AK3,3,0),0) -> 0 | AV29: =+IFERROR(VLOOKUP($AV$17,Sheet1!AH3:AK3,3,0),0) -> 0 | AW29: =+IFERROR(VLOOKUP($AW$17,Sheet1!AH3:AK3,3,0),0) -> 0 | AX29: =+IFERROR(VLOOKUP($AX$17,Sheet1!AH3:AK3,3,0),0) -> 0 | AY29: =+IFERROR(VLOOKUP($AY$17,Sheet1!AH3:AK3,3,0),0) -> 0 | AZ29: =+IFERROR(VLOOKUP($AZ$17,Sheet1!AH3:AK3,3,0),0) -> 0 | BA29: 2800 | BB29: =+IFERROR(VLOOKUP($BB$17,Sheet1!AH3:AK3,3,0),0) -> 0 | BC29: =+IFERROR(VLOOKUP($BC$17,Sheet1!AL3:AO3,3,0),0) -> 0 | BD29: =+IFERROR(VLOOKUP($BD$17,Sheet1!AL3:AO3,3,0),0) -> 0 | BE29: =+IFERROR(VLOOKUP($BE$17,Sheet1!AL3:AO3,3,0),0) -> 0 | BF29: 728 | BG29: =+IFERROR(VLOOKUP($BG$17,Sheet1!AL3:AO3,3,0),0) -> 0 | BH29: =+IFERROR(VLOOKUP($BH$17,Sheet1!AL3:AO3,3,0),0) -> 0 | BI29: =+IFERROR(VLOOKUP($BI$17,Sheet1!AL3:AO3,3,0),0) -> 0 | BJ29: =+IFERROR(VLOOKUP($BJ$17,Sheet1!AL3:AO3,3,0),0) -> 0 | BK29: =+IFERROR(VLOOKUP($BK$17,Sheet1!AL3:AO3,3,0),0) -> 0 | BL29: =+IFERROR(VLOOKUP($BL$17,Sheet1!AL3:AO3,3,0),0) -> 0 | BM29: =+IFERROR(VLOOKUP($BM$17,Sheet1!AP3:AS3,3,0),0) -> 0 | BN29: 75 | BO29: =+IFERROR(VLOOKUP($BO$17,Sheet1!AX3:BA3,3,0),0) -> 0 | BP29: =+IFERROR(VLOOKUP($BP$17,Sheet1!BB3:BE3,3,0),0) -> 0 | BQ29: =+IFERROR(VLOOKUP($BQ$17,Sheet1!BF3:BI3,3,0),0) -> 0 | BR29: =+IFERROR(VLOOKUP($BR$17,Sheet1!BJ3:BM3,3,0),0) -> 0 | BS29: =+IFERROR(VLOOKUP($BS$17,Sheet1!BN3:BQ3,3,0),0) -> 0 | BT29: 39 | BU29: =+IFERROR(VLOOKUP($BU$17,Sheet1!BV3:BY3,3,0),0) -> 0 | BV29: =Sheet1!E3 -> WOOD | BW29: =Sheet1!CV3 -> MD0100048 | BX29: =Sheet1!CW3 -> DRUM - 74 X 35 X 39 X 3 | BY29: =Sheet1!CX3 -> 500 | BZ29: =Sheet1!BZ3 -> 27302 | CA29: =SUMPRODUCT($N$18:$BU$18,N29:BU29)+BZ29 -> 1020837 | CB29: =Sheet1!CB3 -> 0 | CC29: =CA29*CB29 -> 0 | CD29: 0.18 | CE29: =CA29*CD29 -> 183750.66 | CF29: 0 | CG29: =CA29*CF29 -> 0 | CH29: =CA29+CC29+CE29+CG29 -> 1204587.7 | CI29: 0.02 | CJ29: =CH29*CI29 -> 24091.753 | CK29: 0.01 | CL29: =CH29*CK29 -> 12045.877 | CM29: 300 | CN29: 65
A30: =Sheet1!A18 -> ENQ-12232-22-23 | B30: 45380 | C30: =Sheet1!C18 -> FA1100176 | D30: =Sheet1!D18 -> 4 CORE X 300 SQ. MM. AL/ARD - WIRE (XLPE) | E30: =CH30+CJ30+CL30 -> 1527031 | F30: =ROUNDUP(M63,0) -> 19566 | G30: =E30+F30 -> 1546597 | H30: =Sheet1!CP18 -> 0.18 | I30: =G30*H30 -> 278387.46 | J30: =G30+I30 -> 1824984.4 | K30: =2.1+10.32 -> 12.42 | L30: =Sheet1!CT18 -> KMS | M30: =J30*K30 -> 22666307 | N30: =+IFERROR(VLOOKUP($N$17,Sheet1!J18:L18,3,0),0) -> 3240 | O30: =+IFERROR(VLOOKUP($O$17,Sheet1!J18:L18,3,0),0) -> 0 | P30: =+IFERROR(VLOOKUP($P$17,Sheet1!J18:M18,3,0),0) -> 0 | Q30: =+IFERROR(VLOOKUP($Q$17,Sheet1!J18:M18,3,0),0) -> 0 | R30: =+IFERROR(VLOOKUP($R$17,Sheet1!J18:M18,3,0),0) -> 0 | S30: =+IFERROR(VLOOKUP($S$17,Sheet1!N18:Q18,3,0),0) -> 0 | T30: =+IFERROR(VLOOKUP($T$17,Sheet1!N18:Q18,3,0),0) -> 0 | U30: =+IFERROR(VLOOKUP($U$17,Sheet1!F18:I18,3,0),0) -> 0 | V30: =+IFERROR(VLOOKUP($V$17,Sheet1!F18:I18,3,0),0) -> 0 | W30: =+IFERROR(VLOOKUP($W$17,Sheet1!F18:I18,3,0),0) -> 0 | X30: =+IFERROR(VLOOKUP($X$17,Sheet1!F18:I18,3,0),0) -> 0 | Y30: =+IFERROR(VLOOKUP($Y$17,Sheet1!F18:I18,3,0),0) -> 0 | Z30: =+IFERROR(VLOOKUP($Z$17,Sheet1!F18:I18,3,0),0) -> 0 | AA30: =+IFERROR(VLOOKUP($AA$17,Sheet1!F18:I18,3,0),0) -> 0 | AB30: =+IFERROR(VLOOKUP($AB$17,Sheet1!F18:I18,3,0),0) -> 0 | AC30: =+IFERROR(VLOOKUP($AC$17,Sheet1!R18:U18,3,0),0) -> 0 | AD30: =+IFERROR(VLOOKUP($AD$17,Sheet1!R18:U18,2,0),0) -> 0 | AE30: =+IFERROR(VLOOKUP($AE$17,Sheet1!V18:Y18,3,0),0) -> 0 | AF30: 500 | AG30: =+IFERROR(VLOOKUP($AG$17,Sheet1!V18:Y18,3,0),0) -> 0 | AH30: =+IFERROR(VLOOKUP($AH$17,Sheet1!V18:Y18,3,0),0) -> 0 | AI30: =+IFERROR(VLOOKUP($AI$17,Sheet1!V18:Y18,3,0),0) -> 0 | AJ30: =+IFERROR(VLOOKUP($AJ$17,Sheet1!V18:Y18,3,0),0) -> 0 | AK30: =+IFERROR(VLOOKUP($AK$17,Sheet1!Z18:AB18,3,0),0) -> 0 | AL30: =+IFERROR(VLOOKUP($AL$17,Sheet1!AD18:AG18,3,0),0) -> 0 | AM30: =+IFERROR(VLOOKUP($AM$17,Sheet1!AD18:AG18,3,0),0) -> 0 | AN30: =+IFERROR(VLOOKUP($AN$17,Sheet1!AD18:AG18,3,0),0) -> 0 | AO30: =+IFERROR(VLOOKUP($AO$17,Sheet1!AD18:AG18,3,0),0) -> 0 | AP30: =+IFERROR(VLOOKUP($AP$17,Sheet1!AD18:AG18,3,0),0) -> 0 | AQ30: 240 | AR30: =+IFERROR(VLOOKUP($AR$17,Sheet1!AD18:AG18,3,0),0) -> 0 | AS30: =+IFERROR(VLOOKUP($AS$17,Sheet1!AH18:AK18,3,0),0) -> 0 | AT30: =+IFERROR(VLOOKUP($AT$17,Sheet1!AH18:AK18,3,0),0) -> 0 | AU30: =+IFERROR(VLOOKUP($AU$17,Sheet1!AH18:AK18,3,0),0) -> 0 | AV30: =+IFERROR(VLOOKUP($AV$17,Sheet1!AH18:AK18,3,0),0) -> 0 | AW30: =+IFERROR(VLOOKUP($AW$17,Sheet1!AH18:AK18,3,0),0) -> 0 | AX30: =+IFERROR(VLOOKUP($AX$17,Sheet1!AH18:AK18,3,0),0) -> 0 | AY30: =+IFERROR(VLOOKUP($AY$17,Sheet1!AH18:AK18,3,0),0) -> 0 | AZ30: =+IFERROR(VLOOKUP($AZ$17,Sheet1!AH18:AK18,3,0),0) -> 0 | BA30: 3118 | BB30: =+IFERROR(VLOOKUP($BB$17,Sheet1!AH18:AK18,3,0),0) -> 0 | BC30: =+IFERROR(VLOOKUP($BC$17,Sheet1!AL18:AO18,3,0),0) -> 0 | BD30: =+IFERROR(VLOOKUP($BD$17,Sheet1!AL18:AO18,3,0),0) -> 0 | BE30: =+IFERROR(VLOOKUP($BE$17,Sheet1!AL18:AO18,3,0),0) -> 0 | BF30: 880 | BG30: =+IFERROR(VLOOKUP($BG$17,Sheet1!AL18:AO18,3,0),0) -> 0 | BH30: =+IFERROR(VLOOKUP($BH$17,Sheet1!AL18:AO18,3,0),0) -> 0 | BI30: =+IFERROR(VLOOKUP($BI$17,Sheet1!AL18:AO18,3,0),0) -> 0 | BJ30: =+IFERROR(VLOOKUP($BJ$17,Sheet1!AL18:AO18,3,0),0) -> 0 | BK30: =+IFERROR(VLOOKUP($BK$17,Sheet1!AL18:AO18,3,0),0) -> 0 | BL30: =+IFERROR(VLOOKUP($BL$17,Sheet1!AL18:AO18,3,0),0) -> 0 | BM30: =+IFERROR(VLOOKUP($BM$17,Sheet1!AP18:AS18,3,0),0) -> 0 | BN30: 112 | BO30: =+IFERROR(VLOOKUP($BO$17,Sheet1!AX18:BA18,3,0),0) -> 0 | BP30: =+IFERROR(VLOOKUP($BP$17,Sheet1!BB18:BE18,3,0),0) -> 0 | BQ30: =+IFERROR(VLOOKUP($BQ$17,Sheet1!BF18:BI18,3,0),0) -> 0 | BR30: =+IFERROR(VLOOKUP($BR$17,Sheet1!BJ18:BM18,3,0),0) -> 0 | BS30: =+IFERROR(VLOOKUP($BS$17,Sheet1!BN18:BQ18,3,0),0) -> 0 | BT30: 44 | BU30: =+IFERROR(VLOOKUP($BU$17,Sheet1!BV18:BY18,3,0),0) -> 0 | BV30: =Sheet1!E18 -> WOOD | BW30: =Sheet1!CV18 -> MD0100040 | BX30: =Sheet1!CW18 -> DRUM - 86 X 38 X 46 X 4 | BY30: =Sheet1!CX18 -> 500 | BZ30: =Sheet1!BZ18 -> 47086 | CA30: =SUMPRODUCT($N$18:$BU$18,N30:BU30)+BZ30 -> 1256402 | CB30: =Sheet1!CB18 -> 0 | CC30: =CA30*CB30 -> 0 | CD30: 0.18 | CE30: =CA30*CD30 -> 226152.36 | CF30: 0 | CG30: =CA30*CF30 -> 0 | CH30: =CA30+CC30+CE30+CG30 -> 1482554.4 | CI30: 0.02 | CJ30: =CH30*CI30 -> 29651.087 | CK30: 0.01 | CL30: =CH30*CK30 -> 14825.544 | CM30: 475 | CN30: 100
A31: =Sheet1!A9 -> ENQ-12232-22-23 | B31: 45380 | C31: =Sheet1!C9 -> FA0500017 | D31: =Sheet1!D9 -> 1 CORE X 50 SQ. MM. AL/UNARD. (XLPE) | E31: =CH31+CJ31+CL31 -> 58746.845 | F31: =ROUNDUP(M64,0) -> 4154 | G31: =E31+F31 -> 62900.845 | H31: =Sheet1!CP9 -> 0.18 | I31: =G31*H31 -> 11322.152 | J31: =G31+I31 -> 74222.997 | K31: =Sheet1!CS9 -> 6.5 | L31: =Sheet1!CT9 -> KMS | M31: =J31*K31 -> 482449.48 | N31: =+IFERROR(VLOOKUP($N$17,Sheet1!J9:L9,3,0),0) -> 135 | O31: =+IFERROR(VLOOKUP($O$17,Sheet1!J9:L9,3,0),0) -> 0 | P31: =+IFERROR(VLOOKUP($P$17,Sheet1!J9:M9,3,0),0) -> 0 | Q31: =+IFERROR(VLOOKUP($Q$17,Sheet1!J9:M9,3,0),0) -> 0 | R31: =+IFERROR(VLOOKUP($R$17,Sheet1!J9:M9,3,0),0) -> 0 | S31: =+IFERROR(VLOOKUP($S$17,Sheet1!N9:Q9,3,0),0) -> 0 | T31: =+IFERROR(VLOOKUP($T$17,Sheet1!N9:Q9,3,0),0) -> 0 | U31: =+IFERROR(VLOOKUP($U$17,Sheet1!F9:I9,3,0),0) -> 0 | V31: =+IFERROR(VLOOKUP($V$17,Sheet1!F9:I9,3,0),0) -> 0 | W31: =+IFERROR(VLOOKUP($W$17,Sheet1!F9:I9,3,0),0) -> 0 | X31: =+IFERROR(VLOOKUP($X$17,Sheet1!F9:I9,3,0),0) -> 0 | Y31: =+IFERROR(VLOOKUP($Y$17,Sheet1!F9:I9,3,0),0) -> 0 | Z31: =+IFERROR(VLOOKUP($Z$17,Sheet1!F9:I9,3,0),0) -> 0 | AA31: =+IFERROR(VLOOKUP($AA$17,Sheet1!F9:I9,3,0),0) -> 0 | AB31: =+IFERROR(VLOOKUP($AB$17,Sheet1!F9:I9,3,0),0) -> 0 | AC31: =+IFERROR(VLOOKUP($AC$17,Sheet1!R9:U9,3,0),0) -> 0 | AD31: =+IFERROR(VLOOKUP($AD$17,Sheet1!R9:U9,2,0),0) -> 0 | AE31: =+IFERROR(VLOOKUP($AE$17,Sheet1!V9:Y9,3,0),0) -> 0 | AF31: =+IFERROR(VLOOKUP($AF$17,Sheet1!V9:Y9,3,0),0) -> 37 | AG31: =+IFERROR(VLOOKUP($AG$17,Sheet1!V9:Y9,3,0),0) -> 0 | AH31: =+IFERROR(VLOOKUP($AH$17,Sheet1!V9:Y9,3,0),0) -> 0 | AI31: =+IFERROR(VLOOKUP($AI$17,Sheet1!V9:Y9,3,0),0) -> 0 | AJ31: =+IFERROR(VLOOKUP($AJ$17,Sheet1!V9:Y9,3,0),0) -> 0 | AK31: =+IFERROR(VLOOKUP($AK$17,Sheet1!Z9:AB9,3,0),0) -> 0 | AL31: =+IFERROR(VLOOKUP($AL$17,Sheet1!AD9:AG9,3,0),0) -> 0 | AM31: =+IFERROR(VLOOKUP($AM$17,Sheet1!AD9:AG9,3,0),0) -> 0 | AN31: =+IFERROR(VLOOKUP($AN$17,Sheet1!AD9:AG9,3,0),0) -> 0 | AO31: =+IFERROR(VLOOKUP($AO$17,Sheet1!AD9:AG9,3,0),0) -> 0 | AP31: =+IFERROR(VLOOKUP($AP$17,Sheet1!AD9:AG9,3,0),0) -> 0 | AQ31: =+IFERROR(VLOOKUP($AQ$17,Sheet1!AD9:AG9,3,0),0) -> 0 | AR31: =+IFERROR(VLOOKUP($AR$17,Sheet1!AD9:AG9,3,0),0) -> 0 | AS31: =+IFERROR(VLOOKUP($AS$17,Sheet1!AH9:AK9,3,0),0) -> 0 | AT31: =+IFERROR(VLOOKUP($AT$17,Sheet1!AH9:AK9,3,0),0) -> 0 | AU31: =+IFERROR(VLOOKUP($AU$17,Sheet1!AH9:AK9,3,0),0) -> 0 | AV31: =+IFERROR(VLOOKUP($AV$17,Sheet1!AH9:AK9,3,0),0) -> 0 | AW31: =+IFERROR(VLOOKUP($AW$17,Sheet1!AH9:AK9,3,0),0) -> 0 | AX31: =+IFERROR(VLOOKUP($AX$17,Sheet1!AH9:AK9,3,0),0) -> 0 | AY31: =+IFERROR(VLOOKUP($AY$17,Sheet1!AH9:AK9,3,0),0) -> 0 | AZ31: =+IFERROR(VLOOKUP($AZ$17,Sheet1!AH9:AK9,3,0),0) -> 0 | BA31: =+IFERROR(VLOOKUP($BA$17,Sheet1!AH9:AK9,3,0),0) -> 0 | BB31: =+IFERROR(VLOOKUP($BB$17,Sheet1!AH9:AK9,3,0),0) -> 0 | BC31: =+IFERROR(VLOOKUP($BC$17,Sheet1!AL9:AO9,3,0),0) -> 0 | BD31: =+IFERROR(VLOOKUP($BD$17,Sheet1!AL9:AO9,3,0),0) -> 0 | BE31: =+IFERROR(VLOOKUP($BE$17,Sheet1!AL9:AO9,3,0),0) -> 0 | BF31: =+IFERROR(VLOOKUP($BF$17,Sheet1!AL9:AO9,3,0),0) -> 110 | BG31: =+IFERROR(VLOOKUP($BG$17,Sheet1!AL9:AO9,3,0),0) -> 0 | BH31: =+IFERROR(VLOOKUP($BH$17,Sheet1!AL9:AO9,3,0),0) -> 0 | BI31: =+IFERROR(VLOOKUP($BI$17,Sheet1!AL9:AO9,3,0),0) -> 0 | BJ31: =+IFERROR(VLOOKUP($BJ$17,Sheet1!AL9:AO9,3,0),0) -> 0 | BK31: =+IFERROR(VLOOKUP($BK$17,Sheet1!AL9:AO9,3,0),0) -> 0 | BL31: =+IFERROR(VLOOKUP($BL$17,Sheet1!AL9:AO9,3,0),0) -> 0 | BM31: =+IFERROR(VLOOKUP($BM$17,Sheet1!AP9:AS9,3,0),0) -> 0 | BN31: =+IFERROR(VLOOKUP($BN$17,Sheet1!AT9:AW9,3,0),0) -> 0 | BO31: =+IFERROR(VLOOKUP($BO$17,Sheet1!AX9:BA9,3,0),0) -> 0 | BP31: =+IFERROR(VLOOKUP($BP$17,Sheet1!BB9:BE9,3,0),0) -> 0 | BQ31: =+IFERROR(VLOOKUP($BQ$17,Sheet1!BF9:BI9,3,0),0) -> 0 | BR31: =+IFERROR(VLOOKUP($BR$17,Sheet1!BJ9:BM9,3,0),0) -> 0 | BS31: =+IFERROR(VLOOKUP($BS$17,Sheet1!BN9:BQ9,3,0),0) -> 0 | BT31: =+IFERROR(VLOOKUP($BT$17,Sheet1!BR9:BU9,3,0),0) -> 0 | BU31: =+IFERROR(VLOOKUP($BU$17,Sheet1!BV9:BY9,3,0),0) -> 0 | BV31: =Sheet1!E9 -> WOOD | BW31: =Sheet1!CV9 -> MD0100005 | BX31: =Sheet1!CW9 -> DRUM - 36 X 14 X 23 X 2 | BY31: =Sheet1!CX9 -> 1000 | BZ31: =Sheet1!BZ9 -> 2305.4 | CA31: =SUMPRODUCT($N$18:$BU$18,N31:BU31)+BZ31 -> 48335.4 | CB31: =Sheet1!CB9 -> 0 | CC31: =CA31*CB31 -> 0 | CD31: 0.18 | CE31: =CA31*CD31 -> 8700.372 | CF31: 0 | CG31: =CA31*CF31 -> 0 | CH31: =CA31+CC31+CE31+CG31 -> 57035.772 | CI31: 0.02 | CJ31: =CH31*CI31 -> 1140.7154 | CK31: 0.01 | CL31: =CH31*CK31 -> 570.35772 | CM31: 50 | CN31: 15
A32: =Sheet1!A11 -> ENQ-12232-22-23 | B32: 45380 | C32: =Sheet1!C11 -> FA0900117 | D32: =Sheet1!D11 -> 4 CORE X 35 SQ. MM. AL/ARD - WIRE (XLPE) | E32: =CH32+CJ32+CL32 -> 238349.69 | F32: =ROUNDUP(M65,0) -> #DIV/0! | G32: =E32+F32 -> #DIV/0! | H32: =Sheet1!CP11 -> 0.18 | I32: =G32*H32 -> #DIV/0! | J32: =G32+I32 -> #DIV/0! | L32: =Sheet1!CT11 -> KMS | M32: =J32*K32 -> #DIV/0! | N32: 378 | O32: =+IFERROR(VLOOKUP($O$17,Sheet1!J11:L11,3,0),0) -> 0 | P32: =+IFERROR(VLOOKUP($P$17,Sheet1!J11:M11,3,0),0) -> 0 | Q32: =+IFERROR(VLOOKUP($Q$17,Sheet1!J11:M11,3,0),0) -> 0 | R32: =+IFERROR(VLOOKUP($R$17,Sheet1!J11:M11,3,0),0) -> 0 | S32: =+IFERROR(VLOOKUP($S$17,Sheet1!N11:Q11,3,0),0) -> 0 | T32: =+IFERROR(VLOOKUP($T$17,Sheet1!N11:Q11,3,0),0) -> 0 | U32: =+IFERROR(VLOOKUP($U$17,Sheet1!F11:I11,3,0),0) -> 0 | V32: =+IFERROR(VLOOKUP($V$17,Sheet1!F11:I11,3,0),0) -> 0 | W32: =+IFERROR(VLOOKUP($W$17,Sheet1!F11:I11,3,0),0) -> 0 | X32: =+IFERROR(VLOOKUP($X$17,Sheet1!F11:I11,3,0),0) -> 0 | Y32: =+IFERROR(VLOOKUP($Y$17,Sheet1!F11:I11,3,0),0) -> 0 | Z32: =+IFERROR(VLOOKUP($Z$17,Sheet1!F11:I11,3,0),0) -> 0 | AA32: =+IFERROR(VLOOKUP($AA$17,Sheet1!F11:I11,3,0),0) -> 0 | AB32: =+IFERROR(VLOOKUP($AB$17,Sheet1!F11:I11,3,0),0) -> 0 | AC32: =+IFERROR(VLOOKUP($AC$17,Sheet1!R11:U11,3,0),0) -> 0 | AD32: =+IFERROR(VLOOKUP($AD$17,Sheet1!R11:U11,2,0),0) -> 0 | AE32: =+IFERROR(VLOOKUP($AE$17,Sheet1!V11:Y11,3,0),0) -> 0 | AF32: 102 | AG32: =+IFERROR(VLOOKUP($AG$17,Sheet1!V11:Y11,3,0),0) -> 0 | AH32: =+IFERROR(VLOOKUP($AH$17,Sheet1!V11:Y11,3,0),0) -> 0 | AI32: =+IFERROR(VLOOKUP($AI$17,Sheet1!V11:Y11,3,0),0) -> 0 | AJ32: =+IFERROR(VLOOKUP($AJ$17,Sheet1!V11:Y11,3,0),0) -> 0 | AK32: =+IFERROR(VLOOKUP($AK$17,Sheet1!Z11:AB11,3,0),0) -> 0 | AL32: =+IFERROR(VLOOKUP($AL$17,Sheet1!AD11:AG11,3,0),0) -> 0 | AM32: =+IFERROR(VLOOKUP($AM$17,Sheet1!AD11:AG11,3,0),0) -> 0 | AN32: =+IFERROR(VLOOKUP($AN$17,Sheet1!AD11:AG11,3,0),0) -> 0 | AO32: =+IFERROR(VLOOKUP($AO$17,Sheet1!AD11:AG11,3,0),0) -> 0 | AP32: =+IFERROR(VLOOKUP($AP$17,Sheet1!AD11:AG11,3,0),0) -> 0 | AQ32: =+IFERROR(VLOOKUP($AQ$17,Sheet1!AD11:AG11,3,0),0) -> 51 | AR32: =+IFERROR(VLOOKUP($AR$17,Sheet1!AD11:AG11,3,0),0) -> 0 | AS32: =+IFERROR(VLOOKUP($AS$17,Sheet1!AH11:AK11,3,0),0) -> 0 | AT32: =+IFERROR(VLOOKUP($AT$17,Sheet1!AH11:AK11,3,0),0) -> 0 | AU32: =+IFERROR(VLOOKUP($AU$17,Sheet1!AH11:AK11,3,0),0) -> 0 | AV32: =+IFERROR(VLOOKUP($AV$17,Sheet1!AH11:AK11,3,0),0) -> 0 | AW32: =+IFERROR(VLOOKUP($AW$17,Sheet1!AH11:AK11,3,0),0) -> 0 | AX32: =+IFERROR(VLOOKUP($AX$17,Sheet1!AH11:AK11,3,0),0) -> 0 | AY32: =+IFERROR(VLOOKUP($AY$17,Sheet1!AH11:AK11,3,0),0) -> 0 | AZ32: =+IFERROR(VLOOKUP($AZ$17,Sheet1!AH11:AK11,3,0),0) -> 0 | BA32: 770 | BB32: =+IFERROR(VLOOKUP($BB$17,Sheet1!AH11:AK11,3,0),0) -> 0 | BC32: =+IFERROR(VLOOKUP($BC$17,Sheet1!AL11:AO11,3,0),0) -> 0 | BD32: =+IFERROR(VLOOKUP($BD$17,Sheet1!AL11:AO11,3,0),0) -> 0 | BE32: =+IFERROR(VLOOKUP($BE$17,Sheet1!AL11:AO11,3,0),0) -> 0 | BF32: 206 | BG32: =+IFERROR(VLOOKUP($BG$17,Sheet1!AL11:AO11,3,0),0) -> 0 | BH32: =+IFERROR(VLOOKUP($BH$17,Sheet1!AL11:AO11,3,0),0) -> 0 | BI32: =+IFERROR(VLOOKUP($BI$17,Sheet1!AL11:AO11,3,0),0) -> 0 | BJ32: =+IFERROR(VLOOKUP($BJ$17,Sheet1!AL11:AO11,3,0),0) -> 0 | BK32: =+IFERROR(VLOOKUP($BK$17,Sheet1!AL11:AO11,3,0),0) -> 0 | BL32: =+IFERROR(VLOOKUP($BL$17,Sheet1!AL11:AO11,3,0),0) -> 0 | BM32: =+IFERROR(VLOOKUP($BM$17,Sheet1!AP11:AS11,3,0),0) -> 0 | BN32: =+IFERROR(VLOOKUP($BN$17,Sheet1!AT11:AW11,3,0),0) -> 0 | BO32: =+IFERROR(VLOOKUP($BO$17,Sheet1!AX11:BA11,3,0),0) -> 0 | BP32: =+IFERROR(VLOOKUP($BP$17,Sheet1!BB11:BE11,3,0),0) -> 0 | BQ32: =+IFERROR(VLOOKUP($BQ$17,Sheet1!BF11:BI11,3,0),0) -> 0 | BR32: =+IFERROR(VLOOKUP($BR$17,Sheet1!BJ11:BM11,3,0),0) -> 0 | BS32: =+IFERROR(VLOOKUP($BS$17,Sheet1!BN11:BQ11,3,0),0) -> 0 | BT32: 18 | BU32: =+IFERROR(VLOOKUP($BU$17,Sheet1!BV11:BY11,3,0),0) -> 0 | BV32: =Sheet1!E11 -> WOOD | BW32: =Sheet1!CV11 -> MD0100013 | BX32: =Sheet1!CW11 -> DRUM - 48 X 14 X 36 X 2.25 | BY32: =Sheet1!CX11 -> 1000 | BZ32: =Sheet1!BZ11 -> 3743.02 | CA32: =SUMPRODUCT($N$18:$BU$18,N32:BU32)+BZ32 -> 196108.02 | CB32: =Sheet1!CB11 -> 0 | CC32: =CA32*CB32 -> 0 | CD32: 0.18 | CE32: =CA32*CD32 -> 35299.444 | CF32: 0 | CG32: =CA32*CF32 -> 0 | CH32: =CA32+CC32+CE32+CG32 -> 231407.46 | CI32: 0.02 | CJ32: =CH32*CI32 -> 4628.1493 | CK32: 0.01 | CL32: =CH32*CK32 -> 2314.0746 | CM32: 100 | CN32: 25
A33: =Sheet1!A32 -> ENQ-12232-22-23 | B33: 45380 | C33: =Sheet1!C32 -> FA0900041 | D33: =Sheet1!D32 -> 2 CORE X 4 SQ. MM. AL/ARD - WIRE (XLPE) | E33: =CH33+CJ33+CL33 -> 60576.435 | F33: =ROUNDUP(M66,0) -> 969 | G33: =E33+F33 -> 61545.435 | H33: =Sheet1!CP32 -> 0.18 | I33: =G33*H33 -> 11078.178 | J33: =G33+I33 -> 72623.614 | K33: =1731.8+1207.5+16.888 -> 2956.188 | L33: =Sheet1!CT32 -> KMS | M33: =J33*K33 -> 2.1468906e+08 | N33: 22 | O33: =+IFERROR(VLOOKUP($O$17,Sheet1!J32:L32,3,0),0) -> 0 | P33: =+IFERROR(VLOOKUP($P$17,Sheet1!J32:M32,3,0),0) -> 0 | Q33: =+IFERROR(VLOOKUP($Q$17,Sheet1!J32:M32,3,0),0) -> 0 | R33: =+IFERROR(VLOOKUP($R$17,Sheet1!J32:M32,3,0),0) -> 0 | S33: =+IFERROR(VLOOKUP($S$17,Sheet1!N32:Q32,3,0),0) -> 0 | T33: =+IFERROR(VLOOKUP($T$17,Sheet1!N32:Q32,3,0),0) -> 0 | U33: =+IFERROR(VLOOKUP($U$17,Sheet1!F32:I32,3,0),0) -> 0 | V33: =+IFERROR(VLOOKUP($V$17,Sheet1!F32:I32,3,0),0) -> 0 | W33: =+IFERROR(VLOOKUP($W$17,Sheet1!F32:I32,3,0),0) -> 0 | X33: =+IFERROR(VLOOKUP($X$17,Sheet1!F32:I32,3,0),0) -> 0 | Y33: =+IFERROR(VLOOKUP($Y$17,Sheet1!F32:I32,3,0),0) -> 0 | Z33: =+IFERROR(VLOOKUP($Z$17,Sheet1!F32:I32,3,0),0) -> 0 | AA33: =+IFERROR(VLOOKUP($AA$17,Sheet1!F32:I32,3,0),0) -> 0 | AB33: =+IFERROR(VLOOKUP($AB$17,Sheet1!F32:I32,3,0),0) -> 0 | AC33: =+IFERROR(VLOOKUP($AC$17,Sheet1!R32:U32,3,0),0) -> 0 | AD33: =+IFERROR(VLOOKUP($AD$17,Sheet1!R32:U32,2,0),0) -> 0 | AE33: =+IFERROR(VLOOKUP($AE$17,Sheet1!V32:Y32,3,0),0) -> 0 | AF33: 20 | AG33: =+IFERROR(VLOOKUP($AG$17,Sheet1!V32:Y32,3,0),0) -> 0 | AH33: =+IFERROR(VLOOKUP($AH$17,Sheet1!V32:Y32,3,0),0) -> 0 | AI33: =+IFERROR(VLOOKUP($AI$17,Sheet1!V32:Y32,3,0),0) -> 0 | AJ33: =+IFERROR(VLOOKUP($AJ$17,Sheet1!V32:Y32,3,0),0) -> 0 | AK33: =+IFERROR(VLOOKUP($AK$17,Sheet1!Z32:AB32,3,0),0) -> 0 | AL33: =+IFERROR(VLOOKUP($AL$17,Sheet1!AD32:AG32,3,0),0) -> 0 | AM33: =+IFERROR(VLOOKUP($AM$17,Sheet1!AD32:AG32,3,0),0) -> 0 | AN33: =+IFERROR(VLOOKUP($AN$17,Sheet1!AD32:AG32,3,0),0) -> 0 | AO33: =+IFERROR(VLOOKUP($AO$17,Sheet1!AD32:AG32,3,0),0) -> 0 | AP33: =+IFERROR(VLOOKUP($AP$17,Sheet1!AD32:AG32,3,0),0) -> 0 | AQ33: 70 | AR33: =+IFERROR(VLOOKUP($AR$17,Sheet1!AD32:AG32,3,0),0) -> 0 | AS33: =+IFERROR(VLOOKUP($AS$17,Sheet1!AH32:AK32,3,0),0) -> 0 | AT33: =+IFERROR(VLOOKUP($AT$17,Sheet1!AH32:AK32,3,0),0) -> 0 | AU33: =+IFERROR(VLOOKUP($AU$17,Sheet1!AH32:AK32,3,0),0) -> 0 | AV33: =+IFERROR(VLOOKUP($AV$17,Sheet1!AH32:AK32,3,0),0) -> 0 | AW33: =+IFERROR(VLOOKUP($AW$17,Sheet1!AH32:AK32,3,0),0) -> 0 | AX33: =+IFERROR(VLOOKUP($AX$17,Sheet1!AH32:AK32,3,0),0) -> 0 | AY33: =+IFERROR(VLOOKUP($AY$17,Sheet1!AH32:AK32,3,0),0) -> 0 | AZ33: =+IFERROR(VLOOKUP($AZ$17,Sheet1!AH32:AK32,3,0),0) -> 0 | BA33: 252 | BB33: =+IFERROR(VLOOKUP($BB$17,Sheet1!AH32:AK32,3,0),0) -> 0 | BC33: =+IFERROR(VLOOKUP($BC$17,Sheet1!AL32:AO32,3,0),0) -> 0 | BD33: =+IFERROR(VLOOKUP($BD$17,Sheet1!AL32:AO32,3,0),0) -> 0 | BE33: =+IFERROR(VLOOKUP($BE$17,Sheet1!AL32:AO32,3,0),0) -> 0 | BF33: 103 | BG33: =+IFERROR(VLOOKUP($BG$17,Sheet1!AL32:AO32,3,0),0) -> 0 | BH33: =+IFERROR(VLOOKUP($BH$17,Sheet1!AL32:AO32,3,0),0) -> 0 | BI33: =+IFERROR(VLOOKUP($BI$17,Sheet1!AL32:AO32,3,0),0) -> 0 | BJ33: =+IFERROR(VLOOKUP($BJ$17,Sheet1!AL32:AO32,3,0),0) -> 0 | BK33: =+IFERROR(VLOOKUP($BK$17,Sheet1!AL32:AO32,3,0),0) -> 0 | BL33: =+IFERROR(VLOOKUP($BL$17,Sheet1!AL32:AO32,3,0),0) -> 0 | BM33: =+IFERROR(VLOOKUP($BM$17,Sheet1!AP32:AS32,3,0),0) -> 0 | BN33: =+IFERROR(VLOOKUP($BN$17,Sheet1!AT32:AW32,3,0),0) -> 0 | BO33: =+IFERROR(VLOOKUP($BO$17,Sheet1!AX32:BA32,3,0),0) -> 0 | BP33: =+IFERROR(VLOOKUP($BP$17,Sheet1!BB32:BE32,3,0),0) -> 0 | BQ33: =+IFERROR(VLOOKUP($BQ$17,Sheet1!BF32:BI32,3,0),0) -> 0 | BR33: =+IFERROR(VLOOKUP($BR$17,Sheet1!BJ32:BM32,3,0),0) -> 0 | BS33: =+IFERROR(VLOOKUP($BS$17,Sheet1!BN32:BQ32,3,0),0) -> 0 | BT33: 10 | BU33: =+IFERROR(VLOOKUP($BU$17,Sheet1!BV32:BY32,3,0),0) -> 0 | BV33: =Sheet1!E32 -> WOOD | BW33: =Sheet1!CV32 -> MD0100066 | BX33: =Sheet1!CW32 -> DRUM - 40 X 15 X 23 X 2 | BY33: =Sheet1!CX32 -> 1000 | BZ33: =Sheet1!BZ32 -> 2575.74 | CA33: =SUMPRODUCT($N$18:$BU$18,N33:BU33)+BZ33 -> 49840.74 | CB33: =Sheet1!CB32 -> 0 | CC33: =CA33*CB33 -> 0 | CD33: 0.18 | CE33: =CA33*CD33 -> 8971.3332 | CF33: 0 | CG33: =CA33*CF33 -> 0 | CH33: =CA33+CC33+CE33+CG33 -> 58812.073 | CI33: 0.02 | CJ33: =CH33*CI33 -> 1176.2415 | CK33: 0.01 | CL33: =CH33*CK33 -> 588.12073 | CM33: 55 | CN33: 20
A34: =Sheet1!A31 -> ENQ-12232-22-23 | B34: 45380 | C34: =Sheet1!C31 -> FA0900020 | D34: =Sheet1!D31 -> 2 CORE X 6 SQ. MM. AL/ARD - WIRE (XLPE) | E34: =CH34+CJ34+CL34 -> 70266.82 | F34: =ROUNDUP(M67,0) -> 1072 | G34: =E34+F34 -> 71338.82 | H34: =Sheet1!CP31 -> 0.18 | I34: =G34*H34 -> 12840.988 | J34: =G34+I34 -> 84179.807 | K34: =630 -> 630 | L34: =Sheet1!CT31 -> KMS | M34: =J34*K34 -> 53033278 | N34: 33 | O34: =+IFERROR(VLOOKUP($O$17,Sheet1!J31:L31,3,0),0) -> 0 | P34: =+IFERROR(VLOOKUP($P$17,Sheet1!J31:M31,3,0),0) -> 0 | Q34: =+IFERROR(VLOOKUP($Q$17,Sheet1!J31:M31,3,0),0) -> 0 | R34: =+IFERROR(VLOOKUP($R$17,Sheet1!J31:M31,3,0),0) -> 0 | S34: =+IFERROR(VLOOKUP($S$17,Sheet1!N31:Q31,3,0),0) -> 0 | T34: =+IFERROR(VLOOKUP($T$17,Sheet1!N31:Q31,3,0),0) -> 0 | U34: =+IFERROR(VLOOKUP($U$17,Sheet1!F31:I31,3,0),0) -> 0 | V34: =+IFERROR(VLOOKUP($V$17,Sheet1!F31:I31,3,0),0) -> 0 | W34: =+IFERROR(VLOOKUP($W$17,Sheet1!F31:I31,3,0),0) -> 0 | X34: =+IFERROR(VLOOKUP($X$17,Sheet1!F31:I31,3,0),0) -> 0 | Y34: =+IFERROR(VLOOKUP($Y$17,Sheet1!F31:I31,3,0),0) -> 0 | Z34: =+IFERROR(VLOOKUP($Z$17,Sheet1!F31:I31,3,0),0) -> 0 | AA34: =+IFERROR(VLOOKUP($AA$17,Sheet1!F31:I31,3,0),0) -> 0 | AB34: =+IFERROR(VLOOKUP($AB$17,Sheet1!F31:I31,3,0),0) -> 0 | AC34: =+IFERROR(VLOOKUP($AC$17,Sheet1!R31:U31,3,0),0) -> 0 | AD34: =+IFERROR(VLOOKUP($AD$17,Sheet1!R31:U31,2,0),0) -> 0 | AE34: =+IFERROR(VLOOKUP($AE$17,Sheet1!V31:Y31,3,0),0) -> 0 | AF34: 23 | AG34: =+IFERROR(VLOOKUP($AG$17,Sheet1!V31:Y31,3,0),0) -> 0 | AH34: =+IFERROR(VLOOKUP($AH$17,Sheet1!V31:Y31,3,0),0) -> 0 | AI34: =+IFERROR(VLOOKUP($AI$17,Sheet1!V31:Y31,3,0),0) -> 0 | AJ34: =+IFERROR(VLOOKUP($AJ$17,Sheet1!V31:Y31,3,0),0) -> 0 | AK34: =+IFERROR(VLOOKUP($AK$17,Sheet1!Z31:AB31,3,0),0) -> 0 | AL34: =+IFERROR(VLOOKUP($AL$17,Sheet1!AD31:AG31,3,0),0) -> 0 | AM34: =+IFERROR(VLOOKUP($AM$17,Sheet1!AD31:AG31,3,0),0) -> 0 | AN34: =+IFERROR(VLOOKUP($AN$17,Sheet1!AD31:AG31,3,0),0) -> 0 | AO34: =+IFERROR(VLOOKUP($AO$17,Sheet1!AD31:AG31,3,0),0) -> 0 | AP34: =+IFERROR(VLOOKUP($AP$17,Sheet1!AD31:AG31,3,0),0) -> 0 | AQ34: =+IFERROR(VLOOKUP($AQ$17,Sheet1!AD31:AG31,3,0),0) -> 0 | AR34: 78 | AS34: =+IFERROR(VLOOKUP($AS$17,Sheet1!AH31:AK31,3,0),0) -> 0 | AT34: =+IFERROR(VLOOKUP($AT$17,Sheet1!AH31:AK31,3,0),0) -> 0 | AU34: =+IFERROR(VLOOKUP($AU$17,Sheet1!AH31:AK31,3,0),0) -> 0 | AV34: =+IFERROR(VLOOKUP($AV$17,Sheet1!AH31:AK31,3,0),0) -> 0 | AW34: =+IFERROR(VLOOKUP($AW$17,Sheet1!AH31:AK31,3,0),0) -> 0 | AX34: =+IFERROR(VLOOKUP($AX$17,Sheet1!AH31:AK31,3,0),0) -> 0 | AY34: =+IFERROR(VLOOKUP($AY$17,Sheet1!AH31:AK31,3,0),0) -> 0 | AZ34: =+IFERROR(VLOOKUP($AZ$17,Sheet1!AH31:AK31,3,0),0) -> 0 | BA34: 276 | BB34: =+IFERROR(VLOOKUP($BB$17,Sheet1!AH31:AK31,3,0),0) -> 0 | BC34: =+IFERROR(VLOOKUP($BC$17,Sheet1!AL31:AO31,3,0),0) -> 0 | BD34: =+IFERROR(VLOOKUP($BD$17,Sheet1!AL31:AO31,3,0),0) -> 0 | BE34: =+IFERROR(VLOOKUP($BE$17,Sheet1!AL31:AO31,3,0),0) -> 0 | BF34: 108 | BG34: =+IFERROR(VLOOKUP($BG$17,Sheet1!AL31:AO31,3,0),0) -> 0 | BH34: =+IFERROR(VLOOKUP($BH$17,Sheet1!AL31:AO31,3,0),0) -> 0 | BI34: =+IFERROR(VLOOKUP($BI$17,Sheet1!AL31:AO31,3,0),0) -> 0 | BJ34: =+IFERROR(VLOOKUP($BJ$17,Sheet1!AL31:AO31,3,0),0) -> 0 | BK34: =+IFERROR(VLOOKUP($BK$17,Sheet1!AL31:AO31,3,0),0) -> 0 | BL34: =+IFERROR(VLOOKUP($BL$17,Sheet1!AL31:AO31,3,0),0) -> 0 | BM34: =+IFERROR(VLOOKUP($BM$17,Sheet1!AP31:AS31,3,0),0) -> 0 | BN34: =+IFERROR(VLOOKUP($BN$17,Sheet1!AT31:AW31,3,0),0) -> 0 | BO34: =+IFERROR(VLOOKUP($BO$17,Sheet1!AX31:BA31,3,0),0) -> 0 | BP34: =+IFERROR(VLOOKUP($BP$17,Sheet1!BB31:BE31,3,0),0) -> 0 | BQ34: =+IFERROR(VLOOKUP($BQ$17,Sheet1!BF31:BI31,3,0),0) -> 0 | BR34: =+IFERROR(VLOOKUP($BR$17,Sheet1!BJ31:BM31,3,0),0) -> 0 | BS34: =+IFERROR(VLOOKUP($BS$17,Sheet1!BN31:BQ31,3,0),0) -> 0 | BT34: 10 | BU34: =+IFERROR(VLOOKUP($BU$17,Sheet1!BV31:BY31,3,0),0) -> 0 | BV34: =Sheet1!E31 -> WOOD | BW34: =Sheet1!CV31 -> MD0100066 | BX34: =Sheet1!CW31 -> DRUM - 40 X 15 X 23 X 2 | BY34: =Sheet1!CX31 -> 1000 | BZ34: =Sheet1!BZ31 -> 2575.74 | CA34: =SUMPRODUCT($N$18:$BU$18,N34:BU34)+BZ34 -> 57813.74 | CB34: =Sheet1!CB31 -> 0 | CC34: =CA34*CB34 -> 0 | CD34: 0.18 | CE34: =CA34*CD34 -> 10406.473 | CF34: 0 | CG34: =CA34*CF34 -> 0 | CH34: =CA34+CC34+CE34+CG34 -> 68220.213 | CI34: 0.02 | CJ34: =CH34*CI34 -> 1364.4043 | CK34: 0.01 | CL34: =CH34*CK34 -> 682.20213 | CM34: 55 | CN34: 20
A35: =Sheet1!A26 -> ENQ-12232-22-23 | B35: 45380 | C35: =Sheet1!C26 -> FA0900042 | D35: =Sheet1!D26 -> 2 CORE X 10 SQ. MM. ALU/ARD - WIRE (XLPE) | E35: =CH35+CJ35+CL35 -> 91204.868 | F35: =ROUNDUP(M68,0) -> 1696 | G35: =E35+F35 -> 92900.868 | H35: =Sheet1!CP26 -> 0.18 | I35: =G35*H35 -> 16722.156 | J35: =G35+I35 -> 109623.02 | K35: =15.9+35+12.813 -> 63.713 | L35: =Sheet1!CT26 -> KMS | M35: =J35*K35 -> 6984411.7 | N35: =+IFERROR(VLOOKUP($N$17,Sheet1!J26:L26,3,0),0) -> 54 | O35: =+IFERROR(VLOOKUP($O$17,Sheet1!J26:L26,3,0),0) -> 0 | P35: =+IFERROR(VLOOKUP($P$17,Sheet1!J26:M26,3,0),0) -> 0 | Q35: =+IFERROR(VLOOKUP($Q$17,Sheet1!J26:M26,3,0),0) -> 0 | R35: =+IFERROR(VLOOKUP($R$17,Sheet1!J26:M26,3,0),0) -> 0 | S35: =+IFERROR(VLOOKUP($S$17,Sheet1!N26:Q26,3,0),0) -> 0 | T35: =+IFERROR(VLOOKUP($T$17,Sheet1!N26:Q26,3,0),0) -> 0 | U35: =+IFERROR(VLOOKUP($U$17,Sheet1!F26:I26,3,0),0) -> 0 | V35: =+IFERROR(VLOOKUP($V$17,Sheet1!F26:I26,3,0),0) -> 0 | W35: =+IFERROR(VLOOKUP($W$17,Sheet1!F26:I26,3,0),0) -> 0 | X35: =+IFERROR(VLOOKUP($X$17,Sheet1!F26:I26,3,0),0) -> 0 | Y35: =+IFERROR(VLOOKUP($Y$17,Sheet1!F26:I26,3,0),0) -> 0 | Z35: =+IFERROR(VLOOKUP($Z$17,Sheet1!F26:I26,3,0),0) -> 0 | AA35: =+IFERROR(VLOOKUP($AA$17,Sheet1!F26:I26,3,0),0) -> 0 | AB35: =+IFERROR(VLOOKUP($AB$17,Sheet1!F26:I26,3,0),0) -> 0 | AC35: =+IFERROR(VLOOKUP($AC$17,Sheet1!R26:U26,3,0),0) -> 0 | AD35: =+IFERROR(VLOOKUP($AD$17,Sheet1!R26:U26,2,0),0) -> 0 | AE35: =+IFERROR(VLOOKUP($AE$17,Sheet1!V26:Y26,3,0),0) -> 0 | AF35: 25 | AG35: =+IFERROR(VLOOKUP($AG$17,Sheet1!V26:Y26,3,0),0) -> 0 | AH35: =+IFERROR(VLOOKUP($AH$17,Sheet1!V26:Y26,3,0),0) -> 0 | AI35: =+IFERROR(VLOOKUP($AI$17,Sheet1!V26:Y26,3,0),0) -> 0 | AJ35: =+IFERROR(VLOOKUP($AJ$17,Sheet1!V26:Y26,3,0),0) -> 0 | AK35: =+IFERROR(VLOOKUP($AK$17,Sheet1!Z26:AB26,3,0),0) -> 0 | AL35: =+IFERROR(VLOOKUP($AL$17,Sheet1!AD26:AG26,3,0),0) -> 0 | AM35: =+IFERROR(VLOOKUP($AM$17,Sheet1!AD26:AG26,3,0),0) -> 0 | AN35: =+IFERROR(VLOOKUP($AN$17,Sheet1!AD26:AG26,3,0),0) -> 0 | AO35: =+IFERROR(VLOOKUP($AO$17,Sheet1!AD26:AG26,3,0),0) -> 0 | AP35: =+IFERROR(VLOOKUP($AP$17,Sheet1!AD26:AG26,3,0),0) -> 0 | AQ35: =+IFERROR(VLOOKUP($AQ$17,Sheet1!AD26:AG26,3,0),0) -> 0 | AR35: 103 | AS35: =+IFERROR(VLOOKUP($AS$17,Sheet1!AH26:AK26,3,0),0) -> 0 | AT35: =+IFERROR(VLOOKUP($AT$17,Sheet1!AH26:AK26,3,0),0) -> 0 | AU35: =+IFERROR(VLOOKUP($AU$17,Sheet1!AH26:AK26,3,0),0) -> 0 | AV35: =+IFERROR(VLOOKUP($AV$17,Sheet1!AH26:AK26,3,0),0) -> 0 | AW35: =+IFERROR(VLOOKUP($AW$17,Sheet1!AH26:AK26,3,0),0) -> 0 | AX35: =+IFERROR(VLOOKUP($AX$17,Sheet1!AH26:AK26,3,0),0) -> 0 | AY35: =+IFERROR(VLOOKUP($AY$17,Sheet1!AH26:AK26,3,0),0) -> 0 | AZ35: =+IFERROR(VLOOKUP($AZ$17,Sheet1!AH26:AK26,3,0),0) -> 0 | BA35: =+IFERROR(VLOOKUP($BA$17,Sheet1!AH26:AK26,3,0),0) -> 360 | BB35: =+IFERROR(VLOOKUP($BB$17,Sheet1!AH26:AK26,3,0),0) -> 0 | BC35: =+IFERROR(VLOOKUP($BC$17,Sheet1!AL26:AO26,3,0),0) -> 0 | BD35: =+IFERROR(VLOOKUP($BD$17,Sheet1!AL26:AO26,3,0),0) -> 0 | BE35: =+IFERROR(VLOOKUP($BE$17,Sheet1!AL26:AO26,3,0),0) -> 0 | BF35: 120 | BG35: =+IFERROR(VLOOKUP($BG$17,Sheet1!AL26:AO26,3,0),0) -> 0 | BH35: =+IFERROR(VLOOKUP($BH$17,Sheet1!AL26:AO26,3,0),0) -> 0 | BI35: =+IFERROR(VLOOKUP($BI$17,Sheet1!AL26:AO26,3,0),0) -> 0 | BJ35: =+IFERROR(VLOOKUP($BJ$17,Sheet1!AL26:AO26,3,0),0) -> 0 | BK35: =+IFERROR(VLOOKUP($BK$17,Sheet1!AL26:AO26,3,0),0) -> 0 | BL35: =+IFERROR(VLOOKUP($BL$17,Sheet1!AL26:AO26,3,0),0) -> 0 | BM35: =+IFERROR(VLOOKUP($BM$17,Sheet1!AP26:AS26,3,0),0) -> 0 | BN35: =+IFERROR(VLOOKUP($BN$17,Sheet1!AT26:AW26,3,0),0) -> 0 | BO35: =+IFERROR(VLOOKUP($BO$17,Sheet1!AX26:BA26,3,0),0) -> 0 | BP35: =+IFERROR(VLOOKUP($BP$17,Sheet1!BB26:BE26,3,0),0) -> 0 | BQ35: =+IFERROR(VLOOKUP($BQ$17,Sheet1!BF26:BI26,3,0),0) -> 0 | BR35: =+IFERROR(VLOOKUP($BR$17,Sheet1!BJ26:BM26,3,0),0) -> 0 | BS35: =+IFERROR(VLOOKUP($BS$17,Sheet1!BN26:BQ26,3,0),0) -> 0 | BT35: 12 | BU35: =+IFERROR(VLOOKUP($BU$17,Sheet1!BV26:BY26,3,0),0) -> 0 | BV35: =Sheet1!E26 -> WOOD | BW35: =Sheet1!CV26 -> MD0100075 | BX35: =Sheet1!CW26 -> DRUM - 42 X 15 X 23 X 2 | BY35: =Sheet1!CX26 -> 1000 | BZ35: =Sheet1!BZ26 -> 3542.03 | CA35: =SUMPRODUCT($N$18:$BU$18,N35:BU35)+BZ35 -> 75041.03 | CB35: =Sheet1!CB26 -> 0 | CC35: =CA35*CB35 -> 0 | CD35: 0.18 | CE35: =CA35*CD35 -> 13507.385 | CF35: 0 | CG35: =CA35*CF35 -> 0 | CH35: =CA35+CC35+CE35+CG35 -> 88548.415 | CI35: 0.02 | CJ35: =CH35*CI35 -> 1770.9683 | CK35: 0.01 | CL35: =CH35*CK35 -> 885.48415 | CM35: 55 | CN35: 20
A36: =Sheet1!A29 -> ENQ-12232-22-23 | B36: 45380 | C36: =Sheet1!C29 -> FA0900112 | D36: =Sheet1!D29 -> 4 CORE X 10 SQ. MM. AL/ARD - WIRE (XLPE) | E36: =CH36+CJ36+CL36 -> 107877.54 | F36: =ROUNDUP(M69,0) -> 1594 | G36: =E36+F36 -> 109471.54 | H36: =Sheet1!CP29 -> 0.18 | I36: =G36*H36 -> 19704.878 | J36: =G36+I36 -> 129176.42 | K36: =17.9+119+15.626 -> 152.526 | L36: =Sheet1!CT29 -> KMS | M36: =J36*K36 -> 19702763 | N36: 108 | O36: =+IFERROR(VLOOKUP($O$17,Sheet1!J29:L29,3,0),0) -> 0 | P36: =+IFERROR(VLOOKUP($P$17,Sheet1!J29:M29,3,0),0) -> 0 | Q36: =+IFERROR(VLOOKUP($Q$17,Sheet1!J29:M29,3,0),0) -> 0 | R36: =+IFERROR(VLOOKUP($R$17,Sheet1!J29:M29,3,0),0) -> 0 | S36: =+IFERROR(VLOOKUP($S$17,Sheet1!N29:Q29,3,0),0) -> 0 | T36: =+IFERROR(VLOOKUP($T$17,Sheet1!N29:Q29,3,0),0) -> 0 | U36: =+IFERROR(VLOOKUP($U$17,Sheet1!F29:I29,3,0),0) -> 0 | V36: =+IFERROR(VLOOKUP($V$17,Sheet1!F29:I29,3,0),0) -> 0 | W36: =+IFERROR(VLOOKUP($W$17,Sheet1!F29:I29,3,0),0) -> 0 | X36: =+IFERROR(VLOOKUP($X$17,Sheet1!F29:I29,3,0),0) -> 0 | Y36: =+IFERROR(VLOOKUP($Y$17,Sheet1!F29:I29,3,0),0) -> 0 | Z36: =+IFERROR(VLOOKUP($Z$17,Sheet1!F29:I29,3,0),0) -> 0 | AA36: =+IFERROR(VLOOKUP($AA$17,Sheet1!F29:I29,3,0),0) -> 0 | AB36: =+IFERROR(VLOOKUP($AB$17,Sheet1!F29:I29,3,0),0) -> 0 | AC36: =+IFERROR(VLOOKUP($AC$17,Sheet1!R29:U29,3,0),0) -> 0 | AD36: =+IFERROR(VLOOKUP($AD$17,Sheet1!R29:U29,2,0),0) -> 0 | AE36: =+IFERROR(VLOOKUP($AE$17,Sheet1!V29:Y29,3,0),0) -> 0 | AF36: 50 | AG36: =+IFERROR(VLOOKUP($AG$17,Sheet1!V29:Y29,3,0),0) -> 0 | AH36: =+IFERROR(VLOOKUP($AH$17,Sheet1!V29:Y29,3,0),0) -> 0 | AI36: =+IFERROR(VLOOKUP($AI$17,Sheet1!V29:Y29,3,0),0) -> 0 | AJ36: =+IFERROR(VLOOKUP($AJ$17,Sheet1!V29:Y29,3,0),0) -> 0 | AK36: =+IFERROR(VLOOKUP($AK$17,Sheet1!Z29:AB29,3,0),0) -> 0 | AL36: =+IFERROR(VLOOKUP($AL$17,Sheet1!AD29:AG29,3,0),0) -> 0 | AM36: =+IFERROR(VLOOKUP($AM$17,Sheet1!AD29:AG29,3,0),0) -> 0 | AN36: =+IFERROR(VLOOKUP($AN$17,Sheet1!AD29:AG29,3,0),0) -> 0 | AO36: =+IFERROR(VLOOKUP($AO$17,Sheet1!AD29:AG29,3,0),0) -> 0 | AP36: =+IFERROR(VLOOKUP($AP$17,Sheet1!AD29:AG29,3,0),0) -> 0 | AQ36: =+IFERROR(VLOOKUP($AQ$17,Sheet1!AD29:AG29,3,0),0) -> 35 | AR36: =+IFERROR(VLOOKUP($AR$17,Sheet1!AD29:AG29,3,0),0) -> 0 | AS36: =+IFERROR(VLOOKUP($AS$17,Sheet1!AH29:AK29,3,0),0) -> 0 | AT36: =+IFERROR(VLOOKUP($AT$17,Sheet1!AH29:AK29,3,0),0) -> 0 | AU36: =+IFERROR(VLOOKUP($AU$17,Sheet1!AH29:AK29,3,0),0) -> 0 | AV36: =+IFERROR(VLOOKUP($AV$17,Sheet1!AH29:AK29,3,0),0) -> 0 | AW36: =+IFERROR(VLOOKUP($AW$17,Sheet1!AH29:AK29,3,0),0) -> 0 | AX36: =+IFERROR(VLOOKUP($AX$17,Sheet1!AH29:AK29,3,0),0) -> 0 | AY36: =+IFERROR(VLOOKUP($AY$17,Sheet1!AH29:AK29,3,0),0) -> 0 | AZ36: =+IFERROR(VLOOKUP($AZ$17,Sheet1!AH29:AK29,3,0),0) -> 0 | BA36: 377 | BB36: =+IFERROR(VLOOKUP($BB$17,Sheet1!AH29:AK29,3,0),0) -> 0 | BC36: =+IFERROR(VLOOKUP($BC$17,Sheet1!AL29:AO29,3,0),0) -> 0 | BD36: =+IFERROR(VLOOKUP($BD$17,Sheet1!AL29:AO29,3,0),0) -> 0 | BE36: =+IFERROR(VLOOKUP($BE$17,Sheet1!AL29:AO29,3,0),0) -> 0 | BF36: =+IFERROR(VLOOKUP($BF$17,Sheet1!AL29:AO29,3,0),0) -> 151 | BG36: =+IFERROR(VLOOKUP($BG$17,Sheet1!AL29:AO29,3,0),0) -> 0 | BH36: =+IFERROR(VLOOKUP($BH$17,Sheet1!AL29:AO29,3,0),0) -> 0 | BI36: =+IFERROR(VLOOKUP($BI$17,Sheet1!AL29:AO29,3,0),0) -> 0 | BJ36: =+IFERROR(VLOOKUP($BJ$17,Sheet1!AL29:AO29,3,0),0) -> 0 | BK36: =+IFERROR(VLOOKUP($BK$17,Sheet1!AL29:AO29,3,0),0) -> 0 | BL36: =+IFERROR(VLOOKUP($BL$17,Sheet1!AL29:AO29,3,0),0) -> 0 | BM36: =+IFERROR(VLOOKUP($BM$17,Sheet1!AP29:AS29,3,0),0) -> 0 | BN36: =+IFERROR(VLOOKUP($BN$17,Sheet1!AT29:AW29,3,0),0) -> 0 | BO36: =+IFERROR(VLOOKUP($BO$17,Sheet1!AX29:BA29,3,0),0) -> 0 | BP36: =+IFERROR(VLOOKUP($BP$17,Sheet1!BB29:BE29,3,0),0) -> 0 | BQ36: =+IFERROR(VLOOKUP($BQ$17,Sheet1!BF29:BI29,3,0),0) -> 0 | BR36: =+IFERROR(VLOOKUP($BR$17,Sheet1!BJ29:BM29,3,0),0) -> 0 | BS36: =+IFERROR(VLOOKUP($BS$17,Sheet1!BN29:BQ29,3,0),0) -> 0 | BT36: 13.5 | BU36: =+IFERROR(VLOOKUP($BU$17,Sheet1!BV29:BY29,3,0),0) -> 0 | BV36: =Sheet1!E29 -> WOOD | BW36: =Sheet1!CV29 -> MD0100064 | BX36: =Sheet1!CW29 -> DRUM - 42 X 15 X 32 X 2 | BY36: =Sheet1!CX29 -> 1000 | BZ36: =Sheet1!BZ29 -> 4155.88 | CA36: =SUMPRODUCT($N$18:$BU$18,N36:BU36)+BZ36 -> 88758.88 | CB36: =Sheet1!CB29 -> 0 | CC36: =CA36*CB36 -> 0 | CD36: 0.18 | CE36: =CA36*CD36 -> 15976.598 | CF36: 0 | CG36: =CA36*CF36 -> 0 | CH36: =CA36+CC36+CE36+CG36 -> 104735.48 | CI36: 0.02 | CJ36: =CH36*CI36 -> 2094.7096 | CK36: 0.01 | CL36: =CH36*CK36 -> 1047.3548 | CM36: 55 | CN36: 20
A37: =Sheet1!A17 -> ENQ-12232-22-23 | B37: 45380 | C37: =Sheet1!C17 -> FA0300011 | D37: =Sheet1!D17 -> 10 CORE X 2.5 SQ. MM. CU/UNARD. (PVC) | E37: =CH37+CJ37+CL37 -> 258268.22 | F37: =ROUNDUP(M70,0) -> #DIV/0! | G37: =E37+F37 -> #DIV/0! | H37: =Sheet1!CP17 -> 0.18 | I37: =G37*H37 -> #DIV/0! | J37: =G37+I37 -> #DIV/0! | L37: =Sheet1!CT17 -> KMS | M37: =J37*K37 -> #DIV/0! | N37: =+IFERROR(VLOOKUP($N$17,Sheet1!J17:L17,3,0),0) -> 0 | O37: =+IFERROR(VLOOKUP($O$17,Sheet1!J17:L17,3,0),0) -> 0 | P37: =+IFERROR(VLOOKUP($P$17,Sheet1!J17:M17,3,0),0) -> 222 | Q37: =+IFERROR(VLOOKUP($Q$17,Sheet1!J17:M17,3,0),0) -> 0 | R37: =+IFERROR(VLOOKUP($R$17,Sheet1!J17:M17,3,0),0) -> 0 | S37: =+IFERROR(VLOOKUP($S$17,Sheet1!N17:Q17,3,0),0) -> 0 | T37: =+IFERROR(VLOOKUP($T$17,Sheet1!N17:Q17,3,0),0) -> 0 | U37: =+IFERROR(VLOOKUP($U$17,Sheet1!F17:I17,3,0),0) -> 0 | V37: =+IFERROR(VLOOKUP($V$17,Sheet1!F17:I17,3,0),0) -> 0 | W37: =+IFERROR(VLOOKUP($W$17,Sheet1!F17:I17,3,0),0) -> 0 | X37: =+IFERROR(VLOOKUP($X$17,Sheet1!F17:I17,3,0),0) -> 0 | Y37: =+IFERROR(VLOOKUP($Y$17,Sheet1!F17:I17,3,0),0) -> 0 | Z37: =+IFERROR(VLOOKUP($Z$17,Sheet1!F17:I17,3,0),0) -> 0 | AA37: =+IFERROR(VLOOKUP($AA$17,Sheet1!F17:I17,3,0),0) -> 0 | AB37: =+IFERROR(VLOOKUP($AB$17,Sheet1!F17:I17,3,0),0) -> 0 | AC37: =+IFERROR(VLOOKUP($AC$17,Sheet1!R17:U17,3,0),0) -> 0 | AD37: =+IFERROR(VLOOKUP($AD$17,Sheet1!R17:U17,2,0),0) -> 0 | AE37: =+IFERROR(VLOOKUP($AE$17,Sheet1!V17:Y17,3,0),0) -> 0 | AF37: =+IFERROR(VLOOKUP($AF$17,Sheet1!V17:Y17,3,0),0) -> 0 | AG37: =+IFERROR(VLOOKUP($AG$17,Sheet1!V17:Y17,3,0),0) -> 0 | AH37: =+IFERROR(VLOOKUP($AH$17,Sheet1!V17:Y17,3,0),0) -> 0 | AI37: =+IFERROR(VLOOKUP($AI$17,Sheet1!V17:Y17,3,0),0) -> 130 | AJ37: =+IFERROR(VLOOKUP($AJ$17,Sheet1!V17:Y17,3,0),0) -> 0 | AK37: =+IFERROR(VLOOKUP($AK$17,Sheet1!Z17:AB17,3,0),0) -> 5 | AL37: =+IFERROR(VLOOKUP($AL$17,Sheet1!AD17:AG17,3,0),0) -> 0 | AM37: =+IFERROR(VLOOKUP($AM$17,Sheet1!AD17:AG17,3,0),0) -> 0 | AN37: =+IFERROR(VLOOKUP($AN$17,Sheet1!AD17:AG17,3,0),0) -> 0 | AO37: =+IFERROR(VLOOKUP($AO$17,Sheet1!AD17:AG17,3,0),0) -> 0 | AP37: =+IFERROR(VLOOKUP($AP$17,Sheet1!AD17:AG17,3,0),0) -> 0 | AQ37: =+IFERROR(VLOOKUP($AQ$17,Sheet1!AD17:AG17,3,0),0) -> 36 | AR37: =+IFERROR(VLOOKUP($AR$17,Sheet1!AD17:AG17,3,0),0) -> 0 | AS37: =+IFERROR(VLOOKUP($AS$17,Sheet1!AH17:AK17,3,0),0) -> 0 | AT37: =+IFERROR(VLOOKUP($AT$17,Sheet1!AH17:AK17,3,0),0) -> 0 | AU37: =+IFERROR(VLOOKUP($AU$17,Sheet1!AH17:AK17,3,0),0) -> 0 | AV37: =+IFERROR(VLOOKUP($AV$17,Sheet1!AH17:AK17,3,0),0) -> 0 | AW37: =+IFERROR(VLOOKUP($AW$17,Sheet1!AH17:AK17,3,0),0) -> 0 | AX37: =+IFERROR(VLOOKUP($AX$17,Sheet1!AH17:AK17,3,0),0) -> 0 | AY37: =+IFERROR(VLOOKUP($AY$17,Sheet1!AH17:AK17,3,0),0) -> 0 | AZ37: =+IFERROR(VLOOKUP($AZ$17,Sheet1!AH17:AK17,3,0),0) -> 0 | BA37: =+IFERROR(VLOOKUP($BA$17,Sheet1!AH17:AK17,3,0),0) -> 0 | BB37: =+IFERROR(VLOOKUP($BB$17,Sheet1!AH17:AK17,3,0),0) -> 0 | BC37: =+IFERROR(VLOOKUP($BC$17,Sheet1!AL17:AO17,3,0),0) -> 0 | BD37: =+IFERROR(VLOOKUP($BD$17,Sheet1!AL17:AO17,3,0),0) -> 0 | BE37: =+IFERROR(VLOOKUP($BE$17,Sheet1!AL17:AO17,3,0),0) -> 0 | BF37: =+IFERROR(VLOOKUP($BF$17,Sheet1!AL17:AO17,3,0),0) -> 165 | BG37: =+IFERROR(VLOOKUP($BG$17,Sheet1!AL17:AO17,3,0),0) -> 0 | BH37: =+IFERROR(VLOOKUP($BH$17,Sheet1!AL17:AO17,3,0),0) -> 0 | BI37: =+IFERROR(VLOOKUP($BI$17,Sheet1!AL17:AO17,3,0),0) -> 0 | BJ37: =+IFERROR(VLOOKUP($BJ$17,Sheet1!AL17:AO17,3,0),0) -> 0 | BK37: =+IFERROR(VLOOKUP($BK$17,Sheet1!AL17:AO17,3,0),0) -> 0 | BL37: =+IFERROR(VLOOKUP($BL$17,Sheet1!AL17:AO17,3,0),0) -> 0 | BM37: =+IFERROR(VLOOKUP($BM$17,Sheet1!AP17:AS17,3,0),0) -> 0 | BN37: =+IFERROR(VLOOKUP($BN$17,Sheet1!AT17:AW17,3,0),0) -> 0 | BO37: =+IFERROR(VLOOKUP($BO$17,Sheet1!AX17:BA17,3,0),0) -> 0 | BP37: =+IFERROR(VLOOKUP($BP$17,Sheet1!BB17:BE17,3,0),0) -> 0 | BQ37: =+IFERROR(VLOOKUP($BQ$17,Sheet1!BF17:BI17,3,0),0) -> 0 | BR37: =+IFERROR(VLOOKUP($BR$17,Sheet1!BJ17:BM17,3,0),0) -> 0 | BS37: =+IFERROR(VLOOKUP($BS$17,Sheet1!BN17:BQ17,3,0),0) -> 0 | BT37: =+IFERROR(VLOOKUP($BT$17,Sheet1!BR17:BU17,3,0),0) -> 0 | BU37: =+IFERROR(VLOOKUP($BU$17,Sheet1!BV17:BY17,3,0),0) -> 0 | BV37: =Sheet1!E17 -> WOOD | BW37: =Sheet1!CV17 -> MD0100066 | BX37: =Sheet1!CW17 -> DRUM - 40 X 15 X 23 X 2 | BY37: =Sheet1!CX17 -> 500 | BZ37: =Sheet1!BZ17 -> 5151.48 | CA37: =SUMPRODUCT($N$18:$BU$18,N37:BU37)+BZ37 -> 212496.48 | CB37: =Sheet1!CB17 -> 0 | CC37: =CA37*CB37 -> 0 | CD37: 0.18 | CE37: =CA37*CD37 -> 38249.366 | CF37: 0 | CG37: =CA37*CF37 -> 0 | CH37: =CA37+CC37+CE37+CG37 -> 250745.85 | CI37: 0.02 | CJ37: =CH37*CI37 -> 5014.9169 | CK37: 0.01 | CL37: =CH37*CK37 -> 2507.4585 | CM37: 55 | CN37: 20
A38: =Sheet1!A14 -> ENQ-12232-22-23 | B38: 45380 | C38: FA0200005 | D38: 16 CORE X 2.5 SQ. MM. CU/ARD - WIRE (PVC) | E38: =CH38+CJ38+CL38 -> 460295.15 | F38: =ROUNDUP(M71,0) -> 3104 | G38: =E38+F38 -> 463399.15 | H38: =Sheet1!CP14 -> 0.18 | I38: =G38*H38 -> 83411.846 | J38: =G38+I38 -> 546810.99 | K38: =25+2+16.5 -> 43.5 | L38: =Sheet1!CT14 -> KMS | M38: =J38*K38 -> 23786278 | N38: =+IFERROR(VLOOKUP($N$17,Sheet1!J14:L14,3,0),0) -> 0 | O38: =+IFERROR(VLOOKUP($O$17,Sheet1!J14:L14,3,0),0) -> 0 | P38: 355 | Q38: =+IFERROR(VLOOKUP($Q$17,Sheet1!J14:M14,3,0),0) -> 0 | R38: =+IFERROR(VLOOKUP($R$17,Sheet1!J14:M14,3,0),0) -> 0 | S38: =+IFERROR(VLOOKUP($S$17,Sheet1!N14:Q14,3,0),0) -> 0 | T38: =+IFERROR(VLOOKUP($T$17,Sheet1!N14:Q14,3,0),0) -> 0 | U38: =+IFERROR(VLOOKUP($U$17,Sheet1!F14:I14,3,0),0) -> 0 | V38: =+IFERROR(VLOOKUP($V$17,Sheet1!F14:I14,3,0),0) -> 0 | W38: =+IFERROR(VLOOKUP($W$17,Sheet1!F14:I14,3,0),0) -> 0 | X38: =+IFERROR(VLOOKUP($X$17,Sheet1!F14:I14,3,0),0) -> 0 | Y38: =+IFERROR(VLOOKUP($Y$17,Sheet1!F14:I14,3,0),0) -> 0 | Z38: =+IFERROR(VLOOKUP($Z$17,Sheet1!F14:I14,3,0),0) -> 0 | AA38: =+IFERROR(VLOOKUP($AA$17,Sheet1!F14:I14,3,0),0) -> 0 | AB38: =+IFERROR(VLOOKUP($AB$17,Sheet1!F14:I14,3,0),0) -> 0 | AC38: =+IFERROR(VLOOKUP($AC$17,Sheet1!R14:U14,3,0),0) -> 0 | AD38: =+IFERROR(VLOOKUP($AD$17,Sheet1!R14:U14,2,0),0) -> 0 | AE38: =+IFERROR(VLOOKUP($AE$17,Sheet1!V14:Y14,3,0),0) -> 0 | AF38: =+IFERROR(VLOOKUP($AF$17,Sheet1!V14:Y14,3,0),0) -> 0 | AG38: =+IFERROR(VLOOKUP($AG$17,Sheet1!V14:Y14,3,0),0) -> 0 | AH38: =+IFERROR(VLOOKUP($AH$17,Sheet1!V14:Y14,3,0),0) -> 0 | AI38: 214 | AJ38: =+IFERROR(VLOOKUP($AJ$17,Sheet1!V14:Y14,3,0),0) -> 0 | AK38: 6 | AL38: =+IFERROR(VLOOKUP($AL$17,Sheet1!AD14:AG14,3,0),0) -> 0 | AM38: =+IFERROR(VLOOKUP($AM$17,Sheet1!AD14:AG14,3,0),0) -> 0 | AN38: =+IFERROR(VLOOKUP($AN$17,Sheet1!AD14:AG14,3,0),0) -> 0 | AO38: =+IFERROR(VLOOKUP($AO$17,Sheet1!AD14:AG14,3,0),0) -> 0 | AP38: =+IFERROR(VLOOKUP($AP$17,Sheet1!AD14:AG14,3,0),0) -> 0 | AQ38: 58 | AR38: =+IFERROR(VLOOKUP($AR$17,Sheet1!AD14:AG14,3,0),0) -> 0 | AS38: =+IFERROR(VLOOKUP($AS$17,Sheet1!AH14:AK14,3,0),0) -> 0 | AT38: =+IFERROR(VLOOKUP($AT$17,Sheet1!AH14:AK14,3,0),0) -> 0 | AU38: =+IFERROR(VLOOKUP($AU$17,Sheet1!AH14:AK14,3,0),0) -> 0 | AV38: =+IFERROR(VLOOKUP($AV$17,Sheet1!AH14:AK14,3,0),0) -> 0 | AW38: =+IFERROR(VLOOKUP($AW$17,Sheet1!AH14:AK14,3,0),0) -> 0 | AX38: =+IFERROR(VLOOKUP($AX$17,Sheet1!AH14:AK14,3,0),0) -> 0 | AY38: =+IFERROR(VLOOKUP($AY$17,Sheet1!AH14:AK14,3,0),0) -> 0 | AZ38: =+IFERROR(VLOOKUP($AZ$17,Sheet1!AH14:AK14,3,0),0) -> 0 | BA38: 574 | BB38: =+IFERROR(VLOOKUP($BB$17,Sheet1!AH14:AK14,3,0),0) -> 0 | BC38: =+IFERROR(VLOOKUP($BC$17,Sheet1!AL14:AO14,3,0),0) -> 0 | BD38: =+IFERROR(VLOOKUP($BD$17,Sheet1!AL14:AO14,3,0),0) -> 0 | BE38: =+IFERROR(VLOOKUP($BE$17,Sheet1!AL14:AO14,3,0),0) -> 0 | BF38: 193 | BG38: =+IFERROR(VLOOKUP($BG$17,Sheet1!AL14:AO14,3,0),0) -> 0 | BH38: =+IFERROR(VLOOKUP($BH$17,Sheet1!AL14:AO14,3,0),0) -> 0 | BI38: =+IFERROR(VLOOKUP($BI$17,Sheet1!AL14:AO14,3,0),0) -> 0 | BJ38: =+IFERROR(VLOOKUP($BJ$17,Sheet1!AL14:AO14,3,0),0) -> 0 | BK38: =+IFERROR(VLOOKUP($BK$17,Sheet1!AL14:AO14,3,0),0) -> 0 | BL38: =+IFERROR(VLOOKUP($BL$17,Sheet1!AL14:AO14,3,0),0) -> 0 | BM38: =+IFERROR(VLOOKUP($BM$17,Sheet1!AP14:AS14,3,0),0) -> 0 | BN38: =+IFERROR(VLOOKUP($BN$17,Sheet1!AT14:AW14,3,0),0) -> 0 | BO38: =+IFERROR(VLOOKUP($BO$17,Sheet1!AX14:BA14,3,0),0) -> 0 | BP38: =+IFERROR(VLOOKUP($BP$17,Sheet1!BB14:BE14,3,0),0) -> 0 | BQ38: =+IFERROR(VLOOKUP($BQ$17,Sheet1!BF14:BI14,3,0),0) -> 0 | BR38: =+IFERROR(VLOOKUP($BR$17,Sheet1!BJ14:BM14,3,0),0) -> 0 | BS38: =+IFERROR(VLOOKUP($BS$17,Sheet1!BN14:BQ14,3,0),0) -> 0 | BT38: =+IFERROR(VLOOKUP($BT$17,Sheet1!BR14:BU14,3,0),0) -> 0 | BU38: =+IFERROR(VLOOKUP($BU$17,Sheet1!BV14:BY14,3,0),0) -> 0 | BV38: =Sheet1!E14 -> WOOD | BW38: =Sheet1!CV14 -> MD0100075 | BX38: =Sheet1!CW14 -> DRUM - 42 X 15 X 23 X 2 | BY38: =Sheet1!CX14 -> 500 | BZ38: =Sheet1!BZ14 -> 7084.06 | CA38: =SUMPRODUCT($N$18:$BU$18,N38:BU38)+BZ38 -> 378719.06 | CB38: =Sheet1!CB14 -> 0 | CC38: =CA38*CB38 -> 0 | CD38: 0.18 | CE38: =CA38*CD38 -> 68169.431 | CF38: 0 | CG38: =CA38*CF38 -> 0 | CH38: =CA38+CC38+CE38+CG38 -> 446888.49 | CI38: 0.02 | CJ38: =CH38*CI38 -> 8937.7698 | CK38: 0.01 | CL38: =CH38*CK38 -> 4468.8849 | CM38: 55 | CN38: 20
A39: =Sheet1!A13 -> ENQ-12232-22-23 | B39: 45380 | C39: =Sheet1!C13 -> FA0300006 | D39: =Sheet1!D13 -> 4 CORE X 2.5 SQ. MM. CU/UNARD.(PVC) | E39: =CH39+CJ39+CL39 -> 112182.06 | F39: =ROUNDUP(M72,0) -> #DIV/0! | G39: =E39+F39 -> #DIV/0! | H39: =Sheet1!CP13 -> 0.18 | I39: =G39*H39 -> #DIV/0! | J39: =G39+I39 -> #DIV/0! | L39: =Sheet1!CT13 -> KMS | M39: =J39*K39 -> #DIV/0! | N39: =+IFERROR(VLOOKUP($N$17,Sheet1!J13:L13,3,0),0) -> 0 | O39: =+IFERROR(VLOOKUP($O$17,Sheet1!J13:L13,3,0),0) -> 0 | P39: =+IFERROR(VLOOKUP($P$17,Sheet1!J13:M13,3,0),0) -> 88.8 | Q39: =+IFERROR(VLOOKUP($Q$17,Sheet1!J13:M13,3,0),0) -> 0 | R39: =+IFERROR(VLOOKUP($R$17,Sheet1!J13:M13,3,0),0) -> 0 | S39: =+IFERROR(VLOOKUP($S$17,Sheet1!N13:Q13,3,0),0) -> 0 | T39: =+IFERROR(VLOOKUP($T$17,Sheet1!N13:Q13,3,0),0) -> 0 | U39: =+IFERROR(VLOOKUP($U$17,Sheet1!F13:I13,3,0),0) -> 0 | V39: =+IFERROR(VLOOKUP($V$17,Sheet1!F13:I13,3,0),0) -> 0 | W39: =+IFERROR(VLOOKUP($W$17,Sheet1!F13:I13,3,0),0) -> 0 | X39: =+IFERROR(VLOOKUP($X$17,Sheet1!F13:I13,3,0),0) -> 0 | Y39: =+IFERROR(VLOOKUP($Y$17,Sheet1!F13:I13,3,0),0) -> 0 | Z39: =+IFERROR(VLOOKUP($Z$17,Sheet1!F13:I13,3,0),0) -> 0 | AA39: =+IFERROR(VLOOKUP($AA$17,Sheet1!F13:I13,3,0),0) -> 0 | AB39: =+IFERROR(VLOOKUP($AB$17,Sheet1!F13:I13,3,0),0) -> 0 | AC39: =+IFERROR(VLOOKUP($AC$17,Sheet1!R13:U13,3,0),0) -> 0 | AD39: =+IFERROR(VLOOKUP($AD$17,Sheet1!R13:U13,2,0),0) -> 0 | AE39: =+IFERROR(VLOOKUP($AE$17,Sheet1!V13:Y13,3,0),0) -> 0 | AF39: =+IFERROR(VLOOKUP($AF$17,Sheet1!V13:Y13,3,0),0) -> 0 | AG39: =+IFERROR(VLOOKUP($AG$17,Sheet1!V13:Y13,3,0),0) -> 0 | AH39: =+IFERROR(VLOOKUP($AH$17,Sheet1!V13:Y13,3,0),0) -> 0 | AI39: =+IFERROR(VLOOKUP($AI$17,Sheet1!V13:Y13,3,0),0) -> 52 | AJ39: =+IFERROR(VLOOKUP($AJ$17,Sheet1!V13:Y13,3,0),0) -> 0 | AK39: =+IFERROR(VLOOKUP($AK$17,Sheet1!Z13:AB13,3,0),0) -> 4 | AL39: =+IFERROR(VLOOKUP($AL$17,Sheet1!AD13:AG13,3,0),0) -> 0 | AM39: =+IFERROR(VLOOKUP($AM$17,Sheet1!AD13:AG13,3,0),0) -> 0 | AN39: =+IFERROR(VLOOKUP($AN$17,Sheet1!AD13:AG13,3,0),0) -> 0 | AO39: =+IFERROR(VLOOKUP($AO$17,Sheet1!AD13:AG13,3,0),0) -> 0 | AP39: =+IFERROR(VLOOKUP($AP$17,Sheet1!AD13:AG13,3,0),0) -> 0 | AQ39: =+IFERROR(VLOOKUP($AQ$17,Sheet1!AD13:AG13,3,0),0) -> 27 | AR39: =+IFERROR(VLOOKUP($AR$17,Sheet1!AD13:AG13,3,0),0) -> 0 | AS39: =+IFERROR(VLOOKUP($AS$17,Sheet1!AH13:AK13,3,0),0) -> 0 | AT39: =+IFERROR(VLOOKUP($AT$17,Sheet1!AH13:AK13,3,0),0) -> 0 | AU39: =+IFERROR(VLOOKUP($AU$17,Sheet1!AH13:AK13,3,0),0) -> 0 | AV39: =+IFERROR(VLOOKUP($AV$17,Sheet1!AH13:AK13,3,0),0) -> 0 | AW39: =+IFERROR(VLOOKUP($AW$17,Sheet1!AH13:AK13,3,0),0) -> 0 | AX39: =+IFERROR(VLOOKUP($AX$17,Sheet1!AH13:AK13,3,0),0) -> 0 | AY39: =+IFERROR(VLOOKUP($AY$17,Sheet1!AH13:AK13,3,0),0) -> 0 | AZ39: =+IFERROR(VLOOKUP($AZ$17,Sheet1!AH13:AK13,3,0),0) -> 0 | BA39: =+IFERROR(VLOOKUP($BA$17,Sheet1!AH13:AK13,3,0),0) -> 0 | BB39: =+IFERROR(VLOOKUP($BB$17,Sheet1!AH13:AK13,3,0),0) -> 0 | BC39: =+IFERROR(VLOOKUP($BC$17,Sheet1!AL13:AO13,3,0),0) -> 0 | BD39: =+IFERROR(VLOOKUP($BD$17,Sheet1!AL13:AO13,3,0),0) -> 0 | BE39: =+IFERROR(VLOOKUP($BE$17,Sheet1!AL13:AO13,3,0),0) -> 0 | BF39: =+IFERROR(VLOOKUP($BF$17,Sheet1!AL13:AO13,3,0),0) -> 109 | BG39: =+IFERROR(VLOOKUP($BG$17,Sheet1!AL13:AO13,3,0),0) -> 0 | BH39: =+IFERROR(VLOOKUP($BH$17,Sheet1!AL13:AO13,3,0),0) -> 0 | BI39: =+IFERROR(VLOOKUP($BI$17,Sheet1!AL13:AO13,3,0),0) -> 0 | BJ39: =+IFERROR(VLOOKUP($BJ$17,Sheet1!AL13:AO13,3,0),0) -> 0 | BK39: =+IFERROR(VLOOKUP($BK$17,Sheet1!AL13:AO13,3,0),0) -> 0 | BL39: =+IFERROR(VLOOKUP($BL$17,Sheet1!AL13:AO13,3,0),0) -> 0 | BM39: =+IFERROR(VLOOKUP($BM$17,Sheet1!AP13:AS13,3,0),0) -> 0 | BN39: =+IFERROR(VLOOKUP($BN$17,Sheet1!AT13:AW13,3,0),0) -> 0 | BO39: =+IFERROR(VLOOKUP($BO$17,Sheet1!AX13:BA13,3,0),0) -> 0 | BP39: =+IFERROR(VLOOKUP($BP$17,Sheet1!BB13:BE13,3,0),0) -> 0 | BQ39: =+IFERROR(VLOOKUP($BQ$17,Sheet1!BF13:BI13,3,0),0) -> 0 | BR39: =+IFERROR(VLOOKUP($BR$17,Sheet1!BJ13:BM13,3,0),0) -> 0 | BS39: =+IFERROR(VLOOKUP($BS$17,Sheet1!BN13:BQ13,3,0),0) -> 0 | BT39: =+IFERROR(VLOOKUP($BT$17,Sheet1!BR13:BU13,3,0),0) -> 0 | BU39: =+IFERROR(VLOOKUP($BU$17,Sheet1!BV13:BY13,3,0),0) -> 0 | BV39: =Sheet1!E13 -> WOOD | BW39: =Sheet1!CV13 -> MD0100003 | BX39: =Sheet1!CW13 -> DRUM - 28 X 14 X 23 X 2 | BY39: =Sheet1!CX13 -> 500 | BZ39: =Sheet1!BZ13 -> 3850.93 | CA39: =SUMPRODUCT($N$18:$BU$18,N39:BU39)+BZ39 -> 92300.53 | CB39: =Sheet1!CB13 -> 0 | CC39: =CA39*CB39 -> 0 | CD39: 0.18 | CE39: =CA39*CD39 -> 16614.095 | CF39: 0 | CG39: =CA39*CF39 -> 0 | CH39: =CA39+CC39+CE39+CG39 -> 108914.63 | CI39: 0.02 | CJ39: =CH39*CI39 -> 2178.2925 | CK39: 0.01 | CL39: =CH39*CK39 -> 1089.1463 | CM39: 45 | CN39: 15
A40: =Sheet1!A27 -> ENQ-12232-22-23 | B40: 45380 | C40: =Sheet1!C27 -> FA0200011 | D40: =Sheet1!D27 -> 4 CORE X 2.5 SQ. MM. CU/ARD - WIRE (PVC) | E40: =CH40+CJ40+CL40 -> 141131.51 | F40: =ROUNDUP(M73,0) -> 1636 | G40: =E40+F40 -> 142767.51 | H40: =Sheet1!CP27 -> 0.18 | I40: =G40*H40 -> 25698.151 | J40: =G40+I40 -> 168465.66 | K40: =143.155+1.4+20.533 -> 165.088 | L40: =Sheet1!CT27 -> KMS | M40: =J40*K40 -> 27811659 | N40: =+IFERROR(VLOOKUP($N$17,Sheet1!J27:L27,3,0),0) -> 0 | O40: =+IFERROR(VLOOKUP($O$17,Sheet1!J27:L27,3,0),0) -> 0 | P40: =+IFERROR(VLOOKUP($P$17,Sheet1!J27:M27,3,0),0) -> 88.8 | Q40: =+IFERROR(VLOOKUP($Q$17,Sheet1!J27:M27,3,0),0) -> 0 | R40: =+IFERROR(VLOOKUP($R$17,Sheet1!J27:M27,3,0),0) -> 0 | S40: =+IFERROR(VLOOKUP($S$17,Sheet1!N27:Q27,3,0),0) -> 0 | T40: =+IFERROR(VLOOKUP($T$17,Sheet1!N27:Q27,3,0),0) -> 0 | U40: =+IFERROR(VLOOKUP($U$17,Sheet1!F27:I27,3,0),0) -> 0 | V40: =+IFERROR(VLOOKUP($V$17,Sheet1!F27:I27,3,0),0) -> 0 | W40: =+IFERROR(VLOOKUP($W$17,Sheet1!F27:I27,3,0),0) -> 0 | X40: =+IFERROR(VLOOKUP($X$17,Sheet1!F27:I27,3,0),0) -> 0 | Y40: =+IFERROR(VLOOKUP($Y$17,Sheet1!F27:I27,3,0),0) -> 0 | Z40: =+IFERROR(VLOOKUP($Z$17,Sheet1!F27:I27,3,0),0) -> 0 | AA40: =+IFERROR(VLOOKUP($AA$17,Sheet1!F27:I27,3,0),0) -> 0 | AB40: =+IFERROR(VLOOKUP($AB$17,Sheet1!F27:I27,3,0),0) -> 0 | AC40: =+IFERROR(VLOOKUP($AC$17,Sheet1!R27:U27,3,0),0) -> 0 | AD40: =+IFERROR(VLOOKUP($AD$17,Sheet1!R27:U27,2,0),0) -> 0 | AE40: =+IFERROR(VLOOKUP($AE$17,Sheet1!V27:Y27,3,0),0) -> 0 | AF40: =+IFERROR(VLOOKUP($AF$17,Sheet1!V27:Y27,3,0),0) -> 0 | AG40: =+IFERROR(VLOOKUP($AG$17,Sheet1!V27:Y27,3,0),0) -> 0 | AH40: =+IFERROR(VLOOKUP($AH$17,Sheet1!V27:Y27,3,0),0) -> 0 | AI40: =+IFERROR(VLOOKUP($AI$17,Sheet1!V27:Y27,3,0),0) -> 52 | AJ40: =+IFERROR(VLOOKUP($AJ$17,Sheet1!V27:Y27,3,0),0) -> 0 | AK40: =+IFERROR(VLOOKUP($AK$17,Sheet1!Z27:AB27,3,0),0) -> 3 | AL40: =+IFERROR(VLOOKUP($AL$17,Sheet1!AD27:AG27,3,0),0) -> 0 | AM40: =+IFERROR(VLOOKUP($AM$17,Sheet1!AD27:AG27,3,0),0) -> 0 | AN40: =+IFERROR(VLOOKUP($AN$17,Sheet1!AD27:AG27,3,0),0) -> 0 | AO40: =+IFERROR(VLOOKUP($AO$17,Sheet1!AD27:AG27,3,0),0) -> 0 | AP40: =+IFERROR(VLOOKUP($AP$17,Sheet1!AD27:AG27,3,0),0) -> 0 | AQ40: =+IFERROR(VLOOKUP($AQ$17,Sheet1!AD27:AG27,3,0),0) -> 27 | AR40: =+IFERROR(VLOOKUP($AR$17,Sheet1!AD27:AG27,3,0),0) -> 0 | AS40: =+IFERROR(VLOOKUP($AS$17,Sheet1!AH27:AK27,3,0),0) -> 0 | AT40: =+IFERROR(VLOOKUP($AT$17,Sheet1!AH27:AK27,3,0),0) -> 0 | AU40: =+IFERROR(VLOOKUP($AU$17,Sheet1!AH27:AK27,3,0),0) -> 0 | AV40: =+IFERROR(VLOOKUP($AV$17,Sheet1!AH27:AK27,3,0),0) -> 0 | AW40: =+IFERROR(VLOOKUP($AW$17,Sheet1!AH27:AK27,3,0),0) -> 0 | AX40: =+IFERROR(VLOOKUP($AX$17,Sheet1!AH27:AK27,3,0),0) -> 0 | AY40: =+IFERROR(VLOOKUP($AY$17,Sheet1!AH27:AK27,3,0),0) -> 0 | AZ40: =+IFERROR(VLOOKUP($AZ$17,Sheet1!AH27:AK27,3,0),0) -> 0 | BA40: =+IFERROR(VLOOKUP($BA$17,Sheet1!AH27:AK27,3,0),0) -> 289 | BB40: =+IFERROR(VLOOKUP($BB$17,Sheet1!AH27:AK27,3,0),0) -> 0 | BC40: =+IFERROR(VLOOKUP($BC$17,Sheet1!AL27:AO27,3,0),0) -> 0 | BD40: =+IFERROR(VLOOKUP($BD$17,Sheet1!AL27:AO27,3,0),0) -> 0 | BE40: =+IFERROR(VLOOKUP($BE$17,Sheet1!AL27:AO27,3,0),0) -> 0 | BF40: =+IFERROR(VLOOKUP($BF$17,Sheet1!AL27:AO27,3,0),0) -> 104 | BG40: =+IFERROR(VLOOKUP($BG$17,Sheet1!AL27:AO27,3,0),0) -> 0 | BH40: =+IFERROR(VLOOKUP($BH$17,Sheet1!AL27:AO27,3,0),0) -> 0 | BI40: =+IFERROR(VLOOKUP($BI$17,Sheet1!AL27:AO27,3,0),0) -> 0 | BJ40: =+IFERROR(VLOOKUP($BJ$17,Sheet1!AL27:AO27,3,0),0) -> 0 | BK40: =+IFERROR(VLOOKUP($BK$17,Sheet1!AL27:AO27,3,0),0) -> 0 | BL40: =+IFERROR(VLOOKUP($BL$17,Sheet1!AL27:AO27,3,0),0) -> 0 | BM40: =+IFERROR(VLOOKUP($BM$17,Sheet1!AP27:AS27,3,0),0) -> 0 | BN40: =+IFERROR(VLOOKUP($BN$17,Sheet1!AT27:AW27,3,0),0) -> 0 | BO40: =+IFERROR(VLOOKUP($BO$17,Sheet1!AX27:BA27,3,0),0) -> 0 | BP40: =+IFERROR(VLOOKUP($BP$17,Sheet1!BB27:BE27,3,0),0) -> 0 | BQ40: =+IFERROR(VLOOKUP($BQ$17,Sheet1!BF27:BI27,3,0),0) -> 0 | BR40: =+IFERROR(VLOOKUP($BR$17,Sheet1!BJ27:BM27,3,0),0) -> 0 | BS40: =+IFERROR(VLOOKUP($BS$17,Sheet1!BN27:BQ27,3,0),0) -> 0 | BT40: =+IFERROR(VLOOKUP($BT$17,Sheet1!BR27:BU27,3,0),0) -> 0 | BU40: =+IFERROR(VLOOKUP($BU$17,Sheet1!BV27:BY27,3,0),0) -> 0 | BV40: =Sheet1!E27 -> WOOD | BW40: =Sheet1!CV27 -> MD0100005 | BX40: =Sheet1!CW27 -> DRUM - 36 X 14 X 23 X 2 | BY40: =Sheet1!CX27 -> 500 | BZ40: =Sheet1!BZ27 -> 4610.79 | CA40: =SUMPRODUCT($N$18:$BU$18,N40:BU40)+BZ40 -> 116119.39 | CB40: =Sheet1!CB27 -> 0 | CC40: =CA40*CB40 -> 0 | CD40: 0.18 | CE40: =CA40*CD40 -> 20901.49 | CF40: 0 | CG40: =CA40*CF40 -> 0 | CH40: =CA40+CC40+CE40+CG40 -> 137020.88 | CI40: 0.02 | CJ40: =CH40*CI40 -> 2740.4176 | CK40: 0.01 | CL40: =CH40*CK40 -> 1370.2088 | CM40: 50 | CN40: 15
A41: =Sheet1!A25 -> ENQ-12232-22-23 | B41: 45380 | C41: =Sheet1!C25 -> FA0200018 | D41: =Sheet1!D25 -> 7 CORE X 2.5 SQ. MM. CU/ARD - WIRE (PVC) | E41: =CH41+CJ41+CL41 -> 218312.08 | F41: =ROUNDUP(M74,0) -> 1831 | G41: =E41+F41 -> 220143.08 | H41: =Sheet1!CP25 -> 0.18 | I41: =G41*H41 -> 39625.754 | J41: =G41+I41 -> 259768.83 | K41: =72.355+1.4 -> 73.755 | L41: =Sheet1!CT25 -> KMS | M41: =J41*K41 -> 19159250 | N41: =+IFERROR(VLOOKUP($N$17,Sheet1!J25:L25,3,0),0) -> 0 | O41: =+IFERROR(VLOOKUP($O$17,Sheet1!J25:L25,3,0),0) -> 0 | P41: =+IFERROR(VLOOKUP($P$17,Sheet1!J25:M25,3,0),0) -> 155.4 | Q41: =+IFERROR(VLOOKUP($Q$17,Sheet1!J25:M25,3,0),0) -> 0 | R41: =+IFERROR(VLOOKUP($R$17,Sheet1!J25:M25,3,0),0) -> 0 | S41: =+IFERROR(VLOOKUP($S$17,Sheet1!N25:Q25,3,0),0) -> 0 | T41: =+IFERROR(VLOOKUP($T$17,Sheet1!N25:Q25,3,0),0) -> 0 | U41: =+IFERROR(VLOOKUP($U$17,Sheet1!F25:I25,3,0),0) -> 0 | V41: =+IFERROR(VLOOKUP($V$17,Sheet1!F25:I25,3,0),0) -> 0 | W41: =+IFERROR(VLOOKUP($W$17,Sheet1!F25:I25,3,0),0) -> 0 | X41: =+IFERROR(VLOOKUP($X$17,Sheet1!F25:I25,3,0),0) -> 0 | Y41: =+IFERROR(VLOOKUP($Y$17,Sheet1!F25:I25,3,0),0) -> 0 | Z41: =+IFERROR(VLOOKUP($Z$17,Sheet1!F25:I25,3,0),0) -> 0 | AA41: =+IFERROR(VLOOKUP($AA$17,Sheet1!F25:I25,3,0),0) -> 0 | AB41: =+IFERROR(VLOOKUP($AB$17,Sheet1!F25:I25,3,0),0) -> 0 | AC41: =+IFERROR(VLOOKUP($AC$17,Sheet1!R25:U25,3,0),0) -> 0 | AD41: =+IFERROR(VLOOKUP($AD$17,Sheet1!R25:U25,2,0),0) -> 0 | AE41: =+IFERROR(VLOOKUP($AE$17,Sheet1!V25:Y25,3,0),0) -> 0 | AF41: =+IFERROR(VLOOKUP($AF$17,Sheet1!V25:Y25,3,0),0) -> 0 | AG41: =+IFERROR(VLOOKUP($AG$17,Sheet1!V25:Y25,3,0),0) -> 0 | AH41: =+IFERROR(VLOOKUP($AH$17,Sheet1!V25:Y25,3,0),0) -> 0 | AI41: =+IFERROR(VLOOKUP($AI$17,Sheet1!V25:Y25,3,0),0) -> 91 | AJ41: =+IFERROR(VLOOKUP($AJ$17,Sheet1!V25:Y25,3,0),0) -> 0 | AK41: =+IFERROR(VLOOKUP($AK$17,Sheet1!Z25:AB25,3,0),0) -> 4 | AL41: =+IFERROR(VLOOKUP($AL$17,Sheet1!AD25:AG25,3,0),0) -> 0 | AM41: =+IFERROR(VLOOKUP($AM$17,Sheet1!AD25:AG25,3,0),0) -> 0 | AN41: =+IFERROR(VLOOKUP($AN$17,Sheet1!AD25:AG25,3,0),0) -> 0 | AO41: =+IFERROR(VLOOKUP($AO$17,Sheet1!AD25:AG25,3,0),0) -> 0 | AP41: =+IFERROR(VLOOKUP($AP$17,Sheet1!AD25:AG25,3,0),0) -> 0 | AQ41: 33 | AR41: =+IFERROR(VLOOKUP($AR$17,Sheet1!AD25:AG25,3,0),0) -> 0 | AS41: =+IFERROR(VLOOKUP($AS$17,Sheet1!AH25:AK25,3,0),0) -> 0 | AT41: =+IFERROR(VLOOKUP($AT$17,Sheet1!AH25:AK25,3,0),0) -> 0 | AU41: =+IFERROR(VLOOKUP($AU$17,Sheet1!AH25:AK25,3,0),0) -> 0 | AV41: =+IFERROR(VLOOKUP($AV$17,Sheet1!AH25:AK25,3,0),0) -> 0 | AW41: =+IFERROR(VLOOKUP($AW$17,Sheet1!AH25:AK25,3,0),0) -> 0 | AX41: =+IFERROR(VLOOKUP($AX$17,Sheet1!AH25:AK25,3,0),0) -> 0 | AY41: =+IFERROR(VLOOKUP($AY$17,Sheet1!AH25:AK25,3,0),0) -> 0 | AZ41: =+IFERROR(VLOOKUP($AZ$17,Sheet1!AH25:AK25,3,0),0) -> 0 | BA41: 352 | BB41: =+IFERROR(VLOOKUP($BB$17,Sheet1!AH25:AK25,3,0),0) -> 0 | BC41: =+IFERROR(VLOOKUP($BC$17,Sheet1!AL25:AO25,3,0),0) -> 0 | BD41: =+IFERROR(VLOOKUP($BD$17,Sheet1!AL25:AO25,3,0),0) -> 0 | BE41: =+IFERROR(VLOOKUP($BE$17,Sheet1!AL25:AO25,3,0),0) -> 0 | BF41: 120 | BG41: =+IFERROR(VLOOKUP($BG$17,Sheet1!AL25:AO25,3,0),0) -> 0 | BH41: =+IFERROR(VLOOKUP($BH$17,Sheet1!AL25:AO25,3,0),0) -> 0 | BI41: =+IFERROR(VLOOKUP($BI$17,Sheet1!AL25:AO25,3,0),0) -> 0 | BJ41: =+IFERROR(VLOOKUP($BJ$17,Sheet1!AL25:AO25,3,0),0) -> 0 | BK41: =+IFERROR(VLOOKUP($BK$17,Sheet1!AL25:AO25,3,0),0) -> 0 | BL41: =+IFERROR(VLOOKUP($BL$17,Sheet1!AL25:AO25,3,0),0) -> 0 | BM41: =+IFERROR(VLOOKUP($BM$17,Sheet1!AP25:AS25,3,0),0) -> 0 | BN41: =+IFERROR(VLOOKUP($BN$17,Sheet1!AT25:AW25,3,0),0) -> 0 | BO41: =+IFERROR(VLOOKUP($BO$17,Sheet1!AX25:BA25,3,0),0) -> 0 | BP41: =+IFERROR(VLOOKUP($BP$17,Sheet1!BB25:BE25,3,0),0) -> 0 | BQ41: =+IFERROR(VLOOKUP($BQ$17,Sheet1!BF25:BI25,3,0),0) -> 0 | BR41: =+IFERROR(VLOOKUP($BR$17,Sheet1!BJ25:BM25,3,0),0) -> 0 | BS41: =+IFERROR(VLOOKUP($BS$17,Sheet1!BN25:BQ25,3,0),0) -> 0 | BT41: =+IFERROR(VLOOKUP($BT$17,Sheet1!BR25:BU25,3,0),0) -> 0 | BU41: =+IFERROR(VLOOKUP($BU$17,Sheet1!BV25:BY25,3,0),0) -> 0 | BV41: =Sheet1!E25 -> WOOD | BW41: =Sheet1!CV25 -> MD0100005 | BX41: =Sheet1!CW25 -> DRUM - 36 X 14 X 23 X 2 | BY41: =Sheet1!CX25 -> 500 | BZ41: =Sheet1!BZ25 -> 4610.79 | CA41: =SUMPRODUCT($N$18:$BU$18,N41:BU41)+BZ41 -> 179621.59 | CB41: =Sheet1!CB25 -> 0 | CC41: =CA41*CB41 -> 0 | CD41: 0.18 | CE41: =CA41*CD41 -> 32331.886 | CF41: 0 | CG41: =CA41*CF41 -> 0 | CH41: =CA41+CC41+CE41+CG41 -> 211953.48 | CI41: 0.02 | CJ41: =CH41*CI41 -> 4239.0695 | CK41: 0.01 | CL41: =CH41*CK41 -> 2119.5348 | CM41: 50 | CN41: 15
A42: =Sheet1!A24 -> ENQ-12232-22-23 | B42: 45380 | C42: =Sheet1!C24 -> FA0200002 | D42: =Sheet1!D24 -> 10 CORE X 2.5 SQ. MM. CU/ARD - WIRE (PVC) | E42: =CH42+CJ42+CL42 -> 310334.74 | F42: =ROUNDUP(M75,0) -> 2187 | G42: =E42+F42 -> 312521.74 | H42: =Sheet1!CP24 -> 0.18 | I42: =G42*H42 -> 56253.914 | J42: =G42+I42 -> 368775.66 | K42: =58.006+10.5+30.3 -> 98.806 | L42: =Sheet1!CT24 -> KMS | M42: =J42*K42 -> 36437247 | N42: =+IFERROR(VLOOKUP($N$17,Sheet1!J24:L24,3,0),0) -> 0 | O42: =+IFERROR(VLOOKUP($O$17,Sheet1!J24:L24,3,0),0) -> 0 | P42: =+IFERROR(VLOOKUP($P$17,Sheet1!J24:M24,3,0),0) -> 222 | Q42: =+IFERROR(VLOOKUP($Q$17,Sheet1!J24:M24,3,0),0) -> 0 | R42: =+IFERROR(VLOOKUP($R$17,Sheet1!J24:M24,3,0),0) -> 0 | S42: =+IFERROR(VLOOKUP($S$17,Sheet1!N24:Q24,3,0),0) -> 0 | T42: =+IFERROR(VLOOKUP($T$17,Sheet1!N24:Q24,3,0),0) -> 0 | U42: =+IFERROR(VLOOKUP($U$17,Sheet1!F24:I24,3,0),0) -> 0 | V42: =+IFERROR(VLOOKUP($V$17,Sheet1!F24:I24,3,0),0) -> 0 | W42: =+IFERROR(VLOOKUP($W$17,Sheet1!F24:I24,3,0),0) -> 0 | X42: =+IFERROR(VLOOKUP($X$17,Sheet1!F24:I24,3,0),0) -> 0 | Y42: =+IFERROR(VLOOKUP($Y$17,Sheet1!F24:I24,3,0),0) -> 0 | Z42: =+IFERROR(VLOOKUP($Z$17,Sheet1!F24:I24,3,0),0) -> 0 | AA42: =+IFERROR(VLOOKUP($AA$17,Sheet1!F24:I24,3,0),0) -> 0 | AB42: =+IFERROR(VLOOKUP($AB$17,Sheet1!F24:I24,3,0),0) -> 0 | AC42: =+IFERROR(VLOOKUP($AC$17,Sheet1!R24:U24,3,0),0) -> 0 | AD42: =+IFERROR(VLOOKUP($AD$17,Sheet1!R24:U24,2,0),0) -> 0 | AE42: =+IFERROR(VLOOKUP($AE$17,Sheet1!V24:Y24,3,0),0) -> 0 | AF42: =+IFERROR(VLOOKUP($AF$17,Sheet1!V24:Y24,3,0),0) -> 0 | AG42: =+IFERROR(VLOOKUP($AG$17,Sheet1!V24:Y24,3,0),0) -> 0 | AH42: =+IFERROR(VLOOKUP($AH$17,Sheet1!V24:Y24,3,0),0) -> 0 | AI42: =+IFERROR(VLOOKUP($AI$17,Sheet1!V24:Y24,3,0),0) -> 130 | AJ42: =+IFERROR(VLOOKUP($AJ$17,Sheet1!V24:Y24,3,0),0) -> 0 | AK42: =+IFERROR(VLOOKUP($AK$17,Sheet1!Z24:AB24,3,0),0) -> 5 | AL42: =+IFERROR(VLOOKUP($AL$17,Sheet1!AD24:AG24,3,0),0) -> 0 | AM42: =+IFERROR(VLOOKUP($AM$17,Sheet1!AD24:AG24,3,0),0) -> 0 | AN42: =+IFERROR(VLOOKUP($AN$17,Sheet1!AD24:AG24,3,0),0) -> 0 | AO42: =+IFERROR(VLOOKUP($AO$17,Sheet1!AD24:AG24,3,0),0) -> 0 | AP42: =+IFERROR(VLOOKUP($AP$17,Sheet1!AD24:AG24,3,0),0) -> 0 | AQ42: 42 | AR42: =+IFERROR(VLOOKUP($AR$17,Sheet1!AD24:AG24,3,0),0) -> 0 | AS42: =+IFERROR(VLOOKUP($AS$17,Sheet1!AH24:AK24,3,0),0) -> 0 | AT42: =+IFERROR(VLOOKUP($AT$17,Sheet1!AH24:AK24,3,0),0) -> 0 | AU42: =+IFERROR(VLOOKUP($AU$17,Sheet1!AH24:AK24,3,0),0) -> 0 | AV42: =+IFERROR(VLOOKUP($AV$17,Sheet1!AH24:AK24,3,0),0) -> 0 | AW42: =+IFERROR(VLOOKUP($AW$17,Sheet1!AH24:AK24,3,0),0) -> 0 | AX42: =+IFERROR(VLOOKUP($AX$17,Sheet1!AH24:AK24,3,0),0) -> 0 | AY42: =+IFERROR(VLOOKUP($AY$17,Sheet1!AH24:AK24,3,0),0) -> 0 | AZ42: =+IFERROR(VLOOKUP($AZ$17,Sheet1!AH24:AK24,3,0),0) -> 0 | BA42: 509 | BB42: =+IFERROR(VLOOKUP($BB$17,Sheet1!AH24:AK24,3,0),0) -> 0 | BC42: =+IFERROR(VLOOKUP($BC$17,Sheet1!AL24:AO24,3,0),0) -> 0 | BD42: =+IFERROR(VLOOKUP($BD$17,Sheet1!AL24:AO24,3,0),0) -> 0 | BE42: =+IFERROR(VLOOKUP($BE$17,Sheet1!AL24:AO24,3,0),0) -> 0 | BF42: 172 | BG42: =+IFERROR(VLOOKUP($BG$17,Sheet1!AL24:AO24,3,0),0) -> 0 | BH42: =+IFERROR(VLOOKUP($BH$17,Sheet1!AL24:AO24,3,0),0) -> 0 | BI42: =+IFERROR(VLOOKUP($BI$17,Sheet1!AL24:AO24,3,0),0) -> 0 | BJ42: =+IFERROR(VLOOKUP($BJ$17,Sheet1!AL24:AO24,3,0),0) -> 0 | BK42: =+IFERROR(VLOOKUP($BK$17,Sheet1!AL24:AO24,3,0),0) -> 0 | BL42: =+IFERROR(VLOOKUP($BL$17,Sheet1!AL24:AO24,3,0),0) -> 0 | BM42: =+IFERROR(VLOOKUP($BM$17,Sheet1!AP24:AS24,3,0),0) -> 0 | BN42: =+IFERROR(VLOOKUP($BN$17,Sheet1!AT24:AW24,3,0),0) -> 0 | BO42: =+IFERROR(VLOOKUP($BO$17,Sheet1!AX24:BA24,3,0),0) -> 0 | BP42: =+IFERROR(VLOOKUP($BP$17,Sheet1!BB24:BE24,3,0),0) -> 0 | BQ42: =+IFERROR(VLOOKUP($BQ$17,Sheet1!BF24:BI24,3,0),0) -> 0 | BR42: =+IFERROR(VLOOKUP($BR$17,Sheet1!BJ24:BM24,3,0),0) -> 0 | BS42: =+IFERROR(VLOOKUP($BS$17,Sheet1!BN24:BQ24,3,0),0) -> 0 | BT42: =+IFERROR(VLOOKUP($BT$17,Sheet1!BR24:BU24,3,0),0) -> 0 | BU42: =+IFERROR(VLOOKUP($BU$17,Sheet1!BV24:BY24,3,0),0) -> 0 | BV42: =Sheet1!E24 -> WOOD | BW42: =Sheet1!CV24 -> MD0100066 | BX42: =Sheet1!CW24 -> DRUM - 40 X 15 X 23 X 2 | BY42: =Sheet1!CX24 -> 500 | BZ42: =Sheet1!BZ24 -> 5151.48 | CA42: =SUMPRODUCT($N$18:$BU$18,N42:BU42)+BZ42 -> 255335.48 | CB42: =Sheet1!CB24 -> 0 | CC42: =CA42*CB42 -> 0 | CD42: 0.18 | CE42: =CA42*CD42 -> 45960.386 | CF42: 0 | CG42: =CA42*CF42 -> 0 | CH42: =CA42+CC42+CE42+CG42 -> 301295.87 | CI42: 0.02 | CJ42: =CH42*CI42 -> 6025.9173 | CK42: 0.01 | CL42: =CH42*CK42 -> 3012.9587 | CM42: 55 | CN42: 20
A43: =Sheet1!A20 -> ENQ-12232-22-23 | B43: 45380 | C43: =Sheet1!C20 -> FA0200003 | D43: =Sheet1!D20 -> 12 CORE X 2.5 SQ. MM. CU/ARD - WIRE (PVC) | E43: =CH43+CJ43+CL43 -> 358599.25 | F43: =ROUNDUP(M76,0) -> 2586 | G43: =E43+F43 -> 361185.25 | H43: =Sheet1!CP20 -> 0.18 | I43: =G43*H43 -> 65013.345 | J43: =G43+I43 -> 426198.59 | K43: =Sheet1!CS20 -> 62.667 | L43: =Sheet1!CT20 -> KMS | M43: =J43*K43 -> 26708587 | N43: =+IFERROR(VLOOKUP($N$17,Sheet1!J20:L20,3,0),0) -> 0 | O43: =+IFERROR(VLOOKUP($O$17,Sheet1!J20:L20,3,0),0) -> 0 | P43: =+IFERROR(VLOOKUP($P$17,Sheet1!J20:M20,3,0),0) -> 266.4 | Q43: =+IFERROR(VLOOKUP($Q$17,Sheet1!J20:M20,3,0),0) -> 0 | R43: =+IFERROR(VLOOKUP($R$17,Sheet1!J20:M20,3,0),0) -> 0 | S43: =+IFERROR(VLOOKUP($S$17,Sheet1!N20:Q20,3,0),0) -> 0 | T43: =+IFERROR(VLOOKUP($T$17,Sheet1!N20:Q20,3,0),0) -> 0 | U43: =+IFERROR(VLOOKUP($U$17,Sheet1!F20:I20,3,0),0) -> 0 | V43: =+IFERROR(VLOOKUP($V$17,Sheet1!F20:I20,3,0),0) -> 0 | W43: =+IFERROR(VLOOKUP($W$17,Sheet1!F20:I20,3,0),0) -> 0 | X43: =+IFERROR(VLOOKUP($X$17,Sheet1!F20:I20,3,0),0) -> 0 | Y43: =+IFERROR(VLOOKUP($Y$17,Sheet1!F20:I20,3,0),0) -> 0 | Z43: =+IFERROR(VLOOKUP($Z$17,Sheet1!F20:I20,3,0),0) -> 0 | AA43: =+IFERROR(VLOOKUP($AA$17,Sheet1!F20:I20,3,0),0) -> 0 | AB43: =+IFERROR(VLOOKUP($AB$17,Sheet1!F20:I20,3,0),0) -> 0 | AC43: =+IFERROR(VLOOKUP($AC$17,Sheet1!R20:U20,3,0),0) -> 0 | AD43: =+IFERROR(VLOOKUP($AD$17,Sheet1!R20:U20,2,0),0) -> 0 | AE43: =+IFERROR(VLOOKUP($AE$17,Sheet1!V20:Y20,3,0),0) -> 0 | AF43: =+IFERROR(VLOOKUP($AF$17,Sheet1!V20:Y20,3,0),0) -> 0 | AG43: =+IFERROR(VLOOKUP($AG$17,Sheet1!V20:Y20,3,0),0) -> 0 | AH43: =+IFERROR(VLOOKUP($AH$17,Sheet1!V20:Y20,3,0),0) -> 0 | AI43: =+IFERROR(VLOOKUP($AI$17,Sheet1!V20:Y20,3,0),0) -> 156 | AJ43: =+IFERROR(VLOOKUP($AJ$17,Sheet1!V20:Y20,3,0),0) -> 0 | AK43: =+IFERROR(VLOOKUP($AK$17,Sheet1!Z20:AB20,3,0),0) -> 6 | AL43: =+IFERROR(VLOOKUP($AL$17,Sheet1!AD20:AG20,3,0),0) -> 0 | AM43: =+IFERROR(VLOOKUP($AM$17,Sheet1!AD20:AG20,3,0),0) -> 0 | AN43: =+IFERROR(VLOOKUP($AN$17,Sheet1!AD20:AG20,3,0),0) -> 0 | AO43: =+IFERROR(VLOOKUP($AO$17,Sheet1!AD20:AG20,3,0),0) -> 0 | AP43: =+IFERROR(VLOOKUP($AP$17,Sheet1!AD20:AG20,3,0),0) -> 0 | AQ43: 44 | AR43: =+IFERROR(VLOOKUP($AR$17,Sheet1!AD20:AG20,3,0),0) -> 0 | AS43: =+IFERROR(VLOOKUP($AS$17,Sheet1!AH20:AK20,3,0),0) -> 0 | AT43: =+IFERROR(VLOOKUP($AT$17,Sheet1!AH20:AK20,3,0),0) -> 0 | AU43: =+IFERROR(VLOOKUP($AU$17,Sheet1!AH20:AK20,3,0),0) -> 0 | AV43: =+IFERROR(VLOOKUP($AV$17,Sheet1!AH20:AK20,3,0),0) -> 0 | AW43: =+IFERROR(VLOOKUP($AW$17,Sheet1!AH20:AK20,3,0),0) -> 0 | AX43: =+IFERROR(VLOOKUP($AX$17,Sheet1!AH20:AK20,3,0),0) -> 0 | AY43: =+IFERROR(VLOOKUP($AY$17,Sheet1!AH20:AK20,3,0),0) -> 0 | AZ43: =+IFERROR(VLOOKUP($AZ$17,Sheet1!AH20:AK20,3,0),0) -> 0 | BA43: 526 | BB43: =+IFERROR(VLOOKUP($BB$17,Sheet1!AH20:AK20,3,0),0) -> 0 | BC43: =+IFERROR(VLOOKUP($BC$17,Sheet1!AL20:AO20,3,0),0) -> 0 | BD43: =+IFERROR(VLOOKUP($BD$17,Sheet1!AL20:AO20,3,0),0) -> 0 | BE43: =+IFERROR(VLOOKUP($BE$17,Sheet1!AL20:AO20,3,0),0) -> 0 | BF43: 178 | BG43: =+IFERROR(VLOOKUP($BG$17,Sheet1!AL20:AO20,3,0),0) -> 0 | BH43: =+IFERROR(VLOOKUP($BH$17,Sheet1!AL20:AO20,3,0),0) -> 0 | BI43: =+IFERROR(VLOOKUP($BI$17,Sheet1!AL20:AO20,3,0),0) -> 0 | BJ43: =+IFERROR(VLOOKUP($BJ$17,Sheet1!AL20:AO20,3,0),0) -> 0 | BK43: =+IFERROR(VLOOKUP($BK$17,Sheet1!AL20:AO20,3,0),0) -> 0 | BL43: =+IFERROR(VLOOKUP($BL$17,Sheet1!AL20:AO20,3,0),0) -> 0 | BM43: =+IFERROR(VLOOKUP($BM$17,Sheet1!AP20:AS20,3,0),0) -> 0 | BN43: =+IFERROR(VLOOKUP($BN$17,Sheet1!AT20:AW20,3,0),0) -> 0 | BO43: =+IFERROR(VLOOKUP($BO$17,Sheet1!AX20:BA20,3,0),0) -> 0 | BP43: =+IFERROR(VLOOKUP($BP$17,Sheet1!BB20:BE20,3,0),0) -> 0 | BQ43: =+IFERROR(VLOOKUP($BQ$17,Sheet1!BF20:BI20,3,0),0) -> 0 | BR43: =+IFERROR(VLOOKUP($BR$17,Sheet1!BJ20:BM20,3,0),0) -> 0 | BS43: =+IFERROR(VLOOKUP($BS$17,Sheet1!BN20:BQ20,3,0),0) -> 0 | BT43: =+IFERROR(VLOOKUP($BT$17,Sheet1!BR20:BU20,3,0),0) -> 0 | BU43: =+IFERROR(VLOOKUP($BU$17,Sheet1!BV20:BY20,3,0),0) -> 0 | BV43: =Sheet1!E20 -> WOOD | BW43: =Sheet1!CV20 -> MD0100066 | BX43: =Sheet1!CW20 -> DRUM - 40 X 15 X 23 X 2 | BY43: =Sheet1!CX20 -> 500 | BZ43: =Sheet1!BZ20 -> 5151.48 | CA43: =SUMPRODUCT($N$18:$BU$18,N43:BU43)+BZ43 -> 295046.28 | CB43: =Sheet1!CB20 -> 0 | CC43: =CA43*CB43 -> 0 | CD43: 0.18 | CE43: =CA43*CD43 -> 53108.33 | CF43: 0 | CG43: =CA43*CF43 -> 0 | CH43: =CA43+CC43+CE43+CG43 -> 348154.61 | CI43: 0.02 | CJ43: =CH43*CI43 -> 6963.0922 | CK43: 0.01 | CL43: =CH43*CK43 -> 3481.5461 | CM43: 55 | CN43: 20
A44: =Sheet1!A5 -> ENQ-12232-22-23 | B44: 45380 | C44: =Sheet1!C5 -> FA0900024 | D44: =Sheet1!D5 -> 4 CORE X 4 SQ. MM. CU/ARD - WIRE (PVC) | E44: =CH44+CJ44+CL44 -> 205509.3 | F44: =ROUNDUP(M77,0) -> 1500 | G44: =E44+F44 -> 207009.3 | H44: =Sheet1!CP5 -> 0.18 | I44: =G44*H44 -> 37261.674 | J44: =G44+I44 -> 244270.97 | K44: =6+12 -> 18 | L44: =Sheet1!CT5 -> KMS | M44: =J44*K44 -> 4396877.5 | N44: =+IFERROR(VLOOKUP($N$17,Sheet1!J5:L5,3,0),0) -> 0 | O44: =+IFERROR(VLOOKUP($O$17,Sheet1!J5:L5,3,0),0) -> 0 | P44: =+IFERROR(VLOOKUP($P$17,Sheet1!J5:M5,3,0),0) -> 144 | Q44: =+IFERROR(VLOOKUP($Q$17,Sheet1!J5:M5,3,0),0) -> 0 | R44: =+IFERROR(VLOOKUP($R$17,Sheet1!J5:M5,3,0),0) -> 0 | S44: =+IFERROR(VLOOKUP($S$17,Sheet1!N5:Q5,3,0),0) -> 0 | T44: =+IFERROR(VLOOKUP($T$17,Sheet1!N5:Q5,3,0),0) -> 0 | U44: =+IFERROR(VLOOKUP($U$17,Sheet1!F5:I5,3,0),0) -> 0 | V44: =+IFERROR(VLOOKUP($V$17,Sheet1!F5:I5,3,0),0) -> 0 | W44: =+IFERROR(VLOOKUP($W$17,Sheet1!F5:I5,3,0),0) -> 0 | X44: =+IFERROR(VLOOKUP($X$17,Sheet1!F5:I5,3,0),0) -> 0 | Y44: =+IFERROR(VLOOKUP($Y$17,Sheet1!F5:I5,3,0),0) -> 0 | Z44: =+IFERROR(VLOOKUP($Z$17,Sheet1!F5:I5,3,0),0) -> 0 | AA44: =+IFERROR(VLOOKUP($AA$17,Sheet1!F5:I5,3,0),0) -> 0 | AB44: =+IFERROR(VLOOKUP($AB$17,Sheet1!F5:I5,3,0),0) -> 0 | AC44: =+IFERROR(VLOOKUP($AC$17,Sheet1!R5:U5,3,0),0) -> 0 | AD44: =+IFERROR(VLOOKUP($AD$17,Sheet1!R5:U5,2,0),0) -> 0 | AE44: =+IFERROR(VLOOKUP($AE$17,Sheet1!V5:Y5,3,0),0) -> 0 | AF44: =+IFERROR(VLOOKUP($AF$17,Sheet1!V5:Y5,3,0),0) -> 0 | AG44: =+IFERROR(VLOOKUP($AG$17,Sheet1!V5:Y5,3,0),0) -> 0 | AH44: =+IFERROR(VLOOKUP($AH$17,Sheet1!V5:Y5,3,0),0) -> 0 | AI44: =+IFERROR(VLOOKUP($AI$17,Sheet1!V5:Y5,3,0),0) -> 76 | AJ44: =+IFERROR(VLOOKUP($AJ$17,Sheet1!V5:Y5,3,0),0) -> 0 | AK44: =+IFERROR(VLOOKUP($AK$17,Sheet1!Z5:AB5,3,0),0) -> 4 | AL44: =+IFERROR(VLOOKUP($AL$17,Sheet1!AD5:AG5,3,0),0) -> 0 | AM44: =+IFERROR(VLOOKUP($AM$17,Sheet1!AD5:AG5,3,0),0) -> 0 | AN44: =+IFERROR(VLOOKUP($AN$17,Sheet1!AD5:AG5,3,0),0) -> 0 | AO44: =+IFERROR(VLOOKUP($AO$17,Sheet1!AD5:AG5,3,0),0) -> 0 | AP44: =+IFERROR(VLOOKUP($AP$17,Sheet1!AD5:AG5,3,0),0) -> 0 | AQ44: =+IFERROR(VLOOKUP($AQ$17,Sheet1!AD5:AG5,3,0),0) -> 34 | AR44: =+IFERROR(VLOOKUP($AR$17,Sheet1!AD5:AG5,3,0),0) -> 0 | AS44: =+IFERROR(VLOOKUP($AS$17,Sheet1!AH5:AK5,3,0),0) -> 0 | AT44: =+IFERROR(VLOOKUP($AT$17,Sheet1!AH5:AK5,3,0),0) -> 0 | AU44: =+IFERROR(VLOOKUP($AU$17,Sheet1!AH5:AK5,3,0),0) -> 0 | AV44: =+IFERROR(VLOOKUP($AV$17,Sheet1!AH5:AK5,3,0),0) -> 0 | AW44: =+IFERROR(VLOOKUP($AW$17,Sheet1!AH5:AK5,3,0),0) -> 0 | AX44: =+IFERROR(VLOOKUP($AX$17,Sheet1!AH5:AK5,3,0),0) -> 0 | AY44: =+IFERROR(VLOOKUP($AY$17,Sheet1!AH5:AK5,3,0),0) -> 0 | AZ44: =+IFERROR(VLOOKUP($AZ$17,Sheet1!AH5:AK5,3,0),0) -> 0 | BA44: =+IFERROR(VLOOKUP($BA$17,Sheet1!AH5:AK5,3,0),0) -> 352 | BB44: =+IFERROR(VLOOKUP($BB$17,Sheet1!AH5:AK5,3,0),0) -> 0 | BC44: =+IFERROR(VLOOKUP($BC$17,Sheet1!AL5:AO5,3,0),0) -> 0 | BD44: =+IFERROR(VLOOKUP($BD$17,Sheet1!AL5:AO5,3,0),0) -> 0 | BE44: =+IFERROR(VLOOKUP($BE$17,Sheet1!AL5:AO5,3,0),0) -> 0 | BF44: =+IFERROR(VLOOKUP($BF$17,Sheet1!AL5:AO5,3,0),0) -> 119 | BG44: =+IFERROR(VLOOKUP($BG$17,Sheet1!AL5:AO5,3,0),0) -> 0 | BH44: =+IFERROR(VLOOKUP($BH$17,Sheet1!AL5:AO5,3,0),0) -> 0 | BI44: =+IFERROR(VLOOKUP($BI$17,Sheet1!AL5:AO5,3,0),0) -> 0 | BJ44: =+IFERROR(VLOOKUP($BJ$17,Sheet1!AL5:AO5,3,0),0) -> 0 | BK44: =+IFERROR(VLOOKUP($BK$17,Sheet1!AL5:AO5,3,0),0) -> 0 | BL44: =+IFERROR(VLOOKUP($BL$17,Sheet1!AL5:AO5,3,0),0) -> 0 | BM44: =+IFERROR(VLOOKUP($BM$17,Sheet1!AP5:AS5,3,0),0) -> 0 | BN44: =+IFERROR(VLOOKUP($BN$17,Sheet1!AT5:AW5,3,0),0) -> 0 | BO44: =+IFERROR(VLOOKUP($BO$17,Sheet1!AX5:BA5,3,0),0) -> 0 | BP44: =+IFERROR(VLOOKUP($BP$17,Sheet1!BB5:BE5,3,0),0) -> 0 | BQ44: =+IFERROR(VLOOKUP($BQ$17,Sheet1!BF5:BI5,3,0),0) -> 0 | BR44: =+IFERROR(VLOOKUP($BR$17,Sheet1!BJ5:BM5,3,0),0) -> 0 | BS44: =+IFERROR(VLOOKUP($BS$17,Sheet1!BN5:BQ5,3,0),0) -> 0 | BT44: =+IFERROR(VLOOKUP($BT$17,Sheet1!BR5:BU5,3,0),0) -> 0 | BU44: =+IFERROR(VLOOKUP($BU$17,Sheet1!BV5:BY5,3,0),0) -> 0 | BV44: =Sheet1!E5 -> WOOD | BW44: =Sheet1!CV5 -> MD0100005 | BX44: =Sheet1!CW5 -> DRUM - 36 X 14 X 23 X 2 | BY44: =Sheet1!CX5 -> 500 | BZ44: =Sheet1!BZ5 -> 4610.79 | CA44: =SUMPRODUCT($N$18:$BU$18,N44:BU44)+BZ44 -> 169087.79 | CB44: =Sheet1!CB5 -> 0 | CC44: =CA44*CB44 -> 0 | CD44: 0.18 | CE44: =CA44*CD44 -> 30435.802 | CF44: 0 | CG44: =CA44*CF44 -> 0 | CH44: =CA44+CC44+CE44+CG44 -> 199523.59 | CI44: 0.02 | CJ44: =CH44*CI44 -> 3990.4718 | CK44: 0.01 | CL44: =CH44*CK44 -> 1995.2359 | CM44: 50 | CN44: 15
A45: =Sheet1!A4 -> ENQ-12232-22-23 | B45: 45380 | C45: FA0900052 | D45: 4 CORE X 16 SQ. MM. CU/ARD - WIRE (XLPE) | E45: =CH45+CJ45+CL45 -> 631814.41 | F45: =ROUNDUP(M78,0) -> 18000 | G45: =E45+F45 -> 649814.41 | H45: =Sheet1!CP4 -> 0.18 | I45: =G45*H45 -> 116966.59 | J45: =G45+I45 -> 766781.01 | K45: =Sheet1!CS4 -> 1.5 | L45: =Sheet1!CT4 -> KMS | M45: =J45*K45 -> 1150171.5 | N45: =+IFERROR(VLOOKUP($N$17,Sheet1!J4:L4,3,0),0) -> 0 | O45: =+IFERROR(VLOOKUP($O$17,Sheet1!J4:L4,3,0),0) -> 0 | P45: =+IFERROR(VLOOKUP($P$17,Sheet1!J4:M4,3,0),0) -> 568.96 | Q45: =+IFERROR(VLOOKUP($Q$17,Sheet1!J4:M4,3,0),0) -> 0 | R45: =+IFERROR(VLOOKUP($R$17,Sheet1!J4:M4,3,0),0) -> 0 | S45: =+IFERROR(VLOOKUP($S$17,Sheet1!N4:Q4,3,0),0) -> 0 | T45: =+IFERROR(VLOOKUP($T$17,Sheet1!N4:Q4,3,0),0) -> 0 | U45: =+IFERROR(VLOOKUP($U$17,Sheet1!F4:I4,3,0),0) -> 0 | V45: =+IFERROR(VLOOKUP($V$17,Sheet1!F4:I4,3,0),0) -> 0 | W45: =+IFERROR(VLOOKUP($W$17,Sheet1!F4:I4,3,0),0) -> 0 | X45: =+IFERROR(VLOOKUP($X$17,Sheet1!F4:I4,3,0),0) -> 0 | Y45: =+IFERROR(VLOOKUP($Y$17,Sheet1!F4:I4,3,0),0) -> 0 | Z45: =+IFERROR(VLOOKUP($Z$17,Sheet1!F4:I4,3,0),0) -> 0 | AA45: =+IFERROR(VLOOKUP($AA$17,Sheet1!F4:I4,3,0),0) -> 0 | AB45: =+IFERROR(VLOOKUP($AB$17,Sheet1!F4:I4,3,0),0) -> 0 | AC45: =+IFERROR(VLOOKUP($AC$17,Sheet1!R4:U4,3,0),0) -> 0 | AD45: =+IFERROR(VLOOKUP($AD$17,Sheet1!R4:U4,2,0),0) -> 0 | AE45: =+IFERROR(VLOOKUP($AE$17,Sheet1!V4:Y4,3,0),0) -> 0 | AF45: 58 | AG45: =+IFERROR(VLOOKUP($AG$17,Sheet1!V4:Y4,3,0),0) -> 0 | AH45: =+IFERROR(VLOOKUP($AH$17,Sheet1!V4:Y4,3,0),0) -> 0 | AJ45: =+IFERROR(VLOOKUP($AJ$17,Sheet1!V4:Y4,3,0),0) -> 0 | AK45: =+IFERROR(VLOOKUP($AK$17,Sheet1!Z4:AB4,3,0),0) -> 0 | AL45: =+IFERROR(VLOOKUP($AL$17,Sheet1!AD4:AG4,3,0),0) -> 0 | AM45: =+IFERROR(VLOOKUP($AM$17,Sheet1!AD4:AG4,3,0),0) -> 0 | AN45: =+IFERROR(VLOOKUP($AN$17,Sheet1!AD4:AG4,3,0),0) -> 0 | AO45: =+IFERROR(VLOOKUP($AO$17,Sheet1!AD4:AG4,3,0),0) -> 0 | AP45: =+IFERROR(VLOOKUP($AP$17,Sheet1!AD4:AG4,3,0),0) -> 0 | AQ45: 38 | AR45: =+IFERROR(VLOOKUP($AR$17,Sheet1!AD4:AG4,3,0),0) -> 0 | AS45: =+IFERROR(VLOOKUP($AS$17,Sheet1!AH4:AK4,3,0),0) -> 0 | AT45: =+IFERROR(VLOOKUP($AT$17,Sheet1!AH4:AK4,3,0),0) -> 0 | AU45: =+IFERROR(VLOOKUP($AU$17,Sheet1!AH4:AK4,3,0),0) -> 0 | AV45: =+IFERROR(VLOOKUP($AV$17,Sheet1!AH4:AK4,3,0),0) -> 0 | AW45: =+IFERROR(VLOOKUP($AW$17,Sheet1!AH4:AK4,3,0),0) -> 0 | AX45: =+IFERROR(VLOOKUP($AX$17,Sheet1!AH4:AK4,3,0),0) -> 0 | AY45: =+IFERROR(VLOOKUP($AY$17,Sheet1!AH4:AK4,3,0),0) -> 0 | AZ45: =+IFERROR(VLOOKUP($AZ$17,Sheet1!AH4:AK4,3,0),0) -> 0 | BA45: 460 | BB45: =+IFERROR(VLOOKUP($BB$17,Sheet1!AH4:AK4,3,0),0) -> 0 | BC45: =+IFERROR(VLOOKUP($BC$17,Sheet1!AL4:AO4,3,0),0) -> 0 | BD45: =+IFERROR(VLOOKUP($BD$17,Sheet1!AL4:AO4,3,0),0) -> 0 | BE45: =+IFERROR(VLOOKUP($BE$17,Sheet1!AL4:AO4,3,0),0) -> 0 | BF45: 158 | BG45: =+IFERROR(VLOOKUP($BG$17,Sheet1!AL4:AO4,3,0),0) -> 0 | BH45: =+IFERROR(VLOOKUP($BH$17,Sheet1!AL4:AO4,3,0),0) -> 0 | BI45: =+IFERROR(VLOOKUP($BI$17,Sheet1!AL4:AO4,3,0),0) -> 0 | BJ45: =+IFERROR(VLOOKUP($BJ$17,Sheet1!AL4:AO4,3,0),0) -> 0 | BK45: =+IFERROR(VLOOKUP($BK$17,Sheet1!AL4:AO4,3,0),0) -> 0 | BL45: =+IFERROR(VLOOKUP($BL$17,Sheet1!AL4:AO4,3,0),0) -> 0 | BM45: =+IFERROR(VLOOKUP($BM$17,Sheet1!AP4:AS4,3,0),0) -> 0 | BN45: =+IFERROR(VLOOKUP($BN$17,Sheet1!AT4:AW4,3,0),0) -> 0 | BO45: =+IFERROR(VLOOKUP($BO$17,Sheet1!AX4:BA4,3,0),0) -> 0 | BP45: =+IFERROR(VLOOKUP($BP$17,Sheet1!BB4:BE4,3,0),0) -> 0 | BQ45: =+IFERROR(VLOOKUP($BQ$17,Sheet1!BF4:BI4,3,0),0) -> 0 | BR45: =+IFERROR(VLOOKUP($BR$17,Sheet1!BJ4:BM4,3,0),0) -> 0 | BS45: =+IFERROR(VLOOKUP($BS$17,Sheet1!BN4:BQ4,3,0),0) -> 0 | BT45: 14 | BU45: =+IFERROR(VLOOKUP($BU$17,Sheet1!BV4:BY4,3,0),0) -> 0 | BV45: =Sheet1!E4 -> WOOD | BW45: MD0100060 | BX45: DRUM - 52 X 25 X 28 X 3 | BY45: 1000 | BZ45: 6186 | CA45: =SUMPRODUCT($N$18:$BU$18,N45:BU45)+BZ45 -> 519840.72 | CB45: =Sheet1!CB4 -> 0 | CC45: =CA45*CB45 -> 0 | CD45: 0.18 | CE45: =CA45*CD45 -> 93571.33 | CF45: 0 | CG45: =CA45*CF45 -> 0 | CH45: =CA45+CC45+CE45+CG45 -> 613412.05 | CI45: 0.02 | CJ45: =CH45*CI45 -> 12268.241 | CK45: 0.01 | CL45: =CH45*CK45 -> 6134.1205 | CM45: 120 | CN45: 30
A46: =Sheet1!A7 -> ENQ-12232-22-23 | B46: 45380 | C46: FA0900121 | D46: 4 CORE X 10 SQ. MM. CU/ARD - WIRE (XLPE) | E46: =CH46+CJ46+CL46 -> 416153.2 | F46: =ROUNDUP(M79,0) -> 9000 | G46: =E46+F46 -> 425153.2 | H46: =Sheet1!CP7 -> 0.18 | I46: =G46*H46 -> 76527.577 | J46: =G46+I46 -> 501680.78 | K46: =Sheet1!CS7 -> 3 | L46: =Sheet1!CT7 -> KMS | M46: =J46*K46 -> 1505042.3 | N46: =+IFERROR(VLOOKUP($N$17,Sheet1!J7:L7,3,0),0) -> 0 | O46: =+IFERROR(VLOOKUP($O$17,Sheet1!J7:L7,3,0),0) -> 0 | P46: =+IFERROR(VLOOKUP($P$17,Sheet1!J7:M7,3,0),0) -> 355.6 | Q46: =+IFERROR(VLOOKUP($Q$17,Sheet1!J7:M7,3,0),0) -> 0 | R46: =+IFERROR(VLOOKUP($R$17,Sheet1!J7:M7,3,0),0) -> 0 | S46: =+IFERROR(VLOOKUP($S$17,Sheet1!N7:Q7,3,0),0) -> 0 | T46: =+IFERROR(VLOOKUP($T$17,Sheet1!N7:Q7,3,0),0) -> 0 | U46: =+IFERROR(VLOOKUP($U$17,Sheet1!F7:I7,3,0),0) -> 0 | V46: =+IFERROR(VLOOKUP($V$17,Sheet1!F7:I7,3,0),0) -> 0 | W46: =+IFERROR(VLOOKUP($W$17,Sheet1!F7:I7,3,0),0) -> 0 | X46: =+IFERROR(VLOOKUP($X$17,Sheet1!F7:I7,3,0),0) -> 0 | Y46: =+IFERROR(VLOOKUP($Y$17,Sheet1!F7:I7,3,0),0) -> 0 | Z46: =+IFERROR(VLOOKUP($Z$17,Sheet1!F7:I7,3,0),0) -> 0 | AA46: =+IFERROR(VLOOKUP($AA$17,Sheet1!F7:I7,3,0),0) -> 0 | AB46: =+IFERROR(VLOOKUP($AB$17,Sheet1!F7:I7,3,0),0) -> 0 | AC46: =+IFERROR(VLOOKUP($AC$17,Sheet1!R7:U7,3,0),0) -> 0 | AD46: =+IFERROR(VLOOKUP($AD$17,Sheet1!R7:U7,2,0),0) -> 0 | AE46: =+IFERROR(VLOOKUP($AE$17,Sheet1!V7:Y7,3,0),0) -> 0 | AF46: 50 | AG46: =+IFERROR(VLOOKUP($AG$17,Sheet1!V7:Y7,3,0),0) -> 0 | AI46: =+IFERROR(VLOOKUP($AI$17,Sheet1!V7:Y7,3,0),0) -> 0 | AJ46: =+IFERROR(VLOOKUP($AJ$17,Sheet1!V7:Y7,3,0),0) -> 0 | AK46: =+IFERROR(VLOOKUP($AK$17,Sheet1!Z7:AB7,3,0),0) -> 0 | AL46: =+IFERROR(VLOOKUP($AL$17,Sheet1!AD7:AG7,3,0),0) -> 0 | AM46: =+IFERROR(VLOOKUP($AM$17,Sheet1!AD7:AG7,3,0),0) -> 0 | AN46: =+IFERROR(VLOOKUP($AN$17,Sheet1!AD7:AG7,3,0),0) -> 0 | AP46: =+IFERROR(VLOOKUP($AP$17,Sheet1!AD7:AG7,3,0),0) -> 0 | AQ46: 35 | AR46: =+IFERROR(VLOOKUP($AR$17,Sheet1!AD7:AG7,3,0),0) -> 0 | AS46: =+IFERROR(VLOOKUP($AS$17,Sheet1!AH7:AK7,3,0),0) -> 0 | AT46: =+IFERROR(VLOOKUP($AT$17,Sheet1!AH7:AK7,3,0),0) -> 0 | AU46: =+IFERROR(VLOOKUP($AU$17,Sheet1!AH7:AK7,3,0),0) -> 0 | AV46: =+IFERROR(VLOOKUP($AV$17,Sheet1!AH7:AK7,3,0),0) -> 0 | AW46: =+IFERROR(VLOOKUP($AW$17,Sheet1!AH7:AK7,3,0),0) -> 0 | AX46: =+IFERROR(VLOOKUP($AX$17,Sheet1!AH7:AK7,3,0),0) -> 0 | AY46: =+IFERROR(VLOOKUP($AY$17,Sheet1!AH7:AK7,3,0),0) -> 0 | AZ46: =+IFERROR(VLOOKUP($AZ$17,Sheet1!AH7:AK7,3,0),0) -> 0 | BA46: 377 | BB46: =+IFERROR(VLOOKUP($BB$17,Sheet1!AH7:AK7,3,0),0) -> 0 | BC46: =+IFERROR(VLOOKUP($BC$17,Sheet1!AL7:AO7,3,0),0) -> 0 | BD46: =+IFERROR(VLOOKUP($BD$17,Sheet1!AL7:AO7,3,0),0) -> 0 | BE46: =+IFERROR(VLOOKUP($BE$17,Sheet1!AL7:AO7,3,0),0) -> 0 | BF46: 151 | BG46: =+IFERROR(VLOOKUP($BG$17,Sheet1!AL7:AO7,3,0),0) -> 0 | BH46: =+IFERROR(VLOOKUP($BH$17,Sheet1!AL7:AO7,3,0),0) -> 0 | BJ46: =+IFERROR(VLOOKUP($BJ$17,Sheet1!AL7:AO7,3,0),0) -> 0 | BK46: =+IFERROR(VLOOKUP($BK$17,Sheet1!AL7:AO7,3,0),0) -> 0 | BL46: =+IFERROR(VLOOKUP($BL$17,Sheet1!AL7:AO7,3,0),0) -> 0 | BM46: =+IFERROR(VLOOKUP($BM$17,Sheet1!AP7:AS7,3,0),0) -> 0 | BN46: =+IFERROR(VLOOKUP($BN$17,Sheet1!AT7:AW7,3,0),0) -> 0 | BO46: =+IFERROR(VLOOKUP($BO$17,Sheet1!AX7:BA7,3,0),0) -> 0 | BP46: =+IFERROR(VLOOKUP($BP$17,Sheet1!BB7:BE7,3,0),0) -> 0 | BQ46: =+IFERROR(VLOOKUP($BQ$17,Sheet1!BF7:BI7,3,0),0) -> 0 | BR46: =+IFERROR(VLOOKUP($BR$17,Sheet1!BJ7:BM7,3,0),0) -> 0 | BS46: =+IFERROR(VLOOKUP($BS$17,Sheet1!BN7:BQ7,3,0),0) -> 0 | BT46: 13.5 | BU46: =+IFERROR(VLOOKUP($BU$17,Sheet1!BV7:BY7,3,0),0) -> 0 | BV46: =Sheet1!E7 -> WOOD | BW46: MD0100116 | BX46: DRUM - 48 X 24 X 28 X 2 | BY46: 1000 | BZ46: 4342 | CA46: =SUMPRODUCT($N$18:$BU$18,N46:BU46)+BZ46 -> 342400.2 | CB46: =Sheet1!CB7 -> 0 | CC46: =CA46*CB46 -> 0 | CD46: 0.18 | CE46: =CA46*CD46 -> 61632.036 | CF46: 0 | CG46: =CA46*CF46 -> 0 | CH46: =CA46+CC46+CE46+CG46 -> 404032.24 | CI46: 0.02 | CJ46: =CH46*CI46 -> 8080.6447 | CK46: 0.01 | CL46: =CH46*CK46 -> 4040.3224 | CM46: 100 | CN46: 25
A47: =Sheet1!A2 -> ENQ-12232-22-23 | B47: 45380 | C47: FA0800019 | D47: 1 CORE X 16 SQ. MM. CU/ARD (XLPE) | E47: =CH47+CJ47+CL47 -> 173830.25 | F47: =ROUNDUP(M80,0) -> 225000 | G47: =E47+F47 -> 398830.25 | H47: =Sheet1!CP2 -> 0.18 | I47: =G47*H47 -> 71789.445 | J47: =G47+I47 -> 470619.7 | K47: =Sheet1!CS2 -> 0.12 | L47: =Sheet1!CT2 -> KMS | M47: =J47*K47 -> 56474.364 | N47: =+IFERROR(VLOOKUP($N$17,Sheet1!J2:L2,3,0),0) -> 0 | O47: =+IFERROR(VLOOKUP($O$17,Sheet1!J2:L2,3,0),0) -> 0 | P47: =+IFERROR(VLOOKUP($P$17,Sheet1!J2:M2,3,0),0) -> 142.24 | Q47: =+IFERROR(VLOOKUP($Q$17,Sheet1!J2:M2,3,0),0) -> 0 | R47: =+IFERROR(VLOOKUP($R$17,Sheet1!J2:M2,3,0),0) -> 0 | S47: =+IFERROR(VLOOKUP($S$17,Sheet1!N2:Q2,3,0),0) -> 0 | T47: =+IFERROR(VLOOKUP($T$17,Sheet1!N2:Q2,3,0),0) -> 0 | U47: =+IFERROR(VLOOKUP($U$17,Sheet1!F2:I2,3,0),0) -> 0 | V47: =+IFERROR(VLOOKUP($V$17,Sheet1!F2:I2,3,0),0) -> 0 | W47: =+IFERROR(VLOOKUP($W$17,Sheet1!F2:I2,3,0),0) -> 0 | X47: =+IFERROR(VLOOKUP($X$17,Sheet1!F2:I2,3,0),0) -> 0 | Y47: =+IFERROR(VLOOKUP($Y$17,Sheet1!F2:I2,3,0),0) -> 0 | Z47: =+IFERROR(VLOOKUP($Z$17,Sheet1!F2:I2,3,0),0) -> 0 | AA47: =+IFERROR(VLOOKUP($AA$17,Sheet1!F2:I2,3,0),0) -> 0 | AB47: =+IFERROR(VLOOKUP($AB$17,Sheet1!F2:I2,3,0),0) -> 0 | AC47: =+IFERROR(VLOOKUP($AC$17,Sheet1!R2:U2,3,0),0) -> 0 | AD47: =+IFERROR(VLOOKUP($AD$17,Sheet1!R2:U2,2,0),0) -> 0 | AE47: =+IFERROR(VLOOKUP($AE$17,Sheet1!V2:Y2,3,0),0) -> 0 | AF47: 22 | AG47: =+IFERROR(VLOOKUP($AG$17,Sheet1!V2:Y2,3,0),0) -> 0 | AH47: =+IFERROR(VLOOKUP($AH$17,Sheet1!V2:Y2,3,0),0) -> 0 | AJ47: =+IFERROR(VLOOKUP($AJ$17,Sheet1!V2:Y2,3,0),0) -> 0 | AK47: =+IFERROR(VLOOKUP($AK$17,Sheet1!Z2:AB2,3,0),0) -> 0 | AL47: =+IFERROR(VLOOKUP($AL$17,Sheet1!AD2:AG2,3,0),0) -> 0 | AM47: =+IFERROR(VLOOKUP($AM$17,Sheet1!AD2:AG2,3,0),0) -> 0 | AN47: =+IFERROR(VLOOKUP($AN$17,Sheet1!AD2:AG2,3,0),0) -> 0 | AO47: =+IFERROR(VLOOKUP($AO$17,Sheet1!AD2:AG2,3,0),0) -> 0 | AP47: =+IFERROR(VLOOKUP($AP$17,Sheet1!AD2:AG2,3,0),0) -> 0 | AQ47: =+IFERROR(VLOOKUP($AQ$17,Sheet1!AD2:AG2,3,0),0) -> 0 | AR47: =+IFERROR(VLOOKUP($AR$17,Sheet1!AD2:AG2,3,0),0) -> 0 | AS47: =+IFERROR(VLOOKUP($AS$17,Sheet1!AH2:AK2,3,0),0) -> 0 | AT47: =+IFERROR(VLOOKUP($AT$17,Sheet1!AH2:AK2,3,0),0) -> 0 | AU47: =+IFERROR(VLOOKUP($AU$17,Sheet1!AH2:AK2,3,0),0) -> 0 | AV47: 62 | AW47: =+IFERROR(VLOOKUP($AW$17,Sheet1!AH2:AK2,3,0),0) -> 0 | AX47: =+IFERROR(VLOOKUP($AX$17,Sheet1!AH2:AK2,3,0),0) -> 0 | AY47: =+IFERROR(VLOOKUP($AY$17,Sheet1!AH2:AK2,3,0),0) -> 0 | AZ47: =+IFERROR(VLOOKUP($AZ$17,Sheet1!AH2:AK2,3,0),0) -> 0 | BA47: =+IFERROR(VLOOKUP($BA$17,Sheet1!AH2:AK2,3,0),0) -> 0 | BB47: =+IFERROR(VLOOKUP($BB$17,Sheet1!AH2:AK2,3,0),0) -> 0 | BC47: =+IFERROR(VLOOKUP($BC$17,Sheet1!AL2:AO2,3,0),0) -> 0 | BD47: =+IFERROR(VLOOKUP($BD$17,Sheet1!AL2:AO2,3,0),0) -> 0 | BE47: =+IFERROR(VLOOKUP($BE$17,Sheet1!AL2:AO2,3,0),0) -> 0 | BF47: =+IFERROR(VLOOKUP($BF$17,Sheet1!AL2:AO2,3,0),0) -> 88 | BG47: =+IFERROR(VLOOKUP($BG$17,Sheet1!AL2:AO2,3,0),0) -> 0 | BH47: =+IFERROR(VLOOKUP($BH$17,Sheet1!AL2:AO2,3,0),0) -> 0 | BI47: =+IFERROR(VLOOKUP($BI$17,Sheet1!AL2:AO2,3,0),0) -> 0 | BJ47: =+IFERROR(VLOOKUP($BJ$17,Sheet1!AL2:AO2,3,0),0) -> 0 | BK47: =+IFERROR(VLOOKUP($BK$17,Sheet1!AL2:AO2,3,0),0) -> 0 | BL47: =+IFERROR(VLOOKUP($BL$17,Sheet1!AL2:AO2,3,0),0) -> 0 | BM47: =+IFERROR(VLOOKUP($BM$17,Sheet1!AP2:AS2,3,0),0) -> 0 | BN47: =+IFERROR(VLOOKUP($BN$17,Sheet1!AT2:AW2,3,0),0) -> 0 | BO47: =+IFERROR(VLOOKUP($BO$17,Sheet1!AX2:BA2,3,0),0) -> 0 | BP47: =+IFERROR(VLOOKUP($BP$17,Sheet1!BB2:BE2,3,0),0) -> 0 | BQ47: =+IFERROR(VLOOKUP($BQ$17,Sheet1!BF2:BI2,3,0),0) -> 0 | BR47: =+IFERROR(VLOOKUP($BR$17,Sheet1!BJ2:BM2,3,0),0) -> 0 | BS47: =+IFERROR(VLOOKUP($BS$17,Sheet1!BN2:BQ2,3,0),0) -> 0 | BT47: 8 | BU47: =+IFERROR(VLOOKUP($BU$17,Sheet1!BV2:BY2,3,0),0) -> 0 | BV47: =Sheet1!E2 -> WOOD | BW47: MD0100005 | BX47: DRUM - 36 X 14 X 23 X 2 | BY47: 1000 | BZ47: 2305.4 | CA47: =SUMPRODUCT($N$18:$BU$18,N47:BU47)+BZ47 -> 143023.08 | CB47: =Sheet1!CB2 -> 0 | CC47: =CA47*CB47 -> 0 | CD47: 0.18 | CE47: =CA47*CD47 -> 25744.154 | CF47: 0 | CG47: =CA47*CF47 -> 0 | CH47: =CA47+CC47+CE47+CG47 -> 168767.23 | CI47: 0.02 | CJ47: =CH47*CI47 -> 3375.3447 | CK47: 0.01 | CL47: =CH47*CK47 -> 1687.6723 | CM47: 50 | CN47: 15
A48: =Sheet1!A6 -> ENQ-12232-22-23 | B48: 45380 | C48: FA0900171 | D48: 2 CORE X 16 SQ. MM. CU/ARD - WIRE (XLPE) | E48: =CH48+CJ48+CL48 -> 357448.36 | F48: =ROUNDUP(M81,0) -> 12736 | G48: =E48+F48 -> 370184.36 | H48: =Sheet1!CP6 -> 0.18 | I48: =G48*H48 -> 66633.185 | J48: =G48+I48 -> 436817.55 | K48: =Sheet1!CS6 -> 2.12 | L48: =Sheet1!CT6 -> KMS | M48: =J48*K48 -> 926053.2 | N48: =+IFERROR(VLOOKUP($N$17,Sheet1!J6:L6,3,0),0) -> 0 | O48: =+IFERROR(VLOOKUP($O$17,Sheet1!J6:L6,3,0),0) -> 0 | P48: =+IFERROR(VLOOKUP($P$17,Sheet1!J6:M6,3,0),0) -> 284.48 | Q48: =+IFERROR(VLOOKUP($Q$17,Sheet1!J6:M6,3,0),0) -> 0 | R48: =+IFERROR(VLOOKUP($R$17,Sheet1!J6:M6,3,0),0) -> 0 | S48: =+IFERROR(VLOOKUP($S$17,Sheet1!N6:Q6,3,0),0) -> 0 | T48: =+IFERROR(VLOOKUP($T$17,Sheet1!N6:Q6,3,0),0) -> 0 | U48: =+IFERROR(VLOOKUP($U$17,Sheet1!F6:I6,3,0),0) -> 0 | V48: =+IFERROR(VLOOKUP($V$17,Sheet1!F6:I6,3,0),0) -> 0 | W48: =+IFERROR(VLOOKUP($W$17,Sheet1!F6:I6,3,0),0) -> 0 | X48: =+IFERROR(VLOOKUP($X$17,Sheet1!F6:I6,3,0),0) -> 0 | Y48: =+IFERROR(VLOOKUP($Y$17,Sheet1!F6:I6,3,0),0) -> 0 | Z48: =+IFERROR(VLOOKUP($Z$17,Sheet1!F6:I6,3,0),0) -> 0 | AA48: =+IFERROR(VLOOKUP($AA$17,Sheet1!F6:I6,3,0),0) -> 0 | AB48: =+IFERROR(VLOOKUP($AB$17,Sheet1!F6:I6,3,0),0) -> 0 | AC48: =+IFERROR(VLOOKUP($AC$17,Sheet1!R6:U6,3,0),0) -> 0 | AD48: =+IFERROR(VLOOKUP($AD$17,Sheet1!R6:U6,2,0),0) -> 0 | AE48: =+IFERROR(VLOOKUP($AE$17,Sheet1!V6:Y6,3,0),0) -> 0 | AF48: 29 | AG48: =+IFERROR(VLOOKUP($AG$17,Sheet1!V6:Y6,3,0),0) -> 0 | AH48: =+IFERROR(VLOOKUP($AH$17,Sheet1!V6:Y6,3,0),0) -> 0 | AJ48: =+IFERROR(VLOOKUP($AJ$17,Sheet1!V6:Y6,3,0),0) -> 0 | AK48: =+IFERROR(VLOOKUP($AK$17,Sheet1!Z6:AB6,3,0),0) -> 0 | AL48: =+IFERROR(VLOOKUP($AL$17,Sheet1!AD6:AG6,3,0),0) -> 0 | AM48: =+IFERROR(VLOOKUP($AM$17,Sheet1!AD6:AG6,3,0),0) -> 0 | AN48: =+IFERROR(VLOOKUP($AN$17,Sheet1!AD6:AG6,3,0),0) -> 0 | AO48: =+IFERROR(VLOOKUP($AO$17,Sheet1!AD6:AG6,3,0),0) -> 0 | AP48: =+IFERROR(VLOOKUP($AP$17,Sheet1!AD6:AG6,3,0),0) -> 0 | AQ48: 60 | AR48: =+IFERROR(VLOOKUP($AR$17,Sheet1!AD6:AG6,3,0),0) -> 0 | AS48: =+IFERROR(VLOOKUP($AS$17,Sheet1!AH6:AK6,3,0),0) -> 0 | AT48: =+IFERROR(VLOOKUP($AT$17,Sheet1!AH6:AK6,3,0),0) -> 0 | AU48: =+IFERROR(VLOOKUP($AU$17,Sheet1!AH6:AK6,3,0),0) -> 0 | AV48: =+IFERROR(VLOOKUP($AV$17,Sheet1!AH6:AK6,3,0),0) -> 0 | AW48: =+IFERROR(VLOOKUP($AW$17,Sheet1!AH6:AK6,3,0),0) -> 0 | AX48: =+IFERROR(VLOOKUP($AX$17,Sheet1!AH6:AK6,3,0),0) -> 0 | AY48: =+IFERROR(VLOOKUP($AY$17,Sheet1!AH6:AK6,3,0),0) -> 0 | AZ48: =+IFERROR(VLOOKUP($AZ$17,Sheet1!AH6:AK6,3,0),0) -> 0 | BA48: 487 | BB48: =+IFERROR(VLOOKUP($BB$17,Sheet1!AH6:AK6,3,0),0) -> 0 | BC48: =+IFERROR(VLOOKUP($BC$17,Sheet1!AL6:AO6,3,0),0) -> 0 | BD48: =+IFERROR(VLOOKUP($BD$17,Sheet1!AL6:AO6,3,0),0) -> 0 | BE48: =+IFERROR(VLOOKUP($BE$17,Sheet1!AL6:AO6,3,0),0) -> 0 | BF48: 150 | BG48: =+IFERROR(VLOOKUP($BG$17,Sheet1!AL6:AO6,3,0),0) -> 0 | BH48: =+IFERROR(VLOOKUP($BH$17,Sheet1!AL6:AO6,3,0),0) -> 0 | BI48: =+IFERROR(VLOOKUP($BI$17,Sheet1!AL6:AO6,3,0),0) -> 0 | BJ48: =+IFERROR(VLOOKUP($BJ$17,Sheet1!AL6:AO6,3,0),0) -> 0 | BK48: =+IFERROR(VLOOKUP($BK$17,Sheet1!AL6:AO6,3,0),0) -> 0 | BL48: =+IFERROR(VLOOKUP($BL$17,Sheet1!AL6:AO6,3,0),0) -> 0 | BM48: =+IFERROR(VLOOKUP($BM$17,Sheet1!AP6:AS6,3,0),0) -> 0 | BN48: =+IFERROR(VLOOKUP($BN$17,Sheet1!AT6:AW6,3,0),0) -> 0 | BO48: =+IFERROR(VLOOKUP($BO$17,Sheet1!AX6:BA6,3,0),0) -> 0 | BP48: =+IFERROR(VLOOKUP($BP$17,Sheet1!BB6:BE6,3,0),0) -> 0 | BQ48: =+IFERROR(VLOOKUP($BQ$17,Sheet1!BF6:BI6,3,0),0) -> 0 | BR48: =+IFERROR(VLOOKUP($BR$17,Sheet1!BJ6:BM6,3,0),0) -> 0 | BS48: =+IFERROR(VLOOKUP($BS$17,Sheet1!BN6:BQ6,3,0),0) -> 0 | BT48: 13 | BU48: =+IFERROR(VLOOKUP($BU$17,Sheet1!BV6:BY6,3,0),0) -> 0 | BV48: =Sheet1!E6 -> WOOD | BW48: MD0100075 | BX48: DRUM - 42 X 15 X 23 X 2 | BY48: 1000 | BZ48: 3542 | CA48: =SUMPRODUCT($N$18:$BU$18,N48:BU48)+BZ48 -> 294099.36 | CB48: =Sheet1!CB6 -> 0 | CC48: =CA48*CB48 -> 0 | CD48: 0.18 | CE48: =CA48*CD48 -> 52937.885 | CF48: 0 | CG48: =CA48*CF48 -> 0 | CH48: =CA48+CC48+CE48+CG48 -> 347037.24 | CI48: 0.02 | CJ48: =CH48*CI48 -> 6940.7449 | CK48: 0.01 | CL48: =CH48*CK48 -> 3470.3724 | CM48: 55 | CN48: 20
A49: =Sheet1!A8 -> ENQ-12232-22-23 | B49: 45380 | C49: FA0900229 | D49: 2 CORE X 50 SQ. MM. CU/ARD - WIRE (XLPE) | E49: =CH49+CJ49+CL49 -> 975668.43 | F49: =ROUNDUP(M82,0) -> 7398 | G49: =E49+F49 -> 983066.43 | H49: =Sheet1!CP8 -> 0.18 | I49: =G49*H49 -> 176951.96 | J49: =G49+I49 -> 1160018.4 | K49: =Sheet1!CS8 -> 3.65 | L49: =Sheet1!CT8 -> KMS | M49: =J49*K49 -> 4234067.1 | N49: =+IFERROR(VLOOKUP($N$17,Sheet1!J8:L8,3,0),0) -> 0 | O49: =+IFERROR(VLOOKUP($O$17,Sheet1!J8:L8,3,0),0) -> 0 | P49: =+IFERROR(VLOOKUP($P$17,Sheet1!J8:M8,3,0),0) -> 860 | Q49: =+IFERROR(VLOOKUP($Q$17,Sheet1!J8:M8,3,0),0) -> 0 | R49: =+IFERROR(VLOOKUP($R$17,Sheet1!J8:M8,3,0),0) -> 0 | S49: =+IFERROR(VLOOKUP($S$17,Sheet1!N8:Q8,3,0),0) -> 0 | T49: =+IFERROR(VLOOKUP($T$17,Sheet1!N8:Q8,3,0),0) -> 0 | U49: =+IFERROR(VLOOKUP($U$17,Sheet1!F8:I8,3,0),0) -> 0 | V49: =+IFERROR(VLOOKUP($V$17,Sheet1!F8:I8,3,0),0) -> 0 | W49: =+IFERROR(VLOOKUP($W$17,Sheet1!F8:I8,3,0),0) -> 0 | X49: =+IFERROR(VLOOKUP($X$17,Sheet1!F8:I8,3,0),0) -> 0 | Y49: =+IFERROR(VLOOKUP($Y$17,Sheet1!F8:I8,3,0),0) -> 0 | Z49: =+IFERROR(VLOOKUP($Z$17,Sheet1!F8:I8,3,0),0) -> 0 | AA49: =+IFERROR(VLOOKUP($AA$17,Sheet1!F8:I8,3,0),0) -> 0 | AB49: =+IFERROR(VLOOKUP($AB$17,Sheet1!F8:I8,3,0),0) -> 0 | AC49: =+IFERROR(VLOOKUP($AC$17,Sheet1!R8:U8,3,0),0) -> 0 | AD49: =+IFERROR(VLOOKUP($AD$17,Sheet1!R8:U8,2,0),0) -> 0 | AE49: =+IFERROR(VLOOKUP($AE$17,Sheet1!V8:Y8,3,0),0) -> 0 | AF49: 64 | AG49: =+IFERROR(VLOOKUP($AG$17,Sheet1!V8:Y8,3,0),0) -> 0 | AH49: =+IFERROR(VLOOKUP($AH$17,Sheet1!V8:Y8,3,0),0) -> 0 | AJ49: =+IFERROR(VLOOKUP($AJ$17,Sheet1!V8:Y8,3,0),0) -> 0 | AK49: =+IFERROR(VLOOKUP($AK$17,Sheet1!Z8:AB8,3,0),0) -> 0 | AL49: =+IFERROR(VLOOKUP($AL$17,Sheet1!AD8:AG8,3,0),0) -> 0 | AM49: =+IFERROR(VLOOKUP($AM$17,Sheet1!AD8:AG8,3,0),0) -> 0 | AN49: =+IFERROR(VLOOKUP($AN$17,Sheet1!AD8:AG8,3,0),0) -> 0 | AO49: =+IFERROR(VLOOKUP($AO$17,Sheet1!AD8:AG8,3,0),0) -> 0 | AP49: =+IFERROR(VLOOKUP($AP$17,Sheet1!AD8:AG8,3,0),0) -> 0 | AQ49: 80 | AR49: =+IFERROR(VLOOKUP($AR$17,Sheet1!AD8:AG8,3,0),0) -> 0 | AS49: =+IFERROR(VLOOKUP($AS$17,Sheet1!AH8:AK8,3,0),0) -> 0 | AT49: =+IFERROR(VLOOKUP($AT$17,Sheet1!AH8:AK8,3,0),0) -> 0 | AU49: =+IFERROR(VLOOKUP($AU$17,Sheet1!AH8:AK8,3,0),0) -> 0 | AV49: =+IFERROR(VLOOKUP($AV$17,Sheet1!AH8:AK8,3,0),0) -> 0 | AW49: =+IFERROR(VLOOKUP($AW$17,Sheet1!AH8:AK8,3,0),0) -> 0 | AX49: =+IFERROR(VLOOKUP($AX$17,Sheet1!AH8:AK8,3,0),0) -> 0 | AY49: =+IFERROR(VLOOKUP($AY$17,Sheet1!AH8:AK8,3,0),0) -> 0 | AZ49: =+IFERROR(VLOOKUP($AZ$17,Sheet1!AH8:AK8,3,0),0) -> 0 | BA49: 1018 | BB49: =+IFERROR(VLOOKUP($BB$17,Sheet1!AH8:AK8,3,0),0) -> 0 | BC49: =+IFERROR(VLOOKUP($BC$17,Sheet1!AL8:AO8,3,0),0) -> 0 | BD49: =+IFERROR(VLOOKUP($BD$17,Sheet1!AL8:AO8,3,0),0) -> 0 | BE49: =+IFERROR(VLOOKUP($BE$17,Sheet1!AL8:AO8,3,0),0) -> 0 | BF49: 200 | BG49: =+IFERROR(VLOOKUP($BG$17,Sheet1!AL8:AO8,3,0),0) -> 0 | BH49: =+IFERROR(VLOOKUP($BH$17,Sheet1!AL8:AO8,3,0),0) -> 0 | BI49: =+IFERROR(VLOOKUP($BI$17,Sheet1!AL8:AO8,3,0),0) -> 0 | BJ49: =+IFERROR(VLOOKUP($BJ$17,Sheet1!AL8:AO8,3,0),0) -> 0 | BK49: =+IFERROR(VLOOKUP($BK$17,Sheet1!AL8:AO8,3,0),0) -> 0 | BL49: =+IFERROR(VLOOKUP($BL$17,Sheet1!AL8:AO8,3,0),0) -> 0 | BM49: =+IFERROR(VLOOKUP($BM$17,Sheet1!AP8:AS8,3,0),0) -> 0 | BN49: =+IFERROR(VLOOKUP($BN$17,Sheet1!AT8:AW8,3,0),0) -> 0 | BO49: =+IFERROR(VLOOKUP($BO$17,Sheet1!AX8:BA8,3,0),0) -> 0 | BP49: =+IFERROR(VLOOKUP($BP$17,Sheet1!BB8:BE8,3,0),0) -> 0 | BQ49: =+IFERROR(VLOOKUP($BQ$17,Sheet1!BF8:BI8,3,0),0) -> 0 | BR49: =+IFERROR(VLOOKUP($BR$17,Sheet1!BJ8:BM8,3,0),0) -> 0 | BS49: =+IFERROR(VLOOKUP($BS$17,Sheet1!BN8:BQ8,3,0),0) -> 0 | BT49: 18 | BU49: =+IFERROR(VLOOKUP($BU$17,Sheet1!BV8:BY8,3,0),0) -> 0 | BV49: =Sheet1!E8 -> WOOD | BW49: MD0100019 | BX49: DRUM - 54 X 24 X 32 X 3 | BY49: 1000 | BZ49: 6379 | CA49: =SUMPRODUCT($N$18:$BU$18,N49:BU49)+BZ49 -> 802755 | CB49: =Sheet1!CB8 -> 0 | CC49: =CA49*CB49 -> 0 | CD49: 0.18 | CE49: =CA49*CD49 -> 144495.9 | CF49: 0 | CG49: =CA49*CF49 -> 0 | CH49: =CA49+CC49+CE49+CG49 -> 947250.9 | CI49: 0.02 | CJ49: =CH49*CI49 -> 18945.018 | CK49: 0.01 | CL49: =CH49*CK49 -> 9472.509 | CM49: 150 | CN49: 30
E51: Order Quantity | F51: Stnd Length | G51: Truck type | H51: Fare of one truck | I51: No of Drum in one truck | J51: Total length in one Truck | K51: No of Truck | L51: Total Freight | M51: Freight per KM | N51: cable weight per km | P51: Empty Drum Wt. | AF51: single drum weight with cable | AH51: weight in truck
C52: =C19 -> FA0600013 | D52: =D19 -> 1 CORE X 95 SQ. MM. AL/UNARD(XLPE ) | E52: =K19 -> 82.208 | F52: =BY19/1000 -> 1 | G52: 16 MT | H52: 27000 | I52: 31 | J52: =F52*I52 -> 31 | K52: =ROUNDUP((E52/J52),0) -> 3 | L52: =M52*E52 -> 81000 | M52: =(H52*K52)/E52 -> 985.30557 | N52: =SUM(N19:BT19) -> 440.5 | P52: =CM19+CN19 -> 75 | AF52: =((N52*F52)+P52) -> 515.5 | AH52: =I52*AF52 -> 15980.5
C53: =C20 -> FA0600019 | D53: =D20 -> 1 CORE X 150 SQ. MM. AL/UNARD. (XLPE) | E53: =K20 -> 47.838 | F53: =BY20/1000 -> 1 | G53: 16 MT | H53: 27000 | I53: 20 | J53: =F53*I53 -> 20 | K53: =ROUNDUP((E53/J53),0) -> 3 | L53: =M53*E53 -> 81000 | M53: =(H53*K53)/E53 -> 1693.2146 | N53: =SUM(N20:BT20) -> 686 | P53: =CM20+CN20 -> 100 | AF53: =((N53*F53)+P53) -> 786 | AH53: =I53*AF53 -> 15720
C54: =C21 -> FA0600021 | D54: =D21 -> 1 CORE X 185 SQ. MM. AL/UNARD. (XLPE) | E54: =K21 -> 20 | F54: =BY21/1000 -> 1 | G54: 16 MT | H54: 27000 | I54: 17 | J54: =F54*I54 -> 17 | K54: =ROUNDUP((E54/J54),0) -> 2 | L54: =M54*E54 -> 54000 | M54: =(H54*K54)/E54 -> 2700 | N54: =SUM(N21:BT21) -> 828 | P54: =CM21+CN21 -> 100 | AF54: =((N54*F54)+P54) -> 928 | AH54: =I54*AF54 -> 15776
C55: =C22 -> FA0600020 | D55: =D22 -> 1 CORE X 300 SQ. MM. AL/UNARD. (XLPE) | E55: =K22 -> 63.368 | F55: =BY22/1000 -> 1 | G55: 16 MT | H55: 27000 | I55: 10 | J55: =F55*I55 -> 10 | K55: =ROUNDUP((E55/J55),0) -> 7 | L55: =M55*E55 -> 189000 | M55: =(H55*K55)/E55 -> 2982.578 | N55: =SUM(N22:BT22) -> 1225 | P55: =CM22+CN22 -> 150 | AF55: =((N55*F55)+P55) -> 1375 | AH55: =I55*AF55 -> 13750
C56: =C23 -> FA0600032 | D56: =D23 -> 1 CORE X 630 SQ. MM. ALU/UNARD (XLPE) | E56: =K23 -> 81.688 | F56: =BY23/1000 -> 1 | G56: 16 MT | H56: 27000 | I56: 5 | J56: =F56*I56 -> 5 | K56: =ROUNDUP((E56/J56),0) -> 17 | L56: =M56*E56 -> 459000 | M56: =(H56*K56)/E56 -> 5618.9404 | N56: =SUM(N23:BT23) -> 2391 | P56: =CM23+CN23 -> 365 | AF56: =((N56*F56)+P56) -> 2756 | AH56: =I56*AF56 -> 13780
C57: =C24 -> FA1200026 | D57: =D24 -> 4 CORE X 150 SQ. MM. AL/UNARD (XLPE) | E57: =K24 -> 0 | F57: =BY24/1000 -> 0.5 | G57: 16 MT | H57: 27000 | I57: 8 | J57: =F57*I57 -> 4 | K57: =ROUNDUP((E57/J57),0) -> 0 | L57: =M57*E57 -> #DIV/0! | M57: =(H57*K57)/E57 -> #DIV/0! | N57: =SUM(N24:BT24) -> 2622 | P57: =CM24+CN24 -> 300 | AF57: =((N57*F57)+P57) -> 1611 | AH57: =I57*AF57 -> 12888
C58: =C25 -> FA0900111 | D58: =D25 -> 4 CORE X 25 SQ. MM. ALU/ARD - WIRE (XLPE) | E58: =K25 -> 241.116 | F58: =BY25/1000 -> 1 | G58: 16 MT | H58: 27000 | I58: 11 | J58: =F58*I58 -> 11 | K58: =ROUNDUP((E58/J58),0) -> 22 | L58: =M58*E58 -> 594000 | M58: =(H58*K58)/E58 -> 2463.5445 | N58: =SUM(N25:BT25) -> 1251.3 | P58: =CM25+CN25 -> 100 | AF58: =((N58*F58)+P58) -> 1351.3 | AH58: =I58*AF58 -> 14864.3
C59: =C26 -> FA0900116 | D59: =D26 -> 4 CORE X 50 SQ. MM. AL/ARD - WIRE (XLPE) | E59: =K26 -> 27.67 | F59: =BY26/1000 -> 1 | G59: 16 MT | H59: 27000 | I59: 7 | J59: =F59*I59 -> 7 | K59: =ROUNDUP((E59/J59),0) -> 4 | L59: =M59*E59 -> 108000 | M59: =(H59*K59)/E59 -> 3903.1442 | N59: =SUM(N26:BT26) -> 2038 | P59: =CM26+CN26 -> 180 | AF59: =((N59*F59)+P59) -> 2218 | AH59: =I59*AF59 -> 15526
C60: =C27 -> FA1100094 | D60: =D27 -> 4 CORE X 95 SQ. MM. ALU/ARD - WIRE (XLPE) | E60: =K27 -> 149.77 | F60: =BY27/1000 -> 0.5 | G60: 16 MT | H60: 27000 | I60: 9 | J60: =F60*I60 -> 4.5 | K60: =ROUNDUP((E60/J60),0) -> 34 | L60: =M60*E60 -> 918000 | M60: =(H60*K60)/E60 -> 6129.3984 | N60: =SUM(N27:BT27) -> 3033 | P60: =CM27+CN27 -> 190 | AF60: =((N60*F60)+P60) -> 1706.5 | AH60: =I60*AF60 -> 15358.5
C61: =C28 -> FA1100177 | D61: =D28 -> 4 CORE X 150 SQ. MM. AL/ARD - WIRE (XLPE) | E61: =K28 -> 23.595 | F61: =BY28/1000 -> 0.5 | G61: 16 MT | H61: 27000 | I61: 5 | J61: =F61*I61 -> 2.5 | K61: =ROUNDUP((E61/J61),0) -> 10 | L61: =M61*E61 -> 270000 | M61: =(H61*K61)/E61 -> 11443.102 | N61: =SUM(N28:BT28) -> 4939 | P61: =CM28+CN28 -> 315 | AF61: =((N61*F61)+P61) -> 2784.5 | AH61: =I61*AF61 -> 13922.5
C62: =C29 -> FA1100091 | D62: =D29 -> 4 CORE X 240 SQ. MM. AL/ARD - WIRE (XLPE) | E62: =K29 -> 1 | F62: =BY29/1000 -> 0.5 | G62: 16 MT | H62: 27000 | I62: 4 | J62: =F62*I62 -> 2 | K62: =ROUNDUP((E62/J62),0) -> 1 | L62: =M62*E62 -> 27000 | M62: =(H62*K62)/E62 -> 27000 | N62: =SUM(N29:BT29) -> 6837 | P62: =CM29+CN29 -> 365 | AF62: =((N62*F62)+P62) -> 3783.5 | AH62: =I62*AF62 -> 15134
C63: =C30 -> FA1100176 | D63: =D30 -> 4 CORE X 300 SQ. MM. AL/ARD - WIRE (XLPE) | E63: =K30 -> 12.42 | F63: =BY30/1000 -> 0.5 | G63: 16 MT | H63: 27000 | I63: 3 | J63: =F63*I63 -> 1.5 | K63: =ROUNDUP((E63/J63),0) -> 9 | L63: =M63*E63 -> 243000 | M63: =(H63*K63)/E63 -> 19565.217 | N63: =SUM(N30:BT30) -> 8134 | P63: =CM30+CN30 -> 575 | AF63: =((N63*F63)+P63) -> 4642 | AH63: =I63*AF63 -> 13926
... C82: =C49 -> FA0900229 | D82: =D49 -> 2 CORE X 50 SQ. MM. CU/ARD - WIRE (XLPE) | E82: =K49 -> 3.65 | F82: =BY49/1000 -> 1 | G82: 16 MT | H82: 27000 | I82: 6 | J82: =F82*I82 -> 6 | K82: =ROUNDUP((E82/J82),0) -> 1 | L82: =M82*E82 -> 27000 | M82: =(H82*K82)/E82 -> 7397.2603 | N82: =SUM(N49:BT49) -> 2240 | P82: =CM49+CN49 -> 180 | AF82: =((N82*F82)+P82) -> 2420 | AH82: =I82*AF82 -> 14520
A85: DOCKET NO. | B85: Base Date | C85: ITEM CODE | D85: PROPOSE ERP ITEM NAME | E85: EX-WORKS (PER MTR) | F85: FREIGHT PER KM | G85: PRICE INCLUDING FREIGHT (PER KM) | H85: GST % | I85: GST VALUE | J85: PRICE INCLUDING GST & FREIGHT (PER KM) | K85: QTY | L85: Unit | M85: TOTAL PRICE OF FULL QTY (INCLUDING FRIGHT & GST)
A87: =A19 -> ENQ-12232-22-23 | B87: =B19 -> 45380 | C87: =C19 -> FA0600013 | D87: =D19 -> 1 CORE X 95 SQ. MM. AL/UNARD(XLPE ) | E87: =ROUNDUP(E19/1000,2) -> 97.43 | F87: =ROUNDUP(F19/1000,2) -> 0.99 | G87: =E87+F87 -> 98.42 | H87: =H19 -> 0.18 | I87: =G87*H87 -> 17.7156 | J87: =G87+I87 -> 116.1356 | K87: =K19*1000 -> 82208 | L87: MTR | M87: =J87*K87 -> 9547275.4
A88: =A20 -> ENQ-12232-22-23 | B88: =B20 -> 45380 | C88: =C20 -> FA0600019 | D88: =D20 -> 1 CORE X 150 SQ. MM. AL/UNARD. (XLPE) | E88: =ROUNDUP(E20/1000,2) -> 155.62 | F88: =ROUNDUP(F20/1000,2) -> 1.7 | G88: =E88+F88 -> 157.32 | H88: =H20 -> 0.18 | I88: =G88*H88 -> 28.3176 | J88: =G88+I88 -> 185.6376 | K88: =K20*1000 -> 47838 | L88: MTR | M88: =J88*K88 -> 8880531.5
A89: =A21 -> ENQ-12232-22-23 | B89: =B21 -> 45380 | C89: =C21 -> FA0600021 | D89: =D21 -> 1 CORE X 185 SQ. MM. AL/UNARD. (XLPE) | E89: =ROUNDUP(E21/1000,2) -> 190.42 | F89: =ROUNDUP(F21/1000,2) -> 2.7 | G89: =E89+F89 -> 193.12 | H89: =H21 -> 0.18 | I89: =G89*H89 -> 34.7616 | J89: =G89+I89 -> 227.8816 | K89: =K21*1000 -> 20000 | L89: MTR | M89: =J89*K89 -> 4557632
A90: =A22 -> ENQ-12232-22-23 | B90: =B22 -> 45380 | C90: =C22 -> FA0600020 | D90: =D22 -> 1 CORE X 300 SQ. MM. AL/UNARD. (XLPE) | E90: =ROUNDUP(E22/1000,2) -> 290.65 | F90: =ROUNDUP(F22/1000,2) -> 2.99 | G90: =E90+F90 -> 293.64 | H90: =H22 -> 0.18 | I90: =G90*H90 -> 52.8552 | J90: =G90+I90 -> 346.4952 | K90: =K22*1000 -> 63368 | L90: MTR | M90: =J90*K90 -> 21956708
A91: =A23 -> ENQ-12232-22-23 | B91: =B23 -> 45380 | C91: =C23 -> FA0600032 | D91: =D23 -> 1 CORE X 630 SQ. MM. ALU/UNARD (XLPE) | E91: =ROUNDUP(E23/1000,2) -> 590.4 | F91: =ROUNDUP(F23/1000,2) -> 5.62 | G91: =E91+F91 -> 596.02 | H91: =H23 -> 0.18 | I91: =G91*H91 -> 107.2836 | J91: =G91+I91 -> 703.3036 | K91: =K23*1000 -> 81688 | L91: MTR | M91: =J91*K91 -> 57451464
A92: =A24 -> ENQ-12232-22-23 | B92: =B24 -> 45380 | C92: =C24 -> FA1200026 | D92: =D24 -> 4 CORE X 150 SQ. MM. AL/UNARD (XLPE) | E92: =ROUNDUP(E24/1000,2) -> 605.34 | G92: =E92+F92 -> 605.34 | H92: =H24 -> 0.18 | I92: =G92*H92 -> 108.9612 | J92: =G92+I92 -> 714.3012 | K92: =K24*1000 -> 0 | L92: MTR | M92: =J92*K92 -> 0
A93: =A25 -> ENQ-12232-22-23 | B93: =B25 -> 45380 | C93: =C25 -> FA0900111 | D93: =D25 -> 4 CORE X 25 SQ. MM. ALU/ARD - WIRE (XLPE) | E93: =ROUNDUP(E25/1000,2) -> 190.25 | F93: =ROUNDUP(F25/1000,2) -> 2.47 | G93: =E93+F93 -> 192.72 | H93: =H25 -> 0.18 | I93: =G93*H93 -> 34.6896 | J93: =G93+I93 -> 227.4096 | K93: =K25*1000 -> 241116 | L93: MTR | M93: =J93*K93 -> 54832093
A94: =A26 -> ENQ-12232-22-23 | B94: =B26 -> 45380 | C94: =C26 -> FA0900116 | D94: =D26 -> 4 CORE X 50 SQ. MM. AL/ARD - WIRE (XLPE) | E94: =ROUNDUP(E26/1000,2) -> 323.44 | F94: =ROUNDUP(F26/1000,2) -> 3.91 | G94: =E94+F94 -> 327.35 | H94: =H26 -> 0.18 | I94: =G94*H94 -> 58.923 | J94: =G94+I94 -> 386.273 | K94: =K26*1000 -> 27670 | L94: MTR | M94: =J94*K94 -> 10688174
A95: =A27 -> ENQ-12232-22-23 | B95: =B27 -> 45380 | C95: =C27 -> FA1100094 | D95: =D27 -> 4 CORE X 95 SQ. MM. ALU/ARD - WIRE (XLPE) | E95: =ROUNDUP(E27/1000,2) -> 523.87 | F95: =ROUNDUP(F27/1000,2) -> 6.13 | G95: =E95+F95 -> 530 | H95: =H27 -> 0.18 | I95: =G95*H95 -> 95.4 | J95: =G95+I95 -> 625.4 | K95: =K27*1000 -> 149770 | L95: MTR | M95: =J95*K95 -> 93666158
A96: =A28 -> ENQ-12232-22-23 | B96: =B28 -> 45380 | C96: =C28 -> FA1100177 | D96: =D28 -> 4 CORE X 150 SQ. MM. AL/ARD - WIRE (XLPE) | E96: =ROUNDUP(E28/1000,2) -> 852.05 | F96: =ROUNDUP(F28/1000,2) -> 11.45 | G96: =E96+F96 -> 863.5 | H96: =H28 -> 0.18 | I96: =G96*H96 -> 155.43 | J96: =G96+I96 -> 1018.93 | K96: =K28*1000 -> 23595 | L96: MTR | M96: =J96*K96 -> 24041653
A97: =A29 -> ENQ-12232-22-23 | B97: =B29 -> 45380 | C97: =C29 -> FA1100091 | D97: =D29 -> 4 CORE X 240 SQ. MM. AL/ARD - WIRE (XLPE) | E97: =ROUNDUP(E29/1000,2) -> 1240.73 | F97: =ROUNDUP(F29/1000,2) -> 27 | G97: =E97+F97 -> 1267.73 | H97: =H29 -> 0.18 | I97: =G97*H97 -> 228.1914 | J97: =G97+I97 -> 1495.9214 | K97: =K29*1000 -> 1000 | L97: MTR | M97: =J97*K97 -> 1495921.4
A98: =A30 -> ENQ-12232-22-23 | B98: =B30 -> 45380 | C98: =C30 -> FA1100176 | D98: =D30 -> 4 CORE X 300 SQ. MM. AL/ARD - WIRE (XLPE) | E98: =ROUNDUP(E30/1000,2) -> 1527.04 | F98: =ROUNDUP(F30/1000,2) -> 19.57 | G98: =E98+F98 -> 1546.61 | H98: =H30 -> 0.18 | I98: =G98*H98 -> 278.3898 | J98: =G98+I98 -> 1824.9998 | K98: =K30*1000 -> 12420 | L98: MTR | M98: =J98*K98 -> 22666498
A99: =A31 -> ENQ-12232-22-23 | B99: =B31 -> 45380 | C99: =C31 -> FA0500017 | D99: =D31 -> 1 CORE X 50 SQ. MM. AL/UNARD. (XLPE) | E99: =ROUNDUP(E31/1000,2) -> 58.75 | F99: =ROUNDUP(F31/1000,2) -> 4.16 | G99: =E99+F99 -> 62.91 | H99: =H31 -> 0.18 | I99: =G99*H99 -> 11.3238 | J99: =G99+I99 -> 74.2338 | K99: =K31*1000 -> 6500 | L99: MTR | M99: =J99*K99 -> 482519.7
A100: =A32 -> ENQ-12232-22-23 | B100: =B32 -> 45380 | C100: =C32 -> FA0900117 | D100: =D32 -> 4 CORE X 35 SQ. MM. AL/ARD - WIRE (XLPE) | E100: =ROUNDUP(E32/1000,2) -> 238.35 | G100: =E100+F100 -> 238.35 | H100: =H32 -> 0.18 | I100: =G100*H100 -> 42.903 | J100: =G100+I100 -> 281.253 | K100: =K32*1000 -> 0 | L100: MTR | M100: =J100*K100 -> 0
A101: =A33 -> ENQ-12232-22-23 | B101: =B33 -> 45380 | C101: =C33 -> FA0900041 | D101: =D33 -> 2 CORE X 4 SQ. MM. AL/ARD - WIRE (XLPE) | E101: =ROUNDUP(E33/1000,2) -> 60.58 | F101: =ROUNDUP(F33/1000,2) -> 0.97 | G101: =E101+F101 -> 61.55 | H101: =H33 -> 0.18 | I101: =G101*H101 -> 11.079 | J101: =G101+I101 -> 72.629 | K101: =K33*1000 -> 2956188 | L101: MTR | M101: =J101*K101 -> 2.1470498e+08
A102: =A34 -> ENQ-12232-22-23 | B102: =B34 -> 45380 | C102: =C34 -> FA0900020 | D102: =D34 -> 2 CORE X 6 SQ. MM. AL/ARD - WIRE (XLPE) | E102: =ROUNDUP(E34/1000,2) -> 70.27 | F102: =ROUNDUP(F34/1000,2) -> 1.08 | G102: =E102+F102 -> 71.35 | H102: =H34 -> 0.18 | I102: =G102*H102 -> 12.843 | J102: =G102+I102 -> 84.193 | K102: =K34*1000 -> 630000 | L102: MTR | M102: =J102*K102 -> 53041590
A103: =A35 -> ENQ-12232-22-23 | B103: =B35 -> 45380 | C103: =C35 -> FA0900042 | D103: =D35 -> 2 CORE X 10 SQ. MM. ALU/ARD - WIRE (XLPE) | E103: =ROUNDUP(E35/1000,2) -> 91.21 | F103: =ROUNDUP(F35/1000,2) -> 1.7 | G103: =E103+F103 -> 92.91 | H103: =H35 -> 0.18 | I103: =G103*H103 -> 16.7238 | J103: =G103+I103 -> 109.6338 | K103: =K35*1000 -> 63713 | L103: MTR | M103: =J103*K103 -> 6985098.3
A104: =A36 -> ENQ-12232-22-23 | B104: =B36 -> 45380 | C104: =C36 -> FA0900112 | D104: =D36 -> 4 CORE X 10 SQ. MM. AL/ARD - WIRE (XLPE) | E104: =ROUNDUP(E36/1000,2) -> 107.88 | F104: =ROUNDUP(F36/1000,2) -> 1.6 | G104: =E104+F104 -> 109.48 | H104: =H36 -> 0.18 | I104: =G104*H104 -> 19.7064 | J104: =G104+I104 -> 129.1864 | K104: =K36*1000 -> 152526 | L104: MTR | M104: =J104*K104 -> 19704285
A105: =A37 -> ENQ-12232-22-23 | B105: =B37 -> 45380 | C105: =C37 -> FA0300011 | D105: =D37 -> 10 CORE X 2.5 SQ. MM. CU/UNARD. (PVC) | E105: =ROUNDUP(E37/1000,2) -> 258.27 | G105: =E105+F105 -> 258.27 | H105: =H37 -> 0.18 | I105: =G105*H105 -> 46.4886 | J105: =G105+I105 -> 304.7586 | K105: =K37*1000 -> 0 | L105: MTR | M105: =J105*K105 -> 0
A106: =A38 -> ENQ-12232-22-23 | B106: =B38 -> 45380 | C106: =C38 -> FA0200005 | D106: =D38 -> 16 CORE X 2.5 SQ. MM. CU/ARD - WIRE (PVC) | E106: =ROUNDUP(E38/1000,2) -> 460.3 | F106: =ROUNDUP(F38/1000,2) -> 3.11 | G106: =E106+F106 -> 463.41 | H106: =H38 -> 0.18 | I106: =G106*H106 -> 83.4138 | J106: =G106+I106 -> 546.8238 | K106: =K38*1000 -> 43500 | L106: MTR | M106: =J106*K106 -> 23786835
A107: =A39 -> ENQ-12232-22-23 | B107: =B39 -> 45380 | C107: =C39 -> FA0300006 | D107: =D39 -> 4 CORE X 2.5 SQ. MM. CU/UNARD.(PVC) | E107: =ROUNDUP(E39/1000,2) -> 112.19 | G107: =E107+F107 -> 112.19 | H107: =H39 -> 0.18 | I107: =G107*H107 -> 20.1942 | J107: =G107+I107 -> 132.3842 | K107: =K39*1000 -> 0 | L107: MTR | M107: =J107*K107 -> 0
A108: =A40 -> ENQ-12232-22-23 | B108: =B40 -> 45380 | C108: =C40 -> FA0200011 | D108: =D40 -> 4 CORE X 2.5 SQ. MM. CU/ARD - WIRE (PVC) | E108: =ROUNDUP(E40/1000,2) -> 141.14 | F108: =ROUNDUP(F40/1000,2) -> 1.64 | G108: =E108+F108 -> 142.78 | H108: =H40 -> 0.18 | I108: =G108*H108 -> 25.7004 | J108: =G108+I108 -> 168.4804 | K108: =K40*1000 -> 165088 | L108: MTR | M108: =J108*K108 -> 27814092
A109: =A41 -> ENQ-12232-22-23 | B109: =B41 -> 45380 | C109: =C41 -> FA0200018 | D109: =D41 -> 7 CORE X 2.5 SQ. MM. CU/ARD - WIRE (PVC) | E109: =ROUNDUP(E41/1000,2) -> 218.32 | F109: =ROUNDUP(F41/1000,2) -> 1.84 | G109: =E109+F109 -> 220.16 | H109: =H41 -> 0.18 | I109: =G109*H109 -> 39.6288 | J109: =G109+I109 -> 259.7888 | K109: =K41*1000 -> 73755 | L109: MTR | M109: =J109*K109 -> 19160723
A110: =A42 -> ENQ-12232-22-23 | B110: =B42 -> 45380 | C110: =C42 -> FA0200002 | D110: =D42 -> 10 CORE X 2.5 SQ. MM. CU/ARD - WIRE (PVC) | E110: =ROUNDUP(E42/1000,2) -> 310.34 | F110: =ROUNDUP(F42/1000,2) -> 2.19 | G110: =E110+F110 -> 312.53 | H110: =H42 -> 0.18 | I110: =G110*H110 -> 56.2554 | J110: =G110+I110 -> 368.7854 | K110: =K42*1000 -> 98806 | L110: MTR | M110: =J110*K110 -> 36438210
A111: =A43 -> ENQ-12232-22-23 | B111: =B43 -> 45380 | C111: =C43 -> FA0200003 | D111: =D43 -> 12 CORE X 2.5 SQ. MM. CU/ARD - WIRE (PVC) | E111: =ROUNDUP(E43/1000,2) -> 358.6 | F111: =ROUNDUP(F43/1000,2) -> 2.59 | G111: =E111+F111 -> 361.19 | H111: =H43 -> 0.18 | I111: =G111*H111 -> 65.0142 | J111: =G111+I111 -> 426.2042 | K111: =K43*1000 -> 62667 | L111: MTR | M111: =J111*K111 -> 26708939
A112: =A44 -> ENQ-12232-22-23 | B112: =B44 -> 45380 | C112: =C44 -> FA0900024 | D112: =D44 -> 4 CORE X 4 SQ. MM. CU/ARD - WIRE (PVC) | E112: =ROUNDUP(E44/1000,2) -> 205.51 | F112: =ROUNDUP(F44/1000,2) -> 1.5 | G112: =E112+F112 -> 207.01 | H112: =H44 -> 0.18 | I112: =G112*H112 -> 37.2618 | J112: =G112+I112 -> 244.2718 | K112: =K44*1000 -> 18000 | L112: MTR | M112: =J112*K112 -> 4396892.4
A113: =A45 -> ENQ-12232-22-23 | B113: =B45 -> 45380 | C113: =C45 -> FA0900052 | D113: =D45 -> 4 CORE X 16 SQ. MM. CU/ARD - WIRE (XLPE) | E113: =ROUNDUP(E45/1000,2) -> 631.82 | F113: =ROUNDUP(F45/1000,2) -> 18 | G113: =E113+F113 -> 649.82 | H113: =H45 -> 0.18 | I113: =G113*H113 -> 116.9676 | J113: =G113+I113 -> 766.7876 | K113: =K45*1000 -> 1500 | L113: MTR | M113: =J113*K113 -> 1150181.4
A114: =A46 -> ENQ-12232-22-23 | B114: =B46 -> 45380 | C114: =C46 -> FA0900121 | D114: =D46 -> 4 CORE X 10 SQ. MM. CU/ARD - WIRE (XLPE) | E114: =ROUNDUP(E46/1000,2) -> 416.16 | F114: =ROUNDUP(F46/1000,2) -> 9 | G114: =E114+F114 -> 425.16 | H114: =H46 -> 0.18 | I114: =G114*H114 -> 76.5288 | J114: =G114+I114 -> 501.6888 | K114: =K46*1000 -> 3000 | L114: MTR | M114: =J114*K114 -> 1505066.4
A115: =A47 -> ENQ-12232-22-23 | B115: =B47 -> 45380 | C115: =C47 -> FA0800019 | D115: =D47 -> 1 CORE X 16 SQ. MM. CU/ARD (XLPE) | E115: =ROUNDUP(E47/1000,2) -> 173.84 | F115: =ROUNDUP(F47/1000,2) -> 225 | G115: =E115+F115 -> 398.84 | H115: =H47 -> 0.18 | I115: =G115*H115 -> 71.7912 | J115: =G115+I115 -> 470.6312 | K115: =K47*1000 -> 120 | L115: MTR | M115: =J115*K115 -> 56475.744
A116: =A48 -> ENQ-12232-22-23 | B116: =B48 -> 45380 | C116: =C48 -> FA0900171 | D116: =D48 -> 2 CORE X 16 SQ. MM. CU/ARD - WIRE (XLPE) | E116: =ROUNDUP(E48/1000,2) -> 357.45 | F116: =ROUNDUP(F48/1000,2) -> 12.74 | G116: =E116+F116 -> 370.19 | H116: =H48 -> 0.18 | I116: =G116*H116 -> 66.6342 | J116: =G116+I116 -> 436.8242 | K116: =K48*1000 -> 2120 | L116: MTR | M116: =J116*K116 -> 926067.3
A117: =A49 -> ENQ-12232-22-23 | B117: =B49 -> 45380 | C117: =C49 -> FA0900229 | D117: =D49 -> 2 CORE X 50 SQ. MM. CU/ARD - WIRE (XLPE) | E117: =ROUNDUP(E49/1000,2) -> 975.67 | F117: =ROUNDUP(F49/1000,2) -> 7.4 | G117: =E117+F117 -> 983.07 | H117: =H49 -> 0.18 | I117: =G117*H117 -> 176.9526 | J117: =G117+I117 -> 1160.0226 | K117: =K49*1000 -> 3650 | L117: MTR | M117: =J117*K117 -> 4234082.5
M118: =SUM(M87:M117) -> 7.5088014e+08
