Workbook

Sheet Sheet1
A1: DOCKET NO. | B1: Base Date | C1: ITEM CODE | D1: PROPOSE ERP ITEM NAME | E1: Propose Drum Type | F1: Insulation Screening(Metallic) | G1: RM Rate(Insulation Screening(Metallic)) | H1: Weight (Insulation Screening (Metallic)) | I1: Cost Insulation Screening(Metallic) | J1: Conductor | K1: RM Rate(Conductor) | L1: Weight(Conductor) | M1: Cost(Conductor) | N1: AL ALLOY | O1: RM Rate(AL Alloy) | P1: Weight(Al Alloy) | Q1: Cost(AL Alloy) | R1: Insulation Screening(Non-Metallic) | S1: RM Rate(Insulation Screening(Non-Metallic)) | T1: Weight(Insulation Screening(Non-Metallic) | U1: Cost(Insulation Screening(Non-Metallic) | V1: Insulation | W1: RM Rate(Insulation) | X1: Weight(Insulation) | Y1: Cost(Insulation) | Z1: Poly Tape | AA1: RM Rate(Poly Tape) | AB1: Weight(Poly Tape) | AC1: Cost(Poly Tape) | AD1: Inner Sheath | AE1: RM Rate(Inner Sheath) | AF1: Weight(Inner Sheath) | AG1: Cost(Inner Sheath) | AH1: Armouring | AI1: RM Rate(Armouring) | AJ1: Weight(Armouring) | AK1: Cost(Armouring) | AL1: Outer Sheath | AM1: RM Rate(Outer Sheath) | AN1: Weight(Outer Sheath) | AO1: Cost(Outer Sheath) | AP1: Filler | AQ1: RM Rate(Filler) | AR1: Weight(Filler) | AS1: Cost(Filler) | AT1: Grease | AU1: RM Rate(Grease) | AV1: Weight(Grease) | AW1: Cost(Grease) | AX1: Water Swellable Tape | AY1: RM Rate(Water Swellable Tape) | AZ1: Weight(Water Swellable Tape) | BA1: Cost(Water Swellable Tape) | BB1: Semi Conducting Water Swellable Tape | BC1: RM Rate(Semi Conducting Water Swellable Tape) | BD1: Weight(Semi Conducting Water Swellable Tape) | BE1: Cost(Semi Conducting Water Swellable Tape) | BF1: Semicon Tape | BG1: RM Rate(Semicon Tape) | BH1: Weight(Semicon Tape) | BI1: Cost(Semicon Tape) | BJ1: Glass Fiber Tape | BK1: RM Rate(Glass Fiber Tape) | BL1: Weight(Glass Fiber Tape) | BM1: Cost(Glass Fiber Tape) | BN1: Copper Wire 0.8MM | BO1: RM Rate(Copper Wire 0.8MM) | BP1: Weight(Copper Wire 0.8MM) | BQ1: Cost(Copper Wire 0.8MM) | BR1: Rubberized Cotton Tape | BS1: RM Rate(Rubberized Cotton Tape) | BT1: Weight(Rubberized Cotton Tape) | BU1: Cost(Rubberized Cotton Tape) | BV1: Water Tight Compound | BW1: RM Rate(Water Tight Compound) | BX1: Weight(Water Tight Compound) | BY1: Cost(Water Tight Compound) | BZ1: Drum Cost Per KM | CA1: Total RM Cost | CB1: FIRM % | CC1: Firm Value | CD1: MFG% | CE1: MFG Value | CF1: PROF% | CG1: Profit Value | CH1: 1st EX-Works | CI1: Intt % | CJ1: Intt Value | CK1: insp% | CL1: Insp Value | CM1: EX-Works Per KM | CN1: Freight Per KM | CO1: Price Including Freight Per KM | CP1: GST % | CQ1: GST Value | CR1: Price Including GST & Freight Per KM | CS1: QTY | CT1: Unit | CU1: Total Price Of Full QTY(Including Freight&GST) | CV1: DRUM CODE | CW1: DRUM SIZE (FxbXtx Ft) | CX1: Party Standard Length(MTR)
A2: ENQ-13991-22-23 | B2: 45505 | C2: FA0400002 | D2: 3 CORE X 185 SQ MM + 1 CORE X 150 SQ MM (AB CABLES) (BARE) - 11 KV | E2: WOOD | F2: Copper Tape - 0.045 mm | G2: 914.72 | H2: 105 | I2: 96045.6 | J2: Alumimium | K2: 242 | L2: 1504 | M2: 363968 | N2: Alumimium Alloy | O2: 249 | P2: 406 | Q2: 101094 | R2: Extruded Semiconductive | S2: 189 | T2: 226 | U2: 42714 | V2: HT-XLPE | W2: 140 | X2: 677 | Y2: 94780 | AB2: 35 | AF2: 0 | AJ2: 0 | AL2: PE-ST-7 | AM2: 106 | AN2: 796 | AO2: 84376 | AR2: 0 | AV2: 0 | AZ2: 0 | BD2: 0 | BH2: 0 | BL2: 0 | BP2: 0 | BT2: 0 | BX2: 0 | BZ2: 34312 | CA2: 817289.6 | CH2: 817289.6 | CM2: 817289.6 | CO2: 817289.6 | CP2: 0.18 | CQ2: 147112.13 | CR2: 964401.73 | CS2: 20 | CT2: KMS | CU2: 19288035 | CV2: MD0100029 | CW2: DRUM - 80 X 35 X 39 X 3"+ EXTRA SEGMENT | CX2: 500

Sheet AUTO CALCULATION SHEET (2)
A2: NORTH BIHAR POWER DISTRIBUTION CO. LTD, PATNA
A4: TENDER SPECIFICATION NO () | B4: NIT NO-30/PR/NBPDCL/2024
A5: TENDER DESCRIPTION () | B5: 11 kV AB Cable [3CX185 Sq mm+1Cx150Sq mm]
A6: Last Date & Time of Submission () | B6: 10.09.2024 up to 18:00 Hrs
A7: REVERSE AUCTION | B7: Not Mention.
A8: Price () | B8: Price Variation for AB Cable shall be applicable as per current IEEMA circulars and indices for respective items as applicable on the final date of submission of bid.
A9: Validity () | B9: The tenderers should specify the validity period of their offer which should be for a minimum period of 180 days from the last date of submission of bid.
A10: Delivery Period () | B10: The material are required to be delivered within 04 (Four) months from the date of issue of Purchase Order as per the following delivery schedule. Within 2 (two) months - at least 30 % of the ordered quantity During 3rd(Third) month - at least 35 % of the ordered quantity During 4th(Fourth) month - at least 35 % of the ordered quantity
A11: Payment Terms () | B11: 75% payment along with full amount of taxes, duties and freight keeping 10% retention money & 15% against type test report, on submission of triplicate copy of bills with all relevant documents (Sample check list) enclosed in annexure by the vendor after receipt of the material / equipment in good condition. After successful completion of delivery of entire order or modified quantity as decided during its delivery schedule, 10 % retention money may be released after deduction of penalty.
A12: Standard length () | B12: Standard lengths for each size of power and control cables shall be 500/1000 meters. The cable length per drum shall be subject to a tolerance of plus or minus 5% of the standard drum length.
A13: Packing () | B13: The Cables shall be wound on a drum ( Ref. IS : 10418-1972 and its amendments) of suitable size and packed . The ends of cable shall be sealed by means of non-hygroscopic sealing material. The Cables shall be packed in non-returnable wooden drums. The wooden drums should be bearing distinguishing number with following information duly stenciled on the outer side of one flange.
A14: Technical Specification
N16: =Sheet1!J1 -> Conductor | S16: AL ALLOY | U16: Insulation Screening (Metallic) | AC16: Insulation Screening (Non-Metallic) | AE16: Insulation | AK16: POLY TAPE | AL16: Inner Sheath | AS16: Armouring | BC16: Outer Sheath | BM16: FILLER | BN16: GREASE | BO16: Water swellable Tape | BP16: Semi conducting Water Swellable tape | BQ16: SEMICON TAPE | BR16: GLASS FIBER TAPE | BS16: COPPER WIRE 0.8 MM | BT16: RUBBERIZED COTTON TAPE | BU16: Water Tight Compound | BZ16: DRUM COST PER KM | CA16: TOTAL RM COST | CB16: EXTRA CONSUMPTION | CC16: EXTRA CONSUMPTION VALUE
A17: DOCKET NO. | B17: =Sheet1!B1 -> Base Date | C17: ITEM CODE | D17: PROPOSE ERP ITEM NAME | E17: EX-WORKS (PER KM) | F17: FREIGHT PER KM | G17: PRICE INCLUDING FREIGHT (PER KM) | H17: GST % | I17: GST VALUE | J17: PRICE INCLUDING GST & FREIGHT (PER KM) | K17: QTY | L17: Unit | M17: TOTAL PRICE OF FULL QTY (INCLUDING FRIGHT & GST) | N17: Alumimium | O17: Alumimium ALLOY | P17: Copper | Q17: Flexible Copper | R17: Galvanized steel wire | S17: Alumimium | T17: Alumimium ALLOY | U17: Coper tape - 0.1 mm | V17: Copper Tape - 0.03 mm | W17: Copper Tape - 0.035 mm | X17: Copper Tape - 0.04 mm | Y17: Copper Tape - 0.045 mm | Z17: Copper Tape - 0.050 mm | AA17: Copper Tape - 0.060 mm | AB17: Copper Tape - 0.075 mm(DOUBLE) | AC17: Extruded semiconductive | AD17: Extruded Semiconductive(Stripable) | AE17: HT-XLPE | AF17: LT-XLPE | AG17: TR XLPE | AH17: Type A PVC | AI17: Type C PVC (HR) | AJ17: XLPE | AK17: POLY TAPE | AL17: FR PVC Type ST-1 | AM17: FR PVC Type ST-2 | AN17: FRLSH PVC Type ST-2 | AO17: PVC Type ST-1 | AP17: PVC Type ST-1-PRESSURE EXTRUDED | AQ17: PVC Type ST-2 | AR17: PVC Type ST-2-PRESSURE EXTRUDED | AS17: ACSR CORE WIRE | AT17: ACSR DOG STEEL WIRE | AU17: Aluminium Flat Strip | AV17: Aluminium Round Wire | AW17: Double Steel Tape | AX17: Galvanised Steel Flat Strip | AY17: Galvanised Steel Flat Strip (Double) | AZ17: Galvanised Steel Flat Strip-B | BA17: Galvanised Steel Round Wire | BB17: Galvanised Steel Round Wire (Double) | BC17: FR PVC Type ST-1 | BD17: FR PVC Type ST-2 | BE17: FRLSH PVC Type ST-1 | BF17: FRLSH PVC Type ST-2 | BG17: PE, ST-3 | BH17: PE-ST-7 | BI17: PVC Type ST-1 | BJ17: PVC Type ST-2 | BK17: PVC Type ST-2-PRESSURE EXTRUDED | BL17: UV & Track Resistant XLPE | BM17: FILLER | BN17: Grease | BO17: Water swellable Tape | BP17: Semi conducting Water Swellable tape | BQ17: SEMICON TAPE | BR17: GLASS FIBER TAPE | BS17: COPPER WIRE 0.8 MM | BT17: RUBBERIZED COTTON TAPE | BU17: Water Tight Compound | BV17: =Sheet1!E1 -> Propose Drum Type | BW17: =Sheet1!CV1 -> DRUM CODE | BX17: =Sheet1!CW1 -> DRUM SIZE (FxbXtx Ft) | BY17: =Sheet1!CX1 -> Party Standard Length(MTR) | CD17: MFG% | CE17: MFG VALUE | CF17: PROF% | CG17: PROFIT VALUE | CH17: 1ST EX-WORKS | CI17: Intt % | CJ17: INTT VALUE | CK17: insp% | CL17: INSP VALUE
N18: 232 | O18: =+IFERROR(VLOOKUP($O$17,Sheet1!J:L,2,0),0) -> 0 | P18: =+IFERROR(VLOOKUP($P$17,Sheet1!J:M,2,0),0) -> 0 | Q18: =+IFERROR(VLOOKUP($Q$17,Sheet1!J:M,2,0),0) -> 0 | R18: =+IFERROR(VLOOKUP($R$17,Sheet1!J:M,2,0),0) -> 0 | S18: =+IFERROR(VLOOKUP($S$17,Sheet1!N:Q,2,0),0) -> 0 | T18: =N18+7 -> 239 | U18: =+IFERROR(VLOOKUP($U$17,Sheet1!F:I,2,0),0) -> 0 | V18: =+IFERROR(VLOOKUP($V$17,Sheet1!F:I,2,0),0) -> 0 | W18: =+IFERROR(VLOOKUP($W$17,Sheet1!F:I,2,0),0) -> 0 | X18: =+IFERROR(VLOOKUP($X$17,Sheet1!F:I,2,0),0) -> 0 | Y18: 921 | Z18: =+IFERROR(VLOOKUP($Z$17,Sheet1!F:I,2,0),0) -> 0 | AA18: =+IFERROR(VLOOKUP($AA$17,Sheet1!F:I,2,0),0) -> 0 | AB18: =+IFERROR(VLOOKUP($AB$17,Sheet1!F:I,2,0),0) -> 0 | AC18: 194 | AD18: =+IFERROR(VLOOKUP($AD$17,Sheet1!R:U,2,0),0) -> 0 | AE18: 135 | AF18: =+IFERROR(VLOOKUP($AF$17,Sheet1!V:Y,2,0),0) -> 0 | AG18: =+IFERROR(VLOOKUP($AG$17,Sheet1!V:Y,2,0),0) -> 0 | AH18: =+IFERROR(VLOOKUP($AH$17,Sheet1!V:Y,2,0),0) -> 0 | AI18: =+IFERROR(VLOOKUP($AI$17,Sheet1!V:Y,2,0),0) -> 0 | AJ18: =+IFERROR(VLOOKUP($AJ$17,Sheet1!V:Y,2,0),0) -> 0 | AK18: =+IFERROR(VLOOKUP($AK$17,Sheet1!Z2:AA840,2,0),0) -> 0 | AL18: =+IFERROR(VLOOKUP($AL$17,Sheet1!AD2:AG840,2,0),0) -> 0 | AM18: =+IFERROR(VLOOKUP($AM$17,Sheet1!AD2:AG840,2,0),0) -> 0 | AN18: =+IFERROR(VLOOKUP($AN$17,Sheet1!AD2:AG840,2,0),0) -> 0 | AO18: =+IFERROR(VLOOKUP($AO$17,Sheet1!AD2:AG840,2,0),0) -> 0 | AP18: =+IFERROR(VLOOKUP($AP$17,Sheet1!AD2:AG840,2,0),0) -> 0 | AQ18: =+IFERROR(VLOOKUP($AQ$17,Sheet1!AD2:AG840,2,0),0) -> 0 | AR18: =+IFERROR(VLOOKUP($AR$17,Sheet1!AD2:AG840,2,0),0) -> 0 | AS18: =+IFERROR(VLOOKUP($AS$17,Sheet1!AH2:AK840,2,0),0) -> 0 | AT18: =+IFERROR(VLOOKUP($AT$17,Sheet1!AH2:AK840,2,0),0) -> 0 | AU18: =+IFERROR(VLOOKUP($AU$17,Sheet1!AH2:AK840,2,0),0) -> 0 | AV18: =+IFERROR(VLOOKUP($AV$17,Sheet1!AH2:AK840,2,0),0) -> 0 | AW18: =+IFERROR(VLOOKUP($AW$17,Sheet1!AH2:AK840,2,0),0) -> 0 | AX18: =+IFERROR(VLOOKUP($AX$17,Sheet1!AH2:AK840,2,0),0) -> 0 | AY18: =+IFERROR(VLOOKUP($AY$17,Sheet1!AH2:AK840,2,0),0) -> 0 | AZ18: =+IFERROR(VLOOKUP($AZ$17,Sheet1!AH2:AK840,2,0),0) -> 0 | BA18: =+IFERROR(VLOOKUP($BA$17,Sheet1!AH2:AK840,2,0),0) -> 0 | BB18: =+IFERROR(VLOOKUP($BB$17,Sheet1!AH2:AK840,2,0),0) -> 0 | BC18: =+IFERROR(VLOOKUP($BC$17,Sheet1!AL2:AO840,2,0),0) -> 0 | BD18: =+IFERROR(VLOOKUP($BD$17,Sheet1!AL2:AO840,2,0),0) -> 0 | BE18: =+IFERROR(VLOOKUP($BE$17,Sheet1!AL2:AO840,2,0),0) -> 0 | BF18: =+IFERROR(VLOOKUP($BF$17,Sheet1!AL2:AO840,2,0),0) -> 0 | BG18: =+IFERROR(VLOOKUP($BG$17,Sheet1!AL2:AO840,2,0),0) -> 0 | BH18: =+IFERROR(VLOOKUP($BH$17,Sheet1!AL2:AO840,2,0),0) -> 106 | BI18: =+IFERROR(VLOOKUP($BI$17,Sheet1!AL2:AO840,2,0),0) -> 0 | BJ18: =+IFERROR(VLOOKUP($BJ$17,Sheet1!AL2:AO840,2,0),0) -> 0 | BK18: =+IFERROR(VLOOKUP($BK$17,Sheet1!AL2:AO840,2,0),0) -> 0 | BL18: =+IFERROR(VLOOKUP($BL$17,Sheet1!AL2:AO840,2,0),0) -> 0 | BM18: =+IFERROR(VLOOKUP($BM$17,Sheet1!AP2:AS840,2,0),0) -> 0 | BN18: =+IFERROR(VLOOKUP($BN$17,Sheet1!AT2:AW840,2,0),0) -> 0 | BO18: =+IFERROR(VLOOKUP($BO$17,Sheet1!AX2:BA840,2,0),0) -> 0 | BP18: =+IFERROR(VLOOKUP($BP$17,Sheet1!BB2:BE840,2,0),0) -> 0 | BQ18: =+IFERROR(VLOOKUP($BQ$17,Sheet1!BF2:BI840,2,0),0) -> 0 | BR18: =+IFERROR(VLOOKUP($BR$17,Sheet1!BJ2:BM840,2,0),0) -> 0 | BS18: =+IFERROR(VLOOKUP($BS$17,Sheet1!BN2:BQ840,2,0),0) -> 0 | BT18: =+IFERROR(VLOOKUP($BT$17,Sheet1!BR2:BU840,2,0),0) -> 0 | BU18: =+IFERROR(VLOOKUP($BU$17,Sheet1!BV2:BY840,2,0),0) -> 0
A19: =Sheet1!A2 -> ENQ-13991-22-23 | B19: =Sheet1!B2 -> 45505 | C19: =Sheet1!C2 -> FA0400002 | D19: =Sheet1!D2 -> 3 CORE X 185 SQ MM + 1 CORE X 150 SQ MM (AB CABLES) (BARE) - 11 KV | E19: =CH19+CJ19+CL19 -> 1393936.1 | F19: =ROUNDUP(M22,0) -> 14700 | G19: =E19+F19 -> 1408636.1 | H19: =Sheet1!CP2 -> 0.18 | I19: =G19*H19 -> 253554.49 | J19: =G19+I19 -> 1662190.6 | K19: =Sheet1!CS2 -> 20 | L19: =Sheet1!CT2 -> KMS | M19: =J19*K19 -> 33243811 | N19: 1500 | O19: =+IFERROR(VLOOKUP($O$17,Sheet1!J2:L2,3,0),0) -> 0 | P19: =+IFERROR(VLOOKUP($P$17,Sheet1!J2:M2,3,0),0) -> 0 | Q19: =+IFERROR(VLOOKUP($Q$17,Sheet1!J2:M2,3,0),0) -> 0 | R19: =+IFERROR(VLOOKUP($R$17,Sheet1!J2:M2,3,0),0) -> 0 | S19: =+IFERROR(VLOOKUP($S$17,Sheet1!N2:Q2,3,0),0) -> 0 | T19: 413 | U19: =+IFERROR(VLOOKUP($U$17,Sheet1!F2:I2,3,0),0) -> 0 | V19: =+IFERROR(VLOOKUP($V$17,Sheet1!F2:I2,3,0),0) -> 0 | W19: =+IFERROR(VLOOKUP($W$17,Sheet1!F2:I2,3,0),0) -> 0 | X19: =+IFERROR(VLOOKUP($X$17,Sheet1!F2:I2,3,0),0) -> 0 | Y19: 148 | Z19: =+IFERROR(VLOOKUP($Z$17,Sheet1!F2:I2,3,0),0) -> 0 | AA19: =+IFERROR(VLOOKUP($AA$17,Sheet1!F2:I2,3,0),0) -> 0 | AB19: =+IFERROR(VLOOKUP($AB$17,Sheet1!F2:I2,3,0),0) -> 0 | AC19: 392 | AD19: =+IFERROR(VLOOKUP($AD$17,Sheet1!R2:U2,2,0),0) -> 0 | AE19: 670 | AF19: =+IFERROR(VLOOKUP($AF$17,Sheet1!V2:Y2,3,0),0) -> 0 | AG19: =+IFERROR(VLOOKUP($AG$17,Sheet1!V2:Y2,3,0),0) -> 0 | AH19: =+IFERROR(VLOOKUP($AH$17,Sheet1!V2:Y2,3,0),0) -> 0 | AI19: =+IFERROR(VLOOKUP($AI$17,Sheet1!V2:Y2,3,0),0) -> 0 | AJ19: =+IFERROR(VLOOKUP($AJ$17,Sheet1!V2:Y2,3,0),0) -> 0 | AK19: =+IFERROR(VLOOKUP($AK$17,Sheet1!Z2:AB2,3,0),0) -> 0 | AL19: =+IFERROR(VLOOKUP($AL$17,Sheet1!AD2:AG2,3,0),0) -> 0 | AM19: =+IFERROR(VLOOKUP($AM$17,Sheet1!AD2:AG2,3,0),0) -> 0 | AN19: =+IFERROR(VLOOKUP($AN$17,Sheet1!AD2:AG2,3,0),0) -> 0 | AO19: =+IFERROR(VLOOKUP($AO$17,Sheet1!AD2:AG2,3,0),0) -> 0 | AP19: =+IFERROR(VLOOKUP($AP$17,Sheet1!AD2:AG2,3,0),0) -> 0 | AQ19: =+IFERROR(VLOOKUP($AQ$17,Sheet1!AD2:AG2,3,0),0) -> 0 | AR19: =+IFERROR(VLOOKUP($AR$17,Sheet1!AD2:AG2,3,0),0) -> 0 | AS19: =+IFERROR(VLOOKUP($AS$17,Sheet1!AH2:AK2,3,0),0) -> 0 | AT19: =+IFERROR(VLOOKUP($AT$17,Sheet1!AH2:AK2,3,0),0) -> 0 | AU19: =+IFERROR(VLOOKUP($AU$17,Sheet1!AH2:AK2,3,0),0) -> 0 | AV19: =+IFERROR(VLOOKUP($AV$17,Sheet1!AH2:AK2,3,0),0) -> 0 | AW19: =+IFERROR(VLOOKUP($AW$17,Sheet1!AH2:AK2,3,0),0) -> 0 | AX19: =+IFERROR(VLOOKUP($AX$17,Sheet1!AH2:AK2,3,0),0) -> 0 | AY19: =+IFERROR(VLOOKUP($AY$17,Sheet1!AH2:AK2,3,0),0) -> 0 | AZ19: =+IFERROR(VLOOKUP($AZ$17,Sheet1!AH2:AK2,3,0),0) -> 0 | BA19: =+IFERROR(VLOOKUP($BA$17,Sheet1!AH2:AK2,3,0),0) -> 0 | BB19: =+IFERROR(VLOOKUP($BB$17,Sheet1!AH2:AK2,3,0),0) -> 0 | BC19: =+IFERROR(VLOOKUP($BC$17,Sheet1!AL2:AO2,3,0),0) -> 0 | BD19: =+IFERROR(VLOOKUP($BD$17,Sheet1!AL2:AO2,3,0),0) -> 0 | BE19: =+IFERROR(VLOOKUP($BE$17,Sheet1!AL2:AO2,3,0),0) -> 0 | BF19: =+IFERROR(VLOOKUP($BF$17,Sheet1!AL2:AO2,3,0),0) -> 0 | BG19: =+IFERROR(VLOOKUP($BG$17,Sheet1!AL2:AO2,3,0),0) -> 0 | BH19: 585 | BI19: =+IFERROR(VLOOKUP($BI$17,Sheet1!AL2:AO2,3,0),0) -> 0 | BJ19: =+IFERROR(VLOOKUP($BJ$17,Sheet1!AL2:AO2,3,0),0) -> 0 | BK19: =+IFERROR(VLOOKUP($BK$17,Sheet1!AL2:AO2,3,0),0) -> 0 | BL19: =+IFERROR(VLOOKUP($BL$17,Sheet1!AL2:AO2,3,0),0) -> 0 | BM19: =+IFERROR(VLOOKUP($BM$17,Sheet1!AP2:AS2,3,0),0) -> 0 | BN19: =+IFERROR(VLOOKUP($BN$17,Sheet1!AT2:AW2,3,0),0) -> 0 | BO19: =+IFERROR(VLOOKUP($BO$17,Sheet1!AX2:BA2,3,0),0) -> 0 | BP19: =+IFERROR(VLOOKUP($BP$17,Sheet1!BB2:BE2,3,0),0) -> 0 | BQ19: =+IFERROR(VLOOKUP($BQ$17,Sheet1!BF2:BI2,3,0),0) -> 0 | BR19: =+IFERROR(VLOOKUP($BR$17,Sheet1!BJ2:BM2,3,0),0) -> 0 | BS19: =+IFERROR(VLOOKUP($BS$17,Sheet1!BN2:BQ2,3,0),0) -> 0 | BT19: =+IFERROR(VLOOKUP($BT$17,Sheet1!BR2:BU2,3,0),0) -> 0 | BU19: =+IFERROR(VLOOKUP($BU$17,Sheet1!BV2:BY2,3,0),0) -> 0 | BV19: =Sheet1!E2 -> WOOD | BW19: =Sheet1!CV2 -> MD0100029 | BX19: =Sheet1!CW2 -> DRUM - 80 X 35 X 39 X 3"+ EXTRA SEGMENT | BY19: =Sheet1!CX2 -> 500 | BZ19: =Sheet1!BZ2 -> 34312 | CA19: =SUMPRODUCT($N$18:$BU$18,N19:BU19)+BZ19 -> 845835 | CB19: =Sheet1!CB2 -> 0 | CC19: =CA19*CB19 -> 0 | CD19: 0.6 | CE19: =CA19*CD19 -> 507501 | CF19: 0 | CG19: =CA19*CF19 -> 0 | CH19: =CA19+CC19+CE19+CG19 -> 1353336 | CI19: 0.02 | CJ19: =CH19*CI19 -> 27066.72 | CK19: 0.01 | CL19: =CH19*CK19 -> 13533.36
E21: Order Quantity | F21: Stnd Length | G21: Truck type | H21: Fare of one truck | I21: No of Drum in one truck | J21: Total length in one Truck | K21: No of Truck | L21: Total Freight | M21: Freight per KM | T21: CABLE WEIGHT KG/KM | Y21: DRUM WEIGHT | AC21: CABLE+DRUM WEIGHT | AE21: TRUCK WEIGHT
E22: =K19 -> 20 | F22: =BY19/1000 -> 0.5 | G22: 16 MT | H22: 42000 | I22: 6 | J22: =F22*I22 -> 3 | K22: =ROUNDUP((E22/J22),0) -> 7 | L22: =M22*E22 -> 294000 | M22: =(H22*K22)/E22 -> 14700 | T22: =SUM(N19:BH19) -> 3708 | Y22: =450+80 -> 530 | AC22: =((T22*F22)+Y22) -> 2384 | AE22: =I22*AC22 -> 14304
E25: ESTIMATE COST | F25: OUR COST | G25: DIFF % FROM OUR PRICE
D26: =D19 -> 3 CORE X 185 SQ MM + 1 CORE X 150 SQ MM (AB CABLES) (BARE) - 11 KV | E26: 28408606 | F26: =M19 -> 33243811 | G26: =((F26-E26)/F26)*100 -> 14.544677 | H26: INCLUDING GST

Sheet PV HTABC
A1: Base Date | B1: 45505
A2: PV Terms(Price Variation Formula) | B2: Price Variation for AB Cable shall be applicable as per current IEEMA circulars and indices for respective items as applicable on the final date of submission of bid.
A5: Item | B5: Ex-Work
A6: ='AUTO CALCULATION SHEET (2)'!D19 -> 3 CORE X 185 SQ MM + 1 CORE X 150 SQ MM (AB CABLES) (BARE) - 11 KV | B6: ='AUTO CALCULATION SHEET (2)'!E19 -> 1393936.1
AD7: VALUE ADDITION CALCULATION
A9: Item | B9: Calculation part | C9: Date of Inspection | D9: Applicable Date | I9: BASE DATE | N9: FACTORS | U9: Ex-Work Po | V9: PVC of al (PHASE) | W9: PVC of al (MESSENGER) | X9: PVC of CU tape | Y9: PVC of XLPE (PHASE) | Z9: PVC of PVC (PHASE) | AA9: PVC of XLPE (MESSENGER) | AB9: PV/PKM | AC9: Billing Price/PKM | AD9: ='AUTO CALCULATION SHEET (2)'!N17 -> Alumimium | AE9: ='AUTO CALCULATION SHEET (2)'!T17 -> Alumimium ALLOY | AF9: ='AUTO CALCULATION SHEET (2)'!Y17 -> Copper Tape - 0.045 mm | AG9: ='AUTO CALCULATION SHEET (2)'!AC17 -> Extruded semiconductive | AH9: ='AUTO CALCULATION SHEET (2)'!AE17 -> HT-XLPE | AI9: ='AUTO CALCULATION SHEET (2)'!BH17 -> PE-ST-7 | AJ9: RMC | AK9: Drum | AL9: RMC+Drum | AM9: VA | AN9: Groos VA% | AO9: Mfg % | AP9: Int % | AQ9: Ins% | AR9: Net VA
D10: Date | E10: Al | F10: Cc | G10: PVCc (PE ST 7) | H10: CU | I10: Date | J10: Alo | K10: Cco | L10: PVCco (PE ST 7) | M10: Cuo | AD10: 239 | AE10: =AD10+7 -> 246 | AF10: 910 | AG10: 197 | AH10: 130 | AI10: 105
N11: n | O11: Alph | P11: Alm | Q11: CUFtph | R11: CCF1Alph | S11: CCF2Alph | T11: CCFAlm | AD11: Kg/Km | AE11: Kg/Km | AF11: Kg/Km | AG11: Kg/Km | AH11: Kg/Km | AI11: Kg/Km
A12: =A6 -> 3 CORE X 185 SQ MM + 1 CORE X 150 SQ MM (AB CABLES) (BARE) - 11 KV | C12: PROVISIONAL | D12: 45541 | E12: 228435.55 | F12: 174080 | G12: 142250 | H12: 817299.76 | I12: =B1 -> 45505 | J12: 230985 | K12: 174080 | L12: 142250 | M12: 814140 | N12: 3 | O12: 0.533 | P12: 0.425 | Q12: 0.042 | R12: 0.285 | S12: 0.214 | U12: =B6 -> 1393936.1 | V12: =O12*N12*(E12-J12) -> -4076.5706 | W12: =P12*(E12-J12) -> -1083.5163 | X12: =Q12*N12*(H12-M12) -> 398.12976 | Y12: =R12*N12*(F12-K12) -> 0 | Z12: =S12*N12*(G12-L12) -> 0 | AA12: =T12*(F12-K12) -> 0 | AB12: =V12+W12+X12+Y12+Z12+AA12 -> -4761.957 | AC12: =U12+AB12 -> 1389174.1 | AD12: ='AUTO CALCULATION SHEET (2)'!N19 -> 1500 | AE12: ='AUTO CALCULATION SHEET (2)'!T19 -> 413 | AF12: ='AUTO CALCULATION SHEET (2)'!Y19 -> 148 | AG12: ='AUTO CALCULATION SHEET (2)'!AC19 -> 392 | AH12: ='AUTO CALCULATION SHEET (2)'!AE19 -> 670 | AI12: ='AUTO CALCULATION SHEET (2)'!BH19 -> 585 | AJ12: =SUMPRODUCT(AD12:AI12,$AD$10:$AI$10) -> 820527 | AK12: ='AUTO CALCULATION SHEET (2)'!BZ19 -> 34312 | AL12: =AJ12+AK12 -> 854839 | AM12: =AC12-AL12 -> 534335.12 | AN12: =ROUND((AM12/AL12)*100,2) -> 62.51 | AO12: 0 | AP12: 2 | AQ12: 1 | AR12: =AN12-AO12-AP12-AQ12 -> 59.51
