Workbook

Sheet Sheet1
A1: DOCKET NO. | B1: Base Date | C1: ITEM CODE | D1: PROPOSE ERP ITEM NAME | E1: PROPOSE DRUM TYPE | F1: Insulation Screening (Metallic) | G1: RM RATE (Insulation Screening (Metallic)) | H1: Weight (Insulation Screening (Metallic)) | I1: COST(Insulation Screening (Metallic)) | J1: Conductor | K1: RM RATE(Conductor) | L1: WEIGHT(Conductor) | M1: COST(Conductor) | N1: AL ALLOY | O1: RM RATE(Alu Alloy) | P1: WEIGHT(Alu Alloy) | Q1: COST(Alu Alloy) | R1: Insulation Screening (Non-Metallic) | S1: RM RATE(Insulation Screening (Non-Metallic)) | T1: WEIGHT(Insulation Screening (Non-Metallic)) | U1: COST(Insulation Screening (Non-Metallic)) | V1: Insulation | W1: RM RATE(Insulation) | X1: WEIGHT(Insulation) | Y1: COST(Insulation) | Z1: POLY TAPE | AA1: RM RATE (Poly Tape) | AB1: WEIGHT (Poly Tape) | AC1: COST(Poly Tape) | AD1: Inner Sheath | AE1: RM RATE(Inner Sheath) | AF1: WEIGHT(Inner Sheath) | AG1: COST(Inner Sheath) | AH1: Armouring | AI1: RM RATE(Armouring) | AJ1: WEIGHT(Armouring) | AK1: COST(Armouring) | AL1: Outer Sheath | AM1: RM RATE(Outer Sheath) | AN1: WEIGHT(Outer Sheath) | AO1: COST(Outer Sheath) | AP1: FILLER | AQ1: RM RATE(Filler) | AR1: WEIGHT(Filler) | AS1: COST(Filler) | AT1: GREASE | AU1: RM RATE(Grease) | AV1: WEIGHT(Grease) | AW1: COST(Grease) | AX1: Water swellable Tape | AY1: RM RATE(Water swellable Tape) | AZ1: WEIGHT(Water swellable Tape) | BA1: COST(Water swellable Tape) | BB1: Semi conducting Water Swellable tape | BC1: RM RATE(Semi conducting Water Swellable tape) | BD1: WEIGHT(Semi conducting Water Swellable tape) | BE1: COST(Semi conducting Water Swellable tape) | BF1: SEMICON TAPE | BG1: RM RATE(SEMICON TAPE) | BH1: WEIGHT(SEMICON TAPE) | BI1: COST(SEMICON TAPE) | BJ1: GLASS FIBER TAPE | BK1: RM RATE(GLASS FIBER TAPE) | BL1: WEIGHT(GLASS FIBER TAPE) | BM1: COST(GLASS FIBER TAPE) | BN1: COPPER WIRE 0.8 MM | BO1: RM RATE(COPPER WIRE 0.8 MM) | BP1: WEIGHT(COPPER WIRE 0.8 MM) | BQ1: COST(COPPER WIRE 0.8 MM) | BR1: RUBBERIZED COTTON TAPE | BS1: RM RATE(RUBBERIZED COTTON TAPE) | BT1: WEIGHT(RUBBERIZED COTTON TAPE) | BU1: COST(RUBBERIZED COTTON TAPE) | BV1: Water Tight Compound | BW1: RM RATE(Water Tight Compound) | BX1: WEIGHT(Water Tight Compound) | BY1: COST(Water Tight Compound) | BZ1: DRUM COST PER KM | CA1: TOTAL RM COST | CB1: FIRM % | CC1: FIRM VALUE | CD1: MFG% | CE1: MFG VALUE | CF1: PROF% | CG1: PROFIT VALUE | CH1: 1ST EX-WORKS | CI1: Intt % | CJ1: INTT VALUE | CK1: insp% | CL1: INSP VALUE | CM1: EX-WORKS (PER KM) | CN1: FREIGHT PER KM | CO1: PRICE INCLUDING FREIGHT (PER KM) | CP1: GST % | CQ1: GST VALUE | CR1: PRICE INCLUDING GST & FREIGHT (PER KM) | CS1: QTY | CT1: Unit | CU1: TOTAL PRICE OF FULL QTY (INCLUDING FRIGHT & GST) | CV1: DRUM CODE | CW1: DRUM SIZE (FxbXtx Ft) | CX1: PARTY STANDARD LENGTH (MTR)
A2: ENQ-11487-22-23 | B2: 45202 | C2: FA0200003 | D2: 12 CORE X 2.5 SQ. MM. CU/ARD - WIRE (PVC) | E2: WOOD | J2: Tinned Copper | L2: 266.4 | P2: 0 | T2: 0 | V2: Type C PVC (HR) | W2: 104.45 | X2: 156 | Y2: 16294.2 | Z2: POLY TAPE | AA2: 122.4 | AB2: 6 | AC2: 734.4 | AD2: FR PVC Type ST-2 | AE2: 95.5 | AF2: 40 | AG2: 3820 | AH2: Galvanised Steel Round Wire | AI2: 86.62 | AJ2: 508 | AK2: 44002.96 | AL2: FRLSH PVC Type ST-2 | AM2: 94.5 | AN2: 170 | AO2: 16065 | AR2: 0 | AV2: 0 | AZ2: 0 | BD2: 0 | BH2: 0 | BL2: 28 | BP2: 0 | BT2: 0 | BX2: 0 | BZ2: 5151.48 | CA2: 86068.04 | CH2: 86068.04 | CM2: 86068.04 | CO2: 86068.04 | CP2: 0.18 | CQ2: 15492.25 | CR2: 101560.29 | CS2: 20 | CT2: KMS | CU2: 2031206 | CV2: MD0100066 | CW2: DRUM - 40 X 15 X 23 X 2 | CX2: 500
A3: ENQ-11487-22-23 | B3: 45202 | C3: FA0200008 | D3: 2 CORE X 2.5 SQ. MM. CU/ARD - WIRE (PVC) | E3: WOOD | J3: Tinned Copper | L3: 44.4 | P3: 0 | T3: 0 | V3: Type C PVC (HR) | W3: 104.45 | X3: 26 | Y3: 2715.7 | Z3: POLY TAPE | AA3: 122.4 | AB3: 3 | AC3: 367.2 | AD3: FR PVC Type ST-2 | AE3: 95.5 | AF3: 39 | AG3: 3724.5 | AH3: Galvanised Steel Round Wire | AI3: 86.62 | AJ3: 251 | AK3: 21741.62 | AL3: FRLSH PVC Type ST-2 | AM3: 94.5 | AN3: 93 | AO3: 8788.5 | AR3: 0 | AV3: 0 | AZ3: 0 | BD3: 0 | BH3: 0 | BL3: 16 | BP3: 0 | BT3: 0 | BX3: 0 | BZ3: 3850.93 | CA3: 41188.45 | CH3: 41188.45 | CM3: 41188.45 | CO3: 41188.45 | CP3: 0.18 | CQ3: 7413.92 | CR3: 48602.37 | CS3: 23 | CT3: KMS | CU3: 1117855 | CV3: MD0100003 | CW3: DRUM - 28 X 14 X 23 X 2 | CX3: 500
A4: ENQ-11487-22-23 | B4: 45202 | C4: FA0200002 | D4: 10 CORE X 2.5 SQ. MM. CU/ARD - WIRE (PVC) | E4: WOOD | J4: Tinned Copper | L4: 222 | P4: 0 | T4: 0 | V4: Type C PVC (HR) | W4: 104.45 | X4: 130 | Y4: 13578.5 | Z4: POLY TAPE | AA4: 122.4 | AB4: 5 | AC4: 612 | AD4: FR PVC Type ST-2 | AE4: 95.5 | AF4: 38 | AG4: 3629 | AH4: Galvanised Steel Round Wire | AI4: 86.62 | AJ4: 492 | AK4: 42617.04 | AL4: FRLSH PVC Type ST-2 | AM4: 94.5 | AN4: 166 | AO4: 15687 | AR4: 0 | AV4: 0 | AZ4: 0 | BD4: 0 | BH4: 0 | BL4: 28 | BP4: 0 | BT4: 0 | BX4: 0 | BZ4: 5151.48 | CA4: 81275.02 | CH4: 81275.02 | CM4: 81275.02 | CO4: 81275.02 | CP4: 0.18 | CQ4: 14629.5 | CR4: 95904.52 | CS4: 25 | CT4: KMS | CU4: 2397613 | CV4: MD0100066 | CW4: DRUM - 40 X 15 X 23 X 2 | CX4: 500
A5: ENQ-11487-22-23 | B5: 45202 | C5: FA0200011 | D5: 4 CORE X 2.5 SQ. MM. CU/ARD - WIRE (PVC) | E5: WOOD | J5: Tinned Copper | L5: 88.8 | P5: 0 | T5: 0 | V5: Type C PVC (HR) | W5: 104.45 | X5: 52 | Y5: 5431.4 | Z5: POLY TAPE | AA5: 122.4 | AB5: 3 | AC5: 367.2 | AD5: FR PVC Type ST-2 | AE5: 95.5 | AF5: 27 | AG5: 2578.5 | AH5: Galvanised Steel Round Wire | AI5: 86.62 | AJ5: 289 | AK5: 25033.18 | AL5: FRLSH PVC Type ST-2 | AM5: 94.5 | AN5: 104 | AO5: 9828 | AR5: 0 | AV5: 0 | AZ5: 0 | BD5: 0 | BH5: 0 | BL5: 19 | BP5: 0 | BT5: 0 | BX5: 0 | BZ5: 4610.79 | CA5: 47849.07 | CH5: 47849.07 | CM5: 47849.07 | CO5: 47849.07 | CP5: 0.18 | CQ5: 8612.83 | CR5: 56461.9 | CS5: 40 | CT5: KMS | CU5: 2258476 | CV5: MD0100005 | CW5: DRUM - 36 X 14 X 23 X 2 | CX5: 500

Sheet AUTO CALCULATION SHEET (2)
A2: SOUTH BIHAR POWER DISTRIBUTION CO. LTD, PATNA
A4: TENDER SPECIFICATION NO () | B4: 64/PR/SBPDCL/2023
A5: TENDER DESCRIPTION () | B5: TENDER SPECIFICATION FOR i. 1.1 kV Copper Control cable(2Cx 2.5 Sq mm), ii. 1.1 kV Copper Control cable(4Cx 2.5 Sq mm) iii. 1.1 kV Copper Control cable(10Cx 2.5 Sq mm)& iv. 1.1 kV Copper Control cable(12Cx 2.5 Sq mm)
A6: Last Date & Time of Submission () | B6: 16.11.2023, up to 18:00 Hrs
A7: REVERSE AUCTION | B7: Not Mention.
A8: Price () | B8: Price Variation for Control Cable shall be applicable as per current IEEMA as applicable on the final date of submission of bid. The price variation shall be limited to the contractual delivery period. In case actual supplies are made beyond the contractual delivery period, the prices prevailing at the time of contractual delivery period or actual date of supply, whichever is less shall be taken. For the purpose of calculation of PV, date of delivery is to be taken as date on which material is notified as being ready for inspection as per supplier. Base date will be one month prior to the last date of submission of bid against the NIT.
A9: Validity () | B9: The tenderers should specify the validity period of their offer which should be for a minimum period of 180 days from the last date of submission of bid.
A10: Payment Terms () | B10: 90% payment along with full amount of taxes, duties and freight keeping 10% retention money , on submission of triplicate copy of bills with all relevant documents (Sample check list) enclosed in annexure by the vendor after receipt of the material / equipment in good condition. After successful completion of delivery of entire order or modified quantity as decided during its delivery schedule, 10 % retention money may be released after deduction of penalty. Payment will be released normally within 15 working days from the date of submission of bill along with all required relevant document(s) to Sr. Manager (Finance), NBPDCL/SBPDCL.
A11: Standard length () | B11: Standard lengths for each size of power and control cables shall be 500/1000 meters. The cable length per drum shall be subject to a tolerance of plus or minus 5% of the standard drum length.
A12: Packing () | B12: Cables shall be supplied on returnable wooden or steel drums of heavy construction. Wooden drum shall be properly seasoned sound and free from defects. Wood preservative shall be applied to the entire drum.
A13: Technical Specification
N15: =Sheet1!J1 -> Conductor | S15: AL ALLOY | U15: Insulation Screening (Metallic) | AC15: Insulation Screening (Non-Metallic) | AE15: Insulation | AK15: POLY TAPE | AL15: Inner Sheath | AS15: Armouring | BC15: Outer Sheath | BM15: FILLER | BN15: GREASE | BO15: Water swellable Tape | BP15: Semi conducting Water Swellable tape | BQ15: SEMICON TAPE | BR15: GLASS FIBER TAPE | BS15: COPPER WIRE 0.8 MM | BT15: RUBBERIZED COTTON TAPE | BU15: Water Tight Compound | BZ15: DRUM COST PER KM | CA15: TOTAL RM COST | CB15: EXTRA CONSUMPTION | CC15: EXTRA CONSUMPTION VALUE
A16: DOCKET NO. | B16: =Sheet1!B1 -> Base Date | C16: ITEM CODE | D16: PROPOSE ERP ITEM NAME | E16: EX-WORKS (PER KM) | F16: FREIGHT PER KM | G16: PRICE INCLUDING FREIGHT (PER KM) | H16: GST % | I16: GST VALUE | J16: PRICE INCLUDING GST & FREIGHT (PER KM) | K16: QTY | L16: Unit | M16: TOTAL PRICE OF FULL QTY (INCLUDING FRIGHT & GST) | N16: Alumimium | O16: Tinned Copper | P16: Copper | Q16: Flexible Copper | R16: Galvanized steel wire | S16: Alumimium | T16: Alumimium ALLOY | U16: Coper tape - 0.1 mm | V16: Copper Tape - 0.03 mm | W16: Copper Tape - 0.035 mm | X16: Copper Tape - 0.04 mm | Y16: Copper Tape - 0.045 mm | Z16: Copper Tape - 0.050 mm | AA16: Copper Tape - 0.060 mm | AB16: Copper Tape - 0.075 mm(DOUBLE) | AC16: Extruded semiconductive | AD16: Extruded Semiconductive(Stripable) | AE16: HT-XLPE | AF16: LT-XLPE | AG16: TR XLPE | AH16: Type A PVC | AI16: Type C PVC (HR) | AJ16: XLPE | AK16: POLY TAPE | AL16: FR PVC Type ST-1 | AM16: FR PVC Type ST-2 | AN16: FRLSH PVC Type ST-2 | AO16: PVC Type ST-1 | AP16: PVC Type ST-1-PRESSURE EXTRUDED | AQ16: PVC Type ST-2 | AR16: PVC Type ST-2-PRESSURE EXTRUDED | AS16: ACSR CORE WIRE | AT16: ACSR DOG STEEL WIRE | AU16: Aluminium Flat Strip | AV16: Aluminium Round Wire | AW16: Double Steel Tape | AX16: Galvanised Steel Flat Strip | AY16: Galvanised Steel Flat Strip (Double) | AZ16: Galvanised Steel Flat Strip-B | BA16: Galvanised Steel Round Wire | BB16: Galvanised Steel Round Wire (Double) | BC16: FR PVC Type ST-1 | BD16: FR PVC Type ST-2 | BE16: FRLSH PVC Type ST-1 | BF16: FRLSH PVC Type ST-2 | BG16: PE, ST-3 | BH16: PE, ST-7 | BI16: PVC Type ST-1 | BJ16: PVC Type ST-2 | BK16: PVC Type ST-2-PRESSURE EXTRUDED | BL16: UV & Track Resistant XLPE | BM16: FILLER | BN16: Grease | BO16: Water swellable Tape | BP16: Semi conducting Water Swellable tape | BQ16: SEMICON TAPE | BR16: GLASS FIBER TAPE | BS16: COPPER WIRE 0.8 MM | BT16: RUBBERIZED COTTON TAPE | BU16: Water Tight Compound | BV16: =Sheet1!E1 -> PROPOSE DRUM TYPE | BW16: =Sheet1!CV1 -> DRUM CODE | BX16: =Sheet1!CW1 -> DRUM SIZE (FxbXtx Ft) | BY16: =Sheet1!CX1 -> PARTY STANDARD LENGTH (MTR) | CD16: MFG% | CE16: MFG VALUE | CF16: PROF% | CG16: PROFIT VALUE | CH16: 1ST EX-WORKS | CI16: Intt % | CJ16: INTT VALUE | CK16: insp% | CL16: INSP VALUE
N17: =+IFERROR(VLOOKUP($N$16,Sheet1!J:L,2,0),0) -> 0 | O17: =715+100 -> 815 | P17: =+IFERROR(VLOOKUP($P$16,Sheet1!J:M,2,0),0) -> 0 | Q17: =+IFERROR(VLOOKUP($Q$16,Sheet1!J:M,2,0),0) -> 0 | R17: =+IFERROR(VLOOKUP($R$16,Sheet1!J:M,2,0),0) -> 0 | S17: =+IFERROR(VLOOKUP($S$16,Sheet1!N:Q,2,0),0) -> 0 | T17: =+IFERROR(VLOOKUP($T$16,Sheet1!N:O,2,0),0) -> 0 | U17: =+IFERROR(VLOOKUP($U$16,Sheet1!F:I,2,0),0) -> 0 | V17: =+IFERROR(VLOOKUP($V$16,Sheet1!F:I,2,0),0) -> 0 | W17: =+IFERROR(VLOOKUP($W$16,Sheet1!F:I,2,0),0) -> 0 | X17: =+IFERROR(VLOOKUP($X$16,Sheet1!F:I,2,0),0) -> 0 | Y17: =+IFERROR(VLOOKUP($Y$16,Sheet1!F:I,2,0),0) -> 0 | Z17: =+IFERROR(VLOOKUP($Z$16,Sheet1!F:I,2,0),0) -> 0 | AA17: =+IFERROR(VLOOKUP($AA$16,Sheet1!F:I,2,0),0) -> 0 | AB17: =+IFERROR(VLOOKUP($AB$16,Sheet1!F:I,2,0),0) -> 0 | AC17: =+IFERROR(VLOOKUP($AC$16,Sheet1!R:U,2,0),0) -> 0 | AD17: =+IFERROR(VLOOKUP($AD$16,Sheet1!R:U,2,0),0) -> 0 | AE17: =+IFERROR(VLOOKUP($AE$16,Sheet1!V:Y,2,0),0) -> 0 | AF17: =+IFERROR(VLOOKUP($AF$16,Sheet1!V:Y,2,0),0) -> 0 | AG17: =+IFERROR(VLOOKUP($AG$16,Sheet1!V:Y,2,0),0) -> 0 | AH17: =+IFERROR(VLOOKUP($AH$16,Sheet1!V:Y,2,0),0) -> 0 | AI17: 104 | AJ17: =+IFERROR(VLOOKUP($AJ$16,Sheet1!V:Y,2,0),0) -> 0 | AK17: 122 | AL17: =+IFERROR(VLOOKUP($AL$16,Sheet1!AD2:AG840,2,0),0) -> 0 | AM17: 95 | AN17: =+IFERROR(VLOOKUP($AN$16,Sheet1!AD2:AG840,2,0),0) -> 0 | AO17: =+IFERROR(VLOOKUP($AO$16,Sheet1!AD2:AG840,2,0),0) -> 0 | AP17: =+IFERROR(VLOOKUP($AP$16,Sheet1!AD2:AG840,2,0),0) -> 0 | AQ17: =+IFERROR(VLOOKUP($AQ$16,Sheet1!AD2:AG840,2,0),0) -> 0 | AR17: =+IFERROR(VLOOKUP($AR$16,Sheet1!AD2:AG840,2,0),0) -> 0 | AS17: =+IFERROR(VLOOKUP($AS$16,Sheet1!AH2:AK840,2,0),0) -> 0 | AT17: =+IFERROR(VLOOKUP($AT$16,Sheet1!AH2:AK840,2,0),0) -> 0 | AU17: =+IFERROR(VLOOKUP($AU$16,Sheet1!AH2:AK840,2,0),0) -> 0 | AV17: =+IFERROR(VLOOKUP($AV$16,Sheet1!AH2:AK840,2,0),0) -> 0 | AW17: =+IFERROR(VLOOKUP($AW$16,Sheet1!AH2:AK840,2,0),0) -> 0 | AX17: =+IFERROR(VLOOKUP($AX$16,Sheet1!AH2:AK840,2,0),0) -> 0 | AY17: =+IFERROR(VLOOKUP($AY$16,Sheet1!AH2:AK840,2,0),0) -> 0 | AZ17: =+IFERROR(VLOOKUP($AZ$16,Sheet1!AH2:AK840,2,0),0) -> 0 | BA17: 89 | BB17: =+IFERROR(VLOOKUP($BB$16,Sheet1!AH2:AK840,2,0),0) -> 0 | BC17: =+IFERROR(VLOOKUP($BC$16,Sheet1!AL2:AO840,2,0),0) -> 0 | BD17: =+IFERROR(VLOOKUP($BD$16,Sheet1!AL2:AO840,2,0),0) -> 0 | BE17: =+IFERROR(VLOOKUP($BE$16,Sheet1!AL2:AO840,2,0),0) -> 0 | BF17: 94 | BG17: =+IFERROR(VLOOKUP($BG$16,Sheet1!AL2:AO840,2,0),0) -> 0 | BH17: =+IFERROR(VLOOKUP($BH$16,Sheet1!AL2:AO840,2,0),0) -> 0 | BI17: =+IFERROR(VLOOKUP($BI$16,Sheet1!AL2:AO840,2,0),0) -> 0 | BJ17: =+IFERROR(VLOOKUP($BJ$16,Sheet1!AL2:AO840,2,0),0) -> 0 | BK17: =+IFERROR(VLOOKUP($BK$16,Sheet1!AL2:AO840,2,0),0) -> 0 | BL17: =+IFERROR(VLOOKUP($BL$16,Sheet1!AL2:AO840,2,0),0) -> 0 | BM17: =+IFERROR(VLOOKUP($BM$16,Sheet1!AP2:AS840,2,0),0) -> 0 | BN17: =+IFERROR(VLOOKUP($BN$16,Sheet1!AT2:AW840,2,0),0) -> 0 | BO17: =+IFERROR(VLOOKUP($BO$16,Sheet1!AX2:BA840,2,0),0) -> 0 | BP17: =+IFERROR(VLOOKUP($BP$16,Sheet1!BB2:BE840,2,0),0) -> 0 | BQ17: =+IFERROR(VLOOKUP($BQ$16,Sheet1!BF2:BI840,2,0),0) -> 0 | BR17: =+IFERROR(VLOOKUP($BR$16,Sheet1!BJ2:BM840,2,0),0) -> 0 | BS17: =+IFERROR(VLOOKUP($BS$16,Sheet1!BN2:BQ840,2,0),0) -> 0 | BT17: =+IFERROR(VLOOKUP($BT$16,Sheet1!BR2:BU840,2,0),0) -> 0 | BU17: =+IFERROR(VLOOKUP($BU$16,Sheet1!BV2:BY840,2,0),0) -> 0
A18: =Sheet1!A3 -> ENQ-11487-22-23 | B18: 45215 | C18: =Sheet1!C3 -> FA0200008 | D18: =Sheet1!D3 -> 2 CORE X 2.5 SQ. MM. CU/ARD - WIRE (PVC) | E18: =CH18+CJ18+CL18 -> 89109.512 | F18: =ROUNDUP(M24,0) -> 2425 | G18: =E18+F18 -> 91534.512 | H18: =Sheet1!CP3 -> 0.18 | I18: =G18*H18 -> 16476.212 | J18: =G18+I18 -> 108010.72 | K18: 33 | L18: =Sheet1!CT3 -> KMS | M18: =J18*K18 -> 3564353.9 | N18: =+IFERROR(VLOOKUP($N$16,Sheet1!J3:L3,3,0),0) -> 0 | O18: =+IFERROR(VLOOKUP($O$16,Sheet1!J3:L3,3,0),0) -> 44.4 | P18: =+IFERROR(VLOOKUP($P$16,Sheet1!J3:M3,3,0),0) -> 0 | Q18: =+IFERROR(VLOOKUP($Q$16,Sheet1!J3:M3,3,0),0) -> 0 | R18: =+IFERROR(VLOOKUP($R$16,Sheet1!J3:M3,3,0),0) -> 0 | S18: =+IFERROR(VLOOKUP($S$16,Sheet1!N3:Q3,3,0),0) -> 0 | T18: =+IFERROR(VLOOKUP($T$16,Sheet1!N3:Q3,3,0),0) -> 0 | U18: =+IFERROR(VLOOKUP($U$16,Sheet1!F3:I3,3,0),0) -> 0 | V18: =+IFERROR(VLOOKUP($V$16,Sheet1!F3:I3,3,0),0) -> 0 | W18: =+IFERROR(VLOOKUP($W$16,Sheet1!F3:I3,3,0),0) -> 0 | X18: =+IFERROR(VLOOKUP($X$16,Sheet1!F3:I3,3,0),0) -> 0 | Y18: =+IFERROR(VLOOKUP($Y$16,Sheet1!F3:I3,3,0),0) -> 0 | Z18: =+IFERROR(VLOOKUP($Z$16,Sheet1!F3:I3,3,0),0) -> 0 | AA18: =+IFERROR(VLOOKUP($AA$16,Sheet1!F3:I3,3,0),0) -> 0 | AB18: =+IFERROR(VLOOKUP($AB$16,Sheet1!F3:I3,3,0),0) -> 0 | AC18: =+IFERROR(VLOOKUP($AC$16,Sheet1!R3:U3,3,0),0) -> 0 | AD18: =+IFERROR(VLOOKUP($AD$16,Sheet1!R3:U3,2,0),0) -> 0 | AE18: =+IFERROR(VLOOKUP($AE$16,Sheet1!V3:Y3,3,0),0) -> 0 | AF18: =+IFERROR(VLOOKUP($AF$16,Sheet1!V3:Y3,3,0),0) -> 0 | AG18: =+IFERROR(VLOOKUP($AG$16,Sheet1!V3:Y3,3,0),0) -> 0 | AH18: =+IFERROR(VLOOKUP($AH$16,Sheet1!V3:Y3,3,0),0) -> 0 | AI18: =+IFERROR(VLOOKUP($AI$16,Sheet1!V3:Y3,3,0),0) -> 26 | AJ18: =+IFERROR(VLOOKUP($AJ$16,Sheet1!V3:Y3,3,0),0) -> 0 | AK18: =+IFERROR(VLOOKUP($AK$16,Sheet1!Z3:AB3,3,0),0) -> 3 | AL18: =+IFERROR(VLOOKUP($AL$16,Sheet1!AD3:AG3,3,0),0) -> 0 | AM18: =+IFERROR(VLOOKUP($AM$16,Sheet1!AD3:AG3,3,0),0) -> 39 | AN18: =+IFERROR(VLOOKUP($AN$16,Sheet1!AD3:AG3,3,0),0) -> 0 | AO18: =+IFERROR(VLOOKUP($AO$16,Sheet1!AD3:AG3,3,0),0) -> 0 | AP18: =+IFERROR(VLOOKUP($AP$16,Sheet1!AD3:AG3,3,0),0) -> 0 | AQ18: =+IFERROR(VLOOKUP($AQ$16,Sheet1!AD3:AG3,3,0),0) -> 0 | AR18: =+IFERROR(VLOOKUP($AR$16,Sheet1!AD3:AG3,3,0),0) -> 0 | AS18: =+IFERROR(VLOOKUP($AS$16,Sheet1!AH3:AK3,3,0),0) -> 0 | AT18: =+IFERROR(VLOOKUP($AT$16,Sheet1!AH3:AK3,3,0),0) -> 0 | AU18: =+IFERROR(VLOOKUP($AU$16,Sheet1!AH3:AK3,3,0),0) -> 0 | AV18: =+IFERROR(VLOOKUP($AV$16,Sheet1!AH3:AK3,3,0),0) -> 0 | AW18: =+IFERROR(VLOOKUP($AW$16,Sheet1!AH3:AK3,3,0),0) -> 0 | AX18: =+IFERROR(VLOOKUP($AX$16,Sheet1!AH3:AK3,3,0),0) -> 0 | AY18: =+IFERROR(VLOOKUP($AY$16,Sheet1!AH3:AK3,3,0),0) -> 0 | AZ18: =+IFERROR(VLOOKUP($AZ$16,Sheet1!AH3:AK3,3,0),0) -> 0 | BA18: =+IFERROR(VLOOKUP($BA$16,Sheet1!AH3:AK3,3,0),0) -> 251 | BB18: =+IFERROR(VLOOKUP($BB$16,Sheet1!AH3:AK3,3,0),0) -> 0 | BC18: =+IFERROR(VLOOKUP($BC$16,Sheet1!AL3:AO3,3,0),0) -> 0 | BD18: =+IFERROR(VLOOKUP($BD$16,Sheet1!AL3:AO3,3,0),0) -> 0 | BE18: =+IFERROR(VLOOKUP($BE$16,Sheet1!AL3:AO3,3,0),0) -> 0 | BF18: =+IFERROR(VLOOKUP($BF$16,Sheet1!AL3:AO3,3,0),0) -> 93 | BG18: =+IFERROR(VLOOKUP($BG$16,Sheet1!AL3:AO3,3,0),0) -> 0 | BH18: =+IFERROR(VLOOKUP($BH$16,Sheet1!AL3:AO3,3,0),0) -> 0 | BI18: =+IFERROR(VLOOKUP($BI$16,Sheet1!AL3:AO3,3,0),0) -> 0 | BJ18: =+IFERROR(VLOOKUP($BJ$16,Sheet1!AL3:AO3,3,0),0) -> 0 | BK18: =+IFERROR(VLOOKUP($BK$16,Sheet1!AL3:AO3,3,0),0) -> 0 | BL18: =+IFERROR(VLOOKUP($BL$16,Sheet1!AL3:AO3,3,0),0) -> 0 | BM18: =+IFERROR(VLOOKUP($BM$16,Sheet1!AP3:AS3,3,0),0) -> 0 | BN18: =+IFERROR(VLOOKUP($BN$16,Sheet1!AT3:AW3,3,0),0) -> 0 | BO18: =+IFERROR(VLOOKUP($BO$16,Sheet1!AX3:BA3,3,0),0) -> 0 | BP18: =+IFERROR(VLOOKUP($BP$16,Sheet1!BB3:BE3,3,0),0) -> 0 | BQ18: =+IFERROR(VLOOKUP($BQ$16,Sheet1!BF3:BI3,3,0),0) -> 0 | BR18: =+IFERROR(VLOOKUP($BR$16,Sheet1!BJ3:BM3,3,0),0) -> 0 | BS18: =+IFERROR(VLOOKUP($BS$16,Sheet1!BN3:BQ3,3,0),0) -> 0 | BT18: =+IFERROR(VLOOKUP($BT$16,Sheet1!BR3:BU3,3,0),0) -> 0 | BU18: =+IFERROR(VLOOKUP($BU$16,Sheet1!BV3:BY3,3,0),0) -> 0 | BV18: =Sheet1!E3 -> WOOD | BW18: =Sheet1!CV3 -> MD0100003 | BX18: =Sheet1!CW3 -> DRUM - 28 X 14 X 23 X 2 | BY18: =Sheet1!CX3 -> 500 | BZ18: =Sheet1!BZ3 -> 3850.93 | CA18: =SUMPRODUCT($N$17:$BU$17,N18:BU18)+BZ18 -> 77892.93 | CB18: =Sheet1!CB3 -> 0 | CC18: =CA18*CB18 -> 0 | CD18: 0.1 | CE18: =CA18*CD18 -> 7789.293 | CF18: 0 | CG18: =CA18*CF18 -> 0 | CH18: =CA18+CC18+CE18+CG18 -> 85682.223 | CI18: 0.02 | CJ18: =CH18*CI18 -> 1713.6445 | CK18: 0.02 | CL18: =CH18*CK18 -> 1713.6445
A19: =Sheet1!A5 -> ENQ-11487-22-23 | B19: 45215 | C19: =Sheet1!C5 -> FA0200011 | D19: =Sheet1!D5 -> 4 CORE X 2.5 SQ. MM. CU/ARD - WIRE (PVC) | E19: =CH19+CJ19+CL19 -> 138216.7 | F19: =ROUNDUP(M25,0) -> 2000 | G19: =E19+F19 -> 140216.7 | H19: =Sheet1!CP5 -> 0.18 | I19: =G19*H19 -> 25239.005 | J19: =G19+I19 -> 165455.7 | K19: =Sheet1!CS5 -> 40 | L19: =Sheet1!CT5 -> KMS | M19: =J19*K19 -> 6618228 | N19: =+IFERROR(VLOOKUP($N$16,Sheet1!J5:L5,3,0),0) -> 0 | O19: =+IFERROR(VLOOKUP($O$16,Sheet1!J5:L5,3,0),0) -> 88.8 | P19: =+IFERROR(VLOOKUP($P$16,Sheet1!J5:M5,3,0),0) -> 0 | Q19: =+IFERROR(VLOOKUP($Q$16,Sheet1!J5:M5,3,0),0) -> 0 | R19: =+IFERROR(VLOOKUP($R$16,Sheet1!J5:M5,3,0),0) -> 0 | S19: =+IFERROR(VLOOKUP($S$16,Sheet1!N5:Q5,3,0),0) -> 0 | T19: =+IFERROR(VLOOKUP($T$16,Sheet1!N5:Q5,3,0),0) -> 0 | U19: =+IFERROR(VLOOKUP($U$16,Sheet1!F5:I5,3,0),0) -> 0 | V19: =+IFERROR(VLOOKUP($V$16,Sheet1!F5:I5,3,0),0) -> 0 | W19: =+IFERROR(VLOOKUP($W$16,Sheet1!F5:I5,3,0),0) -> 0 | X19: =+IFERROR(VLOOKUP($X$16,Sheet1!F5:I5,3,0),0) -> 0 | Y19: =+IFERROR(VLOOKUP($Y$16,Sheet1!F5:I5,3,0),0) -> 0 | Z19: =+IFERROR(VLOOKUP($Z$16,Sheet1!F5:I5,3,0),0) -> 0 | AA19: =+IFERROR(VLOOKUP($AA$16,Sheet1!F5:I5,3,0),0) -> 0 | AB19: =+IFERROR(VLOOKUP($AB$16,Sheet1!F5:I5,3,0),0) -> 0 | AC19: =+IFERROR(VLOOKUP($AC$16,Sheet1!R5:U5,3,0),0) -> 0 | AD19: =+IFERROR(VLOOKUP($AD$16,Sheet1!R5:U5,2,0),0) -> 0 | AE19: =+IFERROR(VLOOKUP($AE$16,Sheet1!V5:Y5,3,0),0) -> 0 | AF19: =+IFERROR(VLOOKUP($AF$16,Sheet1!V5:Y5,3,0),0) -> 0 | AG19: =+IFERROR(VLOOKUP($AG$16,Sheet1!V5:Y5,3,0),0) -> 0 | AH19: =+IFERROR(VLOOKUP($AH$16,Sheet1!V5:Y5,3,0),0) -> 0 | AI19: =+IFERROR(VLOOKUP($AI$16,Sheet1!V5:Y5,3,0),0) -> 52 | AJ19: =+IFERROR(VLOOKUP($AJ$16,Sheet1!V5:Y5,3,0),0) -> 0 | AK19: =+IFERROR(VLOOKUP($AK$16,Sheet1!Z5:AB5,3,0),0) -> 3 | AL19: =+IFERROR(VLOOKUP($AL$16,Sheet1!AD5:AG5,3,0),0) -> 0 | AM19: =+IFERROR(VLOOKUP($AM$16,Sheet1!AD5:AG5,3,0),0) -> 27 | AN19: =+IFERROR(VLOOKUP($AN$16,Sheet1!AD5:AG5,3,0),0) -> 0 | AO19: =+IFERROR(VLOOKUP($AO$16,Sheet1!AD5:AG5,3,0),0) -> 0 | AP19: =+IFERROR(VLOOKUP($AP$16,Sheet1!AD5:AG5,3,0),0) -> 0 | AQ19: =+IFERROR(VLOOKUP($AQ$16,Sheet1!AD5:AG5,3,0),0) -> 0 | AR19: =+IFERROR(VLOOKUP($AR$16,Sheet1!AD5:AG5,3,0),0) -> 0 | AS19: =+IFERROR(VLOOKUP($AS$16,Sheet1!AH5:AK5,3,0),0) -> 0 | AT19: =+IFERROR(VLOOKUP($AT$16,Sheet1!AH5:AK5,3,0),0) -> 0 | AU19: =+IFERROR(VLOOKUP($AU$16,Sheet1!AH5:AK5,3,0),0) -> 0 | AV19: =+IFERROR(VLOOKUP($AV$16,Sheet1!AH5:AK5,3,0),0) -> 0 | AW19: =+IFERROR(VLOOKUP($AW$16,Sheet1!AH5:AK5,3,0),0) -> 0 | AX19: =+IFERROR(VLOOKUP($AX$16,Sheet1!AH5:AK5,3,0),0) -> 0 | AY19: =+IFERROR(VLOOKUP($AY$16,Sheet1!AH5:AK5,3,0),0) -> 0 | AZ19: =+IFERROR(VLOOKUP($AZ$16,Sheet1!AH5:AK5,3,0),0) -> 0 | BA19: =+IFERROR(VLOOKUP($BA$16,Sheet1!AH5:AK5,3,0),0) -> 289 | BB19: =+IFERROR(VLOOKUP($BB$16,Sheet1!AH5:AK5,3,0),0) -> 0 | BC19: =+IFERROR(VLOOKUP($BC$16,Sheet1!AL5:AO5,3,0),0) -> 0 | BD19: =+IFERROR(VLOOKUP($BD$16,Sheet1!AL5:AO5,3,0),0) -> 0 | BE19: =+IFERROR(VLOOKUP($BE$16,Sheet1!AL5:AO5,3,0),0) -> 0 | BF19: =+IFERROR(VLOOKUP($BF$16,Sheet1!AL5:AO5,3,0),0) -> 104 | BG19: =+IFERROR(VLOOKUP($BG$16,Sheet1!AL5:AO5,3,0),0) -> 0 | BH19: =+IFERROR(VLOOKUP($BH$16,Sheet1!AL5:AO5,3,0),0) -> 0 | BI19: =+IFERROR(VLOOKUP($BI$16,Sheet1!AL5:AO5,3,0),0) -> 0 | BJ19: =+IFERROR(VLOOKUP($BJ$16,Sheet1!AL5:AO5,3,0),0) -> 0 | BK19: =+IFERROR(VLOOKUP($BK$16,Sheet1!AL5:AO5,3,0),0) -> 0 | BL19: =+IFERROR(VLOOKUP($BL$16,Sheet1!AL5:AO5,3,0),0) -> 0 | BM19: =+IFERROR(VLOOKUP($BM$16,Sheet1!AP5:AS5,3,0),0) -> 0 | BN19: =+IFERROR(VLOOKUP($BN$16,Sheet1!AT5:AW5,3,0),0) -> 0 | BO19: =+IFERROR(VLOOKUP($BO$16,Sheet1!AX5:BA5,3,0),0) -> 0 | BP19: =+IFERROR(VLOOKUP($BP$16,Sheet1!BB5:BE5,3,0),0) -> 0 | BQ19: =+IFERROR(VLOOKUP($BQ$16,Sheet1!BF5:BI5,3,0),0) -> 0 | BR19: =+IFERROR(VLOOKUP($BR$16,Sheet1!BJ5:BM5,3,0),0) -> 0 | BS19: =+IFERROR(VLOOKUP($BS$16,Sheet1!BN5:BQ5,3,0),0) -> 0 | BT19: =+IFERROR(VLOOKUP($BT$16,Sheet1!BR5:BU5,3,0),0) -> 0 | BU19: =+IFERROR(VLOOKUP($BU$16,Sheet1!BV5:BY5,3,0),0) -> 0 | BV19: =Sheet1!E5 -> WOOD | BW19: =Sheet1!CV5 -> MD0100005 | BX19: =Sheet1!CW5 -> DRUM - 36 X 14 X 23 X 2 | BY19: =Sheet1!CX5 -> 500 | BZ19: =Sheet1!BZ5 -> 4610.79 | CA19: =SUMPRODUCT($N$17:$BU$17,N19:BU19)+BZ19 -> 120818.79 | CB19: =Sheet1!CB5 -> 0 | CC19: =CA19*CB19 -> 0 | CD19: 0.1 | CE19: =CA19*CD19 -> 12081.879 | CF19: 0 | CG19: =CA19*CF19 -> 0 | CH19: =CA19+CC19+CE19+CG19 -> 132900.67 | CI19: 0.02 | CJ19: =CH19*CI19 -> 2658.0134 | CK19: 0.02 | CL19: =CH19*CK19 -> 2658.0134
A20: =Sheet1!A4 -> ENQ-11487-22-23 | B20: 45215 | C20: =Sheet1!C4 -> FA0200002 | D20: =Sheet1!D4 -> 10 CORE X 2.5 SQ. MM. CU/ARD - WIRE (PVC) | E20: =CH20+CJ20+CL20 -> 301116.22 | F20: =ROUNDUP(M26,0) -> 3429 | G20: =E20+F20 -> 304545.22 | H20: =Sheet1!CP4 -> 0.18 | I20: =G20*H20 -> 54818.14 | J20: =G20+I20 -> 359363.36 | K20: 35 | L20: =Sheet1!CT4 -> KMS | M20: =J20*K20 -> 12577718 | N20: =+IFERROR(VLOOKUP($N$16,Sheet1!J4:L4,3,0),0) -> 0 | O20: =+IFERROR(VLOOKUP($O$16,Sheet1!J4:L4,3,0),0) -> 222 | P20: =+IFERROR(VLOOKUP($P$16,Sheet1!J4:M4,3,0),0) -> 0 | Q20: =+IFERROR(VLOOKUP($Q$16,Sheet1!J4:M4,3,0),0) -> 0 | R20: =+IFERROR(VLOOKUP($R$16,Sheet1!J4:M4,3,0),0) -> 0 | S20: =+IFERROR(VLOOKUP($S$16,Sheet1!N4:Q4,3,0),0) -> 0 | T20: =+IFERROR(VLOOKUP($T$16,Sheet1!N4:Q4,3,0),0) -> 0 | U20: =+IFERROR(VLOOKUP($U$16,Sheet1!F4:I4,3,0),0) -> 0 | V20: =+IFERROR(VLOOKUP($V$16,Sheet1!F4:I4,3,0),0) -> 0 | W20: =+IFERROR(VLOOKUP($W$16,Sheet1!F4:I4,3,0),0) -> 0 | X20: =+IFERROR(VLOOKUP($X$16,Sheet1!F4:I4,3,0),0) -> 0 | Y20: =+IFERROR(VLOOKUP($Y$16,Sheet1!F4:I4,3,0),0) -> 0 | Z20: =+IFERROR(VLOOKUP($Z$16,Sheet1!F4:I4,3,0),0) -> 0 | AA20: =+IFERROR(VLOOKUP($AA$16,Sheet1!F4:I4,3,0),0) -> 0 | AB20: =+IFERROR(VLOOKUP($AB$16,Sheet1!F4:I4,3,0),0) -> 0 | AC20: =+IFERROR(VLOOKUP($AC$16,Sheet1!R4:U4,3,0),0) -> 0 | AD20: =+IFERROR(VLOOKUP($AD$16,Sheet1!R4:U4,2,0),0) -> 0 | AE20: =+IFERROR(VLOOKUP($AE$16,Sheet1!V4:Y4,3,0),0) -> 0 | AF20: =+IFERROR(VLOOKUP($AF$16,Sheet1!V4:Y4,3,0),0) -> 0 | AG20: =+IFERROR(VLOOKUP($AG$16,Sheet1!V4:Y4,3,0),0) -> 0 | AH20: =+IFERROR(VLOOKUP($AH$16,Sheet1!V4:Y4,3,0),0) -> 0 | AI20: =+IFERROR(VLOOKUP($AI$16,Sheet1!V4:Y4,3,0),0) -> 130 | AJ20: =+IFERROR(VLOOKUP($AJ$16,Sheet1!V4:Y4,3,0),0) -> 0 | AK20: =+IFERROR(VLOOKUP($AK$16,Sheet1!Z4:AB4,3,0),0) -> 5 | AL20: =+IFERROR(VLOOKUP($AL$16,Sheet1!AD4:AG4,3,0),0) -> 0 | AM20: =+IFERROR(VLOOKUP($AM$16,Sheet1!AD4:AG4,3,0),0) -> 38 | AN20: =+IFERROR(VLOOKUP($AN$16,Sheet1!AD4:AG4,3,0),0) -> 0 | AO20: =+IFERROR(VLOOKUP($AO$16,Sheet1!AD4:AG4,3,0),0) -> 0 | AP20: =+IFERROR(VLOOKUP($AP$16,Sheet1!AD4:AG4,3,0),0) -> 0 | AQ20: =+IFERROR(VLOOKUP($AQ$16,Sheet1!AD4:AG4,3,0),0) -> 0 | AR20: =+IFERROR(VLOOKUP($AR$16,Sheet1!AD4:AG4,3,0),0) -> 0 | AS20: =+IFERROR(VLOOKUP($AS$16,Sheet1!AH4:AK4,3,0),0) -> 0 | AT20: =+IFERROR(VLOOKUP($AT$16,Sheet1!AH4:AK4,3,0),0) -> 0 | AU20: =+IFERROR(VLOOKUP($AU$16,Sheet1!AH4:AK4,3,0),0) -> 0 | AV20: =+IFERROR(VLOOKUP($AV$16,Sheet1!AH4:AK4,3,0),0) -> 0 | AW20: =+IFERROR(VLOOKUP($AW$16,Sheet1!AH4:AK4,3,0),0) -> 0 | AX20: =+IFERROR(VLOOKUP($AX$16,Sheet1!AH4:AK4,3,0),0) -> 0 | AY20: =+IFERROR(VLOOKUP($AY$16,Sheet1!AH4:AK4,3,0),0) -> 0 | AZ20: =+IFERROR(VLOOKUP($AZ$16,Sheet1!AH4:AK4,3,0),0) -> 0 | BA20: =+IFERROR(VLOOKUP($BA$16,Sheet1!AH4:AK4,3,0),0) -> 492 | BB20: =+IFERROR(VLOOKUP($BB$16,Sheet1!AH4:AK4,3,0),0) -> 0 | BC20: =+IFERROR(VLOOKUP($BC$16,Sheet1!AL4:AO4,3,0),0) -> 0 | BD20: =+IFERROR(VLOOKUP($BD$16,Sheet1!AL4:AO4,3,0),0) -> 0 | BE20: =+IFERROR(VLOOKUP($BE$16,Sheet1!AL4:AO4,3,0),0) -> 0 | BF20: =+IFERROR(VLOOKUP($BF$16,Sheet1!AL4:AO4,3,0),0) -> 166 | BG20: =+IFERROR(VLOOKUP($BG$16,Sheet1!AL4:AO4,3,0),0) -> 0 | BH20: =+IFERROR(VLOOKUP($BH$16,Sheet1!AL4:AO4,3,0),0) -> 0 | BI20: =+IFERROR(VLOOKUP($BI$16,Sheet1!AL4:AO4,3,0),0) -> 0 | BJ20: =+IFERROR(VLOOKUP($BJ$16,Sheet1!AL4:AO4,3,0),0) -> 0 | BK20: =+IFERROR(VLOOKUP($BK$16,Sheet1!AL4:AO4,3,0),0) -> 0 | BL20: =+IFERROR(VLOOKUP($BL$16,Sheet1!AL4:AO4,3,0),0) -> 0 | BM20: =+IFERROR(VLOOKUP($BM$16,Sheet1!AP4:AS4,3,0),0) -> 0 | BN20: =+IFERROR(VLOOKUP($BN$16,Sheet1!AT4:AW4,3,0),0) -> 0 | BO20: =+IFERROR(VLOOKUP($BO$16,Sheet1!AX4:BA4,3,0),0) -> 0 | BP20: =+IFERROR(VLOOKUP($BP$16,Sheet1!BB4:BE4,3,0),0) -> 0 | BQ20: =+IFERROR(VLOOKUP($BQ$16,Sheet1!BF4:BI4,3,0),0) -> 0 | BR20: =+IFERROR(VLOOKUP($BR$16,Sheet1!BJ4:BM4,3,0),0) -> 0 | BS20: =+IFERROR(VLOOKUP($BS$16,Sheet1!BN4:BQ4,3,0),0) -> 0 | BT20: =+IFERROR(VLOOKUP($BT$16,Sheet1!BR4:BU4,3,0),0) -> 0 | BU20: =+IFERROR(VLOOKUP($BU$16,Sheet1!BV4:BY4,3,0),0) -> 0 | BV20: =Sheet1!E4 -> WOOD | BW20: =Sheet1!CV4 -> MD0100066 | BX20: =Sheet1!CW4 -> DRUM - 40 X 15 X 23 X 2 | BY20: =Sheet1!CX4 -> 500 | BZ20: =Sheet1!BZ4 -> 5151.48 | CA20: =SUMPRODUCT($N$17:$BU$17,N20:BU20)+BZ20 -> 263213.48 | CB20: =Sheet1!CB4 -> 0 | CC20: =CA20*CB20 -> 0 | CD20: 0.1 | CE20: =CA20*CD20 -> 26321.348 | CF20: 0 | CG20: =CA20*CF20 -> 0 | CH20: =CA20+CC20+CE20+CG20 -> 289534.83 | CI20: 0.02 | CJ20: =CH20*CI20 -> 5790.6966 | CK20: 0.02 | CL20: =CH20*CK20 -> 5790.6966
A21: =Sheet1!A2 -> ENQ-11487-22-23 | B21: 45215 | C21: =Sheet1!C2 -> FA0200003 | D21: =Sheet1!D2 -> 12 CORE X 2.5 SQ. MM. CU/ARD - WIRE (PVC) | E21: =CH21+CJ21+CL21 -> 348022.51 | F21: =ROUNDUP(M27,0) -> 4000 | G21: =E21+F21 -> 352022.51 | H21: =Sheet1!CP2 -> 0.18 | I21: =G21*H21 -> 63364.052 | J21: =G21+I21 -> 415386.56 | K21: 30 | L21: =Sheet1!CT2 -> KMS | M21: =J21*K21 -> 12461597 | N21: =+IFERROR(VLOOKUP($N$16,Sheet1!J2:L2,3,0),0) -> 0 | O21: =+IFERROR(VLOOKUP($O$16,Sheet1!J2:L2,3,0),0) -> 266.4 | P21: =+IFERROR(VLOOKUP($P$16,Sheet1!J2:M2,3,0),0) -> 0 | Q21: =+IFERROR(VLOOKUP($Q$16,Sheet1!J2:M2,3,0),0) -> 0 | R21: =+IFERROR(VLOOKUP($R$16,Sheet1!J2:M2,3,0),0) -> 0 | S21: =+IFERROR(VLOOKUP($S$16,Sheet1!N2:Q2,3,0),0) -> 0 | T21: =+IFERROR(VLOOKUP($T$16,Sheet1!N2:Q2,3,0),0) -> 0 | U21: =+IFERROR(VLOOKUP($U$16,Sheet1!F2:I2,3,0),0) -> 0 | V21: =+IFERROR(VLOOKUP($V$16,Sheet1!F2:I2,3,0),0) -> 0 | W21: =+IFERROR(VLOOKUP($W$16,Sheet1!F2:I2,3,0),0) -> 0 | X21: =+IFERROR(VLOOKUP($X$16,Sheet1!F2:I2,3,0),0) -> 0 | Y21: =+IFERROR(VLOOKUP($Y$16,Sheet1!F2:I2,3,0),0) -> 0 | Z21: =+IFERROR(VLOOKUP($Z$16,Sheet1!F2:I2,3,0),0) -> 0 | AA21: =+IFERROR(VLOOKUP($AA$16,Sheet1!F2:I2,3,0),0) -> 0 | AB21: =+IFERROR(VLOOKUP($AB$16,Sheet1!F2:I2,3,0),0) -> 0 | AC21: =+IFERROR(VLOOKUP($AC$16,Sheet1!R2:U2,3,0),0) -> 0 | AD21: =+IFERROR(VLOOKUP($AD$16,Sheet1!R2:U2,2,0),0) -> 0 | AE21: =+IFERROR(VLOOKUP($AE$16,Sheet1!V2:Y2,3,0),0) -> 0 | AF21: =+IFERROR(VLOOKUP($AF$16,Sheet1!V2:Y2,3,0),0) -> 0 | AG21: =+IFERROR(VLOOKUP($AG$16,Sheet1!V2:Y2,3,0),0) -> 0 | AH21: =+IFERROR(VLOOKUP($AH$16,Sheet1!V2:Y2,3,0),0) -> 0 | AI21: =+IFERROR(VLOOKUP($AI$16,Sheet1!V2:Y2,3,0),0) -> 156 | AJ21: =+IFERROR(VLOOKUP($AJ$16,Sheet1!V2:Y2,3,0),0) -> 0 | AK21: =+IFERROR(VLOOKUP($AK$16,Sheet1!Z2:AB2,3,0),0) -> 6 | AL21: =+IFERROR(VLOOKUP($AL$16,Sheet1!AD2:AG2,3,0),0) -> 0 | AM21: =+IFERROR(VLOOKUP($AM$16,Sheet1!AD2:AG2,3,0),0) -> 40 | AN21: =+IFERROR(VLOOKUP($AN$16,Sheet1!AD2:AG2,3,0),0) -> 0 | AO21: =+IFERROR(VLOOKUP($AO$16,Sheet1!AD2:AG2,3,0),0) -> 0 | AP21: =+IFERROR(VLOOKUP($AP$16,Sheet1!AD2:AG2,3,0),0) -> 0 | AQ21: =+IFERROR(VLOOKUP($AQ$16,Sheet1!AD2:AG2,3,0),0) -> 0 | AR21: =+IFERROR(VLOOKUP($AR$16,Sheet1!AD2:AG2,3,0),0) -> 0 | AS21: =+IFERROR(VLOOKUP($AS$16,Sheet1!AH2:AK2,3,0),0) -> 0 | AT21: =+IFERROR(VLOOKUP($AT$16,Sheet1!AH2:AK2,3,0),0) -> 0 | AU21: =+IFERROR(VLOOKUP($AU$16,Sheet1!AH2:AK2,3,0),0) -> 0 | AV21: =+IFERROR(VLOOKUP($AV$16,Sheet1!AH2:AK2,3,0),0) -> 0 | AW21: =+IFERROR(VLOOKUP($AW$16,Sheet1!AH2:AK2,3,0),0) -> 0 | AX21: =+IFERROR(VLOOKUP($AX$16,Sheet1!AH2:AK2,3,0),0) -> 0 | AY21: =+IFERROR(VLOOKUP($AY$16,Sheet1!AH2:AK2,3,0),0) -> 0 | AZ21: =+IFERROR(VLOOKUP($AZ$16,Sheet1!AH2:AK2,3,0),0) -> 0 | BA21: =+IFERROR(VLOOKUP($BA$16,Sheet1!AH2:AK2,3,0),0) -> 508 | BB21: =+IFERROR(VLOOKUP($BB$16,Sheet1!AH2:AK2,3,0),0) -> 0 | BC21: =+IFERROR(VLOOKUP($BC$16,Sheet1!AL2:AO2,3,0),0) -> 0 | BD21: =+IFERROR(VLOOKUP($BD$16,Sheet1!AL2:AO2,3,0),0) -> 0 | BE21: =+IFERROR(VLOOKUP($BE$16,Sheet1!AL2:AO2,3,0),0) -> 0 | BF21: =+IFERROR(VLOOKUP($BF$16,Sheet1!AL2:AO2,3,0),0) -> 170 | BG21: =+IFERROR(VLOOKUP($BG$16,Sheet1!AL2:AO2,3,0),0) -> 0 | BH21: =+IFERROR(VLOOKUP($BH$16,Sheet1!AL2:AO2,3,0),0) -> 0 | BI21: =+IFERROR(VLOOKUP($BI$16,Sheet1!AL2:AO2,3,0),0) -> 0 | BJ21: =+IFERROR(VLOOKUP($BJ$16,Sheet1!AL2:AO2,3,0),0) -> 0 | BK21: =+IFERROR(VLOOKUP($BK$16,Sheet1!AL2:AO2,3,0),0) -> 0 | BL21: =+IFERROR(VLOOKUP($BL$16,Sheet1!AL2:AO2,3,0),0) -> 0 | BM21: =+IFERROR(VLOOKUP($BM$16,Sheet1!AP2:AS2,3,0),0) -> 0 | BN21: =+IFERROR(VLOOKUP($BN$16,Sheet1!AT2:AW2,3,0),0) -> 0 | BO21: =+IFERROR(VLOOKUP($BO$16,Sheet1!AX2:BA2,3,0),0) -> 0 | BP21: =+IFERROR(VLOOKUP($BP$16,Sheet1!BB2:BE2,3,0),0) -> 0 | BQ21: =+IFERROR(VLOOKUP($BQ$16,Sheet1!BF2:BI2,3,0),0) -> 0 | BR21: =+IFERROR(VLOOKUP($BR$16,Sheet1!BJ2:BM2,3,0),0) -> 0 | BS21: =+IFERROR(VLOOKUP($BS$16,Sheet1!BN2:BQ2,3,0),0) -> 0 | BT21: =+IFERROR(VLOOKUP($BT$16,Sheet1!BR2:BU2,3,0),0) -> 0 | BU21: =+IFERROR(VLOOKUP($BU$16,Sheet1!BV2:BY2,3,0),0) -> 0 | BV21: =Sheet1!E2 -> WOOD | BW21: =Sheet1!CV2 -> MD0100066 | BX21: =Sheet1!CW2 -> DRUM - 40 X 15 X 23 X 2 | BY21: =Sheet1!CX2 -> 500 | BZ21: =Sheet1!BZ2 -> 5151.48 | CA21: =SUMPRODUCT($N$17:$BU$17,N21:BU21)+BZ21 -> 304215.48 | CB21: =Sheet1!CB2 -> 0 | CC21: =CA21*CB21 -> 0 | CD21: 0.1 | CE21: =CA21*CD21 -> 30421.548 | CF21: 0 | CG21: =CA21*CF21 -> 0 | CH21: =CA21+CC21+CE21+CG21 -> 334637.03 | CI21: 0.02 | CJ21: =CH21*CI21 -> 6692.7406 | CK21: 0.02 | CL21: =CH21*CK21 -> 6692.7406
E23: Order Quantity | F23: Stnd Length | G23: Truck type | H23: Fare of one truck | I23: No of Drum in one truck | J23: Total length in one Truck | K23: No of Truck | L23: Total Freight | M23: Freight per KM
D24: =D18 -> 2 CORE X 2.5 SQ. MM. CU/ARD - WIRE (PVC) | E24: =K18 -> 33 | F24: 0.5 | G24: 16 MT | H24: 40000 | I24: 56 | J24: =F24*I24 -> 28 | K24: =ROUNDUP((E24/J24),0) -> 2 | L24: =M24*E24 -> 80000 | M24: =(H24*K24)/E24 -> 2424.2424
D25: =D19 -> 4 CORE X 2.5 SQ. MM. CU/ARD - WIRE (PVC) | E25: =K19 -> 40 | F25: 0.5 | G25: 16 MT | H25: 40000 | I25: 46 | J25: =F25*I25 -> 23 | K25: =ROUNDUP((E25/J25),0) -> 2 | L25: =M25*E25 -> 80000 | M25: =(H25*K25)/E25 -> 2000
D26: =D20 -> 10 CORE X 2.5 SQ. MM. CU/ARD - WIRE (PVC) | E26: =K20 -> 35 | F26: 0.5 | G26: 16 MT | H26: 40000 | I26: 27 | J26: =F26*I26 -> 13.5 | K26: =ROUNDUP((E26/J26),0) -> 3 | L26: =M26*E26 -> 120000 | M26: =(H26*K26)/E26 -> 3428.5714
D27: =D21 -> 12 CORE X 2.5 SQ. MM. CU/ARD - WIRE (PVC) | E27: =K21 -> 30 | F27: 0.5 | G27: 16 MT | H27: 40000 | I27: 25 | J27: =F27*I27 -> 12.5 | K27: =ROUNDUP((E27/J27),0) -> 3 | L27: =M27*E27 -> 120000 | M27: =(H27*K27)/E27 -> 4000

Sheet CONTROL CABLE
A1: Base Date | B1: 45215
A2: PV FORMULA
A5: Item | B5: Calculation part | D5: Applicable Date | H5: BASE DATE | O5: Ex-Work Po | P5: PVC of Cu | Q5: PVC OF PVC | R5: PVC OF FE | S5: PV/PKM | T5: Billing Price/PKM
D6: Date | E6: Cu | F6: PVCc | G6: Fe | H6: Date | I6: Cuo | J6: PVCco | K6: Feo | U6: ='AUTO CALCULATION SHEET (2)'!O16 -> Tinned Copper | V6: ='AUTO CALCULATION SHEET (2)'!AI16 -> Type C PVC (HR) | W6: ='AUTO CALCULATION SHEET (2)'!AK16 -> POLY TAPE | X6: ='AUTO CALCULATION SHEET (2)'!AM16 -> FR PVC Type ST-2 | Y6: ='AUTO CALCULATION SHEET (2)'!BA16 -> Galvanised Steel Round Wire | Z6: ='AUTO CALCULATION SHEET (2)'!BF16 -> FRLSH PVC Type ST-2 | AA6: RMC | AB6: Drum | AC6: RMC+Drum | AD6: VA | AE6: Groos VA% | AF6: Mfg % | AG6: Int % | AH6: Ins% | AI6: Net VA
L7: CuF | M7: CCFCu | N7: FeF | U7: =723+100 -> 823 | V7: 102 | W7: 123 | X7: 93 | Y7: 89 | Z7: 92
U8: Kg/Km | V8: Kg/Km | W8: Kg/Km | X8: Kg/Km | Y8: Kg/Km | Z8: Kg/Km
A9: ='AUTO CALCULATION SHEET (2)'!D18 -> 2 CORE X 2.5 SQ. MM. CU/ARD - WIRE (PVC) | C9: Provisional | D9: 45239 | E9: 731287.44 | F9: 154575 | G9: 79250 | H9: =$B$1 -> 45215 | I9: 721052 | J9: 154575 | K9: 79250 | L9: 0.047 | M9: 0.139 | N9: 0.277 | O9: ='AUTO CALCULATION SHEET (2)'!E18 -> 89109.512 | P9: =L9*(E9-I9) -> 481.06568 | Q9: =(M9*(F9-J9)) -> 0 | R9: =(N9*(G9-K9)) -> 0 | S9: =+P9+Q9+R9 -> 481.06568 | T9: =O9+S9 -> 89590.578 | U9: ='AUTO CALCULATION SHEET (2)'!O18 -> 44.4 | V9: ='AUTO CALCULATION SHEET (2)'!AI18 -> 26 | W9: ='AUTO CALCULATION SHEET (2)'!AK18 -> 3 | X9: ='AUTO CALCULATION SHEET (2)'!AM18 -> 39 | Y9: ='AUTO CALCULATION SHEET (2)'!BA18 -> 251 | Z9: ='AUTO CALCULATION SHEET (2)'!BF18 -> 93 | AA9: =SUMPRODUCT(U9:Z9,$U$7:Z$7) -> 74084.2 | AB9: ='AUTO CALCULATION SHEET (2)'!BZ18 -> 3850.93 | AC9: =AA9+AB9 -> 77935.13 | AD9: =T9-AC9 -> 11655.448 | AE9: =ROUND((AD9/AC9)*100,2) -> 14.96 | AG9: 2 | AH9: 2 | AI9: =AE9-AF9-AG9-AH9 -> 10.96
A10: ='AUTO CALCULATION SHEET (2)'!D19 -> 4 CORE X 2.5 SQ. MM. CU/ARD - WIRE (PVC) | C10: Provisional | D10: 45239 | E10: 731287.44 | F10: 154575 | G10: 79250 | H10: =$B$1 -> 45215 | I10: 721052 | J10: 154575 | K10: 79250 | L10: 0.094 | M10: 0.179 | N10: 0.314 | O10: ='AUTO CALCULATION SHEET (2)'!E19 -> 138216.7 | P10: =L10*(E10-I10) -> 962.13136 | Q10: =(M10*(F10-J10)) -> 0 | R10: =(N10*(G10-K10)) -> 0 | S10: =+P10+Q10+R10 -> 962.13136 | T10: =O10+S10 -> 139178.83 | U10: ='AUTO CALCULATION SHEET (2)'!O19 -> 88.8 | V10: ='AUTO CALCULATION SHEET (2)'!AI19 -> 52 | W10: ='AUTO CALCULATION SHEET (2)'!AK19 -> 3 | X10: ='AUTO CALCULATION SHEET (2)'!AM19 -> 27 | Y10: ='AUTO CALCULATION SHEET (2)'!BA19 -> 289 | Z10: ='AUTO CALCULATION SHEET (2)'!BF19 -> 104 | AA10: =SUMPRODUCT(U10:Z10,$U$7:Z$7) -> 116555.4 | AB10: ='AUTO CALCULATION SHEET (2)'!BZ19 -> 4610.79 | AC10: =AA10+AB10 -> 121166.19 | AD10: =T10-AC10 -> 18012.637 | AE10: =ROUND((AD10/AC10)*100,2) -> 14.87 | AG10: 2 | AH10: 2 | AI10: =AE10-AF10-AG10-AH10 -> 10.87
A11: ='AUTO CALCULATION SHEET (2)'!D20 -> 10 CORE X 2.5 SQ. MM. CU/ARD - WIRE (PVC) | C11: Provisional | D11: 45239 | E11: 731287.44 | F11: 154575 | G11: 78750 | H11: =$B$1 -> 45215 | I11: 721052 | J11: 154575 | K11: 78750 | L11: 0.235 | M11: 0.337 | N11: 0.535 | O11: ='AUTO CALCULATION SHEET (2)'!E20 -> 301116.22 | P11: =L11*(E11-I11) -> 2405.3284 | Q11: =(M11*(F11-J11)) -> 0 | R11: =(N11*(G11-K11)) -> 0 | S11: =+P11+Q11+R11 -> 2405.3284 | T11: =O11+S11 -> 303521.55 | U11: ='AUTO CALCULATION SHEET (2)'!O20 -> 222 | V11: ='AUTO CALCULATION SHEET (2)'!AI20 -> 130 | W11: ='AUTO CALCULATION SHEET (2)'!AK20 -> 5 | X11: ='AUTO CALCULATION SHEET (2)'!AM20 -> 38 | Y11: ='AUTO CALCULATION SHEET (2)'!BA20 -> 492 | Z11: ='AUTO CALCULATION SHEET (2)'!BF20 -> 166 | AA11: =SUMPRODUCT(U11:Z11,$U$7:Z$7) -> 259175 | AB11: ='AUTO CALCULATION SHEET (2)'!BZ20 -> 5151.48 | AC11: =AA11+AB11 -> 264326.48 | AD11: =T11-AC11 -> 39195.07 | AE11: =ROUND((AD11/AC11)*100,2) -> 14.83 | AG11: 2 | AH11: 2 | AI11: =AE11-AF11-AG11-AH11 -> 10.83
A12: ='AUTO CALCULATION SHEET (2)'!D21 -> 12 CORE X 2.5 SQ. MM. CU/ARD - WIRE (PVC) | C12: Provisional | D12: 45239 | E12: 731287.44 | F12: 154575 | G12: 78750 | H12: =$B$1 -> 45215 | I12: 721052 | J12: 154575 | K12: 78750 | L12: 0.282 | M12: 0.371 | N12: 0.572 | O12: ='AUTO CALCULATION SHEET (2)'!E21 -> 348022.51 | P12: =L12*(E12-I12) -> 2886.3941 | Q12: =(M12*(F12-J12)) -> 0 | R12: =(N12*(G12-K12)) -> 0 | S12: =+P12+Q12+R12 -> 2886.3941 | T12: =O12+S12 -> 350908.9 | U12: ='AUTO CALCULATION SHEET (2)'!O21 -> 266.4 | V12: ='AUTO CALCULATION SHEET (2)'!AI21 -> 156 | W12: ='AUTO CALCULATION SHEET (2)'!AK21 -> 6 | X12: ='AUTO CALCULATION SHEET (2)'!AM21 -> 40 | Y12: ='AUTO CALCULATION SHEET (2)'!BA21 -> 508 | Z12: ='AUTO CALCULATION SHEET (2)'!BF21 -> 170 | AA12: =SUMPRODUCT(U12:Z12,$U$7:Z$7) -> 300469.2 | AB12: ='AUTO CALCULATION SHEET (2)'!BZ21 -> 5151.48 | AC12: =AA12+AB12 -> 305620.68 | AD12: =T12-AC12 -> 45288.223 | AE12: =ROUND((AD12/AC12)*100,2) -> 14.82 | AG12: 2 | AH12: 2 | AI12: =AE12-AF12-AG12-AH12 -> 10.82
