Workbook

Sheet Sheet1
A1: DOCKET NO. | B1: Base Date | C1: ITEM CODE | D1: PROPOSE ERP ITEM NAME | E1: Propose Drum Type | F1: Insulation Screening(Metallic) | G1: RM Rate(Insulation Screening(Metallic)) | H1: Weight (Insulation Screening (Metallic)) | I1: Cost Insulation Screening(Metallic) | J1: Conductor | K1: RM Rate(Conductor) | L1: Weight(Conductor) | M1: Cost(Conductor) | N1: AL ALLOY | O1: RM Rate(AL Alloy) | P1: Weight(Al Alloy) | Q1: Cost(AL Alloy) | R1: Insulation Screening(Non-Metallic) | S1: RM Rate(Insulation Screening(Non-Metallic)) | T1: Weight(Insulation Screening(Non-Metallic) | U1: Cost(Insulation Screening(Non-Metallic) | V1: Insulation | W1: RM Rate(Insulation) | X1: Weight(Insulation) | Y1: Cost(Insulation) | Z1: Poly Tape | AA1: RM Rate(Poly Tape) | AB1: Weight(Poly Tape) | AC1: Cost(Poly Tape) | AD1: Inner Sheath | AE1: RM Rate(Inner Sheath) | AF1: Weight(Inner Sheath) | AG1: Cost(Inner Sheath) | AH1: Armouring | AI1: RM Rate(Armouring) | AJ1: Weight(Armouring) | AK1: Cost(Armouring) | AL1: Outer Sheath | AM1: RM Rate(Outer Sheath) | AN1: Weight(Outer Sheath) | AO1: Cost(Outer Sheath) | AP1: Filler | AQ1: RM Rate(Filler) | AR1: Weight(Filler) | AS1: Cost(Filler) | AT1: Grease | AU1: RM Rate(Grease) | AV1: Weight(Grease) | AW1: Cost(Grease) | AX1: Water Swellable Tape | AY1: RM Rate(Water Swellable Tape) | AZ1: Weight(Water Swellable Tape) | BA1: Cost(Water Swellable Tape) | BB1: Semi Conducting Water Swellable Tape | BC1: RM Rate(Semi Conducting Water Swellable Tape) | BD1: Weight(Semi Conducting Water Swellable Tape) | BE1: Cost(Semi Conducting Water Swellable Tape) | BF1: Semicon Tape | BG1: RM Rate(Semicon Tape) | BH1: Weight(Semicon Tape) | BI1: Cost(Semicon Tape) | BJ1: Glass Fiber Tape | BK1: RM Rate(Glass Fiber Tape) | BL1: Weight(Glass Fiber Tape) | BM1: Cost(Glass Fiber Tape) | BN1: Copper Wire 0.8MM | BO1: RM Rate(Copper Wire 0.8MM) | BP1: Weight(Copper Wire 0.8MM) | BQ1: Cost(Copper Wire 0.8MM) | BR1: Rubberized Cotton Tape | BS1: RM Rate(Rubberized Cotton Tape) | BT1: Weight(Rubberized Cotton Tape) | BU1: Cost(Rubberized Cotton Tape) | BV1: Water Tight Compound | BW1: RM Rate(Water Tight Compound) | BX1: Weight(Water Tight Compound) | BY1: Cost(Water Tight Compound) | BZ1: Drum Cost Per KM | CA1: Total RM Cost | CB1: FIRM % | CC1: Firm Value | CD1: MFG% | CE1: MFG Value | CF1: PROF% | CG1: Profit Value | CH1: 1st EX-Works | CI1: Intt % | CJ1: Intt Value | CK1: insp% | CL1: Insp Value | CM1: TTR CHARGES% | CN1: TTR Value | CO1: EX-Works Per KM | CP1: Freight Per KM | CQ1: Price Including Freight Per KM | CR1: GST % | CS1: GST Value | CT1: Price Including GST & Freight Per KM | CU1: QTY | CV1: Unit | CW1: Total Price Of Full QTY(Including Freight&GST) | CX1: DRUM CODE | CY1: DRUM SIZE (FxbXtx Ft) | CZ1: Party Standard Length(MTR)
A2: ENQ-16528-25-26 | C2: FC3700003 | D2: ACSR : PANTHER CONDUCTOR - 200 SQ. MM. (30/7/3.00) | E2: WOOD | H2: 0 | J2: Alumimium | L2: 588 | P2: 0 | T2: 0 | X2: 0 | AB2: 0 | AF2: 0 | AH2: ACSR CORE WIRE | AJ2: 388 | AN2: 0 | AR2: 0 | AT2: Grease | AV2: 0 | AZ2: 0 | BD2: 0 | BH2: 0 | BL2: 0 | BP2: 0 | BT2: 0 | BX2: 0 | BZ2: 3956 | CA2: 3956 | CH2: 3956 | CO2: 3956 | CQ2: 3956 | CR2: 0.18 | CS2: 712.08 | CT2: 4668.08 | CU2: 10772 | CV2: KMS | CW2: 50284558 | CX2: MD0100061 | CY2: DRUM - 56 X 24 X 32 X 3 | CZ2: 2000
A3: ENQ-16528-25-26 | C3: FC6100001 | D3: ACSR : ZEBRA CONDUCTOR - 420 SQ. MM. (54/7/3.18) | E3: WOOD | H3: 0 | J3: Alumimium | L3: 1186 | P3: 0 | T3: 0 | X3: 0 | AB3: 0 | AF3: 0 | AH3: ACSR CORE WIRE | AJ3: 436 | AN3: 0 | AR3: 0 | AV3: 0 | AZ3: 0 | BD3: 0 | BH3: 0 | BL3: 0 | BP3: 0 | BT3: 0 | BX3: 0 | BZ3: 7182 | CA3: 7182 | CH3: 7182 | CO3: 7182 | CQ3: 7182 | CR3: 0.18 | CS3: 1292.76 | CT3: 8474.76 | CU3: 1566 | CV3: KMS | CW3: 13271474 | CX3: MD0100062 | CY3: DRUM - 74 X 24 X 32 X 3 | CZ3: 2000
A4: ENQ-16528-25-26 | C4: FC6100002 | D4: ACSR : MOOSE CONDUCTOR - 520 SQ. MM. (54/7/3.53) | E4: WOOD | H4: 0 | J4: Alumimium | L4: 1467 | P4: 0 | T4: 0 | X4: 0 | AB4: 0 | AF4: 0 | AH4: ACSR CORE WIRE | AJ4: 537 | AN4: 0 | AR4: 0 | AT4: Grease | AV4: 0 | AZ4: 0 | BD4: 0 | BH4: 0 | BL4: 0 | BP4: 0 | BT4: 0 | BX4: 0 | CR4: 0.18 | CU4: 2200 | CV4: KMS | CZ4: 2000
A5: ENQ-16528-25-26 | C5: FC6200002 | D5: ACSR : DOG CONDUCTOR - 100 SQ. MM. (6/4.72/7/1.57) | E5: WOOD | H5: 0 | J5: Alumimium | L5: 288 | P5: 0 | T5: 0 | X5: 0 | AB5: 0 | AF5: 0 | AH5: ACSR DOG STEEL WIRE | AJ5: 106 | AN5: 0 | AR5: 0 | AT5: Grease | AV5: 0 | AZ5: 0 | BD5: 0 | BH5: 0 | BL5: 0 | BP5: 0 | BT5: 0 | BX5: 0 | BZ5: 2259 | CA5: 2259 | CH5: 2259 | CO5: 2259 | CQ5: 2259 | CR5: 0.18 | CS5: 406.62 | CT5: 2665.62 | CU5: 916 | CV5: KMS | CW5: 2441708 | CX5: MD0100013 | CY5: DRUM - 48 X 14 X 36 X 2.25 | CZ5: 2000

Sheet AUTO CALCULATION SHEET (2)
A2: GUJARAT ENERGY TRANSMISSION CORPORATION LIMITED
A4: TENDER SPECIFICATION NO () | B4: CE (P&C)/TN-07/25-26 (Tender ID- 200421) ACE(P&C)/SE(P&C)/EE(Proc)/I/E-3057/ACSR Conductor/2025-26
A5: TENDER DESCRIPTION () | B5: Purchase of ACSR Dog, Panther, Zebra & Moose Conductors on returnable steel drums as per specifications for F.Y. 2025-26 on variable price basis against tender no. ACE(P&C)/SE(P&C)/EE(Proc)/I/E-3057/ACSR Conductor/2025-26
A6: Last Date & Time of Submission () | B6: 31-07-2025 16:00
A7: REVERSE AUCTION | B7: Inter-se Reverse Bidding = Applicable Item wise Nos. NEW/REGULAR Bidders Particulars 2 No elimination 3 to 5 H-1 Bidder shall be eliminated 6 or more bidders H-1 & H-2 Bidders shall be eliminated
A8: Price () | B8: Base date for price variation will be 1st working day of the month, one month prior to month of opening of tender. The average of prices as on first day of the previous calendar month of the due date of the tender in Rupees of E.C. Grade Aluminum wire Rods per MT exclusive of E.D. and ST as notified by CACMAI without ceiling
A9: Validity () | B9: The offer will have to be kept valid for a period of 120 days from the date of opening of bids. In case of finalization of the tender is likely to be delayed, the tenderer’s will be asked to extend the same without change in the prices or any terms and conditions of the offer.
A10: Delivery Period () | B10: Commencement Period = One Month ACSR Dog Conductor on returnable steel drums = One (01) Quarter ACSR Panther Conductor on returnable steel drums = Three (03) Quarters (Equal quarterly basis) ACSR Zebra Conductor on returnable steel drums = Two (02) Quarters (Equal quarterly basis) ACSR Moose Conductor on returnable steel drums = Two (02) Quarters (Equal quarterly basis) However early delivery will be acceptable.
A11: Payment Terms () | B11: Payment shall be made by GETCO, either directly to you or to suppliers Banker for the materials supplied as per GETCO standard payment terms and conditions i.e. 80% of F.O.R. Destination Price and 100% GST and Cess as applicable, from the date of receipt of material [as mentioned in Truck Receipt Certificate (TRC)]within 30 (Thirty) days on verifying required documents as per A/T conditions and balance 20% of F.O.R. Destination Price within 45 days (Forty Five) on receipt of Store Receipt (S.R.) Note from the consignee.
A12: Standard length () | B12: The standard length of the conductor shall be 2000 meter. ACSR Moose, Zebra, Panther, And Dog. = 2000/2500 meter Only one length of conductor shall be wound on each drum.
A13: Packing () | B13: ACSR Dog Conductor on returnable steel drums ACSR Panther Conductor on returnable steel drums ACSR Zebra Conductor on returnable steel drums ACSR Moose Conductor on returnable steel drums
A14: Technical Specification
N16: Conductor | V16: AL ALLOY | X16: Insulation Screening (Metallic) | AF16: Insulation Screening (Non-Metallic) | AH16: Insulation | AQ16: POLY TAPE | AR16: Inner Sheath | BA16: Armouring | BL16: Outer Sheath | BX16: FILLER | BY16: GREASE | BZ16: Water swellable Tape | CA16: Semi conducting Water Swellable tape | CB16: SEMICON TAPE | CC16: GLASS FIBER TAPE | CD16: COPPER WIRE 0.8 MM | CE16: RUBBERIZED COTTON TAPE | CF16: Water Tight Compound | CG16: DRUM TYPE | CK16: DRUM COST PER KM | CL16: TOTAL RM COST | CM16: EXTRA CONSUMPTION | CN16: EXTRA CONSUMPTION VALUE | CZ16: $A$1
A17: DOCKET NO. | B17: BASE DATE | C17: ITEM CODE | D17: PROPOSE ERP ITEM NAME | E17: EX-WORKS (PER KM) | F17: FREIGHT PER KM | G17: PRICE INCLUDING FREIGHT (PER KM) | H17: GST % | I17: GST VALUE | J17: PRICE INCLUDING GST & FREIGHT (PER KM) | K17: QTY | L17: Unit | M17: TOTAL PRICE OF FULL QTY (INCLUDING FRIGHT & GST) | N17: Alumimium | O17: Alumimium ALLOY | P17: Copper | Q17: AL-59 | R17: AL-4 | S17: AL-7 | T17: Flexible Copper | U17: Galvanized steel wire | V17: Alumimium | W17: Alumimium ALLOY | X17: Coper tape - 0.1 mm | Y17: Copper Tape - 0.03 mm | Z17: Copper Tape - 0.035 mm | AA17: Copper Tape - 0.04 mm | AB17: Copper Tape - 0.045 mm | AC17: Copper Tape - 0.050 mm | AD17: Copper Tape - 0.060 mm | AE17: Copper Tape - 0.075 mm(DOUBLE) | AF17: Extruded semiconductive | AG17: Extruded Semiconductive(Stripable) | AH17: HT-XLPE | AI17: LT-XLPE | AJ17: TR XLPE | AK17: Type A PVC | AL17: Type C PVC (HR) | AM17: Type A PVC-1.45 | AN17: Type A PVC-FR | AO17: Type A PVC-FRLS | AP17: Type A PVC-1.38 | AQ17: POLY TAPE | AR17: FR PVC Type ST-1 | AS17: FR PVC Type ST-2 | AT17: FRLSH PVC Type ST-1 | AU17: FRLSH PVC Type ST-2 | AV17: PVC Type ST-1 | AW17: PVC Type ST-1-PRESSURE EXTRUDED | AX17: PVC Type ST-2 | AY17: PVC COMPOUND 1.48 | AZ17: PVC Type ST-2-PRESSURE EXTRUDED | BA17: ACSR CORE WIRE | BB17: ACSR DOG STEEL WIRE | BC17: Aluminium Flat Strip | BD17: Aluminium Round Wire | BE17: Alumimium Tape | BF17: Double Steel Tape | BG17: Galvanised Steel Flat Strip | BH17: Galvanised Steel Flat Strip (Double) | BI17: Galvanised Steel Flat Strip-B | BJ17: Galvanised Steel Round Wire | BK17: Galvanised Steel Round Wire (Double) | BL17: FR PVC Type ST-1 | BM17: FR PVC Type ST-2 | BN17: FRLSH PVC Type ST-1 | BO17: FRLSH PVC Type ST-2 | BP17: ZHFR | BQ17: PE-ST-3 | BR17: PE-ST-7 | BS17: PVC Type ST-1 | BT17: PVC Type ST-2 | BU17: PVC COMPOUND 1.48 | BV17: PVC Type ST-2-PRESSURE EXTRUDED | BW17: UV & Track Resistant XLPE | BX17: FILLER | BY17: Grease | BZ17: Water swellable Tape | CA17: Semi conducting Water Swellable tape | CB17: SEMICON TAPE | CC17: GLASS FIBER TAPE | CD17: COPPER WIRE 0.8 MM | CE17: RUBBERIZED COTTON TAPE | CF17: Water Tight Compound | CG17: PROPOSE DRUM TYPE | CH17: DRUM CODE | CI17: DRUM SIZE (FxbXtx Ft) | CJ17: PARTY STANDARD LENGTH (MTR) | CO17: MFG% | CP17: MFG VALUE | CQ17: PROF% | CR17: PROFIT VALUE | CS17: 1ST EX-WORKS | CT17: Intt % | CU17: INTT VALUE | CV17: insp% | CW17: INSP VALUE | CX17: TTR Charges% | CY17: TTR Charges VALUE
N18: 260 | O18: =+IFERROR(VLOOKUP($O$17,Sheet1!J:L,2,0),0) -> 0 | P18: =+IFERROR(VLOOKUP($P$17,Sheet1!J:M,2,0),0) -> 0 | Q18: =+IFERROR(VLOOKUP($Q$17,Sheet1!J:M,2,0),0) -> 0 | R18: =+IFERROR(VLOOKUP($R$17,Sheet1!J:M,2,0),0) -> 0 | S18: =+IFERROR(VLOOKUP($S$17,Sheet1!J:M,2,0),0) -> 0 | T18: =+IFERROR(VLOOKUP($T$17,Sheet1!J:M,2,0),0) -> 0 | U18: =+IFERROR(VLOOKUP($U$17,Sheet1!J:M,2,0),0) -> 0 | V18: =+IFERROR(VLOOKUP($V$17,Sheet1!N:Q,2,0),0) -> 0 | W18: =+IFERROR(VLOOKUP($W$17,Sheet1!N:O,2,0),0) -> 0 | X18: =+IFERROR(VLOOKUP($X$17,Sheet1!F:I,2,0),0) -> 0 | Y18: =+IFERROR(VLOOKUP($Y$17,Sheet1!F:I,2,0),0) -> 0 | Z18: =+IFERROR(VLOOKUP($Z$17,Sheet1!F:I,2,0),0) -> 0 | AA18: =+IFERROR(VLOOKUP($AA$17,Sheet1!F:I,2,0),0) -> 0 | AB18: =+IFERROR(VLOOKUP($AB$17,Sheet1!F:I,2,0),0) -> 0 | AC18: =+IFERROR(VLOOKUP($AC$17,Sheet1!F:I,2,0),0) -> 0 | AD18: =+IFERROR(VLOOKUP($AD$17,Sheet1!F:I,2,0),0) -> 0 | AE18: =+IFERROR(VLOOKUP($AE$17,Sheet1!F:I,2,0),0) -> 0 | AF18: =+IFERROR(VLOOKUP($AF$17,Sheet1!R:U,2,0),0) -> 0 | AG18: =+IFERROR(VLOOKUP($AG$17,Sheet1!R:U,2,0),0) -> 0 | AH18: =+IFERROR(VLOOKUP($AH$17,Sheet1!V:Y,2,0),0) -> 0 | AI18: =+IFERROR(VLOOKUP($AI$17,Sheet1!V:Y,2,0),0) -> 0 | AJ18: =+IFERROR(VLOOKUP($AJ$17,Sheet1!V:Y,2,0),0) -> 0 | AK18: =+IFERROR(VLOOKUP($AK$17,Sheet1!V:Y,2,0),0) -> 0 | AL18: =+IFERROR(VLOOKUP($AL$17,Sheet1!V:Y,2,0),0) -> 0 | AM18: =+IFERROR(VLOOKUP($AM$17,Sheet1!V:Y,2,0),0) -> 0 | AN18: =+IFERROR(VLOOKUP($AN$17,Sheet1!V:Y,2,0),0) -> 0 | AO18: =+IFERROR(VLOOKUP($AO$17,Sheet1!V:Y,2,0),0) -> 0 | AP18: =+IFERROR(VLOOKUP($AP$17,Sheet1!V:Y,2,0),0) -> 0 | AQ18: =+IFERROR(VLOOKUP($AQ$17,Sheet1!Z2:AA840,2,0),0) -> 0 | AR18: =+IFERROR(VLOOKUP($AR$17,Sheet1!AD2:AG840,2,0),0) -> 0 | AS18: =+IFERROR(VLOOKUP($AS$17,Sheet1!AD2:AG840,2,0),0) -> 0 | AT18: =+IFERROR(VLOOKUP($AT$17,Sheet1!AD2:AG840,2,0),0) -> 0 | AU18: =+IFERROR(VLOOKUP($AU$17,Sheet1!AD2:AG840,2,0),0) -> 0 | AV18: =+IFERROR(VLOOKUP($AV$17,Sheet1!AD2:AG840,2,0),0) -> 0 | AW18: =+IFERROR(VLOOKUP($AW$17,Sheet1!AD2:AG840,2,0),0) -> 0 | AX18: =+IFERROR(VLOOKUP($AX$17,Sheet1!AD2:AG840,2,0),0) -> 0 | AY18: =+IFERROR(VLOOKUP($AY$17,Sheet1!AD2:AG840,2,0),0) -> 0 | AZ18: =+IFERROR(VLOOKUP($AZ$17,Sheet1!AD2:AG840,2,0),0) -> 0 | BA18: 68 | BB18: 84 | BC18: =+IFERROR(VLOOKUP($BC$17,Sheet1!AH2:AK840,2,0),0) -> 0 | BD18: =+IFERROR(VLOOKUP($BD$17,Sheet1!AH2:AK840,2,0),0) -> 0 | BE18: =+IFERROR(VLOOKUP($BE$17,Sheet1!AH2:AK840,2,0),0) -> 0 | BF18: =+IFERROR(VLOOKUP($BF$17,Sheet1!AH2:AK840,2,0),0) -> 0 | BG18: =+IFERROR(VLOOKUP($BG$17,Sheet1!AH2:AK840,2,0),0) -> 0 | BH18: =+IFERROR(VLOOKUP($BH$17,Sheet1!AH2:AK840,2,0),0) -> 0 | BI18: =+IFERROR(VLOOKUP($BI$17,Sheet1!AH2:AK840,2,0),0) -> 0 | BJ18: =+IFERROR(VLOOKUP($BJ$17,Sheet1!AH2:AK840,2,0),0) -> 0 | BK18: =+IFERROR(VLOOKUP($BK$17,Sheet1!AH2:AK840,2,0),0) -> 0 | BL18: =+IFERROR(VLOOKUP($BL$17,Sheet1!AL2:AO840,2,0),0) -> 0 | BM18: =+IFERROR(VLOOKUP($BM$17,Sheet1!AL2:AO840,2,0),0) -> 0 | BN18: =+IFERROR(VLOOKUP($BN$17,Sheet1!AL2:AO840,2,0),0) -> 0 | BO18: =+IFERROR(VLOOKUP($BO$17,Sheet1!AL2:AO840,2,0),0) -> 0 | BP18: =+IFERROR(VLOOKUP($BP$17,Sheet1!AL2:AO840,2,0),0) -> 0 | BQ18: =+IFERROR(VLOOKUP($BQ$17,Sheet1!AL2:AO840,2,0),0) -> 0 | BR18: =+IFERROR(VLOOKUP($BR$17,Sheet1!AL2:AO840,2,0),0) -> 0 | BS18: =+IFERROR(VLOOKUP($BS$17,Sheet1!AL2:AO840,2,0),0) -> 0 | BT18: =+IFERROR(VLOOKUP($BT$17,Sheet1!AL2:AO840,2,0),0) -> 0 | BU18: =+IFERROR(VLOOKUP($BU$17,Sheet1!AL2:AO840,2,0),0) -> 0 | BV18: =+IFERROR(VLOOKUP($BV$17,Sheet1!AL2:AO840,2,0),0) -> 0 | BW18: =+IFERROR(VLOOKUP($BW$17,Sheet1!AL2:AO840,2,0),0) -> 0 | BX18: =+IFERROR(VLOOKUP($BX$17,Sheet1!AP2:AS840,2,0),0) -> 0 | BY18: 197 | BZ18: =+IFERROR(VLOOKUP($BZ$17,Sheet1!AX2:BA840,2,0),0) -> 0 | CA18: =+IFERROR(VLOOKUP($CA$17,Sheet1!BB2:BE840,2,0),0) -> 0 | CB18: =+IFERROR(VLOOKUP($CB$17,Sheet1!BF2:BI840,2,0),0) -> 0 | CC18: =+IFERROR(VLOOKUP($CC$17,Sheet1!BJ2:BM840,2,0),0) -> 0 | CD18: =+IFERROR(VLOOKUP($CD$17,Sheet1!BN2:BQ840,2,0),0) -> 0 | CE18: =+IFERROR(VLOOKUP($CE$17,Sheet1!BR2:BU840,2,0),0) -> 0 | CF18: =+IFERROR(VLOOKUP($CF$17,Sheet1!BV2:BY840,2,0),0) -> 0
A19: =Sheet1!A5 -> ENQ-16528-25-26 | B19: 45839 | C19: =Sheet1!C5 -> FC6200002 | D19: =Sheet1!D5 -> ACSR : DOG CONDUCTOR - 100 SQ. MM. (6/4.72/7/1.57) | E19: =CS19+CU19+CW19+CY19 -> 98870.988 | F19: =ROUNDUP(M27,0) -> 2852 | G19: =E19+F19 -> 101722.99 | H19: =Sheet1!CR5 -> 0.18 | I19: =G19*H19 -> 18310.138 | J19: =G19+I19 -> 120033.13 | K19: =Sheet1!CU5 -> 916 | L19: =Sheet1!CV5 -> KMS | M19: =J19*K19 -> 1.0995034e+08 | N19: 288.3 | O19: =+IFERROR(VLOOKUP($O$17,Sheet1!J5:L5,3,0),0) -> 0 | P19: =+IFERROR(VLOOKUP($P$17,Sheet1!J5:M5,3,0),0) -> 0 | Q19: =+IFERROR(VLOOKUP($Q$17,Sheet1!J5:M5,3,0),0) -> 0 | R19: =+IFERROR(VLOOKUP($R$17,Sheet1!J5:M5,3,0),0) -> 0 | S19: =+IFERROR(VLOOKUP($S$17,Sheet1!J5:M5,3,0),0) -> 0 | T19: =+IFERROR(VLOOKUP($T$17,Sheet1!J5:M5,3,0),0) -> 0 | U19: =+IFERROR(VLOOKUP($U$17,Sheet1!J5:M5,3,0),0) -> 0 | V19: =+IFERROR(VLOOKUP($V$17,Sheet1!N5:Q5,3,0),0) -> 0 | W19: =+IFERROR(VLOOKUP($W$17,Sheet1!N5:Q5,3,0),0) -> 0 | X19: =+IFERROR(VLOOKUP($X$17,Sheet1!F5:I5,3,0),0) -> 0 | Y19: =+IFERROR(VLOOKUP($Y$17,Sheet1!F5:I5,3,0),0) -> 0 | Z19: =+IFERROR(VLOOKUP($Z$17,Sheet1!F5:I5,3,0),0) -> 0 | AA19: =+IFERROR(VLOOKUP($AA$17,Sheet1!F5:I5,3,0),0) -> 0 | AB19: =+IFERROR(VLOOKUP($AB$17,Sheet1!F5:I5,3,0),0) -> 0 | AC19: =+IFERROR(VLOOKUP($AC$17,Sheet1!F5:I5,3,0),0) -> 0 | AD19: =+IFERROR(VLOOKUP($AD$17,Sheet1!F5:I5,3,0),0) -> 0 | AE19: =+IFERROR(VLOOKUP($AE$17,Sheet1!F5:I5,3,0),0) -> 0 | AF19: =+IFERROR(VLOOKUP($AF$17,Sheet1!R5:U5,3,0),0) -> 0 | AG19: =+IFERROR(VLOOKUP($AG$17,Sheet1!R5:U5,3,0),0) -> 0 | AH19: =+IFERROR(VLOOKUP($AH$17,Sheet1!V5:Y5,3,0),0) -> 0 | AI19: =+IFERROR(VLOOKUP($AI$17,Sheet1!V5:Y5,3,0),0) -> 0 | AJ19: =+IFERROR(VLOOKUP($AJ$17,Sheet1!V5:Y5,3,0),0) -> 0 | AK19: =+IFERROR(VLOOKUP($AK$17,Sheet1!V5:Y5,3,0),0) -> 0 | AL19: =+IFERROR(VLOOKUP($AL$17,Sheet1!V5:Y5,3,0),0) -> 0 | AM19: =+IFERROR(VLOOKUP($AM$17,Sheet1!V5:Y5,3,0),0) -> 0 | AN19: =+IFERROR(VLOOKUP($AN$17,Sheet1!V5:Y5,3,0),0) -> 0 | AO19: =+IFERROR(VLOOKUP($AO$17,Sheet1!V5:Y5,3,0),0) -> 0 | AP19: =+IFERROR(VLOOKUP($AP$17,Sheet1!V5:Y5,3,0),0) -> 0 | AQ19: =+IFERROR(VLOOKUP($AQ$17,Sheet1!Z5:AB5,3,0),0) -> 0 | AR19: =+IFERROR(VLOOKUP($AR$17,Sheet1!AD5:AG5,3,0),0) -> 0 | AS19: =+IFERROR(VLOOKUP($AS$17,Sheet1!AD5:AG5,3,0),0) -> 0 | AT19: =+IFERROR(VLOOKUP($AT$17,Sheet1!AD5:AG5,3,0),0) -> 0 | AU19: =+IFERROR(VLOOKUP($AU$17,Sheet1!AD5:AG5,3,0),0) -> 0 | AV19: =+IFERROR(VLOOKUP($AV$17,Sheet1!AD5:AG5,3,0),0) -> 0 | AW19: =+IFERROR(VLOOKUP($AW$17,Sheet1!AD5:AG5,3,0),0) -> 0 | AX19: =+IFERROR(VLOOKUP($AX$17,Sheet1!AD5:AG5,3,0),0) -> 0 | AY19: =+IFERROR(VLOOKUP($AY$17,Sheet1!AD5:AG5,3,0),0) -> 0 | AZ19: =+IFERROR(VLOOKUP($AZ$17,Sheet1!AD5:AG5,3,0),0) -> 0 | BA19: =+IFERROR(VLOOKUP($BA$17,Sheet1!AH5:AK5,3,0),0) -> 0 | BB19: =+IFERROR(VLOOKUP($BB$17,Sheet1!AH5:AK5,3,0),0) -> 106 | BC19: =+IFERROR(VLOOKUP($BC$17,Sheet1!AH5:AK5,3,0),0) -> 0 | BD19: =+IFERROR(VLOOKUP($BD$17,Sheet1!AH5:AK5,3,0),0) -> 0 | BE19: =+IFERROR(VLOOKUP($BE$17,Sheet1!AH5:AK5,3,0),0) -> 0 | BF19: =+IFERROR(VLOOKUP($BF$17,Sheet1!AH5:AK5,3,0),0) -> 0 | BG19: =+IFERROR(VLOOKUP($BG$17,Sheet1!AH5:AK5,3,0),0) -> 0 | BH19: =+IFERROR(VLOOKUP($BH$17,Sheet1!AH5:AK5,3,0),0) -> 0 | BI19: =+IFERROR(VLOOKUP($BI$17,Sheet1!AH5:AK5,3,0),0) -> 0 | BJ19: =+IFERROR(VLOOKUP($BJ$17,Sheet1!AH5:AK5,3,0),0) -> 0 | BK19: =+IFERROR(VLOOKUP($BK$17,Sheet1!AH5:AK5,3,0),0) -> 0 | BL19: =+IFERROR(VLOOKUP($BL$17,Sheet1!AL5:AO5,3,0),0) -> 0 | BM19: =+IFERROR(VLOOKUP($BM$17,Sheet1!AL5:AO5,3,0),0) -> 0 | BN19: =+IFERROR(VLOOKUP($BN$17,Sheet1!AL5:AO5,3,0),0) -> 0 | BO19: =+IFERROR(VLOOKUP($BO$17,Sheet1!AL5:AO5,3,0),0) -> 0 | BP19: =+IFERROR(VLOOKUP($BP$17,Sheet1!AL5:AO5,3,0),0) -> 0 | BQ19: =+IFERROR(VLOOKUP($BQ$17,Sheet1!AL5:AO5,3,0),0) -> 0 | BR19: =+IFERROR(VLOOKUP($BR$17,Sheet1!AL5:AO5,3,0),0) -> 0 | BS19: =+IFERROR(VLOOKUP($BS$17,Sheet1!AL5:AO5,3,0),0) -> 0 | BT19: =+IFERROR(VLOOKUP($BT$17,Sheet1!AL5:AO5,3,0),0) -> 0 | BU19: =+IFERROR(VLOOKUP($BU$17,Sheet1!AL5:AO5,3,0),0) -> 0 | BV19: =+IFERROR(VLOOKUP($BV$17,Sheet1!AL5:AO5,3,0),0) -> 0 | BW19: =+IFERROR(VLOOKUP($BW$17,Sheet1!AL5:AO5,3,0),0) -> 0 | BX19: =+IFERROR(VLOOKUP($BX$17,Sheet1!AP5:AS5,3,0),0) -> 0 | BY19: 4 | BZ19: =+IFERROR(VLOOKUP($BZ$17,Sheet1!AX5:BA5,3,0),0) -> 0 | CA19: =+IFERROR(VLOOKUP($CA$17,Sheet1!BB5:BE5,3,0),0) -> 0 | CB19: =+IFERROR(VLOOKUP($CB$17,Sheet1!BF5:BI5,3,0),0) -> 0 | CC19: =+IFERROR(VLOOKUP($CC$17,Sheet1!BJ5:BM5,3,0),0) -> 0 | CD19: =+IFERROR(VLOOKUP($CD$17,Sheet1!BN5:BQ5,3,0),0) -> 0 | CE19: =+IFERROR(VLOOKUP($CE$17,Sheet1!BR5:BU5,3,0),0) -> 0 | CF19: =+IFERROR(VLOOKUP($CF$17,Sheet1!BV5:BY5,3,0),0) -> 0 | CG19: STEEL | CH19: SP0400144 | CI19: CORRUGATED DISPATCH STEEL DRUM 1060 X 600 X 965 MM | CJ19: =Sheet1!CZ5 -> 2000 | CK19: =18000/2 -> 9000 | CL19: =SUMPRODUCT($N$18:$CF$18,N19:CF19)+CK19 -> 93650 | CM19: =Sheet1!CB5 -> 0 | CN19: =CL19*CM19 -> 0 | CO19: 0.03 | CP19: =CL19*CO19 -> 2809.5 | CQ19: 0 | CR19: =CL19*CQ19 -> 0 | CS19: =CL19+CN19+CP19+CR19 -> 96459.5 | CT19: 0.02 | CU19: =CS19*CT19 -> 1929.19 | CV19: 0.005 | CW19: =CS19*CV19 -> 482.2975 | CX19: =Sheet1!CM5 -> 0 | CY19: =CX19*CS19 -> 0 | CZ19: 1
A20: =Sheet1!A2 -> ENQ-16528-25-26 | B20: 45839 | C20: =Sheet1!C2 -> FC3700003 | D20: =Sheet1!D2 -> ACSR : PANTHER CONDUCTOR - 200 SQ. MM. (30/7/3.00) | E20: =CS20+CU20+CW20+CY20 -> 198464.11 | F20: =ROUNDUP(M28,0) -> 6023 | G20: =E20+F20 -> 204487.11 | H20: =Sheet1!CR2 -> 0.18 | I20: =G20*H20 -> 36807.679 | J20: =G20+I20 -> 241294.79 | K20: =Sheet1!CU2 -> 10772 | L20: =Sheet1!CV2 -> KMS | M20: =J20*K20 -> 2.5992275e+09 | N20: =+IFERROR(VLOOKUP($N$17,Sheet1!J2:L2,3,0),0) -> 588 | O20: =+IFERROR(VLOOKUP($O$17,Sheet1!J2:L2,3,0),0) -> 0 | P20: =+IFERROR(VLOOKUP($P$17,Sheet1!J2:M2,3,0),0) -> 0 | Q20: =+IFERROR(VLOOKUP($Q$17,Sheet1!J2:M2,3,0),0) -> 0 | R20: =+IFERROR(VLOOKUP($R$17,Sheet1!J2:M2,3,0),0) -> 0 | S20: =+IFERROR(VLOOKUP($S$17,Sheet1!J2:M2,3,0),0) -> 0 | T20: =+IFERROR(VLOOKUP($T$17,Sheet1!J2:M2,3,0),0) -> 0 | U20: =+IFERROR(VLOOKUP($U$17,Sheet1!J2:M2,3,0),0) -> 0 | V20: =+IFERROR(VLOOKUP($V$17,Sheet1!N2:Q2,3,0),0) -> 0 | W20: =+IFERROR(VLOOKUP($W$17,Sheet1!N2:Q2,3,0),0) -> 0 | X20: =+IFERROR(VLOOKUP($X$17,Sheet1!F2:I2,3,0),0) -> 0 | Y20: =+IFERROR(VLOOKUP($Y$17,Sheet1!F2:I2,3,0),0) -> 0 | Z20: =+IFERROR(VLOOKUP($Z$17,Sheet1!F2:I2,3,0),0) -> 0 | AA20: =+IFERROR(VLOOKUP($AA$17,Sheet1!F2:I2,3,0),0) -> 0 | AB20: =+IFERROR(VLOOKUP($AB$17,Sheet1!F2:I2,3,0),0) -> 0 | AC20: =+IFERROR(VLOOKUP($AC$17,Sheet1!F2:I2,3,0),0) -> 0 | AD20: =+IFERROR(VLOOKUP($AD$17,Sheet1!F2:I2,3,0),0) -> 0 | AE20: =+IFERROR(VLOOKUP($AE$17,Sheet1!F2:I2,3,0),0) -> 0 | AF20: =+IFERROR(VLOOKUP($AF$17,Sheet1!R2:U2,3,0),0) -> 0 | AG20: =+IFERROR(VLOOKUP($AG$17,Sheet1!R2:U2,3,0),0) -> 0 | AH20: =+IFERROR(VLOOKUP($AH$17,Sheet1!V2:Y2,3,0),0) -> 0 | AI20: =+IFERROR(VLOOKUP($AI$17,Sheet1!V2:Y2,3,0),0) -> 0 | AJ20: =+IFERROR(VLOOKUP($AJ$17,Sheet1!V2:Y2,3,0),0) -> 0 | AK20: =+IFERROR(VLOOKUP($AK$17,Sheet1!V2:Y2,3,0),0) -> 0 | AL20: =+IFERROR(VLOOKUP($AL$17,Sheet1!V2:Y2,3,0),0) -> 0 | AM20: =+IFERROR(VLOOKUP($AM$17,Sheet1!V2:Y2,3,0),0) -> 0 | AN20: =+IFERROR(VLOOKUP($AN$17,Sheet1!V2:Y2,3,0),0) -> 0 | AO20: =+IFERROR(VLOOKUP($AO$17,Sheet1!V2:Y2,3,0),0) -> 0 | AP20: =+IFERROR(VLOOKUP($AP$17,Sheet1!V2:Y2,3,0),0) -> 0 | AQ20: =+IFERROR(VLOOKUP($AQ$17,Sheet1!Z2:AB2,3,0),0) -> 0 | AR20: =+IFERROR(VLOOKUP($AR$17,Sheet1!AD2:AG2,3,0),0) -> 0 | AS20: =+IFERROR(VLOOKUP($AS$17,Sheet1!AD2:AG2,3,0),0) -> 0 | AT20: =+IFERROR(VLOOKUP($AT$17,Sheet1!AD2:AG2,3,0),0) -> 0 | AU20: =+IFERROR(VLOOKUP($AU$17,Sheet1!AD2:AG2,3,0),0) -> 0 | AV20: =+IFERROR(VLOOKUP($AV$17,Sheet1!AD2:AG2,3,0),0) -> 0 | AW20: =+IFERROR(VLOOKUP($AW$17,Sheet1!AD2:AG2,3,0),0) -> 0 | AX20: =+IFERROR(VLOOKUP($AX$17,Sheet1!AD2:AG2,3,0),0) -> 0 | AY20: =+IFERROR(VLOOKUP($AY$17,Sheet1!AD2:AG2,3,0),0) -> 0 | AZ20: =+IFERROR(VLOOKUP($AZ$17,Sheet1!AD2:AG2,3,0),0) -> 0 | BA20: =+IFERROR(VLOOKUP($BA$17,Sheet1!AH2:AK2,3,0),0) -> 388 | BB20: =+IFERROR(VLOOKUP($BB$17,Sheet1!AH2:AK2,3,0),0) -> 0 | BC20: =+IFERROR(VLOOKUP($BC$17,Sheet1!AH2:AK2,3,0),0) -> 0 | BD20: =+IFERROR(VLOOKUP($BD$17,Sheet1!AH2:AK2,3,0),0) -> 0 | BE20: =+IFERROR(VLOOKUP($BE$17,Sheet1!AH2:AK2,3,0),0) -> 0 | BF20: =+IFERROR(VLOOKUP($BF$17,Sheet1!AH2:AK2,3,0),0) -> 0 | BG20: =+IFERROR(VLOOKUP($BG$17,Sheet1!AH2:AK2,3,0),0) -> 0 | BH20: =+IFERROR(VLOOKUP($BH$17,Sheet1!AH2:AK2,3,0),0) -> 0 | BI20: =+IFERROR(VLOOKUP($BI$17,Sheet1!AH2:AK2,3,0),0) -> 0 | BJ20: =+IFERROR(VLOOKUP($BJ$17,Sheet1!AH2:AK2,3,0),0) -> 0 | BK20: =+IFERROR(VLOOKUP($BK$17,Sheet1!AH2:AK2,3,0),0) -> 0 | BL20: =+IFERROR(VLOOKUP($BL$17,Sheet1!AL2:AO2,3,0),0) -> 0 | BM20: =+IFERROR(VLOOKUP($BM$17,Sheet1!AL2:AO2,3,0),0) -> 0 | BN20: =+IFERROR(VLOOKUP($BN$17,Sheet1!AL2:AO2,3,0),0) -> 0 | BO20: =+IFERROR(VLOOKUP($BO$17,Sheet1!AL2:AO2,3,0),0) -> 0 | BP20: =+IFERROR(VLOOKUP($BP$17,Sheet1!AL2:AO2,3,0),0) -> 0 | BQ20: =+IFERROR(VLOOKUP($BQ$17,Sheet1!AL2:AO2,3,0),0) -> 0 | BR20: =+IFERROR(VLOOKUP($BR$17,Sheet1!AL2:AO2,3,0),0) -> 0 | BS20: =+IFERROR(VLOOKUP($BS$17,Sheet1!AL2:AO2,3,0),0) -> 0 | BT20: =+IFERROR(VLOOKUP($BT$17,Sheet1!AL2:AO2,3,0),0) -> 0 | BU20: =+IFERROR(VLOOKUP($BU$17,Sheet1!AL2:AO2,3,0),0) -> 0 | BV20: =+IFERROR(VLOOKUP($BV$17,Sheet1!AL2:AO2,3,0),0) -> 0 | BW20: =+IFERROR(VLOOKUP($BW$17,Sheet1!AL2:AO2,3,0),0) -> 0 | BX20: =+IFERROR(VLOOKUP($BX$17,Sheet1!AP2:AS2,3,0),0) -> 0 | BY20: 10 | BZ20: =+IFERROR(VLOOKUP($BZ$17,Sheet1!AX2:BA2,3,0),0) -> 0 | CA20: =+IFERROR(VLOOKUP($CA$17,Sheet1!BB2:BE2,3,0),0) -> 0 | CB20: =+IFERROR(VLOOKUP($CB$17,Sheet1!BF2:BI2,3,0),0) -> 0 | CC20: =+IFERROR(VLOOKUP($CC$17,Sheet1!BJ2:BM2,3,0),0) -> 0 | CD20: =+IFERROR(VLOOKUP($CD$17,Sheet1!BN2:BQ2,3,0),0) -> 0 | CE20: =+IFERROR(VLOOKUP($CE$17,Sheet1!BR2:BU2,3,0),0) -> 0 | CF20: =+IFERROR(VLOOKUP($CF$17,Sheet1!BV2:BY2,3,0),0) -> 0 | CG20: STEEL | CH20: SP0400152 | CI20: CORRUGATED DISPATCH STEEL DRUM 1500 X 800 X 915 | CJ20: =Sheet1!CZ2 -> 2000 | CK20: =13500/2 -> 6750 | CL20: =SUMPRODUCT($N$18:$CF$18,N20:CF20)+CK20 -> 187984 | CM20: =Sheet1!CB2 -> 0 | CN20: =CL20*CM20 -> 0 | CO20: 0.03 | CP20: =CL20*CO20 -> 5639.52 | CQ20: 0 | CR20: =CL20*CQ20 -> 0 | CS20: =CL20+CN20+CP20+CR20 -> 193623.52 | CT20: 0.02 | CU20: =CS20*CT20 -> 3872.4704 | CV20: 0.005 | CW20: =CS20*CV20 -> 968.1176 | CX20: =Sheet1!CM2 -> 0 | CY20: =CX20*CS20 -> 0 | CZ20: 2
A21: =Sheet1!A3 -> ENQ-16528-25-26 | B21: 45839 | C21: =Sheet1!C3 -> FC6100001 | D21: =Sheet1!D3 -> ACSR : ZEBRA CONDUCTOR - 420 SQ. MM. (54/7/3.18) | E21: =CS21+CU21+CW21+CY21 -> 368136.86 | F21: =ROUNDUP(M29,0) -> 13050 | G21: =E21+F21 -> 381186.86 | H21: =Sheet1!CR3 -> 0.18 | I21: =G21*H21 -> 68613.634 | J21: =G21+I21 -> 449800.49 | K21: =Sheet1!CU3 -> 1566 | L21: =Sheet1!CV3 -> KMS | M21: =J21*K21 -> 7.0438757e+08 | N21: =+IFERROR(VLOOKUP($N$17,Sheet1!J3:L3,3,0),0) -> 1186 | O21: =+IFERROR(VLOOKUP($O$17,Sheet1!J3:L3,3,0),0) -> 0 | P21: =+IFERROR(VLOOKUP($P$17,Sheet1!J3:M3,3,0),0) -> 0 | Q21: =+IFERROR(VLOOKUP($Q$17,Sheet1!J3:M3,3,0),0) -> 0 | R21: =+IFERROR(VLOOKUP($R$17,Sheet1!J3:M3,3,0),0) -> 0 | S21: =+IFERROR(VLOOKUP($S$17,Sheet1!J3:M3,3,0),0) -> 0 | T21: =+IFERROR(VLOOKUP($T$17,Sheet1!J3:M3,3,0),0) -> 0 | U21: =+IFERROR(VLOOKUP($U$17,Sheet1!J3:M3,3,0),0) -> 0 | V21: =+IFERROR(VLOOKUP($V$17,Sheet1!N3:Q3,3,0),0) -> 0 | W21: =+IFERROR(VLOOKUP($W$17,Sheet1!N3:Q3,3,0),0) -> 0 | X21: =+IFERROR(VLOOKUP($X$17,Sheet1!F3:I3,3,0),0) -> 0 | Y21: =+IFERROR(VLOOKUP($Y$17,Sheet1!F3:I3,3,0),0) -> 0 | Z21: =+IFERROR(VLOOKUP($Z$17,Sheet1!F3:I3,3,0),0) -> 0 | AA21: =+IFERROR(VLOOKUP($AA$17,Sheet1!F3:I3,3,0),0) -> 0 | AB21: =+IFERROR(VLOOKUP($AB$17,Sheet1!F3:I3,3,0),0) -> 0 | AC21: =+IFERROR(VLOOKUP($AC$17,Sheet1!F3:I3,3,0),0) -> 0 | AD21: =+IFERROR(VLOOKUP($AD$17,Sheet1!F3:I3,3,0),0) -> 0 | AE21: =+IFERROR(VLOOKUP($AE$17,Sheet1!F3:I3,3,0),0) -> 0 | AF21: =+IFERROR(VLOOKUP($AF$17,Sheet1!R3:U3,3,0),0) -> 0 | AG21: =+IFERROR(VLOOKUP($AG$17,Sheet1!R3:U3,3,0),0) -> 0 | AH21: =+IFERROR(VLOOKUP($AH$17,Sheet1!V3:Y3,3,0),0) -> 0 | AI21: =+IFERROR(VLOOKUP($AI$17,Sheet1!V3:Y3,3,0),0) -> 0 | AJ21: =+IFERROR(VLOOKUP($AJ$17,Sheet1!V3:Y3,3,0),0) -> 0 | AK21: =+IFERROR(VLOOKUP($AK$17,Sheet1!V3:Y3,3,0),0) -> 0 | AL21: =+IFERROR(VLOOKUP($AL$17,Sheet1!V3:Y3,3,0),0) -> 0 | AM21: =+IFERROR(VLOOKUP($AM$17,Sheet1!V3:Y3,3,0),0) -> 0 | AN21: =+IFERROR(VLOOKUP($AN$17,Sheet1!V3:Y3,3,0),0) -> 0 | AO21: =+IFERROR(VLOOKUP($AO$17,Sheet1!V3:Y3,3,0),0) -> 0 | AP21: =+IFERROR(VLOOKUP($AP$17,Sheet1!V3:Y3,3,0),0) -> 0 | AQ21: =+IFERROR(VLOOKUP($AQ$17,Sheet1!Z3:AB3,3,0),0) -> 0 | AR21: =+IFERROR(VLOOKUP($AR$17,Sheet1!AD3:AG3,3,0),0) -> 0 | AS21: =+IFERROR(VLOOKUP($AS$17,Sheet1!AD3:AG3,3,0),0) -> 0 | AT21: =+IFERROR(VLOOKUP($AT$17,Sheet1!AD3:AG3,3,0),0) -> 0 | AU21: =+IFERROR(VLOOKUP($AU$17,Sheet1!AD3:AG3,3,0),0) -> 0 | AV21: =+IFERROR(VLOOKUP($AV$17,Sheet1!AD3:AG3,3,0),0) -> 0 | AW21: =+IFERROR(VLOOKUP($AW$17,Sheet1!AD3:AG3,3,0),0) -> 0 | AX21: =+IFERROR(VLOOKUP($AX$17,Sheet1!AD3:AG3,3,0),0) -> 0 | AY21: =+IFERROR(VLOOKUP($AY$17,Sheet1!AD3:AG3,3,0),0) -> 0 | AZ21: =+IFERROR(VLOOKUP($AZ$17,Sheet1!AD3:AG3,3,0),0) -> 0 | BA21: =+IFERROR(VLOOKUP($BA$17,Sheet1!AH3:AK3,3,0),0) -> 436 | BB21: =+IFERROR(VLOOKUP($BB$17,Sheet1!AH3:AK3,3,0),0) -> 0 | BC21: =+IFERROR(VLOOKUP($BC$17,Sheet1!AH3:AK3,3,0),0) -> 0 | BD21: =+IFERROR(VLOOKUP($BD$17,Sheet1!AH3:AK3,3,0),0) -> 0 | BE21: =+IFERROR(VLOOKUP($BE$17,Sheet1!AH3:AK3,3,0),0) -> 0 | BF21: =+IFERROR(VLOOKUP($BF$17,Sheet1!AH3:AK3,3,0),0) -> 0 | BG21: =+IFERROR(VLOOKUP($BG$17,Sheet1!AH3:AK3,3,0),0) -> 0 | BH21: =+IFERROR(VLOOKUP($BH$17,Sheet1!AH3:AK3,3,0),0) -> 0 | BI21: =+IFERROR(VLOOKUP($BI$17,Sheet1!AH3:AK3,3,0),0) -> 0 | BJ21: =+IFERROR(VLOOKUP($BJ$17,Sheet1!AH3:AK3,3,0),0) -> 0 | BK21: =+IFERROR(VLOOKUP($BK$17,Sheet1!AH3:AK3,3,0),0) -> 0 | BL21: =+IFERROR(VLOOKUP($BL$17,Sheet1!AL3:AO3,3,0),0) -> 0 | BM21: =+IFERROR(VLOOKUP($BM$17,Sheet1!AL3:AO3,3,0),0) -> 0 | BN21: =+IFERROR(VLOOKUP($BN$17,Sheet1!AL3:AO3,3,0),0) -> 0 | BO21: =+IFERROR(VLOOKUP($BO$17,Sheet1!AL3:AO3,3,0),0) -> 0 | BP21: =+IFERROR(VLOOKUP($BP$17,Sheet1!AL3:AO3,3,0),0) -> 0 | BQ21: =+IFERROR(VLOOKUP($BQ$17,Sheet1!AL3:AO3,3,0),0) -> 0 | BR21: =+IFERROR(VLOOKUP($BR$17,Sheet1!AL3:AO3,3,0),0) -> 0 | BS21: =+IFERROR(VLOOKUP($BS$17,Sheet1!AL3:AO3,3,0),0) -> 0 | BT21: =+IFERROR(VLOOKUP($BT$17,Sheet1!AL3:AO3,3,0),0) -> 0 | BU21: =+IFERROR(VLOOKUP($BU$17,Sheet1!AL3:AO3,3,0),0) -> 0 | BV21: =+IFERROR(VLOOKUP($BV$17,Sheet1!AL3:AO3,3,0),0) -> 0 | BW21: =+IFERROR(VLOOKUP($BW$17,Sheet1!AL3:AO3,3,0),0) -> 0 | BX21: =+IFERROR(VLOOKUP($BX$17,Sheet1!AP3:AS3,3,0),0) -> 0 | BY21: 12 | BZ21: =+IFERROR(VLOOKUP($BZ$17,Sheet1!AX3:BA3,3,0),0) -> 0 | CA21: =+IFERROR(VLOOKUP($CA$17,Sheet1!BB3:BE3,3,0),0) -> 0 | CB21: =+IFERROR(VLOOKUP($CB$17,Sheet1!BF3:BI3,3,0),0) -> 0 | CC21: =+IFERROR(VLOOKUP($CC$17,Sheet1!BJ3:BM3,3,0),0) -> 0 | CD21: =+IFERROR(VLOOKUP($CD$17,Sheet1!BN3:BQ3,3,0),0) -> 0 | CE21: =+IFERROR(VLOOKUP($CE$17,Sheet1!BR3:BU3,3,0),0) -> 0 | CF21: =+IFERROR(VLOOKUP($CF$17,Sheet1!BV3:BY3,3,0),0) -> 0 | CG21: STEEL | CH21: SP0400126 | CI21: CORRUGATED DISPATCH STEEL DRUM 1900 X 830 X 915 MM | CJ21: =Sheet1!CZ3 -> 2000 | CK21: =16650/2 -> 8325 | CL21: =SUMPRODUCT($N$18:$CF$18,N21:CF21)+CK21 -> 348697 | CM21: =Sheet1!CB3 -> 0 | CN21: =CL21*CM21 -> 0 | CO21: 0.03 | CP21: =CL21*CO21 -> 10460.91 | CQ21: 0 | CR21: =CL21*CQ21 -> 0 | CS21: =CL21+CN21+CP21+CR21 -> 359157.91 | CT21: 0.02 | CU21: =CS21*CT21 -> 7183.1582 | CV21: 0.005 | CW21: =CS21*CV21 -> 1795.7895 | CX21: =Sheet1!CM3 -> 0 | CY21: =CX21*CS21 -> 0 | CZ21: 3
A22: =Sheet1!A4 -> ENQ-16528-25-26 | B22: 45839 | C22: =Sheet1!C4 -> FC6100002 | D22: =Sheet1!D4 -> ACSR : MOOSE CONDUCTOR - 520 SQ. MM. (54/7/3.53) | E22: =CS22+CU22+CW22+CY22 -> 459350.49 | F22: =ROUNDUP(M30,0) -> 15600 | G22: =E22+F22 -> 474950.49 | H22: =Sheet1!CR4 -> 0.18 | I22: =G22*H22 -> 85491.088 | J22: =G22+I22 -> 560441.58 | K22: =Sheet1!CU4 -> 2200 | L22: =Sheet1!CV4 -> KMS | M22: =J22*K22 -> 1.2329715e+09 | N22: =+IFERROR(VLOOKUP($N$17,Sheet1!J4:L4,3,0),0) -> 1467 | O22: =+IFERROR(VLOOKUP($O$17,Sheet1!J4:L4,3,0),0) -> 0 | P22: =+IFERROR(VLOOKUP($P$17,Sheet1!J4:M4,3,0),0) -> 0 | Q22: =+IFERROR(VLOOKUP($Q$17,Sheet1!J4:M4,3,0),0) -> 0 | R22: =+IFERROR(VLOOKUP($R$17,Sheet1!J4:M4,3,0),0) -> 0 | S22: =+IFERROR(VLOOKUP($S$17,Sheet1!J4:M4,3,0),0) -> 0 | T22: =+IFERROR(VLOOKUP($T$17,Sheet1!J4:M4,3,0),0) -> 0 | U22: =+IFERROR(VLOOKUP($U$17,Sheet1!J4:M4,3,0),0) -> 0 | V22: =+IFERROR(VLOOKUP($V$17,Sheet1!N4:Q4,3,0),0) -> 0 | W22: =+IFERROR(VLOOKUP($W$17,Sheet1!N4:Q4,3,0),0) -> 0 | X22: =+IFERROR(VLOOKUP($X$17,Sheet1!F4:I4,3,0),0) -> 0 | Y22: =+IFERROR(VLOOKUP($Y$17,Sheet1!F4:I4,3,0),0) -> 0 | Z22: =+IFERROR(VLOOKUP($Z$17,Sheet1!F4:I4,3,0),0) -> 0 | AA22: =+IFERROR(VLOOKUP($AA$17,Sheet1!F4:I4,3,0),0) -> 0 | AB22: =+IFERROR(VLOOKUP($AB$17,Sheet1!F4:I4,3,0),0) -> 0 | AC22: =+IFERROR(VLOOKUP($AC$17,Sheet1!F4:I4,3,0),0) -> 0 | AD22: =+IFERROR(VLOOKUP($AD$17,Sheet1!F4:I4,3,0),0) -> 0 | AE22: =+IFERROR(VLOOKUP($AE$17,Sheet1!F4:I4,3,0),0) -> 0 | AF22: =+IFERROR(VLOOKUP($AF$17,Sheet1!R4:U4,3,0),0) -> 0 | AG22: =+IFERROR(VLOOKUP($AG$17,Sheet1!R4:U4,3,0),0) -> 0 | AH22: =+IFERROR(VLOOKUP($AH$17,Sheet1!V4:Y4,3,0),0) -> 0 | AI22: =+IFERROR(VLOOKUP($AI$17,Sheet1!V4:Y4,3,0),0) -> 0 | AJ22: =+IFERROR(VLOOKUP($AJ$17,Sheet1!V4:Y4,3,0),0) -> 0 | AK22: =+IFERROR(VLOOKUP($AK$17,Sheet1!V4:Y4,3,0),0) -> 0 | AL22: =+IFERROR(VLOOKUP($AL$17,Sheet1!V4:Y4,3,0),0) -> 0 | AM22: =+IFERROR(VLOOKUP($AM$17,Sheet1!V4:Y4,3,0),0) -> 0 | AN22: =+IFERROR(VLOOKUP($AN$17,Sheet1!V4:Y4,3,0),0) -> 0 | AO22: =+IFERROR(VLOOKUP($AO$17,Sheet1!V4:Y4,3,0),0) -> 0 | AP22: =+IFERROR(VLOOKUP($AP$17,Sheet1!V4:Y4,3,0),0) -> 0 | AQ22: =+IFERROR(VLOOKUP($AQ$17,Sheet1!Z4:AB4,3,0),0) -> 0 | AR22: =+IFERROR(VLOOKUP($AR$17,Sheet1!AD4:AG4,3,0),0) -> 0 | AS22: =+IFERROR(VLOOKUP($AS$17,Sheet1!AD4:AG4,3,0),0) -> 0 | AT22: =+IFERROR(VLOOKUP($AT$17,Sheet1!AD4:AG4,3,0),0) -> 0 | AU22: =+IFERROR(VLOOKUP($AU$17,Sheet1!AD4:AG4,3,0),0) -> 0 | AV22: =+IFERROR(VLOOKUP($AV$17,Sheet1!AD4:AG4,3,0),0) -> 0 | AW22: =+IFERROR(VLOOKUP($AW$17,Sheet1!AD4:AG4,3,0),0) -> 0 | AX22: =+IFERROR(VLOOKUP($AX$17,Sheet1!AD4:AG4,3,0),0) -> 0 | AY22: =+IFERROR(VLOOKUP($AY$17,Sheet1!AD4:AG4,3,0),0) -> 0 | AZ22: =+IFERROR(VLOOKUP($AZ$17,Sheet1!AD4:AG4,3,0),0) -> 0 | BA22: =+IFERROR(VLOOKUP($BA$17,Sheet1!AH4:AK4,3,0),0) -> 537 | BB22: =+IFERROR(VLOOKUP($BB$17,Sheet1!AH4:AK4,3,0),0) -> 0 | BC22: =+IFERROR(VLOOKUP($BC$17,Sheet1!AH4:AK4,3,0),0) -> 0 | BD22: =+IFERROR(VLOOKUP($BD$17,Sheet1!AH4:AK4,3,0),0) -> 0 | BE22: =+IFERROR(VLOOKUP($BE$17,Sheet1!AH4:AK4,3,0),0) -> 0 | BF22: =+IFERROR(VLOOKUP($BF$17,Sheet1!AH4:AK4,3,0),0) -> 0 | BG22: =+IFERROR(VLOOKUP($BG$17,Sheet1!AH4:AK4,3,0),0) -> 0 | BH22: =+IFERROR(VLOOKUP($BH$17,Sheet1!AH4:AK4,3,0),0) -> 0 | BI22: =+IFERROR(VLOOKUP($BI$17,Sheet1!AH4:AK4,3,0),0) -> 0 | BJ22: =+IFERROR(VLOOKUP($BJ$17,Sheet1!AH4:AK4,3,0),0) -> 0 | BK22: =+IFERROR(VLOOKUP($BK$17,Sheet1!AH4:AK4,3,0),0) -> 0 | BL22: =+IFERROR(VLOOKUP($BL$17,Sheet1!AL4:AO4,3,0),0) -> 0 | BM22: =+IFERROR(VLOOKUP($BM$17,Sheet1!AL4:AO4,3,0),0) -> 0 | BN22: =+IFERROR(VLOOKUP($BN$17,Sheet1!AL4:AO4,3,0),0) -> 0 | BO22: =+IFERROR(VLOOKUP($BO$17,Sheet1!AL4:AO4,3,0),0) -> 0 | BP22: =+IFERROR(VLOOKUP($BP$17,Sheet1!AL4:AO4,3,0),0) -> 0 | BQ22: =+IFERROR(VLOOKUP($BQ$17,Sheet1!AL4:AO4,3,0),0) -> 0 | BR22: =+IFERROR(VLOOKUP($BR$17,Sheet1!AL4:AO4,3,0),0) -> 0 | BS22: =+IFERROR(VLOOKUP($BS$17,Sheet1!AL4:AO4,3,0),0) -> 0 | BT22: =+IFERROR(VLOOKUP($BT$17,Sheet1!AL4:AO4,3,0),0) -> 0 | BU22: =+IFERROR(VLOOKUP($BU$17,Sheet1!AL4:AO4,3,0),0) -> 0 | BV22: =+IFERROR(VLOOKUP($BV$17,Sheet1!AL4:AO4,3,0),0) -> 0 | BW22: =+IFERROR(VLOOKUP($BW$17,Sheet1!AL4:AO4,3,0),0) -> 0 | BX22: =+IFERROR(VLOOKUP($BX$17,Sheet1!AP4:AS4,3,0),0) -> 0 | BY22: 14 | BZ22: =+IFERROR(VLOOKUP($BZ$17,Sheet1!AX4:BA4,3,0),0) -> 0 | CA22: =+IFERROR(VLOOKUP($CA$17,Sheet1!BB4:BE4,3,0),0) -> 0 | CB22: =+IFERROR(VLOOKUP($CB$17,Sheet1!BF4:BI4,3,0),0) -> 0 | CC22: =+IFERROR(VLOOKUP($CC$17,Sheet1!BJ4:BM4,3,0),0) -> 0 | CD22: =+IFERROR(VLOOKUP($CD$17,Sheet1!BN4:BQ4,3,0),0) -> 0 | CE22: =+IFERROR(VLOOKUP($CE$17,Sheet1!BR4:BU4,3,0),0) -> 0 | CF22: =+IFERROR(VLOOKUP($CF$17,Sheet1!BV4:BY4,3,0),0) -> 0 | CG22: STEEL | CH22: SP0400139 | CI22: CORRUGATED DISPATCH STEEL DRUM 2130 X 890 X 965 | CJ22: =Sheet1!CZ4 -> 2000 | CK22: =28800/2 -> 14400 | CL22: =SUMPRODUCT($N$18:$CF$18,N22:CF22)+CK22 -> 435094 | CM22: =Sheet1!CB4 -> 0 | CN22: =CL22*CM22 -> 0 | CO22: 0.03 | CP22: =CL22*CO22 -> 13052.82 | CQ22: 0 | CR22: =CL22*CQ22 -> 0 | CS22: =CL22+CN22+CP22+CR22 -> 448146.82 | CT22: 0.02 | CU22: =CS22*CT22 -> 8962.9364 | CV22: 0.005 | CW22: =CS22*CV22 -> 2240.7341 | CX22: =Sheet1!CM4 -> 0 | CY22: =CX22*CS22 -> 0 | CZ22: 4
M23: =SUM(M19:M22) -> 4.6465368e+09
E26: Order Quantity | F26: Stnd Length | G26: Truck type | H26: Fare of one truck | I26: No of Drum in one truck | J26: Total length in one Truck | K26: No of Truck | L26: Total Freight | M26: Freight per KM | BA26: CONDUCTOR WEIGHT KG/KM | BB26: DRUM WEIGHT | BY26: CONDUCTOR+DRUM WEIGHT | CG26: TRUCK/TRAILOR WEIGHT
D27: =D19 -> ACSR : DOG CONDUCTOR - 100 SQ. MM. (6/4.72/7/1.57) | E27: =K19 -> 916 | F27: =CJ19/1000 -> 2 | G27: 16 MT | H27: 84250 | I27: 15 | J27: =F27*I27 -> 30 | K27: =ROUNDUP((E27/J27),0) -> 31 | L27: =H27*K27 -> 2611750 | M27: =L27/E27 -> 2851.2555 | N27: =CH19 -> SP0400144 | BA27: =SUM(N19:BY19) -> 398.3 | BB27: 200 | BY27: =((BA27*F27)+BB27) -> 996.6 | CG27: =BY27*I27 -> 14949
D28: =D20 -> ACSR : PANTHER CONDUCTOR - 200 SQ. MM. (30/7/3.00) | E28: =K20 -> 10772 | F28: =CJ20/1000 -> 2 | G28: 16 MT | H28: 84250 | I28: 7 | J28: =F28*I28 -> 14 | K28: =ROUNDUP((E28/J28),0) -> 770 | L28: =H28*K28 -> 64872500 | M28: =L28/E28 -> 6022.3264 | N28: =CH20 -> SP0400152 | BA28: =SUM(N20:BY20) -> 986 | BB28: 150 | BY28: =((BA28*F28)+BB28) -> 2122 | CG28: =BY28*I28 -> 14854
D29: =D21 -> ACSR : ZEBRA CONDUCTOR - 420 SQ. MM. (54/7/3.18) | E29: =K21 -> 1566 | F29: =CJ21/1000 -> 2 | G29: 25 MT TRAILOR | H29: 156000 | I29: 6 | J29: =F29*I29 -> 12 | K29: =ROUNDUP((E29/J29),0) -> 131 | L29: =H29*K29 -> 20436000 | M29: =L29/E29 -> 13049.808 | N29: =CH21 -> SP0400126 | BA29: =SUM(N21:BY21) -> 1634 | BB29: 185 | BY29: =((BA29*F29)+BB29) -> 3453 | CG29: =BY29*I29 -> 20718
D30: =D22 -> ACSR : MOOSE CONDUCTOR - 520 SQ. MM. (54/7/3.53) | E30: =K22 -> 2200 | F30: =CJ22/1000 -> 2 | G30: 25 MT TRAILOR | H30: 156000 | I30: 5 | J30: =F30*I30 -> 10 | K30: =ROUNDUP((E30/J30),0) -> 220 | L30: =H30*K30 -> 34320000 | M30: =L30/E30 -> 15600 | N30: =CH22 -> SP0400139 | BA30: =SUM(N22:BY22) -> 2018 | BB30: 320 | BY30: =((BA30*F30)+BB30) -> 4356 | CG30: =BY30*I30 -> 21780
H32: trailor
G33: GONDAL, GUJARAT-360311 | H33: 165000 | L33: ESTIMATED COST (INCLUDING GST) = | M33: 4311862000
G34: HALDARVA, GUJARAT-392011 | H34: 147000 | L34: OUR COST (INCLUDING GST) = | M34: =M23 -> 4.6465368e+09
G35: average = | H35: =AVERAGE(H33:H34) -> 156000 | L35: DIFF % FROM OUR COST = | M35: =((M34-M33)/M34) -> 0.072026726
H37: 16 mt
G38: GONDAL, GUJARAT-360311 | H38: 92500
G39: HALDARVA, GUJARAT-392011 | H39: 76000
G40: average = | H40: =AVERAGE(H38:H39) -> 84250

Sheet PV AUTO CALCULATION SHEET
A1: GUJARAT ENERGY TRANSMISSION CORPORATION LIMITED
A3: Base Date | B3: 45839
B4: This is the multiplication constant to be adopted for computing price Variation per Km. of the finished goods, which is as under: ACSR Dog Conductor = X = 0.287 ACSR Panther Conductor = X = 0.580 ACSR Zebra Conductor = X = 1.1899 ACSR Moose Conductor = X = 1.464 ACSR Dog Conductor = Y = 0.106 ACSR Panther Conducto = Y = 0.388 ACSR Zebra Conductor = Y = 0.435 ACSR Moose Conductor = Y = 0.534
A8: Item | B8: Calculation part | C8: DI date | D8: Applicable Date | G8: BASE DATE | J8: FACTORS | L8: EX-works rate | M8: PVC of Al | N8: PVC of Fe | O8: PVC per KM | P8: Billing Price/PKM | Q8: VALUE ADDITION CALCULATION
D9: Date | E9: Al | F9: fe | G9: Date | H9: Alo | I9: feo
J10: W | K10: Fe | Q10: ='AUTO CALCULATION SHEET (2)'!N17 -> Alumimium | R10: ='AUTO CALCULATION SHEET (2)'!BA17 -> ACSR CORE WIRE | S10: ='AUTO CALCULATION SHEET (2)'!BB17 -> ACSR DOG STEEL WIRE | T10: ='AUTO CALCULATION SHEET (2)'!BY17 -> Grease | U10: RMC | V10: Drum | W10: RMC+DRUM | X10: VA | Y10: Groos VA% | Z10: Mfg % | AA10: Int % | AB10: Ins% | AC10: Net VA
Q11: 267 | R11: 67 | S11: 82 | T11: 197
A12: ='AUTO CALCULATION SHEET (2)'!D19 -> ACSR : DOG CONDUCTOR - 100 SQ. MM. (6/4.72/7/1.57) | D12: 45839 | E12: 300288 | F12: 173750 | G12: =$B$3 -> 45839 | H12: 300288 | I12: 173750 | J12: 0.287 | K12: 0.106 | L12: ='AUTO CALCULATION SHEET (2)'!E19 -> 98870.988 | M12: =J12*(E12-H12) -> 0 | N12: =K12*(F12-I12) -> 0 | O12: =M12+N12 -> 0 | P12: =L12+O12 -> 98870.988 | Q12: ='AUTO CALCULATION SHEET (2)'!N19 -> 288.3 | R12: ='AUTO CALCULATION SHEET (2)'!BA19 -> 0 | S12: ='AUTO CALCULATION SHEET (2)'!BB19 -> 106 | T12: ='AUTO CALCULATION SHEET (2)'!BY19 -> 4 | U12: =SUMPRODUCT($Q$11:$T$11,Q12:T12) -> 86456.1 | V12: ='AUTO CALCULATION SHEET (2)'!CK19 -> 9000 | W12: =U12+V12 -> 95456.1 | X12: =+P12-W12 -> 3414.8875 | Y12: =X12/W12*100% -> 0.035774429 | AA12: 0.01 | AB12: 0.005 | AC12: =Y12-SUM(Z12:AB12) -> 0.020774429
A13: ='AUTO CALCULATION SHEET (2)'!D20 -> ACSR : PANTHER CONDUCTOR - 200 SQ. MM. (30/7/3.00) | D13: 45839 | E13: 300288 | F13: 157750 | G13: =$B$3 -> 45839 | H13: 300288 | I13: 157750 | J13: 0.58 | K13: 0.388 | L13: ='AUTO CALCULATION SHEET (2)'!E20 -> 198464.11 | M13: =J13*(E13-H13) -> 0 | N13: =K13*(F13-I13) -> 0 | O13: =M13+N13 -> 0 | P13: =L13+O13 -> 198464.11 | Q13: ='AUTO CALCULATION SHEET (2)'!N20 -> 588 | R13: ='AUTO CALCULATION SHEET (2)'!BA20 -> 388 | S13: ='AUTO CALCULATION SHEET (2)'!BB20 -> 0 | T13: ='AUTO CALCULATION SHEET (2)'!BY20 -> 10 | U13: =SUMPRODUCT($Q$11:$T$11,Q13:T13) -> 184962 | V13: ='AUTO CALCULATION SHEET (2)'!CK20 -> 6750 | W13: =U13+V13 -> 191712 | X13: =+P13-W13 -> 6752.108 | Y13: =X13/W13*100% -> 0.035220059 | AA13: 0.01 | AB13: 0.005 | AC13: =Y13-SUM(Z13:AB13) -> 0.020220059
A14: ='AUTO CALCULATION SHEET (2)'!D21 -> ACSR : ZEBRA CONDUCTOR - 420 SQ. MM. (54/7/3.18) | D14: 45839 | E14: 300288 | F14: 157750 | G14: =$B$3 -> 45839 | H14: 300288 | I14: 157750 | J14: 1.1899 | K14: 0.435 | L14: ='AUTO CALCULATION SHEET (2)'!E21 -> 368136.86 | M14: =J14*(E14-H14) -> 0 | N14: =K14*(F14-I14) -> 0 | O14: =M14+N14 -> 0 | P14: =L14+O14 -> 368136.86 | Q14: ='AUTO CALCULATION SHEET (2)'!N21 -> 1186 | R14: ='AUTO CALCULATION SHEET (2)'!BA21 -> 436 | S14: ='AUTO CALCULATION SHEET (2)'!BB21 -> 0 | T14: ='AUTO CALCULATION SHEET (2)'!BY21 -> 12 | U14: =SUMPRODUCT($Q$11:$T$11,Q14:T14) -> 348238 | V14: ='AUTO CALCULATION SHEET (2)'!CK21 -> 8325 | W14: =U14+V14 -> 356563 | X14: =+P14-W14 -> 11573.858 | Y14: =X14/W14*100% -> 0.032459503 | AA14: 0.01 | AB14: 0.005 | AC14: =Y14-SUM(Z14:AB14) -> 0.017459503
A15: ='AUTO CALCULATION SHEET (2)'!D22 -> ACSR : MOOSE CONDUCTOR - 520 SQ. MM. (54/7/3.53) | D15: 45839 | E15: 300288 | F15: 157750 | G15: =$B$3 -> 45839 | H15: 300288 | I15: 157750 | J15: 1.464 | K15: 0.534 | L15: ='AUTO CALCULATION SHEET (2)'!E22 -> 459350.49 | M15: =J15*(E15-H15) -> 0 | N15: =K15*(F15-I15) -> 0 | O15: =M15+N15 -> 0 | P15: =L15+O15 -> 459350.49 | Q15: ='AUTO CALCULATION SHEET (2)'!N22 -> 1467 | R15: ='AUTO CALCULATION SHEET (2)'!BA22 -> 537 | S15: ='AUTO CALCULATION SHEET (2)'!BB22 -> 0 | T15: ='AUTO CALCULATION SHEET (2)'!BY22 -> 14 | U15: =SUMPRODUCT($Q$11:$T$11,Q15:T15) -> 430426 | V15: ='AUTO CALCULATION SHEET (2)'!CK22 -> 14400 | W15: =U15+V15 -> 444826 | X15: =+P15-W15 -> 14524.491 | Y15: =X15/W15*100% -> 0.032652072 | AA15: 0.01 | AB15: 0.005 | AC15: =Y15-SUM(Z15:AB15) -> 0.017652072
Q16: 1

Sheet terms
A1: The quoted prices are on Firm inclusive of packing and forwading but exclusive of GST Statutory levies.
A2: The quoted prices are on VARIABLE basis with PV base Date: DD/MM/YYYY as per "IEEMA", inclusive of packing and forwading but exclusive of GST Statutory levies.
A4: The above prices are quoted on Ex-works basis, where freight will be charged extra.
A5: The above prices are quoted on FOR Destination basis, where freight is included, refer Price offer.
A6: The above prices are quoted on Ex-works+Freight basis.
A8: 20% Advance and Balance against PI (Proforma Invoice) prior to dispatch
A9: 100% against "90 days" LC, where 90 days usance interest will be borne by LPIPL
A10: 100% against "120 days" LC, where 120 days usance interest will be borne by LPIPL
A11: 100% against "45 days" LC, where 45 days usance interest will be borne by LPIPL
A12: 100% against "60 days" LC, where 60 days usance interest will be borne by LPIPL
A13: 100% against "30 days" LC, where 30 days usance interest will be borne by LPIPL
A14: 100% against 60 days PDC from the date of MRC/MRN
... A27: Negotiable
