Workbook

Sheet Sheet1
A1: DOCKET NO. | B1: Base Date | C1: ITEM CODE | D1: PROPOSE ERP ITEM NAME | E1: Propose Drum Type | F1: Insulation Screening(Metallic) | G1: RM Rate(Insulation Screening(Metallic)) | H1: Weight (Insulation Screening (Metallic)) | I1: Cost Insulation Screening(Metallic) | J1: Conductor | K1: RM Rate(Conductor) | L1: Weight(Conductor) | M1: Cost(Conductor) | N1: AL ALLOY | O1: RM Rate(AL Alloy) | P1: Weight(Al Alloy) | Q1: Cost(AL Alloy) | R1: Insulation Screening(Non-Metallic) | S1: RM Rate(Insulation Screening(Non-Metallic)) | T1: Weight(Insulation Screening(Non-Metallic) | U1: Cost(Insulation Screening(Non-Metallic) | V1: Insulation | W1: RM Rate(Insulation) | X1: Weight(Insulation) | Y1: Cost(Insulation) | Z1: Poly Tape | AA1: RM Rate(Poly Tape) | AB1: Weight(Poly Tape) | AC1: Cost(Poly Tape) | AD1: Inner Sheath | AE1: RM Rate(Inner Sheath) | AF1: Weight(Inner Sheath) | AG1: Cost(Inner Sheath) | AH1: Armouring | AI1: RM Rate(Armouring) | AJ1: Weight(Armouring) | AK1: Cost(Armouring) | AL1: Outer Sheath | AM1: RM Rate(Outer Sheath) | AN1: Weight(Outer Sheath) | AO1: Cost(Outer Sheath) | AP1: Filler | AQ1: RM Rate(Filler) | AR1: Weight(Filler) | AS1: Cost(Filler) | AT1: Grease | AU1: RM Rate(Grease) | AV1: Weight(Grease) | AW1: Cost(Grease) | AX1: Water Swellable Tape | AY1: RM Rate(Water Swellable Tape) | AZ1: Weight(Water Swellable Tape) | BA1: Cost(Water Swellable Tape) | BB1: Semi Conducting Water Swellable Tape | BC1: RM Rate(Semi Conducting Water Swellable Tape) | BD1: Weight(Semi Conducting Water Swellable Tape) | BE1: Cost(Semi Conducting Water Swellable Tape) | BF1: Semicon Tape | BG1: RM Rate(Semicon Tape) | BH1: Weight(Semicon Tape) | BI1: Cost(Semicon Tape) | BJ1: Glass Fiber Tape | BK1: RM Rate(Glass Fiber Tape) | BL1: Weight(Glass Fiber Tape) | BM1: Cost(Glass Fiber Tape) | BN1: Copper Wire 0.8MM | BO1: RM Rate(Copper Wire 0.8MM) | BP1: Weight(Copper Wire 0.8MM) | BQ1: Cost(Copper Wire 0.8MM) | BR1: Rubberized Cotton Tape | BS1: RM Rate(Rubberized Cotton Tape) | BT1: Weight(Rubberized Cotton Tape) | BU1: Cost(Rubberized Cotton Tape) | BV1: Water Tight Compound | BW1: RM Rate(Water Tight Compound) | BX1: Weight(Water Tight Compound) | BY1: Cost(Water Tight Compound) | BZ1: Drum Cost Per KM | CA1: Total RM Cost | CB1: FIRM % | CC1: Firm Value | CD1: MFG% | CE1: MFG Value | CF1: PROF% | CG1: Profit Value | CH1: 1st EX-Works | CI1: Intt % | CJ1: Intt Value | CK1: insp% | CL1: Insp Value | CM1: EX-Works Per KM | CN1: Freight Per KM | CO1: Price Including Freight Per KM | CP1: GST % | CQ1: GST Value | CR1: Price Including GST & Freight Per KM | CS1: QTY | CT1: Unit | CU1: Total Price Of Full QTY(Including Freight&GST) | CV1: DRUM CODE | CW1: DRUM SIZE (FxbXtx Ft) | CX1: Party Standard Length(MTR)
A2: ENQ-13992-22-23 | B2: 45548 | C2: FA1300091 | D2: 3 CORE X 300 SQ. MM. AL/ARM - WIRE (XLPE) - 11 KV | E2: STEEL | F2: Copper Tape - 0.045 mm | G2: 936.8 | H2: 122 | I2: 114289.6 | J2: Alumimium | K2: 238 | L2: 2430 | M2: 578340 | P2: 0 | R2: Extruded Semiconductive | S2: 170 | T2: 337 | U2: 57290 | V2: HT-XLPE | W2: 142 | X2: 802 | Y2: 113884 | AB2: 0 | AD2: PVC Type ST-2-PRESSURE EXTRUDED | AE2: 88.86 | AF2: 277 | AG2: 24614.22 | AH2: Galvanised Steel Round Wire | AI2: 85.32 | AJ2: 3753 | AK2: 320205.96 | AL2: FRLSH PVC Type ST-2 | AM2: 90.86 | AN2: 1120 | AO2: 101763.2 | AP2: Polypropylene Filler | AR2: 1258 | AV2: 0 | AX2: Water swellable Tape | AY2: 420 | AZ2: 0 | BA2: 0 | BB2: Semi conducting Water Swellable tape | BC2: 430 | BD2: 115 | BE2: 49450 | BH2: 34 | BL2: 0 | BP2: 0 | BR2: RUBBERIZED COTTON TAPE | BS2: 450 | BT2: 0 | BU2: 0 | BX2: 0 | BZ2: 171000 | CA2: 1530837 | CH2: 1530837 | CM2: 1530837 | CO2: 1530837 | CP2: 0.18 | CQ2: 275550.66 | CR2: 1806387.6 | CS2: 19 | CT2: KMS | CU2: 34321365 | CV2: SP0400136 | CW2: CORRUGATED DISPATCH STEEL DRUM 2200 X 1300 X 1200 MM | CX2: 250
A3: ENQ-13992-22-23 | B3: 45548 | C3: FA1300090 | D3: 3 CORE X 185 SQ. MM AL/ARM - WIRE (XLPE) - 11 KV | E3: STEEL | F3: Copper Tape - 0.045 mm | G3: 936.8 | H3: 105 | I3: 98364 | J3: Alumimium | K3: 238 | L3: 1499 | M3: 356762 | P3: 0 | R3: Extruded Semiconductive | S3: 170 | T3: 276 | U3: 46920 | V3: HT-XLPE | W3: 142 | X3: 663 | Y3: 94146 | AB3: 0 | AD3: PVC Type ST-2-PRESSURE EXTRUDED | AE3: 88.86 | AF3: 237 | AG3: 21059.82 | AH3: Galvanised Steel Round Wire | AI3: 85.32 | AJ3: 3244 | AK3: 276778.08 | AL3: FRLSH PVC Type ST-2 | AM3: 90.86 | AN3: 862 | AO3: 78321.32 | AP3: Polypropylene Filler | AR3: 914 | AV3: 0 | AX3: Water swellable Tape | AY3: 420 | AZ3: 0 | BA3: 0 | BB3: Semi conducting Water Swellable tape | BC3: 430 | BD3: 0 | BE3: 0 | BH3: 0 | BL3: 0 | BP3: 0 | BR3: RUBBERIZED COTTON TAPE | BS3: 450 | BT3: 0 | BU3: 0 | BX3: 0 | BZ3: 76000 | CA3: 1048351.2 | CH3: 1048351.2 | CM3: 1048351.2 | CO3: 1048351.2 | CP3: 0.18 | CQ3: 188703.22 | CR3: 1237054.4 | CS3: 27 | CT3: KMS | CU3: 33400470 | CV3: SP0400111 | CW3: CORRUGATED DISPATCH STEEL DRUM 1900 X 1000 X 1000 MM | CX3: 250
A4: ENQ-13992-22-23 | B4: 45548 | C4: FA1300176 | D4: 3 CORE X 150 SQ. MM. AL/ARM - WIRE (XLPE) - 11 KV | E4: STEEL | F4: Copper Tape - 0.045 mm | G4: 936.8 | H4: 99 | I4: 92743.2 | J4: Alumimium | K4: 238 | L4: 1215 | M4: 289170 | P4: 0 | R4: Extruded Semiconductive | S4: 170 | T4: 246 | U4: 41820 | V4: HT-XLPE | W4: 142 | X4: 620 | Y4: 88040 | AB4: 0 | AD4: PVC Type ST-2-PRESSURE EXTRUDED | AE4: 88.86 | AF4: 200 | AG4: 17772 | AH4: Galvanised Steel Round Wire | AI4: 85.32 | AJ4: 2404 | AK4: 205109.28 | AL4: FRLSH PVC Type ST-2 | AM4: 90.86 | AN4: 755 | AO4: 68599.3 | AP4: Polypropylene Filler | AR4: 809 | AV4: 0 | AX4: Water swellable Tape | AY4: 420 | AZ4: 0 | BA4: 0 | BB4: Semi conducting Water Swellable tape | BC4: 430 | BD4: 162 | BE4: 69660 | BH4: 0 | BL4: 0 | BP4: 0 | BR4: RUBBERIZED COTTON TAPE | BS4: 450 | BT4: 0 | BU4: 0 | BX4: 0 | BZ4: 108300 | CA4: 981213.78 | CH4: 981213.78 | CM4: 981213.78 | CO4: 981213.78 | CP4: 0.18 | CQ4: 176618.48 | CR4: 1157832.3 | CS4: 2 | CT4: KMS | CU4: 2315665 | CV4: SP0400111 | CW4: CORRUGATED DISPATCH STEEL DRUM 1900 X 1000 X 1000 MM | CX4: 250
A5: ENQ-13992-22-23 | B5: 45548 | C5: FA1300098 | D5: 3 CORE X 95 SQ. MM. AL/ARM - WIRE (XLPE) - 11 KV | E5: STEEL | F5: Copper Tape - 0.045 mm | G5: 936.8 | H5: 86 | I5: 80564.8 | J5: Alumimium | K5: 238 | L5: 770 | M5: 183260 | P5: 0 | R5: Extruded Semiconductive | S5: 170 | T5: 205 | U5: 34850 | V5: HT-XLPE | W5: 142 | X5: 520 | Y5: 73840 | AB5: 0 | AD5: PVC Type ST-2-PRESSURE EXTRUDED | AE5: 88.86 | AF5: 173 | AG5: 15372.78 | AH5: Galvanised Steel Round Wire | AI5: 85.32 | AJ5: 2124 | AK5: 181219.68 | AL5: FRLSH PVC Type ST-2 | AM5: 90.86 | AN5: 635 | AO5: 57696.1 | AP5: Polypropylene Filler | AR5: 613 | AV5: 0 | AX5: Water swellable Tape | AY5: 420 | AZ5: 75 | BA5: 31500 | BB5: Semi conducting Water Swellable tape | BC5: 430 | BD5: 0 | BE5: 0 | BH5: 45 | BL5: 0 | BP5: 0 | BR5: RUBBERIZED COTTON TAPE | BS5: 450 | BT5: 35 | BU5: 15750 | BX5: 0 | BZ5: 95000 | CA5: 769053.36 | CH5: 769053.36 | CM5: 769053.36 | CO5: 769053.36 | CP5: 0.18 | CQ5: 138429.6 | CR5: 907482.96 | CS5: 20 | CT5: KMS | CU5: 18149659 | CV5: SP0400118 | CW5: CORRUGATED DISPATCH STEEL DRUM 1700 X 1000 X 1200 | CX5: 250
A6: ENQ-13992-22-23 | B6: 45548 | C6: FA1300066 | D6: 1 CORE X 1000 SQ. MM. AL/ARM (XLPE) - 11 KV | E6: STEEL | F6: Copper Tape - 0.045 mm | G6: 936.8 | H6: 66 | I6: 61828.8 | J6: Alumimium | K6: 238 | L6: 2732 | M6: 650216 | P6: 0 | R6: Extruded Semiconductive | S6: 170 | T6: 200 | U6: 34000 | V6: HT-XLPE | W6: 142 | X6: 465 | Y6: 66030 | Z6: POLY TAPE | AA6: 118 | AB6: 0 | AC6: 0 | AD6: PVC Type ST-2 | AE6: 64.18 | AF6: 185 | AG6: 11873.3 | AH6: Aluminium Round Wire | AI6: 243 | AJ6: 773 | AK6: 187839 | AL6: FRLSH PVC Type ST-2 | AM6: 90.86 | AN6: 655 | AO6: 59513.3 | AR6: 0 | AV6: 0 | AX6: Water swellable Tape | AY6: 420 | AZ6: 0 | BA6: 0 | BB6: Semi conducting Water Swellable tape | BC6: 430 | BD6: 99 | BE6: 42570 | BH6: 59 | BL6: 0 | BP6: 0 | BR6: RUBBERIZED COTTON TAPE | BS6: 450 | BT6: 52 | BU6: 23400 | BX6: 0 | BZ6: 66500 | CA6: 1203770.4 | CH6: 1203770.4 | CM6: 1203770.4 | CO6: 1203770.4 | CP6: 0.18 | CQ6: 216678.67 | CR6: 1420449.1 | CS6: 20 | CT6: KMS | CU6: 28408981 | CV6: SP0400107 | CW6: CORRUGATED DISPATCH STEEL DRUM 2150 X 1080 X 1240 MM | CX6: 500
A7: ENQ-13992-22-23 | B7: 45548 | C7: FA1300016 | D7: 1 CORE X 630 SQ. MM. AL/ARM (XLPE) - 11 KV | E7: STEEL | F7: Copper Tape - 0.045 mm | G7: 936.8 | H7: 54 | I7: 50587.2 | J7: Alumimium | K7: 238 | L7: 1701 | M7: 404838 | P7: 0 | R7: Extruded Semiconductive | S7: 170 | T7: 150 | U7: 25500 | V7: HT-XLPE | W7: 142 | X7: 374 | Y7: 53108 | Z7: POLY TAPE | AA7: 118 | AB7: 0 | AC7: 0 | AD7: PVC Type ST-2 | AE7: 64.18 | AF7: 134 | AG7: 8600.12 | AH7: Aluminium Round Wire | AI7: 243 | AJ7: 511 | AK7: 124173 | AL7: FRLSH PVC Type ST-2 | AM7: 90.86 | AN7: 472 | AO7: 42885.92 | AR7: 0 | AV7: 0 | AX7: Water swellable Tape | AY7: 420 | AZ7: 0 | BA7: 0 | BB7: Semi conducting Water Swellable tape | BC7: 430 | BD7: 70 | BE7: 30100 | BH7: 0 | BL7: 0 | BP7: 0 | BR7: RUBBERIZED COTTON TAPE | BS7: 450 | BT7: 0 | BU7: 0 | BX7: 0 | BZ7: 48450 | CA7: 788242.24 | CH7: 788242.24 | CM7: 788242.24 | CO7: 788242.24 | CP7: 0.18 | CQ7: 141883.6 | CR7: 930125.84 | CS7: 3 | CT7: KMS | CU7: 2790378 | CV7: SP0400091 | CW7: CORRUGATED DISPATCH STEEL DRUM 1800 X 900 X 1000 | CX7: 500
A8: ENQ-13992-22-23 | B8: 45548 | C8: FA1300047 | D8: 1 CORE X 400 SQ. MM. AL/ARM (XLPE) - 11 KV | E8: STEEL | F8: Copper Tape - 0.045 mm | G8: 936.8 | H8: 45 | I8: 42156 | J8: Alumimium | K8: 238 | L8: 1080 | M8: 257040 | P8: 0 | R8: Extruded Semiconductive | S8: 170 | T8: 122 | U8: 20740 | V8: HT-XLPE | W8: 142 | X8: 305 | Y8: 43310 | AB8: 0 | AD8: PVC Type ST-2 | AE8: 64.18 | AF8: 96 | AG8: 6161.28 | AH8: Aluminium Round Wire | AI8: 243 | AJ8: 423 | AK8: 102789 | AL8: FRLSH PVC Type ST-2 | AM8: 90.86 | AN8: 376 | AO8: 34163.36 | AR8: 0 | AV8: 0 | AX8: Water swellable Tape | AY8: 420 | AZ8: 0 | BA8: 0 | BB8: Semi conducting Water Swellable tape | BC8: 430 | BD8: 54 | BE8: 23220 | BH8: 0 | BL8: 0 | BP8: 0 | BT8: 0 | BX8: 0 | BZ8: 34200 | CA8: 563779.64 | CH8: 563779.64 | CM8: 563779.64 | CO8: 563779.64 | CP8: 0.18 | CQ8: 101480.34 | CR8: 665259.98 | CS8: 1 | CT8: KMS | CU8: 665260 | CV8: SP0400125 | CW8: CORRUGATED DISPATCH STEEL DRUM 1600 X 700 X 915 MM | CX8: 500
A9: ENQ-13992-22-23 | B9: 45548 | C9: FA1300009 | D9: 1 CORE X 300 SQ. MM. AL./ARM (XLPE) - 11 KV | E9: STEEL | F9: Copper Tape - 0.045 mm | G9: 936.8 | H9: 41 | I9: 38408.8 | J9: Alumimium | K9: 238 | L9: 810 | M9: 192780 | P9: 0 | R9: Extruded Semiconductive | S9: 170 | T9: 112 | U9: 19040 | V9: HT-XLPE | W9: 142 | X9: 267 | Y9: 37914 | Z9: POLY TAPE | AA9: 118 | AB9: 0 | AC9: 0 | AD9: PVC Type ST-2 | AE9: 64.18 | AF9: 87 | AG9: 5583.66 | AH9: Aluminium Round Wire | AI9: 243 | AJ9: 388 | AK9: 94284 | AL9: FRLSH PVC Type ST-2 | AM9: 90.86 | AN9: 318 | AO9: 28893.48 | AR9: 0 | AV9: 0 | AX9: Water swellable Tape | AY9: 420 | AZ9: 0 | BA9: 0 | BB9: Semi conducting Water Swellable tape | BC9: 430 | BD9: 38 | BE9: 16340 | BH9: 0 | BL9: 0 | BP9: 0 | BR9: RUBBERIZED COTTON TAPE | BS9: 450 | BT9: 0 | BU9: 0 | BX9: 0 | BZ9: 27000 | CA9: 460243.94 | CH9: 460243.94 | CM9: 460243.94 | CO9: 460243.94 | CP9: 0.18 | CQ9: 82843.91 | CR9: 543087.85 | CS9: 2 | CT9: KMS | CU9: 1086176 | CV9: SP0400152 | CW9: CORRUGATED DISPATCH STEEL DRUM 1500 X 800 X 915 | CX9: 500
A10: ENQ-13992-22-23 | B10: 45548 | C10: FA1300020 | D10: 1 CORE X 185 SQ. MM. AL./ARM (XLPE) - 11 KV | E10: STEEL | F10: Copper Tape - 0.045 mm | G10: 936.8 | H10: 35 | I10: 32788 | J10: Alumimium | K10: 238 | L10: 500 | M10: 119000 | P10: 0 | R10: Extruded Semiconductive | S10: 170 | T10: 92 | U10: 15640 | V10: HT-XLPE | W10: 142 | X10: 221 | Y10: 31382 | Z10: POLY TAPE | AA10: 118 | AB10: 0 | AC10: 0 | AD10: PVC Type ST-2 | AE10: 64.18 | AF10: 75 | AG10: 4813.5 | AH10: Aluminium Round Wire | AI10: 243 | AJ10: 335 | AK10: 81405 | AL10: FRLSH PVC Type ST-2 | AM10: 90.86 | AN10: 280 | AO10: 25440.8 | AR10: 0 | AV10: 0 | AX10: Water swellable Tape | AY10: 420 | AZ10: 0 | BA10: 0 | BB10: Semi conducting Water Swellable tape | BC10: 430 | BD10: 0 | BE10: 0 | BH10: 0 | BL10: 0 | BP10: 0 | BR10: RUBBERIZED COTTON TAPE | BS10: 450 | BT10: 0 | BU10: 0 | BX10: 0 | BZ10: 41800 | CA10: 352269.3 | CH10: 352269.3 | CM10: 352269.3 | CO10: 352269.3 | CP10: 0.18 | CQ10: 63408.47 | CR10: 415677.77 | CS10: 4 | CT10: KMS | CU10: 1662711 | CV10: SP0400125 | CW10: CORRUGATED DISPATCH STEEL DRUM 1600 X 700 X 915 MM | CX10: 500
A11: ENQ-13992-22-23 | B11: 45548 | C11: FA1300075 | D11: 1 CORE X 95 SQ. MM. AL.ARM (XLPE) - 11 KV | E11: WOOD | F11: Copper Tape - 0.03 mm | G11: 936.8 | H11: 21 | I11: 19672.8 | J11: Alumimium | K11: 238 | L11: 256 | M11: 60928 | P11: 0 | R11: Extruded Semiconductive | S11: 170 | T11: 68 | U11: 11560 | V11: HT-XLPE | W11: 142 | X11: 173 | Y11: 24566 | AB11: 0 | AD11: PVC Type ST-2 | AE11: 64.18 | AF11: 51 | AG11: 3273.18 | AH11: Aluminium Round Wire | AI11: 243 | AJ11: 220 | AK11: 53460 | AL11: PVC Type ST-2 | AM11: 64.18 | AN11: 205 | AO11: 13156.9 | AR11: 0 | AV11: 0 | AZ11: 0 | BD11: 0 | BH11: 0 | BL11: 0 | BP11: 0 | BT11: 0 | BX11: 0 | BZ11: 7317.08 | CA11: 193933.96 | CH11: 193933.96 | CM11: 193933.96 | CO11: 193933.96 | CP11: 0.18 | CQ11: 34908.11 | CR11: 228842.07 | CS11: 1 | CT11: KMS | CU11: 228842 | CV11: MD0100015 | CW11: DRUM - 48 X 20 X 28 X 2.25 - RDSO | CX11: 500

Sheet AUTO CALCULATION SHEET (2)
A2: TPCODL TPNODL TPSODL TPWODL
A4: TENDER SPECIFICATION NO () | B4: TPCODL/CCG/24-25/1000000981
A5: TENDER DESCRIPTION () | B5: One Year Rate Contract for Supplying 11 KV HT Cables at TPCODL, TPSODL & TPNODL
A6: Last Date & Time of Submission () | B6: 16.09.2024, 17:00 Hours
A7: REVERSE AUCTION | B7: No of bidders allowed to participate in RA process shall be: Total No of bidders on whom tender would be split PLUS 2 more bidders Illustrative example: Total no of qualified bidders is 10 & tender needs to split amongst 4 bidders. PLUS 2 means (04 + 02 = 06) means lowest 6 bidders i.e., L1 to L6 bidders would be allowed in the RA process. Balance, H1 to H4 bidders would not be allowed in the RA process. In case – Total no of qualified bidders is equal to or less than the PLUS 2 number, all qualified bidders shall be allowed in the RA process.
A8: Price () | B8: Prices shall be firm till the validity of the contract.
A9: Validity () | B9: Bids shall remain valid for 180 days from the due date of submission of the bid. Notwithstanding clause above, CCG may solicit the Bidder’s consent to an extension of the Period of Bid Validity. The request and responses thereto shall be made in writing
A10: Delivery Period () | B10: Delivery Period shall be 60 Days from date of receipt of release order / CAT-A issuance, whichever is later.
A11: Payment Terms () | B11: 100% payment within 60 days of submission of error-free Invoice complete in all respects. However, for MSME the payment cycle shall be 45 days.
A12: Standard length () | B12: Cable length on one drum shall be 250 meters max. +/- 5%. (As per PO Terms.) The cable shall be supplied in continuous standard length of 250 (3 cores) & 500 (Single core) running meters with +/- 5% tolerance.
A13: Packing () | B13: Steel drums shall be provided. Drum shall be free from sharp edges and visual defect. Stencil plate on one flange side of the drum and laminated paper sheet on other side flange of drum.
A14: Technical Specification
N16: =Sheet1!J1 -> Conductor | S16: AL ALLOY | U16: Insulation Screening (Metallic) | AC16: Insulation Screening (Non-Metallic) | AE16: Insulation | AK16: POLY TAPE | AL16: Inner Sheath | AS16: Armouring | BC16: Outer Sheath | BE16: Rs 20/kg over for lead free ATR | BM16: FILLER | BN16: GREASE | BO16: Water swellable Tape | BP16: Semi conducting Water Swellable tape | BQ16: SEMICON TAPE | BR16: GLASS FIBER TAPE | BS16: COPPER WIRE 0.8 MM | BT16: RUBBERIZED COTTON TAPE | BU16: Water Tight Compound | BZ16: DRUM COST PER KM | CA16: TOTAL RM COST | CB16: EXTRA CONSUMPTION | CC16: EXTRA CONSUMPTION VALUE
A17: DOCKET NO. | B17: =Sheet1!B1 -> Base Date | C17: ITEM CODE | D17: PROPOSE ERP ITEM NAME | E17: EX-WORKS (PER KM) | F17: FREIGHT PER KM | G17: PRICE INCLUDING FREIGHT (PER KM) | H17: GST % | I17: GST VALUE | J17: PRICE INCLUDING GST & FREIGHT (PER KM) | K17: QTY | L17: Unit | M17: TOTAL PRICE OF FULL QTY (INCLUDING FRIGHT & GST) | N17: Alumimium | O17: Alumimium ALLOY | P17: Copper | Q17: Flexible Copper | R17: Galvanized steel wire | S17: Alumimium | T17: Alumimium ALLOY | U17: Coper tape - 0.1 mm | V17: Copper Tape - 0.03 mm | W17: Copper Tape - 0.035 mm | X17: Copper Tape - 0.04 mm | Y17: Copper Tape - 0.045 mm | Z17: Copper Tape - 0.050 mm | AA17: Copper Tape - 0.060 mm | AB17: Copper Tape - 0.075 mm(DOUBLE) | AC17: Extruded semiconductive | AD17: Extruded Semiconductive(Stripable) | AE17: HT-XLPE | AF17: LT-XLPE | AG17: TR XLPE | AH17: Type A PVC | AI17: Type C PVC (HR) | AJ17: XLPE | AK17: POLY TAPE | AL17: FR PVC Type ST-1 | AM17: FR PVC Type ST-2 | AN17: FRLSH PVC Type ST-2 | AO17: PVC Type ST-1 | AP17: PVC Type ST-1-PRESSURE EXTRUDED | AQ17: PVC Type ST-2 | AR17: PVC Type ST-2-PRESSURE EXTRUDED | AS17: ACSR CORE WIRE | AT17: ACSR DOG STEEL WIRE | AU17: Aluminium Flat Strip | AV17: Aluminium Round Wire | AW17: Double Steel Tape | AX17: Galvanised Steel Flat Strip | AY17: Galvanised Steel Flat Strip (Double) | AZ17: Galvanised Steel Flat Strip-B | BA17: Galvanised Steel Round Wire | BB17: Galvanised Steel Round Wire (Double) | BC17: FR PVC Type ST-1 | BD17: FR PVC Type ST-2 | BE17: FRLSH PVC Type ST-2 ATR | BF17: FRLSH PVC Type ST-2 | BG17: PP FILLER | BH17: PE, ST-7 | BI17: PVC Type ST-1 | BJ17: PVC Type ST-2 | BK17: PVC Type ST-2-PRESSURE EXTRUDED | BL17: UV & Track Resistant XLPE | BM17: FILLER | BN17: NCWBT | BO17: Water swellable Tape | BP17: Semi conducting Water Swellable tape | BQ17: SEMICON TAPE | BR17: GLASS FIBER TAPE | BS17: COPPER WIRE 0.8 MM | BT17: RUBBERIZED COTTON TAPE | BU17: Water Tight Compound | BV17: =Sheet1!E1 -> Propose Drum Type | BW17: =Sheet1!CV1 -> DRUM CODE | BX17: =Sheet1!CW1 -> DRUM SIZE (FxbXtx Ft) | BY17: =Sheet1!CX1 -> Party Standard Length(MTR) | CB17: Consider 1 % extra cost on total cable for special process for all cable. | CD17: MFG% | CE17: MFG VALUE | CF17: PROF% | CG17: PROFIT VALUE | CH17: 1ST EX-WORKS | CI17: Intt % | CJ17: INTT VALUE | CK17: insp% | CL17: INSP VALUE
N18: =+IFERROR(VLOOKUP($N$17,Sheet1!J:L,2,0),0) -> 238 | O18: =+IFERROR(VLOOKUP($O$17,Sheet1!J:L,2,0),0) -> 0 | P18: =+IFERROR(VLOOKUP($P$17,Sheet1!J:M,2,0),0) -> 0 | Q18: =+IFERROR(VLOOKUP($Q$17,Sheet1!J:M,2,0),0) -> 0 | R18: =+IFERROR(VLOOKUP($R$17,Sheet1!J:M,2,0),0) -> 0 | S18: =+IFERROR(VLOOKUP($S$17,Sheet1!N:Q,2,0),0) -> 0 | T18: =+IFERROR(VLOOKUP($T$17,Sheet1!N:O,2,0),0) -> 0 | U18: =+IFERROR(VLOOKUP($U$17,Sheet1!F:I,2,0),0) -> 0 | W18: =+IFERROR(VLOOKUP($W$17,Sheet1!F:I,2,0),0) -> 0 | X18: =+IFERROR(VLOOKUP($X$17,Sheet1!F:I,2,0),0) -> 0 | Y18: 937 | Z18: =+IFERROR(VLOOKUP($Z$17,Sheet1!F:I,2,0),0) -> 0 | AA18: =+IFERROR(VLOOKUP($AA$17,Sheet1!F:I,2,0),0) -> 0 | AB18: =+IFERROR(VLOOKUP($AB$17,Sheet1!F:I,2,0),0) -> 0 | AC18: =+IFERROR(VLOOKUP($AC$17,Sheet1!R:U,2,0),0) -> 170 | AD18: =+IFERROR(VLOOKUP($AD$17,Sheet1!R:U,2,0),0) -> 0 | AE18: =+IFERROR(VLOOKUP($AE$17,Sheet1!V:Y,2,0),0) -> 142 | AF18: =+IFERROR(VLOOKUP($AF$17,Sheet1!V:Y,2,0),0) -> 0 | AG18: =+IFERROR(VLOOKUP($AG$17,Sheet1!V:Y,2,0),0) -> 0 | AH18: =+IFERROR(VLOOKUP($AH$17,Sheet1!V:Y,2,0),0) -> 0 | AI18: =+IFERROR(VLOOKUP($AI$17,Sheet1!V:Y,2,0),0) -> 0 | AJ18: =+IFERROR(VLOOKUP($AJ$17,Sheet1!V:Y,2,0),0) -> 0 | AK18: =+IFERROR(VLOOKUP($AK$17,Sheet1!Z2:AA840,2,0),0) -> 118 | AL18: =+IFERROR(VLOOKUP($AL$17,Sheet1!AD2:AG840,2,0),0) -> 0 | AM18: =+IFERROR(VLOOKUP($AM$17,Sheet1!AD2:AG840,2,0),0) -> 0 | AN18: =+IFERROR(VLOOKUP($AN$17,Sheet1!AD2:AG840,2,0),0) -> 0 | AO18: =+IFERROR(VLOOKUP($AO$17,Sheet1!AD2:AG840,2,0),0) -> 0 | AP18: =+IFERROR(VLOOKUP($AP$17,Sheet1!AD2:AG840,2,0),0) -> 0 | AQ18: 64 | AR18: 89 | AS18: =+IFERROR(VLOOKUP($AS$17,Sheet1!AH2:AK840,2,0),0) -> 0 | AT18: =+IFERROR(VLOOKUP($AT$17,Sheet1!AH2:AK840,2,0),0) -> 0 | AU18: =+IFERROR(VLOOKUP($AU$17,Sheet1!AH2:AK840,2,0),0) -> 0 | AV18: =+IFERROR(VLOOKUP($AV$17,Sheet1!AH2:AK840,2,0),0) -> 243 | AW18: =+IFERROR(VLOOKUP($AW$17,Sheet1!AH2:AK840,2,0),0) -> 0 | AX18: =+IFERROR(VLOOKUP($AX$17,Sheet1!AH2:AK840,2,0),0) -> 0 | AY18: =+IFERROR(VLOOKUP($AY$17,Sheet1!AH2:AK840,2,0),0) -> 0 | AZ18: =+IFERROR(VLOOKUP($AZ$17,Sheet1!AH2:AK840,2,0),0) -> 0 | BA18: 85 | BB18: =+IFERROR(VLOOKUP($BB$17,Sheet1!AH2:AK840,2,0),0) -> 0 | BC18: =+IFERROR(VLOOKUP($BC$17,Sheet1!AL2:AO840,2,0),0) -> 0 | BD18: =+IFERROR(VLOOKUP($BD$17,Sheet1!AL2:AO840,2,0),0) -> 0 | BE18: =91+20 -> 111 | BF18: 91 | BG18: 64 | BH18: =+IFERROR(VLOOKUP($BH$17,Sheet1!AL2:AO840,2,0),0) -> 0 | BI18: =+IFERROR(VLOOKUP($BI$17,Sheet1!AL2:AO840,2,0),0) -> 0 | BK18: =+IFERROR(VLOOKUP($BK$17,Sheet1!AL2:AO840,2,0),0) -> 0 | BL18: =+IFERROR(VLOOKUP($BL$17,Sheet1!AL2:AO840,2,0),0) -> 0 | BM18: =+IFERROR(VLOOKUP($BM$17,Sheet1!AP2:AS840,2,0),0) -> 0 | BN18: 340 | BP18: =+IFERROR(VLOOKUP($BP$17,Sheet1!BB2:BE840,2,0),0) -> 430 | BQ18: =+IFERROR(VLOOKUP($BQ$17,Sheet1!BF2:BI840,2,0),0) -> 0 | BR18: =+IFERROR(VLOOKUP($BR$17,Sheet1!BJ2:BM840,2,0),0) -> 0 | BS18: =+IFERROR(VLOOKUP($BS$17,Sheet1!BN2:BQ840,2,0),0) -> 0 | BT18: =+IFERROR(VLOOKUP($BT$17,Sheet1!BR2:BU840,2,0),0) -> 450 | BU18: =+IFERROR(VLOOKUP($BU$17,Sheet1!BV2:BY840,2,0),0) -> 0
A19: =Sheet1!A2 -> ENQ-13992-22-23 | B19: =Sheet1!B2 -> 45548 | C19: =Sheet1!C2 -> FA1300091 | D19: =Sheet1!D2 -> 3 CORE X 300 SQ. MM. AL/ARM - WIRE (XLPE) - 11 KV | E19: =CH19+CJ19+CL19 -> 2052866.7 | F19: =ROUNDUP(M31,0) -> 47895 | G19: =E19+F19 -> 2100761.7 | H19: =Sheet1!CP2 -> 0.18 | I19: =G19*H19 -> 378137.11 | J19: =G19+I19 -> 2478898.8 | K19: =Sheet1!CS2 -> 19 | L19: =Sheet1!CT2 -> KMS | M19: =J19*K19 -> 47099078 | N19: =+IFERROR(VLOOKUP($N$17,Sheet1!J2:L2,3,0),0) -> 2430 | O19: =+IFERROR(VLOOKUP($O$17,Sheet1!J2:L2,3,0),0) -> 0 | P19: =+IFERROR(VLOOKUP($P$17,Sheet1!J2:M2,3,0),0) -> 0 | Q19: =+IFERROR(VLOOKUP($Q$17,Sheet1!J2:M2,3,0),0) -> 0 | R19: =+IFERROR(VLOOKUP($R$17,Sheet1!J2:M2,3,0),0) -> 0 | S19: =+IFERROR(VLOOKUP($S$17,Sheet1!N2:Q2,3,0),0) -> 0 | T19: =+IFERROR(VLOOKUP($T$17,Sheet1!N2:Q2,3,0),0) -> 0 | U19: =+IFERROR(VLOOKUP($U$17,Sheet1!F2:I2,3,0),0) -> 0 | V19: =+IFERROR(VLOOKUP($V$17,Sheet1!F2:I2,3,0),0) -> 0 | W19: =+IFERROR(VLOOKUP($W$17,Sheet1!F2:I2,3,0),0) -> 0 | X19: =+IFERROR(VLOOKUP($X$17,Sheet1!F2:I2,3,0),0) -> 0 | Y19: 144 | Z19: =+IFERROR(VLOOKUP($Z$17,Sheet1!F2:I2,3,0),0) -> 0 | AA19: =+IFERROR(VLOOKUP($AA$17,Sheet1!F2:I2,3,0),0) -> 0 | AB19: =+IFERROR(VLOOKUP($AB$17,Sheet1!F2:I2,3,0),0) -> 0 | AC19: 370 | AD19: =+IFERROR(VLOOKUP($AD$17,Sheet1!R2:U2,2,0),0) -> 0 | AE19: 838 | AF19: =+IFERROR(VLOOKUP($AF$17,Sheet1!V2:Y2,3,0),0) -> 0 | AG19: =+IFERROR(VLOOKUP($AG$17,Sheet1!V2:Y2,3,0),0) -> 0 | AH19: =+IFERROR(VLOOKUP($AH$17,Sheet1!V2:Y2,3,0),0) -> 0 | AI19: =+IFERROR(VLOOKUP($AI$17,Sheet1!V2:Y2,3,0),0) -> 0 | AJ19: =+IFERROR(VLOOKUP($AJ$17,Sheet1!V2:Y2,3,0),0) -> 0 | AK19: =+IFERROR(VLOOKUP($AK$17,Sheet1!Z2:AB2,3,0),0) -> 0 | AL19: =+IFERROR(VLOOKUP($AL$17,Sheet1!AD2:AG2,3,0),0) -> 0 | AM19: =+IFERROR(VLOOKUP($AM$17,Sheet1!AD2:AG2,3,0),0) -> 0 | AN19: =+IFERROR(VLOOKUP($AN$17,Sheet1!AD2:AG2,3,0),0) -> 0 | AO19: =+IFERROR(VLOOKUP($AO$17,Sheet1!AD2:AG2,3,0),0) -> 0 | AP19: =+IFERROR(VLOOKUP($AP$17,Sheet1!AD2:AG2,3,0),0) -> 0 | AQ19: =+IFERROR(VLOOKUP($AQ$17,Sheet1!AD2:AG2,3,0),0) -> 0 | AR19: 840 | AS19: =+IFERROR(VLOOKUP($AS$17,Sheet1!AH2:AK2,3,0),0) -> 0 | AT19: =+IFERROR(VLOOKUP($AT$17,Sheet1!AH2:AK2,3,0),0) -> 0 | AU19: =+IFERROR(VLOOKUP($AU$17,Sheet1!AH2:AK2,3,0),0) -> 0 | AV19: =+IFERROR(VLOOKUP($AV$17,Sheet1!AH2:AK2,3,0),0) -> 0 | AW19: =+IFERROR(VLOOKUP($AW$17,Sheet1!AH2:AK2,3,0),0) -> 0 | AX19: =+IFERROR(VLOOKUP($AX$17,Sheet1!AH2:AK2,3,0),0) -> 0 | AY19: =+IFERROR(VLOOKUP($AY$17,Sheet1!AH2:AK2,3,0),0) -> 0 | AZ19: =+IFERROR(VLOOKUP($AZ$17,Sheet1!AH2:AK2,3,0),0) -> 0 | BA19: 3945 | BB19: =+IFERROR(VLOOKUP($BB$17,Sheet1!AH2:AK2,3,0),0) -> 0 | BC19: =+IFERROR(VLOOKUP($BC$17,Sheet1!AL2:AO2,3,0),0) -> 0 | BD19: =+IFERROR(VLOOKUP($BD$17,Sheet1!AL2:AO2,3,0),0) -> 0 | BE19: =+IFERROR(VLOOKUP($BE$17,Sheet1!AL2:AO2,3,0),0) -> 0 | BF19: 1170 | BG19: 830 | BH19: =+IFERROR(VLOOKUP($BH$17,Sheet1!AL2:AO2,3,0),0) -> 0 | BI19: =+IFERROR(VLOOKUP($BI$17,Sheet1!AL2:AO2,3,0),0) -> 0 | BJ19: =+IFERROR(VLOOKUP($BJ$17,Sheet1!AL2:AO2,3,0),0) -> 0 | BK19: =+IFERROR(VLOOKUP($BK$17,Sheet1!AL2:AO2,3,0),0) -> 0 | BL19: =+IFERROR(VLOOKUP($BL$17,Sheet1!AL2:AO2,3,0),0) -> 0 | BM19: =+IFERROR(VLOOKUP($BM$17,Sheet1!AP2:AS2,3,0),0) -> 0 | BN19: 38 | BO19: =+IFERROR(VLOOKUP($BO$17,Sheet1!AX2:BA2,3,0),0) -> 0 | BP19: 77 | BQ19: =+IFERROR(VLOOKUP($BQ$17,Sheet1!BF2:BI2,3,0),0) -> 0 | BR19: =+IFERROR(VLOOKUP($BR$17,Sheet1!BJ2:BM2,3,0),0) -> 0 | BS19: =+IFERROR(VLOOKUP($BS$17,Sheet1!BN2:BQ2,3,0),0) -> 0 | BT19: 54 | BU19: =+IFERROR(VLOOKUP($BU$17,Sheet1!BV2:BY2,3,0),0) -> 0 | BV19: =Sheet1!E2 -> STEEL | BW19: =Sheet1!CV2 -> SP0400136 | BX19: =Sheet1!CW2 -> CORRUGATED DISPATCH STEEL DRUM 2200 X 1300 X 1200 MM | BY19: =Sheet1!CX2 -> 250 | BZ19: 112000 | CA19: =SUMPRODUCT($N$18:$BU$18,N19:BU19)+BZ19 -> 1647169 | CB19: 0.01 | CC19: =CA19*CB19 -> 16471.69 | CD19: 0.2 | CE19: =CA19*CD19 -> 329433.8 | CF19: 0 | CG19: =CA19*CF19 -> 0 | CH19: =CA19+CC19+CE19+CG19 -> 1993074.5 | CI19: 0.02 | CJ19: =CH19*CI19 -> 39861.49 | CK19: 0.01 | CL19: =CH19*CK19 -> 19930.745
A20: =Sheet1!A3 -> ENQ-13992-22-23 | B20: =Sheet1!B3 -> 45548 | C20: =Sheet1!C3 -> FA1300090 | D20: =Sheet1!D3 -> 3 CORE X 185 SQ. MM AL/ARM - WIRE (XLPE) - 11 KV | E20: =CH20+CJ20+CL20 -> 1533007.6 | F20: =ROUNDUP(M32,0) -> 46667 | G20: =E20+F20 -> 1579674.6 | H20: =Sheet1!CP3 -> 0.18 | I20: =G20*H20 -> 284341.42 | J20: =G20+I20 -> 1864016 | K20: =Sheet1!CS3 -> 27 | L20: =Sheet1!CT3 -> KMS | M20: =J20*K20 -> 50328432 | N20: =+IFERROR(VLOOKUP($N$17,Sheet1!J3:L3,3,0),0) -> 1499 | O20: =+IFERROR(VLOOKUP($O$17,Sheet1!J3:L3,3,0),0) -> 0 | P20: =+IFERROR(VLOOKUP($P$17,Sheet1!J3:M3,3,0),0) -> 0 | Q20: =+IFERROR(VLOOKUP($Q$17,Sheet1!J3:M3,3,0),0) -> 0 | R20: =+IFERROR(VLOOKUP($R$17,Sheet1!J3:M3,3,0),0) -> 0 | S20: =+IFERROR(VLOOKUP($S$17,Sheet1!N3:Q3,3,0),0) -> 0 | T20: =+IFERROR(VLOOKUP($T$17,Sheet1!N3:Q3,3,0),0) -> 0 | U20: =+IFERROR(VLOOKUP($U$17,Sheet1!F3:I3,3,0),0) -> 0 | V20: =+IFERROR(VLOOKUP($V$17,Sheet1!F3:I3,3,0),0) -> 0 | W20: =+IFERROR(VLOOKUP($W$17,Sheet1!F3:I3,3,0),0) -> 0 | X20: =+IFERROR(VLOOKUP($X$17,Sheet1!F3:I3,3,0),0) -> 0 | Y20: 125 | Z20: =+IFERROR(VLOOKUP($Z$17,Sheet1!F3:I3,3,0),0) -> 0 | AA20: =+IFERROR(VLOOKUP($AA$17,Sheet1!F3:I3,3,0),0) -> 0 | AB20: =+IFERROR(VLOOKUP($AB$17,Sheet1!F3:I3,3,0),0) -> 0 | AC20: 300 | AD20: =+IFERROR(VLOOKUP($AD$17,Sheet1!R3:U3,2,0),0) -> 0 | AE20: 695 | AF20: =+IFERROR(VLOOKUP($AF$17,Sheet1!V3:Y3,3,0),0) -> 0 | AG20: =+IFERROR(VLOOKUP($AG$17,Sheet1!V3:Y3,3,0),0) -> 0 | AH20: =+IFERROR(VLOOKUP($AH$17,Sheet1!V3:Y3,3,0),0) -> 0 | AI20: =+IFERROR(VLOOKUP($AI$17,Sheet1!V3:Y3,3,0),0) -> 0 | AJ20: =+IFERROR(VLOOKUP($AJ$17,Sheet1!V3:Y3,3,0),0) -> 0 | AK20: =+IFERROR(VLOOKUP($AK$17,Sheet1!Z3:AB3,3,0),0) -> 0 | AL20: =+IFERROR(VLOOKUP($AL$17,Sheet1!AD3:AG3,3,0),0) -> 0 | AM20: =+IFERROR(VLOOKUP($AM$17,Sheet1!AD3:AG3,3,0),0) -> 0 | AN20: =+IFERROR(VLOOKUP($AN$17,Sheet1!AD3:AG3,3,0),0) -> 0 | AO20: =+IFERROR(VLOOKUP($AO$17,Sheet1!AD3:AG3,3,0),0) -> 0 | AP20: =+IFERROR(VLOOKUP($AP$17,Sheet1!AD3:AG3,3,0),0) -> 0 | AQ20: =+IFERROR(VLOOKUP($AQ$17,Sheet1!AD3:AG3,3,0),0) -> 0 | AR20: 658 | AS20: =+IFERROR(VLOOKUP($AS$17,Sheet1!AH3:AK3,3,0),0) -> 0 | AT20: =+IFERROR(VLOOKUP($AT$17,Sheet1!AH3:AK3,3,0),0) -> 0 | AU20: =+IFERROR(VLOOKUP($AU$17,Sheet1!AH3:AK3,3,0),0) -> 0 | AV20: =+IFERROR(VLOOKUP($AV$17,Sheet1!AH3:AK3,3,0),0) -> 0 | AW20: =+IFERROR(VLOOKUP($AW$17,Sheet1!AH3:AK3,3,0),0) -> 0 | AX20: =+IFERROR(VLOOKUP($AX$17,Sheet1!AH3:AK3,3,0),0) -> 0 | AY20: =+IFERROR(VLOOKUP($AY$17,Sheet1!AH3:AK3,3,0),0) -> 0 | AZ20: =+IFERROR(VLOOKUP($AZ$17,Sheet1!AH3:AK3,3,0),0) -> 0 | BA20: 3372 | BB20: =+IFERROR(VLOOKUP($BB$17,Sheet1!AH3:AK3,3,0),0) -> 0 | BC20: =+IFERROR(VLOOKUP($BC$17,Sheet1!AL3:AO3,3,0),0) -> 0 | BD20: =+IFERROR(VLOOKUP($BD$17,Sheet1!AL3:AO3,3,0),0) -> 0 | BE20: =+IFERROR(VLOOKUP($BE$17,Sheet1!AL3:AO3,3,0),0) -> 0 | BF20: 920 | BG20: 612 | BH20: =+IFERROR(VLOOKUP($BH$17,Sheet1!AL3:AO3,3,0),0) -> 0 | BI20: =+IFERROR(VLOOKUP($BI$17,Sheet1!AL3:AO3,3,0),0) -> 0 | BJ20: =+IFERROR(VLOOKUP($BJ$17,Sheet1!AL3:AO3,3,0),0) -> 0 | BK20: =+IFERROR(VLOOKUP($BK$17,Sheet1!AL3:AO3,3,0),0) -> 0 | BL20: =+IFERROR(VLOOKUP($BL$17,Sheet1!AL3:AO3,3,0),0) -> 0 | BM20: =+IFERROR(VLOOKUP($BM$17,Sheet1!AP3:AS3,3,0),0) -> 0 | BN20: 35 | BO20: =+IFERROR(VLOOKUP($BO$17,Sheet1!AX3:BA3,3,0),0) -> 0 | BP20: 65 | BQ20: =+IFERROR(VLOOKUP($BQ$17,Sheet1!BF3:BI3,3,0),0) -> 0 | BR20: =+IFERROR(VLOOKUP($BR$17,Sheet1!BJ3:BM3,3,0),0) -> 0 | BS20: =+IFERROR(VLOOKUP($BS$17,Sheet1!BN3:BQ3,3,0),0) -> 0 | BT20: 47 | BU20: =+IFERROR(VLOOKUP($BU$17,Sheet1!BV3:BY3,3,0),0) -> 0 | BV20: =Sheet1!E3 -> STEEL | BW20: =Sheet1!CV3 -> SP0400111 | BX20: =Sheet1!CW3 -> CORRUGATED DISPATCH STEEL DRUM 1900 X 1000 X 1000 MM | BY20: =Sheet1!CX3 -> 250 | BZ20: 77400 | CA20: =SUMPRODUCT($N$18:$BU$18,N20:BU20)+BZ20 -> 1230047 | CB20: 0.01 | CC20: =CA20*CB20 -> 12300.47 | CD20: 0.2 | CE20: =CA20*CD20 -> 246009.4 | CF20: 0 | CG20: =CA20*CF20 -> 0 | CH20: =CA20+CC20+CE20+CG20 -> 1488356.9 | CI20: 0.02 | CJ20: =CH20*CI20 -> 29767.137 | CK20: 0.01 | CL20: =CH20*CK20 -> 14883.569
A21: =Sheet1!A4 -> ENQ-13992-22-23 | B21: =Sheet1!B4 -> 45548 | C21: =Sheet1!C4 -> FA1300176 | D21: =Sheet1!D4 -> 3 CORE X 150 SQ. MM. AL/ARM - WIRE (XLPE) - 11 KV | E21: =CH21+CJ21+CL21 -> 1350074.4 | F21: =ROUNDUP(M33,0) -> 70000 | G21: =E21+F21 -> 1420074.4 | H21: =Sheet1!CP4 -> 0.18 | I21: =G21*H21 -> 255613.39 | J21: =G21+I21 -> 1675687.8 | K21: =Sheet1!CS4 -> 2 | L21: =Sheet1!CT4 -> KMS | M21: =J21*K21 -> 3351375.6 | N21: =+IFERROR(VLOOKUP($N$17,Sheet1!J4:L4,3,0),0) -> 1215 | O21: =+IFERROR(VLOOKUP($O$17,Sheet1!J4:L4,3,0),0) -> 0 | P21: =+IFERROR(VLOOKUP($P$17,Sheet1!J4:M4,3,0),0) -> 0 | Q21: =+IFERROR(VLOOKUP($Q$17,Sheet1!J4:M4,3,0),0) -> 0 | R21: =+IFERROR(VLOOKUP($R$17,Sheet1!J4:M4,3,0),0) -> 0 | S21: =+IFERROR(VLOOKUP($S$17,Sheet1!N4:Q4,3,0),0) -> 0 | T21: =+IFERROR(VLOOKUP($T$17,Sheet1!N4:Q4,3,0),0) -> 0 | U21: =+IFERROR(VLOOKUP($U$17,Sheet1!F4:I4,3,0),0) -> 0 | V21: =+IFERROR(VLOOKUP($V$17,Sheet1!F4:I4,3,0),0) -> 0 | W21: =+IFERROR(VLOOKUP($W$17,Sheet1!F4:I4,3,0),0) -> 0 | X21: =+IFERROR(VLOOKUP($X$17,Sheet1!F4:I4,3,0),0) -> 0 | Y21: 117 | Z21: =+IFERROR(VLOOKUP($Z$17,Sheet1!F4:I4,3,0),0) -> 0 | AA21: =+IFERROR(VLOOKUP($AA$17,Sheet1!F4:I4,3,0),0) -> 0 | AB21: =+IFERROR(VLOOKUP($AB$17,Sheet1!F4:I4,3,0),0) -> 0 | AC21: 280 | AD21: =+IFERROR(VLOOKUP($AD$17,Sheet1!R4:U4,2,0),0) -> 0 | AE21: 642 | AF21: =+IFERROR(VLOOKUP($AF$17,Sheet1!V4:Y4,3,0),0) -> 0 | AG21: =+IFERROR(VLOOKUP($AG$17,Sheet1!V4:Y4,3,0),0) -> 0 | AH21: =+IFERROR(VLOOKUP($AH$17,Sheet1!V4:Y4,3,0),0) -> 0 | AI21: =+IFERROR(VLOOKUP($AI$17,Sheet1!V4:Y4,3,0),0) -> 0 | AJ21: =+IFERROR(VLOOKUP($AJ$17,Sheet1!V4:Y4,3,0),0) -> 0 | AK21: =+IFERROR(VLOOKUP($AK$17,Sheet1!Z4:AB4,3,0),0) -> 0 | AL21: =+IFERROR(VLOOKUP($AL$17,Sheet1!AD4:AG4,3,0),0) -> 0 | AM21: =+IFERROR(VLOOKUP($AM$17,Sheet1!AD4:AG4,3,0),0) -> 0 | AN21: =+IFERROR(VLOOKUP($AN$17,Sheet1!AD4:AG4,3,0),0) -> 0 | AO21: =+IFERROR(VLOOKUP($AO$17,Sheet1!AD4:AG4,3,0),0) -> 0 | AP21: =+IFERROR(VLOOKUP($AP$17,Sheet1!AD4:AG4,3,0),0) -> 0 | AQ21: =+IFERROR(VLOOKUP($AQ$17,Sheet1!AD4:AG4,3,0),0) -> 0 | AR21: 568 | AS21: =+IFERROR(VLOOKUP($AS$17,Sheet1!AH4:AK4,3,0),0) -> 0 | AT21: =+IFERROR(VLOOKUP($AT$17,Sheet1!AH4:AK4,3,0),0) -> 0 | AU21: =+IFERROR(VLOOKUP($AU$17,Sheet1!AH4:AK4,3,0),0) -> 0 | AV21: =+IFERROR(VLOOKUP($AV$17,Sheet1!AH4:AK4,3,0),0) -> 0 | AW21: =+IFERROR(VLOOKUP($AW$17,Sheet1!AH4:AK4,3,0),0) -> 0 | AX21: =+IFERROR(VLOOKUP($AX$17,Sheet1!AH4:AK4,3,0),0) -> 0 | AY21: =+IFERROR(VLOOKUP($AY$17,Sheet1!AH4:AK4,3,0),0) -> 0 | AZ21: =+IFERROR(VLOOKUP($AZ$17,Sheet1!AH4:AK4,3,0),0) -> 0 | BA21: 3117 | BB21: =+IFERROR(VLOOKUP($BB$17,Sheet1!AH4:AK4,3,0),0) -> 0 | BC21: =+IFERROR(VLOOKUP($BC$17,Sheet1!AL4:AO4,3,0),0) -> 0 | BD21: =+IFERROR(VLOOKUP($BD$17,Sheet1!AL4:AO4,3,0),0) -> 0 | BE21: =+IFERROR(VLOOKUP($BE$17,Sheet1!AL4:AO4,3,0),0) -> 0 | BF21: 812 | BG21: 541 | BH21: =+IFERROR(VLOOKUP($BH$17,Sheet1!AL4:AO4,3,0),0) -> 0 | BI21: =+IFERROR(VLOOKUP($BI$17,Sheet1!AL4:AO4,3,0),0) -> 0 | BJ21: =+IFERROR(VLOOKUP($BJ$17,Sheet1!AL4:AO4,3,0),0) -> 0 | BK21: =+IFERROR(VLOOKUP($BK$17,Sheet1!AL4:AO4,3,0),0) -> 0 | BL21: =+IFERROR(VLOOKUP($BL$17,Sheet1!AL4:AO4,3,0),0) -> 0 | BM21: =+IFERROR(VLOOKUP($BM$17,Sheet1!AP4:AS4,3,0),0) -> 0 | BN21: 18 | BO21: =+IFERROR(VLOOKUP($BO$17,Sheet1!AX4:BA4,3,0),0) -> 0 | BP21: 59 | BQ21: =+IFERROR(VLOOKUP($BQ$17,Sheet1!BF4:BI4,3,0),0) -> 0 | BR21: =+IFERROR(VLOOKUP($BR$17,Sheet1!BJ4:BM4,3,0),0) -> 0 | BS21: =+IFERROR(VLOOKUP($BS$17,Sheet1!BN4:BQ4,3,0),0) -> 0 | BT21: 44 | BU21: =+IFERROR(VLOOKUP($BU$17,Sheet1!BV4:BY4,3,0),0) -> 0 | BV21: =Sheet1!E4 -> STEEL | BW21: SP0400118 | BX21: CORRUGATED DISPATCH STEEL DRUM 1700 X 1000 X 1200 | BY21: =Sheet1!CX4 -> 250 | BZ21: 70400 | CA21: =SUMPRODUCT($N$18:$BU$18,N21:BU21)+BZ21 -> 1083266 | CB21: 0.01 | CC21: =CA21*CB21 -> 10832.66 | CD21: 0.2 | CE21: =CA21*CD21 -> 216653.2 | CF21: 0 | CG21: =CA21*CF21 -> 0 | CH21: =CA21+CC21+CE21+CG21 -> 1310751.9 | CI21: 0.02 | CJ21: =CH21*CI21 -> 26215.037 | CK21: 0.01 | CL21: =CH21*CK21 -> 13107.519
A22: =Sheet1!A5 -> ENQ-13992-22-23 | B22: =Sheet1!B5 -> 45548 | C22: =Sheet1!C5 -> FA1300098 | D22: =Sheet1!D5 -> 3 CORE X 95 SQ. MM. AL/ARM - WIRE (XLPE) - 11 KV | E22: =CH22+CJ22+CL22 -> 1029471.2 | F22: =ROUNDUP(M34,0) -> 35000 | G22: =E22+F22 -> 1064471.2 | H22: =Sheet1!CP5 -> 0.18 | I22: =G22*H22 -> 191604.82 | J22: =G22+I22 -> 1256076 | K22: =Sheet1!CS5 -> 20 | L22: =Sheet1!CT5 -> KMS | M22: =J22*K22 -> 25121521 | N22: =+IFERROR(VLOOKUP($N$17,Sheet1!J5:L5,3,0),0) -> 770 | O22: =+IFERROR(VLOOKUP($O$17,Sheet1!J5:L5,3,0),0) -> 0 | P22: =+IFERROR(VLOOKUP($P$17,Sheet1!J5:M5,3,0),0) -> 0 | Q22: =+IFERROR(VLOOKUP($Q$17,Sheet1!J5:M5,3,0),0) -> 0 | R22: =+IFERROR(VLOOKUP($R$17,Sheet1!J5:M5,3,0),0) -> 0 | S22: =+IFERROR(VLOOKUP($S$17,Sheet1!N5:Q5,3,0),0) -> 0 | T22: =+IFERROR(VLOOKUP($T$17,Sheet1!N5:Q5,3,0),0) -> 0 | U22: =+IFERROR(VLOOKUP($U$17,Sheet1!F5:I5,3,0),0) -> 0 | V22: =+IFERROR(VLOOKUP($V$17,Sheet1!F5:I5,3,0),0) -> 0 | W22: =+IFERROR(VLOOKUP($W$17,Sheet1!F5:I5,3,0),0) -> 0 | X22: =+IFERROR(VLOOKUP($X$17,Sheet1!F5:I5,3,0),0) -> 0 | Y22: 102 | Z22: =+IFERROR(VLOOKUP($Z$17,Sheet1!F5:I5,3,0),0) -> 0 | AA22: =+IFERROR(VLOOKUP($AA$17,Sheet1!F5:I5,3,0),0) -> 0 | AB22: =+IFERROR(VLOOKUP($AB$17,Sheet1!F5:I5,3,0),0) -> 0 | AC22: 232 | AD22: =+IFERROR(VLOOKUP($AD$17,Sheet1!R5:U5,2,0),0) -> 0 | AE22: 544 | AF22: =+IFERROR(VLOOKUP($AF$17,Sheet1!V5:Y5,3,0),0) -> 0 | AG22: =+IFERROR(VLOOKUP($AG$17,Sheet1!V5:Y5,3,0),0) -> 0 | AH22: =+IFERROR(VLOOKUP($AH$17,Sheet1!V5:Y5,3,0),0) -> 0 | AI22: =+IFERROR(VLOOKUP($AI$17,Sheet1!V5:Y5,3,0),0) -> 0 | AJ22: =+IFERROR(VLOOKUP($AJ$17,Sheet1!V5:Y5,3,0),0) -> 0 | AK22: =+IFERROR(VLOOKUP($AK$17,Sheet1!Z5:AB5,3,0),0) -> 0 | AL22: =+IFERROR(VLOOKUP($AL$17,Sheet1!AD5:AG5,3,0),0) -> 0 | AM22: =+IFERROR(VLOOKUP($AM$17,Sheet1!AD5:AG5,3,0),0) -> 0 | AN22: =+IFERROR(VLOOKUP($AN$17,Sheet1!AD5:AG5,3,0),0) -> 0 | AO22: =+IFERROR(VLOOKUP($AO$17,Sheet1!AD5:AG5,3,0),0) -> 0 | AP22: =+IFERROR(VLOOKUP($AP$17,Sheet1!AD5:AG5,3,0),0) -> 0 | AQ22: =+IFERROR(VLOOKUP($AQ$17,Sheet1!AD5:AG5,3,0),0) -> 0 | AR22: 460 | AS22: =+IFERROR(VLOOKUP($AS$17,Sheet1!AH5:AK5,3,0),0) -> 0 | AT22: =+IFERROR(VLOOKUP($AT$17,Sheet1!AH5:AK5,3,0),0) -> 0 | AU22: =+IFERROR(VLOOKUP($AU$17,Sheet1!AH5:AK5,3,0),0) -> 0 | AV22: =+IFERROR(VLOOKUP($AV$17,Sheet1!AH5:AK5,3,0),0) -> 0 | AW22: =+IFERROR(VLOOKUP($AW$17,Sheet1!AH5:AK5,3,0),0) -> 0 | AX22: =+IFERROR(VLOOKUP($AX$17,Sheet1!AH5:AK5,3,0),0) -> 0 | AY22: =+IFERROR(VLOOKUP($AY$17,Sheet1!AH5:AK5,3,0),0) -> 0 | AZ22: =+IFERROR(VLOOKUP($AZ$17,Sheet1!AH5:AK5,3,0),0) -> 0 | BA22: 2244 | BB22: =+IFERROR(VLOOKUP($BB$17,Sheet1!AH5:AK5,3,0),0) -> 0 | BC22: =+IFERROR(VLOOKUP($BC$17,Sheet1!AL5:AO5,3,0),0) -> 0 | BD22: =+IFERROR(VLOOKUP($BD$17,Sheet1!AL5:AO5,3,0),0) -> 0 | BE22: =+IFERROR(VLOOKUP($BE$17,Sheet1!AL5:AO5,3,0),0) -> 0 | BF22: 656 | BG22: 416 | BH22: =+IFERROR(VLOOKUP($BH$17,Sheet1!AL5:AO5,3,0),0) -> 0 | BI22: =+IFERROR(VLOOKUP($BI$17,Sheet1!AL5:AO5,3,0),0) -> 0 | BJ22: =+IFERROR(VLOOKUP($BJ$17,Sheet1!AL5:AO5,3,0),0) -> 0 | BK22: =+IFERROR(VLOOKUP($BK$17,Sheet1!AL5:AO5,3,0),0) -> 0 | BL22: =+IFERROR(VLOOKUP($BL$17,Sheet1!AL5:AO5,3,0),0) -> 0 | BM22: =+IFERROR(VLOOKUP($BM$17,Sheet1!AP5:AS5,3,0),0) -> 0 | BN22: 15 | BO22: 0 | BP22: 50 | BQ22: =+IFERROR(VLOOKUP($BQ$17,Sheet1!BF5:BI5,3,0),0) -> 0 | BR22: =+IFERROR(VLOOKUP($BR$17,Sheet1!BJ5:BM5,3,0),0) -> 0 | BS22: =+IFERROR(VLOOKUP($BS$17,Sheet1!BN5:BQ5,3,0),0) -> 0 | BT22: 38 | BU22: =+IFERROR(VLOOKUP($BU$17,Sheet1!BV5:BY5,3,0),0) -> 0 | BV22: =Sheet1!E5 -> STEEL | BW22: SP0400110 | BX22: CORRUGATED DISPATCH STEEL DRUM 1600 X 900 X 1000 MM | BY22: =Sheet1!CX5 -> 250 | BZ22: 68800 | CA22: =SUMPRODUCT($N$18:$BU$18,N22:BU22)+BZ22 -> 826022 | CB22: 0.01 | CC22: =CA22*CB22 -> 8260.22 | CD22: 0.2 | CE22: =CA22*CD22 -> 165204.4 | CF22: 0 | CG22: =CA22*CF22 -> 0 | CH22: =CA22+CC22+CE22+CG22 -> 999486.62 | CI22: 0.02 | CJ22: =CH22*CI22 -> 19989.732 | CK22: 0.01 | CL22: =CH22*CK22 -> 9994.8662
A23: =Sheet1!A6 -> ENQ-13992-22-23 | B23: =Sheet1!B6 -> 45548 | C23: =Sheet1!C6 -> FA1300066 | D23: =Sheet1!D6 -> 1 CORE X 1000 SQ. MM. AL/ARM (XLPE) - 11 KV | E23: =CH23+CJ23+CL23 -> 1583796.8 | F23: =ROUNDUP(M35,0) -> 21000 | G23: =E23+F23 -> 1604796.8 | H23: =Sheet1!CP6 -> 0.18 | I23: =G23*H23 -> 288863.42 | J23: =G23+I23 -> 1893660.2 | K23: =Sheet1!CS6 -> 20 | L23: =Sheet1!CT6 -> KMS | M23: =J23*K23 -> 37873204 | N23: =+IFERROR(VLOOKUP($N$17,Sheet1!J6:L6,3,0),0) -> 2732 | O23: =+IFERROR(VLOOKUP($O$17,Sheet1!J6:L6,3,0),0) -> 0 | P23: =+IFERROR(VLOOKUP($P$17,Sheet1!J6:M6,3,0),0) -> 0 | Q23: =+IFERROR(VLOOKUP($Q$17,Sheet1!J6:M6,3,0),0) -> 0 | R23: =+IFERROR(VLOOKUP($R$17,Sheet1!J6:M6,3,0),0) -> 0 | S23: =+IFERROR(VLOOKUP($S$17,Sheet1!N6:Q6,3,0),0) -> 0 | T23: =+IFERROR(VLOOKUP($T$17,Sheet1!N6:Q6,3,0),0) -> 0 | U23: =+IFERROR(VLOOKUP($U$17,Sheet1!F6:I6,3,0),0) -> 0 | V23: =+IFERROR(VLOOKUP($V$17,Sheet1!F6:I6,3,0),0) -> 0 | W23: =+IFERROR(VLOOKUP($W$17,Sheet1!F6:I6,3,0),0) -> 0 | X23: =+IFERROR(VLOOKUP($X$17,Sheet1!F6:I6,3,0),0) -> 0 | Y23: 77 | Z23: =+IFERROR(VLOOKUP($Z$17,Sheet1!F6:I6,3,0),0) -> 0 | AA23: =+IFERROR(VLOOKUP($AA$17,Sheet1!F6:I6,3,0),0) -> 0 | AB23: =+IFERROR(VLOOKUP($AB$17,Sheet1!F6:I6,3,0),0) -> 0 | AC23: 230 | AD23: =+IFERROR(VLOOKUP($AD$17,Sheet1!R6:U6,2,0),0) -> 0 | AE23: 476 | AF23: =+IFERROR(VLOOKUP($AF$17,Sheet1!V6:Y6,3,0),0) -> 0 | AG23: =+IFERROR(VLOOKUP($AG$17,Sheet1!V6:Y6,3,0),0) -> 0 | AH23: =+IFERROR(VLOOKUP($AH$17,Sheet1!V6:Y6,3,0),0) -> 0 | AI23: =+IFERROR(VLOOKUP($AI$17,Sheet1!V6:Y6,3,0),0) -> 0 | AJ23: =+IFERROR(VLOOKUP($AJ$17,Sheet1!V6:Y6,3,0),0) -> 0 | AK23: 19 | AL23: =+IFERROR(VLOOKUP($AL$17,Sheet1!AD6:AG6,3,0),0) -> 0 | AM23: =+IFERROR(VLOOKUP($AM$17,Sheet1!AD6:AG6,3,0),0) -> 0 | AN23: =+IFERROR(VLOOKUP($AN$17,Sheet1!AD6:AG6,3,0),0) -> 0 | AO23: =+IFERROR(VLOOKUP($AO$17,Sheet1!AD6:AG6,3,0),0) -> 0 | AP23: =+IFERROR(VLOOKUP($AP$17,Sheet1!AD6:AG6,3,0),0) -> 0 | AQ23: 194 | AR23: =+IFERROR(VLOOKUP($AR$17,Sheet1!AD6:AG6,3,0),0) -> 0 | AS23: =+IFERROR(VLOOKUP($AS$17,Sheet1!AH6:AK6,3,0),0) -> 0 | AT23: =+IFERROR(VLOOKUP($AT$17,Sheet1!AH6:AK6,3,0),0) -> 0 | AU23: =+IFERROR(VLOOKUP($AU$17,Sheet1!AH6:AK6,3,0),0) -> 0 | AV23: 1008 | AW23: =+IFERROR(VLOOKUP($AW$17,Sheet1!AH6:AK6,3,0),0) -> 0 | AX23: =+IFERROR(VLOOKUP($AX$17,Sheet1!AH6:AK6,3,0),0) -> 0 | AY23: =+IFERROR(VLOOKUP($AY$17,Sheet1!AH6:AK6,3,0),0) -> 0 | AZ23: =+IFERROR(VLOOKUP($AZ$17,Sheet1!AH6:AK6,3,0),0) -> 0 | BA23: =+IFERROR(VLOOKUP($BA$17,Sheet1!AH6:AK6,3,0),0) -> 0 | BB23: =+IFERROR(VLOOKUP($BB$17,Sheet1!AH6:AK6,3,0),0) -> 0 | BC23: =+IFERROR(VLOOKUP($BC$17,Sheet1!AL6:AO6,3,0),0) -> 0 | BD23: =+IFERROR(VLOOKUP($BD$17,Sheet1!AL6:AO6,3,0),0) -> 0 | BE23: =+IFERROR(VLOOKUP($BE$17,Sheet1!AL6:AO6,3,0),0) -> 0 | BF23: 700 | BG23: =+IFERROR(VLOOKUP($BG$17,Sheet1!AL6:AO6,3,0),0) -> 0 | BH23: =+IFERROR(VLOOKUP($BH$17,Sheet1!AL6:AO6,3,0),0) -> 0 | BI23: =+IFERROR(VLOOKUP($BI$17,Sheet1!AL6:AO6,3,0),0) -> 0 | BJ23: =+IFERROR(VLOOKUP($BJ$17,Sheet1!AL6:AO6,3,0),0) -> 0 | BK23: =+IFERROR(VLOOKUP($BK$17,Sheet1!AL6:AO6,3,0),0) -> 0 | BL23: =+IFERROR(VLOOKUP($BL$17,Sheet1!AL6:AO6,3,0),0) -> 0 | BM23: =+IFERROR(VLOOKUP($BM$17,Sheet1!AP6:AS6,3,0),0) -> 0 | BN23: 39 | BO23: =+IFERROR(VLOOKUP($BO$17,Sheet1!AX6:BA6,3,0),0) -> 0 | BP23: 46 | BQ23: =+IFERROR(VLOOKUP($BQ$17,Sheet1!BF6:BI6,3,0),0) -> 0 | BR23: =+IFERROR(VLOOKUP($BR$17,Sheet1!BJ6:BM6,3,0),0) -> 0 | BS23: =+IFERROR(VLOOKUP($BS$17,Sheet1!BN6:BQ6,3,0),0) -> 0 | BT23: 42 | BU23: =+IFERROR(VLOOKUP($BU$17,Sheet1!BV6:BY6,3,0),0) -> 0 | BV23: =Sheet1!E6 -> STEEL | BW23: =Sheet1!CV6 -> SP0400107 | BX23: =Sheet1!CW6 -> CORRUGATED DISPATCH STEEL DRUM 2150 X 1080 X 1240 MM | BY23: =Sheet1!CX6 -> 500 | BZ23: =Sheet1!BZ6 -> 66500 | CA23: =SUMPRODUCT($N$18:$BU$18,N23:BU23)+BZ23 -> 1270799 | CB23: 0.01 | CC23: =CA23*CB23 -> 12707.99 | CD23: 0.2 | CE23: =CA23*CD23 -> 254159.8 | CF23: 0 | CG23: =CA23*CF23 -> 0 | CH23: =CA23+CC23+CE23+CG23 -> 1537666.8 | CI23: 0.02 | CJ23: =CH23*CI23 -> 30753.336 | CK23: 0.01 | CL23: =CH23*CK23 -> 15376.668
A24: =Sheet1!A7 -> ENQ-13992-22-23 | B24: =Sheet1!B7 -> 45548 | C24: =Sheet1!C7 -> FA1300016 | D24: =Sheet1!D7 -> 1 CORE X 630 SQ. MM. AL/ARM (XLPE) - 11 KV | E24: =CH24+CJ24+CL24 -> 1020272.3 | F24: =ROUNDUP(M36,0) -> 23334 | G24: =E24+F24 -> 1043606.3 | H24: =Sheet1!CP7 -> 0.18 | I24: =G24*H24 -> 187849.13 | J24: =G24+I24 -> 1231455.4 | K24: =Sheet1!CS7 -> 3 | L24: =Sheet1!CT7 -> KMS | M24: =J24*K24 -> 3694366.2 | N24: =+IFERROR(VLOOKUP($N$17,Sheet1!J7:L7,3,0),0) -> 1701 | O24: =+IFERROR(VLOOKUP($O$17,Sheet1!J7:L7,3,0),0) -> 0 | P24: =+IFERROR(VLOOKUP($P$17,Sheet1!J7:M7,3,0),0) -> 0 | Q24: =+IFERROR(VLOOKUP($Q$17,Sheet1!J7:M7,3,0),0) -> 0 | R24: =+IFERROR(VLOOKUP($R$17,Sheet1!J7:M7,3,0),0) -> 0 | S24: =+IFERROR(VLOOKUP($S$17,Sheet1!N7:Q7,3,0),0) -> 0 | T24: =+IFERROR(VLOOKUP($T$17,Sheet1!N7:Q7,3,0),0) -> 0 | U24: =+IFERROR(VLOOKUP($U$17,Sheet1!F7:I7,3,0),0) -> 0 | V24: =+IFERROR(VLOOKUP($V$17,Sheet1!F7:I7,3,0),0) -> 0 | W24: =+IFERROR(VLOOKUP($W$17,Sheet1!F7:I7,3,0),0) -> 0 | X24: =+IFERROR(VLOOKUP($X$17,Sheet1!F7:I7,3,0),0) -> 0 | Y24: 63 | Z24: =+IFERROR(VLOOKUP($Z$17,Sheet1!F7:I7,3,0),0) -> 0 | AA24: =+IFERROR(VLOOKUP($AA$17,Sheet1!F7:I7,3,0),0) -> 0 | AB24: =+IFERROR(VLOOKUP($AB$17,Sheet1!F7:I7,3,0),0) -> 0 | AC24: 170 | AD24: =+IFERROR(VLOOKUP($AD$17,Sheet1!R7:U7,2,0),0) -> 0 | AE24: 380 | AF24: =+IFERROR(VLOOKUP($AF$17,Sheet1!V7:Y7,3,0),0) -> 0 | AG24: =+IFERROR(VLOOKUP($AG$17,Sheet1!V7:Y7,3,0),0) -> 0 | AH24: =+IFERROR(VLOOKUP($AH$17,Sheet1!V7:Y7,3,0),0) -> 0 | AI24: =+IFERROR(VLOOKUP($AI$17,Sheet1!V7:Y7,3,0),0) -> 0 | AJ24: =+IFERROR(VLOOKUP($AJ$17,Sheet1!V7:Y7,3,0),0) -> 0 | AK24: 15 | AL24: =+IFERROR(VLOOKUP($AL$17,Sheet1!AD7:AG7,3,0),0) -> 0 | AM24: =+IFERROR(VLOOKUP($AM$17,Sheet1!AD7:AG7,3,0),0) -> 0 | AN24: =+IFERROR(VLOOKUP($AN$17,Sheet1!AD7:AG7,3,0),0) -> 0 | AO24: =+IFERROR(VLOOKUP($AO$17,Sheet1!AD7:AG7,3,0),0) -> 0 | AP24: =+IFERROR(VLOOKUP($AP$17,Sheet1!AD7:AG7,3,0),0) -> 0 | AQ24: 140 | AR24: =+IFERROR(VLOOKUP($AR$17,Sheet1!AD7:AG7,3,0),0) -> 0 | AS24: =+IFERROR(VLOOKUP($AS$17,Sheet1!AH7:AK7,3,0),0) -> 0 | AT24: =+IFERROR(VLOOKUP($AT$17,Sheet1!AH7:AK7,3,0),0) -> 0 | AU24: =+IFERROR(VLOOKUP($AU$17,Sheet1!AH7:AK7,3,0),0) -> 0 | AV24: 530 | AW24: =+IFERROR(VLOOKUP($AW$17,Sheet1!AH7:AK7,3,0),0) -> 0 | AX24: =+IFERROR(VLOOKUP($AX$17,Sheet1!AH7:AK7,3,0),0) -> 0 | AY24: =+IFERROR(VLOOKUP($AY$17,Sheet1!AH7:AK7,3,0),0) -> 0 | AZ24: =+IFERROR(VLOOKUP($AZ$17,Sheet1!AH7:AK7,3,0),0) -> 0 | BA24: =+IFERROR(VLOOKUP($BA$17,Sheet1!AH7:AK7,3,0),0) -> 0 | BB24: =+IFERROR(VLOOKUP($BB$17,Sheet1!AH7:AK7,3,0),0) -> 0 | BC24: =+IFERROR(VLOOKUP($BC$17,Sheet1!AL7:AO7,3,0),0) -> 0 | BD24: =+IFERROR(VLOOKUP($BD$17,Sheet1!AL7:AO7,3,0),0) -> 0 | BE24: =+IFERROR(VLOOKUP($BE$17,Sheet1!AL7:AO7,3,0),0) -> 0 | BF24: 492 | BG24: =+IFERROR(VLOOKUP($BG$17,Sheet1!AL7:AO7,3,0),0) -> 0 | BH24: =+IFERROR(VLOOKUP($BH$17,Sheet1!AL7:AO7,3,0),0) -> 0 | BI24: =+IFERROR(VLOOKUP($BI$17,Sheet1!AL7:AO7,3,0),0) -> 0 | BJ24: =+IFERROR(VLOOKUP($BJ$17,Sheet1!AL7:AO7,3,0),0) -> 0 | BK24: =+IFERROR(VLOOKUP($BK$17,Sheet1!AL7:AO7,3,0),0) -> 0 | BL24: =+IFERROR(VLOOKUP($BL$17,Sheet1!AL7:AO7,3,0),0) -> 0 | BM24: =+IFERROR(VLOOKUP($BM$17,Sheet1!AP7:AS7,3,0),0) -> 0 | BN24: 26 | BO24: =+IFERROR(VLOOKUP($BO$17,Sheet1!AX7:BA7,3,0),0) -> 0 | BP24: 36 | BQ24: =+IFERROR(VLOOKUP($BQ$17,Sheet1!BF7:BI7,3,0),0) -> 0 | BR24: =+IFERROR(VLOOKUP($BR$17,Sheet1!BJ7:BM7,3,0),0) -> 0 | BS24: =+IFERROR(VLOOKUP($BS$17,Sheet1!BN7:BQ7,3,0),0) -> 0 | BT24: 33 | BU24: =+IFERROR(VLOOKUP($BU$17,Sheet1!BV7:BY7,3,0),0) -> 0 | BV24: =Sheet1!E7 -> STEEL | BW24: =Sheet1!CV7 -> SP0400091 | BX24: =Sheet1!CW7 -> CORRUGATED DISPATCH STEEL DRUM 1800 X 900 X 1000 | BY24: =Sheet1!CX7 -> 500 | BZ24: =Sheet1!BZ7 -> 48450 | CA24: =SUMPRODUCT($N$18:$BU$18,N24:BU24)+BZ24 -> 818641 | CB24: 0.01 | CC24: =CA24*CB24 -> 8186.41 | CD24: 0.2 | CE24: =CA24*CD24 -> 163728.2 | CF24: 0 | CG24: =CA24*CF24 -> 0 | CH24: =CA24+CC24+CE24+CG24 -> 990555.61 | CI24: 0.02 | CJ24: =CH24*CI24 -> 19811.112 | CK24: 0.01 | CL24: =CH24*CK24 -> 9905.5561
A25: =Sheet1!A8 -> ENQ-13992-22-23 | B25: =Sheet1!B8 -> 45548 | C25: =Sheet1!C8 -> FA1300047 | D25: =Sheet1!D8 -> 1 CORE X 400 SQ. MM. AL/ARM (XLPE) - 11 KV | E25: =CH25+CJ25+CL25 -> 767075.22 | F25: =ROUNDUP(M37,0) -> 70000 | G25: =E25+F25 -> 837075.22 | H25: =Sheet1!CP8 -> 0.18 | I25: =G25*H25 -> 150673.54 | J25: =G25+I25 -> 987748.76 | K25: =Sheet1!CS8 -> 1 | L25: =Sheet1!CT8 -> KMS | M25: =J25*K25 -> 987748.76 | N25: =+IFERROR(VLOOKUP($N$17,Sheet1!J8:L8,3,0),0) -> 1080 | O25: =+IFERROR(VLOOKUP($O$17,Sheet1!J8:L8,3,0),0) -> 0 | P25: =+IFERROR(VLOOKUP($P$17,Sheet1!J8:M8,3,0),0) -> 0 | Q25: =+IFERROR(VLOOKUP($Q$17,Sheet1!J8:M8,3,0),0) -> 0 | R25: =+IFERROR(VLOOKUP($R$17,Sheet1!J8:M8,3,0),0) -> 0 | S25: =+IFERROR(VLOOKUP($S$17,Sheet1!N8:Q8,3,0),0) -> 0 | T25: =+IFERROR(VLOOKUP($T$17,Sheet1!N8:Q8,3,0),0) -> 0 | U25: =+IFERROR(VLOOKUP($U$17,Sheet1!F8:I8,3,0),0) -> 0 | V25: =+IFERROR(VLOOKUP($V$17,Sheet1!F8:I8,3,0),0) -> 0 | W25: =+IFERROR(VLOOKUP($W$17,Sheet1!F8:I8,3,0),0) -> 0 | X25: =+IFERROR(VLOOKUP($X$17,Sheet1!F8:I8,3,0),0) -> 0 | Y25: 53 | Z25: =+IFERROR(VLOOKUP($Z$17,Sheet1!F8:I8,3,0),0) -> 0 | AA25: =+IFERROR(VLOOKUP($AA$17,Sheet1!F8:I8,3,0),0) -> 0 | AB25: =+IFERROR(VLOOKUP($AB$17,Sheet1!F8:I8,3,0),0) -> 0 | AC25: 138 | AD25: =+IFERROR(VLOOKUP($AD$17,Sheet1!R8:U8,2,0),0) -> 0 | AE25: 310 | AF25: =+IFERROR(VLOOKUP($AF$17,Sheet1!V8:Y8,3,0),0) -> 0 | AG25: =+IFERROR(VLOOKUP($AG$17,Sheet1!V8:Y8,3,0),0) -> 0 | AH25: =+IFERROR(VLOOKUP($AH$17,Sheet1!V8:Y8,3,0),0) -> 0 | AI25: =+IFERROR(VLOOKUP($AI$17,Sheet1!V8:Y8,3,0),0) -> 0 | AJ25: =+IFERROR(VLOOKUP($AJ$17,Sheet1!V8:Y8,3,0),0) -> 0 | AK25: 13 | AL25: =+IFERROR(VLOOKUP($AL$17,Sheet1!AD8:AG8,3,0),0) -> 0 | AM25: =+IFERROR(VLOOKUP($AM$17,Sheet1!AD8:AG8,3,0),0) -> 0 | AN25: =+IFERROR(VLOOKUP($AN$17,Sheet1!AD8:AG8,3,0),0) -> 0 | AO25: =+IFERROR(VLOOKUP($AO$17,Sheet1!AD8:AG8,3,0),0) -> 0 | AP25: =+IFERROR(VLOOKUP($AP$17,Sheet1!AD8:AG8,3,0),0) -> 0 | AQ25: 102 | AR25: =+IFERROR(VLOOKUP($AR$17,Sheet1!AD8:AG8,3,0),0) -> 0 | AS25: =+IFERROR(VLOOKUP($AS$17,Sheet1!AH8:AK8,3,0),0) -> 0 | AT25: =+IFERROR(VLOOKUP($AT$17,Sheet1!AH8:AK8,3,0),0) -> 0 | AU25: =+IFERROR(VLOOKUP($AU$17,Sheet1!AH8:AK8,3,0),0) -> 0 | AV25: 552 | AW25: =+IFERROR(VLOOKUP($AW$17,Sheet1!AH8:AK8,3,0),0) -> 0 | AX25: =+IFERROR(VLOOKUP($AX$17,Sheet1!AH8:AK8,3,0),0) -> 0 | AY25: =+IFERROR(VLOOKUP($AY$17,Sheet1!AH8:AK8,3,0),0) -> 0 | AZ25: =+IFERROR(VLOOKUP($AZ$17,Sheet1!AH8:AK8,3,0),0) -> 0 | BA25: =+IFERROR(VLOOKUP($BA$17,Sheet1!AH8:AK8,3,0),0) -> 0 | BB25: =+IFERROR(VLOOKUP($BB$17,Sheet1!AH8:AK8,3,0),0) -> 0 | BC25: =+IFERROR(VLOOKUP($BC$17,Sheet1!AL8:AO8,3,0),0) -> 0 | BD25: =+IFERROR(VLOOKUP($BD$17,Sheet1!AL8:AO8,3,0),0) -> 0 | BE25: =+IFERROR(VLOOKUP($BE$17,Sheet1!AL8:AO8,3,0),0) -> 0 | BF25: 403 | BG25: =+IFERROR(VLOOKUP($BG$17,Sheet1!AL8:AO8,3,0),0) -> 0 | BH25: =+IFERROR(VLOOKUP($BH$17,Sheet1!AL8:AO8,3,0),0) -> 0 | BI25: =+IFERROR(VLOOKUP($BI$17,Sheet1!AL8:AO8,3,0),0) -> 0 | BJ25: =+IFERROR(VLOOKUP($BJ$17,Sheet1!AL8:AO8,3,0),0) -> 0 | BK25: =+IFERROR(VLOOKUP($BK$17,Sheet1!AL8:AO8,3,0),0) -> 0 | BL25: =+IFERROR(VLOOKUP($BL$17,Sheet1!AL8:AO8,3,0),0) -> 0 | BM25: =+IFERROR(VLOOKUP($BM$17,Sheet1!AP8:AS8,3,0),0) -> 0 | BN25: 19 | BO25: =+IFERROR(VLOOKUP($BO$17,Sheet1!AX8:BA8,3,0),0) -> 0 | BP25: 29 | BQ25: =+IFERROR(VLOOKUP($BQ$17,Sheet1!BF8:BI8,3,0),0) -> 0 | BR25: =+IFERROR(VLOOKUP($BR$17,Sheet1!BJ8:BM8,3,0),0) -> 0 | BS25: =+IFERROR(VLOOKUP($BS$17,Sheet1!BN8:BQ8,3,0),0) -> 0 | BT25: 30 | BU25: =+IFERROR(VLOOKUP($BU$17,Sheet1!BV8:BY8,3,0),0) -> 0 | BV25: =Sheet1!E8 -> STEEL | BW25: =Sheet1!CV8 -> SP0400125 | BX25: =Sheet1!CW8 -> CORRUGATED DISPATCH STEEL DRUM 1600 X 700 X 915 MM | BY25: =Sheet1!CX8 -> 500 | BZ25: =15000*2 -> 30000 | CA25: =SUMPRODUCT($N$18:$BU$18,N25:BU25)+BZ25 -> 615482 | CB25: 0.01 | CC25: =CA25*CB25 -> 6154.82 | CD25: 0.2 | CE25: =CA25*CD25 -> 123096.4 | CF25: 0 | CG25: =CA25*CF25 -> 0 | CH25: =CA25+CC25+CE25+CG25 -> 744733.22 | CI25: 0.02 | CJ25: =CH25*CI25 -> 14894.664 | CK25: 0.01 | CL25: =CH25*CK25 -> 7447.3322
A26: =Sheet1!A9 -> ENQ-13992-22-23 | B26: =Sheet1!B9 -> 45548 | C26: =Sheet1!C9 -> FA1300009 | D26: =Sheet1!D9 -> 1 CORE X 300 SQ. MM. AL./ARM (XLPE) - 11 KV | E26: =CH26+CJ26+CL26 -> 639892.79 | F26: =ROUNDUP(M38,0) -> 35000 | G26: =E26+F26 -> 674892.79 | H26: =Sheet1!CP9 -> 0.18 | I26: =G26*H26 -> 121480.7 | J26: =G26+I26 -> 796373.5 | K26: =Sheet1!CS9 -> 2 | L26: =Sheet1!CT9 -> KMS | M26: =J26*K26 -> 1592747 | N26: =+IFERROR(VLOOKUP($N$17,Sheet1!J9:L9,3,0),0) -> 810 | O26: =+IFERROR(VLOOKUP($O$17,Sheet1!J9:L9,3,0),0) -> 0 | P26: =+IFERROR(VLOOKUP($P$17,Sheet1!J9:M9,3,0),0) -> 0 | Q26: =+IFERROR(VLOOKUP($Q$17,Sheet1!J9:M9,3,0),0) -> 0 | R26: =+IFERROR(VLOOKUP($R$17,Sheet1!J9:M9,3,0),0) -> 0 | S26: =+IFERROR(VLOOKUP($S$17,Sheet1!N9:Q9,3,0),0) -> 0 | T26: =+IFERROR(VLOOKUP($T$17,Sheet1!N9:Q9,3,0),0) -> 0 | U26: =+IFERROR(VLOOKUP($U$17,Sheet1!F9:I9,3,0),0) -> 0 | V26: =+IFERROR(VLOOKUP($V$17,Sheet1!F9:I9,3,0),0) -> 0 | W26: =+IFERROR(VLOOKUP($W$17,Sheet1!F9:I9,3,0),0) -> 0 | X26: =+IFERROR(VLOOKUP($X$17,Sheet1!F9:I9,3,0),0) -> 0 | Y26: 48 | Z26: =+IFERROR(VLOOKUP($Z$17,Sheet1!F9:I9,3,0),0) -> 0 | AA26: =+IFERROR(VLOOKUP($AA$17,Sheet1!F9:I9,3,0),0) -> 0 | AB26: =+IFERROR(VLOOKUP($AB$17,Sheet1!F9:I9,3,0),0) -> 0 | AC26: 122 | AD26: =+IFERROR(VLOOKUP($AD$17,Sheet1!R9:U9,2,0),0) -> 0 | AE26: 278 | AF26: =+IFERROR(VLOOKUP($AF$17,Sheet1!V9:Y9,3,0),0) -> 0 | AG26: =+IFERROR(VLOOKUP($AG$17,Sheet1!V9:Y9,3,0),0) -> 0 | AH26: =+IFERROR(VLOOKUP($AH$17,Sheet1!V9:Y9,3,0),0) -> 0 | AI26: =+IFERROR(VLOOKUP($AI$17,Sheet1!V9:Y9,3,0),0) -> 0 | AJ26: =+IFERROR(VLOOKUP($AJ$17,Sheet1!V9:Y9,3,0),0) -> 0 | AK26: 11 | AL26: =+IFERROR(VLOOKUP($AL$17,Sheet1!AD9:AG9,3,0),0) -> 0 | AM26: =+IFERROR(VLOOKUP($AM$17,Sheet1!AD9:AG9,3,0),0) -> 0 | AN26: =+IFERROR(VLOOKUP($AN$17,Sheet1!AD9:AG9,3,0),0) -> 0 | AO26: =+IFERROR(VLOOKUP($AO$17,Sheet1!AD9:AG9,3,0),0) -> 0 | AP26: =+IFERROR(VLOOKUP($AP$17,Sheet1!AD9:AG9,3,0),0) -> 0 | AQ26: 92 | AR26: =+IFERROR(VLOOKUP($AR$17,Sheet1!AD9:AG9,3,0),0) -> 0 | AS26: =+IFERROR(VLOOKUP($AS$17,Sheet1!AH9:AK9,3,0),0) -> 0 | AT26: =+IFERROR(VLOOKUP($AT$17,Sheet1!AH9:AK9,3,0),0) -> 0 | AU26: =+IFERROR(VLOOKUP($AU$17,Sheet1!AH9:AK9,3,0),0) -> 0 | AV26: 497 | AW26: =+IFERROR(VLOOKUP($AW$17,Sheet1!AH9:AK9,3,0),0) -> 0 | AX26: =+IFERROR(VLOOKUP($AX$17,Sheet1!AH9:AK9,3,0),0) -> 0 | AY26: =+IFERROR(VLOOKUP($AY$17,Sheet1!AH9:AK9,3,0),0) -> 0 | AZ26: =+IFERROR(VLOOKUP($AZ$17,Sheet1!AH9:AK9,3,0),0) -> 0 | BA26: =+IFERROR(VLOOKUP($BA$17,Sheet1!AH9:AK9,3,0),0) -> 0 | BB26: =+IFERROR(VLOOKUP($BB$17,Sheet1!AH9:AK9,3,0),0) -> 0 | BC26: =+IFERROR(VLOOKUP($BC$17,Sheet1!AL9:AO9,3,0),0) -> 0 | BD26: =+IFERROR(VLOOKUP($BD$17,Sheet1!AL9:AO9,3,0),0) -> 0 | BE26: =+IFERROR(VLOOKUP($BE$17,Sheet1!AL9:AO9,3,0),0) -> 0 | BF26: 345 | BG26: =+IFERROR(VLOOKUP($BG$17,Sheet1!AL9:AO9,3,0),0) -> 0 | BH26: =+IFERROR(VLOOKUP($BH$17,Sheet1!AL9:AO9,3,0),0) -> 0 | BI26: =+IFERROR(VLOOKUP($BI$17,Sheet1!AL9:AO9,3,0),0) -> 0 | BJ26: =+IFERROR(VLOOKUP($BJ$17,Sheet1!AL9:AO9,3,0),0) -> 0 | BK26: =+IFERROR(VLOOKUP($BK$17,Sheet1!AL9:AO9,3,0),0) -> 0 | BL26: =+IFERROR(VLOOKUP($BL$17,Sheet1!AL9:AO9,3,0),0) -> 0 | BM26: =+IFERROR(VLOOKUP($BM$17,Sheet1!AP9:AS9,3,0),0) -> 0 | BN26: 13 | BO26: =+IFERROR(VLOOKUP($BO$17,Sheet1!AX9:BA9,3,0),0) -> 0 | BP26: 25.5 | BQ26: =+IFERROR(VLOOKUP($BQ$17,Sheet1!BF9:BI9,3,0),0) -> 0 | BR26: =+IFERROR(VLOOKUP($BR$17,Sheet1!BJ9:BM9,3,0),0) -> 0 | BS26: =+IFERROR(VLOOKUP($BS$17,Sheet1!BN9:BQ9,3,0),0) -> 0 | BT26: 26.5 | BU26: =+IFERROR(VLOOKUP($BU$17,Sheet1!BV9:BY9,3,0),0) -> 0 | BV26: =Sheet1!E9 -> STEEL | BW26: =Sheet1!CV9 -> SP0400152 | BX26: =Sheet1!CW9 -> CORRUGATED DISPATCH STEEL DRUM 1500 X 800 X 915 | BY26: =Sheet1!CX9 -> 500 | BZ26: 28800 | CA26: =SUMPRODUCT($N$18:$BU$18,N26:BU26)+BZ26 -> 513434 | CB26: 0.01 | CC26: =CA26*CB26 -> 5134.34 | CD26: 0.2 | CE26: =CA26*CD26 -> 102686.8 | CF26: 0 | CG26: =CA26*CF26 -> 0 | CH26: =CA26+CC26+CE26+CG26 -> 621255.14 | CI26: 0.02 | CJ26: =CH26*CI26 -> 12425.103 | CK26: 0.01 | CL26: =CH26*CK26 -> 6212.5514
A27: =Sheet1!A10 -> ENQ-13992-22-23 | B27: =Sheet1!B10 -> 45548 | C27: =Sheet1!C10 -> FA1300020 | D27: =Sheet1!D10 -> 1 CORE X 185 SQ. MM. AL./ARM (XLPE) - 11 KV | E27: =CH27+CJ27+CL27 -> 511206.09 | F27: =ROUNDUP(M39,0) -> 17500 | G27: =E27+F27 -> 528706.09 | H27: =Sheet1!CP10 -> 0.18 | I27: =G27*H27 -> 95167.096 | J27: =G27+I27 -> 623873.18 | K27: =Sheet1!CS10 -> 4 | L27: =Sheet1!CT10 -> KMS | M27: =J27*K27 -> 2495492.7 | N27: 499 | O27: =+IFERROR(VLOOKUP($O$17,Sheet1!J10:L10,3,0),0) -> 0 | P27: =+IFERROR(VLOOKUP($P$17,Sheet1!J10:M10,3,0),0) -> 0 | Q27: =+IFERROR(VLOOKUP($Q$17,Sheet1!J10:M10,3,0),0) -> 0 | R27: =+IFERROR(VLOOKUP($R$17,Sheet1!J10:M10,3,0),0) -> 0 | S27: =+IFERROR(VLOOKUP($S$17,Sheet1!N10:Q10,3,0),0) -> 0 | T27: =+IFERROR(VLOOKUP($T$17,Sheet1!N10:Q10,3,0),0) -> 0 | U27: =+IFERROR(VLOOKUP($U$17,Sheet1!F10:I10,3,0),0) -> 0 | V27: =+IFERROR(VLOOKUP($V$17,Sheet1!F10:I10,3,0),0) -> 0 | W27: =+IFERROR(VLOOKUP($W$17,Sheet1!F10:I10,3,0),0) -> 0 | X27: =+IFERROR(VLOOKUP($X$17,Sheet1!F10:I10,3,0),0) -> 0 | Y27: 47 | Z27: =+IFERROR(VLOOKUP($Z$17,Sheet1!F10:I10,3,0),0) -> 0 | AA27: =+IFERROR(VLOOKUP($AA$17,Sheet1!F10:I10,3,0),0) -> 0 | AB27: =+IFERROR(VLOOKUP($AB$17,Sheet1!F10:I10,3,0),0) -> 0 | AC27: 130 | AD27: =+IFERROR(VLOOKUP($AD$17,Sheet1!R10:U10,2,0),0) -> 0 | AE27: 230 | AF27: =+IFERROR(VLOOKUP($AF$17,Sheet1!V10:Y10,3,0),0) -> 0 | AG27: =+IFERROR(VLOOKUP($AG$17,Sheet1!V10:Y10,3,0),0) -> 0 | AH27: =+IFERROR(VLOOKUP($AH$17,Sheet1!V10:Y10,3,0),0) -> 0 | AI27: =+IFERROR(VLOOKUP($AI$17,Sheet1!V10:Y10,3,0),0) -> 0 | AJ27: =+IFERROR(VLOOKUP($AJ$17,Sheet1!V10:Y10,3,0),0) -> 0 | AK27: 54 | AL27: =+IFERROR(VLOOKUP($AL$17,Sheet1!AD10:AG10,3,0),0) -> 0 | AM27: =+IFERROR(VLOOKUP($AM$17,Sheet1!AD10:AG10,3,0),0) -> 0 | AN27: =+IFERROR(VLOOKUP($AN$17,Sheet1!AD10:AG10,3,0),0) -> 0 | AO27: =+IFERROR(VLOOKUP($AO$17,Sheet1!AD10:AG10,3,0),0) -> 0 | AP27: =+IFERROR(VLOOKUP($AP$17,Sheet1!AD10:AG10,3,0),0) -> 0 | AQ27: 96 | AR27: =+IFERROR(VLOOKUP($AR$17,Sheet1!AD10:AG10,3,0),0) -> 0 | AS27: =+IFERROR(VLOOKUP($AS$17,Sheet1!AH10:AK10,3,0),0) -> 0 | AT27: =+IFERROR(VLOOKUP($AT$17,Sheet1!AH10:AK10,3,0),0) -> 0 | AU27: =+IFERROR(VLOOKUP($AU$17,Sheet1!AH10:AK10,3,0),0) -> 0 | AV27: 371 | AW27: =+IFERROR(VLOOKUP($AW$17,Sheet1!AH10:AK10,3,0),0) -> 0 | AX27: =+IFERROR(VLOOKUP($AX$17,Sheet1!AH10:AK10,3,0),0) -> 0 | AY27: =+IFERROR(VLOOKUP($AY$17,Sheet1!AH10:AK10,3,0),0) -> 0 | AZ27: =+IFERROR(VLOOKUP($AZ$17,Sheet1!AH10:AK10,3,0),0) -> 0 | BA27: =+IFERROR(VLOOKUP($BA$17,Sheet1!AH10:AK10,3,0),0) -> 0 | BB27: =+IFERROR(VLOOKUP($BB$17,Sheet1!AH10:AK10,3,0),0) -> 0 | BC27: =+IFERROR(VLOOKUP($BC$17,Sheet1!AL10:AO10,3,0),0) -> 0 | BD27: =+IFERROR(VLOOKUP($BD$17,Sheet1!AL10:AO10,3,0),0) -> 0 | BE27: 309 | BG27: =+IFERROR(VLOOKUP($BG$17,Sheet1!AL10:AO10,3,0),0) -> 0 | BH27: =+IFERROR(VLOOKUP($BH$17,Sheet1!AL10:AO10,3,0),0) -> 0 | BI27: =+IFERROR(VLOOKUP($BI$17,Sheet1!AL10:AO10,3,0),0) -> 0 | BJ27: =+IFERROR(VLOOKUP($BJ$17,Sheet1!AL10:AO10,3,0),0) -> 0 | BK27: =+IFERROR(VLOOKUP($BK$17,Sheet1!AL10:AO10,3,0),0) -> 0 | BL27: =+IFERROR(VLOOKUP($BL$17,Sheet1!AL10:AO10,3,0),0) -> 0 | BM27: =+IFERROR(VLOOKUP($BM$17,Sheet1!AP10:AS10,3,0),0) -> 0 | BN27: 12 | BO27: =+IFERROR(VLOOKUP($BO$17,Sheet1!AX10:BA10,3,0),0) -> 0 | BP27: 24 | BQ27: =+IFERROR(VLOOKUP($BQ$17,Sheet1!BF10:BI10,3,0),0) -> 0 | BR27: =+IFERROR(VLOOKUP($BR$17,Sheet1!BJ10:BM10,3,0),0) -> 0 | BS27: =+IFERROR(VLOOKUP($BS$17,Sheet1!BN10:BQ10,3,0),0) -> 0 | BT27: 25 | BU27: =+IFERROR(VLOOKUP($BU$17,Sheet1!BV10:BY10,3,0),0) -> 0 | BV27: =Sheet1!E10 -> STEEL | BW27: =Sheet1!CV10 -> SP0400125 | BX27: =Sheet1!CW10 -> CORRUGATED DISPATCH STEEL DRUM 1600 X 700 X 915 MM | BY27: =Sheet1!CX10 -> 500 | BZ27: =15000*2 -> 30000 | CA27: =SUMPRODUCT($N$18:$BU$18,N27:BU27)+BZ27 -> 410179 | CB27: 0.01 | CC27: =CA27*CB27 -> 4101.79 | CD27: 0.2 | CE27: =CA27*CD27 -> 82035.8 | CF27: 0 | CG27: =CA27*CF27 -> 0 | CH27: =CA27+CC27+CE27+CG27 -> 496316.59 | CI27: 0.02 | CJ27: =CH27*CI27 -> 9926.3318 | CK27: 0.01 | CL27: =CH27*CK27 -> 4963.1659
A28: =Sheet1!A11 -> ENQ-13992-22-23 | B28: =Sheet1!B11 -> 45548 | C28: =Sheet1!C11 -> FA1300075 | D28: =Sheet1!D11 -> 1 CORE X 95 SQ. MM. AL.ARM (XLPE) - 11 KV | E28: =CH28+CJ28+CL28 -> 368214.35 | F28: =ROUNDUP(M40,0) -> 15000 | G28: =E28+F28 -> 383214.35 | H28: =Sheet1!CP11 -> 0.18 | I28: =G28*H28 -> 68978.583 | J28: =G28+I28 -> 452192.93 | K28: 4 | L28: =Sheet1!CT11 -> KMS | M28: =J28*K28 -> 1808771.7 | N28: =+IFERROR(VLOOKUP($N$17,Sheet1!J11:L11,3,0),0) -> 256 | O28: =+IFERROR(VLOOKUP($O$17,Sheet1!J11:L11,3,0),0) -> 0 | P28: =+IFERROR(VLOOKUP($P$17,Sheet1!J11:M11,3,0),0) -> 0 | Q28: =+IFERROR(VLOOKUP($Q$17,Sheet1!J11:M11,3,0),0) -> 0 | R28: =+IFERROR(VLOOKUP($R$17,Sheet1!J11:M11,3,0),0) -> 0 | S28: =+IFERROR(VLOOKUP($S$17,Sheet1!N11:Q11,3,0),0) -> 0 | T28: =+IFERROR(VLOOKUP($T$17,Sheet1!N11:Q11,3,0),0) -> 0 | U28: =+IFERROR(VLOOKUP($U$17,Sheet1!F11:I11,3,0),0) -> 0 | V28: 0 | W28: =+IFERROR(VLOOKUP($W$17,Sheet1!F11:I11,3,0),0) -> 0 | X28: =+IFERROR(VLOOKUP($X$17,Sheet1!F11:I11,3,0),0) -> 0 | Y28: 39 | Z28: =+IFERROR(VLOOKUP($Z$17,Sheet1!F11:I11,3,0),0) -> 0 | AA28: =+IFERROR(VLOOKUP($AA$17,Sheet1!F11:I11,3,0),0) -> 0 | AB28: =+IFERROR(VLOOKUP($AB$17,Sheet1!F11:I11,3,0),0) -> 0 | AC28: 100 | AD28: =+IFERROR(VLOOKUP($AD$17,Sheet1!R11:U11,2,0),0) -> 0 | AE28: 180 | AF28: =+IFERROR(VLOOKUP($AF$17,Sheet1!V11:Y11,3,0),0) -> 0 | AG28: =+IFERROR(VLOOKUP($AG$17,Sheet1!V11:Y11,3,0),0) -> 0 | AH28: =+IFERROR(VLOOKUP($AH$17,Sheet1!V11:Y11,3,0),0) -> 0 | AI28: =+IFERROR(VLOOKUP($AI$17,Sheet1!V11:Y11,3,0),0) -> 0 | AJ28: =+IFERROR(VLOOKUP($AJ$17,Sheet1!V11:Y11,3,0),0) -> 0 | AK28: 45 | AL28: =+IFERROR(VLOOKUP($AL$17,Sheet1!AD11:AG11,3,0),0) -> 0 | AM28: =+IFERROR(VLOOKUP($AM$17,Sheet1!AD11:AG11,3,0),0) -> 0 | AN28: =+IFERROR(VLOOKUP($AN$17,Sheet1!AD11:AG11,3,0),0) -> 0 | AO28: =+IFERROR(VLOOKUP($AO$17,Sheet1!AD11:AG11,3,0),0) -> 0 | AP28: =+IFERROR(VLOOKUP($AP$17,Sheet1!AD11:AG11,3,0),0) -> 0 | AQ28: 70 | AR28: =+IFERROR(VLOOKUP($AR$17,Sheet1!AD11:AG11,3,0),0) -> 0 | AS28: =+IFERROR(VLOOKUP($AS$17,Sheet1!AH11:AK11,3,0),0) -> 0 | AT28: =+IFERROR(VLOOKUP($AT$17,Sheet1!AH11:AK11,3,0),0) -> 0 | AU28: =+IFERROR(VLOOKUP($AU$17,Sheet1!AH11:AK11,3,0),0) -> 0 | AV28: 309 | AW28: =+IFERROR(VLOOKUP($AW$17,Sheet1!AH11:AK11,3,0),0) -> 0 | AX28: =+IFERROR(VLOOKUP($AX$17,Sheet1!AH11:AK11,3,0),0) -> 0 | AY28: =+IFERROR(VLOOKUP($AY$17,Sheet1!AH11:AK11,3,0),0) -> 0 | AZ28: =+IFERROR(VLOOKUP($AZ$17,Sheet1!AH11:AK11,3,0),0) -> 0 | BA28: =+IFERROR(VLOOKUP($BA$17,Sheet1!AH11:AK11,3,0),0) -> 0 | BB28: =+IFERROR(VLOOKUP($BB$17,Sheet1!AH11:AK11,3,0),0) -> 0 | BC28: =+IFERROR(VLOOKUP($BC$17,Sheet1!AL11:AO11,3,0),0) -> 0 | BD28: =+IFERROR(VLOOKUP($BD$17,Sheet1!AL11:AO11,3,0),0) -> 0 | BE28: 268 | BG28: =+IFERROR(VLOOKUP($BG$17,Sheet1!AL11:AO11,3,0),0) -> 0 | BH28: =+IFERROR(VLOOKUP($BH$17,Sheet1!AL11:AO11,3,0),0) -> 0 | BI28: =+IFERROR(VLOOKUP($BI$17,Sheet1!AL11:AO11,3,0),0) -> 0 | BJ28: 0 | BK28: =+IFERROR(VLOOKUP($BK$17,Sheet1!AL11:AO11,3,0),0) -> 0 | BL28: =+IFERROR(VLOOKUP($BL$17,Sheet1!AL11:AO11,3,0),0) -> 0 | BM28: =+IFERROR(VLOOKUP($BM$17,Sheet1!AP11:AS11,3,0),0) -> 0 | BN28: 6 | BO28: =+IFERROR(VLOOKUP($BO$17,Sheet1!AX11:BA11,3,0),0) -> 0 | BP28: 20 | BQ28: =+IFERROR(VLOOKUP($BQ$17,Sheet1!BF11:BI11,3,0),0) -> 0 | BR28: =+IFERROR(VLOOKUP($BR$17,Sheet1!BJ11:BM11,3,0),0) -> 0 | BS28: =+IFERROR(VLOOKUP($BS$17,Sheet1!BN11:BQ11,3,0),0) -> 0 | BT28: 21 | BU28: =+IFERROR(VLOOKUP($BU$17,Sheet1!BV11:BY11,3,0),0) -> 0 | BV28: STEEL | BW28: SP0400124 | BX28: CORRUGATED DISPATCH STEEL DRUM 1220 X 550 X 915 MM | BY28: =Sheet1!CX11 -> 500 | BZ28: 20700 | CA28: =SUMPRODUCT($N$18:$BU$18,N28:BU28)+BZ28 -> 295446 | CB28: 0.01 | CC28: =CA28*CB28 -> 2954.46 | CD28: 0.2 | CE28: =CA28*CD28 -> 59089.2 | CF28: 0 | CG28: =CA28*CF28 -> 0 | CH28: =CA28+CC28+CE28+CG28 -> 357489.66 | CI28: 0.02 | CJ28: =CH28*CI28 -> 7149.7932 | CK28: 0.01 | CL28: =CH28*CK28 -> 3574.8966
E30: Order Quantity | F30: Stnd Length | G30: Truck type | H30: Fare of one truck | I30: No of Drum in one truck | J30: Total length in one Truck | K30: No of Truck | L30: Total Freight | M30: Freight per KM | Y30: CABLE WEIGHT KG/KM | AC30: DRUM WEIGHT | AE30: CABLE+DRUM WEIGHT | AK30: TRAILOR
D31: =D19 -> 3 CORE X 300 SQ. MM. AL/ARM - WIRE (XLPE) - 11 KV | E31: =K19 -> 19 | F31: =BY19/1000 -> 0.25 | G31: TRAILER 28 MT | H31: 70000 | I31: 6 | J31: =F31*I31 -> 1.5 | K31: =ROUNDUP((E31/J31),0) -> 13 | L31: =M31*E31 -> 910000 | M31: =(H31*K31)/E31 -> 47894.737 | N31: =BW19 -> SP0400136 | Y31: =SUM(N19:BT19) -> 10736 | AC31: 450 | AE31: =((Y31*F31)+AC31) -> 3134 | AK31: =I31*AE31 -> 18804
D32: =D20 -> 3 CORE X 185 SQ. MM AL/ARM - WIRE (XLPE) - 11 KV | E32: =K20 -> 27 | F32: =BY20/1000 -> 0.25 | G32: TRAILER 28 MT | H32: 70000 | I32: 6 | J32: =F32*I32 -> 1.5 | K32: =ROUNDUP((E32/J32),0) -> 18 | L32: =M32*E32 -> 1260000 | M32: =(H32*K32)/E32 -> 46666.667 | N32: =BW20 -> SP0400111 | Y32: =SUM(N20:BT20) -> 8328 | AC32: 285 | AE32: =((Y32*F32)+AC32) -> 2367 | AK32: =I32*AE32 -> 14202
D33: =D21 -> 3 CORE X 150 SQ. MM. AL/ARM - WIRE (XLPE) - 11 KV | E33: =K21 -> 2 | F33: =BY21/1000 -> 0.25 | G33: TRAILER 28 MT | H33: 70000 | I33: 6 | J33: =F33*I33 -> 1.5 | K33: =ROUNDUP((E33/J33),0) -> 2 | L33: =M33*E33 -> 140000 | M33: =(H33*K33)/E33 -> 70000 | N33: =BW21 -> SP0400118 | Y33: =SUM(N21:BT21) -> 7413 | AC33: 250 | AE33: =((Y33*F33)+AC33) -> 2103.25 | AK33: =I33*AE33 -> 12619.5
D34: =D22 -> 3 CORE X 95 SQ. MM. AL/ARM - WIRE (XLPE) - 11 KV | E34: =K22 -> 20 | F34: =BY22/1000 -> 0.25 | G34: TRAILER 28 MT | H34: 70000 | I34: 8 | J34: =F34*I34 -> 2 | K34: =ROUNDUP((E34/J34),0) -> 10 | L34: =M34*E34 -> 700000 | M34: =(H34*K34)/E34 -> 35000 | N34: =BW22 -> SP0400110 | Y34: =SUM(N22:BT22) -> 5527 | AC34: 250 | AE34: =((Y34*F34)+AC34) -> 1631.75 | AK34: =I34*AE34 -> 13054
D35: =D23 -> 1 CORE X 1000 SQ. MM. AL/ARM (XLPE) - 11 KV | E35: =K23 -> 20 | F35: =BY23/1000 -> 0.5 | G35: TRAILER 28 MT | H35: 70000 | I35: 7 | J35: =F35*I35 -> 3.5 | K35: =ROUNDUP((E35/J35),0) -> 6 | L35: =M35*E35 -> 420000 | M35: =(H35*K35)/E35 -> 21000 | N35: =BW23 -> SP0400107 | Y35: =SUM(N23:BT23) -> 5563 | AC35: 350 | AE35: =((Y35*F35)+AC35) -> 3131.5 | AK35: =I35*AE35 -> 21920.5
D36: =D24 -> 1 CORE X 630 SQ. MM. AL/ARM (XLPE) - 11 KV | E36: =K24 -> 3 | F36: =BY24/1000 -> 0.5 | G36: TRAILER 28 MT | H36: 70000 | I36: 8 | J36: =F36*I36 -> 4 | K36: =ROUNDUP((E36/J36),0) -> 1 | L36: =M36*E36 -> 70000 | M36: =(H36*K36)/E36 -> 23333.333 | N36: =BW24 -> SP0400091 | Y36: =SUM(N24:BT24) -> 3586 | AC36: 255 | AE36: =((Y36*F36)+AC36) -> 2048 | AK36: =I36*AE36 -> 16384
D37: =D25 -> 1 CORE X 400 SQ. MM. AL/ARM (XLPE) - 11 KV | E37: =K25 -> 1 | F37: =BY25/1000 -> 0.5 | G37: TRAILER 28 MT | H37: 70000 | I37: 14 | J37: =F37*I37 -> 7 | K37: =ROUNDUP((E37/J37),0) -> 1 | L37: =M37*E37 -> 70000 | M37: =(H37*K37)/E37 -> 70000 | N37: =BW25 -> SP0400125 | Y37: =SUM(N25:BT25) -> 2729 | AC37: 220 | AE37: =((Y37*F37)+AC37) -> 1584.5 | AK37: =I37*AE37 -> 22183
D38: =D26 -> 1 CORE X 300 SQ. MM. AL./ARM (XLPE) - 11 KV | E38: =K26 -> 2 | F38: =BY26/1000 -> 0.5 | G38: TRAILER 28 MT | H38: 70000 | I38: 16 | J38: =F38*I38 -> 8 | K38: =ROUNDUP((E38/J38),0) -> 1 | L38: =M38*E38 -> 70000 | M38: =(H38*K38)/E38 -> 35000 | N38: =BW26 -> SP0400152 | Y38: =SUM(N26:BT26) -> 2268 | AC38: 250 | AE38: =((Y38*F38)+AC38) -> 1384 | AK38: =I38*AE38 -> 22144
D39: =D27 -> 1 CORE X 185 SQ. MM. AL./ARM (XLPE) - 11 KV | E39: =K27 -> 4 | F39: =BY27/1000 -> 0.5 | G39: TRAILER 28 MT | H39: 70000 | I39: 16 | J39: =F39*I39 -> 8 | K39: =ROUNDUP((E39/J39),0) -> 1 | L39: =M39*E39 -> 70000 | M39: =(H39*K39)/E39 -> 17500 | N39: =BW27 -> SP0400125 | Y39: =SUM(N27:BT27) -> 1797 | AC39: 220 | AE39: =((Y39*F39)+AC39) -> 1118.5 | AK39: =I39*AE39 -> 17896
D40: =D28 -> 1 CORE X 95 SQ. MM. AL.ARM (XLPE) - 11 KV | E40: =K28 -> 4 | F40: =BY28/1000 -> 0.5 | G40: 16 Mt | H40: 30000 | I40: 5 | J40: =F40*I40 -> 2.5 | K40: =ROUNDUP((E40/J40),0) -> 2 | L40: =M40*E40 -> 60000 | M40: =(H40*K40)/E40 -> 15000 | N40: =BW28 -> SP0400124 | Y40: =SUM(N28:BT28) -> 1314 | AC40: 110 | AE40: =((Y40*F40)+AC40) -> 767 | AK40: =I40*AE40 -> 3835
I41: SOMBHU CONFIRMED OVERPHONE
D42: 1 | E42: Consider Al rate from- BALCO/ HINDALCO/ NALCO/ Vedanta only.
D43: 2 | E43: Consider Rs. 1 extra for colour of o/sh-FRLSH
D44: 3 | E44: Consider PVC compound rate from- Shakun/Kalpana/KLJ/ DCM ShriRam only
D45: 4 | E45: Consider Steel armour rate from- TATA Steel/Jindal Steel/ SAIL only
D46: 5 | E46: Consider al armour rate from- TATA/BALCO/HINDALCO/NALCO/Vedanta Only
D47: 6 | E47: Consider XLPE compound rate from- Dow/Borealis/Hanwa only.
D48: 7 | E48: Consider Semiconducting compound rate from- Dow/Borealis/Hanwa only.
D49: 8 | E49: Please do not consider the rate of pressure extruded PVC inner sheath for all cables.
D51: 1 | E51: Consider CU TAPE rate from - Vedanta & Hindustan Copper-only for 1C x 95 SQ.MM & 1 C X 185 SQ. MM.
D52: 2 | E52: Consider Outer Sheath rate Rs 20/kg over (PVC) ST-2 FRLSH for lead free ATR - only for 1C x 95 SQ.MM & 1 C X 185 SQ. MM.
D53: 3 | E53: Consider extra premium percentage only for 1C X 1000SQ. MM, comfirmed from DVG Sir.
D54: 4 | E54: Consider mass of zinc coating 290 gm/m2 for each size galvanized steel wire for all cable.
D55: 5 | E55: Consider 1 % extra cost on total cable for special process for all cable.
A58: DOCKET NO. | B58: Base Date | C58: ITEM CODE | D58: PROPOSE ERP ITEM NAME | E58: EX-WORKS (PER MTR) | F58: FREIGHT PER MTR | G58: PRICE INCLUDING FREIGHT (PER MTR) | H58: GST % | I58: GST VALUE | J58: PRICE INCLUDING GST & FREIGHT (PER MTR) | K58: QTY | L58: Unit | M58: TOTAL PRICE OF FULL QTY (INCLUDING FRIGHT & GST)
A60: =A19 -> ENQ-13992-22-23 | B60: =B19 -> 45548 | C60: =C19 -> FA1300091 | D60: =D19 -> 3 CORE X 300 SQ. MM. AL/ARM - WIRE (XLPE) - 11 KV | E60: =ROUNDUP(E19/1000,2) -> 2052.87 | F60: =ROUNDUP(F19/1000,2) -> 47.9 | G60: =E60+F60 -> 2100.77 | H60: =H19 -> 0.18 | I60: =G60*H60 -> 378.1386 | J60: =G60+I60 -> 2478.9086 | K60: =K19*1000 -> 19000 | L60: MTR | M60: =J60*K60 -> 47099263
A61: =A20 -> ENQ-13992-22-23 | B61: =B20 -> 45548 | C61: =C20 -> FA1300090 | D61: =D20 -> 3 CORE X 185 SQ. MM AL/ARM - WIRE (XLPE) - 11 KV | E61: =ROUNDUP(E20/1000,2) -> 1533.01 | F61: =ROUNDUP(F20/1000,2) -> 46.67 | G61: =E61+F61 -> 1579.68 | H61: =H20 -> 0.18 | I61: =G61*H61 -> 284.3424 | J61: =G61+I61 -> 1864.0224 | K61: =K20*1000 -> 27000 | L61: MTR | M61: =J61*K61 -> 50328605
A62: =A21 -> ENQ-13992-22-23 | B62: =B21 -> 45548 | C62: =C21 -> FA1300176 | D62: =D21 -> 3 CORE X 150 SQ. MM. AL/ARM - WIRE (XLPE) - 11 KV | E62: =ROUNDUP(E21/1000,2) -> 1350.08 | F62: =ROUNDUP(F21/1000,2) -> 70 | G62: =E62+F62 -> 1420.08 | H62: =H21 -> 0.18 | I62: =G62*H62 -> 255.6144 | J62: =G62+I62 -> 1675.6944 | K62: =K21*1000 -> 2000 | L62: MTR | M62: =J62*K62 -> 3351388.8
A63: =A22 -> ENQ-13992-22-23 | B63: =B22 -> 45548 | C63: =C22 -> FA1300098 | D63: =D22 -> 3 CORE X 95 SQ. MM. AL/ARM - WIRE (XLPE) - 11 KV | E63: =ROUNDUP(E22/1000,2) -> 1029.48 | F63: =ROUNDUP(F22/1000,2) -> 35 | G63: =E63+F63 -> 1064.48 | H63: =H22 -> 0.18 | I63: =G63*H63 -> 191.6064 | J63: =G63+I63 -> 1256.0864 | K63: =K22*1000 -> 20000 | L63: MTR | M63: =J63*K63 -> 25121728
A64: =A23 -> ENQ-13992-22-23 | B64: =B23 -> 45548 | C64: =C23 -> FA1300066 | D64: =D23 -> 1 CORE X 1000 SQ. MM. AL/ARM (XLPE) - 11 KV | E64: =ROUNDUP(E23/1000,2) -> 1583.8 | F64: =ROUNDUP(F23/1000,2) -> 21 | G64: =E64+F64 -> 1604.8 | H64: =H23 -> 0.18 | I64: =G64*H64 -> 288.864 | J64: =G64+I64 -> 1893.664 | K64: =K23*1000 -> 20000 | L64: MTR | M64: =J64*K64 -> 37873280
A65: =A24 -> ENQ-13992-22-23 | B65: =B24 -> 45548 | C65: =C24 -> FA1300016 | D65: =D24 -> 1 CORE X 630 SQ. MM. AL/ARM (XLPE) - 11 KV | E65: =ROUNDUP(E24/1000,2) -> 1020.28 | F65: =ROUNDUP(F24/1000,2) -> 23.34 | G65: =E65+F65 -> 1043.62 | H65: =H24 -> 0.18 | I65: =G65*H65 -> 187.8516 | J65: =G65+I65 -> 1231.4716 | K65: =K24*1000 -> 3000 | L65: MTR | M65: =J65*K65 -> 3694414.8
A66: =A25 -> ENQ-13992-22-23 | B66: =B25 -> 45548 | C66: =C25 -> FA1300047 | D66: =D25 -> 1 CORE X 400 SQ. MM. AL/ARM (XLPE) - 11 KV | E66: =ROUNDUP(E25/1000,2) -> 767.08 | F66: =ROUNDUP(F25/1000,2) -> 70 | G66: =E66+F66 -> 837.08 | H66: =H25 -> 0.18 | I66: =G66*H66 -> 150.6744 | J66: =G66+I66 -> 987.7544 | K66: =K25*1000 -> 1000 | L66: MTR | M66: =J66*K66 -> 987754.4
A67: =A26 -> ENQ-13992-22-23 | B67: =B26 -> 45548 | C67: =C26 -> FA1300009 | D67: =D26 -> 1 CORE X 300 SQ. MM. AL./ARM (XLPE) - 11 KV | E67: =ROUNDUP(E26/1000,2) -> 639.9 | F67: =ROUNDUP(F26/1000,2) -> 35 | G67: =E67+F67 -> 674.9 | H67: =H26 -> 0.18 | I67: =G67*H67 -> 121.482 | J67: =G67+I67 -> 796.382 | K67: =K26*1000 -> 2000 | L67: MTR | M67: =J67*K67 -> 1592764
A68: =A27 -> ENQ-13992-22-23 | B68: =B27 -> 45548 | C68: =C27 -> FA1300020 | D68: =D27 -> 1 CORE X 185 SQ. MM. AL./ARM (XLPE) - 11 KV | E68: =ROUNDUP(E27/1000,2) -> 511.21 | F68: =ROUNDUP(F27/1000,2) -> 17.5 | G68: =E68+F68 -> 528.71 | H68: =H27 -> 0.18 | I68: =G68*H68 -> 95.1678 | J68: =G68+I68 -> 623.8778 | K68: =K27*1000 -> 4000 | L68: MTR | M68: =J68*K68 -> 2495511.2
A69: =A28 -> ENQ-13992-22-23 | B69: =B28 -> 45548 | C69: =C28 -> FA1300075 | D69: =D28 -> 1 CORE X 95 SQ. MM. AL.ARM (XLPE) - 11 KV | E69: =ROUNDUP(E28/1000,2) -> 368.22 | F69: =ROUNDUP(F28/1000,2) -> 15 | G69: =E69+F69 -> 383.22 | H69: =H28 -> 0.18 | I69: =G69*H69 -> 68.9796 | J69: =G69+I69 -> 452.1996 | K69: =K28*1000 -> 4000 | L69: MTR | M69: =J69*K69 -> 1808798.4
M70: =SUM(M60:M69) -> 1.7435351e+08

Sheet Sheet2
F8: standard drum length mtr | G8: CABLE WEIGHT KG/KM | H8: OD (MM | I8: Number of drum in trailor
D9: 3 CORE X 300 SQ. MM. AL/ARM - WIRE (XLPE) - 11 KV | E9: CORRUGATED DISPATCH STEEL DRUM 2200 X 1300 X 1200 MM | F9: 250 | G9: 10736 | H9: 82 | I9: 6
D10: 3 CORE X 185 SQ. MM AL/ARM - WIRE (XLPE) - 11 KV | E10: CORRUGATED DISPATCH STEEL DRUM 1900 X 1000 X 1000 MM | F10: 250 | G10: 8328 | H10: 72 | I10: 6
D11: 3 CORE X 150 SQ. MM. AL/ARM - WIRE (XLPE) - 11 KV | E11: CORRUGATED DISPATCH STEEL DRUM 1700 X 1000 X 1200 | F11: 250 | G11: 7413 | H11: 68 | I11: 6
D12: 3 CORE X 95 SQ. MM. AL/ARM - WIRE (XLPE) - 11 KV | E12: CORRUGATED DISPATCH STEEL DRUM 1600 X 900 X 1000 MM | F12: 250 | G12: 5527 | H12: 60 | I12: 8
D13: 1 CORE X 1000 SQ. MM. AL/ARM (XLPE) - 11 KV | E13: CORRUGATED DISPATCH STEEL DRUM 2150 X 1080 X 1240 MM | F13: 500 | G13: 5563 | H13: 63 | I13: 8
D14: 1 CORE X 630 SQ. MM. AL/ARM (XLPE) - 11 KV | E14: CORRUGATED DISPATCH STEEL DRUM 1800 X 900 X 1000 | F14: 500 | G14: 3586 | H14: 51 | I14: 8
D15: 1 CORE X 400 SQ. MM. AL/ARM (XLPE) - 11 KV | E15: CORRUGATED DISPATCH STEEL DRUM 1600 X 700 X 915 MM | F15: 500 | G15: 2729 | H15: 45 | I15: 16
D16: 1 CORE X 300 SQ. MM. AL./ARM (XLPE) - 11 KV | E16: CORRUGATED DISPATCH STEEL DRUM 1500 X 800 X 915 | F16: 500 | G16: 2268 | H16: 41.5 | I16: 16
D17: 1 CORE X 185 SQ. MM. AL./ARM (XLPE) - 11 KV | E17: CORRUGATED DISPATCH STEEL DRUM 1600 X 700 X 915 MM | F17: 500 | G17: 1797 | H17: 37 | I17: 16
D18: 1 CORE X 95 SQ. MM. AL.ARM (XLPE) - 11 KV | E18: CORRUGATED DISPATCH STEEL DRUM 1220 X 550 X 915 MM | F18: 500 | G18: 1314 | H18: 32.5 | I18: 16
