Workbook

Sheet Sheet1
A1: DOCKET NO. | B1: Base Date | C1: ITEM CODE | D1: PROPOSE ERP ITEM NAME | E1: Propose Drum Type | F1: Insulation Screening(Metallic) | G1: RM Rate(Insulation Screening(Metallic)) | H1: Weight (Insulation Screening (Metallic)) | I1: Cost Insulation Screening(Metallic) | J1: Conductor | K1: RM Rate(Conductor) | L1: Weight(Conductor) | M1: Cost(Conductor) | N1: AL ALLOY | O1: RM Rate(AL Alloy) | P1: Weight(Al Alloy) | Q1: Cost(AL Alloy) | R1: Insulation Screening(Non-Metallic) | S1: RM Rate(Insulation Screening(Non-Metallic)) | T1: Weight(Insulation Screening(Non-Metallic) | U1: Cost(Insulation Screening(Non-Metallic) | V1: Insulation | W1: RM Rate(Insulation) | X1: Weight(Insulation) | Y1: Cost(Insulation) | Z1: Poly Tape | AA1: RM Rate(Poly Tape) | AB1: Weight(Poly Tape) | AC1: Cost(Poly Tape) | AD1: Inner Sheath | AE1: RM Rate(Inner Sheath) | AF1: Weight(Inner Sheath) | AG1: Cost(Inner Sheath) | AH1: Armouring | AI1: RM Rate(Armouring) | AJ1: Weight(Armouring) | AK1: Cost(Armouring) | AL1: Outer Sheath | AM1: RM Rate(Outer Sheath) | AN1: Weight(Outer Sheath) | AO1: Cost(Outer Sheath) | AP1: Filler | AQ1: RM Rate(Filler) | AR1: Weight(Filler) | AS1: Cost(Filler) | AT1: Grease | AU1: RM Rate(Grease) | AV1: Weight(Grease) | AW1: Cost(Grease) | AX1: Water Swellable Tape | AY1: RM Rate(Water Swellable Tape) | AZ1: Weight(Water Swellable Tape) | BA1: Cost(Water Swellable Tape) | BB1: Semi Conducting Water Swellable Tape | BC1: RM Rate(Semi Conducting Water Swellable Tape) | BD1: Weight(Semi Conducting Water Swellable Tape) | BE1: Cost(Semi Conducting Water Swellable Tape) | BF1: Semicon Tape | BG1: RM Rate(Semicon Tape) | BH1: Weight(Semicon Tape) | BI1: Cost(Semicon Tape) | BJ1: Glass Fiber Tape | BK1: RM Rate(Glass Fiber Tape) | BL1: Weight(Glass Fiber Tape) | BM1: Cost(Glass Fiber Tape) | BN1: Copper Wire 0.8MM | BO1: RM Rate(Copper Wire 0.8MM) | BP1: Weight(Copper Wire 0.8MM) | BQ1: Cost(Copper Wire 0.8MM) | BR1: Rubberized Cotton Tape | BS1: RM Rate(Rubberized Cotton Tape) | BT1: Weight(Rubberized Cotton Tape) | BU1: Cost(Rubberized Cotton Tape) | BV1: Water Tight Compound | BW1: RM Rate(Water Tight Compound) | BX1: Weight(Water Tight Compound) | BY1: Cost(Water Tight Compound) | BZ1: Drum Cost Per KM | CA1: Total RM Cost | CB1: FIRM % | CC1: Firm Value | CD1: MFG% | CE1: MFG Value | CF1: PROF% | CG1: Profit Value | CH1: 1st EX-Works | CI1: Intt % | CJ1: Intt Value | CK1: insp% | CL1: Insp Value | CM1: TTR CHARGES% | CN1: TTR Value | CO1: EX-Works Per KM | CP1: Freight Per KM | CQ1: Price Including Freight Per KM | CR1: GST % | CS1: GST Value | CT1: Price Including GST & Freight Per KM | CU1: QTY | CV1: Unit | CW1: Total Price Of Full QTY(Including Freight&GST) | CX1: PARTY LENGTH (IF STANDER LENGTH NOT MATCH WITH PAR | CY1: DRUM CODE | CZ1: DRUM SIZE (FxbXtx Ft)
A2: ENQ-19907-25-26 | C2: FC0700035 | D2: ACSR : RABBIT CONDUCTOR - 50 SQ. MM. (6/1/3.35) (XLPE INSULATED) | E2: WOOD | H2: 0 | J2: Alumimium | L2: 145 | P2: 0 | T2: 0 | V2: LT-XLPE | X2: 53 | AB2: 0 | AF2: 0 | AH2: ACSR CORE WIRE | AJ2: 69 | AN2: 0 | AR2: 0 | AV2: 0 | AZ2: 0 | BD2: 0 | BH2: 0 | BL2: 0 | BP2: 0 | BT2: 0 | BX2: 0 | BZ2: 1312.67 | CA2: 1312.67 | CH2: 1312.67 | CO2: 1312.67 | CQ2: 1312.67 | CR2: 0.18 | CS2: 236.28 | CT2: 1548.95 | CU2: 200 | CV2: KMS | CW2: 309790 | CX2: 3000 | CY2: MD0100073 | CZ2: DRUM - 48 X 14 X 26 X 2.25

Sheet AUTO CALCULATION SHEET (2)
A2: JODHPUR VIDYUT VITARAN NIGAM LIMITED
A4: TENDER SPECIFICATION NO () | B4: TN2143 (2026_JdVVN_562439_1)
A5: TENDER DESCRIPTION () | B5: LT XLPE Insulated ACSR Rabbit Conductor
A6: Last Date & Time of Submission () | B6: 11-Jun-2026 12:00 PM OPENING ON 11-Jun-2026 03:00 PM
A7: REVERSE AUCTION | B7: NOT MENTION
A8: Price () | B8: Base date for price variation : 01-05-2026 The price of XLPE Insulated ACSR RABBIT conductor shall be variable without any ceiling, based on the average prices of ex-prime producer of EC grade Aluminum rod and High Tensile Galvanized steel wire prevailing on 01-05-2026, as per CACMAI Circular. The average price of the EC grade Aluminum wire rod and price of High Tensile Galvanized steel wire shall be furnished along with the bid. No Price Variation shall be allowed on XLPE Insulation. No base price other than the prices prevailing on 01-05-2026 as per CACMAI Circular will be acceptable in any case. A. For every one Rupee, increase / decrease per Kg. in the above price of EC grade Aluminum wire Rod, the price per Km. for ACSR Rabbit Conductor shall be increase / decrease by @ Rs.145.00. B. For every one rupee, increase / decrease per Kg. in the above price of high tensile galvanized steel wire the price per Km. of ACSR Rabbit Conductor shall be increase / decrease by Rs.69.00. The above price variation bears no ceiling limit. PV1= (Al-Alo)*145/1000 ; PV2= (S- So)*69/1000 ; Net PV= PV1 + PV2
A9: Validity () | B9: 120 days from the next date of opening of technocommercial bid.
A10: Delivery Period () | B10: The delivery of quoted quantity of conductor should be commenced after 30 days from the date of receipt of purchase order and shall be completed in 05 months thereafter at equal monthly installments. In case of ordered quantity is different than the quoted quantity, then monthly delivery shall be adjusted proportionately. Bids of bidders in which monthly delivery schedule is not quoted shall be considered as Non Responsive.
A11: Payment Terms () | B11: The 70% payment shall be released after receipt of successful Test reports from CTL, JdVVNL Jodhpur for the mandatory testing checking on the samples selected from the material received at stores against first lot and subsequent lot(s) in anticipation of successful type test reports. The balance 30% payment shall be released after receipt of successful type test reports on the samples selected from the material received in the stores.
A12: Standard length () | B12: The standard length of the insulated ACSR RABBIT conductor drum shall be 1000 meters. A tolerance of (+/-) 5% on the standard length offered by the Bidder shall be permitted. All length outside this limit of tolerance shall be treated as random lengths. The maximum length in one drum shall be 3000 meter.
A13: Packing () | B13: The XLPE Insulated ACSR RABBIT Conductor shall be wound on a non returnable wooden drum conforming to IS: 10418/1982 of suitable size.
A14: Technical Specification
O18: Conductor | W18: AL ALLOY | Y18: Insulation Screening (Metallic) | AG18: Insulation Screening (Non-Metallic) | AI18: Insulation | AR18: POLY TAPE | AS18: Inner Sheath | BB18: Armouring | BM18: Outer Sheath | BY18: FILLER | BZ18: GREASE | CA18: Water swellable Tape | CB18: Semi conducting Water Swellable tape | CC18: SEMICON TAPE | CD18: GLASS FIBER TAPE | CE18: COPPER WIRE 0.8 MM | CF18: RUBBERIZED COTTON TAPE | CG18: Water Tight Compound | CH18: DRUM TYPE | CL18: DRUM COST PER KM | CM18: TOTAL RM COST | CN18: EXTRA CONSUMPTION | CO18: EXTRA CONSUMPTION VALUE | DA18: $A$1
A19: DOCKET NO. | B19: BASE DATE | C19: ITEM CODE | D19: PROPOSE ERP ITEM NAME | E19: EX-WORKS (PER KM) | F19: FREIGHT PER KM | G19: PRICE INCLUDING FREIGHT (PER KM) | H19: GST % | I19: GST VALUE | J19: PRICE INCLUDING GST & FREIGHT (PER KM) | K19: QTY | L19: Unit | M19: TOTAL PRICE OF FULL QTY (INCLUDING FRIGHT & GST) | N19: NON CHAIN BOM ID | O19: Alumimium | P19: Alumimium ALLOY | Q19: Copper | R19: AL-59 | S19: AL-4 | T19: AL-7 | U19: Flexible Copper | V19: Galvanized steel wire | W19: Alumimium | X19: Alumimium ALLOY | Y19: Coper tape - 0.1 mm | Z19: Copper Tape - 0.03 mm | AA19: Copper Tape - 0.035 mm | AB19: Copper Tape - 0.04 mm | AC19: Copper Tape - 0.045 mm | AD19: Copper Tape - 0.050 mm | AE19: Copper Tape - 0.060 mm | AF19: Copper Tape - 0.075 mm(DOUBLE) | AG19: Extruded semiconductive | AH19: Extruded Semiconductive(Stripable) | AI19: HT-XLPE | AJ19: LT-XLPE | AK19: TR XLPE | AL19: Type A PVC | AM19: Type C PVC (HR) | AN19: Type A PVC-1.45 | AO19: Type A PVC-FR | AP19: Type A PVC-FRLS | AQ19: Type A PVC-1.38 | AR19: POLY TAPE | AS19: FR PVC Type ST-1 | AT19: FR PVC Type ST-2 | AU19: FRLSH PVC Type ST-1 | AV19: FRLSH PVC Type ST-2 | AW19: PVC Type ST-1 | AX19: PVC Type ST-1-PRESSURE EXTRUDED | AY19: PVC Type ST-2 | AZ19: PVC COMPOUND 1.48 | BA19: PVC Type ST-2-PRESSURE EXTRUDED | BB19: ACSR CORE WIRE | BC19: ACSR DOG STEEL WIRE | BD19: Aluminium Flat Strip | BE19: Aluminium Round Wire | BF19: Alumimium Tape | BG19: Double Steel Tape | BH19: Galvanised Steel Flat Strip | BI19: Galvanised Steel Flat Strip (Double) | BJ19: Galvanised Steel Flat Strip-B | BK19: Galvanised Steel Round Wire | BL19: Galvanised Steel Round Wire (Double) | BM19: FR PVC Type ST-1 | BN19: FR PVC Type ST-2 | BO19: FRLSH PVC Type ST-1 | BP19: FRLSH PVC Type ST-2 | BQ19: ZHFR | BR19: PE-ST-3 | BS19: PE-ST-7 | BT19: PVC Type ST-1 | BU19: PVC Type ST-2 | BV19: PVC COMPOUND 1.48 | BW19: PVC Type ST-2-PRESSURE EXTRUDED | BX19: UV & Track Resistant XLPE | BY19: FILLER | BZ19: Grease | CA19: Water swellable Tape | CB19: Semi conducting Water Swellable tape | CC19: SEMICON TAPE | CD19: GLASS FIBER TAPE | CE19: COPPER WIRE 0.8 MM | CF19: RUBBERIZED COTTON TAPE | CG19: Water Tight Compound | CH19: PROPOSE DRUM TYPE | CI19: DRUM CODE | CJ19: DRUM SIZE (FxbXtx Ft) | CK19: PARTY STANDARD LENGTH (MTR) | CP19: MFG% | CQ19: MFG VALUE | CR19: PROF% | CS19: PROFIT VALUE | CT19: 1ST EX-WORKS | CU19: Intt % | CV19: INTT VALUE | CW19: insp% | CX19: INSP VALUE | CY19: TTR Charges% | CZ19: TTR Charges VALUE
O20: 388 | P20: =+IFERROR(VLOOKUP($P$19,Sheet1!J:L,2,0),0) -> 0 | Q20: =+IFERROR(VLOOKUP($Q$19,Sheet1!J:M,2,0),0) -> 0 | R20: =+IFERROR(VLOOKUP($R$19,Sheet1!J:M,2,0),0) -> 0 | S20: =+IFERROR(VLOOKUP($S$19,Sheet1!J:M,2,0),0) -> 0 | T20: =+IFERROR(VLOOKUP($T$19,Sheet1!J:M,2,0),0) -> 0 | U20: =+IFERROR(VLOOKUP($U$19,Sheet1!J:M,2,0),0) -> 0 | V20: =+IFERROR(VLOOKUP($V$19,Sheet1!J:M,2,0),0) -> 0 | W20: =+IFERROR(VLOOKUP($W$19,Sheet1!N:Q,2,0),0) -> 0 | X20: =+IFERROR(VLOOKUP($X$19,Sheet1!N:O,2,0),0) -> 0 | Y20: =+IFERROR(VLOOKUP($Y$19,Sheet1!F:I,2,0),0) -> 0 | Z20: =+IFERROR(VLOOKUP($Z$19,Sheet1!F:I,2,0),0) -> 0 | AA20: =+IFERROR(VLOOKUP($AA$19,Sheet1!F:I,2,0),0) -> 0 | AB20: =+IFERROR(VLOOKUP($AB$19,Sheet1!F:I,2,0),0) -> 0 | AC20: =+IFERROR(VLOOKUP($AC$19,Sheet1!F:I,2,0),0) -> 0 | AD20: =+IFERROR(VLOOKUP($AD$19,Sheet1!F:I,2,0),0) -> 0 | AE20: =+IFERROR(VLOOKUP($AE$19,Sheet1!F:I,2,0),0) -> 0 | AF20: =+IFERROR(VLOOKUP($AF$19,Sheet1!F:I,2,0),0) -> 0 | AG20: =+IFERROR(VLOOKUP($AG$19,Sheet1!R:U,2,0),0) -> 0 | AH20: =+IFERROR(VLOOKUP($AH$19,Sheet1!R:U,2,0),0) -> 0 | AI20: =+IFERROR(VLOOKUP($AI$19,Sheet1!V:Y,2,0),0) -> 0 | AJ20: 147 | AK20: =+IFERROR(VLOOKUP($AK$19,Sheet1!V:Y,2,0),0) -> 0 | AL20: =+IFERROR(VLOOKUP($AL$19,Sheet1!V:Y,2,0),0) -> 0 | AM20: =+IFERROR(VLOOKUP($AM$19,Sheet1!V:Y,2,0),0) -> 0 | AN20: =+IFERROR(VLOOKUP($AN$19,Sheet1!V:Y,2,0),0) -> 0 | AO20: =+IFERROR(VLOOKUP($AO$19,Sheet1!V:Y,2,0),0) -> 0 | AP20: =+IFERROR(VLOOKUP($AP$19,Sheet1!V:Y,2,0),0) -> 0 | AQ20: =+IFERROR(VLOOKUP($AQ$19,Sheet1!V:Y,2,0),0) -> 0 | AR20: =+IFERROR(VLOOKUP($AR$19,Sheet1!Z2:AA840,2,0),0) -> 0 | AS20: =+IFERROR(VLOOKUP($AS$19,Sheet1!AD2:AG840,2,0),0) -> 0 | AT20: =+IFERROR(VLOOKUP($AT$19,Sheet1!AD2:AG840,2,0),0) -> 0 | AU20: =+IFERROR(VLOOKUP($AU$19,Sheet1!AD2:AG840,2,0),0) -> 0 | AV20: =+IFERROR(VLOOKUP($AV$19,Sheet1!AD2:AG840,2,0),0) -> 0 | AW20: =+IFERROR(VLOOKUP($AW$19,Sheet1!AD2:AG840,2,0),0) -> 0 | AX20: =+IFERROR(VLOOKUP($AX$19,Sheet1!AD2:AG840,2,0),0) -> 0 | AY20: =+IFERROR(VLOOKUP($AY$19,Sheet1!AD2:AG840,2,0),0) -> 0 | AZ20: =+IFERROR(VLOOKUP($AZ$19,Sheet1!AD2:AG840,2,0),0) -> 0 | BA20: =+IFERROR(VLOOKUP($BA$19,Sheet1!AD2:AG840,2,0),0) -> 0 | BB20: 84 | BC20: =+IFERROR(VLOOKUP($BC$19,Sheet1!AH2:AK840,2,0),0) -> 0 | BD20: =+IFERROR(VLOOKUP($BD$19,Sheet1!AH2:AK840,2,0),0) -> 0 | BE20: =+IFERROR(VLOOKUP($BE$19,Sheet1!AH2:AK840,2,0),0) -> 0 | BF20: =+IFERROR(VLOOKUP($BF$19,Sheet1!AH2:AK840,2,0),0) -> 0 | BG20: =+IFERROR(VLOOKUP($BG$19,Sheet1!AH2:AK840,2,0),0) -> 0 | BH20: =+IFERROR(VLOOKUP($BH$19,Sheet1!AH2:AK840,2,0),0) -> 0 | BI20: =+IFERROR(VLOOKUP($BI$19,Sheet1!AH2:AK840,2,0),0) -> 0 | BJ20: =+IFERROR(VLOOKUP($BJ$19,Sheet1!AH2:AK840,2,0),0) -> 0 | BK20: =+IFERROR(VLOOKUP($BK$19,Sheet1!AH2:AK840,2,0),0) -> 0 | BL20: =+IFERROR(VLOOKUP($BL$19,Sheet1!AH2:AK840,2,0),0) -> 0 | BM20: =+IFERROR(VLOOKUP($BM$19,Sheet1!AL2:AO840,2,0),0) -> 0 | BN20: =+IFERROR(VLOOKUP($BN$19,Sheet1!AL2:AO840,2,0),0) -> 0 | BO20: =+IFERROR(VLOOKUP($BO$19,Sheet1!AL2:AO840,2,0),0) -> 0 | BP20: =+IFERROR(VLOOKUP($BP$19,Sheet1!AL2:AO840,2,0),0) -> 0 | BQ20: =+IFERROR(VLOOKUP($BQ$19,Sheet1!AL2:AO840,2,0),0) -> 0 | BR20: =+IFERROR(VLOOKUP($BR$19,Sheet1!AL2:AO840,2,0),0) -> 0 | BS20: =+IFERROR(VLOOKUP($BS$19,Sheet1!AL2:AO840,2,0),0) -> 0 | BT20: =+IFERROR(VLOOKUP($BT$19,Sheet1!AL2:AO840,2,0),0) -> 0 | BU20: =+IFERROR(VLOOKUP($BU$19,Sheet1!AL2:AO840,2,0),0) -> 0 | BV20: =+IFERROR(VLOOKUP($BV$19,Sheet1!AL2:AO840,2,0),0) -> 0 | BW20: =+IFERROR(VLOOKUP($BW$19,Sheet1!AL2:AO840,2,0),0) -> 0 | BX20: =+IFERROR(VLOOKUP($BX$19,Sheet1!AL2:AO840,2,0),0) -> 0 | BY20: =+IFERROR(VLOOKUP($BY$19,Sheet1!AP2:AS840,2,0),0) -> 0 | BZ20: =+IFERROR(VLOOKUP($BZ$19,Sheet1!AT2:AW840,2,0),0) -> 0 | CA20: =+IFERROR(VLOOKUP($CA$19,Sheet1!AX2:BA840,2,0),0) -> 0 | CB20: =+IFERROR(VLOOKUP($CB$19,Sheet1!BB2:BE840,2,0),0) -> 0 | CC20: =+IFERROR(VLOOKUP($CC$19,Sheet1!BF2:BI840,2,0),0) -> 0 | CD20: =+IFERROR(VLOOKUP($CD$19,Sheet1!BJ2:BM840,2,0),0) -> 0 | CE20: =+IFERROR(VLOOKUP($CE$19,Sheet1!BN2:BQ840,2,0),0) -> 0 | CF20: =+IFERROR(VLOOKUP($CF$19,Sheet1!BR2:BU840,2,0),0) -> 0 | CG20: =+IFERROR(VLOOKUP($CG$19,Sheet1!BV2:BY840,2,0),0) -> 0
A21: =Sheet1!A2 -> ENQ-19907-25-26 | B21: 46143 | C21: =Sheet1!C2 -> FC0700035 | D21: =Sheet1!D2 -> ACSR : RABBIT CONDUCTOR - 50 SQ. MM. (6/1/3.35) (XLPE INSULATED) | E21: =CT21+CV21+CX21+CZ21 -> 100000 | F21: =ROUNDUP(M26,0) -> 2200 | G21: =E21+F21 -> 102200 | H21: =Sheet1!CR2 -> 0.18 | I21: =G21*H21 -> 18396 | J21: =G21+I21 -> 120596 | K21: =Sheet1!CU2 -> 200 | L21: =Sheet1!CV2 -> KMS | M21: =J21*K21 -> 24119200 | N21: IS | O21: =+IFERROR(VLOOKUP($O$19,Sheet1!J2:L2,3,0),0) -> 145 | P21: =+IFERROR(VLOOKUP($P$19,Sheet1!J2:L2,3,0),0) -> 0 | Q21: =+IFERROR(VLOOKUP($Q$19,Sheet1!J2:M2,3,0),0) -> 0 | R21: =+IFERROR(VLOOKUP($R$19,Sheet1!J2:M2,3,0),0) -> 0 | S21: =+IFERROR(VLOOKUP($S$19,Sheet1!J2:M2,3,0),0) -> 0 | T21: =+IFERROR(VLOOKUP($T$19,Sheet1!J2:M2,3,0),0) -> 0 | U21: =+IFERROR(VLOOKUP($U$19,Sheet1!J2:M2,3,0),0) -> 0 | V21: =+IFERROR(VLOOKUP($V$19,Sheet1!J2:M2,3,0),0) -> 0 | W21: =+IFERROR(VLOOKUP($W$19,Sheet1!N2:Q2,3,0),0) -> 0 | X21: =+IFERROR(VLOOKUP($X$19,Sheet1!N2:Q2,3,0),0) -> 0 | Y21: =+IFERROR(VLOOKUP($Y$19,Sheet1!F2:I2,3,0),0) -> 0 | Z21: =+IFERROR(VLOOKUP($Z$19,Sheet1!F2:I2,3,0),0) -> 0 | AA21: =+IFERROR(VLOOKUP($AA$19,Sheet1!F2:I2,3,0),0) -> 0 | AB21: =+IFERROR(VLOOKUP($AB$19,Sheet1!F2:I2,3,0),0) -> 0 | AC21: =+IFERROR(VLOOKUP($AC$19,Sheet1!F2:I2,3,0),0) -> 0 | AD21: =+IFERROR(VLOOKUP($AD$19,Sheet1!F2:I2,3,0),0) -> 0 | AE21: =+IFERROR(VLOOKUP($AE$19,Sheet1!F2:I2,3,0),0) -> 0 | AF21: =+IFERROR(VLOOKUP($AF$19,Sheet1!F2:I2,3,0),0) -> 0 | AG21: =+IFERROR(VLOOKUP($AG$19,Sheet1!R2:U2,3,0),0) -> 0 | AH21: =+IFERROR(VLOOKUP($AH$19,Sheet1!R2:U2,3,0),0) -> 0 | AI21: =+IFERROR(VLOOKUP($AI$19,Sheet1!V2:Y2,3,0),0) -> 0 | AJ21: 56 | AK21: =+IFERROR(VLOOKUP($AK$19,Sheet1!V2:Y2,3,0),0) -> 0 | AL21: =+IFERROR(VLOOKUP($AL$19,Sheet1!V2:Y2,3,0),0) -> 0 | AM21: =+IFERROR(VLOOKUP($AM$19,Sheet1!V2:Y2,3,0),0) -> 0 | AN21: =+IFERROR(VLOOKUP($AN$19,Sheet1!V2:Y2,3,0),0) -> 0 | AO21: =+IFERROR(VLOOKUP($AO$19,Sheet1!V2:Y2,3,0),0) -> 0 | AP21: =+IFERROR(VLOOKUP($AP$19,Sheet1!V2:Y2,3,0),0) -> 0 | AQ21: =+IFERROR(VLOOKUP($AQ$19,Sheet1!V2:Y2,3,0),0) -> 0 | AR21: =+IFERROR(VLOOKUP($AR$19,Sheet1!Z2:AB2,3,0),0) -> 0 | AS21: =+IFERROR(VLOOKUP($AS$19,Sheet1!AD2:AG2,3,0),0) -> 0 | AT21: =+IFERROR(VLOOKUP($AT$19,Sheet1!AD2:AG2,3,0),0) -> 0 | AU21: =+IFERROR(VLOOKUP($AU$19,Sheet1!AD2:AG2,3,0),0) -> 0 | AV21: =+IFERROR(VLOOKUP($AV$19,Sheet1!AD2:AG2,3,0),0) -> 0 | AW21: =+IFERROR(VLOOKUP($AW$19,Sheet1!AD2:AG2,3,0),0) -> 0 | AX21: =+IFERROR(VLOOKUP($AX$19,Sheet1!AD2:AG2,3,0),0) -> 0 | AY21: =+IFERROR(VLOOKUP($AY$19,Sheet1!AD2:AG2,3,0),0) -> 0 | AZ21: =+IFERROR(VLOOKUP($AZ$19,Sheet1!AD2:AG2,3,0),0) -> 0 | BA21: =+IFERROR(VLOOKUP($BA$19,Sheet1!AD2:AG2,3,0),0) -> 0 | BB21: =+IFERROR(VLOOKUP($BB$19,Sheet1!AH2:AK2,3,0),0) -> 69 | BC21: =+IFERROR(VLOOKUP($BC$19,Sheet1!AH2:AK2,3,0),0) -> 0 | BD21: =+IFERROR(VLOOKUP($BD$19,Sheet1!AH2:AK2,3,0),0) -> 0 | BE21: =+IFERROR(VLOOKUP($BE$19,Sheet1!AH2:AK2,3,0),0) -> 0 | BF21: =+IFERROR(VLOOKUP($BF$19,Sheet1!AH2:AK2,3,0),0) -> 0 | BG21: =+IFERROR(VLOOKUP($BG$19,Sheet1!AH2:AK2,3,0),0) -> 0 | BH21: =+IFERROR(VLOOKUP($BH$19,Sheet1!AH2:AK2,3,0),0) -> 0 | BI21: =+IFERROR(VLOOKUP($BI$19,Sheet1!AH2:AK2,3,0),0) -> 0 | BJ21: =+IFERROR(VLOOKUP($BJ$19,Sheet1!AH2:AK2,3,0),0) -> 0 | BK21: =+IFERROR(VLOOKUP($BK$19,Sheet1!AH2:AK2,3,0),0) -> 0 | BL21: =+IFERROR(VLOOKUP($BL$19,Sheet1!AH2:AK2,3,0),0) -> 0 | BM21: =+IFERROR(VLOOKUP($BM$19,Sheet1!AL2:AO2,3,0),0) -> 0 | BN21: =+IFERROR(VLOOKUP($BN$19,Sheet1!AL2:AO2,3,0),0) -> 0 | BO21: =+IFERROR(VLOOKUP($BO$19,Sheet1!AL2:AO2,3,0),0) -> 0 | BP21: =+IFERROR(VLOOKUP($BP$19,Sheet1!AL2:AO2,3,0),0) -> 0 | BQ21: =+IFERROR(VLOOKUP($BQ$19,Sheet1!AL2:AO2,3,0),0) -> 0 | BR21: =+IFERROR(VLOOKUP($BR$19,Sheet1!AL2:AO2,3,0),0) -> 0 | BS21: =+IFERROR(VLOOKUP($BS$19,Sheet1!AL2:AO2,3,0),0) -> 0 | BT21: =+IFERROR(VLOOKUP($BT$19,Sheet1!AL2:AO2,3,0),0) -> 0 | BU21: =+IFERROR(VLOOKUP($BU$19,Sheet1!AL2:AO2,3,0),0) -> 0 | BV21: =+IFERROR(VLOOKUP($BV$19,Sheet1!AL2:AO2,3,0),0) -> 0 | BW21: =+IFERROR(VLOOKUP($BW$19,Sheet1!AL2:AO2,3,0),0) -> 0 | BX21: =+IFERROR(VLOOKUP($BX$19,Sheet1!AL2:AO2,3,0),0) -> 0 | BY21: =+IFERROR(VLOOKUP($BY$19,Sheet1!AP2:AS2,3,0),0) -> 0 | BZ21: =+IFERROR(VLOOKUP($BZ$19,Sheet1!AT2:AW2,3,0),0) -> 0 | CA21: =+IFERROR(VLOOKUP($CA$19,Sheet1!AX2:BA2,3,0),0) -> 0 | CB21: =+IFERROR(VLOOKUP($CB$19,Sheet1!BB2:BE2,3,0),0) -> 0 | CC21: =+IFERROR(VLOOKUP($CC$19,Sheet1!BF2:BI2,3,0),0) -> 0 | CD21: =+IFERROR(VLOOKUP($CD$19,Sheet1!BJ2:BM2,3,0),0) -> 0 | CE21: =+IFERROR(VLOOKUP($CE$19,Sheet1!BN2:BQ2,3,0),0) -> 0 | CF21: =+IFERROR(VLOOKUP($CF$19,Sheet1!BR2:BU2,3,0),0) -> 0 | CG21: =+IFERROR(VLOOKUP($CG$19,Sheet1!BV2:BY2,3,0),0) -> 0 | CH21: =Sheet1!E2 -> WOOD | CI21: =Sheet1!CY2 -> MD0100073 | CJ21: =Sheet1!CZ2 -> DRUM - 48 X 14 X 26 X 2.25 | CK21: =Sheet1!CX2 -> 3000 | CL21: =2894/3 -> 964.66667 | CM21: =SUMPRODUCT($O$20:$CG$20,O21:CG21)+CL21 -> 71252.667 | CN21: =Sheet1!CB2 -> 0 | CO21: =CM21*CN21 -> 0 | CP21: 0.34947716 | CQ21: =CM21*CP21 -> 24901.179 | CR21: 0 | CS21: =CM21*CR21 -> 0 | CT21: =CM21+CO21+CQ21+CS21 -> 96153.846 | CU21: 0.02 | CV21: =CT21*CU21 -> 1923.0769 | CW21: 0.02 | CX21: =CT21*CW21 -> 1923.0769 | CY21: =Sheet1!CM2 -> 0 | CZ21: =CY21*CT21 -> 0
E25: Order Quantity | F25: Stnd Length | G25: Truck type | H25: Fare of one truck | I25: No of Drum in one truck | J25: Total length in one Truck | K25: No of Truck | L25: Total Freight | M25: Freight per KM | O25: CABLE WEIGHT KG/KM | AJ25: DRUM WEIGHT | BB25: CABLE+DRUM WEIGHT | CH25: TRUCK WEIGHT
E26: =K21 -> 200 | F26: =CK21/1000 -> 3 | G26: 16 MT | H26: 88000 | I26: 16 | J26: =F26*I26 -> 48 | K26: =ROUNDUP((E26/J26),0) -> 5 | L26: =H26*K26 -> 440000 | M26: =L26/E26 -> 2200 | O26: =SUM(O21:BB21) -> 270 | AJ26: =125+25 -> 150 | BB26: =((O26*F26)+AJ26) -> 960 | CH26: =BB26*I26 -> 15360
E29: Estimated Unit FOR Destination Price | F29: Our Unit FOR Destination Price | G29: Diff % from our cost
E30: 65405.17 | F30: =J21 -> 120596 | G30: =((F30-E30)/F30)*100 -> 45.765059

Sheet PV AUTO CALCULATION SHEET
A1: JODHPUR VIDYUT VITARAN NIGAM LTD.
A2: Base Date | B2: 46143
A3: PV Terms (IEEMA CIRCULAR) | B3: Base date for price variation : 01-05-2026 The price of XLPE Insulated ACSR RABBIT conductor shall be variable without any ceiling, based on the average prices of ex-prime producer of EC grade Aluminum rod and High Tensile Galvanized steel wire prevailing on 01-05-2026, as per CACMAI Circular. The average price of the EC grade Aluminum wire rod and price of High Tensile Galvanized steel wire shall be furnished along with the bid. PV1= (Al-Alo)*145/1000 ; PV2= (S- So)*69/1000 ; Net PV= PV1 + PV2 No Price Variation shall be allowed on XLPE Insulation.
A4: PV FORMULA
A5: P=Po + W (Al - Alo) + Fe (fe-feo)
A8: Item | B8: Ex-Work
A9: ='AUTO CALCULATION SHEET (2)'!D21 -> ACSR : RABBIT CONDUCTOR - 50 SQ. MM. (6/1/3.35) (XLPE INSULATED) | B9: ='AUTO CALCULATION SHEET (2)'!E21 -> 100000
A12: Item | B12: Calculation part | C12: Date of Inspection | D12: Applicable Date | G12: BASE DATE | J12: FACTORS | L12: Ex-Work Po | M12: PVC of Al | N12: PVC of Fe | O12: PVC per KM | P12: Billing Price/PKM | Q12: VALUE ADDITION CALCULATION
D13: Date | E13: Al | F13: fe | G13: Date | H13: Alo | I13: feo
J14: W | K14: Fe | Q14: ='AUTO CALCULATION SHEET (2)'!O19 -> Alumimium | R14: ='AUTO CALCULATION SHEET (2)'!AJ19 -> LT-XLPE | S14: ='AUTO CALCULATION SHEET (2)'!BB19 -> ACSR CORE WIRE | T14: RMC | U14: Drum | V14: RMC+DRUM | W14: VA | X14: Groos VA% | Y14: Mfg % | Z14: Int % | AA14: Ins% | AB14: Net VA
Q15: 408 | R15: 147 | S15: 83
A16: =A9 -> ACSR : RABBIT CONDUCTOR - 50 SQ. MM. (6/1/3.35) (XLPE INSULATED) | C16: PROVISIONAL | D16: 46181 | E16: 451350.5 | F16: 169250 | G16: =$B$2 -> 46143 | H16: 437550 | I16: 169250 | J16: 0.145 | K16: 0.069 | L16: =B9 -> 100000 | M16: =J16*(E16-H16) -> 2001.0725 | N16: =K16*(F16-I16) -> 0 | O16: =M16+N16 -> 2001.0725 | P16: =L16+O16 -> 102001.07 | Q16: ='AUTO CALCULATION SHEET (2)'!O21 -> 145 | R16: ='AUTO CALCULATION SHEET (2)'!AJ21 -> 56 | S16: ='AUTO CALCULATION SHEET (2)'!BB21 -> 69 | T16: =SUMPRODUCT($Q$15:$S$15,Q16:S16) -> 73119 | U16: ='AUTO CALCULATION SHEET (2)'!CL21 -> 964.66667 | V16: =T16+U16 -> 74083.667 | W16: =+P16-V16 -> 27917.406 | X16: =W16/V16*100% -> 0.37683618 | Z16: 0.02 | AA16: 0.02 | AB16: =X16-SUM(Y16:AA16) -> 0.33683618

Sheet terms
A1: The quoted prices are on Firm inclusive of packing and forwading but exclusive of GST Statutory levies.
A2: The quoted prices are on VARIABLE basis with PV base Date: DD/MM/YYYY as per "IEEMA", inclusive of packing and forwading but exclusive of GST Statutory levies.
A4: The above prices are quoted on Ex-works basis, where freight will be charged extra.
A5: The above prices are quoted on FOR Destination basis, where freight is included, refer Price offer.
A6: The above prices are quoted on Ex-works+Freight basis.
A8: 20% Advance and Balance against PI (Proforma Invoice) prior to dispatch
A9: 100% against "90 days" LC, where 90 days usance interest will be borne by LPIPL
A10: 100% against "120 days" LC, where 120 days usance interest will be borne by LPIPL
A11: 100% against "45 days" LC, where 45 days usance interest will be borne by LPIPL
A12: 100% against "60 days" LC, where 60 days usance interest will be borne by LPIPL
A13: 100% against "30 days" LC, where 30 days usance interest will be borne by LPIPL
A14: 100% against 60 days PDC from the date of MRC/MRN
... A27: Negotiable
