Workbook

Sheet Sheet1
A1: DOCKET NO. | B1: Base Date | C1: ITEM CODE | D1: PROPOSE ERP ITEM NAME | E1: PROPOSE DRUM TYPE | F1: Insulation Screening (Metallic) | G1: RM RATE (Insulation Screening (Metallic)) | H1: Weight (Insulation Screening (Metallic)) | I1: COST(Insulation Screening (Metallic)) | J1: Conductor | K1: RM RATE(Conductor) | L1: WEIGHT(Conductor) | M1: COST(Conductor) | N1: AL ALLOY | O1: RM RATE(Alu Alloy) | P1: WEIGHT(Alu Alloy) | Q1: COST(Alu Alloy) | R1: Insulation Screening (Non-Metallic) | S1: RM RATE(Insulation Screening (Non-Metallic)) | T1: WEIGHT(Insulation Screening (Non-Metallic)) | U1: COST(Insulation Screening (Non-Metallic)) | V1: Insulation | W1: RM RATE(Insulation) | X1: WEIGHT(Insulation) | Y1: COST(Insulation) | Z1: POLY TAPE | AA1: RM RATE (Poly Tape) | AB1: WEIGHT (Poly Tape) | AC1: COST(Poly Tape) | AD1: Inner Sheath | AE1: RM RATE(Inner Sheath) | AF1: WEIGHT(Inner Sheath) | AG1: COST(Inner Sheath) | AH1: Armouring | AI1: RM RATE(Armouring) | AJ1: WEIGHT(Armouring) | AK1: COST(Armouring) | AL1: Outer Sheath | AM1: RM RATE(Outer Sheath) | AN1: WEIGHT(Outer Sheath) | AO1: COST(Outer Sheath) | AP1: FILLER | AQ1: RM RATE(Filler) | AR1: WEIGHT(Filler) | AS1: COST(Filler) | AT1: GREASE | AU1: RM RATE(Grease) | AV1: WEIGHT(Grease) | AW1: COST(Grease) | AX1: Water swellable Tape | AY1: RM RATE(Water swellable Tape) | AZ1: WEIGHT(Water swellable Tape) | BA1: COST(Water swellable Tape) | BB1: Semi conducting Water Swellable tape | BC1: RM RATE(Semi conducting Water Swellable tape) | BD1: WEIGHT(Semi conducting Water Swellable tape) | BE1: COST(Semi conducting Water Swellable tape) | BF1: SEMICON TAPE | BG1: RM RATE(SEMICON TAPE) | BH1: WEIGHT(SEMICON TAPE) | BI1: COST(SEMICON TAPE) | BJ1: GLASS FIBER TAPE | BK1: RM RATE(GLASS FIBER TAPE) | BL1: WEIGHT(GLASS FIBER TAPE) | BM1: COST(GLASS FIBER TAPE) | BN1: COPPER WIRE 0.8 MM | BO1: RM RATE(COPPER WIRE 0.8 MM) | BP1: WEIGHT(COPPER WIRE 0.8 MM) | BQ1: COST(COPPER WIRE 0.8 MM) | BR1: RUBBERIZED COTTON TAPE | BS1: RM RATE(RUBBERIZED COTTON TAPE) | BT1: WEIGHT(RUBBERIZED COTTON TAPE) | BU1: COST(RUBBERIZED COTTON TAPE) | BV1: Water Tight Compound | BW1: RM RATE(Water Tight Compound) | BX1: WEIGHT(Water Tight Compound) | BY1: COST(Water Tight Compound) | BZ1: DRUM COST PER KM | CA1: TOTAL RM COST | CB1: FIRM % | CC1: FIRM VALUE | CD1: MFG% | CE1: MFG VALUE | CF1: PROF% | CG1: PROFIT VALUE | CH1: 1ST EX-WORKS | CI1: Intt % | CJ1: INTT VALUE | CK1: insp% | CL1: INSP VALUE | CM1: EX-WORKS (PER KM) | CN1: FREIGHT PER KM | CO1: PRICE INCLUDING FREIGHT (PER KM) | CP1: GST % | CQ1: GST VALUE | CR1: PRICE INCLUDING GST & FREIGHT (PER KM) | CS1: QTY | CT1: Unit | CU1: TOTAL PRICE OF FULL QTY (INCLUDING FRIGHT & GST) | CV1: DRUM CODE | CW1: DRUM SIZE (FxbXtx Ft) | CX1: PARTY STANDARD LENGTH (MTR)
A2: ENQ-11515-22-23 | B2: 45170 | C2: FA1300002 | D2: 3 CORE X 185 SQ. MM AL/ARM - STRIP (XLPE) - 11 KV | E2: WOOD | F2: Copper Tape - 0.03 mm | G2: 859.6 | H2: 75 | I2: 64470 | J2: Alumimium | K2: 212 | L2: 1498.5 | M2: 317682 | P2: 0 | R2: Extruded Semiconductive(Stripable) | S2: 206 | T2: 276 | U2: 56856 | V2: HT-XLPE | W2: 154 | X2: 663 | Y2: 102102 | AB2: 0 | AD2: PVC Type ST-2 | AE2: 61.6 | AF2: 237 | AG2: 14599.2 | AH2: Galvanised Steel Flat Strip | AI2: 77.87 | AJ2: 975 | AK2: 75923.25 | AL2: FRLSH PVC Type ST-2 | AM2: 94 | AN2: 755 | AO2: 70970 | AP2: FILLER | AQ2: 29 | AR2: 914 | AS2: 26506 | AV2: 0 | AZ2: 92 | BD2: 0 | BH2: 0 | BJ2: GLASS FIBER TAPE | BK2: 365 | BL2: 72 | BM2: 26280 | BP2: 0 | BT2: 0 | BX2: 0 | BZ2: 43826 | CA2: 799214.45 | CH2: 799214.45 | CM2: 799214.45 | CO2: 799214.45 | CR2: 799214.45 | CS2: 49.38 | CT2: KMS | CU2: 39465210 | CV2: MD0100079 | CW2: DRUM - 80 X 35 X 39 X 3 | CX2: 500

Sheet AUTO CALCULATION SHEET (2)
A2: KANPUR ELECTRICITY SUPPLY COMPANY LIMITED
A4: TENDER SPECIFICATION NO () | B4: 76/NVY/ABP/23-24
A5: TENDER DESCRIPTION () | B5: 11 KV HT XLPE Cable size 3x185sqmm.
A6: Last Date & Time of Submission () | B6: 06.11.2023
A7: REVERSE AUCTION | B7: Not Mention.
A8: Price () | B8: The prices will be variable and as per IEEMA Date 01.09.2023.
A9: Validity () | B9: The bidder’s proposal must remain valid for acceptance for a period of 180 days from the date of opening of bid (Envelope-1) or any other extended date for their receipt or any other extended period consented upon by the bidders. KESCO may ask the bidder to extend the validity period of their bid) and during this period no bidder shall be allowed to withdraw their bid. Any such withdrawal during the said period will entail forfeiture of EMD deposited by the bidder with their bid. The bidders who agree to such extension shall confirm that they maintain the availability of the professional staff nominated in the proposal or in their confirmation of extension of validity of the proposal.
A10: Payment Terms () | B10: Ninety percent of the f.o.r. contract value of the plant in rupees on receipt by the purchaser of the contractor's invoice giving the number and date of railway receipt covering the dispatch of the plant from the Indian port and of the advice note giving case number and contents, together with a certificate by the contractor to the effect that the plant detailed in the said advice note has actually been dispatched under the says railway receipt and that the contract value of the said plant so dispatched is not less than the amount entered in the invoice. Ten percent of the f.o.r. contract value on presentation of the contractor's invoice when each commercially useable section of the plant is completed and the last portion of such section has been dispatched and the whole material has been delivered at the place fixed for delivery and checked at the site of the work within one month of such delivery, whichever is earlier.
A11: Standard length () | B11: The cables shall be supplied in standard lengths i.e 500.± 5% Non-standard length of not less than 100 meters is acceptable. Total Non-Standard should not exceed 5% of the ordered quantity.
A12: Packing () | B12: The cable shall be supplied on non-returnable Steel (for 3x300sqmm cable)/wooden drums of heavy standard construction conforming to IS: 10418:1982 and latest amendment thereof and being suitable for transport by goods train or truck and for storage at site. The wood used for construction of the drums shall be properly seasoned and wood preservative shall be applied to the entire drum.
A13: Technical Specification
N15: =Sheet1!J1 -> Conductor | S15: AL ALLOY | U15: Insulation Screening (Metallic) | AC15: Insulation Screening (Non-Metallic) | AE15: Insulation | AK15: POLY TAPE | AL15: Inner Sheath | AS15: Armouring | BC15: Outer Sheath | BM15: FILLER | BN15: GREASE | BO15: Water swellable Tape | BP15: Semi conducting Water Swellable tape | BQ15: SEMICON TAPE | BR15: GLASS FIBER TAPE | BS15: COPPER WIRE 0.8 MM | BT15: RUBBERIZED COTTON TAPE | BU15: Water Tight Compound | BZ15: DRUM COST PER KM | CA15: TOTAL RM COST | CB15: EXTRA CONSUMPTION | CC15: EXTRA CONSUMPTION VALUE
A16: DOCKET NO. | B16: =Sheet1!B1 -> Base Date | C16: ITEM CODE | D16: PROPOSE ERP ITEM NAME | E16: EX-WORKS (PER KM) | F16: FREIGHT PER KM | G16: PRICE INCLUDING FREIGHT (PER KM) | H16: GST % | I16: GST VALUE | J16: PRICE INCLUDING GST & FREIGHT (PER KM) | K16: QTY | L16: Unit | M16: TOTAL PRICE OF FULL QTY (INCLUDING FRIGHT & GST) | N16: Alumimium | O16: Alumimium ALLOY | P16: Copper | Q16: Flexible Copper | R16: Galvanized steel wire | S16: Alumimium | T16: Alumimium ALLOY | U16: Coper tape - 0.1 mm | V16: Copper Tape - 0.03 mm | W16: Copper Tape - 0.035 mm | X16: Copper Tape - 0.04 mm | Y16: Copper Tape - 0.045 mm | Z16: Copper Tape - 0.050 mm | AA16: Copper Tape - 0.060 mm | AB16: Copper Tape - 0.075 mm(DOUBLE) | AC16: Extruded semiconductive | AD16: Extruded Semiconductive(Stripable) | AE16: HT-XLPE | AF16: LT-XLPE | AG16: TR XLPE | AH16: Type A PVC | AI16: Type C PVC (HR) | AJ16: XLPE | AK16: POLY TAPE | AL16: FR PVC Type ST-1 | AM16: FR PVC Type ST-2 | AN16: FRLSH PVC Type ST-2 | AO16: PVC Type ST-1 | AP16: PVC Type ST-1-PRESSURE EXTRUDED | AQ16: PVC Type ST-2 | AR16: PVC Type ST-2-PRESSURE EXTRUDED | AS16: ACSR CORE WIRE | AT16: ACSR DOG STEEL WIRE | AU16: Aluminium Flat Strip | AV16: Aluminium Round Wire | AW16: Double Steel Tape | AX16: Galvanised Steel Flat Strip | AY16: Galvanised Steel Flat Strip (Double) | AZ16: Galvanised Steel Flat Strip-B | BA16: Galvanised Steel Round Wire | BB16: Galvanised Steel Round Wire (Double) | BC16: FR PVC Type ST-1 | BD16: FR PVC Type ST-2 | BE16: FRLSH PVC Type ST-1 | BF16: FRLSH PVC Type ST-2 | BG16: PE, ST-3 | BH16: PE, ST-7 | BI16: PVC Type ST-1 | BJ16: PVC Type ST-2 | BK16: PVC Type ST-2-PRESSURE EXTRUDED | BL16: UV & Track Resistant XLPE | BM16: FILLER | BN16: Grease | BO16: Water swellable Tape | BP16: Semi conducting Water Swellable tape | BQ16: SEMICON TAPE | BR16: GLASS FIBER TAPE | BS16: COPPER WIRE 0.8 MM | BT16: RUBBERIZED COTTON TAPE | BU16: Water Tight Compound | BV16: =Sheet1!E1 -> PROPOSE DRUM TYPE | BW16: =Sheet1!CV1 -> DRUM CODE | BX16: =Sheet1!CW1 -> DRUM SIZE (FxbXtx Ft) | BY16: =Sheet1!CX1 -> PARTY STANDARD LENGTH (MTR) | BZ16: CONFIRMED FROM SOMBHU SIR | CD16: MFG% | CE16: MFG VALUE | CF16: PROF% | CG16: PROFIT VALUE | CH16: 1ST EX-WORKS | CI16: Intt % | CJ16: INTT VALUE | CK16: insp% | CL16: INSP VALUE
N17: 212 | O17: =+IFERROR(VLOOKUP($O$16,Sheet1!J:L,2,0),0) -> 0 | P17: =+IFERROR(VLOOKUP($P$16,Sheet1!J:M,2,0),0) -> 0 | Q17: =+IFERROR(VLOOKUP($Q$16,Sheet1!J:M,2,0),0) -> 0 | R17: =+IFERROR(VLOOKUP($R$16,Sheet1!J:M,2,0),0) -> 0 | S17: =+IFERROR(VLOOKUP($S$16,Sheet1!N:Q,2,0),0) -> 0 | T17: =+IFERROR(VLOOKUP($T$16,Sheet1!N:O,2,0),0) -> 0 | U17: =+IFERROR(VLOOKUP($U$16,Sheet1!F:I,2,0),0) -> 0 | W17: =+IFERROR(VLOOKUP($W$16,Sheet1!F:I,2,0),0) -> 0 | X17: 864 | Y17: =+IFERROR(VLOOKUP($Y$16,Sheet1!F:I,2,0),0) -> 0 | Z17: =+IFERROR(VLOOKUP($Z$16,Sheet1!F:I,2,0),0) -> 0 | AA17: =+IFERROR(VLOOKUP($AA$16,Sheet1!F:I,2,0),0) -> 0 | AB17: =+IFERROR(VLOOKUP($AB$16,Sheet1!F:I,2,0),0) -> 0 | AC17: =+IFERROR(VLOOKUP($AC$16,Sheet1!R:U,2,0),0) -> 0 | AD17: 205 | AE17: 150 | AF17: =+IFERROR(VLOOKUP($AF$16,Sheet1!V:Y,2,0),0) -> 0 | AG17: =+IFERROR(VLOOKUP($AG$16,Sheet1!V:Y,2,0),0) -> 0 | AH17: =+IFERROR(VLOOKUP($AH$16,Sheet1!V:Y,2,0),0) -> 0 | AI17: =+IFERROR(VLOOKUP($AI$16,Sheet1!V:Y,2,0),0) -> 0 | AJ17: =+IFERROR(VLOOKUP($AJ$16,Sheet1!V:Y,2,0),0) -> 0 | AK17: =+IFERROR(VLOOKUP($AK$16,Sheet1!Z2:AA840,2,0),0) -> 0 | AL17: =+IFERROR(VLOOKUP($AL$16,Sheet1!AD2:AG840,2,0),0) -> 0 | AM17: =+IFERROR(VLOOKUP($AM$16,Sheet1!AD2:AG840,2,0),0) -> 0 | AN17: =+IFERROR(VLOOKUP($AN$16,Sheet1!AD2:AG840,2,0),0) -> 0 | AO17: =+IFERROR(VLOOKUP($AO$16,Sheet1!AD2:AG840,2,0),0) -> 0 | AP17: =+IFERROR(VLOOKUP($AP$16,Sheet1!AD2:AG840,2,0),0) -> 0 | AQ17: 62 | AR17: =+IFERROR(VLOOKUP($AR$16,Sheet1!AD2:AG840,2,0),0) -> 0 | AS17: =+IFERROR(VLOOKUP($AS$16,Sheet1!AH2:AK840,2,0),0) -> 0 | AT17: =+IFERROR(VLOOKUP($AT$16,Sheet1!AH2:AK840,2,0),0) -> 0 | AU17: =+IFERROR(VLOOKUP($AU$16,Sheet1!AH2:AK840,2,0),0) -> 0 | AV17: =+IFERROR(VLOOKUP($AV$16,Sheet1!AH2:AK840,2,0),0) -> 0 | AW17: =+IFERROR(VLOOKUP($AW$16,Sheet1!AH2:AK840,2,0),0) -> 0 | AX17: 76 | AY17: =+IFERROR(VLOOKUP($AY$16,Sheet1!AH2:AK840,2,0),0) -> 0 | AZ17: =+IFERROR(VLOOKUP($AZ$16,Sheet1!AH2:AK840,2,0),0) -> 0 | BA17: =+IFERROR(VLOOKUP($BA$16,Sheet1!AH2:AK840,2,0),0) -> 0 | BB17: =+IFERROR(VLOOKUP($BB$16,Sheet1!AH2:AK840,2,0),0) -> 0 | BC17: =+IFERROR(VLOOKUP($BC$16,Sheet1!AL2:AO840,2,0),0) -> 0 | BD17: =+IFERROR(VLOOKUP($BD$16,Sheet1!AL2:AO840,2,0),0) -> 0 | BE17: =+IFERROR(VLOOKUP($BE$16,Sheet1!AL2:AO840,2,0),0) -> 0 | BF17: =+IFERROR(VLOOKUP($BF$16,Sheet1!AL2:AO840,2,0),0) -> 94 | BG17: =+IFERROR(VLOOKUP($BG$16,Sheet1!AL2:AO840,2,0),0) -> 0 | BH17: =+IFERROR(VLOOKUP($BH$16,Sheet1!AL2:AO840,2,0),0) -> 0 | BI17: =+IFERROR(VLOOKUP($BI$16,Sheet1!AL2:AO840,2,0),0) -> 0 | BJ17: =+IFERROR(VLOOKUP($BJ$16,Sheet1!AL2:AO840,2,0),0) -> 0 | BK17: =+IFERROR(VLOOKUP($BK$16,Sheet1!AL2:AO840,2,0),0) -> 0 | BL17: =+IFERROR(VLOOKUP($BL$16,Sheet1!AL2:AO840,2,0),0) -> 0 | BM17: =+IFERROR(VLOOKUP($BM$16,Sheet1!AP2:AS840,2,0),0) -> 29 | BN17: =+IFERROR(VLOOKUP($BN$16,Sheet1!AT2:AW840,2,0),0) -> 0 | BO17: =+IFERROR(VLOOKUP($BO$16,Sheet1!AX2:BA840,2,0),0) -> 0 | BP17: =+IFERROR(VLOOKUP($BP$16,Sheet1!BB2:BE840,2,0),0) -> 0 | BQ17: =+IFERROR(VLOOKUP($BQ$16,Sheet1!BF2:BI840,2,0),0) -> 0 | BR17: =+IFERROR(VLOOKUP($BR$16,Sheet1!BJ2:BM840,2,0),0) -> 365 | BS17: =+IFERROR(VLOOKUP($BS$16,Sheet1!BN2:BQ840,2,0),0) -> 0 | BT17: =+IFERROR(VLOOKUP($BT$16,Sheet1!BR2:BU840,2,0),0) -> 0 | BU17: =+IFERROR(VLOOKUP($BU$16,Sheet1!BV2:BY840,2,0),0) -> 0
A18: =Sheet1!A2 -> ENQ-11515-22-23 | B18: =Sheet1!B2 -> 45170 | C18: =Sheet1!C2 -> FA1300002 | D18: =Sheet1!D2 -> 3 CORE X 185 SQ. MM AL/ARM - STRIP (XLPE) - 11 KV | E18: =CH18+CJ18+CL18 -> 1006636.1 | F18: =ROUNDUP(M21,0) -> 33739 | G18: =E18+F18 -> 1040375.1 | H18: 0.18 | I18: =G18*H18 -> 187267.52 | J18: =G18+I18 -> 1227642.6 | K18: =Sheet1!CS2 -> 49.38 | L18: =Sheet1!CT2 -> KMS | M18: =J18*K18 -> 60620994 | N18: 1503 | O18: =+IFERROR(VLOOKUP($O$16,Sheet1!J2:L2,3,0),0) -> 0 | P18: =+IFERROR(VLOOKUP($P$16,Sheet1!J2:M2,3,0),0) -> 0 | Q18: =+IFERROR(VLOOKUP($Q$16,Sheet1!J2:M2,3,0),0) -> 0 | R18: =+IFERROR(VLOOKUP($R$16,Sheet1!J2:M2,3,0),0) -> 0 | S18: =+IFERROR(VLOOKUP($S$16,Sheet1!N2:Q2,3,0),0) -> 0 | T18: =+IFERROR(VLOOKUP($T$16,Sheet1!N2:Q2,3,0),0) -> 0 | U18: =+IFERROR(VLOOKUP($U$16,Sheet1!F2:I2,3,0),0) -> 0 | W18: =+IFERROR(VLOOKUP($W$16,Sheet1!F2:I2,3,0),0) -> 0 | X18: 101 | Y18: =+IFERROR(VLOOKUP($Y$16,Sheet1!F2:I2,3,0),0) -> 0 | Z18: =+IFERROR(VLOOKUP($Z$16,Sheet1!F2:I2,3,0),0) -> 0 | AA18: =+IFERROR(VLOOKUP($AA$16,Sheet1!F2:I2,3,0),0) -> 0 | AB18: =+IFERROR(VLOOKUP($AB$16,Sheet1!F2:I2,3,0),0) -> 0 | AC18: =+IFERROR(VLOOKUP($AC$16,Sheet1!R2:U2,3,0),0) -> 0 | AD18: 268 | AE18: 670 | AF18: =+IFERROR(VLOOKUP($AF$16,Sheet1!V2:Y2,3,0),0) -> 0 | AG18: =+IFERROR(VLOOKUP($AG$16,Sheet1!V2:Y2,3,0),0) -> 0 | AH18: =+IFERROR(VLOOKUP($AH$16,Sheet1!V2:Y2,3,0),0) -> 0 | AI18: =+IFERROR(VLOOKUP($AI$16,Sheet1!V2:Y2,3,0),0) -> 0 | AJ18: =+IFERROR(VLOOKUP($AJ$16,Sheet1!V2:Y2,3,0),0) -> 0 | AK18: =+IFERROR(VLOOKUP($AK$16,Sheet1!Z2:AB2,3,0),0) -> 0 | AL18: =+IFERROR(VLOOKUP($AL$16,Sheet1!AD2:AG2,3,0),0) -> 0 | AM18: =+IFERROR(VLOOKUP($AM$16,Sheet1!AD2:AG2,3,0),0) -> 0 | AN18: =+IFERROR(VLOOKUP($AN$16,Sheet1!AD2:AG2,3,0),0) -> 0 | AO18: =+IFERROR(VLOOKUP($AO$16,Sheet1!AD2:AG2,3,0),0) -> 0 | AP18: =+IFERROR(VLOOKUP($AP$16,Sheet1!AD2:AG2,3,0),0) -> 0 | AQ18: =+IFERROR(VLOOKUP($AQ$16,Sheet1!AD2:AG2,3,0),0) -> 237 | AR18: =+IFERROR(VLOOKUP($AR$16,Sheet1!AD2:AG2,3,0),0) -> 0 | AS18: =+IFERROR(VLOOKUP($AS$16,Sheet1!AH2:AK2,3,0),0) -> 0 | AT18: =+IFERROR(VLOOKUP($AT$16,Sheet1!AH2:AK2,3,0),0) -> 0 | AU18: =+IFERROR(VLOOKUP($AU$16,Sheet1!AH2:AK2,3,0),0) -> 0 | AV18: =+IFERROR(VLOOKUP($AV$16,Sheet1!AH2:AK2,3,0),0) -> 0 | AW18: =+IFERROR(VLOOKUP($AW$16,Sheet1!AH2:AK2,3,0),0) -> 0 | AX18: =+IFERROR(VLOOKUP($AX$16,Sheet1!AH2:AK2,3,0),0) -> 975 | AY18: =+IFERROR(VLOOKUP($AY$16,Sheet1!AH2:AK2,3,0),0) -> 0 | AZ18: =+IFERROR(VLOOKUP($AZ$16,Sheet1!AH2:AK2,3,0),0) -> 0 | BA18: =+IFERROR(VLOOKUP($BA$16,Sheet1!AH2:AK2,3,0),0) -> 0 | BB18: =+IFERROR(VLOOKUP($BB$16,Sheet1!AH2:AK2,3,0),0) -> 0 | BC18: =+IFERROR(VLOOKUP($BC$16,Sheet1!AL2:AO2,3,0),0) -> 0 | BD18: =+IFERROR(VLOOKUP($BD$16,Sheet1!AL2:AO2,3,0),0) -> 0 | BE18: =+IFERROR(VLOOKUP($BE$16,Sheet1!AL2:AO2,3,0),0) -> 0 | BF18: 762 | BG18: =+IFERROR(VLOOKUP($BG$16,Sheet1!AL2:AO2,3,0),0) -> 0 | BH18: =+IFERROR(VLOOKUP($BH$16,Sheet1!AL2:AO2,3,0),0) -> 0 | BI18: =+IFERROR(VLOOKUP($BI$16,Sheet1!AL2:AO2,3,0),0) -> 0 | BJ18: =+IFERROR(VLOOKUP($BJ$16,Sheet1!AL2:AO2,3,0),0) -> 0 | BK18: =+IFERROR(VLOOKUP($BK$16,Sheet1!AL2:AO2,3,0),0) -> 0 | BL18: =+IFERROR(VLOOKUP($BL$16,Sheet1!AL2:AO2,3,0),0) -> 0 | BM18: 923 | BN18: =+IFERROR(VLOOKUP($BN$16,Sheet1!AT2:AW2,3,0),0) -> 0 | BO18: =+IFERROR(VLOOKUP($BO$16,Sheet1!AX2:BA2,3,0),0) -> 0 | BP18: =+IFERROR(VLOOKUP($BP$16,Sheet1!BB2:BE2,3,0),0) -> 0 | BQ18: =+IFERROR(VLOOKUP($BQ$16,Sheet1!BF2:BI2,3,0),0) -> 0 | BR18: 36 | BS18: =+IFERROR(VLOOKUP($BS$16,Sheet1!BN2:BQ2,3,0),0) -> 0 | BT18: =+IFERROR(VLOOKUP($BT$16,Sheet1!BR2:BU2,3,0),0) -> 0 | BU18: =+IFERROR(VLOOKUP($BU$16,Sheet1!BV2:BY2,3,0),0) -> 0 | BV18: STEEL | BY18: =Sheet1!CX2 -> 500 | BZ18: 80000 | CA18: =SUMPRODUCT($N$17:$BU$17,N18:BU18)+BZ18 -> 841669 | CB18: =Sheet1!CB2 -> 0 | CC18: =CA18*CB18 -> 0 | CD18: 0.15 | CE18: =CA18*CD18 -> 126250.35 | CF18: 0 | CG18: =CA18*CF18 -> 0 | CH18: =CA18+CC18+CE18+CG18 -> 967919.35 | CI18: 0.02 | CJ18: =CH18*CI18 -> 19358.387 | CK18: 0.02 | CL18: =CH18*CK18 -> 19358.387
E20: Order Quantity | F20: Stnd Length | G20: Truck type | H20: Fare of one truck | I20: No of Drum in one truck | J20: Total length in one Truck | K20: No of Truck | L20: Total Freight | M20: Freight per KM
E21: =K18 -> 49.38 | F21: 0.5 | G21: 28 MT TRAILER | H21: 98000 | I21: 6 | J21: =F21*I21 -> 3 | K21: =ROUNDUP((E21/J21),0) -> 17 | L21: =M21*E21 -> 1666000 | M21: =(H21*K21)/E21 -> 33738.356
I22: CONFIRMED FROM SOMBHU SIR
I24: =SUM(N18:BR18)/2 -> 2737.5
I25: =I24+200 -> 2937.5
I26: =23000/I25 -> 7.8297872
A28: DOCKET NO. | B28: Base Date | C28: ITEM CODE | D28: PROPOSE ERP ITEM NAME | E28: EX-WORKS (PER MTR) | F28: FREIGHT PER MTR | G28: PRICE INCLUDING FREIGHT (PER MTR) | H28: GST % | I28: GST VALUE | J28: PRICE INCLUDING GST & FREIGHT (PER MTR) | K28: QTY | L28: Unit | M28: TOTAL PRICE OF FULL QTY (INCLUDING FRIGHT & GST)
A30: =A18 -> ENQ-11515-22-23 | B30: =B18 -> 45170 | C30: =C18 -> FA1300002 | D30: =D18 -> 3 CORE X 185 SQ. MM AL/ARM - STRIP (XLPE) - 11 KV | E30: =ROUNDUP(E18/1000,2) -> 1006.64 | F30: =ROUNDUP(F18/1000,2) -> 33.74 | G30: =E30+F30 -> 1040.38 | H30: 0.18 | I30: =G30*H30 -> 187.2684 | J30: =G30+I30 -> 1227.6484 | K30: =K18*1000 -> 49380 | L30: MTR | M30: =J30*K30 -> 60621278

Sheet 11KV HT 
A1: Base Date | B1: 45170
A2: PV Terms(Price Variation Formula) | B2: The prices will be variable and as per IEEMA Date 01.09.2023.
A3: PV FORMULA
A4: P = Po + AIF (Al–Alo) + XLFAL (CC–Cco) + SMIF (SMIF1–SMIF0) + FeF (FeF1–FeF0) + CCFAI (PVCc–PVCco)
A7: Alf | B7: Variation factor for aluminum.
A8: CCFAI | B8: Variation factor for PVC compound/Polymer for aluminum conductor cable.
A9: XLFAL | B9: Variation Factor For XLPE
A10: Fef | B10: Variation factor for steel
A13: Item | B13: Ex-Work
A14: ='AUTO CALCULATION SHEET (2)'!D18 -> 3 CORE X 185 SQ. MM AL/ARM - STRIP (XLPE) - 11 KV | B14: ='AUTO CALCULATION SHEET (2)'!E18 -> 1006636.1
AC15: VALUE ADDITION CALCULATION
A16: Item | B16: Calculation part | C16: Date of Inspection | D16: Applicable Date | J16: BASE DATE | P16: FACTORS | U16: Ex-Work Po | V16: PVC of al | W16: PVC of XLPE | X16: PVC OF PVC | Y16: PVC OF FE | Z16: PVC OF CU TAPE | AA16: PV/PKM | AB16: Billing Price/PKM
D17: Date | E17: Al | F17: Cu | G17: Cc | H17: PVCc | I17: Fe | J17: Date | K17: Alo | L17: Cuo | M17: Cco | N17: PVCco | O17: Feo | AC17: ='AUTO CALCULATION SHEET (2)'!N16 -> Alumimium | AD17: ='AUTO CALCULATION SHEET (2)'!X16 -> Copper Tape - 0.04 mm | AE17: ='AUTO CALCULATION SHEET (2)'!AD16 -> Extruded Semiconductive(Stripable) | AF17: ='AUTO CALCULATION SHEET (2)'!AE16 -> HT-XLPE | AG17: ='AUTO CALCULATION SHEET (2)'!AQ16 -> PVC Type ST-2 | AH17: ='AUTO CALCULATION SHEET (2)'!AX16 -> Galvanised Steel Flat Strip | AI17: ='AUTO CALCULATION SHEET (2)'!BF16 -> FRLSH PVC Type ST-2 | AJ17: ='AUTO CALCULATION SHEET (2)'!BM16 -> FILLER | AK17: ='AUTO CALCULATION SHEET (2)'!BR16 -> GLASS FIBER TAPE | AL17: RMC | AM17: Drum | AN17: RMC+Drum | AO17: VA | AP17: Groos VA% | AQ17: Mfg % | AR17: Int % | AS17: Ins% | AT17: Net VA
P18: Alf | Q18: XLFAL | R18: CCFAI | S18: FeF | T18: Smif | AC18: 220 | AD18: 821 | AE18: 202 | AF18: 146 | AG18: 61 | AH18: 77 | AI18: 92 | AJ18: 29 | AK18: 350
AC19: Kg/Km | AD19: Kg/Km | AE19: Kg/Km | AF19: Kg/Km | AG19: Kg/Km | AH19: Kg/Km | AI19: Kg/Km | AJ19: Kg/Km | AK19: Kg/Km
A20: =A14 -> 3 CORE X 185 SQ. MM AL/ARM - STRIP (XLPE) - 11 KV | C20: PROVISIONAL | D20: 45231 | E20: 212871.36 | F20: 728539.76 | G20: 174651 | H20: 157075 | I20: 82250 | J20: =B1 -> 45170 | K20: 211371 | L20: 748501 | M20: 174651 | N20: 157075 | O20: 82250 | P20: 1.605 | Q20: 0.968 | R20: 2.406 | S20: 1.113 | T20: 0.094 | U20: =B14 -> 1006636.1 | V20: =(P20*(E20-K20)) -> 2408.0778 | W20: =(Q20*(G20-M20)) -> 0 | X20: =(R20*(H20-N20)) -> 0 | Y20: =(S20*(I20-O20)) -> 0 | Z20: =T20*(F20-L20) -> -1876.3566 | AA20: =V20+W20+X20+Y20+Z20 -> 531.72124 | AB20: =+U20+AA20 -> 1007167.8 | AC20: ='AUTO CALCULATION SHEET (2)'!N18 -> 1503 | AD20: ='AUTO CALCULATION SHEET (2)'!X18 -> 101 | AE20: ='AUTO CALCULATION SHEET (2)'!AD18 -> 268 | AF20: ='AUTO CALCULATION SHEET (2)'!AE18 -> 670 | AG20: ='AUTO CALCULATION SHEET (2)'!AQ18 -> 237 | AH20: ='AUTO CALCULATION SHEET (2)'!AX18 -> 975 | AI20: ='AUTO CALCULATION SHEET (2)'!BF18 -> 762 | AJ20: ='AUTO CALCULATION SHEET (2)'!BM18 -> 923 | AK20: ='AUTO CALCULATION SHEET (2)'!BR18 -> 36 | AL20: =SUMPRODUCT(AC20:AK20,$AC$18:$AK$18) -> 764540 | AM20: ='AUTO CALCULATION SHEET (2)'!BZ18 -> 80000 | AN20: =AL20+AM20 -> 844540 | AO20: =AB20-AN20 -> 162627.85 | AP20: =ROUND((AO20/AN20)*100,2) -> 19.26 | AQ20: 0 | AR20: 2 | AS20: 2 | AT20: =AP20-AQ20-AR20-AS20 -> 15.26
