Workbook

Sheet Sheet1
A1: DOCKET NO. | B1: Base Date | C1: ITEM CODE | D1: PROPOSE ERP ITEM NAME | E1: Propose Drum Type | F1: Insulation Screening(Metallic) | G1: RM Rate(Insulation Screening(Metallic)) | H1: Weight (Insulation Screening (Metallic)) | I1: Cost Insulation Screening(Metallic) | J1: Conductor | K1: RM Rate(Conductor) | L1: Weight(Conductor) | M1: Cost(Conductor) | N1: AL ALLOY | O1: RM Rate(AL Alloy) | P1: Weight(Al Alloy) | Q1: Cost(AL Alloy) | R1: Insulation Screening(Non-Metallic) | S1: RM Rate(Insulation Screening(Non-Metallic)) | T1: Weight(Insulation Screening(Non-Metallic) | U1: Cost(Insulation Screening(Non-Metallic) | V1: Insulation | W1: RM Rate(Insulation) | X1: Weight(Insulation) | Y1: Cost(Insulation) | Z1: Poly Tape | AA1: RM Rate(Poly Tape) | AB1: Weight(Poly Tape) | AC1: Cost(Poly Tape) | AD1: Inner Sheath | AE1: RM Rate(Inner Sheath) | AF1: Weight(Inner Sheath) | AG1: Cost(Inner Sheath) | AH1: Armouring | AI1: RM Rate(Armouring) | AJ1: Weight(Armouring) | AK1: Cost(Armouring) | AL1: Outer Sheath | AM1: RM Rate(Outer Sheath) | AN1: Weight(Outer Sheath) | AO1: Cost(Outer Sheath) | AP1: Filler | AQ1: RM Rate(Filler) | AR1: Weight(Filler) | AS1: Cost(Filler) | AT1: Grease | AU1: RM Rate(Grease) | AV1: Weight(Grease) | AW1: Cost(Grease) | AX1: Water Swellable Tape | AY1: RM Rate(Water Swellable Tape) | AZ1: Weight(Water Swellable Tape) | BA1: Cost(Water Swellable Tape) | BB1: Semi Conducting Water Swellable Tape | BC1: RM Rate(Semi Conducting Water Swellable Tape) | BD1: Weight(Semi Conducting Water Swellable Tape) | BE1: Cost(Semi Conducting Water Swellable Tape) | BF1: Semicon Tape | BG1: RM Rate(Semicon Tape) | BH1: Weight(Semicon Tape) | BI1: Cost(Semicon Tape) | BJ1: Glass Fiber Tape | BK1: RM Rate(Glass Fiber Tape) | BL1: Weight(Glass Fiber Tape) | BM1: Cost(Glass Fiber Tape) | BN1: Copper Wire 0.8MM | BO1: RM Rate(Copper Wire 0.8MM) | BP1: Weight(Copper Wire 0.8MM) | BQ1: Cost(Copper Wire 0.8MM) | BR1: Rubberized Cotton Tape | BS1: RM Rate(Rubberized Cotton Tape) | BT1: Weight(Rubberized Cotton Tape) | BU1: Cost(Rubberized Cotton Tape) | BV1: Water Tight Compound | BW1: RM Rate(Water Tight Compound) | BX1: Weight(Water Tight Compound) | BY1: Cost(Water Tight Compound) | BZ1: Drum Cost Per KM | CA1: Total RM Cost | CB1: FIRM % | CC1: Firm Value | CD1: MFG% | CE1: MFG Value | CF1: PROF% | CG1: Profit Value | CH1: 1st EX-Works | CI1: Intt % | CJ1: Intt Value | CK1: insp% | CL1: Insp Value | CM1: TTR CHARGES% | CN1: TTR Value | CO1: EX-Works Per KM | CP1: Freight Per KM | CQ1: Price Including Freight Per KM | CR1: GST % | CS1: GST Value | CT1: Price Including GST & Freight Per KM | CU1: QTY | CV1: Unit | CW1: Total Price Of Full QTY(Including Freight&GST) | CX1: DRUM CODE | CY1: DRUM SIZE (FxbXtx Ft) | CZ1: Party Standard Length(MTR)
A2: ENQ-16531-25-26 | C2: FA0200002 | D2: 10 CORE X 2.5 SQ. MM. CU/ARD - WIRE (PVC) | E2: WOOD | H2: 0 | J2: Tinned Copper | L2: 222 | P2: 0 | T2: 0 | V2: Type C PVC (HR) | X2: 130 | Z2: POLY TAPE | AB2: 5 | AD2: FR PVC Type ST-2 | AF2: 38 | AH2: Galvanised Steel Round Wire | AJ2: 492 | AL2: FRLSH PVC Type ST-2 | AN2: 166 | AR2: 0 | AV2: 0 | AZ2: 0 | BD2: 0 | BH2: 0 | BL2: 28 | BP2: 0 | BT2: 0 | BX2: 0 | BZ2: 5448 | CA2: 5448 | CH2: 5448 | CO2: 5448 | CQ2: 5448 | CR2: 0.18 | CS2: 980.64 | CT2: 6428.64 | CU2: 35 | CV2: KMS | CW2: 225002 | CX2: MD0100066 | CY2: DRUM - 40 X 15 X 23 X 2 | CZ2: 500
A3: ENQ-16531-25-26 | C3: FA0200003 | D3: 12 CORE X 2.5 SQ. MM. CU/ARD - WIRE (PVC) | E3: WOOD | H3: 0 | J3: Tinned Copper | L3: 266 | P3: 0 | T3: 0 | V3: Type C PVC (HR) | X3: 156 | Z3: POLY TAPE | AB3: 6 | AD3: FR PVC Type ST-2 | AF3: 40 | AH3: Galvanised Steel Round Wire | AJ3: 508 | AL3: FRLSH PVC Type ST-2 | AN3: 170 | AR3: 0 | AV3: 0 | AZ3: 0 | BD3: 0 | BH3: 0 | BL3: 28 | BP3: 0 | BT3: 0 | BX3: 0 | BZ3: 5448 | CA3: 5448 | CH3: 5448 | CO3: 5448 | CQ3: 5448 | CR3: 0.18 | CS3: 980.64 | CT3: 6428.64 | CU3: 35 | CV3: KMS | CW3: 225002 | CX3: MD0100066 | CY3: DRUM - 40 X 15 X 23 X 2 | CZ3: 500
A4: ENQ-16531-25-26 | C4: FA0200008 | D4: 2 CORE X 2.5 SQ. MM. CU/ARD - WIRE (PVC) | E4: WOOD | H4: 0 | J4: Tinned Copper | L4: 44 | P4: 0 | T4: 0 | V4: Type C PVC (HR) | X4: 26 | Z4: POLY TAPE | AB4: 3 | AD4: FR PVC Type ST-2 | AF4: 39 | AH4: Galvanised Steel Round Wire | AJ4: 251 | AL4: FRLSH PVC Type ST-2 | AN4: 93 | AR4: 0 | AV4: 0 | AZ4: 0 | BD4: 0 | BH4: 0 | BL4: 16 | BP4: 0 | BT4: 0 | BX4: 0 | BZ4: 4260 | CA4: 4260 | CH4: 4260 | CO4: 4260 | CQ4: 4260 | CR4: 0.18 | CS4: 766.8 | CT4: 5026.8 | CU4: 15 | CV4: KMS | CW4: 75402 | CX4: MD0100003 | CY4: DRUM - 28 X 14 X 23 X 2 | CZ4: 500
A5: ENQ-16531-25-26 | C5: FA0200011 | D5: 4 CORE X 2.5 SQ. MM. CU/ARD - WIRE (PVC) | E5: WOOD | H5: 0 | J5: Tinned Copper | L5: 89 | P5: 0 | T5: 0 | V5: Type C PVC (HR) | X5: 52 | Z5: POLY TAPE | AB5: 3 | AD5: FR PVC Type ST-2 | AF5: 27 | AH5: Galvanised Steel Round Wire | AJ5: 289 | AL5: FRLSH PVC Type ST-2 | AN5: 104 | AR5: 0 | AV5: 0 | AZ5: 0 | BD5: 0 | BH5: 0 | BL5: 19 | BP5: 0 | BT5: 0 | BX5: 0 | BZ5: 5170 | CA5: 5170 | CH5: 5170 | CO5: 5170 | CQ5: 5170 | CR5: 0.18 | CS5: 930.6 | CT5: 6100.6 | CU5: 25 | CV5: KMS | CW5: 152515 | CX5: MD0100005 | CY5: DRUM - 36 X 14 X 23 X 2 | CZ5: 500

Sheet AUTO CALCULATION SHEET (2)
A2: NORTH BIHAR POWER DISTRIBUTION CO. LTD, PATNA
A4: TENDER SPECIFICATION NO () | B4: 72/PR/NBPDCL/2025 (System Tender No.104083)
A5: TENDER DESCRIPTION () | B5: LT Copper control cable of different size for NBPDCL and SBPDCL
A6: Last Date & Time of Submission () | B6: 04-08-2025 06:00 PM
A7: REVERSE AUCTION | B7: Not Mention
A8: Price () | B8: Price Variation for Control Cable shall be applicable as per current IEEMA as applicable on the final date of submission of bid. Base date will be one month prior to the last date of submission of bid against the NIT.
A9: Validity () | B9: 1.11.1. Bidders should specify the validity period of their offer/bid which should be valid for a minimum period of 180 days from the last date of submission of bid.
A10: Payment Terms () | B10: 90% payment along with full amount of taxes, duties and freight keeping 10% retention money , on submission of triplicate copy of bills with all relevant documents (Sample check list) enclosed in annexure by the vendor after receipt of the material / equipment in good condition. After successful completion of delivery of entire order or modified quantity as decided during its delivery schedule, 10 % retention money may be released after deduction of penalty. ii. Payment will be released normally within 15 working days from the date of submission of bill along with all required relevant document(s) to Sr. Manager (Finance), NBPDCL/SBPDCL.
A11: Standard length () | B11: Standard lengths for each size of power and control cables shall be 500/1000 meters. The cable length per drum shall be subject to a tolerance of plus or minus 5% of the standard drum length.
A12: Packing () | B12: Cables shall be supplied on returnable wooden or steel drums of heavy construction. Wooden drum shall be properly seasoned sound and free from defects. Wood preservative shall be applied to the entire drum.
A13: Technical Specification
N15: Conductor | V15: AL ALLOY | X15: Insulation Screening (Metallic) | AF15: Insulation Screening (Non-Metallic) | AH15: Insulation | AQ15: POLY TAPE | AR15: Inner Sheath | BA15: Armouring | BL15: Outer Sheath | BX15: FILLER | BY15: GREASE | BZ15: Water swellable Tape | CA15: Semi conducting Water Swellable tape | CB15: SEMICON TAPE | CC15: GLASS FIBER TAPE | CD15: COPPER WIRE 0.8 MM | CE15: RUBBERIZED COTTON TAPE | CF15: Water Tight Compound | CG15: DRUM TYPE | CK15: DRUM COST PER KM | CL15: TOTAL RM COST | CM15: EXTRA CONSUMPTION | CN15: EXTRA CONSUMPTION VALUE | CZ15: $A$1
A16: DOCKET NO. | B16: BASE DATE | C16: ITEM CODE | D16: PROPOSE ERP ITEM NAME | E16: EX-WORKS (PER KM) | F16: FREIGHT PER KM | G16: PRICE INCLUDING FREIGHT (PER KM) | H16: GST % | I16: GST VALUE | J16: PRICE INCLUDING GST & FREIGHT (PER KM) | K16: QTY | L16: Unit | M16: TOTAL PRICE OF FULL QTY (INCLUDING FRIGHT & GST) | N16: Alumimium | O16: Alumimium ALLOY | P16: Tinned Copper | Q16: AL-59 | R16: AL-4 | S16: AL-7 | T16: Flexible Copper | U16: Galvanized steel wire | V16: Alumimium | W16: Alumimium ALLOY | X16: Coper tape - 0.1 mm | Y16: Copper Tape - 0.03 mm | Z16: Copper Tape - 0.035 mm | AA16: Copper Tape - 0.04 mm | AB16: Copper Tape - 0.045 mm | AC16: Copper Tape - 0.050 mm | AD16: Copper Tape - 0.060 mm | AE16: Copper Tape - 0.075 mm(DOUBLE) | AF16: Extruded semiconductive | AG16: Extruded Semiconductive(Stripable) | AH16: HT-XLPE | AI16: LT-XLPE | AJ16: TR XLPE | AK16: Type A PVC | AL16: Type C PVC (HR) | AM16: Type A PVC-1.45 | AN16: Type A PVC-FR | AO16: Type A PVC-FRLS | AP16: Type A PVC-1.38 | AQ16: POLY TAPE | AR16: FR PVC Type ST-1 | AS16: FR PVC Type ST-2 | AT16: FRLSH PVC Type ST-1 | AU16: FRLSH PVC Type ST-2 | AV16: PVC Type ST-1 | AW16: PVC Type ST-1-PRESSURE EXTRUDED | AX16: PVC Type ST-2 | AY16: PVC COMPOUND 1.48 | AZ16: PVC Type ST-2-PRESSURE EXTRUDED | BA16: ACSR CORE WIRE | BB16: ACSR DOG STEEL WIRE | BC16: Aluminium Flat Strip | BD16: Aluminium Round Wire | BE16: Alumimium Tape | BF16: Double Steel Tape | BG16: Galvanised Steel Flat Strip | BH16: Galvanised Steel Flat Strip (Double) | BI16: Galvanised Steel Flat Strip-B | BJ16: Galvanised Steel Round Wire | BK16: Galvanised Steel Round Wire (Double) | BL16: FR PVC Type ST-1 | BM16: FR PVC Type ST-2 | BN16: FRLSH PVC Type ST-1 | BO16: FRLSH PVC Type ST-2 | BP16: ZHFR | BQ16: PE-ST-3 | BR16: PE-ST-7 | BS16: PVC Type ST-1 | BT16: PVC Type ST-2 | BU16: PVC COMPOUND 1.48 | BV16: PVC Type ST-2-PRESSURE EXTRUDED | BW16: UV & Track Resistant XLPE | BX16: FILLER | BY16: Grease | BZ16: Water swellable Tape | CA16: Semi conducting Water Swellable tape | CB16: SEMICON TAPE | CC16: GLASS FIBER TAPE | CD16: COPPER WIRE 0.8 MM | CE16: RUBBERIZED COTTON TAPE | CF16: Water Tight Compound | CG16: PROPOSE DRUM TYPE | CH16: DRUM CODE | CI16: DRUM SIZE (FxbXtx Ft) | CJ16: PARTY STANDARD LENGTH (MTR) | CO16: MFG% | CP16: MFG VALUE | CQ16: PROF% | CR16: PROFIT VALUE | CS16: 1ST EX-WORKS | CT16: Intt % | CU16: INTT VALUE | CV16: insp% | CW16: INSP VALUE | CX16: TTR Charges% | CY16: TTR Charges VALUE
N17: =+IFERROR(VLOOKUP($N$16,Sheet1!J:L,2,0),0) -> 0 | O17: =+IFERROR(VLOOKUP($O$16,Sheet1!J:L,2,0),0) -> 0 | P17: 964 | Q17: =+IFERROR(VLOOKUP($Q$16,Sheet1!J:M,2,0),0) -> 0 | R17: =+IFERROR(VLOOKUP($R$16,Sheet1!J:M,2,0),0) -> 0 | S17: =+IFERROR(VLOOKUP($S$16,Sheet1!J:M,2,0),0) -> 0 | T17: =+IFERROR(VLOOKUP($T$16,Sheet1!J:M,2,0),0) -> 0 | U17: =+IFERROR(VLOOKUP($U$16,Sheet1!J:M,2,0),0) -> 0 | V17: =+IFERROR(VLOOKUP($V$16,Sheet1!N:Q,2,0),0) -> 0 | W17: =+IFERROR(VLOOKUP($W$16,Sheet1!N:O,2,0),0) -> 0 | X17: =+IFERROR(VLOOKUP($X$16,Sheet1!F:I,2,0),0) -> 0 | Y17: =+IFERROR(VLOOKUP($Y$16,Sheet1!F:I,2,0),0) -> 0 | Z17: =+IFERROR(VLOOKUP($Z$16,Sheet1!F:I,2,0),0) -> 0 | AA17: =+IFERROR(VLOOKUP($AA$16,Sheet1!F:I,2,0),0) -> 0 | AB17: =+IFERROR(VLOOKUP($AB$16,Sheet1!F:I,2,0),0) -> 0 | AC17: =+IFERROR(VLOOKUP($AC$16,Sheet1!F:I,2,0),0) -> 0 | AD17: =+IFERROR(VLOOKUP($AD$16,Sheet1!F:I,2,0),0) -> 0 | AE17: =+IFERROR(VLOOKUP($AE$16,Sheet1!F:I,2,0),0) -> 0 | AF17: =+IFERROR(VLOOKUP($AF$16,Sheet1!R:U,2,0),0) -> 0 | AG17: =+IFERROR(VLOOKUP($AG$16,Sheet1!R:U,2,0),0) -> 0 | AH17: =+IFERROR(VLOOKUP($AH$16,Sheet1!V:Y,2,0),0) -> 0 | AI17: =+IFERROR(VLOOKUP($AI$16,Sheet1!V:Y,2,0),0) -> 0 | AJ17: =+IFERROR(VLOOKUP($AJ$16,Sheet1!V:Y,2,0),0) -> 0 | AK17: =+IFERROR(VLOOKUP($AK$16,Sheet1!V:Y,2,0),0) -> 0 | AL17: 97 | AM17: =+IFERROR(VLOOKUP($AM$16,Sheet1!V:Y,2,0),0) -> 0 | AN17: =+IFERROR(VLOOKUP($AN$16,Sheet1!V:Y,2,0),0) -> 0 | AO17: =+IFERROR(VLOOKUP($AO$16,Sheet1!V:Y,2,0),0) -> 0 | AP17: =+IFERROR(VLOOKUP($AP$16,Sheet1!V:Y,2,0),0) -> 0 | AQ17: 111 | AR17: =+IFERROR(VLOOKUP($AR$16,Sheet1!AD2:AG840,2,0),0) -> 0 | AS17: 81 | AT17: =+IFERROR(VLOOKUP($AT$16,Sheet1!AD2:AG840,2,0),0) -> 0 | AU17: =+IFERROR(VLOOKUP($AU$16,Sheet1!AD2:AG840,2,0),0) -> 0 | AV17: =+IFERROR(VLOOKUP($AV$16,Sheet1!AD2:AG840,2,0),0) -> 0 | AW17: =+IFERROR(VLOOKUP($AW$16,Sheet1!AD2:AG840,2,0),0) -> 0 | AX17: =+IFERROR(VLOOKUP($AX$16,Sheet1!AD2:AG840,2,0),0) -> 0 | AY17: =+IFERROR(VLOOKUP($AY$16,Sheet1!AD2:AG840,2,0),0) -> 0 | AZ17: =+IFERROR(VLOOKUP($AZ$16,Sheet1!AD2:AG840,2,0),0) -> 0 | BA17: =+IFERROR(VLOOKUP($BA$16,Sheet1!AH2:AK840,2,0),0) -> 0 | BB17: =+IFERROR(VLOOKUP($BB$16,Sheet1!AH2:AK840,2,0),0) -> 0 | BC17: =+IFERROR(VLOOKUP($BC$16,Sheet1!AH2:AK840,2,0),0) -> 0 | BD17: =+IFERROR(VLOOKUP($BD$16,Sheet1!AH2:AK840,2,0),0) -> 0 | BE17: =+IFERROR(VLOOKUP($BE$16,Sheet1!AH2:AK840,2,0),0) -> 0 | BF17: =+IFERROR(VLOOKUP($BF$16,Sheet1!AH2:AK840,2,0),0) -> 0 | BG17: =+IFERROR(VLOOKUP($BG$16,Sheet1!AH2:AK840,2,0),0) -> 0 | BH17: =+IFERROR(VLOOKUP($BH$16,Sheet1!AH2:AK840,2,0),0) -> 0 | BI17: =+IFERROR(VLOOKUP($BI$16,Sheet1!AH2:AK840,2,0),0) -> 0 | BJ17: 79 | BK17: =+IFERROR(VLOOKUP($BK$16,Sheet1!AH2:AK840,2,0),0) -> 0 | BL17: =+IFERROR(VLOOKUP($BL$16,Sheet1!AL2:AO840,2,0),0) -> 0 | BM17: =+IFERROR(VLOOKUP($BM$16,Sheet1!AL2:AO840,2,0),0) -> 0 | BN17: =+IFERROR(VLOOKUP($BN$16,Sheet1!AL2:AO840,2,0),0) -> 0 | BO17: 81 | BP17: =+IFERROR(VLOOKUP($BP$16,Sheet1!AL2:AO840,2,0),0) -> 0 | BQ17: =+IFERROR(VLOOKUP($BQ$16,Sheet1!AL2:AO840,2,0),0) -> 0 | BR17: =+IFERROR(VLOOKUP($BR$16,Sheet1!AL2:AO840,2,0),0) -> 0 | BS17: =+IFERROR(VLOOKUP($BS$16,Sheet1!AL2:AO840,2,0),0) -> 0 | BT17: =+IFERROR(VLOOKUP($BT$16,Sheet1!AL2:AO840,2,0),0) -> 0 | BU17: =+IFERROR(VLOOKUP($BU$16,Sheet1!AL2:AO840,2,0),0) -> 0 | BV17: =+IFERROR(VLOOKUP($BV$16,Sheet1!AL2:AO840,2,0),0) -> 0 | BW17: =+IFERROR(VLOOKUP($BW$16,Sheet1!AL2:AO840,2,0),0) -> 0 | BX17: =+IFERROR(VLOOKUP($BX$16,Sheet1!AP2:AS840,2,0),0) -> 0 | BY17: =+IFERROR(VLOOKUP($BY$16,Sheet1!AT2:AW840,2,0),0) -> 0 | BZ17: =+IFERROR(VLOOKUP($BZ$16,Sheet1!AX2:BA840,2,0),0) -> 0 | CA17: =+IFERROR(VLOOKUP($CA$16,Sheet1!BB2:BE840,2,0),0) -> 0 | CB17: =+IFERROR(VLOOKUP($CB$16,Sheet1!BF2:BI840,2,0),0) -> 0 | CC17: =+IFERROR(VLOOKUP($CC$16,Sheet1!BJ2:BM840,2,0),0) -> 0 | CD17: =+IFERROR(VLOOKUP($CD$16,Sheet1!BN2:BQ840,2,0),0) -> 0 | CE17: =+IFERROR(VLOOKUP($CE$16,Sheet1!BR2:BU840,2,0),0) -> 0 | CF17: =+IFERROR(VLOOKUP($CF$16,Sheet1!BV2:BY840,2,0),0) -> 0
A18: =Sheet1!A4 -> ENQ-16531-25-26 | B18: 45839 | C18: =Sheet1!C4 -> FA0200008 | D18: =Sheet1!D4 -> 2 CORE X 2.5 SQ. MM. CU/ARD - WIRE (PVC) | E18: =CS18+CU18+CW18+CY18 -> 88225.309 | F18: =ROUNDUP(M34,0) -> 2967 | G18: =E18+F18 -> 91192.309 | H18: =Sheet1!CR4 -> 0.18 | I18: =G18*H18 -> 16414.616 | J18: =G18+I18 -> 107606.92 | K18: =Sheet1!CU4 -> 15 | L18: =Sheet1!CV4 -> KMS | M18: =J18*K18 -> 1614103.9 | N18: =+IFERROR(VLOOKUP($N$16,Sheet1!J4:L4,3,0),0) -> 0 | O18: =+IFERROR(VLOOKUP($O$16,Sheet1!J4:L4,3,0),0) -> 0 | P18: =+IFERROR(VLOOKUP($P$16,Sheet1!J4:M4,3,0),0) -> 44 | Q18: =+IFERROR(VLOOKUP($Q$16,Sheet1!J4:M4,3,0),0) -> 0 | R18: =+IFERROR(VLOOKUP($R$16,Sheet1!J4:M4,3,0),0) -> 0 | S18: =+IFERROR(VLOOKUP($S$16,Sheet1!J4:M4,3,0),0) -> 0 | T18: =+IFERROR(VLOOKUP($T$16,Sheet1!J4:M4,3,0),0) -> 0 | U18: =+IFERROR(VLOOKUP($U$16,Sheet1!J4:M4,3,0),0) -> 0 | V18: =+IFERROR(VLOOKUP($V$16,Sheet1!N4:Q4,3,0),0) -> 0 | W18: =+IFERROR(VLOOKUP($W$16,Sheet1!N4:Q4,3,0),0) -> 0 | X18: =+IFERROR(VLOOKUP($X$16,Sheet1!F4:I4,3,0),0) -> 0 | Y18: =+IFERROR(VLOOKUP($Y$16,Sheet1!F4:I4,3,0),0) -> 0 | Z18: =+IFERROR(VLOOKUP($Z$16,Sheet1!F4:I4,3,0),0) -> 0 | AA18: =+IFERROR(VLOOKUP($AA$16,Sheet1!F4:I4,3,0),0) -> 0 | AB18: =+IFERROR(VLOOKUP($AB$16,Sheet1!F4:I4,3,0),0) -> 0 | AC18: =+IFERROR(VLOOKUP($AC$16,Sheet1!F4:I4,3,0),0) -> 0 | AD18: =+IFERROR(VLOOKUP($AD$16,Sheet1!F4:I4,3,0),0) -> 0 | AE18: =+IFERROR(VLOOKUP($AE$16,Sheet1!F4:I4,3,0),0) -> 0 | AF18: =+IFERROR(VLOOKUP($AF$16,Sheet1!R4:U4,3,0),0) -> 0 | AG18: =+IFERROR(VLOOKUP($AG$16,Sheet1!R4:U4,3,0),0) -> 0 | AH18: =+IFERROR(VLOOKUP($AH$16,Sheet1!V4:Y4,3,0),0) -> 0 | AI18: =+IFERROR(VLOOKUP($AI$16,Sheet1!V4:Y4,3,0),0) -> 0 | AJ18: =+IFERROR(VLOOKUP($AJ$16,Sheet1!V4:Y4,3,0),0) -> 0 | AK18: =+IFERROR(VLOOKUP($AK$16,Sheet1!V4:Y4,3,0),0) -> 0 | AL18: =+IFERROR(VLOOKUP($AL$16,Sheet1!V4:Y4,3,0),0) -> 26 | AM18: =+IFERROR(VLOOKUP($AM$16,Sheet1!V4:Y4,3,0),0) -> 0 | AN18: =+IFERROR(VLOOKUP($AN$16,Sheet1!V4:Y4,3,0),0) -> 0 | AO18: =+IFERROR(VLOOKUP($AO$16,Sheet1!V4:Y4,3,0),0) -> 0 | AP18: =+IFERROR(VLOOKUP($AP$16,Sheet1!V4:Y4,3,0),0) -> 0 | AQ18: =+IFERROR(VLOOKUP($AQ$16,Sheet1!Z4:AB4,3,0),0) -> 3 | AR18: =+IFERROR(VLOOKUP($AR$16,Sheet1!AD4:AG4,3,0),0) -> 0 | AS18: =+IFERROR(VLOOKUP($AS$16,Sheet1!AD4:AG4,3,0),0) -> 39 | AT18: =+IFERROR(VLOOKUP($AT$16,Sheet1!AD4:AG4,3,0),0) -> 0 | AU18: =+IFERROR(VLOOKUP($AU$16,Sheet1!AD4:AG4,3,0),0) -> 0 | AV18: =+IFERROR(VLOOKUP($AV$16,Sheet1!AD4:AG4,3,0),0) -> 0 | AW18: =+IFERROR(VLOOKUP($AW$16,Sheet1!AD4:AG4,3,0),0) -> 0 | AX18: =+IFERROR(VLOOKUP($AX$16,Sheet1!AD4:AG4,3,0),0) -> 0 | AY18: =+IFERROR(VLOOKUP($AY$16,Sheet1!AD4:AG4,3,0),0) -> 0 | AZ18: =+IFERROR(VLOOKUP($AZ$16,Sheet1!AD4:AG4,3,0),0) -> 0 | BA18: =+IFERROR(VLOOKUP($BA$16,Sheet1!AH4:AK4,3,0),0) -> 0 | BB18: =+IFERROR(VLOOKUP($BB$16,Sheet1!AH4:AK4,3,0),0) -> 0 | BC18: =+IFERROR(VLOOKUP($BC$16,Sheet1!AH4:AK4,3,0),0) -> 0 | BD18: =+IFERROR(VLOOKUP($BD$16,Sheet1!AH4:AK4,3,0),0) -> 0 | BE18: =+IFERROR(VLOOKUP($BE$16,Sheet1!AH4:AK4,3,0),0) -> 0 | BF18: =+IFERROR(VLOOKUP($BF$16,Sheet1!AH4:AK4,3,0),0) -> 0 | BG18: =+IFERROR(VLOOKUP($BG$16,Sheet1!AH4:AK4,3,0),0) -> 0 | BH18: =+IFERROR(VLOOKUP($BH$16,Sheet1!AH4:AK4,3,0),0) -> 0 | BI18: =+IFERROR(VLOOKUP($BI$16,Sheet1!AH4:AK4,3,0),0) -> 0 | BJ18: =+IFERROR(VLOOKUP($BJ$16,Sheet1!AH4:AK4,3,0),0) -> 251 | BK18: =+IFERROR(VLOOKUP($BK$16,Sheet1!AH4:AK4,3,0),0) -> 0 | BL18: =+IFERROR(VLOOKUP($BL$16,Sheet1!AL4:AO4,3,0),0) -> 0 | BM18: =+IFERROR(VLOOKUP($BM$16,Sheet1!AL4:AO4,3,0),0) -> 0 | BN18: =+IFERROR(VLOOKUP($BN$16,Sheet1!AL4:AO4,3,0),0) -> 0 | BO18: =+IFERROR(VLOOKUP($BO$16,Sheet1!AL4:AO4,3,0),0) -> 93 | BP18: =+IFERROR(VLOOKUP($BP$16,Sheet1!AL4:AO4,3,0),0) -> 0 | BQ18: =+IFERROR(VLOOKUP($BQ$16,Sheet1!AL4:AO4,3,0),0) -> 0 | BR18: =+IFERROR(VLOOKUP($BR$16,Sheet1!AL4:AO4,3,0),0) -> 0 | BS18: =+IFERROR(VLOOKUP($BS$16,Sheet1!AL4:AO4,3,0),0) -> 0 | BT18: =+IFERROR(VLOOKUP($BT$16,Sheet1!AL4:AO4,3,0),0) -> 0 | BU18: =+IFERROR(VLOOKUP($BU$16,Sheet1!AL4:AO4,3,0),0) -> 0 | BV18: =+IFERROR(VLOOKUP($BV$16,Sheet1!AL4:AO4,3,0),0) -> 0 | BW18: =+IFERROR(VLOOKUP($BW$16,Sheet1!AL4:AO4,3,0),0) -> 0 | BX18: =+IFERROR(VLOOKUP($BX$16,Sheet1!AP4:AS4,3,0),0) -> 0 | BY18: =+IFERROR(VLOOKUP($BY$16,Sheet1!AT4:AW4,3,0),0) -> 0 | BZ18: =+IFERROR(VLOOKUP($BZ$16,Sheet1!AX4:BA4,3,0),0) -> 0 | CA18: =+IFERROR(VLOOKUP($CA$16,Sheet1!BB4:BE4,3,0),0) -> 0 | CB18: =+IFERROR(VLOOKUP($CB$16,Sheet1!BF4:BI4,3,0),0) -> 0 | CC18: =+IFERROR(VLOOKUP($CC$16,Sheet1!BJ4:BM4,3,0),0) -> 0 | CD18: =+IFERROR(VLOOKUP($CD$16,Sheet1!BN4:BQ4,3,0),0) -> 0 | CE18: =+IFERROR(VLOOKUP($CE$16,Sheet1!BR4:BU4,3,0),0) -> 0 | CF18: =+IFERROR(VLOOKUP($CF$16,Sheet1!BV4:BY4,3,0),0) -> 0 | CG18: =Sheet1!E4 -> WOOD | CH18: =Sheet1!CX4 -> MD0100003 | CI18: =Sheet1!CY4 -> DRUM - 28 X 14 X 23 X 2 | CJ18: =Sheet1!CZ4 -> 500 | CK18: =Sheet1!BZ4 -> 4260 | CL18: =SUMPRODUCT($N$17:$CF$17,N18:CF18)+CK18 -> 80052 | CM18: =Sheet1!CB4 -> 0 | CN18: =CL18*CM18 -> 0 | CO18: 0.07 | CP18: =CL18*CO18 -> 5603.64 | CQ18: 0 | CR18: =CL18*CQ18 -> 0 | CS18: =CL18+CN18+CP18+CR18 -> 85655.64 | CT18: 0.02 | CU18: =CS18*CT18 -> 1713.1128 | CV18: 0.01 | CW18: =CS18*CV18 -> 856.5564 | CX18: =Sheet1!CM4 -> 0 | CY18: =CX18*CS18 -> 0
A19: =Sheet1!A5 -> ENQ-16531-25-26 | B19: 45839 | C19: =Sheet1!C5 -> FA0200011 | D19: =Sheet1!D5 -> 4 CORE X 2.5 SQ. MM. CU/ARD - WIRE (PVC) | E19: =CS19+CU19+CW19+CY19 -> 143036.05 | F19: =ROUNDUP(M35,0) -> 3560 | G19: =E19+F19 -> 146596.05 | H19: =Sheet1!CR5 -> 0.18 | I19: =G19*H19 -> 26387.289 | J19: =G19+I19 -> 172983.34 | K19: =Sheet1!CU5 -> 25 | L19: =Sheet1!CV5 -> KMS | M19: =J19*K19 -> 4324583.4 | N19: =+IFERROR(VLOOKUP($N$16,Sheet1!J5:L5,3,0),0) -> 0 | O19: =+IFERROR(VLOOKUP($O$16,Sheet1!J5:L5,3,0),0) -> 0 | P19: =+IFERROR(VLOOKUP($P$16,Sheet1!J5:M5,3,0),0) -> 89 | Q19: =+IFERROR(VLOOKUP($Q$16,Sheet1!J5:M5,3,0),0) -> 0 | R19: =+IFERROR(VLOOKUP($R$16,Sheet1!J5:M5,3,0),0) -> 0 | S19: =+IFERROR(VLOOKUP($S$16,Sheet1!J5:M5,3,0),0) -> 0 | T19: =+IFERROR(VLOOKUP($T$16,Sheet1!J5:M5,3,0),0) -> 0 | U19: =+IFERROR(VLOOKUP($U$16,Sheet1!J5:M5,3,0),0) -> 0 | V19: =+IFERROR(VLOOKUP($V$16,Sheet1!N5:Q5,3,0),0) -> 0 | W19: =+IFERROR(VLOOKUP($W$16,Sheet1!N5:Q5,3,0),0) -> 0 | X19: =+IFERROR(VLOOKUP($X$16,Sheet1!F5:I5,3,0),0) -> 0 | Y19: =+IFERROR(VLOOKUP($Y$16,Sheet1!F5:I5,3,0),0) -> 0 | Z19: =+IFERROR(VLOOKUP($Z$16,Sheet1!F5:I5,3,0),0) -> 0 | AA19: =+IFERROR(VLOOKUP($AA$16,Sheet1!F5:I5,3,0),0) -> 0 | AB19: =+IFERROR(VLOOKUP($AB$16,Sheet1!F5:I5,3,0),0) -> 0 | AC19: =+IFERROR(VLOOKUP($AC$16,Sheet1!F5:I5,3,0),0) -> 0 | AD19: =+IFERROR(VLOOKUP($AD$16,Sheet1!F5:I5,3,0),0) -> 0 | AE19: =+IFERROR(VLOOKUP($AE$16,Sheet1!F5:I5,3,0),0) -> 0 | AF19: =+IFERROR(VLOOKUP($AF$16,Sheet1!R5:U5,3,0),0) -> 0 | AG19: =+IFERROR(VLOOKUP($AG$16,Sheet1!R5:U5,3,0),0) -> 0 | AH19: =+IFERROR(VLOOKUP($AH$16,Sheet1!V5:Y5,3,0),0) -> 0 | AI19: =+IFERROR(VLOOKUP($AI$16,Sheet1!V5:Y5,3,0),0) -> 0 | AJ19: =+IFERROR(VLOOKUP($AJ$16,Sheet1!V5:Y5,3,0),0) -> 0 | AK19: =+IFERROR(VLOOKUP($AK$16,Sheet1!V5:Y5,3,0),0) -> 0 | AL19: =+IFERROR(VLOOKUP($AL$16,Sheet1!V5:Y5,3,0),0) -> 52 | AM19: =+IFERROR(VLOOKUP($AM$16,Sheet1!V5:Y5,3,0),0) -> 0 | AN19: =+IFERROR(VLOOKUP($AN$16,Sheet1!V5:Y5,3,0),0) -> 0 | AO19: =+IFERROR(VLOOKUP($AO$16,Sheet1!V5:Y5,3,0),0) -> 0 | AP19: =+IFERROR(VLOOKUP($AP$16,Sheet1!V5:Y5,3,0),0) -> 0 | AQ19: =+IFERROR(VLOOKUP($AQ$16,Sheet1!Z5:AB5,3,0),0) -> 3 | AR19: =+IFERROR(VLOOKUP($AR$16,Sheet1!AD5:AG5,3,0),0) -> 0 | AS19: =+IFERROR(VLOOKUP($AS$16,Sheet1!AD5:AG5,3,0),0) -> 27 | AT19: =+IFERROR(VLOOKUP($AT$16,Sheet1!AD5:AG5,3,0),0) -> 0 | AU19: =+IFERROR(VLOOKUP($AU$16,Sheet1!AD5:AG5,3,0),0) -> 0 | AV19: =+IFERROR(VLOOKUP($AV$16,Sheet1!AD5:AG5,3,0),0) -> 0 | AW19: =+IFERROR(VLOOKUP($AW$16,Sheet1!AD5:AG5,3,0),0) -> 0 | AX19: =+IFERROR(VLOOKUP($AX$16,Sheet1!AD5:AG5,3,0),0) -> 0 | AY19: =+IFERROR(VLOOKUP($AY$16,Sheet1!AD5:AG5,3,0),0) -> 0 | AZ19: =+IFERROR(VLOOKUP($AZ$16,Sheet1!AD5:AG5,3,0),0) -> 0 | BA19: =+IFERROR(VLOOKUP($BA$16,Sheet1!AH5:AK5,3,0),0) -> 0 | BB19: =+IFERROR(VLOOKUP($BB$16,Sheet1!AH5:AK5,3,0),0) -> 0 | BC19: =+IFERROR(VLOOKUP($BC$16,Sheet1!AH5:AK5,3,0),0) -> 0 | BD19: =+IFERROR(VLOOKUP($BD$16,Sheet1!AH5:AK5,3,0),0) -> 0 | BE19: =+IFERROR(VLOOKUP($BE$16,Sheet1!AH5:AK5,3,0),0) -> 0 | BF19: =+IFERROR(VLOOKUP($BF$16,Sheet1!AH5:AK5,3,0),0) -> 0 | BG19: =+IFERROR(VLOOKUP($BG$16,Sheet1!AH5:AK5,3,0),0) -> 0 | BH19: =+IFERROR(VLOOKUP($BH$16,Sheet1!AH5:AK5,3,0),0) -> 0 | BI19: =+IFERROR(VLOOKUP($BI$16,Sheet1!AH5:AK5,3,0),0) -> 0 | BJ19: =+IFERROR(VLOOKUP($BJ$16,Sheet1!AH5:AK5,3,0),0) -> 289 | BK19: =+IFERROR(VLOOKUP($BK$16,Sheet1!AH5:AK5,3,0),0) -> 0 | BL19: =+IFERROR(VLOOKUP($BL$16,Sheet1!AL5:AO5,3,0),0) -> 0 | BM19: =+IFERROR(VLOOKUP($BM$16,Sheet1!AL5:AO5,3,0),0) -> 0 | BN19: =+IFERROR(VLOOKUP($BN$16,Sheet1!AL5:AO5,3,0),0) -> 0 | BO19: =+IFERROR(VLOOKUP($BO$16,Sheet1!AL5:AO5,3,0),0) -> 104 | BP19: =+IFERROR(VLOOKUP($BP$16,Sheet1!AL5:AO5,3,0),0) -> 0 | BQ19: =+IFERROR(VLOOKUP($BQ$16,Sheet1!AL5:AO5,3,0),0) -> 0 | BR19: =+IFERROR(VLOOKUP($BR$16,Sheet1!AL5:AO5,3,0),0) -> 0 | BS19: =+IFERROR(VLOOKUP($BS$16,Sheet1!AL5:AO5,3,0),0) -> 0 | BT19: =+IFERROR(VLOOKUP($BT$16,Sheet1!AL5:AO5,3,0),0) -> 0 | BU19: =+IFERROR(VLOOKUP($BU$16,Sheet1!AL5:AO5,3,0),0) -> 0 | BV19: =+IFERROR(VLOOKUP($BV$16,Sheet1!AL5:AO5,3,0),0) -> 0 | BW19: =+IFERROR(VLOOKUP($BW$16,Sheet1!AL5:AO5,3,0),0) -> 0 | BX19: =+IFERROR(VLOOKUP($BX$16,Sheet1!AP5:AS5,3,0),0) -> 0 | BY19: =+IFERROR(VLOOKUP($BY$16,Sheet1!AT5:AW5,3,0),0) -> 0 | BZ19: =+IFERROR(VLOOKUP($BZ$16,Sheet1!AX5:BA5,3,0),0) -> 0 | CA19: =+IFERROR(VLOOKUP($CA$16,Sheet1!BB5:BE5,3,0),0) -> 0 | CB19: =+IFERROR(VLOOKUP($CB$16,Sheet1!BF5:BI5,3,0),0) -> 0 | CC19: =+IFERROR(VLOOKUP($CC$16,Sheet1!BJ5:BM5,3,0),0) -> 0 | CD19: =+IFERROR(VLOOKUP($CD$16,Sheet1!BN5:BQ5,3,0),0) -> 0 | CE19: =+IFERROR(VLOOKUP($CE$16,Sheet1!BR5:BU5,3,0),0) -> 0 | CF19: =+IFERROR(VLOOKUP($CF$16,Sheet1!BV5:BY5,3,0),0) -> 0 | CG19: =Sheet1!E5 -> WOOD | CH19: =Sheet1!CX5 -> MD0100005 | CI19: =Sheet1!CY5 -> DRUM - 36 X 14 X 23 X 2 | CJ19: =Sheet1!CZ5 -> 500 | CK19: =Sheet1!BZ5 -> 5170 | CL19: =SUMPRODUCT($N$17:$CF$17,N19:CF19)+CK19 -> 129785 | CM19: =Sheet1!CB5 -> 0 | CN19: =CL19*CM19 -> 0 | CO19: 0.07 | CP19: =CL19*CO19 -> 9084.95 | CQ19: 0 | CR19: =CL19*CQ19 -> 0 | CS19: =CL19+CN19+CP19+CR19 -> 138869.95 | CT19: 0.02 | CU19: =CS19*CT19 -> 2777.399 | CV19: 0.01 | CW19: =CS19*CV19 -> 1388.6995 | CX19: =Sheet1!CM5 -> 0 | CY19: =CX19*CS19 -> 0
A20: =Sheet1!A2 -> ENQ-16531-25-26 | B20: 45839 | C20: =Sheet1!C2 -> FA0200002 | D20: =Sheet1!D2 -> 10 CORE X 2.5 SQ. MM. CU/ARD - WIRE (PVC) | E20: =CS20+CU20+CW20+CY20 -> 317419.13 | F20: =ROUNDUP(M36,0) -> 3815 | G20: =E20+F20 -> 321234.13 | H20: =Sheet1!CR2 -> 0.18 | I20: =G20*H20 -> 57822.143 | J20: =G20+I20 -> 379056.27 | K20: =Sheet1!CU2 -> 35 | L20: =Sheet1!CV2 -> KMS | M20: =J20*K20 -> 13266969 | N20: =+IFERROR(VLOOKUP($N$16,Sheet1!J2:L2,3,0),0) -> 0 | O20: =+IFERROR(VLOOKUP($O$16,Sheet1!J2:L2,3,0),0) -> 0 | P20: =+IFERROR(VLOOKUP($P$16,Sheet1!J2:M2,3,0),0) -> 222 | Q20: =+IFERROR(VLOOKUP($Q$16,Sheet1!J2:M2,3,0),0) -> 0 | R20: =+IFERROR(VLOOKUP($R$16,Sheet1!J2:M2,3,0),0) -> 0 | S20: =+IFERROR(VLOOKUP($S$16,Sheet1!J2:M2,3,0),0) -> 0 | T20: =+IFERROR(VLOOKUP($T$16,Sheet1!J2:M2,3,0),0) -> 0 | U20: =+IFERROR(VLOOKUP($U$16,Sheet1!J2:M2,3,0),0) -> 0 | V20: =+IFERROR(VLOOKUP($V$16,Sheet1!N2:Q2,3,0),0) -> 0 | W20: =+IFERROR(VLOOKUP($W$16,Sheet1!N2:Q2,3,0),0) -> 0 | X20: =+IFERROR(VLOOKUP($X$16,Sheet1!F2:I2,3,0),0) -> 0 | Y20: =+IFERROR(VLOOKUP($Y$16,Sheet1!F2:I2,3,0),0) -> 0 | Z20: =+IFERROR(VLOOKUP($Z$16,Sheet1!F2:I2,3,0),0) -> 0 | AA20: =+IFERROR(VLOOKUP($AA$16,Sheet1!F2:I2,3,0),0) -> 0 | AB20: =+IFERROR(VLOOKUP($AB$16,Sheet1!F2:I2,3,0),0) -> 0 | AC20: =+IFERROR(VLOOKUP($AC$16,Sheet1!F2:I2,3,0),0) -> 0 | AD20: =+IFERROR(VLOOKUP($AD$16,Sheet1!F2:I2,3,0),0) -> 0 | AE20: =+IFERROR(VLOOKUP($AE$16,Sheet1!F2:I2,3,0),0) -> 0 | AF20: =+IFERROR(VLOOKUP($AF$16,Sheet1!R2:U2,3,0),0) -> 0 | AG20: =+IFERROR(VLOOKUP($AG$16,Sheet1!R2:U2,3,0),0) -> 0 | AH20: =+IFERROR(VLOOKUP($AH$16,Sheet1!V2:Y2,3,0),0) -> 0 | AI20: =+IFERROR(VLOOKUP($AI$16,Sheet1!V2:Y2,3,0),0) -> 0 | AJ20: =+IFERROR(VLOOKUP($AJ$16,Sheet1!V2:Y2,3,0),0) -> 0 | AK20: =+IFERROR(VLOOKUP($AK$16,Sheet1!V2:Y2,3,0),0) -> 0 | AL20: =+IFERROR(VLOOKUP($AL$16,Sheet1!V2:Y2,3,0),0) -> 130 | AM20: =+IFERROR(VLOOKUP($AM$16,Sheet1!V2:Y2,3,0),0) -> 0 | AN20: =+IFERROR(VLOOKUP($AN$16,Sheet1!V2:Y2,3,0),0) -> 0 | AO20: =+IFERROR(VLOOKUP($AO$16,Sheet1!V2:Y2,3,0),0) -> 0 | AP20: =+IFERROR(VLOOKUP($AP$16,Sheet1!V2:Y2,3,0),0) -> 0 | AQ20: =+IFERROR(VLOOKUP($AQ$16,Sheet1!Z2:AB2,3,0),0) -> 5 | AR20: =+IFERROR(VLOOKUP($AR$16,Sheet1!AD2:AG2,3,0),0) -> 0 | AS20: =+IFERROR(VLOOKUP($AS$16,Sheet1!AD2:AG2,3,0),0) -> 38 | AT20: =+IFERROR(VLOOKUP($AT$16,Sheet1!AD2:AG2,3,0),0) -> 0 | AU20: =+IFERROR(VLOOKUP($AU$16,Sheet1!AD2:AG2,3,0),0) -> 0 | AV20: =+IFERROR(VLOOKUP($AV$16,Sheet1!AD2:AG2,3,0),0) -> 0 | AW20: =+IFERROR(VLOOKUP($AW$16,Sheet1!AD2:AG2,3,0),0) -> 0 | AX20: =+IFERROR(VLOOKUP($AX$16,Sheet1!AD2:AG2,3,0),0) -> 0 | AY20: =+IFERROR(VLOOKUP($AY$16,Sheet1!AD2:AG2,3,0),0) -> 0 | AZ20: =+IFERROR(VLOOKUP($AZ$16,Sheet1!AD2:AG2,3,0),0) -> 0 | BA20: =+IFERROR(VLOOKUP($BA$16,Sheet1!AH2:AK2,3,0),0) -> 0 | BB20: =+IFERROR(VLOOKUP($BB$16,Sheet1!AH2:AK2,3,0),0) -> 0 | BC20: =+IFERROR(VLOOKUP($BC$16,Sheet1!AH2:AK2,3,0),0) -> 0 | BD20: =+IFERROR(VLOOKUP($BD$16,Sheet1!AH2:AK2,3,0),0) -> 0 | BE20: =+IFERROR(VLOOKUP($BE$16,Sheet1!AH2:AK2,3,0),0) -> 0 | BF20: =+IFERROR(VLOOKUP($BF$16,Sheet1!AH2:AK2,3,0),0) -> 0 | BG20: =+IFERROR(VLOOKUP($BG$16,Sheet1!AH2:AK2,3,0),0) -> 0 | BH20: =+IFERROR(VLOOKUP($BH$16,Sheet1!AH2:AK2,3,0),0) -> 0 | BI20: =+IFERROR(VLOOKUP($BI$16,Sheet1!AH2:AK2,3,0),0) -> 0 | BJ20: =+IFERROR(VLOOKUP($BJ$16,Sheet1!AH2:AK2,3,0),0) -> 492 | BK20: =+IFERROR(VLOOKUP($BK$16,Sheet1!AH2:AK2,3,0),0) -> 0 | BL20: =+IFERROR(VLOOKUP($BL$16,Sheet1!AL2:AO2,3,0),0) -> 0 | BM20: =+IFERROR(VLOOKUP($BM$16,Sheet1!AL2:AO2,3,0),0) -> 0 | BN20: =+IFERROR(VLOOKUP($BN$16,Sheet1!AL2:AO2,3,0),0) -> 0 | BO20: =+IFERROR(VLOOKUP($BO$16,Sheet1!AL2:AO2,3,0),0) -> 166 | BP20: =+IFERROR(VLOOKUP($BP$16,Sheet1!AL2:AO2,3,0),0) -> 0 | BQ20: =+IFERROR(VLOOKUP($BQ$16,Sheet1!AL2:AO2,3,0),0) -> 0 | BR20: =+IFERROR(VLOOKUP($BR$16,Sheet1!AL2:AO2,3,0),0) -> 0 | BS20: =+IFERROR(VLOOKUP($BS$16,Sheet1!AL2:AO2,3,0),0) -> 0 | BT20: =+IFERROR(VLOOKUP($BT$16,Sheet1!AL2:AO2,3,0),0) -> 0 | BU20: =+IFERROR(VLOOKUP($BU$16,Sheet1!AL2:AO2,3,0),0) -> 0 | BV20: =+IFERROR(VLOOKUP($BV$16,Sheet1!AL2:AO2,3,0),0) -> 0 | BW20: =+IFERROR(VLOOKUP($BW$16,Sheet1!AL2:AO2,3,0),0) -> 0 | BX20: =+IFERROR(VLOOKUP($BX$16,Sheet1!AP2:AS2,3,0),0) -> 0 | BY20: =+IFERROR(VLOOKUP($BY$16,Sheet1!AT2:AW2,3,0),0) -> 0 | BZ20: =+IFERROR(VLOOKUP($BZ$16,Sheet1!AX2:BA2,3,0),0) -> 0 | CA20: =+IFERROR(VLOOKUP($CA$16,Sheet1!BB2:BE2,3,0),0) -> 0 | CB20: =+IFERROR(VLOOKUP($CB$16,Sheet1!BF2:BI2,3,0),0) -> 0 | CC20: =+IFERROR(VLOOKUP($CC$16,Sheet1!BJ2:BM2,3,0),0) -> 0 | CD20: =+IFERROR(VLOOKUP($CD$16,Sheet1!BN2:BQ2,3,0),0) -> 0 | CE20: =+IFERROR(VLOOKUP($CE$16,Sheet1!BR2:BU2,3,0),0) -> 0 | CF20: =+IFERROR(VLOOKUP($CF$16,Sheet1!BV2:BY2,3,0),0) -> 0 | CG20: =Sheet1!E2 -> WOOD | CH20: =Sheet1!CX2 -> MD0100066 | CI20: =Sheet1!CY2 -> DRUM - 40 X 15 X 23 X 2 | CJ20: =Sheet1!CZ2 -> 500 | CK20: =Sheet1!BZ2 -> 5448 | CL20: =SUMPRODUCT($N$17:$CF$17,N20:CF20)+CK20 -> 288013 | CM20: =Sheet1!CB2 -> 0 | CN20: =CL20*CM20 -> 0 | CO20: 0.07 | CP20: =CL20*CO20 -> 20160.91 | CQ20: 0 | CR20: =CL20*CQ20 -> 0 | CS20: =CL20+CN20+CP20+CR20 -> 308173.91 | CT20: 0.02 | CU20: =CS20*CT20 -> 6163.4782 | CV20: 0.01 | CW20: =CS20*CV20 -> 3081.7391 | CX20: =Sheet1!CM2 -> 0 | CY20: =CX20*CS20 -> 0
A21: =Sheet1!A3 -> ENQ-16531-25-26 | B21: 45839 | C21: =Sheet1!C3 -> FA0200003 | D21: =Sheet1!D3 -> 12 CORE X 2.5 SQ. MM. CU/ARD - WIRE (PVC) | E21: =CS21+CU21+CW21+CY21 -> 368996.31 | F21: =ROUNDUP(M37,0) -> 5086 | G21: =E21+F21 -> 374082.31 | H21: =Sheet1!CR3 -> 0.18 | I21: =G21*H21 -> 67334.815 | J21: =G21+I21 -> 441417.12 | K21: =Sheet1!CU3 -> 35 | L21: =Sheet1!CV3 -> KMS | M21: =J21*K21 -> 15449599 | N21: =+IFERROR(VLOOKUP($N$16,Sheet1!J3:L3,3,0),0) -> 0 | O21: =+IFERROR(VLOOKUP($O$16,Sheet1!J3:L3,3,0),0) -> 0 | P21: =+IFERROR(VLOOKUP($P$16,Sheet1!J3:M3,3,0),0) -> 266 | Q21: =+IFERROR(VLOOKUP($Q$16,Sheet1!J3:M3,3,0),0) -> 0 | R21: =+IFERROR(VLOOKUP($R$16,Sheet1!J3:M3,3,0),0) -> 0 | S21: =+IFERROR(VLOOKUP($S$16,Sheet1!J3:M3,3,0),0) -> 0 | T21: =+IFERROR(VLOOKUP($T$16,Sheet1!J3:M3,3,0),0) -> 0 | U21: =+IFERROR(VLOOKUP($U$16,Sheet1!J3:M3,3,0),0) -> 0 | V21: =+IFERROR(VLOOKUP($V$16,Sheet1!N3:Q3,3,0),0) -> 0 | W21: =+IFERROR(VLOOKUP($W$16,Sheet1!N3:Q3,3,0),0) -> 0 | X21: =+IFERROR(VLOOKUP($X$16,Sheet1!F3:I3,3,0),0) -> 0 | Y21: =+IFERROR(VLOOKUP($Y$16,Sheet1!F3:I3,3,0),0) -> 0 | Z21: =+IFERROR(VLOOKUP($Z$16,Sheet1!F3:I3,3,0),0) -> 0 | AA21: =+IFERROR(VLOOKUP($AA$16,Sheet1!F3:I3,3,0),0) -> 0 | AB21: =+IFERROR(VLOOKUP($AB$16,Sheet1!F3:I3,3,0),0) -> 0 | AC21: =+IFERROR(VLOOKUP($AC$16,Sheet1!F3:I3,3,0),0) -> 0 | AD21: =+IFERROR(VLOOKUP($AD$16,Sheet1!F3:I3,3,0),0) -> 0 | AE21: =+IFERROR(VLOOKUP($AE$16,Sheet1!F3:I3,3,0),0) -> 0 | AF21: =+IFERROR(VLOOKUP($AF$16,Sheet1!R3:U3,3,0),0) -> 0 | AG21: =+IFERROR(VLOOKUP($AG$16,Sheet1!R3:U3,3,0),0) -> 0 | AH21: =+IFERROR(VLOOKUP($AH$16,Sheet1!V3:Y3,3,0),0) -> 0 | AI21: =+IFERROR(VLOOKUP($AI$16,Sheet1!V3:Y3,3,0),0) -> 0 | AJ21: =+IFERROR(VLOOKUP($AJ$16,Sheet1!V3:Y3,3,0),0) -> 0 | AK21: =+IFERROR(VLOOKUP($AK$16,Sheet1!V3:Y3,3,0),0) -> 0 | AL21: =+IFERROR(VLOOKUP($AL$16,Sheet1!V3:Y3,3,0),0) -> 156 | AM21: =+IFERROR(VLOOKUP($AM$16,Sheet1!V3:Y3,3,0),0) -> 0 | AN21: =+IFERROR(VLOOKUP($AN$16,Sheet1!V3:Y3,3,0),0) -> 0 | AO21: =+IFERROR(VLOOKUP($AO$16,Sheet1!V3:Y3,3,0),0) -> 0 | AP21: =+IFERROR(VLOOKUP($AP$16,Sheet1!V3:Y3,3,0),0) -> 0 | AQ21: =+IFERROR(VLOOKUP($AQ$16,Sheet1!Z3:AB3,3,0),0) -> 6 | AR21: =+IFERROR(VLOOKUP($AR$16,Sheet1!AD3:AG3,3,0),0) -> 0 | AS21: =+IFERROR(VLOOKUP($AS$16,Sheet1!AD3:AG3,3,0),0) -> 40 | AT21: =+IFERROR(VLOOKUP($AT$16,Sheet1!AD3:AG3,3,0),0) -> 0 | AU21: =+IFERROR(VLOOKUP($AU$16,Sheet1!AD3:AG3,3,0),0) -> 0 | AV21: =+IFERROR(VLOOKUP($AV$16,Sheet1!AD3:AG3,3,0),0) -> 0 | AW21: =+IFERROR(VLOOKUP($AW$16,Sheet1!AD3:AG3,3,0),0) -> 0 | AX21: =+IFERROR(VLOOKUP($AX$16,Sheet1!AD3:AG3,3,0),0) -> 0 | AY21: =+IFERROR(VLOOKUP($AY$16,Sheet1!AD3:AG3,3,0),0) -> 0 | AZ21: =+IFERROR(VLOOKUP($AZ$16,Sheet1!AD3:AG3,3,0),0) -> 0 | BA21: =+IFERROR(VLOOKUP($BA$16,Sheet1!AH3:AK3,3,0),0) -> 0 | BB21: =+IFERROR(VLOOKUP($BB$16,Sheet1!AH3:AK3,3,0),0) -> 0 | BC21: =+IFERROR(VLOOKUP($BC$16,Sheet1!AH3:AK3,3,0),0) -> 0 | BD21: =+IFERROR(VLOOKUP($BD$16,Sheet1!AH3:AK3,3,0),0) -> 0 | BE21: =+IFERROR(VLOOKUP($BE$16,Sheet1!AH3:AK3,3,0),0) -> 0 | BF21: =+IFERROR(VLOOKUP($BF$16,Sheet1!AH3:AK3,3,0),0) -> 0 | BG21: =+IFERROR(VLOOKUP($BG$16,Sheet1!AH3:AK3,3,0),0) -> 0 | BH21: =+IFERROR(VLOOKUP($BH$16,Sheet1!AH3:AK3,3,0),0) -> 0 | BI21: =+IFERROR(VLOOKUP($BI$16,Sheet1!AH3:AK3,3,0),0) -> 0 | BJ21: =+IFERROR(VLOOKUP($BJ$16,Sheet1!AH3:AK3,3,0),0) -> 508 | BK21: =+IFERROR(VLOOKUP($BK$16,Sheet1!AH3:AK3,3,0),0) -> 0 | BL21: =+IFERROR(VLOOKUP($BL$16,Sheet1!AL3:AO3,3,0),0) -> 0 | BM21: =+IFERROR(VLOOKUP($BM$16,Sheet1!AL3:AO3,3,0),0) -> 0 | BN21: =+IFERROR(VLOOKUP($BN$16,Sheet1!AL3:AO3,3,0),0) -> 0 | BO21: =+IFERROR(VLOOKUP($BO$16,Sheet1!AL3:AO3,3,0),0) -> 170 | BP21: =+IFERROR(VLOOKUP($BP$16,Sheet1!AL3:AO3,3,0),0) -> 0 | BQ21: =+IFERROR(VLOOKUP($BQ$16,Sheet1!AL3:AO3,3,0),0) -> 0 | BR21: =+IFERROR(VLOOKUP($BR$16,Sheet1!AL3:AO3,3,0),0) -> 0 | BS21: =+IFERROR(VLOOKUP($BS$16,Sheet1!AL3:AO3,3,0),0) -> 0 | BT21: =+IFERROR(VLOOKUP($BT$16,Sheet1!AL3:AO3,3,0),0) -> 0 | BU21: =+IFERROR(VLOOKUP($BU$16,Sheet1!AL3:AO3,3,0),0) -> 0 | BV21: =+IFERROR(VLOOKUP($BV$16,Sheet1!AL3:AO3,3,0),0) -> 0 | BW21: =+IFERROR(VLOOKUP($BW$16,Sheet1!AL3:AO3,3,0),0) -> 0 | BX21: =+IFERROR(VLOOKUP($BX$16,Sheet1!AP3:AS3,3,0),0) -> 0 | BY21: =+IFERROR(VLOOKUP($BY$16,Sheet1!AT3:AW3,3,0),0) -> 0 | BZ21: =+IFERROR(VLOOKUP($BZ$16,Sheet1!AX3:BA3,3,0),0) -> 0 | CA21: =+IFERROR(VLOOKUP($CA$16,Sheet1!BB3:BE3,3,0),0) -> 0 | CB21: =+IFERROR(VLOOKUP($CB$16,Sheet1!BF3:BI3,3,0),0) -> 0 | CC21: =+IFERROR(VLOOKUP($CC$16,Sheet1!BJ3:BM3,3,0),0) -> 0 | CD21: =+IFERROR(VLOOKUP($CD$16,Sheet1!BN3:BQ3,3,0),0) -> 0 | CE21: =+IFERROR(VLOOKUP($CE$16,Sheet1!BR3:BU3,3,0),0) -> 0 | CF21: =+IFERROR(VLOOKUP($CF$16,Sheet1!BV3:BY3,3,0),0) -> 0 | CG21: =Sheet1!E3 -> WOOD | CH21: =Sheet1!CX3 -> MD0100066 | CI21: =Sheet1!CY3 -> DRUM - 40 X 15 X 23 X 2 | CJ21: =Sheet1!CZ3 -> 500 | CK21: =Sheet1!BZ3 -> 5448 | CL21: =SUMPRODUCT($N$17:$CF$17,N21:CF21)+CK21 -> 334812 | CM21: =Sheet1!CB3 -> 0 | CN21: =CL21*CM21 -> 0 | CO21: 0.07 | CP21: =CL21*CO21 -> 23436.84 | CQ21: 0 | CR21: =CL21*CQ21 -> 0 | CS21: =CL21+CN21+CP21+CR21 -> 358248.84 | CT21: 0.02 | CU21: =CS21*CT21 -> 7164.9768 | CV21: 0.01 | CW21: =CS21*CV21 -> 3582.4884 | CX21: =Sheet1!CM3 -> 0 | CY21: =CX21*CS21 -> 0
A22: =Sheet1!A6 -> 0 | B22: =Sheet1!B6 -> 0 | C22: =Sheet1!C6 -> 0 | D22: =Sheet1!D6 -> 0 | E22: =CS22+CU22+CW22+CY22 -> 0 | F22: =Sheet1!CP6 -> 0 | G22: =E22+F22 -> 0 | H22: =Sheet1!CR6 -> 0 | I22: =G22*H22 -> 0 | J22: =G22+I22 -> 0 | K22: =Sheet1!CU6 -> 0 | L22: =Sheet1!CV6 -> 0 | M22: =J22*K22 -> 0 | N22: =+IFERROR(VLOOKUP($N$16,Sheet1!J6:L6,3,0),0) -> 0 | O22: =+IFERROR(VLOOKUP($O$16,Sheet1!J6:L6,3,0),0) -> 0 | P22: =+IFERROR(VLOOKUP($P$16,Sheet1!J6:M6,3,0),0) -> 0 | Q22: =+IFERROR(VLOOKUP($Q$16,Sheet1!J6:M6,3,0),0) -> 0 | R22: =+IFERROR(VLOOKUP($R$16,Sheet1!J6:M6,3,0),0) -> 0 | S22: =+IFERROR(VLOOKUP($S$16,Sheet1!J6:M6,3,0),0) -> 0 | T22: =+IFERROR(VLOOKUP($T$16,Sheet1!J6:M6,3,0),0) -> 0 | U22: =+IFERROR(VLOOKUP($U$16,Sheet1!J6:M6,3,0),0) -> 0 | V22: =+IFERROR(VLOOKUP($V$16,Sheet1!N6:Q6,3,0),0) -> 0 | W22: =+IFERROR(VLOOKUP($W$16,Sheet1!N6:Q6,3,0),0) -> 0 | X22: =+IFERROR(VLOOKUP($X$16,Sheet1!F6:I6,3,0),0) -> 0 | Y22: =+IFERROR(VLOOKUP($Y$16,Sheet1!F6:I6,3,0),0) -> 0 | Z22: =+IFERROR(VLOOKUP($Z$16,Sheet1!F6:I6,3,0),0) -> 0 | AA22: =+IFERROR(VLOOKUP($AA$16,Sheet1!F6:I6,3,0),0) -> 0 | AB22: =+IFERROR(VLOOKUP($AB$16,Sheet1!F6:I6,3,0),0) -> 0 | AC22: =+IFERROR(VLOOKUP($AC$16,Sheet1!F6:I6,3,0),0) -> 0 | AD22: =+IFERROR(VLOOKUP($AD$16,Sheet1!F6:I6,3,0),0) -> 0 | AE22: =+IFERROR(VLOOKUP($AE$16,Sheet1!F6:I6,3,0),0) -> 0 | AF22: =+IFERROR(VLOOKUP($AF$16,Sheet1!R6:U6,3,0),0) -> 0 | AG22: =+IFERROR(VLOOKUP($AG$16,Sheet1!R6:U6,3,0),0) -> 0 | AH22: =+IFERROR(VLOOKUP($AH$16,Sheet1!V6:Y6,3,0),0) -> 0 | AI22: =+IFERROR(VLOOKUP($AI$16,Sheet1!V6:Y6,3,0),0) -> 0 | AJ22: =+IFERROR(VLOOKUP($AJ$16,Sheet1!V6:Y6,3,0),0) -> 0 | AK22: =+IFERROR(VLOOKUP($AK$16,Sheet1!V6:Y6,3,0),0) -> 0 | AL22: =+IFERROR(VLOOKUP($AL$16,Sheet1!V6:Y6,3,0),0) -> 0 | AM22: =+IFERROR(VLOOKUP($AM$16,Sheet1!V6:Y6,3,0),0) -> 0 | AN22: =+IFERROR(VLOOKUP($AN$16,Sheet1!V6:Y6,3,0),0) -> 0 | AO22: =+IFERROR(VLOOKUP($AO$16,Sheet1!V6:Y6,3,0),0) -> 0 | AP22: =+IFERROR(VLOOKUP($AP$16,Sheet1!V6:Y6,3,0),0) -> 0 | AQ22: =+IFERROR(VLOOKUP($AQ$16,Sheet1!Z6:AB6,3,0),0) -> 0 | AR22: =+IFERROR(VLOOKUP($AR$16,Sheet1!AD6:AG6,3,0),0) -> 0 | AS22: =+IFERROR(VLOOKUP($AS$16,Sheet1!AD6:AG6,3,0),0) -> 0 | AT22: =+IFERROR(VLOOKUP($AT$16,Sheet1!AD6:AG6,3,0),0) -> 0 | AU22: =+IFERROR(VLOOKUP($AU$16,Sheet1!AD6:AG6,3,0),0) -> 0 | AV22: =+IFERROR(VLOOKUP($AV$16,Sheet1!AD6:AG6,3,0),0) -> 0 | AW22: =+IFERROR(VLOOKUP($AW$16,Sheet1!AD6:AG6,3,0),0) -> 0 | AX22: =+IFERROR(VLOOKUP($AX$16,Sheet1!AD6:AG6,3,0),0) -> 0 | AY22: =+IFERROR(VLOOKUP($AY$16,Sheet1!AD6:AG6,3,0),0) -> 0 | AZ22: =+IFERROR(VLOOKUP($AZ$16,Sheet1!AD6:AG6,3,0),0) -> 0 | BA22: =+IFERROR(VLOOKUP($BA$16,Sheet1!AH6:AK6,3,0),0) -> 0 | BB22: =+IFERROR(VLOOKUP($BB$16,Sheet1!AH6:AK6,3,0),0) -> 0 | BC22: =+IFERROR(VLOOKUP($BC$16,Sheet1!AH6:AK6,3,0),0) -> 0 | BD22: =+IFERROR(VLOOKUP($BD$16,Sheet1!AH6:AK6,3,0),0) -> 0 | BE22: =+IFERROR(VLOOKUP($BE$16,Sheet1!AH6:AK6,3,0),0) -> 0 | BF22: =+IFERROR(VLOOKUP($BF$16,Sheet1!AH6:AK6,3,0),0) -> 0 | BG22: =+IFERROR(VLOOKUP($BG$16,Sheet1!AH6:AK6,3,0),0) -> 0 | BH22: =+IFERROR(VLOOKUP($BH$16,Sheet1!AH6:AK6,3,0),0) -> 0 | BI22: =+IFERROR(VLOOKUP($BI$16,Sheet1!AH6:AK6,3,0),0) -> 0 | BJ22: =+IFERROR(VLOOKUP($BJ$16,Sheet1!AH6:AK6,3,0),0) -> 0 | BK22: =+IFERROR(VLOOKUP($BK$16,Sheet1!AH6:AK6,3,0),0) -> 0 | BL22: =+IFERROR(VLOOKUP($BL$16,Sheet1!AL6:AO6,3,0),0) -> 0 | BM22: =+IFERROR(VLOOKUP($BM$16,Sheet1!AL6:AO6,3,0),0) -> 0 | BN22: =+IFERROR(VLOOKUP($BN$16,Sheet1!AL6:AO6,3,0),0) -> 0 | BO22: =+IFERROR(VLOOKUP($BO$16,Sheet1!AL6:AO6,3,0),0) -> 0 | BP22: =+IFERROR(VLOOKUP($BP$16,Sheet1!AL6:AO6,3,0),0) -> 0 | BQ22: =+IFERROR(VLOOKUP($BQ$16,Sheet1!AL6:AO6,3,0),0) -> 0 | BR22: =+IFERROR(VLOOKUP($BR$16,Sheet1!AL6:AO6,3,0),0) -> 0 | BS22: =+IFERROR(VLOOKUP($BS$16,Sheet1!AL6:AO6,3,0),0) -> 0 | BT22: =+IFERROR(VLOOKUP($BT$16,Sheet1!AL6:AO6,3,0),0) -> 0 | BU22: =+IFERROR(VLOOKUP($BU$16,Sheet1!AL6:AO6,3,0),0) -> 0 | BV22: =+IFERROR(VLOOKUP($BV$16,Sheet1!AL6:AO6,3,0),0) -> 0 | BW22: =+IFERROR(VLOOKUP($BW$16,Sheet1!AL6:AO6,3,0),0) -> 0 | BX22: =+IFERROR(VLOOKUP($BX$16,Sheet1!AP6:AS6,3,0),0) -> 0 | BY22: =+IFERROR(VLOOKUP($BY$16,Sheet1!AT6:AW6,3,0),0) -> 0 | BZ22: =+IFERROR(VLOOKUP($BZ$16,Sheet1!AX6:BA6,3,0),0) -> 0 | CA22: =+IFERROR(VLOOKUP($CA$16,Sheet1!BB6:BE6,3,0),0) -> 0 | CB22: =+IFERROR(VLOOKUP($CB$16,Sheet1!BF6:BI6,3,0),0) -> 0 | CC22: =+IFERROR(VLOOKUP($CC$16,Sheet1!BJ6:BM6,3,0),0) -> 0 | CD22: =+IFERROR(VLOOKUP($CD$16,Sheet1!BN6:BQ6,3,0),0) -> 0 | CE22: =+IFERROR(VLOOKUP($CE$16,Sheet1!BR6:BU6,3,0),0) -> 0 | CF22: =+IFERROR(VLOOKUP($CF$16,Sheet1!BV6:BY6,3,0),0) -> 0 | CG22: =Sheet1!E6 -> 0 | CH22: =Sheet1!CX6 -> 0 | CI22: =Sheet1!CY6 -> 0 | CJ22: =Sheet1!CZ6 -> 0 | CK22: =Sheet1!BZ6 -> 0 | CL22: =SUMPRODUCT($N$17:$CF$17,N22:CF22)+CK22 -> 0 | CM22: =Sheet1!CB6 -> 0 | CN22: =CL22*CM22 -> 0 | CO22: =Sheet1!CD6 -> 0 | CP22: =CL22*CO22 -> 0 | CQ22: =Sheet1!CF6 -> 0 | CR22: =CL22*CQ22 -> 0 | CS22: =CL22+CN22+CP22+CR22 -> 0 | CT22: =Sheet1!CI6 -> 0 | CU22: =CS22*CT22 -> 0 | CV22: =Sheet1!CK6 -> 0 | CW22: =CS22*CV22 -> 0 | CX22: =Sheet1!CM6 -> 0 | CY22: =CX22*CS22 -> 0
A23: =Sheet1!A7 -> 0 | B23: =Sheet1!B7 -> 0 | C23: =Sheet1!C7 -> 0 | D23: =Sheet1!D7 -> 0 | E23: =CS23+CU23+CW23+CY23 -> 0 | F23: =Sheet1!CP7 -> 0 | G23: =E23+F23 -> 0 | H23: =Sheet1!CR7 -> 0 | I23: =G23*H23 -> 0 | J23: =G23+I23 -> 0 | K23: =Sheet1!CU7 -> 0 | L23: =Sheet1!CV7 -> 0 | M23: =J23*K23 -> 0 | N23: =+IFERROR(VLOOKUP($N$16,Sheet1!J7:L7,3,0),0) -> 0 | O23: =+IFERROR(VLOOKUP($O$16,Sheet1!J7:L7,3,0),0) -> 0 | P23: =+IFERROR(VLOOKUP($P$16,Sheet1!J7:M7,3,0),0) -> 0 | Q23: =+IFERROR(VLOOKUP($Q$16,Sheet1!J7:M7,3,0),0) -> 0 | R23: =+IFERROR(VLOOKUP($R$16,Sheet1!J7:M7,3,0),0) -> 0 | S23: =+IFERROR(VLOOKUP($S$16,Sheet1!J7:M7,3,0),0) -> 0 | T23: =+IFERROR(VLOOKUP($T$16,Sheet1!J7:M7,3,0),0) -> 0 | U23: =+IFERROR(VLOOKUP($U$16,Sheet1!J7:M7,3,0),0) -> 0 | V23: =+IFERROR(VLOOKUP($V$16,Sheet1!N7:Q7,3,0),0) -> 0 | W23: =+IFERROR(VLOOKUP($W$16,Sheet1!N7:Q7,3,0),0) -> 0 | X23: =+IFERROR(VLOOKUP($X$16,Sheet1!F7:I7,3,0),0) -> 0 | Y23: =+IFERROR(VLOOKUP($Y$16,Sheet1!F7:I7,3,0),0) -> 0 | Z23: =+IFERROR(VLOOKUP($Z$16,Sheet1!F7:I7,3,0),0) -> 0 | AA23: =+IFERROR(VLOOKUP($AA$16,Sheet1!F7:I7,3,0),0) -> 0 | AB23: =+IFERROR(VLOOKUP($AB$16,Sheet1!F7:I7,3,0),0) -> 0 | AC23: =+IFERROR(VLOOKUP($AC$16,Sheet1!F7:I7,3,0),0) -> 0 | AD23: =+IFERROR(VLOOKUP($AD$16,Sheet1!F7:I7,3,0),0) -> 0 | AE23: =+IFERROR(VLOOKUP($AE$16,Sheet1!F7:I7,3,0),0) -> 0 | AF23: =+IFERROR(VLOOKUP($AF$16,Sheet1!R7:U7,3,0),0) -> 0 | AG23: =+IFERROR(VLOOKUP($AG$16,Sheet1!R7:U7,3,0),0) -> 0 | AH23: =+IFERROR(VLOOKUP($AH$16,Sheet1!V7:Y7,3,0),0) -> 0 | AI23: =+IFERROR(VLOOKUP($AI$16,Sheet1!V7:Y7,3,0),0) -> 0 | AJ23: =+IFERROR(VLOOKUP($AJ$16,Sheet1!V7:Y7,3,0),0) -> 0 | AK23: =+IFERROR(VLOOKUP($AK$16,Sheet1!V7:Y7,3,0),0) -> 0 | AL23: =+IFERROR(VLOOKUP($AL$16,Sheet1!V7:Y7,3,0),0) -> 0 | AM23: =+IFERROR(VLOOKUP($AM$16,Sheet1!V7:Y7,3,0),0) -> 0 | AN23: =+IFERROR(VLOOKUP($AN$16,Sheet1!V7:Y7,3,0),0) -> 0 | AO23: =+IFERROR(VLOOKUP($AO$16,Sheet1!V7:Y7,3,0),0) -> 0 | AP23: =+IFERROR(VLOOKUP($AP$16,Sheet1!V7:Y7,3,0),0) -> 0 | AQ23: =+IFERROR(VLOOKUP($AQ$16,Sheet1!Z7:AB7,3,0),0) -> 0 | AR23: =+IFERROR(VLOOKUP($AR$16,Sheet1!AD7:AG7,3,0),0) -> 0 | AS23: =+IFERROR(VLOOKUP($AS$16,Sheet1!AD7:AG7,3,0),0) -> 0 | AT23: =+IFERROR(VLOOKUP($AT$16,Sheet1!AD7:AG7,3,0),0) -> 0 | AU23: =+IFERROR(VLOOKUP($AU$16,Sheet1!AD7:AG7,3,0),0) -> 0 | AV23: =+IFERROR(VLOOKUP($AV$16,Sheet1!AD7:AG7,3,0),0) -> 0 | AW23: =+IFERROR(VLOOKUP($AW$16,Sheet1!AD7:AG7,3,0),0) -> 0 | AX23: =+IFERROR(VLOOKUP($AX$16,Sheet1!AD7:AG7,3,0),0) -> 0 | AY23: =+IFERROR(VLOOKUP($AY$16,Sheet1!AD7:AG7,3,0),0) -> 0 | AZ23: =+IFERROR(VLOOKUP($AZ$16,Sheet1!AD7:AG7,3,0),0) -> 0 | BA23: =+IFERROR(VLOOKUP($BA$16,Sheet1!AH7:AK7,3,0),0) -> 0 | BB23: =+IFERROR(VLOOKUP($BB$16,Sheet1!AH7:AK7,3,0),0) -> 0 | BC23: =+IFERROR(VLOOKUP($BC$16,Sheet1!AH7:AK7,3,0),0) -> 0 | BD23: =+IFERROR(VLOOKUP($BD$16,Sheet1!AH7:AK7,3,0),0) -> 0 | BE23: =+IFERROR(VLOOKUP($BE$16,Sheet1!AH7:AK7,3,0),0) -> 0 | BF23: =+IFERROR(VLOOKUP($BF$16,Sheet1!AH7:AK7,3,0),0) -> 0 | BG23: =+IFERROR(VLOOKUP($BG$16,Sheet1!AH7:AK7,3,0),0) -> 0 | BH23: =+IFERROR(VLOOKUP($BH$16,Sheet1!AH7:AK7,3,0),0) -> 0 | BI23: =+IFERROR(VLOOKUP($BI$16,Sheet1!AH7:AK7,3,0),0) -> 0 | BJ23: =+IFERROR(VLOOKUP($BJ$16,Sheet1!AH7:AK7,3,0),0) -> 0 | BK23: =+IFERROR(VLOOKUP($BK$16,Sheet1!AH7:AK7,3,0),0) -> 0 | BL23: =+IFERROR(VLOOKUP($BL$16,Sheet1!AL7:AO7,3,0),0) -> 0 | BM23: =+IFERROR(VLOOKUP($BM$16,Sheet1!AL7:AO7,3,0),0) -> 0 | BN23: =+IFERROR(VLOOKUP($BN$16,Sheet1!AL7:AO7,3,0),0) -> 0 | BO23: =+IFERROR(VLOOKUP($BO$16,Sheet1!AL7:AO7,3,0),0) -> 0 | BP23: =+IFERROR(VLOOKUP($BP$16,Sheet1!AL7:AO7,3,0),0) -> 0 | BQ23: =+IFERROR(VLOOKUP($BQ$16,Sheet1!AL7:AO7,3,0),0) -> 0 | BR23: =+IFERROR(VLOOKUP($BR$16,Sheet1!AL7:AO7,3,0),0) -> 0 | BS23: =+IFERROR(VLOOKUP($BS$16,Sheet1!AL7:AO7,3,0),0) -> 0 | BT23: =+IFERROR(VLOOKUP($BT$16,Sheet1!AL7:AO7,3,0),0) -> 0 | BU23: =+IFERROR(VLOOKUP($BU$16,Sheet1!AL7:AO7,3,0),0) -> 0 | BV23: =+IFERROR(VLOOKUP($BV$16,Sheet1!AL7:AO7,3,0),0) -> 0 | BW23: =+IFERROR(VLOOKUP($BW$16,Sheet1!AL7:AO7,3,0),0) -> 0 | BX23: =+IFERROR(VLOOKUP($BX$16,Sheet1!AP7:AS7,3,0),0) -> 0 | BY23: =+IFERROR(VLOOKUP($BY$16,Sheet1!AT7:AW7,3,0),0) -> 0 | BZ23: =+IFERROR(VLOOKUP($BZ$16,Sheet1!AX7:BA7,3,0),0) -> 0 | CA23: =+IFERROR(VLOOKUP($CA$16,Sheet1!BB7:BE7,3,0),0) -> 0 | CB23: =+IFERROR(VLOOKUP($CB$16,Sheet1!BF7:BI7,3,0),0) -> 0 | CC23: =+IFERROR(VLOOKUP($CC$16,Sheet1!BJ7:BM7,3,0),0) -> 0 | CD23: =+IFERROR(VLOOKUP($CD$16,Sheet1!BN7:BQ7,3,0),0) -> 0 | CE23: =+IFERROR(VLOOKUP($CE$16,Sheet1!BR7:BU7,3,0),0) -> 0 | CF23: =+IFERROR(VLOOKUP($CF$16,Sheet1!BV7:BY7,3,0),0) -> 0 | CG23: =Sheet1!E7 -> 0 | CH23: =Sheet1!CX7 -> 0 | CI23: =Sheet1!CY7 -> 0 | CJ23: =Sheet1!CZ7 -> 0 | CK23: =Sheet1!BZ7 -> 0 | CL23: =SUMPRODUCT($N$17:$CF$17,N23:CF23)+CK23 -> 0 | CM23: =Sheet1!CB7 -> 0 | CN23: =CL23*CM23 -> 0 | CO23: =Sheet1!CD7 -> 0 | CP23: =CL23*CO23 -> 0 | CQ23: =Sheet1!CF7 -> 0 | CR23: =CL23*CQ23 -> 0 | CS23: =CL23+CN23+CP23+CR23 -> 0 | CT23: =Sheet1!CI7 -> 0 | CU23: =CS23*CT23 -> 0 | CV23: =Sheet1!CK7 -> 0 | CW23: =CS23*CV23 -> 0 | CX23: =Sheet1!CM7 -> 0 | CY23: =CX23*CS23 -> 0
A24: =Sheet1!A8 -> 0 | B24: =Sheet1!B8 -> 0 | C24: =Sheet1!C8 -> 0 | D24: =Sheet1!D8 -> 0 | E24: =CS24+CU24+CW24+CY24 -> 0 | F24: =Sheet1!CP8 -> 0 | G24: =E24+F24 -> 0 | H24: =Sheet1!CR8 -> 0 | I24: =G24*H24 -> 0 | J24: =G24+I24 -> 0 | K24: =Sheet1!CU8 -> 0 | L24: =Sheet1!CV8 -> 0 | M24: =J24*K24 -> 0 | N24: =+IFERROR(VLOOKUP($N$16,Sheet1!J8:L8,3,0),0) -> 0 | O24: =+IFERROR(VLOOKUP($O$16,Sheet1!J8:L8,3,0),0) -> 0 | P24: =+IFERROR(VLOOKUP($P$16,Sheet1!J8:M8,3,0),0) -> 0 | Q24: =+IFERROR(VLOOKUP($Q$16,Sheet1!J8:M8,3,0),0) -> 0 | R24: =+IFERROR(VLOOKUP($R$16,Sheet1!J8:M8,3,0),0) -> 0 | S24: =+IFERROR(VLOOKUP($S$16,Sheet1!J8:M8,3,0),0) -> 0 | T24: =+IFERROR(VLOOKUP($T$16,Sheet1!J8:M8,3,0),0) -> 0 | U24: =+IFERROR(VLOOKUP($U$16,Sheet1!J8:M8,3,0),0) -> 0 | V24: =+IFERROR(VLOOKUP($V$16,Sheet1!N8:Q8,3,0),0) -> 0 | W24: =+IFERROR(VLOOKUP($W$16,Sheet1!N8:Q8,3,0),0) -> 0 | X24: =+IFERROR(VLOOKUP($X$16,Sheet1!F8:I8,3,0),0) -> 0 | Y24: =+IFERROR(VLOOKUP($Y$16,Sheet1!F8:I8,3,0),0) -> 0 | Z24: =+IFERROR(VLOOKUP($Z$16,Sheet1!F8:I8,3,0),0) -> 0 | AA24: =+IFERROR(VLOOKUP($AA$16,Sheet1!F8:I8,3,0),0) -> 0 | AB24: =+IFERROR(VLOOKUP($AB$16,Sheet1!F8:I8,3,0),0) -> 0 | AC24: =+IFERROR(VLOOKUP($AC$16,Sheet1!F8:I8,3,0),0) -> 0 | AD24: =+IFERROR(VLOOKUP($AD$16,Sheet1!F8:I8,3,0),0) -> 0 | AE24: =+IFERROR(VLOOKUP($AE$16,Sheet1!F8:I8,3,0),0) -> 0 | AF24: =+IFERROR(VLOOKUP($AF$16,Sheet1!R8:U8,3,0),0) -> 0 | AG24: =+IFERROR(VLOOKUP($AG$16,Sheet1!R8:U8,3,0),0) -> 0 | AH24: =+IFERROR(VLOOKUP($AH$16,Sheet1!V8:Y8,3,0),0) -> 0 | AI24: =+IFERROR(VLOOKUP($AI$16,Sheet1!V8:Y8,3,0),0) -> 0 | AJ24: =+IFERROR(VLOOKUP($AJ$16,Sheet1!V8:Y8,3,0),0) -> 0 | AK24: =+IFERROR(VLOOKUP($AK$16,Sheet1!V8:Y8,3,0),0) -> 0 | AL24: =+IFERROR(VLOOKUP($AL$16,Sheet1!V8:Y8,3,0),0) -> 0 | AM24: =+IFERROR(VLOOKUP($AM$16,Sheet1!V8:Y8,3,0),0) -> 0 | AN24: =+IFERROR(VLOOKUP($AN$16,Sheet1!V8:Y8,3,0),0) -> 0 | AO24: =+IFERROR(VLOOKUP($AO$16,Sheet1!V8:Y8,3,0),0) -> 0 | AP24: =+IFERROR(VLOOKUP($AP$16,Sheet1!V8:Y8,3,0),0) -> 0 | AQ24: =+IFERROR(VLOOKUP($AQ$16,Sheet1!Z8:AB8,3,0),0) -> 0 | AR24: =+IFERROR(VLOOKUP($AR$16,Sheet1!AD8:AG8,3,0),0) -> 0 | AS24: =+IFERROR(VLOOKUP($AS$16,Sheet1!AD8:AG8,3,0),0) -> 0 | AT24: =+IFERROR(VLOOKUP($AT$16,Sheet1!AD8:AG8,3,0),0) -> 0 | AU24: =+IFERROR(VLOOKUP($AU$16,Sheet1!AD8:AG8,3,0),0) -> 0 | AV24: =+IFERROR(VLOOKUP($AV$16,Sheet1!AD8:AG8,3,0),0) -> 0 | AW24: =+IFERROR(VLOOKUP($AW$16,Sheet1!AD8:AG8,3,0),0) -> 0 | AX24: =+IFERROR(VLOOKUP($AX$16,Sheet1!AD8:AG8,3,0),0) -> 0 | AY24: =+IFERROR(VLOOKUP($AY$16,Sheet1!AD8:AG8,3,0),0) -> 0 | AZ24: =+IFERROR(VLOOKUP($AZ$16,Sheet1!AD8:AG8,3,0),0) -> 0 | BA24: =+IFERROR(VLOOKUP($BA$16,Sheet1!AH8:AK8,3,0),0) -> 0 | BB24: =+IFERROR(VLOOKUP($BB$16,Sheet1!AH8:AK8,3,0),0) -> 0 | BC24: =+IFERROR(VLOOKUP($BC$16,Sheet1!AH8:AK8,3,0),0) -> 0 | BD24: =+IFERROR(VLOOKUP($BD$16,Sheet1!AH8:AK8,3,0),0) -> 0 | BE24: =+IFERROR(VLOOKUP($BE$16,Sheet1!AH8:AK8,3,0),0) -> 0 | BF24: =+IFERROR(VLOOKUP($BF$16,Sheet1!AH8:AK8,3,0),0) -> 0 | BG24: =+IFERROR(VLOOKUP($BG$16,Sheet1!AH8:AK8,3,0),0) -> 0 | BH24: =+IFERROR(VLOOKUP($BH$16,Sheet1!AH8:AK8,3,0),0) -> 0 | BI24: =+IFERROR(VLOOKUP($BI$16,Sheet1!AH8:AK8,3,0),0) -> 0 | BJ24: =+IFERROR(VLOOKUP($BJ$16,Sheet1!AH8:AK8,3,0),0) -> 0 | BK24: =+IFERROR(VLOOKUP($BK$16,Sheet1!AH8:AK8,3,0),0) -> 0 | BL24: =+IFERROR(VLOOKUP($BL$16,Sheet1!AL8:AO8,3,0),0) -> 0 | BM24: =+IFERROR(VLOOKUP($BM$16,Sheet1!AL8:AO8,3,0),0) -> 0 | BN24: =+IFERROR(VLOOKUP($BN$16,Sheet1!AL8:AO8,3,0),0) -> 0 | BO24: =+IFERROR(VLOOKUP($BO$16,Sheet1!AL8:AO8,3,0),0) -> 0 | BP24: =+IFERROR(VLOOKUP($BP$16,Sheet1!AL8:AO8,3,0),0) -> 0 | BQ24: =+IFERROR(VLOOKUP($BQ$16,Sheet1!AL8:AO8,3,0),0) -> 0 | BR24: =+IFERROR(VLOOKUP($BR$16,Sheet1!AL8:AO8,3,0),0) -> 0 | BS24: =+IFERROR(VLOOKUP($BS$16,Sheet1!AL8:AO8,3,0),0) -> 0 | BT24: =+IFERROR(VLOOKUP($BT$16,Sheet1!AL8:AO8,3,0),0) -> 0 | BU24: =+IFERROR(VLOOKUP($BU$16,Sheet1!AL8:AO8,3,0),0) -> 0 | BV24: =+IFERROR(VLOOKUP($BV$16,Sheet1!AL8:AO8,3,0),0) -> 0 | BW24: =+IFERROR(VLOOKUP($BW$16,Sheet1!AL8:AO8,3,0),0) -> 0 | BX24: =+IFERROR(VLOOKUP($BX$16,Sheet1!AP8:AS8,3,0),0) -> 0 | BY24: =+IFERROR(VLOOKUP($BY$16,Sheet1!AT8:AW8,3,0),0) -> 0 | BZ24: =+IFERROR(VLOOKUP($BZ$16,Sheet1!AX8:BA8,3,0),0) -> 0 | CA24: =+IFERROR(VLOOKUP($CA$16,Sheet1!BB8:BE8,3,0),0) -> 0 | CB24: =+IFERROR(VLOOKUP($CB$16,Sheet1!BF8:BI8,3,0),0) -> 0 | CC24: =+IFERROR(VLOOKUP($CC$16,Sheet1!BJ8:BM8,3,0),0) -> 0 | CD24: =+IFERROR(VLOOKUP($CD$16,Sheet1!BN8:BQ8,3,0),0) -> 0 | CE24: =+IFERROR(VLOOKUP($CE$16,Sheet1!BR8:BU8,3,0),0) -> 0 | CF24: =+IFERROR(VLOOKUP($CF$16,Sheet1!BV8:BY8,3,0),0) -> 0 | CG24: =Sheet1!E8 -> 0 | CH24: =Sheet1!CX8 -> 0 | CI24: =Sheet1!CY8 -> 0 | CJ24: =Sheet1!CZ8 -> 0 | CK24: =Sheet1!BZ8 -> 0 | CL24: =SUMPRODUCT($N$17:$CF$17,N24:CF24)+CK24 -> 0 | CM24: =Sheet1!CB8 -> 0 | CN24: =CL24*CM24 -> 0 | CO24: =Sheet1!CD8 -> 0 | CP24: =CL24*CO24 -> 0 | CQ24: =Sheet1!CF8 -> 0 | CR24: =CL24*CQ24 -> 0 | CS24: =CL24+CN24+CP24+CR24 -> 0 | CT24: =Sheet1!CI8 -> 0 | CU24: =CS24*CT24 -> 0 | CV24: =Sheet1!CK8 -> 0 | CW24: =CS24*CV24 -> 0 | CX24: =Sheet1!CM8 -> 0 | CY24: =CX24*CS24 -> 0
A25: =Sheet1!A9 -> 0 | B25: =Sheet1!B9 -> 0 | C25: =Sheet1!C9 -> 0 | D25: =Sheet1!D9 -> 0 | E25: =CS25+CU25+CW25+CY25 -> 0 | F25: =Sheet1!CP9 -> 0 | G25: =E25+F25 -> 0 | H25: =Sheet1!CR9 -> 0 | I25: =G25*H25 -> 0 | J25: =G25+I25 -> 0 | K25: =Sheet1!CU9 -> 0 | L25: =Sheet1!CV9 -> 0 | M25: =J25*K25 -> 0 | N25: =+IFERROR(VLOOKUP($N$16,Sheet1!J9:L9,3,0),0) -> 0 | O25: =+IFERROR(VLOOKUP($O$16,Sheet1!J9:L9,3,0),0) -> 0 | P25: =+IFERROR(VLOOKUP($P$16,Sheet1!J9:M9,3,0),0) -> 0 | Q25: =+IFERROR(VLOOKUP($Q$16,Sheet1!J9:M9,3,0),0) -> 0 | R25: =+IFERROR(VLOOKUP($R$16,Sheet1!J9:M9,3,0),0) -> 0 | S25: =+IFERROR(VLOOKUP($S$16,Sheet1!J9:M9,3,0),0) -> 0 | T25: =+IFERROR(VLOOKUP($T$16,Sheet1!J9:M9,3,0),0) -> 0 | U25: =+IFERROR(VLOOKUP($U$16,Sheet1!J9:M9,3,0),0) -> 0 | V25: =+IFERROR(VLOOKUP($V$16,Sheet1!N9:Q9,3,0),0) -> 0 | W25: =+IFERROR(VLOOKUP($W$16,Sheet1!N9:Q9,3,0),0) -> 0 | X25: =+IFERROR(VLOOKUP($X$16,Sheet1!F9:I9,3,0),0) -> 0 | Y25: =+IFERROR(VLOOKUP($Y$16,Sheet1!F9:I9,3,0),0) -> 0 | Z25: =+IFERROR(VLOOKUP($Z$16,Sheet1!F9:I9,3,0),0) -> 0 | AA25: =+IFERROR(VLOOKUP($AA$16,Sheet1!F9:I9,3,0),0) -> 0 | AB25: =+IFERROR(VLOOKUP($AB$16,Sheet1!F9:I9,3,0),0) -> 0 | AC25: =+IFERROR(VLOOKUP($AC$16,Sheet1!F9:I9,3,0),0) -> 0 | AD25: =+IFERROR(VLOOKUP($AD$16,Sheet1!F9:I9,3,0),0) -> 0 | AE25: =+IFERROR(VLOOKUP($AE$16,Sheet1!F9:I9,3,0),0) -> 0 | AF25: =+IFERROR(VLOOKUP($AF$16,Sheet1!R9:U9,3,0),0) -> 0 | AG25: =+IFERROR(VLOOKUP($AG$16,Sheet1!R9:U9,3,0),0) -> 0 | AH25: =+IFERROR(VLOOKUP($AH$16,Sheet1!V9:Y9,3,0),0) -> 0 | AI25: =+IFERROR(VLOOKUP($AI$16,Sheet1!V9:Y9,3,0),0) -> 0 | AJ25: =+IFERROR(VLOOKUP($AJ$16,Sheet1!V9:Y9,3,0),0) -> 0 | AK25: =+IFERROR(VLOOKUP($AK$16,Sheet1!V9:Y9,3,0),0) -> 0 | AL25: =+IFERROR(VLOOKUP($AL$16,Sheet1!V9:Y9,3,0),0) -> 0 | AM25: =+IFERROR(VLOOKUP($AM$16,Sheet1!V9:Y9,3,0),0) -> 0 | AN25: =+IFERROR(VLOOKUP($AN$16,Sheet1!V9:Y9,3,0),0) -> 0 | AO25: =+IFERROR(VLOOKUP($AO$16,Sheet1!V9:Y9,3,0),0) -> 0 | AP25: =+IFERROR(VLOOKUP($AP$16,Sheet1!V9:Y9,3,0),0) -> 0 | AQ25: =+IFERROR(VLOOKUP($AQ$16,Sheet1!Z9:AB9,3,0),0) -> 0 | AR25: =+IFERROR(VLOOKUP($AR$16,Sheet1!AD9:AG9,3,0),0) -> 0 | AS25: =+IFERROR(VLOOKUP($AS$16,Sheet1!AD9:AG9,3,0),0) -> 0 | AT25: =+IFERROR(VLOOKUP($AT$16,Sheet1!AD9:AG9,3,0),0) -> 0 | AU25: =+IFERROR(VLOOKUP($AU$16,Sheet1!AD9:AG9,3,0),0) -> 0 | AV25: =+IFERROR(VLOOKUP($AV$16,Sheet1!AD9:AG9,3,0),0) -> 0 | AW25: =+IFERROR(VLOOKUP($AW$16,Sheet1!AD9:AG9,3,0),0) -> 0 | AX25: =+IFERROR(VLOOKUP($AX$16,Sheet1!AD9:AG9,3,0),0) -> 0 | AY25: =+IFERROR(VLOOKUP($AY$16,Sheet1!AD9:AG9,3,0),0) -> 0 | AZ25: =+IFERROR(VLOOKUP($AZ$16,Sheet1!AD9:AG9,3,0),0) -> 0 | BA25: =+IFERROR(VLOOKUP($BA$16,Sheet1!AH9:AK9,3,0),0) -> 0 | BB25: =+IFERROR(VLOOKUP($BB$16,Sheet1!AH9:AK9,3,0),0) -> 0 | BC25: =+IFERROR(VLOOKUP($BC$16,Sheet1!AH9:AK9,3,0),0) -> 0 | BD25: =+IFERROR(VLOOKUP($BD$16,Sheet1!AH9:AK9,3,0),0) -> 0 | BE25: =+IFERROR(VLOOKUP($BE$16,Sheet1!AH9:AK9,3,0),0) -> 0 | BF25: =+IFERROR(VLOOKUP($BF$16,Sheet1!AH9:AK9,3,0),0) -> 0 | BG25: =+IFERROR(VLOOKUP($BG$16,Sheet1!AH9:AK9,3,0),0) -> 0 | BH25: =+IFERROR(VLOOKUP($BH$16,Sheet1!AH9:AK9,3,0),0) -> 0 | BI25: =+IFERROR(VLOOKUP($BI$16,Sheet1!AH9:AK9,3,0),0) -> 0 | BJ25: =+IFERROR(VLOOKUP($BJ$16,Sheet1!AH9:AK9,3,0),0) -> 0 | BK25: =+IFERROR(VLOOKUP($BK$16,Sheet1!AH9:AK9,3,0),0) -> 0 | BL25: =+IFERROR(VLOOKUP($BL$16,Sheet1!AL9:AO9,3,0),0) -> 0 | BM25: =+IFERROR(VLOOKUP($BM$16,Sheet1!AL9:AO9,3,0),0) -> 0 | BN25: =+IFERROR(VLOOKUP($BN$16,Sheet1!AL9:AO9,3,0),0) -> 0 | BO25: =+IFERROR(VLOOKUP($BO$16,Sheet1!AL9:AO9,3,0),0) -> 0 | BP25: =+IFERROR(VLOOKUP($BP$16,Sheet1!AL9:AO9,3,0),0) -> 0 | BQ25: =+IFERROR(VLOOKUP($BQ$16,Sheet1!AL9:AO9,3,0),0) -> 0 | BR25: =+IFERROR(VLOOKUP($BR$16,Sheet1!AL9:AO9,3,0),0) -> 0 | BS25: =+IFERROR(VLOOKUP($BS$16,Sheet1!AL9:AO9,3,0),0) -> 0 | BT25: =+IFERROR(VLOOKUP($BT$16,Sheet1!AL9:AO9,3,0),0) -> 0 | BU25: =+IFERROR(VLOOKUP($BU$16,Sheet1!AL9:AO9,3,0),0) -> 0 | BV25: =+IFERROR(VLOOKUP($BV$16,Sheet1!AL9:AO9,3,0),0) -> 0 | BW25: =+IFERROR(VLOOKUP($BW$16,Sheet1!AL9:AO9,3,0),0) -> 0 | BX25: =+IFERROR(VLOOKUP($BX$16,Sheet1!AP9:AS9,3,0),0) -> 0 | BY25: =+IFERROR(VLOOKUP($BY$16,Sheet1!AT9:AW9,3,0),0) -> 0 | BZ25: =+IFERROR(VLOOKUP($BZ$16,Sheet1!AX9:BA9,3,0),0) -> 0 | CA25: =+IFERROR(VLOOKUP($CA$16,Sheet1!BB9:BE9,3,0),0) -> 0 | CB25: =+IFERROR(VLOOKUP($CB$16,Sheet1!BF9:BI9,3,0),0) -> 0 | CC25: =+IFERROR(VLOOKUP($CC$16,Sheet1!BJ9:BM9,3,0),0) -> 0 | CD25: =+IFERROR(VLOOKUP($CD$16,Sheet1!BN9:BQ9,3,0),0) -> 0 | CE25: =+IFERROR(VLOOKUP($CE$16,Sheet1!BR9:BU9,3,0),0) -> 0 | CF25: =+IFERROR(VLOOKUP($CF$16,Sheet1!BV9:BY9,3,0),0) -> 0 | CG25: =Sheet1!E9 -> 0 | CH25: =Sheet1!CX9 -> 0 | CI25: =Sheet1!CY9 -> 0 | CJ25: =Sheet1!CZ9 -> 0 | CK25: =Sheet1!BZ9 -> 0 | CL25: =SUMPRODUCT($N$17:$CF$17,N25:CF25)+CK25 -> 0 | CM25: =Sheet1!CB9 -> 0 | CN25: =CL25*CM25 -> 0 | CO25: =Sheet1!CD9 -> 0 | CP25: =CL25*CO25 -> 0 | CQ25: =Sheet1!CF9 -> 0 | CR25: =CL25*CQ25 -> 0 | CS25: =CL25+CN25+CP25+CR25 -> 0 | CT25: =Sheet1!CI9 -> 0 | CU25: =CS25*CT25 -> 0 | CV25: =Sheet1!CK9 -> 0 | CW25: =CS25*CV25 -> 0 | CX25: =Sheet1!CM9 -> 0 | CY25: =CX25*CS25 -> 0
A26: =Sheet1!A10 -> 0 | B26: =Sheet1!B10 -> 0 | C26: =Sheet1!C10 -> 0 | D26: =Sheet1!D10 -> 0 | E26: =CS26+CU26+CW26+CY26 -> 0 | F26: =Sheet1!CP10 -> 0 | G26: =E26+F26 -> 0 | H26: =Sheet1!CR10 -> 0 | I26: =G26*H26 -> 0 | J26: =G26+I26 -> 0 | K26: =Sheet1!CU10 -> 0 | L26: =Sheet1!CV10 -> 0 | M26: =J26*K26 -> 0 | N26: =+IFERROR(VLOOKUP($N$16,Sheet1!J10:L10,3,0),0) -> 0 | O26: =+IFERROR(VLOOKUP($O$16,Sheet1!J10:L10,3,0),0) -> 0 | P26: =+IFERROR(VLOOKUP($P$16,Sheet1!J10:M10,3,0),0) -> 0 | Q26: =+IFERROR(VLOOKUP($Q$16,Sheet1!J10:M10,3,0),0) -> 0 | R26: =+IFERROR(VLOOKUP($R$16,Sheet1!J10:M10,3,0),0) -> 0 | S26: =+IFERROR(VLOOKUP($S$16,Sheet1!J10:M10,3,0),0) -> 0 | T26: =+IFERROR(VLOOKUP($T$16,Sheet1!J10:M10,3,0),0) -> 0 | U26: =+IFERROR(VLOOKUP($U$16,Sheet1!J10:M10,3,0),0) -> 0 | V26: =+IFERROR(VLOOKUP($V$16,Sheet1!N10:Q10,3,0),0) -> 0 | W26: =+IFERROR(VLOOKUP($W$16,Sheet1!N10:Q10,3,0),0) -> 0 | X26: =+IFERROR(VLOOKUP($X$16,Sheet1!F10:I10,3,0),0) -> 0 | Y26: =+IFERROR(VLOOKUP($Y$16,Sheet1!F10:I10,3,0),0) -> 0 | Z26: =+IFERROR(VLOOKUP($Z$16,Sheet1!F10:I10,3,0),0) -> 0 | AA26: =+IFERROR(VLOOKUP($AA$16,Sheet1!F10:I10,3,0),0) -> 0 | AB26: =+IFERROR(VLOOKUP($AB$16,Sheet1!F10:I10,3,0),0) -> 0 | AC26: =+IFERROR(VLOOKUP($AC$16,Sheet1!F10:I10,3,0),0) -> 0 | AD26: =+IFERROR(VLOOKUP($AD$16,Sheet1!F10:I10,3,0),0) -> 0 | AE26: =+IFERROR(VLOOKUP($AE$16,Sheet1!F10:I10,3,0),0) -> 0 | AF26: =+IFERROR(VLOOKUP($AF$16,Sheet1!R10:U10,3,0),0) -> 0 | AG26: =+IFERROR(VLOOKUP($AG$16,Sheet1!R10:U10,3,0),0) -> 0 | AH26: =+IFERROR(VLOOKUP($AH$16,Sheet1!V10:Y10,3,0),0) -> 0 | AI26: =+IFERROR(VLOOKUP($AI$16,Sheet1!V10:Y10,3,0),0) -> 0 | AJ26: =+IFERROR(VLOOKUP($AJ$16,Sheet1!V10:Y10,3,0),0) -> 0 | AK26: =+IFERROR(VLOOKUP($AK$16,Sheet1!V10:Y10,3,0),0) -> 0 | AL26: =+IFERROR(VLOOKUP($AL$16,Sheet1!V10:Y10,3,0),0) -> 0 | AM26: =+IFERROR(VLOOKUP($AM$16,Sheet1!V10:Y10,3,0),0) -> 0 | AN26: =+IFERROR(VLOOKUP($AN$16,Sheet1!V10:Y10,3,0),0) -> 0 | AO26: =+IFERROR(VLOOKUP($AO$16,Sheet1!V10:Y10,3,0),0) -> 0 | AP26: =+IFERROR(VLOOKUP($AP$16,Sheet1!V10:Y10,3,0),0) -> 0 | AQ26: =+IFERROR(VLOOKUP($AQ$16,Sheet1!Z10:AB10,3,0),0) -> 0 | AR26: =+IFERROR(VLOOKUP($AR$16,Sheet1!AD10:AG10,3,0),0) -> 0 | AS26: =+IFERROR(VLOOKUP($AS$16,Sheet1!AD10:AG10,3,0),0) -> 0 | AT26: =+IFERROR(VLOOKUP($AT$16,Sheet1!AD10:AG10,3,0),0) -> 0 | AU26: =+IFERROR(VLOOKUP($AU$16,Sheet1!AD10:AG10,3,0),0) -> 0 | AV26: =+IFERROR(VLOOKUP($AV$16,Sheet1!AD10:AG10,3,0),0) -> 0 | AW26: =+IFERROR(VLOOKUP($AW$16,Sheet1!AD10:AG10,3,0),0) -> 0 | AX26: =+IFERROR(VLOOKUP($AX$16,Sheet1!AD10:AG10,3,0),0) -> 0 | AY26: =+IFERROR(VLOOKUP($AY$16,Sheet1!AD10:AG10,3,0),0) -> 0 | AZ26: =+IFERROR(VLOOKUP($AZ$16,Sheet1!AD10:AG10,3,0),0) -> 0 | BA26: =+IFERROR(VLOOKUP($BA$16,Sheet1!AH10:AK10,3,0),0) -> 0 | BB26: =+IFERROR(VLOOKUP($BB$16,Sheet1!AH10:AK10,3,0),0) -> 0 | BC26: =+IFERROR(VLOOKUP($BC$16,Sheet1!AH10:AK10,3,0),0) -> 0 | BD26: =+IFERROR(VLOOKUP($BD$16,Sheet1!AH10:AK10,3,0),0) -> 0 | BE26: =+IFERROR(VLOOKUP($BE$16,Sheet1!AH10:AK10,3,0),0) -> 0 | BF26: =+IFERROR(VLOOKUP($BF$16,Sheet1!AH10:AK10,3,0),0) -> 0 | BG26: =+IFERROR(VLOOKUP($BG$16,Sheet1!AH10:AK10,3,0),0) -> 0 | BH26: =+IFERROR(VLOOKUP($BH$16,Sheet1!AH10:AK10,3,0),0) -> 0 | BI26: =+IFERROR(VLOOKUP($BI$16,Sheet1!AH10:AK10,3,0),0) -> 0 | BJ26: =+IFERROR(VLOOKUP($BJ$16,Sheet1!AH10:AK10,3,0),0) -> 0 | BK26: =+IFERROR(VLOOKUP($BK$16,Sheet1!AH10:AK10,3,0),0) -> 0 | BL26: =+IFERROR(VLOOKUP($BL$16,Sheet1!AL10:AO10,3,0),0) -> 0 | BM26: =+IFERROR(VLOOKUP($BM$16,Sheet1!AL10:AO10,3,0),0) -> 0 | BN26: =+IFERROR(VLOOKUP($BN$16,Sheet1!AL10:AO10,3,0),0) -> 0 | BO26: =+IFERROR(VLOOKUP($BO$16,Sheet1!AL10:AO10,3,0),0) -> 0 | BP26: =+IFERROR(VLOOKUP($BP$16,Sheet1!AL10:AO10,3,0),0) -> 0 | BQ26: =+IFERROR(VLOOKUP($BQ$16,Sheet1!AL10:AO10,3,0),0) -> 0 | BR26: =+IFERROR(VLOOKUP($BR$16,Sheet1!AL10:AO10,3,0),0) -> 0 | BS26: =+IFERROR(VLOOKUP($BS$16,Sheet1!AL10:AO10,3,0),0) -> 0 | BT26: =+IFERROR(VLOOKUP($BT$16,Sheet1!AL10:AO10,3,0),0) -> 0 | BU26: =+IFERROR(VLOOKUP($BU$16,Sheet1!AL10:AO10,3,0),0) -> 0 | BV26: =+IFERROR(VLOOKUP($BV$16,Sheet1!AL10:AO10,3,0),0) -> 0 | BW26: =+IFERROR(VLOOKUP($BW$16,Sheet1!AL10:AO10,3,0),0) -> 0 | BX26: =+IFERROR(VLOOKUP($BX$16,Sheet1!AP10:AS10,3,0),0) -> 0 | BY26: =+IFERROR(VLOOKUP($BY$16,Sheet1!AT10:AW10,3,0),0) -> 0 | BZ26: =+IFERROR(VLOOKUP($BZ$16,Sheet1!AX10:BA10,3,0),0) -> 0 | CA26: =+IFERROR(VLOOKUP($CA$16,Sheet1!BB10:BE10,3,0),0) -> 0 | CB26: =+IFERROR(VLOOKUP($CB$16,Sheet1!BF10:BI10,3,0),0) -> 0 | CC26: =+IFERROR(VLOOKUP($CC$16,Sheet1!BJ10:BM10,3,0),0) -> 0 | CD26: =+IFERROR(VLOOKUP($CD$16,Sheet1!BN10:BQ10,3,0),0) -> 0 | CE26: =+IFERROR(VLOOKUP($CE$16,Sheet1!BR10:BU10,3,0),0) -> 0 | CF26: =+IFERROR(VLOOKUP($CF$16,Sheet1!BV10:BY10,3,0),0) -> 0 | CG26: =Sheet1!E10 -> 0 | CH26: =Sheet1!CX10 -> 0 | CI26: =Sheet1!CY10 -> 0 | CJ26: =Sheet1!CZ10 -> 0 | CK26: =Sheet1!BZ10 -> 0 | CL26: =SUMPRODUCT($N$17:$CF$17,N26:CF26)+CK26 -> 0 | CM26: =Sheet1!CB10 -> 0 | CN26: =CL26*CM26 -> 0 | CO26: =Sheet1!CD10 -> 0 | CP26: =CL26*CO26 -> 0 | CQ26: =Sheet1!CF10 -> 0 | CR26: =CL26*CQ26 -> 0 | CS26: =CL26+CN26+CP26+CR26 -> 0 | CT26: =Sheet1!CI10 -> 0 | CU26: =CS26*CT26 -> 0 | CV26: =Sheet1!CK10 -> 0 | CW26: =CS26*CV26 -> 0 | CX26: =Sheet1!CM10 -> 0 | CY26: =CX26*CS26 -> 0
A27: =Sheet1!A11 -> 0 | B27: =Sheet1!B11 -> 0 | C27: =Sheet1!C11 -> 0 | D27: =Sheet1!D11 -> 0 | E27: =CS27+CU27+CW27+CY27 -> 0 | F27: =Sheet1!CP11 -> 0 | G27: =E27+F27 -> 0 | H27: =Sheet1!CR11 -> 0 | I27: =G27*H27 -> 0 | J27: =G27+I27 -> 0 | K27: =Sheet1!CU11 -> 0 | L27: =Sheet1!CV11 -> 0 | M27: =J27*K27 -> 0 | N27: =+IFERROR(VLOOKUP($N$16,Sheet1!J11:L11,3,0),0) -> 0 | O27: =+IFERROR(VLOOKUP($O$16,Sheet1!J11:L11,3,0),0) -> 0 | P27: =+IFERROR(VLOOKUP($P$16,Sheet1!J11:M11,3,0),0) -> 0 | Q27: =+IFERROR(VLOOKUP($Q$16,Sheet1!J11:M11,3,0),0) -> 0 | R27: =+IFERROR(VLOOKUP($R$16,Sheet1!J11:M11,3,0),0) -> 0 | S27: =+IFERROR(VLOOKUP($S$16,Sheet1!J11:M11,3,0),0) -> 0 | T27: =+IFERROR(VLOOKUP($T$16,Sheet1!J11:M11,3,0),0) -> 0 | U27: =+IFERROR(VLOOKUP($U$16,Sheet1!J11:M11,3,0),0) -> 0 | V27: =+IFERROR(VLOOKUP($V$16,Sheet1!N11:Q11,3,0),0) -> 0 | W27: =+IFERROR(VLOOKUP($W$16,Sheet1!N11:Q11,3,0),0) -> 0 | X27: =+IFERROR(VLOOKUP($X$16,Sheet1!F11:I11,3,0),0) -> 0 | Y27: =+IFERROR(VLOOKUP($Y$16,Sheet1!F11:I11,3,0),0) -> 0 | Z27: =+IFERROR(VLOOKUP($Z$16,Sheet1!F11:I11,3,0),0) -> 0 | AA27: =+IFERROR(VLOOKUP($AA$16,Sheet1!F11:I11,3,0),0) -> 0 | AB27: =+IFERROR(VLOOKUP($AB$16,Sheet1!F11:I11,3,0),0) -> 0 | AC27: =+IFERROR(VLOOKUP($AC$16,Sheet1!F11:I11,3,0),0) -> 0 | AD27: =+IFERROR(VLOOKUP($AD$16,Sheet1!F11:I11,3,0),0) -> 0 | AE27: =+IFERROR(VLOOKUP($AE$16,Sheet1!F11:I11,3,0),0) -> 0 | AF27: =+IFERROR(VLOOKUP($AF$16,Sheet1!R11:U11,3,0),0) -> 0 | AG27: =+IFERROR(VLOOKUP($AG$16,Sheet1!R11:U11,3,0),0) -> 0 | AH27: =+IFERROR(VLOOKUP($AH$16,Sheet1!V11:Y11,3,0),0) -> 0 | AI27: =+IFERROR(VLOOKUP($AI$16,Sheet1!V11:Y11,3,0),0) -> 0 | AJ27: =+IFERROR(VLOOKUP($AJ$16,Sheet1!V11:Y11,3,0),0) -> 0 | AK27: =+IFERROR(VLOOKUP($AK$16,Sheet1!V11:Y11,3,0),0) -> 0 | AL27: =+IFERROR(VLOOKUP($AL$16,Sheet1!V11:Y11,3,0),0) -> 0 | AM27: =+IFERROR(VLOOKUP($AM$16,Sheet1!V11:Y11,3,0),0) -> 0 | AN27: =+IFERROR(VLOOKUP($AN$16,Sheet1!V11:Y11,3,0),0) -> 0 | AO27: =+IFERROR(VLOOKUP($AO$16,Sheet1!V11:Y11,3,0),0) -> 0 | AP27: =+IFERROR(VLOOKUP($AP$16,Sheet1!V11:Y11,3,0),0) -> 0 | AQ27: =+IFERROR(VLOOKUP($AQ$16,Sheet1!Z11:AB11,3,0),0) -> 0 | AR27: =+IFERROR(VLOOKUP($AR$16,Sheet1!AD11:AG11,3,0),0) -> 0 | AS27: =+IFERROR(VLOOKUP($AS$16,Sheet1!AD11:AG11,3,0),0) -> 0 | AT27: =+IFERROR(VLOOKUP($AT$16,Sheet1!AD11:AG11,3,0),0) -> 0 | AU27: =+IFERROR(VLOOKUP($AU$16,Sheet1!AD11:AG11,3,0),0) -> 0 | AV27: =+IFERROR(VLOOKUP($AV$16,Sheet1!AD11:AG11,3,0),0) -> 0 | AW27: =+IFERROR(VLOOKUP($AW$16,Sheet1!AD11:AG11,3,0),0) -> 0 | AX27: =+IFERROR(VLOOKUP($AX$16,Sheet1!AD11:AG11,3,0),0) -> 0 | AY27: =+IFERROR(VLOOKUP($AY$16,Sheet1!AD11:AG11,3,0),0) -> 0 | AZ27: =+IFERROR(VLOOKUP($AZ$16,Sheet1!AD11:AG11,3,0),0) -> 0 | BA27: =+IFERROR(VLOOKUP($BA$16,Sheet1!AH11:AK11,3,0),0) -> 0 | BB27: =+IFERROR(VLOOKUP($BB$16,Sheet1!AH11:AK11,3,0),0) -> 0 | BC27: =+IFERROR(VLOOKUP($BC$16,Sheet1!AH11:AK11,3,0),0) -> 0 | BD27: =+IFERROR(VLOOKUP($BD$16,Sheet1!AH11:AK11,3,0),0) -> 0 | BE27: =+IFERROR(VLOOKUP($BE$16,Sheet1!AH11:AK11,3,0),0) -> 0 | BF27: =+IFERROR(VLOOKUP($BF$16,Sheet1!AH11:AK11,3,0),0) -> 0 | BG27: =+IFERROR(VLOOKUP($BG$16,Sheet1!AH11:AK11,3,0),0) -> 0 | BH27: =+IFERROR(VLOOKUP($BH$16,Sheet1!AH11:AK11,3,0),0) -> 0 | BI27: =+IFERROR(VLOOKUP($BI$16,Sheet1!AH11:AK11,3,0),0) -> 0 | BJ27: =+IFERROR(VLOOKUP($BJ$16,Sheet1!AH11:AK11,3,0),0) -> 0 | BK27: =+IFERROR(VLOOKUP($BK$16,Sheet1!AH11:AK11,3,0),0) -> 0 | BL27: =+IFERROR(VLOOKUP($BL$16,Sheet1!AL11:AO11,3,0),0) -> 0 | BM27: =+IFERROR(VLOOKUP($BM$16,Sheet1!AL11:AO11,3,0),0) -> 0 | BN27: =+IFERROR(VLOOKUP($BN$16,Sheet1!AL11:AO11,3,0),0) -> 0 | BO27: =+IFERROR(VLOOKUP($BO$16,Sheet1!AL11:AO11,3,0),0) -> 0 | BP27: =+IFERROR(VLOOKUP($BP$16,Sheet1!AL11:AO11,3,0),0) -> 0 | BQ27: =+IFERROR(VLOOKUP($BQ$16,Sheet1!AL11:AO11,3,0),0) -> 0 | BR27: =+IFERROR(VLOOKUP($BR$16,Sheet1!AL11:AO11,3,0),0) -> 0 | BS27: =+IFERROR(VLOOKUP($BS$16,Sheet1!AL11:AO11,3,0),0) -> 0 | BT27: =+IFERROR(VLOOKUP($BT$16,Sheet1!AL11:AO11,3,0),0) -> 0 | BU27: =+IFERROR(VLOOKUP($BU$16,Sheet1!AL11:AO11,3,0),0) -> 0 | BV27: =+IFERROR(VLOOKUP($BV$16,Sheet1!AL11:AO11,3,0),0) -> 0 | BW27: =+IFERROR(VLOOKUP($BW$16,Sheet1!AL11:AO11,3,0),0) -> 0 | BX27: =+IFERROR(VLOOKUP($BX$16,Sheet1!AP11:AS11,3,0),0) -> 0 | BY27: =+IFERROR(VLOOKUP($BY$16,Sheet1!AT11:AW11,3,0),0) -> 0 | BZ27: =+IFERROR(VLOOKUP($BZ$16,Sheet1!AX11:BA11,3,0),0) -> 0 | CA27: =+IFERROR(VLOOKUP($CA$16,Sheet1!BB11:BE11,3,0),0) -> 0 | CB27: =+IFERROR(VLOOKUP($CB$16,Sheet1!BF11:BI11,3,0),0) -> 0 | CC27: =+IFERROR(VLOOKUP($CC$16,Sheet1!BJ11:BM11,3,0),0) -> 0 | CD27: =+IFERROR(VLOOKUP($CD$16,Sheet1!BN11:BQ11,3,0),0) -> 0 | CE27: =+IFERROR(VLOOKUP($CE$16,Sheet1!BR11:BU11,3,0),0) -> 0 | CF27: =+IFERROR(VLOOKUP($CF$16,Sheet1!BV11:BY11,3,0),0) -> 0 | CG27: =Sheet1!E11 -> 0 | CH27: =Sheet1!CX11 -> 0 | CI27: =Sheet1!CY11 -> 0 | CJ27: =Sheet1!CZ11 -> 0 | CK27: =Sheet1!BZ11 -> 0 | CL27: =SUMPRODUCT($N$17:$CF$17,N27:CF27)+CK27 -> 0 | CM27: =Sheet1!CB11 -> 0 | CN27: =CL27*CM27 -> 0 | CO27: =Sheet1!CD11 -> 0 | CP27: =CL27*CO27 -> 0 | CQ27: =Sheet1!CF11 -> 0 | CR27: =CL27*CQ27 -> 0 | CS27: =CL27+CN27+CP27+CR27 -> 0 | CT27: =Sheet1!CI11 -> 0 | CU27: =CS27*CT27 -> 0 | CV27: =Sheet1!CK11 -> 0 | CW27: =CS27*CV27 -> 0 | CX27: =Sheet1!CM11 -> 0 | CY27: =CX27*CS27 -> 0
A28: =Sheet1!A12 -> 0 | B28: =Sheet1!B12 -> 0 | C28: =Sheet1!C12 -> 0 | D28: =Sheet1!D12 -> 0 | E28: =CS28+CU28+CW28+CY28 -> 0 | F28: =Sheet1!CP12 -> 0 | G28: =E28+F28 -> 0 | H28: =Sheet1!CR12 -> 0 | I28: =G28*H28 -> 0 | J28: =G28+I28 -> 0 | K28: =Sheet1!CU12 -> 0 | L28: =Sheet1!CV12 -> 0 | M28: =J28*K28 -> 0 | N28: =+IFERROR(VLOOKUP($N$16,Sheet1!J12:L12,3,0),0) -> 0 | O28: =+IFERROR(VLOOKUP($O$16,Sheet1!J12:L12,3,0),0) -> 0 | P28: =+IFERROR(VLOOKUP($P$16,Sheet1!J12:M12,3,0),0) -> 0 | Q28: =+IFERROR(VLOOKUP($Q$16,Sheet1!J12:M12,3,0),0) -> 0 | R28: =+IFERROR(VLOOKUP($R$16,Sheet1!J12:M12,3,0),0) -> 0 | S28: =+IFERROR(VLOOKUP($S$16,Sheet1!J12:M12,3,0),0) -> 0 | T28: =+IFERROR(VLOOKUP($T$16,Sheet1!J12:M12,3,0),0) -> 0 | U28: =+IFERROR(VLOOKUP($U$16,Sheet1!J12:M12,3,0),0) -> 0 | V28: =+IFERROR(VLOOKUP($V$16,Sheet1!N12:Q12,3,0),0) -> 0 | W28: =+IFERROR(VLOOKUP($W$16,Sheet1!N12:Q12,3,0),0) -> 0 | X28: =+IFERROR(VLOOKUP($X$16,Sheet1!F12:I12,3,0),0) -> 0 | Y28: =+IFERROR(VLOOKUP($Y$16,Sheet1!F12:I12,3,0),0) -> 0 | Z28: =+IFERROR(VLOOKUP($Z$16,Sheet1!F12:I12,3,0),0) -> 0 | AA28: =+IFERROR(VLOOKUP($AA$16,Sheet1!F12:I12,3,0),0) -> 0 | AB28: =+IFERROR(VLOOKUP($AB$16,Sheet1!F12:I12,3,0),0) -> 0 | AC28: =+IFERROR(VLOOKUP($AC$16,Sheet1!F12:I12,3,0),0) -> 0 | AD28: =+IFERROR(VLOOKUP($AD$16,Sheet1!F12:I12,3,0),0) -> 0 | AE28: =+IFERROR(VLOOKUP($AE$16,Sheet1!F12:I12,3,0),0) -> 0 | AF28: =+IFERROR(VLOOKUP($AF$16,Sheet1!R12:U12,3,0),0) -> 0 | AG28: =+IFERROR(VLOOKUP($AG$16,Sheet1!R12:U12,3,0),0) -> 0 | AH28: =+IFERROR(VLOOKUP($AH$16,Sheet1!V12:Y12,3,0),0) -> 0 | AI28: =+IFERROR(VLOOKUP($AI$16,Sheet1!V12:Y12,3,0),0) -> 0 | AJ28: =+IFERROR(VLOOKUP($AJ$16,Sheet1!V12:Y12,3,0),0) -> 0 | AK28: =+IFERROR(VLOOKUP($AK$16,Sheet1!V12:Y12,3,0),0) -> 0 | AL28: =+IFERROR(VLOOKUP($AL$16,Sheet1!V12:Y12,3,0),0) -> 0 | AM28: =+IFERROR(VLOOKUP($AM$16,Sheet1!V12:Y12,3,0),0) -> 0 | AN28: =+IFERROR(VLOOKUP($AN$16,Sheet1!V12:Y12,3,0),0) -> 0 | AO28: =+IFERROR(VLOOKUP($AO$16,Sheet1!V12:Y12,3,0),0) -> 0 | AP28: =+IFERROR(VLOOKUP($AP$16,Sheet1!V12:Y12,3,0),0) -> 0 | AQ28: =+IFERROR(VLOOKUP($AQ$16,Sheet1!Z12:AB12,3,0),0) -> 0 | AR28: =+IFERROR(VLOOKUP($AR$16,Sheet1!AD12:AG12,3,0),0) -> 0 | AS28: =+IFERROR(VLOOKUP($AS$16,Sheet1!AD12:AG12,3,0),0) -> 0 | AT28: =+IFERROR(VLOOKUP($AT$16,Sheet1!AD12:AG12,3,0),0) -> 0 | AU28: =+IFERROR(VLOOKUP($AU$16,Sheet1!AD12:AG12,3,0),0) -> 0 | AV28: =+IFERROR(VLOOKUP($AV$16,Sheet1!AD12:AG12,3,0),0) -> 0 | AW28: =+IFERROR(VLOOKUP($AW$16,Sheet1!AD12:AG12,3,0),0) -> 0 | AX28: =+IFERROR(VLOOKUP($AX$16,Sheet1!AD12:AG12,3,0),0) -> 0 | AY28: =+IFERROR(VLOOKUP($AY$16,Sheet1!AD12:AG12,3,0),0) -> 0 | AZ28: =+IFERROR(VLOOKUP($AZ$16,Sheet1!AD12:AG12,3,0),0) -> 0 | BA28: =+IFERROR(VLOOKUP($BA$16,Sheet1!AH12:AK12,3,0),0) -> 0 | BB28: =+IFERROR(VLOOKUP($BB$16,Sheet1!AH12:AK12,3,0),0) -> 0 | BC28: =+IFERROR(VLOOKUP($BC$16,Sheet1!AH12:AK12,3,0),0) -> 0 | BD28: =+IFERROR(VLOOKUP($BD$16,Sheet1!AH12:AK12,3,0),0) -> 0 | BE28: =+IFERROR(VLOOKUP($BE$16,Sheet1!AH12:AK12,3,0),0) -> 0 | BF28: =+IFERROR(VLOOKUP($BF$16,Sheet1!AH12:AK12,3,0),0) -> 0 | BG28: =+IFERROR(VLOOKUP($BG$16,Sheet1!AH12:AK12,3,0),0) -> 0 | BH28: =+IFERROR(VLOOKUP($BH$16,Sheet1!AH12:AK12,3,0),0) -> 0 | BI28: =+IFERROR(VLOOKUP($BI$16,Sheet1!AH12:AK12,3,0),0) -> 0 | BJ28: =+IFERROR(VLOOKUP($BJ$16,Sheet1!AH12:AK12,3,0),0) -> 0 | BK28: =+IFERROR(VLOOKUP($BK$16,Sheet1!AH12:AK12,3,0),0) -> 0 | BL28: =+IFERROR(VLOOKUP($BL$16,Sheet1!AL12:AO12,3,0),0) -> 0 | BM28: =+IFERROR(VLOOKUP($BM$16,Sheet1!AL12:AO12,3,0),0) -> 0 | BN28: =+IFERROR(VLOOKUP($BN$16,Sheet1!AL12:AO12,3,0),0) -> 0 | BO28: =+IFERROR(VLOOKUP($BO$16,Sheet1!AL12:AO12,3,0),0) -> 0 | BP28: =+IFERROR(VLOOKUP($BP$16,Sheet1!AL12:AO12,3,0),0) -> 0 | BQ28: =+IFERROR(VLOOKUP($BQ$16,Sheet1!AL12:AO12,3,0),0) -> 0 | BR28: =+IFERROR(VLOOKUP($BR$16,Sheet1!AL12:AO12,3,0),0) -> 0 | BS28: =+IFERROR(VLOOKUP($BS$16,Sheet1!AL12:AO12,3,0),0) -> 0 | BT28: =+IFERROR(VLOOKUP($BT$16,Sheet1!AL12:AO12,3,0),0) -> 0 | BU28: =+IFERROR(VLOOKUP($BU$16,Sheet1!AL12:AO12,3,0),0) -> 0 | BV28: =+IFERROR(VLOOKUP($BV$16,Sheet1!AL12:AO12,3,0),0) -> 0 | BW28: =+IFERROR(VLOOKUP($BW$16,Sheet1!AL12:AO12,3,0),0) -> 0 | BX28: =+IFERROR(VLOOKUP($BX$16,Sheet1!AP12:AS12,3,0),0) -> 0 | BY28: =+IFERROR(VLOOKUP($BY$16,Sheet1!AT12:AW12,3,0),0) -> 0 | BZ28: =+IFERROR(VLOOKUP($BZ$16,Sheet1!AX12:BA12,3,0),0) -> 0 | CA28: =+IFERROR(VLOOKUP($CA$16,Sheet1!BB12:BE12,3,0),0) -> 0 | CB28: =+IFERROR(VLOOKUP($CB$16,Sheet1!BF12:BI12,3,0),0) -> 0 | CC28: =+IFERROR(VLOOKUP($CC$16,Sheet1!BJ12:BM12,3,0),0) -> 0 | CD28: =+IFERROR(VLOOKUP($CD$16,Sheet1!BN12:BQ12,3,0),0) -> 0 | CE28: =+IFERROR(VLOOKUP($CE$16,Sheet1!BR12:BU12,3,0),0) -> 0 | CF28: =+IFERROR(VLOOKUP($CF$16,Sheet1!BV12:BY12,3,0),0) -> 0 | CG28: =Sheet1!E12 -> 0 | CH28: =Sheet1!CX12 -> 0 | CI28: =Sheet1!CY12 -> 0 | CJ28: =Sheet1!CZ12 -> 0 | CK28: =Sheet1!BZ12 -> 0 | CL28: =SUMPRODUCT($N$17:$CF$17,N28:CF28)+CK28 -> 0 | CM28: =Sheet1!CB12 -> 0 | CN28: =CL28*CM28 -> 0 | CO28: =Sheet1!CD12 -> 0 | CP28: =CL28*CO28 -> 0 | CQ28: =Sheet1!CF12 -> 0 | CR28: =CL28*CQ28 -> 0 | CS28: =CL28+CN28+CP28+CR28 -> 0 | CT28: =Sheet1!CI12 -> 0 | CU28: =CS28*CT28 -> 0 | CV28: =Sheet1!CK12 -> 0 | CW28: =CS28*CV28 -> 0 | CX28: =Sheet1!CM12 -> 0 | CY28: =CX28*CS28 -> 0
A29: =Sheet1!A13 -> 0 | B29: =Sheet1!B13 -> 0 | C29: =Sheet1!C13 -> 0 | D29: =Sheet1!D13 -> 0 | E29: =CS29+CU29+CW29+CY29 -> 0 | F29: =Sheet1!CP13 -> 0 | G29: =E29+F29 -> 0 | H29: =Sheet1!CR13 -> 0 | I29: =G29*H29 -> 0 | J29: =G29+I29 -> 0 | K29: =Sheet1!CU13 -> 0 | L29: =Sheet1!CV13 -> 0 | M29: =J29*K29 -> 0 | N29: =+IFERROR(VLOOKUP($N$16,Sheet1!J13:L13,3,0),0) -> 0 | O29: =+IFERROR(VLOOKUP($O$16,Sheet1!J13:L13,3,0),0) -> 0 | P29: =+IFERROR(VLOOKUP($P$16,Sheet1!J13:M13,3,0),0) -> 0 | Q29: =+IFERROR(VLOOKUP($Q$16,Sheet1!J13:M13,3,0),0) -> 0 | R29: =+IFERROR(VLOOKUP($R$16,Sheet1!J13:M13,3,0),0) -> 0 | S29: =+IFERROR(VLOOKUP($S$16,Sheet1!J13:M13,3,0),0) -> 0 | T29: =+IFERROR(VLOOKUP($T$16,Sheet1!J13:M13,3,0),0) -> 0 | U29: =+IFERROR(VLOOKUP($U$16,Sheet1!J13:M13,3,0),0) -> 0 | V29: =+IFERROR(VLOOKUP($V$16,Sheet1!N13:Q13,3,0),0) -> 0 | W29: =+IFERROR(VLOOKUP($W$16,Sheet1!N13:Q13,3,0),0) -> 0 | X29: =+IFERROR(VLOOKUP($X$16,Sheet1!F13:I13,3,0),0) -> 0 | Y29: =+IFERROR(VLOOKUP($Y$16,Sheet1!F13:I13,3,0),0) -> 0 | Z29: =+IFERROR(VLOOKUP($Z$16,Sheet1!F13:I13,3,0),0) -> 0 | AA29: =+IFERROR(VLOOKUP($AA$16,Sheet1!F13:I13,3,0),0) -> 0 | AB29: =+IFERROR(VLOOKUP($AB$16,Sheet1!F13:I13,3,0),0) -> 0 | AC29: =+IFERROR(VLOOKUP($AC$16,Sheet1!F13:I13,3,0),0) -> 0 | AD29: =+IFERROR(VLOOKUP($AD$16,Sheet1!F13:I13,3,0),0) -> 0 | AE29: =+IFERROR(VLOOKUP($AE$16,Sheet1!F13:I13,3,0),0) -> 0 | AF29: =+IFERROR(VLOOKUP($AF$16,Sheet1!R13:U13,3,0),0) -> 0 | AG29: =+IFERROR(VLOOKUP($AG$16,Sheet1!R13:U13,3,0),0) -> 0 | AH29: =+IFERROR(VLOOKUP($AH$16,Sheet1!V13:Y13,3,0),0) -> 0 | AI29: =+IFERROR(VLOOKUP($AI$16,Sheet1!V13:Y13,3,0),0) -> 0 | AJ29: =+IFERROR(VLOOKUP($AJ$16,Sheet1!V13:Y13,3,0),0) -> 0 | AK29: =+IFERROR(VLOOKUP($AK$16,Sheet1!V13:Y13,3,0),0) -> 0 | AL29: =+IFERROR(VLOOKUP($AL$16,Sheet1!V13:Y13,3,0),0) -> 0 | AM29: =+IFERROR(VLOOKUP($AM$16,Sheet1!V13:Y13,3,0),0) -> 0 | AN29: =+IFERROR(VLOOKUP($AN$16,Sheet1!V13:Y13,3,0),0) -> 0 | AO29: =+IFERROR(VLOOKUP($AO$16,Sheet1!V13:Y13,3,0),0) -> 0 | AP29: =+IFERROR(VLOOKUP($AP$16,Sheet1!V13:Y13,3,0),0) -> 0 | AQ29: =+IFERROR(VLOOKUP($AQ$16,Sheet1!Z13:AB13,3,0),0) -> 0 | AR29: =+IFERROR(VLOOKUP($AR$16,Sheet1!AD13:AG13,3,0),0) -> 0 | AS29: =+IFERROR(VLOOKUP($AS$16,Sheet1!AD13:AG13,3,0),0) -> 0 | AT29: =+IFERROR(VLOOKUP($AT$16,Sheet1!AD13:AG13,3,0),0) -> 0 | AU29: =+IFERROR(VLOOKUP($AU$16,Sheet1!AD13:AG13,3,0),0) -> 0 | AV29: =+IFERROR(VLOOKUP($AV$16,Sheet1!AD13:AG13,3,0),0) -> 0 | AW29: =+IFERROR(VLOOKUP($AW$16,Sheet1!AD13:AG13,3,0),0) -> 0 | AX29: =+IFERROR(VLOOKUP($AX$16,Sheet1!AD13:AG13,3,0),0) -> 0 | AY29: =+IFERROR(VLOOKUP($AY$16,Sheet1!AD13:AG13,3,0),0) -> 0 | AZ29: =+IFERROR(VLOOKUP($AZ$16,Sheet1!AD13:AG13,3,0),0) -> 0 | BA29: =+IFERROR(VLOOKUP($BA$16,Sheet1!AH13:AK13,3,0),0) -> 0 | BB29: =+IFERROR(VLOOKUP($BB$16,Sheet1!AH13:AK13,3,0),0) -> 0 | BC29: =+IFERROR(VLOOKUP($BC$16,Sheet1!AH13:AK13,3,0),0) -> 0 | BD29: =+IFERROR(VLOOKUP($BD$16,Sheet1!AH13:AK13,3,0),0) -> 0 | BE29: =+IFERROR(VLOOKUP($BE$16,Sheet1!AH13:AK13,3,0),0) -> 0 | BF29: =+IFERROR(VLOOKUP($BF$16,Sheet1!AH13:AK13,3,0),0) -> 0 | BG29: =+IFERROR(VLOOKUP($BG$16,Sheet1!AH13:AK13,3,0),0) -> 0 | BH29: =+IFERROR(VLOOKUP($BH$16,Sheet1!AH13:AK13,3,0),0) -> 0 | BI29: =+IFERROR(VLOOKUP($BI$16,Sheet1!AH13:AK13,3,0),0) -> 0 | BJ29: =+IFERROR(VLOOKUP($BJ$16,Sheet1!AH13:AK13,3,0),0) -> 0 | BK29: =+IFERROR(VLOOKUP($BK$16,Sheet1!AH13:AK13,3,0),0) -> 0 | BL29: =+IFERROR(VLOOKUP($BL$16,Sheet1!AL13:AO13,3,0),0) -> 0 | BM29: =+IFERROR(VLOOKUP($BM$16,Sheet1!AL13:AO13,3,0),0) -> 0 | BN29: =+IFERROR(VLOOKUP($BN$16,Sheet1!AL13:AO13,3,0),0) -> 0 | BO29: =+IFERROR(VLOOKUP($BO$16,Sheet1!AL13:AO13,3,0),0) -> 0 | BP29: =+IFERROR(VLOOKUP($BP$16,Sheet1!AL13:AO13,3,0),0) -> 0 | BQ29: =+IFERROR(VLOOKUP($BQ$16,Sheet1!AL13:AO13,3,0),0) -> 0 | BR29: =+IFERROR(VLOOKUP($BR$16,Sheet1!AL13:AO13,3,0),0) -> 0 | BS29: =+IFERROR(VLOOKUP($BS$16,Sheet1!AL13:AO13,3,0),0) -> 0 | BT29: =+IFERROR(VLOOKUP($BT$16,Sheet1!AL13:AO13,3,0),0) -> 0 | BU29: =+IFERROR(VLOOKUP($BU$16,Sheet1!AL13:AO13,3,0),0) -> 0 | BV29: =+IFERROR(VLOOKUP($BV$16,Sheet1!AL13:AO13,3,0),0) -> 0 | BW29: =+IFERROR(VLOOKUP($BW$16,Sheet1!AL13:AO13,3,0),0) -> 0 | BX29: =+IFERROR(VLOOKUP($BX$16,Sheet1!AP13:AS13,3,0),0) -> 0 | BY29: =+IFERROR(VLOOKUP($BY$16,Sheet1!AT13:AW13,3,0),0) -> 0 | BZ29: =+IFERROR(VLOOKUP($BZ$16,Sheet1!AX13:BA13,3,0),0) -> 0 | CA29: =+IFERROR(VLOOKUP($CA$16,Sheet1!BB13:BE13,3,0),0) -> 0 | CB29: =+IFERROR(VLOOKUP($CB$16,Sheet1!BF13:BI13,3,0),0) -> 0 | CC29: =+IFERROR(VLOOKUP($CC$16,Sheet1!BJ13:BM13,3,0),0) -> 0 | CD29: =+IFERROR(VLOOKUP($CD$16,Sheet1!BN13:BQ13,3,0),0) -> 0 | CE29: =+IFERROR(VLOOKUP($CE$16,Sheet1!BR13:BU13,3,0),0) -> 0 | CF29: =+IFERROR(VLOOKUP($CF$16,Sheet1!BV13:BY13,3,0),0) -> 0 | CG29: =Sheet1!E13 -> 0 | CH29: =Sheet1!CX13 -> 0 | CI29: =Sheet1!CY13 -> 0 | CJ29: =Sheet1!CZ13 -> 0 | CK29: =Sheet1!BZ13 -> 0 | CL29: =SUMPRODUCT($N$17:$CF$17,N29:CF29)+CK29 -> 0 | CM29: =Sheet1!CB13 -> 0 | CN29: =CL29*CM29 -> 0 | CO29: =Sheet1!CD13 -> 0 | CP29: =CL29*CO29 -> 0 | CQ29: =Sheet1!CF13 -> 0 | CR29: =CL29*CQ29 -> 0 | CS29: =CL29+CN29+CP29+CR29 -> 0 | CT29: =Sheet1!CI13 -> 0 | CU29: =CS29*CT29 -> 0 | CV29: =Sheet1!CK13 -> 0 | CW29: =CS29*CV29 -> 0 | CX29: =Sheet1!CM13 -> 0 | CY29: =CX29*CS29 -> 0
M30: =SUM(M18:M29) -> 34655256
E33: Order Quantity | F33: Stnd Length | G33: Truck type | H33: Fare of one truck | I33: No of Drum in one truck | J33: Total length in one Truck | K33: No of Truck | L33: Total Freight | M33: Freight per KM | AL33: CABLE WEIGHT KG/KM | AQ33: DRUM WEIGHT | AS33: CABLE+DRUM WEIGHT | BJ33: TRUCK WEIGHT
D34: =D18 -> 2 CORE X 2.5 SQ. MM. CU/ARD - WIRE (PVC) | E34: =K18 -> 15 | F34: =CJ18/1000 -> 0.5 | G34: 16 MT | H34: 44500 | I34: 48 | J34: =F34*I34 -> 24 | K34: =ROUNDUP((E34/J34),0) -> 1 | L34: =H34*K34 -> 44500 | M34: =L34/E34 -> 2966.6667 | P34: =CH18 -> MD0100003 | AL34: =SUM(P18:BO18) -> 456 | AQ34: =60+15 -> 75 | AS34: =((AL34*F34)+AQ34) -> 303 | BJ34: =AS34*I34 -> 14544
D35: =D19 -> 4 CORE X 2.5 SQ. MM. CU/ARD - WIRE (PVC) | E35: =K19 -> 25 | F35: =CJ19/1000 -> 0.5 | G35: 16 MT | H35: 44500 | I35: 36 | J35: =F35*I35 -> 18 | K35: =ROUNDUP((E35/J35),0) -> 2 | L35: =H35*K35 -> 89000 | M35: =L35/E35 -> 3560 | P35: =CH19 -> MD0100005 | AL35: =SUM(P19:BO19) -> 564 | AQ35: =65+20 -> 85 | AS35: =((AL35*F35)+AQ35) -> 367 | BJ35: =AS35*I35 -> 13212
D36: =D20 -> 10 CORE X 2.5 SQ. MM. CU/ARD - WIRE (PVC) | E36: =K20 -> 35 | F36: =CJ20/1000 -> 0.5 | G36: 16 MT | H36: 44500 | I36: 24 | J36: =F36*I36 -> 12 | K36: =ROUNDUP((E36/J36),0) -> 3 | L36: =H36*K36 -> 133500 | M36: =L36/E36 -> 3814.2857 | P36: =CH20 -> MD0100066 | AL36: =SUM(P20:BO20) -> 1053 | AQ36: =72+25 -> 97 | AS36: =((AL36*F36)+AQ36) -> 623.5 | BJ36: =AS36*I36 -> 14964
D37: =D21 -> 12 CORE X 2.5 SQ. MM. CU/ARD - WIRE (PVC) | E37: =K21 -> 35 | F37: =CJ21/1000 -> 0.5 | G37: 16 MT | H37: 44500 | I37: 22 | J37: =F37*I37 -> 11 | K37: =ROUNDUP((E37/J37),0) -> 4 | L37: =H37*K37 -> 178000 | M37: =L37/E37 -> 5085.7143 | P37: =CH21 -> MD0100066 | AL37: =SUM(P21:BO21) -> 1146 | AQ37: =72+25 -> 97 | AS37: =((AL37*F37)+AQ37) -> 670 | BJ37: =AS37*I37 -> 14740
L40: ESTIMATED COST = | M40: 28621520
L41: OUR COST = | M41: =M30 -> 34655256
L42: DIFF % FROM OUR COST = | M42: =((M41-M40)/M41)*100 -> 17.41074

Sheet PV AUTO CALCULATION SHEET
A1: Base Date | B1: 45839
A2: PV FORMULA
A5: Item | B5: Calculation part | D5: Applicable Date | H5: BASE DATE | O5: Ex-Work Po | P5: PVC of Cu | Q5: PVC OF PVC | R5: PVC OF FE | S5: PV/PKM | T5: Billing Price/PKM
D6: Date | E6: Cu | F6: PVCc | G6: Fe | H6: Date | I6: Cuo | J6: PVCco | K6: Feo | U6: ='AUTO CALCULATION SHEET (2)'!P16 -> Tinned Copper | V6: ='AUTO CALCULATION SHEET (2)'!AL16 -> Type C PVC (HR) | W6: ='AUTO CALCULATION SHEET (2)'!AQ16 -> POLY TAPE | X6: ='AUTO CALCULATION SHEET (2)'!AS16 -> FR PVC Type ST-2 | Y6: ='AUTO CALCULATION SHEET (2)'!BJ16 -> Galvanised Steel Round Wire | Z6: ='AUTO CALCULATION SHEET (2)'!BO16 -> FRLSH PVC Type ST-2 | AA6: RMC | AB6: Drum | AC6: RMC+Drum | AD6: VA | AE6: Groos VA% | AF6: Mfg % | AG6: Int % | AH6: Ins% | AI6: Net VA
L7: CuF | M7: CCFCu | N7: FeF | U7: 958 | V7: 98 | W7: 108 | X7: 82 | Y7: 78 | Z7: 82
U8: Kg/Km | V8: Kg/Km | W8: Kg/Km | X8: Kg/Km | Y8: Kg/Km | Z8: Kg/Km
A9: ='AUTO CALCULATION SHEET (2)'!D18 -> 2 CORE X 2.5 SQ. MM. CU/ARD - WIRE (PVC) | C9: Provisional | H9: =$B$1 -> 45839 | L9: 0.047 | M9: 0.139 | N9: 0.277 | O9: ='AUTO CALCULATION SHEET (2)'!E18 -> 88225.309 | P9: =L9*(E9-I9) -> 0 | Q9: =(M9*(F9-J9)) -> 0 | R9: =(N9*(G9-K9)) -> 0 | S9: =+P9+Q9+R9 -> 0 | T9: =O9+S9 -> 88225.309 | U9: ='AUTO CALCULATION SHEET (2)'!P18 -> 44 | V9: ='AUTO CALCULATION SHEET (2)'!AL18 -> 26 | W9: ='AUTO CALCULATION SHEET (2)'!AQ18 -> 3 | X9: ='AUTO CALCULATION SHEET (2)'!AS18 -> 39 | Y9: ='AUTO CALCULATION SHEET (2)'!BJ18 -> 251 | Z9: ='AUTO CALCULATION SHEET (2)'!BO18 -> 93 | AA9: =SUMPRODUCT(U9:Z9,$U$7:Z$7) -> 75426 | AB9: ='AUTO CALCULATION SHEET (2)'!CK18 -> 4260 | AC9: =AA9+AB9 -> 79686 | AD9: =T9-AC9 -> 8539.3092 | AE9: =ROUND((AD9/AC9)*100,2) -> 10.72 | AG9: 2 | AH9: 2 | AI9: =AE9-AF9-AG9-AH9 -> 6.72
A10: ='AUTO CALCULATION SHEET (2)'!D19 -> 4 CORE X 2.5 SQ. MM. CU/ARD - WIRE (PVC) | C10: Provisional | H10: =$B$1 -> 45839 | L10: 0.094 | M10: 0.179 | N10: 0.314 | O10: ='AUTO CALCULATION SHEET (2)'!E19 -> 143036.05 | P10: =L10*(E10-I10) -> 0 | Q10: =(M10*(F10-J10)) -> 0 | R10: =(N10*(G10-K10)) -> 0 | S10: =+P10+Q10+R10 -> 0 | T10: =O10+S10 -> 143036.05 | U10: ='AUTO CALCULATION SHEET (2)'!P19 -> 89 | V10: ='AUTO CALCULATION SHEET (2)'!AL19 -> 52 | W10: ='AUTO CALCULATION SHEET (2)'!AQ19 -> 3 | X10: ='AUTO CALCULATION SHEET (2)'!AS19 -> 27 | Y10: ='AUTO CALCULATION SHEET (2)'!BJ19 -> 289 | Z10: ='AUTO CALCULATION SHEET (2)'!BO19 -> 104 | AA10: =SUMPRODUCT(U10:Z10,$U$7:Z$7) -> 123966 | AB10: ='AUTO CALCULATION SHEET (2)'!CK19 -> 5170 | AC10: =AA10+AB10 -> 129136 | AD10: =T10-AC10 -> 13900.049 | AE10: =ROUND((AD10/AC10)*100,2) -> 10.76 | AG10: 2 | AH10: 2 | AI10: =AE10-AF10-AG10-AH10 -> 6.76
A11: ='AUTO CALCULATION SHEET (2)'!D20 -> 10 CORE X 2.5 SQ. MM. CU/ARD - WIRE (PVC) | C11: Provisional | H11: =$B$1 -> 45839 | L11: 0.235 | M11: 0.337 | N11: 0.535 | O11: ='AUTO CALCULATION SHEET (2)'!E20 -> 317419.13 | P11: =L11*(E11-I11) -> 0 | Q11: =(M11*(F11-J11)) -> 0 | R11: =(N11*(G11-K11)) -> 0 | S11: =+P11+Q11+R11 -> 0 | T11: =O11+S11 -> 317419.13 | U11: ='AUTO CALCULATION SHEET (2)'!P20 -> 222 | V11: ='AUTO CALCULATION SHEET (2)'!AL20 -> 130 | W11: ='AUTO CALCULATION SHEET (2)'!AQ20 -> 5 | X11: ='AUTO CALCULATION SHEET (2)'!AS20 -> 38 | Y11: ='AUTO CALCULATION SHEET (2)'!BJ20 -> 492 | Z11: ='AUTO CALCULATION SHEET (2)'!BO20 -> 166 | AA11: =SUMPRODUCT(U11:Z11,$U$7:Z$7) -> 281060 | AB11: ='AUTO CALCULATION SHEET (2)'!CK20 -> 5448 | AC11: =AA11+AB11 -> 286508 | AD11: =T11-AC11 -> 30911.127 | AE11: =ROUND((AD11/AC11)*100,2) -> 10.79 | AG11: 2 | AH11: 2 | AI11: =AE11-AF11-AG11-AH11 -> 6.79
A12: ='AUTO CALCULATION SHEET (2)'!D21 -> 12 CORE X 2.5 SQ. MM. CU/ARD - WIRE (PVC) | C12: Provisional | H12: =$B$1 -> 45839 | L12: 0.282 | M12: 0.371 | N12: 0.572 | O12: ='AUTO CALCULATION SHEET (2)'!E21 -> 368996.31 | P12: =L12*(E12-I12) -> 0 | Q12: =(M12*(F12-J12)) -> 0 | R12: =(N12*(G12-K12)) -> 0 | S12: =+P12+Q12+R12 -> 0 | T12: =O12+S12 -> 368996.31 | U12: ='AUTO CALCULATION SHEET (2)'!P21 -> 266 | V12: ='AUTO CALCULATION SHEET (2)'!AL21 -> 156 | W12: ='AUTO CALCULATION SHEET (2)'!AQ21 -> 6 | X12: ='AUTO CALCULATION SHEET (2)'!AS21 -> 40 | Y12: ='AUTO CALCULATION SHEET (2)'!BJ21 -> 508 | Z12: ='AUTO CALCULATION SHEET (2)'!BO21 -> 170 | AA12: =SUMPRODUCT(U12:Z12,$U$7:Z$7) -> 327608 | AB12: ='AUTO CALCULATION SHEET (2)'!CK21 -> 5448 | AC12: =AA12+AB12 -> 333056 | AD12: =T12-AC12 -> 35940.305 | AE12: =ROUND((AD12/AC12)*100,2) -> 10.79 | AG12: 2 | AH12: 2 | AI12: =AE12-AF12-AG12-AH12 -> 6.79

Sheet terms
A1: The quoted prices are on Firm inclusive of packing and forwading but exclusive of GST Statutory levies.
A2: The quoted prices are on VARIABLE basis with PV base Date: DD/MM/YYYY as per "IEEMA", inclusive of packing and forwading but exclusive of GST Statutory levies.
A4: The above prices are quoted on Ex-works basis, where freight will be charged extra.
A5: The above prices are quoted on FOR Destination basis, where freight is included, refer Price offer.
A6: The above prices are quoted on Ex-works+Freight basis.
A8: 20% Advance and Balance against PI (Proforma Invoice) prior to dispatch
A9: 100% against "90 days" LC, where 90 days usance interest will be borne by LPIPL
A10: 100% against "120 days" LC, where 120 days usance interest will be borne by LPIPL
A11: 100% against "45 days" LC, where 45 days usance interest will be borne by LPIPL
A12: 100% against "60 days" LC, where 60 days usance interest will be borne by LPIPL
A13: 100% against "30 days" LC, where 30 days usance interest will be borne by LPIPL
A14: 100% against 60 days PDC from the date of MRC/MRN
... A27: Negotiable
