Workbook

Sheet Sheet1
A1: DOCKET NO. | B1: Base Date | C1: ITEM CODE | D1: PROPOSE ERP ITEM NAME | E1: Propose Drum Type | F1: Insulation Screening(Metallic) | G1: RM Rate(Insulation Screening(Metallic)) | H1: Weight (Insulation Screening (Metallic)) | I1: Cost Insulation Screening(Metallic) | J1: Conductor | K1: RM Rate(Conductor) | L1: Weight(Conductor) | M1: Cost(Conductor) | N1: AL ALLOY | O1: RM Rate(AL Alloy) | P1: Weight(Al Alloy) | Q1: Cost(AL Alloy) | R1: Insulation Screening(Non-Metallic) | S1: RM Rate(Insulation Screening(Non-Metallic)) | T1: Weight(Insulation Screening(Non-Metallic) | U1: Cost(Insulation Screening(Non-Metallic) | V1: Insulation | W1: RM Rate(Insulation) | X1: Weight(Insulation) | Y1: Cost(Insulation) | Z1: Poly Tape | AA1: RM Rate(Poly Tape) | AB1: Weight(Poly Tape) | AC1: Cost(Poly Tape) | AD1: Inner Sheath | AE1: RM Rate(Inner Sheath) | AF1: Weight(Inner Sheath) | AG1: Cost(Inner Sheath) | AH1: Armouring | AI1: RM Rate(Armouring) | AJ1: Weight(Armouring) | AK1: Cost(Armouring) | AL1: Outer Sheath | AM1: RM Rate(Outer Sheath) | AN1: Weight(Outer Sheath) | AO1: Cost(Outer Sheath) | AP1: Filler | AQ1: RM Rate(Filler) | AR1: Weight(Filler) | AS1: Cost(Filler) | AT1: Grease | AU1: RM Rate(Grease) | AV1: Weight(Grease) | AW1: Cost(Grease) | AX1: Water Swellable Tape | AY1: RM Rate(Water Swellable Tape) | AZ1: Weight(Water Swellable Tape) | BA1: Cost(Water Swellable Tape) | BB1: Semi Conducting Water Swellable Tape | BC1: RM Rate(Semi Conducting Water Swellable Tape) | BD1: Weight(Semi Conducting Water Swellable Tape) | BE1: Cost(Semi Conducting Water Swellable Tape) | BF1: Semicon Tape | BG1: RM Rate(Semicon Tape) | BH1: Weight(Semicon Tape) | BI1: Cost(Semicon Tape) | BJ1: Glass Fiber Tape | BK1: RM Rate(Glass Fiber Tape) | BL1: Weight(Glass Fiber Tape) | BM1: Cost(Glass Fiber Tape) | BN1: Copper Wire 0.8MM | BO1: RM Rate(Copper Wire 0.8MM) | BP1: Weight(Copper Wire 0.8MM) | BQ1: Cost(Copper Wire 0.8MM) | BR1: Rubberized Cotton Tape | BS1: RM Rate(Rubberized Cotton Tape) | BT1: Weight(Rubberized Cotton Tape) | BU1: Cost(Rubberized Cotton Tape) | BV1: Water Tight Compound | BW1: RM Rate(Water Tight Compound) | BX1: Weight(Water Tight Compound) | BY1: Cost(Water Tight Compound) | BZ1: Drum Cost Per KM | CA1: Total RM Cost | CB1: FIRM % | CC1: Firm Value | CD1: MFG% | CE1: MFG Value | CF1: PROF% | CG1: Profit Value | CH1: 1st EX-Works | CI1: Intt % | CJ1: Intt Value | CK1: insp% | CL1: Insp Value | CM1: TTR CHARGES% | CN1: TTR Value | CO1: EX-Works Per KM | CP1: Freight Per KM | CQ1: Price Including Freight Per KM | CR1: GST % | CS1: GST Value | CT1: Price Including GST & Freight Per KM | CU1: QTY | CV1: Unit | CW1: Total Price Of Full QTY(Including Freight&GST) | CX1: PARTY LENGTH (IF STANDER LENGTH NOT MATCH WITH PAR | CY1: DRUM CODE | CZ1: DRUM SIZE (FxbXtx Ft)
A2: ENQ-19909-25-26 | C2: FA1300010 | D2: 3 CORE X 400 SQ.MM. AL/ARM - STRIP (XLPE) - 33KV | H2: 0 | L2: 3240 | P2: 0 | T2: 427 | X2: 2621 | AB2: 0 | AF2: 405 | AJ2: 1600 | AN2: 1560 | AR2: 2672 | AV2: 0 | AZ2: 162 | BD2: 0 | BH2: 52 | BL2: 129 | BP2: 0 | BT2: 0 | BX2: 0 | CR2: 0.18 | CU2: 12.95 | CV2: KMS

Sheet AUTO CALCULATION SHEET (2)
A2: JHARKHAND BIJLI VITRAN NIGAM LIMITED
A4: TENDER SPECIFICATION NO () | B4: 96/PR/JBVNL/2026-27 (2026_JSEB_114304_1)
A5: TENDER DESCRIPTION () | B5: Manufacturing, Testing and Supply of ISI marked 33 kv XLPE Underground cable 400 sqmm under deposit headof ESA, Jamshedpur
A6: Last Date & Time of Submission () | B6: 11-Jun-2026 02:00 PM Opening on 12-Jun-2026 03:00 PM
A7: REVERSE AUCTION | B7: Not Mention
A8: Price () | B8: FIRM price Rate in figures and in words must be quoted in the enclosed proforma of price part on ‘FIRM PRICE’, subject to any statutory change in due course of time, indicating therein Ex-factory price, freight element up to destination, input tax credit under section -171 of CGST/SGST act or scheme to be retained by the supplier.
A9: Validity () | B9: Tenderer should specify the validity period of their offer which should not be less than 180 (One Hundred Eighty) days from the date of opening of tender. The offers with lesser validity period may be out- rightly rejected.
A10: Delivery Period () | B10: Materials must be delivered within 30 Days of issue of Purchase order. The materials are to be delivered within 30 Days of issue of Purchase Order. Early delivery may be preferred. The commencement of delivery period shall be reckoned from the date of issue of PO.
A11: Payment Terms () | B11: 100% payment will be made by Manager (F&A), ESA, Jamshedpur on submission of 5% Bank Guarantee(0.5% for MSE unit of Jharkhand only) from any Nationalized/Scheduled Bank of ordered value on non-judicial stamp Rs. 100/- (Rupees hundred) only valid for Guarantee period and on receipt of SRV duly signed by the concerned consignee after receipt of the materials in good condition along with tax invoice in triplicate.
A12: Standard length () | B12: The cable shall be supplied in standard drum length of 500 mtrs. + 5% tolerance for all the sizes of cable. Overall tolerance in total quantity of ordered cables shall be -2% max.
A13: Packing () | B13: The cable shall be wound on wooden drums as per IS:10418/1996 and packed in drums suitable for vertical / horizontal transport, as the case may be and shall be suitable to withstand rough handling during transport and outer storage. The wooden drums shall be reinforced with steel bends and strips for better protection.
A14: Technical Specification
O19: Conductor | W19: AL ALLOY | Y19: Insulation Screening (Metallic) | AG19: Insulation Screening (Non-Metallic) | AI19: Insulation | AR19: POLY TAPE | AS19: Inner Sheath | BB19: Armouring | BM19: ATR | BY19: FILLER | BZ19: GREASE | CA19: Water swellable Tape | CB19: Semi conducting Water Swellable tape | CC19: SEMICON TAPE | CD19: GLASS FIBER TAPE | CE19: COPPER WIRE 0.8 MM | CF19: RUBBERIZED COTTON TAPE | CG19: Water Tight Compound | CH19: DRUM TYPE | CL19: DRUM COST PER KM | CM19: TOTAL RM COST | CN19: EXTRA CONSUMPTION | CO19: EXTRA CONSUMPTION VALUE | DA19: $A$1
A20: DOCKET NO. | B20: BASE DATE | C20: ITEM CODE | D20: PROPOSE ERP ITEM NAME | E20: EX-WORKS (PER KM) | F20: FREIGHT PER KM | G20: PRICE INCLUDING FREIGHT (PER KM) | H20: GST % | I20: GST VALUE | J20: PRICE INCLUDING GST & FREIGHT (PER KM) | K20: QTY | L20: Unit | M20: TOTAL PRICE OF FULL QTY (INCLUDING FRIGHT & GST) | N20: NON CHAIN BOM ID | O20: Alumimium | P20: Alumimium ALLOY | Q20: Copper | R20: AL-59 | S20: AL-4 | T20: AL-7 | U20: Flexible Copper | V20: Galvanized steel wire | W20: Alumimium | X20: Alumimium ALLOY | Y20: Coper tape - 0.1 mm | Z20: Copper Tape - 0.03 mm | AA20: Copper Tape - 0.035 mm | AB20: Copper Tape - 0.04 mm | AC20: Copper Tape - 0.045 mm | AD20: Copper Tape - 0.050 mm | AE20: Copper Tape - 0.060 mm | AF20: Copper Tape - 0.075 mm(DOUBLE) | AG20: Extruded semiconductive | AH20: Extruded Semiconductive(Stripable) | AI20: HT-XLPE | AJ20: LT-XLPE | AK20: TR XLPE | AL20: Type A PVC | AM20: Type C PVC (HR) | AN20: Type A PVC-1.45 | AO20: Type A PVC-FR | AP20: Type A PVC-FRLS | AQ20: Type A PVC-1.38 | AR20: POLY TAPE | AS20: FR PVC Type ST-1 | AT20: FR PVC Type ST-2 | AU20: FRLSH PVC Type ST-1 | AV20: FRLSH PVC Type ST-2 | AW20: PVC Type ST-1 | AX20: PVC Type ST-1-PRESSURE EXTRUDED | AY20: PVC Type ST-2 | AZ20: PVC COMPOUND 1.48 | BA20: PVC Type ST-2-PRESSURE EXTRUDED | BB20: ACSR CORE WIRE | BC20: ACSR DOG STEEL WIRE | BD20: Aluminium Flat Strip | BE20: Aluminium Round Wire | BF20: Alumimium Tape | BG20: Double Steel Tape | BH20: Galvanised Steel Flat Strip | BI20: Galvanised Steel Flat Strip (Double) | BJ20: Galvanised Steel Flat Strip-B | BK20: Galvanised Steel Round Wire | BL20: Galvanised Steel Round Wire (Double) | BM20: FR PVC Type ST-1 | BN20: FR PVC Type ST-2 | BO20: FRLSH PVC Type ST-1 | BP20: FRLSH PVC Type ST-2 | BQ20: ZHFR | BR20: PE-ST-3 | BS20: PE-ST-7 | BT20: PVC Type ST-1 | BU20: PVC Type ST-2 | BV20: PVC COMPOUND 1.48 | BW20: PVC Type ST-2-PRESSURE EXTRUDED | BX20: UV & Track Resistant XLPE | BY20: FILLER | BZ20: Grease | CA20: Water swellable Tape | CB20: Semi conducting Water Swellable tape | CC20: SEMICON TAPE | CD20: GLASS FIBER TAPE | CE20: COPPER WIRE 0.8 MM | CF20: RUBBERIZED COTTON TAPE | CG20: Water Tight Compound | CH20: PROPOSE DRUM TYPE | CI20: DRUM CODE | CJ20: DRUM SIZE (FxbXtx Ft) | CK20: PARTY STANDARD LENGTH (MTR) | CP20: MFG% | CQ20: MFG VALUE | CR20: PROF% | CS20: PROFIT VALUE | CT20: 1ST EX-WORKS | CU20: Intt % | CV20: INTT VALUE | CW20: insp% | CX20: INSP VALUE | CY20: TTR Charges% | CZ20: TTR Charges VALUE
O21: 406 | P21: =+IFERROR(VLOOKUP($P$20,Sheet1!J:L,2,0),0) -> 0 | Q21: =+IFERROR(VLOOKUP($Q$20,Sheet1!J:M,2,0),0) -> 0 | R21: =+IFERROR(VLOOKUP($R$20,Sheet1!J:M,2,0),0) -> 0 | S21: =+IFERROR(VLOOKUP($S$20,Sheet1!J:M,2,0),0) -> 0 | T21: =+IFERROR(VLOOKUP($T$20,Sheet1!J:M,2,0),0) -> 0 | U21: =+IFERROR(VLOOKUP($U$20,Sheet1!J:M,2,0),0) -> 0 | V21: =+IFERROR(VLOOKUP($V$20,Sheet1!J:M,2,0),0) -> 0 | W21: =+IFERROR(VLOOKUP($W$20,Sheet1!N:Q,2,0),0) -> 0 | X21: =+IFERROR(VLOOKUP($X$20,Sheet1!N:O,2,0),0) -> 0 | Y21: =+IFERROR(VLOOKUP($Y$20,Sheet1!F:I,2,0),0) -> 0 | Z21: 1567 | AA21: =+IFERROR(VLOOKUP($AA$20,Sheet1!F:I,2,0),0) -> 0 | AB21: =+IFERROR(VLOOKUP($AB$20,Sheet1!F:I,2,0),0) -> 0 | AC21: =+IFERROR(VLOOKUP($AC$20,Sheet1!F:I,2,0),0) -> 0 | AD21: =+IFERROR(VLOOKUP($AD$20,Sheet1!F:I,2,0),0) -> 0 | AE21: =+IFERROR(VLOOKUP($AE$20,Sheet1!F:I,2,0),0) -> 0 | AF21: =+IFERROR(VLOOKUP($AF$20,Sheet1!F:I,2,0),0) -> 0 | AG21: =+IFERROR(VLOOKUP($AG$20,Sheet1!R:U,2,0),0) -> 0 | AH21: 219 | AI21: 199 | AJ21: =+IFERROR(VLOOKUP($AJ$20,Sheet1!V:Y,2,0),0) -> 0 | AK21: =+IFERROR(VLOOKUP($AK$20,Sheet1!V:Y,2,0),0) -> 0 | AL21: =+IFERROR(VLOOKUP($AL$20,Sheet1!V:Y,2,0),0) -> 0 | AM21: =+IFERROR(VLOOKUP($AM$20,Sheet1!V:Y,2,0),0) -> 0 | AN21: =+IFERROR(VLOOKUP($AN$20,Sheet1!V:Y,2,0),0) -> 0 | AO21: =+IFERROR(VLOOKUP($AO$20,Sheet1!V:Y,2,0),0) -> 0 | AP21: =+IFERROR(VLOOKUP($AP$20,Sheet1!V:Y,2,0),0) -> 0 | AQ21: =+IFERROR(VLOOKUP($AQ$20,Sheet1!V:Y,2,0),0) -> 0 | AR21: =+IFERROR(VLOOKUP($AR$20,Sheet1!Z2:AA840,2,0),0) -> 0 | AS21: =+IFERROR(VLOOKUP($AS$20,Sheet1!AD2:AG840,2,0),0) -> 0 | AT21: =+IFERROR(VLOOKUP($AT$20,Sheet1!AD2:AG840,2,0),0) -> 0 | AU21: =+IFERROR(VLOOKUP($AU$20,Sheet1!AD2:AG840,2,0),0) -> 0 | AV21: =+IFERROR(VLOOKUP($AV$20,Sheet1!AD2:AG840,2,0),0) -> 0 | AW21: =+IFERROR(VLOOKUP($AW$20,Sheet1!AD2:AG840,2,0),0) -> 0 | AX21: =+IFERROR(VLOOKUP($AX$20,Sheet1!AD2:AG840,2,0),0) -> 0 | AY21: 77 | AZ21: =+IFERROR(VLOOKUP($AZ$20,Sheet1!AD2:AG840,2,0),0) -> 0 | BA21: =+IFERROR(VLOOKUP($BA$20,Sheet1!AD2:AG840,2,0),0) -> 0 | BB21: =+IFERROR(VLOOKUP($BB$20,Sheet1!AH2:AK840,2,0),0) -> 0 | BC21: =+IFERROR(VLOOKUP($BC$20,Sheet1!AH2:AK840,2,0),0) -> 0 | BD21: =+IFERROR(VLOOKUP($BD$20,Sheet1!AH2:AK840,2,0),0) -> 0 | BE21: =+IFERROR(VLOOKUP($BE$20,Sheet1!AH2:AK840,2,0),0) -> 0 | BF21: =+IFERROR(VLOOKUP($BF$20,Sheet1!AH2:AK840,2,0),0) -> 0 | BG21: =+IFERROR(VLOOKUP($BG$20,Sheet1!AH2:AK840,2,0),0) -> 0 | BH21: 87 | BI21: =+IFERROR(VLOOKUP($BI$20,Sheet1!AH2:AK840,2,0),0) -> 0 | BJ21: =+IFERROR(VLOOKUP($BJ$20,Sheet1!AH2:AK840,2,0),0) -> 0 | BK21: =+IFERROR(VLOOKUP($BK$20,Sheet1!AH2:AK840,2,0),0) -> 0 | BL21: =+IFERROR(VLOOKUP($BL$20,Sheet1!AH2:AK840,2,0),0) -> 0 | BM21: =+IFERROR(VLOOKUP($BM$20,Sheet1!AL2:AO840,2,0),0) -> 0 | BN21: =+IFERROR(VLOOKUP($BN$20,Sheet1!AL2:AO840,2,0),0) -> 0 | BO21: =+IFERROR(VLOOKUP($BO$20,Sheet1!AL2:AO840,2,0),0) -> 0 | BP21: =+IFERROR(VLOOKUP($BP$20,Sheet1!AL2:AO840,2,0),0) -> 0 | BQ21: =+IFERROR(VLOOKUP($BQ$20,Sheet1!AL2:AO840,2,0),0) -> 0 | BR21: =+IFERROR(VLOOKUP($BR$20,Sheet1!AL2:AO840,2,0),0) -> 0 | BS21: =+IFERROR(VLOOKUP($BS$20,Sheet1!AL2:AO840,2,0),0) -> 0 | BT21: =+IFERROR(VLOOKUP($BT$20,Sheet1!AL2:AO840,2,0),0) -> 0 | BU21: =AY21+8 -> 85 | BV21: =+IFERROR(VLOOKUP($BV$20,Sheet1!AL2:AO840,2,0),0) -> 0 | BW21: =+IFERROR(VLOOKUP($BW$20,Sheet1!AL2:AO840,2,0),0) -> 0 | BX21: =+IFERROR(VLOOKUP($BX$20,Sheet1!AL2:AO840,2,0),0) -> 0 | BY21: 32 | BZ21: =+IFERROR(VLOOKUP($BZ$20,Sheet1!AT2:AW840,2,0),0) -> 0 | CA21: =+IFERROR(VLOOKUP($CA$20,Sheet1!AX2:BA840,2,0),0) -> 0 | CB21: =+IFERROR(VLOOKUP($CB$20,Sheet1!BB2:BE840,2,0),0) -> 0 | CC21: =+IFERROR(VLOOKUP($CC$20,Sheet1!BF2:BI840,2,0),0) -> 0 | CD21: =+IFERROR(VLOOKUP($CD$20,Sheet1!BJ2:BM840,2,0),0) -> 0 | CE21: =+IFERROR(VLOOKUP($CE$20,Sheet1!BN2:BQ840,2,0),0) -> 0 | CF21: =+IFERROR(VLOOKUP($CF$20,Sheet1!BR2:BU840,2,0),0) -> 0 | CG21: =+IFERROR(VLOOKUP($CG$20,Sheet1!BV2:BY840,2,0),0) -> 0
A22: =Sheet1!A2 -> ENQ-19909-25-26 | B22: 46183 | C22: =Sheet1!C2 -> FA1300010 | D22: =Sheet1!D2 -> 3 CORE X 400 SQ.MM. AL/ARM - STRIP (XLPE) - 33KV | E22: =NORMAL!E22 -> 3032940.7 | F22: =ROUNDUP(M27,0) -> 65251 | G22: =E22+F22 -> 3098191.7 | H22: =Sheet1!CR2 -> 0.18 | I22: =G22*H22 -> 557674.5 | J22: =G22+I22 -> 3655866.2 | K22: =Sheet1!CU2 -> 12.95 | L22: =Sheet1!CV2 -> KMS | M22: =J22*K22 -> 47343467 | N22: IS | O22: 3240 | P22: =+IFERROR(VLOOKUP($P$20,Sheet1!J2:L2,3,0),0) -> 0 | Q22: =+IFERROR(VLOOKUP($Q$20,Sheet1!J2:M2,3,0),0) -> 0 | R22: =+IFERROR(VLOOKUP($R$20,Sheet1!J2:M2,3,0),0) -> 0 | S22: =+IFERROR(VLOOKUP($S$20,Sheet1!J2:M2,3,0),0) -> 0 | T22: =+IFERROR(VLOOKUP($T$20,Sheet1!J2:M2,3,0),0) -> 0 | U22: =+IFERROR(VLOOKUP($U$20,Sheet1!J2:M2,3,0),0) -> 0 | V22: =+IFERROR(VLOOKUP($V$20,Sheet1!J2:M2,3,0),0) -> 0 | W22: =+IFERROR(VLOOKUP($W$20,Sheet1!N2:Q2,3,0),0) -> 0 | X22: =+IFERROR(VLOOKUP($X$20,Sheet1!N2:Q2,3,0),0) -> 0 | Y22: =+IFERROR(VLOOKUP($Y$20,Sheet1!F2:I2,3,0),0) -> 0 | Z22: 129 | AA22: =+IFERROR(VLOOKUP($AA$20,Sheet1!F2:I2,3,0),0) -> 0 | AB22: =+IFERROR(VLOOKUP($AB$20,Sheet1!F2:I2,3,0),0) -> 0 | AC22: =+IFERROR(VLOOKUP($AC$20,Sheet1!F2:I2,3,0),0) -> 0 | AD22: =+IFERROR(VLOOKUP($AD$20,Sheet1!F2:I2,3,0),0) -> 0 | AE22: =+IFERROR(VLOOKUP($AE$20,Sheet1!F2:I2,3,0),0) -> 0 | AF22: =+IFERROR(VLOOKUP($AF$20,Sheet1!F2:I2,3,0),0) -> 0 | AG22: =+IFERROR(VLOOKUP($AG$20,Sheet1!R2:U2,3,0),0) -> 0 | AH22: 427 | AI22: 2621 | AJ22: =+IFERROR(VLOOKUP($AJ$20,Sheet1!V2:Y2,3,0),0) -> 0 | AK22: =+IFERROR(VLOOKUP($AK$20,Sheet1!V2:Y2,3,0),0) -> 0 | AL22: =+IFERROR(VLOOKUP($AL$20,Sheet1!V2:Y2,3,0),0) -> 0 | AM22: =+IFERROR(VLOOKUP($AM$20,Sheet1!V2:Y2,3,0),0) -> 0 | AN22: =+IFERROR(VLOOKUP($AN$20,Sheet1!V2:Y2,3,0),0) -> 0 | AO22: =+IFERROR(VLOOKUP($AO$20,Sheet1!V2:Y2,3,0),0) -> 0 | AP22: =+IFERROR(VLOOKUP($AP$20,Sheet1!V2:Y2,3,0),0) -> 0 | AQ22: =+IFERROR(VLOOKUP($AQ$20,Sheet1!V2:Y2,3,0),0) -> 0 | AR22: =+IFERROR(VLOOKUP($AR$20,Sheet1!Z2:AB2,3,0),0) -> 0 | AS22: =+IFERROR(VLOOKUP($AS$20,Sheet1!AD2:AG2,3,0),0) -> 0 | AT22: =+IFERROR(VLOOKUP($AT$20,Sheet1!AD2:AG2,3,0),0) -> 0 | AU22: =+IFERROR(VLOOKUP($AU$20,Sheet1!AD2:AG2,3,0),0) -> 0 | AV22: =+IFERROR(VLOOKUP($AV$20,Sheet1!AD2:AG2,3,0),0) -> 0 | AW22: =+IFERROR(VLOOKUP($AW$20,Sheet1!AD2:AG2,3,0),0) -> 0 | AX22: =+IFERROR(VLOOKUP($AX$20,Sheet1!AD2:AG2,3,0),0) -> 0 | AY22: 405 | AZ22: =+IFERROR(VLOOKUP($AZ$20,Sheet1!AD2:AG2,3,0),0) -> 0 | BA22: =+IFERROR(VLOOKUP($BA$20,Sheet1!AD2:AG2,3,0),0) -> 0 | BB22: =+IFERROR(VLOOKUP($BB$20,Sheet1!AH2:AK2,3,0),0) -> 0 | BC22: =+IFERROR(VLOOKUP($BC$20,Sheet1!AH2:AK2,3,0),0) -> 0 | BD22: =+IFERROR(VLOOKUP($BD$20,Sheet1!AH2:AK2,3,0),0) -> 0 | BE22: =+IFERROR(VLOOKUP($BE$20,Sheet1!AH2:AK2,3,0),0) -> 0 | BF22: =+IFERROR(VLOOKUP($BF$20,Sheet1!AH2:AK2,3,0),0) -> 0 | BG22: =+IFERROR(VLOOKUP($BG$20,Sheet1!AH2:AK2,3,0),0) -> 0 | BH22: 1600 | BI22: =+IFERROR(VLOOKUP($BI$20,Sheet1!AH2:AK2,3,0),0) -> 0 | BJ22: =+IFERROR(VLOOKUP($BJ$20,Sheet1!AH2:AK2,3,0),0) -> 0 | BK22: =+IFERROR(VLOOKUP($BK$20,Sheet1!AH2:AK2,3,0),0) -> 0 | BL22: =+IFERROR(VLOOKUP($BL$20,Sheet1!AH2:AK2,3,0),0) -> 0 | BM22: =+IFERROR(VLOOKUP($BM$20,Sheet1!AL2:AO2,3,0),0) -> 0 | BN22: =+IFERROR(VLOOKUP($BN$20,Sheet1!AL2:AO2,3,0),0) -> 0 | BO22: =+IFERROR(VLOOKUP($BO$20,Sheet1!AL2:AO2,3,0),0) -> 0 | BP22: =+IFERROR(VLOOKUP($BP$20,Sheet1!AL2:AO2,3,0),0) -> 0 | BQ22: =+IFERROR(VLOOKUP($BQ$20,Sheet1!AL2:AO2,3,0),0) -> 0 | BR22: =+IFERROR(VLOOKUP($BR$20,Sheet1!AL2:AO2,3,0),0) -> 0 | BS22: =+IFERROR(VLOOKUP($BS$20,Sheet1!AL2:AO2,3,0),0) -> 0 | BT22: =+IFERROR(VLOOKUP($BT$20,Sheet1!AL2:AO2,3,0),0) -> 0 | BU22: 1560 | BV22: =+IFERROR(VLOOKUP($BV$20,Sheet1!AL2:AO2,3,0),0) -> 0 | BW22: =+IFERROR(VLOOKUP($BW$20,Sheet1!AL2:AO2,3,0),0) -> 0 | BX22: =+IFERROR(VLOOKUP($BX$20,Sheet1!AL2:AO2,3,0),0) -> 0 | BY22: 2704 | BZ22: =+IFERROR(VLOOKUP($BZ$20,Sheet1!AT2:AW2,3,0),0) -> 0 | CA22: =+IFERROR(VLOOKUP($CA$20,Sheet1!AX2:BA2,3,0),0) -> 0 | CB22: =+IFERROR(VLOOKUP($CB$20,Sheet1!BB2:BE2,3,0),0) -> 0 | CC22: =+IFERROR(VLOOKUP($CC$20,Sheet1!BF2:BI2,3,0),0) -> 0 | CD22: =+IFERROR(VLOOKUP($CD$20,Sheet1!BJ2:BM2,3,0),0) -> 0 | CE22: =+IFERROR(VLOOKUP($CE$20,Sheet1!BN2:BQ2,3,0),0) -> 0 | CF22: =+IFERROR(VLOOKUP($CF$20,Sheet1!BR2:BU2,3,0),0) -> 0 | CG22: =+IFERROR(VLOOKUP($CG$20,Sheet1!BV2:BY2,3,0),0) -> 0 | CH22: STEEL | CI22: SP0400105 | CJ22: CORRUGATED DISPATCH STEEL DRUM 2500 X 1500 X 1400 | CK22: 250 | CL22: =22000/0.25 -> 88000 | CM22: =SUMPRODUCT($O$21:$CG$21,O22:CG22)+CL22 -> 2610188 | CN22: =Sheet1!CB2 -> 0 | CO22: =CM22*CN22 -> 0 | CP22: =((CT22-CM22)/CM22) -> 0.075891238 | CQ22: =CM22*CP22 -> 198090.4 | CR22: 0 | CS22: =CM22*CR22 -> 0 | CT22: =(E22/(((CU22+CW22)*100)+100))*100 -> 2808278.4 | CU22: 0.02 | CV22: =CT22*CU22 -> 56165.568 | CW22: 0.06 | CX22: =CT22*CW22 -> 168496.7 | CY22: =Sheet1!CM2 -> 0 | CZ22: =CY22*CT22 -> 0
E26: Order Quantity | F26: Stnd Length | G26: Truck type | H26: Fare of one truck | I26: No of Drum in one truck | J26: Total length in one Truck | K26: No of Truck | L26: Total Freight | M26: Freight per KM | O26: CABLE WEIGHT KG/KM | Z26: DRUM WEIGHT | AH26: CABLE+DRUM WEIGHT | AI26: TRAILOR WEIGHT
E27: =K22 -> 12.95 | F27: =CK22/1000 -> 0.25 | G27: 25 MT TRAILOR | H27: 65000 | I27: 4 | J27: =F27*I27 -> 1 | K27: =ROUNDUP((E27/J27),0) -> 13 | L27: =H27*K27 -> 845000 | M27: =L27/E27 -> 65250.965 | O27: =SUM(O22:BY22) -> 12686 | Z27: 400 | AH27: =((O27*F27)+Z27) -> 3571.5 | AI27: =AH27*I27 -> 14286

Sheet NORMAL
A2: JHARKHAND BIJLI VITRAN NIGAM LIMITED
A4: TENDER SPECIFICATION NO () | B4: 96/PR/JBVNL/2026-27 (2026_JSEB_114304_1)
A5: TENDER DESCRIPTION () | B5: Manufacturing, Testing and Supply of ISI marked 33 kv XLPE Underground cable 400 sqmm under deposit headof ESA, Jamshedpur
A6: Last Date & Time of Submission () | B6: 11-Jun-2026 02:00 PM Opening on 12-Jun-2026 03:00 PM
A7: REVERSE AUCTION | B7: Not Mention
A8: Price () | B8: FIRM price Rate in figures and in words must be quoted in the enclosed proforma of price part on ‘FIRM PRICE’, subject to any statutory change in due course of time, indicating therein Ex-factory price, freight element up to destination, input tax credit under section -171 of CGST/SGST act or scheme to be retained by the supplier.
A9: Validity () | B9: Tenderer should specify the validity period of their offer which should not be less than 180 (One Hundred Eighty) days from the date of opening of tender. The offers with lesser validity period may be out- rightly rejected.
A10: Delivery Period () | B10: Materials must be delivered within 30 Days of issue of Purchase order. The materials are to be delivered within 30 Days of issue of Purchase Order. Early delivery may be preferred. The commencement of delivery period shall be reckoned from the date of issue of PO.
A11: Payment Terms () | B11: 100% payment will be made by Manager (F&A), ESA, Jamshedpur on submission of 5% Bank Guarantee(0.5% for MSE unit of Jharkhand only) from any Nationalized/Scheduled Bank of ordered value on non-judicial stamp Rs. 100/- (Rupees hundred) only valid for Guarantee period and on receipt of SRV duly signed by the concerned consignee after receipt of the materials in good condition along with tax invoice in triplicate.
A12: Standard length () | B12: The cable shall be supplied in standard drum length of 500 mtrs. + 5% tolerance for all the sizes of cable. Overall tolerance in total quantity of ordered cables shall be -2% max.
A13: Packing () | B13: The cable shall be wound on wooden drums as per IS:10418/1996 and packed in drums suitable for vertical / horizontal transport, as the case may be and shall be suitable to withstand rough handling during transport and outer storage. The wooden drums shall be reinforced with steel bends and strips for better protection.
A14: Technical Specification
O19: Conductor | W19: AL ALLOY | Y19: Insulation Screening (Metallic) | AG19: Insulation Screening (Non-Metallic) | AI19: Insulation | AR19: POLY TAPE | AS19: Inner Sheath | BB19: Armouring | BM19: ATR | BY19: FILLER | BZ19: GREASE | CA19: Water swellable Tape | CB19: Semi conducting Water Swellable tape | CC19: SEMICON TAPE | CD19: GLASS FIBER TAPE | CE19: COPPER WIRE 0.8 MM | CF19: RUBBERIZED COTTON TAPE | CG19: Water Tight Compound | CH19: DRUM TYPE | CL19: DRUM COST PER KM | CM19: TOTAL RM COST | CN19: EXTRA CONSUMPTION | CO19: EXTRA CONSUMPTION VALUE | DA19: $A$1
A20: DOCKET NO. | B20: BASE DATE | C20: ITEM CODE | D20: PROPOSE ERP ITEM NAME | E20: EX-WORKS (PER KM) | F20: FREIGHT PER KM | G20: PRICE INCLUDING FREIGHT (PER KM) | H20: GST % | I20: GST VALUE | J20: PRICE INCLUDING GST & FREIGHT (PER KM) | K20: QTY | L20: Unit | M20: TOTAL PRICE OF FULL QTY (INCLUDING FRIGHT & GST) | N20: NON CHAIN BOM ID | O20: Aluminium Wire Rod | P20: Copper Tape - 50 X 0.030 MM | Q20: Semi Con - CCV | R20: XLPE CCV | S20: PVC FILLER | T20: PVC COMPOUND 1.60 | U20: RP PVC BLACK 1.45 | V20: STEEL STRIP 4*0.60 MM | W20: Alumimium | X20: Alumimium ALLOY | Y20: Coper tape - 0.1 mm | Z20: Copper Tape - 0.03 mm | AA20: Copper Tape - 0.035 mm | AB20: Copper Tape - 0.04 mm | AC20: Copper Tape - 0.045 mm | AD20: Copper Tape - 0.050 mm | AE20: Copper Tape - 0.060 mm | AF20: Copper Tape - 0.075 mm(DOUBLE) | AG20: Extruded semiconductive | AH20: Extruded Semiconductive(Stripable) | AI20: HT-XLPE | AJ20: LT-XLPE | AK20: TR XLPE | AL20: Type A PVC | AM20: Type C PVC (HR) | AN20: Type A PVC-1.45 | AO20: Type A PVC-FR | AP20: Type A PVC-FRLS | AQ20: Type A PVC-1.38 | AR20: POLY TAPE | AS20: FR PVC Type ST-1 | AT20: FR PVC Type ST-2 | AU20: FRLSH PVC Type ST-1 | AV20: FRLSH PVC Type ST-2 | AW20: PVC Type ST-1 | AX20: PVC Type ST-1-PRESSURE EXTRUDED | AY20: PVC Type ST-2 | AZ20: PVC COMPOUND 1.48 | BA20: PVC Type ST-2-PRESSURE EXTRUDED | BB20: ACSR CORE WIRE | BC20: ACSR DOG STEEL WIRE | BD20: Aluminium Flat Strip | BE20: Aluminium Round Wire | BF20: Alumimium Tape | BG20: Double Steel Tape | BH20: Galvanised Steel Flat Strip | BI20: Galvanised Steel Flat Strip (Double) | BJ20: Galvanised Steel Flat Strip-B | BK20: Galvanised Steel Round Wire | BL20: Galvanised Steel Round Wire (Double) | BM20: FR PVC Type ST-1 | BN20: FR PVC Type ST-2 | BO20: FRLSH PVC Type ST-1 | BP20: FRLSH PVC Type ST-2 | BQ20: ZHFR | BR20: PE-ST-3 | BS20: PE-ST-7 | BT20: PVC Type ST-1 | BU20: PVC Type ST-2 | BV20: PVC COMPOUND 1.48 | BW20: PVC Type ST-2-PRESSURE EXTRUDED | BX20: UV & Track Resistant XLPE | BY20: FILLER | BZ20: Grease | CA20: Water swellable Tape | CB20: Semi conducting Water Swellable tape | CC20: SEMICON TAPE | CD20: GLASS FIBER TAPE | CE20: COPPER WIRE 0.8 MM | CF20: RUBBERIZED COTTON TAPE | CG20: Water Tight Compound | CH20: PROPOSE DRUM TYPE | CI20: DRUM CODE | CJ20: DRUM SIZE (FxbXtx Ft) | CK20: PARTY STANDARD LENGTH (MTR) | CP20: MFG% | CQ20: MFG VALUE | CR20: PROF% | CS20: PROFIT VALUE | CT20: 1ST EX-WORKS | CU20: Intt % | CV20: INTT VALUE | CW20: insp% | CX20: INSP VALUE | CY20: TTR Charges% | CZ20: TTR Charges VALUE
O21: 406 | P21: 1583 | Q21: 209 | R21: 199 | S21: 32 | T21: 74.7 | U21: 54 | V21: 85 | W21: =+IFERROR(VLOOKUP($W$20,Sheet1!N:Q,2,0),0) -> 0 | X21: =+IFERROR(VLOOKUP($X$20,Sheet1!N:O,2,0),0) -> 0 | Y21: =+IFERROR(VLOOKUP($Y$20,Sheet1!F:I,2,0),0) -> 0 | Z21: 1567 | AA21: =+IFERROR(VLOOKUP($AA$20,Sheet1!F:I,2,0),0) -> 0 | AB21: =+IFERROR(VLOOKUP($AB$20,Sheet1!F:I,2,0),0) -> 0 | AC21: =+IFERROR(VLOOKUP($AC$20,Sheet1!F:I,2,0),0) -> 0 | AD21: =+IFERROR(VLOOKUP($AD$20,Sheet1!F:I,2,0),0) -> 0 | AE21: =+IFERROR(VLOOKUP($AE$20,Sheet1!F:I,2,0),0) -> 0 | AF21: =+IFERROR(VLOOKUP($AF$20,Sheet1!F:I,2,0),0) -> 0 | AG21: =+IFERROR(VLOOKUP($AG$20,Sheet1!R:U,2,0),0) -> 0 | AH21: 219 | AI21: 199 | AJ21: =+IFERROR(VLOOKUP($AJ$20,Sheet1!V:Y,2,0),0) -> 0 | AK21: =+IFERROR(VLOOKUP($AK$20,Sheet1!V:Y,2,0),0) -> 0 | AL21: =+IFERROR(VLOOKUP($AL$20,Sheet1!V:Y,2,0),0) -> 0 | AM21: =+IFERROR(VLOOKUP($AM$20,Sheet1!V:Y,2,0),0) -> 0 | AN21: =+IFERROR(VLOOKUP($AN$20,Sheet1!V:Y,2,0),0) -> 0 | AO21: =+IFERROR(VLOOKUP($AO$20,Sheet1!V:Y,2,0),0) -> 0 | AP21: =+IFERROR(VLOOKUP($AP$20,Sheet1!V:Y,2,0),0) -> 0 | AQ21: =+IFERROR(VLOOKUP($AQ$20,Sheet1!V:Y,2,0),0) -> 0 | AR21: =+IFERROR(VLOOKUP($AR$20,Sheet1!Z2:AA840,2,0),0) -> 0 | AS21: =+IFERROR(VLOOKUP($AS$20,Sheet1!AD2:AG840,2,0),0) -> 0 | AT21: =+IFERROR(VLOOKUP($AT$20,Sheet1!AD2:AG840,2,0),0) -> 0 | AU21: =+IFERROR(VLOOKUP($AU$20,Sheet1!AD2:AG840,2,0),0) -> 0 | AV21: =+IFERROR(VLOOKUP($AV$20,Sheet1!AD2:AG840,2,0),0) -> 0 | AW21: =+IFERROR(VLOOKUP($AW$20,Sheet1!AD2:AG840,2,0),0) -> 0 | AX21: =+IFERROR(VLOOKUP($AX$20,Sheet1!AD2:AG840,2,0),0) -> 0 | AY21: 77 | AZ21: =+IFERROR(VLOOKUP($AZ$20,Sheet1!AD2:AG840,2,0),0) -> 0 | BA21: =+IFERROR(VLOOKUP($BA$20,Sheet1!AD2:AG840,2,0),0) -> 0 | BB21: =+IFERROR(VLOOKUP($BB$20,Sheet1!AH2:AK840,2,0),0) -> 0 | BC21: =+IFERROR(VLOOKUP($BC$20,Sheet1!AH2:AK840,2,0),0) -> 0 | BD21: =+IFERROR(VLOOKUP($BD$20,Sheet1!AH2:AK840,2,0),0) -> 0 | BE21: =+IFERROR(VLOOKUP($BE$20,Sheet1!AH2:AK840,2,0),0) -> 0 | BF21: =+IFERROR(VLOOKUP($BF$20,Sheet1!AH2:AK840,2,0),0) -> 0 | BG21: =+IFERROR(VLOOKUP($BG$20,Sheet1!AH2:AK840,2,0),0) -> 0 | BH21: 87 | BI21: =+IFERROR(VLOOKUP($BI$20,Sheet1!AH2:AK840,2,0),0) -> 0 | BJ21: =+IFERROR(VLOOKUP($BJ$20,Sheet1!AH2:AK840,2,0),0) -> 0 | BK21: =+IFERROR(VLOOKUP($BK$20,Sheet1!AH2:AK840,2,0),0) -> 0 | BL21: =+IFERROR(VLOOKUP($BL$20,Sheet1!AH2:AK840,2,0),0) -> 0 | BM21: =+IFERROR(VLOOKUP($BM$20,Sheet1!AL2:AO840,2,0),0) -> 0 | BN21: =+IFERROR(VLOOKUP($BN$20,Sheet1!AL2:AO840,2,0),0) -> 0 | BO21: =+IFERROR(VLOOKUP($BO$20,Sheet1!AL2:AO840,2,0),0) -> 0 | BP21: =+IFERROR(VLOOKUP($BP$20,Sheet1!AL2:AO840,2,0),0) -> 0 | BQ21: =+IFERROR(VLOOKUP($BQ$20,Sheet1!AL2:AO840,2,0),0) -> 0 | BR21: =+IFERROR(VLOOKUP($BR$20,Sheet1!AL2:AO840,2,0),0) -> 0 | BS21: =+IFERROR(VLOOKUP($BS$20,Sheet1!AL2:AO840,2,0),0) -> 0 | BT21: =+IFERROR(VLOOKUP($BT$20,Sheet1!AL2:AO840,2,0),0) -> 0 | BU21: =AY21+8 -> 85 | BV21: =+IFERROR(VLOOKUP($BV$20,Sheet1!AL2:AO840,2,0),0) -> 0 | BW21: =+IFERROR(VLOOKUP($BW$20,Sheet1!AL2:AO840,2,0),0) -> 0 | BX21: =+IFERROR(VLOOKUP($BX$20,Sheet1!AL2:AO840,2,0),0) -> 0 | BY21: 32 | BZ21: =+IFERROR(VLOOKUP($BZ$20,Sheet1!AT2:AW840,2,0),0) -> 0 | CA21: =+IFERROR(VLOOKUP($CA$20,Sheet1!AX2:BA840,2,0),0) -> 0 | CB21: =+IFERROR(VLOOKUP($CB$20,Sheet1!BB2:BE840,2,0),0) -> 0 | CC21: =+IFERROR(VLOOKUP($CC$20,Sheet1!BF2:BI840,2,0),0) -> 0 | CD21: =+IFERROR(VLOOKUP($CD$20,Sheet1!BJ2:BM840,2,0),0) -> 0 | CE21: =+IFERROR(VLOOKUP($CE$20,Sheet1!BN2:BQ840,2,0),0) -> 0 | CF21: =+IFERROR(VLOOKUP($CF$20,Sheet1!BR2:BU840,2,0),0) -> 0 | CG21: =+IFERROR(VLOOKUP($CG$20,Sheet1!BV2:BY840,2,0),0) -> 0
A22: =Sheet1!A2 -> ENQ-19909-25-26 | B22: 46183 | C22: =Sheet1!C2 -> FA1300010 | D22: =Sheet1!D2 -> 3 CORE X 400 SQ.MM. AL/ARM - STRIP (XLPE) - 33KV | E22: =CT22+CV22+CX22+CZ22 -> 3032940.7 | F22: =ROUNDUP(M27,0) -> 65251 | G22: =E22+F22 -> 3098191.7 | H22: =Sheet1!CR2 -> 0.18 | I22: =G22*H22 -> 557674.5 | J22: =G22+I22 -> 3655866.2 | K22: =Sheet1!CU2 -> 12.95 | L22: =Sheet1!CV2 -> KMS | M22: =J22*K22 -> 47343467 | N22: U1-C0003-2498 | O22: 2805 | P22: 119 | Q22: 380 | R22: 2600 | S22: 2650 | T22: 1550 | U22: 380 | V22: 1260 | BZ22: =+IFERROR(VLOOKUP($BZ$20,Sheet1!AT2:AW2,3,0),0) -> 0 | CA22: =+IFERROR(VLOOKUP($CA$20,Sheet1!AX2:BA2,3,0),0) -> 0 | CB22: =+IFERROR(VLOOKUP($CB$20,Sheet1!BB2:BE2,3,0),0) -> 0 | CC22: =+IFERROR(VLOOKUP($CC$20,Sheet1!BF2:BI2,3,0),0) -> 0 | CD22: =+IFERROR(VLOOKUP($CD$20,Sheet1!BJ2:BM2,3,0),0) -> 0 | CE22: =+IFERROR(VLOOKUP($CE$20,Sheet1!BN2:BQ2,3,0),0) -> 0 | CF22: =+IFERROR(VLOOKUP($CF$20,Sheet1!BR2:BU2,3,0),0) -> 0 | CG22: =+IFERROR(VLOOKUP($CG$20,Sheet1!BV2:BY2,3,0),0) -> 0 | CH22: STEEL | CI22: SP0400105 | CJ22: CORRUGATED DISPATCH STEEL DRUM 2500 X 1500 X 1400 | CK22: 250 | CL22: =22000/0.25 -> 88000 | CM22: =SUMPRODUCT($O$21:$CG$21,O22:CG22)+CL22 -> 2340232 | CN22: =Sheet1!CB2 -> 0 | CO22: =CM22*CN22 -> 0 | CP22: 0.2 | CQ22: =CM22*CP22 -> 468046.4 | CR22: 0 | CS22: =CM22*CR22 -> 0 | CT22: =CM22+CO22+CQ22+CS22 -> 2808278.4 | CU22: 0.02 | CV22: =CT22*CU22 -> 56165.568 | CW22: 0.06 | CX22: =CT22*CW22 -> 168496.7 | CY22: =Sheet1!CM2 -> 0 | CZ22: =CY22*CT22 -> 0
O23: RA0100002 | P23: RC0100011 | Q23: RE0100002 | R23: RE0100005 | S23: RP0100012 | T23: RP0100015 | U23: RP0100027 | V23: RS0100027
E26: Order Quantity | F26: Stnd Length | G26: Truck type | H26: Fare of one truck | I26: No of Drum in one truck | J26: Total length in one Truck | K26: No of Truck | L26: Total Freight | M26: Freight per KM | O26: CABLE WEIGHT KG/KM | P26: DRUM WEIGHT | Q26: CABLE+DRUM WEIGHT | R26: TRAILOR WEIGHT
E27: =K22 -> 12.95 | F27: =CK22/1000 -> 0.25 | G27: 25 MT TRAILOR | H27: 65000 | I27: 4 | J27: =F27*I27 -> 1 | K27: =ROUNDUP((E27/J27),0) -> 13 | L27: =H27*K27 -> 845000 | M27: =L27/E27 -> 65250.965 | O27: =SUM(O22:BY22) -> 11744 | P27: 400 | Q27: =((O27*F27)+P27) -> 3336 | R27: =Q27*I27 -> 13344

Sheet terms
A1: The quoted prices are on Firm inclusive of packing and forwading but exclusive of GST Statutory levies.
A2: The quoted prices are on VARIABLE basis with PV base Date: DD/MM/YYYY as per "IEEMA", inclusive of packing and forwading but exclusive of GST Statutory levies.
A4: The above prices are quoted on Ex-works basis, where freight will be charged extra.
A5: The above prices are quoted on FOR Destination basis, where freight is included, refer Price offer.
A6: The above prices are quoted on Ex-works+Freight basis.
A8: 20% Advance and Balance against PI (Proforma Invoice) prior to dispatch
A9: 100% against "90 days" LC, where 90 days usance interest will be borne by LPIPL
A10: 100% against "120 days" LC, where 120 days usance interest will be borne by LPIPL
A11: 100% against "45 days" LC, where 45 days usance interest will be borne by LPIPL
A12: 100% against "60 days" LC, where 60 days usance interest will be borne by LPIPL
A13: 100% against "30 days" LC, where 30 days usance interest will be borne by LPIPL
A14: 100% against 60 days PDC from the date of MRC/MRN
... A27: Negotiable
