Workbook

Sheet Sheet1
A1: DOCKET NO. | B1: Base Date | C1: ITEM CODE | D1: PROPOSE ERP ITEM NAME | E1: Propose Drum Type | F1: Insulation Screening(Metallic) | G1: RM Rate(Insulation Screening(Metallic)) | H1: Weight (Insulation Screening (Metallic)) | I1: Cost Insulation Screening(Metallic) | J1: Conductor | K1: RM Rate(Conductor) | L1: Weight(Conductor) | M1: Cost(Conductor) | N1: AL ALLOY | O1: RM Rate(AL Alloy) | P1: Weight(Al Alloy) | Q1: Cost(AL Alloy) | R1: Insulation Screening(Non-Metallic) | S1: RM Rate(Insulation Screening(Non-Metallic)) | T1: Weight(Insulation Screening(Non-Metallic) | U1: Cost(Insulation Screening(Non-Metallic) | V1: Insulation | W1: RM Rate(Insulation) | X1: Weight(Insulation) | Y1: Cost(Insulation) | Z1: Poly Tape | AA1: RM Rate(Poly Tape) | AB1: Weight(Poly Tape) | AC1: Cost(Poly Tape) | AD1: Inner Sheath | AE1: RM Rate(Inner Sheath) | AF1: Weight(Inner Sheath) | AG1: Cost(Inner Sheath) | AH1: Armouring | AI1: RM Rate(Armouring) | AJ1: Weight(Armouring) | AK1: Cost(Armouring) | AL1: Outer Sheath | AM1: RM Rate(Outer Sheath) | AN1: Weight(Outer Sheath) | AO1: Cost(Outer Sheath) | AP1: Filler | AQ1: RM Rate(Filler) | AR1: Weight(Filler) | AS1: Cost(Filler) | AT1: Grease | AU1: RM Rate(Grease) | AV1: Weight(Grease) | AW1: Cost(Grease) | AX1: Water Swellable Tape | AY1: RM Rate(Water Swellable Tape) | AZ1: Weight(Water Swellable Tape) | BA1: Cost(Water Swellable Tape) | BB1: Semi Conducting Water Swellable Tape | BC1: RM Rate(Semi Conducting Water Swellable Tape) | BD1: Weight(Semi Conducting Water Swellable Tape) | BE1: Cost(Semi Conducting Water Swellable Tape) | BF1: Semicon Tape | BG1: RM Rate(Semicon Tape) | BH1: Weight(Semicon Tape) | BI1: Cost(Semicon Tape) | BJ1: Glass Fiber Tape | BK1: RM Rate(Glass Fiber Tape) | BL1: Weight(Glass Fiber Tape) | BM1: Cost(Glass Fiber Tape) | BN1: Copper Wire 0.8MM | BO1: RM Rate(Copper Wire 0.8MM) | BP1: Weight(Copper Wire 0.8MM) | BQ1: Cost(Copper Wire 0.8MM) | BR1: Rubberized Cotton Tape | BS1: RM Rate(Rubberized Cotton Tape) | BT1: Weight(Rubberized Cotton Tape) | BU1: Cost(Rubberized Cotton Tape) | BV1: Water Tight Compound | BW1: RM Rate(Water Tight Compound) | BX1: Weight(Water Tight Compound) | BY1: Cost(Water Tight Compound) | BZ1: Drum Cost Per KM | CA1: Total RM Cost | CB1: FIRM % | CC1: Firm Value | CD1: MFG% | CE1: MFG Value | CF1: PROF% | CG1: Profit Value | CH1: 1st EX-Works | CI1: Intt % | CJ1: Intt Value | CK1: insp% | CL1: Insp Value | CM1: EX-Works Per KM | CN1: Freight Per KM | CO1: Price Including Freight Per KM | CP1: GST % | CQ1: GST Value | CR1: Price Including GST & Freight Per KM | CS1: QTY | CT1: Unit | CU1: Total Price Of Full QTY(Including Freight&GST) | CV1: DRUM CODE | CW1: DRUM SIZE (FxbXtx Ft) | CX1: PARTY LENGTH (IF STANDER LENGTH NOT MATCH WITH PAR
A2: ENQ-13856-22-23 | B2: 45474 | C2: FA0500017 | D2: 1 CORE X 50 SQ. MM. AL/UNARD. (XLPE) | E2: WOOD | H2: 0 | J2: Alumimium | K2: 252.6 | L2: 135 | M2: 34101 | P2: 0 | T2: 0 | V2: LT-XLPE | W2: 117 | X2: 36.841 | Y2: 4310.4 | AB2: 0 | AF2: 0 | AJ2: 0 | AL2: PVC Type ST-2 | AM2: 71.14 | AN2: 110 | AO2: 7825.4 | AR2: 0 | AV2: 0 | AZ2: 0 | BD2: 0 | BH2: 0 | BL2: 0 | BP2: 0 | BT2: 0 | BX2: 0 | BZ2: 2305.4 | CA2: 48542.2 | CH2: 48542.2 | CM2: 48542.2 | CO2: 48542.2 | CP2: 0.18 | CQ2: 8737.6 | CR2: 57279.8 | CS2: 980 | CT2: KMS | CU2: 56134200 | CV2: MD0100005 | CW2: DRUM - 36 X 14 X 23 X 2 | CX2: 1000
A3: ENQ-13856-22-23 | B3: 45474 | C3: FA0600009 | D3: 1 CORE X 70 SQ. MM AL/UNARD ( XLPE ) | E3: WOOD | H3: 0 | J3: Alumimium | K3: 252.6 | L3: 189 | M3: 47741.4 | P3: 0 | T3: 0 | V3: LT-XLPE | W3: 117 | X3: 43.433 | Y3: 5081.67 | AB3: 0 | AF3: 0 | AJ3: 0 | AL3: PVC Type ST-2 | AM3: 71.14 | AN3: 125 | AO3: 8892.5 | AR3: 0 | AV3: 0 | AZ3: 0 | BD3: 0 | BH3: 0 | BL3: 0 | BP3: 0 | BT3: 0 | BX3: 0 | BZ3: 5151.48 | CA3: 66867.05 | CH3: 66867.05 | CM3: 66867.05 | CO3: 66867.05 | CP3: 0.18 | CQ3: 12036.07 | CR3: 78903.12 | CS3: 850 | CT3: KMS | CU3: 67067651 | CV3: MD0100066 | CW3: DRUM - 40 X 15 X 23 X 2 | CX3: 500
A4: ENQ-13856-22-23 | B4: 45474 | C4: FA0600019 | D4: 1 CORE X 150 SQ. MM. AL/UNARD. (XLPE) | E4: WOOD | H4: 0 | J4: Alumimium | K4: 252.6 | L4: 405 | M4: 102303 | P4: 0 | T4: 0 | V4: LT-XLPE | W4: 117 | X4: 71.592 | Y4: 8376.27 | AB4: 0 | AF4: 0 | AJ4: 0 | AL4: PVC Type ST-2 | AM4: 71.14 | AN4: 187 | AO4: 13303.18 | AR4: 0 | AV4: 0 | AZ4: 0 | BD4: 0 | BH4: 0 | BL4: 0 | BP4: 0 | BT4: 0 | BX4: 0 | BZ4: 8030.31 | CA4: 132012.76 | CH4: 132012.76 | CM4: 132012.76 | CO4: 132012.76 | CP4: 0.18 | CQ4: 23762.3 | CR4: 155775.06 | CS4: 580 | CT4: KMS | CU4: 90349533 | CV4: MD0100014 | CW4: DRUM - 48 X 21 X 32 X 2.25 | CX4: 500
A5: ENQ-13856-22-23 | B5: 45474 | C5: FA0600020 | D5: 1 CORE X 300 SQ. MM. AL/UNARD. (XLPE) | E5: WOOD | H5: 0 | J5: Alumimium | K5: 252.6 | L5: 810 | M5: 204606 | P5: 0 | T5: 0 | V5: LT-XLPE | W5: 117 | X5: 132.446 | Y5: 15496.19 | AB5: 0 | AF5: 0 | AJ5: 0 | AL5: PVC Type ST-2 | AM5: 71.14 | AN5: 251 | AO5: 17856.14 | AR5: 0 | AV5: 0 | AZ5: 0 | BD5: 0 | BH5: 0 | BL5: 0 | BP5: 0 | BT5: 0 | BX5: 0 | BZ5: 9913.67 | CA5: 247872 | CH5: 247872 | CM5: 247872 | CO5: 247872 | CP5: 0.18 | CQ5: 44616.96 | CR5: 292488.96 | CS5: 270 | CT5: KMS | CU5: 78972019 | CV5: MD0100017 | CW5: DRUM - 52 X 18 X 36 X 2.5 | CX5: 500

Sheet AUTO CALCULATION SHEET (2)
A2: Chhattisgarh State Power Distribution Company Ltd.
A4: TENDER SPECIFICATION NO () | B4: TENDER SPECIFICATION NO. 02-03/ED(S&P)/870
A5: TENDER DESCRIPTION () | B5: “ISI” marked 1.1KV grade, Single Core, stranded Aluminium conductor XLPE insulated, PVC Sheathed un-armoured Cables of Various Sizes
A6: Last Date & Time of Submission () | B6: 22.08.2024
A7: REVERSE AUCTION | B7: Not Mention.
A8: Price () | B8: The base date of prices against Tender shall be as on 1st working day of one month prior to date of opening of tender notified initially i.e. 22.08.2024. In event of extension of due date of opening of tender, the base date of quoted prices shall remain unchanged, which should be noted by the bidder carefully, while quoting their prices.
A9: Validity () | B9: The tenderers are required to confirm specifically that the offer submitted by them shall be valid for acceptance for a period of 180 days from the date of opening of tender.
A10: Delivery Period () | B10: Normally the supply shall be commenced within two months from the date of issue of detailed order and 50% of the order quantity to be completed within three months thereafter. For balance 50% quantity manufacturing clearance will be issued separately after reviewing the performance of the material and field requirement. However, delivery can be deferred/advanced as per our requirement i.e. delivery can be rescheduled.
A11: Payment Terms () | B11: 100% payment along with full taxes and duties shall be made generally within 45 days from date of acceptance or deemed acceptance of materials received in good condition at Area Stores. Here, “Day of acceptance” or “Deemed acceptance‟ means that:- (a) The day of the actual delivery of materials. OR (b) where any objection is made in writing by the Purchaser regarding acceptance of material within 15days from the day of the delivery of material, the day on which such objection is removed by the supplier. (c) “The day of deemed acceptance” means, where no objection is made in writing by the Purchaser regarding acceptance of material within fifteen days from the day of delivery of material, the day of the actual delivery of material.
A12: Standard length () | B12: The cable length shall be 1000 meters for single core 50sqmm XLPE Insulated Cables & 500 meters for single core 70sqmm, 150sqmm & 300sqmm XLPE Insulated Cables and wound on a drum (refer IS: 10418: 1982) of suitable size and packed. The packing shall be robust enough for rough handling during transportation by Rail/Road. The ends of the cable shall be sealed by means of non-hygroscopic sealing material.
A13: Packing () | B13: The Cable in (Drum) must bear “ISI” certification Mark. In this connection, a certified photo copy of valid `ISI' Marking License rights duly attested must be submitted along with the tender as documentary evidence. In absence of this, offer is liable for rejection.
A14: Technical Specification
N16: =Sheet1!J1 -> Conductor | S16: AL ALLOY | U16: Insulation Screening (Metallic) | AC16: Insulation Screening (Non-Metallic) | AE16: Insulation | AK16: POLY TAPE | AL16: Inner Sheath | AS16: Armouring | BC16: Outer Sheath | BM16: FILLER | BN16: GREASE | BO16: Water swellable Tape | BP16: Semi conducting Water Swellable tape | BQ16: SEMICON TAPE | BR16: GLASS FIBER TAPE | BS16: COPPER WIRE 0.8 MM | BT16: RUBBERIZED COTTON TAPE | BU16: Water Tight Compound | BZ16: DRUM COST PER KM | CA16: TOTAL RM COST | CB16: EXTRA CONSUMPTION | CC16: EXTRA CONSUMPTION VALUE
A17: DOCKET NO. | B17: =Sheet1!B1 -> Base Date | C17: ITEM CODE | D17: PROPOSE ERP ITEM NAME | E17: EX-WORKS (PER KM) | F17: FREIGHT PER KM | G17: PRICE INCLUDING FREIGHT (PER KM) | H17: GST % | I17: GST VALUE | J17: PRICE INCLUDING GST & FREIGHT (PER KM) | K17: QTY | L17: Unit | M17: TOTAL PRICE OF FULL QTY (INCLUDING FRIGHT & GST) | N17: Alumimium | O17: Alumimium ALLOY | P17: Copper | Q17: Flexible Copper | R17: Galvanized steel wire | S17: Alumimium | T17: Alumimium ALLOY | U17: Coper tape - 0.1 mm | V17: Copper Tape - 0.03 mm | W17: Copper Tape - 0.035 mm | X17: Copper Tape - 0.04 mm | Y17: Copper Tape - 0.045 mm | Z17: Copper Tape - 0.050 mm | AA17: Copper Tape - 0.060 mm | AB17: Copper Tape - 0.075 mm(DOUBLE) | AC17: Extruded semiconductive | AD17: Extruded Semiconductive(Stripable) | AE17: HT-XLPE | AF17: LT-XLPE | AG17: TR XLPE | AH17: Type A PVC | AI17: Type C PVC (HR) | AJ17: XLPE | AK17: POLY TAPE | AL17: FR PVC Type ST-1 | AM17: FR PVC Type ST-2 | AN17: FRLSH PVC Type ST-2 | AO17: PVC Type ST-1 | AP17: PVC Type ST-1-PRESSURE EXTRUDED | AQ17: PVC Type ST-2 | AR17: PVC Type ST-2-PRESSURE EXTRUDED | AS17: ACSR CORE WIRE | AT17: ACSR DOG STEEL WIRE | AU17: Aluminium Flat Strip | AV17: Aluminium Round Wire | AW17: Double Steel Tape | AX17: Galvanised Steel Flat Strip | AY17: Galvanised Steel Flat Strip (Double) | AZ17: Galvanised Steel Flat Strip-B | BA17: Galvanised Steel Round Wire | BB17: Galvanised Steel Round Wire (Double) | BC17: FR PVC Type ST-1 | BD17: FR PVC Type ST-2 | BE17: FRLSH PVC Type ST-1 | BF17: FRLSH PVC Type ST-2 | BG17: PE, ST-3 | BH17: PE, ST-7 | BI17: PVC Type ST-1 | BJ17: PVC Type ST-2 | BK17: PVC Type ST-2-PRESSURE EXTRUDED | BL17: UV & Track Resistant XLPE | BM17: FILLER | BN17: Grease | BO17: Water swellable Tape | BP17: Semi conducting Water Swellable tape | BQ17: SEMICON TAPE | BR17: GLASS FIBER TAPE | BS17: COPPER WIRE 0.8 MM | BT17: RUBBERIZED COTTON TAPE | BU17: Water Tight Compound | BV17: =Sheet1!E1 -> Propose Drum Type | BW17: =Sheet1!CV1 -> DRUM CODE | BX17: =Sheet1!CW1 -> DRUM SIZE (FxbXtx Ft) | BY17: =Sheet1!CX1 -> PARTY LENGTH (IF STANDER LENGTH NOT MATCH WITH PAR | CD17: MFG% | CE17: MFG VALUE | CF17: PROF% | CG17: PROFIT VALUE | CH17: 1ST EX-WORKS | CI17: Intt % | CJ17: INTT VALUE | CK17: insp% | CL17: INSP VALUE | CN17: LP ARP 24 | CO17: DISC %
N18: 235 | O18: =+IFERROR(VLOOKUP($O$17,Sheet1!J:L,2,0),0) -> 0 | P18: =+IFERROR(VLOOKUP($P$17,Sheet1!J:M,2,0),0) -> 0 | Q18: =+IFERROR(VLOOKUP($Q$17,Sheet1!J:M,2,0),0) -> 0 | R18: =+IFERROR(VLOOKUP($R$17,Sheet1!J:M,2,0),0) -> 0 | S18: =+IFERROR(VLOOKUP($S$17,Sheet1!N:Q,2,0),0) -> 0 | T18: =+IFERROR(VLOOKUP($T$17,Sheet1!N:O,2,0),0) -> 0 | U18: =+IFERROR(VLOOKUP($U$17,Sheet1!F:I,2,0),0) -> 0 | V18: =+IFERROR(VLOOKUP($V$17,Sheet1!F:I,2,0),0) -> 0 | W18: =+IFERROR(VLOOKUP($W$17,Sheet1!F:I,2,0),0) -> 0 | X18: =+IFERROR(VLOOKUP($X$17,Sheet1!F:I,2,0),0) -> 0 | Y18: =+IFERROR(VLOOKUP($Y$17,Sheet1!F:I,2,0),0) -> 0 | Z18: =+IFERROR(VLOOKUP($Z$17,Sheet1!F:I,2,0),0) -> 0 | AA18: =+IFERROR(VLOOKUP($AA$17,Sheet1!F:I,2,0),0) -> 0 | AB18: =+IFERROR(VLOOKUP($AB$17,Sheet1!F:I,2,0),0) -> 0 | AC18: =+IFERROR(VLOOKUP($AC$17,Sheet1!R:U,2,0),0) -> 0 | AD18: =+IFERROR(VLOOKUP($AD$17,Sheet1!R:U,2,0),0) -> 0 | AE18: =+IFERROR(VLOOKUP($AE$17,Sheet1!V:Y,2,0),0) -> 0 | AF18: =+IFERROR(VLOOKUP($AF$17,Sheet1!V:Y,2,0),0) -> 117 | AG18: =+IFERROR(VLOOKUP($AG$17,Sheet1!V:Y,2,0),0) -> 0 | AH18: =+IFERROR(VLOOKUP($AH$17,Sheet1!V:Y,2,0),0) -> 0 | AI18: =+IFERROR(VLOOKUP($AI$17,Sheet1!V:Y,2,0),0) -> 0 | AJ18: =+IFERROR(VLOOKUP($AJ$17,Sheet1!V:Y,2,0),0) -> 0 | AK18: =+IFERROR(VLOOKUP($AK$17,Sheet1!Z2:AA840,2,0),0) -> 0 | AL18: =+IFERROR(VLOOKUP($AL$17,Sheet1!AD2:AG840,2,0),0) -> 0 | AM18: =+IFERROR(VLOOKUP($AM$17,Sheet1!AD2:AG840,2,0),0) -> 0 | AN18: =+IFERROR(VLOOKUP($AN$17,Sheet1!AD2:AG840,2,0),0) -> 0 | AO18: =+IFERROR(VLOOKUP($AO$17,Sheet1!AD2:AG840,2,0),0) -> 0 | AP18: =+IFERROR(VLOOKUP($AP$17,Sheet1!AD2:AG840,2,0),0) -> 0 | AQ18: =+IFERROR(VLOOKUP($AQ$17,Sheet1!AD2:AG840,2,0),0) -> 0 | AR18: =+IFERROR(VLOOKUP($AR$17,Sheet1!AD2:AG840,2,0),0) -> 0 | AS18: =+IFERROR(VLOOKUP($AS$17,Sheet1!AH2:AK840,2,0),0) -> 0 | AT18: =+IFERROR(VLOOKUP($AT$17,Sheet1!AH2:AK840,2,0),0) -> 0 | AU18: =+IFERROR(VLOOKUP($AU$17,Sheet1!AH2:AK840,2,0),0) -> 0 | AV18: =+IFERROR(VLOOKUP($AV$17,Sheet1!AH2:AK840,2,0),0) -> 0 | AW18: =+IFERROR(VLOOKUP($AW$17,Sheet1!AH2:AK840,2,0),0) -> 0 | AX18: =+IFERROR(VLOOKUP($AX$17,Sheet1!AH2:AK840,2,0),0) -> 0 | AY18: =+IFERROR(VLOOKUP($AY$17,Sheet1!AH2:AK840,2,0),0) -> 0 | AZ18: =+IFERROR(VLOOKUP($AZ$17,Sheet1!AH2:AK840,2,0),0) -> 0 | BA18: =+IFERROR(VLOOKUP($BA$17,Sheet1!AH2:AK840,2,0),0) -> 0 | BB18: =+IFERROR(VLOOKUP($BB$17,Sheet1!AH2:AK840,2,0),0) -> 0 | BC18: =+IFERROR(VLOOKUP($BC$17,Sheet1!AL2:AO840,2,0),0) -> 0 | BD18: =+IFERROR(VLOOKUP($BD$17,Sheet1!AL2:AO840,2,0),0) -> 0 | BE18: =+IFERROR(VLOOKUP($BE$17,Sheet1!AL2:AO840,2,0),0) -> 0 | BF18: =+IFERROR(VLOOKUP($BF$17,Sheet1!AL2:AO840,2,0),0) -> 0 | BG18: =+IFERROR(VLOOKUP($BG$17,Sheet1!AL2:AO840,2,0),0) -> 0 | BH18: =+IFERROR(VLOOKUP($BH$17,Sheet1!AL2:AO840,2,0),0) -> 0 | BI18: =+IFERROR(VLOOKUP($BI$17,Sheet1!AL2:AO840,2,0),0) -> 0 | BJ18: 68 | BK18: =+IFERROR(VLOOKUP($BK$17,Sheet1!AL2:AO840,2,0),0) -> 0 | BL18: =+IFERROR(VLOOKUP($BL$17,Sheet1!AL2:AO840,2,0),0) -> 0 | BM18: =+IFERROR(VLOOKUP($BM$17,Sheet1!AP2:AS840,2,0),0) -> 0 | BN18: =+IFERROR(VLOOKUP($BN$17,Sheet1!AT2:AW840,2,0),0) -> 0 | BO18: =+IFERROR(VLOOKUP($BO$17,Sheet1!AX2:BA840,2,0),0) -> 0 | BP18: =+IFERROR(VLOOKUP($BP$17,Sheet1!BB2:BE840,2,0),0) -> 0 | BQ18: =+IFERROR(VLOOKUP($BQ$17,Sheet1!BF2:BI840,2,0),0) -> 0 | BR18: =+IFERROR(VLOOKUP($BR$17,Sheet1!BJ2:BM840,2,0),0) -> 0 | BS18: =+IFERROR(VLOOKUP($BS$17,Sheet1!BN2:BQ840,2,0),0) -> 0 | BT18: =+IFERROR(VLOOKUP($BT$17,Sheet1!BR2:BU840,2,0),0) -> 0 | BU18: =+IFERROR(VLOOKUP($BU$17,Sheet1!BV2:BY840,2,0),0) -> 0
A19: =Sheet1!A2 -> ENQ-13856-22-23 | B19: =Sheet1!B2 -> 45474 | C19: =Sheet1!C2 -> FA0500017 | D19: =Sheet1!D2 -> 1 CORE X 50 SQ. MM. AL/UNARD. (XLPE) | E19: =CH19+CJ19+CL19 -> 50887.18 | F19: =ROUNDUP(M25,0) -> 1286 | G19: =E19+F19 -> 52173.18 | H19: =Sheet1!CP2 -> 0.18 | I19: =G19*H19 -> 9391.1723 | J19: =G19+I19 -> 61564.352 | K19: =Sheet1!CS2 -> 980 | L19: =Sheet1!CT2 -> KMS | M19: =J19*K19 -> 60333065 | N19: =+IFERROR(VLOOKUP($N$17,Sheet1!J2:L2,3,0),0) -> 135 | O19: =+IFERROR(VLOOKUP($O$17,Sheet1!J2:L2,3,0),0) -> 0 | P19: =+IFERROR(VLOOKUP($P$17,Sheet1!J2:M2,3,0),0) -> 0 | Q19: =+IFERROR(VLOOKUP($Q$17,Sheet1!J2:M2,3,0),0) -> 0 | R19: =+IFERROR(VLOOKUP($R$17,Sheet1!J2:M2,3,0),0) -> 0 | S19: =+IFERROR(VLOOKUP($S$17,Sheet1!N2:Q2,3,0),0) -> 0 | T19: =+IFERROR(VLOOKUP($T$17,Sheet1!N2:Q2,3,0),0) -> 0 | U19: =+IFERROR(VLOOKUP($U$17,Sheet1!F2:I2,3,0),0) -> 0 | V19: =+IFERROR(VLOOKUP($V$17,Sheet1!F2:I2,3,0),0) -> 0 | W19: =+IFERROR(VLOOKUP($W$17,Sheet1!F2:I2,3,0),0) -> 0 | X19: =+IFERROR(VLOOKUP($X$17,Sheet1!F2:I2,3,0),0) -> 0 | Y19: =+IFERROR(VLOOKUP($Y$17,Sheet1!F2:I2,3,0),0) -> 0 | Z19: =+IFERROR(VLOOKUP($Z$17,Sheet1!F2:I2,3,0),0) -> 0 | AA19: =+IFERROR(VLOOKUP($AA$17,Sheet1!F2:I2,3,0),0) -> 0 | AB19: =+IFERROR(VLOOKUP($AB$17,Sheet1!F2:I2,3,0),0) -> 0 | AC19: =+IFERROR(VLOOKUP($AC$17,Sheet1!R2:U2,3,0),0) -> 0 | AD19: =+IFERROR(VLOOKUP($AD$17,Sheet1!R2:U2,2,0),0) -> 0 | AE19: =+IFERROR(VLOOKUP($AE$17,Sheet1!V2:Y2,3,0),0) -> 0 | AF19: =+IFERROR(VLOOKUP($AF$17,Sheet1!V2:Y2,3,0),0) -> 36.841 | AG19: =+IFERROR(VLOOKUP($AG$17,Sheet1!V2:Y2,3,0),0) -> 0 | AH19: =+IFERROR(VLOOKUP($AH$17,Sheet1!V2:Y2,3,0),0) -> 0 | AI19: =+IFERROR(VLOOKUP($AI$17,Sheet1!V2:Y2,3,0),0) -> 0 | AJ19: =+IFERROR(VLOOKUP($AJ$17,Sheet1!V2:Y2,3,0),0) -> 0 | AK19: =+IFERROR(VLOOKUP($AK$17,Sheet1!Z2:AB2,3,0),0) -> 0 | AL19: =+IFERROR(VLOOKUP($AL$17,Sheet1!AD2:AG2,3,0),0) -> 0 | AM19: =+IFERROR(VLOOKUP($AM$17,Sheet1!AD2:AG2,3,0),0) -> 0 | AN19: =+IFERROR(VLOOKUP($AN$17,Sheet1!AD2:AG2,3,0),0) -> 0 | AO19: =+IFERROR(VLOOKUP($AO$17,Sheet1!AD2:AG2,3,0),0) -> 0 | AP19: =+IFERROR(VLOOKUP($AP$17,Sheet1!AD2:AG2,3,0),0) -> 0 | AQ19: =+IFERROR(VLOOKUP($AQ$17,Sheet1!AD2:AG2,3,0),0) -> 0 | AR19: =+IFERROR(VLOOKUP($AR$17,Sheet1!AD2:AG2,3,0),0) -> 0 | AS19: =+IFERROR(VLOOKUP($AS$17,Sheet1!AH2:AK2,3,0),0) -> 0 | AT19: =+IFERROR(VLOOKUP($AT$17,Sheet1!AH2:AK2,3,0),0) -> 0 | AU19: =+IFERROR(VLOOKUP($AU$17,Sheet1!AH2:AK2,3,0),0) -> 0 | AV19: =+IFERROR(VLOOKUP($AV$17,Sheet1!AH2:AK2,3,0),0) -> 0 | AW19: =+IFERROR(VLOOKUP($AW$17,Sheet1!AH2:AK2,3,0),0) -> 0 | AX19: =+IFERROR(VLOOKUP($AX$17,Sheet1!AH2:AK2,3,0),0) -> 0 | AY19: =+IFERROR(VLOOKUP($AY$17,Sheet1!AH2:AK2,3,0),0) -> 0 | AZ19: =+IFERROR(VLOOKUP($AZ$17,Sheet1!AH2:AK2,3,0),0) -> 0 | BA19: =+IFERROR(VLOOKUP($BA$17,Sheet1!AH2:AK2,3,0),0) -> 0 | BB19: =+IFERROR(VLOOKUP($BB$17,Sheet1!AH2:AK2,3,0),0) -> 0 | BC19: =+IFERROR(VLOOKUP($BC$17,Sheet1!AL2:AO2,3,0),0) -> 0 | BD19: =+IFERROR(VLOOKUP($BD$17,Sheet1!AL2:AO2,3,0),0) -> 0 | BE19: =+IFERROR(VLOOKUP($BE$17,Sheet1!AL2:AO2,3,0),0) -> 0 | BF19: =+IFERROR(VLOOKUP($BF$17,Sheet1!AL2:AO2,3,0),0) -> 0 | BG19: =+IFERROR(VLOOKUP($BG$17,Sheet1!AL2:AO2,3,0),0) -> 0 | BH19: =+IFERROR(VLOOKUP($BH$17,Sheet1!AL2:AO2,3,0),0) -> 0 | BI19: =+IFERROR(VLOOKUP($BI$17,Sheet1!AL2:AO2,3,0),0) -> 0 | BJ19: =+IFERROR(VLOOKUP($BJ$17,Sheet1!AL2:AO2,3,0),0) -> 110 | BK19: =+IFERROR(VLOOKUP($BK$17,Sheet1!AL2:AO2,3,0),0) -> 0 | BL19: =+IFERROR(VLOOKUP($BL$17,Sheet1!AL2:AO2,3,0),0) -> 0 | BM19: =+IFERROR(VLOOKUP($BM$17,Sheet1!AP2:AS2,3,0),0) -> 0 | BN19: =+IFERROR(VLOOKUP($BN$17,Sheet1!AT2:AW2,3,0),0) -> 0 | BO19: =+IFERROR(VLOOKUP($BO$17,Sheet1!AX2:BA2,3,0),0) -> 0 | BP19: =+IFERROR(VLOOKUP($BP$17,Sheet1!BB2:BE2,3,0),0) -> 0 | BQ19: =+IFERROR(VLOOKUP($BQ$17,Sheet1!BF2:BI2,3,0),0) -> 0 | BR19: =+IFERROR(VLOOKUP($BR$17,Sheet1!BJ2:BM2,3,0),0) -> 0 | BS19: =+IFERROR(VLOOKUP($BS$17,Sheet1!BN2:BQ2,3,0),0) -> 0 | BT19: =+IFERROR(VLOOKUP($BT$17,Sheet1!BR2:BU2,3,0),0) -> 0 | BU19: =+IFERROR(VLOOKUP($BU$17,Sheet1!BV2:BY2,3,0),0) -> 0 | BV19: =Sheet1!E2 -> WOOD | BW19: MD0100121 | BX19: DRUM - 34 X 14 X 23 X 2 | BY19: =Sheet1!CX2 -> 1000 | BZ19: 2230 | CA19: =SUMPRODUCT($N$18:$BU$18,N19:BU19)+BZ19 -> 45745.397 | CB19: =Sheet1!CB2 -> 0 | CC19: =CA19*CB19 -> 0 | CD19: 0.08 | CE19: =CA19*CD19 -> 3659.6318 | CF19: 0 | CG19: =CA19*CF19 -> 0 | CH19: =CA19+CC19+CE19+CG19 -> 49405.029 | CI19: 0.02 | CJ19: =CH19*CI19 -> 988.10058 | CK19: 0.01 | CL19: =CH19*CK19 -> 494.05029 | CN19: =216*1000 -> 216000 | CO19: =((CN19-E19)/CN19)*100 -> 76.441121
A20: =Sheet1!A3 -> ENQ-13856-22-23 | B20: =Sheet1!B3 -> 45474 | C20: =Sheet1!C3 -> FA0600009 | D20: =Sheet1!D3 -> 1 CORE X 70 SQ. MM AL/UNARD ( XLPE ) | E20: =CH20+CJ20+CL20 -> 69644.762 | F20: =ROUNDUP(M26,0) -> 2542 | G20: =E20+F20 -> 72186.762 | H20: =Sheet1!CP3 -> 0.18 | I20: =G20*H20 -> 12993.617 | J20: =G20+I20 -> 85180.379 | K20: =Sheet1!CS3 -> 850 | L20: =Sheet1!CT3 -> KMS | M20: =J20*K20 -> 72403322 | N20: =+IFERROR(VLOOKUP($N$17,Sheet1!J3:L3,3,0),0) -> 189 | O20: =+IFERROR(VLOOKUP($O$17,Sheet1!J3:L3,3,0),0) -> 0 | P20: =+IFERROR(VLOOKUP($P$17,Sheet1!J3:M3,3,0),0) -> 0 | Q20: =+IFERROR(VLOOKUP($Q$17,Sheet1!J3:M3,3,0),0) -> 0 | R20: =+IFERROR(VLOOKUP($R$17,Sheet1!J3:M3,3,0),0) -> 0 | S20: =+IFERROR(VLOOKUP($S$17,Sheet1!N3:Q3,3,0),0) -> 0 | T20: =+IFERROR(VLOOKUP($T$17,Sheet1!N3:Q3,3,0),0) -> 0 | U20: =+IFERROR(VLOOKUP($U$17,Sheet1!F3:I3,3,0),0) -> 0 | V20: =+IFERROR(VLOOKUP($V$17,Sheet1!F3:I3,3,0),0) -> 0 | W20: =+IFERROR(VLOOKUP($W$17,Sheet1!F3:I3,3,0),0) -> 0 | X20: =+IFERROR(VLOOKUP($X$17,Sheet1!F3:I3,3,0),0) -> 0 | Y20: =+IFERROR(VLOOKUP($Y$17,Sheet1!F3:I3,3,0),0) -> 0 | Z20: =+IFERROR(VLOOKUP($Z$17,Sheet1!F3:I3,3,0),0) -> 0 | AA20: =+IFERROR(VLOOKUP($AA$17,Sheet1!F3:I3,3,0),0) -> 0 | AB20: =+IFERROR(VLOOKUP($AB$17,Sheet1!F3:I3,3,0),0) -> 0 | AC20: =+IFERROR(VLOOKUP($AC$17,Sheet1!R3:U3,3,0),0) -> 0 | AD20: =+IFERROR(VLOOKUP($AD$17,Sheet1!R3:U3,2,0),0) -> 0 | AE20: =+IFERROR(VLOOKUP($AE$17,Sheet1!V3:Y3,3,0),0) -> 0 | AF20: =+IFERROR(VLOOKUP($AF$17,Sheet1!V3:Y3,3,0),0) -> 43.433 | AG20: =+IFERROR(VLOOKUP($AG$17,Sheet1!V3:Y3,3,0),0) -> 0 | AH20: =+IFERROR(VLOOKUP($AH$17,Sheet1!V3:Y3,3,0),0) -> 0 | AI20: =+IFERROR(VLOOKUP($AI$17,Sheet1!V3:Y3,3,0),0) -> 0 | AJ20: =+IFERROR(VLOOKUP($AJ$17,Sheet1!V3:Y3,3,0),0) -> 0 | AK20: =+IFERROR(VLOOKUP($AK$17,Sheet1!Z3:AB3,3,0),0) -> 0 | AL20: =+IFERROR(VLOOKUP($AL$17,Sheet1!AD3:AG3,3,0),0) -> 0 | AM20: =+IFERROR(VLOOKUP($AM$17,Sheet1!AD3:AG3,3,0),0) -> 0 | AN20: =+IFERROR(VLOOKUP($AN$17,Sheet1!AD3:AG3,3,0),0) -> 0 | AO20: =+IFERROR(VLOOKUP($AO$17,Sheet1!AD3:AG3,3,0),0) -> 0 | AP20: =+IFERROR(VLOOKUP($AP$17,Sheet1!AD3:AG3,3,0),0) -> 0 | AQ20: =+IFERROR(VLOOKUP($AQ$17,Sheet1!AD3:AG3,3,0),0) -> 0 | AR20: =+IFERROR(VLOOKUP($AR$17,Sheet1!AD3:AG3,3,0),0) -> 0 | AS20: =+IFERROR(VLOOKUP($AS$17,Sheet1!AH3:AK3,3,0),0) -> 0 | AT20: =+IFERROR(VLOOKUP($AT$17,Sheet1!AH3:AK3,3,0),0) -> 0 | AU20: =+IFERROR(VLOOKUP($AU$17,Sheet1!AH3:AK3,3,0),0) -> 0 | AV20: =+IFERROR(VLOOKUP($AV$17,Sheet1!AH3:AK3,3,0),0) -> 0 | AW20: =+IFERROR(VLOOKUP($AW$17,Sheet1!AH3:AK3,3,0),0) -> 0 | AX20: =+IFERROR(VLOOKUP($AX$17,Sheet1!AH3:AK3,3,0),0) -> 0 | AY20: =+IFERROR(VLOOKUP($AY$17,Sheet1!AH3:AK3,3,0),0) -> 0 | AZ20: =+IFERROR(VLOOKUP($AZ$17,Sheet1!AH3:AK3,3,0),0) -> 0 | BA20: =+IFERROR(VLOOKUP($BA$17,Sheet1!AH3:AK3,3,0),0) -> 0 | BB20: =+IFERROR(VLOOKUP($BB$17,Sheet1!AH3:AK3,3,0),0) -> 0 | BC20: =+IFERROR(VLOOKUP($BC$17,Sheet1!AL3:AO3,3,0),0) -> 0 | BD20: =+IFERROR(VLOOKUP($BD$17,Sheet1!AL3:AO3,3,0),0) -> 0 | BE20: =+IFERROR(VLOOKUP($BE$17,Sheet1!AL3:AO3,3,0),0) -> 0 | BF20: =+IFERROR(VLOOKUP($BF$17,Sheet1!AL3:AO3,3,0),0) -> 0 | BG20: =+IFERROR(VLOOKUP($BG$17,Sheet1!AL3:AO3,3,0),0) -> 0 | BH20: =+IFERROR(VLOOKUP($BH$17,Sheet1!AL3:AO3,3,0),0) -> 0 | BI20: =+IFERROR(VLOOKUP($BI$17,Sheet1!AL3:AO3,3,0),0) -> 0 | BJ20: =+IFERROR(VLOOKUP($BJ$17,Sheet1!AL3:AO3,3,0),0) -> 125 | BK20: =+IFERROR(VLOOKUP($BK$17,Sheet1!AL3:AO3,3,0),0) -> 0 | BL20: =+IFERROR(VLOOKUP($BL$17,Sheet1!AL3:AO3,3,0),0) -> 0 | BM20: =+IFERROR(VLOOKUP($BM$17,Sheet1!AP3:AS3,3,0),0) -> 0 | BN20: =+IFERROR(VLOOKUP($BN$17,Sheet1!AT3:AW3,3,0),0) -> 0 | BO20: =+IFERROR(VLOOKUP($BO$17,Sheet1!AX3:BA3,3,0),0) -> 0 | BP20: =+IFERROR(VLOOKUP($BP$17,Sheet1!BB3:BE3,3,0),0) -> 0 | BQ20: =+IFERROR(VLOOKUP($BQ$17,Sheet1!BF3:BI3,3,0),0) -> 0 | BR20: =+IFERROR(VLOOKUP($BR$17,Sheet1!BJ3:BM3,3,0),0) -> 0 | BS20: =+IFERROR(VLOOKUP($BS$17,Sheet1!BN3:BQ3,3,0),0) -> 0 | BT20: =+IFERROR(VLOOKUP($BT$17,Sheet1!BR3:BU3,3,0),0) -> 0 | BU20: =+IFERROR(VLOOKUP($BU$17,Sheet1!BV3:BY3,3,0),0) -> 0 | BV20: =Sheet1!E3 -> WOOD | BW20: MD0100005 | BX20: DRUM - 36 X 14 X 23 X 2 | BY20: =Sheet1!CX3 -> 500 | BZ20: 4611 | CA20: =SUMPRODUCT($N$18:$BU$18,N20:BU20)+BZ20 -> 62607.661 | CB20: =Sheet1!CB3 -> 0 | CC20: =CA20*CB20 -> 0 | CD20: 0.08 | CE20: =CA20*CD20 -> 5008.6129 | CF20: 0 | CG20: =CA20*CF20 -> 0 | CH20: =CA20+CC20+CE20+CG20 -> 67616.274 | CI20: 0.02 | CJ20: =CH20*CI20 -> 1352.3255 | CK20: 0.01 | CL20: =CH20*CK20 -> 676.16274 | CN20: =298*1000 -> 298000 | CO20: =((CN20-E20)/CN20)*100 -> 76.629274
A21: =Sheet1!A4 -> ENQ-13856-22-23 | B21: =Sheet1!B4 -> 45474 | C21: =Sheet1!C4 -> FA0600019 | D21: =Sheet1!D4 -> 1 CORE X 150 SQ. MM. AL/UNARD. (XLPE) | E21: =CH21+CJ21+CL21 -> 135065.68 | F21: =ROUNDUP(M27,0) -> 2561 | G21: =E21+F21 -> 137626.68 | H21: =Sheet1!CP4 -> 0.18 | I21: =G21*H21 -> 24772.802 | J21: =G21+I21 -> 162399.48 | K21: =Sheet1!CS4 -> 580 | L21: =Sheet1!CT4 -> KMS | M21: =J21*K21 -> 94191698 | N21: =+IFERROR(VLOOKUP($N$17,Sheet1!J4:L4,3,0),0) -> 405 | O21: =+IFERROR(VLOOKUP($O$17,Sheet1!J4:L4,3,0),0) -> 0 | P21: =+IFERROR(VLOOKUP($P$17,Sheet1!J4:M4,3,0),0) -> 0 | Q21: =+IFERROR(VLOOKUP($Q$17,Sheet1!J4:M4,3,0),0) -> 0 | R21: =+IFERROR(VLOOKUP($R$17,Sheet1!J4:M4,3,0),0) -> 0 | S21: =+IFERROR(VLOOKUP($S$17,Sheet1!N4:Q4,3,0),0) -> 0 | T21: =+IFERROR(VLOOKUP($T$17,Sheet1!N4:Q4,3,0),0) -> 0 | U21: =+IFERROR(VLOOKUP($U$17,Sheet1!F4:I4,3,0),0) -> 0 | V21: =+IFERROR(VLOOKUP($V$17,Sheet1!F4:I4,3,0),0) -> 0 | W21: =+IFERROR(VLOOKUP($W$17,Sheet1!F4:I4,3,0),0) -> 0 | X21: =+IFERROR(VLOOKUP($X$17,Sheet1!F4:I4,3,0),0) -> 0 | Y21: =+IFERROR(VLOOKUP($Y$17,Sheet1!F4:I4,3,0),0) -> 0 | Z21: =+IFERROR(VLOOKUP($Z$17,Sheet1!F4:I4,3,0),0) -> 0 | AA21: =+IFERROR(VLOOKUP($AA$17,Sheet1!F4:I4,3,0),0) -> 0 | AB21: =+IFERROR(VLOOKUP($AB$17,Sheet1!F4:I4,3,0),0) -> 0 | AC21: =+IFERROR(VLOOKUP($AC$17,Sheet1!R4:U4,3,0),0) -> 0 | AD21: =+IFERROR(VLOOKUP($AD$17,Sheet1!R4:U4,2,0),0) -> 0 | AE21: =+IFERROR(VLOOKUP($AE$17,Sheet1!V4:Y4,3,0),0) -> 0 | AF21: =+IFERROR(VLOOKUP($AF$17,Sheet1!V4:Y4,3,0),0) -> 71.592 | AG21: =+IFERROR(VLOOKUP($AG$17,Sheet1!V4:Y4,3,0),0) -> 0 | AH21: =+IFERROR(VLOOKUP($AH$17,Sheet1!V4:Y4,3,0),0) -> 0 | AI21: =+IFERROR(VLOOKUP($AI$17,Sheet1!V4:Y4,3,0),0) -> 0 | AJ21: =+IFERROR(VLOOKUP($AJ$17,Sheet1!V4:Y4,3,0),0) -> 0 | AK21: =+IFERROR(VLOOKUP($AK$17,Sheet1!Z4:AB4,3,0),0) -> 0 | AL21: =+IFERROR(VLOOKUP($AL$17,Sheet1!AD4:AG4,3,0),0) -> 0 | AM21: =+IFERROR(VLOOKUP($AM$17,Sheet1!AD4:AG4,3,0),0) -> 0 | AN21: =+IFERROR(VLOOKUP($AN$17,Sheet1!AD4:AG4,3,0),0) -> 0 | AO21: =+IFERROR(VLOOKUP($AO$17,Sheet1!AD4:AG4,3,0),0) -> 0 | AP21: =+IFERROR(VLOOKUP($AP$17,Sheet1!AD4:AG4,3,0),0) -> 0 | AQ21: =+IFERROR(VLOOKUP($AQ$17,Sheet1!AD4:AG4,3,0),0) -> 0 | AR21: =+IFERROR(VLOOKUP($AR$17,Sheet1!AD4:AG4,3,0),0) -> 0 | AS21: =+IFERROR(VLOOKUP($AS$17,Sheet1!AH4:AK4,3,0),0) -> 0 | AT21: =+IFERROR(VLOOKUP($AT$17,Sheet1!AH4:AK4,3,0),0) -> 0 | AU21: =+IFERROR(VLOOKUP($AU$17,Sheet1!AH4:AK4,3,0),0) -> 0 | AV21: =+IFERROR(VLOOKUP($AV$17,Sheet1!AH4:AK4,3,0),0) -> 0 | AW21: =+IFERROR(VLOOKUP($AW$17,Sheet1!AH4:AK4,3,0),0) -> 0 | AX21: =+IFERROR(VLOOKUP($AX$17,Sheet1!AH4:AK4,3,0),0) -> 0 | AY21: =+IFERROR(VLOOKUP($AY$17,Sheet1!AH4:AK4,3,0),0) -> 0 | AZ21: =+IFERROR(VLOOKUP($AZ$17,Sheet1!AH4:AK4,3,0),0) -> 0 | BA21: =+IFERROR(VLOOKUP($BA$17,Sheet1!AH4:AK4,3,0),0) -> 0 | BB21: =+IFERROR(VLOOKUP($BB$17,Sheet1!AH4:AK4,3,0),0) -> 0 | BC21: =+IFERROR(VLOOKUP($BC$17,Sheet1!AL4:AO4,3,0),0) -> 0 | BD21: =+IFERROR(VLOOKUP($BD$17,Sheet1!AL4:AO4,3,0),0) -> 0 | BE21: =+IFERROR(VLOOKUP($BE$17,Sheet1!AL4:AO4,3,0),0) -> 0 | BF21: =+IFERROR(VLOOKUP($BF$17,Sheet1!AL4:AO4,3,0),0) -> 0 | BG21: =+IFERROR(VLOOKUP($BG$17,Sheet1!AL4:AO4,3,0),0) -> 0 | BH21: =+IFERROR(VLOOKUP($BH$17,Sheet1!AL4:AO4,3,0),0) -> 0 | BI21: =+IFERROR(VLOOKUP($BI$17,Sheet1!AL4:AO4,3,0),0) -> 0 | BJ21: =+IFERROR(VLOOKUP($BJ$17,Sheet1!AL4:AO4,3,0),0) -> 187 | BK21: =+IFERROR(VLOOKUP($BK$17,Sheet1!AL4:AO4,3,0),0) -> 0 | BL21: =+IFERROR(VLOOKUP($BL$17,Sheet1!AL4:AO4,3,0),0) -> 0 | BM21: =+IFERROR(VLOOKUP($BM$17,Sheet1!AP4:AS4,3,0),0) -> 0 | BN21: =+IFERROR(VLOOKUP($BN$17,Sheet1!AT4:AW4,3,0),0) -> 0 | BO21: =+IFERROR(VLOOKUP($BO$17,Sheet1!AX4:BA4,3,0),0) -> 0 | BP21: =+IFERROR(VLOOKUP($BP$17,Sheet1!BB4:BE4,3,0),0) -> 0 | BQ21: =+IFERROR(VLOOKUP($BQ$17,Sheet1!BF4:BI4,3,0),0) -> 0 | BR21: =+IFERROR(VLOOKUP($BR$17,Sheet1!BJ4:BM4,3,0),0) -> 0 | BS21: =+IFERROR(VLOOKUP($BS$17,Sheet1!BN4:BQ4,3,0),0) -> 0 | BT21: =+IFERROR(VLOOKUP($BT$17,Sheet1!BR4:BU4,3,0),0) -> 0 | BU21: =+IFERROR(VLOOKUP($BU$17,Sheet1!BV4:BY4,3,0),0) -> 0 | BV21: =Sheet1!E4 -> WOOD | BW21: MD0100066 | BX21: DRUM - 40 X 15 X 23 X 2 | BY21: =Sheet1!CX4 -> 500 | BZ21: 5151 | CA21: =SUMPRODUCT($N$18:$BU$18,N21:BU21)+BZ21 -> 121418.26 | CB21: =Sheet1!CB4 -> 0 | CC21: =CA21*CB21 -> 0 | CD21: 0.08 | CE21: =CA21*CD21 -> 9713.4611 | CF21: 0 | CG21: =CA21*CF21 -> 0 | CH21: =CA21+CC21+CE21+CG21 -> 131131.73 | CI21: 0.02 | CJ21: =CH21*CI21 -> 2622.6345 | CK21: 0.01 | CL21: =CH21*CK21 -> 1311.3173 | CN21: =589*1000 -> 589000 | CO21: =((CN21-E21)/CN21)*100 -> 77.068646
A22: =Sheet1!A5 -> ENQ-13856-22-23 | B22: =Sheet1!B5 -> 45474 | C22: =Sheet1!C5 -> FA0600020 | D22: =Sheet1!D5 -> 1 CORE X 300 SQ. MM. AL/UNARD. (XLPE) | E22: =CH22+CJ22+CL22 -> 255218.13 | F22: =ROUNDUP(M28,0) -> 4500 | G22: =E22+F22 -> 259718.13 | H22: =Sheet1!CP5 -> 0.18 | I22: =G22*H22 -> 46749.264 | J22: =G22+I22 -> 306467.4 | K22: =Sheet1!CS5 -> 270 | L22: =Sheet1!CT5 -> KMS | M22: =J22*K22 -> 82746198 | N22: =+IFERROR(VLOOKUP($N$17,Sheet1!J5:L5,3,0),0) -> 810 | O22: =+IFERROR(VLOOKUP($O$17,Sheet1!J5:L5,3,0),0) -> 0 | P22: =+IFERROR(VLOOKUP($P$17,Sheet1!J5:M5,3,0),0) -> 0 | Q22: =+IFERROR(VLOOKUP($Q$17,Sheet1!J5:M5,3,0),0) -> 0 | R22: =+IFERROR(VLOOKUP($R$17,Sheet1!J5:M5,3,0),0) -> 0 | S22: =+IFERROR(VLOOKUP($S$17,Sheet1!N5:Q5,3,0),0) -> 0 | T22: =+IFERROR(VLOOKUP($T$17,Sheet1!N5:Q5,3,0),0) -> 0 | U22: =+IFERROR(VLOOKUP($U$17,Sheet1!F5:I5,3,0),0) -> 0 | V22: =+IFERROR(VLOOKUP($V$17,Sheet1!F5:I5,3,0),0) -> 0 | W22: =+IFERROR(VLOOKUP($W$17,Sheet1!F5:I5,3,0),0) -> 0 | X22: =+IFERROR(VLOOKUP($X$17,Sheet1!F5:I5,3,0),0) -> 0 | Y22: =+IFERROR(VLOOKUP($Y$17,Sheet1!F5:I5,3,0),0) -> 0 | Z22: =+IFERROR(VLOOKUP($Z$17,Sheet1!F5:I5,3,0),0) -> 0 | AA22: =+IFERROR(VLOOKUP($AA$17,Sheet1!F5:I5,3,0),0) -> 0 | AB22: =+IFERROR(VLOOKUP($AB$17,Sheet1!F5:I5,3,0),0) -> 0 | AC22: =+IFERROR(VLOOKUP($AC$17,Sheet1!R5:U5,3,0),0) -> 0 | AD22: =+IFERROR(VLOOKUP($AD$17,Sheet1!R5:U5,2,0),0) -> 0 | AE22: =+IFERROR(VLOOKUP($AE$17,Sheet1!V5:Y5,3,0),0) -> 0 | AF22: =+IFERROR(VLOOKUP($AF$17,Sheet1!V5:Y5,3,0),0) -> 132.446 | AG22: =+IFERROR(VLOOKUP($AG$17,Sheet1!V5:Y5,3,0),0) -> 0 | AH22: =+IFERROR(VLOOKUP($AH$17,Sheet1!V5:Y5,3,0),0) -> 0 | AI22: =+IFERROR(VLOOKUP($AI$17,Sheet1!V5:Y5,3,0),0) -> 0 | AJ22: =+IFERROR(VLOOKUP($AJ$17,Sheet1!V5:Y5,3,0),0) -> 0 | AK22: =+IFERROR(VLOOKUP($AK$17,Sheet1!Z5:AB5,3,0),0) -> 0 | AL22: =+IFERROR(VLOOKUP($AL$17,Sheet1!AD5:AG5,3,0),0) -> 0 | AM22: =+IFERROR(VLOOKUP($AM$17,Sheet1!AD5:AG5,3,0),0) -> 0 | AN22: =+IFERROR(VLOOKUP($AN$17,Sheet1!AD5:AG5,3,0),0) -> 0 | AO22: =+IFERROR(VLOOKUP($AO$17,Sheet1!AD5:AG5,3,0),0) -> 0 | AP22: =+IFERROR(VLOOKUP($AP$17,Sheet1!AD5:AG5,3,0),0) -> 0 | AQ22: =+IFERROR(VLOOKUP($AQ$17,Sheet1!AD5:AG5,3,0),0) -> 0 | AR22: =+IFERROR(VLOOKUP($AR$17,Sheet1!AD5:AG5,3,0),0) -> 0 | AS22: =+IFERROR(VLOOKUP($AS$17,Sheet1!AH5:AK5,3,0),0) -> 0 | AT22: =+IFERROR(VLOOKUP($AT$17,Sheet1!AH5:AK5,3,0),0) -> 0 | AU22: =+IFERROR(VLOOKUP($AU$17,Sheet1!AH5:AK5,3,0),0) -> 0 | AV22: =+IFERROR(VLOOKUP($AV$17,Sheet1!AH5:AK5,3,0),0) -> 0 | AW22: =+IFERROR(VLOOKUP($AW$17,Sheet1!AH5:AK5,3,0),0) -> 0 | AX22: =+IFERROR(VLOOKUP($AX$17,Sheet1!AH5:AK5,3,0),0) -> 0 | AY22: =+IFERROR(VLOOKUP($AY$17,Sheet1!AH5:AK5,3,0),0) -> 0 | AZ22: =+IFERROR(VLOOKUP($AZ$17,Sheet1!AH5:AK5,3,0),0) -> 0 | BA22: =+IFERROR(VLOOKUP($BA$17,Sheet1!AH5:AK5,3,0),0) -> 0 | BB22: =+IFERROR(VLOOKUP($BB$17,Sheet1!AH5:AK5,3,0),0) -> 0 | BC22: =+IFERROR(VLOOKUP($BC$17,Sheet1!AL5:AO5,3,0),0) -> 0 | BD22: =+IFERROR(VLOOKUP($BD$17,Sheet1!AL5:AO5,3,0),0) -> 0 | BE22: =+IFERROR(VLOOKUP($BE$17,Sheet1!AL5:AO5,3,0),0) -> 0 | BF22: =+IFERROR(VLOOKUP($BF$17,Sheet1!AL5:AO5,3,0),0) -> 0 | BG22: =+IFERROR(VLOOKUP($BG$17,Sheet1!AL5:AO5,3,0),0) -> 0 | BH22: =+IFERROR(VLOOKUP($BH$17,Sheet1!AL5:AO5,3,0),0) -> 0 | BI22: =+IFERROR(VLOOKUP($BI$17,Sheet1!AL5:AO5,3,0),0) -> 0 | BJ22: =+IFERROR(VLOOKUP($BJ$17,Sheet1!AL5:AO5,3,0),0) -> 251 | BK22: =+IFERROR(VLOOKUP($BK$17,Sheet1!AL5:AO5,3,0),0) -> 0 | BL22: =+IFERROR(VLOOKUP($BL$17,Sheet1!AL5:AO5,3,0),0) -> 0 | BM22: =+IFERROR(VLOOKUP($BM$17,Sheet1!AP5:AS5,3,0),0) -> 0 | BN22: =+IFERROR(VLOOKUP($BN$17,Sheet1!AT5:AW5,3,0),0) -> 0 | BO22: =+IFERROR(VLOOKUP($BO$17,Sheet1!AX5:BA5,3,0),0) -> 0 | BP22: =+IFERROR(VLOOKUP($BP$17,Sheet1!BB5:BE5,3,0),0) -> 0 | BQ22: =+IFERROR(VLOOKUP($BQ$17,Sheet1!BF5:BI5,3,0),0) -> 0 | BR22: =+IFERROR(VLOOKUP($BR$17,Sheet1!BJ5:BM5,3,0),0) -> 0 | BS22: =+IFERROR(VLOOKUP($BS$17,Sheet1!BN5:BQ5,3,0),0) -> 0 | BT22: =+IFERROR(VLOOKUP($BT$17,Sheet1!BR5:BU5,3,0),0) -> 0 | BU22: =+IFERROR(VLOOKUP($BU$17,Sheet1!BV5:BY5,3,0),0) -> 0 | BV22: =Sheet1!E5 -> WOOD | BW22: MD0100085 | BX22: DRUM - 43 X 15 X 28 X 2.25 | BY22: =Sheet1!CX5 -> 500 | BZ22: 6516 | CA22: =SUMPRODUCT($N$18:$BU$18,N22:BU22)+BZ22 -> 229430.18 | CB22: =Sheet1!CB5 -> 0 | CC22: =CA22*CB22 -> 0 | CD22: 0.08 | CE22: =CA22*CD22 -> 18354.415 | CF22: 0 | CG22: =CA22*CF22 -> 0 | CH22: =CA22+CC22+CE22+CG22 -> 247784.6 | CI22: 0.02 | CJ22: =CH22*CI22 -> 4955.6919 | CK22: 0.01 | CL22: =CH22*CK22 -> 2477.846 | CN22: =1145*1000 -> 1145000 | CO22: =((CN22-E22)/CN22)*100 -> 77.710207
E24: Order Quantity | F24: Stnd Length | G24: Truck type | H24: Fare of one truck | I24: No of Drum in one truck | J24: Total length in one Truck | K24: No of Truck | L24: Total Freight | M24: Freight per KM | AF24: CABLES WEIGHT KG/KM | BJ24: DRUM WEIGHT | BV24: CABLES+DRUM WEIGHT | BW24: TRUCK WEIGHT
D25: =D19 -> 1 CORE X 50 SQ. MM. AL/UNARD. (XLPE) | E25: =K19 -> 980 | F25: =BY19/1000 -> 1 | G25: 16 MT | H25: 45000 | I25: 36 | J25: =F25*I25 -> 36 | K25: =ROUNDUP((E25/J25),0) -> 28 | L25: =M25*E25 -> 1260000 | M25: =(H25*K25)/E25 -> 1285.7143 | AF25: =SUM(N19:BJ19) -> 281.841 | BJ25: 55 | BV25: =((AF25*F25)+BJ25) -> 336.841 | BW25: =BV25*I25 -> 12126.276
D26: =D20 -> 1 CORE X 70 SQ. MM AL/UNARD ( XLPE ) | E26: =K20 -> 850 | F26: =BY20/1000 -> 0.5 | G26: 16 MT | H26: 45000 | I26: 36 | J26: =F26*I26 -> 18 | K26: =ROUNDUP((E26/J26),0) -> 48 | L26: =M26*E26 -> 2160000 | M26: =(H26*K26)/E26 -> 2541.1765 | AF26: =SUM(N20:BJ20) -> 357.433 | BJ26: =50+15 -> 65 | BV26: =((AF26*F26)+BJ26) -> 243.7165 | BW26: =BV26*I26 -> 8773.794
D27: =D21 -> 1 CORE X 150 SQ. MM. AL/UNARD. (XLPE) | E27: =K21 -> 580 | F27: =BY21/1000 -> 0.5 | G27: 16 MT | H27: 45000 | I27: 36 | J27: =F27*I27 -> 18 | K27: =ROUNDUP((E27/J27),0) -> 33 | L27: =M27*E27 -> 1485000 | M27: =(H27*K27)/E27 -> 2560.3448 | AF27: =SUM(N21:BJ21) -> 663.592 | BJ27: =55+20 -> 75 | BV27: =((AF27*F27)+BJ27) -> 406.796 | BW27: =BV27*I27 -> 14644.656
D28: =D22 -> 1 CORE X 300 SQ. MM. AL/UNARD. (XLPE) | E28: =K22 -> 270 | F28: =BY22/1000 -> 0.5 | G28: 16 MT | H28: 45000 | I28: 20 | J28: =F28*I28 -> 10 | K28: =ROUNDUP((E28/J28),0) -> 27 | L28: =M28*E28 -> 1215000 | M28: =(H28*K28)/E28 -> 4500 | AF28: =SUM(N22:BJ22) -> 1193.446 | BJ28: =75+25 -> 100 | BV28: =((AF28*F28)+BJ28) -> 696.723 | BW28: =BV28*I28 -> 13934.46

Sheet PV
A1: Base Date | B1: 45474
A2: PV Terms(Price Variation Formula) | B2: The base date of prices against Tender shall be as on 1st working day of one month prior to date of opening of tender notified initially.
A3: PV FORMULA
A4: P = Po + ALF ( Al – Alo ) + CCFAI (Cc – Cco) +FeF (Fe – Feo)
A8: Item | B8: Calculation part | C8: Date of Inspection | D8: Applicable Date | H8: BASE DATE | L8: FACTORS | O8: Ex-Work Po | P8: PVC of al | Q8: PVC OF PVC | R8: PVC OF FE | S8: PV/PKM | T8: Billing Price/PKM | U8: VALUE ADDITION CALCULATION
D9: Date | E9: Al | F9: Cc | G9: Pvc | H9: Date | I9: Alo | J9: Cco | K9: Pvc
L10: Alf | M10: XLFAL | N10: CCFAI | U10: ='AUTO CALCULATION SHEET (2)'!N17 -> Alumimium | V10: ='AUTO CALCULATION SHEET (2)'!AF17 -> LT-XLPE | W10: ='AUTO CALCULATION SHEET (2)'!BJ17 -> PVC Type ST-2 | X10: RMC | Y10: Drum | Z10: RMC+Drum | AA10: VA | AB10: Groos VA% | AC10: Mfg % | AD10: Int % | AE10: Ins% | AF10: Net VA
U11: 243 | V11: 117 | W11: 65
A12: ='AUTO CALCULATION SHEET (2)'!D19 -> 1 CORE X 50 SQ. MM. AL/UNARD. (XLPE) | C12: Provisional | D12: 45524 | E12: 214901.38 | F12: 155060 | G12: 166325 | H12: =$B$1 -> 45474 | I12: 232711 | J12: 155060 | K12: 166325 | L12: 0.137 | M12: 0.033 | N12: 0.124 | O12: ='AUTO CALCULATION SHEET (2)'!E19 -> 50887.18 | P12: =(L12*(E12-I12)) -> -2439.9179 | Q12: =M12*(F12-J12) -> 0 | R12: =N12*(G12-K12) -> 0 | S12: =P12+Q12+R12 -> -2439.9179 | T12: =O12+S12 -> 48447.262 | U12: ='AUTO CALCULATION SHEET (2)'!N19 -> 135 | V12: ='AUTO CALCULATION SHEET (2)'!AF19 -> 36.841 | W12: ='AUTO CALCULATION SHEET (2)'!BJ19 -> 110 | X12: =SUMPRODUCT(U12:W12,$U$11:$W$11) -> 44265.397 | Y12: ='AUTO CALCULATION SHEET (2)'!BZ19 -> 2230 | Z12: =X12+Y12 -> 46495.397 | AA12: =T12-Z12 -> 1951.8647 | AB12: =ROUND((AA12/Z12)*100,2) -> 4.2 | AF12: =AB12-AC12-AD12-AE12 -> 4.2
A13: ='AUTO CALCULATION SHEET (2)'!D20 -> 1 CORE X 70 SQ. MM AL/UNARD ( XLPE ) | C13: Provisional | D13: 45524 | E13: 214901.38 | F13: 155060 | G13: 166325 | H13: =$B$1 -> 45474 | I13: 232711 | J13: 155060 | K13: 166325 | L13: 0.197 | M13: 0.042 | N13: 0.146 | O13: ='AUTO CALCULATION SHEET (2)'!E20 -> 69644.762 | P13: =(L13*(E13-I13)) -> -3508.4951 | Q13: =M13*(F13-J13) -> 0 | R13: =N13*(G13-K13) -> 0 | S13: =P13+Q13+R13 -> -3508.4951 | T13: =O13+S13 -> 66136.267 | U13: ='AUTO CALCULATION SHEET (2)'!N20 -> 189 | V13: ='AUTO CALCULATION SHEET (2)'!AF20 -> 43.433 | W13: ='AUTO CALCULATION SHEET (2)'!BJ20 -> 125 | X13: =SUMPRODUCT(U13:W13,$U$11:$W$11) -> 59133.661 | Y13: ='AUTO CALCULATION SHEET (2)'!BZ20 -> 4611 | Z13: =X13+Y13 -> 63744.661 | AA13: =T13-Z13 -> 2391.606 | AB13: =ROUND((AA13/Z13)*100,2) -> 3.75 | AF13: =AB13-AC13-AD13-AE13 -> 3.75
A14: ='AUTO CALCULATION SHEET (2)'!D21 -> 1 CORE X 150 SQ. MM. AL/UNARD. (XLPE) | C14: Provisional | D14: 45524 | E14: 214901.38 | F14: 155060 | G14: 166325 | H14: =$B$1 -> 45474 | I14: 232711 | J14: 155060 | K14: 166325 | L14: 0.425 | M14: 0.078 | N14: 0.217 | O14: ='AUTO CALCULATION SHEET (2)'!E21 -> 135065.68 | P14: =(L14*(E14-I14)) -> -7569.0885 | Q14: =M14*(F14-J14) -> 0 | R14: =N14*(G14-K14) -> 0 | S14: =P14+Q14+R14 -> -7569.0885 | T14: =O14+S14 -> 127496.59 | U14: ='AUTO CALCULATION SHEET (2)'!N21 -> 405 | V14: ='AUTO CALCULATION SHEET (2)'!AF21 -> 71.592 | W14: ='AUTO CALCULATION SHEET (2)'!BJ21 -> 187 | X14: =SUMPRODUCT(U14:W14,$U$11:$W$11) -> 118946.26 | Y14: ='AUTO CALCULATION SHEET (2)'!BZ21 -> 5151 | Z14: =X14+Y14 -> 124097.26 | AA14: =T14-Z14 -> 3399.3244 | AB14: =ROUND((AA14/Z14)*100,2) -> 2.74 | AF14: =AB14-AC14-AD14-AE14 -> 2.74
A15: ='AUTO CALCULATION SHEET (2)'!D22 -> 1 CORE X 300 SQ. MM. AL/UNARD. (XLPE) | C15: Provisional | D15: 45524 | E15: 214901.38 | F15: 155060 | G15: 166325 | H15: =$B$1 -> 45474 | I15: 232711 | J15: 155060 | K15: 166325 | L15: 0.879 | M15: 0.138 | N15: 0.303 | O15: ='AUTO CALCULATION SHEET (2)'!E22 -> 255218.13 | P15: =(L15*(E15-I15)) -> -15654.656 | Q15: =M15*(F15-J15) -> 0 | R15: =N15*(G15-K15) -> 0 | S15: =P15+Q15+R15 -> -15654.656 | T15: =O15+S15 -> 239563.48 | U15: ='AUTO CALCULATION SHEET (2)'!N22 -> 810 | V15: ='AUTO CALCULATION SHEET (2)'!AF22 -> 132.446 | W15: ='AUTO CALCULATION SHEET (2)'!BJ22 -> 251 | X15: =SUMPRODUCT(U15:W15,$U$11:$W$11) -> 228641.18 | Y15: ='AUTO CALCULATION SHEET (2)'!BZ22 -> 6516 | Z15: =X15+Y15 -> 235157.18 | AA15: =T15-Z15 -> 4406.2965 | AB15: =ROUND((AA15/Z15)*100,2) -> 1.87 | AF15: =AB15-AC15-AD15-AE15 -> 1.87
