Workbook

Sheet Sheet1
A1: DOCKET NO. | B1: Base Date | C1: ITEM CODE | D1: PROPOSE ERP ITEM NAME | E1: PROPOSE DRUM TYPE | F1: Insulation Screening (Metallic) | G1: RM RATE (Insulation Screening (Metallic)) | H1: Weight (Insulation Screening (Metallic)) | I1: COST(Insulation Screening (Metallic)) | J1: Conductor | K1: RM RATE(Conductor) | L1: WEIGHT(Conductor) | M1: COST(Conductor) | N1: AL ALLOY | O1: RM RATE(Alu Alloy) | P1: WEIGHT(Alu Alloy) | Q1: COST(Alu Alloy) | R1: Insulation Screening (Non-Metallic) | S1: RM RATE(Insulation Screening (Non-Metallic)) | T1: WEIGHT(Insulation Screening (Non-Metallic)) | U1: COST(Insulation Screening (Non-Metallic)) | V1: Insulation | W1: RM RATE(Insulation) | X1: WEIGHT(Insulation) | Y1: COST(Insulation) | Z1: POLY TAPE | AA1: RM RATE (Poly Tape) | AB1: WEIGHT (Poly Tape) | AC1: COST(Poly Tape) | AD1: Inner Sheath | AE1: RM RATE(Inner Sheath) | AF1: WEIGHT(Inner Sheath) | AG1: COST(Inner Sheath) | AH1: Armouring | AI1: RM RATE(Armouring) | AJ1: WEIGHT(Armouring) | AK1: COST(Armouring) | AL1: Outer Sheath | AM1: RM RATE(Outer Sheath) | AN1: WEIGHT(Outer Sheath) | AO1: COST(Outer Sheath) | AP1: FILLER | AQ1: RM RATE(Filler) | AR1: WEIGHT(Filler) | AS1: COST(Filler) | AT1: GREASE | AU1: RM RATE(Grease) | AV1: WEIGHT(Grease) | AW1: COST(Grease) | AX1: Water swellable Tape | AY1: RM RATE(Water swellable Tape) | AZ1: WEIGHT(Water swellable Tape) | BA1: COST(Water swellable Tape) | BB1: Semi conducting Water Swellable tape | BC1: RM RATE(Semi conducting Water Swellable tape) | BD1: WEIGHT(Semi conducting Water Swellable tape) | BE1: COST(Semi conducting Water Swellable tape) | BF1: SEMICON TAPE | BG1: RM RATE(SEMICON TAPE) | BH1: WEIGHT(SEMICON TAPE) | BI1: COST(SEMICON TAPE) | BJ1: GLASS FIBER TAPE | BK1: RM RATE(GLASS FIBER TAPE) | BL1: WEIGHT(GLASS FIBER TAPE) | BM1: COST(GLASS FIBER TAPE) | BN1: COPPER WIRE 0.8 MM | BO1: RM RATE(COPPER WIRE 0.8 MM) | BP1: WEIGHT(COPPER WIRE 0.8 MM) | BQ1: COST(COPPER WIRE 0.8 MM) | BR1: RUBBERIZED COTTON TAPE | BS1: RM RATE(RUBBERIZED COTTON TAPE) | BT1: WEIGHT(RUBBERIZED COTTON TAPE) | BU1: COST(RUBBERIZED COTTON TAPE) | BV1: Water Tight Compound | BW1: RM RATE(Water Tight Compound) | BX1: WEIGHT(Water Tight Compound) | BY1: COST(Water Tight Compound) | BZ1: DRUM COST PER KM | CA1: TOTAL RM COST | CB1: FIRM % | CC1: FIRM VALUE | CD1: MFG% | CE1: MFG VALUE | CF1: PROF% | CG1: PROFIT VALUE | CH1: 1ST EX-WORKS | CI1: Intt % | CJ1: INTT VALUE | CK1: insp% | CL1: INSP VALUE | CM1: EX-WORKS (PER KM) | CN1: FREIGHT PER KM | CO1: PRICE INCLUDING FREIGHT (PER KM) | CP1: GST % | CQ1: GST VALUE | CR1: PRICE INCLUDING GST & FREIGHT (PER KM) | CS1: QTY | CT1: Unit | CU1: TOTAL PRICE OF FULL QTY (INCLUDING FRIGHT & GST) | CV1: DRUM CODE | CW1: DRUM SIZE (FxbXtx Ft) | CX1: PARTY STANDARD LENGTH (MTR)
A2: ENQ-11584-22-23 | B2: 45231 | C2: FA0200003 | D2: 12 CORE X 2.5 SQ. MM. CU/ARD - WIRE (PVC) | E2: WOOD | J2: Copper | K2: 723.5 | L2: 266.4 | M2: 192740.4 | P2: 0 | T2: 0 | V2: Type C PVC (HR) | W2: 101.8 | X2: 156 | Y2: 15880.8 | Z2: POLY TAPE | AA2: 123 | AB2: 6 | AC2: 738 | AD2: PVC Type ST-2 | AE2: 60.8 | AF2: 40 | AG2: 2432 | AH2: Galvanised Steel Round Wire | AI2: 88.78 | AJ2: 508 | AK2: 45100.24 | AL2: FRLSH PVC Type ST-2 | AM2: 92 | AN2: 170 | AO2: 15640 | AR2: 0 | AV2: 0 | AZ2: 0 | BD2: 0 | BH2: 0 | BL2: 28 | BP2: 0 | BT2: 0 | BX2: 0 | BZ2: 5151.48 | CA2: 277682.92 | CH2: 277682.92 | CM2: 277682.92 | CO2: 277682.92 | CP2: 0.18 | CQ2: 49982.93 | CR2: 327665.85 | CS2: 40 | CT2: KMS | CU2: 13106634 | CV2: MD0100066 | CW2: DRUM - 40 X 15 X 23 X 2
A3: ENQ-11584-22-23 | B3: 45231 | C3: FA0200019 | D3: 8 CORE X 2.5 SQ. MM. CU/ARD - WIRE (PVC) | E3: WOOD | J3: Copper | K3: 723.5 | L3: 177.6 | M3: 128493.6 | P3: 0 | T3: 0 | V3: Type C PVC (HR) | W3: 101.8 | X3: 104 | Y3: 10587.2 | Z3: POLY TAPE | AA3: 123 | AB3: 4 | AC3: 492 | AD3: PVC Type ST-2 | AE3: 60.8 | AF3: 31 | AG3: 1884.8 | AH3: Galvanised Steel Round Wire | AI3: 88.78 | AJ3: 365 | AK3: 32404.7 | AL3: FRLSH PVC Type ST-2 | AM3: 92 | AN3: 135 | AO3: 12420 | AR3: 0 | AV3: 0 | AZ3: 0 | BD3: 0 | BH3: 0 | BL3: 0 | BP3: 0 | BT3: 0 | BX3: 0 | BZ3: 4610.79 | CA3: 190893.09 | CH3: 190893.09 | CM3: 190893.09 | CO3: 190893.09 | CP3: 0.18 | CQ3: 34360.76 | CR3: 225253.85 | CS3: 40 | CT3: KMS | CU3: 9010154 | CV3: MD0100005 | CW3: DRUM - 36 X 14 X 23 X 2
A4: ENQ-11584-22-23 | B4: 45231 | C4: FA0200011 | D4: 4 CORE X 2.5 SQ. MM. CU/ARD - WIRE (PVC) | E4: WOOD | J4: Copper | K4: 723.5 | L4: 88.8 | M4: 64246.8 | P4: 0 | T4: 0 | V4: Type C PVC (HR) | W4: 101.8 | X4: 52 | Y4: 5293.6 | Z4: POLY TAPE | AA4: 123 | AB4: 3 | AC4: 369 | AD4: PVC Type ST-2 | AE4: 60.8 | AF4: 27 | AG4: 1641.6 | AH4: Galvanised Steel Round Wire | AI4: 88.78 | AJ4: 289 | AK4: 25657.42 | AL4: FRLSH PVC Type ST-2 | AM4: 92 | AN4: 104 | AO4: 9568 | AR4: 0 | AV4: 0 | AZ4: 0 | BD4: 0 | BH4: 0 | BL4: 19 | BP4: 0 | BT4: 0 | BX4: 0 | BZ4: 4610.79 | CA4: 111387.21 | CH4: 111387.21 | CM4: 111387.21 | CO4: 111387.21 | CP4: 0.18 | CQ4: 20049.7 | CR4: 131436.91 | CS4: 60 | CT4: KMS | CU4: 7886214 | CV4: MD0100005 | CW4: DRUM - 36 X 14 X 23 X 2
A5: ENQ-11584-22-23 | B5: 45231 | C5: FA1000002 | D5: 2 CORE X 6 SQ. MM. AL/UNARD (PVC) | E5: WOOD | J5: Alumimium | K5: 220 | L5: 32.4 | M5: 7128 | P5: 0 | T5: 0 | V5: Type A PVC | W5: 71.8 | X5: 40 | Y5: 2872 | AB5: 0 | AD5: PVC Type ST-1 | AE5: 58.8 | AF5: 68 | AG5: 3998.4 | AJ5: 0 | AL5: PVC Type ST-1 | AM5: 58.8 | AN5: 109 | AO5: 6409.2 | AR5: 0 | AV5: 0 | AZ5: 0 | BD5: 0 | BH5: 0 | BL5: 0 | BP5: 0 | BT5: 0 | BX5: 0 | BZ5: 3751.68 | CA5: 24159.28 | CH5: 24159.28 | CM5: 24159.28 | CO5: 24159.28 | CP5: 0.18 | CQ5: 4348.67 | CR5: 28507.95 | CS5: 200 | CT5: KMS | CU5: 5701590 | CV5: MD0100004 | CW5: DRUM - 28 X 10 X 23 X 2

Sheet AUTO CALCULATION SHEET (2)
A2: WEST BENGAL STATE ELECTRICITY DISTRIBUTION COMPANY LIMITED
A4: TENDER SPECIFICATION NO () | B4: P-43/2023-24/PC-III/CuCC_PVC
A5: TENDER DESCRIPTION () | B5: CONTROL CABLE.
A6: Last Date & Time of Submission () | B6: 11.12.2023 up to 14.30 Hrs.
A7: REVERSE AUCTION | B7: Not Mention.
A8: Price () | B8: The prices are Variable as per IEEMA formula with base date as on 01.11.2023.
A9: Validity () | B9: 120 days from the next date of opening of Tender.
A10: Delivery Period () | B10: 1st lot 2nd lot 3rd lot 4th lot 5th lot 6th lot 1.1 KV Copper Control Cable 4 Core x 2.5 sq. mm. 10 KM 10 KM 10 KM 10 KM 10 KM 10 KM 1.1 KV Copper Control Cable 8 Core x 2.5 sq. mm. 14 KMS 13 KMS 13 KMS 1.1 KV Copper Control Cable 12 Core x 2.5 sq. mm. 14 KMS 13 KMS 13 KMS 1.1 KV PVC Insulated Cable 2 Core x 6sq. mm. 68 KMS 66 KMS 66 KMS 180days against the item no(i) and 90 days against the item no (ii), (iii) and (iv) from the next date of issuance of order
A11: Payment Terms () | B11: 90% payment inclusive of Price Variation bill, along with 100% taxes and duties will be made within 45 (forty five) days from the date of submission of bill against : • Original receipted Challan/Invoice signed by an officer in the rank of Superintending Engineer/Asstt. Manager/Jr. Manager(Stores) attached to the respective stores. And • Report for in-house testing, if done after delivery of the items at different site stores signed by the Engineers of Dist. Testing Department. • Balance 10% payment will be made within 45 (forty five) days of submission of bills along with SRV.
A12: Standard length () | B12: The Cables shall be supplied in Drum lengths of 500 Mtr.
A13: Packing () | B13: The Cables shall be wound on a drum ( Ref. IS : 10418-1972 and its amendments) of suitable size and packed . The ends of cable shall be sealed by means of non-hygroscopic sealing material. The Cables shall be packed in non-returnable wooden drums. The wooden drums should be bearing distinguishing number with following information duly stenciled on the outer side of one flange.
A14: Technical Specification
D16: AVG NOVEMBER 2023 | N16: =Sheet1!J1 -> Conductor | S16: AL ALLOY | U16: Insulation Screening (Metallic) | AC16: Insulation Screening (Non-Metallic) | AE16: Insulation | AK16: POLY TAPE | AL16: Inner Sheath | AS16: Armouring | BC16: Outer Sheath | BM16: FILLER | BN16: GREASE | BO16: Water swellable Tape | BP16: Semi conducting Water Swellable tape | BQ16: SEMICON TAPE | BR16: GLASS FIBER TAPE | BS16: COPPER WIRE 0.8 MM | BT16: RUBBERIZED COTTON TAPE | BU16: Water Tight Compound | BZ16: DRUM COST PER KM | CA16: TOTAL RM COST | CB16: EXTRA CONSUMPTION | CC16: EXTRA CONSUMPTION VALUE
A17: DOCKET NO. | B17: =Sheet1!B1 -> Base Date | C17: ITEM CODE | D17: PROPOSE ERP ITEM NAME | E17: EX-WORKS (PER KM) | F17: FREIGHT PER KM | G17: PRICE INCLUDING FREIGHT (PER KM) | H17: GST % | I17: GST VALUE | J17: PRICE INCLUDING GST & FREIGHT (PER KM) | K17: QTY | L17: Unit | M17: TOTAL PRICE OF FULL QTY (INCLUDING FRIGHT & GST) | N17: Alumimium | O17: Alumimium ALLOY | P17: Copper | Q17: Flexible Copper | R17: Galvanized steel wire | S17: Alumimium | T17: Alumimium ALLOY | U17: Coper tape - 0.1 mm | V17: Copper Tape - 0.03 mm | W17: Copper Tape - 0.035 mm | X17: Copper Tape - 0.04 mm | Y17: Copper Tape - 0.045 mm | Z17: Copper Tape - 0.050 mm | AA17: Copper Tape - 0.060 mm | AB17: Copper Tape - 0.075 mm(DOUBLE) | AC17: Extruded semiconductive | AD17: Extruded Semiconductive(Stripable) | AE17: HT-XLPE | AF17: LT-XLPE | AG17: TR XLPE | AH17: Type A PVC | AI17: Type C PVC (HR) | AJ17: XLPE | AK17: POLY TAPE | AL17: FR PVC Type ST-1 | AM17: FR PVC Type ST-2 | AN17: FRLSH PVC Type ST-2 | AO17: PVC Type ST-1 | AP17: PVC Type ST-1-PRESSURE EXTRUDED | AQ17: PVC Type ST-2 | AR17: PVC Type ST-2-PRESSURE EXTRUDED | AS17: ACSR CORE WIRE | AT17: ACSR DOG STEEL WIRE | AU17: Aluminium Flat Strip | AV17: Aluminium Round Wire | AW17: Double Steel Tape | AX17: Galvanised Steel Flat Strip | AY17: Galvanised Steel Flat Strip (Double) | AZ17: Galvanised Steel Flat Strip-B | BA17: Galvanised Steel Round Wire | BB17: Galvanised Steel Round Wire (Double) | BC17: FR PVC Type ST-1 | BD17: FR PVC Type ST-2 | BE17: FRLSH PVC Type ST-1 | BF17: FRLSH PVC Type ST-2 | BG17: PE, ST-3 | BH17: PE, ST-7 | BI17: PVC Type ST-1 | BJ17: PVC Type ST-2 | BK17: PVC Type ST-2-PRESSURE EXTRUDED | BL17: UV & Track Resistant XLPE | BM17: FILLER | BN17: Grease | BO17: Water swellable Tape | BP17: Semi conducting Water Swellable tape | BQ17: SEMICON TAPE | BR17: GLASS FIBER TAPE | BS17: COPPER WIRE 0.8 MM | BT17: RUBBERIZED COTTON TAPE | BU17: Water Tight Compound | BV17: =Sheet1!E1 -> PROPOSE DRUM TYPE | BW17: =Sheet1!CV1 -> DRUM CODE | BX17: =Sheet1!CW1 -> DRUM SIZE (FxbXtx Ft) | BY17: =Sheet1!CX1 -> PARTY STANDARD LENGTH (MTR) | CD17: MFG% | CE17: MFG VALUE | CF17: PROF% | CG17: PROFIT VALUE | CH17: 1ST EX-WORKS | CI17: Intt % | CJ17: INTT VALUE | CK17: insp% | CL17: INSP VALUE
N18: 215 | P18: 735 | AH18: 71 | AI18: 101 | AK18: 123 | AM18: 93 | AO18: 58 | BA18: 88 | BF18: 92 | BI18: 58 | BJ18: =+IFERROR(VLOOKUP($BJ$17,Sheet1!AL2:AO840,2,0),0) -> 0 | BK18: =+IFERROR(VLOOKUP($BK$17,Sheet1!AL2:AO840,2,0),0) -> 0 | BL18: =+IFERROR(VLOOKUP($BL$17,Sheet1!AL2:AO840,2,0),0) -> 0 | BM18: =+IFERROR(VLOOKUP($BM$17,Sheet1!AP2:AS840,2,0),0) -> 0 | BN18: =+IFERROR(VLOOKUP($BN$17,Sheet1!AT2:AW840,2,0),0) -> 0 | BO18: =+IFERROR(VLOOKUP($BO$17,Sheet1!AX2:BA840,2,0),0) -> 0 | BP18: =+IFERROR(VLOOKUP($BP$17,Sheet1!BB2:BE840,2,0),0) -> 0 | BQ18: =+IFERROR(VLOOKUP($BQ$17,Sheet1!BF2:BI840,2,0),0) -> 0 | BR18: =+IFERROR(VLOOKUP($BR$17,Sheet1!BJ2:BM840,2,0),0) -> 0 | BS18: =+IFERROR(VLOOKUP($BS$17,Sheet1!BN2:BQ840,2,0),0) -> 0 | BT18: =+IFERROR(VLOOKUP($BT$17,Sheet1!BR2:BU840,2,0),0) -> 0 | BU18: =+IFERROR(VLOOKUP($BU$17,Sheet1!BV2:BY840,2,0),0) -> 0
A19: =Sheet1!A4 -> ENQ-11584-22-23 | B19: =Sheet1!B4 -> 45231 | C19: =Sheet1!C4 -> FA0200011 | D19: =Sheet1!D4 -> 4 CORE X 2.5 SQ. MM. CU/ARD - WIRE (PVC) | E19: =CH19+CJ19+CL19 -> 124549.19 | F19: =ROUNDUP(M25,0) -> 1200 | G19: =E19+F19 -> 125749.19 | H19: =Sheet1!CP4 -> 0.18 | I19: =G19*H19 -> 22634.854 | J19: =G19+I19 -> 148384.05 | K19: =Sheet1!CS4 -> 60 | L19: =Sheet1!CT4 -> KMS | M19: =J19*K19 -> 8903042.8 | N19: =+IFERROR(VLOOKUP($N$17,Sheet1!J4:L4,3,0),0) -> 0 | O19: =+IFERROR(VLOOKUP($O$17,Sheet1!J4:L4,3,0),0) -> 0 | P19: =+IFERROR(VLOOKUP($P$17,Sheet1!J4:M4,3,0),0) -> 88.8 | Q19: =+IFERROR(VLOOKUP($Q$17,Sheet1!J4:M4,3,0),0) -> 0 | R19: =+IFERROR(VLOOKUP($R$17,Sheet1!J4:M4,3,0),0) -> 0 | S19: =+IFERROR(VLOOKUP($S$17,Sheet1!N4:Q4,3,0),0) -> 0 | T19: =+IFERROR(VLOOKUP($T$17,Sheet1!N4:Q4,3,0),0) -> 0 | U19: =+IFERROR(VLOOKUP($U$17,Sheet1!F4:I4,3,0),0) -> 0 | V19: =+IFERROR(VLOOKUP($V$17,Sheet1!F4:I4,3,0),0) -> 0 | W19: =+IFERROR(VLOOKUP($W$17,Sheet1!F4:I4,3,0),0) -> 0 | X19: =+IFERROR(VLOOKUP($X$17,Sheet1!F4:I4,3,0),0) -> 0 | Y19: =+IFERROR(VLOOKUP($Y$17,Sheet1!F4:I4,3,0),0) -> 0 | Z19: =+IFERROR(VLOOKUP($Z$17,Sheet1!F4:I4,3,0),0) -> 0 | AA19: =+IFERROR(VLOOKUP($AA$17,Sheet1!F4:I4,3,0),0) -> 0 | AB19: =+IFERROR(VLOOKUP($AB$17,Sheet1!F4:I4,3,0),0) -> 0 | AC19: =+IFERROR(VLOOKUP($AC$17,Sheet1!R4:U4,3,0),0) -> 0 | AD19: =+IFERROR(VLOOKUP($AD$17,Sheet1!R4:U4,2,0),0) -> 0 | AE19: =+IFERROR(VLOOKUP($AE$17,Sheet1!V4:Y4,3,0),0) -> 0 | AF19: =+IFERROR(VLOOKUP($AF$17,Sheet1!V4:Y4,3,0),0) -> 0 | AG19: =+IFERROR(VLOOKUP($AG$17,Sheet1!V4:Y4,3,0),0) -> 0 | AH19: =+IFERROR(VLOOKUP($AH$17,Sheet1!V4:Y4,3,0),0) -> 0 | AI19: =+IFERROR(VLOOKUP($AI$17,Sheet1!V4:Y4,3,0),0) -> 52 | AJ19: =+IFERROR(VLOOKUP($AJ$17,Sheet1!V4:Y4,3,0),0) -> 0 | AK19: =+IFERROR(VLOOKUP($AK$17,Sheet1!Z4:AB4,3,0),0) -> 3 | AL19: =+IFERROR(VLOOKUP($AL$17,Sheet1!AD4:AG4,3,0),0) -> 0 | AM19: 27 | AN19: =+IFERROR(VLOOKUP($AN$17,Sheet1!AD4:AG4,3,0),0) -> 0 | AO19: =+IFERROR(VLOOKUP($AO$17,Sheet1!AD4:AG4,3,0),0) -> 0 | AP19: =+IFERROR(VLOOKUP($AP$17,Sheet1!AD4:AG4,3,0),0) -> 0 | AQ19: 0 | AR19: =+IFERROR(VLOOKUP($AR$17,Sheet1!AD4:AG4,3,0),0) -> 0 | AS19: =+IFERROR(VLOOKUP($AS$17,Sheet1!AH4:AK4,3,0),0) -> 0 | AT19: =+IFERROR(VLOOKUP($AT$17,Sheet1!AH4:AK4,3,0),0) -> 0 | AU19: =+IFERROR(VLOOKUP($AU$17,Sheet1!AH4:AK4,3,0),0) -> 0 | AV19: =+IFERROR(VLOOKUP($AV$17,Sheet1!AH4:AK4,3,0),0) -> 0 | AW19: =+IFERROR(VLOOKUP($AW$17,Sheet1!AH4:AK4,3,0),0) -> 0 | AX19: =+IFERROR(VLOOKUP($AX$17,Sheet1!AH4:AK4,3,0),0) -> 0 | AY19: =+IFERROR(VLOOKUP($AY$17,Sheet1!AH4:AK4,3,0),0) -> 0 | AZ19: =+IFERROR(VLOOKUP($AZ$17,Sheet1!AH4:AK4,3,0),0) -> 0 | BA19: =+IFERROR(VLOOKUP($BA$17,Sheet1!AH4:AK4,3,0),0) -> 289 | BB19: =+IFERROR(VLOOKUP($BB$17,Sheet1!AH4:AK4,3,0),0) -> 0 | BC19: =+IFERROR(VLOOKUP($BC$17,Sheet1!AL4:AO4,3,0),0) -> 0 | BD19: =+IFERROR(VLOOKUP($BD$17,Sheet1!AL4:AO4,3,0),0) -> 0 | BE19: =+IFERROR(VLOOKUP($BE$17,Sheet1!AL4:AO4,3,0),0) -> 0 | BF19: =+IFERROR(VLOOKUP($BF$17,Sheet1!AL4:AO4,3,0),0) -> 104 | BG19: =+IFERROR(VLOOKUP($BG$17,Sheet1!AL4:AO4,3,0),0) -> 0 | BH19: =+IFERROR(VLOOKUP($BH$17,Sheet1!AL4:AO4,3,0),0) -> 0 | BI19: =+IFERROR(VLOOKUP($BI$17,Sheet1!AL4:AO4,3,0),0) -> 0 | BJ19: =+IFERROR(VLOOKUP($BJ$17,Sheet1!AL4:AO4,3,0),0) -> 0 | BK19: =+IFERROR(VLOOKUP($BK$17,Sheet1!AL4:AO4,3,0),0) -> 0 | BL19: =+IFERROR(VLOOKUP($BL$17,Sheet1!AL4:AO4,3,0),0) -> 0 | BM19: =+IFERROR(VLOOKUP($BM$17,Sheet1!AP4:AS4,3,0),0) -> 0 | BN19: =+IFERROR(VLOOKUP($BN$17,Sheet1!AT4:AW4,3,0),0) -> 0 | BO19: =+IFERROR(VLOOKUP($BO$17,Sheet1!AX4:BA4,3,0),0) -> 0 | BP19: =+IFERROR(VLOOKUP($BP$17,Sheet1!BB4:BE4,3,0),0) -> 0 | BQ19: =+IFERROR(VLOOKUP($BQ$17,Sheet1!BF4:BI4,3,0),0) -> 0 | BR19: =+IFERROR(VLOOKUP($BR$17,Sheet1!BJ4:BM4,3,0),0) -> 0 | BS19: =+IFERROR(VLOOKUP($BS$17,Sheet1!BN4:BQ4,3,0),0) -> 0 | BT19: =+IFERROR(VLOOKUP($BT$17,Sheet1!BR4:BU4,3,0),0) -> 0 | BU19: =+IFERROR(VLOOKUP($BU$17,Sheet1!BV4:BY4,3,0),0) -> 0 | BV19: =Sheet1!E4 -> WOOD | BW19: =Sheet1!CV4 -> MD0100005 | BX19: =Sheet1!CW4 -> DRUM - 36 X 14 X 23 X 2 | BY19: 500 | BZ19: =Sheet1!BZ4 -> 4610.79 | CA19: =SUMPRODUCT($N$18:$BU$18,N19:BU19)+BZ19 -> 113010.79 | CB19: =Sheet1!CB4 -> 0 | CC19: =CA19*CB19 -> 0 | CD19: 0.07 | CE19: =CA19*CD19 -> 7910.7553 | CF19: 0 | CG19: =CA19*CF19 -> 0 | CH19: =CA19+CC19+CE19+CG19 -> 120921.55 | CI19: 0.02 | CJ19: =CH19*CI19 -> 2418.4309 | CK19: 0.01 | CL19: =CH19*CK19 -> 1209.2155
A20: =Sheet1!A3 -> ENQ-11584-22-23 | B20: =Sheet1!B3 -> 45231 | C20: =Sheet1!C3 -> FA0200019 | D20: =Sheet1!D3 -> 8 CORE X 2.5 SQ. MM. CU/ARD - WIRE (PVC) | E20: =CH20+CJ20+CL20 -> 217666.72 | F20: =ROUNDUP(M26,0) -> 1350 | G20: =E20+F20 -> 219016.72 | H20: =Sheet1!CP3 -> 0.18 | I20: =G20*H20 -> 39423.01 | J20: =G20+I20 -> 258439.73 | K20: =Sheet1!CS3 -> 40 | L20: =Sheet1!CT3 -> KMS | M20: =J20*K20 -> 10337589 | N20: =+IFERROR(VLOOKUP($N$17,Sheet1!J3:L3,3,0),0) -> 0 | O20: =+IFERROR(VLOOKUP($O$17,Sheet1!J3:L3,3,0),0) -> 0 | P20: 178 | Q20: =+IFERROR(VLOOKUP($Q$17,Sheet1!J3:M3,3,0),0) -> 0 | R20: =+IFERROR(VLOOKUP($R$17,Sheet1!J3:M3,3,0),0) -> 0 | S20: =+IFERROR(VLOOKUP($S$17,Sheet1!N3:Q3,3,0),0) -> 0 | T20: =+IFERROR(VLOOKUP($T$17,Sheet1!N3:Q3,3,0),0) -> 0 | U20: =+IFERROR(VLOOKUP($U$17,Sheet1!F3:I3,3,0),0) -> 0 | V20: =+IFERROR(VLOOKUP($V$17,Sheet1!F3:I3,3,0),0) -> 0 | W20: =+IFERROR(VLOOKUP($W$17,Sheet1!F3:I3,3,0),0) -> 0 | X20: =+IFERROR(VLOOKUP($X$17,Sheet1!F3:I3,3,0),0) -> 0 | Y20: =+IFERROR(VLOOKUP($Y$17,Sheet1!F3:I3,3,0),0) -> 0 | Z20: =+IFERROR(VLOOKUP($Z$17,Sheet1!F3:I3,3,0),0) -> 0 | AA20: =+IFERROR(VLOOKUP($AA$17,Sheet1!F3:I3,3,0),0) -> 0 | AB20: =+IFERROR(VLOOKUP($AB$17,Sheet1!F3:I3,3,0),0) -> 0 | AC20: =+IFERROR(VLOOKUP($AC$17,Sheet1!R3:U3,3,0),0) -> 0 | AD20: =+IFERROR(VLOOKUP($AD$17,Sheet1!R3:U3,2,0),0) -> 0 | AE20: =+IFERROR(VLOOKUP($AE$17,Sheet1!V3:Y3,3,0),0) -> 0 | AF20: =+IFERROR(VLOOKUP($AF$17,Sheet1!V3:Y3,3,0),0) -> 0 | AG20: =+IFERROR(VLOOKUP($AG$17,Sheet1!V3:Y3,3,0),0) -> 0 | AH20: =+IFERROR(VLOOKUP($AH$17,Sheet1!V3:Y3,3,0),0) -> 0 | AI20: 120 | AJ20: =+IFERROR(VLOOKUP($AJ$17,Sheet1!V3:Y3,3,0),0) -> 0 | AK20: 5 | AL20: =+IFERROR(VLOOKUP($AL$17,Sheet1!AD3:AG3,3,0),0) -> 0 | AM20: 34 | AN20: =+IFERROR(VLOOKUP($AN$17,Sheet1!AD3:AG3,3,0),0) -> 0 | AO20: =+IFERROR(VLOOKUP($AO$17,Sheet1!AD3:AG3,3,0),0) -> 0 | AP20: =+IFERROR(VLOOKUP($AP$17,Sheet1!AD3:AG3,3,0),0) -> 0 | AQ20: 0 | AR20: =+IFERROR(VLOOKUP($AR$17,Sheet1!AD3:AG3,3,0),0) -> 0 | AS20: =+IFERROR(VLOOKUP($AS$17,Sheet1!AH3:AK3,3,0),0) -> 0 | AT20: =+IFERROR(VLOOKUP($AT$17,Sheet1!AH3:AK3,3,0),0) -> 0 | AU20: =+IFERROR(VLOOKUP($AU$17,Sheet1!AH3:AK3,3,0),0) -> 0 | AV20: =+IFERROR(VLOOKUP($AV$17,Sheet1!AH3:AK3,3,0),0) -> 0 | AW20: =+IFERROR(VLOOKUP($AW$17,Sheet1!AH3:AK3,3,0),0) -> 0 | AX20: =+IFERROR(VLOOKUP($AX$17,Sheet1!AH3:AK3,3,0),0) -> 0 | AY20: =+IFERROR(VLOOKUP($AY$17,Sheet1!AH3:AK3,3,0),0) -> 0 | AZ20: =+IFERROR(VLOOKUP($AZ$17,Sheet1!AH3:AK3,3,0),0) -> 0 | BA20: 373 | BB20: =+IFERROR(VLOOKUP($BB$17,Sheet1!AH3:AK3,3,0),0) -> 0 | BC20: =+IFERROR(VLOOKUP($BC$17,Sheet1!AL3:AO3,3,0),0) -> 0 | BD20: =+IFERROR(VLOOKUP($BD$17,Sheet1!AL3:AO3,3,0),0) -> 0 | BE20: =+IFERROR(VLOOKUP($BE$17,Sheet1!AL3:AO3,3,0),0) -> 0 | BF20: 145 | BG20: =+IFERROR(VLOOKUP($BG$17,Sheet1!AL3:AO3,3,0),0) -> 0 | BH20: =+IFERROR(VLOOKUP($BH$17,Sheet1!AL3:AO3,3,0),0) -> 0 | BI20: =+IFERROR(VLOOKUP($BI$17,Sheet1!AL3:AO3,3,0),0) -> 0 | BJ20: =+IFERROR(VLOOKUP($BJ$17,Sheet1!AL3:AO3,3,0),0) -> 0 | BK20: =+IFERROR(VLOOKUP($BK$17,Sheet1!AL3:AO3,3,0),0) -> 0 | BL20: =+IFERROR(VLOOKUP($BL$17,Sheet1!AL3:AO3,3,0),0) -> 0 | BM20: =+IFERROR(VLOOKUP($BM$17,Sheet1!AP3:AS3,3,0),0) -> 0 | BN20: =+IFERROR(VLOOKUP($BN$17,Sheet1!AT3:AW3,3,0),0) -> 0 | BO20: =+IFERROR(VLOOKUP($BO$17,Sheet1!AX3:BA3,3,0),0) -> 0 | BP20: =+IFERROR(VLOOKUP($BP$17,Sheet1!BB3:BE3,3,0),0) -> 0 | BQ20: =+IFERROR(VLOOKUP($BQ$17,Sheet1!BF3:BI3,3,0),0) -> 0 | BR20: =+IFERROR(VLOOKUP($BR$17,Sheet1!BJ3:BM3,3,0),0) -> 0 | BS20: =+IFERROR(VLOOKUP($BS$17,Sheet1!BN3:BQ3,3,0),0) -> 0 | BT20: =+IFERROR(VLOOKUP($BT$17,Sheet1!BR3:BU3,3,0),0) -> 0 | BU20: =+IFERROR(VLOOKUP($BU$17,Sheet1!BV3:BY3,3,0),0) -> 0 | BV20: =Sheet1!E3 -> WOOD | BW20: =Sheet1!CV3 -> MD0100005 | BX20: =Sheet1!CW3 -> DRUM - 36 X 14 X 23 X 2 | BY20: 500 | BZ20: =Sheet1!BZ3 -> 4610.79 | CA20: =SUMPRODUCT($N$18:$BU$18,N20:BU20)+BZ20 -> 197501.79 | CB20: =Sheet1!CB3 -> 0 | CC20: =CA20*CB20 -> 0 | CD20: 0.07 | CE20: =CA20*CD20 -> 13825.125 | CF20: 0 | CG20: =CA20*CF20 -> 0 | CH20: =CA20+CC20+CE20+CG20 -> 211326.92 | CI20: 0.02 | CJ20: =CH20*CI20 -> 4226.5383 | CK20: 0.01 | CL20: =CH20*CK20 -> 2113.2692
A21: =Sheet1!A2 -> ENQ-11584-22-23 | B21: =Sheet1!B2 -> 45231 | C21: =Sheet1!C2 -> FA0200003 | D21: =Sheet1!D2 -> 12 CORE X 2.5 SQ. MM. CU/ARD - WIRE (PVC) | E21: =CH21+CJ21+CL21 -> 310256.01 | F21: =ROUNDUP(M27,0) -> 1350 | G21: =E21+F21 -> 311606.01 | H21: =Sheet1!CP2 -> 0.18 | I21: =G21*H21 -> 56089.081 | J21: =G21+I21 -> 367695.09 | K21: =Sheet1!CS2 -> 40 | L21: =Sheet1!CT2 -> KMS | M21: =J21*K21 -> 14707803 | N21: =+IFERROR(VLOOKUP($N$17,Sheet1!J2:L2,3,0),0) -> 0 | O21: =+IFERROR(VLOOKUP($O$17,Sheet1!J2:L2,3,0),0) -> 0 | P21: =+IFERROR(VLOOKUP($P$17,Sheet1!J2:M2,3,0),0) -> 266.4 | Q21: =+IFERROR(VLOOKUP($Q$17,Sheet1!J2:M2,3,0),0) -> 0 | R21: =+IFERROR(VLOOKUP($R$17,Sheet1!J2:M2,3,0),0) -> 0 | S21: =+IFERROR(VLOOKUP($S$17,Sheet1!N2:Q2,3,0),0) -> 0 | T21: =+IFERROR(VLOOKUP($T$17,Sheet1!N2:Q2,3,0),0) -> 0 | U21: =+IFERROR(VLOOKUP($U$17,Sheet1!F2:I2,3,0),0) -> 0 | V21: =+IFERROR(VLOOKUP($V$17,Sheet1!F2:I2,3,0),0) -> 0 | W21: =+IFERROR(VLOOKUP($W$17,Sheet1!F2:I2,3,0),0) -> 0 | X21: =+IFERROR(VLOOKUP($X$17,Sheet1!F2:I2,3,0),0) -> 0 | Y21: =+IFERROR(VLOOKUP($Y$17,Sheet1!F2:I2,3,0),0) -> 0 | Z21: =+IFERROR(VLOOKUP($Z$17,Sheet1!F2:I2,3,0),0) -> 0 | AA21: =+IFERROR(VLOOKUP($AA$17,Sheet1!F2:I2,3,0),0) -> 0 | AB21: =+IFERROR(VLOOKUP($AB$17,Sheet1!F2:I2,3,0),0) -> 0 | AC21: =+IFERROR(VLOOKUP($AC$17,Sheet1!R2:U2,3,0),0) -> 0 | AD21: =+IFERROR(VLOOKUP($AD$17,Sheet1!R2:U2,2,0),0) -> 0 | AE21: =+IFERROR(VLOOKUP($AE$17,Sheet1!V2:Y2,3,0),0) -> 0 | AF21: =+IFERROR(VLOOKUP($AF$17,Sheet1!V2:Y2,3,0),0) -> 0 | AG21: =+IFERROR(VLOOKUP($AG$17,Sheet1!V2:Y2,3,0),0) -> 0 | AH21: =+IFERROR(VLOOKUP($AH$17,Sheet1!V2:Y2,3,0),0) -> 0 | AI21: =+IFERROR(VLOOKUP($AI$17,Sheet1!V2:Y2,3,0),0) -> 156 | AJ21: =+IFERROR(VLOOKUP($AJ$17,Sheet1!V2:Y2,3,0),0) -> 0 | AK21: =+IFERROR(VLOOKUP($AK$17,Sheet1!Z2:AB2,3,0),0) -> 6 | AL21: =+IFERROR(VLOOKUP($AL$17,Sheet1!AD2:AG2,3,0),0) -> 0 | AM21: 40 | AN21: =+IFERROR(VLOOKUP($AN$17,Sheet1!AD2:AG2,3,0),0) -> 0 | AO21: =+IFERROR(VLOOKUP($AO$17,Sheet1!AD2:AG2,3,0),0) -> 0 | AP21: =+IFERROR(VLOOKUP($AP$17,Sheet1!AD2:AG2,3,0),0) -> 0 | AQ21: 0 | AR21: =+IFERROR(VLOOKUP($AR$17,Sheet1!AD2:AG2,3,0),0) -> 0 | AS21: =+IFERROR(VLOOKUP($AS$17,Sheet1!AH2:AK2,3,0),0) -> 0 | AT21: =+IFERROR(VLOOKUP($AT$17,Sheet1!AH2:AK2,3,0),0) -> 0 | AU21: =+IFERROR(VLOOKUP($AU$17,Sheet1!AH2:AK2,3,0),0) -> 0 | AV21: =+IFERROR(VLOOKUP($AV$17,Sheet1!AH2:AK2,3,0),0) -> 0 | AW21: =+IFERROR(VLOOKUP($AW$17,Sheet1!AH2:AK2,3,0),0) -> 0 | AX21: =+IFERROR(VLOOKUP($AX$17,Sheet1!AH2:AK2,3,0),0) -> 0 | AY21: =+IFERROR(VLOOKUP($AY$17,Sheet1!AH2:AK2,3,0),0) -> 0 | AZ21: =+IFERROR(VLOOKUP($AZ$17,Sheet1!AH2:AK2,3,0),0) -> 0 | BA21: =+IFERROR(VLOOKUP($BA$17,Sheet1!AH2:AK2,3,0),0) -> 508 | BB21: =+IFERROR(VLOOKUP($BB$17,Sheet1!AH2:AK2,3,0),0) -> 0 | BC21: =+IFERROR(VLOOKUP($BC$17,Sheet1!AL2:AO2,3,0),0) -> 0 | BD21: =+IFERROR(VLOOKUP($BD$17,Sheet1!AL2:AO2,3,0),0) -> 0 | BE21: =+IFERROR(VLOOKUP($BE$17,Sheet1!AL2:AO2,3,0),0) -> 0 | BF21: =+IFERROR(VLOOKUP($BF$17,Sheet1!AL2:AO2,3,0),0) -> 170 | BG21: =+IFERROR(VLOOKUP($BG$17,Sheet1!AL2:AO2,3,0),0) -> 0 | BH21: =+IFERROR(VLOOKUP($BH$17,Sheet1!AL2:AO2,3,0),0) -> 0 | BI21: =+IFERROR(VLOOKUP($BI$17,Sheet1!AL2:AO2,3,0),0) -> 0 | BJ21: =+IFERROR(VLOOKUP($BJ$17,Sheet1!AL2:AO2,3,0),0) -> 0 | BK21: =+IFERROR(VLOOKUP($BK$17,Sheet1!AL2:AO2,3,0),0) -> 0 | BL21: =+IFERROR(VLOOKUP($BL$17,Sheet1!AL2:AO2,3,0),0) -> 0 | BM21: =+IFERROR(VLOOKUP($BM$17,Sheet1!AP2:AS2,3,0),0) -> 0 | BN21: =+IFERROR(VLOOKUP($BN$17,Sheet1!AT2:AW2,3,0),0) -> 0 | BO21: =+IFERROR(VLOOKUP($BO$17,Sheet1!AX2:BA2,3,0),0) -> 0 | BP21: =+IFERROR(VLOOKUP($BP$17,Sheet1!BB2:BE2,3,0),0) -> 0 | BQ21: =+IFERROR(VLOOKUP($BQ$17,Sheet1!BF2:BI2,3,0),0) -> 0 | BR21: =+IFERROR(VLOOKUP($BR$17,Sheet1!BJ2:BM2,3,0),0) -> 0 | BS21: =+IFERROR(VLOOKUP($BS$17,Sheet1!BN2:BQ2,3,0),0) -> 0 | BT21: =+IFERROR(VLOOKUP($BT$17,Sheet1!BR2:BU2,3,0),0) -> 0 | BU21: =+IFERROR(VLOOKUP($BU$17,Sheet1!BV2:BY2,3,0),0) -> 0 | BV21: =Sheet1!E2 -> WOOD | BW21: =Sheet1!CV2 -> MD0100066 | BX21: =Sheet1!CW2 -> DRUM - 40 X 15 X 23 X 2 | BY21: 500 | BZ21: =Sheet1!BZ2 -> 5151.48 | CA21: =SUMPRODUCT($N$18:$BU$18,N21:BU21)+BZ21 -> 281513.48 | CB21: =Sheet1!CB2 -> 0 | CC21: =CA21*CB21 -> 0 | CD21: 0.07 | CE21: =CA21*CD21 -> 19705.944 | CF21: 0 | CG21: =CA21*CF21 -> 0 | CH21: =CA21+CC21+CE21+CG21 -> 301219.42 | CI21: 0.02 | CJ21: =CH21*CI21 -> 6024.3885 | CK21: 0.01 | CL21: =CH21*CK21 -> 3012.1942
A22: =Sheet1!A5 -> ENQ-11584-22-23 | B22: =Sheet1!B5 -> 45231 | C22: =Sheet1!C5 -> FA1000002 | D22: =Sheet1!D5 -> 2 CORE X 6 SQ. MM. AL/UNARD (PVC) | E22: =CH22+CJ22+CL22 -> 26256.078 | F22: =ROUNDUP(M28,0) -> 450 | G22: =E22+F22 -> 26706.078 | H22: =Sheet1!CP5 -> 0.18 | I22: =G22*H22 -> 4807.094 | J22: =G22+I22 -> 31513.172 | K22: =Sheet1!CS5 -> 200 | L22: =Sheet1!CT5 -> KMS | M22: =J22*K22 -> 6302634.3 | N22: =+IFERROR(VLOOKUP($N$17,Sheet1!J5:L5,3,0),0) -> 32.4 | O22: =+IFERROR(VLOOKUP($O$17,Sheet1!J5:L5,3,0),0) -> 0 | P22: =+IFERROR(VLOOKUP($P$17,Sheet1!J5:M5,3,0),0) -> 0 | Q22: =+IFERROR(VLOOKUP($Q$17,Sheet1!J5:M5,3,0),0) -> 0 | R22: =+IFERROR(VLOOKUP($R$17,Sheet1!J5:M5,3,0),0) -> 0 | S22: =+IFERROR(VLOOKUP($S$17,Sheet1!N5:Q5,3,0),0) -> 0 | T22: =+IFERROR(VLOOKUP($T$17,Sheet1!N5:Q5,3,0),0) -> 0 | U22: =+IFERROR(VLOOKUP($U$17,Sheet1!F5:I5,3,0),0) -> 0 | V22: =+IFERROR(VLOOKUP($V$17,Sheet1!F5:I5,3,0),0) -> 0 | W22: =+IFERROR(VLOOKUP($W$17,Sheet1!F5:I5,3,0),0) -> 0 | X22: =+IFERROR(VLOOKUP($X$17,Sheet1!F5:I5,3,0),0) -> 0 | Y22: =+IFERROR(VLOOKUP($Y$17,Sheet1!F5:I5,3,0),0) -> 0 | Z22: =+IFERROR(VLOOKUP($Z$17,Sheet1!F5:I5,3,0),0) -> 0 | AA22: =+IFERROR(VLOOKUP($AA$17,Sheet1!F5:I5,3,0),0) -> 0 | AB22: =+IFERROR(VLOOKUP($AB$17,Sheet1!F5:I5,3,0),0) -> 0 | AC22: =+IFERROR(VLOOKUP($AC$17,Sheet1!R5:U5,3,0),0) -> 0 | AD22: =+IFERROR(VLOOKUP($AD$17,Sheet1!R5:U5,2,0),0) -> 0 | AE22: =+IFERROR(VLOOKUP($AE$17,Sheet1!V5:Y5,3,0),0) -> 0 | AF22: =+IFERROR(VLOOKUP($AF$17,Sheet1!V5:Y5,3,0),0) -> 0 | AG22: =+IFERROR(VLOOKUP($AG$17,Sheet1!V5:Y5,3,0),0) -> 0 | AH22: =+IFERROR(VLOOKUP($AH$17,Sheet1!V5:Y5,3,0),0) -> 40 | AI22: =+IFERROR(VLOOKUP($AI$17,Sheet1!V5:Y5,3,0),0) -> 0 | AJ22: =+IFERROR(VLOOKUP($AJ$17,Sheet1!V5:Y5,3,0),0) -> 0 | AK22: =+IFERROR(VLOOKUP($AK$17,Sheet1!Z5:AB5,3,0),0) -> 0 | AL22: =+IFERROR(VLOOKUP($AL$17,Sheet1!AD5:AG5,3,0),0) -> 0 | AM22: =+IFERROR(VLOOKUP($AM$17,Sheet1!AD5:AG5,3,0),0) -> 0 | AN22: =+IFERROR(VLOOKUP($AN$17,Sheet1!AD5:AG5,3,0),0) -> 0 | AO22: =+IFERROR(VLOOKUP($AO$17,Sheet1!AD5:AG5,3,0),0) -> 68 | AP22: =+IFERROR(VLOOKUP($AP$17,Sheet1!AD5:AG5,3,0),0) -> 0 | AQ22: =+IFERROR(VLOOKUP($AQ$17,Sheet1!AD5:AG5,3,0),0) -> 0 | AR22: =+IFERROR(VLOOKUP($AR$17,Sheet1!AD5:AG5,3,0),0) -> 0 | AS22: =+IFERROR(VLOOKUP($AS$17,Sheet1!AH5:AK5,3,0),0) -> 0 | AT22: =+IFERROR(VLOOKUP($AT$17,Sheet1!AH5:AK5,3,0),0) -> 0 | AU22: =+IFERROR(VLOOKUP($AU$17,Sheet1!AH5:AK5,3,0),0) -> 0 | AV22: =+IFERROR(VLOOKUP($AV$17,Sheet1!AH5:AK5,3,0),0) -> 0 | AW22: =+IFERROR(VLOOKUP($AW$17,Sheet1!AH5:AK5,3,0),0) -> 0 | AX22: =+IFERROR(VLOOKUP($AX$17,Sheet1!AH5:AK5,3,0),0) -> 0 | AY22: =+IFERROR(VLOOKUP($AY$17,Sheet1!AH5:AK5,3,0),0) -> 0 | AZ22: =+IFERROR(VLOOKUP($AZ$17,Sheet1!AH5:AK5,3,0),0) -> 0 | BA22: =+IFERROR(VLOOKUP($BA$17,Sheet1!AH5:AK5,3,0),0) -> 0 | BB22: =+IFERROR(VLOOKUP($BB$17,Sheet1!AH5:AK5,3,0),0) -> 0 | BC22: =+IFERROR(VLOOKUP($BC$17,Sheet1!AL5:AO5,3,0),0) -> 0 | BD22: =+IFERROR(VLOOKUP($BD$17,Sheet1!AL5:AO5,3,0),0) -> 0 | BE22: =+IFERROR(VLOOKUP($BE$17,Sheet1!AL5:AO5,3,0),0) -> 0 | BF22: =+IFERROR(VLOOKUP($BF$17,Sheet1!AL5:AO5,3,0),0) -> 0 | BG22: =+IFERROR(VLOOKUP($BG$17,Sheet1!AL5:AO5,3,0),0) -> 0 | BH22: =+IFERROR(VLOOKUP($BH$17,Sheet1!AL5:AO5,3,0),0) -> 0 | BI22: =+IFERROR(VLOOKUP($BI$17,Sheet1!AL5:AO5,3,0),0) -> 109 | BJ22: =+IFERROR(VLOOKUP($BJ$17,Sheet1!AL5:AO5,3,0),0) -> 0 | BK22: =+IFERROR(VLOOKUP($BK$17,Sheet1!AL5:AO5,3,0),0) -> 0 | BL22: =+IFERROR(VLOOKUP($BL$17,Sheet1!AL5:AO5,3,0),0) -> 0 | BM22: =+IFERROR(VLOOKUP($BM$17,Sheet1!AP5:AS5,3,0),0) -> 0 | BN22: =+IFERROR(VLOOKUP($BN$17,Sheet1!AT5:AW5,3,0),0) -> 0 | BO22: =+IFERROR(VLOOKUP($BO$17,Sheet1!AX5:BA5,3,0),0) -> 0 | BP22: =+IFERROR(VLOOKUP($BP$17,Sheet1!BB5:BE5,3,0),0) -> 0 | BQ22: =+IFERROR(VLOOKUP($BQ$17,Sheet1!BF5:BI5,3,0),0) -> 0 | BR22: =+IFERROR(VLOOKUP($BR$17,Sheet1!BJ5:BM5,3,0),0) -> 0 | BS22: =+IFERROR(VLOOKUP($BS$17,Sheet1!BN5:BQ5,3,0),0) -> 0 | BT22: =+IFERROR(VLOOKUP($BT$17,Sheet1!BR5:BU5,3,0),0) -> 0 | BU22: =+IFERROR(VLOOKUP($BU$17,Sheet1!BV5:BY5,3,0),0) -> 0 | BV22: =Sheet1!E5 -> WOOD | BW22: =Sheet1!CV5 -> MD0100004 | BX22: =Sheet1!CW5 -> DRUM - 28 X 10 X 23 X 2 | BY22: 500 | BZ22: =Sheet1!BZ5 -> 3751.68 | CA22: =SUMPRODUCT($N$18:$BU$18,N22:BU22)+BZ22 -> 23823.68 | CB22: =Sheet1!CB5 -> 0 | CC22: =CA22*CB22 -> 0 | CD22: 0.07 | CE22: =CA22*CD22 -> 1667.6576 | CF22: 0 | CG22: =CA22*CF22 -> 0 | CH22: =CA22+CC22+CE22+CG22 -> 25491.338 | CI22: 0.02 | CJ22: =CH22*CI22 -> 509.82675 | CK22: 0.01 | CL22: =CH22*CK22 -> 254.91338
E24: Order Quantity | F24: Stnd Length | G24: Truck type | H24: Fare of one truck | I24: No of Drum in one truck | J24: Total length in one Truck | K24: No of Truck | L24: Total Freight | M24: Freight per KM
D25: =D19 -> 4 CORE X 2.5 SQ. MM. CU/ARD - WIRE (PVC) | E25: =K19 -> 60 | F25: 0.5 | G25: 16 MT | H25: 18000 | I25: 36 | J25: =F25*I25 -> 18 | K25: =ROUNDUP((E25/J25),0) -> 4 | L25: =M25*E25 -> 72000 | M25: =(H25*K25)/E25 -> 1200
D26: =D20 -> 8 CORE X 2.5 SQ. MM. CU/ARD - WIRE (PVC) | E26: =K20 -> 40 | F26: 0.5 | G26: 16 MT | H26: 18000 | I26: 27 | J26: =F26*I26 -> 13.5 | K26: =ROUNDUP((E26/J26),0) -> 3 | L26: =M26*E26 -> 54000 | M26: =(H26*K26)/E26 -> 1350
D27: =D21 -> 12 CORE X 2.5 SQ. MM. CU/ARD - WIRE (PVC) | E27: =K21 -> 40 | F27: 0.5 | G27: 16 MT | H27: 18000 | I27: 27 | J27: =F27*I27 -> 13.5 | K27: =ROUNDUP((E27/J27),0) -> 3 | L27: =M27*E27 -> 54000 | M27: =(H27*K27)/E27 -> 1350
D28: =D22 -> 2 CORE X 6 SQ. MM. AL/UNARD (PVC) | E28: =K22 -> 200 | F28: 0.5 | G28: 16 MT | H28: 18000 | I28: 80 | J28: =F28*I28 -> 40 | K28: =ROUNDUP((E28/J28),0) -> 5 | L28: =M28*E28 -> 90000 | M28: =(H28*K28)/E28 -> 450
I29: CONFIRMED FROM SOMBHU SIR OVERPHONE in last docket 10689

Sheet Cable
A1: West Bengal State Electricity Distribution Company (WBSEDCL)
A3: Base Date | B3: 45231
B4: The price is Variable as per PV Formula of IEEMA with base date 01.11.2023.
A5: CuF | B5: Variation Factor For Aluminium Rod
A6: CCFCu | B6: Variation factor for PVC compound.
A7: For unarmoued control cables FeF = 0
A9: Item | B9: Calculation part | C9: Date of Inspection | D9: Applicable Date | H9: BASE DATE | L9: FACTORS | O9: Ex-Work Po | P9: PVC of Cu/Alf | Q9: PVC of PVC | R9: PVC of FE | S9: PV/PKM | T9: Billing Price/PKM | U9: VALUE ADDITION CALCULATION
D10: Date | E10: Cu/Al | F10: PVC | G10: Fe | H10: Date | I10: Cuo/Alo | J10: PVCo | K10: Feo
L11: CuF/AIF | M11: CCFCu | N11: FeF | U11: Alumimium | V11: Copper | W11: Type A PVC | X11: Type C PVC (HR) | Y11: POLY TAPE | Z11: ='AUTO CALCULATION SHEET (2)'!AM17 -> FR PVC Type ST-2 | AA11: PVC Type ST-1 | AB11: Galvanised Steel Round Wire | AC11: FRLSH PVC Type ST-2 | AD11: PVC Type ST-1 | AE11: RMC | AF11: Drum | AG11: RMC+Drum | AH11: VA | AI11: Gross VA% | AJ11: Mfg % | AK11: Int % | AL11: Ins% | AM11: Net VA
U12: 211 | V12: 751 | W12: 72 | X12: 102 | Y12: 123 | Z12: 95 | AA12: 59 | AB12: 87 | AC12: 94 | AD12: 59
A13: ='AUTO CALCULATION SHEET (2)'!D19 -> 4 CORE X 2.5 SQ. MM. CU/ARD - WIRE (PVC) | C13: Provisional | D13: 45267 | E13: 757901.46 | F13: 150825 | G13: 77250 | H13: =$B$3 -> 45231 | I13: 738675 | J13: 150825 | K13: 77250 | L13: 0.094 | M13: 0.179 | N13: 0.314 | O13: ='AUTO CALCULATION SHEET (2)'!E19 -> 124549.19 | P13: =(L13*(E13-I13)) -> 1807.2872 | Q13: =(M13*(F13-J13)) -> 0 | R13: =(N13*(G13-K13)) -> 0 | S13: =P13+Q13+R13 -> 1807.2872 | T13: =+O13+S13 -> 126356.48 | U13: ='AUTO CALCULATION SHEET (2)'!N19 -> 0 | V13: ='AUTO CALCULATION SHEET (2)'!P19 -> 88.8 | W13: ='AUTO CALCULATION SHEET (2)'!AH19 -> 0 | X13: ='AUTO CALCULATION SHEET (2)'!AI19 -> 52 | Y13: ='AUTO CALCULATION SHEET (2)'!AK19 -> 3 | Z13: ='AUTO CALCULATION SHEET (2)'!AM19 -> 27 | AA13: ='AUTO CALCULATION SHEET (2)'!AO19 -> 0 | AB13: ='AUTO CALCULATION SHEET (2)'!BA19 -> 289 | AC13: ='AUTO CALCULATION SHEET (2)'!BF19 -> 104 | AD13: ='AUTO CALCULATION SHEET (2)'!BI19 -> 0 | AE13: =SUMPRODUCT(U13:AD13,$U$12:$AD$12) -> 109845.8 | AF13: ='AUTO CALCULATION SHEET (2)'!BZ19 -> 4610.79 | AG13: =AE13+AF13 -> 114456.59 | AH13: =T13-AG13 -> 11899.889 | AI13: =ROUND((AH13/AG13)*100,2) -> 10.4 | AJ13: 0 | AK13: 2 | AL13: 1 | AM13: =AI13-AJ13-AK13-AL13 -> 7.4
A14: ='AUTO CALCULATION SHEET (2)'!D20 -> 8 CORE X 2.5 SQ. MM. CU/ARD - WIRE (PVC) | C14: Provisional | D14: 45267 | E14: 757901.46 | F14: 150825 | G14: 77250 | H14: =$B$3 -> 45231 | I14: 738675 | J14: 150825 | K14: 77250 | L14: 0.182 | M14: 0.325 | N14: 0.456 | O14: ='AUTO CALCULATION SHEET (2)'!E20 -> 217666.72 | P14: =(L14*(E14-I14)) -> 3499.2157 | Q14: =(M14*(F14-J14)) -> 0 | R14: =(N14*(G14-K14)) -> 0 | S14: =P14+Q14+R14 -> 3499.2157 | T14: =+O14+S14 -> 221165.94 | U14: ='AUTO CALCULATION SHEET (2)'!N20 -> 0 | V14: ='AUTO CALCULATION SHEET (2)'!P20 -> 178 | W14: ='AUTO CALCULATION SHEET (2)'!AH20 -> 0 | X14: ='AUTO CALCULATION SHEET (2)'!AI20 -> 120 | Y14: ='AUTO CALCULATION SHEET (2)'!AK20 -> 5 | Z14: ='AUTO CALCULATION SHEET (2)'!AM20 -> 34 | AA14: ='AUTO CALCULATION SHEET (2)'!AO20 -> 0 | AB14: ='AUTO CALCULATION SHEET (2)'!BA20 -> 373 | AC14: ='AUTO CALCULATION SHEET (2)'!BF20 -> 145 | AD14: ='AUTO CALCULATION SHEET (2)'!BI20 -> 0 | AE14: =SUMPRODUCT(U14:AD14,$U$12:$AD$12) -> 195844 | AF14: ='AUTO CALCULATION SHEET (2)'!BZ20 -> 4610.79 | AG14: =AE14+AF14 -> 200454.79 | AH14: =T14-AG14 -> 20711.148 | AI14: =ROUND((AH14/AG14)*100,2) -> 10.33 | AJ14: 0 | AK14: 2 | AL14: 1 | AM14: =AI14-AJ14-AK14-AL14 -> 7.33
A15: ='AUTO CALCULATION SHEET (2)'!D21 -> 12 CORE X 2.5 SQ. MM. CU/ARD - WIRE (PVC) | C15: Provisional | D15: 45267 | E15: 757901.46 | F15: 150825 | G15: 76750 | H15: =$B$3 -> 45231 | I15: 738675 | J15: 150825 | K15: 76750 | L15: 0.282 | M15: 0.371 | N15: 0.572 | O15: ='AUTO CALCULATION SHEET (2)'!E21 -> 310256.01 | P15: =(L15*(E15-I15)) -> 5421.8617 | Q15: =(M15*(F15-J15)) -> 0 | R15: =(N15*(G15-K15)) -> 0 | S15: =P15+Q15+R15 -> 5421.8617 | T15: =+O15+S15 -> 315677.87 | U15: ='AUTO CALCULATION SHEET (2)'!N21 -> 0 | V15: ='AUTO CALCULATION SHEET (2)'!P21 -> 266.4 | W15: ='AUTO CALCULATION SHEET (2)'!AH21 -> 0 | X15: ='AUTO CALCULATION SHEET (2)'!AI21 -> 156 | Y15: ='AUTO CALCULATION SHEET (2)'!AK21 -> 6 | Z15: ='AUTO CALCULATION SHEET (2)'!AM21 -> 40 | AA15: ='AUTO CALCULATION SHEET (2)'!AO21 -> 0 | AB15: ='AUTO CALCULATION SHEET (2)'!BA21 -> 508 | AC15: ='AUTO CALCULATION SHEET (2)'!BF21 -> 170 | AD15: ='AUTO CALCULATION SHEET (2)'!BI21 -> 0 | AE15: =SUMPRODUCT(U15:AD15,$U$12:$AD$12) -> 280692.4 | AF15: ='AUTO CALCULATION SHEET (2)'!BZ21 -> 5151.48 | AG15: =AE15+AF15 -> 285843.88 | AH15: =T15-AG15 -> 29833.988 | AI15: =ROUND((AH15/AG15)*100,2) -> 10.44 | AJ15: 0 | AK15: 2 | AL15: 1 | AM15: =AI15-AJ15-AK15-AL15 -> 7.44
A16: ='AUTO CALCULATION SHEET (2)'!D22 -> 2 CORE X 6 SQ. MM. AL/UNARD (PVC) | C16: Provisional | D16: 45267 | E16: 204174.48 | F16: 150825 | H16: =$B$3 -> 45231 | I16: 212415 | J16: 150825 | L16: 0.034 | M16: 0.154 | O16: ='AUTO CALCULATION SHEET (2)'!E22 -> 26256.078 | P16: =(L16*(E16-I16)) -> -280.17768 | Q16: =(M16*(F16-J16)) -> 0 | R16: =(N16*(G16-K16)) -> 0 | S16: =P16+Q16+R16 -> -280.17768 | T16: =+O16+S16 -> 25975.9 | U16: ='AUTO CALCULATION SHEET (2)'!N22 -> 32.4 | V16: ='AUTO CALCULATION SHEET (2)'!P22 -> 0 | W16: ='AUTO CALCULATION SHEET (2)'!AH22 -> 40 | X16: ='AUTO CALCULATION SHEET (2)'!AI22 -> 0 | Y16: ='AUTO CALCULATION SHEET (2)'!AK22 -> 0 | Z16: ='AUTO CALCULATION SHEET (2)'!AM22 -> 0 | AA16: ='AUTO CALCULATION SHEET (2)'!AO22 -> 68 | AB16: ='AUTO CALCULATION SHEET (2)'!BA22 -> 0 | AC16: ='AUTO CALCULATION SHEET (2)'!BF22 -> 0 | AD16: ='AUTO CALCULATION SHEET (2)'!BI22 -> 109 | AE16: =SUMPRODUCT(U16:AD16,$U$12:$AD$12) -> 20159.4 | AF16: ='AUTO CALCULATION SHEET (2)'!BZ22 -> 3751.68 | AG16: =AE16+AF16 -> 23911.08 | AH16: =T16-AG16 -> 2064.82 | AI16: =ROUND((AH16/AG16)*100,2) -> 8.64 | AJ16: 0 | AK16: 2 | AL16: 1 | AM16: =AI16-AJ16-AK16-AL16 -> 5.64
