Workbook

Sheet Sheet1
A1: DOCKET NO. | B1: Base Date | C1: ITEM CODE | D1: PROPOSE ERP ITEM NAME | E1: PROPOSE DRUM TYPE | F1: Insulation Screening (Metallic) | G1: RM RATE (Insulation Screening (Metallic)) | H1: Weight (Insulation Screening (Metallic)) | I1: COST(Insulation Screening (Metallic)) | J1: Conductor | K1: RM RATE(Conductor) | L1: WEIGHT(Conductor) | M1: COST(Conductor) | N1: AL ALLOY | O1: RM RATE(Alu Alloy) | P1: WEIGHT(Alu Alloy) | Q1: COST(Alu Alloy) | R1: Insulation Screening (Non-Metallic) | S1: RM RATE(Insulation Screening (Non-Metallic)) | T1: WEIGHT(Insulation Screening (Non-Metallic)) | U1: COST(Insulation Screening (Non-Metallic)) | V1: Insulation | W1: RM RATE(Insulation) | X1: WEIGHT(Insulation) | Y1: COST(Insulation) | Z1: POLY TAPE | AA1: RM RATE (Poly Tape) | AB1: WEIGHT (Poly Tape) | AC1: COST(Poly Tape) | AD1: Inner Sheath | AE1: RM RATE(Inner Sheath) | AF1: WEIGHT(Inner Sheath) | AG1: COST(Inner Sheath) | AH1: Armouring | AI1: RM RATE(Armouring) | AJ1: WEIGHT(Armouring) | AK1: COST(Armouring) | AL1: Outer Sheath | AM1: RM RATE(Outer Sheath) | AN1: WEIGHT(Outer Sheath) | AO1: COST(Outer Sheath) | AP1: FILLER | AQ1: RM RATE(Filler) | AR1: WEIGHT(Filler) | AS1: COST(Filler) | AT1: GREASE | AU1: RM RATE(Grease) | AV1: WEIGHT(Grease) | AW1: COST(Grease) | AX1: Water swellable Tape | AY1: RM RATE(Water swellable Tape) | AZ1: WEIGHT(Water swellable Tape) | BA1: COST(Water swellable Tape) | BB1: Semi conducting Water Swellable tape | BC1: RM RATE(Semi conducting Water Swellable tape) | BD1: WEIGHT(Semi conducting Water Swellable tape) | BE1: COST(Semi conducting Water Swellable tape) | BF1: SEMICON TAPE | BG1: RM RATE(SEMICON TAPE) | BH1: WEIGHT(SEMICON TAPE) | BI1: COST(SEMICON TAPE) | BJ1: GLASS FIBER TAPE | BK1: RM RATE(GLASS FIBER TAPE) | BL1: WEIGHT(GLASS FIBER TAPE) | BM1: COST(GLASS FIBER TAPE) | BN1: COPPER WIRE 0.8 MM | BO1: RM RATE(COPPER WIRE 0.8 MM) | BP1: WEIGHT(COPPER WIRE 0.8 MM) | BQ1: COST(COPPER WIRE 0.8 MM) | BR1: RUBBERIZED COTTON TAPE | BS1: RM RATE(RUBBERIZED COTTON TAPE) | BT1: WEIGHT(RUBBERIZED COTTON TAPE) | BU1: COST(RUBBERIZED COTTON TAPE) | BV1: Water Tight Compound | BW1: RM RATE(Water Tight Compound) | BX1: WEIGHT(Water Tight Compound) | BY1: COST(Water Tight Compound) | BZ1: DRUM COST PER KM | CA1: TOTAL RM COST | CB1: FIRM % | CC1: FIRM VALUE | CD1: MFG% | CE1: MFG VALUE | CF1: PROF% | CG1: PROFIT VALUE | CH1: 1ST EX-WORKS | CI1: Intt % | CJ1: INTT VALUE | CK1: insp% | CL1: INSP VALUE | CM1: TTR CHARGES% | CN1: TTR VALUE | CO1: EX-WORKS (PER KM) | CP1: FREIGHT PER KM | CQ1: PRICE INCLUDING FREIGHT (PER KM) | CR1: GST % | CS1: GST VALUE | CT1: PRICE INCLUDING GST & FREIGHT (PER KM) | CU1: QTY | CV1: Unit | CW1: TOTAL PRICE OF FULL QTY (INCLUDING FRIGHT & GST) | CX1: DRUM CODE | CY1: DRUM SIZE (FxbXtx Ft) | CZ1: PARTY STANDARD LENGTH (MTR)
A2: ENQ-13581-22-23 | B2: 45474 | C2: FC4900001 | D2: ACSR : BERSIMIS CONDUCTOR - 690 SQ. MM. (42/4.57/7/2.54) | E2: STEEL | J2: Alumimium | K2: 253 | L2: 1906 | M2: 482218 | P2: 0 | T2: 0 | X2: 0 | AB2: 0 | AF2: 0 | AH2: ACSR CORE WIRE | AI2: 76.75 | AJ2: 281 | AK2: 21566.75 | AN2: 0 | AR2: 0 | AV2: 0 | AZ2: 0 | BD2: 0 | BH2: 0 | BL2: 0 | BP2: 0 | BT2: 0 | BX2: 0 | BZ2: 19000 | CA2: 522784.75 | CB2: 0 | CC2: 0 | CD2: 0.15 | CE2: 78417.72 | CF2: 0 | CG2: 0 | CH2: 601202.47 | CI2: 0.03 | CJ2: 18036.08 | CK2: 0.015 | CL2: 9018.04 | CO2: 628256.59 | CQ2: 628256.59 | CR2: 0.18 | CS2: 113086.19 | CT2: 741342.78 | CU2: 150 | CV2: KMS | CW2: 111201416 | CX2: SP0400151 | CY2: CORRUGATED DISPATCH STEEL DRUM 2100 X 730 X 1000 MM | CZ2: 2100
A3: ENQ-13581-22-23 | B3: 45474 | C3: FC6400002 | D3: ACSR : LAPWING CONDUCTOR - 804.1 SQ. MM. (45/4.77//7/3.18) | E3: STEEL | J3: Alumimium | K3: 253 | L3: 2230 | M3: 564190 | P3: 0 | T3: 0 | X3: 0 | AB3: 0 | AF3: 0 | AH3: ACSR CORE WIRE | AI3: 76.75 | AJ3: 424 | AK3: 32542 | AN3: 0 | AR3: 0 | AV3: 0 | AZ3: 0 | BD3: 0 | BH3: 0 | BL3: 0 | BP3: 0 | BT3: 0 | BX3: 0 | BZ3: 18472.23 | CA3: 615204.23 | CB3: 0 | CC3: 0 | CD3: 0.15 | CE3: 92280.64 | CF3: 0 | CG3: 0 | CH3: 707484.87 | CI3: 0.03 | CJ3: 21224.55 | CK3: 0.015 | CL3: 10612.28 | CO3: 739321.7 | CQ3: 739321.7 | CR3: 0.18 | CS3: 133077.91 | CT3: 872399.61 | CU3: 150 | CV3: KMS | CW3: 130859941 | CX3: SP0400107 | CY3: CORRUGATED DISPATCH STEEL DRUM 2150 X 1080 X 1240 MM | CZ3: 1800
A4: ENQ-13581-22-23 | B4: 45474 | C4: FC6100001 | D4: ACSR : ZEBRA CONDUCTOR - 420 SQ. MM. (54/7/3.18) | E4: STEEL | J4: Alumimium | K4: 253 | L4: 1186 | M4: 300058 | P4: 0 | T4: 0 | X4: 0 | AB4: 0 | AF4: 0 | AH4: ACSR CORE WIRE | AI4: 76.75 | AJ4: 436 | AK4: 33463 | AN4: 0 | AR4: 0 | AV4: 0 | AZ4: 0 | BD4: 0 | BH4: 0 | BL4: 0 | BP4: 0 | BT4: 0 | BX4: 0 | CA4: 333521 | CB4: 0 | CC4: 0 | CD4: 0.15 | CE4: 50028.15 | CF4: 0 | CG4: 0 | CH4: 383549.15 | CI4: 0.03 | CJ4: 11506.48 | CK4: 0.015 | CL4: 5753.24 | CO4: 400808.87 | CQ4: 400808.87 | CR4: 0.18 | CS4: 72145.6 | CT4: 472954.47 | CU4: 250 | CV4: KMS | CW4: 118238617 | CZ4: 3000
A5: ENQ-13581-22-23 | B5: 45474 | C5: FC6100002 | D5: ACSR : MOOSE CONDUCTOR - 520 SQ. MM. (54/7/3.53) | E5: STEEL | J5: Alumimium | K5: 253 | L5: 1467 | M5: 371151 | P5: 0 | T5: 0 | X5: 0 | AB5: 0 | AF5: 0 | AH5: ACSR CORE WIRE | AI5: 76.75 | AJ5: 537 | AK5: 41214.75 | AN5: 0 | AR5: 0 | AV5: 0 | AZ5: 0 | BD5: 0 | BH5: 0 | BL5: 0 | BP5: 0 | BT5: 0 | BX5: 0 | CA5: 412365.75 | CB5: 0 | CC5: 0 | CD5: 0.15 | CE5: 61854.87 | CF5: 0 | CG5: 0 | CH5: 474220.62 | CI5: 0.03 | CJ5: 14226.62 | CK5: 0.015 | CL5: 7113.31 | CO5: 495560.55 | CQ5: 495560.55 | CR5: 0.18 | CS5: 89200.9 | CT5: 584761.45 | CU5: 750 | CV5: KMS | CW5: 438571087 | CZ5: 2400
A6: ENQ-13581-22-23 | B6: 45474 | C6: FC3700003 | D6: ACSR : PANTHER CONDUCTOR - 200 SQ. MM. (30/7/3.00) | E6: WOOD | J6: Alumimium | K6: 253 | L6: 588.5 | M6: 148890.5 | P6: 0 | T6: 0 | X6: 0 | AB6: 0 | AF6: 0 | AH6: ACSR CORE WIRE | AI6: 76.75 | AJ6: 388 | AK6: 29779 | AN6: 0 | AR6: 0 | AV6: 0 | AZ6: 0 | BD6: 0 | BH6: 0 | BL6: 0 | BP6: 0 | BT6: 0 | BX6: 0 | CA6: 178669.5 | CB6: 0 | CC6: 0 | CD6: 0.15 | CE6: 26800.43 | CF6: 0 | CG6: 0 | CH6: 205469.93 | CI6: 0.03 | CJ6: 6164.1 | CK6: 0.015 | CL6: 3082.05 | CO6: 214716.08 | CQ6: 214716.08 | CR6: 0.18 | CS6: 38648.89 | CT6: 253364.97 | CU6: 1200 | CV6: KMS | CW6: 304037969 | CZ6: 3500

Sheet AUTO CALCULATION SHEET (2)
D1: Spec No: CC/NT/G-COND/DOM/A00/24/05628
D2: Bulk Proc Conductor Package - CD02 | N2: =Sheet1!J1 -> Conductor | S2: AL ALLOY | U2: Insulation Screening (Metallic) | AC2: Insulation Screening (Non-Metallic) | AE2: Insulation | AK2: POLY TAPE | AL2: Inner Sheath | AS2: Armouring | BC2: Outer Sheath | BM2: FILLER | BN2: GREASE | BO2: Water swellable Tape | BP2: Semi conducting Water Swellable tape | BQ2: SEMICON TAPE | BR2: GLASS FIBER TAPE | BS2: COPPER WIRE 0.8 MM | BT2: RUBBERIZED COTTON TAPE | BU2: Water Tight Compound | CB2: DRUM COST PER KM | CC2: TOTAL RM COST | CD2: EXTRA CONSUMPTION | CE2: EXTRA CONSUMPTION VALUE
A3: DOCKET NO. | B3: =Sheet1!B1 -> Base Date | C3: ITEM CODE | D3: PROPOSE ERP ITEM NAME | E3: EX-WORKS (PER KM) | F3: FREIGHT PER KM | G3: PRICE INCLUDING FREIGHT (PER KM) | H3: GST % | I3: GST VALUE | J3: PRICE INCLUDING GST & FREIGHT (PER KM) | K3: QTY | L3: Unit | M3: TOTAL PRICE OF FULL QTY (INCLUDING FRIGHT & GST) | N3: Alumimium | O3: Alumimium ALLOY | P3: Copper | Q3: Flexible Copper | R3: Galvanized steel wire | S3: Alumimium | T3: Alumimium ALLOY | U3: Coper tape - 0.1 mm | V3: Copper Tape - 0.03 mm | W3: Copper Tape - 0.035 mm | X3: Copper Tape - 0.04 mm | Y3: Copper Tape - 0.045 mm | Z3: Copper Tape - 0.050 mm | AA3: Copper Tape - 0.060 mm | AB3: Copper Tape - 0.075 mm(DOUBLE) | AC3: Extruded semiconductive | AD3: Extruded Semiconductive(Stripable) | AE3: HT-XLPE | AF3: LT-XLPE | AG3: TR XLPE | AH3: Type A PVC | AI3: Type C PVC (HR) | AJ3: XLPE | AK3: POLY TAPE | AL3: FR PVC Type ST-1 | AM3: FR PVC Type ST-2 | AN3: FRLSH PVC Type ST-2 | AO3: PVC Type ST-1 | AP3: PVC Type ST-1-PRESSURE EXTRUDED | AQ3: PVC Type ST-2 | AR3: PVC Type ST-2-PRESSURE EXTRUDED | AS3: ACSR CORE WIRE | AT3: ACSR DOG STEEL WIRE | AU3: Aluminium Flat Strip | AV3: Aluminium Round Wire | AW3: Double Steel Tape | AX3: Galvanised Steel Flat Strip | AY3: Galvanised Steel Flat Strip (Double) | AZ3: Galvanised Steel Flat Strip-B | BA3: Galvanised Steel Round Wire | BB3: Galvanised Steel Round Wire (Double) | BC3: FR PVC Type ST-1 | BD3: FR PVC Type ST-2 | BE3: FRLSH PVC Type ST-1 | BF3: FRLSH PVC Type ST-2 | BG3: PE, ST-3 | BH3: PE, ST-7 | BI3: PVC Type ST-1 | BJ3: PVC Type ST-2 | BK3: PVC Type ST-2-PRESSURE EXTRUDED | BL3: UV & Track Resistant XLPE | BM3: FILLER | BN3: Grease | BO3: Water swellable Tape | BP3: Semi conducting Water Swellable tape | BQ3: SEMICON TAPE | BR3: GLASS FIBER TAPE | BS3: COPPER WIRE 0.8 MM | BT3: RUBBERIZED COTTON TAPE | BU3: Water Tight Compound | BV3: =Sheet1!E1 -> PROPOSE DRUM TYPE | BX3: =Sheet1!CX1 -> DRUM CODE | BY3: =Sheet1!CY1 -> DRUM SIZE (FxbXtx Ft) | BZ3: DRUM WEIGHT IN KG | CA3: =Sheet1!CZ1 -> PARTY STANDARD LENGTH (MTR) | CB3: 90 RS/KG | CF3: MFG% | CG3: MFG VALUE | CH3: PROF% | CI3: PROFIT VALUE | CJ3: 1ST EX-WORKS | CK3: Intt % | CL3: INTT VALUE | CM3: insp% | CN3: INSP VALUE | CO3: =Sheet1!CM1 -> TTR CHARGES% | CP3: =Sheet1!CN1 -> TTR VALUE
N4: 235 | O4: =+IFERROR(VLOOKUP($O$3,Sheet1!J:L,2,0),0) -> 0 | P4: =+IFERROR(VLOOKUP($P$3,Sheet1!J:M,2,0),0) -> 0 | Q4: =+IFERROR(VLOOKUP($Q$3,Sheet1!J:M,2,0),0) -> 0 | R4: =+IFERROR(VLOOKUP($R$3,Sheet1!J:M,2,0),0) -> 0 | S4: =+IFERROR(VLOOKUP($S$3,Sheet1!N:Q,2,0),0) -> 0 | T4: =+IFERROR(VLOOKUP($T$3,Sheet1!N:O,2,0),0) -> 0 | U4: =+IFERROR(VLOOKUP($U$3,Sheet1!F:I,2,0),0) -> 0 | V4: =+IFERROR(VLOOKUP($V$3,Sheet1!F:I,2,0),0) -> 0 | W4: =+IFERROR(VLOOKUP($W$3,Sheet1!F:I,2,0),0) -> 0 | X4: =+IFERROR(VLOOKUP($X$3,Sheet1!F:I,2,0),0) -> 0 | Y4: =+IFERROR(VLOOKUP($Y$3,Sheet1!F:I,2,0),0) -> 0 | Z4: =+IFERROR(VLOOKUP($Z$3,Sheet1!F:I,2,0),0) -> 0 | AA4: =+IFERROR(VLOOKUP($AA$3,Sheet1!F:I,2,0),0) -> 0 | AB4: =+IFERROR(VLOOKUP($AB$3,Sheet1!F:I,2,0),0) -> 0 | AC4: =+IFERROR(VLOOKUP($AC$3,Sheet1!R:U,2,0),0) -> 0 | AD4: =+IFERROR(VLOOKUP($AD$3,Sheet1!R:U,2,0),0) -> 0 | AE4: =+IFERROR(VLOOKUP($AE$3,Sheet1!V:Y,2,0),0) -> 0 | AF4: =+IFERROR(VLOOKUP($AF$3,Sheet1!V:Y,2,0),0) -> 0 | AG4: =+IFERROR(VLOOKUP($AG$3,Sheet1!V:Y,2,0),0) -> 0 | AH4: =+IFERROR(VLOOKUP($AH$3,Sheet1!V:Y,2,0),0) -> 0 | AI4: =+IFERROR(VLOOKUP($AI$3,Sheet1!V:Y,2,0),0) -> 0 | AJ4: =+IFERROR(VLOOKUP($AJ$3,Sheet1!V:Y,2,0),0) -> 0 | AK4: =+IFERROR(VLOOKUP($AK$3,Sheet1!Z2:AA840,2,0),0) -> 0 | AL4: =+IFERROR(VLOOKUP($AL$3,Sheet1!AD2:AG840,2,0),0) -> 0 | AM4: =+IFERROR(VLOOKUP($AM$3,Sheet1!AD2:AG840,2,0),0) -> 0 | AN4: =+IFERROR(VLOOKUP($AN$3,Sheet1!AD2:AG840,2,0),0) -> 0 | AO4: =+IFERROR(VLOOKUP($AO$3,Sheet1!AD2:AG840,2,0),0) -> 0 | AP4: =+IFERROR(VLOOKUP($AP$3,Sheet1!AD2:AG840,2,0),0) -> 0 | AQ4: =+IFERROR(VLOOKUP($AQ$3,Sheet1!AD2:AG840,2,0),0) -> 0 | AR4: =+IFERROR(VLOOKUP($AR$3,Sheet1!AD2:AG840,2,0),0) -> 0 | AS4: 73 | AT4: =+IFERROR(VLOOKUP($AT$3,Sheet1!AH2:AK840,2,0),0) -> 0 | AU4: =+IFERROR(VLOOKUP($AU$3,Sheet1!AH2:AK840,2,0),0) -> 0 | AV4: =+IFERROR(VLOOKUP($AV$3,Sheet1!AH2:AK840,2,0),0) -> 0 | AW4: =+IFERROR(VLOOKUP($AW$3,Sheet1!AH2:AK840,2,0),0) -> 0 | AX4: =+IFERROR(VLOOKUP($AX$3,Sheet1!AH2:AK840,2,0),0) -> 0 | AY4: =+IFERROR(VLOOKUP($AY$3,Sheet1!AH2:AK840,2,0),0) -> 0 | AZ4: =+IFERROR(VLOOKUP($AZ$3,Sheet1!AH2:AK840,2,0),0) -> 0 | BA4: =+IFERROR(VLOOKUP($BA$3,Sheet1!AH2:AK840,2,0),0) -> 0 | BB4: =+IFERROR(VLOOKUP($BB$3,Sheet1!AH2:AK840,2,0),0) -> 0 | BC4: =+IFERROR(VLOOKUP($BC$3,Sheet1!AL2:AO840,2,0),0) -> 0 | BD4: =+IFERROR(VLOOKUP($BD$3,Sheet1!AL2:AO840,2,0),0) -> 0 | BE4: =+IFERROR(VLOOKUP($BE$3,Sheet1!AL2:AO840,2,0),0) -> 0 | BF4: =+IFERROR(VLOOKUP($BF$3,Sheet1!AL2:AO840,2,0),0) -> 0 | BG4: =+IFERROR(VLOOKUP($BG$3,Sheet1!AL2:AO840,2,0),0) -> 0 | BH4: =+IFERROR(VLOOKUP($BH$3,Sheet1!AL2:AO840,2,0),0) -> 0 | BI4: =+IFERROR(VLOOKUP($BI$3,Sheet1!AL2:AO840,2,0),0) -> 0 | BJ4: =+IFERROR(VLOOKUP($BJ$3,Sheet1!AL2:AO840,2,0),0) -> 0 | BK4: =+IFERROR(VLOOKUP($BK$3,Sheet1!AL2:AO840,2,0),0) -> 0 | BL4: =+IFERROR(VLOOKUP($BL$3,Sheet1!AL2:AO840,2,0),0) -> 0 | BM4: =+IFERROR(VLOOKUP($BM$3,Sheet1!AP2:AS840,2,0),0) -> 0 | BN4: =+IFERROR(VLOOKUP($BN$3,Sheet1!AT2:AW840,2,0),0) -> 0 | BO4: =+IFERROR(VLOOKUP($BO$3,Sheet1!AX2:BA840,2,0),0) -> 0 | BP4: =+IFERROR(VLOOKUP($BP$3,Sheet1!BB2:BE840,2,0),0) -> 0 | BQ4: =+IFERROR(VLOOKUP($BQ$3,Sheet1!BF2:BI840,2,0),0) -> 0 | BR4: =+IFERROR(VLOOKUP($BR$3,Sheet1!BJ2:BM840,2,0),0) -> 0 | BS4: =+IFERROR(VLOOKUP($BS$3,Sheet1!BN2:BQ840,2,0),0) -> 0 | BT4: =+IFERROR(VLOOKUP($BT$3,Sheet1!BR2:BU840,2,0),0) -> 0 | BU4: =+IFERROR(VLOOKUP($BU$3,Sheet1!BV2:BY840,2,0),0) -> 0
A5: =Sheet1!A5 -> ENQ-13581-22-23 | B5: =Sheet1!B5 -> 45474 | C5: =Sheet1!C5 -> FC6100002 | D5: =Sheet1!D5 -> ACSR : MOOSE CONDUCTOR - 520 SQ. MM. (54/7/3.53) | E5: =CJ5+CL5+CN5 -> 410043.6 | F5: =ROUNDUP(M14,0) -> 6320 | G5: =E5+F5 -> 416363.6 | H5: =Sheet1!CR5 -> 0.18 | I5: =G5*H5 -> 74945.448 | J5: =G5+I5 -> 491309.05 | K5: =Sheet1!CU5 -> 750 | L5: =Sheet1!CV5 -> KMS | M5: =J5*K5 -> 3.6848178e+08 | N5: =+IFERROR(VLOOKUP($N$3,Sheet1!J5:L5,3,0),0) -> 1467 | O5: =+IFERROR(VLOOKUP($O$3,Sheet1!J5:L5,3,0),0) -> 0 | P5: =+IFERROR(VLOOKUP($P$3,Sheet1!J5:M5,3,0),0) -> 0 | Q5: =+IFERROR(VLOOKUP($Q$3,Sheet1!J5:M5,3,0),0) -> 0 | R5: =+IFERROR(VLOOKUP($R$3,Sheet1!J5:M5,3,0),0) -> 0 | S5: =+IFERROR(VLOOKUP($S$3,Sheet1!N5:Q5,3,0),0) -> 0 | T5: =+IFERROR(VLOOKUP($T$3,Sheet1!N5:Q5,3,0),0) -> 0 | U5: =+IFERROR(VLOOKUP($U$3,Sheet1!F5:I5,3,0),0) -> 0 | V5: =+IFERROR(VLOOKUP($V$3,Sheet1!F5:I5,3,0),0) -> 0 | W5: =+IFERROR(VLOOKUP($W$3,Sheet1!F5:I5,3,0),0) -> 0 | X5: =+IFERROR(VLOOKUP($X$3,Sheet1!F5:I5,3,0),0) -> 0 | Y5: =+IFERROR(VLOOKUP($Y$3,Sheet1!F5:I5,3,0),0) -> 0 | Z5: =+IFERROR(VLOOKUP($Z$3,Sheet1!F5:I5,3,0),0) -> 0 | AA5: =+IFERROR(VLOOKUP($AA$3,Sheet1!F5:I5,3,0),0) -> 0 | AB5: =+IFERROR(VLOOKUP($AB$3,Sheet1!F5:I5,3,0),0) -> 0 | AC5: =+IFERROR(VLOOKUP($AC$3,Sheet1!R5:U5,3,0),0) -> 0 | AD5: =+IFERROR(VLOOKUP($AD$3,Sheet1!R5:U5,3,0),0) -> 0 | AE5: =+IFERROR(VLOOKUP($AE$3,Sheet1!V5:Y5,3,0),0) -> 0 | AF5: =+IFERROR(VLOOKUP($AF$3,Sheet1!V5:Y5,3,0),0) -> 0 | AG5: =+IFERROR(VLOOKUP($AG$3,Sheet1!V5:Y5,3,0),0) -> 0 | AH5: =+IFERROR(VLOOKUP($AH$3,Sheet1!V5:Y5,3,0),0) -> 0 | AI5: =+IFERROR(VLOOKUP($AI$3,Sheet1!V5:Y5,3,0),0) -> 0 | AJ5: =+IFERROR(VLOOKUP($AJ$3,Sheet1!V5:Y5,3,0),0) -> 0 | AK5: =+IFERROR(VLOOKUP($AK$3,Sheet1!Z5:AB5,3,0),0) -> 0 | AL5: =+IFERROR(VLOOKUP($AL$3,Sheet1!AD5:AG5,3,0),0) -> 0 | AM5: =+IFERROR(VLOOKUP($AM$3,Sheet1!AD5:AG5,3,0),0) -> 0 | AN5: =+IFERROR(VLOOKUP($AN$3,Sheet1!AD5:AG5,3,0),0) -> 0 | AO5: =+IFERROR(VLOOKUP($AO$3,Sheet1!AD5:AG5,3,0),0) -> 0 | AP5: =+IFERROR(VLOOKUP($AP$3,Sheet1!AD5:AG5,3,0),0) -> 0 | AQ5: =+IFERROR(VLOOKUP($AQ$3,Sheet1!AD5:AG5,3,0),0) -> 0 | AR5: =+IFERROR(VLOOKUP($AR$3,Sheet1!AD5:AG5,3,0),0) -> 0 | AS5: =+IFERROR(VLOOKUP($AS$3,Sheet1!AH5:AK5,3,0),0) -> 537 | AT5: =+IFERROR(VLOOKUP($AT$3,Sheet1!AH5:AK5,3,0),0) -> 0 | AU5: =+IFERROR(VLOOKUP($AU$3,Sheet1!AH5:AK5,3,0),0) -> 0 | AV5: =+IFERROR(VLOOKUP($AV$3,Sheet1!AH5:AK5,3,0),0) -> 0 | AW5: =+IFERROR(VLOOKUP($AW$3,Sheet1!AH5:AK5,3,0),0) -> 0 | AX5: =+IFERROR(VLOOKUP($AX$3,Sheet1!AH5:AK5,3,0),0) -> 0 | AY5: =+IFERROR(VLOOKUP($AY$3,Sheet1!AH5:AK5,3,0),0) -> 0 | AZ5: =+IFERROR(VLOOKUP($AZ$3,Sheet1!AH5:AK5,3,0),0) -> 0 | BA5: =+IFERROR(VLOOKUP($BA$3,Sheet1!AH5:AK5,3,0),0) -> 0 | BB5: =+IFERROR(VLOOKUP($BB$3,Sheet1!AH5:AK5,3,0),0) -> 0 | BC5: =+IFERROR(VLOOKUP($BC$3,Sheet1!AL5:AO5,3,0),0) -> 0 | BD5: =+IFERROR(VLOOKUP($BD$3,Sheet1!AL5:AO5,3,0),0) -> 0 | BE5: =+IFERROR(VLOOKUP($BE$3,Sheet1!AL5:AO5,3,0),0) -> 0 | BF5: =+IFERROR(VLOOKUP($BF$3,Sheet1!AL5:AO5,3,0),0) -> 0 | BG5: =+IFERROR(VLOOKUP($BG$3,Sheet1!AL5:AO5,3,0),0) -> 0 | BH5: =+IFERROR(VLOOKUP($BH$3,Sheet1!AL5:AO5,3,0),0) -> 0 | BI5: =+IFERROR(VLOOKUP($BI$3,Sheet1!AL5:AO5,3,0),0) -> 0 | BJ5: =+IFERROR(VLOOKUP($BJ$3,Sheet1!AL5:AO5,3,0),0) -> 0 | BK5: =+IFERROR(VLOOKUP($BK$3,Sheet1!AL5:AO5,3,0),0) -> 0 | BL5: =+IFERROR(VLOOKUP($BL$3,Sheet1!AL5:AO5,3,0),0) -> 0 | BM5: =+IFERROR(VLOOKUP($BM$3,Sheet1!AP5:AS5,3,0),0) -> 0 | BN5: =+IFERROR(VLOOKUP($BN$3,Sheet1!AT5:AW5,3,0),0) -> 0 | BO5: =+IFERROR(VLOOKUP($BO$3,Sheet1!AX5:BA5,3,0),0) -> 0 | BP5: =+IFERROR(VLOOKUP($BP$3,Sheet1!BB5:BE5,3,0),0) -> 0 | BQ5: =+IFERROR(VLOOKUP($BQ$3,Sheet1!BF5:BI5,3,0),0) -> 0 | BR5: =+IFERROR(VLOOKUP($BR$3,Sheet1!BJ5:BM5,3,0),0) -> 0 | BS5: =+IFERROR(VLOOKUP($BS$3,Sheet1!BN5:BQ5,3,0),0) -> 0 | BT5: =+IFERROR(VLOOKUP($BT$3,Sheet1!BR5:BU5,3,0),0) -> 0 | BU5: =+IFERROR(VLOOKUP($BU$3,Sheet1!BV5:BY5,3,0),0) -> 0 | BV5: =Sheet1!E5 -> STEEL | BW5: =SUM(N5:AS5) -> 2004 | BY5: CORRUGATED DISPATCH STEEL DRUM 2200 X 800 X 965 MM | BZ5: 480 | CA5: =Sheet1!CZ5 -> 2400 | CB5: =(((BZ5*90)/(CA5/1000))/2)/2 -> 4500 | CC5: =SUMPRODUCT($N$4:$BU$4,N5:BU5)+CB5 -> 388446 | CD5: =Sheet1!CB5 -> 0 | CE5: =CC5*CD5 -> 0 | CF5: 0.04 | CG5: =CC5*CF5 -> 15537.84 | CH5: =Sheet1!CF5 -> 0 | CI5: =CC5*CH5 -> 0 | CJ5: =CC5+CE5+CG5+CI5 -> 403983.84 | CK5: 0.01 | CL5: =CJ5*CK5 -> 4039.8384 | CM5: 0.005 | CN5: =CJ5*CM5 -> 2019.9192 | CO5: =Sheet1!CM5 -> 0 | CP5: =CJ5*CO5 -> 0
A6: =Sheet1!A2 -> ENQ-13581-22-23 | B6: =Sheet1!B2 -> 45474 | C6: =Sheet1!C2 -> FC4900001 | D6: =Sheet1!D2 -> ACSR : BERSIMIS CONDUCTOR - 690 SQ. MM. (42/4.57/7/2.54) | E6: =CJ6+CL6+CN6+CP6 -> 499896.12 | F6: =ROUNDUP(M15,0) -> 7200 | G6: =E6+F6 -> 507096.12 | H6: =Sheet1!CR2 -> 0.18 | I6: =G6*H6 -> 91277.301 | J6: =G6+I6 -> 598373.42 | K6: =Sheet1!CU2 -> 150 | L6: =Sheet1!CV2 -> KMS | M6: =J6*K6 -> 89756013 | N6: =+IFERROR(VLOOKUP($N$3,Sheet1!J2:L2,3,0),0) -> 1906 | O6: =+IFERROR(VLOOKUP($O$3,Sheet1!J2:L2,3,0),0) -> 0 | P6: =+IFERROR(VLOOKUP($P$3,Sheet1!J2:M2,3,0),0) -> 0 | Q6: =+IFERROR(VLOOKUP($Q$3,Sheet1!J2:M2,3,0),0) -> 0 | R6: =+IFERROR(VLOOKUP($R$3,Sheet1!J2:M2,3,0),0) -> 0 | S6: =+IFERROR(VLOOKUP($S$3,Sheet1!N2:Q2,3,0),0) -> 0 | T6: =+IFERROR(VLOOKUP($T$3,Sheet1!N2:Q2,3,0),0) -> 0 | U6: =+IFERROR(VLOOKUP($U$3,Sheet1!F2:I2,3,0),0) -> 0 | V6: =+IFERROR(VLOOKUP($V$3,Sheet1!F2:I2,3,0),0) -> 0 | W6: =+IFERROR(VLOOKUP($W$3,Sheet1!F2:I2,3,0),0) -> 0 | X6: =+IFERROR(VLOOKUP($X$3,Sheet1!F2:I2,3,0),0) -> 0 | Y6: =+IFERROR(VLOOKUP($Y$3,Sheet1!F2:I2,3,0),0) -> 0 | Z6: =+IFERROR(VLOOKUP($Z$3,Sheet1!F2:I2,3,0),0) -> 0 | AA6: =+IFERROR(VLOOKUP($AA$3,Sheet1!F2:I2,3,0),0) -> 0 | AB6: =+IFERROR(VLOOKUP($AB$3,Sheet1!F2:I2,3,0),0) -> 0 | AC6: =+IFERROR(VLOOKUP($AC$3,Sheet1!R2:U2,3,0),0) -> 0 | AD6: =+IFERROR(VLOOKUP($AD$3,Sheet1!R2:U2,3,0),0) -> 0 | AE6: =+IFERROR(VLOOKUP($AE$3,Sheet1!V2:Y2,3,0),0) -> 0 | AF6: =+IFERROR(VLOOKUP($AF$3,Sheet1!V2:Y2,3,0),0) -> 0 | AG6: =+IFERROR(VLOOKUP($AG$3,Sheet1!V2:Y2,3,0),0) -> 0 | AH6: =+IFERROR(VLOOKUP($AH$3,Sheet1!V2:Y2,3,0),0) -> 0 | AI6: =+IFERROR(VLOOKUP($AI$3,Sheet1!V2:Y2,3,0),0) -> 0 | AJ6: =+IFERROR(VLOOKUP($AJ$3,Sheet1!V2:Y2,3,0),0) -> 0 | AK6: =+IFERROR(VLOOKUP($AK$3,Sheet1!Z2:AB2,3,0),0) -> 0 | AL6: =+IFERROR(VLOOKUP($AL$3,Sheet1!AD2:AG2,3,0),0) -> 0 | AM6: =+IFERROR(VLOOKUP($AM$3,Sheet1!AD2:AG2,3,0),0) -> 0 | AN6: =+IFERROR(VLOOKUP($AN$3,Sheet1!AD2:AG2,3,0),0) -> 0 | AO6: =+IFERROR(VLOOKUP($AO$3,Sheet1!AD2:AG2,3,0),0) -> 0 | AP6: =+IFERROR(VLOOKUP($AP$3,Sheet1!AD2:AG2,3,0),0) -> 0 | AQ6: =+IFERROR(VLOOKUP($AQ$3,Sheet1!AD2:AG2,3,0),0) -> 0 | AR6: =+IFERROR(VLOOKUP($AR$3,Sheet1!AD2:AG2,3,0),0) -> 0 | AS6: =+IFERROR(VLOOKUP($AS$3,Sheet1!AH2:AK2,3,0),0) -> 281 | AT6: =+IFERROR(VLOOKUP($AT$3,Sheet1!AH2:AK2,3,0),0) -> 0 | AU6: =+IFERROR(VLOOKUP($AU$3,Sheet1!AH2:AK2,3,0),0) -> 0 | AV6: =+IFERROR(VLOOKUP($AV$3,Sheet1!AH2:AK2,3,0),0) -> 0 | AW6: =+IFERROR(VLOOKUP($AW$3,Sheet1!AH2:AK2,3,0),0) -> 0 | AX6: =+IFERROR(VLOOKUP($AX$3,Sheet1!AH2:AK2,3,0),0) -> 0 | AY6: =+IFERROR(VLOOKUP($AY$3,Sheet1!AH2:AK2,3,0),0) -> 0 | AZ6: =+IFERROR(VLOOKUP($AZ$3,Sheet1!AH2:AK2,3,0),0) -> 0 | BA6: =+IFERROR(VLOOKUP($BA$3,Sheet1!AH2:AK2,3,0),0) -> 0 | BB6: =+IFERROR(VLOOKUP($BB$3,Sheet1!AH2:AK2,3,0),0) -> 0 | BC6: =+IFERROR(VLOOKUP($BC$3,Sheet1!AL2:AO2,3,0),0) -> 0 | BD6: =+IFERROR(VLOOKUP($BD$3,Sheet1!AL2:AO2,3,0),0) -> 0 | BE6: =+IFERROR(VLOOKUP($BE$3,Sheet1!AL2:AO2,3,0),0) -> 0 | BF6: =+IFERROR(VLOOKUP($BF$3,Sheet1!AL2:AO2,3,0),0) -> 0 | BG6: =+IFERROR(VLOOKUP($BG$3,Sheet1!AL2:AO2,3,0),0) -> 0 | BH6: =+IFERROR(VLOOKUP($BH$3,Sheet1!AL2:AO2,3,0),0) -> 0 | BI6: =+IFERROR(VLOOKUP($BI$3,Sheet1!AL2:AO2,3,0),0) -> 0 | BJ6: =+IFERROR(VLOOKUP($BJ$3,Sheet1!AL2:AO2,3,0),0) -> 0 | BK6: =+IFERROR(VLOOKUP($BK$3,Sheet1!AL2:AO2,3,0),0) -> 0 | BL6: =+IFERROR(VLOOKUP($BL$3,Sheet1!AL2:AO2,3,0),0) -> 0 | BM6: =+IFERROR(VLOOKUP($BM$3,Sheet1!AP2:AS2,3,0),0) -> 0 | BN6: =+IFERROR(VLOOKUP($BN$3,Sheet1!AT2:AW2,3,0),0) -> 0 | BO6: =+IFERROR(VLOOKUP($BO$3,Sheet1!AX2:BA2,3,0),0) -> 0 | BP6: =+IFERROR(VLOOKUP($BP$3,Sheet1!BB2:BE2,3,0),0) -> 0 | BQ6: =+IFERROR(VLOOKUP($BQ$3,Sheet1!BF2:BI2,3,0),0) -> 0 | BR6: =+IFERROR(VLOOKUP($BR$3,Sheet1!BJ2:BM2,3,0),0) -> 0 | BS6: =+IFERROR(VLOOKUP($BS$3,Sheet1!BN2:BQ2,3,0),0) -> 0 | BT6: =+IFERROR(VLOOKUP($BT$3,Sheet1!BR2:BU2,3,0),0) -> 0 | BU6: =+IFERROR(VLOOKUP($BU$3,Sheet1!BV2:BY2,3,0),0) -> 0 | BV6: =Sheet1!E2 -> STEEL | BW6: =SUM(N6:AS6) -> 2187 | BY6: CORRUGATED DISPATCH STEEL DRUM 2200 X 800 X 965 MM | BZ6: 480 | CA6: =Sheet1!CZ2 -> 2100 | CB6: =(((BZ6*90)/(CA6/1000))/2)/2 -> 5142.8571 | CC6: =SUMPRODUCT($N$4:$BU$4,N6:BU6)+CB6 -> 473565.86 | CD6: =Sheet1!CB2 -> 0 | CE6: =CC6*CD6 -> 0 | CF6: 0.04 | CG6: =CC6*CF6 -> 18942.634 | CH6: =Sheet1!CF2 -> 0 | CI6: =CC6*CH6 -> 0 | CJ6: =CC6+CE6+CG6+CI6 -> 492508.49 | CK6: 0.01 | CL6: =CJ6*CK6 -> 4925.0849 | CM6: 0.005 | CN6: =CJ6*CM6 -> 2462.5425 | CO6: =Sheet1!CM2 -> 0 | CP6: =CJ6*CO6 -> 0
A7: =Sheet1!A3 -> ENQ-13581-22-23 | B7: =Sheet1!B3 -> 45474 | C7: =Sheet1!C3 -> FC6400002 | D7: =Sheet1!D3 -> ACSR : LAPWING CONDUCTOR - 804.1 SQ. MM. (45/4.77//7/3.18) | E7: =CJ7+CL7+CN7 -> 593024.47 | F7: =ROUNDUP(M16,0) -> 8400 | G7: =E7+F7 -> 601424.47 | H7: =Sheet1!CR3 -> 0.18 | I7: =G7*H7 -> 108256.4 | J7: =G7+I7 -> 709680.87 | K7: =Sheet1!CU3 -> 150 | L7: =Sheet1!CV3 -> KMS | M7: =J7*K7 -> 1.0645213e+08 | N7: 2229 | O7: =+IFERROR(VLOOKUP($O$3,Sheet1!J3:L3,3,0),0) -> 0 | P7: =+IFERROR(VLOOKUP($P$3,Sheet1!J3:M3,3,0),0) -> 0 | Q7: =+IFERROR(VLOOKUP($Q$3,Sheet1!J3:M3,3,0),0) -> 0 | R7: =+IFERROR(VLOOKUP($R$3,Sheet1!J3:M3,3,0),0) -> 0 | S7: =+IFERROR(VLOOKUP($S$3,Sheet1!N3:Q3,3,0),0) -> 0 | T7: =+IFERROR(VLOOKUP($T$3,Sheet1!N3:Q3,3,0),0) -> 0 | U7: =+IFERROR(VLOOKUP($U$3,Sheet1!F3:I3,3,0),0) -> 0 | V7: =+IFERROR(VLOOKUP($V$3,Sheet1!F3:I3,3,0),0) -> 0 | W7: =+IFERROR(VLOOKUP($W$3,Sheet1!F3:I3,3,0),0) -> 0 | X7: =+IFERROR(VLOOKUP($X$3,Sheet1!F3:I3,3,0),0) -> 0 | Y7: =+IFERROR(VLOOKUP($Y$3,Sheet1!F3:I3,3,0),0) -> 0 | Z7: =+IFERROR(VLOOKUP($Z$3,Sheet1!F3:I3,3,0),0) -> 0 | AA7: =+IFERROR(VLOOKUP($AA$3,Sheet1!F3:I3,3,0),0) -> 0 | AB7: =+IFERROR(VLOOKUP($AB$3,Sheet1!F3:I3,3,0),0) -> 0 | AC7: =+IFERROR(VLOOKUP($AC$3,Sheet1!R3:U3,3,0),0) -> 0 | AD7: =+IFERROR(VLOOKUP($AD$3,Sheet1!R3:U3,3,0),0) -> 0 | AE7: =+IFERROR(VLOOKUP($AE$3,Sheet1!V3:Y3,3,0),0) -> 0 | AF7: =+IFERROR(VLOOKUP($AF$3,Sheet1!V3:Y3,3,0),0) -> 0 | AG7: =+IFERROR(VLOOKUP($AG$3,Sheet1!V3:Y3,3,0),0) -> 0 | AH7: =+IFERROR(VLOOKUP($AH$3,Sheet1!V3:Y3,3,0),0) -> 0 | AI7: =+IFERROR(VLOOKUP($AI$3,Sheet1!V3:Y3,3,0),0) -> 0 | AJ7: =+IFERROR(VLOOKUP($AJ$3,Sheet1!V3:Y3,3,0),0) -> 0 | AK7: =+IFERROR(VLOOKUP($AK$3,Sheet1!Z3:AB3,3,0),0) -> 0 | AL7: =+IFERROR(VLOOKUP($AL$3,Sheet1!AD3:AG3,3,0),0) -> 0 | AM7: =+IFERROR(VLOOKUP($AM$3,Sheet1!AD3:AG3,3,0),0) -> 0 | AN7: =+IFERROR(VLOOKUP($AN$3,Sheet1!AD3:AG3,3,0),0) -> 0 | AO7: =+IFERROR(VLOOKUP($AO$3,Sheet1!AD3:AG3,3,0),0) -> 0 | AP7: =+IFERROR(VLOOKUP($AP$3,Sheet1!AD3:AG3,3,0),0) -> 0 | AQ7: =+IFERROR(VLOOKUP($AQ$3,Sheet1!AD3:AG3,3,0),0) -> 0 | AR7: =+IFERROR(VLOOKUP($AR$3,Sheet1!AD3:AG3,3,0),0) -> 0 | AS7: 438 | AT7: =+IFERROR(VLOOKUP($AT$3,Sheet1!AH3:AK3,3,0),0) -> 0 | AU7: =+IFERROR(VLOOKUP($AU$3,Sheet1!AH3:AK3,3,0),0) -> 0 | AV7: =+IFERROR(VLOOKUP($AV$3,Sheet1!AH3:AK3,3,0),0) -> 0 | AW7: =+IFERROR(VLOOKUP($AW$3,Sheet1!AH3:AK3,3,0),0) -> 0 | AX7: =+IFERROR(VLOOKUP($AX$3,Sheet1!AH3:AK3,3,0),0) -> 0 | AY7: =+IFERROR(VLOOKUP($AY$3,Sheet1!AH3:AK3,3,0),0) -> 0 | AZ7: =+IFERROR(VLOOKUP($AZ$3,Sheet1!AH3:AK3,3,0),0) -> 0 | BA7: =+IFERROR(VLOOKUP($BA$3,Sheet1!AH3:AK3,3,0),0) -> 0 | BB7: =+IFERROR(VLOOKUP($BB$3,Sheet1!AH3:AK3,3,0),0) -> 0 | BC7: =+IFERROR(VLOOKUP($BC$3,Sheet1!AL3:AO3,3,0),0) -> 0 | BD7: =+IFERROR(VLOOKUP($BD$3,Sheet1!AL3:AO3,3,0),0) -> 0 | BE7: =+IFERROR(VLOOKUP($BE$3,Sheet1!AL3:AO3,3,0),0) -> 0 | BF7: =+IFERROR(VLOOKUP($BF$3,Sheet1!AL3:AO3,3,0),0) -> 0 | BG7: =+IFERROR(VLOOKUP($BG$3,Sheet1!AL3:AO3,3,0),0) -> 0 | BH7: =+IFERROR(VLOOKUP($BH$3,Sheet1!AL3:AO3,3,0),0) -> 0 | BI7: =+IFERROR(VLOOKUP($BI$3,Sheet1!AL3:AO3,3,0),0) -> 0 | BJ7: =+IFERROR(VLOOKUP($BJ$3,Sheet1!AL3:AO3,3,0),0) -> 0 | BK7: =+IFERROR(VLOOKUP($BK$3,Sheet1!AL3:AO3,3,0),0) -> 0 | BL7: =+IFERROR(VLOOKUP($BL$3,Sheet1!AL3:AO3,3,0),0) -> 0 | BM7: =+IFERROR(VLOOKUP($BM$3,Sheet1!AP3:AS3,3,0),0) -> 0 | BN7: =+IFERROR(VLOOKUP($BN$3,Sheet1!AT3:AW3,3,0),0) -> 0 | BO7: =+IFERROR(VLOOKUP($BO$3,Sheet1!AX3:BA3,3,0),0) -> 0 | BP7: =+IFERROR(VLOOKUP($BP$3,Sheet1!BB3:BE3,3,0),0) -> 0 | BQ7: =+IFERROR(VLOOKUP($BQ$3,Sheet1!BF3:BI3,3,0),0) -> 0 | BR7: =+IFERROR(VLOOKUP($BR$3,Sheet1!BJ3:BM3,3,0),0) -> 0 | BS7: =+IFERROR(VLOOKUP($BS$3,Sheet1!BN3:BQ3,3,0),0) -> 0 | BT7: =+IFERROR(VLOOKUP($BT$3,Sheet1!BR3:BU3,3,0),0) -> 0 | BU7: =+IFERROR(VLOOKUP($BU$3,Sheet1!BV3:BY3,3,0),0) -> 0 | BV7: =Sheet1!E3 -> STEEL | BW7: =SUM(N7:AS7) -> 2667 | BY7: CORRUGATED DISPATCH STEEL DRUM 2200 X 800 X 965 MM | BZ7: 480 | CA7: =Sheet1!CZ3 -> 1800 | CB7: =(((BZ7*90)/(CA7/1000))/2)/2 -> 6000 | CC7: =SUMPRODUCT($N$4:$BU$4,N7:BU7)+CB7 -> 561789 | CD7: =Sheet1!CB3 -> 0 | CE7: =CC7*CD7 -> 0 | CF7: 0.04 | CG7: =CC7*CF7 -> 22471.56 | CH7: =Sheet1!CF3 -> 0 | CI7: =CC7*CH7 -> 0 | CJ7: =CC7+CE7+CG7+CI7 -> 584260.56 | CK7: 0.01 | CL7: =CJ7*CK7 -> 5842.6056 | CM7: 0.005 | CN7: =CJ7*CM7 -> 2921.3028 | CO7: =Sheet1!CM3 -> 0 | CP7: =CJ7*CO7 -> 0
A8: =Sheet1!A4 -> ENQ-13581-22-23 | B8: =Sheet1!B4 -> 45474 | C8: =Sheet1!C4 -> FC6100001 | D8: =Sheet1!D4 -> ACSR : ZEBRA CONDUCTOR - 420 SQ. MM. (54/7/3.18) | E8: =CJ8+CL8+CN8 -> 331604.07 | F8: =ROUNDUP(M17,0) -> 5040 | G8: =E8+F8 -> 336644.07 | H8: =Sheet1!CR4 -> 0.18 | I8: =G8*H8 -> 60595.933 | J8: =G8+I8 -> 397240.01 | K8: =Sheet1!CU4 -> 250 | L8: =Sheet1!CV4 -> KMS | M8: =J8*K8 -> 99310001 | N8: =+IFERROR(VLOOKUP($N$3,Sheet1!J4:L4,3,0),0) -> 1186 | O8: =+IFERROR(VLOOKUP($O$3,Sheet1!J4:L4,3,0),0) -> 0 | P8: =+IFERROR(VLOOKUP($P$3,Sheet1!J4:M4,3,0),0) -> 0 | Q8: =+IFERROR(VLOOKUP($Q$3,Sheet1!J4:M4,3,0),0) -> 0 | R8: =+IFERROR(VLOOKUP($R$3,Sheet1!J4:M4,3,0),0) -> 0 | S8: =+IFERROR(VLOOKUP($S$3,Sheet1!N4:Q4,3,0),0) -> 0 | T8: =+IFERROR(VLOOKUP($T$3,Sheet1!N4:Q4,3,0),0) -> 0 | U8: =+IFERROR(VLOOKUP($U$3,Sheet1!F4:I4,3,0),0) -> 0 | V8: =+IFERROR(VLOOKUP($V$3,Sheet1!F4:I4,3,0),0) -> 0 | W8: =+IFERROR(VLOOKUP($W$3,Sheet1!F4:I4,3,0),0) -> 0 | X8: =+IFERROR(VLOOKUP($X$3,Sheet1!F4:I4,3,0),0) -> 0 | Y8: =+IFERROR(VLOOKUP($Y$3,Sheet1!F4:I4,3,0),0) -> 0 | Z8: =+IFERROR(VLOOKUP($Z$3,Sheet1!F4:I4,3,0),0) -> 0 | AA8: =+IFERROR(VLOOKUP($AA$3,Sheet1!F4:I4,3,0),0) -> 0 | AB8: =+IFERROR(VLOOKUP($AB$3,Sheet1!F4:I4,3,0),0) -> 0 | AC8: =+IFERROR(VLOOKUP($AC$3,Sheet1!R4:U4,3,0),0) -> 0 | AD8: =+IFERROR(VLOOKUP($AD$3,Sheet1!R4:U4,3,0),0) -> 0 | AE8: =+IFERROR(VLOOKUP($AE$3,Sheet1!V4:Y4,3,0),0) -> 0 | AF8: =+IFERROR(VLOOKUP($AF$3,Sheet1!V4:Y4,3,0),0) -> 0 | AG8: =+IFERROR(VLOOKUP($AG$3,Sheet1!V4:Y4,3,0),0) -> 0 | AH8: =+IFERROR(VLOOKUP($AH$3,Sheet1!V4:Y4,3,0),0) -> 0 | AI8: =+IFERROR(VLOOKUP($AI$3,Sheet1!V4:Y4,3,0),0) -> 0 | AJ8: =+IFERROR(VLOOKUP($AJ$3,Sheet1!V4:Y4,3,0),0) -> 0 | AK8: =+IFERROR(VLOOKUP($AK$3,Sheet1!Z4:AB4,3,0),0) -> 0 | AL8: =+IFERROR(VLOOKUP($AL$3,Sheet1!AD4:AG4,3,0),0) -> 0 | AM8: =+IFERROR(VLOOKUP($AM$3,Sheet1!AD4:AG4,3,0),0) -> 0 | AN8: =+IFERROR(VLOOKUP($AN$3,Sheet1!AD4:AG4,3,0),0) -> 0 | AO8: =+IFERROR(VLOOKUP($AO$3,Sheet1!AD4:AG4,3,0),0) -> 0 | AP8: =+IFERROR(VLOOKUP($AP$3,Sheet1!AD4:AG4,3,0),0) -> 0 | AQ8: =+IFERROR(VLOOKUP($AQ$3,Sheet1!AD4:AG4,3,0),0) -> 0 | AR8: =+IFERROR(VLOOKUP($AR$3,Sheet1!AD4:AG4,3,0),0) -> 0 | AS8: =+IFERROR(VLOOKUP($AS$3,Sheet1!AH4:AK4,3,0),0) -> 436 | AT8: =+IFERROR(VLOOKUP($AT$3,Sheet1!AH4:AK4,3,0),0) -> 0 | AU8: =+IFERROR(VLOOKUP($AU$3,Sheet1!AH4:AK4,3,0),0) -> 0 | AV8: =+IFERROR(VLOOKUP($AV$3,Sheet1!AH4:AK4,3,0),0) -> 0 | AW8: =+IFERROR(VLOOKUP($AW$3,Sheet1!AH4:AK4,3,0),0) -> 0 | AX8: =+IFERROR(VLOOKUP($AX$3,Sheet1!AH4:AK4,3,0),0) -> 0 | AY8: =+IFERROR(VLOOKUP($AY$3,Sheet1!AH4:AK4,3,0),0) -> 0 | AZ8: =+IFERROR(VLOOKUP($AZ$3,Sheet1!AH4:AK4,3,0),0) -> 0 | BA8: =+IFERROR(VLOOKUP($BA$3,Sheet1!AH4:AK4,3,0),0) -> 0 | BB8: =+IFERROR(VLOOKUP($BB$3,Sheet1!AH4:AK4,3,0),0) -> 0 | BC8: =+IFERROR(VLOOKUP($BC$3,Sheet1!AL4:AO4,3,0),0) -> 0 | BD8: =+IFERROR(VLOOKUP($BD$3,Sheet1!AL4:AO4,3,0),0) -> 0 | BE8: =+IFERROR(VLOOKUP($BE$3,Sheet1!AL4:AO4,3,0),0) -> 0 | BF8: =+IFERROR(VLOOKUP($BF$3,Sheet1!AL4:AO4,3,0),0) -> 0 | BG8: =+IFERROR(VLOOKUP($BG$3,Sheet1!AL4:AO4,3,0),0) -> 0 | BH8: =+IFERROR(VLOOKUP($BH$3,Sheet1!AL4:AO4,3,0),0) -> 0 | BI8: =+IFERROR(VLOOKUP($BI$3,Sheet1!AL4:AO4,3,0),0) -> 0 | BJ8: =+IFERROR(VLOOKUP($BJ$3,Sheet1!AL4:AO4,3,0),0) -> 0 | BK8: =+IFERROR(VLOOKUP($BK$3,Sheet1!AL4:AO4,3,0),0) -> 0 | BL8: =+IFERROR(VLOOKUP($BL$3,Sheet1!AL4:AO4,3,0),0) -> 0 | BM8: =+IFERROR(VLOOKUP($BM$3,Sheet1!AP4:AS4,3,0),0) -> 0 | BN8: =+IFERROR(VLOOKUP($BN$3,Sheet1!AT4:AW4,3,0),0) -> 0 | BO8: =+IFERROR(VLOOKUP($BO$3,Sheet1!AX4:BA4,3,0),0) -> 0 | BP8: =+IFERROR(VLOOKUP($BP$3,Sheet1!BB4:BE4,3,0),0) -> 0 | BQ8: =+IFERROR(VLOOKUP($BQ$3,Sheet1!BF4:BI4,3,0),0) -> 0 | BR8: =+IFERROR(VLOOKUP($BR$3,Sheet1!BJ4:BM4,3,0),0) -> 0 | BS8: =+IFERROR(VLOOKUP($BS$3,Sheet1!BN4:BQ4,3,0),0) -> 0 | BT8: =+IFERROR(VLOOKUP($BT$3,Sheet1!BR4:BU4,3,0),0) -> 0 | BU8: =+IFERROR(VLOOKUP($BU$3,Sheet1!BV4:BY4,3,0),0) -> 0 | BV8: =Sheet1!E4 -> STEEL | BW8: =SUM(N8:AS8) -> 1622 | BY8: CORRUGATED DISPATCH STEEL DRUM 2200 X 800 X 965 MM | BZ8: 480 | CA8: =Sheet1!CZ4 -> 3000 | CB8: =(((BZ8*90)/(CA8/1000))/2)/2 -> 3600 | CC8: =SUMPRODUCT($N$4:$BU$4,N8:BU8)+CB8 -> 314138 | CD8: =Sheet1!CB4 -> 0 | CE8: =CC8*CD8 -> 0 | CF8: 0.04 | CG8: =CC8*CF8 -> 12565.52 | CH8: =Sheet1!CF4 -> 0 | CI8: =CC8*CH8 -> 0 | CJ8: =CC8+CE8+CG8+CI8 -> 326703.52 | CK8: 0.01 | CL8: =CJ8*CK8 -> 3267.0352 | CM8: 0.005 | CN8: =CJ8*CM8 -> 1633.5176 | CO8: =Sheet1!CM4 -> 0 | CP8: =CJ8*CO8 -> 0
A9: =Sheet1!A6 -> ENQ-13581-22-23 | B9: =Sheet1!B6 -> 45474 | C9: =Sheet1!C6 -> FC3700003 | D9: =Sheet1!D6 -> ACSR : PANTHER CONDUCTOR - 200 SQ. MM. (30/7/3.00) | E9: =CJ9+CL9+CN9 -> 178328.62 | F9: =ROUNDUP(M18,0) -> 2900 | G9: =E9+F9 -> 181228.62 | H9: =Sheet1!CR6 -> 0.18 | I9: =G9*H9 -> 32621.151 | J9: =G9+I9 -> 213849.77 | K9: =Sheet1!CU6 -> 1200 | L9: =Sheet1!CV6 -> KMS | M9: =J9*K9 -> 2.5661972e+08 | N9: =+IFERROR(VLOOKUP($N$3,Sheet1!J6:L6,3,0),0) -> 588.5 | O9: =+IFERROR(VLOOKUP($O$3,Sheet1!J6:L6,3,0),0) -> 0 | P9: =+IFERROR(VLOOKUP($P$3,Sheet1!J6:M6,3,0),0) -> 0 | Q9: =+IFERROR(VLOOKUP($Q$3,Sheet1!J6:M6,3,0),0) -> 0 | R9: =+IFERROR(VLOOKUP($R$3,Sheet1!J6:M6,3,0),0) -> 0 | S9: =+IFERROR(VLOOKUP($S$3,Sheet1!N6:Q6,3,0),0) -> 0 | T9: =+IFERROR(VLOOKUP($T$3,Sheet1!N6:Q6,3,0),0) -> 0 | U9: =+IFERROR(VLOOKUP($U$3,Sheet1!F6:I6,3,0),0) -> 0 | V9: =+IFERROR(VLOOKUP($V$3,Sheet1!F6:I6,3,0),0) -> 0 | W9: =+IFERROR(VLOOKUP($W$3,Sheet1!F6:I6,3,0),0) -> 0 | X9: =+IFERROR(VLOOKUP($X$3,Sheet1!F6:I6,3,0),0) -> 0 | Y9: =+IFERROR(VLOOKUP($Y$3,Sheet1!F6:I6,3,0),0) -> 0 | Z9: =+IFERROR(VLOOKUP($Z$3,Sheet1!F6:I6,3,0),0) -> 0 | AA9: =+IFERROR(VLOOKUP($AA$3,Sheet1!F6:I6,3,0),0) -> 0 | AB9: =+IFERROR(VLOOKUP($AB$3,Sheet1!F6:I6,3,0),0) -> 0 | AC9: =+IFERROR(VLOOKUP($AC$3,Sheet1!R6:U6,3,0),0) -> 0 | AD9: =+IFERROR(VLOOKUP($AD$3,Sheet1!R6:U6,3,0),0) -> 0 | AE9: =+IFERROR(VLOOKUP($AE$3,Sheet1!V6:Y6,3,0),0) -> 0 | AF9: =+IFERROR(VLOOKUP($AF$3,Sheet1!V6:Y6,3,0),0) -> 0 | AG9: =+IFERROR(VLOOKUP($AG$3,Sheet1!V6:Y6,3,0),0) -> 0 | AH9: =+IFERROR(VLOOKUP($AH$3,Sheet1!V6:Y6,3,0),0) -> 0 | AI9: =+IFERROR(VLOOKUP($AI$3,Sheet1!V6:Y6,3,0),0) -> 0 | AJ9: =+IFERROR(VLOOKUP($AJ$3,Sheet1!V6:Y6,3,0),0) -> 0 | AK9: =+IFERROR(VLOOKUP($AK$3,Sheet1!Z6:AB6,3,0),0) -> 0 | AL9: =+IFERROR(VLOOKUP($AL$3,Sheet1!AD6:AG6,3,0),0) -> 0 | AM9: =+IFERROR(VLOOKUP($AM$3,Sheet1!AD6:AG6,3,0),0) -> 0 | AN9: =+IFERROR(VLOOKUP($AN$3,Sheet1!AD6:AG6,3,0),0) -> 0 | AO9: =+IFERROR(VLOOKUP($AO$3,Sheet1!AD6:AG6,3,0),0) -> 0 | AP9: =+IFERROR(VLOOKUP($AP$3,Sheet1!AD6:AG6,3,0),0) -> 0 | AQ9: =+IFERROR(VLOOKUP($AQ$3,Sheet1!AD6:AG6,3,0),0) -> 0 | AR9: =+IFERROR(VLOOKUP($AR$3,Sheet1!AD6:AG6,3,0),0) -> 0 | AS9: =+IFERROR(VLOOKUP($AS$3,Sheet1!AH6:AK6,3,0),0) -> 388 | AT9: =+IFERROR(VLOOKUP($AT$3,Sheet1!AH6:AK6,3,0),0) -> 0 | AU9: =+IFERROR(VLOOKUP($AU$3,Sheet1!AH6:AK6,3,0),0) -> 0 | AV9: =+IFERROR(VLOOKUP($AV$3,Sheet1!AH6:AK6,3,0),0) -> 0 | AW9: =+IFERROR(VLOOKUP($AW$3,Sheet1!AH6:AK6,3,0),0) -> 0 | AX9: =+IFERROR(VLOOKUP($AX$3,Sheet1!AH6:AK6,3,0),0) -> 0 | AY9: =+IFERROR(VLOOKUP($AY$3,Sheet1!AH6:AK6,3,0),0) -> 0 | AZ9: =+IFERROR(VLOOKUP($AZ$3,Sheet1!AH6:AK6,3,0),0) -> 0 | BA9: =+IFERROR(VLOOKUP($BA$3,Sheet1!AH6:AK6,3,0),0) -> 0 | BB9: =+IFERROR(VLOOKUP($BB$3,Sheet1!AH6:AK6,3,0),0) -> 0 | BC9: =+IFERROR(VLOOKUP($BC$3,Sheet1!AL6:AO6,3,0),0) -> 0 | BD9: =+IFERROR(VLOOKUP($BD$3,Sheet1!AL6:AO6,3,0),0) -> 0 | BE9: =+IFERROR(VLOOKUP($BE$3,Sheet1!AL6:AO6,3,0),0) -> 0 | BF9: =+IFERROR(VLOOKUP($BF$3,Sheet1!AL6:AO6,3,0),0) -> 0 | BG9: =+IFERROR(VLOOKUP($BG$3,Sheet1!AL6:AO6,3,0),0) -> 0 | BH9: =+IFERROR(VLOOKUP($BH$3,Sheet1!AL6:AO6,3,0),0) -> 0 | BI9: =+IFERROR(VLOOKUP($BI$3,Sheet1!AL6:AO6,3,0),0) -> 0 | BJ9: =+IFERROR(VLOOKUP($BJ$3,Sheet1!AL6:AO6,3,0),0) -> 0 | BK9: =+IFERROR(VLOOKUP($BK$3,Sheet1!AL6:AO6,3,0),0) -> 0 | BL9: =+IFERROR(VLOOKUP($BL$3,Sheet1!AL6:AO6,3,0),0) -> 0 | BM9: =+IFERROR(VLOOKUP($BM$3,Sheet1!AP6:AS6,3,0),0) -> 0 | BN9: =+IFERROR(VLOOKUP($BN$3,Sheet1!AT6:AW6,3,0),0) -> 0 | BO9: =+IFERROR(VLOOKUP($BO$3,Sheet1!AX6:BA6,3,0),0) -> 0 | BP9: =+IFERROR(VLOOKUP($BP$3,Sheet1!BB6:BE6,3,0),0) -> 0 | BQ9: =+IFERROR(VLOOKUP($BQ$3,Sheet1!BF6:BI6,3,0),0) -> 0 | BR9: =+IFERROR(VLOOKUP($BR$3,Sheet1!BJ6:BM6,3,0),0) -> 0 | BS9: =+IFERROR(VLOOKUP($BS$3,Sheet1!BN6:BQ6,3,0),0) -> 0 | BT9: =+IFERROR(VLOOKUP($BT$3,Sheet1!BR6:BU6,3,0),0) -> 0 | BU9: =+IFERROR(VLOOKUP($BU$3,Sheet1!BV6:BY6,3,0),0) -> 0 | BV9: =Sheet1!E6 -> WOOD | BW9: =SUM(N9:AS9) -> 976.5 | BY9: CORRUGATED DISPATCH STEEL DRUM 1800 X 800 X 915 MM | BZ9: 360 | CA9: =Sheet1!CZ6 -> 3500 | CB9: =(((BZ9*90)/(CA9/1000))/2)/2 -> 2314.2857 | CC9: =SUMPRODUCT($N$4:$BU$4,N9:BU9)+CB9 -> 168935.79 | CD9: =Sheet1!CB6 -> 0 | CE9: =CC9*CD9 -> 0 | CF9: 0.04 | CG9: =CC9*CF9 -> 6757.4314 | CH9: =Sheet1!CF6 -> 0 | CI9: =CC9*CH9 -> 0 | CJ9: =CC9+CE9+CG9+CI9 -> 175693.22 | CK9: 0.01 | CL9: =CJ9*CK9 -> 1756.9322 | CM9: 0.005 | CN9: =CJ9*CM9 -> 878.46609 | CO9: =Sheet1!CM6 -> 0 | CP9: =CJ9*CO9 -> 0
M10: =SUM(M5:M9) -> 9.2061965e+08 | CF10: DEVESH SIR INSTRUCTION OVERPHONE
E13: Order Quantity | F13: Stnd Length | G13: Truck type | H13: Fare of one truck | I13: No of Drum in one truck | J13: Total length in one Truck | K13: No of Truck | L13: Total Freight | M13: Freight per KM | BY13: conductor+drum weight in kg | BZ13: truck weight in kg
D14: =D5 -> ACSR : MOOSE CONDUCTOR - 520 SQ. MM. (54/7/3.53) | E14: =K5 -> 750 | F14: =CA5/1000 -> 2.4 | G14: 25 MT TRAILER | H14: 60000 | I14: 4 | J14: =F14*I14 -> 9.6 | K14: =ROUNDUP((E14/J14),0) -> 79 | L14: =M14*E14 -> 4740000 | M14: =(H14*K14)/E14 -> 6320 | BY14: =(SUM(N5:AS5)*F14)+BZ5 -> 5289.6 | BZ14: =BY14*I14 -> 21158.4
D15: =D6 -> ACSR : BERSIMIS CONDUCTOR - 690 SQ. MM. (42/4.57/7/2.54) | E15: =K6 -> 150 | F15: =CA6/1000 -> 2.1 | G15: 25 MT TRAILER | H15: 60000 | I15: 4 | J15: =F15*I15 -> 8.4 | K15: =ROUNDUP((E15/J15),0) -> 18 | L15: =M15*E15 -> 1080000 | M15: =(H15*K15)/E15 -> 7200 | BY15: =(SUM(N6:AS6)*F15)+BZ6 -> 5072.7 | BZ15: =BY15*I15 -> 20290.8
D16: =D7 -> ACSR : LAPWING CONDUCTOR - 804.1 SQ. MM. (45/4.77//7/3.18) | E16: =K7 -> 150 | F16: =CA7/1000 -> 1.8 | G16: 25 MT TRAILER | H16: 60000 | I16: 4 | J16: =F16*I16 -> 7.2 | K16: =ROUNDUP((E16/J16),0) -> 21 | L16: =M16*E16 -> 1260000 | M16: =(H16*K16)/E16 -> 8400 | BY16: =(SUM(N7:AS7)*F16)+BZ7 -> 5280.6 | BZ16: =BY16*I16 -> 21122.4
D17: =D8 -> ACSR : ZEBRA CONDUCTOR - 420 SQ. MM. (54/7/3.18) | E17: =K8 -> 250 | F17: =CA8/1000 -> 3 | G17: 25 MT TRAILER | H17: 60000 | I17: 4 | J17: =F17*I17 -> 12 | K17: =ROUNDUP((E17/J17),0) -> 21 | L17: =M17*E17 -> 1260000 | M17: =(H17*K17)/E17 -> 5040 | BY17: =(SUM(N8:AS8)*F17)+BZ8 -> 5346 | BZ17: =BY17*I17 -> 21384
D18: =D9 -> ACSR : PANTHER CONDUCTOR - 200 SQ. MM. (30/7/3.00) | E18: =K9 -> 1200 | F18: =CA9/1000 -> 3.5 | G18: 25 MT TRAILER | H18: 60000 | I18: 6 | J18: =F18*I18 -> 21 | K18: =ROUNDUP((E18/J18),0) -> 58 | L18: =M18*E18 -> 3480000 | M18: =(H18*K18)/E18 -> 2900 | BY18: =(SUM(N9:AS9)*F18)+BZ9 -> 3777.75 | BZ18: =BY18*I18 -> 22666.5
D21: Due date 05-08-2024 11:00:00 am and Opening dated 05-08-2024 11:30:00 am
D22: Extended due date 12-08-2024 and Opening dated 12-08-2024
D23: Freight Clause : The evaluation of bids shall be done considering the destination 500 km away from the works
D24: The payment of the inland transportation, In-transit insurance, and loading & unloading charges (F&I Charges) shall be made on actual distance basis. The computation of the distance for such payment shall be based on the shortest feasible distance by national highway, state highway, or other roads, in the order of preference, as indicated on such resources as internat websites like Google Maps, Map my India.
D25: Variable price : indices as on calendar month preceding the month of opening of bids.
D26: Ra Qualification Rule : 50% lowest Priced Technically Qualified Bidders.
D27: Evaluation Method : Total value wise evaluation
D28: Splitting : Total package award value shall be divided/split amongst two bidders L-1 and L-2 in the bid Splitting ratio of 60% and 40% respectively subject to the condition of matching the L1 bidder's price.
D29: Delivery : Commencement = 2nd month and Completion = 24th month. Completion schedule shall be progressively 24 months from NOA/GeM Contract Order. Which shall be extendable for a further period of 1 year on same rates, terms and Condition, on mutual consent.
D30: Payment :
D31: a) No initial advance is applicable.
D32: b) 90% of the Ex-works price shall be paid progressively after dispatch of the Goods and on submission of documents.
... D35: Incase of Ex-works supply of goods, GST shall be reimburse along with progressive payment on dispatch.

Sheet CONDUCTOR
B1: TENDER SUBMISSION DATE | C1: 45509
B2: Base Date | C2: 45478
B3: PV Terms | C3: Subscript '0' refers to indices as on Calendar month preceding the month of opening of Bids, for materials & labour Subscript '1' refers to indices as on Calendar month preceding the month of shipment, for material & labour
B4: PV FORMULA (IEEMA)
B5: P1 = Po x {0.15 + a x (A1/A0) + b x (B1/B0) + c x (C1/C0) + l x (L1/L0)} - P0
B8: P1 = Price adjustment amount, shipment-wise (if it works out negative, that would mean the amount to be recovered by the Purchaser from the supplier)
B9: P0 = Ex-works price of Conductor.
B10: A = Monthly average of "Aluminium LME SELLER Settlement Price including Premium of Al Ingots and Customs duty converted in Rs./MT" as published by IEEMA/Nationally recognized publised price index of EC Grade Aluminum Ingots acceptable to the purchaser, in case index is not publised by IEEMA.
B11: B = Nationally recognized published Price Index for High Carbon Steel acceptable to the Purchaser. B = Monthly Price exclusive of all duties of "High Tensile Galvanised Steel Wire (FE)" in Rs./MT as published by IEEMA/Nationally recognized published Price Index for High Tensile Galvanised Wire acceptable to the Purchaser, in case index is not published by IEEMA.
B12: C = Nationally recognized published Price Index for High Grade Electrolytic Zinc acceptable to the Purchaser.
B13: L = Indian field labour index - namely All India average consumer price index for Industrial Workers (monthly) (Base: 2001=100), as published by Labour Bureau, Shimla, Government of India (www.labourbureau.nic.in)
B15: a = Co-efficient for EC Grade Aluminium Ingots, which shall be 0.65
B16: b = Co-efficient for High Carbon Steel, which shall be 0.13
B17: c = Co-efficient for High Grade Electrolytic Zinc, which shall be 0.02
B18: l = Co-efficient for labour component, which shall be 0.05
B19: For bidders who intend to quote their prices based on High Tensile Galvanised Steel Wire, the coefficient for the same (i.e. coefficient 'b' for High Tensile Galvanised Steel Wire) shall be 0.15 and coefficient 'c' shall not be applicable.
B22: Item | C22: Calculation part | D22: Date of Inspection | E22: Applicable Date | J22: BASE DATE | O22: Co-efficient | S22: Ex-Work Po | T22: a x (A1/A0) | U22: b x (B1/B0) | V22: c x (C1/C0) | W22: l x (L1/L0) | X22: {0.15 + a x (A1/A0) + b x (B1/B0) + c x (C1/C0) + l x (L1/L0)} | Y22: P1 = Po x {0.15 + a x (A1/A0) + b x (B1/B0) + c x (C1/C0) + l x (L1/L0)} - P0 | Z22: Billing price/km | AA22: VALUE ADDITION CALCULATION
E23: Date | F23: A1 | G23: B1 | H23: C1 | I23: L1 | J23: Date | K23: Ao | L23: Bo | M23: Co | N23: Lo
O24: a | P24: b | Q24: c | R24: l | AA24: Al @ | AB24: ST @ | AC24: RMC | AD24: Drum | AE24: RMC+DRUM | AF24: VA | AG24: Groos VA% | AH24: Mfg % | AI24: Int % | AJ24: Ins% | AK24: Net VA
AA25: 243 | AB25: 73
B26: ACSR : MOOSE CONDUCTOR - 520 SQ. MM. (54/7/3.53) | D26: PROVISIONAL | E26: 45503 | J26: 45478 | O26: 0.65 | P26: 0.13 | Q26: 0.02 | R26: 0.05 | S26: ='AUTO CALCULATION SHEET (2)'!E5 -> 410043.6 | T26: =O26*(F26/K26) -> #DIV/0! | U26: =P26*(G26/L26) -> #DIV/0! | W26: =R26*(I26/N26) -> #DIV/0! | X26: =0.15+T26+U26+V26+W26 -> #DIV/0! | Y26: =(S26*X26)-S26 -> #DIV/0! | Z26: =S26+Y26 -> #DIV/0! | AA26: ='AUTO CALCULATION SHEET (2)'!N5 -> 1467 | AB26: ='AUTO CALCULATION SHEET (2)'!AS5 -> 537 | AC26: =SUMPRODUCT($AA$25:$AB$25,AA26:AB26) -> 395682 | AD26: ='AUTO CALCULATION SHEET (2)'!CB5 -> 4500 | AE26: =AC26+AD26 -> 400182 | AF26: =+Z26-AE26 -> #DIV/0! | AG26: =AF26/AE26*100% -> #DIV/0! | AI26: 0.03 | AJ26: 0.01 | AK26: =AG26-SUM(AH26:AJ26) -> #DIV/0!
B27: ACSR : BERSIMIS CONDUCTOR - 690 SQ. MM. (42/4.57/7/2.54) | D27: PROVISIONAL | E27: 45503 | J27: 45478 | O27: 0.65 | P27: 0.13 | Q27: 0.02 | R27: 0.05 | S27: ='AUTO CALCULATION SHEET (2)'!E6 -> 499896.12 | T27: =O27*(F27/K27) -> #DIV/0! | U27: =P27*(G27/L27) -> #DIV/0! | W27: =R27*(I27/N27) -> #DIV/0! | X27: =0.15+T27+U27+V27+W27 -> #DIV/0! | Y27: =(S27*X27)-S27 -> #DIV/0! | Z27: =S27+Y27 -> #DIV/0! | AA27: ='AUTO CALCULATION SHEET (2)'!N6 -> 1906 | AB27: ='AUTO CALCULATION SHEET (2)'!AS6 -> 281 | AC27: =SUMPRODUCT($AA$25:$AB$25,AA27:AB27) -> 483671 | AD27: ='AUTO CALCULATION SHEET (2)'!CB6 -> 5142.8571 | AE27: =AC27+AD27 -> 488813.86 | AF27: =+Z27-AE27 -> #DIV/0! | AG27: =AF27/AE27*100% -> #DIV/0! | AI27: 0.03 | AJ27: 0.01 | AK27: =AG27-SUM(AH27:AJ27) -> #DIV/0!
B28: ACSR : LAPWING CONDUCTOR - 804.1 SQ. MM. (45/4.77//7/3.18) | D28: PROVISIONAL | E28: 45503 | J28: 45478 | O28: 0.65 | P28: 0.13 | Q28: 0.02 | R28: 0.05 | S28: ='AUTO CALCULATION SHEET (2)'!E7 -> 593024.47 | T28: =O28*(F28/K28) -> #DIV/0! | U28: =P28*(G28/L28) -> #DIV/0! | W28: =R28*(I28/N28) -> #DIV/0! | X28: =0.15+T28+U28+V28+W28 -> #DIV/0! | Y28: =(S28*X28)-S28 -> #DIV/0! | Z28: =S28+Y28 -> #DIV/0! | AA28: ='AUTO CALCULATION SHEET (2)'!N7 -> 2229 | AB28: ='AUTO CALCULATION SHEET (2)'!AS7 -> 438 | AC28: =SUMPRODUCT($AA$25:$AB$25,AA28:AB28) -> 573621 | AD28: ='AUTO CALCULATION SHEET (2)'!CB7 -> 6000 | AE28: =AC28+AD28 -> 579621 | AF28: =+Z28-AE28 -> #DIV/0! | AG28: =AF28/AE28*100% -> #DIV/0! | AI28: 0.03 | AJ28: 0.01 | AK28: =AG28-SUM(AH28:AJ28) -> #DIV/0!
B29: ACSR : ZEBRA CONDUCTOR - 420 SQ. MM. (54/7/3.18) | D29: PROVISIONAL | E29: 45503 | J29: 45478 | O29: 0.65 | P29: 0.13 | Q29: 0.02 | R29: 0.05 | S29: ='AUTO CALCULATION SHEET (2)'!E8 -> 331604.07 | T29: =O29*(F29/K29) -> #DIV/0! | U29: =P29*(G29/L29) -> #DIV/0! | W29: =R29*(I29/N29) -> #DIV/0! | X29: =0.15+T29+U29+V29+W29 -> #DIV/0! | Y29: =(S29*X29)-S29 -> #DIV/0! | Z29: =S29+Y29 -> #DIV/0! | AA29: ='AUTO CALCULATION SHEET (2)'!N8 -> 1186 | AB29: ='AUTO CALCULATION SHEET (2)'!AS8 -> 436 | AC29: =SUMPRODUCT($AA$25:$AB$25,AA29:AB29) -> 320026 | AD29: ='AUTO CALCULATION SHEET (2)'!CB8 -> 3600 | AE29: =AC29+AD29 -> 323626 | AF29: =+Z29-AE29 -> #DIV/0! | AG29: =AF29/AE29*100% -> #DIV/0! | AI29: 0.03 | AJ29: 0.01 | AK29: =AG29-SUM(AH29:AJ29) -> #DIV/0!
B30: ACSR : PANTHER CONDUCTOR - 200 SQ. MM. (30/7/3.00) | D30: PROVISIONAL | E30: 45503 | J30: 45478 | O30: 0.65 | P30: 0.13 | Q30: 0.02 | R30: 0.05 | S30: ='AUTO CALCULATION SHEET (2)'!E9 -> 178328.62 | T30: =O30*(F30/K30) -> #DIV/0! | U30: =P30*(G30/L30) -> #DIV/0! | W30: =R30*(I30/N30) -> #DIV/0! | X30: =0.15+T30+U30+V30+W30 -> #DIV/0! | Y30: =(S30*X30)-S30 -> #DIV/0! | Z30: =S30+Y30 -> #DIV/0! | AA30: ='AUTO CALCULATION SHEET (2)'!N9 -> 588.5 | AB30: ='AUTO CALCULATION SHEET (2)'!AS9 -> 388 | AC30: =SUMPRODUCT($AA$25:$AB$25,AA30:AB30) -> 171329.5 | AD30: ='AUTO CALCULATION SHEET (2)'!CB9 -> 2314.2857 | AE30: =AC30+AD30 -> 173643.79 | AF30: =+Z30-AE30 -> #DIV/0! | AG30: =AF30/AE30*100% -> #DIV/0! | AI30: 0.03 | AJ30: 0.01 | AK30: =AG30-SUM(AH30:AJ30) -> #DIV/0!
