Workbook

Sheet Sheet1
A1: DOCKET NO. | B1: Base Date | C1: ITEM CODE | D1: PROPOSE ERP ITEM NAME | E1: Propose Drum Type | F1: Insulation Screening(Metallic) | G1: RM Rate(Insulation Screening(Metallic)) | H1: Weight (Insulation Screening (Metallic)) | I1: Cost Insulation Screening(Metallic) | J1: Conductor | K1: RM Rate(Conductor) | L1: Weight(Conductor) | M1: Cost(Conductor) | N1: AL ALLOY | O1: RM Rate(AL Alloy) | P1: Weight(Al Alloy) | Q1: Cost(AL Alloy) | R1: Insulation Screening(Non-Metallic) | S1: RM Rate(Insulation Screening(Non-Metallic)) | T1: Weight(Insulation Screening(Non-Metallic) | U1: Cost(Insulation Screening(Non-Metallic) | V1: Insulation | W1: RM Rate(Insulation) | X1: Weight(Insulation) | Y1: Cost(Insulation) | Z1: Poly Tape | AA1: RM Rate(Poly Tape) | AB1: Weight(Poly Tape) | AC1: Cost(Poly Tape) | AD1: Inner Sheath | AE1: RM Rate(Inner Sheath) | AF1: Weight(Inner Sheath) | AG1: Cost(Inner Sheath) | AH1: Armouring | AI1: RM Rate(Armouring) | AJ1: Weight(Armouring) | AK1: Cost(Armouring) | AL1: Outer Sheath | AM1: RM Rate(Outer Sheath) | AN1: Weight(Outer Sheath) | AO1: Cost(Outer Sheath) | AP1: Filler | AQ1: RM Rate(Filler) | AR1: Weight(Filler) | AS1: Cost(Filler) | AT1: Grease | AU1: RM Rate(Grease) | AV1: Weight(Grease) | AW1: Cost(Grease) | AX1: Water Swellable Tape | AY1: RM Rate(Water Swellable Tape) | AZ1: Weight(Water Swellable Tape) | BA1: Cost(Water Swellable Tape) | BB1: Semi Conducting Water Swellable Tape | BC1: RM Rate(Semi Conducting Water Swellable Tape) | BD1: Weight(Semi Conducting Water Swellable Tape) | BE1: Cost(Semi Conducting Water Swellable Tape) | BF1: Semicon Tape | BG1: RM Rate(Semicon Tape) | BH1: Weight(Semicon Tape) | BI1: Cost(Semicon Tape) | BJ1: Glass Fiber Tape | BK1: RM Rate(Glass Fiber Tape) | BL1: Weight(Glass Fiber Tape) | BM1: Cost(Glass Fiber Tape) | BN1: Copper Wire 0.8MM | BO1: RM Rate(Copper Wire 0.8MM) | BP1: Weight(Copper Wire 0.8MM) | BQ1: Cost(Copper Wire 0.8MM) | BR1: Rubberized Cotton Tape | BS1: RM Rate(Rubberized Cotton Tape) | BT1: Weight(Rubberized Cotton Tape) | BU1: Cost(Rubberized Cotton Tape) | BV1: Water Tight Compound | BW1: RM Rate(Water Tight Compound) | BX1: Weight(Water Tight Compound) | BY1: Cost(Water Tight Compound) | BZ1: Drum Cost Per KM | CA1: Total RM Cost | CB1: FIRM % | CC1: Firm Value | CD1: MFG% | CE1: MFG Value | CF1: PROF% | CG1: Profit Value | CH1: 1st EX-Works | CI1: Intt % | CJ1: Intt Value | CK1: insp% | CL1: Insp Value | CM1: TTR CHARGES% | CN1: TTR Value | CO1: EX-Works Per KM | CP1: Freight Per KM | CQ1: Price Including Freight Per KM | CR1: GST % | CS1: GST Value | CT1: Price Including GST & Freight Per KM | CU1: QTY | CV1: Unit | CW1: Total Price Of Full QTY(Including Freight&GST) | CX1: PARTY LENGTH (IF STANDER LENGTH NOT MATCH WITH PAR | CY1: DRUM CODE | CZ1: DRUM SIZE (FxbXtx Ft)
A2: ENQ-18390-25-26 | C2: FA1300009 | D2: 1 CORE X 300 SQ. MM. AL./ARM (XLPE) - 11 KV | E2: STEEL | F2: Copper Tape - 0.045 mm | H2: 41 | J2: Alumimium | L2: 810 | P2: 0 | R2: Extruded Semiconductive | T2: 112 | V2: HT-XLPE | X2: 267 | Z2: POLY TAPE | AB2: 0 | AD2: PVC Type ST-2 | AF2: 87 | AH2: Aluminium Round Wire | AJ2: 388 | AL2: FRLSH PVC Type ST-2 | AN2: 318 | AR2: 0 | AV2: 0 | AX2: Water swellable Tape | AZ2: 0 | BB2: Semi conducting Water Swellable tape | BD2: 38 | BH2: 0 | BL2: 0 | BP2: 0 | BR2: RUBBERIZED COTTON TAPE | BT2: 0 | BX2: 0 | BZ2: 27000 | CA2: 27000 | CH2: 27000 | CO2: 27000 | CQ2: 27000 | CR2: 0.18 | CS2: 4860 | CT2: 31860 | CU2: 3 | CV2: KMS | CW2: 95580 | CX2: 500 | CY2: SP0400152 | CZ2: CORRUGATED DISPATCH STEEL DRUM 1500 X 800 X 915
A3: ENQ-18390-25-26 | C3: FA1300016 | D3: 1 CORE X 630 SQ. MM. AL/ARM (XLPE) - 11 KV | E3: STEEL | F3: Copper Tape - 0.045 mm | H3: 54 | J3: Alumimium | L3: 1701 | P3: 0 | R3: Extruded Semiconductive | T3: 150 | V3: HT-XLPE | X3: 374 | Z3: POLY TAPE | AB3: 0 | AD3: PVC Type ST-2 | AF3: 134 | AH3: Aluminium Round Wire | AJ3: 511 | AL3: FRLSH PVC Type ST-2 | AN3: 472 | AR3: 0 | AV3: 0 | AX3: Water swellable Tape | AZ3: 0 | BB3: Semi conducting Water Swellable tape | BD3: 70 | BH3: 0 | BL3: 0 | BP3: 0 | BR3: RUBBERIZED COTTON TAPE | BT3: 0 | BX3: 0 | BZ3: 48450 | CA3: 48450 | CH3: 48450 | CO3: 48450 | CQ3: 48450 | CR3: 0.18 | CS3: 8721 | CT3: 57171 | CU3: 13 | CV3: KMS | CW3: 743223 | CX3: 500 | CY3: SP0400091 | CZ3: CORRUGATED DISPATCH STEEL DRUM 1800 X 900 X 1000
A4: ENQ-18390-25-26 | C4: FA1300018 | D4: 1 CORE X 400 SQ. MM. AL/ARM (XLPE) - 33 KV | E4: STEEL | F4: Copper Tape - 0.045 mm | H4: 60 | J4: Alumimium | L4: 1080 | P4: 0 | R4: Extruded Semiconductive | T4: 141 | V4: HT-XLPE | X4: 870 | Z4: POLY TAPE | AB4: 0 | AD4: PVC Type ST-2 | AF4: 147 | AH4: Aluminium Round Wire | AJ4: 702 | AL4: FRLSH PVC Type ST-2 | AN4: 575 | AR4: 0 | AV4: 0 | AX4: Water swellable Tape | AZ4: 54 | BB4: Semi conducting Water Swellable tape | BD4: 0 | BH4: 52 | BL4: 0 | BP4: 0 | BR4: RUBBERIZED COTTON TAPE | BT4: 0 | BX4: 0 | BZ4: 53200 | CA4: 53200 | CH4: 53200 | CO4: 53200 | CQ4: 53200 | CR4: 0.18 | CS4: 9576 | CT4: 62776 | CU4: 16 | CV4: KMS | CW4: 1004416 | CX4: 500 | CY4: SP0400112 | CZ4: CORRUGATED DISPATCH STEEL DRUM 2000 X 1000 X 1000 MM
A5: ENQ-18390-25-26 | C5: FA1300019 | D5: 1 CORE X 300 SQ. MM. AL/ARM (XLPE) - 33 KV | E5: STEEL | F5: Copper Tape - 0.045 mm | H5: 55 | J5: Alumimium | L5: 810 | P5: 0 | R5: Extruded Semiconductive | T5: 128 | V5: HT-XLPE | X5: 792 | Z5: POLY TAPE | AB5: 0 | AD5: PVC Type ST-2 | AF5: 138 | AH5: Aluminium Round Wire | AJ5: 648 | AL5: FRLSH PVC Type ST-2 | AN5: 542 | AR5: 0 | AV5: 0 | AX5: Water swellable Tape | AZ5: 0 | BB5: Semi conducting Water Swellable tape | BD5: 0 | BH5: 0 | BL5: 0 | BP5: 0 | BR5: RUBBERIZED COTTON TAPE | BT5: 0 | BX5: 0 | BZ5: 47500 | CA5: 47500 | CH5: 47500 | CO5: 47500 | CQ5: 47500 | CR5: 0.18 | CS5: 8550 | CT5: 56050 | CU5: 3 | CV5: KMS | CW5: 168150 | CX5: 500 | CY5: SP0400110 | CZ5: CORRUGATED DISPATCH STEEL DRUM 1600 X 900 X 1000 MM
A6: ENQ-18390-25-26 | C6: FA1300022 | D6: 3 CORE X 50 SQ. MM. AL/ARD - WIRE (XLPE) - 33 KV (E) | E6: STEEL | F6: Copper Tape - 0.045 mm | J6: Alumimium | R6: Extruded Semiconductive | V6: HT-XLPE | AD6: PVC Type ST-2-PRESSURE EXTRUDED | AH6: Galvanised Steel Round Wire | AL6: FRLSH PVC Type ST-2 | AP6: Polypropylene Filler | AX6: Water swellable Tape | BB6: Semi conducting Water Swellable tape | BR6: RUBBERIZED COTTON TAPE | BZ6: 106400 | CA6: 106400 | CH6: 106400 | CO6: 106400 | CQ6: 106400 | CR6: 0.18 | CS6: 19152 | CT6: 125552 | CU6: 2.5 | CV6: KMS | CW6: 313880 | CX6: 250 | CY6: SP0400112 | CZ6: CORRUGATED DISPATCH STEEL DRUM 2000 X 1000 X 1000 MM
A7: ENQ-18390-25-26 | C7: FA1300027 | D7: 1 CORE X 630 SQ. MM. AL/ARM (XLPE) - 33 KV | E7: STEEL | F7: Copper Tape - 0.045 mm | H7: 69 | J7: Alumimium | L7: 1701 | P7: 0 | R7: Extruded Semiconductive | T7: 172 | V7: HT-XLPE | X7: 1040 | Z7: POLY TAPE | AB7: 0 | AD7: PVC Type ST-2 | AF7: 193 | AH7: Aluminium Round Wire | AJ7: 800 | AL7: FRLSH PVC Type ST-2 | AN7: 738 | AR7: 0 | AV7: 0 | AX7: Water swellable Tape | AZ7: 0 | BB7: Semi conducting Water Swellable tape | BD7: 0 | BH7: 0 | BL7: 0 | BP7: 0 | BR7: RUBBERIZED COTTON TAPE | BT7: 0 | BX7: 0 | BZ7: 53200 | CA7: 53200 | CH7: 53200 | CO7: 53200 | CQ7: 53200 | CR7: 0.18 | CS7: 9576 | CT7: 62776 | CU7: 105 | CV7: KMS | CW7: 6591480 | CX7: 500 | CY7: SP0400123 | CZ7: CORRUGATED DISPATCH STEEL DRUM 2000 X 1000 X 1200 MM
A8: ENQ-18390-25-26 | C8: FA1300047 | D8: 1 CORE X 400 SQ. MM. AL/ARM (XLPE) - 11 KV | E8: STEEL | F8: Copper Tape - 0.045 mm | H8: 45 | J8: Alumimium | L8: 1080 | P8: 0 | R8: Extruded Semiconductive | T8: 122 | V8: HT-XLPE | X8: 305 | AB8: 0 | AD8: PVC Type ST-2 | AF8: 96 | AH8: Aluminium Round Wire | AJ8: 423 | AL8: FRLSH PVC Type ST-2 | AN8: 376 | AR8: 0 | AV8: 0 | AX8: Water swellable Tape | AZ8: 0 | BB8: Semi conducting Water Swellable tape | BD8: 54 | BH8: 0 | BL8: 0 | BP8: 0 | BT8: 0 | BX8: 0 | BZ8: 34200 | CA8: 34200 | CH8: 34200 | CO8: 34200 | CQ8: 34200 | CR8: 0.18 | CS8: 6156 | CT8: 40356 | CU8: 6.5 | CV8: KMS | CW8: 262314 | CX8: 500 | CY8: SP0400125 | CZ8: CORRUGATED DISPATCH STEEL DRUM 1600 X 700 X 915 MM
A9: ENQ-18390-25-26 | C9: FA1300066 | D9: 1 CORE X 1000 SQ. MM. AL/ARM (XLPE) - 11 KV | E9: STEEL | F9: Copper Tape - 0.045 mm | H9: 66 | J9: Alumimium | L9: 2732 | P9: 0 | R9: Extruded Semiconductive | T9: 200 | V9: HT-XLPE | X9: 465 | Z9: POLY TAPE | AB9: 0 | AD9: PVC Type ST-2 | AF9: 185 | AH9: Aluminium Round Wire | AJ9: 773 | AL9: FRLSH PVC Type ST-2 | AN9: 655 | AR9: 0 | AV9: 0 | AX9: Water swellable Tape | AZ9: 0 | BB9: Semi conducting Water Swellable tape | BD9: 99 | BH9: 59 | BL9: 0 | BP9: 0 | BR9: RUBBERIZED COTTON TAPE | BT9: 52 | BX9: 0 | BZ9: 66500 | CA9: 66500 | CH9: 66500 | CO9: 66500 | CQ9: 66500 | CR9: 0.18 | CS9: 11970 | CT9: 78470 | CU9: 7.5 | CV9: KMS | CW9: 588525 | CX9: 500 | CY9: SP0400107 | CZ9: CORRUGATED DISPATCH STEEL DRUM 2150 X 1080 X 1240 MM
A10: ENQ-18390-25-26 | C10: FA1300079 | D10: 3 CORE X 185 SQ. MM AL/ARM - WIRE (XLPE) - 33 KV | E10: STEEL | F10: Copper Tape - 0.045 mm | H10: 149 | J10: Alumimium | L10: 1499 | P10: 0 | R10: Extruded Semiconductive | T10: 326 | V10: HT-XLPE | X10: 2040 | AB10: 0 | AD10: PVC Type ST-2-PRESSURE EXTRUDED | AF10: 335 | AH10: Galvanised Steel Round Wire | AJ10: 5745 | AL10: FRLSH PVC Type ST-2 | AN10: 1411 | AP10: Polypropylene Filler | AR10: 1838 | AV10: 0 | AX10: Water swellable Tape | AZ10: 0 | BB10: Semi conducting Water Swellable tape | BD10: 0 | BH10: 0 | BL10: 0 | BP10: 0 | BR10: RUBBERIZED COTTON TAPE | BT10: 0 | BX10: 0 | BZ10: 171000 | CA10: 171000 | CH10: 171000 | CO10: 171000 | CQ10: 171000 | CR10: 0.18 | CS10: 30780 | CT10: 201780 | CU10: 28.5 | CV10: KMS | CW10: 5750730 | CX10: 250 | CY10: SP0400081 | CZ10: CORRUGATED DISPATCH STEEL DRUM 2500 X 1400 X 1250 MM
A11: ENQ-18390-25-26 | C11: FA1300080 | D11: 3 CORE X 400 SQ. MM AL/ARM - WIRE (XLPE) - 33 KV | E11: STEEL | F11: Copper Tape - 0.045 mm | H11: 179 | J11: Alumimium | L11: 3240 | P11: 0 | R11: Extruded Semiconductive | T11: 427 | V11: HT-XLPE | X11: 2621 | AB11: 0 | AD11: PVC Type ST-2-PRESSURE EXTRUDED | AF11: 405 | AH11: Galvanised Steel Round Wire | AJ11: 6975 | AL11: FRLSH PVC Type ST-2 | AN11: 1660 | AP11: Polypropylene Filler | AR11: 2672 | AV11: 0 | AX11: Water swellable Tape | AZ11: 120 | BB11: Semi conducting Water Swellable tape | BD11: 0 | BH11: 144 | BL11: 0 | BP11: 0 | BR11: RUBBERIZED COTTON TAPE | BT11: 0 | BX11: 0 | BZ11: 190000 | CA11: 190000 | CH11: 190000 | CO11: 190000 | CQ11: 190000 | CR11: 0.18 | CS11: 34200 | CT11: 224200 | CU11: 321.5 | CV11: KMS | CW11: 72080300 | CX11: 250 | CY11: SP0400137 | CZ11: CORRUGATED DISPATCH STEEL DRUM 2600 X 1600 X 1600 MM
A12: ENQ-18390-25-26 | C12: FA1300081 | D12: 3 CORE X 300 SQ. MM. AL/ARM - WIRE (XLPE) - 33 KV | E12: STEEL | F12: Copper Tape - 0.045 mm | H12: 165 | J12: Alumimium | L12: 2430 | P12: 0 | R12: Extruded Semiconductive | T12: 386 | V12: HT-XLPE | X12: 2385 | AB12: 0 | AD12: PVC Type ST-2-PRESSURE EXTRUDED | AF12: 378 | AH12: Galvanised Steel Round Wire | AJ12: 6463 | AL12: FRLSH PVC Type ST-2 | AN12: 1558 | AP12: Polypropylene Filler | AR12: 2315 | AV12: 0 | AX12: Water swellable Tape | AZ12: 0 | BB12: Semi conducting Water Swellable tape | BD12: 0 | BH12: 0 | BL12: 0 | BP12: 0 | BR12: RUBBERIZED COTTON TAPE | BT12: 0 | BX12: 0 | BZ12: 190000 | CA12: 190000 | CH12: 190000 | CO12: 190000 | CQ12: 190000 | CR12: 0.18 | CS12: 34200 | CT12: 224200 | CU12: 45 | CV12: KMS | CW12: 10089000 | CX12: 250 | CY12: SP0400137 | CZ12: CORRUGATED DISPATCH STEEL DRUM 2600 X 1600 X 1600
A13: ENQ-18390-25-26 | C13: FA1300083 | D13: 3 CORE X 400 SQ. MM. AL/ARM - WIRE (XLPE) - 11 KV | E13: STEEL | F13: Copper Tape - 0.045 mm | H13: 136 | J13: Alumimium | L13: 3240 | P13: 0 | R13: Extruded Semiconductive | T13: 366 | V13: HT-XLPE | X13: 908 | AB13: 0 | AD13: PVC Type ST-2-PRESSURE EXTRUDED | AF13: 305 | AH13: Galvanised Steel Round Wire | AJ13: 5335 | AL13: FRLSH PVC Type ST-2 | AN13: 1308 | AP13: Polypropylene Filler | AR13: 1535 | AV13: 0 | AX13: Water swellable Tape | AZ13: 0 | BB13: Semi conducting Water Swellable tape | BD13: 64 | BH13: 0 | BL13: 0 | BP13: 0 | BR13: RUBBERIZED COTTON TAPE | BT13: 0 | BX13: 0 | BZ13: 182400 | CA13: 182400 | CH13: 182400 | CO13: 182400 | CQ13: 182400 | CR13: 0.18 | CS13: 32832 | CT13: 215232 | CU13: 209 | CV13: KMS | CW13: 44983488 | CX13: 250 | CY13: SP0400105 | CZ13: CORRUGATED DISPATCH STEEL DRUM 2500 X 1500 X 1400
A14: ENQ-18390-25-26 | C14: FA1300090 | D14: 3 CORE X 185 SQ. MM AL/ARM - WIRE (XLPE) - 11 KV | E14: STEEL | F14: Copper Tape - 0.045 mm | H14: 105 | J14: Alumimium | L14: 1499 | P14: 0 | R14: Extruded Semiconductive | T14: 276 | V14: HT-XLPE | X14: 663 | AB14: 0 | AD14: PVC Type ST-2-PRESSURE EXTRUDED | AF14: 237 | AH14: Galvanised Steel Round Wire | AJ14: 3244 | AL14: FRLSH PVC Type ST-2 | AN14: 862 | AP14: Polypropylene Filler | AR14: 914 | AV14: 0 | AX14: Water swellable Tape | AZ14: 0 | BB14: Semi conducting Water Swellable tape | BD14: 0 | BH14: 0 | BL14: 0 | BP14: 0 | BR14: RUBBERIZED COTTON TAPE | BT14: 0 | BX14: 0 | BZ14: 76000 | CA14: 76000 | CH14: 76000 | CO14: 76000 | CQ14: 76000 | CR14: 0.18 | CS14: 13680 | CT14: 89680 | CU14: 17 | CV14: KMS | CW14: 1524560 | CX14: 250 | CY14: SP0400111 | CZ14: CORRUGATED DISPATCH STEEL DRUM 1900 X 1000 X 1000 MM
A15: ENQ-18390-25-26 | C15: FA1300091 | D15: 3 CORE X 300 SQ. MM. AL/ARM - WIRE (XLPE) - 11 KV | E15: STEEL | F15: Copper Tape - 0.045 mm | H15: 122 | J15: Alumimium | L15: 2430 | P15: 0 | R15: Extruded Semiconductive | T15: 337 | V15: HT-XLPE | X15: 802 | AB15: 0 | AD15: PVC Type ST-2-PRESSURE EXTRUDED | AF15: 277 | AH15: Galvanised Steel Round Wire | AJ15: 3753 | AL15: FRLSH PVC Type ST-2 | AN15: 1120 | AP15: Polypropylene Filler | AR15: 1258 | AV15: 0 | AX15: Water swellable Tape | AZ15: 0 | BB15: Semi conducting Water Swellable tape | BD15: 115 | BH15: 34 | BL15: 0 | BP15: 0 | BR15: RUBBERIZED COTTON TAPE | BT15: 0 | BX15: 0 | BZ15: 171000 | CA15: 171000 | CH15: 171000 | CO15: 171000 | CQ15: 171000 | CR15: 0.18 | CS15: 30780 | CT15: 201780 | CU15: 151 | CV15: KMS | CW15: 30468780 | CX15: 250 | CY15: SP0400136 | CZ15: CORRUGATED DISPATCH STEEL DRUM 2200 X 1300 X 1200 MM
A16: ENQ-18390-25-26 | C16: FA1300097 | D16: 3 CORE X 70 SQ. MM. AL/ARM - WIRE (XLPE) - 11 KV | E16: STEEL | F16: Copper Tape - 0.045 mm | H16: 80 | J16: Alumimium | L16: 567 | P16: 0 | R16: Extruded Semiconductive | T16: 188 | V16: HT-XLPE | X16: 474 | AB16: 0 | AD16: PVC Type ST-2-PRESSURE EXTRUDED | AF16: 142 | AH16: Galvanised Steel Round Wire | AJ16: 1964 | AL16: FRLSH PVC Type ST-2 | AN16: 557 | AP16: Polypropylene Filler | AR16: 533 | AV16: 0 | AX16: Water swellable Tape | AZ16: 0 | BB16: Semi conducting Water Swellable tape | BD16: 0 | BH16: 22 | BL16: 0 | BP16: 0 | BR16: RUBBERIZED COTTON TAPE | BT16: 0 | BX16: 0 | BZ16: 92000 | CA16: 92000 | CH16: 92000 | CO16: 92000 | CQ16: 92000 | CR16: 0.18 | CS16: 16560 | CT16: 108560 | CU16: 5.5 | CV16: KMS | CW16: 597080 | CX16: 250 | CY16: SP0400110 | CZ16: CORRUGATED DISPATCH STEEL DRUM 1600 X 900 X 1000 MM
A17: ENQ-18390-25-26 | C17: FA1300098 | D17: 3 CORE X 95 SQ. MM. AL/ARM - WIRE (XLPE) - 11 KV | E17: STEEL | F17: Copper Tape - 0.045 mm | H17: 86 | J17: Alumimium | L17: 770 | P17: 0 | R17: Extruded Semiconductive | T17: 205 | V17: HT-XLPE | X17: 520 | AB17: 0 | AD17: PVC Type ST-2-PRESSURE EXTRUDED | AF17: 173 | AH17: Galvanised Steel Round Wire | AJ17: 2124 | AL17: FRLSH PVC Type ST-2 | AN17: 635 | AP17: Polypropylene Filler | AR17: 613 | AV17: 0 | AX17: Water swellable Tape | AZ17: 75 | BB17: Semi conducting Water Swellable tape | BD17: 0 | BH17: 45 | BL17: 0 | BP17: 0 | BR17: RUBBERIZED COTTON TAPE | BT17: 35 | BX17: 0 | BZ17: 95000 | CA17: 95000 | CH17: 95000 | CO17: 95000 | CQ17: 95000 | CR17: 0.18 | CS17: 17100 | CT17: 112100 | CU17: 25.5 | CV17: KMS | CW17: 2858550 | CX17: 250 | CY17: SP0400118 | CZ17: CORRUGATED DISPATCH STEEL DRUM 1700 X 1000 X 1200
A18: ENQ-18390-25-26 | C18: FA1300114 | D18: 3 CORE X 35 SQ. MM. AL/ARM - WIRE (XLPE) - 11 KV | H18: 0 | L18: 284 | P18: 0 | T18: 150 | X18: 384 | AB18: 0 | AF18: 122 | AJ18: 1360 | AN18: 437 | AR18: 390 | AV18: 0 | AZ18: 0 | BD18: 0 | BH18: 0 | BL18: 0 | BP18: 0 | BT18: 0 | BX18: 0 | CR18: 0.18 | CU18: 7.5 | CV18: KMS | CX18: 250
A19: ENQ-18390-25-26 | C19: FA1300120 | D19: 3 CORE X 70 SQ. MM. AL/ARM - WIRE (XLPE) - 33 KV | E19: STEEL | F19: Copper Tape - 0.045 mm | H19: 134 | J19: Alumimium | L19: 567 | P19: 0 | R19: Extruded Semiconductive | T19: 245 | V19: HT-XLPE | X19: 1561 | AB19: 0 | AD19: PVC Type ST-2-PRESSURE EXTRUDED | AF19: 280 | AH19: Galvanised Steel Round Wire | AJ19: 3818 | AL19: FRLSH PVC Type ST-2 | AN19: 1124 | AP19: Polypropylene Filler | AR19: 1267 | AV19: 0 | AX19: Water swellable Tape | AZ19: 0 | BB19: Semi conducting Water Swellable tape | BD19: 0 | BH19: 0 | BL19: 0 | BP19: 0 | BR19: RUBBERIZED COTTON TAPE | BT19: 0 | BX19: 0 | BZ19: 171000 | CA19: 171000 | CH19: 171000 | CO19: 171000 | CQ19: 171000 | CR19: 0.18 | CS19: 30780 | CT19: 201780 | CU19: 2 | CV19: KMS | CW19: 403560 | CX19: 250 | CY19: SP0400136 | CZ19: CORRUGATED DISPATCH STEEL DRUM 2200 X 1300 X 1200 MM
A20: ENQ-18390-25-26 | C20: FA1300176 | D20: 3 CORE X 150 SQ. MM. AL/ARM - WIRE (XLPE) - 11 KV | E20: STEEL | F20: Copper Tape - 0.045 mm | H20: 99 | J20: Alumimium | L20: 1215 | P20: 0 | R20: Extruded Semiconductive | T20: 246 | V20: HT-XLPE | X20: 620 | AB20: 0 | AD20: PVC Type ST-2-PRESSURE EXTRUDED | AF20: 200 | AH20: Galvanised Steel Round Wire | AJ20: 2404 | AL20: FRLSH PVC Type ST-2 | AN20: 755 | AP20: Polypropylene Filler | AR20: 809 | AV20: 0 | AX20: Water swellable Tape | AZ20: 0 | BB20: Semi conducting Water Swellable tape | BD20: 162 | BH20: 0 | BL20: 0 | BP20: 0 | BR20: RUBBERIZED COTTON TAPE | BT20: 0 | BX20: 0 | BZ20: 108300 | CA20: 108300 | CH20: 108300 | CO20: 108300 | CQ20: 108300 | CR20: 0.18 | CS20: 19494 | CT20: 127794 | CU20: 4 | CV20: KMS | CW20: 511176 | CX20: 250 | CY20: SP0400111 | CZ20: CORRUGATED DISPATCH STEEL DRUM 1900 X 1000 X 1000 MM
A21: ENQ-18390-25-26 | C21: FA1300197 | D21: 3 CORE X 120 SQ. MM. AL/ARM - WIRE (XLPE) - 11 KV | E21: STEEL | F21: Copper Tape - 0.045 mm | H21: 93 | J21: Alumimium | L21: 972 | P21: 0 | R21: Extruded Semiconductive | T21: 232 | V21: HT-XLPE | X21: 567 | AB21: 0 | AD21: PVC Type ST-2-PRESSURE EXTRUDED | AF21: 185 | AH21: Galvanised Steel Round Wire | AJ21: 2244 | AL21: FRLSH PVC Type ST-2 | AN21: 669 | AP21: Polypropylene Filler | AR21: 704 | AV21: 0 | AX21: Water swellable Tape | AZ21: 0 | BB21: Semi conducting Water Swellable tape | BD21: 59 | BH21: 0 | BL21: 0 | BP21: 0 | BR21: RUBBERIZED COTTON TAPE | BT21: 0 | BX21: 0 | BZ21: 95000 | CA21: 95000 | CH21: 95000 | CO21: 95000 | CQ21: 95000 | CR21: 0.18 | CS21: 17100 | CT21: 112100 | CU21: 8 | CV21: KMS | CW21: 896800 | CX21: 250 | CY21: SP0400118 | CZ21: CORRUGATED DISPATCH STEEL DRUM 1700 X 1000 X 1200
A22: ENQ-18390-25-26 | C22: FA1300200 | D22: 3 CORE X 95 SQ. MM. AL/ARM WIRE (XLPE) - 33 KV | E22: STEEL | F22: Copper Tape - 0.045 mm | H22: 129 | J22: Alumimium | L22: 770 | P22: 0 | R22: Extruded Semiconductive | T22: 265 | V22: HT-XLPE | X22: 1670 | AB22: 0 | AD22: PVC Type ST-2-PRESSURE EXTRUDED | AF22: 292 | AH22: Galvanised Steel Round Wire | AJ22: 3945 | AL22: FRLSH PVC Type ST-2 | AN22: 1228 | AP22: Polypropylene Filler | AR22: 1389 | AV22: 0 | AX22: Water swellable Tape | AZ22: 0 | BB22: Semi conducting Water Swellable tape | BD22: 0 | BH22: 0 | BL22: 0 | BP22: 0 | BR22: RUBBERIZED COTTON TAPE | BT22: 0 | BX22: 0 | BZ22: 147200 | CA22: 147200 | CH22: 147200 | CO22: 147200 | CQ22: 147200 | CR22: 0.18 | CS22: 26496 | CT22: 173696 | CU22: 10.5 | CV22: KMS | CW22: 1823808 | CX22: 250 | CY22: SP0400136 | CZ22: CORRUGATED DISPATCH STEEL DRUM 2200 X 1300 X 1200 MM
A23: ENQ-18390-25-26 | C23: FA1300297 | D23: 3 CORE X 35 SQ. MM. AL/ARM - WIRE (XLPE) - 33 KV (E) | E23: STEEL | F23: Copper Tape - 0.045 mm | J23: Alumimium | R23: Extruded Semiconductive | V23: HT-XLPE | AD23: PVC Type ST-2-PRESSURE EXTRUDED | AH23: Galvanised Steel Round Wire | AL23: FRLSH PVC Type ST-2 | AP23: Polypropylene Filler | AX23: Water swellable Tape | BB23: Semi conducting Water Swellable tape | BR23: RUBBERIZED COTTON TAPE | BZ23: 80000 | CA23: 80000 | CH23: 80000 | CO23: 80000 | CQ23: 80000 | CR23: 0.18 | CS23: 14400 | CT23: 94400 | CU23: 2.5 | CV23: KMS | CW23: 236000 | CX23: 250 | CY23: SP0400112 | CZ23: CORRUGATED DISPATCH STEEL DRUM 2000 X 1000 X 1000 MM
A24: ENQ-18390-25-26 | C24: FA1300313 | D24: 3 CORE X 50 SQ. MM. AL/ARD - WIRE (XLPE) - 11 KV | E24: STEEL | F24: Copper Tape - 0.045 mm | J24: Alumimium | R24: Extruded Semiconductive | V24: HT-XLPE | AD24: PVC Type ST-2 | AH24: Galvanised Steel Round Wire | AL24: FRLSH PVC Type ST-2 | AP24: Polypropylene Filler | AX24: Water swellable Tape | BB24: Semi conducting Water Swellable tape | BR24: RUBBERIZED COTTON TAPE | CR24: 0.18 | CU24: 8 | CV24: KMS | CX24: 250

Sheet AUTO CALCULATION SHEET (2)
A2: Centralized Contracts Group; TP Odisha DISCOMs TPCODL TPNODL TPSODL TPWODL (TATA Power and Odisha Government Joint Venture)
A4: TENDER SPECIFICATION NO () | B4: TPCODL / CCG / FY 25-26 / 1000008015
A5: TENDER DESCRIPTION () | B5: Two Year Rate Contract for supply of HT Cables at TPCODL, TPNODL, TPSODL & TPWODL
A6: Last Date & Time of Submission () | B6: 19.02.2026 [16:00 Hrs] OPENING ON '19.02.2026 [16:30 Hrs]
A7: REVERSE AUCTION | B7: Bidders shall be allowed to participate in Reverse auction as per following criteria hence bidders are advised to quote their most competitive rates while submitting the bids to avoid disqualification from participation in Reverse Auction. No of bidders allowed to participate in RA process shall be: Total No of bidders on whom tender would be split PLUS 2 more bidders CCG reserves the right to split the order quantity wise among 3-5 Nos of Bidders.
A8: Price () | B8: The line-item prices shall be subject to Price Variation clause as per latest IEEMA Circular. (Base Date of IEEMA for price consideration shall be Dec-25).
A9: Validity () | B9: Bids shall remain valid for 180 days from the due date of submission of the bid.
A10: Delivery Period () | B10: The delivery period for a quantity of up to 40 KM shall be 90 days from the date of issuance of the RO or GTP drawing approval, whichever is later. For quantities exceeding 40 KM, the delivery period shall be mutually agreed upon between the BA and the DISCOM. DISCOMs may also plan delivery in a staggered manner based on business requirements, as per the mutual agreement. In such cases, a month-wise delivery plan along with delivery date will be specified in the SCC of the RO.
A11: Payment Terms () | B11: 100% payment will be made within 60 days of submission of error-free certified invoice complete in all respects. For MSME payment cycle shall be within 45 days.
A12: Standard length () | B12: Cable length on one drum shall be 250 meters for 3 core cables & 500 meters for 1 core cables max. +/- 5%. (As per PO Terms.) The cable shall be supplied in continuous standard length of 250 (3 cores) & 500 (Single core) running meters with +/- 5% tolerance.
A13: Packing () | B13: Steel drums shall be provided. The cable shall be wound on non-returnable steel drums without any extra cost to TPWODL/ TPCODL/ TPNODL/ TPSODL/TPC/TPDDL/TPADL as per IS 10418 and its latest amendments.
A14: Technical Specification
N18: Conductor | V18: AL ALLOY | X18: Insulation Screening (Metallic) | AF18: Insulation Screening (Non-Metallic) | AH18: Insulation | AQ18: POLY TAPE | AR18: Inner Sheath | BA18: Armouring | BL18: Rs. 15/kg extra | BX18: FILLER | BY18: GREASE | BZ18: Water swellable Tape | CA18: Semi conducting Water Swellable tape | CB18: SEMICON TAPE | CC18: GLASS FIBER TAPE | CD18: COPPER WIRE 0.8 MM | CE18: RUBBERIZED COTTON TAPE | CF18: Water Tight Compound | CG18: DRUM TYPE | CK18: DRUM COST PER KM | CL18: TOTAL RM COST | CM18: EXTRA CONSUMPTION | CN18: EXTRA CONSUMPTION VALUE | CZ18: $A$1
A19: DOCKET NO. | B19: BASE DATE | C19: ITEM CODE | D19: PROPOSE ERP ITEM NAME | E19: EX-WORKS (PER KM) | F19: FREIGHT PER KM | G19: PRICE INCLUDING FREIGHT (PER KM) | H19: GST % | I19: GST VALUE | J19: PRICE INCLUDING GST & FREIGHT (PER KM) | K19: QTY | L19: Unit | M19: TOTAL PRICE OF FULL QTY (INCLUDING FRIGHT & GST) | N19: Alumimium | O19: Alumimium ALLOY | P19: Copper | Q19: AL-59 | R19: AL-4 | S19: AL-7 | T19: Flexible Copper | U19: Galvanized steel wire | V19: Alumimium | W19: Alumimium ALLOY | X19: Coper tape - 0.1 mm | Y19: Copper Tape - 0.03 mm | Z19: Copper Tape - 0.035 mm | AA19: Copper Tape - 0.04 mm | AB19: Copper Tape - 0.045 mm | AC19: Copper Tape - 0.050 mm | AD19: Copper Tape - 0.060 mm | AE19: Copper Tape - 0.075 mm(DOUBLE) | AF19: Extruded semiconductive | AG19: Extruded Semiconductive(Stripable) | AH19: HT-XLPE | AI19: LT-XLPE | AJ19: TR XLPE | AK19: Type A PVC | AL19: Type C PVC (HR) | AM19: Type A PVC-1.45 | AN19: Type A PVC-FR | AO19: Type A PVC-FRLS | AP19: Type A PVC-1.38 | AQ19: POLY TAPE | AR19: FR PVC Type ST-1 | AS19: FR PVC Type ST-2 | AT19: FRLSH PVC Type ST-1 | AU19: FRLSH PVC Type ST-2 | AV19: PVC Type ST-1 | AW19: PVC Type ST-1-PRESSURE EXTRUDED | AX19: PVC Type ST-2 | AY19: PVC COMPOUND 1.48 | AZ19: PVC Type ST-2-PRESSURE EXTRUDED | BA19: ACSR CORE WIRE | BB19: ACSR DOG STEEL WIRE | BC19: Aluminium Flat Strip | BD19: Aluminium Round Wire | BE19: Alumimium Tape | BF19: Double Steel Tape | BG19: Galvanised Steel Flat Strip | BH19: Galvanised Steel Flat Strip (Double) | BI19: Galvanised Steel Flat Strip-B | BJ19: Galvanised Steel Round Wire | BK19: Galvanised Steel Round Wire (Double) | BL19: FR PVC Type ST-1 | BM19: FR PVC Type ST-2 | BN19: FRLSH PVC Type ST-1 | BO19: FRLSH PVC Type ST-2 | BP19: ZHFR | BQ19: PE-ST-3 | BR19: PE-ST-7 | BS19: PVC Type ST-1 | BT19: PVC Type ST-2 | BU19: PVC COMPOUND 1.48 | BV19: PVC Type ST-2-PRESSURE EXTRUDED | BW19: UV & Track Resistant XLPE | BX19: PP FILLER | BY19: NCWBT | BZ19: Water swellable Tape | CA19: Semi conducting Water Swellable tape | CB19: SEMICON TAPE | CC19: GLASS FIBER TAPE | CD19: COPPER WIRE 0.8 MM | CE19: RUBBERIZED COTTON TAPE | CF19: Water Tight Compound | CG19: PROPOSE DRUM TYPE | CH19: DRUM CODE | CI19: DRUM SIZE (FxbXtx Ft) | CJ19: PARTY STANDARD LENGTH (MTR) | CM19: Consider 1% extra cost for complete cable . | CN19: Consider 1% extra cost for complete cable . | CO19: MFG% | CP19: MFG VALUE | CQ19: PROF% | CR19: PROFIT VALUE | CS19: 1ST EX-WORKS | CT19: Intt % | CU19: INTT VALUE | CV19: insp% | CW19: INSP VALUE | CX19: TTR Charges% | CY19: TTR Charges VALUE
N20: 299 | O20: =+IFERROR(VLOOKUP($O$19,Sheet1!J:L,2,0),0) -> 0 | P20: =+IFERROR(VLOOKUP($P$19,Sheet1!J:M,2,0),0) -> 0 | Q20: =+IFERROR(VLOOKUP($Q$19,Sheet1!J:M,2,0),0) -> 0 | R20: =+IFERROR(VLOOKUP($R$19,Sheet1!J:M,2,0),0) -> 0 | S20: =+IFERROR(VLOOKUP($S$19,Sheet1!J:M,2,0),0) -> 0 | T20: =+IFERROR(VLOOKUP($T$19,Sheet1!J:M,2,0),0) -> 0 | U20: =+IFERROR(VLOOKUP($U$19,Sheet1!J:M,2,0),0) -> 0 | V20: =+IFERROR(VLOOKUP($V$19,Sheet1!N:Q,2,0),0) -> 0 | W20: =+IFERROR(VLOOKUP($W$19,Sheet1!N:O,2,0),0) -> 0 | X20: =+IFERROR(VLOOKUP($X$19,Sheet1!F:I,2,0),0) -> 0 | Y20: =+IFERROR(VLOOKUP($Y$19,Sheet1!F:I,2,0),0) -> 0 | Z20: =+IFERROR(VLOOKUP($Z$19,Sheet1!F:I,2,0),0) -> 0 | AA20: =+IFERROR(VLOOKUP($AA$19,Sheet1!F:I,2,0),0) -> 0 | AB20: 1211 | AC20: =+IFERROR(VLOOKUP($AC$19,Sheet1!F:I,2,0),0) -> 0 | AD20: =+IFERROR(VLOOKUP($AD$19,Sheet1!F:I,2,0),0) -> 0 | AE20: =+IFERROR(VLOOKUP($AE$19,Sheet1!F:I,2,0),0) -> 0 | AF20: 162 | AG20: =+IFERROR(VLOOKUP($AG$19,Sheet1!R:U,2,0),0) -> 0 | AH20: 125 | AI20: =+IFERROR(VLOOKUP($AI$19,Sheet1!V:Y,2,0),0) -> 0 | AJ20: =+IFERROR(VLOOKUP($AJ$19,Sheet1!V:Y,2,0),0) -> 0 | AK20: =+IFERROR(VLOOKUP($AK$19,Sheet1!V:Y,2,0),0) -> 0 | AL20: =+IFERROR(VLOOKUP($AL$19,Sheet1!V:Y,2,0),0) -> 0 | AM20: =+IFERROR(VLOOKUP($AM$19,Sheet1!V:Y,2,0),0) -> 0 | AN20: =+IFERROR(VLOOKUP($AN$19,Sheet1!V:Y,2,0),0) -> 0 | AO20: =+IFERROR(VLOOKUP($AO$19,Sheet1!V:Y,2,0),0) -> 0 | AP20: =+IFERROR(VLOOKUP($AP$19,Sheet1!V:Y,2,0),0) -> 0 | AQ20: 109 | AR20: =+IFERROR(VLOOKUP($AR$19,Sheet1!AD2:AG840,2,0),0) -> 0 | AS20: =+IFERROR(VLOOKUP($AS$19,Sheet1!AD2:AG840,2,0),0) -> 0 | AT20: =+IFERROR(VLOOKUP($AT$19,Sheet1!AD2:AG840,2,0),0) -> 0 | AU20: =+IFERROR(VLOOKUP($AU$19,Sheet1!AD2:AG840,2,0),0) -> 0 | AV20: =+IFERROR(VLOOKUP($AV$19,Sheet1!AD2:AG840,2,0),0) -> 0 | AW20: =+IFERROR(VLOOKUP($AW$19,Sheet1!AD2:AG840,2,0),0) -> 0 | AX20: 59 | AY20: =+IFERROR(VLOOKUP($AY$19,Sheet1!AD2:AG840,2,0),0) -> 0 | AZ20: =+IFERROR(VLOOKUP($AZ$19,Sheet1!AD2:AG840,2,0),0) -> 0 | BA20: =+IFERROR(VLOOKUP($BA$19,Sheet1!AH2:AK840,2,0),0) -> 0 | BB20: =+IFERROR(VLOOKUP($BB$19,Sheet1!AH2:AK840,2,0),0) -> 0 | BC20: =+IFERROR(VLOOKUP($BC$19,Sheet1!AH2:AK840,2,0),0) -> 0 | BD20: =N20+5 -> 304 | BE20: =+IFERROR(VLOOKUP($BE$19,Sheet1!AH2:AK840,2,0),0) -> 0 | BF20: =+IFERROR(VLOOKUP($BF$19,Sheet1!AH2:AK840,2,0),0) -> 0 | BG20: =+IFERROR(VLOOKUP($BG$19,Sheet1!AH2:AK840,2,0),0) -> 0 | BH20: =+IFERROR(VLOOKUP($BH$19,Sheet1!AH2:AK840,2,0),0) -> 0 | BI20: =+IFERROR(VLOOKUP($BI$19,Sheet1!AH2:AK840,2,0),0) -> 0 | BJ20: 81 | BK20: =+IFERROR(VLOOKUP($BK$19,Sheet1!AH2:AK840,2,0),0) -> 0 | BL20: =+IFERROR(VLOOKUP($BL$19,Sheet1!AL2:AO840,2,0),0) -> 0 | BM20: =+IFERROR(VLOOKUP($BM$19,Sheet1!AL2:AO840,2,0),0) -> 0 | BN20: =+IFERROR(VLOOKUP($BN$19,Sheet1!AL2:AO840,2,0),0) -> 0 | BO20: =76+15 -> 91 | BP20: =+IFERROR(VLOOKUP($BP$19,Sheet1!AL2:AO840,2,0),0) -> 0 | BQ20: =+IFERROR(VLOOKUP($BQ$19,Sheet1!AL2:AO840,2,0),0) -> 0 | BR20: =+IFERROR(VLOOKUP($BR$19,Sheet1!AL2:AO840,2,0),0) -> 0 | BS20: =+IFERROR(VLOOKUP($BS$19,Sheet1!AL2:AO840,2,0),0) -> 0 | BT20: =+IFERROR(VLOOKUP($BT$19,Sheet1!AL2:AO840,2,0),0) -> 0 | BU20: =+IFERROR(VLOOKUP($BU$19,Sheet1!AL2:AO840,2,0),0) -> 0 | BV20: =+IFERROR(VLOOKUP($BV$19,Sheet1!AL2:AO840,2,0),0) -> 0 | BW20: =+IFERROR(VLOOKUP($BW$19,Sheet1!AL2:AO840,2,0),0) -> 0 | BX20: 75 | BY20: 310 | BZ20: =+IFERROR(VLOOKUP($BZ$19,Sheet1!AX2:BA840,2,0),0) -> 0 | CA20: 393 | CB20: =+IFERROR(VLOOKUP($CB$19,Sheet1!BF2:BI840,2,0),0) -> 0 | CC20: =+IFERROR(VLOOKUP($CC$19,Sheet1!BJ2:BM840,2,0),0) -> 0 | CD20: =+IFERROR(VLOOKUP($CD$19,Sheet1!BN2:BQ840,2,0),0) -> 0 | CE20: 284 | CF20: =+IFERROR(VLOOKUP($CF$19,Sheet1!BV2:BY840,2,0),0) -> 0 | CI20: NON RETURNABLE STEEL DRUM
A21: =Sheet1!A13 -> ENQ-18390-25-26 | B21: 46357 | C21: =Sheet1!C13 -> FA1300083 | D21: =Sheet1!D13 -> 3 CORE X 400 SQ. MM. AL/ARM - WIRE (XLPE) - 11 KV | E21: =CS21+CU21+CW21+CY21 -> 2800573.7 | F21: =ROUNDUP(M49,0) -> 58278 | G21: =E21+F21 -> 2858851.7 | H21: =Sheet1!CR13 -> 0.18 | I21: =G21*H21 -> 514593.31 | J21: =G21+I21 -> 3373445.1 | K21: =Sheet1!CU13 -> 209 | L21: =Sheet1!CV13 -> KMS | M21: =J21*K21 -> 7.0505002e+08 | N21: =+IFERROR(VLOOKUP($N$19,Sheet1!J13:L13,3,0),0) -> 3240 | O21: =+IFERROR(VLOOKUP($O$19,Sheet1!J13:L13,3,0),0) -> 0 | P21: =+IFERROR(VLOOKUP($P$19,Sheet1!J13:M13,3,0),0) -> 0 | Q21: =+IFERROR(VLOOKUP($Q$19,Sheet1!J13:M13,3,0),0) -> 0 | R21: =+IFERROR(VLOOKUP($R$19,Sheet1!J13:M13,3,0),0) -> 0 | S21: =+IFERROR(VLOOKUP($S$19,Sheet1!J13:M13,3,0),0) -> 0 | T21: =+IFERROR(VLOOKUP($T$19,Sheet1!J13:M13,3,0),0) -> 0 | U21: =+IFERROR(VLOOKUP($U$19,Sheet1!J13:M13,3,0),0) -> 0 | V21: =+IFERROR(VLOOKUP($V$19,Sheet1!N13:Q13,3,0),0) -> 0 | W21: =+IFERROR(VLOOKUP($W$19,Sheet1!N13:Q13,3,0),0) -> 0 | X21: =+IFERROR(VLOOKUP($X$19,Sheet1!F13:I13,3,0),0) -> 0 | Y21: =+IFERROR(VLOOKUP($Y$19,Sheet1!F13:I13,3,0),0) -> 0 | Z21: =+IFERROR(VLOOKUP($Z$19,Sheet1!F13:I13,3,0),0) -> 0 | AA21: =+IFERROR(VLOOKUP($AA$19,Sheet1!F13:I13,3,0),0) -> 0 | AB21: 176 | AC21: =+IFERROR(VLOOKUP($AC$19,Sheet1!F13:I13,3,0),0) -> 0 | AD21: =+IFERROR(VLOOKUP($AD$19,Sheet1!F13:I13,3,0),0) -> 0 | AE21: =+IFERROR(VLOOKUP($AE$19,Sheet1!F13:I13,3,0),0) -> 0 | AF21: 518 | AG21: =+IFERROR(VLOOKUP($AG$19,Sheet1!R13:U13,3,0),0) -> 0 | AH21: 930 | AI21: =+IFERROR(VLOOKUP($AI$19,Sheet1!V13:Y13,3,0),0) -> 0 | AJ21: =+IFERROR(VLOOKUP($AJ$19,Sheet1!V13:Y13,3,0),0) -> 0 | AK21: =+IFERROR(VLOOKUP($AK$19,Sheet1!V13:Y13,3,0),0) -> 0 | AL21: =+IFERROR(VLOOKUP($AL$19,Sheet1!V13:Y13,3,0),0) -> 0 | AM21: =+IFERROR(VLOOKUP($AM$19,Sheet1!V13:Y13,3,0),0) -> 0 | AN21: =+IFERROR(VLOOKUP($AN$19,Sheet1!V13:Y13,3,0),0) -> 0 | AO21: =+IFERROR(VLOOKUP($AO$19,Sheet1!V13:Y13,3,0),0) -> 0 | AP21: =+IFERROR(VLOOKUP($AP$19,Sheet1!V13:Y13,3,0),0) -> 0 | AQ21: =+IFERROR(VLOOKUP($AQ$19,Sheet1!Z13:AB13,3,0),0) -> 0 | AR21: =+IFERROR(VLOOKUP($AR$19,Sheet1!AD13:AG13,3,0),0) -> 0 | AS21: =+IFERROR(VLOOKUP($AS$19,Sheet1!AD13:AG13,3,0),0) -> 0 | AT21: =+IFERROR(VLOOKUP($AT$19,Sheet1!AD13:AG13,3,0),0) -> 0 | AU21: =+IFERROR(VLOOKUP($AU$19,Sheet1!AD13:AG13,3,0),0) -> 0 | AV21: =+IFERROR(VLOOKUP($AV$19,Sheet1!AD13:AG13,3,0),0) -> 0 | AW21: =+IFERROR(VLOOKUP($AW$19,Sheet1!AD13:AG13,3,0),0) -> 0 | AX21: 1130 | AY21: =+IFERROR(VLOOKUP($AY$19,Sheet1!AD13:AG13,3,0),0) -> 0 | BA21: =+IFERROR(VLOOKUP($BA$19,Sheet1!AH13:AK13,3,0),0) -> 0 | BB21: =+IFERROR(VLOOKUP($BB$19,Sheet1!AH13:AK13,3,0),0) -> 0 | BC21: =+IFERROR(VLOOKUP($BC$19,Sheet1!AH13:AK13,3,0),0) -> 0 | BD21: =+IFERROR(VLOOKUP($BD$19,Sheet1!AH13:AK13,3,0),0) -> 0 | BE21: =+IFERROR(VLOOKUP($BE$19,Sheet1!AH13:AK13,3,0),0) -> 0 | BF21: =+IFERROR(VLOOKUP($BF$19,Sheet1!AH13:AK13,3,0),0) -> 0 | BG21: =+IFERROR(VLOOKUP($BG$19,Sheet1!AH13:AK13,3,0),0) -> 0 | BH21: =+IFERROR(VLOOKUP($BH$19,Sheet1!AH13:AK13,3,0),0) -> 0 | BI21: =+IFERROR(VLOOKUP($BI$19,Sheet1!AH13:AK13,3,0),0) -> 0 | BJ21: 5643 | BK21: =+IFERROR(VLOOKUP($BK$19,Sheet1!AH13:AK13,3,0),0) -> 0 | BL21: =+IFERROR(VLOOKUP($BL$19,Sheet1!AL13:AO13,3,0),0) -> 0 | BM21: =+IFERROR(VLOOKUP($BM$19,Sheet1!AL13:AO13,3,0),0) -> 0 | BN21: =+IFERROR(VLOOKUP($BN$19,Sheet1!AL13:AO13,3,0),0) -> 0 | BO21: 1377 | BP21: =+IFERROR(VLOOKUP($BP$19,Sheet1!AL13:AO13,3,0),0) -> 0 | BQ21: =+IFERROR(VLOOKUP($BQ$19,Sheet1!AL13:AO13,3,0),0) -> 0 | BR21: =+IFERROR(VLOOKUP($BR$19,Sheet1!AL13:AO13,3,0),0) -> 0 | BS21: =+IFERROR(VLOOKUP($BS$19,Sheet1!AL13:AO13,3,0),0) -> 0 | BT21: =+IFERROR(VLOOKUP($BT$19,Sheet1!AL13:AO13,3,0),0) -> 0 | BU21: =+IFERROR(VLOOKUP($BU$19,Sheet1!AL13:AO13,3,0),0) -> 0 | BV21: =+IFERROR(VLOOKUP($BV$19,Sheet1!AL13:AO13,3,0),0) -> 0 | BW21: =+IFERROR(VLOOKUP($BW$19,Sheet1!AL13:AO13,3,0),0) -> 0 | BX21: 1032 | BY21: 58 | BZ21: =+IFERROR(VLOOKUP($BZ$19,Sheet1!AX13:BA13,3,0),0) -> 0 | CA21: 95 | CB21: =+IFERROR(VLOOKUP($CB$19,Sheet1!BF13:BI13,3,0),0) -> 0 | CC21: =+IFERROR(VLOOKUP($CC$19,Sheet1!BJ13:BM13,3,0),0) -> 0 | CD21: =+IFERROR(VLOOKUP($CD$19,Sheet1!BN13:BQ13,3,0),0) -> 0 | CE21: 60 | CF21: =+IFERROR(VLOOKUP($CF$19,Sheet1!BV13:BY13,3,0),0) -> 0 | CG21: =Sheet1!E13 -> STEEL | CH21: SP0400136 | CI21: CORRUGATED DISPATCH STEEL DRUM 2200 X 1300 X 1200 MM | CJ21: =Sheet1!CX13 -> 250 | CK21: =26000/0.25 -> 104000 | CL21: =SUMPRODUCT($N$20:$CF$20,N21:CF21)+CK21 -> 2284877 | CM21: 0.01 | CN21: =CL21*CM21 -> 22848.77 | CO21: 0.18 | CP21: =CL21*CO21 -> 411277.86 | CQ21: =Sheet1!CF13 -> 0 | CR21: =CL21*CQ21 -> 0 | CS21: =CL21+CN21+CP21+CR21 -> 2719003.6 | CT21: 0.02 | CU21: =CS21*CT21 -> 54380.073 | CV21: 0.01 | CW21: =CS21*CV21 -> 27190.036 | CX21: =Sheet1!CM13 -> 0 | CY21: =CX21*CS21 -> 0
A22: =Sheet1!A15 -> ENQ-18390-25-26 | B22: 46357 | C22: =Sheet1!C15 -> FA1300091 | D22: =Sheet1!D15 -> 3 CORE X 300 SQ. MM. AL/ARM - WIRE (XLPE) - 11 KV | E22: =CS22+CU22+CW22+CY22 -> 2238616 | F22: =ROUNDUP(M50,0) -> 58097 | G22: =E22+F22 -> 2296713 | H22: =Sheet1!CR15 -> 0.18 | I22: =G22*H22 -> 413408.35 | J22: =G22+I22 -> 2710121.4 | K22: =Sheet1!CU15 -> 151 | L22: =Sheet1!CV15 -> KMS | M22: =J22*K22 -> 4.0922833e+08 | N22: =+IFERROR(VLOOKUP($N$19,Sheet1!J15:L15,3,0),0) -> 2430 | O22: =+IFERROR(VLOOKUP($O$19,Sheet1!J15:L15,3,0),0) -> 0 | P22: =+IFERROR(VLOOKUP($P$19,Sheet1!J15:M15,3,0),0) -> 0 | Q22: =+IFERROR(VLOOKUP($Q$19,Sheet1!J15:M15,3,0),0) -> 0 | R22: =+IFERROR(VLOOKUP($R$19,Sheet1!J15:M15,3,0),0) -> 0 | S22: =+IFERROR(VLOOKUP($S$19,Sheet1!J15:M15,3,0),0) -> 0 | T22: =+IFERROR(VLOOKUP($T$19,Sheet1!J15:M15,3,0),0) -> 0 | U22: =+IFERROR(VLOOKUP($U$19,Sheet1!J15:M15,3,0),0) -> 0 | V22: =+IFERROR(VLOOKUP($V$19,Sheet1!N15:Q15,3,0),0) -> 0 | W22: =+IFERROR(VLOOKUP($W$19,Sheet1!N15:Q15,3,0),0) -> 0 | X22: =+IFERROR(VLOOKUP($X$19,Sheet1!F15:I15,3,0),0) -> 0 | Y22: =+IFERROR(VLOOKUP($Y$19,Sheet1!F15:I15,3,0),0) -> 0 | Z22: =+IFERROR(VLOOKUP($Z$19,Sheet1!F15:I15,3,0),0) -> 0 | AA22: =+IFERROR(VLOOKUP($AA$19,Sheet1!F15:I15,3,0),0) -> 0 | AB22: 161 | AC22: =+IFERROR(VLOOKUP($AC$19,Sheet1!F15:I15,3,0),0) -> 0 | AD22: =+IFERROR(VLOOKUP($AD$19,Sheet1!F15:I15,3,0),0) -> 0 | AE22: =+IFERROR(VLOOKUP($AE$19,Sheet1!F15:I15,3,0),0) -> 0 | AF22: 465 | AG22: =+IFERROR(VLOOKUP($AG$19,Sheet1!R15:U15,3,0),0) -> 0 | AH22: 835 | AI22: =+IFERROR(VLOOKUP($AI$19,Sheet1!V15:Y15,3,0),0) -> 0 | AJ22: =+IFERROR(VLOOKUP($AJ$19,Sheet1!V15:Y15,3,0),0) -> 0 | AK22: =+IFERROR(VLOOKUP($AK$19,Sheet1!V15:Y15,3,0),0) -> 0 | AL22: =+IFERROR(VLOOKUP($AL$19,Sheet1!V15:Y15,3,0),0) -> 0 | AM22: =+IFERROR(VLOOKUP($AM$19,Sheet1!V15:Y15,3,0),0) -> 0 | AN22: =+IFERROR(VLOOKUP($AN$19,Sheet1!V15:Y15,3,0),0) -> 0 | AO22: =+IFERROR(VLOOKUP($AO$19,Sheet1!V15:Y15,3,0),0) -> 0 | AP22: =+IFERROR(VLOOKUP($AP$19,Sheet1!V15:Y15,3,0),0) -> 0 | AQ22: =+IFERROR(VLOOKUP($AQ$19,Sheet1!Z15:AB15,3,0),0) -> 0 | AR22: =+IFERROR(VLOOKUP($AR$19,Sheet1!AD15:AG15,3,0),0) -> 0 | AS22: =+IFERROR(VLOOKUP($AS$19,Sheet1!AD15:AG15,3,0),0) -> 0 | AT22: =+IFERROR(VLOOKUP($AT$19,Sheet1!AD15:AG15,3,0),0) -> 0 | AU22: =+IFERROR(VLOOKUP($AU$19,Sheet1!AD15:AG15,3,0),0) -> 0 | AV22: =+IFERROR(VLOOKUP($AV$19,Sheet1!AD15:AG15,3,0),0) -> 0 | AW22: =+IFERROR(VLOOKUP($AW$19,Sheet1!AD15:AG15,3,0),0) -> 0 | AX22: 974 | AY22: =+IFERROR(VLOOKUP($AY$19,Sheet1!AD15:AG15,3,0),0) -> 0 | BA22: =+IFERROR(VLOOKUP($BA$19,Sheet1!AH15:AK15,3,0),0) -> 0 | BB22: =+IFERROR(VLOOKUP($BB$19,Sheet1!AH15:AK15,3,0),0) -> 0 | BC22: =+IFERROR(VLOOKUP($BC$19,Sheet1!AH15:AK15,3,0),0) -> 0 | BD22: =+IFERROR(VLOOKUP($BD$19,Sheet1!AH15:AK15,3,0),0) -> 0 | BE22: =+IFERROR(VLOOKUP($BE$19,Sheet1!AH15:AK15,3,0),0) -> 0 | BF22: =+IFERROR(VLOOKUP($BF$19,Sheet1!AH15:AK15,3,0),0) -> 0 | BG22: =+IFERROR(VLOOKUP($BG$19,Sheet1!AH15:AK15,3,0),0) -> 0 | BH22: =+IFERROR(VLOOKUP($BH$19,Sheet1!AH15:AK15,3,0),0) -> 0 | BI22: =+IFERROR(VLOOKUP($BI$19,Sheet1!AH15:AK15,3,0),0) -> 0 | BJ22: 4072 | BK22: =+IFERROR(VLOOKUP($BK$19,Sheet1!AH15:AK15,3,0),0) -> 0 | BL22: =+IFERROR(VLOOKUP($BL$19,Sheet1!AL15:AO15,3,0),0) -> 0 | BM22: =+IFERROR(VLOOKUP($BM$19,Sheet1!AL15:AO15,3,0),0) -> 0 | BN22: =+IFERROR(VLOOKUP($BN$19,Sheet1!AL15:AO15,3,0),0) -> 0 | BO22: 1190 | BP22: =+IFERROR(VLOOKUP($BP$19,Sheet1!AL15:AO15,3,0),0) -> 0 | BQ22: =+IFERROR(VLOOKUP($BQ$19,Sheet1!AL15:AO15,3,0),0) -> 0 | BR22: =+IFERROR(VLOOKUP($BR$19,Sheet1!AL15:AO15,3,0),0) -> 0 | BS22: =+IFERROR(VLOOKUP($BS$19,Sheet1!AL15:AO15,3,0),0) -> 0 | BT22: =+IFERROR(VLOOKUP($BT$19,Sheet1!AL15:AO15,3,0),0) -> 0 | BU22: =+IFERROR(VLOOKUP($BU$19,Sheet1!AL15:AO15,3,0),0) -> 0 | BV22: =+IFERROR(VLOOKUP($BV$19,Sheet1!AL15:AO15,3,0),0) -> 0 | BW22: =+IFERROR(VLOOKUP($BW$19,Sheet1!AL15:AO15,3,0),0) -> 0 | BX22: 862 | BY22: 38 | BZ22: =+IFERROR(VLOOKUP($BZ$19,Sheet1!AX15:BA15,3,0),0) -> 0 | CA22: 86 | CB22: =+IFERROR(VLOOKUP($CB$19,Sheet1!BF15:BI15,3,0),0) -> 0 | CC22: =+IFERROR(VLOOKUP($CC$19,Sheet1!BJ15:BM15,3,0),0) -> 0 | CD22: =+IFERROR(VLOOKUP($CD$19,Sheet1!BN15:BQ15,3,0),0) -> 0 | CE22: 54 | CF22: =+IFERROR(VLOOKUP($CF$19,Sheet1!BV15:BY15,3,0),0) -> 0 | CG22: =Sheet1!E15 -> STEEL | CH22: SP0400136 | CI22: CORRUGATED DISPATCH STEEL DRUM 2200 X 1300 X 1200 MM | CJ22: =Sheet1!CX15 -> 250 | CK22: =26000/0.25 -> 104000 | CL22: =SUMPRODUCT($N$20:$CF$20,N22:CF22)+CK22 -> 1826398 | CM22: 0.01 | CN22: =CL22*CM22 -> 18263.98 | CO22: 0.18 | CP22: =CL22*CO22 -> 328751.64 | CQ22: =Sheet1!CF15 -> 0 | CR22: =CL22*CQ22 -> 0 | CS22: =CL22+CN22+CP22+CR22 -> 2173413.6 | CT22: 0.02 | CU22: =CS22*CT22 -> 43468.272 | CV22: 0.01 | CW22: =CS22*CV22 -> 21734.136 | CX22: =Sheet1!CM15 -> 0 | CY22: =CX22*CS22 -> 0
A23: =Sheet1!A14 -> ENQ-18390-25-26 | B23: 46357 | C23: =Sheet1!C14 -> FA1300090 | D23: =Sheet1!D14 -> 3 CORE X 185 SQ. MM AL/ARM - WIRE (XLPE) - 11 KV | E23: =CS23+CU23+CW23+CY23 -> 1652693.4 | F23: =ROUNDUP(M51,0) -> 34118 | G23: =E23+F23 -> 1686811.4 | H23: =Sheet1!CR14 -> 0.18 | I23: =G23*H23 -> 303626.06 | J23: =G23+I23 -> 1990437.5 | K23: =Sheet1!CU14 -> 17 | L23: =Sheet1!CV14 -> KMS | M23: =J23*K23 -> 33837437 | N23: =+IFERROR(VLOOKUP($N$19,Sheet1!J14:L14,3,0),0) -> 1499 | O23: =+IFERROR(VLOOKUP($O$19,Sheet1!J14:L14,3,0),0) -> 0 | P23: =+IFERROR(VLOOKUP($P$19,Sheet1!J14:M14,3,0),0) -> 0 | Q23: =+IFERROR(VLOOKUP($Q$19,Sheet1!J14:M14,3,0),0) -> 0 | R23: =+IFERROR(VLOOKUP($R$19,Sheet1!J14:M14,3,0),0) -> 0 | S23: =+IFERROR(VLOOKUP($S$19,Sheet1!J14:M14,3,0),0) -> 0 | T23: =+IFERROR(VLOOKUP($T$19,Sheet1!J14:M14,3,0),0) -> 0 | U23: =+IFERROR(VLOOKUP($U$19,Sheet1!J14:M14,3,0),0) -> 0 | V23: =+IFERROR(VLOOKUP($V$19,Sheet1!N14:Q14,3,0),0) -> 0 | W23: =+IFERROR(VLOOKUP($W$19,Sheet1!N14:Q14,3,0),0) -> 0 | X23: =+IFERROR(VLOOKUP($X$19,Sheet1!F14:I14,3,0),0) -> 0 | Y23: =+IFERROR(VLOOKUP($Y$19,Sheet1!F14:I14,3,0),0) -> 0 | Z23: =+IFERROR(VLOOKUP($Z$19,Sheet1!F14:I14,3,0),0) -> 0 | AA23: =+IFERROR(VLOOKUP($AA$19,Sheet1!F14:I14,3,0),0) -> 0 | AB23: 138 | AC23: =+IFERROR(VLOOKUP($AC$19,Sheet1!F14:I14,3,0),0) -> 0 | AD23: =+IFERROR(VLOOKUP($AD$19,Sheet1!F14:I14,3,0),0) -> 0 | AE23: =+IFERROR(VLOOKUP($AE$19,Sheet1!F14:I14,3,0),0) -> 0 | AF23: 387 | AG23: =+IFERROR(VLOOKUP($AG$19,Sheet1!R14:U14,3,0),0) -> 0 | AH23: 693 | AI23: =+IFERROR(VLOOKUP($AI$19,Sheet1!V14:Y14,3,0),0) -> 0 | AJ23: =+IFERROR(VLOOKUP($AJ$19,Sheet1!V14:Y14,3,0),0) -> 0 | AK23: =+IFERROR(VLOOKUP($AK$19,Sheet1!V14:Y14,3,0),0) -> 0 | AL23: =+IFERROR(VLOOKUP($AL$19,Sheet1!V14:Y14,3,0),0) -> 0 | AM23: =+IFERROR(VLOOKUP($AM$19,Sheet1!V14:Y14,3,0),0) -> 0 | AN23: =+IFERROR(VLOOKUP($AN$19,Sheet1!V14:Y14,3,0),0) -> 0 | AO23: =+IFERROR(VLOOKUP($AO$19,Sheet1!V14:Y14,3,0),0) -> 0 | AP23: =+IFERROR(VLOOKUP($AP$19,Sheet1!V14:Y14,3,0),0) -> 0 | AQ23: =+IFERROR(VLOOKUP($AQ$19,Sheet1!Z14:AB14,3,0),0) -> 0 | AR23: =+IFERROR(VLOOKUP($AR$19,Sheet1!AD14:AG14,3,0),0) -> 0 | AS23: =+IFERROR(VLOOKUP($AS$19,Sheet1!AD14:AG14,3,0),0) -> 0 | AT23: =+IFERROR(VLOOKUP($AT$19,Sheet1!AD14:AG14,3,0),0) -> 0 | AU23: =+IFERROR(VLOOKUP($AU$19,Sheet1!AD14:AG14,3,0),0) -> 0 | AV23: =+IFERROR(VLOOKUP($AV$19,Sheet1!AD14:AG14,3,0),0) -> 0 | AW23: =+IFERROR(VLOOKUP($AW$19,Sheet1!AD14:AG14,3,0),0) -> 0 | AX23: 809 | AY23: =+IFERROR(VLOOKUP($AY$19,Sheet1!AD14:AG14,3,0),0) -> 0 | BA23: =+IFERROR(VLOOKUP($BA$19,Sheet1!AH14:AK14,3,0),0) -> 0 | BB23: =+IFERROR(VLOOKUP($BB$19,Sheet1!AH14:AK14,3,0),0) -> 0 | BC23: =+IFERROR(VLOOKUP($BC$19,Sheet1!AH14:AK14,3,0),0) -> 0 | BD23: =+IFERROR(VLOOKUP($BD$19,Sheet1!AH14:AK14,3,0),0) -> 0 | BE23: =+IFERROR(VLOOKUP($BE$19,Sheet1!AH14:AK14,3,0),0) -> 0 | BF23: =+IFERROR(VLOOKUP($BF$19,Sheet1!AH14:AK14,3,0),0) -> 0 | BG23: =+IFERROR(VLOOKUP($BG$19,Sheet1!AH14:AK14,3,0),0) -> 0 | BH23: =+IFERROR(VLOOKUP($BH$19,Sheet1!AH14:AK14,3,0),0) -> 0 | BI23: =+IFERROR(VLOOKUP($BI$19,Sheet1!AH14:AK14,3,0),0) -> 0 | BJ23: 3500 | BK23: =+IFERROR(VLOOKUP($BK$19,Sheet1!AH14:AK14,3,0),0) -> 0 | BL23: =+IFERROR(VLOOKUP($BL$19,Sheet1!AL14:AO14,3,0),0) -> 0 | BM23: =+IFERROR(VLOOKUP($BM$19,Sheet1!AL14:AO14,3,0),0) -> 0 | BN23: =+IFERROR(VLOOKUP($BN$19,Sheet1!AL14:AO14,3,0),0) -> 0 | BO23: 945 | BP23: =+IFERROR(VLOOKUP($BP$19,Sheet1!AL14:AO14,3,0),0) -> 0 | BQ23: =+IFERROR(VLOOKUP($BQ$19,Sheet1!AL14:AO14,3,0),0) -> 0 | BR23: =+IFERROR(VLOOKUP($BR$19,Sheet1!AL14:AO14,3,0),0) -> 0 | BS23: =+IFERROR(VLOOKUP($BS$19,Sheet1!AL14:AO14,3,0),0) -> 0 | BT23: =+IFERROR(VLOOKUP($BT$19,Sheet1!AL14:AO14,3,0),0) -> 0 | BU23: =+IFERROR(VLOOKUP($BU$19,Sheet1!AL14:AO14,3,0),0) -> 0 | BV23: =+IFERROR(VLOOKUP($BV$19,Sheet1!AL14:AO14,3,0),0) -> 0 | BW23: =+IFERROR(VLOOKUP($BW$19,Sheet1!AL14:AO14,3,0),0) -> 0 | BX23: 615 | BY23: 35 | BZ23: =+IFERROR(VLOOKUP($BZ$19,Sheet1!AX14:BA14,3,0),0) -> 0 | CA23: 72 | CB23: =+IFERROR(VLOOKUP($CB$19,Sheet1!BF14:BI14,3,0),0) -> 0 | CC23: =+IFERROR(VLOOKUP($CC$19,Sheet1!BJ14:BM14,3,0),0) -> 0 | CD23: =+IFERROR(VLOOKUP($CD$19,Sheet1!BN14:BQ14,3,0),0) -> 0 | CE23: 48 | CF23: =+IFERROR(VLOOKUP($CF$19,Sheet1!BV14:BY14,3,0),0) -> 0 | CG23: =Sheet1!E14 -> STEEL | CH23: SP0400111 | CI23: CORRUGATED DISPATCH STEEL DRUM 1900 X 1000 X 1000 MM | CJ23: =Sheet1!CX14 -> 250 | CK23: =16900/0.25 -> 67600 | CL23: =SUMPRODUCT($N$20:$CF$20,N23:CF23)+CK23 -> 1348367 | CM23: 0.01 | CN23: =CL23*CM23 -> 13483.67 | CO23: 0.18 | CP23: =CL23*CO23 -> 242706.06 | CQ23: =Sheet1!CF14 -> 0 | CR23: =CL23*CQ23 -> 0 | CS23: =CL23+CN23+CP23+CR23 -> 1604556.7 | CT23: 0.02 | CU23: =CS23*CT23 -> 32091.135 | CV23: 0.01 | CW23: =CS23*CV23 -> 16045.567 | CX23: =Sheet1!CM14 -> 0 | CY23: =CX23*CS23 -> 0
A24: =Sheet1!A20 -> ENQ-18390-25-26 | B24: 46357 | C24: =Sheet1!C20 -> FA1300176 | D24: =Sheet1!D20 -> 3 CORE X 150 SQ. MM. AL/ARM - WIRE (XLPE) - 11 KV | E24: =CS24+CU24+CW24+CY24 -> 1369163.3 | F24: =ROUNDUP(M52,0) -> 36250 | G24: =E24+F24 -> 1405413.3 | H24: =Sheet1!CR20 -> 0.18 | I24: =G24*H24 -> 252974.39 | J24: =G24+I24 -> 1658387.7 | K24: =Sheet1!CU20 -> 4 | L24: =Sheet1!CV20 -> KMS | M24: =J24*K24 -> 6633550.7 | N24: =+IFERROR(VLOOKUP($N$19,Sheet1!J20:L20,3,0),0) -> 1215 | O24: =+IFERROR(VLOOKUP($O$19,Sheet1!J20:L20,3,0),0) -> 0 | P24: =+IFERROR(VLOOKUP($P$19,Sheet1!J20:M20,3,0),0) -> 0 | Q24: =+IFERROR(VLOOKUP($Q$19,Sheet1!J20:M20,3,0),0) -> 0 | R24: =+IFERROR(VLOOKUP($R$19,Sheet1!J20:M20,3,0),0) -> 0 | S24: =+IFERROR(VLOOKUP($S$19,Sheet1!J20:M20,3,0),0) -> 0 | T24: =+IFERROR(VLOOKUP($T$19,Sheet1!J20:M20,3,0),0) -> 0 | U24: =+IFERROR(VLOOKUP($U$19,Sheet1!J20:M20,3,0),0) -> 0 | V24: =+IFERROR(VLOOKUP($V$19,Sheet1!N20:Q20,3,0),0) -> 0 | W24: =+IFERROR(VLOOKUP($W$19,Sheet1!N20:Q20,3,0),0) -> 0 | X24: =+IFERROR(VLOOKUP($X$19,Sheet1!F20:I20,3,0),0) -> 0 | Y24: =+IFERROR(VLOOKUP($Y$19,Sheet1!F20:I20,3,0),0) -> 0 | Z24: =+IFERROR(VLOOKUP($Z$19,Sheet1!F20:I20,3,0),0) -> 0 | AA24: =+IFERROR(VLOOKUP($AA$19,Sheet1!F20:I20,3,0),0) -> 0 | AB24: 130 | AC24: =+IFERROR(VLOOKUP($AC$19,Sheet1!F20:I20,3,0),0) -> 0 | AD24: =+IFERROR(VLOOKUP($AD$19,Sheet1!F20:I20,3,0),0) -> 0 | AE24: =+IFERROR(VLOOKUP($AE$19,Sheet1!F20:I20,3,0),0) -> 0 | AF24: 359 | AG24: =+IFERROR(VLOOKUP($AG$19,Sheet1!R20:U20,3,0),0) -> 0 | AH24: 642 | AI24: =+IFERROR(VLOOKUP($AI$19,Sheet1!V20:Y20,3,0),0) -> 0 | AJ24: =+IFERROR(VLOOKUP($AJ$19,Sheet1!V20:Y20,3,0),0) -> 0 | AK24: =+IFERROR(VLOOKUP($AK$19,Sheet1!V20:Y20,3,0),0) -> 0 | AL24: =+IFERROR(VLOOKUP($AL$19,Sheet1!V20:Y20,3,0),0) -> 0 | AM24: =+IFERROR(VLOOKUP($AM$19,Sheet1!V20:Y20,3,0),0) -> 0 | AN24: =+IFERROR(VLOOKUP($AN$19,Sheet1!V20:Y20,3,0),0) -> 0 | AO24: =+IFERROR(VLOOKUP($AO$19,Sheet1!V20:Y20,3,0),0) -> 0 | AP24: =+IFERROR(VLOOKUP($AP$19,Sheet1!V20:Y20,3,0),0) -> 0 | AQ24: =+IFERROR(VLOOKUP($AQ$19,Sheet1!Z20:AB20,3,0),0) -> 0 | AR24: =+IFERROR(VLOOKUP($AR$19,Sheet1!AD20:AG20,3,0),0) -> 0 | AS24: =+IFERROR(VLOOKUP($AS$19,Sheet1!AD20:AG20,3,0),0) -> 0 | AT24: =+IFERROR(VLOOKUP($AT$19,Sheet1!AD20:AG20,3,0),0) -> 0 | AU24: =+IFERROR(VLOOKUP($AU$19,Sheet1!AD20:AG20,3,0),0) -> 0 | AV24: =+IFERROR(VLOOKUP($AV$19,Sheet1!AD20:AG20,3,0),0) -> 0 | AW24: =+IFERROR(VLOOKUP($AW$19,Sheet1!AD20:AG20,3,0),0) -> 0 | AX24: 666 | AY24: =+IFERROR(VLOOKUP($AY$19,Sheet1!AD20:AG20,3,0),0) -> 0 | BA24: =+IFERROR(VLOOKUP($BA$19,Sheet1!AH20:AK20,3,0),0) -> 0 | BB24: =+IFERROR(VLOOKUP($BB$19,Sheet1!AH20:AK20,3,0),0) -> 0 | BC24: =+IFERROR(VLOOKUP($BC$19,Sheet1!AH20:AK20,3,0),0) -> 0 | BD24: =+IFERROR(VLOOKUP($BD$19,Sheet1!AH20:AK20,3,0),0) -> 0 | BE24: =+IFERROR(VLOOKUP($BE$19,Sheet1!AH20:AK20,3,0),0) -> 0 | BF24: =+IFERROR(VLOOKUP($BF$19,Sheet1!AH20:AK20,3,0),0) -> 0 | BG24: =+IFERROR(VLOOKUP($BG$19,Sheet1!AH20:AK20,3,0),0) -> 0 | BH24: =+IFERROR(VLOOKUP($BH$19,Sheet1!AH20:AK20,3,0),0) -> 0 | BI24: =+IFERROR(VLOOKUP($BI$19,Sheet1!AH20:AK20,3,0),0) -> 0 | BJ24: 2605 | BK24: =+IFERROR(VLOOKUP($BK$19,Sheet1!AH20:AK20,3,0),0) -> 0 | BL24: =+IFERROR(VLOOKUP($BL$19,Sheet1!AL20:AO20,3,0),0) -> 0 | BM24: =+IFERROR(VLOOKUP($BM$19,Sheet1!AL20:AO20,3,0),0) -> 0 | BN24: =+IFERROR(VLOOKUP($BN$19,Sheet1!AL20:AO20,3,0),0) -> 0 | BO24: 812 | BP24: =+IFERROR(VLOOKUP($BP$19,Sheet1!AL20:AO20,3,0),0) -> 0 | BQ24: =+IFERROR(VLOOKUP($BQ$19,Sheet1!AL20:AO20,3,0),0) -> 0 | BR24: =+IFERROR(VLOOKUP($BR$19,Sheet1!AL20:AO20,3,0),0) -> 0 | BS24: =+IFERROR(VLOOKUP($BS$19,Sheet1!AL20:AO20,3,0),0) -> 0 | BT24: =+IFERROR(VLOOKUP($BT$19,Sheet1!AL20:AO20,3,0),0) -> 0 | BU24: =+IFERROR(VLOOKUP($BU$19,Sheet1!AL20:AO20,3,0),0) -> 0 | BV24: =+IFERROR(VLOOKUP($BV$19,Sheet1!AL20:AO20,3,0),0) -> 0 | BW24: =+IFERROR(VLOOKUP($BW$19,Sheet1!AL20:AO20,3,0),0) -> 0 | BX24: 567 | BY24: 18 | BZ24: =+IFERROR(VLOOKUP($BZ$19,Sheet1!AX20:BA20,3,0),0) -> 0 | CA24: 67 | CB24: =+IFERROR(VLOOKUP($CB$19,Sheet1!BF20:BI20,3,0),0) -> 0 | CC24: =+IFERROR(VLOOKUP($CC$19,Sheet1!BJ20:BM20,3,0),0) -> 0 | CD24: =+IFERROR(VLOOKUP($CD$19,Sheet1!BN20:BQ20,3,0),0) -> 0 | CE24: 44 | CF24: =+IFERROR(VLOOKUP($CF$19,Sheet1!BV20:BY20,3,0),0) -> 0 | CG24: =Sheet1!E20 -> STEEL | CH24: SP0400118 | CI24: CORRUGATED DISPATCH STEEL DRUM 1700 X 1000 X 1200 | CJ24: =Sheet1!CX20 -> 250 | CK24: =11700/0.25 -> 46800 | CL24: =SUMPRODUCT($N$20:$CF$20,N24:CF24)+CK24 -> 1117046 | CM24: 0.01 | CN24: =CL24*CM24 -> 11170.46 | CO24: 0.18 | CP24: =CL24*CO24 -> 201068.28 | CQ24: =Sheet1!CF20 -> 0 | CR24: =CL24*CQ24 -> 0 | CS24: =CL24+CN24+CP24+CR24 -> 1329284.7 | CT24: 0.02 | CU24: =CS24*CT24 -> 26585.695 | CV24: 0.01 | CW24: =CS24*CV24 -> 13292.847 | CX24: =Sheet1!CM20 -> 0 | CY24: =CX24*CS24 -> 0
A25: =Sheet1!A21 -> ENQ-18390-25-26 | B25: 46357 | C25: =Sheet1!C21 -> FA1300197 | D25: =Sheet1!D21 -> 3 CORE X 120 SQ. MM. AL/ARM - WIRE (XLPE) - 11 KV | E25: =CS25+CU25+CW25+CY25 -> 1221563.3 | F25: =ROUNDUP(M53,0) -> 36250 | G25: =E25+F25 -> 1257813.3 | H25: =Sheet1!CR21 -> 0.18 | I25: =G25*H25 -> 226406.39 | J25: =G25+I25 -> 1484219.6 | K25: =Sheet1!CU21 -> 8 | L25: =Sheet1!CV21 -> KMS | M25: =J25*K25 -> 11873757 | N25: =+IFERROR(VLOOKUP($N$19,Sheet1!J21:L21,3,0),0) -> 972 | O25: =+IFERROR(VLOOKUP($O$19,Sheet1!J21:L21,3,0),0) -> 0 | P25: =+IFERROR(VLOOKUP($P$19,Sheet1!J21:M21,3,0),0) -> 0 | Q25: =+IFERROR(VLOOKUP($Q$19,Sheet1!J21:M21,3,0),0) -> 0 | R25: =+IFERROR(VLOOKUP($R$19,Sheet1!J21:M21,3,0),0) -> 0 | S25: =+IFERROR(VLOOKUP($S$19,Sheet1!J21:M21,3,0),0) -> 0 | T25: =+IFERROR(VLOOKUP($T$19,Sheet1!J21:M21,3,0),0) -> 0 | U25: =+IFERROR(VLOOKUP($U$19,Sheet1!J21:M21,3,0),0) -> 0 | V25: =+IFERROR(VLOOKUP($V$19,Sheet1!N21:Q21,3,0),0) -> 0 | W25: =+IFERROR(VLOOKUP($W$19,Sheet1!N21:Q21,3,0),0) -> 0 | X25: =+IFERROR(VLOOKUP($X$19,Sheet1!F21:I21,3,0),0) -> 0 | Y25: =+IFERROR(VLOOKUP($Y$19,Sheet1!F21:I21,3,0),0) -> 0 | Z25: =+IFERROR(VLOOKUP($Z$19,Sheet1!F21:I21,3,0),0) -> 0 | AA25: =+IFERROR(VLOOKUP($AA$19,Sheet1!F21:I21,3,0),0) -> 0 | AB25: 123 | AC25: =+IFERROR(VLOOKUP($AC$19,Sheet1!F21:I21,3,0),0) -> 0 | AD25: =+IFERROR(VLOOKUP($AD$19,Sheet1!F21:I21,3,0),0) -> 0 | AE25: =+IFERROR(VLOOKUP($AE$19,Sheet1!F21:I21,3,0),0) -> 0 | AF25: 332 | AG25: =+IFERROR(VLOOKUP($AG$19,Sheet1!R21:U21,3,0),0) -> 0 | AH25: 593 | AI25: =+IFERROR(VLOOKUP($AI$19,Sheet1!V21:Y21,3,0),0) -> 0 | AJ25: =+IFERROR(VLOOKUP($AJ$19,Sheet1!V21:Y21,3,0),0) -> 0 | AK25: =+IFERROR(VLOOKUP($AK$19,Sheet1!V21:Y21,3,0),0) -> 0 | AL25: =+IFERROR(VLOOKUP($AL$19,Sheet1!V21:Y21,3,0),0) -> 0 | AM25: =+IFERROR(VLOOKUP($AM$19,Sheet1!V21:Y21,3,0),0) -> 0 | AN25: =+IFERROR(VLOOKUP($AN$19,Sheet1!V21:Y21,3,0),0) -> 0 | AO25: =+IFERROR(VLOOKUP($AO$19,Sheet1!V21:Y21,3,0),0) -> 0 | AP25: =+IFERROR(VLOOKUP($AP$19,Sheet1!V21:Y21,3,0),0) -> 0 | AQ25: =+IFERROR(VLOOKUP($AQ$19,Sheet1!Z21:AB21,3,0),0) -> 0 | AR25: =+IFERROR(VLOOKUP($AR$19,Sheet1!AD21:AG21,3,0),0) -> 0 | AS25: =+IFERROR(VLOOKUP($AS$19,Sheet1!AD21:AG21,3,0),0) -> 0 | AT25: =+IFERROR(VLOOKUP($AT$19,Sheet1!AD21:AG21,3,0),0) -> 0 | AU25: =+IFERROR(VLOOKUP($AU$19,Sheet1!AD21:AG21,3,0),0) -> 0 | AV25: =+IFERROR(VLOOKUP($AV$19,Sheet1!AD21:AG21,3,0),0) -> 0 | AW25: =+IFERROR(VLOOKUP($AW$19,Sheet1!AD21:AG21,3,0),0) -> 0 | AX25: 605 | AY25: =+IFERROR(VLOOKUP($AY$19,Sheet1!AD21:AG21,3,0),0) -> 0 | BA25: =+IFERROR(VLOOKUP($BA$19,Sheet1!AH21:AK21,3,0),0) -> 0 | BB25: =+IFERROR(VLOOKUP($BB$19,Sheet1!AH21:AK21,3,0),0) -> 0 | BC25: =+IFERROR(VLOOKUP($BC$19,Sheet1!AH21:AK21,3,0),0) -> 0 | BD25: =+IFERROR(VLOOKUP($BD$19,Sheet1!AH21:AK21,3,0),0) -> 0 | BE25: =+IFERROR(VLOOKUP($BE$19,Sheet1!AH21:AK21,3,0),0) -> 0 | BF25: =+IFERROR(VLOOKUP($BF$19,Sheet1!AH21:AK21,3,0),0) -> 0 | BG25: =+IFERROR(VLOOKUP($BG$19,Sheet1!AH21:AK21,3,0),0) -> 0 | BH25: =+IFERROR(VLOOKUP($BH$19,Sheet1!AH21:AK21,3,0),0) -> 0 | BI25: =+IFERROR(VLOOKUP($BI$19,Sheet1!AH21:AK21,3,0),0) -> 0 | BJ25: 2485 | BK25: =+IFERROR(VLOOKUP($BK$19,Sheet1!AH21:AK21,3,0),0) -> 0 | BL25: =+IFERROR(VLOOKUP($BL$19,Sheet1!AL21:AO21,3,0),0) -> 0 | BM25: =+IFERROR(VLOOKUP($BM$19,Sheet1!AL21:AO21,3,0),0) -> 0 | BN25: =+IFERROR(VLOOKUP($BN$19,Sheet1!AL21:AO21,3,0),0) -> 0 | BO25: 726 | BP25: =+IFERROR(VLOOKUP($BP$19,Sheet1!AL21:AO21,3,0),0) -> 0 | BQ25: =+IFERROR(VLOOKUP($BQ$19,Sheet1!AL21:AO21,3,0),0) -> 0 | BR25: =+IFERROR(VLOOKUP($BR$19,Sheet1!AL21:AO21,3,0),0) -> 0 | BS25: =+IFERROR(VLOOKUP($BS$19,Sheet1!AL21:AO21,3,0),0) -> 0 | BT25: =+IFERROR(VLOOKUP($BT$19,Sheet1!AL21:AO21,3,0),0) -> 0 | BU25: =+IFERROR(VLOOKUP($BU$19,Sheet1!AL21:AO21,3,0),0) -> 0 | BV25: =+IFERROR(VLOOKUP($BV$19,Sheet1!AL21:AO21,3,0),0) -> 0 | BW25: =+IFERROR(VLOOKUP($BW$19,Sheet1!AL21:AO21,3,0),0) -> 0 | BX25: 503 | BY25: 17 | BZ25: =+IFERROR(VLOOKUP($BZ$19,Sheet1!AX21:BA21,3,0),0) -> 0 | CA25: 62 | CB25: =+IFERROR(VLOOKUP($CB$19,Sheet1!BF21:BI21,3,0),0) -> 0 | CC25: =+IFERROR(VLOOKUP($CC$19,Sheet1!BJ21:BM21,3,0),0) -> 0 | CD25: =+IFERROR(VLOOKUP($CD$19,Sheet1!BN21:BQ21,3,0),0) -> 0 | CE25: 42 | CF25: =+IFERROR(VLOOKUP($CF$19,Sheet1!BV21:BY21,3,0),0) -> 0 | CG25: =Sheet1!E21 -> STEEL | CH25: SP0400118 | CI25: CORRUGATED DISPATCH STEEL DRUM 1700 X 1000 X 1200 | CJ25: =Sheet1!CX21 -> 250 | CK25: =11700/0.25 -> 46800 | CL25: =SUMPRODUCT($N$20:$CF$20,N25:CF25)+CK25 -> 996625 | CM25: 0.01 | CN25: =CL25*CM25 -> 9966.25 | CO25: 0.18 | CP25: =CL25*CO25 -> 179392.5 | CQ25: =Sheet1!CF21 -> 0 | CR25: =CL25*CQ25 -> 0 | CS25: =CL25+CN25+CP25+CR25 -> 1185983.8 | CT25: 0.02 | CU25: =CS25*CT25 -> 23719.675 | CV25: 0.01 | CW25: =CS25*CV25 -> 11859.837 | CX25: =Sheet1!CM21 -> 0 | CY25: =CX25*CS25 -> 0
A26: =Sheet1!A17 -> ENQ-18390-25-26 | B26: 46357 | C26: =Sheet1!C17 -> FA1300098 | D26: =Sheet1!D17 -> 3 CORE X 95 SQ. MM. AL/ARM - WIRE (XLPE) - 11 KV | E26: =CS26+CU26+CW26+CY26 -> 1179376.7 | F26: =ROUNDUP(M54,0) -> 25589 | G26: =E26+F26 -> 1204965.7 | H26: =Sheet1!CR17 -> 0.18 | I26: =G26*H26 -> 216893.83 | J26: =G26+I26 -> 1421859.5 | K26: =Sheet1!CU17 -> 25.5 | L26: =Sheet1!CV17 -> KMS | M26: =J26*K26 -> 36257418 | N26: =+IFERROR(VLOOKUP($N$19,Sheet1!J17:L17,3,0),0) -> 770 | O26: =+IFERROR(VLOOKUP($O$19,Sheet1!J17:L17,3,0),0) -> 0 | P26: =+IFERROR(VLOOKUP($P$19,Sheet1!J17:M17,3,0),0) -> 0 | Q26: =+IFERROR(VLOOKUP($Q$19,Sheet1!J17:M17,3,0),0) -> 0 | R26: =+IFERROR(VLOOKUP($R$19,Sheet1!J17:M17,3,0),0) -> 0 | S26: =+IFERROR(VLOOKUP($S$19,Sheet1!J17:M17,3,0),0) -> 0 | T26: =+IFERROR(VLOOKUP($T$19,Sheet1!J17:M17,3,0),0) -> 0 | U26: =+IFERROR(VLOOKUP($U$19,Sheet1!J17:M17,3,0),0) -> 0 | V26: =+IFERROR(VLOOKUP($V$19,Sheet1!N17:Q17,3,0),0) -> 0 | W26: =+IFERROR(VLOOKUP($W$19,Sheet1!N17:Q17,3,0),0) -> 0 | X26: =+IFERROR(VLOOKUP($X$19,Sheet1!F17:I17,3,0),0) -> 0 | Y26: =+IFERROR(VLOOKUP($Y$19,Sheet1!F17:I17,3,0),0) -> 0 | Z26: =+IFERROR(VLOOKUP($Z$19,Sheet1!F17:I17,3,0),0) -> 0 | AA26: =+IFERROR(VLOOKUP($AA$19,Sheet1!F17:I17,3,0),0) -> 0 | AB26: 115 | AC26: =+IFERROR(VLOOKUP($AC$19,Sheet1!F17:I17,3,0),0) -> 0 | AD26: =+IFERROR(VLOOKUP($AD$19,Sheet1!F17:I17,3,0),0) -> 0 | AE26: =+IFERROR(VLOOKUP($AE$19,Sheet1!F17:I17,3,0),0) -> 0 | AF26: 304 | AG26: =+IFERROR(VLOOKUP($AG$19,Sheet1!R17:U17,3,0),0) -> 0 | AH26: 542 | AI26: =+IFERROR(VLOOKUP($AI$19,Sheet1!V17:Y17,3,0),0) -> 0 | AJ26: =+IFERROR(VLOOKUP($AJ$19,Sheet1!V17:Y17,3,0),0) -> 0 | AK26: =+IFERROR(VLOOKUP($AK$19,Sheet1!V17:Y17,3,0),0) -> 0 | AL26: =+IFERROR(VLOOKUP($AL$19,Sheet1!V17:Y17,3,0),0) -> 0 | AM26: =+IFERROR(VLOOKUP($AM$19,Sheet1!V17:Y17,3,0),0) -> 0 | AN26: =+IFERROR(VLOOKUP($AN$19,Sheet1!V17:Y17,3,0),0) -> 0 | AO26: =+IFERROR(VLOOKUP($AO$19,Sheet1!V17:Y17,3,0),0) -> 0 | AP26: =+IFERROR(VLOOKUP($AP$19,Sheet1!V17:Y17,3,0),0) -> 0 | AQ26: =+IFERROR(VLOOKUP($AQ$19,Sheet1!Z17:AB17,3,0),0) -> 0 | AR26: =+IFERROR(VLOOKUP($AR$19,Sheet1!AD17:AG17,3,0),0) -> 0 | AS26: =+IFERROR(VLOOKUP($AS$19,Sheet1!AD17:AG17,3,0),0) -> 0 | AT26: =+IFERROR(VLOOKUP($AT$19,Sheet1!AD17:AG17,3,0),0) -> 0 | AU26: =+IFERROR(VLOOKUP($AU$19,Sheet1!AD17:AG17,3,0),0) -> 0 | AV26: =+IFERROR(VLOOKUP($AV$19,Sheet1!AD17:AG17,3,0),0) -> 0 | AW26: =+IFERROR(VLOOKUP($AW$19,Sheet1!AD17:AG17,3,0),0) -> 0 | AX26: 576 | AY26: =+IFERROR(VLOOKUP($AY$19,Sheet1!AD17:AG17,3,0),0) -> 0 | BA26: =+IFERROR(VLOOKUP($BA$19,Sheet1!AH17:AK17,3,0),0) -> 0 | BB26: =+IFERROR(VLOOKUP($BB$19,Sheet1!AH17:AK17,3,0),0) -> 0 | BC26: =+IFERROR(VLOOKUP($BC$19,Sheet1!AH17:AK17,3,0),0) -> 0 | BD26: =+IFERROR(VLOOKUP($BD$19,Sheet1!AH17:AK17,3,0),0) -> 0 | BE26: =+IFERROR(VLOOKUP($BE$19,Sheet1!AH17:AK17,3,0),0) -> 0 | BF26: =+IFERROR(VLOOKUP($BF$19,Sheet1!AH17:AK17,3,0),0) -> 0 | BG26: =+IFERROR(VLOOKUP($BG$19,Sheet1!AH17:AK17,3,0),0) -> 0 | BH26: =+IFERROR(VLOOKUP($BH$19,Sheet1!AH17:AK17,3,0),0) -> 0 | BI26: =+IFERROR(VLOOKUP($BI$19,Sheet1!AH17:AK17,3,0),0) -> 0 | BJ26: 2324 | BK26: =+IFERROR(VLOOKUP($BK$19,Sheet1!AH17:AK17,3,0),0) -> 0 | BL26: =+IFERROR(VLOOKUP($BL$19,Sheet1!AL17:AO17,3,0),0) -> 0 | BM26: =+IFERROR(VLOOKUP($BM$19,Sheet1!AL17:AO17,3,0),0) -> 0 | BN26: =+IFERROR(VLOOKUP($BN$19,Sheet1!AL17:AO17,3,0),0) -> 0 | BO26: 685 | BP26: =+IFERROR(VLOOKUP($BP$19,Sheet1!AL17:AO17,3,0),0) -> 0 | BQ26: =+IFERROR(VLOOKUP($BQ$19,Sheet1!AL17:AO17,3,0),0) -> 0 | BR26: =+IFERROR(VLOOKUP($BR$19,Sheet1!AL17:AO17,3,0),0) -> 0 | BS26: =+IFERROR(VLOOKUP($BS$19,Sheet1!AL17:AO17,3,0),0) -> 0 | BT26: =+IFERROR(VLOOKUP($BT$19,Sheet1!AL17:AO17,3,0),0) -> 0 | BU26: =+IFERROR(VLOOKUP($BU$19,Sheet1!AL17:AO17,3,0),0) -> 0 | BV26: =+IFERROR(VLOOKUP($BV$19,Sheet1!AL17:AO17,3,0),0) -> 0 | BW26: =+IFERROR(VLOOKUP($BW$19,Sheet1!AL17:AO17,3,0),0) -> 0 | BX26: 418 | BY26: 15 | BZ26: =+IFERROR(VLOOKUP($BZ$19,Sheet1!AX17:BA17,3,0),0) -> 75 | CA26: 57 | CB26: =+IFERROR(VLOOKUP($CB$19,Sheet1!BF17:BI17,3,0),0) -> 0 | CC26: =+IFERROR(VLOOKUP($CC$19,Sheet1!BJ17:BM17,3,0),0) -> 0 | CD26: =+IFERROR(VLOOKUP($CD$19,Sheet1!BN17:BQ17,3,0),0) -> 0 | CE26: 40 | CF26: =+IFERROR(VLOOKUP($CF$19,Sheet1!BV17:BY17,3,0),0) -> 0 | CG26: =Sheet1!E17 -> STEEL | CH26: SP0400110 | CI26: CORRUGATED DISPATCH STEEL DRUM 1600 X 900 X 1000 MM | CJ26: =Sheet1!CX17 -> 250 | CK26: =11700/0.25 -> 46800 | CL26: =SUMPRODUCT($N$20:$CF$20,N26:CF26)+CK26 -> 887617 | CM26: 0.01 | CN26: =CL26*CM26 -> 8876.17 | CO26: 0.28 | CP26: =CL26*CO26 -> 248532.76 | CQ26: =Sheet1!CF17 -> 0 | CR26: =CL26*CQ26 -> 0 | CS26: =CL26+CN26+CP26+CR26 -> 1145025.9 | CT26: 0.02 | CU26: =CS26*CT26 -> 22900.519 | CV26: 0.01 | CW26: =CS26*CV26 -> 11450.259 | CX26: =Sheet1!CM17 -> 0 | CY26: =CX26*CS26 -> 0
A27: =Sheet1!A16 -> ENQ-18390-25-26 | B27: 46357 | C27: =Sheet1!C16 -> FA1300097 | D27: =Sheet1!D16 -> 3 CORE X 70 SQ. MM. AL/ARM - WIRE (XLPE) - 11 KV | E27: =CS27+CU27+CW27+CY27 -> 1034557.7 | F27: =ROUNDUP(M55,0) -> 26364 | G27: =E27+F27 -> 1060921.7 | H27: =Sheet1!CR16 -> 0.18 | I27: =G27*H27 -> 190965.91 | J27: =G27+I27 -> 1251887.6 | K27: =Sheet1!CU16 -> 5.5 | L27: =Sheet1!CV16 -> KMS | M27: =J27*K27 -> 6885381.9 | N27: =+IFERROR(VLOOKUP($N$19,Sheet1!J16:L16,3,0),0) -> 567 | O27: =+IFERROR(VLOOKUP($O$19,Sheet1!J16:L16,3,0),0) -> 0 | P27: =+IFERROR(VLOOKUP($P$19,Sheet1!J16:M16,3,0),0) -> 0 | Q27: =+IFERROR(VLOOKUP($Q$19,Sheet1!J16:M16,3,0),0) -> 0 | R27: =+IFERROR(VLOOKUP($R$19,Sheet1!J16:M16,3,0),0) -> 0 | S27: =+IFERROR(VLOOKUP($S$19,Sheet1!J16:M16,3,0),0) -> 0 | T27: =+IFERROR(VLOOKUP($T$19,Sheet1!J16:M16,3,0),0) -> 0 | U27: =+IFERROR(VLOOKUP($U$19,Sheet1!J16:M16,3,0),0) -> 0 | V27: =+IFERROR(VLOOKUP($V$19,Sheet1!N16:Q16,3,0),0) -> 0 | W27: =+IFERROR(VLOOKUP($W$19,Sheet1!N16:Q16,3,0),0) -> 0 | X27: =+IFERROR(VLOOKUP($X$19,Sheet1!F16:I16,3,0),0) -> 0 | Y27: =+IFERROR(VLOOKUP($Y$19,Sheet1!F16:I16,3,0),0) -> 0 | Z27: =+IFERROR(VLOOKUP($Z$19,Sheet1!F16:I16,3,0),0) -> 0 | AA27: =+IFERROR(VLOOKUP($AA$19,Sheet1!F16:I16,3,0),0) -> 0 | AB27: 107 | AC27: =+IFERROR(VLOOKUP($AC$19,Sheet1!F16:I16,3,0),0) -> 0 | AD27: =+IFERROR(VLOOKUP($AD$19,Sheet1!F16:I16,3,0),0) -> 0 | AE27: =+IFERROR(VLOOKUP($AE$19,Sheet1!F16:I16,3,0),0) -> 0 | AF27: 268 | AG27: =+IFERROR(VLOOKUP($AG$19,Sheet1!R16:U16,3,0),0) -> 0 | AH27: 497 | AI27: =+IFERROR(VLOOKUP($AI$19,Sheet1!V16:Y16,3,0),0) -> 0 | AJ27: =+IFERROR(VLOOKUP($AJ$19,Sheet1!V16:Y16,3,0),0) -> 0 | AK27: =+IFERROR(VLOOKUP($AK$19,Sheet1!V16:Y16,3,0),0) -> 0 | AL27: =+IFERROR(VLOOKUP($AL$19,Sheet1!V16:Y16,3,0),0) -> 0 | AM27: =+IFERROR(VLOOKUP($AM$19,Sheet1!V16:Y16,3,0),0) -> 0 | AN27: =+IFERROR(VLOOKUP($AN$19,Sheet1!V16:Y16,3,0),0) -> 0 | AO27: =+IFERROR(VLOOKUP($AO$19,Sheet1!V16:Y16,3,0),0) -> 0 | AP27: =+IFERROR(VLOOKUP($AP$19,Sheet1!V16:Y16,3,0),0) -> 0 | AQ27: =+IFERROR(VLOOKUP($AQ$19,Sheet1!Z16:AB16,3,0),0) -> 0 | AR27: =+IFERROR(VLOOKUP($AR$19,Sheet1!AD16:AG16,3,0),0) -> 0 | AS27: =+IFERROR(VLOOKUP($AS$19,Sheet1!AD16:AG16,3,0),0) -> 0 | AT27: =+IFERROR(VLOOKUP($AT$19,Sheet1!AD16:AG16,3,0),0) -> 0 | AU27: =+IFERROR(VLOOKUP($AU$19,Sheet1!AD16:AG16,3,0),0) -> 0 | AV27: =+IFERROR(VLOOKUP($AV$19,Sheet1!AD16:AG16,3,0),0) -> 0 | AW27: =+IFERROR(VLOOKUP($AW$19,Sheet1!AD16:AG16,3,0),0) -> 0 | AX27: 477 | AY27: =+IFERROR(VLOOKUP($AY$19,Sheet1!AD16:AG16,3,0),0) -> 0 | BA27: =+IFERROR(VLOOKUP($BA$19,Sheet1!AH16:AK16,3,0),0) -> 0 | BB27: =+IFERROR(VLOOKUP($BB$19,Sheet1!AH16:AK16,3,0),0) -> 0 | BC27: =+IFERROR(VLOOKUP($BC$19,Sheet1!AH16:AK16,3,0),0) -> 0 | BD27: =+IFERROR(VLOOKUP($BD$19,Sheet1!AH16:AK16,3,0),0) -> 0 | BE27: =+IFERROR(VLOOKUP($BE$19,Sheet1!AH16:AK16,3,0),0) -> 0 | BF27: =+IFERROR(VLOOKUP($BF$19,Sheet1!AH16:AK16,3,0),0) -> 0 | BG27: =+IFERROR(VLOOKUP($BG$19,Sheet1!AH16:AK16,3,0),0) -> 0 | BH27: =+IFERROR(VLOOKUP($BH$19,Sheet1!AH16:AK16,3,0),0) -> 0 | BI27: =+IFERROR(VLOOKUP($BI$19,Sheet1!AH16:AK16,3,0),0) -> 0 | BJ27: 2204 | BK27: =+IFERROR(VLOOKUP($BK$19,Sheet1!AH16:AK16,3,0),0) -> 0 | BL27: =+IFERROR(VLOOKUP($BL$19,Sheet1!AL16:AO16,3,0),0) -> 0 | BM27: =+IFERROR(VLOOKUP($BM$19,Sheet1!AL16:AO16,3,0),0) -> 0 | BN27: =+IFERROR(VLOOKUP($BN$19,Sheet1!AL16:AO16,3,0),0) -> 0 | BO27: 610 | BP27: =+IFERROR(VLOOKUP($BP$19,Sheet1!AL16:AO16,3,0),0) -> 0 | BQ27: =+IFERROR(VLOOKUP($BQ$19,Sheet1!AL16:AO16,3,0),0) -> 0 | BR27: =+IFERROR(VLOOKUP($BR$19,Sheet1!AL16:AO16,3,0),0) -> 0 | BS27: =+IFERROR(VLOOKUP($BS$19,Sheet1!AL16:AO16,3,0),0) -> 0 | BT27: =+IFERROR(VLOOKUP($BT$19,Sheet1!AL16:AO16,3,0),0) -> 0 | BU27: =+IFERROR(VLOOKUP($BU$19,Sheet1!AL16:AO16,3,0),0) -> 0 | BV27: =+IFERROR(VLOOKUP($BV$19,Sheet1!AL16:AO16,3,0),0) -> 0 | BW27: =+IFERROR(VLOOKUP($BW$19,Sheet1!AL16:AO16,3,0),0) -> 0 | BX27: 383 | BY27: 15 | BZ27: =+IFERROR(VLOOKUP($BZ$19,Sheet1!AX16:BA16,3,0),0) -> 0 | CA27: 53 | CB27: =+IFERROR(VLOOKUP($CB$19,Sheet1!BF16:BI16,3,0),0) -> 0 | CC27: =+IFERROR(VLOOKUP($CC$19,Sheet1!BJ16:BM16,3,0),0) -> 0 | CD27: =+IFERROR(VLOOKUP($CD$19,Sheet1!BN16:BQ16,3,0),0) -> 0 | CE27: 38 | CF27: =+IFERROR(VLOOKUP($CF$19,Sheet1!BV16:BY16,3,0),0) -> 0 | CG27: =Sheet1!E16 -> STEEL | CH27: SP0400125 | CI27: CORRUGATED DISPATCH STEEL DRUM 1600 X 700 X 915 MM | CJ27: =Sheet1!CX16 -> 250 | CK27: =11700/0.25 -> 46800 | CL27: =SUMPRODUCT($N$20:$CF$20,N27:CF27)+CK27 -> 778624 | CM27: 0.01 | CN27: =CL27*CM27 -> 7786.24 | CO27: 0.28 | CP27: =CL27*CO27 -> 218014.72 | CQ27: =Sheet1!CF16 -> 0 | CR27: =CL27*CQ27 -> 0 | CS27: =CL27+CN27+CP27+CR27 -> 1004425 | CT27: 0.02 | CU27: =CS27*CT27 -> 20088.499 | CV27: 0.01 | CW27: =CS27*CV27 -> 10044.25 | CX27: =Sheet1!CM16 -> 0 | CY27: =CX27*CS27 -> 0
A28: =Sheet1!A24 -> ENQ-18390-25-26 | B28: 46357 | C28: =Sheet1!C24 -> FA1300313 | D28: =Sheet1!D24 -> 3 CORE X 50 SQ. MM. AL/ARD - WIRE (XLPE) - 11 KV | E28: =CS28+CU28+CW28+CY28 -> 1009460.3 | F28: =ROUNDUP(M56,0) -> 27188 | G28: =E28+F28 -> 1036648.3 | H28: =Sheet1!CR24 -> 0.18 | I28: =G28*H28 -> 186596.7 | J28: =G28+I28 -> 1223245 | K28: =Sheet1!CU24 -> 8 | L28: =Sheet1!CV24 -> KMS | M28: =J28*K28 -> 9785960.3 | N28: 405 | O28: =+IFERROR(VLOOKUP($O$19,Sheet1!J24:L24,3,0),0) -> 0 | P28: =+IFERROR(VLOOKUP($P$19,Sheet1!J24:M24,3,0),0) -> 0 | Q28: =+IFERROR(VLOOKUP($Q$19,Sheet1!J24:M24,3,0),0) -> 0 | R28: =+IFERROR(VLOOKUP($R$19,Sheet1!J24:M24,3,0),0) -> 0 | S28: =+IFERROR(VLOOKUP($S$19,Sheet1!J24:M24,3,0),0) -> 0 | T28: =+IFERROR(VLOOKUP($T$19,Sheet1!J24:M24,3,0),0) -> 0 | U28: =+IFERROR(VLOOKUP($U$19,Sheet1!J24:M24,3,0),0) -> 0 | V28: =+IFERROR(VLOOKUP($V$19,Sheet1!N24:Q24,3,0),0) -> 0 | W28: =+IFERROR(VLOOKUP($W$19,Sheet1!N24:Q24,3,0),0) -> 0 | X28: =+IFERROR(VLOOKUP($X$19,Sheet1!F24:I24,3,0),0) -> 0 | Y28: =+IFERROR(VLOOKUP($Y$19,Sheet1!F24:I24,3,0),0) -> 0 | Z28: =+IFERROR(VLOOKUP($Z$19,Sheet1!F24:I24,3,0),0) -> 0 | AA28: =+IFERROR(VLOOKUP($AA$19,Sheet1!F24:I24,3,0),0) -> 0 | AB28: 99 | AC28: =+IFERROR(VLOOKUP($AC$19,Sheet1!F24:I24,3,0),0) -> 0 | AD28: =+IFERROR(VLOOKUP($AD$19,Sheet1!F24:I24,3,0),0) -> 0 | AE28: =+IFERROR(VLOOKUP($AE$19,Sheet1!F24:I24,3,0),0) -> 0 | AF28: 241 | AG28: =+IFERROR(VLOOKUP($AG$19,Sheet1!R24:U24,3,0),0) -> 0 | AH28: 446 | AI28: =+IFERROR(VLOOKUP($AI$19,Sheet1!V24:Y24,3,0),0) -> 0 | AJ28: =+IFERROR(VLOOKUP($AJ$19,Sheet1!V24:Y24,3,0),0) -> 0 | AK28: =+IFERROR(VLOOKUP($AK$19,Sheet1!V24:Y24,3,0),0) -> 0 | AL28: =+IFERROR(VLOOKUP($AL$19,Sheet1!V24:Y24,3,0),0) -> 0 | AM28: =+IFERROR(VLOOKUP($AM$19,Sheet1!V24:Y24,3,0),0) -> 0 | AN28: =+IFERROR(VLOOKUP($AN$19,Sheet1!V24:Y24,3,0),0) -> 0 | AO28: =+IFERROR(VLOOKUP($AO$19,Sheet1!V24:Y24,3,0),0) -> 0 | AP28: =+IFERROR(VLOOKUP($AP$19,Sheet1!V24:Y24,3,0),0) -> 0 | AQ28: =+IFERROR(VLOOKUP($AQ$19,Sheet1!Z24:AB24,3,0),0) -> 0 | AR28: =+IFERROR(VLOOKUP($AR$19,Sheet1!AD24:AG24,3,0),0) -> 0 | AS28: =+IFERROR(VLOOKUP($AS$19,Sheet1!AD24:AG24,3,0),0) -> 0 | AT28: =+IFERROR(VLOOKUP($AT$19,Sheet1!AD24:AG24,3,0),0) -> 0 | AU28: =+IFERROR(VLOOKUP($AU$19,Sheet1!AD24:AG24,3,0),0) -> 0 | AV28: =+IFERROR(VLOOKUP($AV$19,Sheet1!AD24:AG24,3,0),0) -> 0 | AW28: =+IFERROR(VLOOKUP($AW$19,Sheet1!AD24:AG24,3,0),0) -> 0 | AX28: 407 | AY28: =+IFERROR(VLOOKUP($AY$19,Sheet1!AD24:AG24,3,0),0) -> 0 | AZ28: =+IFERROR(VLOOKUP($AZ$19,Sheet1!AD24:AG24,3,0),0) -> 0 | BA28: =+IFERROR(VLOOKUP($BA$19,Sheet1!AH24:AK24,3,0),0) -> 0 | BB28: =+IFERROR(VLOOKUP($BB$19,Sheet1!AH24:AK24,3,0),0) -> 0 | BC28: =+IFERROR(VLOOKUP($BC$19,Sheet1!AH24:AK24,3,0),0) -> 0 | BD28: =+IFERROR(VLOOKUP($BD$19,Sheet1!AH24:AK24,3,0),0) -> 0 | BE28: =+IFERROR(VLOOKUP($BE$19,Sheet1!AH24:AK24,3,0),0) -> 0 | BF28: =+IFERROR(VLOOKUP($BF$19,Sheet1!AH24:AK24,3,0),0) -> 0 | BG28: =+IFERROR(VLOOKUP($BG$19,Sheet1!AH24:AK24,3,0),0) -> 0 | BH28: =+IFERROR(VLOOKUP($BH$19,Sheet1!AH24:AK24,3,0),0) -> 0 | BI28: =+IFERROR(VLOOKUP($BI$19,Sheet1!AH24:AK24,3,0),0) -> 0 | BJ28: 2044 | BK28: =+IFERROR(VLOOKUP($BK$19,Sheet1!AH24:AK24,3,0),0) -> 0 | BL28: =+IFERROR(VLOOKUP($BL$19,Sheet1!AL24:AO24,3,0),0) -> 0 | BM28: =+IFERROR(VLOOKUP($BM$19,Sheet1!AL24:AO24,3,0),0) -> 0 | BN28: =+IFERROR(VLOOKUP($BN$19,Sheet1!AL24:AO24,3,0),0) -> 0 | BO28: 566 | BP28: =+IFERROR(VLOOKUP($BP$19,Sheet1!AL24:AO24,3,0),0) -> 0 | BQ28: =+IFERROR(VLOOKUP($BQ$19,Sheet1!AL24:AO24,3,0),0) -> 0 | BR28: =+IFERROR(VLOOKUP($BR$19,Sheet1!AL24:AO24,3,0),0) -> 0 | BS28: =+IFERROR(VLOOKUP($BS$19,Sheet1!AL24:AO24,3,0),0) -> 0 | BT28: =+IFERROR(VLOOKUP($BT$19,Sheet1!AL24:AO24,3,0),0) -> 0 | BU28: =+IFERROR(VLOOKUP($BU$19,Sheet1!AL24:AO24,3,0),0) -> 0 | BV28: =+IFERROR(VLOOKUP($BV$19,Sheet1!AL24:AO24,3,0),0) -> 0 | BW28: =+IFERROR(VLOOKUP($BW$19,Sheet1!AL24:AO24,3,0),0) -> 0 | BX28: 330 | BY28: 6 | BZ28: =+IFERROR(VLOOKUP($BZ$19,Sheet1!AX24:BA24,3,0),0) -> 0 | CA28: 48 | CB28: =+IFERROR(VLOOKUP($CB$19,Sheet1!BF24:BI24,3,0),0) -> 0 | CC28: =+IFERROR(VLOOKUP($CC$19,Sheet1!BJ24:BM24,3,0),0) -> 0 | CD28: =+IFERROR(VLOOKUP($CD$19,Sheet1!BN24:BQ24,3,0),0) -> 0 | CE28: 35 | CF28: =+IFERROR(VLOOKUP($CF$19,Sheet1!BV24:BY24,3,0),0) -> 0 | CG28: =Sheet1!E24 -> STEEL | CH28: SP0400152 | CI28: CORRUGATED DISPATCH STEEL DRUM 1500 X 800 X 915 | CJ28: =Sheet1!CX24 -> 250 | CK28: =9750/0.25 -> 39000 | CL28: =SUMPRODUCT($N$20:$CF$20,N28:CF28)+CK28 -> 671273 | CM28: 0.01 | CN28: =CL28*CM28 -> 6712.73 | CO28: 0.45 | CP28: =CL28*CO28 -> 302072.85 | CQ28: =Sheet1!CF24 -> 0 | CR28: =CL28*CQ28 -> 0 | CS28: =CL28+CN28+CP28+CR28 -> 980058.58 | CT28: 0.02 | CU28: =CS28*CT28 -> 19601.172 | CV28: 0.01 | CW28: =CS28*CV28 -> 9800.5858 | CX28: =Sheet1!CM24 -> 0 | CY28: =CX28*CS28 -> 0
A29: =Sheet1!A18 -> ENQ-18390-25-26 | B29: 46357 | C29: =Sheet1!C18 -> FA1300114 | D29: =Sheet1!D18 -> 3 CORE X 35 SQ. MM. AL/ARM - WIRE (XLPE) - 11 KV | E29: =CS29+CU29+CW29+CY29 -> 847155.2 | F29: =ROUNDUP(M57,0) -> 29000 | G29: =E29+F29 -> 876155.2 | H29: =Sheet1!CR18 -> 0.18 | I29: =G29*H29 -> 157707.94 | J29: =G29+I29 -> 1033863.1 | K29: =Sheet1!CU18 -> 7.5 | L29: =Sheet1!CV18 -> KMS | M29: =J29*K29 -> 7753973.6 | N29: 284 | O29: =+IFERROR(VLOOKUP($O$19,Sheet1!J18:L18,3,0),0) -> 0 | P29: =+IFERROR(VLOOKUP($P$19,Sheet1!J18:M18,3,0),0) -> 0 | Q29: =+IFERROR(VLOOKUP($Q$19,Sheet1!J18:M18,3,0),0) -> 0 | R29: =+IFERROR(VLOOKUP($R$19,Sheet1!J18:M18,3,0),0) -> 0 | S29: =+IFERROR(VLOOKUP($S$19,Sheet1!J18:M18,3,0),0) -> 0 | T29: =+IFERROR(VLOOKUP($T$19,Sheet1!J18:M18,3,0),0) -> 0 | U29: =+IFERROR(VLOOKUP($U$19,Sheet1!J18:M18,3,0),0) -> 0 | V29: =+IFERROR(VLOOKUP($V$19,Sheet1!N18:Q18,3,0),0) -> 0 | W29: =+IFERROR(VLOOKUP($W$19,Sheet1!N18:Q18,3,0),0) -> 0 | X29: =+IFERROR(VLOOKUP($X$19,Sheet1!F18:I18,3,0),0) -> 0 | Y29: =+IFERROR(VLOOKUP($Y$19,Sheet1!F18:I18,3,0),0) -> 0 | Z29: =+IFERROR(VLOOKUP($Z$19,Sheet1!F18:I18,3,0),0) -> 0 | AA29: =+IFERROR(VLOOKUP($AA$19,Sheet1!F18:I18,3,0),0) -> 0 | AB29: 93 | AC29: =+IFERROR(VLOOKUP($AC$19,Sheet1!F18:I18,3,0),0) -> 0 | AD29: =+IFERROR(VLOOKUP($AD$19,Sheet1!F18:I18,3,0),0) -> 0 | AE29: =+IFERROR(VLOOKUP($AE$19,Sheet1!F18:I18,3,0),0) -> 0 | AF29: 220 | AG29: =+IFERROR(VLOOKUP($AG$19,Sheet1!R18:U18,3,0),0) -> 0 | AH29: 410 | AI29: =+IFERROR(VLOOKUP($AI$19,Sheet1!V18:Y18,3,0),0) -> 0 | AJ29: =+IFERROR(VLOOKUP($AJ$19,Sheet1!V18:Y18,3,0),0) -> 0 | AK29: =+IFERROR(VLOOKUP($AK$19,Sheet1!V18:Y18,3,0),0) -> 0 | AL29: =+IFERROR(VLOOKUP($AL$19,Sheet1!V18:Y18,3,0),0) -> 0 | AM29: =+IFERROR(VLOOKUP($AM$19,Sheet1!V18:Y18,3,0),0) -> 0 | AN29: =+IFERROR(VLOOKUP($AN$19,Sheet1!V18:Y18,3,0),0) -> 0 | AO29: =+IFERROR(VLOOKUP($AO$19,Sheet1!V18:Y18,3,0),0) -> 0 | AP29: =+IFERROR(VLOOKUP($AP$19,Sheet1!V18:Y18,3,0),0) -> 0 | AQ29: =+IFERROR(VLOOKUP($AQ$19,Sheet1!Z18:AB18,3,0),0) -> 0 | AR29: =+IFERROR(VLOOKUP($AR$19,Sheet1!AD18:AG18,3,0),0) -> 0 | AS29: =+IFERROR(VLOOKUP($AS$19,Sheet1!AD18:AG18,3,0),0) -> 0 | AT29: =+IFERROR(VLOOKUP($AT$19,Sheet1!AD18:AG18,3,0),0) -> 0 | AU29: =+IFERROR(VLOOKUP($AU$19,Sheet1!AD18:AG18,3,0),0) -> 0 | AV29: =+IFERROR(VLOOKUP($AV$19,Sheet1!AD18:AG18,3,0),0) -> 0 | AW29: =+IFERROR(VLOOKUP($AW$19,Sheet1!AD18:AG18,3,0),0) -> 0 | AX29: 335 | AY29: =+IFERROR(VLOOKUP($AY$19,Sheet1!AD18:AG18,3,0),0) -> 0 | AZ29: =+IFERROR(VLOOKUP($AZ$19,Sheet1!AD18:AG18,3,0),0) -> 0 | BA29: =+IFERROR(VLOOKUP($BA$19,Sheet1!AH18:AK18,3,0),0) -> 0 | BB29: =+IFERROR(VLOOKUP($BB$19,Sheet1!AH18:AK18,3,0),0) -> 0 | BC29: =+IFERROR(VLOOKUP($BC$19,Sheet1!AH18:AK18,3,0),0) -> 0 | BD29: =+IFERROR(VLOOKUP($BD$19,Sheet1!AH18:AK18,3,0),0) -> 0 | BE29: =+IFERROR(VLOOKUP($BE$19,Sheet1!AH18:AK18,3,0),0) -> 0 | BF29: =+IFERROR(VLOOKUP($BF$19,Sheet1!AH18:AK18,3,0),0) -> 0 | BG29: =+IFERROR(VLOOKUP($BG$19,Sheet1!AH18:AK18,3,0),0) -> 0 | BH29: =+IFERROR(VLOOKUP($BH$19,Sheet1!AH18:AK18,3,0),0) -> 0 | BI29: =+IFERROR(VLOOKUP($BI$19,Sheet1!AH18:AK18,3,0),0) -> 0 | BJ29: 1539 | BK29: =+IFERROR(VLOOKUP($BK$19,Sheet1!AH18:AK18,3,0),0) -> 0 | BL29: =+IFERROR(VLOOKUP($BL$19,Sheet1!AL18:AO18,3,0),0) -> 0 | BM29: =+IFERROR(VLOOKUP($BM$19,Sheet1!AL18:AO18,3,0),0) -> 0 | BN29: =+IFERROR(VLOOKUP($BN$19,Sheet1!AL18:AO18,3,0),0) -> 0 | BO29: 500 | BP29: =+IFERROR(VLOOKUP($BP$19,Sheet1!AL18:AO18,3,0),0) -> 0 | BQ29: =+IFERROR(VLOOKUP($BQ$19,Sheet1!AL18:AO18,3,0),0) -> 0 | BR29: =+IFERROR(VLOOKUP($BR$19,Sheet1!AL18:AO18,3,0),0) -> 0 | BS29: =+IFERROR(VLOOKUP($BS$19,Sheet1!AL18:AO18,3,0),0) -> 0 | BT29: =+IFERROR(VLOOKUP($BT$19,Sheet1!AL18:AO18,3,0),0) -> 0 | BU29: =+IFERROR(VLOOKUP($BU$19,Sheet1!AL18:AO18,3,0),0) -> 0 | BV29: =+IFERROR(VLOOKUP($BV$19,Sheet1!AL18:AO18,3,0),0) -> 0 | BW29: =+IFERROR(VLOOKUP($BW$19,Sheet1!AL18:AO18,3,0),0) -> 0 | BX29: 290 | BY29: 6 | BZ29: =+IFERROR(VLOOKUP($BZ$19,Sheet1!AX18:BA18,3,0),0) -> 0 | CA29: 44 | CB29: =+IFERROR(VLOOKUP($CB$19,Sheet1!BF18:BI18,3,0),0) -> 0 | CC29: =+IFERROR(VLOOKUP($CC$19,Sheet1!BJ18:BM18,3,0),0) -> 0 | CD29: =+IFERROR(VLOOKUP($CD$19,Sheet1!BN18:BQ18,3,0),0) -> 0 | CE29: 32 | CF29: =+IFERROR(VLOOKUP($CF$19,Sheet1!BV18:BY18,3,0),0) -> 0 | CG29: STEEL | CH29: SP0400152 | CI29: CORRUGATED DISPATCH STEEL DRUM 1500 X 800 X 915 | CJ29: =Sheet1!CX18 -> 250 | CK29: =9750/0.25 -> 39000 | CL29: =SUMPRODUCT($N$20:$CF$20,N29:CF29)+CK29 -> 563343 | CM29: 0.01 | CN29: =CL29*CM29 -> 5633.43 | CO29: 0.45 | CP29: =CL29*CO29 -> 253504.35 | CQ29: =Sheet1!CF18 -> 0 | CR29: =CL29*CQ29 -> 0 | CS29: =CL29+CN29+CP29+CR29 -> 822480.78 | CT29: 0.02 | CU29: =CS29*CT29 -> 16449.616 | CV29: 0.01 | CW29: =CS29*CV29 -> 8224.8078 | CX29: =Sheet1!CM18 -> 0 | CY29: =CX29*CS29 -> 0
A30: =Sheet1!A9 -> ENQ-18390-25-26 | B30: 46357 | C30: =Sheet1!C9 -> FA1300066 | D30: =Sheet1!D9 -> 1 CORE X 1000 SQ. MM. AL/ARM (XLPE) - 11 KV | E30: =CS30+CU30+CW30+CY30 -> 1757602.3 | F30: =ROUNDUP(M58,0) -> 29000 | G30: =E30+F30 -> 1786602.3 | H30: =Sheet1!CR9 -> 0.18 | I30: =G30*H30 -> 321588.42 | J30: =G30+I30 -> 2108190.7 | K30: =Sheet1!CU9 -> 7.5 | L30: =Sheet1!CV9 -> KMS | M30: =J30*K30 -> 15811431 | N30: =+IFERROR(VLOOKUP($N$19,Sheet1!J9:L9,3,0),0) -> 2732 | O30: =+IFERROR(VLOOKUP($O$19,Sheet1!J9:L9,3,0),0) -> 0 | P30: =+IFERROR(VLOOKUP($P$19,Sheet1!J9:M9,3,0),0) -> 0 | Q30: =+IFERROR(VLOOKUP($Q$19,Sheet1!J9:M9,3,0),0) -> 0 | R30: =+IFERROR(VLOOKUP($R$19,Sheet1!J9:M9,3,0),0) -> 0 | S30: =+IFERROR(VLOOKUP($S$19,Sheet1!J9:M9,3,0),0) -> 0 | T30: =+IFERROR(VLOOKUP($T$19,Sheet1!J9:M9,3,0),0) -> 0 | U30: =+IFERROR(VLOOKUP($U$19,Sheet1!J9:M9,3,0),0) -> 0 | V30: =+IFERROR(VLOOKUP($V$19,Sheet1!N9:Q9,3,0),0) -> 0 | W30: =+IFERROR(VLOOKUP($W$19,Sheet1!N9:Q9,3,0),0) -> 0 | X30: =+IFERROR(VLOOKUP($X$19,Sheet1!F9:I9,3,0),0) -> 0 | Y30: =+IFERROR(VLOOKUP($Y$19,Sheet1!F9:I9,3,0),0) -> 0 | Z30: =+IFERROR(VLOOKUP($Z$19,Sheet1!F9:I9,3,0),0) -> 0 | AA30: =+IFERROR(VLOOKUP($AA$19,Sheet1!F9:I9,3,0),0) -> 0 | AB30: 84 | AC30: =+IFERROR(VLOOKUP($AC$19,Sheet1!F9:I9,3,0),0) -> 0 | AD30: =+IFERROR(VLOOKUP($AD$19,Sheet1!F9:I9,3,0),0) -> 0 | AE30: =+IFERROR(VLOOKUP($AE$19,Sheet1!F9:I9,3,0),0) -> 0 | AF30: 276 | AG30: =+IFERROR(VLOOKUP($AG$19,Sheet1!R9:U9,3,0),0) -> 0 | AH30: 480 | AI30: =+IFERROR(VLOOKUP($AI$19,Sheet1!V9:Y9,3,0),0) -> 0 | AJ30: =+IFERROR(VLOOKUP($AJ$19,Sheet1!V9:Y9,3,0),0) -> 0 | AK30: =+IFERROR(VLOOKUP($AK$19,Sheet1!V9:Y9,3,0),0) -> 0 | AL30: =+IFERROR(VLOOKUP($AL$19,Sheet1!V9:Y9,3,0),0) -> 0 | AM30: =+IFERROR(VLOOKUP($AM$19,Sheet1!V9:Y9,3,0),0) -> 0 | AN30: =+IFERROR(VLOOKUP($AN$19,Sheet1!V9:Y9,3,0),0) -> 0 | AO30: =+IFERROR(VLOOKUP($AO$19,Sheet1!V9:Y9,3,0),0) -> 0 | AP30: =+IFERROR(VLOOKUP($AP$19,Sheet1!V9:Y9,3,0),0) -> 0 | AQ30: 35 | AR30: =+IFERROR(VLOOKUP($AR$19,Sheet1!AD9:AG9,3,0),0) -> 0 | AS30: =+IFERROR(VLOOKUP($AS$19,Sheet1!AD9:AG9,3,0),0) -> 0 | AT30: =+IFERROR(VLOOKUP($AT$19,Sheet1!AD9:AG9,3,0),0) -> 0 | AU30: =+IFERROR(VLOOKUP($AU$19,Sheet1!AD9:AG9,3,0),0) -> 0 | AV30: =+IFERROR(VLOOKUP($AV$19,Sheet1!AD9:AG9,3,0),0) -> 0 | AW30: =+IFERROR(VLOOKUP($AW$19,Sheet1!AD9:AG9,3,0),0) -> 0 | AX30: 218 | AY30: =+IFERROR(VLOOKUP($AY$19,Sheet1!AD9:AG9,3,0),0) -> 0 | AZ30: =+IFERROR(VLOOKUP($AZ$19,Sheet1!AD9:AG9,3,0),0) -> 0 | BA30: =+IFERROR(VLOOKUP($BA$19,Sheet1!AH9:AK9,3,0),0) -> 0 | BB30: =+IFERROR(VLOOKUP($BB$19,Sheet1!AH9:AK9,3,0),0) -> 0 | BC30: =+IFERROR(VLOOKUP($BC$19,Sheet1!AH9:AK9,3,0),0) -> 0 | BD30: 814 | BE30: =+IFERROR(VLOOKUP($BE$19,Sheet1!AH9:AK9,3,0),0) -> 0 | BF30: =+IFERROR(VLOOKUP($BF$19,Sheet1!AH9:AK9,3,0),0) -> 0 | BG30: =+IFERROR(VLOOKUP($BG$19,Sheet1!AH9:AK9,3,0),0) -> 0 | BH30: =+IFERROR(VLOOKUP($BH$19,Sheet1!AH9:AK9,3,0),0) -> 0 | BI30: =+IFERROR(VLOOKUP($BI$19,Sheet1!AH9:AK9,3,0),0) -> 0 | BJ30: =+IFERROR(VLOOKUP($BJ$19,Sheet1!AH9:AK9,3,0),0) -> 0 | BK30: =+IFERROR(VLOOKUP($BK$19,Sheet1!AH9:AK9,3,0),0) -> 0 | BL30: =+IFERROR(VLOOKUP($BL$19,Sheet1!AL9:AO9,3,0),0) -> 0 | BM30: =+IFERROR(VLOOKUP($BM$19,Sheet1!AL9:AO9,3,0),0) -> 0 | BN30: =+IFERROR(VLOOKUP($BN$19,Sheet1!AL9:AO9,3,0),0) -> 0 | BO30: 706 | BP30: =+IFERROR(VLOOKUP($BP$19,Sheet1!AL9:AO9,3,0),0) -> 0 | BQ30: =+IFERROR(VLOOKUP($BQ$19,Sheet1!AL9:AO9,3,0),0) -> 0 | BR30: =+IFERROR(VLOOKUP($BR$19,Sheet1!AL9:AO9,3,0),0) -> 0 | BS30: =+IFERROR(VLOOKUP($BS$19,Sheet1!AL9:AO9,3,0),0) -> 0 | BT30: =+IFERROR(VLOOKUP($BT$19,Sheet1!AL9:AO9,3,0),0) -> 0 | BU30: =+IFERROR(VLOOKUP($BU$19,Sheet1!AL9:AO9,3,0),0) -> 0 | BV30: =+IFERROR(VLOOKUP($BV$19,Sheet1!AL9:AO9,3,0),0) -> 0 | BW30: =+IFERROR(VLOOKUP($BW$19,Sheet1!AL9:AO9,3,0),0) -> 0 | BX30: =+IFERROR(VLOOKUP($BX$19,Sheet1!AP9:AS9,3,0),0) -> 0 | BY30: 39 | BZ30: =+IFERROR(VLOOKUP($BZ$19,Sheet1!AX9:BA9,3,0),0) -> 0 | CA30: 49 | CB30: =+IFERROR(VLOOKUP($CB$19,Sheet1!BF9:BI9,3,0),0) -> 0 | CC30: =+IFERROR(VLOOKUP($CC$19,Sheet1!BJ9:BM9,3,0),0) -> 0 | CD30: =+IFERROR(VLOOKUP($CD$19,Sheet1!BN9:BQ9,3,0),0) -> 0 | CE30: 42 | CF30: =+IFERROR(VLOOKUP($CF$19,Sheet1!BV9:BY9,3,0),0) -> 0 | CG30: =Sheet1!E9 -> STEEL | CH30: SP0400123 | CI30: CORRUGATED DISPATCH STEEL DRUM 2000 X 1000 X 1200 MM | CJ30: =Sheet1!CX9 -> 500 | CK30: =19500/0.5 -> 39000 | CL30: =SUMPRODUCT($N$20:$CF$20,N30:CF30)+CK30 -> 1433958 | CM30: 0.01 | CN30: =CL30*CM30 -> 14339.58 | CO30: 0.18 | CP30: =CL30*CO30 -> 258112.44 | CQ30: =Sheet1!CF9 -> 0 | CR30: =CL30*CQ30 -> 0 | CS30: =CL30+CN30+CP30+CR30 -> 1706410 | CT30: 0.02 | CU30: =CS30*CT30 -> 34128.2 | CV30: 0.01 | CW30: =CS30*CV30 -> 17064.1 | CX30: =Sheet1!CM9 -> 0 | CY30: =CX30*CS30 -> 0
A31: =Sheet1!A3 -> ENQ-18390-25-26 | B31: 46357 | C31: =Sheet1!C3 -> FA1300016 | D31: =Sheet1!D3 -> 1 CORE X 630 SQ. MM. AL/ARM (XLPE) - 11 KV | E31: =CS31+CU31+CW31+CY31 -> 1178291.1 | F31: =ROUNDUP(M59,0) -> 16731 | G31: =E31+F31 -> 1195022.1 | H31: =Sheet1!CR3 -> 0.18 | I31: =G31*H31 -> 215103.99 | J31: =G31+I31 -> 1410126.1 | K31: =Sheet1!CU3 -> 13 | L31: =Sheet1!CV3 -> KMS | M31: =J31*K31 -> 18331640 | N31: =+IFERROR(VLOOKUP($N$19,Sheet1!J3:L3,3,0),0) -> 1701 | O31: =+IFERROR(VLOOKUP($O$19,Sheet1!J3:L3,3,0),0) -> 0 | P31: =+IFERROR(VLOOKUP($P$19,Sheet1!J3:M3,3,0),0) -> 0 | Q31: =+IFERROR(VLOOKUP($Q$19,Sheet1!J3:M3,3,0),0) -> 0 | R31: =+IFERROR(VLOOKUP($R$19,Sheet1!J3:M3,3,0),0) -> 0 | S31: =+IFERROR(VLOOKUP($S$19,Sheet1!J3:M3,3,0),0) -> 0 | T31: =+IFERROR(VLOOKUP($T$19,Sheet1!J3:M3,3,0),0) -> 0 | U31: =+IFERROR(VLOOKUP($U$19,Sheet1!J3:M3,3,0),0) -> 0 | V31: =+IFERROR(VLOOKUP($V$19,Sheet1!N3:Q3,3,0),0) -> 0 | W31: =+IFERROR(VLOOKUP($W$19,Sheet1!N3:Q3,3,0),0) -> 0 | X31: =+IFERROR(VLOOKUP($X$19,Sheet1!F3:I3,3,0),0) -> 0 | Y31: =+IFERROR(VLOOKUP($Y$19,Sheet1!F3:I3,3,0),0) -> 0 | Z31: =+IFERROR(VLOOKUP($Z$19,Sheet1!F3:I3,3,0),0) -> 0 | AA31: =+IFERROR(VLOOKUP($AA$19,Sheet1!F3:I3,3,0),0) -> 0 | AB31: 69 | AC31: =+IFERROR(VLOOKUP($AC$19,Sheet1!F3:I3,3,0),0) -> 0 | AD31: =+IFERROR(VLOOKUP($AD$19,Sheet1!F3:I3,3,0),0) -> 0 | AE31: =+IFERROR(VLOOKUP($AE$19,Sheet1!F3:I3,3,0),0) -> 0 | AF31: 213 | AG31: =+IFERROR(VLOOKUP($AG$19,Sheet1!R3:U3,3,0),0) -> 0 | AH31: 380 | AI31: =+IFERROR(VLOOKUP($AI$19,Sheet1!V3:Y3,3,0),0) -> 0 | AJ31: =+IFERROR(VLOOKUP($AJ$19,Sheet1!V3:Y3,3,0),0) -> 0 | AK31: =+IFERROR(VLOOKUP($AK$19,Sheet1!V3:Y3,3,0),0) -> 0 | AL31: =+IFERROR(VLOOKUP($AL$19,Sheet1!V3:Y3,3,0),0) -> 0 | AM31: =+IFERROR(VLOOKUP($AM$19,Sheet1!V3:Y3,3,0),0) -> 0 | AN31: =+IFERROR(VLOOKUP($AN$19,Sheet1!V3:Y3,3,0),0) -> 0 | AO31: =+IFERROR(VLOOKUP($AO$19,Sheet1!V3:Y3,3,0),0) -> 0 | AP31: =+IFERROR(VLOOKUP($AP$19,Sheet1!V3:Y3,3,0),0) -> 0 | AQ31: 29 | AR31: =+IFERROR(VLOOKUP($AR$19,Sheet1!AD3:AG3,3,0),0) -> 0 | AS31: =+IFERROR(VLOOKUP($AS$19,Sheet1!AD3:AG3,3,0),0) -> 0 | AT31: =+IFERROR(VLOOKUP($AT$19,Sheet1!AD3:AG3,3,0),0) -> 0 | AU31: =+IFERROR(VLOOKUP($AU$19,Sheet1!AD3:AG3,3,0),0) -> 0 | AV31: =+IFERROR(VLOOKUP($AV$19,Sheet1!AD3:AG3,3,0),0) -> 0 | AW31: =+IFERROR(VLOOKUP($AW$19,Sheet1!AD3:AG3,3,0),0) -> 0 | AX31: 159 | AY31: =+IFERROR(VLOOKUP($AY$19,Sheet1!AD3:AG3,3,0),0) -> 0 | AZ31: =+IFERROR(VLOOKUP($AZ$19,Sheet1!AD3:AG3,3,0),0) -> 0 | BA31: =+IFERROR(VLOOKUP($BA$19,Sheet1!AH3:AK3,3,0),0) -> 0 | BB31: =+IFERROR(VLOOKUP($BB$19,Sheet1!AH3:AK3,3,0),0) -> 0 | BC31: =+IFERROR(VLOOKUP($BC$19,Sheet1!AH3:AK3,3,0),0) -> 0 | BD31: 539 | BE31: =+IFERROR(VLOOKUP($BE$19,Sheet1!AH3:AK3,3,0),0) -> 0 | BF31: =+IFERROR(VLOOKUP($BF$19,Sheet1!AH3:AK3,3,0),0) -> 0 | BG31: =+IFERROR(VLOOKUP($BG$19,Sheet1!AH3:AK3,3,0),0) -> 0 | BH31: =+IFERROR(VLOOKUP($BH$19,Sheet1!AH3:AK3,3,0),0) -> 0 | BI31: =+IFERROR(VLOOKUP($BI$19,Sheet1!AH3:AK3,3,0),0) -> 0 | BJ31: =+IFERROR(VLOOKUP($BJ$19,Sheet1!AH3:AK3,3,0),0) -> 0 | BK31: =+IFERROR(VLOOKUP($BK$19,Sheet1!AH3:AK3,3,0),0) -> 0 | BL31: =+IFERROR(VLOOKUP($BL$19,Sheet1!AL3:AO3,3,0),0) -> 0 | BM31: =+IFERROR(VLOOKUP($BM$19,Sheet1!AL3:AO3,3,0),0) -> 0 | BN31: =+IFERROR(VLOOKUP($BN$19,Sheet1!AL3:AO3,3,0),0) -> 0 | BO31: 500 | BP31: =+IFERROR(VLOOKUP($BP$19,Sheet1!AL3:AO3,3,0),0) -> 0 | BQ31: =+IFERROR(VLOOKUP($BQ$19,Sheet1!AL3:AO3,3,0),0) -> 0 | BR31: =+IFERROR(VLOOKUP($BR$19,Sheet1!AL3:AO3,3,0),0) -> 0 | BS31: =+IFERROR(VLOOKUP($BS$19,Sheet1!AL3:AO3,3,0),0) -> 0 | BT31: =+IFERROR(VLOOKUP($BT$19,Sheet1!AL3:AO3,3,0),0) -> 0 | BU31: =+IFERROR(VLOOKUP($BU$19,Sheet1!AL3:AO3,3,0),0) -> 0 | BV31: =+IFERROR(VLOOKUP($BV$19,Sheet1!AL3:AO3,3,0),0) -> 0 | BW31: =+IFERROR(VLOOKUP($BW$19,Sheet1!AL3:AO3,3,0),0) -> 0 | BX31: =+IFERROR(VLOOKUP($BX$19,Sheet1!AP3:AS3,3,0),0) -> 0 | BY31: 26 | BZ31: =+IFERROR(VLOOKUP($BZ$19,Sheet1!AX3:BA3,3,0),0) -> 0 | CA31: 39 | CB31: =+IFERROR(VLOOKUP($CB$19,Sheet1!BF3:BI3,3,0),0) -> 0 | CC31: =+IFERROR(VLOOKUP($CC$19,Sheet1!BJ3:BM3,3,0),0) -> 0 | CD31: =+IFERROR(VLOOKUP($CD$19,Sheet1!BN3:BQ3,3,0),0) -> 0 | CE31: 33 | CF31: =+IFERROR(VLOOKUP($CF$19,Sheet1!BV3:BY3,3,0),0) -> 0 | CG31: =Sheet1!E3 -> STEEL | CH31: SP0400091 | CI31: CORRUGATED DISPATCH STEEL DRUM 1800 X 900 X 1000 | CJ31: =Sheet1!CX3 -> 500 | CK31: =16250/0.5 -> 32500 | CL31: =SUMPRODUCT($N$20:$CF$20,N31:CF31)+CK31 -> 961321 | CM31: 0.01 | CN31: =CL31*CM31 -> 9613.21 | CO31: 0.18 | CP31: =CL31*CO31 -> 173037.78 | CQ31: =Sheet1!CF3 -> 0 | CR31: =CL31*CQ31 -> 0 | CS31: =CL31+CN31+CP31+CR31 -> 1143972 | CT31: 0.02 | CU31: =CS31*CT31 -> 22879.44 | CV31: 0.01 | CW31: =CS31*CV31 -> 11439.72 | CX31: =Sheet1!CM3 -> 0 | CY31: =CX31*CS31 -> 0
A32: =Sheet1!A8 -> ENQ-18390-25-26 | B32: 46357 | C32: =Sheet1!C8 -> FA1300047 | D32: =Sheet1!D8 -> 1 CORE X 400 SQ. MM. AL/ARM (XLPE) - 11 KV | E32: =CS32+CU32+CW32+CY32 -> 854705.12 | F32: =ROUNDUP(M60,0) -> 11154 | G32: =E32+F32 -> 865859.12 | H32: =Sheet1!CR8 -> 0.18 | I32: =G32*H32 -> 155854.64 | J32: =G32+I32 -> 1021713.8 | K32: =Sheet1!CU8 -> 6.5 | L32: =Sheet1!CV8 -> KMS | M32: =J32*K32 -> 6641139.5 | N32: =+IFERROR(VLOOKUP($N$19,Sheet1!J8:L8,3,0),0) -> 1080 | O32: =+IFERROR(VLOOKUP($O$19,Sheet1!J8:L8,3,0),0) -> 0 | P32: =+IFERROR(VLOOKUP($P$19,Sheet1!J8:M8,3,0),0) -> 0 | Q32: =+IFERROR(VLOOKUP($Q$19,Sheet1!J8:M8,3,0),0) -> 0 | R32: =+IFERROR(VLOOKUP($R$19,Sheet1!J8:M8,3,0),0) -> 0 | S32: =+IFERROR(VLOOKUP($S$19,Sheet1!J8:M8,3,0),0) -> 0 | T32: =+IFERROR(VLOOKUP($T$19,Sheet1!J8:M8,3,0),0) -> 0 | U32: =+IFERROR(VLOOKUP($U$19,Sheet1!J8:M8,3,0),0) -> 0 | V32: =+IFERROR(VLOOKUP($V$19,Sheet1!N8:Q8,3,0),0) -> 0 | W32: =+IFERROR(VLOOKUP($W$19,Sheet1!N8:Q8,3,0),0) -> 0 | X32: =+IFERROR(VLOOKUP($X$19,Sheet1!F8:I8,3,0),0) -> 0 | Y32: =+IFERROR(VLOOKUP($Y$19,Sheet1!F8:I8,3,0),0) -> 0 | Z32: =+IFERROR(VLOOKUP($Z$19,Sheet1!F8:I8,3,0),0) -> 0 | AA32: =+IFERROR(VLOOKUP($AA$19,Sheet1!F8:I8,3,0),0) -> 0 | AB32: 59 | AC32: =+IFERROR(VLOOKUP($AC$19,Sheet1!F8:I8,3,0),0) -> 0 | AD32: =+IFERROR(VLOOKUP($AD$19,Sheet1!F8:I8,3,0),0) -> 0 | AE32: =+IFERROR(VLOOKUP($AE$19,Sheet1!F8:I8,3,0),0) -> 0 | AF32: 172 | AG32: =+IFERROR(VLOOKUP($AG$19,Sheet1!R8:U8,3,0),0) -> 0 | AH32: 310 | AI32: =+IFERROR(VLOOKUP($AI$19,Sheet1!V8:Y8,3,0),0) -> 0 | AJ32: =+IFERROR(VLOOKUP($AJ$19,Sheet1!V8:Y8,3,0),0) -> 0 | AK32: =+IFERROR(VLOOKUP($AK$19,Sheet1!V8:Y8,3,0),0) -> 0 | AL32: =+IFERROR(VLOOKUP($AL$19,Sheet1!V8:Y8,3,0),0) -> 0 | AM32: =+IFERROR(VLOOKUP($AM$19,Sheet1!V8:Y8,3,0),0) -> 0 | AN32: =+IFERROR(VLOOKUP($AN$19,Sheet1!V8:Y8,3,0),0) -> 0 | AO32: =+IFERROR(VLOOKUP($AO$19,Sheet1!V8:Y8,3,0),0) -> 0 | AP32: =+IFERROR(VLOOKUP($AP$19,Sheet1!V8:Y8,3,0),0) -> 0 | AQ32: 24 | AR32: =+IFERROR(VLOOKUP($AR$19,Sheet1!AD8:AG8,3,0),0) -> 0 | AS32: =+IFERROR(VLOOKUP($AS$19,Sheet1!AD8:AG8,3,0),0) -> 0 | AT32: =+IFERROR(VLOOKUP($AT$19,Sheet1!AD8:AG8,3,0),0) -> 0 | AU32: =+IFERROR(VLOOKUP($AU$19,Sheet1!AD8:AG8,3,0),0) -> 0 | AV32: =+IFERROR(VLOOKUP($AV$19,Sheet1!AD8:AG8,3,0),0) -> 0 | AW32: =+IFERROR(VLOOKUP($AW$19,Sheet1!AD8:AG8,3,0),0) -> 0 | AX32: 115 | AY32: =+IFERROR(VLOOKUP($AY$19,Sheet1!AD8:AG8,3,0),0) -> 0 | AZ32: =+IFERROR(VLOOKUP($AZ$19,Sheet1!AD8:AG8,3,0),0) -> 0 | BA32: =+IFERROR(VLOOKUP($BA$19,Sheet1!AH8:AK8,3,0),0) -> 0 | BB32: =+IFERROR(VLOOKUP($BB$19,Sheet1!AH8:AK8,3,0),0) -> 0 | BC32: =+IFERROR(VLOOKUP($BC$19,Sheet1!AH8:AK8,3,0),0) -> 0 | BD32: 460 | BE32: =+IFERROR(VLOOKUP($BE$19,Sheet1!AH8:AK8,3,0),0) -> 0 | BF32: =+IFERROR(VLOOKUP($BF$19,Sheet1!AH8:AK8,3,0),0) -> 0 | BG32: =+IFERROR(VLOOKUP($BG$19,Sheet1!AH8:AK8,3,0),0) -> 0 | BH32: =+IFERROR(VLOOKUP($BH$19,Sheet1!AH8:AK8,3,0),0) -> 0 | BI32: =+IFERROR(VLOOKUP($BI$19,Sheet1!AH8:AK8,3,0),0) -> 0 | BJ32: =+IFERROR(VLOOKUP($BJ$19,Sheet1!AH8:AK8,3,0),0) -> 0 | BK32: =+IFERROR(VLOOKUP($BK$19,Sheet1!AH8:AK8,3,0),0) -> 0 | BL32: =+IFERROR(VLOOKUP($BL$19,Sheet1!AL8:AO8,3,0),0) -> 0 | BM32: =+IFERROR(VLOOKUP($BM$19,Sheet1!AL8:AO8,3,0),0) -> 0 | BN32: =+IFERROR(VLOOKUP($BN$19,Sheet1!AL8:AO8,3,0),0) -> 0 | BO32: 400 | BP32: =+IFERROR(VLOOKUP($BP$19,Sheet1!AL8:AO8,3,0),0) -> 0 | BQ32: =+IFERROR(VLOOKUP($BQ$19,Sheet1!AL8:AO8,3,0),0) -> 0 | BR32: =+IFERROR(VLOOKUP($BR$19,Sheet1!AL8:AO8,3,0),0) -> 0 | BS32: =+IFERROR(VLOOKUP($BS$19,Sheet1!AL8:AO8,3,0),0) -> 0 | BT32: =+IFERROR(VLOOKUP($BT$19,Sheet1!AL8:AO8,3,0),0) -> 0 | BU32: =+IFERROR(VLOOKUP($BU$19,Sheet1!AL8:AO8,3,0),0) -> 0 | BV32: =+IFERROR(VLOOKUP($BV$19,Sheet1!AL8:AO8,3,0),0) -> 0 | BW32: =+IFERROR(VLOOKUP($BW$19,Sheet1!AL8:AO8,3,0),0) -> 0 | BX32: =+IFERROR(VLOOKUP($BX$19,Sheet1!AP8:AS8,3,0),0) -> 0 | BY32: 20 | BZ32: =+IFERROR(VLOOKUP($BZ$19,Sheet1!AX8:BA8,3,0),0) -> 0 | CA32: 32 | CB32: =+IFERROR(VLOOKUP($CB$19,Sheet1!BF8:BI8,3,0),0) -> 0 | CC32: =+IFERROR(VLOOKUP($CC$19,Sheet1!BJ8:BM8,3,0),0) -> 0 | CD32: =+IFERROR(VLOOKUP($CD$19,Sheet1!BN8:BQ8,3,0),0) -> 0 | CE32: 30 | CF32: =+IFERROR(VLOOKUP($CF$19,Sheet1!BV8:BY8,3,0),0) -> 0 | CG32: =Sheet1!E8 -> STEEL | CH32: SP0400125 | CI32: CORRUGATED DISPATCH STEEL DRUM 1600 X 700 X 915 MM | CJ32: =Sheet1!CX8 -> 500 | CK32: =11700/0.5 -> 23400 | CL32: =SUMPRODUCT($N$20:$CF$20,N32:CF32)+CK32 -> 697320 | CM32: 0.01 | CN32: =CL32*CM32 -> 6973.2 | CO32: 0.18 | CP32: =CL32*CO32 -> 125517.6 | CQ32: =Sheet1!CF8 -> 0 | CR32: =CL32*CQ32 -> 0 | CS32: =CL32+CN32+CP32+CR32 -> 829810.8 | CT32: 0.02 | CU32: =CS32*CT32 -> 16596.216 | CV32: 0.01 | CW32: =CS32*CV32 -> 8298.108 | CX32: =Sheet1!CM8 -> 0 | CY32: =CX32*CS32 -> 0
A33: =Sheet1!A2 -> ENQ-18390-25-26 | B33: 46357 | C33: =Sheet1!C2 -> FA1300009 | D33: =Sheet1!D2 -> 1 CORE X 300 SQ. MM. AL./ARM (XLPE) - 11 KV | E33: =CS33+CU33+CW33+CY33 -> 709362.84 | F33: =ROUNDUP(M61,0) -> 24167 | G33: =E33+F33 -> 733529.84 | H33: =Sheet1!CR2 -> 0.18 | I33: =G33*H33 -> 132035.37 | J33: =G33+I33 -> 865565.22 | K33: =Sheet1!CU2 -> 3 | L33: =Sheet1!CV2 -> KMS | M33: =J33*K33 -> 2596695.6 | N33: =+IFERROR(VLOOKUP($N$19,Sheet1!J2:L2,3,0),0) -> 810 | O33: =+IFERROR(VLOOKUP($O$19,Sheet1!J2:L2,3,0),0) -> 0 | P33: =+IFERROR(VLOOKUP($P$19,Sheet1!J2:M2,3,0),0) -> 0 | Q33: =+IFERROR(VLOOKUP($Q$19,Sheet1!J2:M2,3,0),0) -> 0 | R33: =+IFERROR(VLOOKUP($R$19,Sheet1!J2:M2,3,0),0) -> 0 | S33: =+IFERROR(VLOOKUP($S$19,Sheet1!J2:M2,3,0),0) -> 0 | T33: =+IFERROR(VLOOKUP($T$19,Sheet1!J2:M2,3,0),0) -> 0 | U33: =+IFERROR(VLOOKUP($U$19,Sheet1!J2:M2,3,0),0) -> 0 | V33: =+IFERROR(VLOOKUP($V$19,Sheet1!N2:Q2,3,0),0) -> 0 | W33: =+IFERROR(VLOOKUP($W$19,Sheet1!N2:Q2,3,0),0) -> 0 | X33: =+IFERROR(VLOOKUP($X$19,Sheet1!F2:I2,3,0),0) -> 0 | Y33: =+IFERROR(VLOOKUP($Y$19,Sheet1!F2:I2,3,0),0) -> 0 | Z33: =+IFERROR(VLOOKUP($Z$19,Sheet1!F2:I2,3,0),0) -> 0 | AA33: =+IFERROR(VLOOKUP($AA$19,Sheet1!F2:I2,3,0),0) -> 0 | AB33: 54 | AC33: =+IFERROR(VLOOKUP($AC$19,Sheet1!F2:I2,3,0),0) -> 0 | AD33: =+IFERROR(VLOOKUP($AD$19,Sheet1!F2:I2,3,0),0) -> 0 | AE33: =+IFERROR(VLOOKUP($AE$19,Sheet1!F2:I2,3,0),0) -> 0 | AF33: 155 | AG33: =+IFERROR(VLOOKUP($AG$19,Sheet1!R2:U2,3,0),0) -> 0 | AH33: 278 | AI33: =+IFERROR(VLOOKUP($AI$19,Sheet1!V2:Y2,3,0),0) -> 0 | AJ33: =+IFERROR(VLOOKUP($AJ$19,Sheet1!V2:Y2,3,0),0) -> 0 | AK33: =+IFERROR(VLOOKUP($AK$19,Sheet1!V2:Y2,3,0),0) -> 0 | AL33: =+IFERROR(VLOOKUP($AL$19,Sheet1!V2:Y2,3,0),0) -> 0 | AM33: =+IFERROR(VLOOKUP($AM$19,Sheet1!V2:Y2,3,0),0) -> 0 | AN33: =+IFERROR(VLOOKUP($AN$19,Sheet1!V2:Y2,3,0),0) -> 0 | AO33: =+IFERROR(VLOOKUP($AO$19,Sheet1!V2:Y2,3,0),0) -> 0 | AP33: =+IFERROR(VLOOKUP($AP$19,Sheet1!V2:Y2,3,0),0) -> 0 | AQ33: 22 | AR33: =+IFERROR(VLOOKUP($AR$19,Sheet1!AD2:AG2,3,0),0) -> 0 | AS33: =+IFERROR(VLOOKUP($AS$19,Sheet1!AD2:AG2,3,0),0) -> 0 | AT33: =+IFERROR(VLOOKUP($AT$19,Sheet1!AD2:AG2,3,0),0) -> 0 | AU33: =+IFERROR(VLOOKUP($AU$19,Sheet1!AD2:AG2,3,0),0) -> 0 | AV33: =+IFERROR(VLOOKUP($AV$19,Sheet1!AD2:AG2,3,0),0) -> 0 | AW33: =+IFERROR(VLOOKUP($AW$19,Sheet1!AD2:AG2,3,0),0) -> 0 | AX33: 105 | AY33: =+IFERROR(VLOOKUP($AY$19,Sheet1!AD2:AG2,3,0),0) -> 0 | AZ33: =+IFERROR(VLOOKUP($AZ$19,Sheet1!AD2:AG2,3,0),0) -> 0 | BA33: =+IFERROR(VLOOKUP($BA$19,Sheet1!AH2:AK2,3,0),0) -> 0 | BB33: =+IFERROR(VLOOKUP($BB$19,Sheet1!AH2:AK2,3,0),0) -> 0 | BC33: =+IFERROR(VLOOKUP($BC$19,Sheet1!AH2:AK2,3,0),0) -> 0 | BD33: 424 | BE33: =+IFERROR(VLOOKUP($BE$19,Sheet1!AH2:AK2,3,0),0) -> 0 | BF33: =+IFERROR(VLOOKUP($BF$19,Sheet1!AH2:AK2,3,0),0) -> 0 | BG33: =+IFERROR(VLOOKUP($BG$19,Sheet1!AH2:AK2,3,0),0) -> 0 | BH33: =+IFERROR(VLOOKUP($BH$19,Sheet1!AH2:AK2,3,0),0) -> 0 | BI33: =+IFERROR(VLOOKUP($BI$19,Sheet1!AH2:AK2,3,0),0) -> 0 | BJ33: =+IFERROR(VLOOKUP($BJ$19,Sheet1!AH2:AK2,3,0),0) -> 0 | BK33: =+IFERROR(VLOOKUP($BK$19,Sheet1!AH2:AK2,3,0),0) -> 0 | BL33: =+IFERROR(VLOOKUP($BL$19,Sheet1!AL2:AO2,3,0),0) -> 0 | BM33: =+IFERROR(VLOOKUP($BM$19,Sheet1!AL2:AO2,3,0),0) -> 0 | BN33: =+IFERROR(VLOOKUP($BN$19,Sheet1!AL2:AO2,3,0),0) -> 0 | BO33: 343 | BP33: =+IFERROR(VLOOKUP($BP$19,Sheet1!AL2:AO2,3,0),0) -> 0 | BQ33: =+IFERROR(VLOOKUP($BQ$19,Sheet1!AL2:AO2,3,0),0) -> 0 | BR33: =+IFERROR(VLOOKUP($BR$19,Sheet1!AL2:AO2,3,0),0) -> 0 | BS33: =+IFERROR(VLOOKUP($BS$19,Sheet1!AL2:AO2,3,0),0) -> 0 | BT33: =+IFERROR(VLOOKUP($BT$19,Sheet1!AL2:AO2,3,0),0) -> 0 | BU33: =+IFERROR(VLOOKUP($BU$19,Sheet1!AL2:AO2,3,0),0) -> 0 | BV33: =+IFERROR(VLOOKUP($BV$19,Sheet1!AL2:AO2,3,0),0) -> 0 | BW33: =+IFERROR(VLOOKUP($BW$19,Sheet1!AL2:AO2,3,0),0) -> 0 | BX33: =+IFERROR(VLOOKUP($BX$19,Sheet1!AP2:AS2,3,0),0) -> 0 | BY33: 13 | BZ33: =+IFERROR(VLOOKUP($BZ$19,Sheet1!AX2:BA2,3,0),0) -> 0 | CA33: 29 | CB33: =+IFERROR(VLOOKUP($CB$19,Sheet1!BF2:BI2,3,0),0) -> 0 | CC33: =+IFERROR(VLOOKUP($CC$19,Sheet1!BJ2:BM2,3,0),0) -> 0 | CD33: =+IFERROR(VLOOKUP($CD$19,Sheet1!BN2:BQ2,3,0),0) -> 0 | CE33: 27 | CF33: =+IFERROR(VLOOKUP($CF$19,Sheet1!BV2:BY2,3,0),0) -> 0 | CG33: =Sheet1!E2 -> STEEL | CH33: SP0400152 | CI33: CORRUGATED DISPATCH STEEL DRUM 1500 X 800 X 915 | CJ33: =Sheet1!CX2 -> 500 | CK33: =9750/0.5 -> 19500 | CL33: =SUMPRODUCT($N$20:$CF$20,N33:CF33)+CK33 -> 578741 | CM33: 0.01 | CN33: =CL33*CM33 -> 5787.41 | CO33: 0.18 | CP33: =CL33*CO33 -> 104173.38 | CQ33: =Sheet1!CF2 -> 0 | CR33: =CL33*CQ33 -> 0 | CS33: =CL33+CN33+CP33+CR33 -> 688701.79 | CT33: 0.02 | CU33: =CS33*CT33 -> 13774.036 | CV33: 0.01 | CW33: =CS33*CV33 -> 6887.0179 | CX33: =Sheet1!CM2 -> 0 | CY33: =CX33*CS33 -> 0
A34: =Sheet1!A11 -> ENQ-18390-25-26 | B34: 46357 | C34: =Sheet1!C11 -> FA1300080 | D34: =Sheet1!D11 -> 3 CORE X 400 SQ. MM AL/ARM - WIRE (XLPE) - 33 KV | E34: =CS34+CU34+CW34+CY34 -> 3548343.9 | F34: =ROUNDUP(M62,0) -> 72613 | G34: =E34+F34 -> 3620956.9 | H34: =Sheet1!CR11 -> 0.18 | I34: =G34*H34 -> 651772.24 | J34: =G34+I34 -> 4272729.1 | K34: =Sheet1!CU11 -> 321.5 | L34: =Sheet1!CV11 -> KMS | M34: =J34*K34 -> 1.3736824e+09 | N34: =+IFERROR(VLOOKUP($N$19,Sheet1!J11:L11,3,0),0) -> 3240 | O34: =+IFERROR(VLOOKUP($O$19,Sheet1!J11:L11,3,0),0) -> 0 | P34: =+IFERROR(VLOOKUP($P$19,Sheet1!J11:M11,3,0),0) -> 0 | Q34: =+IFERROR(VLOOKUP($Q$19,Sheet1!J11:M11,3,0),0) -> 0 | R34: =+IFERROR(VLOOKUP($R$19,Sheet1!J11:M11,3,0),0) -> 0 | S34: =+IFERROR(VLOOKUP($S$19,Sheet1!J11:M11,3,0),0) -> 0 | T34: =+IFERROR(VLOOKUP($T$19,Sheet1!J11:M11,3,0),0) -> 0 | U34: =+IFERROR(VLOOKUP($U$19,Sheet1!J11:M11,3,0),0) -> 0 | V34: =+IFERROR(VLOOKUP($V$19,Sheet1!N11:Q11,3,0),0) -> 0 | W34: =+IFERROR(VLOOKUP($W$19,Sheet1!N11:Q11,3,0),0) -> 0 | X34: =+IFERROR(VLOOKUP($X$19,Sheet1!F11:I11,3,0),0) -> 0 | Y34: =+IFERROR(VLOOKUP($Y$19,Sheet1!F11:I11,3,0),0) -> 0 | Z34: =+IFERROR(VLOOKUP($Z$19,Sheet1!F11:I11,3,0),0) -> 0 | AA34: =+IFERROR(VLOOKUP($AA$19,Sheet1!F11:I11,3,0),0) -> 0 | AB34: 229 | AC34: =+IFERROR(VLOOKUP($AC$19,Sheet1!F11:I11,3,0),0) -> 0 | AD34: =+IFERROR(VLOOKUP($AD$19,Sheet1!F11:I11,3,0),0) -> 0 | AE34: =+IFERROR(VLOOKUP($AE$19,Sheet1!F11:I11,3,0),0) -> 0 | AF34: 618 | AG34: =+IFERROR(VLOOKUP($AG$19,Sheet1!R11:U11,3,0),0) -> 0 | AH34: 2674 | AI34: =+IFERROR(VLOOKUP($AI$19,Sheet1!V11:Y11,3,0),0) -> 0 | AJ34: =+IFERROR(VLOOKUP($AJ$19,Sheet1!V11:Y11,3,0),0) -> 0 | AK34: =+IFERROR(VLOOKUP($AK$19,Sheet1!V11:Y11,3,0),0) -> 0 | AL34: =+IFERROR(VLOOKUP($AL$19,Sheet1!V11:Y11,3,0),0) -> 0 | AM34: =+IFERROR(VLOOKUP($AM$19,Sheet1!V11:Y11,3,0),0) -> 0 | AN34: =+IFERROR(VLOOKUP($AN$19,Sheet1!V11:Y11,3,0),0) -> 0 | AO34: =+IFERROR(VLOOKUP($AO$19,Sheet1!V11:Y11,3,0),0) -> 0 | AP34: =+IFERROR(VLOOKUP($AP$19,Sheet1!V11:Y11,3,0),0) -> 0 | AQ34: =+IFERROR(VLOOKUP($AQ$19,Sheet1!Z11:AB11,3,0),0) -> 0 | AR34: =+IFERROR(VLOOKUP($AR$19,Sheet1!AD11:AG11,3,0),0) -> 0 | AS34: =+IFERROR(VLOOKUP($AS$19,Sheet1!AD11:AG11,3,0),0) -> 0 | AT34: =+IFERROR(VLOOKUP($AT$19,Sheet1!AD11:AG11,3,0),0) -> 0 | AU34: =+IFERROR(VLOOKUP($AU$19,Sheet1!AD11:AG11,3,0),0) -> 0 | AV34: =+IFERROR(VLOOKUP($AV$19,Sheet1!AD11:AG11,3,0),0) -> 0 | AW34: =+IFERROR(VLOOKUP($AW$19,Sheet1!AD11:AG11,3,0),0) -> 0 | AX34: 1792 | AY34: =+IFERROR(VLOOKUP($AY$19,Sheet1!AD11:AG11,3,0),0) -> 0 | BA34: =+IFERROR(VLOOKUP($BA$19,Sheet1!AH11:AK11,3,0),0) -> 0 | BB34: =+IFERROR(VLOOKUP($BB$19,Sheet1!AH11:AK11,3,0),0) -> 0 | BC34: =+IFERROR(VLOOKUP($BC$19,Sheet1!AH11:AK11,3,0),0) -> 0 | BD34: =+IFERROR(VLOOKUP($BD$19,Sheet1!AH11:AK11,3,0),0) -> 0 | BE34: =+IFERROR(VLOOKUP($BE$19,Sheet1!AH11:AK11,3,0),0) -> 0 | BF34: =+IFERROR(VLOOKUP($BF$19,Sheet1!AH11:AK11,3,0),0) -> 0 | BG34: =+IFERROR(VLOOKUP($BG$19,Sheet1!AH11:AK11,3,0),0) -> 0 | BH34: =+IFERROR(VLOOKUP($BH$19,Sheet1!AH11:AK11,3,0),0) -> 0 | BI34: =+IFERROR(VLOOKUP($BI$19,Sheet1!AH11:AK11,3,0),0) -> 0 | BJ34: 7284 | BK34: =+IFERROR(VLOOKUP($BK$19,Sheet1!AH11:AK11,3,0),0) -> 0 | BL34: =+IFERROR(VLOOKUP($BL$19,Sheet1!AL11:AO11,3,0),0) -> 0 | BM34: =+IFERROR(VLOOKUP($BM$19,Sheet1!AL11:AO11,3,0),0) -> 0 | BN34: =+IFERROR(VLOOKUP($BN$19,Sheet1!AL11:AO11,3,0),0) -> 0 | BO34: 1760 | BP34: =+IFERROR(VLOOKUP($BP$19,Sheet1!AL11:AO11,3,0),0) -> 0 | BQ34: =+IFERROR(VLOOKUP($BQ$19,Sheet1!AL11:AO11,3,0),0) -> 0 | BR34: =+IFERROR(VLOOKUP($BR$19,Sheet1!AL11:AO11,3,0),0) -> 0 | BS34: =+IFERROR(VLOOKUP($BS$19,Sheet1!AL11:AO11,3,0),0) -> 0 | BT34: =+IFERROR(VLOOKUP($BT$19,Sheet1!AL11:AO11,3,0),0) -> 0 | BU34: =+IFERROR(VLOOKUP($BU$19,Sheet1!AL11:AO11,3,0),0) -> 0 | BV34: =+IFERROR(VLOOKUP($BV$19,Sheet1!AL11:AO11,3,0),0) -> 0 | BW34: =+IFERROR(VLOOKUP($BW$19,Sheet1!AL11:AO11,3,0),0) -> 0 | BX34: 1750 | BY34: 58 | BZ34: =+IFERROR(VLOOKUP($BZ$19,Sheet1!AX11:BA11,3,0),0) -> 120 | CA34: 114 | CB34: =+IFERROR(VLOOKUP($CB$19,Sheet1!BF11:BI11,3,0),0) -> 0 | CC34: =+IFERROR(VLOOKUP($CC$19,Sheet1!BJ11:BM11,3,0),0) -> 0 | CD34: =+IFERROR(VLOOKUP($CD$19,Sheet1!BN11:BQ11,3,0),0) -> 0 | CE34: 76 | CF34: =+IFERROR(VLOOKUP($CF$19,Sheet1!BV11:BY11,3,0),0) -> 0 | CG34: =Sheet1!E11 -> STEEL | CH34: SP0400137 | CI34: CORRUGATED DISPATCH STEEL DRUM 2600 X 1600 X 1600 MM | CJ34: =Sheet1!CX11 -> 250 | CK34: =35750/0.25 -> 143000 | CL34: =SUMPRODUCT($N$20:$CF$20,N34:CF34)+CK34 -> 2894953 | CM34: 0.01 | CN34: =CL34*CM34 -> 28949.53 | CO34: 0.18 | CP34: =CL34*CO34 -> 521091.54 | CQ34: =Sheet1!CF11 -> 0 | CR34: =CL34*CQ34 -> 0 | CS34: =CL34+CN34+CP34+CR34 -> 3444994.1 | CT34: 0.02 | CU34: =CS34*CT34 -> 68899.881 | CV34: 0.01 | CW34: =CS34*CV34 -> 34449.941 | CX34: =Sheet1!CM11 -> 0 | CY34: =CX34*CS34 -> 0
A35: =Sheet1!A12 -> ENQ-18390-25-26 | B35: 46357 | C35: =Sheet1!C12 -> FA1300081 | D35: =Sheet1!D12 -> 3 CORE X 300 SQ. MM. AL/ARM - WIRE (XLPE) - 33 KV | E35: =CS35+CU35+CW35+CY35 -> 3068370.8 | F35: =ROUNDUP(M63,0) -> 72500 | G35: =E35+F35 -> 3140870.8 | H35: =Sheet1!CR12 -> 0.18 | I35: =G35*H35 -> 565356.74 | J35: =G35+I35 -> 3706227.5 | K35: =Sheet1!CU12 -> 45 | L35: =Sheet1!CV12 -> KMS | M35: =J35*K35 -> 1.6678024e+08 | N35: =+IFERROR(VLOOKUP($N$19,Sheet1!J12:L12,3,0),0) -> 2430 | O35: =+IFERROR(VLOOKUP($O$19,Sheet1!J12:L12,3,0),0) -> 0 | P35: =+IFERROR(VLOOKUP($P$19,Sheet1!J12:M12,3,0),0) -> 0 | Q35: =+IFERROR(VLOOKUP($Q$19,Sheet1!J12:M12,3,0),0) -> 0 | R35: =+IFERROR(VLOOKUP($R$19,Sheet1!J12:M12,3,0),0) -> 0 | S35: =+IFERROR(VLOOKUP($S$19,Sheet1!J12:M12,3,0),0) -> 0 | T35: =+IFERROR(VLOOKUP($T$19,Sheet1!J12:M12,3,0),0) -> 0 | U35: =+IFERROR(VLOOKUP($U$19,Sheet1!J12:M12,3,0),0) -> 0 | V35: =+IFERROR(VLOOKUP($V$19,Sheet1!N12:Q12,3,0),0) -> 0 | W35: =+IFERROR(VLOOKUP($W$19,Sheet1!N12:Q12,3,0),0) -> 0 | X35: =+IFERROR(VLOOKUP($X$19,Sheet1!F12:I12,3,0),0) -> 0 | Y35: =+IFERROR(VLOOKUP($Y$19,Sheet1!F12:I12,3,0),0) -> 0 | Z35: =+IFERROR(VLOOKUP($Z$19,Sheet1!F12:I12,3,0),0) -> 0 | AA35: =+IFERROR(VLOOKUP($AA$19,Sheet1!F12:I12,3,0),0) -> 0 | AB35: 214 | AC35: =+IFERROR(VLOOKUP($AC$19,Sheet1!F12:I12,3,0),0) -> 0 | AD35: =+IFERROR(VLOOKUP($AD$19,Sheet1!F12:I12,3,0),0) -> 0 | AE35: =+IFERROR(VLOOKUP($AE$19,Sheet1!F12:I12,3,0),0) -> 0 | AF35: 564 | AG35: =+IFERROR(VLOOKUP($AG$19,Sheet1!R12:U12,3,0),0) -> 0 | AH35: 2438 | AI35: =+IFERROR(VLOOKUP($AI$19,Sheet1!V12:Y12,3,0),0) -> 0 | AJ35: =+IFERROR(VLOOKUP($AJ$19,Sheet1!V12:Y12,3,0),0) -> 0 | AK35: =+IFERROR(VLOOKUP($AK$19,Sheet1!V12:Y12,3,0),0) -> 0 | AL35: =+IFERROR(VLOOKUP($AL$19,Sheet1!V12:Y12,3,0),0) -> 0 | AM35: =+IFERROR(VLOOKUP($AM$19,Sheet1!V12:Y12,3,0),0) -> 0 | AN35: =+IFERROR(VLOOKUP($AN$19,Sheet1!V12:Y12,3,0),0) -> 0 | AO35: =+IFERROR(VLOOKUP($AO$19,Sheet1!V12:Y12,3,0),0) -> 0 | AP35: =+IFERROR(VLOOKUP($AP$19,Sheet1!V12:Y12,3,0),0) -> 0 | AQ35: =+IFERROR(VLOOKUP($AQ$19,Sheet1!Z12:AB12,3,0),0) -> 0 | AR35: =+IFERROR(VLOOKUP($AR$19,Sheet1!AD12:AG12,3,0),0) -> 0 | AS35: =+IFERROR(VLOOKUP($AS$19,Sheet1!AD12:AG12,3,0),0) -> 0 | AT35: =+IFERROR(VLOOKUP($AT$19,Sheet1!AD12:AG12,3,0),0) -> 0 | AU35: =+IFERROR(VLOOKUP($AU$19,Sheet1!AD12:AG12,3,0),0) -> 0 | AV35: =+IFERROR(VLOOKUP($AV$19,Sheet1!AD12:AG12,3,0),0) -> 0 | AW35: =+IFERROR(VLOOKUP($AW$19,Sheet1!AD12:AG12,3,0),0) -> 0 | AX35: 1594 | AY35: =+IFERROR(VLOOKUP($AY$19,Sheet1!AD12:AG12,3,0),0) -> 0 | BA35: =+IFERROR(VLOOKUP($BA$19,Sheet1!AH12:AK12,3,0),0) -> 0 | BB35: =+IFERROR(VLOOKUP($BB$19,Sheet1!AH12:AK12,3,0),0) -> 0 | BC35: =+IFERROR(VLOOKUP($BC$19,Sheet1!AH12:AK12,3,0),0) -> 0 | BD35: =+IFERROR(VLOOKUP($BD$19,Sheet1!AH12:AK12,3,0),0) -> 0 | BE35: =+IFERROR(VLOOKUP($BE$19,Sheet1!AH12:AK12,3,0),0) -> 0 | BF35: =+IFERROR(VLOOKUP($BF$19,Sheet1!AH12:AK12,3,0),0) -> 0 | BG35: =+IFERROR(VLOOKUP($BG$19,Sheet1!AH12:AK12,3,0),0) -> 0 | BH35: =+IFERROR(VLOOKUP($BH$19,Sheet1!AH12:AK12,3,0),0) -> 0 | BI35: =+IFERROR(VLOOKUP($BI$19,Sheet1!AH12:AK12,3,0),0) -> 0 | BJ35: 6874 | BK35: =+IFERROR(VLOOKUP($BK$19,Sheet1!AH12:AK12,3,0),0) -> 0 | BL35: =+IFERROR(VLOOKUP($BL$19,Sheet1!AL12:AO12,3,0),0) -> 0 | BM35: =+IFERROR(VLOOKUP($BM$19,Sheet1!AL12:AO12,3,0),0) -> 0 | BN35: =+IFERROR(VLOOKUP($BN$19,Sheet1!AL12:AO12,3,0),0) -> 0 | BO35: 1655 | BP35: =+IFERROR(VLOOKUP($BP$19,Sheet1!AL12:AO12,3,0),0) -> 0 | BQ35: =+IFERROR(VLOOKUP($BQ$19,Sheet1!AL12:AO12,3,0),0) -> 0 | BR35: =+IFERROR(VLOOKUP($BR$19,Sheet1!AL12:AO12,3,0),0) -> 0 | BS35: =+IFERROR(VLOOKUP($BS$19,Sheet1!AL12:AO12,3,0),0) -> 0 | BT35: =+IFERROR(VLOOKUP($BT$19,Sheet1!AL12:AO12,3,0),0) -> 0 | BU35: =+IFERROR(VLOOKUP($BU$19,Sheet1!AL12:AO12,3,0),0) -> 0 | BV35: =+IFERROR(VLOOKUP($BV$19,Sheet1!AL12:AO12,3,0),0) -> 0 | BW35: =+IFERROR(VLOOKUP($BW$19,Sheet1!AL12:AO12,3,0),0) -> 0 | BX35: 1525 | BY35: 38 | BZ35: =+IFERROR(VLOOKUP($BZ$19,Sheet1!AX12:BA12,3,0),0) -> 0 | CA35: 104 | CB35: =+IFERROR(VLOOKUP($CB$19,Sheet1!BF12:BI12,3,0),0) -> 0 | CC35: =+IFERROR(VLOOKUP($CC$19,Sheet1!BJ12:BM12,3,0),0) -> 0 | CD35: =+IFERROR(VLOOKUP($CD$19,Sheet1!BN12:BQ12,3,0),0) -> 0 | CE35: 72 | CF35: =+IFERROR(VLOOKUP($CF$19,Sheet1!BV12:BY12,3,0),0) -> 0 | CG35: =Sheet1!E12 -> STEEL | CH35: SP0400105 | CI35: CORRUGATED DISPATCH STEEL DRUM 2500 X 1500 X 1400 | CJ35: =Sheet1!CX12 -> 250 | CK35: =33150/0.25 -> 132600 | CL35: =SUMPRODUCT($N$20:$CF$20,N35:CF35)+CK35 -> 2503362 | CM35: 0.01 | CN35: =CL35*CM35 -> 25033.62 | CO35: 0.18 | CP35: =CL35*CO35 -> 450605.16 | CQ35: =Sheet1!CF12 -> 0 | CR35: =CL35*CQ35 -> 0 | CS35: =CL35+CN35+CP35+CR35 -> 2979000.8 | CT35: 0.02 | CU35: =CS35*CT35 -> 59580.016 | CV35: 0.01 | CW35: =CS35*CV35 -> 29790.008 | CX35: =Sheet1!CM12 -> 0 | CY35: =CX35*CS35 -> 0
A36: =Sheet1!A10 -> ENQ-18390-25-26 | B36: 46357 | C36: =Sheet1!C10 -> FA1300079 | D36: =Sheet1!D10 -> 3 CORE X 185 SQ. MM AL/ARM - WIRE (XLPE) - 33 KV | E36: =CS36+CU36+CW36+CY36 -> 2439534 | F36: =ROUNDUP(M64,0) -> 58509 | G36: =E36+F36 -> 2498043 | H36: =Sheet1!CR10 -> 0.18 | I36: =G36*H36 -> 449647.74 | J36: =G36+I36 -> 2947690.7 | K36: =Sheet1!CU10 -> 28.5 | L36: =Sheet1!CV10 -> KMS | M36: =J36*K36 -> 84009186 | N36: =+IFERROR(VLOOKUP($N$19,Sheet1!J10:L10,3,0),0) -> 1499 | O36: =+IFERROR(VLOOKUP($O$19,Sheet1!J10:L10,3,0),0) -> 0 | P36: =+IFERROR(VLOOKUP($P$19,Sheet1!J10:M10,3,0),0) -> 0 | Q36: =+IFERROR(VLOOKUP($Q$19,Sheet1!J10:M10,3,0),0) -> 0 | R36: =+IFERROR(VLOOKUP($R$19,Sheet1!J10:M10,3,0),0) -> 0 | S36: =+IFERROR(VLOOKUP($S$19,Sheet1!J10:M10,3,0),0) -> 0 | T36: =+IFERROR(VLOOKUP($T$19,Sheet1!J10:M10,3,0),0) -> 0 | U36: =+IFERROR(VLOOKUP($U$19,Sheet1!J10:M10,3,0),0) -> 0 | V36: =+IFERROR(VLOOKUP($V$19,Sheet1!N10:Q10,3,0),0) -> 0 | W36: =+IFERROR(VLOOKUP($W$19,Sheet1!N10:Q10,3,0),0) -> 0 | X36: =+IFERROR(VLOOKUP($X$19,Sheet1!F10:I10,3,0),0) -> 0 | Y36: =+IFERROR(VLOOKUP($Y$19,Sheet1!F10:I10,3,0),0) -> 0 | Z36: =+IFERROR(VLOOKUP($Z$19,Sheet1!F10:I10,3,0),0) -> 0 | AA36: =+IFERROR(VLOOKUP($AA$19,Sheet1!F10:I10,3,0),0) -> 0 | AB36: 191 | AC36: =+IFERROR(VLOOKUP($AC$19,Sheet1!F10:I10,3,0),0) -> 0 | AD36: =+IFERROR(VLOOKUP($AD$19,Sheet1!F10:I10,3,0),0) -> 0 | AE36: =+IFERROR(VLOOKUP($AE$19,Sheet1!F10:I10,3,0),0) -> 0 | AF36: 486 | AG36: =+IFERROR(VLOOKUP($AG$19,Sheet1!R10:U10,3,0),0) -> 0 | AH36: 2091 | AI36: =+IFERROR(VLOOKUP($AI$19,Sheet1!V10:Y10,3,0),0) -> 0 | AJ36: =+IFERROR(VLOOKUP($AJ$19,Sheet1!V10:Y10,3,0),0) -> 0 | AK36: =+IFERROR(VLOOKUP($AK$19,Sheet1!V10:Y10,3,0),0) -> 0 | AL36: =+IFERROR(VLOOKUP($AL$19,Sheet1!V10:Y10,3,0),0) -> 0 | AM36: =+IFERROR(VLOOKUP($AM$19,Sheet1!V10:Y10,3,0),0) -> 0 | AN36: =+IFERROR(VLOOKUP($AN$19,Sheet1!V10:Y10,3,0),0) -> 0 | AO36: =+IFERROR(VLOOKUP($AO$19,Sheet1!V10:Y10,3,0),0) -> 0 | AP36: =+IFERROR(VLOOKUP($AP$19,Sheet1!V10:Y10,3,0),0) -> 0 | AQ36: =+IFERROR(VLOOKUP($AQ$19,Sheet1!Z10:AB10,3,0),0) -> 0 | AR36: =+IFERROR(VLOOKUP($AR$19,Sheet1!AD10:AG10,3,0),0) -> 0 | AS36: =+IFERROR(VLOOKUP($AS$19,Sheet1!AD10:AG10,3,0),0) -> 0 | AT36: =+IFERROR(VLOOKUP($AT$19,Sheet1!AD10:AG10,3,0),0) -> 0 | AU36: =+IFERROR(VLOOKUP($AU$19,Sheet1!AD10:AG10,3,0),0) -> 0 | AV36: =+IFERROR(VLOOKUP($AV$19,Sheet1!AD10:AG10,3,0),0) -> 0 | AW36: =+IFERROR(VLOOKUP($AW$19,Sheet1!AD10:AG10,3,0),0) -> 0 | AX36: 1305 | AY36: =+IFERROR(VLOOKUP($AY$19,Sheet1!AD10:AG10,3,0),0) -> 0 | BA36: =+IFERROR(VLOOKUP($BA$19,Sheet1!AH10:AK10,3,0),0) -> 0 | BB36: =+IFERROR(VLOOKUP($BB$19,Sheet1!AH10:AK10,3,0),0) -> 0 | BC36: =+IFERROR(VLOOKUP($BC$19,Sheet1!AH10:AK10,3,0),0) -> 0 | BD36: =+IFERROR(VLOOKUP($BD$19,Sheet1!AH10:AK10,3,0),0) -> 0 | BE36: =+IFERROR(VLOOKUP($BE$19,Sheet1!AH10:AK10,3,0),0) -> 0 | BF36: =+IFERROR(VLOOKUP($BF$19,Sheet1!AH10:AK10,3,0),0) -> 0 | BG36: =+IFERROR(VLOOKUP($BG$19,Sheet1!AH10:AK10,3,0),0) -> 0 | BH36: =+IFERROR(VLOOKUP($BH$19,Sheet1!AH10:AK10,3,0),0) -> 0 | BI36: =+IFERROR(VLOOKUP($BI$19,Sheet1!AH10:AK10,3,0),0) -> 0 | BJ36: 6155 | BK36: =+IFERROR(VLOOKUP($BK$19,Sheet1!AH10:AK10,3,0),0) -> 0 | BL36: =+IFERROR(VLOOKUP($BL$19,Sheet1!AL10:AO10,3,0),0) -> 0 | BM36: =+IFERROR(VLOOKUP($BM$19,Sheet1!AL10:AO10,3,0),0) -> 0 | BN36: =+IFERROR(VLOOKUP($BN$19,Sheet1!AL10:AO10,3,0),0) -> 0 | BO36: 1480 | BP36: =+IFERROR(VLOOKUP($BP$19,Sheet1!AL10:AO10,3,0),0) -> 0 | BQ36: =+IFERROR(VLOOKUP($BQ$19,Sheet1!AL10:AO10,3,0),0) -> 0 | BR36: =+IFERROR(VLOOKUP($BR$19,Sheet1!AL10:AO10,3,0),0) -> 0 | BS36: =+IFERROR(VLOOKUP($BS$19,Sheet1!AL10:AO10,3,0),0) -> 0 | BT36: =+IFERROR(VLOOKUP($BT$19,Sheet1!AL10:AO10,3,0),0) -> 0 | BU36: =+IFERROR(VLOOKUP($BU$19,Sheet1!AL10:AO10,3,0),0) -> 0 | BV36: =+IFERROR(VLOOKUP($BV$19,Sheet1!AL10:AO10,3,0),0) -> 0 | BW36: =+IFERROR(VLOOKUP($BW$19,Sheet1!AL10:AO10,3,0),0) -> 0 | BX36: 1224 | BY36: 35 | BZ36: =+IFERROR(VLOOKUP($BZ$19,Sheet1!AX10:BA10,3,0),0) -> 0 | CA36: 90 | CB36: =+IFERROR(VLOOKUP($CB$19,Sheet1!BF10:BI10,3,0),0) -> 0 | CC36: =+IFERROR(VLOOKUP($CC$19,Sheet1!BJ10:BM10,3,0),0) -> 0 | CD36: =+IFERROR(VLOOKUP($CD$19,Sheet1!BN10:BQ10,3,0),0) -> 0 | CE36: 65 | CF36: =+IFERROR(VLOOKUP($CF$19,Sheet1!BV10:BY10,3,0),0) -> 0 | CG36: =Sheet1!E10 -> STEEL | CH36: SP0400108 | CI36: CORRUGATED DISPATCH STEEL DRUM 2250 X 1200 X 1400 MM | CJ36: =Sheet1!CX10 -> 250 | CK36: =26000/0.25 -> 104000 | CL36: =SUMPRODUCT($N$20:$CF$20,N36:CF36)+CK36 -> 1990319 | CM36: 0.01 | CN36: =CL36*CM36 -> 19903.19 | CO36: 0.18 | CP36: =CL36*CO36 -> 358257.42 | CQ36: =Sheet1!CF10 -> 0 | CR36: =CL36*CQ36 -> 0 | CS36: =CL36+CN36+CP36+CR36 -> 2368479.6 | CT36: 0.02 | CU36: =CS36*CT36 -> 47369.592 | CV36: 0.01 | CW36: =CS36*CV36 -> 23684.796 | CX36: =Sheet1!CM10 -> 0 | CY36: =CX36*CS36 -> 0
A37: =Sheet1!A22 -> ENQ-18390-25-26 | B37: 46357 | C37: =Sheet1!C22 -> FA1300200 | D37: =Sheet1!D22 -> 3 CORE X 95 SQ. MM. AL/ARM WIRE (XLPE) - 33 KV | E37: =CS37+CU37+CW37+CY37 -> 1943727.3 | F37: =ROUNDUP(M65,0) -> 41429 | G37: =E37+F37 -> 1985156.3 | H37: =Sheet1!CR22 -> 0.18 | I37: =G37*H37 -> 357328.14 | J37: =G37+I37 -> 2342484.5 | K37: =Sheet1!CU22 -> 10.5 | L37: =Sheet1!CV22 -> KMS | M37: =J37*K37 -> 24596087 | N37: =+IFERROR(VLOOKUP($N$19,Sheet1!J22:L22,3,0),0) -> 770 | O37: =+IFERROR(VLOOKUP($O$19,Sheet1!J22:L22,3,0),0) -> 0 | P37: =+IFERROR(VLOOKUP($P$19,Sheet1!J22:M22,3,0),0) -> 0 | Q37: =+IFERROR(VLOOKUP($Q$19,Sheet1!J22:M22,3,0),0) -> 0 | R37: =+IFERROR(VLOOKUP($R$19,Sheet1!J22:M22,3,0),0) -> 0 | S37: =+IFERROR(VLOOKUP($S$19,Sheet1!J22:M22,3,0),0) -> 0 | T37: =+IFERROR(VLOOKUP($T$19,Sheet1!J22:M22,3,0),0) -> 0 | U37: =+IFERROR(VLOOKUP($U$19,Sheet1!J22:M22,3,0),0) -> 0 | V37: =+IFERROR(VLOOKUP($V$19,Sheet1!N22:Q22,3,0),0) -> 0 | W37: =+IFERROR(VLOOKUP($W$19,Sheet1!N22:Q22,3,0),0) -> 0 | X37: =+IFERROR(VLOOKUP($X$19,Sheet1!F22:I22,3,0),0) -> 0 | Y37: =+IFERROR(VLOOKUP($Y$19,Sheet1!F22:I22,3,0),0) -> 0 | Z37: =+IFERROR(VLOOKUP($Z$19,Sheet1!F22:I22,3,0),0) -> 0 | AA37: =+IFERROR(VLOOKUP($AA$19,Sheet1!F22:I22,3,0),0) -> 0 | AB37: 167 | AC37: =+IFERROR(VLOOKUP($AC$19,Sheet1!F22:I22,3,0),0) -> 0 | AD37: =+IFERROR(VLOOKUP($AD$19,Sheet1!F22:I22,3,0),0) -> 0 | AE37: =+IFERROR(VLOOKUP($AE$19,Sheet1!F22:I22,3,0),0) -> 0 | AF37: 403 | AG37: =+IFERROR(VLOOKUP($AG$19,Sheet1!R22:U22,3,0),0) -> 0 | AH37: 1724 | AI37: =+IFERROR(VLOOKUP($AI$19,Sheet1!V22:Y22,3,0),0) -> 0 | AJ37: =+IFERROR(VLOOKUP($AJ$19,Sheet1!V22:Y22,3,0),0) -> 0 | AK37: =+IFERROR(VLOOKUP($AK$19,Sheet1!V22:Y22,3,0),0) -> 0 | AL37: =+IFERROR(VLOOKUP($AL$19,Sheet1!V22:Y22,3,0),0) -> 0 | AM37: =+IFERROR(VLOOKUP($AM$19,Sheet1!V22:Y22,3,0),0) -> 0 | AN37: =+IFERROR(VLOOKUP($AN$19,Sheet1!V22:Y22,3,0),0) -> 0 | AO37: =+IFERROR(VLOOKUP($AO$19,Sheet1!V22:Y22,3,0),0) -> 0 | AP37: =+IFERROR(VLOOKUP($AP$19,Sheet1!V22:Y22,3,0),0) -> 0 | AQ37: =+IFERROR(VLOOKUP($AQ$19,Sheet1!Z22:AB22,3,0),0) -> 0 | AR37: =+IFERROR(VLOOKUP($AR$19,Sheet1!AD22:AG22,3,0),0) -> 0 | AS37: =+IFERROR(VLOOKUP($AS$19,Sheet1!AD22:AG22,3,0),0) -> 0 | AT37: =+IFERROR(VLOOKUP($AT$19,Sheet1!AD22:AG22,3,0),0) -> 0 | AU37: =+IFERROR(VLOOKUP($AU$19,Sheet1!AD22:AG22,3,0),0) -> 0 | AV37: =+IFERROR(VLOOKUP($AV$19,Sheet1!AD22:AG22,3,0),0) -> 0 | AW37: =+IFERROR(VLOOKUP($AW$19,Sheet1!AD22:AG22,3,0),0) -> 0 | AX37: 1045 | AY37: =+IFERROR(VLOOKUP($AY$19,Sheet1!AD22:AG22,3,0),0) -> 0 | BA37: =+IFERROR(VLOOKUP($BA$19,Sheet1!AH22:AK22,3,0),0) -> 0 | BB37: =+IFERROR(VLOOKUP($BB$19,Sheet1!AH22:AK22,3,0),0) -> 0 | BC37: =+IFERROR(VLOOKUP($BC$19,Sheet1!AH22:AK22,3,0),0) -> 0 | BD37: =+IFERROR(VLOOKUP($BD$19,Sheet1!AH22:AK22,3,0),0) -> 0 | BE37: =+IFERROR(VLOOKUP($BE$19,Sheet1!AH22:AK22,3,0),0) -> 0 | BF37: =+IFERROR(VLOOKUP($BF$19,Sheet1!AH22:AK22,3,0),0) -> 0 | BG37: =+IFERROR(VLOOKUP($BG$19,Sheet1!AH22:AK22,3,0),0) -> 0 | BH37: =+IFERROR(VLOOKUP($BH$19,Sheet1!AH22:AK22,3,0),0) -> 0 | BI37: =+IFERROR(VLOOKUP($BI$19,Sheet1!AH22:AK22,3,0),0) -> 0 | BJ37: 4262 | BK37: =+IFERROR(VLOOKUP($BK$19,Sheet1!AH22:AK22,3,0),0) -> 0 | BL37: =+IFERROR(VLOOKUP($BL$19,Sheet1!AL22:AO22,3,0),0) -> 0 | BM37: =+IFERROR(VLOOKUP($BM$19,Sheet1!AL22:AO22,3,0),0) -> 0 | BN37: =+IFERROR(VLOOKUP($BN$19,Sheet1!AL22:AO22,3,0),0) -> 0 | BO37: 1296 | BP37: =+IFERROR(VLOOKUP($BP$19,Sheet1!AL22:AO22,3,0),0) -> 0 | BQ37: =+IFERROR(VLOOKUP($BQ$19,Sheet1!AL22:AO22,3,0),0) -> 0 | BR37: =+IFERROR(VLOOKUP($BR$19,Sheet1!AL22:AO22,3,0),0) -> 0 | BS37: =+IFERROR(VLOOKUP($BS$19,Sheet1!AL22:AO22,3,0),0) -> 0 | BT37: =+IFERROR(VLOOKUP($BT$19,Sheet1!AL22:AO22,3,0),0) -> 0 | BU37: =+IFERROR(VLOOKUP($BU$19,Sheet1!AL22:AO22,3,0),0) -> 0 | BV37: =+IFERROR(VLOOKUP($BV$19,Sheet1!AL22:AO22,3,0),0) -> 0 | BW37: =+IFERROR(VLOOKUP($BW$19,Sheet1!AL22:AO22,3,0),0) -> 0 | BX37: 940 | BY37: 15 | BZ37: =+IFERROR(VLOOKUP($BZ$19,Sheet1!AX22:BA22,3,0),0) -> 0 | CA37: 75 | CB37: =+IFERROR(VLOOKUP($CB$19,Sheet1!BF22:BI22,3,0),0) -> 0 | CC37: =+IFERROR(VLOOKUP($CC$19,Sheet1!BJ22:BM22,3,0),0) -> 0 | CD37: =+IFERROR(VLOOKUP($CD$19,Sheet1!BN22:BQ22,3,0),0) -> 0 | CE37: 57 | CF37: =+IFERROR(VLOOKUP($CF$19,Sheet1!BV22:BY22,3,0),0) -> 0 | CG37: =Sheet1!E22 -> STEEL | CH37: SP0400136 | CI37: CORRUGATED DISPATCH STEEL DRUM 2200 X 1300 X 1200 MM | CJ37: =Sheet1!CX22 -> 250 | CK37: =26000/0.25 -> 104000 | CL37: =SUMPRODUCT($N$20:$CF$20,N37:CF37)+CK37 -> 1462879 | CM37: 0.01 | CN37: =CL37*CM37 -> 14628.79 | CO37: 0.28 | CP37: =CL37*CO37 -> 409606.12 | CQ37: =Sheet1!CF22 -> 0 | CR37: =CL37*CQ37 -> 0 | CS37: =CL37+CN37+CP37+CR37 -> 1887113.9 | CT37: 0.02 | CU37: =CS37*CT37 -> 37742.278 | CV37: 0.01 | CW37: =CS37*CV37 -> 18871.139 | CX37: =Sheet1!CM22 -> 0 | CY37: =CX37*CS37 -> 0
A38: =Sheet1!A19 -> ENQ-18390-25-26 | B38: 46357 | C38: =Sheet1!C19 -> FA1300120 | D38: =Sheet1!D19 -> 3 CORE X 70 SQ. MM. AL/ARM - WIRE (XLPE) - 33 KV | E38: =CS38+CU38+CW38+CY38 -> 1780637.4 | F38: =ROUNDUP(M66,0) -> 36250 | G38: =E38+F38 -> 1816887.4 | H38: =Sheet1!CR19 -> 0.18 | I38: =G38*H38 -> 327039.73 | J38: =G38+I38 -> 2143927.1 | K38: =Sheet1!CU19 -> 2 | L38: =Sheet1!CV19 -> KMS | M38: =J38*K38 -> 4287854.2 | N38: =+IFERROR(VLOOKUP($N$19,Sheet1!J19:L19,3,0),0) -> 567 | O38: =+IFERROR(VLOOKUP($O$19,Sheet1!J19:L19,3,0),0) -> 0 | P38: =+IFERROR(VLOOKUP($P$19,Sheet1!J19:M19,3,0),0) -> 0 | Q38: =+IFERROR(VLOOKUP($Q$19,Sheet1!J19:M19,3,0),0) -> 0 | R38: =+IFERROR(VLOOKUP($R$19,Sheet1!J19:M19,3,0),0) -> 0 | S38: =+IFERROR(VLOOKUP($S$19,Sheet1!J19:M19,3,0),0) -> 0 | T38: =+IFERROR(VLOOKUP($T$19,Sheet1!J19:M19,3,0),0) -> 0 | U38: =+IFERROR(VLOOKUP($U$19,Sheet1!J19:M19,3,0),0) -> 0 | V38: =+IFERROR(VLOOKUP($V$19,Sheet1!N19:Q19,3,0),0) -> 0 | W38: =+IFERROR(VLOOKUP($W$19,Sheet1!N19:Q19,3,0),0) -> 0 | X38: =+IFERROR(VLOOKUP($X$19,Sheet1!F19:I19,3,0),0) -> 0 | Y38: =+IFERROR(VLOOKUP($Y$19,Sheet1!F19:I19,3,0),0) -> 0 | Z38: =+IFERROR(VLOOKUP($Z$19,Sheet1!F19:I19,3,0),0) -> 0 | AA38: =+IFERROR(VLOOKUP($AA$19,Sheet1!F19:I19,3,0),0) -> 0 | AB38: 161 | AC38: =+IFERROR(VLOOKUP($AC$19,Sheet1!F19:I19,3,0),0) -> 0 | AD38: =+IFERROR(VLOOKUP($AD$19,Sheet1!F19:I19,3,0),0) -> 0 | AE38: =+IFERROR(VLOOKUP($AE$19,Sheet1!F19:I19,3,0),0) -> 0 | AF38: 378 | AG38: =+IFERROR(VLOOKUP($AG$19,Sheet1!R19:U19,3,0),0) -> 0 | AH38: 1615 | AI38: =+IFERROR(VLOOKUP($AI$19,Sheet1!V19:Y19,3,0),0) -> 0 | AJ38: =+IFERROR(VLOOKUP($AJ$19,Sheet1!V19:Y19,3,0),0) -> 0 | AK38: =+IFERROR(VLOOKUP($AK$19,Sheet1!V19:Y19,3,0),0) -> 0 | AL38: =+IFERROR(VLOOKUP($AL$19,Sheet1!V19:Y19,3,0),0) -> 0 | AM38: =+IFERROR(VLOOKUP($AM$19,Sheet1!V19:Y19,3,0),0) -> 0 | AN38: =+IFERROR(VLOOKUP($AN$19,Sheet1!V19:Y19,3,0),0) -> 0 | AO38: =+IFERROR(VLOOKUP($AO$19,Sheet1!V19:Y19,3,0),0) -> 0 | AP38: =+IFERROR(VLOOKUP($AP$19,Sheet1!V19:Y19,3,0),0) -> 0 | AQ38: =+IFERROR(VLOOKUP($AQ$19,Sheet1!Z19:AB19,3,0),0) -> 0 | AR38: =+IFERROR(VLOOKUP($AR$19,Sheet1!AD19:AG19,3,0),0) -> 0 | AS38: =+IFERROR(VLOOKUP($AS$19,Sheet1!AD19:AG19,3,0),0) -> 0 | AT38: =+IFERROR(VLOOKUP($AT$19,Sheet1!AD19:AG19,3,0),0) -> 0 | AU38: =+IFERROR(VLOOKUP($AU$19,Sheet1!AD19:AG19,3,0),0) -> 0 | AV38: =+IFERROR(VLOOKUP($AV$19,Sheet1!AD19:AG19,3,0),0) -> 0 | AW38: =+IFERROR(VLOOKUP($AW$19,Sheet1!AD19:AG19,3,0),0) -> 0 | AX38: 974 | AY38: =+IFERROR(VLOOKUP($AY$19,Sheet1!AD19:AG19,3,0),0) -> 0 | BA38: =+IFERROR(VLOOKUP($BA$19,Sheet1!AH19:AK19,3,0),0) -> 0 | BB38: =+IFERROR(VLOOKUP($BB$19,Sheet1!AH19:AK19,3,0),0) -> 0 | BC38: =+IFERROR(VLOOKUP($BC$19,Sheet1!AH19:AK19,3,0),0) -> 0 | BD38: =+IFERROR(VLOOKUP($BD$19,Sheet1!AH19:AK19,3,0),0) -> 0 | BE38: =+IFERROR(VLOOKUP($BE$19,Sheet1!AH19:AK19,3,0),0) -> 0 | BF38: =+IFERROR(VLOOKUP($BF$19,Sheet1!AH19:AK19,3,0),0) -> 0 | BG38: =+IFERROR(VLOOKUP($BG$19,Sheet1!AH19:AK19,3,0),0) -> 0 | BH38: =+IFERROR(VLOOKUP($BH$19,Sheet1!AH19:AK19,3,0),0) -> 0 | BI38: =+IFERROR(VLOOKUP($BI$19,Sheet1!AH19:AK19,3,0),0) -> 0 | BJ38: 4072 | BK38: =+IFERROR(VLOOKUP($BK$19,Sheet1!AH19:AK19,3,0),0) -> 0 | BL38: =+IFERROR(VLOOKUP($BL$19,Sheet1!AL19:AO19,3,0),0) -> 0 | BM38: =+IFERROR(VLOOKUP($BM$19,Sheet1!AL19:AO19,3,0),0) -> 0 | BN38: =+IFERROR(VLOOKUP($BN$19,Sheet1!AL19:AO19,3,0),0) -> 0 | BO38: 1190 | BP38: =+IFERROR(VLOOKUP($BP$19,Sheet1!AL19:AO19,3,0),0) -> 0 | BQ38: =+IFERROR(VLOOKUP($BQ$19,Sheet1!AL19:AO19,3,0),0) -> 0 | BR38: =+IFERROR(VLOOKUP($BR$19,Sheet1!AL19:AO19,3,0),0) -> 0 | BS38: =+IFERROR(VLOOKUP($BS$19,Sheet1!AL19:AO19,3,0),0) -> 0 | BT38: =+IFERROR(VLOOKUP($BT$19,Sheet1!AL19:AO19,3,0),0) -> 0 | BU38: =+IFERROR(VLOOKUP($BU$19,Sheet1!AL19:AO19,3,0),0) -> 0 | BV38: =+IFERROR(VLOOKUP($BV$19,Sheet1!AL19:AO19,3,0),0) -> 0 | BW38: =+IFERROR(VLOOKUP($BW$19,Sheet1!AL19:AO19,3,0),0) -> 0 | BX38: 862 | BY38: 15 | BZ38: =+IFERROR(VLOOKUP($BZ$19,Sheet1!AX19:BA19,3,0),0) -> 0 | CA38: 72 | CB38: =+IFERROR(VLOOKUP($CB$19,Sheet1!BF19:BI19,3,0),0) -> 0 | CC38: =+IFERROR(VLOOKUP($CC$19,Sheet1!BJ19:BM19,3,0),0) -> 0 | CD38: =+IFERROR(VLOOKUP($CD$19,Sheet1!BN19:BQ19,3,0),0) -> 0 | CE38: 54 | CF38: =+IFERROR(VLOOKUP($CF$19,Sheet1!BV19:BY19,3,0),0) -> 0 | CG38: =Sheet1!E19 -> STEEL | CH38: SP0400136 | CI38: CORRUGATED DISPATCH STEEL DRUM 2200 X 1300 X 1200 MM | CJ38: =Sheet1!CX19 -> 250 | CK38: =26000/0.25 -> 104000 | CL38: =SUMPRODUCT($N$20:$CF$20,N38:CF38)+CK38 -> 1340135 | CM38: 0.01 | CN38: =CL38*CM38 -> 13401.35 | CO38: 0.28 | CP38: =CL38*CO38 -> 375237.8 | CQ38: =Sheet1!CF19 -> 0 | CR38: =CL38*CQ38 -> 0 | CS38: =CL38+CN38+CP38+CR38 -> 1728774.2 | CT38: 0.02 | CU38: =CS38*CT38 -> 34575.483 | CV38: 0.01 | CW38: =CS38*CV38 -> 17287.742 | CX38: =Sheet1!CM19 -> 0 | CY38: =CX38*CS38 -> 0
A39: =Sheet1!A6 -> ENQ-18390-25-26 | B39: 46357 | C39: =Sheet1!C6 -> FA1300022 | D39: =Sheet1!D6 -> 3 CORE X 50 SQ. MM. AL/ARD - WIRE (XLPE) - 33 KV (E) | E39: =CS39+CU39+CW39+CY39 -> 1785743 | F39: =ROUNDUP(M67,0) -> 58000 | G39: =E39+F39 -> 1843743 | H39: =Sheet1!CR6 -> 0.18 | I39: =G39*H39 -> 331873.73 | J39: =G39+I39 -> 2175616.7 | K39: =Sheet1!CU6 -> 2.5 | L39: =Sheet1!CV6 -> KMS | M39: =J39*K39 -> 5439041.7 | N39: 405 | O39: =+IFERROR(VLOOKUP($O$19,Sheet1!J6:L6,3,0),0) -> 0 | P39: =+IFERROR(VLOOKUP($P$19,Sheet1!J6:M6,3,0),0) -> 0 | Q39: =+IFERROR(VLOOKUP($Q$19,Sheet1!J6:M6,3,0),0) -> 0 | R39: =+IFERROR(VLOOKUP($R$19,Sheet1!J6:M6,3,0),0) -> 0 | S39: =+IFERROR(VLOOKUP($S$19,Sheet1!J6:M6,3,0),0) -> 0 | T39: =+IFERROR(VLOOKUP($T$19,Sheet1!J6:M6,3,0),0) -> 0 | U39: =+IFERROR(VLOOKUP($U$19,Sheet1!J6:M6,3,0),0) -> 0 | V39: =+IFERROR(VLOOKUP($V$19,Sheet1!N6:Q6,3,0),0) -> 0 | W39: =+IFERROR(VLOOKUP($W$19,Sheet1!N6:Q6,3,0),0) -> 0 | X39: =+IFERROR(VLOOKUP($X$19,Sheet1!F6:I6,3,0),0) -> 0 | Y39: =+IFERROR(VLOOKUP($Y$19,Sheet1!F6:I6,3,0),0) -> 0 | Z39: =+IFERROR(VLOOKUP($Z$19,Sheet1!F6:I6,3,0),0) -> 0 | AA39: =+IFERROR(VLOOKUP($AA$19,Sheet1!F6:I6,3,0),0) -> 0 | AB39: 153 | AC39: =+IFERROR(VLOOKUP($AC$19,Sheet1!F6:I6,3,0),0) -> 0 | AD39: =+IFERROR(VLOOKUP($AD$19,Sheet1!F6:I6,3,0),0) -> 0 | AE39: =+IFERROR(VLOOKUP($AE$19,Sheet1!F6:I6,3,0),0) -> 0 | AF39: 350 | AG39: =+IFERROR(VLOOKUP($AG$19,Sheet1!R6:U6,3,0),0) -> 0 | AH39: 1490 | AI39: =+IFERROR(VLOOKUP($AI$19,Sheet1!V6:Y6,3,0),0) -> 0 | AJ39: =+IFERROR(VLOOKUP($AJ$19,Sheet1!V6:Y6,3,0),0) -> 0 | AK39: =+IFERROR(VLOOKUP($AK$19,Sheet1!V6:Y6,3,0),0) -> 0 | AL39: =+IFERROR(VLOOKUP($AL$19,Sheet1!V6:Y6,3,0),0) -> 0 | AM39: =+IFERROR(VLOOKUP($AM$19,Sheet1!V6:Y6,3,0),0) -> 0 | AN39: =+IFERROR(VLOOKUP($AN$19,Sheet1!V6:Y6,3,0),0) -> 0 | AO39: =+IFERROR(VLOOKUP($AO$19,Sheet1!V6:Y6,3,0),0) -> 0 | AP39: =+IFERROR(VLOOKUP($AP$19,Sheet1!V6:Y6,3,0),0) -> 0 | AQ39: =+IFERROR(VLOOKUP($AQ$19,Sheet1!Z6:AB6,3,0),0) -> 0 | AR39: =+IFERROR(VLOOKUP($AR$19,Sheet1!AD6:AG6,3,0),0) -> 0 | AS39: =+IFERROR(VLOOKUP($AS$19,Sheet1!AD6:AG6,3,0),0) -> 0 | AT39: =+IFERROR(VLOOKUP($AT$19,Sheet1!AD6:AG6,3,0),0) -> 0 | AU39: =+IFERROR(VLOOKUP($AU$19,Sheet1!AD6:AG6,3,0),0) -> 0 | AV39: =+IFERROR(VLOOKUP($AV$19,Sheet1!AD6:AG6,3,0),0) -> 0 | AW39: =+IFERROR(VLOOKUP($AW$19,Sheet1!AD6:AG6,3,0),0) -> 0 | AX39: 878 | AY39: =+IFERROR(VLOOKUP($AY$19,Sheet1!AD6:AG6,3,0),0) -> 0 | AZ39: =+IFERROR(VLOOKUP($AZ$19,Sheet1!AD6:AG6,3,0),0) -> 0 | BA39: =+IFERROR(VLOOKUP($BA$19,Sheet1!AH6:AK6,3,0),0) -> 0 | BB39: =+IFERROR(VLOOKUP($BB$19,Sheet1!AH6:AK6,3,0),0) -> 0 | BC39: =+IFERROR(VLOOKUP($BC$19,Sheet1!AH6:AK6,3,0),0) -> 0 | BD39: =+IFERROR(VLOOKUP($BD$19,Sheet1!AH6:AK6,3,0),0) -> 0 | BE39: =+IFERROR(VLOOKUP($BE$19,Sheet1!AH6:AK6,3,0),0) -> 0 | BF39: =+IFERROR(VLOOKUP($BF$19,Sheet1!AH6:AK6,3,0),0) -> 0 | BG39: =+IFERROR(VLOOKUP($BG$19,Sheet1!AH6:AK6,3,0),0) -> 0 | BH39: =+IFERROR(VLOOKUP($BH$19,Sheet1!AH6:AK6,3,0),0) -> 0 | BI39: =+IFERROR(VLOOKUP($BI$19,Sheet1!AH6:AK6,3,0),0) -> 0 | BJ39: 3881 | BK39: =+IFERROR(VLOOKUP($BK$19,Sheet1!AH6:AK6,3,0),0) -> 0 | BL39: =+IFERROR(VLOOKUP($BL$19,Sheet1!AL6:AO6,3,0),0) -> 0 | BM39: =+IFERROR(VLOOKUP($BM$19,Sheet1!AL6:AO6,3,0),0) -> 0 | BN39: =+IFERROR(VLOOKUP($BN$19,Sheet1!AL6:AO6,3,0),0) -> 0 | BO39: 1080 | BP39: =+IFERROR(VLOOKUP($BP$19,Sheet1!AL6:AO6,3,0),0) -> 0 | BQ39: =+IFERROR(VLOOKUP($BQ$19,Sheet1!AL6:AO6,3,0),0) -> 0 | BR39: =+IFERROR(VLOOKUP($BR$19,Sheet1!AL6:AO6,3,0),0) -> 0 | BS39: =+IFERROR(VLOOKUP($BS$19,Sheet1!AL6:AO6,3,0),0) -> 0 | BT39: =+IFERROR(VLOOKUP($BT$19,Sheet1!AL6:AO6,3,0),0) -> 0 | BU39: =+IFERROR(VLOOKUP($BU$19,Sheet1!AL6:AO6,3,0),0) -> 0 | BV39: =+IFERROR(VLOOKUP($BV$19,Sheet1!AL6:AO6,3,0),0) -> 0 | BW39: =+IFERROR(VLOOKUP($BW$19,Sheet1!AL6:AO6,3,0),0) -> 0 | BX39: 778 | BY39: 6 | BZ39: =+IFERROR(VLOOKUP($BZ$19,Sheet1!AX6:BA6,3,0),0) -> 0 | CA39: 66 | CB39: =+IFERROR(VLOOKUP($CB$19,Sheet1!BF6:BI6,3,0),0) -> 0 | CC39: =+IFERROR(VLOOKUP($CC$19,Sheet1!BJ6:BM6,3,0),0) -> 0 | CD39: =+IFERROR(VLOOKUP($CD$19,Sheet1!BN6:BQ6,3,0),0) -> 0 | CE39: 52 | CF39: =+IFERROR(VLOOKUP($CF$19,Sheet1!BV6:BY6,3,0),0) -> 0 | CG39: =Sheet1!E6 -> STEEL | CH39: SP0400112 | CI39: CORRUGATED DISPATCH STEEL DRUM 2000 X 1000 X 1000 MM | CJ39: =Sheet1!CX6 -> 250 | CK39: =18200/0.25 -> 72800 | CL39: =SUMPRODUCT($N$20:$CF$20,N39:CF39)+CK39 -> 1187487 | CM39: 0.01 | CN39: =CL39*CM39 -> 11874.87 | CO39: 0.45 | CP39: =CL39*CO39 -> 534369.15 | CQ39: =Sheet1!CF6 -> 0 | CR39: =CL39*CQ39 -> 0 | CS39: =CL39+CN39+CP39+CR39 -> 1733731 | CT39: 0.02 | CU39: =CS39*CT39 -> 34674.62 | CV39: 0.01 | CW39: =CS39*CV39 -> 17337.31 | CX39: =Sheet1!CM6 -> 0 | CY39: =CX39*CS39 -> 0
A40: =Sheet1!A23 -> ENQ-18390-25-26 | B40: 46357 | C40: =Sheet1!C23 -> FA1300297 | D40: =Sheet1!D23 -> 3 CORE X 35 SQ. MM. AL/ARM - WIRE (XLPE) - 33 KV (E) | E40: =CS40+CU40+CW40+CY40 -> 1785743 | F40: =ROUNDUP(M68,0) -> 58000 | G40: =E40+F40 -> 1843743 | H40: =Sheet1!CR23 -> 0.18 | I40: =G40*H40 -> 331873.73 | J40: =G40+I40 -> 2175616.7 | K40: =Sheet1!CU23 -> 2.5 | L40: =Sheet1!CV23 -> KMS | M40: =J40*K40 -> 5439041.7 | N40: 405 | O40: =+IFERROR(VLOOKUP($O$19,Sheet1!J23:L23,3,0),0) -> 0 | P40: =+IFERROR(VLOOKUP($P$19,Sheet1!J23:M23,3,0),0) -> 0 | Q40: =+IFERROR(VLOOKUP($Q$19,Sheet1!J23:M23,3,0),0) -> 0 | R40: =+IFERROR(VLOOKUP($R$19,Sheet1!J23:M23,3,0),0) -> 0 | S40: =+IFERROR(VLOOKUP($S$19,Sheet1!J23:M23,3,0),0) -> 0 | T40: =+IFERROR(VLOOKUP($T$19,Sheet1!J23:M23,3,0),0) -> 0 | U40: =+IFERROR(VLOOKUP($U$19,Sheet1!J23:M23,3,0),0) -> 0 | V40: =+IFERROR(VLOOKUP($V$19,Sheet1!N23:Q23,3,0),0) -> 0 | W40: =+IFERROR(VLOOKUP($W$19,Sheet1!N23:Q23,3,0),0) -> 0 | X40: =+IFERROR(VLOOKUP($X$19,Sheet1!F23:I23,3,0),0) -> 0 | Y40: =+IFERROR(VLOOKUP($Y$19,Sheet1!F23:I23,3,0),0) -> 0 | Z40: =+IFERROR(VLOOKUP($Z$19,Sheet1!F23:I23,3,0),0) -> 0 | AA40: =+IFERROR(VLOOKUP($AA$19,Sheet1!F23:I23,3,0),0) -> 0 | AB40: 153 | AC40: =+IFERROR(VLOOKUP($AC$19,Sheet1!F23:I23,3,0),0) -> 0 | AD40: =+IFERROR(VLOOKUP($AD$19,Sheet1!F23:I23,3,0),0) -> 0 | AE40: =+IFERROR(VLOOKUP($AE$19,Sheet1!F23:I23,3,0),0) -> 0 | AF40: 350 | AG40: =+IFERROR(VLOOKUP($AG$19,Sheet1!R23:U23,3,0),0) -> 0 | AH40: 1490 | AI40: =+IFERROR(VLOOKUP($AI$19,Sheet1!V23:Y23,3,0),0) -> 0 | AJ40: =+IFERROR(VLOOKUP($AJ$19,Sheet1!V23:Y23,3,0),0) -> 0 | AK40: =+IFERROR(VLOOKUP($AK$19,Sheet1!V23:Y23,3,0),0) -> 0 | AL40: =+IFERROR(VLOOKUP($AL$19,Sheet1!V23:Y23,3,0),0) -> 0 | AM40: =+IFERROR(VLOOKUP($AM$19,Sheet1!V23:Y23,3,0),0) -> 0 | AN40: =+IFERROR(VLOOKUP($AN$19,Sheet1!V23:Y23,3,0),0) -> 0 | AO40: =+IFERROR(VLOOKUP($AO$19,Sheet1!V23:Y23,3,0),0) -> 0 | AP40: =+IFERROR(VLOOKUP($AP$19,Sheet1!V23:Y23,3,0),0) -> 0 | AQ40: =+IFERROR(VLOOKUP($AQ$19,Sheet1!Z23:AB23,3,0),0) -> 0 | AR40: =+IFERROR(VLOOKUP($AR$19,Sheet1!AD23:AG23,3,0),0) -> 0 | AS40: =+IFERROR(VLOOKUP($AS$19,Sheet1!AD23:AG23,3,0),0) -> 0 | AT40: =+IFERROR(VLOOKUP($AT$19,Sheet1!AD23:AG23,3,0),0) -> 0 | AU40: =+IFERROR(VLOOKUP($AU$19,Sheet1!AD23:AG23,3,0),0) -> 0 | AV40: =+IFERROR(VLOOKUP($AV$19,Sheet1!AD23:AG23,3,0),0) -> 0 | AW40: =+IFERROR(VLOOKUP($AW$19,Sheet1!AD23:AG23,3,0),0) -> 0 | AX40: 878 | AY40: =+IFERROR(VLOOKUP($AY$19,Sheet1!AD23:AG23,3,0),0) -> 0 | AZ40: =+IFERROR(VLOOKUP($AZ$19,Sheet1!AD23:AG23,3,0),0) -> 0 | BA40: =+IFERROR(VLOOKUP($BA$19,Sheet1!AH23:AK23,3,0),0) -> 0 | BB40: =+IFERROR(VLOOKUP($BB$19,Sheet1!AH23:AK23,3,0),0) -> 0 | BC40: =+IFERROR(VLOOKUP($BC$19,Sheet1!AH23:AK23,3,0),0) -> 0 | BD40: =+IFERROR(VLOOKUP($BD$19,Sheet1!AH23:AK23,3,0),0) -> 0 | BE40: =+IFERROR(VLOOKUP($BE$19,Sheet1!AH23:AK23,3,0),0) -> 0 | BF40: =+IFERROR(VLOOKUP($BF$19,Sheet1!AH23:AK23,3,0),0) -> 0 | BG40: =+IFERROR(VLOOKUP($BG$19,Sheet1!AH23:AK23,3,0),0) -> 0 | BH40: =+IFERROR(VLOOKUP($BH$19,Sheet1!AH23:AK23,3,0),0) -> 0 | BI40: =+IFERROR(VLOOKUP($BI$19,Sheet1!AH23:AK23,3,0),0) -> 0 | BJ40: 3881 | BK40: =+IFERROR(VLOOKUP($BK$19,Sheet1!AH23:AK23,3,0),0) -> 0 | BL40: =+IFERROR(VLOOKUP($BL$19,Sheet1!AL23:AO23,3,0),0) -> 0 | BM40: =+IFERROR(VLOOKUP($BM$19,Sheet1!AL23:AO23,3,0),0) -> 0 | BN40: =+IFERROR(VLOOKUP($BN$19,Sheet1!AL23:AO23,3,0),0) -> 0 | BO40: 1080 | BP40: =+IFERROR(VLOOKUP($BP$19,Sheet1!AL23:AO23,3,0),0) -> 0 | BQ40: =+IFERROR(VLOOKUP($BQ$19,Sheet1!AL23:AO23,3,0),0) -> 0 | BR40: =+IFERROR(VLOOKUP($BR$19,Sheet1!AL23:AO23,3,0),0) -> 0 | BS40: =+IFERROR(VLOOKUP($BS$19,Sheet1!AL23:AO23,3,0),0) -> 0 | BT40: =+IFERROR(VLOOKUP($BT$19,Sheet1!AL23:AO23,3,0),0) -> 0 | BU40: =+IFERROR(VLOOKUP($BU$19,Sheet1!AL23:AO23,3,0),0) -> 0 | BV40: =+IFERROR(VLOOKUP($BV$19,Sheet1!AL23:AO23,3,0),0) -> 0 | BW40: =+IFERROR(VLOOKUP($BW$19,Sheet1!AL23:AO23,3,0),0) -> 0 | BX40: 778 | BY40: 6 | BZ40: =+IFERROR(VLOOKUP($BZ$19,Sheet1!AX23:BA23,3,0),0) -> 0 | CA40: 66 | CB40: =+IFERROR(VLOOKUP($CB$19,Sheet1!BF23:BI23,3,0),0) -> 0 | CC40: =+IFERROR(VLOOKUP($CC$19,Sheet1!BJ23:BM23,3,0),0) -> 0 | CD40: =+IFERROR(VLOOKUP($CD$19,Sheet1!BN23:BQ23,3,0),0) -> 0 | CE40: 52 | CF40: =+IFERROR(VLOOKUP($CF$19,Sheet1!BV23:BY23,3,0),0) -> 0 | CG40: =Sheet1!E23 -> STEEL | CH40: SP0400112 | CI40: CORRUGATED DISPATCH STEEL DRUM 2000 X 1000 X 1000 MM | CJ40: =Sheet1!CX23 -> 250 | CK40: =18200/0.25 -> 72800 | CL40: =SUMPRODUCT($N$20:$CF$20,N40:CF40)+CK40 -> 1187487 | CM40: 0.01 | CN40: =CL40*CM40 -> 11874.87 | CO40: 0.45 | CP40: =CL40*CO40 -> 534369.15 | CQ40: =Sheet1!CF23 -> 0 | CR40: =CL40*CQ40 -> 0 | CS40: =CL40+CN40+CP40+CR40 -> 1733731 | CT40: 0.02 | CU40: =CS40*CT40 -> 34674.62 | CV40: 0.01 | CW40: =CS40*CV40 -> 17337.31 | CX40: =Sheet1!CM23 -> 0 | CY40: =CX40*CS40 -> 0
A41: =Sheet1!A7 -> ENQ-18390-25-26 | B41: 46357 | C41: =Sheet1!C7 -> FA1300027 | D41: =Sheet1!D7 -> 1 CORE X 630 SQ. MM. AL/ARM (XLPE) - 33 KV | E41: =CS41+CU41+CW41+CY41 -> 1477550.7 | F41: =ROUNDUP(M69,0) -> 18643 | G41: =E41+F41 -> 1496193.7 | H41: =Sheet1!CR7 -> 0.18 | I41: =G41*H41 -> 269314.87 | J41: =G41+I41 -> 1765508.6 | K41: =Sheet1!CU7 -> 105 | L41: =Sheet1!CV7 -> KMS | M41: =J41*K41 -> 1.853784e+08 | N41: =+IFERROR(VLOOKUP($N$19,Sheet1!J7:L7,3,0),0) -> 1701 | O41: =+IFERROR(VLOOKUP($O$19,Sheet1!J7:L7,3,0),0) -> 0 | P41: =+IFERROR(VLOOKUP($P$19,Sheet1!J7:M7,3,0),0) -> 0 | Q41: =+IFERROR(VLOOKUP($Q$19,Sheet1!J7:M7,3,0),0) -> 0 | R41: =+IFERROR(VLOOKUP($R$19,Sheet1!J7:M7,3,0),0) -> 0 | S41: =+IFERROR(VLOOKUP($S$19,Sheet1!J7:M7,3,0),0) -> 0 | T41: =+IFERROR(VLOOKUP($T$19,Sheet1!J7:M7,3,0),0) -> 0 | U41: =+IFERROR(VLOOKUP($U$19,Sheet1!J7:M7,3,0),0) -> 0 | V41: =+IFERROR(VLOOKUP($V$19,Sheet1!N7:Q7,3,0),0) -> 0 | W41: =+IFERROR(VLOOKUP($W$19,Sheet1!N7:Q7,3,0),0) -> 0 | X41: =+IFERROR(VLOOKUP($X$19,Sheet1!F7:I7,3,0),0) -> 0 | Y41: =+IFERROR(VLOOKUP($Y$19,Sheet1!F7:I7,3,0),0) -> 0 | Z41: =+IFERROR(VLOOKUP($Z$19,Sheet1!F7:I7,3,0),0) -> 0 | AA41: =+IFERROR(VLOOKUP($AA$19,Sheet1!F7:I7,3,0),0) -> 0 | AB41: 87 | AC41: =+IFERROR(VLOOKUP($AC$19,Sheet1!F7:I7,3,0),0) -> 0 | AD41: =+IFERROR(VLOOKUP($AD$19,Sheet1!F7:I7,3,0),0) -> 0 | AE41: =+IFERROR(VLOOKUP($AE$19,Sheet1!F7:I7,3,0),0) -> 0 | AF41: 243 | AG41: =+IFERROR(VLOOKUP($AG$19,Sheet1!R7:U7,3,0),0) -> 0 | AH41: 1056 | AI41: =+IFERROR(VLOOKUP($AI$19,Sheet1!V7:Y7,3,0),0) -> 0 | AJ41: =+IFERROR(VLOOKUP($AJ$19,Sheet1!V7:Y7,3,0),0) -> 0 | AK41: =+IFERROR(VLOOKUP($AK$19,Sheet1!V7:Y7,3,0),0) -> 0 | AL41: =+IFERROR(VLOOKUP($AL$19,Sheet1!V7:Y7,3,0),0) -> 0 | AM41: =+IFERROR(VLOOKUP($AM$19,Sheet1!V7:Y7,3,0),0) -> 0 | AN41: =+IFERROR(VLOOKUP($AN$19,Sheet1!V7:Y7,3,0),0) -> 0 | AO41: =+IFERROR(VLOOKUP($AO$19,Sheet1!V7:Y7,3,0),0) -> 0 | AP41: =+IFERROR(VLOOKUP($AP$19,Sheet1!V7:Y7,3,0),0) -> 0 | AQ41: 36 | AR41: =+IFERROR(VLOOKUP($AR$19,Sheet1!AD7:AG7,3,0),0) -> 0 | AS41: =+IFERROR(VLOOKUP($AS$19,Sheet1!AD7:AG7,3,0),0) -> 0 | AT41: =+IFERROR(VLOOKUP($AT$19,Sheet1!AD7:AG7,3,0),0) -> 0 | AU41: =+IFERROR(VLOOKUP($AU$19,Sheet1!AD7:AG7,3,0),0) -> 0 | AV41: =+IFERROR(VLOOKUP($AV$19,Sheet1!AD7:AG7,3,0),0) -> 0 | AW41: =+IFERROR(VLOOKUP($AW$19,Sheet1!AD7:AG7,3,0),0) -> 0 | AX41: 224 | AY41: =+IFERROR(VLOOKUP($AY$19,Sheet1!AD7:AG7,3,0),0) -> 0 | AZ41: =+IFERROR(VLOOKUP($AZ$19,Sheet1!AD7:AG7,3,0),0) -> 0 | BA41: =+IFERROR(VLOOKUP($BA$19,Sheet1!AH7:AK7,3,0),0) -> 0 | BB41: =+IFERROR(VLOOKUP($BB$19,Sheet1!AH7:AK7,3,0),0) -> 0 | BC41: =+IFERROR(VLOOKUP($BC$19,Sheet1!AH7:AK7,3,0),0) -> 0 | BD41: 842 | BE41: =+IFERROR(VLOOKUP($BE$19,Sheet1!AH7:AK7,3,0),0) -> 0 | BF41: =+IFERROR(VLOOKUP($BF$19,Sheet1!AH7:AK7,3,0),0) -> 0 | BG41: =+IFERROR(VLOOKUP($BG$19,Sheet1!AH7:AK7,3,0),0) -> 0 | BH41: =+IFERROR(VLOOKUP($BH$19,Sheet1!AH7:AK7,3,0),0) -> 0 | BI41: =+IFERROR(VLOOKUP($BI$19,Sheet1!AH7:AK7,3,0),0) -> 0 | BJ41: =+IFERROR(VLOOKUP($BJ$19,Sheet1!AH7:AK7,3,0),0) -> 0 | BK41: =+IFERROR(VLOOKUP($BK$19,Sheet1!AH7:AK7,3,0),0) -> 0 | BL41: =+IFERROR(VLOOKUP($BL$19,Sheet1!AL7:AO7,3,0),0) -> 0 | BM41: =+IFERROR(VLOOKUP($BM$19,Sheet1!AL7:AO7,3,0),0) -> 0 | BN41: =+IFERROR(VLOOKUP($BN$19,Sheet1!AL7:AO7,3,0),0) -> 0 | BO41: 769 | BP41: =+IFERROR(VLOOKUP($BP$19,Sheet1!AL7:AO7,3,0),0) -> 0 | BQ41: =+IFERROR(VLOOKUP($BQ$19,Sheet1!AL7:AO7,3,0),0) -> 0 | BR41: =+IFERROR(VLOOKUP($BR$19,Sheet1!AL7:AO7,3,0),0) -> 0 | BS41: =+IFERROR(VLOOKUP($BS$19,Sheet1!AL7:AO7,3,0),0) -> 0 | BT41: =+IFERROR(VLOOKUP($BT$19,Sheet1!AL7:AO7,3,0),0) -> 0 | BU41: =+IFERROR(VLOOKUP($BU$19,Sheet1!AL7:AO7,3,0),0) -> 0 | BV41: =+IFERROR(VLOOKUP($BV$19,Sheet1!AL7:AO7,3,0),0) -> 0 | BW41: =+IFERROR(VLOOKUP($BW$19,Sheet1!AL7:AO7,3,0),0) -> 0 | BX41: =+IFERROR(VLOOKUP($BX$19,Sheet1!AP7:AS7,3,0),0) -> 0 | BY41: 26 | BZ41: =+IFERROR(VLOOKUP($BZ$19,Sheet1!AX7:BA7,3,0),0) -> 0 | CA41: 46 | CB41: =+IFERROR(VLOOKUP($CB$19,Sheet1!BF7:BI7,3,0),0) -> 0 | CC41: =+IFERROR(VLOOKUP($CC$19,Sheet1!BJ7:BM7,3,0),0) -> 0 | CD41: =+IFERROR(VLOOKUP($CD$19,Sheet1!BN7:BQ7,3,0),0) -> 0 | CE41: 42 | CF41: =+IFERROR(VLOOKUP($CF$19,Sheet1!BV7:BY7,3,0),0) -> 0 | CG41: =Sheet1!E7 -> STEEL | CH41: SP0400123 | CI41: CORRUGATED DISPATCH STEEL DRUM 2000 X 1000 X 1200 MM | CJ41: =Sheet1!CX7 -> 500 | CK41: =19500/0.5 -> 39000 | CL41: =SUMPRODUCT($N$20:$CF$20,N41:CF41)+CK41 -> 1205475 | CM41: 0.01 | CN41: =CL41*CM41 -> 12054.75 | CO41: 0.18 | CP41: =CL41*CO41 -> 216985.5 | CQ41: =Sheet1!CF7 -> 0 | CR41: =CL41*CQ41 -> 0 | CS41: =CL41+CN41+CP41+CR41 -> 1434515.2 | CT41: 0.02 | CU41: =CS41*CT41 -> 28690.305 | CV41: 0.01 | CW41: =CS41*CV41 -> 14345.153 | CX41: =Sheet1!CM7 -> 0 | CY41: =CX41*CS41 -> 0
A42: =Sheet1!A4 -> ENQ-18390-25-26 | B42: 46357 | C42: =Sheet1!C4 -> FA1300018 | D42: =Sheet1!D4 -> 1 CORE X 400 SQ. MM. AL/ARM (XLPE) - 33 KV | E42: =CS42+CU42+CW42+CY42 -> 1125356.8 | F42: =ROUNDUP(M70,0) -> 18125 | G42: =E42+F42 -> 1143481.8 | H42: =Sheet1!CR4 -> 0.18 | I42: =G42*H42 -> 205826.73 | J42: =G42+I42 -> 1349308.6 | K42: =Sheet1!CU4 -> 16 | L42: =Sheet1!CV4 -> KMS | M42: =J42*K42 -> 21588937 | N42: =+IFERROR(VLOOKUP($N$19,Sheet1!J4:L4,3,0),0) -> 1080 | O42: =+IFERROR(VLOOKUP($O$19,Sheet1!J4:L4,3,0),0) -> 0 | P42: =+IFERROR(VLOOKUP($P$19,Sheet1!J4:M4,3,0),0) -> 0 | Q42: =+IFERROR(VLOOKUP($Q$19,Sheet1!J4:M4,3,0),0) -> 0 | R42: =+IFERROR(VLOOKUP($R$19,Sheet1!J4:M4,3,0),0) -> 0 | S42: =+IFERROR(VLOOKUP($S$19,Sheet1!J4:M4,3,0),0) -> 0 | T42: =+IFERROR(VLOOKUP($T$19,Sheet1!J4:M4,3,0),0) -> 0 | U42: =+IFERROR(VLOOKUP($U$19,Sheet1!J4:M4,3,0),0) -> 0 | V42: =+IFERROR(VLOOKUP($V$19,Sheet1!N4:Q4,3,0),0) -> 0 | W42: =+IFERROR(VLOOKUP($W$19,Sheet1!N4:Q4,3,0),0) -> 0 | X42: =+IFERROR(VLOOKUP($X$19,Sheet1!F4:I4,3,0),0) -> 0 | Y42: =+IFERROR(VLOOKUP($Y$19,Sheet1!F4:I4,3,0),0) -> 0 | Z42: =+IFERROR(VLOOKUP($Z$19,Sheet1!F4:I4,3,0),0) -> 0 | AA42: =+IFERROR(VLOOKUP($AA$19,Sheet1!F4:I4,3,0),0) -> 0 | AB42: 76 | AC42: =+IFERROR(VLOOKUP($AC$19,Sheet1!F4:I4,3,0),0) -> 0 | AD42: =+IFERROR(VLOOKUP($AD$19,Sheet1!F4:I4,3,0),0) -> 0 | AE42: =+IFERROR(VLOOKUP($AE$19,Sheet1!F4:I4,3,0),0) -> 0 | AF42: 206 | AG42: =+IFERROR(VLOOKUP($AG$19,Sheet1!R4:U4,3,0),0) -> 0 | AH42: 890 | AI42: =+IFERROR(VLOOKUP($AI$19,Sheet1!V4:Y4,3,0),0) -> 0 | AJ42: =+IFERROR(VLOOKUP($AJ$19,Sheet1!V4:Y4,3,0),0) -> 0 | AK42: =+IFERROR(VLOOKUP($AK$19,Sheet1!V4:Y4,3,0),0) -> 0 | AL42: =+IFERROR(VLOOKUP($AL$19,Sheet1!V4:Y4,3,0),0) -> 0 | AM42: =+IFERROR(VLOOKUP($AM$19,Sheet1!V4:Y4,3,0),0) -> 0 | AN42: =+IFERROR(VLOOKUP($AN$19,Sheet1!V4:Y4,3,0),0) -> 0 | AO42: =+IFERROR(VLOOKUP($AO$19,Sheet1!V4:Y4,3,0),0) -> 0 | AP42: =+IFERROR(VLOOKUP($AP$19,Sheet1!V4:Y4,3,0),0) -> 0 | AQ42: 32 | AR42: =+IFERROR(VLOOKUP($AR$19,Sheet1!AD4:AG4,3,0),0) -> 0 | AS42: =+IFERROR(VLOOKUP($AS$19,Sheet1!AD4:AG4,3,0),0) -> 0 | AT42: =+IFERROR(VLOOKUP($AT$19,Sheet1!AD4:AG4,3,0),0) -> 0 | AU42: =+IFERROR(VLOOKUP($AU$19,Sheet1!AD4:AG4,3,0),0) -> 0 | AV42: =+IFERROR(VLOOKUP($AV$19,Sheet1!AD4:AG4,3,0),0) -> 0 | AW42: =+IFERROR(VLOOKUP($AW$19,Sheet1!AD4:AG4,3,0),0) -> 0 | AX42: 172 | AY42: =+IFERROR(VLOOKUP($AY$19,Sheet1!AD4:AG4,3,0),0) -> 0 | AZ42: =+IFERROR(VLOOKUP($AZ$19,Sheet1!AD4:AG4,3,0),0) -> 0 | BA42: =+IFERROR(VLOOKUP($BA$19,Sheet1!AH4:AK4,3,0),0) -> 0 | BB42: =+IFERROR(VLOOKUP($BB$19,Sheet1!AH4:AK4,3,0),0) -> 0 | BC42: =+IFERROR(VLOOKUP($BC$19,Sheet1!AH4:AK4,3,0),0) -> 0 | BD42: 731 | BE42: =+IFERROR(VLOOKUP($BE$19,Sheet1!AH4:AK4,3,0),0) -> 0 | BF42: =+IFERROR(VLOOKUP($BF$19,Sheet1!AH4:AK4,3,0),0) -> 0 | BG42: =+IFERROR(VLOOKUP($BG$19,Sheet1!AH4:AK4,3,0),0) -> 0 | BH42: =+IFERROR(VLOOKUP($BH$19,Sheet1!AH4:AK4,3,0),0) -> 0 | BI42: =+IFERROR(VLOOKUP($BI$19,Sheet1!AH4:AK4,3,0),0) -> 0 | BJ42: =+IFERROR(VLOOKUP($BJ$19,Sheet1!AH4:AK4,3,0),0) -> 0 | BK42: =+IFERROR(VLOOKUP($BK$19,Sheet1!AH4:AK4,3,0),0) -> 0 | BL42: =+IFERROR(VLOOKUP($BL$19,Sheet1!AL4:AO4,3,0),0) -> 0 | BM42: =+IFERROR(VLOOKUP($BM$19,Sheet1!AL4:AO4,3,0),0) -> 0 | BN42: =+IFERROR(VLOOKUP($BN$19,Sheet1!AL4:AO4,3,0),0) -> 0 | BO42: 604 | BP42: =+IFERROR(VLOOKUP($BP$19,Sheet1!AL4:AO4,3,0),0) -> 0 | BQ42: =+IFERROR(VLOOKUP($BQ$19,Sheet1!AL4:AO4,3,0),0) -> 0 | BR42: =+IFERROR(VLOOKUP($BR$19,Sheet1!AL4:AO4,3,0),0) -> 0 | BS42: =+IFERROR(VLOOKUP($BS$19,Sheet1!AL4:AO4,3,0),0) -> 0 | BT42: =+IFERROR(VLOOKUP($BT$19,Sheet1!AL4:AO4,3,0),0) -> 0 | BU42: =+IFERROR(VLOOKUP($BU$19,Sheet1!AL4:AO4,3,0),0) -> 0 | BV42: =+IFERROR(VLOOKUP($BV$19,Sheet1!AL4:AO4,3,0),0) -> 0 | BW42: =+IFERROR(VLOOKUP($BW$19,Sheet1!AL4:AO4,3,0),0) -> 0 | BX42: =+IFERROR(VLOOKUP($BX$19,Sheet1!AP4:AS4,3,0),0) -> 0 | BY42: 19 | BZ42: =+IFERROR(VLOOKUP($BZ$19,Sheet1!AX4:BA4,3,0),0) -> 54 | CA42: 38 | CB42: =+IFERROR(VLOOKUP($CB$19,Sheet1!BF4:BI4,3,0),0) -> 0 | CC42: =+IFERROR(VLOOKUP($CC$19,Sheet1!BJ4:BM4,3,0),0) -> 0 | CD42: =+IFERROR(VLOOKUP($CD$19,Sheet1!BN4:BQ4,3,0),0) -> 0 | CE42: 37 | CF42: =+IFERROR(VLOOKUP($CF$19,Sheet1!BV4:BY4,3,0),0) -> 0 | CG42: =Sheet1!E4 -> STEEL | CH42: SP0400112 | CI42: CORRUGATED DISPATCH STEEL DRUM 2000 X 1000 X 1000 MM | CJ42: =Sheet1!CX4 -> 500 | CK42: =18200/0.5 -> 36400 | CL42: =SUMPRODUCT($N$20:$CF$20,N42:CF42)+CK42 -> 918134 | CM42: 0.01 | CN42: =CL42*CM42 -> 9181.34 | CO42: 0.18 | CP42: =CL42*CO42 -> 165264.12 | CQ42: =Sheet1!CF4 -> 0 | CR42: =CL42*CQ42 -> 0 | CS42: =CL42+CN42+CP42+CR42 -> 1092579.5 | CT42: 0.02 | CU42: =CS42*CT42 -> 21851.589 | CV42: 0.01 | CW42: =CS42*CV42 -> 10925.795 | CX42: =Sheet1!CM4 -> 0 | CY42: =CX42*CS42 -> 0
A43: =Sheet1!A5 -> ENQ-18390-25-26 | B43: 46357 | C43: =Sheet1!C5 -> FA1300019 | D43: =Sheet1!D5 -> 1 CORE X 300 SQ. MM. AL/ARM (XLPE) - 33 KV | E43: =CS43+CU43+CW43+CY43 -> 975214.72 | F43: =ROUNDUP(M71,0) -> 24167 | G43: =E43+F43 -> 999381.72 | H43: =Sheet1!CR5 -> 0.18 | I43: =G43*H43 -> 179888.71 | J43: =G43+I43 -> 1179270.4 | K43: =Sheet1!CU5 -> 3 | L43: =Sheet1!CV5 -> KMS | M43: =J43*K43 -> 3537811.3 | N43: =+IFERROR(VLOOKUP($N$19,Sheet1!J5:L5,3,0),0) -> 810 | O43: =+IFERROR(VLOOKUP($O$19,Sheet1!J5:L5,3,0),0) -> 0 | P43: =+IFERROR(VLOOKUP($P$19,Sheet1!J5:M5,3,0),0) -> 0 | Q43: =+IFERROR(VLOOKUP($Q$19,Sheet1!J5:M5,3,0),0) -> 0 | R43: =+IFERROR(VLOOKUP($R$19,Sheet1!J5:M5,3,0),0) -> 0 | S43: =+IFERROR(VLOOKUP($S$19,Sheet1!J5:M5,3,0),0) -> 0 | T43: =+IFERROR(VLOOKUP($T$19,Sheet1!J5:M5,3,0),0) -> 0 | U43: =+IFERROR(VLOOKUP($U$19,Sheet1!J5:M5,3,0),0) -> 0 | V43: =+IFERROR(VLOOKUP($V$19,Sheet1!N5:Q5,3,0),0) -> 0 | W43: =+IFERROR(VLOOKUP($W$19,Sheet1!N5:Q5,3,0),0) -> 0 | X43: =+IFERROR(VLOOKUP($X$19,Sheet1!F5:I5,3,0),0) -> 0 | Y43: =+IFERROR(VLOOKUP($Y$19,Sheet1!F5:I5,3,0),0) -> 0 | Z43: =+IFERROR(VLOOKUP($Z$19,Sheet1!F5:I5,3,0),0) -> 0 | AA43: =+IFERROR(VLOOKUP($AA$19,Sheet1!F5:I5,3,0),0) -> 0 | AB43: 71 | AC43: =+IFERROR(VLOOKUP($AC$19,Sheet1!F5:I5,3,0),0) -> 0 | AD43: =+IFERROR(VLOOKUP($AD$19,Sheet1!F5:I5,3,0),0) -> 0 | AE43: =+IFERROR(VLOOKUP($AE$19,Sheet1!F5:I5,3,0),0) -> 0 | AF43: 187 | AG43: =+IFERROR(VLOOKUP($AG$19,Sheet1!R5:U5,3,0),0) -> 0 | AH43: 810 | AI43: =+IFERROR(VLOOKUP($AI$19,Sheet1!V5:Y5,3,0),0) -> 0 | AJ43: =+IFERROR(VLOOKUP($AJ$19,Sheet1!V5:Y5,3,0),0) -> 0 | AK43: =+IFERROR(VLOOKUP($AK$19,Sheet1!V5:Y5,3,0),0) -> 0 | AL43: =+IFERROR(VLOOKUP($AL$19,Sheet1!V5:Y5,3,0),0) -> 0 | AM43: =+IFERROR(VLOOKUP($AM$19,Sheet1!V5:Y5,3,0),0) -> 0 | AN43: =+IFERROR(VLOOKUP($AN$19,Sheet1!V5:Y5,3,0),0) -> 0 | AO43: =+IFERROR(VLOOKUP($AO$19,Sheet1!V5:Y5,3,0),0) -> 0 | AP43: =+IFERROR(VLOOKUP($AP$19,Sheet1!V5:Y5,3,0),0) -> 0 | AQ43: 30 | AR43: =+IFERROR(VLOOKUP($AR$19,Sheet1!AD5:AG5,3,0),0) -> 0 | AS43: =+IFERROR(VLOOKUP($AS$19,Sheet1!AD5:AG5,3,0),0) -> 0 | AT43: =+IFERROR(VLOOKUP($AT$19,Sheet1!AD5:AG5,3,0),0) -> 0 | AU43: =+IFERROR(VLOOKUP($AU$19,Sheet1!AD5:AG5,3,0),0) -> 0 | AV43: =+IFERROR(VLOOKUP($AV$19,Sheet1!AD5:AG5,3,0),0) -> 0 | AW43: =+IFERROR(VLOOKUP($AW$19,Sheet1!AD5:AG5,3,0),0) -> 0 | AX43: 161 | AY43: =+IFERROR(VLOOKUP($AY$19,Sheet1!AD5:AG5,3,0),0) -> 0 | AZ43: =+IFERROR(VLOOKUP($AZ$19,Sheet1!AD5:AG5,3,0),0) -> 0 | BA43: =+IFERROR(VLOOKUP($BA$19,Sheet1!AH5:AK5,3,0),0) -> 0 | BB43: =+IFERROR(VLOOKUP($BB$19,Sheet1!AH5:AK5,3,0),0) -> 0 | BC43: =+IFERROR(VLOOKUP($BC$19,Sheet1!AH5:AK5,3,0),0) -> 0 | BD43: 690 | BE43: =+IFERROR(VLOOKUP($BE$19,Sheet1!AH5:AK5,3,0),0) -> 0 | BF43: =+IFERROR(VLOOKUP($BF$19,Sheet1!AH5:AK5,3,0),0) -> 0 | BG43: =+IFERROR(VLOOKUP($BG$19,Sheet1!AH5:AK5,3,0),0) -> 0 | BH43: =+IFERROR(VLOOKUP($BH$19,Sheet1!AH5:AK5,3,0),0) -> 0 | BI43: =+IFERROR(VLOOKUP($BI$19,Sheet1!AH5:AK5,3,0),0) -> 0 | BJ43: =+IFERROR(VLOOKUP($BJ$19,Sheet1!AH5:AK5,3,0),0) -> 0 | BK43: =+IFERROR(VLOOKUP($BK$19,Sheet1!AH5:AK5,3,0),0) -> 0 | BL43: =+IFERROR(VLOOKUP($BL$19,Sheet1!AL5:AO5,3,0),0) -> 0 | BM43: =+IFERROR(VLOOKUP($BM$19,Sheet1!AL5:AO5,3,0),0) -> 0 | BN43: =+IFERROR(VLOOKUP($BN$19,Sheet1!AL5:AO5,3,0),0) -> 0 | BO43: 570 | BP43: =+IFERROR(VLOOKUP($BP$19,Sheet1!AL5:AO5,3,0),0) -> 0 | BQ43: =+IFERROR(VLOOKUP($BQ$19,Sheet1!AL5:AO5,3,0),0) -> 0 | BR43: =+IFERROR(VLOOKUP($BR$19,Sheet1!AL5:AO5,3,0),0) -> 0 | BS43: =+IFERROR(VLOOKUP($BS$19,Sheet1!AL5:AO5,3,0),0) -> 0 | BT43: =+IFERROR(VLOOKUP($BT$19,Sheet1!AL5:AO5,3,0),0) -> 0 | BU43: =+IFERROR(VLOOKUP($BU$19,Sheet1!AL5:AO5,3,0),0) -> 0 | BV43: =+IFERROR(VLOOKUP($BV$19,Sheet1!AL5:AO5,3,0),0) -> 0 | BW43: =+IFERROR(VLOOKUP($BW$19,Sheet1!AL5:AO5,3,0),0) -> 0 | BX43: =+IFERROR(VLOOKUP($BX$19,Sheet1!AP5:AS5,3,0),0) -> 0 | BY43: 13 | BZ43: =+IFERROR(VLOOKUP($BZ$19,Sheet1!AX5:BA5,3,0),0) -> 0 | CA43: 35 | CB43: =+IFERROR(VLOOKUP($CB$19,Sheet1!BF5:BI5,3,0),0) -> 0 | CC43: =+IFERROR(VLOOKUP($CC$19,Sheet1!BJ5:BM5,3,0),0) -> 0 | CD43: =+IFERROR(VLOOKUP($CD$19,Sheet1!BN5:BQ5,3,0),0) -> 0 | CE43: 35 | CF43: =+IFERROR(VLOOKUP($CF$19,Sheet1!BV5:BY5,3,0),0) -> 0 | CG43: =Sheet1!E5 -> STEEL | CH43: SP0400126 | CI43: CORRUGATED DISPATCH STEEL DRUM 1900 X 830 X 915 MM | CJ43: =Sheet1!CX5 -> 500 | CK43: =16900/0.5 -> 33800 | CL43: =SUMPRODUCT($N$20:$CF$20,N43:CF43)+CK43 -> 795639 | CM43: 0.01 | CN43: =CL43*CM43 -> 7956.39 | CO43: 0.18 | CP43: =CL43*CO43 -> 143215.02 | CQ43: =Sheet1!CF5 -> 0 | CR43: =CL43*CQ43 -> 0 | CS43: =CL43+CN43+CP43+CR43 -> 946810.41 | CT43: 0.02 | CU43: =CS43*CT43 -> 18936.208 | CV43: 0.01 | CW43: =CS43*CV43 -> 9468.1041 | CX43: =Sheet1!CM5 -> 0 | CY43: =CX43*CS43 -> 0
M44: =SUM(M21:M43) -> 3.1454257e+09
E48: Order Quantity | F48: Stnd Length | G48: Truck type | H48: Fare of one truck | I48: No of Drum in one truck | J48: Total length in one Truck | K48: No of Truck | L48: Total Freight | M48: Freight per KM | AB48: CABLE WEIGHT KG/KM | AF48: DRUM WEIGHT | AH48: CABLE + DRUM WEIGHT | AQ48: TRAILOR WEIGHT
B49: FREIGHT CHARGES | D49: =D21 -> 3 CORE X 400 SQ. MM. AL/ARM - WIRE (XLPE) - 11 KV | E49: =K21 -> 209 | F49: =CJ21/1000 -> 0.25 | G49: 25 MT TRAILOR | H49: 72500 | I49: 5 | J49: =F49*I49 -> 1.25 | K49: =ROUNDUP((E49/J49),0) -> 168 | L49: =H49*K49 -> 12180000 | M49: =L49/E49 -> 58277.512 | N49: =CH21 -> SP0400136 | AB49: =SUM(N21:CE21) -> 14259 | AF49: 400 | AH49: =((AB49*F49)+AF49) -> 3964.75 | AQ49: =AH49*I49 -> 19823.75
B50: 25 MT TRAILER | D50: =D22 -> 3 CORE X 300 SQ. MM. AL/ARM - WIRE (XLPE) - 11 KV | E50: =K22 -> 151 | F50: =CJ22/1000 -> 0.25 | G50: 25 MT TRAILOR | H50: 72500 | I50: 5 | J50: =F50*I50 -> 1.25 | K50: =ROUNDUP((E50/J50),0) -> 121 | L50: =H50*K50 -> 8772500 | M50: =L50/E50 -> 58096.026 | N50: =CH22 -> SP0400136 | AB50: =SUM(N22:CE22) -> 11167 | AF50: 400 | AH50: =((AB50*F50)+AF50) -> 3191.75 | AQ50: =AH50*I50 -> 15958.75
A51: BHUBANESWAR | B51: 65000 | D51: =D23 -> 3 CORE X 185 SQ. MM AL/ARM - WIRE (XLPE) - 11 KV | E51: =K23 -> 17 | F51: =CJ23/1000 -> 0.25 | G51: 25 MT TRAILOR | H51: 72500 | I51: 9 | J51: =F51*I51 -> 2.25 | K51: =ROUNDUP((E51/J51),0) -> 8 | L51: =H51*K51 -> 580000 | M51: =L51/E51 -> 34117.647 | N51: =CH23 -> SP0400111 | AB51: =SUM(N23:CE23) -> 8741 | AF51: 260 | AH51: =((AB51*F51)+AF51) -> 2445.25 | AQ51: =AH51*I51 -> 22007.25
A52: BALIA | B52: 70000 | D52: =D24 -> 3 CORE X 150 SQ. MM. AL/ARM - WIRE (XLPE) - 11 KV | E52: =K24 -> 4 | F52: =CJ24/1000 -> 0.25 | G52: 25 MT TRAILOR | H52: 72500 | I52: 9 | J52: =F52*I52 -> 2.25 | K52: =ROUNDUP((E52/J52),0) -> 2 | L52: =H52*K52 -> 145000 | M52: =L52/E52 -> 36250 | N52: =CH24 -> SP0400118 | AB52: =SUM(N24:CE24) -> 7125 | AF52: 180 | AH52: =((AB52*F52)+AF52) -> 1961.25 | AQ52: =AH52*I52 -> 17651.25
A53: BERHAMPUR | B53: 80000 | D53: =D25 -> 3 CORE X 120 SQ. MM. AL/ARM - WIRE (XLPE) - 11 KV | E53: =K25 -> 8 | F53: =CJ25/1000 -> 0.25 | G53: 25 MT TRAILOR | H53: 72500 | I53: 9 | J53: =F53*I53 -> 2.25 | K53: =ROUNDUP((E53/J53),0) -> 4 | L53: =H53*K53 -> 290000 | M53: =L53/E53 -> 36250 | N53: =CH25 -> SP0400118 | AB53: =SUM(N25:CE25) -> 6460 | AF53: 180 | AH53: =((AB53*F53)+AF53) -> 1795 | AQ53: =AH53*I53 -> 16155
A54: BURLA | B54: 75000 | D54: =D26 -> 3 CORE X 95 SQ. MM. AL/ARM - WIRE (XLPE) - 11 KV | E54: =K26 -> 25.5 | F54: =CJ26/1000 -> 0.25 | G54: 25 MT TRAILOR | H54: 72500 | I54: 12 | J54: =F54*I54 -> 3 | K54: =ROUNDUP((E54/J54),0) -> 9 | L54: =H54*K54 -> 652500 | M54: =L54/E54 -> 25588.235 | N54: =CH26 -> SP0400110 | AB54: =SUM(N26:CE26) -> 5921 | AF54: 180 | AH54: =((AB54*F54)+AF54) -> 1660.25 | AQ54: =AH54*I54 -> 19923
A55: AVERAGE = | B55: =AVERAGE(B51:B54) -> 72500 | D55: =D27 -> 3 CORE X 70 SQ. MM. AL/ARM - WIRE (XLPE) - 11 KV | E55: =K27 -> 5.5 | F55: =CJ27/1000 -> 0.25 | G55: 25 MT TRAILOR | H55: 72500 | I55: 14 | J55: =F55*I55 -> 3.5 | K55: =ROUNDUP((E55/J55),0) -> 2 | L55: =H55*K55 -> 145000 | M55: =L55/E55 -> 26363.636 | N55: =CH27 -> SP0400125 | AB55: =SUM(N27:CE27) -> 5219 | AF55: 180 | AH55: =((AB55*F55)+AF55) -> 1484.75 | AQ55: =AH55*I55 -> 20786.5
D56: =D28 -> 3 CORE X 50 SQ. MM. AL/ARD - WIRE (XLPE) - 11 KV | E56: =K28 -> 8 | F56: =CJ28/1000 -> 0.25 | G56: 25 MT TRAILOR | H56: 72500 | I56: 14 | J56: =F56*I56 -> 3.5 | K56: =ROUNDUP((E56/J56),0) -> 3 | L56: =H56*K56 -> 217500 | M56: =L56/E56 -> 27187.5 | N56: =CH28 -> SP0400152 | AB56: =SUM(N28:CE28) -> 4627 | AF56: 150 | AH56: =((AB56*F56)+AF56) -> 1306.75 | AQ56: =AH56*I56 -> 18294.5
D57: =D29 -> 3 CORE X 35 SQ. MM. AL/ARM - WIRE (XLPE) - 11 KV | E57: =K29 -> 7.5 | F57: =CJ29/1000 -> 0.25 | G57: 25 MT TRAILOR | H57: 72500 | I57: 14 | J57: =F57*I57 -> 3.5 | K57: =ROUNDUP((E57/J57),0) -> 3 | L57: =H57*K57 -> 217500 | M57: =L57/E57 -> 29000 | N57: =CH29 -> SP0400152 | AB57: =SUM(N29:CE29) -> 3753 | AF57: 150 | AH57: =((AB57*F57)+AF57) -> 1088.25 | AQ57: =AH57*I57 -> 15235.5
D58: =D30 -> 1 CORE X 1000 SQ. MM. AL/ARM (XLPE) - 11 KV | E58: =K30 -> 7.5 | F58: =CJ30/1000 -> 0.5 | G58: 25 MT TRAILOR | H58: 72500 | I58: 6 | J58: =F58*I58 -> 3 | K58: =ROUNDUP((E58/J58),0) -> 3 | L58: =H58*K58 -> 217500 | M58: =L58/E58 -> 29000 | N58: =CH30 -> SP0400123 | AB58: =SUM(N30:CE30) -> 5475 | AF58: 300 | AH58: =((AB58*F58)+AF58) -> 3037.5 | AQ58: =AH58*I58 -> 18225
D59: =D31 -> 1 CORE X 630 SQ. MM. AL/ARM (XLPE) - 11 KV | E59: =K31 -> 13 | F59: =CJ31/1000 -> 0.5 | G59: 25 MT TRAILOR | H59: 72500 | I59: 10 | J59: =F59*I59 -> 5 | K59: =ROUNDUP((E59/J59),0) -> 3 | L59: =H59*K59 -> 217500 | M59: =L59/E59 -> 16730.769 | N59: =CH31 -> SP0400091 | AB59: =SUM(N31:CE31) -> 3688 | AF59: 250 | AH59: =((AB59*F59)+AF59) -> 2094 | AQ59: =AH59*I59 -> 20940
D60: =D32 -> 1 CORE X 400 SQ. MM. AL/ARM (XLPE) - 11 KV | E60: =K32 -> 6.5 | F60: =CJ32/1000 -> 0.5 | G60: 25 MT TRAILOR | H60: 72500 | I60: 14 | J60: =F60*I60 -> 7 | K60: =ROUNDUP((E60/J60),0) -> 1 | L60: =H60*K60 -> 72500 | M60: =L60/E60 -> 11153.846 | N60: =CH32 -> SP0400125 | AB60: =SUM(N32:CE32) -> 2702 | AF60: 180 | AH60: =((AB60*F60)+AF60) -> 1531 | AQ60: =AH60*I60 -> 21434
D61: =D33 -> 1 CORE X 300 SQ. MM. AL./ARM (XLPE) - 11 KV | E61: =K33 -> 3 | F61: =CJ33/1000 -> 0.5 | G61: 25 MT TRAILOR | H61: 72500 | I61: 14 | J61: =F61*I61 -> 7 | K61: =ROUNDUP((E61/J61),0) -> 1 | L61: =H61*K61 -> 72500 | M61: =L61/E61 -> 24166.667 | N61: =CH33 -> SP0400152 | AB61: =SUM(N33:CE33) -> 2260 | AF61: 150 | AH61: =((AB61*F61)+AF61) -> 1280 | AQ61: =AH61*I61 -> 17920
D62: =D34 -> 3 CORE X 400 SQ. MM AL/ARM - WIRE (XLPE) - 33 KV | E62: =K34 -> 321.5 | F62: =CJ34/1000 -> 0.25 | G62: 25 MT TRAILOR | H62: 72500 | I62: 4 | J62: =F62*I62 -> 1 | K62: =ROUNDUP((E62/J62),0) -> 322 | L62: =H62*K62 -> 23345000 | M62: =L62/E62 -> 72612.753 | N62: =CH34 -> SP0400137 | AB62: =SUM(N34:CE34) -> 19715 | AF62: 550 | AH62: =((AB62*F62)+AF62) -> 5478.75 | AQ62: =AH62*I62 -> 21915
D63: =D35 -> 3 CORE X 300 SQ. MM. AL/ARM - WIRE (XLPE) - 33 KV | E63: =K35 -> 45 | F63: =CJ35/1000 -> 0.25 | G63: 25 MT TRAILOR | H63: 72500 | I63: 4 | J63: =F63*I63 -> 1 | K63: =ROUNDUP((E63/J63),0) -> 45 | L63: =H63*K63 -> 3262500 | M63: =L63/E63 -> 72500 | N63: =CH35 -> SP0400105 | AB63: =SUM(N35:CE35) -> 17508 | AF63: 510 | AH63: =((AB63*F63)+AF63) -> 4887 | AQ63: =AH63*I63 -> 19548
D64: =D36 -> 3 CORE X 185 SQ. MM AL/ARM - WIRE (XLPE) - 33 KV | E64: =K36 -> 28.5 | F64: =CJ36/1000 -> 0.25 | G64: 25 MT TRAILOR | H64: 72500 | I64: 5 | J64: =F64*I64 -> 1.25 | K64: =ROUNDUP((E64/J64),0) -> 23 | L64: =H64*K64 -> 1667500 | M64: =L64/E64 -> 58508.772 | N64: =CH36 -> SP0400108 | AB64: =SUM(N36:CE36) -> 14621 | AF64: 400 | AH64: =((AB64*F64)+AF64) -> 4055.25 | AQ64: =AH64*I64 -> 20276.25
D65: =D37 -> 3 CORE X 95 SQ. MM. AL/ARM WIRE (XLPE) - 33 KV | E65: =K37 -> 10.5 | F65: =CJ37/1000 -> 0.25 | G65: 25 MT TRAILOR | H65: 72500 | I65: 7 | J65: =F65*I65 -> 1.75 | K65: =ROUNDUP((E65/J65),0) -> 6 | L65: =H65*K65 -> 435000 | M65: =L65/E65 -> 41428.571 | N65: =CH37 -> SP0400136 | AB65: =SUM(N37:CE37) -> 10754 | AF65: 400 | AH65: =((AB65*F65)+AF65) -> 3088.5 | AQ65: =AH65*I65 -> 21619.5
D66: =D38 -> 3 CORE X 70 SQ. MM. AL/ARM - WIRE (XLPE) - 33 KV | E66: =K38 -> 2 | F66: =CJ38/1000 -> 0.25 | G66: 25 MT TRAILOR | H66: 72500 | I66: 8 | J66: =F66*I66 -> 2 | K66: =ROUNDUP((E66/J66),0) -> 1 | L66: =H66*K66 -> 72500 | M66: =L66/E66 -> 36250 | N66: =CH38 -> SP0400136 | AB66: =SUM(N38:CE38) -> 9960 | AF66: 400 | AH66: =((AB66*F66)+AF66) -> 2890 | AQ66: =AH66*I66 -> 23120
D67: =D39 -> 3 CORE X 50 SQ. MM. AL/ARD - WIRE (XLPE) - 33 KV (E) | E67: =K39 -> 2.5 | F67: =CJ39/1000 -> 0.25 | G67: 25 MT TRAILOR | H67: 72500 | I67: 9 | J67: =F67*I67 -> 2.25 | K67: =ROUNDUP((E67/J67),0) -> 2 | L67: =H67*K67 -> 145000 | M67: =L67/E67 -> 58000 | N67: =CH39 -> SP0400112 | AB67: =SUM(N39:CE39) -> 9139 | AF67: 280 | AH67: =((AB67*F67)+AF67) -> 2564.75 | AQ67: =AH67*I67 -> 23082.75
... D71: =D43 -> 1 CORE X 300 SQ. MM. AL/ARM (XLPE) - 33 KV | E71: =K43 -> 3 | F71: =CJ43/1000 -> 0.5 | G71: 25 MT TRAILOR | H71: 72500 | I71: 11 | J71: =F71*I71 -> 5.5 | K71: =ROUNDUP((E71/J71),0) -> 1 | L71: =H71*K71 -> 72500 | M71: =L71/E71 -> 24166.667 | N71: =CH43 -> SP0400126 | AB71: =SUM(N43:CE43) -> 3412 | AF71: 260 | AH71: =((AB71*F71)+AF71) -> 1966 | AQ71: =AH71*I71 -> 21626
A76: DOCKET NO. | B76: BASE DATE | C76: ITEM CODE | D76: PROPOSE ERP ITEM NAME | E76: EX-WORKS (PER MTR) | F76: FREIGHT PER MTR | G76: PRICE INCLUDING FREIGHT (PER MTR) | H76: GST % | I76: GST VALUE | J76: PRICE INCLUDING GST & FREIGHT (PER MTR) | K76: QTY | L76: Unit | M76: TOTAL PRICE OF FULL QTY (INCLUDING FRIGHT & GST)
A78: =A21 -> ENQ-18390-25-26 | B78: =B21 -> 46357 | C78: =C21 -> FA1300083 | D78: =D21 -> 3 CORE X 400 SQ. MM. AL/ARM - WIRE (XLPE) - 11 KV | E78: =ROUNDUP(E21/1000,2) -> 2800.58 | F78: =ROUNDUP(F21/1000,2) -> 58.28 | G78: =E78+F78 -> 2858.86 | H78: =H21 -> 0.18 | I78: =G78*H78 -> 514.5948 | J78: =G78+I78 -> 3373.4548 | K78: =K21*1000 -> 209000 | L78: MTR | M78: =J78*K78 -> 7.0505205e+08
A79: =A22 -> ENQ-18390-25-26 | B79: =B22 -> 46357 | C79: =C22 -> FA1300091 | D79: =D22 -> 3 CORE X 300 SQ. MM. AL/ARM - WIRE (XLPE) - 11 KV | E79: =ROUNDUP(E22/1000,2) -> 2238.62 | F79: =ROUNDUP(F22/1000,2) -> 58.1 | G79: =E79+F79 -> 2296.72 | H79: =H22 -> 0.18 | I79: =G79*H79 -> 413.4096 | J79: =G79+I79 -> 2710.1296 | K79: =K22*1000 -> 151000 | L79: MTR | M79: =J79*K79 -> 4.0922957e+08
A80: =A23 -> ENQ-18390-25-26 | B80: =B23 -> 46357 | C80: =C23 -> FA1300090 | D80: =D23 -> 3 CORE X 185 SQ. MM AL/ARM - WIRE (XLPE) - 11 KV | E80: =ROUNDUP(E23/1000,2) -> 1652.7 | F80: =ROUNDUP(F23/1000,2) -> 34.12 | G80: =E80+F80 -> 1686.82 | H80: =H23 -> 0.18 | I80: =G80*H80 -> 303.6276 | J80: =G80+I80 -> 1990.4476 | K80: =K23*1000 -> 17000 | L80: MTR | M80: =J80*K80 -> 33837609
A81: =A24 -> ENQ-18390-25-26 | B81: =B24 -> 46357 | C81: =C24 -> FA1300176 | D81: =D24 -> 3 CORE X 150 SQ. MM. AL/ARM - WIRE (XLPE) - 11 KV | E81: =ROUNDUP(E24/1000,2) -> 1369.17 | F81: =ROUNDUP(F24/1000,2) -> 36.25 | G81: =E81+F81 -> 1405.42 | H81: =H24 -> 0.18 | I81: =G81*H81 -> 252.9756 | J81: =G81+I81 -> 1658.3956 | K81: =K24*1000 -> 4000 | L81: MTR | M81: =J81*K81 -> 6633582.4
A82: =A25 -> ENQ-18390-25-26 | B82: =B25 -> 46357 | C82: =C25 -> FA1300197 | D82: =D25 -> 3 CORE X 120 SQ. MM. AL/ARM - WIRE (XLPE) - 11 KV | E82: =ROUNDUP(E25/1000,2) -> 1221.57 | F82: =ROUNDUP(F25/1000,2) -> 36.25 | G82: =E82+F82 -> 1257.82 | H82: =H25 -> 0.18 | I82: =G82*H82 -> 226.4076 | J82: =G82+I82 -> 1484.2276 | K82: =K25*1000 -> 8000 | L82: MTR | M82: =J82*K82 -> 11873821
A83: =A26 -> ENQ-18390-25-26 | B83: =B26 -> 46357 | C83: =C26 -> FA1300098 | D83: =D26 -> 3 CORE X 95 SQ. MM. AL/ARM - WIRE (XLPE) - 11 KV | E83: =ROUNDUP(E26/1000,2) -> 1179.38 | F83: =ROUNDUP(F26/1000,2) -> 25.59 | G83: =E83+F83 -> 1204.97 | H83: =H26 -> 0.18 | I83: =G83*H83 -> 216.8946 | J83: =G83+I83 -> 1421.8646 | K83: =K26*1000 -> 25500 | L83: MTR | M83: =J83*K83 -> 36257547
A84: =A27 -> ENQ-18390-25-26 | B84: =B27 -> 46357 | C84: =C27 -> FA1300097 | D84: =D27 -> 3 CORE X 70 SQ. MM. AL/ARM - WIRE (XLPE) - 11 KV | E84: =ROUNDUP(E27/1000,2) -> 1034.56 | F84: =ROUNDUP(F27/1000,2) -> 26.37 | G84: =E84+F84 -> 1060.93 | H84: =H27 -> 0.18 | I84: =G84*H84 -> 190.9674 | J84: =G84+I84 -> 1251.8974 | K84: =K27*1000 -> 5500 | L84: MTR | M84: =J84*K84 -> 6885435.7
A85: =A28 -> ENQ-18390-25-26 | B85: =B28 -> 46357 | C85: =C28 -> FA1300313 | D85: =D28 -> 3 CORE X 50 SQ. MM. AL/ARD - WIRE (XLPE) - 11 KV | E85: =ROUNDUP(E28/1000,2) -> 1009.47 | F85: =ROUNDUP(F28/1000,2) -> 27.19 | G85: =E85+F85 -> 1036.66 | H85: =H28 -> 0.18 | I85: =G85*H85 -> 186.5988 | J85: =G85+I85 -> 1223.2588 | K85: =K28*1000 -> 8000 | L85: MTR | M85: =J85*K85 -> 9786070.4
A86: =A29 -> ENQ-18390-25-26 | B86: =B29 -> 46357 | C86: =C29 -> FA1300114 | D86: =D29 -> 3 CORE X 35 SQ. MM. AL/ARM - WIRE (XLPE) - 11 KV | E86: =ROUNDUP(E29/1000,2) -> 847.16 | F86: =ROUNDUP(F29/1000,2) -> 29 | G86: =E86+F86 -> 876.16 | H86: =H29 -> 0.18 | I86: =G86*H86 -> 157.7088 | J86: =G86+I86 -> 1033.8688 | K86: =K29*1000 -> 7500 | L86: MTR | M86: =J86*K86 -> 7754016
A87: =A30 -> ENQ-18390-25-26 | B87: =B30 -> 46357 | C87: =C30 -> FA1300066 | D87: =D30 -> 1 CORE X 1000 SQ. MM. AL/ARM (XLPE) - 11 KV | E87: =ROUNDUP(E30/1000,2) -> 1757.61 | F87: =ROUNDUP(F30/1000,2) -> 29 | G87: =E87+F87 -> 1786.61 | H87: =H30 -> 0.18 | I87: =G87*H87 -> 321.5898 | J87: =G87+I87 -> 2108.1998 | K87: =K30*1000 -> 7500 | L87: MTR | M87: =J87*K87 -> 15811498
A88: =A31 -> ENQ-18390-25-26 | B88: =B31 -> 46357 | C88: =C31 -> FA1300016 | D88: =D31 -> 1 CORE X 630 SQ. MM. AL/ARM (XLPE) - 11 KV | E88: =ROUNDUP(E31/1000,2) -> 1178.3 | F88: =ROUNDUP(F31/1000,2) -> 16.74 | G88: =E88+F88 -> 1195.04 | H88: =H31 -> 0.18 | I88: =G88*H88 -> 215.1072 | J88: =G88+I88 -> 1410.1472 | K88: =K31*1000 -> 13000 | L88: MTR | M88: =J88*K88 -> 18331914
A89: =A32 -> ENQ-18390-25-26 | B89: =B32 -> 46357 | C89: =C32 -> FA1300047 | D89: =D32 -> 1 CORE X 400 SQ. MM. AL/ARM (XLPE) - 11 KV | E89: =ROUNDUP(E32/1000,2) -> 854.71 | F89: =ROUNDUP(F32/1000,2) -> 11.16 | G89: =E89+F89 -> 865.87 | H89: =H32 -> 0.18 | I89: =G89*H89 -> 155.8566 | J89: =G89+I89 -> 1021.7266 | K89: =K32*1000 -> 6500 | L89: MTR | M89: =J89*K89 -> 6641222.9
... A100: =A43 -> ENQ-18390-25-26 | B100: =B43 -> 46357 | C100: =C43 -> FA1300019 | D100: =D43 -> 1 CORE X 300 SQ. MM. AL/ARM (XLPE) - 33 KV | E100: =ROUNDUP(E43/1000,2) -> 975.22 | F100: =ROUNDUP(F43/1000,2) -> 24.17 | G100: =E100+F100 -> 999.39 | H100: =H43 -> 0.18 | I100: =G100*H100 -> 179.8902 | J100: =G100+I100 -> 1179.2802 | K100: =K43*1000 -> 3000 | L100: MTR | M100: =J100*K100 -> 3537840.6
M101: =SUM(M78:M100) -> 3.1454381e+09
M102: =M101-M44 -> 12335.141

Sheet PV AUTOCALCULATION SHEET
A1: Base Date | B1: 45992
A2: PV Terms(Price Variation Formula) | B2: The line-item prices shall be subject to Price Variation clause as per latest IEEMA Circular. (Base Date of IEEMA for price consideration shall be Dec-25).
A3: PV FORMULA
A4: P=Po+Alf (Al-Alo)+XLFAL(CC-Cco)+CCFAI(PVCc-PVCco)+FeF (Fe-Feo)+SMIF(SMIF1 - SMIF0)
A7: Alf | B7: Variation factor for aluminum.
A8: CCFAI | B8: Variation factor for PVC compound/Polymer for aluminum conductor cable.
A9: XLFAL | B9: Variation Factor For XLPE
A10: Fef | B10: Variation factor for steel
A13: Item | B13: Ex-Work | AK13: Rs. 15/kg extra
AC14: VALUE ADDITION CALCULATION
A15: Item | B15: Calculation part | C15: Date of Inspection | D15: Applicable Date | J15: BASE DATE | P15: FACTORS | U15: Ex-Work Po | V15: PVC of al | W15: PVC of XLPE | X15: PVC OF PVC | Y15: PVC OF FE | Z15: PVC OF CU TAPE | AA15: PV/PKM | AB15: Billing Price/PKM
D16: Date | E16: Al | F16: Cu | G16: Cc | H16: PVCc | I16: Fe | J16: Date | K16: Alo | L16: Cuo | M16: Cco | N16: PVCco | O16: Feo | AC16: ='AUTO CALCULATION SHEET (2)'!N19 -> Alumimium | AD16: ='AUTO CALCULATION SHEET (2)'!AB19 -> Copper Tape - 0.045 mm | AE16: ='AUTO CALCULATION SHEET (2)'!AF19 -> Extruded semiconductive | AF16: ='AUTO CALCULATION SHEET (2)'!AH19 -> HT-XLPE | AG16: ='AUTO CALCULATION SHEET (2)'!AQ19 -> POLY TAPE | AH16: ='AUTO CALCULATION SHEET (2)'!AX19 -> PVC Type ST-2 | AI16: ='AUTO CALCULATION SHEET (2)'!BD19 -> Aluminium Round Wire | AJ16: ='AUTO CALCULATION SHEET (2)'!BJ19 -> Galvanised Steel Round Wire | AK16: ='AUTO CALCULATION SHEET (2)'!BO19 -> FRLSH PVC Type ST-2 | AL16: ='AUTO CALCULATION SHEET (2)'!BX19 -> PP FILLER | AM16: ='AUTO CALCULATION SHEET (2)'!BY19 -> NCWBT | AN16: ='AUTO CALCULATION SHEET (2)'!CA19 -> Semi conducting Water Swellable tape | AO16: ='AUTO CALCULATION SHEET (2)'!CE19 -> RUBBERIZED COTTON TAPE | AP16: RMC | AQ16: Drum | AR16: RMC+Drum | AS16: VA | AT16: Groos VA% | AU16: Mfg % | AV16: Int % | AW16: Ins% | AX16: Net VA
P17: Alf | Q17: XLFAL | R17: CCFAI | S17: FeF | T17: Smif | AC17: 316 | AD17: 1406 | AE17: 160 | AF17: 125 | AG17: 115 | AH17: 65 | AI17: =AC17+5 -> 321 | AJ17: 85 | AK17: =79+15 -> 94 | AL17: 77 | AM17: 310 | AN17: 368 | AO17: 283
B18: ARM WIRE DIA | AC18: Kg/Km | AD18: Kg/Km | AE18: Kg/Km | AF18: Kg/Km | AG18: Kg/Km | AH18: Kg/Km | AI18: Kg/Km | AJ18: Kg/Km | AK18: Kg/Km | AL18: Kg/Km | AM18: Kg/Km | AN18: Kg/Km | AO18: Kg/Km
A19: ='AUTO CALCULATION SHEET (2)'!D21 -> 3 CORE X 400 SQ. MM. AL/ARM - WIRE (XLPE) - 11 KV | B19: 4 | C19: PROVISIONAL | D19: 46070 | E19: 316036.08 | F19: 1266186.6 | G19: 194965 | H19: 153825 | I19: 74250 | J19: =$B$1 -> 45992 | K19: 298490 | L19: 1144212 | M19: 195005 | N19: 152825 | O19: 72250 | P19: 3.374 | Q19: 1.314 | R19: 3.664 | S19: 6.658 | T19: 0.124 | U19: ='AUTO CALCULATION SHEET (2)'!G78*1000 -> 2858860 | V19: =(P19*(E19-K19)) -> 59200.474 | W19: =(Q19*(G19-M19)) -> -52.56 | X19: =(R19*(H19-N19)) -> 3664 | Y19: =(S19*(I19-O19)) -> 13316 | Z19: =T19*(F19-L19) -> 15124.852 | AA19: =V19+W19+X19+Y19+Z19 -> 91252.766 | AB19: =+U19+AA19 -> 2950112.8 | AC19: ='AUTO CALCULATION SHEET (2)'!N21 -> 3240 | AD19: ='AUTO CALCULATION SHEET (2)'!AB21 -> 176 | AE19: ='AUTO CALCULATION SHEET (2)'!AF21 -> 518 | AF19: ='AUTO CALCULATION SHEET (2)'!AH21 -> 930 | AG19: ='AUTO CALCULATION SHEET (2)'!AQ21 -> 0 | AH19: ='AUTO CALCULATION SHEET (2)'!AX21 -> 1130 | AI19: ='AUTO CALCULATION SHEET (2)'!BD21 -> 0 | AJ19: ='AUTO CALCULATION SHEET (2)'!BJ21 -> 5643 | AK19: ='AUTO CALCULATION SHEET (2)'!BO21 -> 1377 | AL19: ='AUTO CALCULATION SHEET (2)'!BX21 -> 1032 | AM19: ='AUTO CALCULATION SHEET (2)'!BY21 -> 58 | AN19: ='AUTO CALCULATION SHEET (2)'!CA21 -> 95 | AO19: ='AUTO CALCULATION SHEET (2)'!CE21 -> 60 | AP19: =SUMPRODUCT(AC19:AO19,$AC$17:$AO$17) -> 2302353 | AQ19: ='AUTO CALCULATION SHEET (2)'!CK21 -> 104000 | AR19: =AP19+AQ19 -> 2406353 | AS19: =AB19-AR19 -> 543759.77 | AT19: =ROUND((AS19/AB19)*100,2) -> 18.43 | AU19: 0 | AV19: 2 | AW19: 1 | AX19: =AT19-AU19-AV19-AW19 -> 15.43
A20: ='AUTO CALCULATION SHEET (2)'!D22 -> 3 CORE X 300 SQ. MM. AL/ARM - WIRE (XLPE) - 11 KV | B20: 3.15 | C20: PROVISIONAL | D20: 46070 | E20: 316036.08 | F20: 1266186.6 | G20: 194965 | H20: 153825 | I20: 74250 | J20: =$B$1 -> 45992 | K20: 298490 | L20: 1144212 | M20: 195005 | N20: 152825 | O20: 72250 | P20: 2.635 | Q20: 1.167 | R20: 3.161 | S20: 5.182 | T20: 0.11 | U20: ='AUTO CALCULATION SHEET (2)'!G79*1000 -> 2296720 | V20: =(P20*(E20-K20)) -> 46233.921 | W20: =(Q20*(G20-M20)) -> -46.68 | X20: =(R20*(H20-N20)) -> 3161 | Y20: =(S20*(I20-O20)) -> 10364 | Z20: =T20*(F20-L20) -> 13417.207 | AA20: =V20+W20+X20+Y20+Z20 -> 73129.448 | AB20: =+U20+AA20 -> 2369849.4 | AC20: ='AUTO CALCULATION SHEET (2)'!N22 -> 2430 | AD20: ='AUTO CALCULATION SHEET (2)'!AB22 -> 161 | AE20: ='AUTO CALCULATION SHEET (2)'!AF22 -> 465 | AF20: ='AUTO CALCULATION SHEET (2)'!AH22 -> 835 | AG20: ='AUTO CALCULATION SHEET (2)'!AQ22 -> 0 | AH20: ='AUTO CALCULATION SHEET (2)'!AX22 -> 974 | AI20: ='AUTO CALCULATION SHEET (2)'!BD22 -> 0 | AJ20: ='AUTO CALCULATION SHEET (2)'!BJ22 -> 4072 | AK20: ='AUTO CALCULATION SHEET (2)'!BO22 -> 1190 | AL20: ='AUTO CALCULATION SHEET (2)'!BX22 -> 862 | AM20: ='AUTO CALCULATION SHEET (2)'!BY22 -> 38 | AN20: ='AUTO CALCULATION SHEET (2)'!CA22 -> 86 | AO20: ='AUTO CALCULATION SHEET (2)'!CE22 -> 54 | AP20: =SUMPRODUCT(AC20:AO20,$AC$17:$AO$17) -> 1819395 | AQ20: ='AUTO CALCULATION SHEET (2)'!CK22 -> 104000 | AR20: =AP20+AQ20 -> 1923395 | AS20: =AB20-AR20 -> 446454.45 | AT20: =ROUND((AS20/AB20)*100,2) -> 18.84 | AU20: 0 | AV20: 2 | AW20: 1 | AX20: =AT20-AU20-AV20-AW20 -> 15.84
A21: ='AUTO CALCULATION SHEET (2)'!D23 -> 3 CORE X 185 SQ. MM AL/ARM - WIRE (XLPE) - 11 KV | B21: 3.15 | C21: PROVISIONAL | D21: 46070 | E21: 316036.08 | F21: 1266186.6 | G21: 194965 | H21: 153825 | I21: 74250 | J21: =$B$1 -> 45992 | K21: 298490 | L21: 1144212 | M21: 195005 | N21: 152825 | O21: 72250 | P21: 1.605 | Q21: 0.968 | R21: 2.406 | S21: 4.148 | T21: 0.094 | U21: ='AUTO CALCULATION SHEET (2)'!G80*1000 -> 1686820 | V21: =(P21*(E21-K21)) -> 28161.458 | W21: =(Q21*(G21-M21)) -> -38.72 | X21: =(R21*(H21-N21)) -> 2406 | Y21: =(S21*(I21-O21)) -> 8296 | Z21: =T21*(F21-L21) -> 11465.613 | AA21: =V21+W21+X21+Y21+Z21 -> 50290.352 | AB21: =+U21+AA21 -> 1737110.4 | AC21: ='AUTO CALCULATION SHEET (2)'!N23 -> 1499 | AD21: ='AUTO CALCULATION SHEET (2)'!AB23 -> 138 | AE21: ='AUTO CALCULATION SHEET (2)'!AF23 -> 387 | AF21: ='AUTO CALCULATION SHEET (2)'!AH23 -> 693 | AG21: ='AUTO CALCULATION SHEET (2)'!AQ23 -> 0 | AH21: ='AUTO CALCULATION SHEET (2)'!AX23 -> 809 | AI21: ='AUTO CALCULATION SHEET (2)'!BD23 -> 0 | AJ21: ='AUTO CALCULATION SHEET (2)'!BJ23 -> 3500 | AK21: ='AUTO CALCULATION SHEET (2)'!BO23 -> 945 | AL21: ='AUTO CALCULATION SHEET (2)'!BX23 -> 615 | AM21: ='AUTO CALCULATION SHEET (2)'!BY23 -> 35 | AN21: ='AUTO CALCULATION SHEET (2)'!CA23 -> 72 | AO21: ='AUTO CALCULATION SHEET (2)'!CE23 -> 48 | AP21: =SUMPRODUCT(AC21:AO21,$AC$17:$AO$17) -> 1353457 | AQ21: ='AUTO CALCULATION SHEET (2)'!CK23 -> 67600 | AR21: =AP21+AQ21 -> 1421057 | AS21: =AB21-AR21 -> 316053.35 | AT21: =ROUND((AS21/AB21)*100,2) -> 18.19 | AU21: 0 | AV21: 2 | AW21: 1 | AX21: =AT21-AU21-AV21-AW21 -> 15.19
A22: ='AUTO CALCULATION SHEET (2)'!D24 -> 3 CORE X 150 SQ. MM. AL/ARM - WIRE (XLPE) - 11 KV | B22: 2.5 | C22: PROVISIONAL | D22: 46070 | E22: 316036.08 | F22: 1266186.6 | G22: 194965 | H22: 153825 | I22: 75250 | J22: =$B$1 -> 45992 | K22: 298490 | L22: 1144212 | M22: 195005 | N22: 152825 | O22: 73250 | P22: 1.279 | Q22: 0.89 | R22: 2.061 | S22: 3.265 | T22: 0.088 | U22: ='AUTO CALCULATION SHEET (2)'!G81*1000 -> 1405420 | V22: =(P22*(E22-K22)) -> 22441.436 | W22: =(Q22*(G22-M22)) -> -35.6 | X22: =(R22*(H22-N22)) -> 2061 | Y22: =(S22*(I22-O22)) -> 6530 | Z22: =T22*(F22-L22) -> 10733.766 | AA22: =V22+W22+X22+Y22+Z22 -> 41730.602 | AB22: =+U22+AA22 -> 1447150.6 | AC22: ='AUTO CALCULATION SHEET (2)'!N24 -> 1215 | AD22: ='AUTO CALCULATION SHEET (2)'!AB24 -> 130 | AE22: ='AUTO CALCULATION SHEET (2)'!AF24 -> 359 | AF22: ='AUTO CALCULATION SHEET (2)'!AH24 -> 642 | AG22: ='AUTO CALCULATION SHEET (2)'!AQ24 -> 0 | AH22: ='AUTO CALCULATION SHEET (2)'!AX24 -> 666 | AI22: ='AUTO CALCULATION SHEET (2)'!BD24 -> 0 | AJ22: ='AUTO CALCULATION SHEET (2)'!BJ24 -> 2605 | AK22: ='AUTO CALCULATION SHEET (2)'!BO24 -> 812 | AL22: ='AUTO CALCULATION SHEET (2)'!BX24 -> 567 | AM22: ='AUTO CALCULATION SHEET (2)'!BY24 -> 18 | AN22: ='AUTO CALCULATION SHEET (2)'!CA24 -> 67 | AO22: ='AUTO CALCULATION SHEET (2)'!CE24 -> 44 | AP22: =SUMPRODUCT(AC22:AO22,$AC$17:$AO$17) -> 1131800 | AQ22: ='AUTO CALCULATION SHEET (2)'!CK24 -> 46800 | AR22: =AP22+AQ22 -> 1178600 | AS22: =AB22-AR22 -> 268550.6 | AT22: =ROUND((AS22/AB22)*100,2) -> 18.56 | AU22: 0 | AV22: 2 | AW22: 1 | AX22: =AT22-AU22-AV22-AW22 -> 15.56
A23: ='AUTO CALCULATION SHEET (2)'!D25 -> 3 CORE X 120 SQ. MM. AL/ARM - WIRE (XLPE) - 11 KV | B23: 2.5 | C23: PROVISIONAL | D23: 46070 | E23: 316036.08 | F23: 1266186.6 | G23: 194965 | H23: 153825 | I23: 75250 | J23: =$B$1 -> 45992 | K23: 298490 | L23: 1144212 | M23: 195005 | N23: 152825 | O23: 73250 | P23: 1.036 | Q23: 0.822 | R23: 1.877 | S23: 2.882 | T23: 0.083 | U23: ='AUTO CALCULATION SHEET (2)'!G82*1000 -> 1257820 | V23: =(P23*(E23-K23)) -> 18177.739 | W23: =(Q23*(G23-M23)) -> -32.88 | X23: =(R23*(H23-N23)) -> 1877 | Y23: =(S23*(I23-O23)) -> 5764 | Z23: =T23*(F23-L23) -> 10123.893 | AA23: =V23+W23+X23+Y23+Z23 -> 35909.752 | AB23: =+U23+AA23 -> 1293729.8 | AC23: ='AUTO CALCULATION SHEET (2)'!N25 -> 972 | AD23: ='AUTO CALCULATION SHEET (2)'!AB25 -> 123 | AE23: ='AUTO CALCULATION SHEET (2)'!AF25 -> 332 | AF23: ='AUTO CALCULATION SHEET (2)'!AH25 -> 593 | AG23: ='AUTO CALCULATION SHEET (2)'!AQ25 -> 0 | AH23: ='AUTO CALCULATION SHEET (2)'!AX25 -> 605 | AI23: ='AUTO CALCULATION SHEET (2)'!BD25 -> 0 | AJ23: ='AUTO CALCULATION SHEET (2)'!BJ25 -> 2485 | AK23: ='AUTO CALCULATION SHEET (2)'!BO25 -> 726 | AL23: ='AUTO CALCULATION SHEET (2)'!BX25 -> 503 | AM23: ='AUTO CALCULATION SHEET (2)'!BY25 -> 17 | AN23: ='AUTO CALCULATION SHEET (2)'!CA25 -> 62 | AO23: ='AUTO CALCULATION SHEET (2)'!CE25 -> 42 | AP23: =SUMPRODUCT(AC23:AO23,$AC$17:$AO$17) -> 1004832 | AQ23: ='AUTO CALCULATION SHEET (2)'!CK25 -> 46800 | AR23: =AP23+AQ23 -> 1051632 | AS23: =AB23-AR23 -> 242097.75 | AT23: =ROUND((AS23/AB23)*100,2) -> 18.71 | AU23: 0 | AV23: 2 | AW23: 1 | AX23: =AT23-AU23-AV23-AW23 -> 15.71
A24: ='AUTO CALCULATION SHEET (2)'!D26 -> 3 CORE X 95 SQ. MM. AL/ARM - WIRE (XLPE) - 11 KV | B24: 2.5 | C24: PROVISIONAL | D24: 46070 | E24: 316036.08 | F24: 1266186.6 | G24: 194965 | H24: 153825 | I24: 75250 | J24: =$B$1 -> 45992 | K24: 298490 | L24: 1144212 | M24: 195005 | N24: 152825 | O24: 73250 | P24: 0.821 | Q24: 0.755 | R24: 1.647 | S24: 2.718 | T24: 0.077 | U24: ='AUTO CALCULATION SHEET (2)'!G83*1000 -> 1204970 | V24: =(P24*(E24-K24)) -> 14405.332 | W24: =(Q24*(G24-M24)) -> -30.2 | X24: =(R24*(H24-N24)) -> 1647 | Y24: =(S24*(I24-O24)) -> 5436 | Z24: =T24*(F24-L24) -> 9392.045 | AA24: =V24+W24+X24+Y24+Z24 -> 30850.177 | AB24: =+U24+AA24 -> 1235820.2 | AC24: ='AUTO CALCULATION SHEET (2)'!N26 -> 770 | AD24: ='AUTO CALCULATION SHEET (2)'!AB26 -> 115 | AE24: ='AUTO CALCULATION SHEET (2)'!AF26 -> 304 | AF24: ='AUTO CALCULATION SHEET (2)'!AH26 -> 542 | AG24: ='AUTO CALCULATION SHEET (2)'!AQ26 -> 0 | AH24: ='AUTO CALCULATION SHEET (2)'!AX26 -> 576 | AI24: ='AUTO CALCULATION SHEET (2)'!BD26 -> 0 | AJ24: ='AUTO CALCULATION SHEET (2)'!BJ26 -> 2324 | AK24: ='AUTO CALCULATION SHEET (2)'!BO26 -> 685 | AL24: ='AUTO CALCULATION SHEET (2)'!BX26 -> 418 | AM24: ='AUTO CALCULATION SHEET (2)'!BY26 -> 15 | AN24: ='AUTO CALCULATION SHEET (2)'!CA26 -> 57 | AO24: ='AUTO CALCULATION SHEET (2)'!CE26 -> 40 | AP24: =SUMPRODUCT(AC24:AO24,$AC$17:$AO$17) -> 889902 | AQ24: ='AUTO CALCULATION SHEET (2)'!CK26 -> 46800 | AR24: =AP24+AQ24 -> 936702 | AS24: =AB24-AR24 -> 299118.18 | AT24: =ROUND((AS24/AB24)*100,2) -> 24.2 | AU24: 0 | AV24: 2 | AW24: 1 | AX24: =AT24-AU24-AV24-AW24 -> 21.2
A25: ='AUTO CALCULATION SHEET (2)'!D27 -> 3 CORE X 70 SQ. MM. AL/ARM - WIRE (XLPE) - 11 KV | B25: 2.5 | C25: PROVISIONAL | D25: 46070 | E25: 316036.08 | F25: 1266186.6 | G25: 194965 | H25: 153825 | I25: 75250 | J25: =$B$1 -> 45992 | K25: 298490 | L25: 1144212 | M25: 195005 | N25: 152825 | O25: 73250 | P25: 0.593 | Q25: 0.679 | R25: 1.396 | S25: 2.503 | T25: 0.071 | U25: ='AUTO CALCULATION SHEET (2)'!G84*1000 -> 1060930 | V25: =(P25*(E25-K25)) -> 10404.825 | W25: =(Q25*(G25-M25)) -> -27.16 | X25: =(R25*(H25-N25)) -> 1396 | Y25: =(S25*(I25-O25)) -> 5006 | Z25: =T25*(F25-L25) -> 8660.1973 | AA25: =V25+W25+X25+Y25+Z25 -> 25439.863 | AB25: =+U25+AA25 -> 1086369.9 | AC25: ='AUTO CALCULATION SHEET (2)'!N27 -> 567 | AD25: ='AUTO CALCULATION SHEET (2)'!AB27 -> 107 | AE25: ='AUTO CALCULATION SHEET (2)'!AF27 -> 268 | AF25: ='AUTO CALCULATION SHEET (2)'!AH27 -> 497 | AG25: ='AUTO CALCULATION SHEET (2)'!AQ27 -> 0 | AH25: ='AUTO CALCULATION SHEET (2)'!AX27 -> 477 | AI25: ='AUTO CALCULATION SHEET (2)'!BD27 -> 0 | AJ25: ='AUTO CALCULATION SHEET (2)'!BJ27 -> 2204 | AK25: ='AUTO CALCULATION SHEET (2)'!BO27 -> 610 | AL25: ='AUTO CALCULATION SHEET (2)'!BX27 -> 383 | AM25: ='AUTO CALCULATION SHEET (2)'!BY27 -> 15 | AN25: ='AUTO CALCULATION SHEET (2)'!CA27 -> 53 | AO25: ='AUTO CALCULATION SHEET (2)'!CE27 -> 38 | AP25: =SUMPRODUCT(AC25:AO25,$AC$17:$AO$17) -> 774703 | AQ25: ='AUTO CALCULATION SHEET (2)'!CK27 -> 46800 | AR25: =AP25+AQ25 -> 821503 | AS25: =AB25-AR25 -> 264866.86 | AT25: =ROUND((AS25/AB25)*100,2) -> 24.38 | AU25: 0 | AV25: 2 | AW25: 1 | AX25: =AT25-AU25-AV25-AW25 -> 21.38
A26: ='AUTO CALCULATION SHEET (2)'!D28 -> 3 CORE X 50 SQ. MM. AL/ARD - WIRE (XLPE) - 11 KV | B26: 2.5 | C26: PROVISIONAL | D26: 46070 | E26: 316036.08 | F26: 1266186.6 | G26: 194965 | H26: 153825 | I26: 75250 | J26: =$B$1 -> 45992 | K26: 298490 | L26: 1144212 | M26: 195005 | N26: 152825 | O26: 73250 | P26: 0.41 | Q26: 0.6 | R26: 1.26 | S26: 2.321 | T26: 0.065 | U26: ='AUTO CALCULATION SHEET (2)'!G85*1000 -> 1036660 | V26: =(P26*(E26-K26)) -> 7193.8928 | W26: =(Q26*(G26-M26)) -> -24 | X26: =(R26*(H26-N26)) -> 1260 | Y26: =(S26*(I26-O26)) -> 4642 | Z26: =T26*(F26-L26) -> 7928.3497 | AA26: =V26+W26+X26+Y26+Z26 -> 21000.242 | AB26: =+U26+AA26 -> 1057660.2 | AC26: ='AUTO CALCULATION SHEET (2)'!N28 -> 405 | AD26: ='AUTO CALCULATION SHEET (2)'!AB28 -> 99 | AE26: ='AUTO CALCULATION SHEET (2)'!AF28 -> 241 | AF26: ='AUTO CALCULATION SHEET (2)'!AH28 -> 446 | AG26: ='AUTO CALCULATION SHEET (2)'!AQ28 -> 0 | AH26: ='AUTO CALCULATION SHEET (2)'!AX28 -> 407 | AI26: ='AUTO CALCULATION SHEET (2)'!BD28 -> 0 | AJ26: ='AUTO CALCULATION SHEET (2)'!BJ28 -> 2044 | AK26: ='AUTO CALCULATION SHEET (2)'!BO28 -> 566 | AL26: ='AUTO CALCULATION SHEET (2)'!BX28 -> 330 | AM26: ='AUTO CALCULATION SHEET (2)'!BY28 -> 6 | AN26: ='AUTO CALCULATION SHEET (2)'!CA28 -> 48 | AO26: ='AUTO CALCULATION SHEET (2)'!CE28 -> 35 | AP26: =SUMPRODUCT(AC26:AO26,$AC$17:$AO$17) -> 669722 | AQ26: ='AUTO CALCULATION SHEET (2)'!CK28 -> 39000 | AR26: =AP26+AQ26 -> 708722 | AS26: =AB26-AR26 -> 348938.24 | AT26: =ROUND((AS26/AB26)*100,2) -> 32.99 | AU26: 0 | AV26: 2 | AW26: 1 | AX26: =AT26-AU26-AV26-AW26 -> 29.99
A27: ='AUTO CALCULATION SHEET (2)'!D29 -> 3 CORE X 35 SQ. MM. AL/ARM - WIRE (XLPE) - 11 KV | B27: 2 | C27: PROVISIONAL | D27: 46070 | E27: 316036.08 | F27: 1266186.6 | G27: 194965 | H27: 153825 | I27: 77250 | J27: =$B$1 -> 45992 | K27: 298490 | L27: 1144212 | M27: 195005 | N27: 152825 | O27: 75250 | P27: 0.302 | Q27: 0.545 | R27: 1.142 | S27: 1.853 | T27: 0.061 | U27: ='AUTO CALCULATION SHEET (2)'!G86*1000 -> 876160 | V27: =(P27*(E27-K27)) -> 5298.9162 | W27: =(Q27*(G27-M27)) -> -21.8 | X27: =(R27*(H27-N27)) -> 1142 | Y27: =(S27*(I27-O27)) -> 3706 | Z27: =T27*(F27-L27) -> 7440.4512 | AA27: =V27+W27+X27+Y27+Z27 -> 17565.567 | AB27: =+U27+AA27 -> 893725.57 | AC27: ='AUTO CALCULATION SHEET (2)'!N29 -> 284 | AD27: ='AUTO CALCULATION SHEET (2)'!AB29 -> 93 | AE27: ='AUTO CALCULATION SHEET (2)'!AF29 -> 220 | AF27: ='AUTO CALCULATION SHEET (2)'!AH29 -> 410 | AG27: ='AUTO CALCULATION SHEET (2)'!AQ29 -> 0 | AH27: ='AUTO CALCULATION SHEET (2)'!AX29 -> 335 | AI27: ='AUTO CALCULATION SHEET (2)'!BD29 -> 0 | AJ27: ='AUTO CALCULATION SHEET (2)'!BJ29 -> 1539 | AK27: ='AUTO CALCULATION SHEET (2)'!BO29 -> 500 | AL27: ='AUTO CALCULATION SHEET (2)'!BX29 -> 290 | AM27: ='AUTO CALCULATION SHEET (2)'!BY29 -> 6 | AN27: ='AUTO CALCULATION SHEET (2)'!CA29 -> 44 | AO27: ='AUTO CALCULATION SHEET (2)'!CE29 -> 32 | AP27: =SUMPRODUCT(AC27:AO27,$AC$17:$AO$17) -> 555980 | AQ27: ='AUTO CALCULATION SHEET (2)'!CK29 -> 39000 | AR27: =AP27+AQ27 -> 594980 | AS27: =AB27-AR27 -> 298745.57 | AT27: =ROUND((AS27/AB27)*100,2) -> 33.43 | AU27: 0 | AV27: 2 | AW27: 1 | AX27: =AT27-AU27-AV27-AW27 -> 30.43
A28: ='AUTO CALCULATION SHEET (2)'!D30 -> 1 CORE X 1000 SQ. MM. AL/ARM (XLPE) - 11 KV | B28: 2.5 | C28: PROVISIONAL | D28: 46070 | E28: 316036.08 | F28: 1266186.6 | G28: 194965 | H28: 153825 | J28: =$B$1 -> 45992 | K28: 298490 | L28: 1144212 | M28: 195005 | N28: 152825 | P28: 3.749 | Q28: 0.66 | R28: 1.035 | T28: 0.058 | U28: ='AUTO CALCULATION SHEET (2)'!G87*1000 -> 1786610 | V28: =(P28*(E28-K28)) -> 65780.254 | W28: =(Q28*(G28-M28)) -> -26.4 | X28: =(R28*(H28-N28)) -> 1035 | Y28: =(S28*(I28-O28)) -> 0 | Z28: =T28*(F28-L28) -> 7074.5274 | AA28: =V28+W28+X28+Y28+Z28 -> 73863.381 | AB28: =+U28+AA28 -> 1860473.4 | AC28: ='AUTO CALCULATION SHEET (2)'!N30 -> 2732 | AD28: ='AUTO CALCULATION SHEET (2)'!AB30 -> 84 | AE28: ='AUTO CALCULATION SHEET (2)'!AF30 -> 276 | AF28: ='AUTO CALCULATION SHEET (2)'!AH30 -> 480 | AG28: ='AUTO CALCULATION SHEET (2)'!AQ30 -> 35 | AH28: ='AUTO CALCULATION SHEET (2)'!AX30 -> 218 | AI28: ='AUTO CALCULATION SHEET (2)'!BD30 -> 814 | AJ28: ='AUTO CALCULATION SHEET (2)'!BJ30 -> 0 | AK28: ='AUTO CALCULATION SHEET (2)'!BO30 -> 706 | AL28: ='AUTO CALCULATION SHEET (2)'!BX30 -> 0 | AM28: ='AUTO CALCULATION SHEET (2)'!BY30 -> 39 | AN28: ='AUTO CALCULATION SHEET (2)'!CA30 -> 49 | AO28: ='AUTO CALCULATION SHEET (2)'!CE30 -> 42 | AP28: =SUMPRODUCT(AC28:AO28,$AC$17:$AO$17) -> 1473437 | AQ28: ='AUTO CALCULATION SHEET (2)'!CK30 -> 39000 | AR28: =AP28+AQ28 -> 1512437 | AS28: =AB28-AR28 -> 348036.38 | AT28: =ROUND((AS28/AB28)*100,2) -> 18.71 | AU28: 0 | AV28: 2 | AW28: 1 | AX28: =AT28-AU28-AV28-AW28 -> 15.71
A29: ='AUTO CALCULATION SHEET (2)'!D31 -> 1 CORE X 630 SQ. MM. AL/ARM (XLPE) - 11 KV | B29: 2 | C29: PROVISIONAL | D29: 46070 | E29: 316036.08 | F29: 1266186.6 | G29: 194965 | H29: 153825 | J29: =$B$1 -> 45992 | K29: 298490 | L29: 1144212 | M29: 195005 | N29: 152825 | P29: 2.369 | Q29: 0.529 | R29: 0.739 | T29: 0.05 | U29: ='AUTO CALCULATION SHEET (2)'!G88*1000 -> 1195040 | V29: =(P29*(E29-K29)) -> 41566.664 | W29: =(Q29*(G29-M29)) -> -21.16 | X29: =(R29*(H29-N29)) -> 739 | Y29: =(S29*(I29-O29)) -> 0 | Z29: =T29*(F29-L29) -> 6098.7305 | AA29: =V29+W29+X29+Y29+Z29 -> 48383.234 | AB29: =+U29+AA29 -> 1243423.2 | AC29: ='AUTO CALCULATION SHEET (2)'!N31 -> 1701 | AD29: ='AUTO CALCULATION SHEET (2)'!AB31 -> 69 | AE29: ='AUTO CALCULATION SHEET (2)'!AF31 -> 213 | AF29: ='AUTO CALCULATION SHEET (2)'!AH31 -> 380 | AG29: ='AUTO CALCULATION SHEET (2)'!AQ31 -> 29 | AH29: ='AUTO CALCULATION SHEET (2)'!AX31 -> 159 | AI29: ='AUTO CALCULATION SHEET (2)'!BD31 -> 539 | AJ29: ='AUTO CALCULATION SHEET (2)'!BJ31 -> 0 | AK29: ='AUTO CALCULATION SHEET (2)'!BO31 -> 500 | AL29: ='AUTO CALCULATION SHEET (2)'!BX31 -> 0 | AM29: ='AUTO CALCULATION SHEET (2)'!BY31 -> 26 | AN29: ='AUTO CALCULATION SHEET (2)'!CA31 -> 39 | AO29: ='AUTO CALCULATION SHEET (2)'!CE31 -> 33 | AP29: =SUMPRODUCT(AC29:AO29,$AC$17:$AO$17) -> 981550 | AQ29: ='AUTO CALCULATION SHEET (2)'!CK31 -> 32500 | AR29: =AP29+AQ29 -> 1014050 | AS29: =AB29-AR29 -> 229373.23 | AT29: =ROUND((AS29/AB29)*100,2) -> 18.45 | AU29: 0 | AV29: 2 | AW29: 1 | AX29: =AT29-AU29-AV29-AW29 -> 15.45
A30: ='AUTO CALCULATION SHEET (2)'!D32 -> 1 CORE X 400 SQ. MM. AL/ARM (XLPE) - 11 KV | B30: 2 | C30: PROVISIONAL | D30: 46070 | E30: 316036.08 | F30: 1266186.6 | G30: 194965 | H30: 153825 | J30: =$B$1 -> 45992 | K30: 298490 | L30: 1144212 | M30: 195005 | N30: 152825 | P30: 1.565 | Q30: 0.42 | R30: 0.578 | T30: 0.041 | U30: ='AUTO CALCULATION SHEET (2)'!G89*1000 -> 865870 | V30: =(P30*(E30-K30)) -> 27459.615 | W30: =(Q30*(G30-M30)) -> -16.8 | X30: =(R30*(H30-N30)) -> 578 | Y30: =(S30*(I30-O30)) -> 0 | Z30: =T30*(F30-L30) -> 5000.959 | AA30: =V30+W30+X30+Y30+Z30 -> 33021.774 | AB30: =+U30+AA30 -> 898891.77 | AC30: ='AUTO CALCULATION SHEET (2)'!N32 -> 1080 | AD30: ='AUTO CALCULATION SHEET (2)'!AB32 -> 59 | AE30: ='AUTO CALCULATION SHEET (2)'!AF32 -> 172 | AF30: ='AUTO CALCULATION SHEET (2)'!AH32 -> 310 | AG30: ='AUTO CALCULATION SHEET (2)'!AQ32 -> 24 | AH30: ='AUTO CALCULATION SHEET (2)'!AX32 -> 115 | AI30: ='AUTO CALCULATION SHEET (2)'!BD32 -> 460 | AJ30: ='AUTO CALCULATION SHEET (2)'!BJ32 -> 0 | AK30: ='AUTO CALCULATION SHEET (2)'!BO32 -> 400 | AL30: ='AUTO CALCULATION SHEET (2)'!BX32 -> 0 | AM30: ='AUTO CALCULATION SHEET (2)'!BY32 -> 20 | AN30: ='AUTO CALCULATION SHEET (2)'!CA32 -> 32 | AO30: ='AUTO CALCULATION SHEET (2)'!CE32 -> 30 | AP30: =SUMPRODUCT(AC30:AO30,$AC$17:$AO$17) -> 712465 | AQ30: ='AUTO CALCULATION SHEET (2)'!CK32 -> 23400 | AR30: =AP30+AQ30 -> 735865 | AS30: =AB30-AR30 -> 163026.77 | AT30: =ROUND((AS30/AB30)*100,2) -> 18.14 | AU30: 0 | AV30: 2 | AW30: 1 | AX30: =AT30-AU30-AV30-AW30 -> 15.14
A31: ='AUTO CALCULATION SHEET (2)'!D33 -> 1 CORE X 300 SQ. MM. AL./ARM (XLPE) - 11 KV | B31: 2 | C31: PROVISIONAL | D31: 46070 | E31: 316036.08 | F31: 1266186.6 | G31: 194965 | H31: 153825 | J31: =$B$1 -> 45992 | K31: 298490 | L31: 1144212 | M31: 195005 | N31: 152825 | P31: 1.283 | Q31: 0.372 | R31: 0.506 | T31: 0.036 | U31: ='AUTO CALCULATION SHEET (2)'!G90*1000 -> 733540 | V31: =(P31*(E31-K31)) -> 22511.621 | W31: =(Q31*(G31-M31)) -> -14.88 | X31: =(R31*(H31-N31)) -> 506 | Y31: =(S31*(I31-O31)) -> 0 | Z31: =T31*(F31-L31) -> 4391.086 | AA31: =V31+W31+X31+Y31+Z31 -> 27393.827 | AB31: =+U31+AA31 -> 760933.83 | AC31: ='AUTO CALCULATION SHEET (2)'!N33 -> 810 | AD31: ='AUTO CALCULATION SHEET (2)'!AB33 -> 54 | AE31: ='AUTO CALCULATION SHEET (2)'!AF33 -> 155 | AF31: ='AUTO CALCULATION SHEET (2)'!AH33 -> 278 | AG31: ='AUTO CALCULATION SHEET (2)'!AQ33 -> 22 | AH31: ='AUTO CALCULATION SHEET (2)'!AX33 -> 105 | AI31: ='AUTO CALCULATION SHEET (2)'!BD33 -> 424 | AJ31: ='AUTO CALCULATION SHEET (2)'!BJ33 -> 0 | AK31: ='AUTO CALCULATION SHEET (2)'!BO33 -> 343 | AL31: ='AUTO CALCULATION SHEET (2)'!BX33 -> 0 | AM31: ='AUTO CALCULATION SHEET (2)'!BY33 -> 13 | AN31: ='AUTO CALCULATION SHEET (2)'!CA33 -> 29 | AO31: ='AUTO CALCULATION SHEET (2)'!CE33 -> 27 | AP31: =SUMPRODUCT(AC31:AO31,$AC$17:$AO$17) -> 591478 | AQ31: ='AUTO CALCULATION SHEET (2)'!CK33 -> 19500 | AR31: =AP31+AQ31 -> 610978 | AS31: =AB31-AR31 -> 149955.83 | AT31: =ROUND((AS31/AB31)*100,2) -> 19.71 | AU31: 0 | AV31: 2 | AW31: 1 | AX31: =AT31-AU31-AV31-AW31 -> 16.71
A32: ='AUTO CALCULATION SHEET (2)'!D34 -> 3 CORE X 400 SQ. MM AL/ARM - WIRE (XLPE) - 33 KV | B32: 4 | C32: PROVISIONAL | D32: 46070 | E32: 316036.08 | F32: 1266186.6 | G32: 194965 | H32: 153825 | I32: 74250 | J32: =$B$1 -> 45992 | K32: 298490 | L32: 1144212 | M32: 195005 | N32: 152825 | O32: 72250 | P32: 3.374 | Q32: 3.229 | R32: 5.736 | S32: 8.76 | T32: 0.164 | U32: ='AUTO CALCULATION SHEET (2)'!G91*1000 -> 3620970 | V32: =(P32*(E32-K32)) -> 59200.474 | W32: =(Q32*(G32-M32)) -> -129.16 | X32: =(R32*(H32-N32)) -> 5736 | Y32: =(S32*(I32-O32)) -> 17520 | Z32: =T32*(F32-L32) -> 20003.836 | AA32: =V32+W32+X32+Y32+Z32 -> 102331.15 | AB32: =+U32+AA32 -> 3723301.1 | AC32: ='AUTO CALCULATION SHEET (2)'!N34 -> 3240 | AD32: ='AUTO CALCULATION SHEET (2)'!AB34 -> 229 | AE32: ='AUTO CALCULATION SHEET (2)'!AF34 -> 618 | AF32: ='AUTO CALCULATION SHEET (2)'!AH34 -> 2674 | AG32: ='AUTO CALCULATION SHEET (2)'!AQ34 -> 0 | AH32: ='AUTO CALCULATION SHEET (2)'!AX34 -> 1792 | AI32: ='AUTO CALCULATION SHEET (2)'!BD34 -> 0 | AJ32: ='AUTO CALCULATION SHEET (2)'!BJ34 -> 7284 | AK32: ='AUTO CALCULATION SHEET (2)'!BO34 -> 1760 | AL32: ='AUTO CALCULATION SHEET (2)'!BX34 -> 1750 | AM32: ='AUTO CALCULATION SHEET (2)'!BY34 -> 58 | AN32: ='AUTO CALCULATION SHEET (2)'!CA34 -> 114 | AO32: ='AUTO CALCULATION SHEET (2)'!CE34 -> 76 | AP32: =SUMPRODUCT(AC32:AO32,$AC$17:$AO$17) -> 2896194 | AQ32: ='AUTO CALCULATION SHEET (2)'!CK34 -> 143000 | AR32: =AP32+AQ32 -> 3039194 | AS32: =AB32-AR32 -> 684107.15 | AT32: =ROUND((AS32/AB32)*100,2) -> 18.37 | AU32: 0 | AV32: 2 | AW32: 1 | AX32: =AT32-AU32-AV32-AW32 -> 15.37
A33: ='AUTO CALCULATION SHEET (2)'!D35 -> 3 CORE X 300 SQ. MM. AL/ARM - WIRE (XLPE) - 33 KV | B33: 4 | C33: PROVISIONAL | D33: 46070 | E33: 316036.08 | F33: 1266186.6 | G33: 194965 | H33: 153825 | I33: 74250 | J33: =$B$1 -> 45992 | K33: 298490 | L33: 1144212 | M33: 195005 | N33: 152825 | O33: 72250 | P33: 2.635 | Q33: 2.919 | R33: 5.029 | S33: 8.187 | T33: 0.15 | U33: ='AUTO CALCULATION SHEET (2)'!G92*1000 -> 3140880 | V33: =(P33*(E33-K33)) -> 46233.921 | W33: =(Q33*(G33-M33)) -> -116.76 | X33: =(R33*(H33-N33)) -> 5029 | Y33: =(S33*(I33-O33)) -> 16374 | Z33: =T33*(F33-L33) -> 18296.192 | AA33: =V33+W33+X33+Y33+Z33 -> 85816.352 | AB33: =+U33+AA33 -> 3226696.4 | AC33: ='AUTO CALCULATION SHEET (2)'!N35 -> 2430 | AD33: ='AUTO CALCULATION SHEET (2)'!AB35 -> 214 | AE33: ='AUTO CALCULATION SHEET (2)'!AF35 -> 564 | AF33: ='AUTO CALCULATION SHEET (2)'!AH35 -> 2438 | AG33: ='AUTO CALCULATION SHEET (2)'!AQ35 -> 0 | AH33: ='AUTO CALCULATION SHEET (2)'!AX35 -> 1594 | AI33: ='AUTO CALCULATION SHEET (2)'!BD35 -> 0 | AJ33: ='AUTO CALCULATION SHEET (2)'!BJ35 -> 6874 | AK33: ='AUTO CALCULATION SHEET (2)'!BO35 -> 1655 | AL33: ='AUTO CALCULATION SHEET (2)'!BX35 -> 1525 | AM33: ='AUTO CALCULATION SHEET (2)'!BY35 -> 38 | AN33: ='AUTO CALCULATION SHEET (2)'!CA35 -> 104 | AO33: ='AUTO CALCULATION SHEET (2)'!CE35 -> 72 | AP33: =SUMPRODUCT(AC33:AO33,$AC$17:$AO$17) -> 2495077 | AQ33: ='AUTO CALCULATION SHEET (2)'!CK35 -> 132600 | AR33: =AP33+AQ33 -> 2627677 | AS33: =AB33-AR33 -> 599019.35 | AT33: =ROUND((AS33/AB33)*100,2) -> 18.56 | AU33: 0 | AV33: 2 | AW33: 1 | AX33: =AT33-AU33-AV33-AW33 -> 15.56
A34: ='AUTO CALCULATION SHEET (2)'!D36 -> 3 CORE X 185 SQ. MM AL/ARM - WIRE (XLPE) - 33 KV | B34: 4 | C34: PROVISIONAL | D34: 46070 | E34: 316036.08 | F34: 1266186.6 | G34: 194965 | H34: 153825 | I34: 74250 | J34: =$B$1 -> 45992 | K34: 298490 | L34: 1144212 | M34: 195005 | N34: 152825 | O34: 72250 | P34: 1.605 | Q34: 2.513 | R34: 4.166 | S34: 7.356 | T34: 0.134 | U34: ='AUTO CALCULATION SHEET (2)'!G93*1000 -> 2498050 | V34: =(P34*(E34-K34)) -> 28161.458 | W34: =(Q34*(G34-M34)) -> -100.52 | X34: =(R34*(H34-N34)) -> 4166 | Y34: =(S34*(I34-O34)) -> 14712 | Z34: =T34*(F34-L34) -> 16344.598 | AA34: =V34+W34+X34+Y34+Z34 -> 63283.536 | AB34: =+U34+AA34 -> 2561333.5 | AC34: ='AUTO CALCULATION SHEET (2)'!N36 -> 1499 | AD34: ='AUTO CALCULATION SHEET (2)'!AB36 -> 191 | AE34: ='AUTO CALCULATION SHEET (2)'!AF36 -> 486 | AF34: ='AUTO CALCULATION SHEET (2)'!AH36 -> 2091 | AG34: ='AUTO CALCULATION SHEET (2)'!AQ36 -> 0 | AH34: ='AUTO CALCULATION SHEET (2)'!AX36 -> 1305 | AI34: ='AUTO CALCULATION SHEET (2)'!BD36 -> 0 | AJ34: ='AUTO CALCULATION SHEET (2)'!BJ36 -> 6155 | AK34: ='AUTO CALCULATION SHEET (2)'!BO36 -> 1480 | AL34: ='AUTO CALCULATION SHEET (2)'!BX36 -> 1224 | AM34: ='AUTO CALCULATION SHEET (2)'!BY36 -> 35 | AN34: ='AUTO CALCULATION SHEET (2)'!CA36 -> 90 | AO34: ='AUTO CALCULATION SHEET (2)'!CE36 -> 65 | AP34: =SUMPRODUCT(AC34:AO34,$AC$17:$AO$17) -> 1985098 | AQ34: ='AUTO CALCULATION SHEET (2)'!CK36 -> 104000 | AR34: =AP34+AQ34 -> 2089098 | AS34: =AB34-AR34 -> 472235.54 | AT34: =ROUND((AS34/AB34)*100,2) -> 18.44 | AU34: 0 | AV34: 2 | AW34: 1 | AX34: =AT34-AU34-AV34-AW34 -> 15.44
A35: ='AUTO CALCULATION SHEET (2)'!D37 -> 3 CORE X 95 SQ. MM. AL/ARM WIRE (XLPE) - 33 KV | B35: 3.15 | C35: PROVISIONAL | D35: 46070 | E35: 316036.08 | F35: 1266186.6 | G35: 194965 | H35: 153825 | I35: 74250 | J35: =$B$1 -> 45992 | K35: 298490 | L35: 1144212 | M35: 195005 | N35: 152825 | O35: 72250 | P35: 0.821 | Q35: 2.071 | R35: 3.367 | S35: 5.437 | T35: 0.117 | U35: ='AUTO CALCULATION SHEET (2)'!G94*1000 -> 1985160 | V35: =(P35*(E35-K35)) -> 14405.332 | W35: =(Q35*(G35-M35)) -> -82.84 | X35: =(R35*(H35-N35)) -> 3367 | Y35: =(S35*(I35-O35)) -> 10874 | Z35: =T35*(F35-L35) -> 14271.029 | AA35: =V35+W35+X35+Y35+Z35 -> 42834.521 | AB35: =+U35+AA35 -> 2027994.5 | AC35: ='AUTO CALCULATION SHEET (2)'!N37 -> 770 | AD35: ='AUTO CALCULATION SHEET (2)'!AB37 -> 167 | AE35: ='AUTO CALCULATION SHEET (2)'!AF37 -> 403 | AF35: ='AUTO CALCULATION SHEET (2)'!AH37 -> 1724 | AG35: ='AUTO CALCULATION SHEET (2)'!AQ37 -> 0 | AH35: ='AUTO CALCULATION SHEET (2)'!AX37 -> 1045 | AI35: ='AUTO CALCULATION SHEET (2)'!BD37 -> 0 | AJ35: ='AUTO CALCULATION SHEET (2)'!BJ37 -> 4262 | AK35: ='AUTO CALCULATION SHEET (2)'!BO37 -> 1296 | AL35: ='AUTO CALCULATION SHEET (2)'!BX37 -> 940 | AM35: ='AUTO CALCULATION SHEET (2)'!BY37 -> 15 | AN35: ='AUTO CALCULATION SHEET (2)'!CA37 -> 75 | AO35: ='AUTO CALCULATION SHEET (2)'!CE37 -> 57 | AP35: =SUMPRODUCT(AC35:AO35,$AC$17:$AO$17) -> 1430882 | AQ35: ='AUTO CALCULATION SHEET (2)'!CK37 -> 104000 | AR35: =AP35+AQ35 -> 1534882 | AS35: =AB35-AR35 -> 493112.52 | AT35: =ROUND((AS35/AB35)*100,2) -> 24.32 | AU35: 0 | AV35: 2 | AW35: 1 | AX35: =AT35-AU35-AV35-AW35 -> 21.32
A36: ='AUTO CALCULATION SHEET (2)'!D38 -> 3 CORE X 70 SQ. MM. AL/ARM - WIRE (XLPE) - 33 KV | B36: 3.15 | C36: PROVISIONAL | D36: 46070 | E36: 316036.08 | F36: 1266186.6 | G36: 194965 | H36: 153825 | I36: 74250 | J36: =$B$1 -> 45992 | K36: 298490 | L36: 1144212 | M36: 195005 | N36: 152825 | O36: 72250 | P36: 0.593 | Q36: 1.916 | R36: 3.219 | S36: 4.809 | T36: 0.111 | U36: ='AUTO CALCULATION SHEET (2)'!G95*1000 -> 1816890 | V36: =(P36*(E36-K36)) -> 10404.825 | W36: =(Q36*(G36-M36)) -> -76.64 | X36: =(R36*(H36-N36)) -> 3219 | Y36: =(S36*(I36-O36)) -> 9618 | Z36: =T36*(F36-L36) -> 13539.182 | AA36: =V36+W36+X36+Y36+Z36 -> 36704.367 | AB36: =+U36+AA36 -> 1853594.4 | AC36: ='AUTO CALCULATION SHEET (2)'!N38 -> 567 | AD36: ='AUTO CALCULATION SHEET (2)'!AB38 -> 161 | AE36: ='AUTO CALCULATION SHEET (2)'!AF38 -> 378 | AF36: ='AUTO CALCULATION SHEET (2)'!AH38 -> 1615 | AG36: ='AUTO CALCULATION SHEET (2)'!AQ38 -> 0 | AH36: ='AUTO CALCULATION SHEET (2)'!AX38 -> 974 | AI36: ='AUTO CALCULATION SHEET (2)'!BD38 -> 0 | AJ36: ='AUTO CALCULATION SHEET (2)'!BJ38 -> 4072 | AK36: ='AUTO CALCULATION SHEET (2)'!BO38 -> 1190 | AL36: ='AUTO CALCULATION SHEET (2)'!BX38 -> 862 | AM36: ='AUTO CALCULATION SHEET (2)'!BY38 -> 15 | AN36: ='AUTO CALCULATION SHEET (2)'!CA38 -> 72 | AO36: ='AUTO CALCULATION SHEET (2)'!CE38 -> 54 | AP36: =SUMPRODUCT(AC36:AO36,$AC$17:$AO$17) -> 1301985 | AQ36: ='AUTO CALCULATION SHEET (2)'!CK38 -> 104000 | AR36: =AP36+AQ36 -> 1405985 | AS36: =AB36-AR36 -> 447609.37 | AT36: =ROUND((AS36/AB36)*100,2) -> 24.15 | AU36: 0 | AV36: 2 | AW36: 1 | AX36: =AT36-AU36-AV36-AW36 -> 21.15
A37: ='AUTO CALCULATION SHEET (2)'!D39 -> 3 CORE X 50 SQ. MM. AL/ARD - WIRE (XLPE) - 33 KV (E) | B37: 3.15 | C37: PROVISIONAL | D37: 46070 | E37: 316036.08 | F37: 1266186.6 | G37: 194965 | H37: 153825 | I37: 74250 | J37: =$B$1 -> 45992 | K37: 298490 | L37: 1144212 | M37: 195005 | N37: 152825 | O37: 72250 | P37: 0.41 | Q37: 1.751 | R37: 2.864 | S37: 4.569 | T37: 0.104 | U37: ='AUTO CALCULATION SHEET (2)'!G96*1000 -> 1843750 | V37: =(P37*(E37-K37)) -> 7193.8928 | W37: =(Q37*(G37-M37)) -> -70.04 | X37: =(R37*(H37-N37)) -> 2864 | Y37: =(S37*(I37-O37)) -> 9138 | Z37: =T37*(F37-L37) -> 12685.359 | AA37: =V37+W37+X37+Y37+Z37 -> 31811.212 | AB37: =+U37+AA37 -> 1875561.2 | AC37: ='AUTO CALCULATION SHEET (2)'!N39 -> 405 | AD37: ='AUTO CALCULATION SHEET (2)'!AB39 -> 153 | AE37: ='AUTO CALCULATION SHEET (2)'!AF39 -> 350 | AF37: ='AUTO CALCULATION SHEET (2)'!AH39 -> 1490 | AG37: ='AUTO CALCULATION SHEET (2)'!AQ39 -> 0 | AH37: ='AUTO CALCULATION SHEET (2)'!AX39 -> 878 | AI37: ='AUTO CALCULATION SHEET (2)'!BD39 -> 0 | AJ37: ='AUTO CALCULATION SHEET (2)'!BJ39 -> 3881 | AK37: ='AUTO CALCULATION SHEET (2)'!BO39 -> 1080 | AL37: ='AUTO CALCULATION SHEET (2)'!BX39 -> 778 | AM37: ='AUTO CALCULATION SHEET (2)'!BY39 -> 6 | AN37: ='AUTO CALCULATION SHEET (2)'!CA39 -> 66 | AO37: ='AUTO CALCULATION SHEET (2)'!CE39 -> 52 | AP37: =SUMPRODUCT(AC37:AO37,$AC$17:$AO$17) -> 1174593 | AQ37: ='AUTO CALCULATION SHEET (2)'!CK39 -> 72800 | AR37: =AP37+AQ37 -> 1247393 | AS37: =AB37-AR37 -> 628168.21 | AT37: =ROUND((AS37/AB37)*100,2) -> 33.49 | AU37: 0 | AV37: 2 | AW37: 1 | AX37: =AT37-AU37-AV37-AW37 -> 30.49
A38: ='AUTO CALCULATION SHEET (2)'!D40 -> 3 CORE X 35 SQ. MM. AL/ARM - WIRE (XLPE) - 33 KV (E) | B38: 3.15 | C38: PROVISIONAL | D38: 46070 | E38: 316036.08 | F38: 1266186.6 | G38: 194965 | H38: 153825 | I38: 74250 | J38: =$B$1 -> 45992 | K38: 298490 | L38: 1144212 | M38: 195005 | N38: 152825 | O38: 72250 | P38: 0.302 | Q38: 1.638 | R38: 2.864 | S38: 2.517 | T38: 0.104 | U38: ='AUTO CALCULATION SHEET (2)'!G97*1000 -> 1843750 | V38: =(P38*(E38-K38)) -> 5298.9162 | W38: =(Q38*(G38-M38)) -> -65.52 | X38: =(R38*(H38-N38)) -> 2864 | Y38: =(S38*(I38-O38)) -> 5034 | Z38: =T38*(F38-L38) -> 12685.359 | AA38: =V38+W38+X38+Y38+Z38 -> 25816.756 | AB38: =+U38+AA38 -> 1869566.8 | AC38: ='AUTO CALCULATION SHEET (2)'!N40 -> 405 | AD38: ='AUTO CALCULATION SHEET (2)'!AB40 -> 153 | AE38: ='AUTO CALCULATION SHEET (2)'!AF40 -> 350 | AF38: ='AUTO CALCULATION SHEET (2)'!AH40 -> 1490 | AG38: ='AUTO CALCULATION SHEET (2)'!AQ40 -> 0 | AH38: ='AUTO CALCULATION SHEET (2)'!AX40 -> 878 | AI38: ='AUTO CALCULATION SHEET (2)'!BD40 -> 0 | AJ38: ='AUTO CALCULATION SHEET (2)'!BJ40 -> 3881 | AK38: ='AUTO CALCULATION SHEET (2)'!BO40 -> 1080 | AL38: ='AUTO CALCULATION SHEET (2)'!BX40 -> 778 | AM38: ='AUTO CALCULATION SHEET (2)'!BY40 -> 6 | AN38: ='AUTO CALCULATION SHEET (2)'!CA40 -> 66 | AO38: ='AUTO CALCULATION SHEET (2)'!CE40 -> 52 | AP38: =SUMPRODUCT(AC38:AO38,$AC$17:$AO$17) -> 1174593 | AQ38: ='AUTO CALCULATION SHEET (2)'!CK40 -> 72800 | AR38: =AP38+AQ38 -> 1247393 | AS38: =AB38-AR38 -> 622173.76 | AT38: =ROUND((AS38/AB38)*100,2) -> 33.28 | AU38: 0 | AV38: 2 | AW38: 1 | AX38: =AT38-AU38-AV38-AW38 -> 30.28
A39: ='AUTO CALCULATION SHEET (2)'!D41 -> 1 CORE X 630 SQ. MM. AL/ARM (XLPE) - 33 KV | B39: 2.5 | C39: PROVISIONAL | D39: 46070 | E39: 316036.08 | F39: 1266186.6 | G39: 194965 | H39: 153825 | J39: =$B$1 -> 45992 | K39: 298490 | L39: 1144212 | M39: 195005 | N39: 152825 | P39: 2.978 | Q39: 1.265 | R39: 1.168 | T39: 0.063 | U39: ='AUTO CALCULATION SHEET (2)'!G98*1000 -> 1496210 | V39: =(P39*(E39-K39)) -> 52252.226 | W39: =(Q39*(G39-M39)) -> -50.6 | X39: =(R39*(H39-N39)) -> 1168 | Y39: =(S39*(I39-O39)) -> 0 | Z39: =T39*(F39-L39) -> 7684.4004 | AA39: =V39+W39+X39+Y39+Z39 -> 61054.027 | AB39: =+U39+AA39 -> 1557264 | AC39: ='AUTO CALCULATION SHEET (2)'!N41 -> 1701 | AD39: ='AUTO CALCULATION SHEET (2)'!AB41 -> 87 | AE39: ='AUTO CALCULATION SHEET (2)'!AF41 -> 243 | AF39: ='AUTO CALCULATION SHEET (2)'!AH41 -> 1056 | AG39: ='AUTO CALCULATION SHEET (2)'!AQ41 -> 36 | AH39: ='AUTO CALCULATION SHEET (2)'!AX41 -> 224 | AI39: ='AUTO CALCULATION SHEET (2)'!BD41 -> 842 | AJ39: ='AUTO CALCULATION SHEET (2)'!BJ41 -> 0 | AK39: ='AUTO CALCULATION SHEET (2)'!BO41 -> 769 | AL39: ='AUTO CALCULATION SHEET (2)'!BX41 -> 0 | AM39: ='AUTO CALCULATION SHEET (2)'!BY41 -> 26 | AN39: ='AUTO CALCULATION SHEET (2)'!CA41 -> 46 | AO39: ='AUTO CALCULATION SHEET (2)'!CE41 -> 42 | AP39: =SUMPRODUCT(AC39:AO39,$AC$17:$AO$17) -> 1228860 | AQ39: ='AUTO CALCULATION SHEET (2)'!CK41 -> 39000 | AR39: =AP39+AQ39 -> 1267860 | AS39: =AB39-AR39 -> 289404.03 | AT39: =ROUND((AS39/AB39)*100,2) -> 18.58 | AU39: 0 | AV39: 2 | AW39: 1 | AX39: =AT39-AU39-AV39-AW39 -> 15.58
A40: ='AUTO CALCULATION SHEET (2)'!D42 -> 1 CORE X 400 SQ. MM. AL/ARM (XLPE) - 33 KV | B40: 2.5 | C40: PROVISIONAL | D40: 46070 | E40: 316036.08 | F40: 1266186.6 | G40: 194965 | H40: 153825 | J40: =$B$1 -> 45992 | K40: 298490 | L40: 1144212 | M40: 195005 | N40: 152825 | P40: 2.046 | Q40: 1.041 | R40: 0.866 | T40: 0.054 | U40: ='AUTO CALCULATION SHEET (2)'!G99*1000 -> 1143490 | V40: =(P40*(E40-K40)) -> 35899.28 | W40: =(Q40*(G40-M40)) -> -41.64 | X40: =(R40*(H40-N40)) -> 866 | Y40: =(S40*(I40-O40)) -> 0 | Z40: =T40*(F40-L40) -> 6586.6289 | AA40: =V40+W40+X40+Y40+Z40 -> 43310.269 | AB40: =+U40+AA40 -> 1186800.3 | AC40: ='AUTO CALCULATION SHEET (2)'!N42 -> 1080 | AD40: ='AUTO CALCULATION SHEET (2)'!AB42 -> 76 | AE40: ='AUTO CALCULATION SHEET (2)'!AF42 -> 206 | AF40: ='AUTO CALCULATION SHEET (2)'!AH42 -> 890 | AG40: ='AUTO CALCULATION SHEET (2)'!AQ42 -> 32 | AH40: ='AUTO CALCULATION SHEET (2)'!AX42 -> 172 | AI40: ='AUTO CALCULATION SHEET (2)'!BD42 -> 731 | AJ40: ='AUTO CALCULATION SHEET (2)'!BJ42 -> 0 | AK40: ='AUTO CALCULATION SHEET (2)'!BO42 -> 604 | AL40: ='AUTO CALCULATION SHEET (2)'!BX42 -> 0 | AM40: ='AUTO CALCULATION SHEET (2)'!BY42 -> 19 | AN40: ='AUTO CALCULATION SHEET (2)'!CA42 -> 38 | AO40: ='AUTO CALCULATION SHEET (2)'!CE42 -> 37 | AP40: =SUMPRODUCT(AC40:AO40,$AC$17:$AO$17) -> 928978 | AQ40: ='AUTO CALCULATION SHEET (2)'!CK42 -> 36400 | AR40: =AP40+AQ40 -> 965378 | AS40: =AB40-AR40 -> 221422.27 | AT40: =ROUND((AS40/AB40)*100,2) -> 18.66 | AU40: 0 | AV40: 2 | AW40: 1 | AX40: =AT40-AU40-AV40-AW40 -> 15.66
A41: ='AUTO CALCULATION SHEET (2)'!D43 -> 1 CORE X 300 SQ. MM. AL/ARM (XLPE) - 33 KV | B41: 2.5 | C41: PROVISIONAL | D41: 46070 | E41: 316036.08 | F41: 1266186.6 | G41: 194965 | H41: 153825 | J41: =$B$1 -> 45992 | K41: 298490 | L41: 1144212 | M41: 195005 | N41: 152825 | P41: 1.753 | Q41: 0.943 | R41: 0.811 | T41: 0.05 | U41: ='AUTO CALCULATION SHEET (2)'!G100*1000 -> 999390 | V41: =(P41*(E41-K41)) -> 30758.278 | W41: =(Q41*(G41-M41)) -> -37.72 | X41: =(R41*(H41-N41)) -> 811 | Y41: =(S41*(I41-O41)) -> 0 | Z41: =T41*(F41-L41) -> 6098.7305 | AA41: =V41+W41+X41+Y41+Z41 -> 37630.289 | AB41: =+U41+AA41 -> 1037020.3 | AC41: ='AUTO CALCULATION SHEET (2)'!N43 -> 810 | AD41: ='AUTO CALCULATION SHEET (2)'!AB43 -> 71 | AE41: ='AUTO CALCULATION SHEET (2)'!AF43 -> 187 | AF41: ='AUTO CALCULATION SHEET (2)'!AH43 -> 810 | AG41: ='AUTO CALCULATION SHEET (2)'!AQ43 -> 30 | AH41: ='AUTO CALCULATION SHEET (2)'!AX43 -> 161 | AI41: ='AUTO CALCULATION SHEET (2)'!BD43 -> 690 | AJ41: ='AUTO CALCULATION SHEET (2)'!BJ43 -> 0 | AK41: ='AUTO CALCULATION SHEET (2)'!BO43 -> 570 | AL41: ='AUTO CALCULATION SHEET (2)'!BX43 -> 0 | AM41: ='AUTO CALCULATION SHEET (2)'!BY43 -> 13 | AN41: ='AUTO CALCULATION SHEET (2)'!CA43 -> 35 | AO41: ='AUTO CALCULATION SHEET (2)'!CE43 -> 35 | AP41: =SUMPRODUCT(AC41:AO41,$AC$17:$AO$17) -> 802756 | AQ41: ='AUTO CALCULATION SHEET (2)'!CK43 -> 33800 | AR41: =AP41+AQ41 -> 836556 | AS41: =AB41-AR41 -> 200464.29 | AT41: =ROUND((AS41/AB41)*100,2) -> 19.33 | AU41: 0 | AV41: 2 | AW41: 1 | AX41: =AT41-AU41-AV41-AW41 -> 16.33

Sheet terms
A1: The quoted prices are on Firm inclusive of packing and forwading but exclusive of GST Statutory levies.
A2: The quoted prices are on VARIABLE basis with PV base Date: DD/MM/YYYY as per "IEEMA", inclusive of packing and forwading but exclusive of GST Statutory levies.
A4: The above prices are quoted on Ex-works basis, where freight will be charged extra.
A5: The above prices are quoted on FOR Destination basis, where freight is included, refer Price offer.
A6: The above prices are quoted on Ex-works+Freight basis.
A8: 20% Advance and Balance against PI (Proforma Invoice) prior to dispatch
A9: 100% against "90 days" LC, where 90 days usance interest will be borne by LPIPL
A10: 100% against "120 days" LC, where 120 days usance interest will be borne by LPIPL
A11: 100% against "45 days" LC, where 45 days usance interest will be borne by LPIPL
A12: 100% against "60 days" LC, where 60 days usance interest will be borne by LPIPL
A13: 100% against "30 days" LC, where 30 days usance interest will be borne by LPIPL
A14: 100% against 60 days PDC from the date of MRC/MRN
... A27: Negotiable
