Workbook

Sheet Sheet1
A1: DOCKET NO. | B1: Base Date | C1: ITEM CODE | D1: PROPOSE ERP ITEM NAME | E1: PROPOSE DRUM TYPE | F1: Insulation Screening (Metallic) | G1: RM RATE (Insulation Screening (Metallic)) | H1: Weight (Insulation Screening (Metallic)) | I1: COST(Insulation Screening (Metallic)) | J1: Conductor | K1: RM RATE(Conductor) | L1: WEIGHT(Conductor) | M1: COST(Conductor) | N1: AL ALLOY | O1: RM RATE(Alu Alloy) | P1: WEIGHT(Alu Alloy) | Q1: COST(Alu Alloy) | R1: Insulation Screening (Non-Metallic) | S1: RM RATE(Insulation Screening (Non-Metallic)) | T1: WEIGHT(Insulation Screening (Non-Metallic)) | U1: COST(Insulation Screening (Non-Metallic)) | V1: Insulation | W1: RM RATE(Insulation) | X1: WEIGHT(Insulation) | Y1: COST(Insulation) | Z1: POLY TAPE | AA1: RM RATE (Poly Tape) | AB1: WEIGHT (Poly Tape) | AC1: COST(Poly Tape) | AD1: Inner Sheath | AE1: RM RATE(Inner Sheath) | AF1: WEIGHT(Inner Sheath) | AG1: COST(Inner Sheath) | AH1: Armouring | AI1: RM RATE(Armouring) | AJ1: WEIGHT(Armouring) | AK1: COST(Armouring) | AL1: Outer Sheath | AM1: RM RATE(Outer Sheath) | AN1: WEIGHT(Outer Sheath) | AO1: COST(Outer Sheath) | AP1: FILLER | AQ1: RM RATE(Filler) | AR1: WEIGHT(Filler) | AS1: COST(Filler) | AT1: GREASE | AU1: RM RATE(Grease) | AV1: WEIGHT(Grease) | AW1: COST(Grease) | AX1: Water swellable Tape | AY1: RM RATE(Water swellable Tape) | AZ1: WEIGHT(Water swellable Tape) | BA1: COST(Water swellable Tape) | BB1: Semi conducting Water Swellable tape | BC1: RM RATE(Semi conducting Water Swellable tape) | BD1: WEIGHT(Semi conducting Water Swellable tape) | BE1: COST(Semi conducting Water Swellable tape) | BF1: SEMICON TAPE | BG1: RM RATE(SEMICON TAPE) | BH1: WEIGHT(SEMICON TAPE) | BI1: COST(SEMICON TAPE) | BJ1: GLASS FIBER TAPE | BK1: RM RATE(GLASS FIBER TAPE) | BL1: WEIGHT(GLASS FIBER TAPE) | BM1: COST(GLASS FIBER TAPE) | BN1: COPPER WIRE 0.8 MM | BO1: RM RATE(COPPER WIRE 0.8 MM) | BP1: WEIGHT(COPPER WIRE 0.8 MM) | BQ1: COST(COPPER WIRE 0.8 MM) | BR1: RUBBERIZED COTTON TAPE | BS1: RM RATE(RUBBERIZED COTTON TAPE) | BT1: WEIGHT(RUBBERIZED COTTON TAPE) | BU1: COST(RUBBERIZED COTTON TAPE) | BV1: Water Tight Compound | BW1: RM RATE(Water Tight Compound) | BX1: WEIGHT(Water Tight Compound) | BY1: COST(Water Tight Compound) | BZ1: DRUM COST PER KM | CA1: TOTAL RM COST | CB1: FIRM % | CC1: FIRM VALUE | CD1: MFG% | CE1: MFG VALUE | CF1: PROF% | CG1: PROFIT VALUE | CH1: 1ST EX-WORKS | CI1: Intt % | CJ1: INTT VALUE | CK1: insp% | CL1: INSP VALUE | CM1: EX-WORKS (PER KM) | CN1: FREIGHT PER KM | CO1: PRICE INCLUDING FREIGHT (PER KM) | CP1: GST % | CQ1: GST VALUE | CR1: PRICE INCLUDING GST & FREIGHT (PER KM) | CS1: QTY | CT1: Unit | CU1: TOTAL PRICE OF FULL QTY (INCLUDING FRIGHT & GST) | CV1: DRUM CODE | CW1: DRUM SIZE (FxbXtx Ft) | CX1: PARTY STANDARD LENGTH (MTR)
A2: ENQ-11516-22-23 | B2: 45170 | C2: FA0100079 | D2: 3 CORE X 150 SQ MM + 1 CORE X 125 SQ MM + 1 CORE X 16 SQ MM (AB CABLES) (BARE) | E2: WOOD | J2: Alumimium | K2: 212 | L2: 1258 | M2: 266696 | N2: Alumimium Alloy | O2: 219 | P2: 338 | Q2: 74022 | T2: 0 | V2: LT-XLPE | W2: 116 | X2: 330 | Y2: 38280 | AB2: 0 | AF2: 0 | AJ2: 0 | AN2: 0 | AR2: 0 | AV2: 0 | AZ2: 0 | BD2: 0 | BH2: 0 | BL2: 0 | BP2: 0 | BT2: 0 | BX2: 0 | BZ2: 17580.08 | CA2: 396578.08 | CH2: 396578.08 | CM2: 396578.08 | CO2: 396578.08 | CR2: 396578.08 | CS2: 34.84 | CT2: KMS | CU2: 13816780 | CV2: MD0100043 | CW2: DRUM - 66 X 29 X 36 X 3 | CX2: 500
A3: ENQ-11516-22-23 | B3: 45170 | C3: FA0100001 | D3: 3 CORE X 120 SQ MM + 1 CORE X 16 SQ MM + 1 CORE X 95 SQ MM (AB CABLES) (BARE) | E3: WOOD | J3: Alumimium | K3: 212 | L3: 1015 | M3: 215180 | N3: Alumimium Alloy | O3: 219 | P3: 256 | Q3: 56064 | T3: 0 | V3: LT-XLPE | W3: 116 | X3: 279 | Y3: 32364 | AB3: 0 | AF3: 0 | AJ3: 0 | AN3: 0 | AR3: 0 | AV3: 0 | AZ3: 0 | BD3: 0 | BH3: 0 | BL3: 0 | BP3: 0 | BT3: 0 | BX3: 0 | BZ3: 7486.04 | CA3: 311094.04 | CH3: 311094.04 | CM3: 311094.04 | CO3: 311094.04 | CR3: 311094.04 | CS3: 60.56 | CT3: KMS | CU3: 18839855 | CV3: MD0100013 | CW3: DRUM - 48 X 14 X 36 X 2.25 | CX3: 500

Sheet AUTO CALCULATION SHEET (2)
A2: KANPUR ELECTRICITY SUPPLY COMPANY LIMITED
A4: TENDER SPECIFICATION NO () | B4: 74/23-24
A5: TENDER DESCRIPTION () | B5: Tender description (brief details of supply): various size of Arial Bunch Cable
A6: Last Date & Time of Submission () | B6: 45236
A7: REVERSE AUCTION | B7: Not mention.
A8: Price () | B8: The prices will be variable and as per CACMAI Based dated 01.09.2023.
A9: Validity () | B9: The bidder’s proposal must remain valid for acceptance for a period of 180 days from the date of opening of bid (Envelope-1) or any other extended date for their receipt or any other extended period consented upon by the bidders. KESCO may ask the bidder to extend the validity period of their bid) and during this period no bidder shall be allowed to withdraw their bid. Any such withdrawal during the said period will entail forfeiture of EMD deposited by the bidder with their bid. The bidders who agree to such extension shall confirm that they maintain the availability of the professional staff nominated in the proposal or in their confirmation of extension of validity of the proposal.
A10: Payment Terms () | B10: Ninety percent of the f.o.r. contract value of the plant in rupees on receipt by the purchaser of the contractor's invoice giving the number and date of railway receipt covering the dispatch of the plant from the Indian port and of the advice note giving case number and contents, together with a certificate by the contractor to the effect that the plant detailed in the said advice note has actually been dispatched under the says railway receipt and that the contract value of the said plant so dispatched is not less than the amount entered in the invoice. Ten percent of the f.o.r. contract value on presentation of the contractor's invoice when each commercially useable section of the plant is completed and the last portion of such section has been dispatched and the whole material has been delivered at the place fixed for delivery and checked at the site of the work within one month of such delivery, whichever is earlier.
A11: Standard length () | B11: The cable shall be supplied in standard drum lengths i.e. 500±5% meters Non-standard lengths of not less than 100 meters is acceptable. Total non-standard length should not exceed 5% of the ordered quantity.
A12: Packing () | B12: The cable shall be supplied on non-returnable wooden drums of heavy standard construction conforming to IS: 10418: 1982 and latest amendment thereof and being suitable for transport by goods train or truck and for storage at site. The wood used for construction of the drums shall be properly seasoned and wood preservative shall be applied to the entire drum.
A13: Technical Specification
N15: =Sheet1!J1 -> Conductor | S15: AL ALLOY | U15: Insulation Screening (Metallic) | AC15: Insulation Screening (Non-Metallic) | AE15: Insulation | AK15: POLY TAPE | AL15: Inner Sheath | AS15: Armouring | BC15: Outer Sheath | BM15: FILLER | BN15: GREASE | BO15: Water swellable Tape | BP15: Semi conducting Water Swellable tape | BQ15: SEMICON TAPE | BR15: GLASS FIBER TAPE | BS15: COPPER WIRE 0.8 MM | BT15: RUBBERIZED COTTON TAPE | BU15: Water Tight Compound | BZ15: DRUM COST PER KM | CA15: TOTAL RM COST | CB15: EXTRA CONSUMPTION | CC15: EXTRA CONSUMPTION VALUE
A16: DOCKET NO. | B16: =Sheet1!B1 -> Base Date | C16: ITEM CODE | D16: PROPOSE ERP ITEM NAME | E16: EX-WORKS (PER KM) | F16: FREIGHT PER KM | G16: PRICE INCLUDING FREIGHT (PER KM) | H16: GST % | I16: GST VALUE | J16: PRICE INCLUDING GST & FREIGHT (PER KM) | K16: QTY | L16: Unit | M16: TOTAL PRICE OF FULL QTY (INCLUDING FRIGHT & GST) | N16: Alumimium | O16: Alumimium ALLOY | P16: Copper | Q16: Flexible Copper | R16: Galvanized steel wire | S16: Alumimium | T16: Alumimium ALLOY | U16: Coper tape - 0.1 mm | V16: Copper Tape - 0.03 mm | W16: Copper Tape - 0.035 mm | X16: Copper Tape - 0.04 mm | Y16: Copper Tape - 0.045 mm | Z16: Copper Tape - 0.050 mm | AA16: Copper Tape - 0.060 mm | AB16: Copper Tape - 0.075 mm(DOUBLE) | AC16: Extruded semiconductive | AD16: Extruded Semiconductive(Stripable) | AE16: HT-XLPE | AF16: LT-XLPE | AG16: TR XLPE | AH16: Type A PVC | AI16: Type C PVC (HR) | AJ16: XLPE | AK16: POLY TAPE | AL16: FR PVC Type ST-1 | AM16: FR PVC Type ST-2 | AN16: FRLSH PVC Type ST-2 | AO16: PVC Type ST-1 | AP16: PVC Type ST-1-PRESSURE EXTRUDED | AQ16: PVC Type ST-2 | AR16: PVC Type ST-2-PRESSURE EXTRUDED | AS16: ACSR CORE WIRE | AT16: ACSR DOG STEEL WIRE | AU16: Aluminium Flat Strip | AV16: Aluminium Round Wire | AW16: Double Steel Tape | AX16: Galvanised Steel Flat Strip | AY16: Galvanised Steel Flat Strip (Double) | AZ16: Galvanised Steel Flat Strip-B | BA16: Galvanised Steel Round Wire | BB16: Galvanised Steel Round Wire (Double) | BC16: FR PVC Type ST-1 | BD16: FR PVC Type ST-2 | BE16: FRLSH PVC Type ST-1 | BF16: FRLSH PVC Type ST-2 | BG16: PE, ST-3 | BH16: PE, ST-7 | BI16: PVC Type ST-1 | BJ16: PVC Type ST-2 | BK16: PVC Type ST-2-PRESSURE EXTRUDED | BL16: UV & Track Resistant XLPE | BM16: FILLER | BN16: Grease | BO16: Water swellable Tape | BP16: Semi conducting Water Swellable tape | BQ16: SEMICON TAPE | BR16: GLASS FIBER TAPE | BS16: COPPER WIRE 0.8 MM | BT16: RUBBERIZED COTTON TAPE | BU16: Water Tight Compound | BV16: =Sheet1!E1 -> PROPOSE DRUM TYPE | BW16: =Sheet1!CV1 -> DRUM CODE | BX16: =Sheet1!CW1 -> DRUM SIZE (FxbXtx Ft) | BY16: =Sheet1!CX1 -> PARTY STANDARD LENGTH (MTR) | CD16: MFG% | CE16: MFG VALUE | CF16: PROF% | CG16: PROFIT VALUE | CH16: 1ST EX-WORKS | CI16: Intt % | CJ16: INTT VALUE | CK16: insp% | CL16: INSP VALUE
N17: 212 | O17: =+IFERROR(VLOOKUP($O$16,Sheet1!J:L,2,0),0) -> 0 | P17: =+IFERROR(VLOOKUP($P$16,Sheet1!J:M,2,0),0) -> 0 | Q17: =+IFERROR(VLOOKUP($Q$16,Sheet1!J:M,2,0),0) -> 0 | R17: =+IFERROR(VLOOKUP($R$16,Sheet1!J:M,2,0),0) -> 0 | S17: =+IFERROR(VLOOKUP($S$16,Sheet1!N:Q,2,0),0) -> 0 | T17: =N17+7 -> 219 | U17: =+IFERROR(VLOOKUP($U$16,Sheet1!F:I,2,0),0) -> 0 | V17: =+IFERROR(VLOOKUP($V$16,Sheet1!F:I,2,0),0) -> 0 | W17: =+IFERROR(VLOOKUP($W$16,Sheet1!F:I,2,0),0) -> 0 | X17: =+IFERROR(VLOOKUP($X$16,Sheet1!F:I,2,0),0) -> 0 | Y17: =+IFERROR(VLOOKUP($Y$16,Sheet1!F:I,2,0),0) -> 0 | Z17: =+IFERROR(VLOOKUP($Z$16,Sheet1!F:I,2,0),0) -> 0 | AA17: =+IFERROR(VLOOKUP($AA$16,Sheet1!F:I,2,0),0) -> 0 | AB17: =+IFERROR(VLOOKUP($AB$16,Sheet1!F:I,2,0),0) -> 0 | AC17: =+IFERROR(VLOOKUP($AC$16,Sheet1!R:U,2,0),0) -> 0 | AD17: =+IFERROR(VLOOKUP($AD$16,Sheet1!R:U,2,0),0) -> 0 | AE17: =+IFERROR(VLOOKUP($AE$16,Sheet1!V:Y,2,0),0) -> 0 | AF17: =+IFERROR(VLOOKUP($AF$16,Sheet1!V:Y,2,0),0) -> 116 | AG17: =+IFERROR(VLOOKUP($AG$16,Sheet1!V:Y,2,0),0) -> 0 | AH17: =+IFERROR(VLOOKUP($AH$16,Sheet1!V:Y,2,0),0) -> 0 | AI17: =+IFERROR(VLOOKUP($AI$16,Sheet1!V:Y,2,0),0) -> 0 | AJ17: =+IFERROR(VLOOKUP($AJ$16,Sheet1!V:Y,2,0),0) -> 0 | AK17: =+IFERROR(VLOOKUP($AK$16,Sheet1!Z2:AA840,2,0),0) -> 0 | AL17: =+IFERROR(VLOOKUP($AL$16,Sheet1!AD2:AG840,2,0),0) -> 0 | AM17: =+IFERROR(VLOOKUP($AM$16,Sheet1!AD2:AG840,2,0),0) -> 0 | AN17: =+IFERROR(VLOOKUP($AN$16,Sheet1!AD2:AG840,2,0),0) -> 0 | AO17: =+IFERROR(VLOOKUP($AO$16,Sheet1!AD2:AG840,2,0),0) -> 0 | AP17: =+IFERROR(VLOOKUP($AP$16,Sheet1!AD2:AG840,2,0),0) -> 0 | AQ17: =+IFERROR(VLOOKUP($AQ$16,Sheet1!AD2:AG840,2,0),0) -> 0 | AR17: =+IFERROR(VLOOKUP($AR$16,Sheet1!AD2:AG840,2,0),0) -> 0 | AS17: =+IFERROR(VLOOKUP($AS$16,Sheet1!AH2:AK840,2,0),0) -> 0 | AT17: =+IFERROR(VLOOKUP($AT$16,Sheet1!AH2:AK840,2,0),0) -> 0 | AU17: =+IFERROR(VLOOKUP($AU$16,Sheet1!AH2:AK840,2,0),0) -> 0 | AV17: =+IFERROR(VLOOKUP($AV$16,Sheet1!AH2:AK840,2,0),0) -> 0 | AW17: =+IFERROR(VLOOKUP($AW$16,Sheet1!AH2:AK840,2,0),0) -> 0 | AX17: =+IFERROR(VLOOKUP($AX$16,Sheet1!AH2:AK840,2,0),0) -> 0 | AY17: =+IFERROR(VLOOKUP($AY$16,Sheet1!AH2:AK840,2,0),0) -> 0 | AZ17: =+IFERROR(VLOOKUP($AZ$16,Sheet1!AH2:AK840,2,0),0) -> 0 | BA17: =+IFERROR(VLOOKUP($BA$16,Sheet1!AH2:AK840,2,0),0) -> 0 | BB17: =+IFERROR(VLOOKUP($BB$16,Sheet1!AH2:AK840,2,0),0) -> 0 | BC17: =+IFERROR(VLOOKUP($BC$16,Sheet1!AL2:AO840,2,0),0) -> 0 | BD17: =+IFERROR(VLOOKUP($BD$16,Sheet1!AL2:AO840,2,0),0) -> 0 | BE17: =+IFERROR(VLOOKUP($BE$16,Sheet1!AL2:AO840,2,0),0) -> 0 | BF17: =+IFERROR(VLOOKUP($BF$16,Sheet1!AL2:AO840,2,0),0) -> 0 | BG17: =+IFERROR(VLOOKUP($BG$16,Sheet1!AL2:AO840,2,0),0) -> 0 | BH17: =+IFERROR(VLOOKUP($BH$16,Sheet1!AL2:AO840,2,0),0) -> 0 | BI17: =+IFERROR(VLOOKUP($BI$16,Sheet1!AL2:AO840,2,0),0) -> 0 | BJ17: =+IFERROR(VLOOKUP($BJ$16,Sheet1!AL2:AO840,2,0),0) -> 0 | BK17: =+IFERROR(VLOOKUP($BK$16,Sheet1!AL2:AO840,2,0),0) -> 0 | BL17: =+IFERROR(VLOOKUP($BL$16,Sheet1!AL2:AO840,2,0),0) -> 0 | BM17: =+IFERROR(VLOOKUP($BM$16,Sheet1!AP2:AS840,2,0),0) -> 0 | BN17: =+IFERROR(VLOOKUP($BN$16,Sheet1!AT2:AW840,2,0),0) -> 0 | BO17: =+IFERROR(VLOOKUP($BO$16,Sheet1!AX2:BA840,2,0),0) -> 0 | BP17: =+IFERROR(VLOOKUP($BP$16,Sheet1!BB2:BE840,2,0),0) -> 0 | BQ17: =+IFERROR(VLOOKUP($BQ$16,Sheet1!BF2:BI840,2,0),0) -> 0 | BR17: =+IFERROR(VLOOKUP($BR$16,Sheet1!BJ2:BM840,2,0),0) -> 0 | BS17: =+IFERROR(VLOOKUP($BS$16,Sheet1!BN2:BQ840,2,0),0) -> 0 | BT17: =+IFERROR(VLOOKUP($BT$16,Sheet1!BR2:BU840,2,0),0) -> 0 | BU17: =+IFERROR(VLOOKUP($BU$16,Sheet1!BV2:BY840,2,0),0) -> 0
A18: =Sheet1!A3 -> ENQ-11516-22-23 | B18: =Sheet1!B3 -> 45170 | C18: =Sheet1!C3 -> FA0100001 | D18: =Sheet1!D3 -> 3 CORE X 120 SQ MM + 1 CORE X 16 SQ MM + 1 CORE X 95 SQ MM (AB CABLES) (BARE) | E18: =CH18+CJ18+CL18 -> 367356.23 | F18: =ROUNDUP(M22,0) -> 5549 | G18: =E18+F18 -> 372905.23 | H18: 0.18 | I18: =G18*H18 -> 67122.942 | J18: =G18+I18 -> 440028.17 | K18: =Sheet1!CS3 -> 60.56 | L18: =Sheet1!CT3 -> KMS | M18: =J18*K18 -> 26648106 | N18: 1018 | O18: =+IFERROR(VLOOKUP($O$16,Sheet1!J3:L3,3,0),0) -> 0 | P18: =+IFERROR(VLOOKUP($P$16,Sheet1!J3:M3,3,0),0) -> 0 | Q18: =+IFERROR(VLOOKUP($Q$16,Sheet1!J3:M3,3,0),0) -> 0 | R18: =+IFERROR(VLOOKUP($R$16,Sheet1!J3:M3,3,0),0) -> 0 | S18: =+IFERROR(VLOOKUP($S$16,Sheet1!N3:Q3,3,0),0) -> 0 | T18: 260 | U18: =+IFERROR(VLOOKUP($U$16,Sheet1!F3:I3,3,0),0) -> 0 | V18: =+IFERROR(VLOOKUP($V$16,Sheet1!F3:I3,3,0),0) -> 0 | W18: =+IFERROR(VLOOKUP($W$16,Sheet1!F3:I3,3,0),0) -> 0 | X18: =+IFERROR(VLOOKUP($X$16,Sheet1!F3:I3,3,0),0) -> 0 | Y18: =+IFERROR(VLOOKUP($Y$16,Sheet1!F3:I3,3,0),0) -> 0 | Z18: =+IFERROR(VLOOKUP($Z$16,Sheet1!F3:I3,3,0),0) -> 0 | AA18: =+IFERROR(VLOOKUP($AA$16,Sheet1!F3:I3,3,0),0) -> 0 | AB18: =+IFERROR(VLOOKUP($AB$16,Sheet1!F3:I3,3,0),0) -> 0 | AC18: =+IFERROR(VLOOKUP($AC$16,Sheet1!R3:U3,3,0),0) -> 0 | AD18: =+IFERROR(VLOOKUP($AD$16,Sheet1!R3:U3,2,0),0) -> 0 | AE18: =+IFERROR(VLOOKUP($AE$16,Sheet1!V3:Y3,3,0),0) -> 0 | AF18: 232 | AG18: =+IFERROR(VLOOKUP($AG$16,Sheet1!V3:Y3,3,0),0) -> 0 | AH18: =+IFERROR(VLOOKUP($AH$16,Sheet1!V3:Y3,3,0),0) -> 0 | AI18: =+IFERROR(VLOOKUP($AI$16,Sheet1!V3:Y3,3,0),0) -> 0 | AJ18: =+IFERROR(VLOOKUP($AJ$16,Sheet1!V3:Y3,3,0),0) -> 0 | AK18: =+IFERROR(VLOOKUP($AK$16,Sheet1!Z3:AB3,3,0),0) -> 0 | AL18: =+IFERROR(VLOOKUP($AL$16,Sheet1!AD3:AG3,3,0),0) -> 0 | AM18: =+IFERROR(VLOOKUP($AM$16,Sheet1!AD3:AG3,3,0),0) -> 0 | AN18: =+IFERROR(VLOOKUP($AN$16,Sheet1!AD3:AG3,3,0),0) -> 0 | AO18: =+IFERROR(VLOOKUP($AO$16,Sheet1!AD3:AG3,3,0),0) -> 0 | AP18: =+IFERROR(VLOOKUP($AP$16,Sheet1!AD3:AG3,3,0),0) -> 0 | AQ18: =+IFERROR(VLOOKUP($AQ$16,Sheet1!AD3:AG3,3,0),0) -> 0 | AR18: =+IFERROR(VLOOKUP($AR$16,Sheet1!AD3:AG3,3,0),0) -> 0 | AS18: =+IFERROR(VLOOKUP($AS$16,Sheet1!AH3:AK3,3,0),0) -> 0 | AT18: =+IFERROR(VLOOKUP($AT$16,Sheet1!AH3:AK3,3,0),0) -> 0 | AU18: =+IFERROR(VLOOKUP($AU$16,Sheet1!AH3:AK3,3,0),0) -> 0 | AV18: =+IFERROR(VLOOKUP($AV$16,Sheet1!AH3:AK3,3,0),0) -> 0 | AW18: =+IFERROR(VLOOKUP($AW$16,Sheet1!AH3:AK3,3,0),0) -> 0 | AX18: =+IFERROR(VLOOKUP($AX$16,Sheet1!AH3:AK3,3,0),0) -> 0 | AY18: =+IFERROR(VLOOKUP($AY$16,Sheet1!AH3:AK3,3,0),0) -> 0 | AZ18: =+IFERROR(VLOOKUP($AZ$16,Sheet1!AH3:AK3,3,0),0) -> 0 | BA18: =+IFERROR(VLOOKUP($BA$16,Sheet1!AH3:AK3,3,0),0) -> 0 | BB18: =+IFERROR(VLOOKUP($BB$16,Sheet1!AH3:AK3,3,0),0) -> 0 | BC18: =+IFERROR(VLOOKUP($BC$16,Sheet1!AL3:AO3,3,0),0) -> 0 | BD18: =+IFERROR(VLOOKUP($BD$16,Sheet1!AL3:AO3,3,0),0) -> 0 | BE18: =+IFERROR(VLOOKUP($BE$16,Sheet1!AL3:AO3,3,0),0) -> 0 | BF18: =+IFERROR(VLOOKUP($BF$16,Sheet1!AL3:AO3,3,0),0) -> 0 | BG18: =+IFERROR(VLOOKUP($BG$16,Sheet1!AL3:AO3,3,0),0) -> 0 | BH18: =+IFERROR(VLOOKUP($BH$16,Sheet1!AL3:AO3,3,0),0) -> 0 | BI18: =+IFERROR(VLOOKUP($BI$16,Sheet1!AL3:AO3,3,0),0) -> 0 | BJ18: =+IFERROR(VLOOKUP($BJ$16,Sheet1!AL3:AO3,3,0),0) -> 0 | BK18: =+IFERROR(VLOOKUP($BK$16,Sheet1!AL3:AO3,3,0),0) -> 0 | BL18: =+IFERROR(VLOOKUP($BL$16,Sheet1!AL3:AO3,3,0),0) -> 0 | BM18: =+IFERROR(VLOOKUP($BM$16,Sheet1!AP3:AS3,3,0),0) -> 0 | BN18: =+IFERROR(VLOOKUP($BN$16,Sheet1!AT3:AW3,3,0),0) -> 0 | BO18: =+IFERROR(VLOOKUP($BO$16,Sheet1!AX3:BA3,3,0),0) -> 0 | BP18: =+IFERROR(VLOOKUP($BP$16,Sheet1!BB3:BE3,3,0),0) -> 0 | BQ18: =+IFERROR(VLOOKUP($BQ$16,Sheet1!BF3:BI3,3,0),0) -> 0 | BR18: =+IFERROR(VLOOKUP($BR$16,Sheet1!BJ3:BM3,3,0),0) -> 0 | BS18: =+IFERROR(VLOOKUP($BS$16,Sheet1!BN3:BQ3,3,0),0) -> 0 | BT18: =+IFERROR(VLOOKUP($BT$16,Sheet1!BR3:BU3,3,0),0) -> 0 | BU18: =+IFERROR(VLOOKUP($BU$16,Sheet1!BV3:BY3,3,0),0) -> 0 | BV18: =Sheet1!E3 -> WOOD | BW18: =Sheet1!CV3 -> MD0100013 | BX18: =Sheet1!CW3 -> DRUM - 48 X 14 X 36 X 2.25 | BY18: =Sheet1!CX3 -> 500 | BZ18: =Sheet1!BZ3 -> 7486.04 | CA18: =SUMPRODUCT($N$17:$BU$17,N18:BU18)+BZ18 -> 307154.04 | CB18: =Sheet1!CB3 -> 0 | CC18: =CA18*CB18 -> 0 | CD18: 0.15 | CE18: =CA18*CD18 -> 46073.106 | CF18: 0 | CG18: =CA18*CF18 -> 0 | CH18: =CA18+CC18+CE18+CG18 -> 353227.15 | CI18: 0.02 | CJ18: =CH18*CI18 -> 7064.5429 | CK18: 0.02 | CL18: =CH18*CK18 -> 7064.5429
A19: =Sheet1!A2 -> ENQ-11516-22-23 | B19: =Sheet1!B2 -> 45170 | C19: =Sheet1!C2 -> FA0100079 | D19: =Sheet1!D2 -> 3 CORE X 150 SQ MM + 1 CORE X 125 SQ MM + 1 CORE X 16 SQ MM (AB CABLES) (BARE) | E19: =CH19+CJ19+CL19 -> 473525.2 | F19: =ROUNDUP(M23,0) -> 12400 | G19: =E19+F19 -> 485925.2 | H19: 0.18 | I19: =G19*H19 -> 87466.536 | J19: =G19+I19 -> 573391.74 | K19: =Sheet1!CS2 -> 34.84 | L19: =Sheet1!CT2 -> KMS | M19: =J19*K19 -> 19976968 | N19: 1261 | O19: =+IFERROR(VLOOKUP($O$16,Sheet1!J2:L2,3,0),0) -> 0 | P19: =+IFERROR(VLOOKUP($P$16,Sheet1!J2:M2,3,0),0) -> 0 | Q19: =+IFERROR(VLOOKUP($Q$16,Sheet1!J2:M2,3,0),0) -> 0 | R19: =+IFERROR(VLOOKUP($R$16,Sheet1!J2:M2,3,0),0) -> 0 | S19: =+IFERROR(VLOOKUP($S$16,Sheet1!N2:Q2,3,0),0) -> 0 | T19: 348 | U19: =+IFERROR(VLOOKUP($U$16,Sheet1!F2:I2,3,0),0) -> 0 | V19: =+IFERROR(VLOOKUP($V$16,Sheet1!F2:I2,3,0),0) -> 0 | W19: =+IFERROR(VLOOKUP($W$16,Sheet1!F2:I2,3,0),0) -> 0 | X19: =+IFERROR(VLOOKUP($X$16,Sheet1!F2:I2,3,0),0) -> 0 | Y19: =+IFERROR(VLOOKUP($Y$16,Sheet1!F2:I2,3,0),0) -> 0 | Z19: =+IFERROR(VLOOKUP($Z$16,Sheet1!F2:I2,3,0),0) -> 0 | AA19: =+IFERROR(VLOOKUP($AA$16,Sheet1!F2:I2,3,0),0) -> 0 | AB19: =+IFERROR(VLOOKUP($AB$16,Sheet1!F2:I2,3,0),0) -> 0 | AC19: =+IFERROR(VLOOKUP($AC$16,Sheet1!R2:U2,3,0),0) -> 0 | AD19: =+IFERROR(VLOOKUP($AD$16,Sheet1!R2:U2,2,0),0) -> 0 | AE19: =+IFERROR(VLOOKUP($AE$16,Sheet1!V2:Y2,3,0),0) -> 0 | AF19: 300 | AG19: =+IFERROR(VLOOKUP($AG$16,Sheet1!V2:Y2,3,0),0) -> 0 | AH19: =+IFERROR(VLOOKUP($AH$16,Sheet1!V2:Y2,3,0),0) -> 0 | AI19: =+IFERROR(VLOOKUP($AI$16,Sheet1!V2:Y2,3,0),0) -> 0 | AJ19: =+IFERROR(VLOOKUP($AJ$16,Sheet1!V2:Y2,3,0),0) -> 0 | AK19: =+IFERROR(VLOOKUP($AK$16,Sheet1!Z2:AB2,3,0),0) -> 0 | AL19: =+IFERROR(VLOOKUP($AL$16,Sheet1!AD2:AG2,3,0),0) -> 0 | AM19: =+IFERROR(VLOOKUP($AM$16,Sheet1!AD2:AG2,3,0),0) -> 0 | AN19: =+IFERROR(VLOOKUP($AN$16,Sheet1!AD2:AG2,3,0),0) -> 0 | AO19: =+IFERROR(VLOOKUP($AO$16,Sheet1!AD2:AG2,3,0),0) -> 0 | AP19: =+IFERROR(VLOOKUP($AP$16,Sheet1!AD2:AG2,3,0),0) -> 0 | AQ19: =+IFERROR(VLOOKUP($AQ$16,Sheet1!AD2:AG2,3,0),0) -> 0 | AR19: =+IFERROR(VLOOKUP($AR$16,Sheet1!AD2:AG2,3,0),0) -> 0 | AS19: =+IFERROR(VLOOKUP($AS$16,Sheet1!AH2:AK2,3,0),0) -> 0 | AT19: =+IFERROR(VLOOKUP($AT$16,Sheet1!AH2:AK2,3,0),0) -> 0 | AU19: =+IFERROR(VLOOKUP($AU$16,Sheet1!AH2:AK2,3,0),0) -> 0 | AV19: =+IFERROR(VLOOKUP($AV$16,Sheet1!AH2:AK2,3,0),0) -> 0 | AW19: =+IFERROR(VLOOKUP($AW$16,Sheet1!AH2:AK2,3,0),0) -> 0 | AX19: =+IFERROR(VLOOKUP($AX$16,Sheet1!AH2:AK2,3,0),0) -> 0 | AY19: =+IFERROR(VLOOKUP($AY$16,Sheet1!AH2:AK2,3,0),0) -> 0 | AZ19: =+IFERROR(VLOOKUP($AZ$16,Sheet1!AH2:AK2,3,0),0) -> 0 | BA19: =+IFERROR(VLOOKUP($BA$16,Sheet1!AH2:AK2,3,0),0) -> 0 | BB19: =+IFERROR(VLOOKUP($BB$16,Sheet1!AH2:AK2,3,0),0) -> 0 | BC19: =+IFERROR(VLOOKUP($BC$16,Sheet1!AL2:AO2,3,0),0) -> 0 | BD19: =+IFERROR(VLOOKUP($BD$16,Sheet1!AL2:AO2,3,0),0) -> 0 | BE19: =+IFERROR(VLOOKUP($BE$16,Sheet1!AL2:AO2,3,0),0) -> 0 | BF19: =+IFERROR(VLOOKUP($BF$16,Sheet1!AL2:AO2,3,0),0) -> 0 | BG19: =+IFERROR(VLOOKUP($BG$16,Sheet1!AL2:AO2,3,0),0) -> 0 | BH19: =+IFERROR(VLOOKUP($BH$16,Sheet1!AL2:AO2,3,0),0) -> 0 | BI19: =+IFERROR(VLOOKUP($BI$16,Sheet1!AL2:AO2,3,0),0) -> 0 | BJ19: =+IFERROR(VLOOKUP($BJ$16,Sheet1!AL2:AO2,3,0),0) -> 0 | BK19: =+IFERROR(VLOOKUP($BK$16,Sheet1!AL2:AO2,3,0),0) -> 0 | BL19: =+IFERROR(VLOOKUP($BL$16,Sheet1!AL2:AO2,3,0),0) -> 0 | BM19: =+IFERROR(VLOOKUP($BM$16,Sheet1!AP2:AS2,3,0),0) -> 0 | BN19: =+IFERROR(VLOOKUP($BN$16,Sheet1!AT2:AW2,3,0),0) -> 0 | BO19: =+IFERROR(VLOOKUP($BO$16,Sheet1!AX2:BA2,3,0),0) -> 0 | BP19: =+IFERROR(VLOOKUP($BP$16,Sheet1!BB2:BE2,3,0),0) -> 0 | BQ19: =+IFERROR(VLOOKUP($BQ$16,Sheet1!BF2:BI2,3,0),0) -> 0 | BR19: =+IFERROR(VLOOKUP($BR$16,Sheet1!BJ2:BM2,3,0),0) -> 0 | BS19: =+IFERROR(VLOOKUP($BS$16,Sheet1!BN2:BQ2,3,0),0) -> 0 | BT19: =+IFERROR(VLOOKUP($BT$16,Sheet1!BR2:BU2,3,0),0) -> 0 | BU19: =+IFERROR(VLOOKUP($BU$16,Sheet1!BV2:BY2,3,0),0) -> 0 | BV19: =Sheet1!E2 -> WOOD | BW19: =Sheet1!CV2 -> MD0100043 | BX19: =Sheet1!CW2 -> DRUM - 66 X 29 X 36 X 3 | BY19: =Sheet1!CX2 -> 500 | BZ19: =Sheet1!BZ2 -> 17580.08 | CA19: =SUMPRODUCT($N$17:$BU$17,N19:BU19)+BZ19 -> 395924.08 | CB19: =Sheet1!CB2 -> 0 | CC19: =CA19*CB19 -> 0 | CD19: 0.15 | CE19: =CA19*CD19 -> 59388.612 | CF19: 0 | CG19: =CA19*CF19 -> 0 | CH19: =CA19+CC19+CE19+CG19 -> 455312.69 | CI19: 0.02 | CJ19: =CH19*CI19 -> 9106.2538 | CK19: 0.02 | CL19: =CH19*CK19 -> 9106.2538
E21: Order Quantity | F21: Stnd Length | G21: Truck type | H21: Fare of one truck | I21: No of Drum in one truck | J21: Total length in one Truck | K21: No of Truck | L21: Total Freight | M21: Freight per KM
D22: =D18 -> 3 CORE X 120 SQ MM + 1 CORE X 16 SQ MM + 1 CORE X 95 SQ MM (AB CABLES) (BARE) | E22: =K18 -> 60.56 | F22: 0.5 | G22: 16 MT | H22: 48000 | I22: 18 | J22: =F22*I22 -> 9 | K22: =ROUNDUP((E22/J22),0) -> 7 | L22: =M22*E22 -> 336000 | M22: =(H22*K22)/E22 -> 5548.2166
D23: =D19 -> 3 CORE X 150 SQ MM + 1 CORE X 125 SQ MM + 1 CORE X 16 SQ MM (AB CABLES) (BARE) | E23: =K19 -> 34.84 | F23: 0.5 | G23: 16 MT | H23: 48000 | I23: 8 | J23: =F23*I23 -> 4 | K23: =ROUNDUP((E23/J23),0) -> 9 | L23: =M23*E23 -> 432000 | M23: =(H23*K23)/E23 -> 12399.541

Sheet LT ABC
A1: ='AUTO CALCULATION SHEET (2)'!A2:R2 -> KANPUR ELECTRICITY SUPPLY COMPANY LIMITED
A2: P = Po + AIph*n* (Al – Alo)+ AIm (Al – Alo)+ AIsl (Al – Alo)+CCFAIph*n*(CC-CCo)+CCFAIm(CC-CCo)+ CCFAIsl(CC-CCo)
A3: Base Date | B3: 45170
A4: PV Terms()
A5: PV FORMULA (IEEMA)
A6: P = Po + AIph*n* (Al – Alo)+ AIm (Al – Alo)+ AIsl (Al – Alo)+CCFAIph*n*(CC-CCo)+CCFAIm(CC-CCo)+ CCFAIsl(CC-CCo)
A9: n | B9: No. of Phase Conductor
A10: Alph | B10: Aluminium factor for phase conductor
A11: Alm | B11: Aluminium factor for messenger conductor
A12: CCFAIph | B12: XLPE factor for phase conductor
A13: CCFAIm | B13: XLPE factor for messenger conductor (For bare messenger,XLPE factor CCFAIm=0)
A14: PV TERMS (page 68) | B14: The prices will be variable and as per CACMAI Based dated 01.09.2023. | J14: CONSIDER IEEMA FOR PV CALCULATION
A17: Item | B17: Ex-Work
A18: ='AUTO CALCULATION SHEET (2)'!D18 -> 3 CORE X 120 SQ MM + 1 CORE X 16 SQ MM + 1 CORE X 95 SQ MM (AB CABLES) (BARE) | B18: ='AUTO CALCULATION SHEET (2)'!E18 -> 367356.23
A19: ='AUTO CALCULATION SHEET (2)'!D19 -> 3 CORE X 150 SQ MM + 1 CORE X 125 SQ MM + 1 CORE X 16 SQ MM (AB CABLES) (BARE) | B19: ='AUTO CALCULATION SHEET (2)'!E19 -> 473525.2
A21: Item | B21: Calculation part | C21: Date of Inspection | D21: Applicable Date | H21: BASE DATE | L21: FACTORS | T21: Ex-Work Po | U21: PVC of Al | V21: PVC of AlM | W21: PVC of Alsl | X21: PVC of CCFAIph | Y21: PVC of CCFAIm | Z21: PVC of CCFAIsl | AA21: PV/PKM | AB21: Billing Price/PKM | AC21: VALUE ADDITION CALCULATION WITH RESPECT TO PERCENTAGE
D22: Date | E22: Al | G22: CC | H22: Date | I22: Alo | K22: Cco
L23: n | M23: Alph | N23: Alm | O23: Alsl | P23: CCFAIph | Q23: CCFAIm | R23: CCFAIsl | S23: CCFAlph | AC23: Al @ | AD23: alloy | AE23: LT-XLPE | AF23: RMC | AG23: Drum | AH23: RMC+Drum | AI23: VA | AJ23: Groos VA% | AK23: Mfg % | AL23: Int % | AM23: Ins% | AN23: Net VA %
AC24: 219 | AD24: =AC24+7 -> 226 | AE24: 99
A25: =A18 -> 3 CORE X 120 SQ MM + 1 CORE X 16 SQ MM + 1 CORE X 95 SQ MM (AB CABLES) (BARE) | C25: PROVISIONAL | D25: 45233 | E25: 212174.68 | G25: 148904 | H25: =$B$3 -> 45170 | I25: 211371 | K25: 148904 | L25: 3 | M25: 0.346 | N25: 0.274 | O25: 0.046 | P25: 0.073 | R25: 0.024 | T25: =B18 -> 367356.23 | U25: =(M25*L25*(E25-I25)) -> 834.21984 | V25: =N25*(E25-I25) -> 220.20832 | W25: =O25*(E25-I25) -> 36.96928 | X25: =(P25*L25*(G25-K25)) -> 0 | Y25: =Q25*(G25-K25) -> 0 | Z25: =R25*(G25-K25) -> 0 | AA25: =U25+V25+W25+X25+Y25+Z25 -> 1091.3974 | AB25: =T25+AA25 -> 368447.63 | AC25: ='AUTO CALCULATION SHEET (2)'!N18 -> 1018 | AD25: ='AUTO CALCULATION SHEET (2)'!T18 -> 260 | AE25: ='AUTO CALCULATION SHEET (2)'!AF18 -> 232 | AF25: =SUMPRODUCT($AC$24:$AE$24,AC25:AE25) -> 304670 | AG25: ='AUTO CALCULATION SHEET (2)'!BZ18 -> 7486.04 | AH25: =+AF25+AG25 -> 312156.04 | AI25: =+AB25-AH25 -> 56291.589 | AJ25: =+AI25/AH25 -> 0.18033157 | AL25: 0.02 | AM25: 0.02 | AN25: =+AJ25-(AK25+AL25+AM25) -> 0.14033157
A26: =A19 -> 3 CORE X 150 SQ MM + 1 CORE X 125 SQ MM + 1 CORE X 16 SQ MM (AB CABLES) (BARE) | C26: PROVISIONAL | D26: 45233 | E26: 212174.68 | G26: 148904 | H26: =$B$3 -> 45170 | I26: 211371 | K26: 148904 | L26: 3 | M26: 0.425 | N26: 0.346 | O26: 0.046 | P26: 0.085 | R26: 0.024 | T26: =B19 -> 473525.2 | U26: =(M26*L26*(E26-I26)) -> 1024.692 | V26: =N26*(E26-I26) -> 278.07328 | W26: =O26*(E26-I26) -> 36.96928 | X26: =(P26*L26*(G26-K26)) -> 0 | Y26: =Q26*(G26-K26) -> 0 | Z26: =R26*(G26-K26) -> 0 | AA26: =U26+V26+W26+X26+Y26+Z26 -> 1339.7346 | AB26: =T26+AA26 -> 474864.93 | AC26: ='AUTO CALCULATION SHEET (2)'!N19 -> 1261 | AD26: ='AUTO CALCULATION SHEET (2)'!T19 -> 348 | AE26: ='AUTO CALCULATION SHEET (2)'!AF19 -> 300 | AF26: =SUMPRODUCT($AC$24:$AE$24,AC26:AE26) -> 384507 | AG26: ='AUTO CALCULATION SHEET (2)'!BZ19 -> 17580.08 | AH26: =+AF26+AG26 -> 402087.08 | AI26: =+AB26-AH26 -> 72777.854 | AJ26: =+AI26/AH26 -> 0.18100023 | AL26: 0.02 | AM26: 0.02 | AN26: =+AJ26-(AK26+AL26+AM26) -> 0.14100023
