Workbook

Sheet Sheet1
A1: DOCKET NO. | B1: Base Date | C1: ITEM CODE | D1: PROPOSE ERP ITEM NAME | E1: PROPOSE DRUM TYPE | F1: Insulation Screening (Metallic) | G1: RM RATE (Insulation Screening (Metallic)) | H1: Weight (Insulation Screening (Metallic)) | I1: COST(Insulation Screening (Metallic)) | J1: Conductor | K1: RM RATE(Conductor) | L1: WEIGHT(Conductor) | M1: COST(Conductor) | N1: AL ALLOY | O1: RM RATE(Alu Alloy) | P1: WEIGHT(Alu Alloy) | Q1: COST(Alu Alloy) | R1: Insulation Screening (Non-Metallic) | S1: RM RATE(Insulation Screening (Non-Metallic)) | T1: WEIGHT(Insulation Screening (Non-Metallic)) | U1: COST(Insulation Screening (Non-Metallic)) | V1: Insulation | W1: RM RATE(Insulation) | X1: WEIGHT(Insulation) | Y1: COST(Insulation) | Z1: POLY TAPE | AA1: RM RATE (Poly Tape) | AB1: WEIGHT (Poly Tape) | AC1: COST(Poly Tape) | AD1: Inner Sheath | AE1: RM RATE(Inner Sheath) | AF1: WEIGHT(Inner Sheath) | AG1: COST(Inner Sheath) | AH1: Armouring | AI1: RM RATE(Armouring) | AJ1: WEIGHT(Armouring) | AK1: COST(Armouring) | AL1: Outer Sheath | AM1: RM RATE(Outer Sheath) | AN1: WEIGHT(Outer Sheath) | AO1: COST(Outer Sheath) | AP1: FILLER | AQ1: RM RATE(Filler) | AR1: WEIGHT(Filler) | AS1: COST(Filler) | AT1: GREASE | AU1: RM RATE(Grease) | AV1: WEIGHT(Grease) | AW1: COST(Grease) | AX1: Water swellable Tape | AY1: RM RATE(Water swellable Tape) | AZ1: WEIGHT(Water swellable Tape) | BA1: COST(Water swellable Tape) | BB1: Semi conducting Water Swellable tape | BC1: RM RATE(Semi conducting Water Swellable tape) | BD1: WEIGHT(Semi conducting Water Swellable tape) | BE1: COST(Semi conducting Water Swellable tape) | BF1: SEMICON TAPE | BG1: RM RATE(SEMICON TAPE) | BH1: WEIGHT(SEMICON TAPE) | BI1: COST(SEMICON TAPE) | BJ1: GLASS FIBER TAPE | BK1: RM RATE(GLASS FIBER TAPE) | BL1: WEIGHT(GLASS FIBER TAPE) | BM1: COST(GLASS FIBER TAPE) | BN1: COPPER WIRE 0.8 MM | BO1: RM RATE(COPPER WIRE 0.8 MM) | BP1: WEIGHT(COPPER WIRE 0.8 MM) | BQ1: COST(COPPER WIRE 0.8 MM) | BR1: RUBBERIZED COTTON TAPE | BS1: RM RATE(RUBBERIZED COTTON TAPE) | BT1: WEIGHT(RUBBERIZED COTTON TAPE) | BU1: COST(RUBBERIZED COTTON TAPE) | BV1: Water Tight Compound | BW1: RM RATE(Water Tight Compound) | BX1: WEIGHT(Water Tight Compound) | BY1: COST(Water Tight Compound) | BZ1: DRUM COST PER KM | CA1: TOTAL RM COST | CB1: FIRM % | CC1: FIRM VALUE | CD1: MFG% | CE1: MFG VALUE | CF1: PROF% | CG1: PROFIT VALUE | CH1: 1ST EX-WORKS | CI1: Intt % | CJ1: INTT VALUE | CK1: insp% | CL1: INSP VALUE | CM1: EX-WORKS (PER KM) | CN1: FREIGHT PER KM | CO1: PRICE INCLUDING FREIGHT (PER KM) | CP1: GST % | CQ1: GST VALUE | CR1: PRICE INCLUDING GST & FREIGHT (PER KM) | CS1: QTY | CT1: Unit | CU1: TOTAL PRICE OF FULL QTY (INCLUDING FRIGHT & GST) | CV1: DRUM CODE | CW1: DRUM SIZE (FxbXtx Ft) | CX1: PARTY STANDARD LENGTH (MTR)
A2: ENQ-12472-22-23 | B2: 45366 | C2: FA2900029 | D2: COVERED CONDUCTOR - 1 CORE X 55 SQ. MM. (AAAC) - 11 KV | E2: WOOD | J2: Alumimium Alloy | K2: 223 | R2: Extruded Semiconductive | S2: 195 | V2: HT-XLPE | W2: 142 | AL2: UV & Track Resistant XLPE | AM2: 219 | BV2: Water Tight Compound | BW2: 220 | BZ2: 2305.4 | CA2: 2305.4 | CH2: 2305.4 | CM2: 2305.4 | CO2: 2305.4 | CP2: 0.18 | CQ2: 414.97 | CR2: 2720.37 | CS2: 5 | CT2: KMS | CU2: 13602 | CV2: MD0100005 | CW2: DRUM - 36 X 14 X 23 X 2 | CX2: 1000
A3: ENQ-12472-22-23 | B3: 45366 | C3: FA2900034 | D3: COVERED CONDUCTOR - 1 CORE X 80 SQ. MM. (AAAC) - 11 KV | E3: WOOD | J3: Alumimium Alloy | K3: 223 | R3: Extruded Semiconductive | S3: 195 | V3: HT-XLPE | W3: 142 | AL3: UV & Track Resistant XLPE | AM3: 219 | BV3: Water Tight Compound | BW3: 220 | BZ3: 3257.88 | CA3: 3257.88 | CH3: 3257.88 | CM3: 3257.88 | CO3: 3257.88 | CP3: 0.18 | CQ3: 586.42 | CR3: 3844.3 | CS3: 6 | CT3: KMS | CU3: 23066 | CV3: MD0100085 | CW3: DRUM - 43 X 15 X 28 X 2.25 | CX3: 1000
A4: ENQ-12472-22-23 | B4: 45366 | C4: FA2900008 | D4: COVERED CONDUCTOR - 1 CORE X 99 SQ. MM. (AAAC) - 33 KV | E4: WOOD | J4: Alumimium Alloy | K4: 223 | R4: Extruded Semiconductive | S4: 195 | V4: HT-XLPE | W4: 142 | AL4: UV & Track Resistant XLPE | AM4: 219 | BV4: Water Tight Compound | BW4: 220 | BZ4: 3658.54 | CA4: 3658.54 | CH4: 3658.54 | CM4: 3658.54 | CO4: 3658.54 | CP4: 0.18 | CQ4: 658.54 | CR4: 4317.08 | CS4: 41 | CT4: KMS | CU4: 177000 | CV4: MD0100015 | CW4: DRUM - 48 X 20 X 28 X 2.25 | CX4: 1000
A5: ENQ-12472-22-23 | B5: 45366 | C5: FA2900014 | D5: COVERED CONDUCTOR - 1 CORE x 150 SQ. MM. (XLPE) (AAAC) - 33 KV | E5: WOOD | J5: Alumimium Alloy | K5: 223 | R5: Extruded Semiconductive | S5: 195 | V5: HT-XLPE | W5: 142 | AL5: UV & Track Resistant XLPE | AM5: 219 | BV5: Water Tight Compound | BW5: 220 | BZ5: 4716.61 | CA5: 4716.61 | CH5: 4716.61 | CM5: 4716.61 | CO5: 4716.61 | CP5: 0.18 | CQ5: 848.99 | CR5: 5565.6 | CS5: 119.467 | CT5: KMS | CU5: 664906 | CV5: MD0100099 | CW5: DRUM - 48 X 14 X 36 X 2.25 (LOMBU) | CX5: 1000
A6: ENQ-12472-22-23 | B6: 45366 | C6: FA2900032 | D6: COVERED CONDUCTOR - 1 CORE X 232 SQ. MM. (AAAC) - 33 KV | E6: WOOD | J6: Alumimium Alloy | K6: 223 | R6: Extruded Semiconductive | S6: 195 | V6: HT-XLPE | W6: 142 | AL6: UV & Track Resistant XLPE | AM6: 219 | BV6: Water Tight Compound | BW6: 220 | BZ6: 6378.74 | CA6: 6378.74 | CH6: 6378.74 | CM6: 6378.74 | CO6: 6378.74 | CP6: 0.18 | CQ6: 1148.17 | CR6: 7526.91 | CS6: 150 | CT6: KMS | CU6: 1129037 | CV6: MD0100019 | CW6: DRUM - 54 X 24 X 32 X 3 | CX6: 1000
A7: ENQ-12472-22-23 | B7: 45366 | C7: FA2900004 | D7: COVERED CONDUCTOR - 1 CORE x 100 SQ. MM. (AAAC) - 11KV | E7: WOOD | J7: Alumimium Alloy | K7: 223 | N7: Alumimium Alloy | O7: 223 | R7: Extruded Semiconductive | S7: 195 | V7: HT-XLPE | W7: 142 | AL7: UV & Track Resistant XLPE | AM7: 219 | BV7: Water Tight Compound | BW7: 220 | BZ7: 3542.03 | CA7: 3542.03 | CH7: 3542.03 | CM7: 3542.03 | CO7: 3542.03 | CP7: 0.18 | CQ7: 637.57 | CR7: 4179.6 | CS7: 321.17 | CT7: KMS | CU7: 1342361 | CV7: MD0100075 | CW7: DRUM - 42 X 15 X 23 X 2 (LOMBU) | CX7: 1000

Sheet AUTO CALCULATION SHEET (2)
A2: Tata Power Odisha DISCOMs
A4: TENDER SPECIFICATION NO () | B4: TPCODL/CCG/23-24/1000000578
A5: TENDER DESCRIPTION () | B5: Rate Contract for Supply of Covered Conductor of various sizes.
A6: Last Date & Time of Submission () | B6: 18/03/2024 [17:00 Hrs.]
A7: REVERSE AUCTION | B7: No. of bidders allowed to participate in RA process shall be: Total No. of bidders on whom tender would be split PLUS 2 more bidders.
A8: Price () | B8: Price will be fixed and FIRM during the contractual period.
A9: Validity () | B9: Bids shall remain valid for 180 days from the due date of submission of the bid. Notwithstanding clause above, CCG may solicit the Bidder’s consent to an extension of the Period of Bid Validity. The request and responses thereto shall be made in writing.
A10: Delivery Period () | B10: Delivery Period shall be 60 Days from date of receipt of release order / CAT-A GTP approval, whichever is later.
A11: Payment Terms () | B11: 100% payment within 90 days of submission of error-free Invoice complete in all respects. However, for MSME the payment cycle shall be 45 days.
A12: Standard length () | B12: Standard Packing length - 1000 (+/- 5%) as per PO terms
A13: Packing () | B13: Supplier shall ensure that all the equipment covered under this specification shall be prepared for rail/road transport and be packed in such a manner so as to protect the equipment from damage in transit. The material used for packing shall be environmentally friendly. The bidder shall provide instructions regarding handling and storage precautions to be taken at site. The Conductor shall be wound on wooden/STEEL drums and packed in line with requirements of IS 10418- 1982. The ends of the Conductor shall be sealed by means of non-hygroscopic sealing material. Heat or cold Shrinkable end caps with sealant shall be used for effectively sealing the end terminals of the covered conductor. The inner diameter range of cap shall be such that it shall tightly fit to the covered conductors to prevent moisture ingress.
A14: Technical Specification
N16: =Sheet1!J1 -> Conductor | S16: AL ALLOY | U16: Insulation Screening (Metallic) | AC16: Insulation Screening (Non-Metallic) | AE16: Insulation | AK16: POLY TAPE | AL16: Inner Sheath | AS16: Armouring | BC16: Outer Sheath | BM16: FILLER | BN16: GREASE | BO16: Water swellable Tape | BP16: Semi conducting Water Swellable tape | BQ16: SEMICON TAPE | BR16: GLASS FIBER TAPE | BS16: COPPER WIRE 0.8 MM | BT16: RUBBERIZED COTTON TAPE | BU16: Water Tight Compound | BZ16: DRUM COST PER KM | CA16: TOTAL RM COST | CB16: EXTRA CONSUMPTION | CC16: EXTRA CONSUMPTION VALUE
A17: DOCKET NO. | B17: =Sheet1!B1 -> Base Date | C17: ITEM CODE | D17: PROPOSE ERP ITEM NAME | E17: EX-WORKS (PER KM) | F17: FREIGHT PER KM | G17: PRICE INCLUDING FREIGHT (PER KM) | H17: GST % | I17: GST VALUE | J17: PRICE INCLUDING GST & FREIGHT (PER KM) | K17: QTY | L17: Unit | M17: TOTAL PRICE OF FULL QTY (INCLUDING FRIGHT & GST) | N17: Alumimium | O17: Alumimium ALLOY | P17: Copper | Q17: Flexible Copper | R17: Galvanized steel wire | S17: Alumimium | T17: Alumimium ALLOY | U17: Coper tape - 0.1 mm | V17: Copper Tape - 0.03 mm | W17: Copper Tape - 0.035 mm | X17: Copper Tape - 0.04 mm | Y17: Copper Tape - 0.045 mm | Z17: Copper Tape - 0.050 mm | AA17: Copper Tape - 0.060 mm | AB17: Copper Tape - 0.075 mm(DOUBLE) | AC17: Extruded semiconductive | AD17: Extruded Semiconductive(Stripable) | AE17: HT-XLPE | AF17: LT-XLPE | AG17: TR XLPE | AH17: Type A PVC | AI17: Type C PVC (HR) | AJ17: XLPE | AK17: POLY TAPE | AL17: FR PVC Type ST-1 | AM17: FR PVC Type ST-2 | AN17: FRLSH PVC Type ST-2 | AO17: PVC Type ST-1 | AP17: PVC Type ST-1-PRESSURE EXTRUDED | AQ17: PVC Type ST-2 | AR17: PVC Type ST-2-PRESSURE EXTRUDED | AS17: ACSR CORE WIRE | AT17: ACSR DOG STEEL WIRE | AU17: Aluminium Flat Strip | AV17: Aluminium Round Wire | AW17: Double Steel Tape | AX17: Galvanised Steel Flat Strip | AY17: Galvanised Steel Flat Strip (Double) | AZ17: Galvanised Steel Flat Strip-B | BA17: Galvanised Steel Round Wire | BB17: Galvanised Steel Round Wire (Double) | BC17: FR PVC Type ST-1 | BD17: FR PVC Type ST-2 | BE17: FRLSH PVC Type ST-1 | BF17: FRLSH PVC Type ST-2 | BG17: PE, ST-3 | BH17: PE, ST-7 | BI17: PVC Type ST-1 | BJ17: PVC Type ST-2 | BK17: PVC Type ST-2-PRESSURE EXTRUDED | BL17: UV & Track Resistant XLPE | BM17: FILLER | BN17: Grease | BO17: Water swellable Tape | BP17: Semi conducting Water Swellable tape | BQ17: SEMICON TAPE | BR17: GLASS FIBER TAPE | BS17: COPPER WIRE 0.8 MM | BT17: RUBBERIZED COTTON TAPE | BU17: Water Tight Compound | BV17: =Sheet1!E1 -> PROPOSE DRUM TYPE | BW17: =Sheet1!CV1 -> DRUM CODE | BX17: =Sheet1!CW1 -> DRUM SIZE (FxbXtx Ft) | BY17: =Sheet1!CX1 -> PARTY STANDARD LENGTH (MTR) | CD17: MFG% | CE17: MFG VALUE | CF17: PROF% | CG17: PROFIT VALUE | CH17: 1ST EX-WORKS | CI17: Intt % | CJ17: INTT VALUE | CK17: insp% | CL17: INSP VALUE
N18: =+IFERROR(VLOOKUP($N$17,Sheet1!J:L,2,0),0) -> 0 | P18: =+IFERROR(VLOOKUP($P$17,Sheet1!J:M,2,0),0) -> 0 | Q18: =+IFERROR(VLOOKUP($Q$17,Sheet1!J:M,2,0),0) -> 0 | R18: =+IFERROR(VLOOKUP($R$17,Sheet1!J:M,2,0),0) -> 0 | S18: =+IFERROR(VLOOKUP($S$17,Sheet1!N:Q,2,0),0) -> 0 | T18: =+IFERROR(VLOOKUP($T$17,Sheet1!N:O,2,0),0) -> 223 | U18: =+IFERROR(VLOOKUP($U$17,Sheet1!F:I,2,0),0) -> 0 | V18: =+IFERROR(VLOOKUP($V$17,Sheet1!F:I,2,0),0) -> 0 | W18: =+IFERROR(VLOOKUP($W$17,Sheet1!F:I,2,0),0) -> 0 | X18: =+IFERROR(VLOOKUP($X$17,Sheet1!F:I,2,0),0) -> 0 | Y18: =+IFERROR(VLOOKUP($Y$17,Sheet1!F:I,2,0),0) -> 0 | Z18: =+IFERROR(VLOOKUP($Z$17,Sheet1!F:I,2,0),0) -> 0 | AA18: =+IFERROR(VLOOKUP($AA$17,Sheet1!F:I,2,0),0) -> 0 | AB18: =+IFERROR(VLOOKUP($AB$17,Sheet1!F:I,2,0),0) -> 0 | AC18: =+IFERROR(VLOOKUP($AC$17,Sheet1!R:U,2,0),0) -> 195 | AD18: =+IFERROR(VLOOKUP($AD$17,Sheet1!R:U,2,0),0) -> 0 | AE18: =+IFERROR(VLOOKUP($AE$17,Sheet1!V:Y,2,0),0) -> 142 | AF18: =+IFERROR(VLOOKUP($AF$17,Sheet1!V:Y,2,0),0) -> 0 | AG18: =+IFERROR(VLOOKUP($AG$17,Sheet1!V:Y,2,0),0) -> 0 | AH18: =+IFERROR(VLOOKUP($AH$17,Sheet1!V:Y,2,0),0) -> 0 | AI18: =+IFERROR(VLOOKUP($AI$17,Sheet1!V:Y,2,0),0) -> 0 | AJ18: =+IFERROR(VLOOKUP($AJ$17,Sheet1!V:Y,2,0),0) -> 0 | AK18: =+IFERROR(VLOOKUP($AK$17,Sheet1!Z2:AA840,2,0),0) -> 0 | AL18: =+IFERROR(VLOOKUP($AL$17,Sheet1!AD2:AG840,2,0),0) -> 0 | AM18: =+IFERROR(VLOOKUP($AM$17,Sheet1!AD2:AG840,2,0),0) -> 0 | AN18: =+IFERROR(VLOOKUP($AN$17,Sheet1!AD2:AG840,2,0),0) -> 0 | AO18: =+IFERROR(VLOOKUP($AO$17,Sheet1!AD2:AG840,2,0),0) -> 0 | AP18: =+IFERROR(VLOOKUP($AP$17,Sheet1!AD2:AG840,2,0),0) -> 0 | AQ18: =+IFERROR(VLOOKUP($AQ$17,Sheet1!AD2:AG840,2,0),0) -> 0 | AR18: =+IFERROR(VLOOKUP($AR$17,Sheet1!AD2:AG840,2,0),0) -> 0 | AS18: =+IFERROR(VLOOKUP($AS$17,Sheet1!AH2:AK840,2,0),0) -> 0 | AT18: =+IFERROR(VLOOKUP($AT$17,Sheet1!AH2:AK840,2,0),0) -> 0 | AU18: =+IFERROR(VLOOKUP($AU$17,Sheet1!AH2:AK840,2,0),0) -> 0 | AV18: =+IFERROR(VLOOKUP($AV$17,Sheet1!AH2:AK840,2,0),0) -> 0 | AW18: =+IFERROR(VLOOKUP($AW$17,Sheet1!AH2:AK840,2,0),0) -> 0 | AX18: =+IFERROR(VLOOKUP($AX$17,Sheet1!AH2:AK840,2,0),0) -> 0 | AY18: =+IFERROR(VLOOKUP($AY$17,Sheet1!AH2:AK840,2,0),0) -> 0 | AZ18: =+IFERROR(VLOOKUP($AZ$17,Sheet1!AH2:AK840,2,0),0) -> 0 | BA18: =+IFERROR(VLOOKUP($BA$17,Sheet1!AH2:AK840,2,0),0) -> 0 | BB18: =+IFERROR(VLOOKUP($BB$17,Sheet1!AH2:AK840,2,0),0) -> 0 | BC18: =+IFERROR(VLOOKUP($BC$17,Sheet1!AL2:AO840,2,0),0) -> 0 | BD18: =+IFERROR(VLOOKUP($BD$17,Sheet1!AL2:AO840,2,0),0) -> 0 | BE18: =+IFERROR(VLOOKUP($BE$17,Sheet1!AL2:AO840,2,0),0) -> 0 | BF18: =+IFERROR(VLOOKUP($BF$17,Sheet1!AL2:AO840,2,0),0) -> 0 | BG18: =+IFERROR(VLOOKUP($BG$17,Sheet1!AL2:AO840,2,0),0) -> 0 | BH18: =+IFERROR(VLOOKUP($BH$17,Sheet1!AL2:AO840,2,0),0) -> 0 | BI18: =+IFERROR(VLOOKUP($BI$17,Sheet1!AL2:AO840,2,0),0) -> 0 | BJ18: =+IFERROR(VLOOKUP($BJ$17,Sheet1!AL2:AO840,2,0),0) -> 0 | BK18: =+IFERROR(VLOOKUP($BK$17,Sheet1!AL2:AO840,2,0),0) -> 0 | BL18: =+IFERROR(VLOOKUP($BL$17,Sheet1!AL2:AO840,2,0),0) -> 219 | BM18: =+IFERROR(VLOOKUP($BM$17,Sheet1!AP2:AS840,2,0),0) -> 0 | BN18: =+IFERROR(VLOOKUP($BN$17,Sheet1!AT2:AW840,2,0),0) -> 0 | BO18: =+IFERROR(VLOOKUP($BO$17,Sheet1!AX2:BA840,2,0),0) -> 0 | BP18: =+IFERROR(VLOOKUP($BP$17,Sheet1!BB2:BE840,2,0),0) -> 0 | BQ18: =+IFERROR(VLOOKUP($BQ$17,Sheet1!BF2:BI840,2,0),0) -> 0 | BR18: =+IFERROR(VLOOKUP($BR$17,Sheet1!BJ2:BM840,2,0),0) -> 0 | BS18: =+IFERROR(VLOOKUP($BS$17,Sheet1!BN2:BQ840,2,0),0) -> 0 | BT18: =+IFERROR(VLOOKUP($BT$17,Sheet1!BR2:BU840,2,0),0) -> 0 | BU18: =+IFERROR(VLOOKUP($BU$17,Sheet1!BV2:BY840,2,0),0) -> 220
A19: =Sheet1!A2 -> ENQ-12472-22-23 | B19: =Sheet1!B2 -> 45366 | C19: =Sheet1!C2 -> FA2900029 | D19: =Sheet1!D2 -> COVERED CONDUCTOR - 1 CORE X 55 SQ. MM. (AAAC) - 11 KV | E19: =CH19+CJ19+CL19 -> 96194.134 | F19: =ROUNDUP(M27,0) -> 5400 | G19: =E19+F19 -> 101594.13 | H19: =Sheet1!CP2 -> 0.18 | I19: =G19*H19 -> 18286.944 | J19: =G19+I19 -> 119881.08 | K19: =Sheet1!CS2 -> 5 | L19: =Sheet1!CT2 -> KMS | M19: =J19*K19 -> 599405.39 | N19: =+IFERROR(VLOOKUP($N$17,Sheet1!J2:L2,3,0),0) -> 0 | O19: =+IFERROR(VLOOKUP($O$17,Sheet1!J2:L2,3,0),0) -> 0 | P19: =+IFERROR(VLOOKUP($P$17,Sheet1!J2:M2,3,0),0) -> 0 | Q19: =+IFERROR(VLOOKUP($Q$17,Sheet1!J2:M2,3,0),0) -> 0 | R19: =+IFERROR(VLOOKUP($R$17,Sheet1!J2:M2,3,0),0) -> 0 | S19: =+IFERROR(VLOOKUP($S$17,Sheet1!N2:Q2,3,0),0) -> 0 | T19: 150 | U19: =+IFERROR(VLOOKUP($U$17,Sheet1!F2:I2,3,0),0) -> 0 | V19: =+IFERROR(VLOOKUP($V$17,Sheet1!F2:I2,3,0),0) -> 0 | W19: =+IFERROR(VLOOKUP($W$17,Sheet1!F2:I2,3,0),0) -> 0 | X19: =+IFERROR(VLOOKUP($X$17,Sheet1!F2:I2,3,0),0) -> 0 | Y19: =+IFERROR(VLOOKUP($Y$17,Sheet1!F2:I2,3,0),0) -> 0 | Z19: =+IFERROR(VLOOKUP($Z$17,Sheet1!F2:I2,3,0),0) -> 0 | AA19: =+IFERROR(VLOOKUP($AA$17,Sheet1!F2:I2,3,0),0) -> 0 | AB19: =+IFERROR(VLOOKUP($AB$17,Sheet1!F2:I2,3,0),0) -> 0 | AC19: 35 | AD19: =+IFERROR(VLOOKUP($AD$17,Sheet1!R2:U2,2,0),0) -> 0 | AE19: 45 | AF19: =+IFERROR(VLOOKUP($AF$17,Sheet1!V2:Y2,3,0),0) -> 0 | AG19: =+IFERROR(VLOOKUP($AG$17,Sheet1!V2:Y2,3,0),0) -> 0 | AH19: =+IFERROR(VLOOKUP($AH$17,Sheet1!V2:Y2,3,0),0) -> 0 | AI19: =+IFERROR(VLOOKUP($AI$17,Sheet1!V2:Y2,3,0),0) -> 0 | AJ19: =+IFERROR(VLOOKUP($AJ$17,Sheet1!V2:Y2,3,0),0) -> 0 | AK19: =+IFERROR(VLOOKUP($AK$17,Sheet1!Z2:AB2,3,0),0) -> 0 | AL19: =+IFERROR(VLOOKUP($AL$17,Sheet1!AD2:AG2,3,0),0) -> 0 | AM19: =+IFERROR(VLOOKUP($AM$17,Sheet1!AD2:AG2,3,0),0) -> 0 | AN19: =+IFERROR(VLOOKUP($AN$17,Sheet1!AD2:AG2,3,0),0) -> 0 | AO19: =+IFERROR(VLOOKUP($AO$17,Sheet1!AD2:AG2,3,0),0) -> 0 | AP19: =+IFERROR(VLOOKUP($AP$17,Sheet1!AD2:AG2,3,0),0) -> 0 | AQ19: =+IFERROR(VLOOKUP($AQ$17,Sheet1!AD2:AG2,3,0),0) -> 0 | AR19: =+IFERROR(VLOOKUP($AR$17,Sheet1!AD2:AG2,3,0),0) -> 0 | AS19: =+IFERROR(VLOOKUP($AS$17,Sheet1!AH2:AK2,3,0),0) -> 0 | AT19: =+IFERROR(VLOOKUP($AT$17,Sheet1!AH2:AK2,3,0),0) -> 0 | AU19: =+IFERROR(VLOOKUP($AU$17,Sheet1!AH2:AK2,3,0),0) -> 0 | AV19: =+IFERROR(VLOOKUP($AV$17,Sheet1!AH2:AK2,3,0),0) -> 0 | AW19: =+IFERROR(VLOOKUP($AW$17,Sheet1!AH2:AK2,3,0),0) -> 0 | AX19: =+IFERROR(VLOOKUP($AX$17,Sheet1!AH2:AK2,3,0),0) -> 0 | AY19: =+IFERROR(VLOOKUP($AY$17,Sheet1!AH2:AK2,3,0),0) -> 0 | AZ19: =+IFERROR(VLOOKUP($AZ$17,Sheet1!AH2:AK2,3,0),0) -> 0 | BA19: =+IFERROR(VLOOKUP($BA$17,Sheet1!AH2:AK2,3,0),0) -> 0 | BB19: =+IFERROR(VLOOKUP($BB$17,Sheet1!AH2:AK2,3,0),0) -> 0 | BC19: =+IFERROR(VLOOKUP($BC$17,Sheet1!AL2:AO2,3,0),0) -> 0 | BD19: =+IFERROR(VLOOKUP($BD$17,Sheet1!AL2:AO2,3,0),0) -> 0 | BE19: =+IFERROR(VLOOKUP($BE$17,Sheet1!AL2:AO2,3,0),0) -> 0 | BF19: =+IFERROR(VLOOKUP($BF$17,Sheet1!AL2:AO2,3,0),0) -> 0 | BG19: =+IFERROR(VLOOKUP($BG$17,Sheet1!AL2:AO2,3,0),0) -> 0 | BH19: =+IFERROR(VLOOKUP($BH$17,Sheet1!AL2:AO2,3,0),0) -> 0 | BI19: =+IFERROR(VLOOKUP($BI$17,Sheet1!AL2:AO2,3,0),0) -> 0 | BJ19: =+IFERROR(VLOOKUP($BJ$17,Sheet1!AL2:AO2,3,0),0) -> 0 | BK19: =+IFERROR(VLOOKUP($BK$17,Sheet1!AL2:AO2,3,0),0) -> 0 | BL19: 63 | BM19: =+IFERROR(VLOOKUP($BM$17,Sheet1!AP2:AS2,3,0),0) -> 0 | BN19: =+IFERROR(VLOOKUP($BN$17,Sheet1!AT2:AW2,3,0),0) -> 0 | BO19: =+IFERROR(VLOOKUP($BO$17,Sheet1!AX2:BA2,3,0),0) -> 0 | BP19: =+IFERROR(VLOOKUP($BP$17,Sheet1!BB2:BE2,3,0),0) -> 0 | BQ19: =+IFERROR(VLOOKUP($BQ$17,Sheet1!BF2:BI2,3,0),0) -> 0 | BR19: =+IFERROR(VLOOKUP($BR$17,Sheet1!BJ2:BM2,3,0),0) -> 0 | BS19: =+IFERROR(VLOOKUP($BS$17,Sheet1!BN2:BQ2,3,0),0) -> 0 | BT19: =+IFERROR(VLOOKUP($BT$17,Sheet1!BR2:BU2,3,0),0) -> 0 | BU19: 15 | BV19: =Sheet1!E2 -> WOOD | BW19: =Sheet1!CV2 -> MD0100005 | BX19: =Sheet1!CW2 -> DRUM - 36 X 14 X 23 X 2 | BY19: =Sheet1!CX2 -> 1000 | BZ19: =Sheet1!BZ2 -> 2305.4 | CA19: =SUMPRODUCT($N$18:$BU$18,N19:BU19)+BZ19 -> 66067.4 | CB19: =Sheet1!CB2 -> 0 | CC19: =CA19*CB19 -> 0 | CD19: 0.4 | CE19: =CA19*CD19 -> 26426.96 | CF19: 0 | CG19: =CA19*CF19 -> 0 | CH19: =CA19+CC19+CE19+CG19 -> 92494.36 | CI19: 0.03 | CJ19: =CH19*CI19 -> 2774.8308 | CK19: 0.01 | CL19: =CH19*CK19 -> 924.9436
A20: =Sheet1!A3 -> ENQ-12472-22-23 | B20: =Sheet1!B3 -> 45366 | C20: =Sheet1!C3 -> FA2900034 | D20: =Sheet1!D3 -> COVERED CONDUCTOR - 1 CORE X 80 SQ. MM. (AAAC) - 11 KV | E20: =CH20+CJ20+CL20 -> 125859.38 | F20: =ROUNDUP(M28,0) -> 4500 | G20: =E20+F20 -> 130359.38 | H20: =Sheet1!CP3 -> 0.18 | I20: =G20*H20 -> 23464.688 | J20: =G20+I20 -> 153824.07 | K20: =Sheet1!CS3 -> 6 | L20: =Sheet1!CT3 -> KMS | M20: =J20*K20 -> 922944.39 | N20: =+IFERROR(VLOOKUP($N$17,Sheet1!J3:L3,3,0),0) -> 0 | O20: =+IFERROR(VLOOKUP($O$17,Sheet1!J3:L3,3,0),0) -> 0 | P20: =+IFERROR(VLOOKUP($P$17,Sheet1!J3:M3,3,0),0) -> 0 | Q20: =+IFERROR(VLOOKUP($Q$17,Sheet1!J3:M3,3,0),0) -> 0 | R20: =+IFERROR(VLOOKUP($R$17,Sheet1!J3:M3,3,0),0) -> 0 | S20: =+IFERROR(VLOOKUP($S$17,Sheet1!N3:Q3,3,0),0) -> 0 | T20: 219 | U20: =+IFERROR(VLOOKUP($U$17,Sheet1!F3:I3,3,0),0) -> 0 | V20: =+IFERROR(VLOOKUP($V$17,Sheet1!F3:I3,3,0),0) -> 0 | W20: =+IFERROR(VLOOKUP($W$17,Sheet1!F3:I3,3,0),0) -> 0 | X20: =+IFERROR(VLOOKUP($X$17,Sheet1!F3:I3,3,0),0) -> 0 | Y20: =+IFERROR(VLOOKUP($Y$17,Sheet1!F3:I3,3,0),0) -> 0 | Z20: =+IFERROR(VLOOKUP($Z$17,Sheet1!F3:I3,3,0),0) -> 0 | AA20: =+IFERROR(VLOOKUP($AA$17,Sheet1!F3:I3,3,0),0) -> 0 | AB20: =+IFERROR(VLOOKUP($AB$17,Sheet1!F3:I3,3,0),0) -> 0 | AC20: 42 | AD20: =+IFERROR(VLOOKUP($AD$17,Sheet1!R3:U3,2,0),0) -> 0 | AE20: 53 | AF20: =+IFERROR(VLOOKUP($AF$17,Sheet1!V3:Y3,3,0),0) -> 0 | AG20: =+IFERROR(VLOOKUP($AG$17,Sheet1!V3:Y3,3,0),0) -> 0 | AH20: =+IFERROR(VLOOKUP($AH$17,Sheet1!V3:Y3,3,0),0) -> 0 | AI20: =+IFERROR(VLOOKUP($AI$17,Sheet1!V3:Y3,3,0),0) -> 0 | AJ20: =+IFERROR(VLOOKUP($AJ$17,Sheet1!V3:Y3,3,0),0) -> 0 | AK20: =+IFERROR(VLOOKUP($AK$17,Sheet1!Z3:AB3,3,0),0) -> 0 | AL20: =+IFERROR(VLOOKUP($AL$17,Sheet1!AD3:AG3,3,0),0) -> 0 | AM20: =+IFERROR(VLOOKUP($AM$17,Sheet1!AD3:AG3,3,0),0) -> 0 | AN20: =+IFERROR(VLOOKUP($AN$17,Sheet1!AD3:AG3,3,0),0) -> 0 | AO20: =+IFERROR(VLOOKUP($AO$17,Sheet1!AD3:AG3,3,0),0) -> 0 | AP20: =+IFERROR(VLOOKUP($AP$17,Sheet1!AD3:AG3,3,0),0) -> 0 | AQ20: =+IFERROR(VLOOKUP($AQ$17,Sheet1!AD3:AG3,3,0),0) -> 0 | AR20: =+IFERROR(VLOOKUP($AR$17,Sheet1!AD3:AG3,3,0),0) -> 0 | AS20: =+IFERROR(VLOOKUP($AS$17,Sheet1!AH3:AK3,3,0),0) -> 0 | AT20: =+IFERROR(VLOOKUP($AT$17,Sheet1!AH3:AK3,3,0),0) -> 0 | AU20: =+IFERROR(VLOOKUP($AU$17,Sheet1!AH3:AK3,3,0),0) -> 0 | AV20: =+IFERROR(VLOOKUP($AV$17,Sheet1!AH3:AK3,3,0),0) -> 0 | AW20: =+IFERROR(VLOOKUP($AW$17,Sheet1!AH3:AK3,3,0),0) -> 0 | AX20: =+IFERROR(VLOOKUP($AX$17,Sheet1!AH3:AK3,3,0),0) -> 0 | AY20: =+IFERROR(VLOOKUP($AY$17,Sheet1!AH3:AK3,3,0),0) -> 0 | AZ20: =+IFERROR(VLOOKUP($AZ$17,Sheet1!AH3:AK3,3,0),0) -> 0 | BA20: =+IFERROR(VLOOKUP($BA$17,Sheet1!AH3:AK3,3,0),0) -> 0 | BB20: =+IFERROR(VLOOKUP($BB$17,Sheet1!AH3:AK3,3,0),0) -> 0 | BC20: =+IFERROR(VLOOKUP($BC$17,Sheet1!AL3:AO3,3,0),0) -> 0 | BD20: =+IFERROR(VLOOKUP($BD$17,Sheet1!AL3:AO3,3,0),0) -> 0 | BE20: =+IFERROR(VLOOKUP($BE$17,Sheet1!AL3:AO3,3,0),0) -> 0 | BF20: =+IFERROR(VLOOKUP($BF$17,Sheet1!AL3:AO3,3,0),0) -> 0 | BG20: =+IFERROR(VLOOKUP($BG$17,Sheet1!AL3:AO3,3,0),0) -> 0 | BH20: =+IFERROR(VLOOKUP($BH$17,Sheet1!AL3:AO3,3,0),0) -> 0 | BI20: =+IFERROR(VLOOKUP($BI$17,Sheet1!AL3:AO3,3,0),0) -> 0 | BJ20: =+IFERROR(VLOOKUP($BJ$17,Sheet1!AL3:AO3,3,0),0) -> 0 | BK20: =+IFERROR(VLOOKUP($BK$17,Sheet1!AL3:AO3,3,0),0) -> 0 | BL20: 69 | BM20: =+IFERROR(VLOOKUP($BM$17,Sheet1!AP3:AS3,3,0),0) -> 0 | BN20: =+IFERROR(VLOOKUP($BN$17,Sheet1!AT3:AW3,3,0),0) -> 0 | BO20: =+IFERROR(VLOOKUP($BO$17,Sheet1!AX3:BA3,3,0),0) -> 0 | BP20: =+IFERROR(VLOOKUP($BP$17,Sheet1!BB3:BE3,3,0),0) -> 0 | BQ20: =+IFERROR(VLOOKUP($BQ$17,Sheet1!BF3:BI3,3,0),0) -> 0 | BR20: =+IFERROR(VLOOKUP($BR$17,Sheet1!BJ3:BM3,3,0),0) -> 0 | BS20: =+IFERROR(VLOOKUP($BS$17,Sheet1!BN3:BQ3,3,0),0) -> 0 | BT20: =+IFERROR(VLOOKUP($BT$17,Sheet1!BR3:BU3,3,0),0) -> 0 | BU20: 16 | BV20: =Sheet1!E3 -> WOOD | BW20: =Sheet1!CV3 -> MD0100085 | BX20: =Sheet1!CW3 -> DRUM - 43 X 15 X 28 X 2.25 | BY20: =Sheet1!CX3 -> 1000 | BZ20: =Sheet1!BZ3 -> 3257.88 | CA20: =SUMPRODUCT($N$18:$BU$18,N20:BU20)+BZ20 -> 86441.88 | CB20: =Sheet1!CB3 -> 0 | CC20: =CA20*CB20 -> 0 | CD20: 0.4 | CE20: =CA20*CD20 -> 34576.752 | CF20: 0 | CG20: =CA20*CF20 -> 0 | CH20: =CA20+CC20+CE20+CG20 -> 121018.63 | CI20: 0.03 | CJ20: =CH20*CI20 -> 3630.559 | CK20: 0.01 | CL20: =CH20*CK20 -> 1210.1863
A21: =Sheet1!A7 -> ENQ-12472-22-23 | B21: =Sheet1!B7 -> 45366 | C21: =Sheet1!C7 -> FA2900004 | D21: =Sheet1!D7 -> COVERED CONDUCTOR - 1 CORE x 100 SQ. MM. (AAAC) - 11KV | E21: =CH21+CJ21+CL21 -> 147570.01 | F21: =ROUNDUP(M29,0) -> 1009 | G21: =E21+F21 -> 148579.01 | H21: =Sheet1!CP7 -> 0.18 | I21: =G21*H21 -> 26744.222 | J21: =G21+I21 -> 175323.23 | K21: =Sheet1!CS7 -> 321.17 | L21: =Sheet1!CT7 -> KMS | M21: =J21*K21 -> 56308563 | N21: =+IFERROR(VLOOKUP($N$17,Sheet1!J7:L7,3,0),0) -> 0 | O21: =+IFERROR(VLOOKUP($O$17,Sheet1!J7:L7,3,0),0) -> 0 | P21: =+IFERROR(VLOOKUP($P$17,Sheet1!J7:M7,3,0),0) -> 0 | Q21: =+IFERROR(VLOOKUP($Q$17,Sheet1!J7:M7,3,0),0) -> 0 | R21: =+IFERROR(VLOOKUP($R$17,Sheet1!J7:M7,3,0),0) -> 0 | S21: =+IFERROR(VLOOKUP($S$17,Sheet1!N7:Q7,3,0),0) -> 0 | T21: 273 | U21: =+IFERROR(VLOOKUP($U$17,Sheet1!F7:I7,3,0),0) -> 0 | V21: =+IFERROR(VLOOKUP($V$17,Sheet1!F7:I7,3,0),0) -> 0 | W21: =+IFERROR(VLOOKUP($W$17,Sheet1!F7:I7,3,0),0) -> 0 | X21: =+IFERROR(VLOOKUP($X$17,Sheet1!F7:I7,3,0),0) -> 0 | Y21: =+IFERROR(VLOOKUP($Y$17,Sheet1!F7:I7,3,0),0) -> 0 | Z21: =+IFERROR(VLOOKUP($Z$17,Sheet1!F7:I7,3,0),0) -> 0 | AA21: =+IFERROR(VLOOKUP($AA$17,Sheet1!F7:I7,3,0),0) -> 0 | AB21: =+IFERROR(VLOOKUP($AB$17,Sheet1!F7:I7,3,0),0) -> 0 | AC21: 46 | AD21: =+IFERROR(VLOOKUP($AD$17,Sheet1!R7:U7,2,0),0) -> 0 | AE21: 58 | AF21: =+IFERROR(VLOOKUP($AF$17,Sheet1!V7:Y7,3,0),0) -> 0 | AG21: =+IFERROR(VLOOKUP($AG$17,Sheet1!V7:Y7,3,0),0) -> 0 | AH21: =+IFERROR(VLOOKUP($AH$17,Sheet1!V7:Y7,3,0),0) -> 0 | AI21: =+IFERROR(VLOOKUP($AI$17,Sheet1!V7:Y7,3,0),0) -> 0 | AJ21: =+IFERROR(VLOOKUP($AJ$17,Sheet1!V7:Y7,3,0),0) -> 0 | AK21: =+IFERROR(VLOOKUP($AK$17,Sheet1!Z7:AB7,3,0),0) -> 0 | AL21: =+IFERROR(VLOOKUP($AL$17,Sheet1!AD7:AG7,3,0),0) -> 0 | AM21: =+IFERROR(VLOOKUP($AM$17,Sheet1!AD7:AG7,3,0),0) -> 0 | AN21: =+IFERROR(VLOOKUP($AN$17,Sheet1!AD7:AG7,3,0),0) -> 0 | AO21: =+IFERROR(VLOOKUP($AO$17,Sheet1!AD7:AG7,3,0),0) -> 0 | AP21: =+IFERROR(VLOOKUP($AP$17,Sheet1!AD7:AG7,3,0),0) -> 0 | AQ21: =+IFERROR(VLOOKUP($AQ$17,Sheet1!AD7:AG7,3,0),0) -> 0 | AR21: =+IFERROR(VLOOKUP($AR$17,Sheet1!AD7:AG7,3,0),0) -> 0 | AS21: =+IFERROR(VLOOKUP($AS$17,Sheet1!AH7:AK7,3,0),0) -> 0 | AT21: =+IFERROR(VLOOKUP($AT$17,Sheet1!AH7:AK7,3,0),0) -> 0 | AU21: =+IFERROR(VLOOKUP($AU$17,Sheet1!AH7:AK7,3,0),0) -> 0 | AV21: =+IFERROR(VLOOKUP($AV$17,Sheet1!AH7:AK7,3,0),0) -> 0 | AW21: =+IFERROR(VLOOKUP($AW$17,Sheet1!AH7:AK7,3,0),0) -> 0 | AX21: =+IFERROR(VLOOKUP($AX$17,Sheet1!AH7:AK7,3,0),0) -> 0 | AY21: =+IFERROR(VLOOKUP($AY$17,Sheet1!AH7:AK7,3,0),0) -> 0 | AZ21: =+IFERROR(VLOOKUP($AZ$17,Sheet1!AH7:AK7,3,0),0) -> 0 | BA21: =+IFERROR(VLOOKUP($BA$17,Sheet1!AH7:AK7,3,0),0) -> 0 | BB21: =+IFERROR(VLOOKUP($BB$17,Sheet1!AH7:AK7,3,0),0) -> 0 | BC21: =+IFERROR(VLOOKUP($BC$17,Sheet1!AL7:AO7,3,0),0) -> 0 | BD21: =+IFERROR(VLOOKUP($BD$17,Sheet1!AL7:AO7,3,0),0) -> 0 | BE21: =+IFERROR(VLOOKUP($BE$17,Sheet1!AL7:AO7,3,0),0) -> 0 | BF21: =+IFERROR(VLOOKUP($BF$17,Sheet1!AL7:AO7,3,0),0) -> 0 | BG21: =+IFERROR(VLOOKUP($BG$17,Sheet1!AL7:AO7,3,0),0) -> 0 | BH21: =+IFERROR(VLOOKUP($BH$17,Sheet1!AL7:AO7,3,0),0) -> 0 | BI21: =+IFERROR(VLOOKUP($BI$17,Sheet1!AL7:AO7,3,0),0) -> 0 | BJ21: =+IFERROR(VLOOKUP($BJ$17,Sheet1!AL7:AO7,3,0),0) -> 0 | BK21: =+IFERROR(VLOOKUP($BK$17,Sheet1!AL7:AO7,3,0),0) -> 0 | BL21: 74 | BM21: =+IFERROR(VLOOKUP($BM$17,Sheet1!AP7:AS7,3,0),0) -> 0 | BN21: =+IFERROR(VLOOKUP($BN$17,Sheet1!AT7:AW7,3,0),0) -> 0 | BO21: =+IFERROR(VLOOKUP($BO$17,Sheet1!AX7:BA7,3,0),0) -> 0 | BP21: =+IFERROR(VLOOKUP($BP$17,Sheet1!BB7:BE7,3,0),0) -> 0 | BQ21: =+IFERROR(VLOOKUP($BQ$17,Sheet1!BF7:BI7,3,0),0) -> 0 | BR21: =+IFERROR(VLOOKUP($BR$17,Sheet1!BJ7:BM7,3,0),0) -> 0 | BS21: =+IFERROR(VLOOKUP($BS$17,Sheet1!BN7:BQ7,3,0),0) -> 0 | BT21: =+IFERROR(VLOOKUP($BT$17,Sheet1!BR7:BU7,3,0),0) -> 0 | BU21: 16 | BV21: =Sheet1!E7 -> WOOD | BW21: =Sheet1!CV7 -> MD0100075 | BX21: =Sheet1!CW7 -> DRUM - 42 X 15 X 23 X 2 (LOMBU) | BY21: =Sheet1!CX7 -> 1000 | BZ21: =Sheet1!BZ7 -> 3542.03 | CA21: =SUMPRODUCT($N$18:$BU$18,N21:BU21)+BZ21 -> 101353.03 | CB21: =Sheet1!CB7 -> 0 | CC21: =CA21*CB21 -> 0 | CD21: 0.4 | CE21: =CA21*CD21 -> 40541.212 | CF21: 0 | CG21: =CA21*CF21 -> 0 | CH21: =CA21+CC21+CE21+CG21 -> 141894.24 | CI21: 0.03 | CJ21: =CH21*CI21 -> 4256.8273 | CK21: 0.01 | CL21: =CH21*CK21 -> 1418.9424
A22: =Sheet1!A4 -> ENQ-12472-22-23 | B22: =Sheet1!B4 -> 45366 | C22: =Sheet1!C4 -> FA2900008 | D22: =Sheet1!D4 -> COVERED CONDUCTOR - 1 CORE X 99 SQ. MM. (AAAC) - 33 KV | E22: =CH22+CJ22+CL22 -> 166918.08 | F22: =ROUNDUP(M30,0) -> 1976 | G22: =E22+F22 -> 168894.08 | H22: =Sheet1!CP4 -> 0.18 | I22: =G22*H22 -> 30400.935 | J22: =G22+I22 -> 199295.02 | K22: =Sheet1!CS4 -> 41 | L22: =Sheet1!CT4 -> KMS | M22: =J22*K22 -> 8171095.7 | N22: =+IFERROR(VLOOKUP($N$17,Sheet1!J4:L4,3,0),0) -> 0 | O22: =+IFERROR(VLOOKUP($O$17,Sheet1!J4:L4,3,0),0) -> 0 | P22: =+IFERROR(VLOOKUP($P$17,Sheet1!J4:M4,3,0),0) -> 0 | Q22: =+IFERROR(VLOOKUP($Q$17,Sheet1!J4:M4,3,0),0) -> 0 | R22: =+IFERROR(VLOOKUP($R$17,Sheet1!J4:M4,3,0),0) -> 0 | S22: =+IFERROR(VLOOKUP($S$17,Sheet1!N4:Q4,3,0),0) -> 0 | T22: 273 | U22: =+IFERROR(VLOOKUP($U$17,Sheet1!F4:I4,3,0),0) -> 0 | V22: =+IFERROR(VLOOKUP($V$17,Sheet1!F4:I4,3,0),0) -> 0 | W22: =+IFERROR(VLOOKUP($W$17,Sheet1!F4:I4,3,0),0) -> 0 | X22: =+IFERROR(VLOOKUP($X$17,Sheet1!F4:I4,3,0),0) -> 0 | Y22: =+IFERROR(VLOOKUP($Y$17,Sheet1!F4:I4,3,0),0) -> 0 | Z22: =+IFERROR(VLOOKUP($Z$17,Sheet1!F4:I4,3,0),0) -> 0 | AA22: =+IFERROR(VLOOKUP($AA$17,Sheet1!F4:I4,3,0),0) -> 0 | AB22: =+IFERROR(VLOOKUP($AB$17,Sheet1!F4:I4,3,0),0) -> 0 | AC22: 46 | AD22: =+IFERROR(VLOOKUP($AD$17,Sheet1!R4:U4,2,0),0) -> 0 | AE22: 123 | AF22: =+IFERROR(VLOOKUP($AF$17,Sheet1!V4:Y4,3,0),0) -> 0 | AG22: =+IFERROR(VLOOKUP($AG$17,Sheet1!V4:Y4,3,0),0) -> 0 | AH22: =+IFERROR(VLOOKUP($AH$17,Sheet1!V4:Y4,3,0),0) -> 0 | AI22: =+IFERROR(VLOOKUP($AI$17,Sheet1!V4:Y4,3,0),0) -> 0 | AJ22: =+IFERROR(VLOOKUP($AJ$17,Sheet1!V4:Y4,3,0),0) -> 0 | AK22: =+IFERROR(VLOOKUP($AK$17,Sheet1!Z4:AB4,3,0),0) -> 0 | AL22: =+IFERROR(VLOOKUP($AL$17,Sheet1!AD4:AG4,3,0),0) -> 0 | AM22: =+IFERROR(VLOOKUP($AM$17,Sheet1!AD4:AG4,3,0),0) -> 0 | AN22: =+IFERROR(VLOOKUP($AN$17,Sheet1!AD4:AG4,3,0),0) -> 0 | AO22: =+IFERROR(VLOOKUP($AO$17,Sheet1!AD4:AG4,3,0),0) -> 0 | AP22: =+IFERROR(VLOOKUP($AP$17,Sheet1!AD4:AG4,3,0),0) -> 0 | AQ22: =+IFERROR(VLOOKUP($AQ$17,Sheet1!AD4:AG4,3,0),0) -> 0 | AR22: =+IFERROR(VLOOKUP($AR$17,Sheet1!AD4:AG4,3,0),0) -> 0 | AS22: =+IFERROR(VLOOKUP($AS$17,Sheet1!AH4:AK4,3,0),0) -> 0 | AT22: =+IFERROR(VLOOKUP($AT$17,Sheet1!AH4:AK4,3,0),0) -> 0 | AU22: =+IFERROR(VLOOKUP($AU$17,Sheet1!AH4:AK4,3,0),0) -> 0 | AV22: =+IFERROR(VLOOKUP($AV$17,Sheet1!AH4:AK4,3,0),0) -> 0 | AW22: =+IFERROR(VLOOKUP($AW$17,Sheet1!AH4:AK4,3,0),0) -> 0 | AX22: =+IFERROR(VLOOKUP($AX$17,Sheet1!AH4:AK4,3,0),0) -> 0 | AY22: =+IFERROR(VLOOKUP($AY$17,Sheet1!AH4:AK4,3,0),0) -> 0 | AZ22: =+IFERROR(VLOOKUP($AZ$17,Sheet1!AH4:AK4,3,0),0) -> 0 | BA22: =+IFERROR(VLOOKUP($BA$17,Sheet1!AH4:AK4,3,0),0) -> 0 | BB22: =+IFERROR(VLOOKUP($BB$17,Sheet1!AH4:AK4,3,0),0) -> 0 | BC22: =+IFERROR(VLOOKUP($BC$17,Sheet1!AL4:AO4,3,0),0) -> 0 | BD22: =+IFERROR(VLOOKUP($BD$17,Sheet1!AL4:AO4,3,0),0) -> 0 | BE22: =+IFERROR(VLOOKUP($BE$17,Sheet1!AL4:AO4,3,0),0) -> 0 | BF22: =+IFERROR(VLOOKUP($BF$17,Sheet1!AL4:AO4,3,0),0) -> 0 | BG22: =+IFERROR(VLOOKUP($BG$17,Sheet1!AL4:AO4,3,0),0) -> 0 | BH22: =+IFERROR(VLOOKUP($BH$17,Sheet1!AL4:AO4,3,0),0) -> 0 | BI22: =+IFERROR(VLOOKUP($BI$17,Sheet1!AL4:AO4,3,0),0) -> 0 | BJ22: =+IFERROR(VLOOKUP($BJ$17,Sheet1!AL4:AO4,3,0),0) -> 0 | BK22: =+IFERROR(VLOOKUP($BK$17,Sheet1!AL4:AO4,3,0),0) -> 0 | BL22: 92 | BM22: =+IFERROR(VLOOKUP($BM$17,Sheet1!AP4:AS4,3,0),0) -> 0 | BN22: =+IFERROR(VLOOKUP($BN$17,Sheet1!AT4:AW4,3,0),0) -> 0 | BO22: =+IFERROR(VLOOKUP($BO$17,Sheet1!AX4:BA4,3,0),0) -> 0 | BP22: =+IFERROR(VLOOKUP($BP$17,Sheet1!BB4:BE4,3,0),0) -> 0 | BQ22: =+IFERROR(VLOOKUP($BQ$17,Sheet1!BF4:BI4,3,0),0) -> 0 | BR22: =+IFERROR(VLOOKUP($BR$17,Sheet1!BJ4:BM4,3,0),0) -> 0 | BS22: =+IFERROR(VLOOKUP($BS$17,Sheet1!BN4:BQ4,3,0),0) -> 0 | BT22: =+IFERROR(VLOOKUP($BT$17,Sheet1!BR4:BU4,3,0),0) -> 0 | BU22: 16 | BV22: =Sheet1!E4 -> WOOD | BW22: =Sheet1!CV4 -> MD0100015 | BX22: =Sheet1!CW4 -> DRUM - 48 X 20 X 28 X 2.25 | BY22: =Sheet1!CX4 -> 1000 | BZ22: =Sheet1!BZ4 -> 3658.54 | CA22: =SUMPRODUCT($N$18:$BU$18,N22:BU22)+BZ22 -> 114641.54 | CB22: =Sheet1!CB4 -> 0 | CC22: =CA22*CB22 -> 0 | CD22: 0.4 | CE22: =CA22*CD22 -> 45856.616 | CF22: 0 | CG22: =CA22*CF22 -> 0 | CH22: =CA22+CC22+CE22+CG22 -> 160498.16 | CI22: 0.03 | CJ22: =CH22*CI22 -> 4814.9447 | CK22: 0.01 | CL22: =CH22*CK22 -> 1604.9816
A23: =Sheet1!A5 -> ENQ-12472-22-23 | B23: =Sheet1!B5 -> 45366 | C23: =Sheet1!C5 -> FA2900014 | D23: =Sheet1!D5 -> COVERED CONDUCTOR - 1 CORE x 150 SQ. MM. (XLPE) (AAAC) - 33 KV | E23: =CH23+CJ23+CL23 -> 227662.5 | F23: =ROUNDUP(M31,0) -> 1583 | G23: =E23+F23 -> 229245.5 | H23: =Sheet1!CP5 -> 0.18 | I23: =G23*H23 -> 41264.191 | J23: =G23+I23 -> 270509.69 | K23: =Sheet1!CS5 -> 119.467 | L23: =Sheet1!CT5 -> KMS | M23: =J23*K23 -> 32316982 | N23: =+IFERROR(VLOOKUP($N$17,Sheet1!J5:L5,3,0),0) -> 0 | O23: =+IFERROR(VLOOKUP($O$17,Sheet1!J5:L5,3,0),0) -> 0 | P23: =+IFERROR(VLOOKUP($P$17,Sheet1!J5:M5,3,0),0) -> 0 | Q23: =+IFERROR(VLOOKUP($Q$17,Sheet1!J5:M5,3,0),0) -> 0 | R23: =+IFERROR(VLOOKUP($R$17,Sheet1!J5:M5,3,0),0) -> 0 | S23: =+IFERROR(VLOOKUP($S$17,Sheet1!N5:Q5,3,0),0) -> 0 | T23: 407 | U23: =+IFERROR(VLOOKUP($U$17,Sheet1!F5:I5,3,0),0) -> 0 | V23: =+IFERROR(VLOOKUP($V$17,Sheet1!F5:I5,3,0),0) -> 0 | W23: =+IFERROR(VLOOKUP($W$17,Sheet1!F5:I5,3,0),0) -> 0 | X23: =+IFERROR(VLOOKUP($X$17,Sheet1!F5:I5,3,0),0) -> 0 | Y23: =+IFERROR(VLOOKUP($Y$17,Sheet1!F5:I5,3,0),0) -> 0 | Z23: =+IFERROR(VLOOKUP($Z$17,Sheet1!F5:I5,3,0),0) -> 0 | AA23: =+IFERROR(VLOOKUP($AA$17,Sheet1!F5:I5,3,0),0) -> 0 | AB23: =+IFERROR(VLOOKUP($AB$17,Sheet1!F5:I5,3,0),0) -> 0 | AC23: 56 | AD23: =+IFERROR(VLOOKUP($AD$17,Sheet1!R5:U5,2,0),0) -> 0 | AE23: 145 | AF23: =+IFERROR(VLOOKUP($AF$17,Sheet1!V5:Y5,3,0),0) -> 0 | AG23: =+IFERROR(VLOOKUP($AG$17,Sheet1!V5:Y5,3,0),0) -> 0 | AH23: =+IFERROR(VLOOKUP($AH$17,Sheet1!V5:Y5,3,0),0) -> 0 | AI23: =+IFERROR(VLOOKUP($AI$17,Sheet1!V5:Y5,3,0),0) -> 0 | AJ23: =+IFERROR(VLOOKUP($AJ$17,Sheet1!V5:Y5,3,0),0) -> 0 | AK23: =+IFERROR(VLOOKUP($AK$17,Sheet1!Z5:AB5,3,0),0) -> 0 | AL23: =+IFERROR(VLOOKUP($AL$17,Sheet1!AD5:AG5,3,0),0) -> 0 | AM23: =+IFERROR(VLOOKUP($AM$17,Sheet1!AD5:AG5,3,0),0) -> 0 | AN23: =+IFERROR(VLOOKUP($AN$17,Sheet1!AD5:AG5,3,0),0) -> 0 | AO23: =+IFERROR(VLOOKUP($AO$17,Sheet1!AD5:AG5,3,0),0) -> 0 | AP23: =+IFERROR(VLOOKUP($AP$17,Sheet1!AD5:AG5,3,0),0) -> 0 | AQ23: =+IFERROR(VLOOKUP($AQ$17,Sheet1!AD5:AG5,3,0),0) -> 0 | AR23: =+IFERROR(VLOOKUP($AR$17,Sheet1!AD5:AG5,3,0),0) -> 0 | AS23: =+IFERROR(VLOOKUP($AS$17,Sheet1!AH5:AK5,3,0),0) -> 0 | AT23: =+IFERROR(VLOOKUP($AT$17,Sheet1!AH5:AK5,3,0),0) -> 0 | AU23: =+IFERROR(VLOOKUP($AU$17,Sheet1!AH5:AK5,3,0),0) -> 0 | AV23: =+IFERROR(VLOOKUP($AV$17,Sheet1!AH5:AK5,3,0),0) -> 0 | AW23: =+IFERROR(VLOOKUP($AW$17,Sheet1!AH5:AK5,3,0),0) -> 0 | AX23: =+IFERROR(VLOOKUP($AX$17,Sheet1!AH5:AK5,3,0),0) -> 0 | AY23: =+IFERROR(VLOOKUP($AY$17,Sheet1!AH5:AK5,3,0),0) -> 0 | AZ23: =+IFERROR(VLOOKUP($AZ$17,Sheet1!AH5:AK5,3,0),0) -> 0 | BA23: =+IFERROR(VLOOKUP($BA$17,Sheet1!AH5:AK5,3,0),0) -> 0 | BB23: =+IFERROR(VLOOKUP($BB$17,Sheet1!AH5:AK5,3,0),0) -> 0 | BC23: =+IFERROR(VLOOKUP($BC$17,Sheet1!AL5:AO5,3,0),0) -> 0 | BD23: =+IFERROR(VLOOKUP($BD$17,Sheet1!AL5:AO5,3,0),0) -> 0 | BE23: =+IFERROR(VLOOKUP($BE$17,Sheet1!AL5:AO5,3,0),0) -> 0 | BF23: =+IFERROR(VLOOKUP($BF$17,Sheet1!AL5:AO5,3,0),0) -> 0 | BG23: =+IFERROR(VLOOKUP($BG$17,Sheet1!AL5:AO5,3,0),0) -> 0 | BH23: =+IFERROR(VLOOKUP($BH$17,Sheet1!AL5:AO5,3,0),0) -> 0 | BI23: =+IFERROR(VLOOKUP($BI$17,Sheet1!AL5:AO5,3,0),0) -> 0 | BJ23: =+IFERROR(VLOOKUP($BJ$17,Sheet1!AL5:AO5,3,0),0) -> 0 | BK23: =+IFERROR(VLOOKUP($BK$17,Sheet1!AL5:AO5,3,0),0) -> 0 | BL23: 106 | BM23: =+IFERROR(VLOOKUP($BM$17,Sheet1!AP5:AS5,3,0),0) -> 0 | BN23: =+IFERROR(VLOOKUP($BN$17,Sheet1!AT5:AW5,3,0),0) -> 0 | BO23: =+IFERROR(VLOOKUP($BO$17,Sheet1!AX5:BA5,3,0),0) -> 0 | BP23: =+IFERROR(VLOOKUP($BP$17,Sheet1!BB5:BE5,3,0),0) -> 0 | BQ23: =+IFERROR(VLOOKUP($BQ$17,Sheet1!BF5:BI5,3,0),0) -> 0 | BR23: =+IFERROR(VLOOKUP($BR$17,Sheet1!BJ5:BM5,3,0),0) -> 0 | BS23: =+IFERROR(VLOOKUP($BS$17,Sheet1!BN5:BQ5,3,0),0) -> 0 | BT23: =+IFERROR(VLOOKUP($BT$17,Sheet1!BR5:BU5,3,0),0) -> 0 | BU23: 28 | BV23: =Sheet1!E5 -> WOOD | BW23: =Sheet1!CV5 -> MD0100099 | BX23: =Sheet1!CW5 -> DRUM - 48 X 14 X 36 X 2.25 (LOMBU) | BY23: =Sheet1!CX5 -> 1000 | BZ23: =Sheet1!BZ5 -> 4716.61 | CA23: =SUMPRODUCT($N$18:$BU$18,N23:BU23)+BZ23 -> 156361.61 | CB23: =Sheet1!CB5 -> 0 | CC23: =CA23*CB23 -> 0 | CD23: 0.4 | CE23: =CA23*CD23 -> 62544.644 | CF23: 0 | CG23: =CA23*CF23 -> 0 | CH23: =CA23+CC23+CE23+CG23 -> 218906.25 | CI23: 0.03 | CJ23: =CH23*CI23 -> 6567.1876 | CK23: 0.01 | CL23: =CH23*CK23 -> 2189.0625
A24: =Sheet1!A6 -> ENQ-12472-22-23 | B24: =Sheet1!B6 -> 45366 | C24: =Sheet1!C6 -> FA2900032 | D24: =Sheet1!D6 -> COVERED CONDUCTOR - 1 CORE X 232 SQ. MM. (AAAC) - 33 KV | E24: =CH24+CJ24+CL24 -> 324314.89 | F24: =ROUNDUP(M32,0) -> 3060 | G24: =E24+F24 -> 327374.89 | H24: =Sheet1!CP6 -> 0.18 | I24: =G24*H24 -> 58927.479 | J24: =G24+I24 -> 386302.36 | K24: =Sheet1!CS6 -> 150 | L24: =Sheet1!CT6 -> KMS | M24: =J24*K24 -> 57945355 | N24: =+IFERROR(VLOOKUP($N$17,Sheet1!J6:L6,3,0),0) -> 0 | O24: =+IFERROR(VLOOKUP($O$17,Sheet1!J6:L6,3,0),0) -> 0 | P24: =+IFERROR(VLOOKUP($P$17,Sheet1!J6:M6,3,0),0) -> 0 | Q24: =+IFERROR(VLOOKUP($Q$17,Sheet1!J6:M6,3,0),0) -> 0 | R24: =+IFERROR(VLOOKUP($R$17,Sheet1!J6:M6,3,0),0) -> 0 | S24: =+IFERROR(VLOOKUP($S$17,Sheet1!N6:Q6,3,0),0) -> 0 | T24: 637 | U24: =+IFERROR(VLOOKUP($U$17,Sheet1!F6:I6,3,0),0) -> 0 | V24: =+IFERROR(VLOOKUP($V$17,Sheet1!F6:I6,3,0),0) -> 0 | W24: =+IFERROR(VLOOKUP($W$17,Sheet1!F6:I6,3,0),0) -> 0 | X24: =+IFERROR(VLOOKUP($X$17,Sheet1!F6:I6,3,0),0) -> 0 | Y24: =+IFERROR(VLOOKUP($Y$17,Sheet1!F6:I6,3,0),0) -> 0 | Z24: =+IFERROR(VLOOKUP($Z$17,Sheet1!F6:I6,3,0),0) -> 0 | AA24: =+IFERROR(VLOOKUP($AA$17,Sheet1!F6:I6,3,0),0) -> 0 | AB24: =+IFERROR(VLOOKUP($AB$17,Sheet1!F6:I6,3,0),0) -> 0 | AC24: 70 | AD24: =+IFERROR(VLOOKUP($AD$17,Sheet1!R6:U6,2,0),0) -> 0 | AE24: 174 | AF24: =+IFERROR(VLOOKUP($AF$17,Sheet1!V6:Y6,3,0),0) -> 0 | AG24: =+IFERROR(VLOOKUP($AG$17,Sheet1!V6:Y6,3,0),0) -> 0 | AH24: =+IFERROR(VLOOKUP($AH$17,Sheet1!V6:Y6,3,0),0) -> 0 | AI24: =+IFERROR(VLOOKUP($AI$17,Sheet1!V6:Y6,3,0),0) -> 0 | AJ24: =+IFERROR(VLOOKUP($AJ$17,Sheet1!V6:Y6,3,0),0) -> 0 | AK24: =+IFERROR(VLOOKUP($AK$17,Sheet1!Z6:AB6,3,0),0) -> 0 | AL24: =+IFERROR(VLOOKUP($AL$17,Sheet1!AD6:AG6,3,0),0) -> 0 | AM24: =+IFERROR(VLOOKUP($AM$17,Sheet1!AD6:AG6,3,0),0) -> 0 | AN24: =+IFERROR(VLOOKUP($AN$17,Sheet1!AD6:AG6,3,0),0) -> 0 | AO24: =+IFERROR(VLOOKUP($AO$17,Sheet1!AD6:AG6,3,0),0) -> 0 | AP24: =+IFERROR(VLOOKUP($AP$17,Sheet1!AD6:AG6,3,0),0) -> 0 | AQ24: =+IFERROR(VLOOKUP($AQ$17,Sheet1!AD6:AG6,3,0),0) -> 0 | AR24: =+IFERROR(VLOOKUP($AR$17,Sheet1!AD6:AG6,3,0),0) -> 0 | AS24: =+IFERROR(VLOOKUP($AS$17,Sheet1!AH6:AK6,3,0),0) -> 0 | AT24: =+IFERROR(VLOOKUP($AT$17,Sheet1!AH6:AK6,3,0),0) -> 0 | AU24: =+IFERROR(VLOOKUP($AU$17,Sheet1!AH6:AK6,3,0),0) -> 0 | AV24: =+IFERROR(VLOOKUP($AV$17,Sheet1!AH6:AK6,3,0),0) -> 0 | AW24: =+IFERROR(VLOOKUP($AW$17,Sheet1!AH6:AK6,3,0),0) -> 0 | AX24: =+IFERROR(VLOOKUP($AX$17,Sheet1!AH6:AK6,3,0),0) -> 0 | AY24: =+IFERROR(VLOOKUP($AY$17,Sheet1!AH6:AK6,3,0),0) -> 0 | AZ24: =+IFERROR(VLOOKUP($AZ$17,Sheet1!AH6:AK6,3,0),0) -> 0 | BA24: =+IFERROR(VLOOKUP($BA$17,Sheet1!AH6:AK6,3,0),0) -> 0 | BB24: =+IFERROR(VLOOKUP($BB$17,Sheet1!AH6:AK6,3,0),0) -> 0 | BC24: =+IFERROR(VLOOKUP($BC$17,Sheet1!AL6:AO6,3,0),0) -> 0 | BD24: =+IFERROR(VLOOKUP($BD$17,Sheet1!AL6:AO6,3,0),0) -> 0 | BE24: =+IFERROR(VLOOKUP($BE$17,Sheet1!AL6:AO6,3,0),0) -> 0 | BF24: =+IFERROR(VLOOKUP($BF$17,Sheet1!AL6:AO6,3,0),0) -> 0 | BG24: =+IFERROR(VLOOKUP($BG$17,Sheet1!AL6:AO6,3,0),0) -> 0 | BH24: =+IFERROR(VLOOKUP($BH$17,Sheet1!AL6:AO6,3,0),0) -> 0 | BI24: =+IFERROR(VLOOKUP($BI$17,Sheet1!AL6:AO6,3,0),0) -> 0 | BJ24: =+IFERROR(VLOOKUP($BJ$17,Sheet1!AL6:AO6,3,0),0) -> 0 | BK24: =+IFERROR(VLOOKUP($BK$17,Sheet1!AL6:AO6,3,0),0) -> 0 | BL24: 124 | BM24: =+IFERROR(VLOOKUP($BM$17,Sheet1!AP6:AS6,3,0),0) -> 0 | BN24: =+IFERROR(VLOOKUP($BN$17,Sheet1!AT6:AW6,3,0),0) -> 0 | BO24: =+IFERROR(VLOOKUP($BO$17,Sheet1!AX6:BA6,3,0),0) -> 0 | BP24: =+IFERROR(VLOOKUP($BP$17,Sheet1!BB6:BE6,3,0),0) -> 0 | BQ24: =+IFERROR(VLOOKUP($BQ$17,Sheet1!BF6:BI6,3,0),0) -> 0 | BR24: =+IFERROR(VLOOKUP($BR$17,Sheet1!BJ6:BM6,3,0),0) -> 0 | BS24: =+IFERROR(VLOOKUP($BS$17,Sheet1!BN6:BQ6,3,0),0) -> 0 | BT24: =+IFERROR(VLOOKUP($BT$17,Sheet1!BR6:BU6,3,0),0) -> 0 | BU24: 40 | BV24: =Sheet1!E6 -> WOOD | BW24: =Sheet1!CV6 -> MD0100019 | BX24: =Sheet1!CW6 -> DRUM - 54 X 24 X 32 X 3 | BY24: =Sheet1!CX6 -> 1000 | BZ24: =Sheet1!BZ6 -> 6378.74 | CA24: =SUMPRODUCT($N$18:$BU$18,N24:BU24)+BZ24 -> 222743.74 | CB24: =Sheet1!CB6 -> 0 | CC24: =CA24*CB24 -> 0 | CD24: 0.4 | CE24: =CA24*CD24 -> 89097.496 | CF24: 0 | CG24: =CA24*CF24 -> 0 | CH24: =CA24+CC24+CE24+CG24 -> 311841.24 | CI24: 0.03 | CJ24: =CH24*CI24 -> 9355.2371 | CK24: 0.01 | CL24: =CH24*CK24 -> 3118.4124
E26: Order Quantity | F26: Stnd Length | G26: Truck type | H26: Fare of one truck | I26: No of Drum in one truck | J26: Total length in one Truck | K26: No of Truck | L26: Total Freight | M26: Freight per KM | T26: CABLE WEIGHT KG/KM | AC26: DRUM WEIGHT | AE26: CABLE+DRUM
C27: =BW19 -> MD0100005 | D27: =D19 -> COVERED CONDUCTOR - 1 CORE X 55 SQ. MM. (AAAC) - 11 KV | E27: =K19 -> 5 | F27: =BY19/1000 -> 1 | G27: 16 MT | H27: 27000 | I27: 36 | J27: =F27*I27 -> 36 | K27: =ROUNDUP((E27/J27),0) -> 1 | L27: =M27*E27 -> 27000 | M27: =(H27*K27)/E27 -> 5400 | T27: =SUM(T19:BU19) -> 308 | AC27: =50+15 -> 65 | AE27: =((T27*F27)+AC27) -> 373 | BL27: =I27*AE27 -> 13428
C28: =BW20 -> MD0100085 | D28: =D20 -> COVERED CONDUCTOR - 1 CORE X 80 SQ. MM. (AAAC) - 11 KV | E28: =K20 -> 6 | F28: =BY20/1000 -> 1 | G28: 16 MT | H28: 27000 | I28: 27 | J28: =F28*I28 -> 27 | K28: =ROUNDUP((E28/J28),0) -> 1 | L28: =M28*E28 -> 27000 | M28: =(H28*K28)/E28 -> 4500 | T28: =SUM(T20:BU20) -> 399 | AC28: =75+25 -> 100 | AE28: =((T28*F28)+AC28) -> 499 | BL28: =I28*AE28 -> 13473
C29: =BW21 -> MD0100075 | D29: =D21 -> COVERED CONDUCTOR - 1 CORE x 100 SQ. MM. (AAAC) - 11KV | E29: =K21 -> 321.17 | F29: =BY21/1000 -> 1 | G29: 16 MT | H29: 27000 | I29: 27 | J29: =F29*I29 -> 27 | K29: =ROUNDUP((E29/J29),0) -> 12 | L29: =M29*E29 -> 324000 | M29: =(H29*K29)/E29 -> 1008.8115 | T29: =SUM(T21:BU21) -> 467 | AC29: =55+20 -> 75 | AE29: =((T29*F29)+AC29) -> 542 | BL29: =I29*AE29 -> 14634
C30: =BW22 -> MD0100015 | D30: =D22 -> COVERED CONDUCTOR - 1 CORE X 99 SQ. MM. (AAAC) - 33 KV | E30: =K22 -> 41 | F30: =BY22/1000 -> 1 | G30: 16 MT | H30: 27000 | I30: 18 | J30: =F30*I30 -> 18 | K30: =ROUNDUP((E30/J30),0) -> 3 | L30: =M30*E30 -> 81000 | M30: =(H30*K30)/E30 -> 1975.6098 | T30: =SUM(T22:BU22) -> 550 | AC30: =100+25 -> 125 | AE30: =((T30*F30)+AC30) -> 675 | BL30: =I30*AE30 -> 12150
C31: =BW23 -> MD0100099 | D31: =D23 -> COVERED CONDUCTOR - 1 CORE x 150 SQ. MM. (XLPE) (AAAC) - 33 KV | E31: =K23 -> 119.467 | F31: =BY23/1000 -> 1 | G31: 16 MT | H31: 27000 | I31: 18 | J31: =F31*I31 -> 18 | K31: =ROUNDUP((E31/J31),0) -> 7 | L31: =M31*E31 -> 189000 | M31: =(H31*K31)/E31 -> 1582.0268 | T31: =SUM(T23:BU23) -> 742 | AC31: =100+25 -> 125 | AE31: =((T31*F31)+AC31) -> 867 | BL31: =I31*AE31 -> 15606
C32: =BW24 -> MD0100019 | D32: =D24 -> COVERED CONDUCTOR - 1 CORE X 232 SQ. MM. (AAAC) - 33 KV | E32: =K24 -> 150 | F32: =BY24/1000 -> 1 | G32: 16 MT | H32: 27000 | I32: 9 | J32: =F32*I32 -> 9 | K32: =ROUNDUP((E32/J32),0) -> 17 | L32: =M32*E32 -> 459000 | M32: =(H32*K32)/E32 -> 3060 | T32: =SUM(T24:BU24) -> 1045 | AC32: =150+30 -> 180 | AE32: =((T32*F32)+AC32) -> 1225 | BL32: =I32*AE32 -> 11025
I33: SOMBHU SIR CONFIRMED OVERPHONE
A36: DOCKET NO. | B36: Base Date | C36: ITEM CODE | D36: PROPOSE ERP ITEM NAME | E36: EX-WORKS (PER MTR) | F36: FREIGHT PER MTR | G36: PRICE INCLUDING FREIGHT (PER MTR) | H36: GST % | I36: GST VALUE | J36: PRICE INCLUDING GST & FREIGHT (PER MTR) | K36: QTY | L36: Unit | M36: TOTAL PRICE OF FULL QTY (INCLUDING FRIGHT & GST)
A38: =A19 -> ENQ-12472-22-23 | B38: =B19 -> 45366 | C38: =C19 -> FA2900029 | D38: =D19 -> COVERED CONDUCTOR - 1 CORE X 55 SQ. MM. (AAAC) - 11 KV | E38: =ROUNDUP(E19/1000,2) -> 96.2 | F38: =ROUNDUP(F19/1000,2) -> 5.4 | G38: =E38+F38 -> 101.6 | H38: =H19 -> 0.18 | I38: =G38*H38 -> 18.288 | J38: =G38+I38 -> 119.888 | K38: =K19*1000 -> 5000 | L38: MTR | M38: =J38*K38 -> 599440
A39: =A20 -> ENQ-12472-22-23 | B39: =B20 -> 45366 | C39: =C20 -> FA2900034 | D39: =D20 -> COVERED CONDUCTOR - 1 CORE X 80 SQ. MM. (AAAC) - 11 KV | E39: =ROUNDUP(E20/1000,2) -> 125.86 | F39: =ROUNDUP(F20/1000,2) -> 4.5 | G39: =E39+F39 -> 130.36 | H39: =H20 -> 0.18 | I39: =G39*H39 -> 23.4648 | J39: =G39+I39 -> 153.8248 | K39: =K20*1000 -> 6000 | L39: MTR | M39: =J39*K39 -> 922948.8
A40: =A21 -> ENQ-12472-22-23 | B40: =B21 -> 45366 | C40: =C21 -> FA2900004 | D40: =D21 -> COVERED CONDUCTOR - 1 CORE x 100 SQ. MM. (AAAC) - 11KV | E40: =ROUNDUP(E21/1000,2) -> 147.58 | F40: =ROUNDUP(F21/1000,2) -> 1.01 | G40: =E40+F40 -> 148.59 | H40: =H21 -> 0.18 | I40: =G40*H40 -> 26.7462 | J40: =G40+I40 -> 175.3362 | K40: =K21*1000 -> 321170 | L40: MTR | M40: =J40*K40 -> 56312727
A41: =A22 -> ENQ-12472-22-23 | B41: =B22 -> 45366 | C41: =C22 -> FA2900008 | D41: =D22 -> COVERED CONDUCTOR - 1 CORE X 99 SQ. MM. (AAAC) - 33 KV | E41: =ROUNDUP(E22/1000,2) -> 166.92 | F41: =ROUNDUP(F22/1000,2) -> 1.98 | G41: =E41+F41 -> 168.9 | H41: =H22 -> 0.18 | I41: =G41*H41 -> 30.402 | J41: =G41+I41 -> 199.302 | K41: =K22*1000 -> 41000 | L41: MTR | M41: =J41*K41 -> 8171382
A42: =A23 -> ENQ-12472-22-23 | B42: =B23 -> 45366 | C42: =C23 -> FA2900014 | D42: =D23 -> COVERED CONDUCTOR - 1 CORE x 150 SQ. MM. (XLPE) (AAAC) - 33 KV | E42: =ROUNDUP(E23/1000,2) -> 227.67 | F42: =ROUNDUP(F23/1000,2) -> 1.59 | G42: =E42+F42 -> 229.26 | H42: =H23 -> 0.18 | I42: =G42*H42 -> 41.2668 | J42: =G42+I42 -> 270.5268 | K42: =K23*1000 -> 119467 | L42: MTR | M42: =J42*K42 -> 32319025
A43: =A24 -> ENQ-12472-22-23 | B43: =B24 -> 45366 | C43: =C24 -> FA2900032 | D43: =D24 -> COVERED CONDUCTOR - 1 CORE X 232 SQ. MM. (AAAC) - 33 KV | E43: =ROUNDUP(E24/1000,2) -> 324.32 | F43: =ROUNDUP(F24/1000,2) -> 3.06 | G43: =E43+F43 -> 327.38 | H43: =H24 -> 0.18 | I43: =G43*H43 -> 58.9284 | J43: =G43+I43 -> 386.3084 | K43: =K24*1000 -> 150000 | L43: MTR | M43: =J43*K43 -> 57946260
