Workbook

Sheet Sheet1
A1: DOCKET NO. | B1: Base Date | C1: ITEM CODE | D1: PROPOSE ERP ITEM NAME | E1: PROPOSE DRUM TYPE | F1: Insulation Screening (Metallic) | G1: RM RATE (Insulation Screening (Metallic)) | H1: Weight (Insulation Screening (Metallic)) | I1: COST(Insulation Screening (Metallic)) | J1: Conductor | K1: RM RATE(Conductor) | L1: WEIGHT(Conductor) | M1: COST(Conductor) | N1: AL ALLOY | O1: RM RATE(Alu Alloy) | P1: WEIGHT(Alu Alloy) | Q1: COST(Alu Alloy) | R1: Insulation Screening (Non-Metallic) | S1: RM RATE(Insulation Screening (Non-Metallic)) | T1: WEIGHT(Insulation Screening (Non-Metallic)) | U1: COST(Insulation Screening (Non-Metallic)) | V1: Insulation | W1: RM RATE(Insulation) | X1: WEIGHT(Insulation) | Y1: COST(Insulation) | Z1: POLY TAPE | AA1: RM RATE (Poly Tape) | AB1: WEIGHT (Poly Tape) | AC1: COST(Poly Tape) | AD1: Inner Sheath | AE1: RM RATE(Inner Sheath) | AF1: WEIGHT(Inner Sheath) | AG1: COST(Inner Sheath) | AH1: Armouring | AI1: RM RATE(Armouring) | AJ1: WEIGHT(Armouring) | AK1: COST(Armouring) | AL1: Outer Sheath | AM1: RM RATE(Outer Sheath) | AN1: WEIGHT(Outer Sheath) | AO1: COST(Outer Sheath) | AP1: FILLER | AQ1: RM RATE(Filler) | AR1: WEIGHT(Filler) | AS1: COST(Filler) | AT1: GREASE | AU1: RM RATE(Grease) | AV1: WEIGHT(Grease) | AW1: COST(Grease) | AX1: Water swellable Tape | AY1: RM RATE(Water swellable Tape) | AZ1: WEIGHT(Water swellable Tape) | BA1: COST(Water swellable Tape) | BB1: Semi conducting Water Swellable tape | BC1: RM RATE(Semi conducting Water Swellable tape) | BD1: WEIGHT(Semi conducting Water Swellable tape) | BE1: COST(Semi conducting Water Swellable tape) | BF1: SEMICON TAPE | BG1: RM RATE(SEMICON TAPE) | BH1: WEIGHT(SEMICON TAPE) | BI1: COST(SEMICON TAPE) | BJ1: GLASS FIBER TAPE | BK1: RM RATE(GLASS FIBER TAPE) | BL1: WEIGHT(GLASS FIBER TAPE) | BM1: COST(GLASS FIBER TAPE) | BN1: COPPER WIRE 0.8 MM | BO1: RM RATE(COPPER WIRE 0.8 MM) | BP1: WEIGHT(COPPER WIRE 0.8 MM) | BQ1: COST(COPPER WIRE 0.8 MM) | BR1: RUBBERIZED COTTON TAPE | BS1: RM RATE(RUBBERIZED COTTON TAPE) | BT1: WEIGHT(RUBBERIZED COTTON TAPE) | BU1: COST(RUBBERIZED COTTON TAPE) | BV1: Water Tight Compound | BW1: RM RATE(Water Tight Compound) | BX1: WEIGHT(Water Tight Compound) | BY1: COST(Water Tight Compound) | BZ1: DRUM COST PER KM | CA1: TOTAL RM COST | CB1: FIRM % | CC1: FIRM VALUE | CD1: MFG% | CE1: MFG VALUE | CF1: PROF% | CG1: PROFIT VALUE | CH1: 1ST EX-WORKS | CI1: Intt % | CJ1: INTT VALUE | CK1: insp% | CL1: INSP VALUE | CM1: EX-WORKS (PER KM) | CN1: FREIGHT PER KM | CO1: PRICE INCLUDING FREIGHT (PER KM) | CP1: GST % | CQ1: GST VALUE | CR1: PRICE INCLUDING GST & FREIGHT (PER KM) | CS1: QTY | CT1: Unit | CU1: TOTAL PRICE OF FULL QTY (INCLUDING FRIGHT & GST) | CV1: DRUM CODE | CW1: DRUM SIZE (FxbXtx Ft) | CX1: PARTY STANDARD LENGTH (MTR)
A2: ENQ-10908-22-23 | B2: 45149 | C2: FA1500004 | D2: 1 CORE X 35 SQ. MM. + 1 CORE X 25 SQ. MM. AB CABLE ( INSULATED) | E2: WOOD | J2: Alumimium | K2: 212 | L2: 95 | M2: 20140 | N2: Alumimium Alloy | O2: 220 | P2: 67.5 | Q2: 14850 | T2: 0 | V2: LT-XLPE | W2: 116 | X2: 60 | Y2: 6960 | AB2: 0 | AF2: 0 | AJ2: 0 | AN2: 0 | AR2: 0 | AV2: 0 | AZ2: 0 | BD2: 0 | BH2: 0 | BL2: 0 | BP2: 0 | BT2: 0 | BX2: 0 | BZ2: 3262.33 | CA2: 45212.33 | CH2: 45212.33 | CM2: 45212.33 | CO2: 45212.33 | CP2: 0.18 | CQ2: 8138.22 | CR2: 53350.55 | CS2: 250 | CT2: KMS | CU2: 13337637 | CV2: MD0100004 | CW2: DRUM - 28 X 10 X 23 X 2 | CX2: 500

Sheet AUTO CALCULATION SHEET (2)
A2: TP WESTERN ODISHA DISTRIBUTION LIMITED
A4: TENDER SPECIFICATION NO () | B4: TPWODL/SA/O/SU/031
A5: TENDER DESCRIPTION () | B5: Rate Contract for Supply of (1X35+1X25) Sq mm LT AB Cable
A6: Last Date & Time of Submission () | B6: 18-August-2023 [15:00 Hrs.]
A7: REVERSE AUCTION | B7: TPWODL reserves the right to conduct the reverse auction (instead of public opening of price bids) for the products/ services being asked for in the tender. The terms and conditions for such reverse auction events shall be as per the Acceptance Form attached as Annexure VI of this document. The bidders along with the tender document shall mandatorily submit a duly signed copy of the Acceptance Form attached as Annexure VI as a token of acceptance for the same.
A8: Price () | B8: The prices shall remain firm during the entire contract period.
A9: Validity () | B9: Bids shall remain valid for 180 days from the due date of submission of the bid. Notwithstanding clause above, the TPWODL may solicit the Bidder’s consent to an extension of the Period of Bid Validity. The request and responses thereto shall be made in writing. RC Validity: - The validity of this rate contract shall be one year from the date of issuance.
A10: Delivery Period () | B10: Release Orders shall be placed against the awarded Rate Contract by TPWODL as and when the requirements arise& Delivery within 60 Days from RO.
A11: Payment Terms () | B11: On delivery of the materials in good condition and certification of acceptance by certified official, Associate shall submit the Bills/ Invoices in original in the name of TP Western Odisha Distribution Limited to Invoice Desk. The payment shall be released within 60 days from the date of submission of certified bills/ invoices.
A12: Technical Specification
N14: =Sheet1!J1 -> Conductor | S14: AL ALLOY | U14: Insulation Screening (Metallic) | AC14: Insulation Screening (Non-Metallic) | AE14: Insulation | AK14: POLY TAPE | AL14: Inner Sheath | AS14: Armouring | BC14: Outer Sheath | BM14: FILLER | BN14: GREASE | BO14: Water swellable Tape | BP14: Semi conducting Water Swellable tape | BQ14: SEMICON TAPE | BR14: GLASS FIBER TAPE | BS14: COPPER WIRE 0.8 MM | BT14: RUBBERIZED COTTON TAPE | BU14: Water Tight Compound | BZ14: DRUM COST PER KM | CA14: TOTAL RM COST | CB14: EXTRA CONSUMPTION | CC14: EXTRA CONSUMPTION VALUE
A15: DOCKET NO. | B15: =Sheet1!B1 -> Base Date | C15: ITEM CODE | D15: PROPOSE ERP ITEM NAME | E15: EX-WORKS (PER KM) | F15: FREIGHT PER KM | G15: PRICE INCLUDING FREIGHT (PER KM) | H15: GST % | I15: GST VALUE | J15: PRICE INCLUDING GST & FREIGHT (PER KM) | K15: QTY | L15: Unit | M15: TOTAL PRICE OF FULL QTY (INCLUDING FRIGHT & GST) | N15: Alumimium | O15: Alumimium ALLOY | P15: Copper | Q15: Flexible Copper | R15: Galvanized steel wire | S15: Alumimium | T15: Alumimium ALLOY | U15: Coper tape - 0.1 mm | V15: Copper Tape - 0.03 mm | W15: Copper Tape - 0.035 mm | X15: Copper Tape - 0.04 mm | Y15: Copper Tape - 0.045 mm | Z15: Copper Tape - 0.050 mm | AA15: Copper Tape - 0.060 mm | AB15: Copper Tape - 0.075 mm(DOUBLE) | AC15: Extruded semiconductive | AD15: Extruded Semiconductive(Stripable) | AE15: HT-XLPE | AF15: LT-XLPE | AG15: TR XLPE | AH15: Type A PVC | AI15: Type C PVC (HR) | AJ15: XLPE | AK15: POLY TAPE | AL15: FR PVC Type ST-1 | AM15: FR PVC Type ST-2 | AN15: FRLSH PVC Type ST-2 | AO15: PVC Type ST-1 | AP15: PVC Type ST-1-PRESSURE EXTRUDED | AQ15: PVC Type ST-2 | AR15: PVC Type ST-2-PRESSURE EXTRUDED | AS15: ACSR CORE WIRE | AT15: ACSR DOG STEEL WIRE | AU15: Aluminium Flat Strip | AV15: Aluminium Round Wire | AW15: Double Steel Tape | AX15: Galvanised Steel Flat Strip | AY15: Galvanised Steel Flat Strip (Double) | AZ15: Galvanised Steel Flat Strip-B | BA15: Galvanised Steel Round Wire | BB15: Galvanised Steel Round Wire (Double) | BC15: FR PVC Type ST-1 | BD15: FR PVC Type ST-2 | BE15: FRLSH PVC Type ST-1 | BF15: FRLSH PVC Type ST-2 | BG15: PE, ST-3 | BH15: PE, ST-7 | BI15: PVC Type ST-1 | BJ15: PVC Type ST-2 | BK15: PVC Type ST-2-PRESSURE EXTRUDED | BL15: UV & Track Resistant XLPE | BM15: FILLER | BN15: Grease | BO15: Water swellable Tape | BP15: Semi conducting Water Swellable tape | BQ15: SEMICON TAPE | BR15: GLASS FIBER TAPE | BS15: COPPER WIRE 0.8 MM | BT15: RUBBERIZED COTTON TAPE | BU15: Water Tight Compound | BV15: =Sheet1!E1 -> PROPOSE DRUM TYPE | BW15: =Sheet1!CV1 -> DRUM CODE | BX15: =Sheet1!CW1 -> DRUM SIZE (FxbXtx Ft) | BY15: =Sheet1!CX1 -> PARTY STANDARD LENGTH (MTR) | CD15: MFG% | CE15: MFG VALUE | CF15: PROF% | CG15: PROFIT VALUE | CH15: 1ST EX-WORKS | CI15: Intt % | CJ15: INTT VALUE | CK15: insp% | CL15: INSP VALUE
N16: 214 | O16: =+IFERROR(VLOOKUP($O$15,Sheet1!J:L,2,0),0) -> 0 | P16: =+IFERROR(VLOOKUP($P$15,Sheet1!J:M,2,0),0) -> 0 | Q16: =+IFERROR(VLOOKUP($Q$15,Sheet1!J:M,2,0),0) -> 0 | R16: =+IFERROR(VLOOKUP($R$15,Sheet1!J:M,2,0),0) -> 0 | S16: =+IFERROR(VLOOKUP($S$15,Sheet1!N:Q,2,0),0) -> 0 | T16: =N16+7 -> 221 | U16: =+IFERROR(VLOOKUP($U$15,Sheet1!F:I,2,0),0) -> 0 | V16: =+IFERROR(VLOOKUP($V$15,Sheet1!F:I,2,0),0) -> 0 | W16: =+IFERROR(VLOOKUP($W$15,Sheet1!F:I,2,0),0) -> 0 | X16: =+IFERROR(VLOOKUP($X$15,Sheet1!F:I,2,0),0) -> 0 | Y16: =+IFERROR(VLOOKUP($Y$15,Sheet1!F:I,2,0),0) -> 0 | Z16: =+IFERROR(VLOOKUP($Z$15,Sheet1!F:I,2,0),0) -> 0 | AA16: =+IFERROR(VLOOKUP($AA$15,Sheet1!F:I,2,0),0) -> 0 | AB16: =+IFERROR(VLOOKUP($AB$15,Sheet1!F:I,2,0),0) -> 0 | AC16: =+IFERROR(VLOOKUP($AC$15,Sheet1!R:U,2,0),0) -> 0 | AD16: =+IFERROR(VLOOKUP($AD$15,Sheet1!R:U,2,0),0) -> 0 | AE16: =+IFERROR(VLOOKUP($AE$15,Sheet1!V:Y,2,0),0) -> 0 | AF16: =+IFERROR(VLOOKUP($AF$15,Sheet1!V:Y,2,0),0) -> 116 | AG16: =+IFERROR(VLOOKUP($AG$15,Sheet1!V:Y,2,0),0) -> 0 | AH16: =+IFERROR(VLOOKUP($AH$15,Sheet1!V:Y,2,0),0) -> 0 | AI16: =+IFERROR(VLOOKUP($AI$15,Sheet1!V:Y,2,0),0) -> 0 | AJ16: =+IFERROR(VLOOKUP($AJ$15,Sheet1!V:Y,2,0),0) -> 0 | AK16: =+IFERROR(VLOOKUP($AK$15,Sheet1!Z2:AA840,2,0),0) -> 0 | AL16: =+IFERROR(VLOOKUP($AL$15,Sheet1!AD2:AG840,2,0),0) -> 0 | AM16: =+IFERROR(VLOOKUP($AM$15,Sheet1!AD2:AG840,2,0),0) -> 0 | AN16: =+IFERROR(VLOOKUP($AN$15,Sheet1!AD2:AG840,2,0),0) -> 0 | AO16: =+IFERROR(VLOOKUP($AO$15,Sheet1!AD2:AG840,2,0),0) -> 0 | AP16: =+IFERROR(VLOOKUP($AP$15,Sheet1!AD2:AG840,2,0),0) -> 0 | AQ16: =+IFERROR(VLOOKUP($AQ$15,Sheet1!AD2:AG840,2,0),0) -> 0 | AR16: =+IFERROR(VLOOKUP($AR$15,Sheet1!AD2:AG840,2,0),0) -> 0 | AS16: =+IFERROR(VLOOKUP($AS$15,Sheet1!AH2:AK840,2,0),0) -> 0 | AT16: =+IFERROR(VLOOKUP($AT$15,Sheet1!AH2:AK840,2,0),0) -> 0 | AU16: =+IFERROR(VLOOKUP($AU$15,Sheet1!AH2:AK840,2,0),0) -> 0 | AV16: =+IFERROR(VLOOKUP($AV$15,Sheet1!AH2:AK840,2,0),0) -> 0 | AW16: =+IFERROR(VLOOKUP($AW$15,Sheet1!AH2:AK840,2,0),0) -> 0 | AX16: =+IFERROR(VLOOKUP($AX$15,Sheet1!AH2:AK840,2,0),0) -> 0 | AY16: =+IFERROR(VLOOKUP($AY$15,Sheet1!AH2:AK840,2,0),0) -> 0 | AZ16: =+IFERROR(VLOOKUP($AZ$15,Sheet1!AH2:AK840,2,0),0) -> 0 | BA16: =+IFERROR(VLOOKUP($BA$15,Sheet1!AH2:AK840,2,0),0) -> 0 | BB16: =+IFERROR(VLOOKUP($BB$15,Sheet1!AH2:AK840,2,0),0) -> 0 | BC16: =+IFERROR(VLOOKUP($BC$15,Sheet1!AL2:AO840,2,0),0) -> 0 | BD16: =+IFERROR(VLOOKUP($BD$15,Sheet1!AL2:AO840,2,0),0) -> 0 | BE16: =+IFERROR(VLOOKUP($BE$15,Sheet1!AL2:AO840,2,0),0) -> 0 | BF16: =+IFERROR(VLOOKUP($BF$15,Sheet1!AL2:AO840,2,0),0) -> 0 | BG16: =+IFERROR(VLOOKUP($BG$15,Sheet1!AL2:AO840,2,0),0) -> 0 | BH16: =+IFERROR(VLOOKUP($BH$15,Sheet1!AL2:AO840,2,0),0) -> 0 | BI16: =+IFERROR(VLOOKUP($BI$15,Sheet1!AL2:AO840,2,0),0) -> 0 | BJ16: =+IFERROR(VLOOKUP($BJ$15,Sheet1!AL2:AO840,2,0),0) -> 0 | BK16: =+IFERROR(VLOOKUP($BK$15,Sheet1!AL2:AO840,2,0),0) -> 0 | BL16: =+IFERROR(VLOOKUP($BL$15,Sheet1!AL2:AO840,2,0),0) -> 0 | BM16: =+IFERROR(VLOOKUP($BM$15,Sheet1!AP2:AS840,2,0),0) -> 0 | BN16: =+IFERROR(VLOOKUP($BN$15,Sheet1!AT2:AW840,2,0),0) -> 0 | BO16: =+IFERROR(VLOOKUP($BO$15,Sheet1!AX2:BA840,2,0),0) -> 0 | BP16: =+IFERROR(VLOOKUP($BP$15,Sheet1!BB2:BE840,2,0),0) -> 0 | BQ16: =+IFERROR(VLOOKUP($BQ$15,Sheet1!BF2:BI840,2,0),0) -> 0 | BR16: =+IFERROR(VLOOKUP($BR$15,Sheet1!BJ2:BM840,2,0),0) -> 0 | BS16: =+IFERROR(VLOOKUP($BS$15,Sheet1!BN2:BQ840,2,0),0) -> 0 | BT16: =+IFERROR(VLOOKUP($BT$15,Sheet1!BR2:BU840,2,0),0) -> 0 | BU16: =+IFERROR(VLOOKUP($BU$15,Sheet1!BV2:BY840,2,0),0) -> 0
A17: =Sheet1!A2 -> ENQ-10908-22-23 | B17: =Sheet1!B2 -> 45149 | C17: =Sheet1!C2 -> FA1500004 | D17: =Sheet1!D2 -> 1 CORE X 35 SQ. MM. + 1 CORE X 25 SQ. MM. AB CABLE ( INSULATED) | E17: =CH17+CJ17+CL17 -> 71121.495 | F17: =ROUNDUP(M20,2) -> 700 | G17: =E17+F17 -> 71821.495 | H17: =Sheet1!CP2 -> 0.18 | I17: =G17*H17 -> 12927.869 | J17: =G17+I17 -> 84749.364 | K17: =Sheet1!CS2 -> 250 | L17: =Sheet1!CT2 -> KMS | M17: =J17*K17 -> 21187341 | N17: =+IFERROR(VLOOKUP($N$15,Sheet1!J2:L2,3,0),0) -> 95 | O17: =+IFERROR(VLOOKUP($O$15,Sheet1!J2:L2,3,0),0) -> 0 | P17: =+IFERROR(VLOOKUP($P$15,Sheet1!J2:M2,3,0),0) -> 0 | Q17: =+IFERROR(VLOOKUP($Q$15,Sheet1!J2:M2,3,0),0) -> 0 | R17: =+IFERROR(VLOOKUP($R$15,Sheet1!J2:M2,3,0),0) -> 0 | S17: =+IFERROR(VLOOKUP($S$15,Sheet1!N2:Q2,3,0),0) -> 0 | T17: 69 | U17: =+IFERROR(VLOOKUP($U$15,Sheet1!F2:I2,3,0),0) -> 0 | V17: =+IFERROR(VLOOKUP($V$15,Sheet1!F2:I2,3,0),0) -> 0 | W17: =+IFERROR(VLOOKUP($W$15,Sheet1!F2:I2,3,0),0) -> 0 | X17: =+IFERROR(VLOOKUP($X$15,Sheet1!F2:I2,3,0),0) -> 0 | Y17: =+IFERROR(VLOOKUP($Y$15,Sheet1!F2:I2,3,0),0) -> 0 | Z17: =+IFERROR(VLOOKUP($Z$15,Sheet1!F2:I2,3,0),0) -> 0 | AA17: =+IFERROR(VLOOKUP($AA$15,Sheet1!F2:I2,3,0),0) -> 0 | AB17: =+IFERROR(VLOOKUP($AB$15,Sheet1!F2:I2,3,0),0) -> 0 | AC17: =+IFERROR(VLOOKUP($AC$15,Sheet1!R2:U2,3,0),0) -> 0 | AD17: =+IFERROR(VLOOKUP($AD$15,Sheet1!R2:U2,2,0),0) -> 0 | AE17: =+IFERROR(VLOOKUP($AE$15,Sheet1!V2:Y2,3,0),0) -> 0 | AF17: 62 | AG17: =+IFERROR(VLOOKUP($AG$15,Sheet1!V2:Y2,3,0),0) -> 0 | AH17: =+IFERROR(VLOOKUP($AH$15,Sheet1!V2:Y2,3,0),0) -> 0 | AI17: =+IFERROR(VLOOKUP($AI$15,Sheet1!V2:Y2,3,0),0) -> 0 | AJ17: =+IFERROR(VLOOKUP($AJ$15,Sheet1!V2:Y2,3,0),0) -> 0 | AK17: =+IFERROR(VLOOKUP($AK$15,Sheet1!Z2:AB2,3,0),0) -> 0 | AL17: =+IFERROR(VLOOKUP($AL$15,Sheet1!AD2:AG2,3,0),0) -> 0 | AM17: =+IFERROR(VLOOKUP($AM$15,Sheet1!AD2:AG2,3,0),0) -> 0 | AN17: =+IFERROR(VLOOKUP($AN$15,Sheet1!AD2:AG2,3,0),0) -> 0 | AO17: =+IFERROR(VLOOKUP($AO$15,Sheet1!AD2:AG2,3,0),0) -> 0 | AP17: =+IFERROR(VLOOKUP($AP$15,Sheet1!AD2:AG2,3,0),0) -> 0 | AQ17: =+IFERROR(VLOOKUP($AQ$15,Sheet1!AD2:AG2,3,0),0) -> 0 | AR17: =+IFERROR(VLOOKUP($AR$15,Sheet1!AD2:AG2,3,0),0) -> 0 | AS17: =+IFERROR(VLOOKUP($AS$15,Sheet1!AH2:AK2,3,0),0) -> 0 | AT17: =+IFERROR(VLOOKUP($AT$15,Sheet1!AH2:AK2,3,0),0) -> 0 | AU17: =+IFERROR(VLOOKUP($AU$15,Sheet1!AH2:AK2,3,0),0) -> 0 | AV17: =+IFERROR(VLOOKUP($AV$15,Sheet1!AH2:AK2,3,0),0) -> 0 | AW17: =+IFERROR(VLOOKUP($AW$15,Sheet1!AH2:AK2,3,0),0) -> 0 | AX17: =+IFERROR(VLOOKUP($AX$15,Sheet1!AH2:AK2,3,0),0) -> 0 | AY17: =+IFERROR(VLOOKUP($AY$15,Sheet1!AH2:AK2,3,0),0) -> 0 | AZ17: =+IFERROR(VLOOKUP($AZ$15,Sheet1!AH2:AK2,3,0),0) -> 0 | BA17: =+IFERROR(VLOOKUP($BA$15,Sheet1!AH2:AK2,3,0),0) -> 0 | BB17: =+IFERROR(VLOOKUP($BB$15,Sheet1!AH2:AK2,3,0),0) -> 0 | BC17: =+IFERROR(VLOOKUP($BC$15,Sheet1!AL2:AO2,3,0),0) -> 0 | BD17: =+IFERROR(VLOOKUP($BD$15,Sheet1!AL2:AO2,3,0),0) -> 0 | BE17: =+IFERROR(VLOOKUP($BE$15,Sheet1!AL2:AO2,3,0),0) -> 0 | BF17: =+IFERROR(VLOOKUP($BF$15,Sheet1!AL2:AO2,3,0),0) -> 0 | BG17: =+IFERROR(VLOOKUP($BG$15,Sheet1!AL2:AO2,3,0),0) -> 0 | BH17: =+IFERROR(VLOOKUP($BH$15,Sheet1!AL2:AO2,3,0),0) -> 0 | BI17: =+IFERROR(VLOOKUP($BI$15,Sheet1!AL2:AO2,3,0),0) -> 0 | BJ17: =+IFERROR(VLOOKUP($BJ$15,Sheet1!AL2:AO2,3,0),0) -> 0 | BK17: =+IFERROR(VLOOKUP($BK$15,Sheet1!AL2:AO2,3,0),0) -> 0 | BL17: =+IFERROR(VLOOKUP($BL$15,Sheet1!AL2:AO2,3,0),0) -> 0 | BM17: =+IFERROR(VLOOKUP($BM$15,Sheet1!AP2:AS2,3,0),0) -> 0 | BN17: =+IFERROR(VLOOKUP($BN$15,Sheet1!AT2:AW2,3,0),0) -> 0 | BO17: =+IFERROR(VLOOKUP($BO$15,Sheet1!AX2:BA2,3,0),0) -> 0 | BP17: =+IFERROR(VLOOKUP($BP$15,Sheet1!BB2:BE2,3,0),0) -> 0 | BQ17: =+IFERROR(VLOOKUP($BQ$15,Sheet1!BF2:BI2,3,0),0) -> 0 | BR17: =+IFERROR(VLOOKUP($BR$15,Sheet1!BJ2:BM2,3,0),0) -> 0 | BS17: =+IFERROR(VLOOKUP($BS$15,Sheet1!BN2:BQ2,3,0),0) -> 0 | BT17: =+IFERROR(VLOOKUP($BT$15,Sheet1!BR2:BU2,3,0),0) -> 0 | BU17: =+IFERROR(VLOOKUP($BU$15,Sheet1!BV2:BY2,3,0),0) -> 0 | BV17: =Sheet1!E2 -> WOOD | BW17: =Sheet1!CV2 -> MD0100004 | BX17: =Sheet1!CW2 -> DRUM - 28 X 10 X 23 X 2 | BY17: =Sheet1!CX2 -> 500 | BZ17: =Sheet1!BZ2 -> 3262.33 | CA17: =SUMPRODUCT($N$16:$BU$16,N17:BU17)+BZ17 -> 46033.33 | CB17: =Sheet1!CB2 -> 0 | CC17: =CA17*CB17 -> 0 | CD17: 0.5 | CE17: =CA17*CD17 -> 23016.665 | CF17: 0 | CG17: =CA17*CF17 -> 0 | CH17: =CA17+CC17+CE17+CG17 -> 69049.995 | CI17: 0.02 | CJ17: =CH17*CI17 -> 1380.9999 | CK17: 0.01 | CL17: =CH17*CK17 -> 690.49995
E19: Order Quantity | F19: Stnd Length | G19: Truck type | H19: Fare of one truck | I19: No of Drum in one truck | J19: Total length in one Truck | K19: No of Truck | L19: Total Freight | M19: Freight per KM
D20: =D17 -> 1 CORE X 35 SQ. MM. + 1 CORE X 25 SQ. MM. AB CABLE ( INSULATED) | E20: =K17 -> 250 | F20: 0.5 | G20: 16 MT | H20: 25000 | I20: 72 | J20: =F20*I20 -> 36 | K20: =ROUNDUP((E20/J20),0) -> 7 | L20: =M20*E20 -> 175000 | M20: =(H20*K20)/E20 -> 700
A23: DOCKET NO. | B23: Base Date | C23: ITEM CODE | D23: PROPOSE ERP ITEM NAME | E23: EX-WORKS (PER MTR) | F23: FREIGHT PER MTR | G23: PRICE INCLUDING FREIGHT (PER MTR) | H23: GST % | I23: GST VALUE | J23: PRICE INCLUDING GST & FREIGHT (PER MTR) | K23: QTY | L23: Unit | M23: TOTAL PRICE OF FULL QTY (INCLUDING FRIGHT & GST)
A25: =A17 -> ENQ-10908-22-23 | B25: =B17 -> 45149 | C25: =C17 -> FA1500004 | D25: =D17 -> 1 CORE X 35 SQ. MM. + 1 CORE X 25 SQ. MM. AB CABLE ( INSULATED) | E25: =ROUNDUP(E17/1000,2) -> 71.13 | F25: =ROUNDUP(F17/1000,2) -> 0.7 | G25: =E25+F25 -> 71.83 | H25: =H17 -> 0.18 | I25: =G25*H25 -> 12.9294 | J25: =G25+I25 -> 84.7594 | K25: =K17*1000 -> 250000 | L25: MTR | M25: =J25*K25 -> 21189850

Sheet Sheet2
A1: DOCKET NO. | B1: Base Date | C1: ITEM CODE | D1: PROPOSE ERP ITEM NAME | E1: PROPOSE DRUM TYPE | F1: Insulation Screening (Metallic) | G1: RM RATE (Insulation Screening (Metallic)) | H1: Weight (Insulation Screening (Metallic)) | I1: COST(Insulation Screening (Metallic)) | J1: Conductor | K1: RM RATE(Conductor) | L1: WEIGHT(Conductor) | M1: COST(Conductor) | N1: AL ALLOY | O1: RM RATE(Alu Alloy) | P1: WEIGHT(Alu Alloy) | Q1: COST(Alu Alloy) | R1: Insulation Screening (Non-Metallic) | S1: RM RATE(Insulation Screening (Non-Metallic)) | T1: WEIGHT(Insulation Screening (Non-Metallic)) | U1: COST(Insulation Screening (Non-Metallic)) | V1: Insulation | W1: RM RATE(Insulation) | X1: WEIGHT(Insulation) | Y1: COST(Insulation) | Z1: POLY TAPE | AA1: RM RATE (Poly Tape) | AB1: WEIGHT (Poly Tape) | AC1: COST(Poly Tape) | AD1: Inner Sheath | AE1: RM RATE(Inner Sheath) | AF1: WEIGHT(Inner Sheath) | AG1: COST(Inner Sheath) | AH1: Armouring | AI1: RM RATE(Armouring) | AJ1: WEIGHT(Armouring) | AK1: COST(Armouring) | AL1: Outer Sheath | AM1: RM RATE(Outer Sheath) | AN1: WEIGHT(Outer Sheath) | AO1: COST(Outer Sheath) | AP1: FILLER | AQ1: RM RATE(Filler) | AR1: WEIGHT(Filler) | AS1: COST(Filler) | AT1: GREASE | AU1: RM RATE(Grease) | AV1: WEIGHT(Grease) | AW1: COST(Grease) | AX1: Water swellable Tape | AY1: RM RATE(Water swellable Tape) | AZ1: WEIGHT(Water swellable Tape) | BA1: COST(Water swellable Tape) | BB1: Semi conducting Water Swellable tape | BC1: RM RATE(Semi conducting Water Swellable tape) | BD1: WEIGHT(Semi conducting Water Swellable tape) | BE1: COST(Semi conducting Water Swellable tape) | BF1: SEMICON TAPE | BG1: RM RATE(SEMICON TAPE) | BH1: WEIGHT(SEMICON TAPE) | BI1: COST(SEMICON TAPE) | BJ1: GLASS FIBER TAPE | BK1: RM RATE(GLASS FIBER TAPE) | BL1: WEIGHT(GLASS FIBER TAPE) | BM1: COST(GLASS FIBER TAPE) | BN1: COPPER WIRE 0.8 MM | BO1: RM RATE(COPPER WIRE 0.8 MM) | BP1: WEIGHT(COPPER WIRE 0.8 MM) | BQ1: COST(COPPER WIRE 0.8 MM) | BR1: RUBBERIZED COTTON TAPE | BS1: RM RATE(RUBBERIZED COTTON TAPE) | BT1: WEIGHT(RUBBERIZED COTTON TAPE) | BU1: COST(RUBBERIZED COTTON TAPE) | BV1: Water Tight Compound | BW1: RM RATE(Water Tight Compound) | BX1: WEIGHT(Water Tight Compound) | BY1: COST(Water Tight Compound) | BZ1: DRUM COST PER KM | CA1: TOTAL RM COST | CB1: FIRM % | CC1: FIRM VALUE | CD1: MFG% | CE1: MFG VALUE | CF1: PROF% | CG1: PROFIT VALUE | CH1: 1ST EX-WORKS | CI1: Intt % | CJ1: INTT VALUE | CK1: insp% | CL1: INSP VALUE | CM1: EX-WORKS (PER KM) | CN1: FREIGHT PER KM | CO1: PRICE INCLUDING FREIGHT (PER KM) | CP1: GST % | CQ1: GST VALUE | CR1: PRICE INCLUDING GST & FREIGHT (PER KM) | CS1: QTY | CT1: Unit | CU1: TOTAL PRICE OF FULL QTY (INCLUDING FRIGHT & GST) | CV1: DRUM CODE | CW1: DRUM SIZE (FxbXtx Ft) | CX1: PARTY STANDARD LENGTH (MTR)
A2: ENQ-10908-22-23 | B2: 45149 | C2: FA1500004 | D2: 1 CORE X 35 SQ. MM. + 1 CORE X 25 SQ. MM. AB CABLE ( INSULATED) | E2: WOOD | J2: Alumimium | K2: 212 | L2: 95 | M2: 20140 | N2: Alumimium Alloy | O2: 220 | P2: 67.5 | Q2: 14850 | T2: 0 | V2: LT-XLPE | W2: 116 | X2: 60 | Y2: 6960 | AB2: 0 | AF2: 0 | AJ2: 0 | AN2: 0 | AR2: 0 | AV2: 0 | AZ2: 0 | BD2: 0 | BH2: 0 | BL2: 0 | BP2: 0 | BT2: 0 | BX2: 0 | BZ2: 3262.33 | CA2: 45212.33 | CH2: 45212.33 | CM2: 45212.33 | CO2: 45212.33 | CP2: 0.18 | CQ2: 8138.22 | CR2: 53350.55 | CS2: 250 | CT2: KMS | CU2: 13337637 | CV2: MD0100004 | CW2: DRUM - 28 X 10 X 23 X 2 | CX2: 500
