Workbook

Sheet Sheet1
A1: DOCKET NO. | B1: Base Date | C1: ITEM CODE | D1: PROPOSE ERP ITEM NAME | E1: Propose Drum Type | F1: Insulation Screening(Metallic) | G1: RM Rate(Insulation Screening(Metallic)) | H1: Weight (Insulation Screening (Metallic)) | I1: Cost Insulation Screening(Metallic) | J1: Conductor | K1: RM Rate(Conductor) | L1: Weight(Conductor) | M1: Cost(Conductor) | N1: AL ALLOY | O1: RM Rate(AL Alloy) | P1: Weight(Al Alloy) | Q1: Cost(AL Alloy) | R1: Insulation Screening(Non-Metallic) | S1: RM Rate(Insulation Screening(Non-Metallic)) | T1: Weight(Insulation Screening(Non-Metallic) | U1: Cost(Insulation Screening(Non-Metallic) | V1: Insulation | W1: RM Rate(Insulation) | X1: Weight(Insulation) | Y1: Cost(Insulation) | Z1: Poly Tape | AA1: RM Rate(Poly Tape) | AB1: Weight(Poly Tape) | AC1: Cost(Poly Tape) | AD1: Inner Sheath | AE1: RM Rate(Inner Sheath) | AF1: Weight(Inner Sheath) | AG1: Cost(Inner Sheath) | AH1: Armouring | AI1: RM Rate(Armouring) | AJ1: Weight(Armouring) | AK1: Cost(Armouring) | AL1: Outer Sheath | AM1: RM Rate(Outer Sheath) | AN1: Weight(Outer Sheath) | AO1: Cost(Outer Sheath) | AP1: Filler | AQ1: RM Rate(Filler) | AR1: Weight(Filler) | AS1: Cost(Filler) | AT1: Grease | AU1: RM Rate(Grease) | AV1: Weight(Grease) | AW1: Cost(Grease) | AX1: Water Swellable Tape | AY1: RM Rate(Water Swellable Tape) | AZ1: Weight(Water Swellable Tape) | BA1: Cost(Water Swellable Tape) | BB1: Semi Conducting Water Swellable Tape | BC1: RM Rate(Semi Conducting Water Swellable Tape) | BD1: Weight(Semi Conducting Water Swellable Tape) | BE1: Cost(Semi Conducting Water Swellable Tape) | BF1: Semicon Tape | BG1: RM Rate(Semicon Tape) | BH1: Weight(Semicon Tape) | BI1: Cost(Semicon Tape) | BJ1: Glass Fiber Tape | BK1: RM Rate(Glass Fiber Tape) | BL1: Weight(Glass Fiber Tape) | BM1: Cost(Glass Fiber Tape) | BN1: Copper Wire 0.8MM | BO1: RM Rate(Copper Wire 0.8MM) | BP1: Weight(Copper Wire 0.8MM) | BQ1: Cost(Copper Wire 0.8MM) | BR1: Rubberized Cotton Tape | BS1: RM Rate(Rubberized Cotton Tape) | BT1: Weight(Rubberized Cotton Tape) | BU1: Cost(Rubberized Cotton Tape) | BV1: Water Tight Compound | BW1: RM Rate(Water Tight Compound) | BX1: Weight(Water Tight Compound) | BY1: Cost(Water Tight Compound) | BZ1: Drum Cost Per KM | CA1: Total RM Cost | CB1: FIRM % | CC1: Firm Value | CD1: MFG% | CE1: MFG Value | CF1: PROF% | CG1: Profit Value | CH1: 1st EX-Works | CI1: Intt % | CJ1: Intt Value | CK1: insp% | CL1: Insp Value | CM1: TTR CHARGES% | CN1: TTR Value | CO1: EX-Works Per KM | CP1: Freight Per KM | CQ1: Price Including Freight Per KM | CR1: GST % | CS1: GST Value | CT1: Price Including GST & Freight Per KM | CU1: QTY | CV1: Unit | CW1: Total Price Of Full QTY(Including Freight&GST) | CX1: PARTY LENGTH (IF STANDER LENGTH NOT MATCH WITH PAR | CY1: DRUM CODE | CZ1: DRUM SIZE (FxbXtx Ft)
A2: ENQ-19376-25-26 | C2: FC6200002 | D2: ACSR : DOG CONDUCTOR - 100 SQ. MM. (6/4.72/7/1.57) | E2: WOOD | H2: 0 | J2: Alumimium | L2: 288 | P2: 0 | T2: 0 | X2: 0 | AB2: 0 | AF2: 0 | AH2: ACSR DOG STEEL WIRE | AJ2: 106 | AN2: 0 | AR2: 0 | AV2: 0 | AZ2: 0 | BD2: 0 | BH2: 0 | BL2: 0 | BP2: 0 | BT2: 0 | BX2: 0 | BZ2: 1774.8 | CA2: 1774.8 | CH2: 1774.8 | CO2: 1774.8 | CQ2: 1774.8 | CR2: 0.18 | CS2: 319.46 | CT2: 2094.26 | CU2: 800 | CV2: KMS | CW2: 1675411 | CX2: 2500 | CY2: MD0100015 | CZ2: DRUM - 48 X 20 X 28 X 2.25 - RDSO

Sheet AUTO CALCULATION SHEET (2)
A2: JHARKHAND BIJLI VITRAN NIGAM LIMITED (JBVNL)
A4: TENDER SPECIFICATION NO () | B4: 19/PR/JBVNL/2026-27 (2026_JSEB_113059_1)
A5: TENDER DESCRIPTION () | B5: ISI marked ACSR Dog Conductor
A6: Last Date & Time of Submission () | B6: 05-May-2026 06:00 PM OPENING ON 06-May-2026 06:05 PM
A7: REVERSE AUCTION | B7: Not Mention
A8: Price () | B8: Rate in figures and in words must be quoted in the enclosed proforma of price part on ‘FIRM PRICE’, subject to any statutory change in due course of time, indicating therein Ex-factory price, freight element up to destination, input tax credit under section -171 of CGST/SGST act or scheme to be retained by the supplier.
A9: Validity () | B9: Tenderer should specify the validity period of their offer which should not be less than 180 (One Hundred Eighty) days from the date of opening of tender.
A10: Delivery Period () | B10: Early delivery may be preferred. Monthly delivery schedule for tender quantity i.e. 800 Km. 1st month = Nil, 2nd month = 150 Km, 3rd month = 150 Km, 4th month = 150 Km, 5th month = 150 Km, 6th month = 100 Km, 7th month= 100 km
A11: Payment Terms () | B11: 100% payment will be made by Sr. Manager, JBVNL, Headquarter, Ranchi on submission of 5% Bank Guarantee(0.5% for MSE unit of Jharkhand only) from any Nationalized/Scheduled Bank of ordered value on non-judicial stamp Rs. 100/- (Rupees hundred) only valid for Guarantee period and on receipt of SRV duly signed by the concerned consignee after receipt of the materials in good condition along with approved routine test certificate and duly filled check list for payment from Stores & Purchase wing.
A12: Standard length () | B12: Normal wire length of conductor is 1.25 Km, longer length will be acceptable (short length not less than 1 KM shall be acceptable to the maximum extent of 10% of the quantity ordered.) No. of length in each drum ---- 1 to 4
A13: Packing () | B13: The conductors shall be wound in non-returnable reels of drums confirming to ISS : 1778 / 1961 Specification for reels/drums for Bare wire
A14: Technical Specification
N17: Conductor | V17: AL ALLOY | X17: Insulation Screening (Metallic) | AF17: Insulation Screening (Non-Metallic) | AH17: Insulation | AQ17: POLY TAPE | AR17: Inner Sheath | BA17: Armouring | BL17: Outer Sheath | BX17: FILLER | BY17: GREASE | BZ17: Water swellable Tape | CA17: Semi conducting Water Swellable tape | CB17: SEMICON TAPE | CC17: GLASS FIBER TAPE | CD17: COPPER WIRE 0.8 MM | CE17: RUBBERIZED COTTON TAPE | CF17: Water Tight Compound | CG17: DRUM TYPE | CK17: DRUM COST PER KM | CL17: TOTAL RM COST | CM17: EXTRA CONSUMPTION | CN17: EXTRA CONSUMPTION VALUE | CZ17: $A$1
A18: DOCKET NO. | B18: BASE DATE | C18: ITEM CODE | D18: PROPOSE ERP ITEM NAME | E18: EX-WORKS (PER KM) | F18: FREIGHT PER KM | G18: PRICE INCLUDING FREIGHT (PER KM) | H18: GST % | I18: GST VALUE | J18: PRICE INCLUDING GST & FREIGHT (PER KM) | K18: QTY | L18: Unit | M18: TOTAL PRICE OF FULL QTY (INCLUDING FRIGHT & GST) | N18: Alumimium | O18: Alumimium ALLOY | P18: Copper | Q18: AL-59 | R18: AL-4 | S18: AL-7 | T18: Flexible Copper | U18: Galvanized steel wire | V18: Alumimium | W18: Alumimium ALLOY | X18: Coper tape - 0.1 mm | Y18: Copper Tape - 0.03 mm | Z18: Copper Tape - 0.035 mm | AA18: Copper Tape - 0.04 mm | AB18: Copper Tape - 0.045 mm | AC18: Copper Tape - 0.050 mm | AD18: Copper Tape - 0.060 mm | AE18: Copper Tape - 0.075 mm(DOUBLE) | AF18: Extruded semiconductive | AG18: Extruded Semiconductive(Stripable) | AH18: HT-XLPE | AI18: LT-XLPE | AJ18: TR XLPE | AK18: Type A PVC | AL18: Type C PVC (HR) | AM18: Type A PVC-1.45 | AN18: Type A PVC-FR | AO18: Type A PVC-FRLS | AP18: Type A PVC-1.38 | AQ18: POLY TAPE | AR18: FR PVC Type ST-1 | AS18: FR PVC Type ST-2 | AT18: FRLSH PVC Type ST-1 | AU18: FRLSH PVC Type ST-2 | AV18: PVC Type ST-1 | AW18: PVC Type ST-1-PRESSURE EXTRUDED | AX18: PVC Type ST-2 | AY18: PVC COMPOUND 1.48 | AZ18: PVC Type ST-2-PRESSURE EXTRUDED | BA18: ACSR CORE WIRE | BB18: ACSR DOG STEEL WIRE | BC18: Aluminium Flat Strip | BD18: Aluminium Round Wire | BE18: Alumimium Tape | BF18: Double Steel Tape | BG18: Galvanised Steel Flat Strip | BH18: Galvanised Steel Flat Strip (Double) | BI18: Galvanised Steel Flat Strip-B | BJ18: Galvanised Steel Round Wire | BK18: Galvanised Steel Round Wire (Double) | BL18: FR PVC Type ST-1 | BM18: FR PVC Type ST-2 | BN18: FRLSH PVC Type ST-1 | BO18: FRLSH PVC Type ST-2 | BP18: ZHFR | BQ18: PE-ST-3 | BR18: PE-ST-7 | BS18: PVC Type ST-1 | BT18: PVC Type ST-2 | BU18: PVC COMPOUND 1.48 | BV18: PVC Type ST-2-PRESSURE EXTRUDED | BW18: UV & Track Resistant XLPE | BX18: FILLER | BY18: Grease | BZ18: Water swellable Tape | CA18: Semi conducting Water Swellable tape | CB18: SEMICON TAPE | CC18: GLASS FIBER TAPE | CD18: COPPER WIRE 0.8 MM | CE18: RUBBERIZED COTTON TAPE | CF18: Water Tight Compound | CG18: PROPOSE DRUM TYPE | CH18: DRUM CODE | CI18: DRUM SIZE (FxbXtx Ft) | CJ18: PARTY STANDARD LENGTH (MTR) | CO18: MFG% | CP18: MFG VALUE | CQ18: PROF% | CR18: PROFIT VALUE | CS18: 1ST EX-WORKS | CT18: Intt % | CU18: INTT VALUE | CV18: insp% | CW18: INSP VALUE | CX18: TTR Charges% | CY18: TTR Charges VALUE
N19: 392 | O19: =+IFERROR(VLOOKUP($O$18,Sheet1!J:L,2,0),0) -> 0 | P19: =+IFERROR(VLOOKUP($P$18,Sheet1!J:M,2,0),0) -> 0 | Q19: =+IFERROR(VLOOKUP($Q$18,Sheet1!J:M,2,0),0) -> 0 | R19: =+IFERROR(VLOOKUP($R$18,Sheet1!J:M,2,0),0) -> 0 | S19: =+IFERROR(VLOOKUP($S$18,Sheet1!J:M,2,0),0) -> 0 | T19: =+IFERROR(VLOOKUP($T$18,Sheet1!J:M,2,0),0) -> 0 | U19: =+IFERROR(VLOOKUP($U$18,Sheet1!J:M,2,0),0) -> 0 | V19: =+IFERROR(VLOOKUP($V$18,Sheet1!N:Q,2,0),0) -> 0 | W19: =+IFERROR(VLOOKUP($W$18,Sheet1!N:O,2,0),0) -> 0 | X19: =+IFERROR(VLOOKUP($X$18,Sheet1!F:I,2,0),0) -> 0 | Y19: =+IFERROR(VLOOKUP($Y$18,Sheet1!F:I,2,0),0) -> 0 | Z19: =+IFERROR(VLOOKUP($Z$18,Sheet1!F:I,2,0),0) -> 0 | AA19: =+IFERROR(VLOOKUP($AA$18,Sheet1!F:I,2,0),0) -> 0 | AB19: =+IFERROR(VLOOKUP($AB$18,Sheet1!F:I,2,0),0) -> 0 | AC19: =+IFERROR(VLOOKUP($AC$18,Sheet1!F:I,2,0),0) -> 0 | AD19: =+IFERROR(VLOOKUP($AD$18,Sheet1!F:I,2,0),0) -> 0 | AE19: =+IFERROR(VLOOKUP($AE$18,Sheet1!F:I,2,0),0) -> 0 | AF19: =+IFERROR(VLOOKUP($AF$18,Sheet1!R:U,2,0),0) -> 0 | AG19: =+IFERROR(VLOOKUP($AG$18,Sheet1!R:U,2,0),0) -> 0 | AH19: =+IFERROR(VLOOKUP($AH$18,Sheet1!V:Y,2,0),0) -> 0 | AI19: =+IFERROR(VLOOKUP($AI$18,Sheet1!V:Y,2,0),0) -> 0 | AJ19: =+IFERROR(VLOOKUP($AJ$18,Sheet1!V:Y,2,0),0) -> 0 | AK19: =+IFERROR(VLOOKUP($AK$18,Sheet1!V:Y,2,0),0) -> 0 | AL19: =+IFERROR(VLOOKUP($AL$18,Sheet1!V:Y,2,0),0) -> 0 | AM19: =+IFERROR(VLOOKUP($AM$18,Sheet1!V:Y,2,0),0) -> 0 | AN19: =+IFERROR(VLOOKUP($AN$18,Sheet1!V:Y,2,0),0) -> 0 | AO19: =+IFERROR(VLOOKUP($AO$18,Sheet1!V:Y,2,0),0) -> 0 | AP19: =+IFERROR(VLOOKUP($AP$18,Sheet1!V:Y,2,0),0) -> 0 | AQ19: =+IFERROR(VLOOKUP($AQ$18,Sheet1!Z2:AA840,2,0),0) -> 0 | AR19: =+IFERROR(VLOOKUP($AR$18,Sheet1!AD2:AG840,2,0),0) -> 0 | AS19: =+IFERROR(VLOOKUP($AS$18,Sheet1!AD2:AG840,2,0),0) -> 0 | AT19: =+IFERROR(VLOOKUP($AT$18,Sheet1!AD2:AG840,2,0),0) -> 0 | AU19: =+IFERROR(VLOOKUP($AU$18,Sheet1!AD2:AG840,2,0),0) -> 0 | AV19: =+IFERROR(VLOOKUP($AV$18,Sheet1!AD2:AG840,2,0),0) -> 0 | AW19: =+IFERROR(VLOOKUP($AW$18,Sheet1!AD2:AG840,2,0),0) -> 0 | AX19: =+IFERROR(VLOOKUP($AX$18,Sheet1!AD2:AG840,2,0),0) -> 0 | AY19: =+IFERROR(VLOOKUP($AY$18,Sheet1!AD2:AG840,2,0),0) -> 0 | AZ19: =+IFERROR(VLOOKUP($AZ$18,Sheet1!AD2:AG840,2,0),0) -> 0 | BA19: =+IFERROR(VLOOKUP($BA$18,Sheet1!AH2:AK840,2,0),0) -> 0 | BB19: 102 | BC19: =+IFERROR(VLOOKUP($BC$18,Sheet1!AH2:AK840,2,0),0) -> 0 | BD19: =+IFERROR(VLOOKUP($BD$18,Sheet1!AH2:AK840,2,0),0) -> 0 | BE19: =+IFERROR(VLOOKUP($BE$18,Sheet1!AH2:AK840,2,0),0) -> 0 | BF19: =+IFERROR(VLOOKUP($BF$18,Sheet1!AH2:AK840,2,0),0) -> 0 | BG19: =+IFERROR(VLOOKUP($BG$18,Sheet1!AH2:AK840,2,0),0) -> 0 | BH19: =+IFERROR(VLOOKUP($BH$18,Sheet1!AH2:AK840,2,0),0) -> 0 | BI19: =+IFERROR(VLOOKUP($BI$18,Sheet1!AH2:AK840,2,0),0) -> 0 | BJ19: =+IFERROR(VLOOKUP($BJ$18,Sheet1!AH2:AK840,2,0),0) -> 0 | BK19: =+IFERROR(VLOOKUP($BK$18,Sheet1!AH2:AK840,2,0),0) -> 0 | BL19: =+IFERROR(VLOOKUP($BL$18,Sheet1!AL2:AO840,2,0),0) -> 0 | BM19: =+IFERROR(VLOOKUP($BM$18,Sheet1!AL2:AO840,2,0),0) -> 0 | BN19: =+IFERROR(VLOOKUP($BN$18,Sheet1!AL2:AO840,2,0),0) -> 0 | BO19: =+IFERROR(VLOOKUP($BO$18,Sheet1!AL2:AO840,2,0),0) -> 0 | BP19: =+IFERROR(VLOOKUP($BP$18,Sheet1!AL2:AO840,2,0),0) -> 0 | BQ19: =+IFERROR(VLOOKUP($BQ$18,Sheet1!AL2:AO840,2,0),0) -> 0 | BR19: =+IFERROR(VLOOKUP($BR$18,Sheet1!AL2:AO840,2,0),0) -> 0 | BS19: =+IFERROR(VLOOKUP($BS$18,Sheet1!AL2:AO840,2,0),0) -> 0 | BT19: =+IFERROR(VLOOKUP($BT$18,Sheet1!AL2:AO840,2,0),0) -> 0 | BU19: =+IFERROR(VLOOKUP($BU$18,Sheet1!AL2:AO840,2,0),0) -> 0 | BV19: =+IFERROR(VLOOKUP($BV$18,Sheet1!AL2:AO840,2,0),0) -> 0 | BW19: =+IFERROR(VLOOKUP($BW$18,Sheet1!AL2:AO840,2,0),0) -> 0 | BX19: =+IFERROR(VLOOKUP($BX$18,Sheet1!AP2:AS840,2,0),0) -> 0 | BY19: =+IFERROR(VLOOKUP($BY$18,Sheet1!AT2:AW840,2,0),0) -> 0 | BZ19: =+IFERROR(VLOOKUP($BZ$18,Sheet1!AX2:BA840,2,0),0) -> 0 | CA19: =+IFERROR(VLOOKUP($CA$18,Sheet1!BB2:BE840,2,0),0) -> 0 | CB19: =+IFERROR(VLOOKUP($CB$18,Sheet1!BF2:BI840,2,0),0) -> 0 | CC19: =+IFERROR(VLOOKUP($CC$18,Sheet1!BJ2:BM840,2,0),0) -> 0 | CD19: =+IFERROR(VLOOKUP($CD$18,Sheet1!BN2:BQ840,2,0),0) -> 0 | CE19: =+IFERROR(VLOOKUP($CE$18,Sheet1!BR2:BU840,2,0),0) -> 0 | CF19: =+IFERROR(VLOOKUP($CF$18,Sheet1!BV2:BY840,2,0),0) -> 0
A20: =Sheet1!A2 -> ENQ-19376-25-26 | B20: 46144 | C20: =Sheet1!C2 -> FC6200002 | D20: =Sheet1!D2 -> ACSR : DOG CONDUCTOR - 100 SQ. MM. (6/4.72/7/1.57) | E20: =CS20+CU20+CW20+CY20 -> 149339.26 | F20: =ROUNDUP(M25,0) -> 1093 | G20: =E20+F20 -> 150432.26 | H20: =Sheet1!CR2 -> 0.18 | I20: =G20*H20 -> 27077.806 | J20: =G20+I20 -> 177510.06 | K20: =Sheet1!CU2 -> 800 | L20: =Sheet1!CV2 -> KMS | M20: =J20*K20 -> 1.4200805e+08 | N20: =+IFERROR(VLOOKUP($N$18,Sheet1!J2:L2,3,0),0) -> 288 | O20: =+IFERROR(VLOOKUP($O$18,Sheet1!J2:L2,3,0),0) -> 0 | P20: =+IFERROR(VLOOKUP($P$18,Sheet1!J2:M2,3,0),0) -> 0 | Q20: =+IFERROR(VLOOKUP($Q$18,Sheet1!J2:M2,3,0),0) -> 0 | R20: =+IFERROR(VLOOKUP($R$18,Sheet1!J2:M2,3,0),0) -> 0 | S20: =+IFERROR(VLOOKUP($S$18,Sheet1!J2:M2,3,0),0) -> 0 | T20: =+IFERROR(VLOOKUP($T$18,Sheet1!J2:M2,3,0),0) -> 0 | U20: =+IFERROR(VLOOKUP($U$18,Sheet1!J2:M2,3,0),0) -> 0 | V20: =+IFERROR(VLOOKUP($V$18,Sheet1!N2:Q2,3,0),0) -> 0 | W20: =+IFERROR(VLOOKUP($W$18,Sheet1!N2:Q2,3,0),0) -> 0 | X20: =+IFERROR(VLOOKUP($X$18,Sheet1!F2:I2,3,0),0) -> 0 | Y20: =+IFERROR(VLOOKUP($Y$18,Sheet1!F2:I2,3,0),0) -> 0 | Z20: =+IFERROR(VLOOKUP($Z$18,Sheet1!F2:I2,3,0),0) -> 0 | AA20: =+IFERROR(VLOOKUP($AA$18,Sheet1!F2:I2,3,0),0) -> 0 | AB20: =+IFERROR(VLOOKUP($AB$18,Sheet1!F2:I2,3,0),0) -> 0 | AC20: =+IFERROR(VLOOKUP($AC$18,Sheet1!F2:I2,3,0),0) -> 0 | AD20: =+IFERROR(VLOOKUP($AD$18,Sheet1!F2:I2,3,0),0) -> 0 | AE20: =+IFERROR(VLOOKUP($AE$18,Sheet1!F2:I2,3,0),0) -> 0 | AF20: =+IFERROR(VLOOKUP($AF$18,Sheet1!R2:U2,3,0),0) -> 0 | AG20: =+IFERROR(VLOOKUP($AG$18,Sheet1!R2:U2,3,0),0) -> 0 | AH20: =+IFERROR(VLOOKUP($AH$18,Sheet1!V2:Y2,3,0),0) -> 0 | AI20: =+IFERROR(VLOOKUP($AI$18,Sheet1!V2:Y2,3,0),0) -> 0 | AJ20: =+IFERROR(VLOOKUP($AJ$18,Sheet1!V2:Y2,3,0),0) -> 0 | AK20: =+IFERROR(VLOOKUP($AK$18,Sheet1!V2:Y2,3,0),0) -> 0 | AL20: =+IFERROR(VLOOKUP($AL$18,Sheet1!V2:Y2,3,0),0) -> 0 | AM20: =+IFERROR(VLOOKUP($AM$18,Sheet1!V2:Y2,3,0),0) -> 0 | AN20: =+IFERROR(VLOOKUP($AN$18,Sheet1!V2:Y2,3,0),0) -> 0 | AO20: =+IFERROR(VLOOKUP($AO$18,Sheet1!V2:Y2,3,0),0) -> 0 | AP20: =+IFERROR(VLOOKUP($AP$18,Sheet1!V2:Y2,3,0),0) -> 0 | AQ20: =+IFERROR(VLOOKUP($AQ$18,Sheet1!Z2:AB2,3,0),0) -> 0 | AR20: =+IFERROR(VLOOKUP($AR$18,Sheet1!AD2:AG2,3,0),0) -> 0 | AS20: =+IFERROR(VLOOKUP($AS$18,Sheet1!AD2:AG2,3,0),0) -> 0 | AT20: =+IFERROR(VLOOKUP($AT$18,Sheet1!AD2:AG2,3,0),0) -> 0 | AU20: =+IFERROR(VLOOKUP($AU$18,Sheet1!AD2:AG2,3,0),0) -> 0 | AV20: =+IFERROR(VLOOKUP($AV$18,Sheet1!AD2:AG2,3,0),0) -> 0 | AW20: =+IFERROR(VLOOKUP($AW$18,Sheet1!AD2:AG2,3,0),0) -> 0 | AX20: =+IFERROR(VLOOKUP($AX$18,Sheet1!AD2:AG2,3,0),0) -> 0 | AY20: =+IFERROR(VLOOKUP($AY$18,Sheet1!AD2:AG2,3,0),0) -> 0 | AZ20: =+IFERROR(VLOOKUP($AZ$18,Sheet1!AD2:AG2,3,0),0) -> 0 | BA20: =+IFERROR(VLOOKUP($BA$18,Sheet1!AH2:AK2,3,0),0) -> 0 | BB20: =+IFERROR(VLOOKUP($BB$18,Sheet1!AH2:AK2,3,0),0) -> 106 | BC20: =+IFERROR(VLOOKUP($BC$18,Sheet1!AH2:AK2,3,0),0) -> 0 | BD20: =+IFERROR(VLOOKUP($BD$18,Sheet1!AH2:AK2,3,0),0) -> 0 | BE20: =+IFERROR(VLOOKUP($BE$18,Sheet1!AH2:AK2,3,0),0) -> 0 | BF20: =+IFERROR(VLOOKUP($BF$18,Sheet1!AH2:AK2,3,0),0) -> 0 | BG20: =+IFERROR(VLOOKUP($BG$18,Sheet1!AH2:AK2,3,0),0) -> 0 | BH20: =+IFERROR(VLOOKUP($BH$18,Sheet1!AH2:AK2,3,0),0) -> 0 | BI20: =+IFERROR(VLOOKUP($BI$18,Sheet1!AH2:AK2,3,0),0) -> 0 | BJ20: =+IFERROR(VLOOKUP($BJ$18,Sheet1!AH2:AK2,3,0),0) -> 0 | BK20: =+IFERROR(VLOOKUP($BK$18,Sheet1!AH2:AK2,3,0),0) -> 0 | BL20: =+IFERROR(VLOOKUP($BL$18,Sheet1!AL2:AO2,3,0),0) -> 0 | BM20: =+IFERROR(VLOOKUP($BM$18,Sheet1!AL2:AO2,3,0),0) -> 0 | BN20: =+IFERROR(VLOOKUP($BN$18,Sheet1!AL2:AO2,3,0),0) -> 0 | BO20: =+IFERROR(VLOOKUP($BO$18,Sheet1!AL2:AO2,3,0),0) -> 0 | BP20: =+IFERROR(VLOOKUP($BP$18,Sheet1!AL2:AO2,3,0),0) -> 0 | BQ20: =+IFERROR(VLOOKUP($BQ$18,Sheet1!AL2:AO2,3,0),0) -> 0 | BR20: =+IFERROR(VLOOKUP($BR$18,Sheet1!AL2:AO2,3,0),0) -> 0 | BS20: =+IFERROR(VLOOKUP($BS$18,Sheet1!AL2:AO2,3,0),0) -> 0 | BT20: =+IFERROR(VLOOKUP($BT$18,Sheet1!AL2:AO2,3,0),0) -> 0 | BU20: =+IFERROR(VLOOKUP($BU$18,Sheet1!AL2:AO2,3,0),0) -> 0 | BV20: =+IFERROR(VLOOKUP($BV$18,Sheet1!AL2:AO2,3,0),0) -> 0 | BW20: =+IFERROR(VLOOKUP($BW$18,Sheet1!AL2:AO2,3,0),0) -> 0 | BX20: =+IFERROR(VLOOKUP($BX$18,Sheet1!AP2:AS2,3,0),0) -> 0 | BY20: =+IFERROR(VLOOKUP($BY$18,Sheet1!AT2:AW2,3,0),0) -> 0 | BZ20: =+IFERROR(VLOOKUP($BZ$18,Sheet1!AX2:BA2,3,0),0) -> 0 | CA20: =+IFERROR(VLOOKUP($CA$18,Sheet1!BB2:BE2,3,0),0) -> 0 | CB20: =+IFERROR(VLOOKUP($CB$18,Sheet1!BF2:BI2,3,0),0) -> 0 | CC20: =+IFERROR(VLOOKUP($CC$18,Sheet1!BJ2:BM2,3,0),0) -> 0 | CD20: =+IFERROR(VLOOKUP($CD$18,Sheet1!BN2:BQ2,3,0),0) -> 0 | CE20: =+IFERROR(VLOOKUP($CE$18,Sheet1!BR2:BU2,3,0),0) -> 0 | CF20: =+IFERROR(VLOOKUP($CF$18,Sheet1!BV2:BY2,3,0),0) -> 0 | CG20: =Sheet1!E2 -> WOOD | CH20: MD0100013 | CI20: DRUM-1220 X 600 X 710 | CJ20: =Sheet1!CX2 -> 2500 | CK20: =2894/2.5 -> 1157.6 | CL20: =SUMPRODUCT($N$19:$CF$19,N20:CF20)+CK20 -> 124865.6 | CM20: =Sheet1!CB2 -> 0 | CN20: =CL20*CM20 -> 0 | CO20: 0.15 | CP20: =CL20*CO20 -> 18729.84 | CQ20: 0 | CR20: =CL20*CQ20 -> 0 | CS20: =CL20+CN20+CP20+CR20 -> 143595.44 | CT20: 0.02 | CU20: =CS20*CT20 -> 2871.9088 | CV20: 0.02 | CW20: =CS20*CV20 -> 2871.9088 | CX20: =Sheet1!CM2 -> 0 | CY20: =CX20*CS20 -> 0
E24: Order Quantity | F24: Stnd Length | G24: Truck type | H24: Fare of one truck | I24: No of Drum in one truck | J24: Total length in one Truck | K24: No of Truck | L24: Total Freight | M24: Freight per KM | BB24: conductor wegiht | CG24: drum weight | CH24: conductor+drum weight | CI24: truck weight
E25: =K20 -> 800 | F25: =CJ20/1000 -> 2.5 | G25: 16 MT | H25: 38000 | I25: 14 | J25: =F25*I25 -> 35 | K25: =ROUNDUP((E25/J25),0) -> 23 | L25: =H25*K25 -> 874000 | M25: =L25/E25 -> 1092.5 | BB25: =N20+BB20 -> 394 | CG25: =125+25 -> 150 | CH25: =((BB25*F25)+CG25) -> 1135 | CI25: =CH25*I25 -> 15890

Sheet terms
A1: The quoted prices are on Firm inclusive of packing and forwading but exclusive of GST Statutory levies.
A2: The quoted prices are on VARIABLE basis with PV base Date: DD/MM/YYYY as per "IEEMA", inclusive of packing and forwading but exclusive of GST Statutory levies.
A4: The above prices are quoted on Ex-works basis, where freight will be charged extra.
A5: The above prices are quoted on FOR Destination basis, where freight is included, refer Price offer.
A6: The above prices are quoted on Ex-works+Freight basis.
A8: 20% Advance and Balance against PI (Proforma Invoice) prior to dispatch
A9: 100% against "90 days" LC, where 90 days usance interest will be borne by LPIPL
A10: 100% against "120 days" LC, where 120 days usance interest will be borne by LPIPL
A11: 100% against "45 days" LC, where 45 days usance interest will be borne by LPIPL
A12: 100% against "60 days" LC, where 60 days usance interest will be borne by LPIPL
A13: 100% against "30 days" LC, where 30 days usance interest will be borne by LPIPL
A14: 100% against 60 days PDC from the date of MRC/MRN
... A27: Negotiable
