Workbook

Sheet Sheet1
A1: DOCKET NO. | B1: Base Date | C1: ITEM CODE | D1: PROPOSE ERP ITEM NAME | E1: Propose Drum Type | F1: Insulation Screening(Metallic) | G1: RM Rate(Insulation Screening(Metallic)) | H1: Weight (Insulation Screening (Metallic)) | I1: Cost Insulation Screening(Metallic) | J1: Conductor | K1: RM Rate(Conductor) | L1: Weight(Conductor) | M1: Cost(Conductor) | N1: AL ALLOY | O1: RM Rate(AL Alloy) | P1: Weight(Al Alloy) | Q1: Cost(AL Alloy) | R1: Insulation Screening(Non-Metallic) | S1: RM Rate(Insulation Screening(Non-Metallic)) | T1: Weight(Insulation Screening(Non-Metallic) | U1: Cost(Insulation Screening(Non-Metallic) | V1: Insulation | W1: RM Rate(Insulation) | X1: Weight(Insulation) | Y1: Cost(Insulation) | Z1: Poly Tape | AA1: RM Rate(Poly Tape) | AB1: Weight(Poly Tape) | AC1: Cost(Poly Tape) | AD1: Inner Sheath | AE1: RM Rate(Inner Sheath) | AF1: Weight(Inner Sheath) | AG1: Cost(Inner Sheath) | AH1: Armouring | AI1: RM Rate(Armouring) | AJ1: Weight(Armouring) | AK1: Cost(Armouring) | AL1: Outer Sheath | AM1: RM Rate(Outer Sheath) | AN1: Weight(Outer Sheath) | AO1: Cost(Outer Sheath) | AP1: Filler | AQ1: RM Rate(Filler) | AR1: Weight(Filler) | AS1: Cost(Filler) | AT1: Grease | AU1: RM Rate(Grease) | AV1: Weight(Grease) | AW1: Cost(Grease) | AX1: Water Swellable Tape | AY1: RM Rate(Water Swellable Tape) | AZ1: Weight(Water Swellable Tape) | BA1: Cost(Water Swellable Tape) | BB1: Semi Conducting Water Swellable Tape | BC1: RM Rate(Semi Conducting Water Swellable Tape) | BD1: Weight(Semi Conducting Water Swellable Tape) | BE1: Cost(Semi Conducting Water Swellable Tape) | BF1: Semicon Tape | BG1: RM Rate(Semicon Tape) | BH1: Weight(Semicon Tape) | BI1: Cost(Semicon Tape) | BJ1: Glass Fiber Tape | BK1: RM Rate(Glass Fiber Tape) | BL1: Weight(Glass Fiber Tape) | BM1: Cost(Glass Fiber Tape) | BN1: Copper Wire 0.8MM | BO1: RM Rate(Copper Wire 0.8MM) | BP1: Weight(Copper Wire 0.8MM) | BQ1: Cost(Copper Wire 0.8MM) | BR1: Rubberized Cotton Tape | BS1: RM Rate(Rubberized Cotton Tape) | BT1: Weight(Rubberized Cotton Tape) | BU1: Cost(Rubberized Cotton Tape) | BV1: Water Tight Compound | BW1: RM Rate(Water Tight Compound) | BX1: Weight(Water Tight Compound) | BY1: Cost(Water Tight Compound) | BZ1: Drum Cost Per KM | CA1: Total RM Cost | CB1: FIRM % | CC1: Firm Value | CD1: MFG% | CE1: MFG Value | CF1: PROF% | CG1: Profit Value | CH1: 1st EX-Works | CI1: Intt % | CJ1: Intt Value | CK1: insp% | CL1: Insp Value | CM1: EX-Works Per KM | CN1: Freight Per KM | CO1: Price Including Freight Per KM | CP1: GST % | CQ1: GST Value | CR1: Price Including GST & Freight Per KM | CS1: QTY | CT1: Unit | CU1: Total Price Of Full QTY(Including Freight&GST) | CV1: DRUM CODE | CW1: DRUM SIZE (FxbXtx Ft) | CX1: Party Standard Length(MTR)
A2: ENQ-15363-22-23 | B2: 45658 | C2: FA0400012 | D2: 3 CORE X 120 SQ MM + 1 CORE X 120 SQ MM (AB CABLES) (BARE) - 11 KV | E2: STEEL | F2: Copper Tape - 0.060 mm | G2: 940.2 | H2: 124 | I2: 116584.8 | J2: Alumimium | K2: 254.47 | L2: 977 | M2: 248617.19 | N2: Alumimium Alloy | O2: 261.47 | P2: 325 | Q2: 84977.75 | R2: Extruded Semiconductive | S2: 180 | T2: 191 | U2: 34380 | V2: HT-XLPE | W2: 140 | X2: 577 | Y2: 80780 | AB2: 31 | AF2: 0 | AJ2: 0 | AL2: PVC Type ST-2 | AM2: 71.74 | AN2: 706 | AO2: 50648.44 | AR2: 0 | AV2: 0 | AZ2: 0 | BD2: 0 | BH2: 0 | BL2: 0 | BP2: 0 | BT2: 0 | BX2: 0 | BZ2: 60800 | CA2: 676788.18 | CH2: 676788.18 | CM2: 676788.18 | CO2: 676788.18 | CP2: 0.18 | CQ2: 121821.87 | CR2: 798610.05 | CS2: 22 | CT2: KMS | CU2: 17569421 | CV2: SP0400141 | CW2: CORRUGATED DISPATCH STEEL DRUM 2080 X 1000 X 1400 MM
A3: ENQ-15363-22-23 | B3: 45658 | C3: FA1300004 | D3: 3 CORE X 300 SQ. MM. AL/ARM - STRIP (XLPE) - 11 KV | H3: 0 | L3: 2430 | P3: 0 | T3: 337 | X3: 802 | AB3: 0 | AF3: 277 | AJ3: 1125 | AN3: 995 | AR3: 1258 | AV3: 0 | AZ3: 0 | BD3: 0 | BH3: 0 | BL3: 88 | BP3: 0 | BT3: 0 | BX3: 0 | CP3: 0.18 | CS3: 150 | CT3: KMS
A4: ENQ-15363-22-23 | B4: 45658 | C4: FA1300006 | D4: 3 CORE X 70 SQ. MM. AL/ARM - STRIP (XLPE) - 11 KV | H4: 0 | L4: 567 | P4: 0 | T4: 188 | X4: 474 | AB4: 0 | AF4: 142 | AJ4: 750 | AN4: 474 | AR4: 533 | AV4: 0 | AZ4: 0 | BD4: 0 | BH4: 0 | BL4: 0 | BP4: 0 | BT4: 0 | BX4: 0 | CP4: 0.18 | CS4: 14 | CT4: KMS
A5: ENQ-15363-22-23 | B5: 45658 | C5: FA1300010 | D5: 3 CORE X 400 SQ. MM. AL/ARM - STRIP (XLPE) - 33 KV | H5: 0 | L5: 3240 | P5: 0 | T5: 427 | X5: 2621 | AB5: 0 | AF5: 405 | AJ5: 1600 | AN5: 1560 | AR5: 2672 | AV5: 0 | AZ5: 162 | BD5: 0 | BH5: 52 | BL5: 129 | BP5: 0 | BT5: 0 | BX5: 0 | CP5: 0.18 | CS5: 77 | CT5: KMS
A6: ENQ-15363-22-23 | B6: 45658 | C6: FA1300052 | D6: 3 CORE X 150 SQ. MM. AL/ARM - STRIP (XLPE) - 11 KV | H6: 0 | L6: 1215 | P6: 0 | T6: 246 | X6: 620 | AB6: 0 | AF6: 200 | AJ6: 900 | AN6: 672 | AR6: 809 | AV6: 0 | AZ6: 0 | BD6: 0 | BH6: 0 | BL6: 0 | BP6: 0 | BT6: 0 | BX6: 0 | CP6: 0.18 | CS6: 12 | CT6: KMS

Sheet AUTO CALCULATION SHEET (2)
A2: Noida Power Company Ltd.
A4: TENDER SPECIFICATION NO () | B4: NPCL/FY24-25/HTCAB/029 Dated 11.02.2025
A5: TENDER DESCRIPTION () | B5: TENDER NOTIFICATION FOR ANNUAL RATE CONTRACT OF SUPPLY OF HT and HT ABC CABLE
A6: Last Date & Time of Submission () | B6: 04.03.2025 (up to 15:30 hours)
A7: REVERSE AUCTION | B7: Purchaser reserves the right to use Reverse Auction through SAP-SRM as an optional tool as an integral part of the entire tendering process. All techno-commercially qualified bidders shall participate in this event.
A8: Price () | B8: Prices quoted by the Bidder shall be “As per latest IEEMA Price Variation Clause”. After finalization of the tender, Rate Contract shall be issued to the successful bidder with a validity period of One Year. FEB 2025 is the Base Month for PVC (IEEMA Circular JAN 2025). Within the validity of the rate contract and as per requirement of material, release order shall be issued from time to time.
A9: Validity () | B9: Bids shall remain valid for 120 days from the due date of submission of the Bid & subsequent corrigendum / amendment / extension of due date of submission.
A10: Delivery Period () | B10: 45 Days from the date of issuance of LOI / Order; however, firm delivery dates will be mentioned in the LOI / Order.
A11: Payment Terms () | B11: 20% payment shall be paid as interest free advance against submission of Advance Bank Guarantee (ABG) of a nationalized/scheduled bank(s) located at State Capital/Delhi NCR, payable at Delhi/Noida / Corporate Guarantee as may be acceptable to the NPCL, for the equal amount valid up to the PO supply completion period plus 3 months claim period. In case of delay, the BG shall be extended suitably by the bidder. Bidder can request to submit Corporate guarantee in place of ABG, Same request can be considered with discretion of NPCL management only. 75% Payment shall be released on pro-rata basic within 45 days from the receipt of material at NPCL site with complete set of documents as mentioned in order. Your invoices complete in all respect along with all required documents should reach our office within 3 days. Any delay in submission of any of these documents will be to your account. It may please be noted that for payment purposes the date of receipt of documents will be considered on the basis of the date of receipt of last document, in case partial documents were received earlier.
A12: Standard length ()
A13: Packing ()
A14: Technical Specification
O16: =Sheet1!J1 -> Conductor | T16: AL ALLOY | V16: Insulation Screening (Metallic) | AD16: Insulation Screening (Non-Metallic) | AF16: Insulation | AL16: POLY TAPE | AM16: Inner Sheath | AT16: Armouring | BD16: Outer Sheath | BN16: FILLER | BO16: GREASE | BP16: Water swellable Tape | BQ16: Semi conducting Water Swellable tape | BR16: SEMICON TAPE | BS16: GLASS FIBER TAPE | BT16: COPPER WIRE 0.8 MM | BU16: RUBBERIZED COTTON TAPE | BV16: Water Tight Compound | CC16: DRUM COST PER KM | CD16: TOTAL RM COST | CE16: EXTRA CONSUMPTION | CF16: EXTRA CONSUMPTION VALUE
A17: DOCKET NO. | B17: =Sheet1!B1 -> Base Date | C17: ITEM CODE | D17: PROPOSE ERP ITEM NAME | E17: ERP NAME | F17: EX-WORKS (PER KM) | G17: FREIGHT PER KM | H17: PRICE INCLUDING FREIGHT (PER KM) | I17: GST % | J17: GST VALUE | K17: PRICE INCLUDING GST & FREIGHT (PER KM) | L17: QTY | M17: Unit | N17: TOTAL PRICE OF FULL QTY (INCLUDING FRIGHT & GST) | O17: Alumimium | P17: Alumimium ALLOY | Q17: Copper | R17: Flexible Copper | S17: Galvanized steel wire | T17: Alumimium | U17: Alumimium ALLOY | V17: Coper tape - 0.1 mm | W17: Copper Tape - 0.03 mm | X17: Copper Tape - 0.035 mm | Y17: Copper Tape - 0.04 mm | Z17: Copper Tape - 0.045 mm | AA17: Copper Tape - 0.050 mm | AB17: Copper Tape - 0.060 mm | AC17: Copper Tape - 0.075 mm(DOUBLE) | AD17: Extruded semiconductive | AE17: Extruded Semiconductive(Stripable) | AF17: HT-XLPE | AG17: LT-XLPE | AH17: TR XLPE | AI17: Type A PVC | AJ17: Type C PVC (HR) | AK17: XLPE | AL17: POLY TAPE | AM17: FR PVC Type ST-1 | AN17: FR PVC Type ST-2 | AO17: FRLSH PVC Type ST-2 | AP17: PVC Type ST-1 | AQ17: PVC Type ST-1-PRESSURE EXTRUDED | AR17: PVC Type ST-2 | AS17: PVC Type ST-2-PRESSURE EXTRUDED | AT17: ACSR CORE WIRE | AU17: ACSR DOG STEEL WIRE | AV17: Aluminium Flat Strip | AW17: Aluminium Round Wire | AX17: Double Steel Tape | AY17: Galvanised Steel Flat Strip | AZ17: Galvanised Steel Flat Strip (Double) | BA17: Galvanised Steel Flat Strip-B | BB17: Galvanised Steel Round Wire | BC17: Galvanised Steel Round Wire (Double) | BD17: FR PVC Type ST-1 | BE17: FR PVC Type ST-2 | BF17: FRLSH PVC Type ST-1 | BG17: FRLSH PVC Type ST-2 | BH17: PE, ST-3 | BI17: PE, ST-7 | BJ17: PVC Type ST-1 | BK17: PVC Type ST-2 | BL17: PVC Type ST-2-PRESSURE EXTRUDED | BM17: UV & Track Resistant XLPE | BN17: FILLER | BO17: Grease | BP17: Water swellable Tape | BQ17: Semi conducting Water Swellable tape | BR17: SEMICON TAPE | BS17: GLASS FIBER TAPE | BT17: COPPER WIRE 0.8 MM | BU17: RUBBERIZED COTTON TAPE | BV17: Water Tight Compound | BW17: =Sheet1!E1 -> Propose Drum Type | BX17: WEIGHT OF CABLE | BY17: OD | BZ17: =Sheet1!CV1 -> DRUM CODE | CA17: =Sheet1!CW1 -> DRUM SIZE (FxbXtx Ft) | CB17: =Sheet1!CX1 -> Party Standard Length(MTR) | CG17: MFG% | CH17: MFG VALUE | CI17: PROF% | CJ17: PROFIT VALUE | CK17: 1ST EX-WORKS | CL17: Intt % | CM17: INTT VALUE | CN17: insp% | CO17: INSP VALUE
O18: 262 | U18: =O18+7 -> 269 | Y18: 984 | AB18: 984 | AD18: 175 | AF18: 160 | AR18: 69 | AY18: 72 | BK18: 69 | BN18: 28 | BO18: =+IFERROR(VLOOKUP($BO$17,Sheet1!AT2:AW840,2,0),0) -> 0 | BP18: =+IFERROR(VLOOKUP($BP$17,Sheet1!AX2:BA840,2,0),0) -> 0 | BQ18: =+IFERROR(VLOOKUP($BQ$17,Sheet1!BB2:BE840,2,0),0) -> 0 | BR18: =+IFERROR(VLOOKUP($BR$17,Sheet1!BF2:BI840,2,0),0) -> 0 | BS18: =+IFERROR(VLOOKUP($BS$17,Sheet1!BJ2:BM840,2,0),0) -> 0 | BT18: =+IFERROR(VLOOKUP($BT$17,Sheet1!BN2:BQ840,2,0),0) -> 0 | BU18: =+IFERROR(VLOOKUP($BU$17,Sheet1!BR2:BU840,2,0),0) -> 0 | BV18: =+IFERROR(VLOOKUP($BV$17,Sheet1!BV2:BY840,2,0),0) -> 0
A19: =Sheet1!A4 -> ENQ-15363-22-23 | B19: =Sheet1!B4 -> 45658 | C19: =Sheet1!C4 -> FA1300006 | D19: =Sheet1!D4 -> 3 CORE X 70 SQ. MM. AL/ARM - STRIP (XLPE) - 11 KV | F19: =CK19+CM19+CO19 -> 774262.84 | G19: =ROUNDUP(N27,0) -> 25715 | H19: =F19+G19 -> 799977.84 | I19: =Sheet1!CP4 -> 0.18 | J19: =H19*I19 -> 143996.01 | K19: =H19+J19 -> 943973.86 | L19: =Sheet1!CS4 -> 14 | M19: =Sheet1!CT4 -> KMS | N19: =K19*L19 -> 13215634 | O19: 567 | P19: =+IFERROR(VLOOKUP($P$17,Sheet1!J4:L4,3,0),0) -> 0 | Q19: =+IFERROR(VLOOKUP($Q$17,Sheet1!J4:M4,3,0),0) -> 0 | R19: =+IFERROR(VLOOKUP($R$17,Sheet1!J4:M4,3,0),0) -> 0 | S19: =+IFERROR(VLOOKUP($S$17,Sheet1!J4:M4,3,0),0) -> 0 | T19: =+IFERROR(VLOOKUP($T$17,Sheet1!N4:Q4,3,0),0) -> 0 | U19: =+IFERROR(VLOOKUP($U$17,Sheet1!N4:Q4,3,0),0) -> 0 | V19: =+IFERROR(VLOOKUP($V$17,Sheet1!F4:I4,3,0),0) -> 0 | W19: =+IFERROR(VLOOKUP($W$17,Sheet1!F4:I4,3,0),0) -> 0 | X19: =+IFERROR(VLOOKUP($X$17,Sheet1!F4:I4,3,0),0) -> 0 | Y19: 78 | Z19: =+IFERROR(VLOOKUP($Z$17,Sheet1!F4:I4,3,0),0) -> 0 | AA19: =+IFERROR(VLOOKUP($AA$17,Sheet1!F4:I4,3,0),0) -> 0 | AB19: =+IFERROR(VLOOKUP($AB$17,Sheet1!F4:I4,3,0),0) -> 0 | AC19: =+IFERROR(VLOOKUP($AC$17,Sheet1!F4:I4,3,0),0) -> 0 | AD19: 190 | AE19: =+IFERROR(VLOOKUP($AE$17,Sheet1!R4:U4,2,0),0) -> 0 | AF19: 510 | AG19: =+IFERROR(VLOOKUP($AG$17,Sheet1!V4:Y4,3,0),0) -> 0 | AH19: =+IFERROR(VLOOKUP($AH$17,Sheet1!V4:Y4,3,0),0) -> 0 | AI19: =+IFERROR(VLOOKUP($AI$17,Sheet1!V4:Y4,3,0),0) -> 0 | AJ19: =+IFERROR(VLOOKUP($AJ$17,Sheet1!V4:Y4,3,0),0) -> 0 | AK19: =+IFERROR(VLOOKUP($AK$17,Sheet1!V4:Y4,3,0),0) -> 0 | AL19: =+IFERROR(VLOOKUP($AL$17,Sheet1!Z4:AB4,3,0),0) -> 0 | AM19: =+IFERROR(VLOOKUP($AM$17,Sheet1!AD4:AG4,3,0),0) -> 0 | AN19: =+IFERROR(VLOOKUP($AN$17,Sheet1!AD4:AG4,3,0),0) -> 0 | AO19: =+IFERROR(VLOOKUP($AO$17,Sheet1!AD4:AG4,3,0),0) -> 0 | AP19: =+IFERROR(VLOOKUP($AP$17,Sheet1!AD4:AG4,3,0),0) -> 0 | AQ19: =+IFERROR(VLOOKUP($AQ$17,Sheet1!AD4:AG4,3,0),0) -> 0 | AR19: 155 | AS19: =+IFERROR(VLOOKUP($AS$17,Sheet1!AD4:AG4,3,0),0) -> 0 | AT19: =+IFERROR(VLOOKUP($AT$17,Sheet1!AH4:AK4,3,0),0) -> 0 | AU19: =+IFERROR(VLOOKUP($AU$17,Sheet1!AH4:AK4,3,0),0) -> 0 | AV19: =+IFERROR(VLOOKUP($AV$17,Sheet1!AH4:AK4,3,0),0) -> 0 | AW19: =+IFERROR(VLOOKUP($AW$17,Sheet1!AH4:AK4,3,0),0) -> 0 | AX19: =+IFERROR(VLOOKUP($AX$17,Sheet1!AH4:AK4,3,0),0) -> 0 | AY19: 775 | AZ19: =+IFERROR(VLOOKUP($AZ$17,Sheet1!AH4:AK4,3,0),0) -> 0 | BA19: =+IFERROR(VLOOKUP($BA$17,Sheet1!AH4:AK4,3,0),0) -> 0 | BB19: =+IFERROR(VLOOKUP($BB$17,Sheet1!AH4:AK4,3,0),0) -> 0 | BC19: =+IFERROR(VLOOKUP($BC$17,Sheet1!AH4:AK4,3,0),0) -> 0 | BD19: =+IFERROR(VLOOKUP($BD$17,Sheet1!AL4:AO4,3,0),0) -> 0 | BE19: =+IFERROR(VLOOKUP($BE$17,Sheet1!AL4:AO4,3,0),0) -> 0 | BF19: =+IFERROR(VLOOKUP($BF$17,Sheet1!AL4:AO4,3,0),0) -> 0 | BG19: =+IFERROR(VLOOKUP($BG$17,Sheet1!AL4:AO4,3,0),0) -> 0 | BH19: =+IFERROR(VLOOKUP($BH$17,Sheet1!AL4:AO4,3,0),0) -> 0 | BI19: =+IFERROR(VLOOKUP($BI$17,Sheet1!AL4:AO4,3,0),0) -> 0 | BJ19: =+IFERROR(VLOOKUP($BJ$17,Sheet1!AL4:AO4,3,0),0) -> 0 | BK19: 490 | BL19: =+IFERROR(VLOOKUP($BL$17,Sheet1!AL4:AO4,3,0),0) -> 0 | BM19: =+IFERROR(VLOOKUP($BM$17,Sheet1!AL4:AO4,3,0),0) -> 0 | BN19: 560 | BO19: =+IFERROR(VLOOKUP($BO$17,Sheet1!AT4:AW4,3,0),0) -> 0 | BP19: =+IFERROR(VLOOKUP($BP$17,Sheet1!AX4:BA4,3,0),0) -> 0 | BQ19: =+IFERROR(VLOOKUP($BQ$17,Sheet1!BB4:BE4,3,0),0) -> 0 | BR19: =+IFERROR(VLOOKUP($BR$17,Sheet1!BF4:BI4,3,0),0) -> 0 | BS19: =+IFERROR(VLOOKUP($BS$17,Sheet1!BJ4:BM4,3,0),0) -> 0 | BT19: =+IFERROR(VLOOKUP($BT$17,Sheet1!BN4:BQ4,3,0),0) -> 0 | BU19: =+IFERROR(VLOOKUP($BU$17,Sheet1!BR4:BU4,3,0),0) -> 0 | BV19: =+IFERROR(VLOOKUP($BV$17,Sheet1!BV4:BY4,3,0),0) -> 0 | BW19: STEEL | BX19: =SUM(O19:BN19) -> 3325 | BY19: 50 | BZ19: SP0400118 | CA19: CORRUGATED DISPATCH STEEL DRUM 1700 X 1000 X 1200 | CB19: 500 | CC19: 45000 | CD19: =SUMPRODUCT($O$18:$BV$18,O19:BV19)+CC19 -> 501141 | CE19: =Sheet1!CB4 -> 0 | CF19: =CD19*CE19 -> 0 | CG19: 0.5 | CH19: =CD19*CG19 -> 250570.5 | CI19: =Sheet1!CF4 -> 0 | CJ19: =CD19*CI19 -> 0 | CK19: =CD19+CF19+CH19+CJ19 -> 751711.5 | CL19: 0.02 | CM19: =CK19*CL19 -> 15034.23 | CN19: 0.01 | CO19: =CK19*CN19 -> 7517.115
A20: =Sheet1!A6 -> ENQ-15363-22-23 | B20: =Sheet1!B6 -> 45658 | C20: =Sheet1!C6 -> FA1300052 | D20: =Sheet1!D6 -> 3 CORE X 150 SQ. MM. AL/ARM - STRIP (XLPE) - 11 KV | F20: =CK20+CM20+CO20 -> 1172727.6 | G20: =ROUNDUP(N28,0) -> 30000 | H20: =F20+G20 -> 1202727.6 | I20: =Sheet1!CP6 -> 0.18 | J20: =H20*I20 -> 216490.97 | K20: =H20+J20 -> 1419218.6 | L20: =Sheet1!CS6 -> 12 | M20: =Sheet1!CT6 -> KMS | N20: =K20*L20 -> 17030623 | O20: 1215 | P20: =+IFERROR(VLOOKUP($P$17,Sheet1!J6:L6,3,0),0) -> 0 | Q20: =+IFERROR(VLOOKUP($Q$17,Sheet1!J6:M6,3,0),0) -> 0 | R20: =+IFERROR(VLOOKUP($R$17,Sheet1!J6:M6,3,0),0) -> 0 | S20: =+IFERROR(VLOOKUP($S$17,Sheet1!J6:M6,3,0),0) -> 0 | T20: =+IFERROR(VLOOKUP($T$17,Sheet1!N6:Q6,3,0),0) -> 0 | U20: =+IFERROR(VLOOKUP($U$17,Sheet1!N6:Q6,3,0),0) -> 0 | V20: =+IFERROR(VLOOKUP($V$17,Sheet1!F6:I6,3,0),0) -> 0 | W20: =+IFERROR(VLOOKUP($W$17,Sheet1!F6:I6,3,0),0) -> 0 | X20: =+IFERROR(VLOOKUP($X$17,Sheet1!F6:I6,3,0),0) -> 0 | Y20: 96 | Z20: =+IFERROR(VLOOKUP($Z$17,Sheet1!F6:I6,3,0),0) -> 0 | AA20: =+IFERROR(VLOOKUP($AA$17,Sheet1!F6:I6,3,0),0) -> 0 | AB20: =+IFERROR(VLOOKUP($AB$17,Sheet1!F6:I6,3,0),0) -> 0 | AC20: =+IFERROR(VLOOKUP($AC$17,Sheet1!F6:I6,3,0),0) -> 0 | AD20: 250 | AE20: =+IFERROR(VLOOKUP($AE$17,Sheet1!R6:U6,2,0),0) -> 0 | AF20: 663 | AG20: =+IFERROR(VLOOKUP($AG$17,Sheet1!V6:Y6,3,0),0) -> 0 | AH20: =+IFERROR(VLOOKUP($AH$17,Sheet1!V6:Y6,3,0),0) -> 0 | AI20: =+IFERROR(VLOOKUP($AI$17,Sheet1!V6:Y6,3,0),0) -> 0 | AJ20: =+IFERROR(VLOOKUP($AJ$17,Sheet1!V6:Y6,3,0),0) -> 0 | AK20: =+IFERROR(VLOOKUP($AK$17,Sheet1!V6:Y6,3,0),0) -> 0 | AL20: =+IFERROR(VLOOKUP($AL$17,Sheet1!Z6:AB6,3,0),0) -> 0 | AM20: =+IFERROR(VLOOKUP($AM$17,Sheet1!AD6:AG6,3,0),0) -> 0 | AN20: =+IFERROR(VLOOKUP($AN$17,Sheet1!AD6:AG6,3,0),0) -> 0 | AO20: =+IFERROR(VLOOKUP($AO$17,Sheet1!AD6:AG6,3,0),0) -> 0 | AP20: =+IFERROR(VLOOKUP($AP$17,Sheet1!AD6:AG6,3,0),0) -> 0 | AQ20: =+IFERROR(VLOOKUP($AQ$17,Sheet1!AD6:AG6,3,0),0) -> 0 | AR20: 214 | AS20: =+IFERROR(VLOOKUP($AS$17,Sheet1!AD6:AG6,3,0),0) -> 0 | AT20: =+IFERROR(VLOOKUP($AT$17,Sheet1!AH6:AK6,3,0),0) -> 0 | AU20: =+IFERROR(VLOOKUP($AU$17,Sheet1!AH6:AK6,3,0),0) -> 0 | AV20: =+IFERROR(VLOOKUP($AV$17,Sheet1!AH6:AK6,3,0),0) -> 0 | AW20: =+IFERROR(VLOOKUP($AW$17,Sheet1!AH6:AK6,3,0),0) -> 0 | AX20: =+IFERROR(VLOOKUP($AX$17,Sheet1!AH6:AK6,3,0),0) -> 0 | AY20: 925 | AZ20: =+IFERROR(VLOOKUP($AZ$17,Sheet1!AH6:AK6,3,0),0) -> 0 | BA20: =+IFERROR(VLOOKUP($BA$17,Sheet1!AH6:AK6,3,0),0) -> 0 | BB20: =+IFERROR(VLOOKUP($BB$17,Sheet1!AH6:AK6,3,0),0) -> 0 | BC20: =+IFERROR(VLOOKUP($BC$17,Sheet1!AH6:AK6,3,0),0) -> 0 | BD20: =+IFERROR(VLOOKUP($BD$17,Sheet1!AL6:AO6,3,0),0) -> 0 | BE20: =+IFERROR(VLOOKUP($BE$17,Sheet1!AL6:AO6,3,0),0) -> 0 | BF20: =+IFERROR(VLOOKUP($BF$17,Sheet1!AL6:AO6,3,0),0) -> 0 | BG20: =+IFERROR(VLOOKUP($BG$17,Sheet1!AL6:AO6,3,0),0) -> 0 | BH20: =+IFERROR(VLOOKUP($BH$17,Sheet1!AL6:AO6,3,0),0) -> 0 | BI20: =+IFERROR(VLOOKUP($BI$17,Sheet1!AL6:AO6,3,0),0) -> 0 | BJ20: =+IFERROR(VLOOKUP($BJ$17,Sheet1!AL6:AO6,3,0),0) -> 0 | BK20: 725 | BL20: =+IFERROR(VLOOKUP($BL$17,Sheet1!AL6:AO6,3,0),0) -> 0 | BM20: =+IFERROR(VLOOKUP($BM$17,Sheet1!AL6:AO6,3,0),0) -> 0 | BN20: 844 | BO20: =+IFERROR(VLOOKUP($BO$17,Sheet1!AT6:AW6,3,0),0) -> 0 | BP20: =+IFERROR(VLOOKUP($BP$17,Sheet1!AX6:BA6,3,0),0) -> 0 | BQ20: =+IFERROR(VLOOKUP($BQ$17,Sheet1!BB6:BE6,3,0),0) -> 0 | BR20: =+IFERROR(VLOOKUP($BR$17,Sheet1!BF6:BI6,3,0),0) -> 0 | BS20: =+IFERROR(VLOOKUP($BS$17,Sheet1!BJ6:BM6,3,0),0) -> 0 | BT20: =+IFERROR(VLOOKUP($BT$17,Sheet1!BN6:BQ6,3,0),0) -> 0 | BU20: =+IFERROR(VLOOKUP($BU$17,Sheet1!BR6:BU6,3,0),0) -> 0 | BV20: =+IFERROR(VLOOKUP($BV$17,Sheet1!BV6:BY6,3,0),0) -> 0 | BW20: STEEL | BX20: =SUM(O20:BN20) -> 4932 | BY20: 61 | BZ20: SP0400123 | CA20: CORRUGATED DISPATCH STEEL DRUM 2000 X 1000 X 1200 MM | CB20: 500 | CC20: 41400 | CD20: =SUMPRODUCT($O$18:$BV$18,O20:BV20)+CC20 -> 759047 | CE20: =Sheet1!CB6 -> 0 | CF20: =CD20*CE20 -> 0 | CG20: 0.5 | CH20: =CD20*CG20 -> 379523.5 | CI20: =Sheet1!CF6 -> 0 | CJ20: =CD20*CI20 -> 0 | CK20: =CD20+CF20+CH20+CJ20 -> 1138570.5 | CL20: 0.02 | CM20: =CK20*CL20 -> 22771.41 | CN20: 0.01 | CO20: =CK20*CN20 -> 11385.705
A21: =Sheet1!A3 -> ENQ-15363-22-23 | B21: =Sheet1!B3 -> 45658 | C21: =Sheet1!C3 -> FA1300004 | D21: =Sheet1!D3 -> 3 CORE X 300 SQ. MM. AL/ARM - STRIP (XLPE) - 11 KV | F21: =CK21+CM21+CO21 -> 1904002.4 | G21: =ROUNDUP(N29,0) -> 48000 | H21: =F21+G21 -> 1952002.4 | I21: =Sheet1!CP3 -> 0.18 | J21: =H21*I21 -> 351360.43 | K21: =H21+J21 -> 2303362.8 | L21: =Sheet1!CS3 -> 150 | M21: =Sheet1!CT3 -> KMS | N21: =K21*L21 -> 3.4550442e+08 | O21: 2430 | P21: =+IFERROR(VLOOKUP($P$17,Sheet1!J3:L3,3,0),0) -> 0 | Q21: =+IFERROR(VLOOKUP($Q$17,Sheet1!J3:M3,3,0),0) -> 0 | R21: =+IFERROR(VLOOKUP($R$17,Sheet1!J3:M3,3,0),0) -> 0 | S21: =+IFERROR(VLOOKUP($S$17,Sheet1!J3:M3,3,0),0) -> 0 | T21: =+IFERROR(VLOOKUP($T$17,Sheet1!N3:Q3,3,0),0) -> 0 | U21: =+IFERROR(VLOOKUP($U$17,Sheet1!N3:Q3,3,0),0) -> 0 | V21: =+IFERROR(VLOOKUP($V$17,Sheet1!F3:I3,3,0),0) -> 0 | W21: =+IFERROR(VLOOKUP($W$17,Sheet1!F3:I3,3,0),0) -> 0 | X21: =+IFERROR(VLOOKUP($X$17,Sheet1!F3:I3,3,0),0) -> 0 | Y21: 119 | Z21: =+IFERROR(VLOOKUP($Z$17,Sheet1!F3:I3,3,0),0) -> 0 | AA21: =+IFERROR(VLOOKUP($AA$17,Sheet1!F3:I3,3,0),0) -> 0 | AB21: =+IFERROR(VLOOKUP($AB$17,Sheet1!F3:I3,3,0),0) -> 0 | AC21: =+IFERROR(VLOOKUP($AC$17,Sheet1!F3:I3,3,0),0) -> 0 | AD21: 328 | AE21: =+IFERROR(VLOOKUP($AE$17,Sheet1!R3:U3,2,0),0) -> 0 | AF21: 870 | AG21: =+IFERROR(VLOOKUP($AG$17,Sheet1!V3:Y3,3,0),0) -> 0 | AH21: =+IFERROR(VLOOKUP($AH$17,Sheet1!V3:Y3,3,0),0) -> 0 | AI21: =+IFERROR(VLOOKUP($AI$17,Sheet1!V3:Y3,3,0),0) -> 0 | AJ21: =+IFERROR(VLOOKUP($AJ$17,Sheet1!V3:Y3,3,0),0) -> 0 | AK21: =+IFERROR(VLOOKUP($AK$17,Sheet1!V3:Y3,3,0),0) -> 0 | AL21: =+IFERROR(VLOOKUP($AL$17,Sheet1!Z3:AB3,3,0),0) -> 0 | AM21: =+IFERROR(VLOOKUP($AM$17,Sheet1!AD3:AG3,3,0),0) -> 0 | AN21: =+IFERROR(VLOOKUP($AN$17,Sheet1!AD3:AG3,3,0),0) -> 0 | AO21: =+IFERROR(VLOOKUP($AO$17,Sheet1!AD3:AG3,3,0),0) -> 0 | AP21: =+IFERROR(VLOOKUP($AP$17,Sheet1!AD3:AG3,3,0),0) -> 0 | AQ21: =+IFERROR(VLOOKUP($AQ$17,Sheet1!AD3:AG3,3,0),0) -> 0 | AR21: 300 | AS21: =+IFERROR(VLOOKUP($AS$17,Sheet1!AD3:AG3,3,0),0) -> 0 | AT21: =+IFERROR(VLOOKUP($AT$17,Sheet1!AH3:AK3,3,0),0) -> 0 | AU21: =+IFERROR(VLOOKUP($AU$17,Sheet1!AH3:AK3,3,0),0) -> 0 | AV21: =+IFERROR(VLOOKUP($AV$17,Sheet1!AH3:AK3,3,0),0) -> 0 | AW21: =+IFERROR(VLOOKUP($AW$17,Sheet1!AH3:AK3,3,0),0) -> 0 | AX21: =+IFERROR(VLOOKUP($AX$17,Sheet1!AH3:AK3,3,0),0) -> 0 | AY21: 1150 | AZ21: =+IFERROR(VLOOKUP($AZ$17,Sheet1!AH3:AK3,3,0),0) -> 0 | BA21: =+IFERROR(VLOOKUP($BA$17,Sheet1!AH3:AK3,3,0),0) -> 0 | BB21: =+IFERROR(VLOOKUP($BB$17,Sheet1!AH3:AK3,3,0),0) -> 0 | BC21: =+IFERROR(VLOOKUP($BC$17,Sheet1!AH3:AK3,3,0),0) -> 0 | BD21: =+IFERROR(VLOOKUP($BD$17,Sheet1!AL3:AO3,3,0),0) -> 0 | BE21: =+IFERROR(VLOOKUP($BE$17,Sheet1!AL3:AO3,3,0),0) -> 0 | BF21: =+IFERROR(VLOOKUP($BF$17,Sheet1!AL3:AO3,3,0),0) -> 0 | BG21: =+IFERROR(VLOOKUP($BG$17,Sheet1!AL3:AO3,3,0),0) -> 0 | BH21: =+IFERROR(VLOOKUP($BH$17,Sheet1!AL3:AO3,3,0),0) -> 0 | BI21: =+IFERROR(VLOOKUP($BI$17,Sheet1!AL3:AO3,3,0),0) -> 0 | BJ21: =+IFERROR(VLOOKUP($BJ$17,Sheet1!AL3:AO3,3,0),0) -> 0 | BK21: 1012 | BL21: =+IFERROR(VLOOKUP($BL$17,Sheet1!AL3:AO3,3,0),0) -> 0 | BM21: =+IFERROR(VLOOKUP($BM$17,Sheet1!AL3:AO3,3,0),0) -> 0 | BN21: 1310 | BO21: =+IFERROR(VLOOKUP($BO$17,Sheet1!AT3:AW3,3,0),0) -> 0 | BP21: =+IFERROR(VLOOKUP($BP$17,Sheet1!AX3:BA3,3,0),0) -> 0 | BQ21: =+IFERROR(VLOOKUP($BQ$17,Sheet1!BB3:BE3,3,0),0) -> 0 | BR21: =+IFERROR(VLOOKUP($BR$17,Sheet1!BF3:BI3,3,0),0) -> 0 | BS21: =+IFERROR(VLOOKUP($BS$17,Sheet1!BJ3:BM3,3,0),0) -> 0 | BT21: =+IFERROR(VLOOKUP($BT$17,Sheet1!BN3:BQ3,3,0),0) -> 0 | BU21: =+IFERROR(VLOOKUP($BU$17,Sheet1!BR3:BU3,3,0),0) -> 0 | BV21: =+IFERROR(VLOOKUP($BV$17,Sheet1!BV3:BY3,3,0),0) -> 0 | BW21: STEEL | BX21: =SUM(O21:BN21) -> 7519 | BY21: 75 | BZ21: SP0400109 | CA21: CORRUGATED DISPATCH STEEL DRUM 2200 X 1000 X 1450 MM | CB21: 500 | CC21: 72000 | CD21: =SUMPRODUCT($O$18:$BV$18,O21:BV21)+CC21 -> 1232364 | CE21: =Sheet1!CB3 -> 0 | CF21: =CD21*CE21 -> 0 | CG21: 0.5 | CH21: =CD21*CG21 -> 616182 | CI21: =Sheet1!CF3 -> 0 | CJ21: =CD21*CI21 -> 0 | CK21: =CD21+CF21+CH21+CJ21 -> 1848546 | CL21: 0.02 | CM21: =CK21*CL21 -> 36970.92 | CN21: 0.01 | CO21: =CK21*CN21 -> 18485.46
A22: =Sheet1!A5 -> ENQ-15363-22-23 | B22: =Sheet1!B5 -> 45658 | C22: =Sheet1!C5 -> FA1300010 | D22: =Sheet1!D5 -> 3 CORE X 400 SQ. MM. AL/ARM - STRIP (XLPE) - 33 KV | F22: =CK22+CM22+CO22 -> 3044048.6 | G22: =ROUNDUP(N30,0) -> 81039 | H22: =F22+G22 -> 3125087.6 | I22: =Sheet1!CP5 -> 0.18 | J22: =H22*I22 -> 562515.77 | K22: =H22+J22 -> 3687603.4 | L22: =Sheet1!CS5 -> 77 | M22: =Sheet1!CT5 -> KMS | N22: =K22*L22 -> 2.8394546e+08 | O22: 3240 | P22: =+IFERROR(VLOOKUP($P$17,Sheet1!J5:L5,3,0),0) -> 0 | Q22: =+IFERROR(VLOOKUP($Q$17,Sheet1!J5:M5,3,0),0) -> 0 | R22: =+IFERROR(VLOOKUP($R$17,Sheet1!J5:M5,3,0),0) -> 0 | S22: =+IFERROR(VLOOKUP($S$17,Sheet1!J5:M5,3,0),0) -> 0 | T22: =+IFERROR(VLOOKUP($T$17,Sheet1!N5:Q5,3,0),0) -> 0 | U22: =+IFERROR(VLOOKUP($U$17,Sheet1!N5:Q5,3,0),0) -> 0 | V22: =+IFERROR(VLOOKUP($V$17,Sheet1!F5:I5,3,0),0) -> 0 | W22: =+IFERROR(VLOOKUP($W$17,Sheet1!F5:I5,3,0),0) -> 0 | X22: =+IFERROR(VLOOKUP($X$17,Sheet1!F5:I5,3,0),0) -> 0 | Y22: 172 | Z22: =+IFERROR(VLOOKUP($Z$17,Sheet1!F5:I5,3,0),0) -> 0 | AA22: =+IFERROR(VLOOKUP($AA$17,Sheet1!F5:I5,3,0),0) -> 0 | AB22: =+IFERROR(VLOOKUP($AB$17,Sheet1!F5:I5,3,0),0) -> 0 | AC22: =+IFERROR(VLOOKUP($AC$17,Sheet1!F5:I5,3,0),0) -> 0 | AD22: 424 | AE22: =+IFERROR(VLOOKUP($AE$17,Sheet1!R5:U5,2,0),0) -> 0 | AF22: 2725 | AG22: =+IFERROR(VLOOKUP($AG$17,Sheet1!V5:Y5,3,0),0) -> 0 | AH22: =+IFERROR(VLOOKUP($AH$17,Sheet1!V5:Y5,3,0),0) -> 0 | AI22: =+IFERROR(VLOOKUP($AI$17,Sheet1!V5:Y5,3,0),0) -> 0 | AJ22: =+IFERROR(VLOOKUP($AJ$17,Sheet1!V5:Y5,3,0),0) -> 0 | AK22: =+IFERROR(VLOOKUP($AK$17,Sheet1!V5:Y5,3,0),0) -> 0 | AL22: =+IFERROR(VLOOKUP($AL$17,Sheet1!Z5:AB5,3,0),0) -> 0 | AM22: =+IFERROR(VLOOKUP($AM$17,Sheet1!AD5:AG5,3,0),0) -> 0 | AN22: =+IFERROR(VLOOKUP($AN$17,Sheet1!AD5:AG5,3,0),0) -> 0 | AO22: =+IFERROR(VLOOKUP($AO$17,Sheet1!AD5:AG5,3,0),0) -> 0 | AP22: =+IFERROR(VLOOKUP($AP$17,Sheet1!AD5:AG5,3,0),0) -> 0 | AQ22: =+IFERROR(VLOOKUP($AQ$17,Sheet1!AD5:AG5,3,0),0) -> 0 | AR22: 430 | AS22: =+IFERROR(VLOOKUP($AS$17,Sheet1!AD5:AG5,3,0),0) -> 0 | AT22: =+IFERROR(VLOOKUP($AT$17,Sheet1!AH5:AK5,3,0),0) -> 0 | AU22: =+IFERROR(VLOOKUP($AU$17,Sheet1!AH5:AK5,3,0),0) -> 0 | AV22: =+IFERROR(VLOOKUP($AV$17,Sheet1!AH5:AK5,3,0),0) -> 0 | AW22: =+IFERROR(VLOOKUP($AW$17,Sheet1!AH5:AK5,3,0),0) -> 0 | AX22: =+IFERROR(VLOOKUP($AX$17,Sheet1!AH5:AK5,3,0),0) -> 0 | AY22: 1625 | AZ22: =+IFERROR(VLOOKUP($AZ$17,Sheet1!AH5:AK5,3,0),0) -> 0 | BA22: =+IFERROR(VLOOKUP($BA$17,Sheet1!AH5:AK5,3,0),0) -> 0 | BB22: =+IFERROR(VLOOKUP($BB$17,Sheet1!AH5:AK5,3,0),0) -> 0 | BC22: =+IFERROR(VLOOKUP($BC$17,Sheet1!AH5:AK5,3,0),0) -> 0 | BD22: =+IFERROR(VLOOKUP($BD$17,Sheet1!AL5:AO5,3,0),0) -> 0 | BE22: =+IFERROR(VLOOKUP($BE$17,Sheet1!AL5:AO5,3,0),0) -> 0 | BF22: =+IFERROR(VLOOKUP($BF$17,Sheet1!AL5:AO5,3,0),0) -> 0 | BG22: =+IFERROR(VLOOKUP($BG$17,Sheet1!AL5:AO5,3,0),0) -> 0 | BH22: =+IFERROR(VLOOKUP($BH$17,Sheet1!AL5:AO5,3,0),0) -> 0 | BI22: =+IFERROR(VLOOKUP($BI$17,Sheet1!AL5:AO5,3,0),0) -> 0 | BJ22: =+IFERROR(VLOOKUP($BJ$17,Sheet1!AL5:AO5,3,0),0) -> 0 | BK22: 1600 | BL22: =+IFERROR(VLOOKUP($BL$17,Sheet1!AL5:AO5,3,0),0) -> 0 | BM22: =+IFERROR(VLOOKUP($BM$17,Sheet1!AL5:AO5,3,0),0) -> 0 | BN22: 2745 | BO22: =+IFERROR(VLOOKUP($BO$17,Sheet1!AT5:AW5,3,0),0) -> 0 | BP22: =+IFERROR(VLOOKUP($BP$17,Sheet1!AX5:BA5,3,0),0) -> 0 | BQ22: =+IFERROR(VLOOKUP($BQ$17,Sheet1!BB5:BE5,3,0),0) -> 0 | BR22: =+IFERROR(VLOOKUP($BR$17,Sheet1!BF5:BI5,3,0),0) -> 0 | BS22: =+IFERROR(VLOOKUP($BS$17,Sheet1!BJ5:BM5,3,0),0) -> 0 | BT22: =+IFERROR(VLOOKUP($BT$17,Sheet1!BN5:BQ5,3,0),0) -> 0 | BU22: =+IFERROR(VLOOKUP($BU$17,Sheet1!BR5:BU5,3,0),0) -> 0 | BV22: =+IFERROR(VLOOKUP($BV$17,Sheet1!BV5:BY5,3,0),0) -> 0 | BW22: STEEL | BX22: =SUM(O22:BN22) -> 12961 | BY22: 105 | BZ22: SP0400094 | CA22: CORRUGATED DISPATCH STEEL DRUM 2750 X 1400 X 1750 | CB22: 500 | CC22: 108000 | CD22: =SUMPRODUCT($O$18:$BV$18,O22:BV22)+CC22 -> 1970258 | CE22: =Sheet1!CB5 -> 0 | CF22: =CD22*CE22 -> 0 | CG22: 0.5 | CH22: =CD22*CG22 -> 985129 | CI22: =Sheet1!CF5 -> 0 | CJ22: =CD22*CI22 -> 0 | CK22: =CD22+CF22+CH22+CJ22 -> 2955387 | CL22: 0.02 | CM22: =CK22*CL22 -> 59107.74 | CN22: 0.01 | CO22: =CK22*CN22 -> 29553.87
A23: =Sheet1!A2 -> ENQ-15363-22-23 | B23: =Sheet1!B2 -> 45658 | C23: =Sheet1!C2 -> FA0400012 | D23: =Sheet1!D2 -> 3 CORE X 120 SQ MM + 1 CORE X 120 SQ MM (AB CABLES) (BARE) - 11 KV | E23: 3 CORE X 120 SQ MM + 1 CORE X 125 SQ MM (AB CABLES) (INSULATED) - 11 KV | F23: =CK23+CM23+CO23 -> 1111947.3 | G23: =ROUNDUP(N31,0) -> 32728 | H23: =F23+G23 -> 1144675.3 | I23: =Sheet1!CP2 -> 0.18 | J23: =H23*I23 -> 206041.56 | K23: =H23+J23 -> 1350716.9 | L23: =Sheet1!CS2 -> 22 | M23: =Sheet1!CT2 -> KMS | N23: =K23*L23 -> 29715771 | O23: 972 | P23: =+IFERROR(VLOOKUP($P$17,Sheet1!J2:L2,3,0),0) -> 0 | Q23: =+IFERROR(VLOOKUP($Q$17,Sheet1!J2:M2,3,0),0) -> 0 | R23: =+IFERROR(VLOOKUP($R$17,Sheet1!J2:M2,3,0),0) -> 0 | S23: =+IFERROR(VLOOKUP($S$17,Sheet1!J2:M2,3,0),0) -> 0 | T23: =+IFERROR(VLOOKUP($T$17,Sheet1!N2:Q2,3,0),0) -> 0 | U23: 348 | V23: =+IFERROR(VLOOKUP($V$17,Sheet1!F2:I2,3,0),0) -> 0 | W23: =+IFERROR(VLOOKUP($W$17,Sheet1!F2:I2,3,0),0) -> 0 | X23: =+IFERROR(VLOOKUP($X$17,Sheet1!F2:I2,3,0),0) -> 0 | Y23: =+IFERROR(VLOOKUP($Y$17,Sheet1!F2:I2,3,0),0) -> 0 | Z23: =+IFERROR(VLOOKUP($Z$17,Sheet1!F2:I2,3,0),0) -> 0 | AA23: =+IFERROR(VLOOKUP($AA$17,Sheet1!F2:I2,3,0),0) -> 0 | AB23: 134 | AC23: =+IFERROR(VLOOKUP($AC$17,Sheet1!F2:I2,3,0),0) -> 0 | AD23: 252 | AE23: =+IFERROR(VLOOKUP($AE$17,Sheet1!R2:U2,2,0),0) -> 0 | AF23: =+IFERROR(VLOOKUP($AF$17,Sheet1!V2:Y2,3,0),0) -> 577 | AG23: =+IFERROR(VLOOKUP($AG$17,Sheet1!V2:Y2,3,0),0) -> 0 | AH23: =+IFERROR(VLOOKUP($AH$17,Sheet1!V2:Y2,3,0),0) -> 0 | AI23: =+IFERROR(VLOOKUP($AI$17,Sheet1!V2:Y2,3,0),0) -> 0 | AJ23: =+IFERROR(VLOOKUP($AJ$17,Sheet1!V2:Y2,3,0),0) -> 0 | AK23: =+IFERROR(VLOOKUP($AK$17,Sheet1!V2:Y2,3,0),0) -> 0 | AL23: =+IFERROR(VLOOKUP($AL$17,Sheet1!Z2:AB2,3,0),0) -> 0 | AM23: =+IFERROR(VLOOKUP($AM$17,Sheet1!AD2:AG2,3,0),0) -> 0 | AN23: =+IFERROR(VLOOKUP($AN$17,Sheet1!AD2:AG2,3,0),0) -> 0 | AO23: =+IFERROR(VLOOKUP($AO$17,Sheet1!AD2:AG2,3,0),0) -> 0 | AP23: =+IFERROR(VLOOKUP($AP$17,Sheet1!AD2:AG2,3,0),0) -> 0 | AQ23: =+IFERROR(VLOOKUP($AQ$17,Sheet1!AD2:AG2,3,0),0) -> 0 | AR23: 135 | AS23: =+IFERROR(VLOOKUP($AS$17,Sheet1!AD2:AG2,3,0),0) -> 0 | AT23: =+IFERROR(VLOOKUP($AT$17,Sheet1!AH2:AK2,3,0),0) -> 0 | AU23: =+IFERROR(VLOOKUP($AU$17,Sheet1!AH2:AK2,3,0),0) -> 0 | AV23: =+IFERROR(VLOOKUP($AV$17,Sheet1!AH2:AK2,3,0),0) -> 0 | AW23: =+IFERROR(VLOOKUP($AW$17,Sheet1!AH2:AK2,3,0),0) -> 0 | AX23: =+IFERROR(VLOOKUP($AX$17,Sheet1!AH2:AK2,3,0),0) -> 0 | AY23: =+IFERROR(VLOOKUP($AY$17,Sheet1!AH2:AK2,3,0),0) -> 0 | AZ23: =+IFERROR(VLOOKUP($AZ$17,Sheet1!AH2:AK2,3,0),0) -> 0 | BA23: =+IFERROR(VLOOKUP($BA$17,Sheet1!AH2:AK2,3,0),0) -> 0 | BB23: =+IFERROR(VLOOKUP($BB$17,Sheet1!AH2:AK2,3,0),0) -> 0 | BC23: =+IFERROR(VLOOKUP($BC$17,Sheet1!AH2:AK2,3,0),0) -> 0 | BD23: =+IFERROR(VLOOKUP($BD$17,Sheet1!AL2:AO2,3,0),0) -> 0 | BE23: =+IFERROR(VLOOKUP($BE$17,Sheet1!AL2:AO2,3,0),0) -> 0 | BF23: =+IFERROR(VLOOKUP($BF$17,Sheet1!AL2:AO2,3,0),0) -> 0 | BG23: =+IFERROR(VLOOKUP($BG$17,Sheet1!AL2:AO2,3,0),0) -> 0 | BH23: =+IFERROR(VLOOKUP($BH$17,Sheet1!AL2:AO2,3,0),0) -> 0 | BI23: =+IFERROR(VLOOKUP($BI$17,Sheet1!AL2:AO2,3,0),0) -> 0 | BJ23: =+IFERROR(VLOOKUP($BJ$17,Sheet1!AL2:AO2,3,0),0) -> 0 | BK23: 760 | BL23: =+IFERROR(VLOOKUP($BL$17,Sheet1!AL2:AO2,3,0),0) -> 0 | BM23: =+IFERROR(VLOOKUP($BM$17,Sheet1!AL2:AO2,3,0),0) -> 0 | BN23: =+IFERROR(VLOOKUP($BN$17,Sheet1!AP2:AS2,3,0),0) -> 0 | BO23: =+IFERROR(VLOOKUP($BO$17,Sheet1!AT2:AW2,3,0),0) -> 0 | BP23: =+IFERROR(VLOOKUP($BP$17,Sheet1!AX2:BA2,3,0),0) -> 0 | BQ23: =+IFERROR(VLOOKUP($BQ$17,Sheet1!BB2:BE2,3,0),0) -> 0 | BR23: =+IFERROR(VLOOKUP($BR$17,Sheet1!BF2:BI2,3,0),0) -> 0 | BS23: =+IFERROR(VLOOKUP($BS$17,Sheet1!BJ2:BM2,3,0),0) -> 0 | BT23: =+IFERROR(VLOOKUP($BT$17,Sheet1!BN2:BQ2,3,0),0) -> 0 | BU23: =+IFERROR(VLOOKUP($BU$17,Sheet1!BR2:BU2,3,0),0) -> 0 | BV23: =+IFERROR(VLOOKUP($BV$17,Sheet1!BV2:BY2,3,0),0) -> 0 | BW23: =Sheet1!E2 -> STEEL | BX23: =SUM(O23:BN23) -> 3178 | BY23: 63 | BZ23: SP0400123 | CA23: CORRUGATED DISPATCH STEEL DRUM 2000 X 1000 X 1200 MM | CB23: 500 | CC23: 41400 | CD23: =SUMPRODUCT($O$18:$BV$18,O23:BV23)+CC23 -> 719707 | CE23: =Sheet1!CB2 -> 0 | CF23: =CD23*CE23 -> 0 | CG23: 0.5 | CH23: =CD23*CG23 -> 359853.5 | CI23: =Sheet1!CF2 -> 0 | CJ23: =CD23*CI23 -> 0 | CK23: =CD23+CF23+CH23+CJ23 -> 1079560.5 | CL23: 0.02 | CM23: =CK23*CL23 -> 21591.21 | CN23: 0.01 | CO23: =CK23*CN23 -> 10795.605
N24: =SUM(N19:N23) -> 6.8941191e+08
F26: Order Quantity | G26: Stnd Length | H26: Truck type | I26: Fare of one truck | J26: No of Drum in one truck | K26: Total length in one Truck | L26: No of Truck | M26: Total Freight | N26: Freight per KM | U26: CABLE WEIGHT KG/KM | Y26: DRUM WEIGHT | AB26: CABLE+DRUM WEIGHT | AD26: TRAILOR WEIGHT
E27: =D19 -> 3 CORE X 70 SQ. MM. AL/ARM - STRIP (XLPE) - 11 KV | F27: =L19 -> 14 | G27: =CB19/1000 -> 0.5 | H27: 25 MT TRAILER | I27: 120000 | J27: 10 | K27: =G27*J27 -> 5 | L27: =ROUNDUP((F27/K27),0) -> 3 | M27: =N27*F27 -> 360000 | N27: =(I27*L27)/F27 -> 25714.286 | U27: =SUM(O19:BN19) -> 3325 | Y27: =22500/90 -> 250 | AB27: =((U27*G27)+Y27) -> 1912.5 | AD27: =J27*AB27 -> 19125
E28: =D20 -> 3 CORE X 150 SQ. MM. AL/ARM - STRIP (XLPE) - 11 KV | F28: =L20 -> 12 | G28: =CB20/1000 -> 0.5 | H28: 25 MT TRAILER | I28: 120000 | J28: 8 | K28: =G28*J28 -> 4 | L28: =ROUNDUP((F28/K28),0) -> 3 | M28: =N28*F28 -> 360000 | N28: =(I28*L28)/F28 -> 30000 | U28: =SUM(O20:BN20) -> 4932 | Y28: =20700/90 -> 230 | AB28: =((U28*G28)+Y28) -> 2696 | AD28: =J28*AB28 -> 21568
E29: =D21 -> 3 CORE X 300 SQ. MM. AL/ARM - STRIP (XLPE) - 11 KV | F29: =L21 -> 150 | G29: =CB21/1000 -> 0.5 | H29: 25 MT TRAILER | I29: 120000 | J29: 5 | K29: =G29*J29 -> 2.5 | L29: =ROUNDUP((F29/K29),0) -> 60 | M29: =N29*F29 -> 7200000 | N29: =(I29*L29)/F29 -> 48000 | U29: =SUM(O21:BN21) -> 7519 | Y29: =36000/90 -> 400 | AB29: =((U29*G29)+Y29) -> 4159.5 | AD29: =J29*AB29 -> 20797.5
E30: =D22 -> 3 CORE X 400 SQ. MM. AL/ARM - STRIP (XLPE) - 33 KV | F30: =L22 -> 77 | G30: =CB22/1000 -> 0.5 | H30: 25 MT TRAILER | I30: 120000 | J30: 3 | K30: =G30*J30 -> 1.5 | L30: =ROUNDUP((F30/K30),0) -> 52 | M30: =N30*F30 -> 6240000 | N30: =(I30*L30)/F30 -> 81038.961 | U30: =SUM(O22:BN22) -> 12961 | Y30: =54000/90 -> 600 | AB30: =((U30*G30)+Y30) -> 7080.5 | AD30: =J30*AB30 -> 21241.5
E31: =E23 -> 3 CORE X 120 SQ MM + 1 CORE X 125 SQ MM (AB CABLES) (INSULATED) - 11 KV | F31: =L23 -> 22 | G31: =CB23/1000 -> 0.5 | H31: 25 MT TRAILER | I31: 120000 | J31: 8 | K31: =G31*J31 -> 4 | L31: =ROUNDUP((F31/K31),0) -> 6 | M31: =N31*F31 -> 720000 | N31: =(I31*L31)/F31 -> 32727.273 | U31: =SUM(O23:BN23) -> 3178 | Y31: =20700/90 -> 230 | AB31: =((U31*G31)+Y31) -> 1819 | AD31: =J31*AB31 -> 14552
J32: SOMBHU SIR CONFIRMED OVERPHONE
A35: DOCKET NO. | B35: Base Date | C35: ITEM CODE | D35: PROPOSE ERP ITEM NAME | E35: ERP NAME | F35: EX-WORKS (PER MTR) | G35: FREIGHT PER MTR | H35: PRICE INCLUDING FREIGHT (PER MTR) | I35: GST % | J35: GST VALUE | K35: PRICE INCLUDING GST & FREIGHT (PER MTR) | L35: QTY | M35: Unit | N35: TOTAL PRICE OF FULL QTY (INCLUDING FRIGHT & GST)
A37: =A19 -> ENQ-15363-22-23 | B37: =B19 -> 45658 | C37: =C19 -> FA1300006 | D37: =D19 -> 3 CORE X 70 SQ. MM. AL/ARM - STRIP (XLPE) - 11 KV | E37: =E19 -> 0 | F37: =ROUNDUP(F19/1000,2) -> 774.27 | G37: =ROUNDUP(G19/1000,2) -> 25.72 | H37: =F37+G37 -> 799.99 | I37: =I19 -> 0.18 | J37: =ROUND(H37*I37,2) -> 144 | K37: =ROUND(H37+J37,2) -> 943.99 | L37: =L19*1000 -> 14000 | M37: MTR | N37: =K37*L37 -> 13215860
A38: =A20 -> ENQ-15363-22-23 | B38: =B20 -> 45658 | C38: =C20 -> FA1300052 | D38: =D20 -> 3 CORE X 150 SQ. MM. AL/ARM - STRIP (XLPE) - 11 KV | E38: =E20 -> 0 | F38: =ROUNDUP(F20/1000,2) -> 1172.73 | G38: =ROUNDUP(G20/1000,2) -> 30 | H38: =F38+G38 -> 1202.73 | I38: =I20 -> 0.18 | J38: =ROUND(H38*I38,2) -> 216.49 | K38: =ROUND(H38+J38,2) -> 1419.22 | L38: =L20*1000 -> 12000 | M38: MTR | N38: =K38*L38 -> 17030640
A39: =A21 -> ENQ-15363-22-23 | B39: =B21 -> 45658 | C39: =C21 -> FA1300004 | D39: =D21 -> 3 CORE X 300 SQ. MM. AL/ARM - STRIP (XLPE) - 11 KV | E39: =E21 -> 0 | F39: =ROUNDUP(F21/1000,2) -> 1904.01 | G39: =ROUNDUP(G21/1000,2) -> 48 | H39: =F39+G39 -> 1952.01 | I39: =I21 -> 0.18 | J39: =ROUND(H39*I39,2) -> 351.36 | K39: =ROUND(H39+J39,2) -> 2303.37 | L39: =L21*1000 -> 150000 | M39: MTR | N39: =K39*L39 -> 345505500
A40: =A22 -> ENQ-15363-22-23 | B40: =B22 -> 45658 | C40: =C22 -> FA1300010 | D40: =D22 -> 3 CORE X 400 SQ. MM. AL/ARM - STRIP (XLPE) - 33 KV | E40: =E22 -> 0 | F40: =ROUNDUP(F22/1000,2) -> 3044.05 | G40: =ROUNDUP(G22/1000,2) -> 81.04 | H40: =F40+G40 -> 3125.09 | I40: =I22 -> 0.18 | J40: =ROUND(H40*I40,2) -> 562.52 | K40: =ROUND(H40+J40,2) -> 3687.61 | L40: =L22*1000 -> 77000 | M40: MTR | N40: =K40*L40 -> 283945970
A41: =A23 -> ENQ-15363-22-23 | B41: =B23 -> 45658 | C41: =C23 -> FA0400012 | D41: =D23 -> 3 CORE X 120 SQ MM + 1 CORE X 120 SQ MM (AB CABLES) (BARE) - 11 KV | E41: =E23 -> 3 CORE X 120 SQ MM + 1 CORE X 125 SQ MM (AB CABLES) (INSULATED) - 11 KV | F41: =ROUNDUP(F23/1000,2) -> 1111.95 | G41: =ROUNDUP(G23/1000,2) -> 32.73 | H41: =F41+G41 -> 1144.68 | I41: =I23 -> 0.18 | J41: =ROUND(H41*I41,2) -> 206.04 | K41: =ROUND(H41+J41,2) -> 1350.72 | L41: =L23*1000 -> 22000 | M41: MTR | N41: =K41*L41 -> 29715840
N42: =SUM(N37:N41) -> 689413810
N43: =N42-N24 -> 1900.2902

Sheet PV
A2: Base Date | B2: 45658
A3: PV Terms()
A4: PV FORMULA (IEEMA)
Y9: Ex-Work Po | AJ9: ='AUTO CALCULATION SHEET (2)'!O17 -> Alumimium | AK9: ='AUTO CALCULATION SHEET (2)'!Y17 -> Copper Tape - 0.04 mm | AL9: ='AUTO CALCULATION SHEET (2)'!AD17 -> Extruded semiconductive | AM9: ='AUTO CALCULATION SHEET (2)'!AF17 -> HT-XLPE | AN9: ='AUTO CALCULATION SHEET (2)'!AR17 -> PVC Type ST-2 | AO9: ='AUTO CALCULATION SHEET (2)'!AY17 -> Galvanised Steel Flat Strip | AP9: ='AUTO CALCULATION SHEET (2)'!BK17 -> PVC Type ST-2 | AQ9: ='AUTO CALCULATION SHEET (2)'!BN17 -> FILLER | AR9: RMC | AS9: Drum | AT9: RMC+Drum | AU9: VA | AV9: Groos VA% | AW9: Mfg % | AX9: Int % | AY9: Ins% | AZ9: Net VA %
D10: Date | E10: Al | F10: Cu | G10: CC | H10: PVCC | I10: Fe | J10: Date | K10: Alo | L10: Cuo | M10: Cco | N10: PVCCo | O10: Feo | P10: ALF | Q10: SMIF | R10: XLFL | S10: CCFAI | T10: FEF | Z10: PVC of Al | AA10: PVC of Cu Tape | AB10: PVC of XLPE | AC10: PVC of PVCC | AD10: PVC OF FE | AJ10: 273 | AK10: 996 | AL10: 178 | AM10: 151 | AN10: 72 | AO10: 72 | AP10: 72 | AQ10: 28
A11: ='AUTO CALCULATION SHEET (2)'!D19 -> 3 CORE X 70 SQ. MM. AL/ARM - STRIP (XLPE) - 11 KV | C11: PROVISIONAL | D11: 45719 | E11: 268999.31 | F11: 886720.47 | G11: 176136 | H11: 160825 | I11: 76250 | J11: =$B$2 -> 45658 | K11: 264189 | L11: 837521 | M11: 176136 | N11: 160825 | O11: 76250 | P11: 0.593 | Q11: 0.0712 | R11: 0.679 | S11: 1.396 | T11: 0.849 | Y11: ='AUTO CALCULATION SHEET (2)'!F19 -> 774262.84 | Z11: =P11*(E11-K11) -> 2852.5138 | AA11: =Q11*(F11-L11) -> 3503.0023 | AB11: =R11*(G11-M11) -> 0 | AC11: =S11*(H11-N11) -> 0 | AD11: =T11*(I11-O11) -> 0 | AH11: =Z11+AA11+AB11+AC11+AD11+AE11+AF11+AG11 -> 6355.5161 | AI11: =Y11+AH11 -> 780618.36 | AJ11: ='AUTO CALCULATION SHEET (2)'!O19 -> 567 | AK11: ='AUTO CALCULATION SHEET (2)'!Y19 -> 78 | AL11: ='AUTO CALCULATION SHEET (2)'!AD19 -> 190 | AM11: ='AUTO CALCULATION SHEET (2)'!AF19 -> 510 | AN11: ='AUTO CALCULATION SHEET (2)'!AR19 -> 155 | AO11: ='AUTO CALCULATION SHEET (2)'!AY19 -> 775 | AP11: ='AUTO CALCULATION SHEET (2)'!BK19 -> 490 | AQ11: ='AUTO CALCULATION SHEET (2)'!BN19 -> 560 | AR11: =SUMPRODUCT($AJ$10:$AQ$10,AJ11:AQ11) -> 461229 | AS11: ='AUTO CALCULATION SHEET (2)'!CC19 -> 45000 | AT11: =+AR11+AS11 -> 506229 | AU11: =+AI11-AT11 -> 274389.36 | AV11: =+AU11/AT11 -> 0.54202616 | AX11: 0.02 | AY11: 0.01 | AZ11: =+AV11-(AW11+AX11+AY11) -> 0.51202616
A12: ='AUTO CALCULATION SHEET (2)'!D20 -> 3 CORE X 150 SQ. MM. AL/ARM - STRIP (XLPE) - 11 KV | C12: PROVISIONAL | D12: 45719 | E12: 268999.31 | F12: 886720.47 | G12: 176136 | H12: 160825 | I12: 76250 | J12: =$B$2 -> 45658 | K12: 264189 | L12: 837521 | M12: 176136 | N12: 160825 | O12: 76250 | P12: 1.279 | Q12: 0.0878 | R12: 0.89 | S12: 2.061 | T12: 1.055 | Y12: ='AUTO CALCULATION SHEET (2)'!F20 -> 1172727.6 | Z12: =P12*(E12-K12) -> 6152.3865 | AA12: =Q12*(F12-L12) -> 4319.7135 | AB12: =R12*(G12-M12) -> 0 | AC12: =S12*(H12-N12) -> 0 | AD12: =T12*(I12-O12) -> 0 | AH12: =Z12+AA12+AB12+AC12+AD12+AE12+AF12+AG12 -> 10472.1 | AI12: =Y12+AH12 -> 1183199.7 | AJ12: ='AUTO CALCULATION SHEET (2)'!O20 -> 1215 | AK12: ='AUTO CALCULATION SHEET (2)'!Y20 -> 96 | AL12: ='AUTO CALCULATION SHEET (2)'!AD20 -> 250 | AM12: ='AUTO CALCULATION SHEET (2)'!AF20 -> 663 | AN12: ='AUTO CALCULATION SHEET (2)'!AR20 -> 214 | AO12: ='AUTO CALCULATION SHEET (2)'!AY20 -> 925 | AP12: ='AUTO CALCULATION SHEET (2)'!BK20 -> 725 | AQ12: ='AUTO CALCULATION SHEET (2)'!BN20 -> 844 | AR12: =SUMPRODUCT($AJ$10:$AQ$10,AJ12:AQ12) -> 729764 | AS12: ='AUTO CALCULATION SHEET (2)'!CC20 -> 41400 | AT12: =+AR12+AS12 -> 771164 | AU12: =+AI12-AT12 -> 412035.71 | AV12: =+AU12/AT12 -> 0.53430362 | AX12: 0.02 | AY12: 0.01 | AZ12: =+AV12-(AW12+AX12+AY12) -> 0.50430362
A13: ='AUTO CALCULATION SHEET (2)'!D21 -> 3 CORE X 300 SQ. MM. AL/ARM - STRIP (XLPE) - 11 KV | C13: PROVISIONAL | D13: 45719 | E13: 268999.31 | F13: 886720.47 | G13: 176136 | H13: 160825 | I13: 76250 | J13: =$B$2 -> 45658 | K13: 264189 | L13: 837521 | M13: 176136 | N13: 160825 | O13: 76250 | P13: 2.635 | Q13: 0.1102 | R13: 1.167 | S13: 3.161 | T13: 1.318 | Y13: ='AUTO CALCULATION SHEET (2)'!F21 -> 1904002.4 | Z13: =P13*(E13-K13) -> 12675.167 | AA13: =Q13*(F13-L13) -> 5421.7816 | AB13: =R13*(G13-M13) -> 0 | AC13: =S13*(H13-N13) -> 0 | AD13: =T13*(I13-O13) -> 0 | AH13: =Z13+AA13+AB13+AC13+AD13+AE13+AF13+AG13 -> 18096.948 | AI13: =Y13+AH13 -> 1922099.3 | AJ13: ='AUTO CALCULATION SHEET (2)'!O21 -> 2430 | AK13: ='AUTO CALCULATION SHEET (2)'!Y21 -> 119 | AL13: ='AUTO CALCULATION SHEET (2)'!AD21 -> 328 | AM13: ='AUTO CALCULATION SHEET (2)'!AF21 -> 870 | AN13: ='AUTO CALCULATION SHEET (2)'!AR21 -> 300 | AO13: ='AUTO CALCULATION SHEET (2)'!AY21 -> 1150 | AP13: ='AUTO CALCULATION SHEET (2)'!BK21 -> 1012 | AQ13: ='AUTO CALCULATION SHEET (2)'!BN21 -> 1310 | AR13: =SUMPRODUCT($AJ$10:$AQ$10,AJ13:AQ13) -> 1185612 | AS13: ='AUTO CALCULATION SHEET (2)'!CC21 -> 72000 | AT13: =+AR13+AS13 -> 1257612 | AU13: =+AI13-AT13 -> 664487.33 | AV13: =+AU13/AT13 -> 0.52837229 | AX13: 0.02 | AY13: 0.01 | AZ13: =+AV13-(AW13+AX13+AY13) -> 0.49837229
A14: ='AUTO CALCULATION SHEET (2)'!D22 -> 3 CORE X 400 SQ. MM. AL/ARM - STRIP (XLPE) - 33 KV | C14: PROVISIONAL | D14: 45719 | E14: 268999.31 | F14: 886720.47 | G14: 176136 | H14: 160825 | I14: 76250 | J14: =$B$2 -> 45658 | K14: 264189 | L14: 837521 | M14: 176136 | N14: 160825 | O14: 76250 | P14: 3.374 | Q14: 0.1638 | R14: 3.229 | S14: 5.736 | T14: 1.876 | Y14: ='AUTO CALCULATION SHEET (2)'!F22 -> 3044048.6 | Z14: =P14*(E14-K14) -> 16229.986 | AA14: =Q14*(F14-L14) -> 8058.8732 | AB14: =R14*(G14-M14) -> 0 | AC14: =S14*(H14-N14) -> 0 | AD14: =T14*(I14-O14) -> 0 | AH14: =Z14+AA14+AB14+AC14+AD14+AE14+AF14+AG14 -> 24288.859 | AI14: =Y14+AH14 -> 3068337.5 | AJ14: ='AUTO CALCULATION SHEET (2)'!O22 -> 3240 | AK14: ='AUTO CALCULATION SHEET (2)'!Y22 -> 172 | AL14: ='AUTO CALCULATION SHEET (2)'!AD22 -> 424 | AM14: ='AUTO CALCULATION SHEET (2)'!AF22 -> 2725 | AN14: ='AUTO CALCULATION SHEET (2)'!AR22 -> 430 | AO14: ='AUTO CALCULATION SHEET (2)'!AY22 -> 1625 | AP14: ='AUTO CALCULATION SHEET (2)'!BK22 -> 1600 | AQ14: ='AUTO CALCULATION SHEET (2)'!BN22 -> 2745 | AR14: =SUMPRODUCT($AJ$10:$AQ$10,AJ14:AQ14) -> 1882799 | AS14: ='AUTO CALCULATION SHEET (2)'!CC22 -> 108000 | AT14: =+AR14+AS14 -> 1990799 | AU14: =+AI14-AT14 -> 1077538.5 | AV14: =+AU14/AT14 -> 0.5412593 | AX14: 0.02 | AY14: 0.01 | AZ14: =+AV14-(AW14+AX14+AY14) -> 0.5112593
A18: Item | B18: Calculation part | C18: Date of Inspection | D18: Applicable Date | J18: BASE DATE | P18: FACTORS | Y18: Ex-Work Po | Z18: PVC of Al | AA18: PVC of AlM | AB18: PVC of Alsl | AC18: PVC of CUFtph | AD18: PVC of CCFAIph | AE18: PVC of CCFAIm | AF18: PVC of CCFAIsl | AG18: PVC of CCFAlph | AH18: PV/PKM | AI18: Billing Price/PKM | AJ18: VALUE ADDITION CALCULATION WITH RESPECT TO PERCENTAGE
D19: Date | E19: Al | F19: Cu | G19: CC | H19: PVCC | J19: Date | K19: Alo | L19: Cuo | M19: Cco | N19: PVCco
P20: n | Q20: Alph | R20: Alm | S20: Alsl | T20: CUFtph | U20: CCFAIph | V20: CCFAIm | W20: CCFAIsl | X20: CCFAlph | AJ20: ='AUTO CALCULATION SHEET (2)'!O17 -> Alumimium | AK20: ='AUTO CALCULATION SHEET (2)'!U17 -> Alumimium ALLOY | AL20: ='AUTO CALCULATION SHEET (2)'!AB17 -> Copper Tape - 0.060 mm | AM20: ='AUTO CALCULATION SHEET (2)'!AD17 -> Extruded semiconductive | AN20: ='AUTO CALCULATION SHEET (2)'!AF17 -> HT-XLPE | AO20: ='AUTO CALCULATION SHEET (2)'!AR17 -> PVC Type ST-2 | AP20: ='AUTO CALCULATION SHEET (2)'!BK17 -> PVC Type ST-2 | AR20: RMC | AS20: Drum | AT20: RMC+Drum | AU20: VA | AV20: Groos VA% | AW20: Mfg % | AX20: Int % | AY20: Ins% | AZ20: Net VA %
AJ21: 273 | AK21: =AJ21+7 -> 280 | AL21: 996 | AM21: 178 | AN21: 151 | AO21: 72 | AP21: 72
A22: ='AUTO CALCULATION SHEET (2)'!E23 -> 3 CORE X 120 SQ MM + 1 CORE X 125 SQ MM (AB CABLES) (INSULATED) - 11 KV | C22: PROVISIONAL | D22: 45719 | E22: 268999.31 | F22: 886720.47 | G22: 176136 | H22: 160825 | J22: =$B$2 -> 45658 | K22: 264189 | L22: 837521 | M22: 176136 | N22: 160825 | P22: 3 | Q22: 0.346 | R22: 0.346 | T22: 0.036 | U22: 0.241 | X22: 0.265 | Y22: ='AUTO CALCULATION SHEET (2)'!F23 -> 1111947.3 | Z22: =(Q22*P22*(E22-K22)) -> 4993.1018 | AA22: =R22*(E22-K22) -> 1664.3673 | AB22: =S22*(E22-K22) -> 0 | AC22: =P22*T22*(F22-L22) -> 5313.5428 | AD22: =(U22*P22*(G22-M22)) -> 0 | AE22: =V22*(G22-M22) -> 0 | AF22: =W22*(G22-M22) -> 0 | AG22: =P22*X22*(H22-N22) -> 0 | AH22: =Z22+AA22+AB22+AC22+AD22+AE22+AF22+AG22 -> 11971.012 | AI22: =Y22+AH22 -> 1123918.3 | AJ22: ='AUTO CALCULATION SHEET (2)'!O23 -> 972 | AK22: ='AUTO CALCULATION SHEET (2)'!U23 -> 348 | AL22: ='AUTO CALCULATION SHEET (2)'!AB23 -> 134 | AM22: ='AUTO CALCULATION SHEET (2)'!AD23 -> 252 | AN22: ='AUTO CALCULATION SHEET (2)'!AF23 -> 577 | AO22: ='AUTO CALCULATION SHEET (2)'!AR23 -> 135 | AP22: ='AUTO CALCULATION SHEET (2)'!BK23 -> 760 | AR22: =SUMPRODUCT($AJ$21:$AP$21,AJ22:AP22) -> 692683 | AS22: ='AUTO CALCULATION SHEET (2)'!CC23 -> 41400 | AT22: =+AR22+AS22 -> 734083 | AU22: =+AI22-AT22 -> 389835.33 | AV22: =+AU22/AT22 -> 0.53105075 | AX22: 0.02 | AY22: 0.01 | AZ22: =+AV22-(AW22+AX22+AY22) -> 0.50105075
