Workbook

Sheet Sheet1
A1: DOCKET NO. | B1: Base Date | C1: ITEM CODE | D1: PROPOSE ERP ITEM NAME | E1: Propose Drum Type | F1: Insulation Screening(Metallic) | G1: RM Rate(Insulation Screening(Metallic)) | H1: Weight (Insulation Screening (Metallic)) | I1: Cost Insulation Screening(Metallic) | J1: Conductor | K1: RM Rate(Conductor) | L1: Weight(Conductor) | M1: Cost(Conductor) | N1: AL ALLOY | O1: RM Rate(AL Alloy) | P1: Weight(Al Alloy) | Q1: Cost(AL Alloy) | R1: Insulation Screening(Non-Metallic) | S1: RM Rate(Insulation Screening(Non-Metallic)) | T1: Weight(Insulation Screening(Non-Metallic) | U1: Cost(Insulation Screening(Non-Metallic) | V1: Insulation | W1: RM Rate(Insulation) | X1: Weight(Insulation) | Y1: Cost(Insulation) | Z1: Poly Tape | AA1: RM Rate(Poly Tape) | AB1: Weight(Poly Tape) | AC1: Cost(Poly Tape) | AD1: Inner Sheath | AE1: RM Rate(Inner Sheath) | AF1: Weight(Inner Sheath) | AG1: Cost(Inner Sheath) | AH1: Armouring | AI1: RM Rate(Armouring) | AJ1: Weight(Armouring) | AK1: Cost(Armouring) | AL1: Outer Sheath | AM1: RM Rate(Outer Sheath) | AN1: Weight(Outer Sheath) | AO1: Cost(Outer Sheath) | AP1: Filler | AQ1: RM Rate(Filler) | AR1: Weight(Filler) | AS1: Cost(Filler) | AT1: Grease | AU1: RM Rate(Grease) | AV1: Weight(Grease) | AW1: Cost(Grease) | AX1: Water Swellable Tape | AY1: RM Rate(Water Swellable Tape) | AZ1: Weight(Water Swellable Tape) | BA1: Cost(Water Swellable Tape) | BB1: Semi Conducting Water Swellable Tape | BC1: RM Rate(Semi Conducting Water Swellable Tape) | BD1: Weight(Semi Conducting Water Swellable Tape) | BE1: Cost(Semi Conducting Water Swellable Tape) | BF1: Semicon Tape | BG1: RM Rate(Semicon Tape) | BH1: Weight(Semicon Tape) | BI1: Cost(Semicon Tape) | BJ1: Glass Fiber Tape | BK1: RM Rate(Glass Fiber Tape) | BL1: Weight(Glass Fiber Tape) | BM1: Cost(Glass Fiber Tape) | BN1: Copper Wire 0.8MM | BO1: RM Rate(Copper Wire 0.8MM) | BP1: Weight(Copper Wire 0.8MM) | BQ1: Cost(Copper Wire 0.8MM) | BR1: Rubberized Cotton Tape | BS1: RM Rate(Rubberized Cotton Tape) | BT1: Weight(Rubberized Cotton Tape) | BU1: Cost(Rubberized Cotton Tape) | BV1: Water Tight Compound | BW1: RM Rate(Water Tight Compound) | BX1: Weight(Water Tight Compound) | BY1: Cost(Water Tight Compound) | BZ1: Drum Cost Per KM | CA1: Total RM Cost | CB1: FIRM % | CC1: Firm Value | CD1: MFG% | CE1: MFG Value | CF1: PROF% | CG1: Profit Value | CH1: 1st EX-Works | CI1: Intt % | CJ1: Intt Value | CK1: insp% | CL1: Insp Value | CM1: EX-Works Per KM | CN1: Freight Per KM | CO1: Price Including Freight Per KM | CP1: GST % | CQ1: GST Value | CR1: Price Including GST & Freight Per KM | CS1: QTY | CT1: Unit | CU1: Total Price Of Full QTY(Including Freight&GST) | CV1: DRUM CODE | CW1: DRUM SIZE (FxbXtx Ft) | CX1: Party Standard Length(MTR)
A2: ENQ-15853-22-23 | B2: 45748 | C2: FA0300004 | D2: 2 CORE X 2.5 SQ. MM. CU/UNARD.(PVC) | E2: WOOD | H2: 0 | J2: Copper | K2: 884 | L2: 44 | M2: 38896 | P2: 0 | T2: 0 | V2: Type A PVC | W2: 70 | X2: 26 | Y2: 1820 | Z2: POLY TAPE | AA2: 117 | AB2: 3 | AC2: 351 | AD2: PVC Type ST-1 | AE2: 65.86 | AF2: 39 | AG2: 2568.54 | AJ2: 0 | AL2: PVC Type ST-1 | AM2: 65.86 | AN2: 100 | AO2: 6586 | AR2: 0 | AV2: 0 | AZ2: 0 | BD2: 0 | BH2: 0 | BL2: 0 | BP2: 0 | BT2: 0 | BX2: 0 | BZ2: 1973 | CA2: 52194.54 | CH2: 52194.54 | CM2: 52194.54 | CO2: 52194.54 | CP2: 0.18 | CQ2: 9395.02 | CR2: 61589.56 | CS2: 115.28 | CT2: KMS | CU2: 7100044 | CV2: MD0100004 | CW2: DRUM - 28 X 10 X 23 X 2 | CX2: 1000
A3: ENQ-15853-22-23 | B3: 45748 | C3: FA0300006 | D3: 4 CORE X 2.5 SQ. MM. CU/UNARD.(PVC) | E3: WOOD | H3: 0 | J3: Copper | K3: 884 | L3: 89 | M3: 78676 | P3: 0 | T3: 0 | V3: Type A PVC | W3: 70 | X3: 52 | Y3: 3640 | Z3: POLY TAPE | AA3: 117 | AB3: 4 | AC3: 468 | AD3: PVC Type ST-1 | AE3: 65.86 | AF3: 27 | AG3: 1778.22 | AJ3: 0 | AL3: PVC Type ST-1 | AM3: 65.86 | AN3: 109 | AO3: 7178.74 | AR3: 0 | AV3: 0 | AZ3: 0 | BD3: 0 | BH3: 0 | BL3: 15 | BP3: 0 | BT3: 0 | BX3: 0 | BZ3: 2585 | CA3: 94325.96 | CH3: 94325.96 | CM3: 94325.96 | CO3: 94325.96 | CP3: 0.18 | CQ3: 16978.67 | CR3: 111304.63 | CS3: 121.14 | CT3: KMS | CU3: 13483443 | CV3: MD0100005 | CW3: DRUM - 36 X 14 X 23 X 2 | CX3: 1000
A4: ENQ-15853-22-23 | B4: 45748 | C4: FA0300011 | D4: 10 CORE X 2.5 SQ. MM. CU/UNARD. (PVC) | E4: WOOD | H4: 0 | J4: Copper | K4: 884 | L4: 222 | M4: 196248 | P4: 0 | T4: 0 | V4: Type A PVC | W4: 70 | X4: 130 | Y4: 9100 | Z4: POLY TAPE | AA4: 117 | AB4: 5 | AC4: 585 | AD4: PVC Type ST-1 | AE4: 65.86 | AF4: 36 | AG4: 2370.96 | AJ4: 0 | AL4: PVC Type ST-1 | AM4: 65.86 | AN4: 165 | AO4: 10866.9 | AR4: 0 | AV4: 0 | AZ4: 0 | BD4: 0 | BH4: 0 | BL4: 0 | BP4: 0 | BT4: 0 | BX4: 0 | BZ4: 5448 | CA4: 224618.86 | CH4: 224618.86 | CM4: 224618.86 | CO4: 224618.86 | CP4: 0.18 | CQ4: 40431.39 | CR4: 265050.25 | CS4: 67.91 | CT4: KMS | CU4: 17999563 | CV4: MD0100066 | CW4: DRUM - 40 X 15 X 23 X 2 | CX4: 500
A5: ENQ-15853-22-23 | B5: 45748 | C5: FA0300030 | D5: 6 CORE X 2.5 SQ. MM. CU/UNARD.(PVC) | E5: WOOD | H5: 0 | J5: Copper | K5: 884 | L5: 133 | M5: 117572 | P5: 0 | T5: 0 | V5: Type A PVC | W5: 70 | X5: 78 | Y5: 5460 | Z5: POLY TAPE | AA5: 117 | AB5: 4 | AC5: 468 | AD5: PVC Type ST-1 | AE5: 65.86 | AF5: 27 | AG5: 1778.22 | AJ5: 0 | AL5: PVC Type ST-1 | AM5: 65.86 | AN5: 117 | AO5: 7705.62 | AR5: 0 | AV5: 0 | AZ5: 0 | BD5: 0 | BH5: 0 | BL5: 0 | BP5: 0 | BT5: 0 | BX5: 0 | BZ5: 3113 | CA5: 136096.84 | CH5: 136096.84 | CM5: 136096.84 | CO5: 136096.84 | CP5: 0.18 | CQ5: 24497.43 | CR5: 160594.27 | CS5: 125.62 | CT5: KMS | CU5: 20173852 | CV5: MD0100067 | CW5: DRUM - 40 X 18 X 23 X 2 | CX5: 1000

Sheet AUTO CALCULATION SHEET (2)
A2: TRANSMISSION CORPORATION OF TELANGANA LIMITED
A4: TENDER SPECIFICATION NO () | B4: TGPMM11-12/2025
A5: TENDER DESCRIPTION () | B5: supply of 2 Core // 4 Core // 6 Core // 10 Core x 2.5 Sq.mm Copper Control Cables
A6: Last Date & Time of Submission () | B6: 03:00 P.M. on 08.05.2025
A7: REVERSE AUCTION | B7: Not mention
A8: Price () | B8: The prices quoted shall be Variable. Bids will be called for with prices FADS inclusive of packing and forwarding, GST and other legally permissible duties and levies wherever applicable, handling charges to cover the transport by road from destination railway station to site/stores, unloading at site/stores and insurance (transit and storage at site for 45 days).
A9: Validity () | B9: Bids will remain valid for the period of ninety (90) days from the date of bid opening prescribed by the Purchaser. A bid valid for a shorter period will be rejected.
A10: Delivery Period () | B10: 2 C x 2.5 Sq.mm Copper Control Cable -> 115.28 km -> To commence supply with atleast 60.28 kM within two months from the date of LOI and complete balance qty. in the next month thereafter. 4 C x 2.5 Sq.mm Copper Control Cable -> 121.14 km -> To commence supply with atleast 60.14 kM within two months from the date of LOI and complete balance qty. in the next month thereafter. 6 C x 2.5 Sq.mm Copper Control Cable -> 125.62 km -> To commence supply with atleast 60.62 kM within two months from the date of LOI and complete balance qty. in the next month thereafter. 10 C x 2.5 Sq.mm Copper Control Cable -> 67.91 km -> To complete total supply within two months from the date of LOI.
A11: Payment Terms () | B11: 100% payment will be arranged within 45 days reckoned from the check measurement date in Form-13 duly transferring the said amount to the bank account of the supplier by the purchaser bank. The supplier will have to predefine the Bank details while entering into contract. The supplier will have to predefine the Bank Account details after receipt of LOI and before entering into contract for electronic transfer of payment. However payment in advance may be considered by TGTRANSCO after availing a rebate/ discount @ 0.3% per week or part there of for the advancement depending on the availability of funds.
A12: Standard length () | B12: Each cable drum shall contain one SINGLE CONTINUOUS LENGTH. The desired drum lengths shall be 1000 meters ± 10 % for 2/ 4/ 6 Core cables and 1000/500 metres ± 10 % for 10/12 core cables. The overall quantity tolerance shall be ± 5 % for each size. The Purchaser reserves the right to alter the drum lengths, if required, while placing the order. The bidder may also offer the maximum drum lengths he is capable of supplying against each size.
A13: Packing () | B13: The cable shall be wound on a non-returnable wooden/steel drum (conforming to the latest version of IS:10810) of suitable size and packed. The ends of the cable shall be sealed by means of non-hygroscopic sealing material. The drum packing shall be robust enough for rough handling that may be subjected to during transit by water/rail /road. Type and material of the drum shall be specified by the Bidder by means of a dimensional drawing.
A14: Technical Specification
N16: =Sheet1!J1 -> Conductor | S16: AL ALLOY | U16: Insulation Screening (Metallic) | AC16: Insulation Screening (Non-Metallic) | AE16: Insulation | AK16: POLY TAPE | AL16: Inner Sheath | AS16: Armouring | BC16: Outer Sheath | BM16: FILLER | BN16: GREASE | BO16: Water swellable Tape | BP16: Semi conducting Water Swellable tape | BQ16: SEMICON TAPE | BR16: GLASS FIBER TAPE | BS16: COPPER WIRE 0.8 MM | BT16: RUBBERIZED COTTON TAPE | BU16: Water Tight Compound | BZ16: DRUM COST PER KM | CA16: TOTAL RM COST | CB16: EXTRA CONSUMPTION | CC16: EXTRA CONSUMPTION VALUE
A17: DOCKET NO. | B17: =Sheet1!B1 -> Base Date | C17: ITEM CODE | D17: PROPOSE ERP ITEM NAME | E17: EX-WORKS (PER KM) | F17: FREIGHT PER KM | G17: PRICE INCLUDING FREIGHT (PER KM) | H17: GST % | I17: GST VALUE | J17: PRICE INCLUDING GST & FREIGHT (PER KM) | K17: QTY | L17: Unit | M17: TOTAL PRICE OF FULL QTY (INCLUDING FRIGHT & GST) | N17: Alumimium | O17: Alumimium ALLOY | P17: Copper | Q17: Flexible Copper | R17: Galvanized steel wire | S17: Alumimium | T17: Alumimium ALLOY | U17: Coper tape - 0.1 mm | V17: Copper Tape - 0.03 mm | W17: Copper Tape - 0.035 mm | X17: Copper Tape - 0.04 mm | Y17: Copper Tape - 0.045 mm | Z17: Copper Tape - 0.050 mm | AA17: Copper Tape - 0.060 mm | AB17: Copper Tape - 0.075 mm(DOUBLE) | AC17: Extruded semiconductive | AD17: Extruded Semiconductive(Stripable) | AE17: HT-XLPE | AF17: LT-XLPE | AG17: TR XLPE | AH17: Type A PVC | AI17: Type C PVC (HR) | AJ17: XLPE | AK17: POLY TAPE | AL17: FR PVC Type ST-1 | AM17: FR PVC Type ST-2 | AN17: FRLSH PVC Type ST-2 | AO17: PVC Type ST-1 | AP17: PVC Type ST-1-PRESSURE EXTRUDED | AQ17: PVC Type ST-2 | AR17: PVC Type ST-2-PRESSURE EXTRUDED | AS17: ACSR CORE WIRE | AT17: ACSR DOG STEEL WIRE | AU17: Aluminium Flat Strip | AV17: Aluminium Round Wire | AW17: Double Steel Tape | AX17: Galvanised Steel Flat Strip | AY17: Galvanised Steel Flat Strip (Double) | AZ17: Galvanised Steel Flat Strip-B | BA17: Galvanised Steel Round Wire | BB17: Galvanised Steel Round Wire (Double) | BC17: FR PVC Type ST-1 | BD17: FR PVC Type ST-2 | BE17: FRLSH PVC Type ST-1 | BF17: FRLSH PVC Type ST-2 | BG17: PE, ST-3 | BH17: PE, ST-7 | BI17: ATR PVC Type ST-1 | BJ17: PVC Type ST-2 | BK17: PVC Type ST-2-PRESSURE EXTRUDED | BL17: UV & Track Resistant XLPE | BM17: FILLER | BN17: Grease | BO17: Water swellable Tape | BP17: Semi conducting Water Swellable tape | BQ17: SEMICON TAPE | BR17: GLASS FIBER TAPE | BS17: COPPER WIRE 0.8 MM | BT17: RUBBERIZED COTTON TAPE | BU17: Water Tight Compound | BV17: =Sheet1!E1 -> Propose Drum Type | BW17: =Sheet1!CV1 -> DRUM CODE | BX17: =Sheet1!CW1 -> DRUM SIZE (FxbXtx Ft) | BY17: =Sheet1!CX1 -> Party Standard Length(MTR) | CD17: MFG% | CE17: MFG VALUE | CF17: PROF% | CG17: PROFIT VALUE | CH17: 1ST EX-WORKS | CI17: Intt % | CJ17: INTT VALUE | CK17: insp% | CL17: INSP VALUE | CN17: LP FEB 25 | CO17: DISC %
N18: =+IFERROR(VLOOKUP($N$17,Sheet1!J:L,2,0),0) -> 0 | O18: =+IFERROR(VLOOKUP($O$17,Sheet1!J:L,2,0),0) -> 0 | P18: 855 | Q18: =+IFERROR(VLOOKUP($Q$17,Sheet1!J:M,2,0),0) -> 0 | R18: =+IFERROR(VLOOKUP($R$17,Sheet1!J:M,2,0),0) -> 0 | S18: =+IFERROR(VLOOKUP($S$17,Sheet1!N:Q,2,0),0) -> 0 | T18: =+IFERROR(VLOOKUP($T$17,Sheet1!N:O,2,0),0) -> 0 | U18: =+IFERROR(VLOOKUP($U$17,Sheet1!F:I,2,0),0) -> 0 | V18: =+IFERROR(VLOOKUP($V$17,Sheet1!F:I,2,0),0) -> 0 | W18: =+IFERROR(VLOOKUP($W$17,Sheet1!F:I,2,0),0) -> 0 | X18: =+IFERROR(VLOOKUP($X$17,Sheet1!F:I,2,0),0) -> 0 | Y18: =+IFERROR(VLOOKUP($Y$17,Sheet1!F:I,2,0),0) -> 0 | Z18: =+IFERROR(VLOOKUP($Z$17,Sheet1!F:I,2,0),0) -> 0 | AA18: =+IFERROR(VLOOKUP($AA$17,Sheet1!F:I,2,0),0) -> 0 | AB18: =+IFERROR(VLOOKUP($AB$17,Sheet1!F:I,2,0),0) -> 0 | AC18: =+IFERROR(VLOOKUP($AC$17,Sheet1!R:U,2,0),0) -> 0 | AD18: =+IFERROR(VLOOKUP($AD$17,Sheet1!R:U,2,0),0) -> 0 | AE18: =+IFERROR(VLOOKUP($AE$17,Sheet1!V:Y,2,0),0) -> 0 | AF18: =+IFERROR(VLOOKUP($AF$17,Sheet1!V:Y,2,0),0) -> 0 | AG18: =+IFERROR(VLOOKUP($AG$17,Sheet1!V:Y,2,0),0) -> 0 | AH18: 66 | AI18: =+IFERROR(VLOOKUP($AI$17,Sheet1!V:Y,2,0),0) -> 0 | AJ18: =+IFERROR(VLOOKUP($AJ$17,Sheet1!V:Y,2,0),0) -> 0 | AK18: =+IFERROR(VLOOKUP($AK$17,Sheet1!Z2:AA840,2,0),0) -> 117 | AL18: =+IFERROR(VLOOKUP($AL$17,Sheet1!AD2:AG840,2,0),0) -> 0 | AM18: =+IFERROR(VLOOKUP($AM$17,Sheet1!AD2:AG840,2,0),0) -> 0 | AN18: =+IFERROR(VLOOKUP($AN$17,Sheet1!AD2:AG840,2,0),0) -> 0 | AO18: 61 | AP18: =+IFERROR(VLOOKUP($AP$17,Sheet1!AD2:AG840,2,0),0) -> 0 | AQ18: =+IFERROR(VLOOKUP($AQ$17,Sheet1!AD2:AG840,2,0),0) -> 0 | AR18: =+IFERROR(VLOOKUP($AR$17,Sheet1!AD2:AG840,2,0),0) -> 0 | AS18: =+IFERROR(VLOOKUP($AS$17,Sheet1!AH2:AK840,2,0),0) -> 0 | AT18: =+IFERROR(VLOOKUP($AT$17,Sheet1!AH2:AK840,2,0),0) -> 0 | AU18: =+IFERROR(VLOOKUP($AU$17,Sheet1!AH2:AK840,2,0),0) -> 0 | AV18: =+IFERROR(VLOOKUP($AV$17,Sheet1!AH2:AK840,2,0),0) -> 0 | AW18: =+IFERROR(VLOOKUP($AW$17,Sheet1!AH2:AK840,2,0),0) -> 0 | AX18: =+IFERROR(VLOOKUP($AX$17,Sheet1!AH2:AK840,2,0),0) -> 0 | AY18: =+IFERROR(VLOOKUP($AY$17,Sheet1!AH2:AK840,2,0),0) -> 0 | AZ18: =+IFERROR(VLOOKUP($AZ$17,Sheet1!AH2:AK840,2,0),0) -> 0 | BA18: =+IFERROR(VLOOKUP($BA$17,Sheet1!AH2:AK840,2,0),0) -> 0 | BB18: =+IFERROR(VLOOKUP($BB$17,Sheet1!AH2:AK840,2,0),0) -> 0 | BC18: =+IFERROR(VLOOKUP($BC$17,Sheet1!AL2:AO840,2,0),0) -> 0 | BD18: =+IFERROR(VLOOKUP($BD$17,Sheet1!AL2:AO840,2,0),0) -> 0 | BE18: =+IFERROR(VLOOKUP($BE$17,Sheet1!AL2:AO840,2,0),0) -> 0 | BF18: =+IFERROR(VLOOKUP($BF$17,Sheet1!AL2:AO840,2,0),0) -> 0 | BG18: =+IFERROR(VLOOKUP($BG$17,Sheet1!AL2:AO840,2,0),0) -> 0 | BH18: =+IFERROR(VLOOKUP($BH$17,Sheet1!AL2:AO840,2,0),0) -> 0 | BI18: =AO18+7 -> 68 | BJ18: =+IFERROR(VLOOKUP($BJ$17,Sheet1!AL2:AO840,2,0),0) -> 0 | BK18: =+IFERROR(VLOOKUP($BK$17,Sheet1!AL2:AO840,2,0),0) -> 0 | BL18: =+IFERROR(VLOOKUP($BL$17,Sheet1!AL2:AO840,2,0),0) -> 0 | BM18: =+IFERROR(VLOOKUP($BM$17,Sheet1!AP2:AS840,2,0),0) -> 0 | BN18: =+IFERROR(VLOOKUP($BN$17,Sheet1!AT2:AW840,2,0),0) -> 0 | BO18: =+IFERROR(VLOOKUP($BO$17,Sheet1!AX2:BA840,2,0),0) -> 0 | BP18: =+IFERROR(VLOOKUP($BP$17,Sheet1!BB2:BE840,2,0),0) -> 0 | BQ18: =+IFERROR(VLOOKUP($BQ$17,Sheet1!BF2:BI840,2,0),0) -> 0 | BR18: =+IFERROR(VLOOKUP($BR$17,Sheet1!BJ2:BM840,2,0),0) -> 0 | BS18: =+IFERROR(VLOOKUP($BS$17,Sheet1!BN2:BQ840,2,0),0) -> 0 | BT18: =+IFERROR(VLOOKUP($BT$17,Sheet1!BR2:BU840,2,0),0) -> 0 | BU18: =+IFERROR(VLOOKUP($BU$17,Sheet1!BV2:BY840,2,0),0) -> 0
A19: =Sheet1!A2 -> ENQ-15853-22-23 | B19: =Sheet1!B2 -> 45748 | C19: =Sheet1!C2 -> FA0300004 | D19: =Sheet1!D2 -> 2 CORE X 2.5 SQ. MM. CU/UNARD.(PVC) | E19: =CH19+CJ19+CL19 -> 68632.65 | F19: =ROUNDUP(M25,0) -> 1692 | G19: =E19+F19 -> 70324.65 | H19: =Sheet1!CP2 -> 0.18 | I19: =G19*H19 -> 12658.437 | J19: =G19+I19 -> 82983.087 | K19: =Sheet1!CS2 -> 115.28 | L19: =Sheet1!CT2 -> KMS | M19: =J19*K19 -> 9566290.3 | N19: =+IFERROR(VLOOKUP($N$17,Sheet1!J2:L2,3,0),0) -> 0 | O19: =+IFERROR(VLOOKUP($O$17,Sheet1!J2:L2,3,0),0) -> 0 | P19: =+IFERROR(VLOOKUP($P$17,Sheet1!J2:M2,3,0),0) -> 44 | Q19: =+IFERROR(VLOOKUP($Q$17,Sheet1!J2:M2,3,0),0) -> 0 | R19: =+IFERROR(VLOOKUP($R$17,Sheet1!J2:M2,3,0),0) -> 0 | S19: =+IFERROR(VLOOKUP($S$17,Sheet1!N2:Q2,3,0),0) -> 0 | T19: =+IFERROR(VLOOKUP($T$17,Sheet1!N2:Q2,3,0),0) -> 0 | U19: =+IFERROR(VLOOKUP($U$17,Sheet1!F2:I2,3,0),0) -> 0 | V19: =+IFERROR(VLOOKUP($V$17,Sheet1!F2:I2,3,0),0) -> 0 | W19: =+IFERROR(VLOOKUP($W$17,Sheet1!F2:I2,3,0),0) -> 0 | X19: =+IFERROR(VLOOKUP($X$17,Sheet1!F2:I2,3,0),0) -> 0 | Y19: =+IFERROR(VLOOKUP($Y$17,Sheet1!F2:I2,3,0),0) -> 0 | Z19: =+IFERROR(VLOOKUP($Z$17,Sheet1!F2:I2,3,0),0) -> 0 | AA19: =+IFERROR(VLOOKUP($AA$17,Sheet1!F2:I2,3,0),0) -> 0 | AB19: =+IFERROR(VLOOKUP($AB$17,Sheet1!F2:I2,3,0),0) -> 0 | AC19: =+IFERROR(VLOOKUP($AC$17,Sheet1!R2:U2,3,0),0) -> 0 | AD19: =+IFERROR(VLOOKUP($AD$17,Sheet1!R2:U2,2,0),0) -> 0 | AE19: =+IFERROR(VLOOKUP($AE$17,Sheet1!V2:Y2,3,0),0) -> 0 | AF19: =+IFERROR(VLOOKUP($AF$17,Sheet1!V2:Y2,3,0),0) -> 0 | AG19: =+IFERROR(VLOOKUP($AG$17,Sheet1!V2:Y2,3,0),0) -> 0 | AH19: =+IFERROR(VLOOKUP($AH$17,Sheet1!V2:Y2,3,0),0) -> 26 | AI19: =+IFERROR(VLOOKUP($AI$17,Sheet1!V2:Y2,3,0),0) -> 0 | AJ19: =+IFERROR(VLOOKUP($AJ$17,Sheet1!V2:Y2,3,0),0) -> 0 | AK19: =+IFERROR(VLOOKUP($AK$17,Sheet1!Z2:AB2,3,0),0) -> 3 | AL19: =+IFERROR(VLOOKUP($AL$17,Sheet1!AD2:AG2,3,0),0) -> 0 | AM19: =+IFERROR(VLOOKUP($AM$17,Sheet1!AD2:AG2,3,0),0) -> 0 | AN19: =+IFERROR(VLOOKUP($AN$17,Sheet1!AD2:AG2,3,0),0) -> 0 | AO19: =+IFERROR(VLOOKUP($AO$17,Sheet1!AD2:AG2,3,0),0) -> 39 | AP19: =+IFERROR(VLOOKUP($AP$17,Sheet1!AD2:AG2,3,0),0) -> 0 | AQ19: =+IFERROR(VLOOKUP($AQ$17,Sheet1!AD2:AG2,3,0),0) -> 0 | AR19: =+IFERROR(VLOOKUP($AR$17,Sheet1!AD2:AG2,3,0),0) -> 0 | AS19: =+IFERROR(VLOOKUP($AS$17,Sheet1!AH2:AK2,3,0),0) -> 0 | AT19: =+IFERROR(VLOOKUP($AT$17,Sheet1!AH2:AK2,3,0),0) -> 0 | AU19: =+IFERROR(VLOOKUP($AU$17,Sheet1!AH2:AK2,3,0),0) -> 0 | AV19: =+IFERROR(VLOOKUP($AV$17,Sheet1!AH2:AK2,3,0),0) -> 0 | AW19: =+IFERROR(VLOOKUP($AW$17,Sheet1!AH2:AK2,3,0),0) -> 0 | AX19: =+IFERROR(VLOOKUP($AX$17,Sheet1!AH2:AK2,3,0),0) -> 0 | AY19: =+IFERROR(VLOOKUP($AY$17,Sheet1!AH2:AK2,3,0),0) -> 0 | AZ19: =+IFERROR(VLOOKUP($AZ$17,Sheet1!AH2:AK2,3,0),0) -> 0 | BA19: =+IFERROR(VLOOKUP($BA$17,Sheet1!AH2:AK2,3,0),0) -> 0 | BB19: =+IFERROR(VLOOKUP($BB$17,Sheet1!AH2:AK2,3,0),0) -> 0 | BC19: =+IFERROR(VLOOKUP($BC$17,Sheet1!AL2:AO2,3,0),0) -> 0 | BD19: =+IFERROR(VLOOKUP($BD$17,Sheet1!AL2:AO2,3,0),0) -> 0 | BE19: =+IFERROR(VLOOKUP($BE$17,Sheet1!AL2:AO2,3,0),0) -> 0 | BF19: =+IFERROR(VLOOKUP($BF$17,Sheet1!AL2:AO2,3,0),0) -> 0 | BG19: =+IFERROR(VLOOKUP($BG$17,Sheet1!AL2:AO2,3,0),0) -> 0 | BH19: =+IFERROR(VLOOKUP($BH$17,Sheet1!AL2:AO2,3,0),0) -> 0 | BI19: 100 | BJ19: =+IFERROR(VLOOKUP($BJ$17,Sheet1!AL2:AO2,3,0),0) -> 0 | BK19: =+IFERROR(VLOOKUP($BK$17,Sheet1!AL2:AO2,3,0),0) -> 0 | BL19: =+IFERROR(VLOOKUP($BL$17,Sheet1!AL2:AO2,3,0),0) -> 0 | BM19: =+IFERROR(VLOOKUP($BM$17,Sheet1!AP2:AS2,3,0),0) -> 0 | BN19: =+IFERROR(VLOOKUP($BN$17,Sheet1!AT2:AW2,3,0),0) -> 0 | BO19: =+IFERROR(VLOOKUP($BO$17,Sheet1!AX2:BA2,3,0),0) -> 0 | BP19: =+IFERROR(VLOOKUP($BP$17,Sheet1!BB2:BE2,3,0),0) -> 0 | BQ19: =+IFERROR(VLOOKUP($BQ$17,Sheet1!BF2:BI2,3,0),0) -> 0 | BR19: =+IFERROR(VLOOKUP($BR$17,Sheet1!BJ2:BM2,3,0),0) -> 0 | BS19: =+IFERROR(VLOOKUP($BS$17,Sheet1!BN2:BQ2,3,0),0) -> 0 | BT19: =+IFERROR(VLOOKUP($BT$17,Sheet1!BR2:BU2,3,0),0) -> 0 | BU19: =+IFERROR(VLOOKUP($BU$17,Sheet1!BV2:BY2,3,0),0) -> 0 | BV19: =Sheet1!E2 -> WOOD | BW19: =Sheet1!CV2 -> MD0100004 | BX19: =Sheet1!CW2 -> DRUM - 28 X 10 X 23 X 2 | BY19: =Sheet1!CX2 -> 1000 | BZ19: =Sheet1!BZ2 -> 1973 | CA19: =SUMPRODUCT($N$18:$BU$18,N19:BU19)+BZ19 -> 50839 | CB19: =Sheet1!CB2 -> 0 | CC19: =CA19*CB19 -> 0 | CD19: 0.25 | CE19: =CA19*CD19 -> 12709.75 | CF19: 0 | CG19: =CA19*CF19 -> 0 | CH19: =CA19+CC19+CE19+CG19 -> 63548.75 | CI19: 0.05 | CJ19: =CH19*CI19 -> 3177.4375 | CK19: 0.03 | CL19: =CH19*CK19 -> 1906.4625 | CN19: =258*1000 -> 258000 | CO19: =((CN19-E19)/CN19)*100 -> 73.398198
A20: =Sheet1!A3 -> ENQ-15853-22-23 | B20: =Sheet1!B3 -> 45748 | C20: =Sheet1!C3 -> FA0300006 | D20: =Sheet1!D3 -> 4 CORE X 2.5 SQ. MM. CU/UNARD.(PVC) | E20: =CH20+CJ20+CL20 -> 123712.65 | F20: =ROUNDUP(M26,0) -> 2147 | G20: =E20+F20 -> 125859.65 | H20: =Sheet1!CP3 -> 0.18 | I20: =G20*H20 -> 22654.737 | J20: =G20+I20 -> 148514.39 | K20: =Sheet1!CS3 -> 121.14 | L20: =Sheet1!CT3 -> KMS | M20: =J20*K20 -> 17991033 | N20: =+IFERROR(VLOOKUP($N$17,Sheet1!J3:L3,3,0),0) -> 0 | O20: =+IFERROR(VLOOKUP($O$17,Sheet1!J3:L3,3,0),0) -> 0 | P20: =+IFERROR(VLOOKUP($P$17,Sheet1!J3:M3,3,0),0) -> 89 | Q20: =+IFERROR(VLOOKUP($Q$17,Sheet1!J3:M3,3,0),0) -> 0 | R20: =+IFERROR(VLOOKUP($R$17,Sheet1!J3:M3,3,0),0) -> 0 | S20: =+IFERROR(VLOOKUP($S$17,Sheet1!N3:Q3,3,0),0) -> 0 | T20: =+IFERROR(VLOOKUP($T$17,Sheet1!N3:Q3,3,0),0) -> 0 | U20: =+IFERROR(VLOOKUP($U$17,Sheet1!F3:I3,3,0),0) -> 0 | V20: =+IFERROR(VLOOKUP($V$17,Sheet1!F3:I3,3,0),0) -> 0 | W20: =+IFERROR(VLOOKUP($W$17,Sheet1!F3:I3,3,0),0) -> 0 | X20: =+IFERROR(VLOOKUP($X$17,Sheet1!F3:I3,3,0),0) -> 0 | Y20: =+IFERROR(VLOOKUP($Y$17,Sheet1!F3:I3,3,0),0) -> 0 | Z20: =+IFERROR(VLOOKUP($Z$17,Sheet1!F3:I3,3,0),0) -> 0 | AA20: =+IFERROR(VLOOKUP($AA$17,Sheet1!F3:I3,3,0),0) -> 0 | AB20: =+IFERROR(VLOOKUP($AB$17,Sheet1!F3:I3,3,0),0) -> 0 | AC20: =+IFERROR(VLOOKUP($AC$17,Sheet1!R3:U3,3,0),0) -> 0 | AD20: =+IFERROR(VLOOKUP($AD$17,Sheet1!R3:U3,2,0),0) -> 0 | AE20: =+IFERROR(VLOOKUP($AE$17,Sheet1!V3:Y3,3,0),0) -> 0 | AF20: =+IFERROR(VLOOKUP($AF$17,Sheet1!V3:Y3,3,0),0) -> 0 | AG20: =+IFERROR(VLOOKUP($AG$17,Sheet1!V3:Y3,3,0),0) -> 0 | AH20: =+IFERROR(VLOOKUP($AH$17,Sheet1!V3:Y3,3,0),0) -> 52 | AI20: =+IFERROR(VLOOKUP($AI$17,Sheet1!V3:Y3,3,0),0) -> 0 | AJ20: =+IFERROR(VLOOKUP($AJ$17,Sheet1!V3:Y3,3,0),0) -> 0 | AK20: =+IFERROR(VLOOKUP($AK$17,Sheet1!Z3:AB3,3,0),0) -> 4 | AL20: =+IFERROR(VLOOKUP($AL$17,Sheet1!AD3:AG3,3,0),0) -> 0 | AM20: =+IFERROR(VLOOKUP($AM$17,Sheet1!AD3:AG3,3,0),0) -> 0 | AN20: =+IFERROR(VLOOKUP($AN$17,Sheet1!AD3:AG3,3,0),0) -> 0 | AO20: =+IFERROR(VLOOKUP($AO$17,Sheet1!AD3:AG3,3,0),0) -> 27 | AP20: =+IFERROR(VLOOKUP($AP$17,Sheet1!AD3:AG3,3,0),0) -> 0 | AQ20: =+IFERROR(VLOOKUP($AQ$17,Sheet1!AD3:AG3,3,0),0) -> 0 | AR20: =+IFERROR(VLOOKUP($AR$17,Sheet1!AD3:AG3,3,0),0) -> 0 | AS20: =+IFERROR(VLOOKUP($AS$17,Sheet1!AH3:AK3,3,0),0) -> 0 | AT20: =+IFERROR(VLOOKUP($AT$17,Sheet1!AH3:AK3,3,0),0) -> 0 | AU20: =+IFERROR(VLOOKUP($AU$17,Sheet1!AH3:AK3,3,0),0) -> 0 | AV20: =+IFERROR(VLOOKUP($AV$17,Sheet1!AH3:AK3,3,0),0) -> 0 | AW20: =+IFERROR(VLOOKUP($AW$17,Sheet1!AH3:AK3,3,0),0) -> 0 | AX20: =+IFERROR(VLOOKUP($AX$17,Sheet1!AH3:AK3,3,0),0) -> 0 | AY20: =+IFERROR(VLOOKUP($AY$17,Sheet1!AH3:AK3,3,0),0) -> 0 | AZ20: =+IFERROR(VLOOKUP($AZ$17,Sheet1!AH3:AK3,3,0),0) -> 0 | BA20: =+IFERROR(VLOOKUP($BA$17,Sheet1!AH3:AK3,3,0),0) -> 0 | BB20: =+IFERROR(VLOOKUP($BB$17,Sheet1!AH3:AK3,3,0),0) -> 0 | BC20: =+IFERROR(VLOOKUP($BC$17,Sheet1!AL3:AO3,3,0),0) -> 0 | BD20: =+IFERROR(VLOOKUP($BD$17,Sheet1!AL3:AO3,3,0),0) -> 0 | BE20: =+IFERROR(VLOOKUP($BE$17,Sheet1!AL3:AO3,3,0),0) -> 0 | BF20: =+IFERROR(VLOOKUP($BF$17,Sheet1!AL3:AO3,3,0),0) -> 0 | BG20: =+IFERROR(VLOOKUP($BG$17,Sheet1!AL3:AO3,3,0),0) -> 0 | BH20: =+IFERROR(VLOOKUP($BH$17,Sheet1!AL3:AO3,3,0),0) -> 0 | BI20: 109 | BJ20: =+IFERROR(VLOOKUP($BJ$17,Sheet1!AL3:AO3,3,0),0) -> 0 | BK20: =+IFERROR(VLOOKUP($BK$17,Sheet1!AL3:AO3,3,0),0) -> 0 | BL20: =+IFERROR(VLOOKUP($BL$17,Sheet1!AL3:AO3,3,0),0) -> 0 | BM20: =+IFERROR(VLOOKUP($BM$17,Sheet1!AP3:AS3,3,0),0) -> 0 | BN20: =+IFERROR(VLOOKUP($BN$17,Sheet1!AT3:AW3,3,0),0) -> 0 | BO20: =+IFERROR(VLOOKUP($BO$17,Sheet1!AX3:BA3,3,0),0) -> 0 | BP20: =+IFERROR(VLOOKUP($BP$17,Sheet1!BB3:BE3,3,0),0) -> 0 | BQ20: =+IFERROR(VLOOKUP($BQ$17,Sheet1!BF3:BI3,3,0),0) -> 0 | BR20: =+IFERROR(VLOOKUP($BR$17,Sheet1!BJ3:BM3,3,0),0) -> 0 | BS20: =+IFERROR(VLOOKUP($BS$17,Sheet1!BN3:BQ3,3,0),0) -> 0 | BT20: =+IFERROR(VLOOKUP($BT$17,Sheet1!BR3:BU3,3,0),0) -> 0 | BU20: =+IFERROR(VLOOKUP($BU$17,Sheet1!BV3:BY3,3,0),0) -> 0 | BV20: =Sheet1!E3 -> WOOD | BW20: =Sheet1!CV3 -> MD0100005 | BX20: =Sheet1!CW3 -> DRUM - 36 X 14 X 23 X 2 | BY20: =Sheet1!CX3 -> 1000 | BZ20: =Sheet1!BZ3 -> 2585 | CA20: =SUMPRODUCT($N$18:$BU$18,N20:BU20)+BZ20 -> 91639 | CB20: =Sheet1!CB3 -> 0 | CC20: =CA20*CB20 -> 0 | CD20: 0.25 | CE20: =CA20*CD20 -> 22909.75 | CF20: 0 | CG20: =CA20*CF20 -> 0 | CH20: =CA20+CC20+CE20+CG20 -> 114548.75 | CI20: 0.05 | CJ20: =CH20*CI20 -> 5727.4375 | CK20: 0.03 | CL20: =CH20*CK20 -> 3436.4625 | CN20: =486*1000 -> 486000 | CO20: =((CN20-E20)/CN20)*100 -> 74.544722
A21: =Sheet1!A5 -> ENQ-15853-22-23 | B21: =Sheet1!B5 -> 45748 | C21: =Sheet1!C5 -> FA0300030 | D21: =Sheet1!D5 -> 6 CORE X 2.5 SQ. MM. CU/UNARD.(PVC) | E21: =CH21+CJ21+CL21 -> 178263.45 | F21: =ROUNDUP(M27,0) -> 2070 | G21: =E21+F21 -> 180333.45 | H21: =Sheet1!CP5 -> 0.18 | I21: =G21*H21 -> 32460.021 | J21: =G21+I21 -> 212793.47 | K21: =Sheet1!CS5 -> 125.62 | L21: =Sheet1!CT5 -> KMS | M21: =J21*K21 -> 26731116 | N21: =+IFERROR(VLOOKUP($N$17,Sheet1!J5:L5,3,0),0) -> 0 | O21: =+IFERROR(VLOOKUP($O$17,Sheet1!J5:L5,3,0),0) -> 0 | P21: =+IFERROR(VLOOKUP($P$17,Sheet1!J5:M5,3,0),0) -> 133 | Q21: =+IFERROR(VLOOKUP($Q$17,Sheet1!J5:M5,3,0),0) -> 0 | R21: =+IFERROR(VLOOKUP($R$17,Sheet1!J5:M5,3,0),0) -> 0 | S21: =+IFERROR(VLOOKUP($S$17,Sheet1!N5:Q5,3,0),0) -> 0 | T21: =+IFERROR(VLOOKUP($T$17,Sheet1!N5:Q5,3,0),0) -> 0 | U21: =+IFERROR(VLOOKUP($U$17,Sheet1!F5:I5,3,0),0) -> 0 | V21: =+IFERROR(VLOOKUP($V$17,Sheet1!F5:I5,3,0),0) -> 0 | W21: =+IFERROR(VLOOKUP($W$17,Sheet1!F5:I5,3,0),0) -> 0 | X21: =+IFERROR(VLOOKUP($X$17,Sheet1!F5:I5,3,0),0) -> 0 | Y21: =+IFERROR(VLOOKUP($Y$17,Sheet1!F5:I5,3,0),0) -> 0 | Z21: =+IFERROR(VLOOKUP($Z$17,Sheet1!F5:I5,3,0),0) -> 0 | AA21: =+IFERROR(VLOOKUP($AA$17,Sheet1!F5:I5,3,0),0) -> 0 | AB21: =+IFERROR(VLOOKUP($AB$17,Sheet1!F5:I5,3,0),0) -> 0 | AC21: =+IFERROR(VLOOKUP($AC$17,Sheet1!R5:U5,3,0),0) -> 0 | AD21: =+IFERROR(VLOOKUP($AD$17,Sheet1!R5:U5,2,0),0) -> 0 | AE21: =+IFERROR(VLOOKUP($AE$17,Sheet1!V5:Y5,3,0),0) -> 0 | AF21: =+IFERROR(VLOOKUP($AF$17,Sheet1!V5:Y5,3,0),0) -> 0 | AG21: =+IFERROR(VLOOKUP($AG$17,Sheet1!V5:Y5,3,0),0) -> 0 | AH21: =+IFERROR(VLOOKUP($AH$17,Sheet1!V5:Y5,3,0),0) -> 78 | AI21: =+IFERROR(VLOOKUP($AI$17,Sheet1!V5:Y5,3,0),0) -> 0 | AJ21: =+IFERROR(VLOOKUP($AJ$17,Sheet1!V5:Y5,3,0),0) -> 0 | AK21: =+IFERROR(VLOOKUP($AK$17,Sheet1!Z5:AB5,3,0),0) -> 4 | AL21: =+IFERROR(VLOOKUP($AL$17,Sheet1!AD5:AG5,3,0),0) -> 0 | AM21: =+IFERROR(VLOOKUP($AM$17,Sheet1!AD5:AG5,3,0),0) -> 0 | AN21: =+IFERROR(VLOOKUP($AN$17,Sheet1!AD5:AG5,3,0),0) -> 0 | AO21: =+IFERROR(VLOOKUP($AO$17,Sheet1!AD5:AG5,3,0),0) -> 27 | AP21: =+IFERROR(VLOOKUP($AP$17,Sheet1!AD5:AG5,3,0),0) -> 0 | AQ21: =+IFERROR(VLOOKUP($AQ$17,Sheet1!AD5:AG5,3,0),0) -> 0 | AR21: =+IFERROR(VLOOKUP($AR$17,Sheet1!AD5:AG5,3,0),0) -> 0 | AS21: =+IFERROR(VLOOKUP($AS$17,Sheet1!AH5:AK5,3,0),0) -> 0 | AT21: =+IFERROR(VLOOKUP($AT$17,Sheet1!AH5:AK5,3,0),0) -> 0 | AU21: =+IFERROR(VLOOKUP($AU$17,Sheet1!AH5:AK5,3,0),0) -> 0 | AV21: =+IFERROR(VLOOKUP($AV$17,Sheet1!AH5:AK5,3,0),0) -> 0 | AW21: =+IFERROR(VLOOKUP($AW$17,Sheet1!AH5:AK5,3,0),0) -> 0 | AX21: =+IFERROR(VLOOKUP($AX$17,Sheet1!AH5:AK5,3,0),0) -> 0 | AY21: =+IFERROR(VLOOKUP($AY$17,Sheet1!AH5:AK5,3,0),0) -> 0 | AZ21: =+IFERROR(VLOOKUP($AZ$17,Sheet1!AH5:AK5,3,0),0) -> 0 | BA21: =+IFERROR(VLOOKUP($BA$17,Sheet1!AH5:AK5,3,0),0) -> 0 | BB21: =+IFERROR(VLOOKUP($BB$17,Sheet1!AH5:AK5,3,0),0) -> 0 | BC21: =+IFERROR(VLOOKUP($BC$17,Sheet1!AL5:AO5,3,0),0) -> 0 | BD21: =+IFERROR(VLOOKUP($BD$17,Sheet1!AL5:AO5,3,0),0) -> 0 | BE21: =+IFERROR(VLOOKUP($BE$17,Sheet1!AL5:AO5,3,0),0) -> 0 | BF21: =+IFERROR(VLOOKUP($BF$17,Sheet1!AL5:AO5,3,0),0) -> 0 | BG21: =+IFERROR(VLOOKUP($BG$17,Sheet1!AL5:AO5,3,0),0) -> 0 | BH21: =+IFERROR(VLOOKUP($BH$17,Sheet1!AL5:AO5,3,0),0) -> 0 | BI21: 117 | BJ21: =+IFERROR(VLOOKUP($BJ$17,Sheet1!AL5:AO5,3,0),0) -> 0 | BK21: =+IFERROR(VLOOKUP($BK$17,Sheet1!AL5:AO5,3,0),0) -> 0 | BL21: =+IFERROR(VLOOKUP($BL$17,Sheet1!AL5:AO5,3,0),0) -> 0 | BM21: =+IFERROR(VLOOKUP($BM$17,Sheet1!AP5:AS5,3,0),0) -> 0 | BN21: =+IFERROR(VLOOKUP($BN$17,Sheet1!AT5:AW5,3,0),0) -> 0 | BO21: =+IFERROR(VLOOKUP($BO$17,Sheet1!AX5:BA5,3,0),0) -> 0 | BP21: =+IFERROR(VLOOKUP($BP$17,Sheet1!BB5:BE5,3,0),0) -> 0 | BQ21: =+IFERROR(VLOOKUP($BQ$17,Sheet1!BF5:BI5,3,0),0) -> 0 | BR21: =+IFERROR(VLOOKUP($BR$17,Sheet1!BJ5:BM5,3,0),0) -> 0 | BS21: =+IFERROR(VLOOKUP($BS$17,Sheet1!BN5:BQ5,3,0),0) -> 0 | BT21: =+IFERROR(VLOOKUP($BT$17,Sheet1!BR5:BU5,3,0),0) -> 0 | BU21: =+IFERROR(VLOOKUP($BU$17,Sheet1!BV5:BY5,3,0),0) -> 0 | BV21: =Sheet1!E5 -> WOOD | BW21: =Sheet1!CV5 -> MD0100067 | BX21: =Sheet1!CW5 -> DRUM - 40 X 18 X 23 X 2 | BY21: =Sheet1!CX5 -> 1000 | BZ21: =Sheet1!BZ5 -> 3113 | CA21: =SUMPRODUCT($N$18:$BU$18,N21:BU21)+BZ21 -> 132047 | CB21: =Sheet1!CB5 -> 0 | CC21: =CA21*CB21 -> 0 | CD21: 0.25 | CE21: =CA21*CD21 -> 33011.75 | CF21: 0 | CG21: =CA21*CF21 -> 0 | CH21: =CA21+CC21+CE21+CG21 -> 165058.75 | CI21: 0.05 | CJ21: =CH21*CI21 -> 8252.9375 | CK21: 0.03 | CL21: =CH21*CK21 -> 4951.7625 | CN21: =721*1000 -> 721000 | CO21: =((CN21-E21)/CN21)*100 -> 75.275527
A22: =Sheet1!A4 -> ENQ-15853-22-23 | B22: =Sheet1!B4 -> 45748 | C22: =Sheet1!C4 -> FA0300011 | D22: =Sheet1!D4 -> 10 CORE X 2.5 SQ. MM. CU/UNARD. (PVC) | E22: =CH22+CJ22+CL22 -> 294082.65 | F22: =ROUNDUP(M28,0) -> 3829 | G22: =E22+F22 -> 297911.65 | H22: =Sheet1!CP4 -> 0.18 | I22: =G22*H22 -> 53624.097 | J22: =G22+I22 -> 351535.75 | K22: =Sheet1!CS4 -> 67.91 | L22: =Sheet1!CT4 -> KMS | M22: =J22*K22 -> 23872793 | N22: =+IFERROR(VLOOKUP($N$17,Sheet1!J4:L4,3,0),0) -> 0 | O22: =+IFERROR(VLOOKUP($O$17,Sheet1!J4:L4,3,0),0) -> 0 | P22: =+IFERROR(VLOOKUP($P$17,Sheet1!J4:M4,3,0),0) -> 222 | Q22: =+IFERROR(VLOOKUP($Q$17,Sheet1!J4:M4,3,0),0) -> 0 | R22: =+IFERROR(VLOOKUP($R$17,Sheet1!J4:M4,3,0),0) -> 0 | S22: =+IFERROR(VLOOKUP($S$17,Sheet1!N4:Q4,3,0),0) -> 0 | T22: =+IFERROR(VLOOKUP($T$17,Sheet1!N4:Q4,3,0),0) -> 0 | U22: =+IFERROR(VLOOKUP($U$17,Sheet1!F4:I4,3,0),0) -> 0 | V22: =+IFERROR(VLOOKUP($V$17,Sheet1!F4:I4,3,0),0) -> 0 | W22: =+IFERROR(VLOOKUP($W$17,Sheet1!F4:I4,3,0),0) -> 0 | X22: =+IFERROR(VLOOKUP($X$17,Sheet1!F4:I4,3,0),0) -> 0 | Y22: =+IFERROR(VLOOKUP($Y$17,Sheet1!F4:I4,3,0),0) -> 0 | Z22: =+IFERROR(VLOOKUP($Z$17,Sheet1!F4:I4,3,0),0) -> 0 | AA22: =+IFERROR(VLOOKUP($AA$17,Sheet1!F4:I4,3,0),0) -> 0 | AB22: =+IFERROR(VLOOKUP($AB$17,Sheet1!F4:I4,3,0),0) -> 0 | AC22: =+IFERROR(VLOOKUP($AC$17,Sheet1!R4:U4,3,0),0) -> 0 | AD22: =+IFERROR(VLOOKUP($AD$17,Sheet1!R4:U4,2,0),0) -> 0 | AE22: =+IFERROR(VLOOKUP($AE$17,Sheet1!V4:Y4,3,0),0) -> 0 | AF22: =+IFERROR(VLOOKUP($AF$17,Sheet1!V4:Y4,3,0),0) -> 0 | AG22: =+IFERROR(VLOOKUP($AG$17,Sheet1!V4:Y4,3,0),0) -> 0 | AH22: =+IFERROR(VLOOKUP($AH$17,Sheet1!V4:Y4,3,0),0) -> 130 | AI22: =+IFERROR(VLOOKUP($AI$17,Sheet1!V4:Y4,3,0),0) -> 0 | AJ22: =+IFERROR(VLOOKUP($AJ$17,Sheet1!V4:Y4,3,0),0) -> 0 | AK22: =+IFERROR(VLOOKUP($AK$17,Sheet1!Z4:AB4,3,0),0) -> 5 | AL22: =+IFERROR(VLOOKUP($AL$17,Sheet1!AD4:AG4,3,0),0) -> 0 | AM22: =+IFERROR(VLOOKUP($AM$17,Sheet1!AD4:AG4,3,0),0) -> 0 | AN22: =+IFERROR(VLOOKUP($AN$17,Sheet1!AD4:AG4,3,0),0) -> 0 | AO22: =+IFERROR(VLOOKUP($AO$17,Sheet1!AD4:AG4,3,0),0) -> 36 | AP22: =+IFERROR(VLOOKUP($AP$17,Sheet1!AD4:AG4,3,0),0) -> 0 | AQ22: =+IFERROR(VLOOKUP($AQ$17,Sheet1!AD4:AG4,3,0),0) -> 0 | AR22: =+IFERROR(VLOOKUP($AR$17,Sheet1!AD4:AG4,3,0),0) -> 0 | AS22: =+IFERROR(VLOOKUP($AS$17,Sheet1!AH4:AK4,3,0),0) -> 0 | AT22: =+IFERROR(VLOOKUP($AT$17,Sheet1!AH4:AK4,3,0),0) -> 0 | AU22: =+IFERROR(VLOOKUP($AU$17,Sheet1!AH4:AK4,3,0),0) -> 0 | AV22: =+IFERROR(VLOOKUP($AV$17,Sheet1!AH4:AK4,3,0),0) -> 0 | AW22: =+IFERROR(VLOOKUP($AW$17,Sheet1!AH4:AK4,3,0),0) -> 0 | AX22: =+IFERROR(VLOOKUP($AX$17,Sheet1!AH4:AK4,3,0),0) -> 0 | AY22: =+IFERROR(VLOOKUP($AY$17,Sheet1!AH4:AK4,3,0),0) -> 0 | AZ22: =+IFERROR(VLOOKUP($AZ$17,Sheet1!AH4:AK4,3,0),0) -> 0 | BA22: =+IFERROR(VLOOKUP($BA$17,Sheet1!AH4:AK4,3,0),0) -> 0 | BB22: =+IFERROR(VLOOKUP($BB$17,Sheet1!AH4:AK4,3,0),0) -> 0 | BC22: =+IFERROR(VLOOKUP($BC$17,Sheet1!AL4:AO4,3,0),0) -> 0 | BD22: =+IFERROR(VLOOKUP($BD$17,Sheet1!AL4:AO4,3,0),0) -> 0 | BE22: =+IFERROR(VLOOKUP($BE$17,Sheet1!AL4:AO4,3,0),0) -> 0 | BF22: =+IFERROR(VLOOKUP($BF$17,Sheet1!AL4:AO4,3,0),0) -> 0 | BG22: =+IFERROR(VLOOKUP($BG$17,Sheet1!AL4:AO4,3,0),0) -> 0 | BH22: =+IFERROR(VLOOKUP($BH$17,Sheet1!AL4:AO4,3,0),0) -> 0 | BI22: 165 | BJ22: =+IFERROR(VLOOKUP($BJ$17,Sheet1!AL4:AO4,3,0),0) -> 0 | BK22: =+IFERROR(VLOOKUP($BK$17,Sheet1!AL4:AO4,3,0),0) -> 0 | BL22: =+IFERROR(VLOOKUP($BL$17,Sheet1!AL4:AO4,3,0),0) -> 0 | BM22: =+IFERROR(VLOOKUP($BM$17,Sheet1!AP4:AS4,3,0),0) -> 0 | BN22: =+IFERROR(VLOOKUP($BN$17,Sheet1!AT4:AW4,3,0),0) -> 0 | BO22: =+IFERROR(VLOOKUP($BO$17,Sheet1!AX4:BA4,3,0),0) -> 0 | BP22: =+IFERROR(VLOOKUP($BP$17,Sheet1!BB4:BE4,3,0),0) -> 0 | BQ22: =+IFERROR(VLOOKUP($BQ$17,Sheet1!BF4:BI4,3,0),0) -> 0 | BR22: =+IFERROR(VLOOKUP($BR$17,Sheet1!BJ4:BM4,3,0),0) -> 0 | BS22: =+IFERROR(VLOOKUP($BS$17,Sheet1!BN4:BQ4,3,0),0) -> 0 | BT22: =+IFERROR(VLOOKUP($BT$17,Sheet1!BR4:BU4,3,0),0) -> 0 | BU22: =+IFERROR(VLOOKUP($BU$17,Sheet1!BV4:BY4,3,0),0) -> 0 | BV22: =Sheet1!E4 -> WOOD | BW22: =Sheet1!CV4 -> MD0100066 | BX22: =Sheet1!CW4 -> DRUM - 40 X 15 X 23 X 2 | BY22: =Sheet1!CX4 -> 500 | BZ22: =Sheet1!BZ4 -> 5448 | CA22: =SUMPRODUCT($N$18:$BU$18,N22:BU22)+BZ22 -> 217839 | CB22: =Sheet1!CB4 -> 0 | CC22: =CA22*CB22 -> 0 | CD22: 0.25 | CE22: =CA22*CD22 -> 54459.75 | CF22: 0 | CG22: =CA22*CF22 -> 0 | CH22: =CA22+CC22+CE22+CG22 -> 272298.75 | CI22: 0.05 | CJ22: =CH22*CI22 -> 13614.938 | CK22: 0.03 | CL22: =CH22*CK22 -> 8168.9625 | CN22: =1068*1000 -> 1068000 | CO22: =((CN22-E22)/CN22)*100 -> 72.464171
E24: Order Quantity | F24: Stnd Length | G24: Truck type | H24: Fare of one truck | I24: No of Drum in one truck | J24: Total length in one Truck | K24: No of Truck | L24: Total Freight | M24: Freight per KM | AH24: CABLE WEIGHT KG/KM | AK24: DRUM WEIGHT | AO24: CABLE+DRUM WEIGHT | BI24: TRUCK WEIGHT
D25: =D19 -> 2 CORE X 2.5 SQ. MM. CU/UNARD.(PVC) | E25: =K19 -> 115.28 | F25: =BY19/1000 -> 1 | G25: 16 MT | H25: 65000 | I25: 48 | J25: =F25*I25 -> 48 | K25: =ROUNDUP((E25/J25),0) -> 3 | L25: =M25*E25 -> 195000 | M25: =(H25*K25)/E25 -> 1691.5337 | P25: =BW19 -> MD0100004 | AH25: =SUM(P19:BI19) -> 212 | AK25: =60+15 -> 75 | AO25: =((AH25*F25)+AK25) -> 287 | BI25: =I25*AO25 -> 13776
D26: =D20 -> 4 CORE X 2.5 SQ. MM. CU/UNARD.(PVC) | E26: =K20 -> 121.14 | F26: =BY20/1000 -> 1 | G26: 16 MT | H26: 65000 | I26: 36 | J26: =F26*I26 -> 36 | K26: =ROUNDUP((E26/J26),0) -> 4 | L26: =M26*E26 -> 260000 | M26: =(H26*K26)/E26 -> 2146.277 | P26: =BW20 -> MD0100005 | AH26: =SUM(P20:BI20) -> 281 | AK26: =65+20 -> 85 | AO26: =((AH26*F26)+AK26) -> 366 | BI26: =I26*AO26 -> 13176
D27: =D21 -> 6 CORE X 2.5 SQ. MM. CU/UNARD.(PVC) | E27: =K21 -> 125.62 | F27: =BY21/1000 -> 1 | G27: 16 MT | H27: 65000 | I27: 34 | J27: =F27*I27 -> 34 | K27: =ROUNDUP((E27/J27),0) -> 4 | L27: =M27*E27 -> 260000 | M27: =(H27*K27)/E27 -> 2069.7341 | P27: =BW21 -> MD0100067 | AH27: =SUM(P21:BI21) -> 359 | AK27: =75+25 -> 100 | AO27: =((AH27*F27)+AK27) -> 459 | BI27: =I27*AO27 -> 15606
D28: =D22 -> 10 CORE X 2.5 SQ. MM. CU/UNARD. (PVC) | E28: =K22 -> 67.91 | F28: =BY22/1000 -> 0.5 | G28: 16 MT | H28: 65000 | I28: 36 | J28: =F28*I28 -> 18 | K28: =ROUNDUP((E28/J28),0) -> 4 | L28: =M28*E28 -> 260000 | M28: =(H28*K28)/E28 -> 3828.5967 | P28: =BW22 -> MD0100066 | AH28: =SUM(P22:BI22) -> 558 | AK28: =75+25 -> 100 | AO28: =((AH28*F28)+AK28) -> 379 | BI28: =I28*AO28 -> 13644
E30: NOTE: | F30: Please consider 7 RS/Kg extra on outer sheath for ATR for all items.
E32: ESTIMATE COST | F32: OUR COST | G32: DIFF % FROM OUR COST
D33: =D25 -> 2 CORE X 2.5 SQ. MM. CU/UNARD.(PVC) | E33: 7933108.5 | F33: =M19 -> 9566290.3 | G33: =((F33-E33)/F33)*100 -> 17.072258 | H33: INCLUDING GST
D34: =D26 -> 4 CORE X 2.5 SQ. MM. CU/UNARD.(PVC) | E34: 14801127 | F34: =M20 -> 17991033 | G34: =((F34-E34)/F34)*100 -> 17.730529 | H34: INCLUDING GST
D35: =D27 -> 6 CORE X 2.5 SQ. MM. CU/UNARD.(PVC) | E35: 24285612 | F35: =M21 -> 26731116 | G35: =((F35-E35)/F35)*100 -> 9.1485283 | H35: INCLUDING GST
D36: =D28 -> 10 CORE X 2.5 SQ. MM. CU/UNARD. (PVC) | E36: 19880177 | F36: =M22 -> 23872793 | G36: =((F36-E36)/F36)*100 -> 16.724543 | H36: INCLUDING GST

Sheet Cable
A1: TRANSMISSION CORPORATION OF TELANGANA LIMITED
A3: Base Date | B3: 45748
A4: PV FORMULA | B4: P= P0 + CuF (Cu - Cu0) + CCFCu (CC – CC0) + FeF(Fe-Fe0)
A5: For unarmoued control cables FeF = 0
A7: Item | B7: Calculation part | C7: Date of Inspection | D7: Applicable Date | H7: BASE DATE | L7: FACTORS | O7: Ex-Work Po | P7: PVC of Cu | Q7: PVC of PVC | R7: PVC of FE | S7: PV/PKM | T7: Billing Price/PKM | U7: VALUE ADDITION CALCULATION
D8: Date | E8: Cu | F8: PVC | G8: Fe | H8: Date | I8: Cuo | J8: PVCo | K8: Feo
L9: CuF | M9: CCFCu | N9: FeF | U9: ='AUTO CALCULATION SHEET (2)'!P17 -> Copper | V9: ='AUTO CALCULATION SHEET (2)'!AH17 -> Type A PVC | W9: ='AUTO CALCULATION SHEET (2)'!AK17 -> POLY TAPE | X9: ='AUTO CALCULATION SHEET (2)'!AO17 -> PVC Type ST-1 | Y9: ='AUTO CALCULATION SHEET (2)'!BI17 -> ATR PVC Type ST-1 | Z9: RMC | AA9: Drum | AB9: RMC+Drum | AC9: VA | AD9: Gross VA% | AE9: Mfg % | AF9: Int % | AG9: Ins% | AH9: Net VA
U10: 846 | V10: 64 | W10: 117 | X10: 60 | Y10: =X10+7 -> 67
A11: ='AUTO CALCULATION SHEET (2)'!D19 -> 2 CORE X 2.5 SQ. MM. CU/UNARD.(PVC) | C11: Provisional | D11: 45783 | E11: 852266.45 | F11: 156325 | H11: =$B$3 -> 45748 | I11: 853722 | J11: 156325 | L11: 0.047 | M11: 0.125 | O11: ='AUTO CALCULATION SHEET (2)'!E19 -> 68632.65 | P11: =(L11*(E11-I11)) -> -68.41085 | Q11: =(M11*(F11-J11)) -> 0 | R11: =(N11*(G11-K11)) -> 0 | S11: =P11+Q11+R11 -> -68.41085 | T11: =+O11+S11 -> 68564.239 | U11: ='AUTO CALCULATION SHEET (2)'!P19 -> 44 | V11: ='AUTO CALCULATION SHEET (2)'!AH19 -> 26 | W11: ='AUTO CALCULATION SHEET (2)'!AK19 -> 3 | X11: ='AUTO CALCULATION SHEET (2)'!AO19 -> 39 | Y11: ='AUTO CALCULATION SHEET (2)'!BI19 -> 100 | Z11: =SUMPRODUCT(U11:Y11,$U$10:$Y$10) -> 48279 | AA11: ='AUTO CALCULATION SHEET (2)'!BZ19 -> 1973 | AB11: =Z11+AA11 -> 50252 | AC11: =T11-AB11 -> 18312.239 | AD11: =ROUND((AC11/AB11)*100,2) -> 36.44 | AE11: 0 | AF11: 2 | AG11: 1 | AH11: =AD11-AE11-AF11-AG11 -> 33.44
A12: ='AUTO CALCULATION SHEET (2)'!D20 -> 4 CORE X 2.5 SQ. MM. CU/UNARD.(PVC) | C12: Provisional | D12: 45783 | E12: 852266.45 | F12: 156325 | H12: =$B$3 -> 45748 | I12: 853722 | J12: 156325 | L12: 0.094 | M12: 0.161 | O12: ='AUTO CALCULATION SHEET (2)'!E20 -> 123712.65 | P12: =(L12*(E12-I12)) -> -136.8217 | Q12: =(M12*(F12-J12)) -> 0 | R12: =(N12*(G12-K12)) -> 0 | S12: =P12+Q12+R12 -> -136.8217 | T12: =+O12+S12 -> 123575.83 | U12: ='AUTO CALCULATION SHEET (2)'!P20 -> 89 | V12: ='AUTO CALCULATION SHEET (2)'!AH20 -> 52 | W12: ='AUTO CALCULATION SHEET (2)'!AK20 -> 4 | X12: ='AUTO CALCULATION SHEET (2)'!AO20 -> 27 | Y12: ='AUTO CALCULATION SHEET (2)'!BI20 -> 109 | Z12: =SUMPRODUCT(U12:Y12,$U$10:$Y$10) -> 88013 | AA12: ='AUTO CALCULATION SHEET (2)'!BZ20 -> 2585 | AB12: =Z12+AA12 -> 90598 | AC12: =T12-AB12 -> 32977.828 | AD12: =ROUND((AC12/AB12)*100,2) -> 36.4 | AE12: 0 | AF12: 2 | AG12: 1 | AH12: =AD12-AE12-AF12-AG12 -> 33.4
A13: ='AUTO CALCULATION SHEET (2)'!D21 -> 6 CORE X 2.5 SQ. MM. CU/UNARD.(PVC) | C13: Provisional | D13: 45783 | E13: 852266.45 | F13: 156325 | H13: =$B$3 -> 45748 | I13: 853722 | J13: 156325 | L13: 0.141 | M13: 0.234 | O13: ='AUTO CALCULATION SHEET (2)'!E21 -> 178263.45 | P13: =(L13*(E13-I13)) -> -205.23255 | Q13: =(M13*(F13-J13)) -> 0 | R13: =(N13*(G13-K13)) -> 0 | S13: =P13+Q13+R13 -> -205.23255 | T13: =+O13+S13 -> 178058.22 | U13: ='AUTO CALCULATION SHEET (2)'!P21 -> 133 | V13: ='AUTO CALCULATION SHEET (2)'!AH21 -> 78 | W13: ='AUTO CALCULATION SHEET (2)'!AK21 -> 4 | X13: ='AUTO CALCULATION SHEET (2)'!AO21 -> 27 | Y13: ='AUTO CALCULATION SHEET (2)'!BI21 -> 117 | Z13: =SUMPRODUCT(U13:Y13,$U$10:$Y$10) -> 127437 | AA13: ='AUTO CALCULATION SHEET (2)'!BZ21 -> 3113 | AB13: =Z13+AA13 -> 130550 | AC13: =T13-AB13 -> 47508.217 | AD13: =ROUND((AC13/AB13)*100,2) -> 36.39 | AE13: 0 | AF13: 2 | AG13: 1 | AH13: =AD13-AE13-AF13-AG13 -> 33.39
A14: ='AUTO CALCULATION SHEET (2)'!D22 -> 10 CORE X 2.5 SQ. MM. CU/UNARD. (PVC) | C14: Provisional | D14: 45783 | E14: 852266.45 | F14: 156325 | H14: =$B$3 -> 45748 | I14: 853722 | J14: 156325 | L14: 0.235 | M14: 0.303 | O14: ='AUTO CALCULATION SHEET (2)'!E22 -> 294082.65 | P14: =(L14*(E14-I14)) -> -342.05425 | Q14: =(M14*(F14-J14)) -> 0 | R14: =(N14*(G14-K14)) -> 0 | S14: =P14+Q14+R14 -> -342.05425 | T14: =+O14+S14 -> 293740.6 | U14: ='AUTO CALCULATION SHEET (2)'!P22 -> 222 | V14: ='AUTO CALCULATION SHEET (2)'!AH22 -> 130 | W14: ='AUTO CALCULATION SHEET (2)'!AK22 -> 5 | X14: ='AUTO CALCULATION SHEET (2)'!AO22 -> 36 | Y14: ='AUTO CALCULATION SHEET (2)'!BI22 -> 165 | Z14: =SUMPRODUCT(U14:Y14,$U$10:$Y$10) -> 209932 | AA14: ='AUTO CALCULATION SHEET (2)'!BZ22 -> 5448 | AB14: =Z14+AA14 -> 215380 | AC14: =T14-AB14 -> 78360.596 | AD14: =ROUND((AC14/AB14)*100,2) -> 36.38 | AE14: 0 | AF14: 2 | AG14: 1 | AH14: =AD14-AE14-AF14-AG14 -> 33.38
