Workbook

Sheet Sheet1
A1: DOCKET NO. | B1: Base Date | C1: ITEM CODE | D1: PROPOSE ERP ITEM NAME | E1: Propose Drum Type | F1: Insulation Screening(Metallic) | G1: RM Rate(Insulation Screening(Metallic)) | H1: Weight (Insulation Screening (Metallic)) | I1: Cost Insulation Screening(Metallic) | J1: Conductor | K1: RM Rate(Conductor) | L1: Weight(Conductor) | M1: Cost(Conductor) | N1: AL ALLOY | O1: RM Rate(AL Alloy) | P1: Weight(Al Alloy) | Q1: Cost(AL Alloy) | R1: Insulation Screening(Non-Metallic) | S1: RM Rate(Insulation Screening(Non-Metallic)) | T1: Weight(Insulation Screening(Non-Metallic) | U1: Cost(Insulation Screening(Non-Metallic) | V1: Insulation | W1: RM Rate(Insulation) | X1: Weight(Insulation) | Y1: Cost(Insulation) | Z1: Poly Tape | AA1: RM Rate(Poly Tape) | AB1: Weight(Poly Tape) | AC1: Cost(Poly Tape) | AD1: Inner Sheath | AE1: RM Rate(Inner Sheath) | AF1: Weight(Inner Sheath) | AG1: Cost(Inner Sheath) | AH1: Armouring | AI1: RM Rate(Armouring) | AJ1: Weight(Armouring) | AK1: Cost(Armouring) | AL1: Outer Sheath | AM1: RM Rate(Outer Sheath) | AN1: Weight(Outer Sheath) | AO1: Cost(Outer Sheath) | AP1: Filler | AQ1: RM Rate(Filler) | AR1: Weight(Filler) | AS1: Cost(Filler) | AT1: Grease | AU1: RM Rate(Grease) | AV1: Weight(Grease) | AW1: Cost(Grease) | AX1: Water Swellable Tape | AY1: RM Rate(Water Swellable Tape) | AZ1: Weight(Water Swellable Tape) | BA1: Cost(Water Swellable Tape) | BB1: Semi Conducting Water Swellable Tape | BC1: RM Rate(Semi Conducting Water Swellable Tape) | BD1: Weight(Semi Conducting Water Swellable Tape) | BE1: Cost(Semi Conducting Water Swellable Tape) | BF1: Semicon Tape | BG1: RM Rate(Semicon Tape) | BH1: Weight(Semicon Tape) | BI1: Cost(Semicon Tape) | BJ1: Glass Fiber Tape | BK1: RM Rate(Glass Fiber Tape) | BL1: Weight(Glass Fiber Tape) | BM1: Cost(Glass Fiber Tape) | BN1: Copper Wire 0.8MM | BO1: RM Rate(Copper Wire 0.8MM) | BP1: Weight(Copper Wire 0.8MM) | BQ1: Cost(Copper Wire 0.8MM) | BR1: Rubberized Cotton Tape | BS1: RM Rate(Rubberized Cotton Tape) | BT1: Weight(Rubberized Cotton Tape) | BU1: Cost(Rubberized Cotton Tape) | BV1: Water Tight Compound | BW1: RM Rate(Water Tight Compound) | BX1: Weight(Water Tight Compound) | BY1: Cost(Water Tight Compound) | BZ1: Drum Cost Per KM | CA1: Total RM Cost | CB1: FIRM % | CC1: Firm Value | CD1: MFG% | CE1: MFG Value | CF1: PROF% | CG1: Profit Value | CH1: 1st EX-Works | CI1: Intt % | CJ1: Intt Value | CK1: insp% | CL1: Insp Value | CM1: TTR CHARGES% | CN1: TTR Value | CO1: EX-Works Per KM | CP1: Freight Per KM | CQ1: Price Including Freight Per KM | CR1: GST % | CS1: GST Value | CT1: Price Including GST & Freight Per KM | CU1: QTY | CV1: Unit | CW1: Total Price Of Full QTY(Including Freight&GST) | CX1: DRUM CODE | CY1: DRUM SIZE (FxbXtx Ft) | CZ1: PARTY LENGTH (IF STANDER LENGTH NOT MATCH WITH PAR
A2: ENQ-13772-22-23 | B2: 45523 | C2: FC3700002 | D2: ACSR : WOLF CONDUCTOR - 150 SQ. MM. (30/7/2.59) | E2: WOOD | H2: 0 | J2: Alumimium | K2: 236 | L2: 438 | M2: 103368 | P2: 0 | T2: 0 | X2: 0 | AB2: 0 | AF2: 0 | AH2: ACSR CORE WIRE | AI2: 71.4 | AJ2: 289 | AK2: 20634.6 | AN2: 0 | AR2: 0 | AV2: 0 | AZ2: 0 | BD2: 0 | BH2: 0 | BL2: 0 | BP2: 0 | BT2: 0 | BX2: 0 | BZ2: 1871.51 | CA2: 125874.11 | CB2: 0 | CC2: 0 | CD2: 0.12 | CE2: 15104.9 | CF2: 0 | CG2: 0 | CH2: 140979.01 | CI2: 0.03 | CJ2: 4229.38 | CK2: 0.015 | CL2: 2114.69 | CO2: 147323.08 | CQ2: 147323.08 | CR2: 0.18 | CS2: 26518.15 | CT2: 173841.23 | CU2: 56 | CV2: KMS | CW2: 9735109 | CX2: MD0100013 | CY2: DRUM - 48 X 14 X 36 X 2.25 | CZ2: 2000

Sheet AUTO CALCULATION SHEET (2)
N1: =Sheet1!J1 -> Conductor | S1: AL ALLOY | U1: Insulation Screening (Metallic) | AC1: Insulation Screening (Non-Metallic) | AE1: Insulation | AK1: POLY TAPE | AL1: Inner Sheath | AS1: Armouring | BC1: Outer Sheath | BM1: FILLER | BN1: GREASE | BO1: Water swellable Tape | BP1: Semi conducting Water Swellable tape | BQ1: SEMICON TAPE | BR1: GLASS FIBER TAPE | BS1: COPPER WIRE 0.8 MM | BT1: RUBBERIZED COTTON TAPE | BU1: Water Tight Compound | BZ1: DRUM COST PER KM | CA1: TOTAL RM COST | CB1: EXTRA CONSUMPTION | CC1: EXTRA CONSUMPTION VALUE
A2: DOCKET NO. | B2: =Sheet1!B1 -> Base Date | C2: ITEM CODE | D2: PROPOSE ERP ITEM NAME | E2: EX-WORKS (PER KM) | F2: FREIGHT PER KM | G2: PRICE INCLUDING FREIGHT (PER KM) | H2: GST % | I2: GST VALUE | J2: PRICE INCLUDING GST & FREIGHT (PER KM) | K2: QTY | L2: Unit | M2: TOTAL PRICE OF FULL QTY (INCLUDING FRIGHT & GST) | N2: Alumimium | O2: Alumimium ALLOY | P2: Copper | Q2: Flexible Copper | R2: Galvanized steel wire | S2: Alumimium | T2: Alumimium ALLOY | U2: Coper tape - 0.1 mm | V2: Copper Tape - 0.03 mm | W2: Copper Tape - 0.035 mm | X2: Copper Tape - 0.04 mm | Y2: Copper Tape - 0.045 mm | Z2: Copper Tape - 0.050 mm | AA2: Copper Tape - 0.060 mm | AB2: Copper Tape - 0.075 mm(DOUBLE) | AC2: Extruded semiconductive | AD2: Extruded Semiconductive(Stripable) | AE2: HT-XLPE | AF2: LT-XLPE | AG2: TR XLPE | AH2: Type A PVC | AI2: Type C PVC (HR) | AJ2: XLPE | AK2: POLY TAPE | AL2: FR PVC Type ST-1 | AM2: FR PVC Type ST-2 | AN2: FRLSH PVC Type ST-2 | AO2: PVC Type ST-1 | AP2: PVC Type ST-1-PRESSURE EXTRUDED | AQ2: PVC Type ST-2 | AR2: PVC Type ST-2-PRESSURE EXTRUDED | AS2: ACSR CORE WIRE | AT2: ACSR DOG STEEL WIRE | AU2: Aluminium Flat Strip | AV2: Aluminium Round Wire | AW2: Double Steel Tape | AX2: Galvanised Steel Flat Strip | AY2: Galvanised Steel Flat Strip (Double) | AZ2: Galvanised Steel Flat Strip-B | BA2: Galvanised Steel Round Wire | BB2: Galvanised Steel Round Wire (Double) | BC2: FR PVC Type ST-1 | BD2: FR PVC Type ST-2 | BE2: FRLSH PVC Type ST-1 | BF2: FRLSH PVC Type ST-2 | BG2: PE, ST-3 | BH2: PE, ST-7 | BI2: PVC Type ST-1 | BJ2: PVC Type ST-2 | BK2: PVC Type ST-2-PRESSURE EXTRUDED | BL2: UV & Track Resistant XLPE | BM2: FILLER | BN2: Grease | BO2: Water swellable Tape | BP2: Semi conducting Water Swellable tape | BQ2: SEMICON TAPE | BR2: GLASS FIBER TAPE | BS2: COPPER WIRE 0.8 MM | BT2: RUBBERIZED COTTON TAPE | BU2: Water Tight Compound | BV2: =Sheet1!E1 -> Propose Drum Type | BW2: =Sheet1!CX1 -> DRUM CODE | BX2: =Sheet1!CY1 -> DRUM SIZE (FxbXtx Ft) | BY2: =Sheet1!CZ1 -> PARTY LENGTH (IF STANDER LENGTH NOT MATCH WITH PAR | CD2: MFG% | CE2: MFG VALUE | CF2: PROF% | CG2: PROFIT VALUE | CH2: 1ST EX-WORKS | CI2: Intt % | CJ2: INTT VALUE | CK2: insp% | CL2: INSP VALUE | CM2: =Sheet1!CM1 -> TTR CHARGES% | CN2: =Sheet1!CN1 -> TTR Value
N3: 243 | O3: =+IFERROR(VLOOKUP($O$2,Sheet1!J:L,2,0),0) -> 0 | P3: =+IFERROR(VLOOKUP($P$2,Sheet1!J:M,2,0),0) -> 0 | Q3: =+IFERROR(VLOOKUP($Q$2,Sheet1!J:M,2,0),0) -> 0 | R3: =+IFERROR(VLOOKUP($R$2,Sheet1!J:M,2,0),0) -> 0 | S3: =+IFERROR(VLOOKUP($S$2,Sheet1!N:Q,2,0),0) -> 0 | T3: =+IFERROR(VLOOKUP($T$2,Sheet1!N:O,2,0),0) -> 0 | U3: =+IFERROR(VLOOKUP($U$2,Sheet1!F:I,2,0),0) -> 0 | V3: =+IFERROR(VLOOKUP($V$2,Sheet1!F:I,2,0),0) -> 0 | W3: =+IFERROR(VLOOKUP($W$2,Sheet1!F:I,2,0),0) -> 0 | X3: =+IFERROR(VLOOKUP($X$2,Sheet1!F:I,2,0),0) -> 0 | Y3: =+IFERROR(VLOOKUP($Y$2,Sheet1!F:I,2,0),0) -> 0 | Z3: =+IFERROR(VLOOKUP($Z$2,Sheet1!F:I,2,0),0) -> 0 | AA3: =+IFERROR(VLOOKUP($AA$2,Sheet1!F:I,2,0),0) -> 0 | AB3: =+IFERROR(VLOOKUP($AB$2,Sheet1!F:I,2,0),0) -> 0 | AC3: =+IFERROR(VLOOKUP($AC$2,Sheet1!R:U,2,0),0) -> 0 | AD3: =+IFERROR(VLOOKUP($AD$2,Sheet1!R:U,2,0),0) -> 0 | AE3: =+IFERROR(VLOOKUP($AE$2,Sheet1!V:Y,2,0),0) -> 0 | AF3: =+IFERROR(VLOOKUP($AF$2,Sheet1!V:Y,2,0),0) -> 0 | AG3: =+IFERROR(VLOOKUP($AG$2,Sheet1!V:Y,2,0),0) -> 0 | AH3: =+IFERROR(VLOOKUP($AH$2,Sheet1!V:Y,2,0),0) -> 0 | AI3: =+IFERROR(VLOOKUP($AI$2,Sheet1!V:Y,2,0),0) -> 0 | AJ3: =+IFERROR(VLOOKUP($AJ$2,Sheet1!V:Y,2,0),0) -> 0 | AK3: =+IFERROR(VLOOKUP($AK$2,Sheet1!Z2:AA840,2,0),0) -> 0 | AL3: =+IFERROR(VLOOKUP($AL$2,Sheet1!AD2:AG840,2,0),0) -> 0 | AM3: =+IFERROR(VLOOKUP($AM$2,Sheet1!AD2:AG840,2,0),0) -> 0 | AN3: =+IFERROR(VLOOKUP($AN$2,Sheet1!AD2:AG840,2,0),0) -> 0 | AO3: =+IFERROR(VLOOKUP($AO$2,Sheet1!AD2:AG840,2,0),0) -> 0 | AP3: =+IFERROR(VLOOKUP($AP$2,Sheet1!AD2:AG840,2,0),0) -> 0 | AQ3: =+IFERROR(VLOOKUP($AQ$2,Sheet1!AD2:AG840,2,0),0) -> 0 | AR3: =+IFERROR(VLOOKUP($AR$2,Sheet1!AD2:AG840,2,0),0) -> 0 | AS3: =+IFERROR(VLOOKUP($AS$2,Sheet1!AH2:AK840,2,0),0) -> 71.4 | AT3: =+IFERROR(VLOOKUP($AT$2,Sheet1!AH2:AK840,2,0),0) -> 0 | AU3: =+IFERROR(VLOOKUP($AU$2,Sheet1!AH2:AK840,2,0),0) -> 0 | AV3: =+IFERROR(VLOOKUP($AV$2,Sheet1!AH2:AK840,2,0),0) -> 0 | AW3: =+IFERROR(VLOOKUP($AW$2,Sheet1!AH2:AK840,2,0),0) -> 0 | AX3: =+IFERROR(VLOOKUP($AX$2,Sheet1!AH2:AK840,2,0),0) -> 0 | AY3: =+IFERROR(VLOOKUP($AY$2,Sheet1!AH2:AK840,2,0),0) -> 0 | AZ3: =+IFERROR(VLOOKUP($AZ$2,Sheet1!AH2:AK840,2,0),0) -> 0 | BA3: =+IFERROR(VLOOKUP($BA$2,Sheet1!AH2:AK840,2,0),0) -> 0 | BB3: =+IFERROR(VLOOKUP($BB$2,Sheet1!AH2:AK840,2,0),0) -> 0 | BC3: =+IFERROR(VLOOKUP($BC$2,Sheet1!AL2:AO840,2,0),0) -> 0 | BD3: =+IFERROR(VLOOKUP($BD$2,Sheet1!AL2:AO840,2,0),0) -> 0 | BE3: =+IFERROR(VLOOKUP($BE$2,Sheet1!AL2:AO840,2,0),0) -> 0 | BF3: =+IFERROR(VLOOKUP($BF$2,Sheet1!AL2:AO840,2,0),0) -> 0 | BG3: =+IFERROR(VLOOKUP($BG$2,Sheet1!AL2:AO840,2,0),0) -> 0 | BH3: =+IFERROR(VLOOKUP($BH$2,Sheet1!AL2:AO840,2,0),0) -> 0 | BI3: =+IFERROR(VLOOKUP($BI$2,Sheet1!AL2:AO840,2,0),0) -> 0 | BJ3: =+IFERROR(VLOOKUP($BJ$2,Sheet1!AL2:AO840,2,0),0) -> 0 | BK3: =+IFERROR(VLOOKUP($BK$2,Sheet1!AL2:AO840,2,0),0) -> 0 | BL3: =+IFERROR(VLOOKUP($BL$2,Sheet1!AL2:AO840,2,0),0) -> 0 | BM3: =+IFERROR(VLOOKUP($BM$2,Sheet1!AP2:AS840,2,0),0) -> 0 | BN3: =+IFERROR(VLOOKUP($BN$2,Sheet1!AT2:AW840,2,0),0) -> 0 | BO3: =+IFERROR(VLOOKUP($BO$2,Sheet1!AX2:BA840,2,0),0) -> 0 | BP3: =+IFERROR(VLOOKUP($BP$2,Sheet1!BB2:BE840,2,0),0) -> 0 | BQ3: =+IFERROR(VLOOKUP($BQ$2,Sheet1!BF2:BI840,2,0),0) -> 0 | BR3: =+IFERROR(VLOOKUP($BR$2,Sheet1!BJ2:BM840,2,0),0) -> 0 | BS3: =+IFERROR(VLOOKUP($BS$2,Sheet1!BN2:BQ840,2,0),0) -> 0 | BT3: =+IFERROR(VLOOKUP($BT$2,Sheet1!BR2:BU840,2,0),0) -> 0 | BU3: =+IFERROR(VLOOKUP($BU$2,Sheet1!BV2:BY840,2,0),0) -> 0
A4: =Sheet1!A2 -> ENQ-13772-22-23 | B4: 45524 | C4: =Sheet1!C2 -> FC3700002 | D4: =Sheet1!D2 -> ACSR : WOLF CONDUCTOR - 150 SQ. MM. (30/7/2.59) | E4: =CH4+CJ4+CL4+CN4 -> 145540.19 | F4: =ROUNDUP(M7,0) -> 4822 | G4: =E4+F4 -> 150362.19 | H4: =Sheet1!CR2 -> 0.18 | I4: =G4*H4 -> 27065.195 | J4: =G4+I4 -> 177427.39 | K4: =Sheet1!CU2 -> 56 | L4: =Sheet1!CV2 -> KMS | M4: =J4*K4 -> 9935933.7 | N4: =+IFERROR(VLOOKUP($N$2,Sheet1!J2:L2,3,0),0) -> 438 | O4: =+IFERROR(VLOOKUP($O$2,Sheet1!J2:L2,3,0),0) -> 0 | P4: =+IFERROR(VLOOKUP($P$2,Sheet1!J2:M2,3,0),0) -> 0 | Q4: =+IFERROR(VLOOKUP($Q$2,Sheet1!J2:M2,3,0),0) -> 0 | R4: =+IFERROR(VLOOKUP($R$2,Sheet1!J2:M2,3,0),0) -> 0 | S4: =+IFERROR(VLOOKUP($S$2,Sheet1!N2:Q2,3,0),0) -> 0 | T4: =+IFERROR(VLOOKUP($T$2,Sheet1!N2:Q2,3,0),0) -> 0 | U4: =+IFERROR(VLOOKUP($U$2,Sheet1!F2:I2,3,0),0) -> 0 | V4: =+IFERROR(VLOOKUP($V$2,Sheet1!F2:I2,3,0),0) -> 0 | W4: =+IFERROR(VLOOKUP($W$2,Sheet1!F2:I2,3,0),0) -> 0 | X4: =+IFERROR(VLOOKUP($X$2,Sheet1!F2:I2,3,0),0) -> 0 | Y4: =+IFERROR(VLOOKUP($Y$2,Sheet1!F2:I2,3,0),0) -> 0 | Z4: =+IFERROR(VLOOKUP($Z$2,Sheet1!F2:I2,3,0),0) -> 0 | AA4: =+IFERROR(VLOOKUP($AA$2,Sheet1!F2:I2,3,0),0) -> 0 | AB4: =+IFERROR(VLOOKUP($AB$2,Sheet1!F2:I2,3,0),0) -> 0 | AC4: =+IFERROR(VLOOKUP($AC$2,Sheet1!R2:U2,3,0),0) -> 0 | AD4: =+IFERROR(VLOOKUP($AD$2,Sheet1!R2:U2,3,0),0) -> 0 | AE4: =+IFERROR(VLOOKUP($AE$2,Sheet1!V2:Y2,3,0),0) -> 0 | AF4: =+IFERROR(VLOOKUP($AF$2,Sheet1!V2:Y2,3,0),0) -> 0 | AG4: =+IFERROR(VLOOKUP($AG$2,Sheet1!V2:Y2,3,0),0) -> 0 | AH4: =+IFERROR(VLOOKUP($AH$2,Sheet1!V2:Y2,3,0),0) -> 0 | AI4: =+IFERROR(VLOOKUP($AI$2,Sheet1!V2:Y2,3,0),0) -> 0 | AJ4: =+IFERROR(VLOOKUP($AJ$2,Sheet1!V2:Y2,3,0),0) -> 0 | AK4: =+IFERROR(VLOOKUP($AK$2,Sheet1!Z2:AB2,3,0),0) -> 0 | AL4: =+IFERROR(VLOOKUP($AL$2,Sheet1!AD2:AG2,3,0),0) -> 0 | AM4: =+IFERROR(VLOOKUP($AM$2,Sheet1!AD2:AG2,3,0),0) -> 0 | AN4: =+IFERROR(VLOOKUP($AN$2,Sheet1!AD2:AG2,3,0),0) -> 0 | AO4: =+IFERROR(VLOOKUP($AO$2,Sheet1!AD2:AG2,3,0),0) -> 0 | AP4: =+IFERROR(VLOOKUP($AP$2,Sheet1!AD2:AG2,3,0),0) -> 0 | AQ4: =+IFERROR(VLOOKUP($AQ$2,Sheet1!AD2:AG2,3,0),0) -> 0 | AR4: =+IFERROR(VLOOKUP($AR$2,Sheet1!AD2:AG2,3,0),0) -> 0 | AS4: =+IFERROR(VLOOKUP($AS$2,Sheet1!AH2:AK2,3,0),0) -> 289 | AT4: =+IFERROR(VLOOKUP($AT$2,Sheet1!AH2:AK2,3,0),0) -> 0 | AU4: =+IFERROR(VLOOKUP($AU$2,Sheet1!AH2:AK2,3,0),0) -> 0 | AV4: =+IFERROR(VLOOKUP($AV$2,Sheet1!AH2:AK2,3,0),0) -> 0 | AW4: =+IFERROR(VLOOKUP($AW$2,Sheet1!AH2:AK2,3,0),0) -> 0 | AX4: =+IFERROR(VLOOKUP($AX$2,Sheet1!AH2:AK2,3,0),0) -> 0 | AY4: =+IFERROR(VLOOKUP($AY$2,Sheet1!AH2:AK2,3,0),0) -> 0 | AZ4: =+IFERROR(VLOOKUP($AZ$2,Sheet1!AH2:AK2,3,0),0) -> 0 | BA4: =+IFERROR(VLOOKUP($BA$2,Sheet1!AH2:AK2,3,0),0) -> 0 | BB4: =+IFERROR(VLOOKUP($BB$2,Sheet1!AH2:AK2,3,0),0) -> 0 | BC4: =+IFERROR(VLOOKUP($BC$2,Sheet1!AL2:AO2,3,0),0) -> 0 | BD4: =+IFERROR(VLOOKUP($BD$2,Sheet1!AL2:AO2,3,0),0) -> 0 | BE4: =+IFERROR(VLOOKUP($BE$2,Sheet1!AL2:AO2,3,0),0) -> 0 | BF4: =+IFERROR(VLOOKUP($BF$2,Sheet1!AL2:AO2,3,0),0) -> 0 | BG4: =+IFERROR(VLOOKUP($BG$2,Sheet1!AL2:AO2,3,0),0) -> 0 | BH4: =+IFERROR(VLOOKUP($BH$2,Sheet1!AL2:AO2,3,0),0) -> 0 | BI4: =+IFERROR(VLOOKUP($BI$2,Sheet1!AL2:AO2,3,0),0) -> 0 | BJ4: =+IFERROR(VLOOKUP($BJ$2,Sheet1!AL2:AO2,3,0),0) -> 0 | BK4: =+IFERROR(VLOOKUP($BK$2,Sheet1!AL2:AO2,3,0),0) -> 0 | BL4: =+IFERROR(VLOOKUP($BL$2,Sheet1!AL2:AO2,3,0),0) -> 0 | BM4: =+IFERROR(VLOOKUP($BM$2,Sheet1!AP2:AS2,3,0),0) -> 0 | BN4: =+IFERROR(VLOOKUP($BN$2,Sheet1!AT2:AW2,3,0),0) -> 0 | BO4: =+IFERROR(VLOOKUP($BO$2,Sheet1!AX2:BA2,3,0),0) -> 0 | BP4: =+IFERROR(VLOOKUP($BP$2,Sheet1!BB2:BE2,3,0),0) -> 0 | BQ4: =+IFERROR(VLOOKUP($BQ$2,Sheet1!BF2:BI2,3,0),0) -> 0 | BR4: =+IFERROR(VLOOKUP($BR$2,Sheet1!BJ2:BM2,3,0),0) -> 0 | BS4: =+IFERROR(VLOOKUP($BS$2,Sheet1!BN2:BQ2,3,0),0) -> 0 | BT4: =+IFERROR(VLOOKUP($BT$2,Sheet1!BR2:BU2,3,0),0) -> 0 | BU4: =+IFERROR(VLOOKUP($BU$2,Sheet1!BV2:BY2,3,0),0) -> 0 | BV4: =Sheet1!E2 -> WOOD | BW4: MD0100060 | BX4: Drum - 1345 x 600 x 710 (wood) | BY4: =Sheet1!CZ2 -> 2000 | BZ4: =6186/2 -> 3093 | CA4: =SUMPRODUCT($N$3:$BU$3,N4:BU4)+BZ4 -> 130161.6 | CB4: =Sheet1!CB2 -> 0 | CC4: =CA4*CB4 -> 0 | CD4: 0.07 | CE4: =CA4*CD4 -> 9111.312 | CF4: =Sheet1!CF2 -> 0 | CG4: =CA4*CF4 -> 0 | CH4: =CA4+CC4+CE4+CG4 -> 139272.91 | CI4: =Sheet1!CI2 -> 0.03 | CJ4: =CH4*CI4 -> 4178.1874 | CK4: =Sheet1!CK2 -> 0.015 | CL4: =CH4*CK4 -> 2089.0937 | CM4: =Sheet1!CM2 -> 0 | CN4: =CH4*CM4 -> 0
D6: Lapalang, Shillong, Meghalaya - 793006 | E6: Order Quantity | F6: Stnd Length | G6: Truck type | H6: Fare of one truck | I6: No of Drum in one truck | J6: Total length in one Truck | K6: No of Truck | L6: Total Freight | M6: Freight per KM | AS6: conductor weight kg/km | BV6: drum weight | BW6: conductor+drum weight | BX6: truck weight
E7: =K4 -> 56 | F7: 2 | G7: 16 MT | H7: 90000 | I7: 10 | J7: =F7*I7 -> 20 | K7: =ROUNDUP((E7/J7),0) -> 3 | L7: =M7*E7 -> 270000 | M7: =(H7*K7)/E7 -> 4821.4286 | AS7: =N4+AS4 -> 727 | BV7: =120+30 -> 150 | BW7: =((AS7*F7)+BV7) -> 1604 | BX7: =I7*BW7 -> 16040
A10: DOCKET NO. | B10: Base Date | C10: ITEM CODE | D10: PROPOSE ERP ITEM NAME | E10: EX-WORKS (PER Mtr) | F10: FREIGHT PER MTR | G10: PRICE INCLUDING FREIGHT (PER MTR) | H10: GST % | I10: GST VALUE | J10: PRICE INCLUDING GST & FREIGHT (PER MTR) | K10: QTY | L10: Unit | M10: TOTAL PRICE OF FULL QTY (INCLUDING FRIGHT & GST)
A12: =A4 -> ENQ-13772-22-23 | B12: =B4 -> 45524 | C12: =C4 -> FC3700002 | D12: =D4 -> ACSR : WOLF CONDUCTOR - 150 SQ. MM. (30/7/2.59) | E12: =ROUNDUP(E4/1000,2) -> 145.55 | F12: =ROUNDUP(F4/1000,2) -> 4.83 | G12: =E12+F12 -> 150.38 | H12: =H4 -> 0.18 | I12: =G12*H12 -> 27.0684 | J12: =G12+I12 -> 177.4484 | K12: =K4*1000 -> 56000 | L12: MTR | M12: =J12*K12 -> 9937110.4
