Workbook

Sheet Sheet1
A1: DOCKET NO. | B1: Base Date | C1: ITEM CODE | D1: PROPOSE ERP ITEM NAME | E1: PROPOSE DRUM TYPE | F1: Insulation Screening (Metallic) | G1: RM RATE (Insulation Screening (Metallic)) | H1: Weight (Insulation Screening (Metallic)) | I1: COST(Insulation Screening (Metallic)) | J1: Conductor | K1: RM RATE(Conductor) | L1: WEIGHT(Conductor) | M1: COST(Conductor) | N1: AL ALLOY | O1: RM RATE(Alu Alloy) | P1: WEIGHT(Alu Alloy) | Q1: COST(Alu Alloy) | R1: Insulation Screening (Non-Metallic) | S1: RM RATE(Insulation Screening (Non-Metallic)) | T1: WEIGHT(Insulation Screening (Non-Metallic)) | U1: COST(Insulation Screening (Non-Metallic)) | V1: Insulation | W1: RM RATE(Insulation) | X1: WEIGHT(Insulation) | Y1: COST(Insulation) | Z1: POLY TAPE | AA1: RM RATE (Poly Tape) | AB1: WEIGHT (Poly Tape) | AC1: COST(Poly Tape) | AD1: Inner Sheath | AE1: RM RATE(Inner Sheath) | AF1: WEIGHT(Inner Sheath) | AG1: COST(Inner Sheath) | AH1: Armouring | AI1: RM RATE(Armouring) | AJ1: WEIGHT(Armouring) | AK1: COST(Armouring) | AL1: Outer Sheath | AM1: RM RATE(Outer Sheath) | AN1: WEIGHT(Outer Sheath) | AO1: COST(Outer Sheath) | AP1: FILLER | AQ1: RM RATE(Filler) | AR1: WEIGHT(Filler) | AS1: COST(Filler) | AT1: GREASE | AU1: RM RATE(Grease) | AV1: WEIGHT(Grease) | AW1: COST(Grease) | AX1: Water swellable Tape | AY1: RM RATE(Water swellable Tape) | AZ1: WEIGHT(Water swellable Tape) | BA1: COST(Water swellable Tape) | BB1: Semi conducting Water Swellable tape | BC1: RM RATE(Semi conducting Water Swellable tape) | BD1: WEIGHT(Semi conducting Water Swellable tape) | BE1: COST(Semi conducting Water Swellable tape) | BF1: SEMICON TAPE | BG1: RM RATE(SEMICON TAPE) | BH1: WEIGHT(SEMICON TAPE) | BI1: COST(SEMICON TAPE) | BJ1: GLASS FIBER TAPE | BK1: RM RATE(GLASS FIBER TAPE) | BL1: WEIGHT(GLASS FIBER TAPE) | BM1: COST(GLASS FIBER TAPE) | BN1: COPPER WIRE 0.8 MM | BO1: RM RATE(COPPER WIRE 0.8 MM) | BP1: WEIGHT(COPPER WIRE 0.8 MM) | BQ1: COST(COPPER WIRE 0.8 MM) | BR1: RUBBERIZED COTTON TAPE | BS1: RM RATE(RUBBERIZED COTTON TAPE) | BT1: WEIGHT(RUBBERIZED COTTON TAPE) | BU1: COST(RUBBERIZED COTTON TAPE) | BV1: Water Tight Compound | BW1: RM RATE(Water Tight Compound) | BX1: WEIGHT(Water Tight Compound) | BY1: COST(Water Tight Compound) | BZ1: DRUM COST PER KM | CA1: TOTAL RM COST | CB1: FIRM % | CC1: FIRM VALUE | CD1: MFG% | CE1: MFG VALUE | CF1: PROF% | CG1: PROFIT VALUE | CH1: 1ST EX-WORKS | CI1: Intt % | CJ1: INTT VALUE | CK1: insp% | CL1: INSP VALUE | CM1: EX-WORKS (PER KM) | CN1: FREIGHT PER KM | CO1: PRICE INCLUDING FREIGHT (PER KM) | CP1: GST % | CQ1: GST VALUE | CR1: PRICE INCLUDING GST & FREIGHT (PER KM) | CS1: QTY | CT1: Unit | CU1: TOTAL PRICE OF FULL QTY (INCLUDING FRIGHT & GST) | CV1: DRUM CODE | CW1: DRUM SIZE (FxbXtx Ft) | CX1: PARTY STANDARD LENGTH (MTR)
A2: ENQ-11781-22-23 | B2: 45200 | C2: FA0900014 | D2: 4 CORE X 25 SQ. MM. AL/ARD - STRIP (PVC) | E2: WOOD | J2: Alumimium | K2: 219 | L2: 270 | M2: 59130 | P2: 0 | T2: 0 | V2: Type A PVC | W2: 74.45 | X2: 160 | Y2: 11912 | AB2: 0 | AD2: PVC Type ST-1 | AE2: 60.87 | AF2: 47 | AG2: 2860.89 | AH2: Galvanised Steel Flat Strip | AI2: 76.25 | AJ2: 372 | AK2: 28365 | AL2: PVC Type ST-1 | AM2: 60.87 | AN2: 177 | AO2: 10773.99 | AR2: 0 | AV2: 0 | AZ2: 0 | BD2: 0 | BH2: 0 | BL2: 0 | BP2: 0 | BT2: 0 | BX2: 0 | BZ2: 5151.48 | CA2: 118193.36 | CH2: 118193.36 | CM2: 118193.36 | CN2: 1875 | CO2: 120068.36 | CP2: 0.18 | CQ2: 21612.3 | CR2: 141680.66 | CS2: 200 | CT2: KMS | CU2: 28336133 | CV2: MD0100066 | CW2: DRUM - 40 X 15 X 23 X 2 | CX2: 500
A3: ENQ-11781-22-23 | B3: 45200 | C3: FA0900011 | D3: 4 CORE X 10 SQ. MM. AL/ARD - STRIP (PVC) | E3: WOOD | J3: Alumimium | K3: 219 | L3: 108 | M3: 23652 | P3: 0 | T3: 0 | V3: Type A PVC | W3: 74.45 | X3: 98 | Y3: 7296.1 | AB3: 0 | AD3: PVC Type ST-1 | AE3: 60.87 | AF3: 35 | AG3: 2130.45 | AH3: Galvanised Steel Flat Strip | AI3: 76.25 | AJ3: 281 | AK3: 21426.25 | AL3: PVC Type ST-1 | AM3: 60.87 | AN3: 139 | AO3: 8460.93 | AR3: 0 | AV3: 0 | AZ3: 0 | BD3: 0 | BH3: 0 | BL3: 25 | BP3: 0 | BT3: 0 | BX3: 0 | BZ3: 4610.79 | CA3: 67576.52 | CH3: 67576.52 | CM3: 67576.52 | CN3: 1250 | CO3: 68826.52 | CP3: 0.18 | CQ3: 12388.77 | CR3: 81215.29 | CS3: 1500 | CT3: KMS | CU3: 121822940 | CV3: MD0100005 | CW3: DRUM - 36 X 14 X 23 X 2 | CX3: 500

Sheet AUTO CALCULATION SHEET (2)
A2: WEST BENGAL STATE ELECTRICITY DISTRIBUTION COMPANY LIMITED
A4: TENDER SPECIFICATION NO () | B4: P-46/2023-24/PC-III/PVC
A5: TENDER DESCRIPTION () | B5: LT POWER CABLE TENDER
A6: Last Date & Time of Submission () | B6: 19.12.2023 up to 14.00 Hrs
A7: REVERSE AUCTION | B7: through electronic tendering (etendering) process followed by Reverse Auction (Tender cum Auction)
A8: Price () | B8: The price is Variable as per PV Formula of IEEMA with base date 01.10.2023.
A9: Validity () | B9: The offer against tender should remain valid for a minimum period of 120 days from the next day of opening of the tender. However, WBSEDCL may, on the merit of case, request for extension of validity of the offer for a further suitable period without any change in terms & conditions of the offer.
A10: Delivery Period () | B10: The date of receipt of offer for inspection of the materials/ equipment along with works test certificate will be treated as the date of delivery of that particular lot provided the materials pass in inspection and testing. Delay in offer beyond the delivery schedule to be incorporated in the order shall attract imposition of L.D. as per L.D. Clause. The materials should reach the destination store within. a. 21 working days from the date of issue of the Dispatch Instruction for the manufacturer located outside state. b. 10 working days from the date of issue of the Dispatch Instruction for the manufacturer located within West Bengal. Otherwise L.D. will be levied as per L.D. Clause. Delay beyond the date of delivery as per schedule of Purchase order shall attract imposition of L.D. as per L.D. Clause.
A11: Payment Terms () | B11: 90% payment inclusive of Price Variation bill, along with 100% taxes and duties will be made within 45 (forty five) days from the date of submission of bill against : e) Original receipted Challan/Invoice signed by an officer in the rank of Superintending Engineer/Asstt. Manager/Jr. Manager(Stores) attached to the respective stores. And f) Report for in-house testing, if done after delivery of the items at different site stores signed by the Engineers of Dist. Testing Department. g) Balance 10% payment will be made within 45 (forty five) days of submission of bills along with SRV.
A12: Standard length () | B12: 1.1 KV PVC Cable 4 Core 10 sq. mm - 500 + 5% 1.1 KV PVC Cable 4 Core 25 sq. mm - 500 + 5%
A13: Packing () | B13: The Cable shall be supplied in non-returnable wooden drums having drum length as mentioned below with tolerance of + 5% per drum subject to overall maximum minus (-) 1% on total delivered quantity will be accepted.
A14: Technical Specification
N16: =Sheet1!J1 -> Conductor | S16: AL ALLOY | U16: Insulation Screening (Metallic) | AC16: Insulation Screening (Non-Metallic) | AE16: Insulation | AK16: POLY TAPE | AL16: Inner Sheath | AS16: Armouring | BC16: Outer Sheath | BM16: FILLER | BN16: GREASE | BO16: Water swellable Tape | BP16: Semi conducting Water Swellable tape | BQ16: SEMICON TAPE | BR16: GLASS FIBER TAPE | BS16: COPPER WIRE 0.8 MM | BT16: RUBBERIZED COTTON TAPE | BU16: Water Tight Compound | BZ16: DRUM COST PER KM | CA16: TOTAL RM COST | CB16: EXTRA CONSUMPTION | CC16: EXTRA CONSUMPTION VALUE
A17: DOCKET NO. | B17: =Sheet1!B1 -> Base Date | C17: ITEM CODE | D17: PROPOSE ERP ITEM NAME | E17: EX-WORKS (PER KM) | F17: FREIGHT PER KM | G17: PRICE INCLUDING FREIGHT (PER KM) | H17: GST % | I17: GST VALUE | J17: PRICE INCLUDING GST & FREIGHT (PER KM) | K17: QTY | L17: Unit | M17: TOTAL PRICE OF FULL QTY (INCLUDING FRIGHT & GST) | N17: Alumimium | O17: Alumimium ALLOY | P17: Copper | Q17: Flexible Copper | R17: Galvanized steel wire | S17: Alumimium | T17: Alumimium ALLOY | U17: Coper tape - 0.1 mm | V17: Copper Tape - 0.03 mm | W17: Copper Tape - 0.035 mm | X17: Copper Tape - 0.04 mm | Y17: Copper Tape - 0.045 mm | Z17: Copper Tape - 0.050 mm | AA17: Copper Tape - 0.060 mm | AB17: Copper Tape - 0.075 mm(DOUBLE) | AC17: Extruded semiconductive | AD17: Extruded Semiconductive(Stripable) | AE17: HT-XLPE | AF17: LT-XLPE | AG17: TR XLPE | AH17: Type A PVC | AI17: Type C PVC (HR) | AJ17: XLPE | AK17: POLY TAPE | AL17: FR PVC Type ST-1 | AM17: FR PVC Type ST-2 | AN17: FRLSH PVC Type ST-2 | AO17: PVC Type ST-1 | AP17: PVC Type ST-1-PRESSURE EXTRUDED | AQ17: PVC Type ST-2 | AR17: PVC Type ST-2-PRESSURE EXTRUDED | AS17: ACSR CORE WIRE | AT17: ACSR DOG STEEL WIRE | AU17: Aluminium Flat Strip | AV17: Aluminium Round Wire | AW17: Double Steel Tape | AX17: Galvanised Steel Flat Strip | AY17: Galvanised Steel Flat Strip (Double) | AZ17: Galvanised Steel Flat Strip-B | BA17: Galvanised Steel Round Wire | BB17: Galvanised Steel Round Wire (Double) | BC17: FR PVC Type ST-1 | BD17: FR PVC Type ST-2 | BE17: FRLSH PVC Type ST-1 | BF17: FRLSH PVC Type ST-2 | BG17: PE, ST-3 | BH17: PE, ST-7 | BI17: PVC Type ST-1 | BJ17: PVC Type ST-2 | BK17: PVC Type ST-2-PRESSURE EXTRUDED | BL17: UV & Track Resistant XLPE | BM17: FILLER | BN17: Grease | BO17: Water swellable Tape | BP17: Semi conducting Water Swellable tape | BQ17: SEMICON TAPE | BR17: GLASS FIBER TAPE | BS17: COPPER WIRE 0.8 MM | BT17: RUBBERIZED COTTON TAPE | BU17: Water Tight Compound | BV17: =Sheet1!E1 -> PROPOSE DRUM TYPE | BW17: =Sheet1!CV1 -> DRUM CODE | BX17: =Sheet1!CW1 -> DRUM SIZE (FxbXtx Ft) | BY17: =Sheet1!CX1 -> PARTY STANDARD LENGTH (MTR) | CD17: MFG% | CE17: MFG VALUE | CF17: PROF% | CG17: PROFIT VALUE | CH17: 1ST EX-WORKS | CI17: Intt % | CJ17: INTT VALUE | CK17: insp% | CL17: INSP VALUE
N18: 214 | O18: =+IFERROR(VLOOKUP($O$17,Sheet1!J:L,2,0),0) -> 0 | P18: =+IFERROR(VLOOKUP($P$17,Sheet1!J:M,2,0),0) -> 0 | Q18: =+IFERROR(VLOOKUP($Q$17,Sheet1!J:M,2,0),0) -> 0 | R18: =+IFERROR(VLOOKUP($R$17,Sheet1!J:M,2,0),0) -> 0 | S18: =+IFERROR(VLOOKUP($S$17,Sheet1!N:Q,2,0),0) -> 0 | T18: =+IFERROR(VLOOKUP($T$17,Sheet1!N:O,2,0),0) -> 0 | U18: =+IFERROR(VLOOKUP($U$17,Sheet1!F:I,2,0),0) -> 0 | V18: =+IFERROR(VLOOKUP($V$17,Sheet1!F:I,2,0),0) -> 0 | W18: =+IFERROR(VLOOKUP($W$17,Sheet1!F:I,2,0),0) -> 0 | X18: =+IFERROR(VLOOKUP($X$17,Sheet1!F:I,2,0),0) -> 0 | Y18: =+IFERROR(VLOOKUP($Y$17,Sheet1!F:I,2,0),0) -> 0 | Z18: =+IFERROR(VLOOKUP($Z$17,Sheet1!F:I,2,0),0) -> 0 | AA18: =+IFERROR(VLOOKUP($AA$17,Sheet1!F:I,2,0),0) -> 0 | AB18: =+IFERROR(VLOOKUP($AB$17,Sheet1!F:I,2,0),0) -> 0 | AC18: =+IFERROR(VLOOKUP($AC$17,Sheet1!R:U,2,0),0) -> 0 | AD18: =+IFERROR(VLOOKUP($AD$17,Sheet1!R:U,2,0),0) -> 0 | AE18: =+IFERROR(VLOOKUP($AE$17,Sheet1!V:Y,2,0),0) -> 0 | AF18: =+IFERROR(VLOOKUP($AF$17,Sheet1!V:Y,2,0),0) -> 0 | AG18: =+IFERROR(VLOOKUP($AG$17,Sheet1!V:Y,2,0),0) -> 0 | AH18: 74 | AI18: =+IFERROR(VLOOKUP($AI$17,Sheet1!V:Y,2,0),0) -> 0 | AJ18: =+IFERROR(VLOOKUP($AJ$17,Sheet1!V:Y,2,0),0) -> 0 | AK18: =+IFERROR(VLOOKUP($AK$17,Sheet1!Z2:AA840,2,0),0) -> 0 | AL18: =+IFERROR(VLOOKUP($AL$17,Sheet1!AD2:AG840,2,0),0) -> 0 | AM18: =+IFERROR(VLOOKUP($AM$17,Sheet1!AD2:AG840,2,0),0) -> 0 | AN18: =+IFERROR(VLOOKUP($AN$17,Sheet1!AD2:AG840,2,0),0) -> 0 | AO18: 60 | AP18: =+IFERROR(VLOOKUP($AP$17,Sheet1!AD2:AG840,2,0),0) -> 0 | AQ18: =+IFERROR(VLOOKUP($AQ$17,Sheet1!AD2:AG840,2,0),0) -> 0 | AR18: =+IFERROR(VLOOKUP($AR$17,Sheet1!AD2:AG840,2,0),0) -> 0 | AS18: =+IFERROR(VLOOKUP($AS$17,Sheet1!AH2:AK840,2,0),0) -> 0 | AT18: =+IFERROR(VLOOKUP($AT$17,Sheet1!AH2:AK840,2,0),0) -> 0 | AU18: =+IFERROR(VLOOKUP($AU$17,Sheet1!AH2:AK840,2,0),0) -> 0 | AV18: =+IFERROR(VLOOKUP($AV$17,Sheet1!AH2:AK840,2,0),0) -> 0 | AW18: =+IFERROR(VLOOKUP($AW$17,Sheet1!AH2:AK840,2,0),0) -> 0 | AX18: 77 | AY18: =+IFERROR(VLOOKUP($AY$17,Sheet1!AH2:AK840,2,0),0) -> 0 | AZ18: =+IFERROR(VLOOKUP($AZ$17,Sheet1!AH2:AK840,2,0),0) -> 0 | BA18: =+IFERROR(VLOOKUP($BA$17,Sheet1!AH2:AK840,2,0),0) -> 0 | BB18: =+IFERROR(VLOOKUP($BB$17,Sheet1!AH2:AK840,2,0),0) -> 0 | BC18: =+IFERROR(VLOOKUP($BC$17,Sheet1!AL2:AO840,2,0),0) -> 0 | BD18: =+IFERROR(VLOOKUP($BD$17,Sheet1!AL2:AO840,2,0),0) -> 0 | BE18: =+IFERROR(VLOOKUP($BE$17,Sheet1!AL2:AO840,2,0),0) -> 0 | BF18: =+IFERROR(VLOOKUP($BF$17,Sheet1!AL2:AO840,2,0),0) -> 0 | BG18: =+IFERROR(VLOOKUP($BG$17,Sheet1!AL2:AO840,2,0),0) -> 0 | BH18: =+IFERROR(VLOOKUP($BH$17,Sheet1!AL2:AO840,2,0),0) -> 0 | BI18: 60 | BJ18: =+IFERROR(VLOOKUP($BJ$17,Sheet1!AL2:AO840,2,0),0) -> 0 | BK18: =+IFERROR(VLOOKUP($BK$17,Sheet1!AL2:AO840,2,0),0) -> 0 | BL18: =+IFERROR(VLOOKUP($BL$17,Sheet1!AL2:AO840,2,0),0) -> 0 | BM18: =+IFERROR(VLOOKUP($BM$17,Sheet1!AP2:AS840,2,0),0) -> 0 | BN18: =+IFERROR(VLOOKUP($BN$17,Sheet1!AT2:AW840,2,0),0) -> 0 | BO18: =+IFERROR(VLOOKUP($BO$17,Sheet1!AX2:BA840,2,0),0) -> 0 | BP18: =+IFERROR(VLOOKUP($BP$17,Sheet1!BB2:BE840,2,0),0) -> 0 | BQ18: =+IFERROR(VLOOKUP($BQ$17,Sheet1!BF2:BI840,2,0),0) -> 0 | BR18: =+IFERROR(VLOOKUP($BR$17,Sheet1!BJ2:BM840,2,0),0) -> 0 | BS18: =+IFERROR(VLOOKUP($BS$17,Sheet1!BN2:BQ840,2,0),0) -> 0 | BT18: =+IFERROR(VLOOKUP($BT$17,Sheet1!BR2:BU840,2,0),0) -> 0 | BU18: =+IFERROR(VLOOKUP($BU$17,Sheet1!BV2:BY840,2,0),0) -> 0
A19: =Sheet1!A3 -> ENQ-11781-22-23 | B19: =Sheet1!B3 -> 45200 | C19: =Sheet1!C3 -> FA0900011 | D19: =Sheet1!D3 -> 4 CORE X 10 SQ. MM. AL/ARD - STRIP (PVC) | E19: =CH19+CJ19+CL19 -> 89782.347 | F19: =ROUNDUP(M23,0) -> 1000 | G19: =E19+F19 -> 90782.347 | H19: =Sheet1!CP3 -> 0.18 | I19: =G19*H19 -> 16340.822 | J19: =G19+I19 -> 107123.17 | K19: =Sheet1!CS3 -> 1500 | L19: =Sheet1!CT3 -> KMS | M19: =J19*K19 -> 1.6068475e+08 | N19: =+IFERROR(VLOOKUP($N$17,Sheet1!J3:L3,3,0),0) -> 108 | O19: =+IFERROR(VLOOKUP($O$17,Sheet1!J3:L3,3,0),0) -> 0 | P19: =+IFERROR(VLOOKUP($P$17,Sheet1!J3:M3,3,0),0) -> 0 | Q19: =+IFERROR(VLOOKUP($Q$17,Sheet1!J3:M3,3,0),0) -> 0 | R19: =+IFERROR(VLOOKUP($R$17,Sheet1!J3:M3,3,0),0) -> 0 | S19: =+IFERROR(VLOOKUP($S$17,Sheet1!N3:Q3,3,0),0) -> 0 | T19: =+IFERROR(VLOOKUP($T$17,Sheet1!N3:Q3,3,0),0) -> 0 | U19: =+IFERROR(VLOOKUP($U$17,Sheet1!F3:I3,3,0),0) -> 0 | V19: =+IFERROR(VLOOKUP($V$17,Sheet1!F3:I3,3,0),0) -> 0 | W19: =+IFERROR(VLOOKUP($W$17,Sheet1!F3:I3,3,0),0) -> 0 | X19: =+IFERROR(VLOOKUP($X$17,Sheet1!F3:I3,3,0),0) -> 0 | Y19: =+IFERROR(VLOOKUP($Y$17,Sheet1!F3:I3,3,0),0) -> 0 | Z19: =+IFERROR(VLOOKUP($Z$17,Sheet1!F3:I3,3,0),0) -> 0 | AA19: =+IFERROR(VLOOKUP($AA$17,Sheet1!F3:I3,3,0),0) -> 0 | AB19: =+IFERROR(VLOOKUP($AB$17,Sheet1!F3:I3,3,0),0) -> 0 | AC19: =+IFERROR(VLOOKUP($AC$17,Sheet1!R3:U3,3,0),0) -> 0 | AD19: =+IFERROR(VLOOKUP($AD$17,Sheet1!R3:U3,2,0),0) -> 0 | AE19: =+IFERROR(VLOOKUP($AE$17,Sheet1!V3:Y3,3,0),0) -> 0 | AF19: =+IFERROR(VLOOKUP($AF$17,Sheet1!V3:Y3,3,0),0) -> 0 | AG19: =+IFERROR(VLOOKUP($AG$17,Sheet1!V3:Y3,3,0),0) -> 0 | AH19: =+IFERROR(VLOOKUP($AH$17,Sheet1!V3:Y3,3,0),0) -> 98 | AI19: =+IFERROR(VLOOKUP($AI$17,Sheet1!V3:Y3,3,0),0) -> 0 | AJ19: =+IFERROR(VLOOKUP($AJ$17,Sheet1!V3:Y3,3,0),0) -> 0 | AK19: =+IFERROR(VLOOKUP($AK$17,Sheet1!Z3:AB3,3,0),0) -> 0 | AL19: =+IFERROR(VLOOKUP($AL$17,Sheet1!AD3:AG3,3,0),0) -> 0 | AM19: =+IFERROR(VLOOKUP($AM$17,Sheet1!AD3:AG3,3,0),0) -> 0 | AN19: =+IFERROR(VLOOKUP($AN$17,Sheet1!AD3:AG3,3,0),0) -> 0 | AO19: =+IFERROR(VLOOKUP($AO$17,Sheet1!AD3:AG3,3,0),0) -> 35 | AP19: =+IFERROR(VLOOKUP($AP$17,Sheet1!AD3:AG3,3,0),0) -> 0 | AQ19: =+IFERROR(VLOOKUP($AQ$17,Sheet1!AD3:AG3,3,0),0) -> 0 | AR19: =+IFERROR(VLOOKUP($AR$17,Sheet1!AD3:AG3,3,0),0) -> 0 | AS19: =+IFERROR(VLOOKUP($AS$17,Sheet1!AH3:AK3,3,0),0) -> 0 | AT19: =+IFERROR(VLOOKUP($AT$17,Sheet1!AH3:AK3,3,0),0) -> 0 | AU19: =+IFERROR(VLOOKUP($AU$17,Sheet1!AH3:AK3,3,0),0) -> 0 | AV19: =+IFERROR(VLOOKUP($AV$17,Sheet1!AH3:AK3,3,0),0) -> 0 | AW19: =+IFERROR(VLOOKUP($AW$17,Sheet1!AH3:AK3,3,0),0) -> 0 | AX19: =+IFERROR(VLOOKUP($AX$17,Sheet1!AH3:AK3,3,0),0) -> 281 | AY19: =+IFERROR(VLOOKUP($AY$17,Sheet1!AH3:AK3,3,0),0) -> 0 | AZ19: =+IFERROR(VLOOKUP($AZ$17,Sheet1!AH3:AK3,3,0),0) -> 0 | BA19: =+IFERROR(VLOOKUP($BA$17,Sheet1!AH3:AK3,3,0),0) -> 0 | BB19: =+IFERROR(VLOOKUP($BB$17,Sheet1!AH3:AK3,3,0),0) -> 0 | BC19: =+IFERROR(VLOOKUP($BC$17,Sheet1!AL3:AO3,3,0),0) -> 0 | BD19: =+IFERROR(VLOOKUP($BD$17,Sheet1!AL3:AO3,3,0),0) -> 0 | BE19: =+IFERROR(VLOOKUP($BE$17,Sheet1!AL3:AO3,3,0),0) -> 0 | BF19: =+IFERROR(VLOOKUP($BF$17,Sheet1!AL3:AO3,3,0),0) -> 0 | BG19: =+IFERROR(VLOOKUP($BG$17,Sheet1!AL3:AO3,3,0),0) -> 0 | BH19: =+IFERROR(VLOOKUP($BH$17,Sheet1!AL3:AO3,3,0),0) -> 0 | BI19: =+IFERROR(VLOOKUP($BI$17,Sheet1!AL3:AO3,3,0),0) -> 139 | BJ19: =+IFERROR(VLOOKUP($BJ$17,Sheet1!AL3:AO3,3,0),0) -> 0 | BK19: =+IFERROR(VLOOKUP($BK$17,Sheet1!AL3:AO3,3,0),0) -> 0 | BL19: =+IFERROR(VLOOKUP($BL$17,Sheet1!AL3:AO3,3,0),0) -> 0 | BM19: =+IFERROR(VLOOKUP($BM$17,Sheet1!AP3:AS3,3,0),0) -> 0 | BN19: =+IFERROR(VLOOKUP($BN$17,Sheet1!AT3:AW3,3,0),0) -> 0 | BO19: =+IFERROR(VLOOKUP($BO$17,Sheet1!AX3:BA3,3,0),0) -> 0 | BP19: =+IFERROR(VLOOKUP($BP$17,Sheet1!BB3:BE3,3,0),0) -> 0 | BQ19: =+IFERROR(VLOOKUP($BQ$17,Sheet1!BF3:BI3,3,0),0) -> 0 | BR19: =+IFERROR(VLOOKUP($BR$17,Sheet1!BJ3:BM3,3,0),0) -> 0 | BS19: =+IFERROR(VLOOKUP($BS$17,Sheet1!BN3:BQ3,3,0),0) -> 0 | BT19: =+IFERROR(VLOOKUP($BT$17,Sheet1!BR3:BU3,3,0),0) -> 0 | BU19: =+IFERROR(VLOOKUP($BU$17,Sheet1!BV3:BY3,3,0),0) -> 0 | BV19: =Sheet1!E3 -> WOOD | BW19: =Sheet1!CV3 -> MD0100005 | BX19: =Sheet1!CW3 -> DRUM - 36 X 14 X 23 X 2 | BY19: =Sheet1!CX3 -> 500 | BZ19: =Sheet1!BZ3 -> 4610.79 | CA19: =SUMPRODUCT($N$18:$BU$18,N19:BU19)+BZ19 -> 67051.79 | CB19: =Sheet1!CB3 -> 0 | CC19: =CA19*CB19 -> 0 | CD19: 0.3 | CE19: =CA19*CD19 -> 20115.537 | CF19: 0 | CG19: =CA19*CF19 -> 0 | CH19: =CA19+CC19+CE19+CG19 -> 87167.327 | CI19: 0.02 | CJ19: =CH19*CI19 -> 1743.3465 | CK19: 0.01 | CL19: =CH19*CK19 -> 871.67327
A20: =Sheet1!A2 -> ENQ-11781-22-23 | B20: =Sheet1!B2 -> 45200 | C20: =Sheet1!C2 -> FA0900014 | D20: =Sheet1!D2 -> 4 CORE X 25 SQ. MM. AL/ARD - STRIP (PVC) | E20: =CH20+CJ20+CL20 -> 156469.49 | F20: =ROUNDUP(M24,0) -> 1500 | G20: =E20+F20 -> 157969.49 | H20: =Sheet1!CP2 -> 0.18 | I20: =G20*H20 -> 28434.508 | J20: =G20+I20 -> 186404 | K20: =Sheet1!CS2 -> 200 | L20: =Sheet1!CT2 -> KMS | M20: =J20*K20 -> 37280799 | N20: =+IFERROR(VLOOKUP($N$17,Sheet1!J2:L2,3,0),0) -> 270 | O20: =+IFERROR(VLOOKUP($O$17,Sheet1!J2:L2,3,0),0) -> 0 | P20: =+IFERROR(VLOOKUP($P$17,Sheet1!J2:M2,3,0),0) -> 0 | Q20: =+IFERROR(VLOOKUP($Q$17,Sheet1!J2:M2,3,0),0) -> 0 | R20: =+IFERROR(VLOOKUP($R$17,Sheet1!J2:M2,3,0),0) -> 0 | S20: =+IFERROR(VLOOKUP($S$17,Sheet1!N2:Q2,3,0),0) -> 0 | T20: =+IFERROR(VLOOKUP($T$17,Sheet1!N2:Q2,3,0),0) -> 0 | U20: =+IFERROR(VLOOKUP($U$17,Sheet1!F2:I2,3,0),0) -> 0 | V20: =+IFERROR(VLOOKUP($V$17,Sheet1!F2:I2,3,0),0) -> 0 | W20: =+IFERROR(VLOOKUP($W$17,Sheet1!F2:I2,3,0),0) -> 0 | X20: =+IFERROR(VLOOKUP($X$17,Sheet1!F2:I2,3,0),0) -> 0 | Y20: =+IFERROR(VLOOKUP($Y$17,Sheet1!F2:I2,3,0),0) -> 0 | Z20: =+IFERROR(VLOOKUP($Z$17,Sheet1!F2:I2,3,0),0) -> 0 | AA20: =+IFERROR(VLOOKUP($AA$17,Sheet1!F2:I2,3,0),0) -> 0 | AB20: =+IFERROR(VLOOKUP($AB$17,Sheet1!F2:I2,3,0),0) -> 0 | AC20: =+IFERROR(VLOOKUP($AC$17,Sheet1!R2:U2,3,0),0) -> 0 | AD20: =+IFERROR(VLOOKUP($AD$17,Sheet1!R2:U2,2,0),0) -> 0 | AE20: =+IFERROR(VLOOKUP($AE$17,Sheet1!V2:Y2,3,0),0) -> 0 | AF20: =+IFERROR(VLOOKUP($AF$17,Sheet1!V2:Y2,3,0),0) -> 0 | AG20: =+IFERROR(VLOOKUP($AG$17,Sheet1!V2:Y2,3,0),0) -> 0 | AH20: =+IFERROR(VLOOKUP($AH$17,Sheet1!V2:Y2,3,0),0) -> 160 | AI20: =+IFERROR(VLOOKUP($AI$17,Sheet1!V2:Y2,3,0),0) -> 0 | AJ20: =+IFERROR(VLOOKUP($AJ$17,Sheet1!V2:Y2,3,0),0) -> 0 | AK20: =+IFERROR(VLOOKUP($AK$17,Sheet1!Z2:AB2,3,0),0) -> 0 | AL20: =+IFERROR(VLOOKUP($AL$17,Sheet1!AD2:AG2,3,0),0) -> 0 | AM20: =+IFERROR(VLOOKUP($AM$17,Sheet1!AD2:AG2,3,0),0) -> 0 | AN20: =+IFERROR(VLOOKUP($AN$17,Sheet1!AD2:AG2,3,0),0) -> 0 | AO20: =+IFERROR(VLOOKUP($AO$17,Sheet1!AD2:AG2,3,0),0) -> 47 | AP20: =+IFERROR(VLOOKUP($AP$17,Sheet1!AD2:AG2,3,0),0) -> 0 | AQ20: =+IFERROR(VLOOKUP($AQ$17,Sheet1!AD2:AG2,3,0),0) -> 0 | AR20: =+IFERROR(VLOOKUP($AR$17,Sheet1!AD2:AG2,3,0),0) -> 0 | AS20: =+IFERROR(VLOOKUP($AS$17,Sheet1!AH2:AK2,3,0),0) -> 0 | AT20: =+IFERROR(VLOOKUP($AT$17,Sheet1!AH2:AK2,3,0),0) -> 0 | AU20: =+IFERROR(VLOOKUP($AU$17,Sheet1!AH2:AK2,3,0),0) -> 0 | AV20: =+IFERROR(VLOOKUP($AV$17,Sheet1!AH2:AK2,3,0),0) -> 0 | AW20: =+IFERROR(VLOOKUP($AW$17,Sheet1!AH2:AK2,3,0),0) -> 0 | AX20: =+IFERROR(VLOOKUP($AX$17,Sheet1!AH2:AK2,3,0),0) -> 372 | AY20: =+IFERROR(VLOOKUP($AY$17,Sheet1!AH2:AK2,3,0),0) -> 0 | AZ20: =+IFERROR(VLOOKUP($AZ$17,Sheet1!AH2:AK2,3,0),0) -> 0 | BA20: =+IFERROR(VLOOKUP($BA$17,Sheet1!AH2:AK2,3,0),0) -> 0 | BB20: =+IFERROR(VLOOKUP($BB$17,Sheet1!AH2:AK2,3,0),0) -> 0 | BC20: =+IFERROR(VLOOKUP($BC$17,Sheet1!AL2:AO2,3,0),0) -> 0 | BD20: =+IFERROR(VLOOKUP($BD$17,Sheet1!AL2:AO2,3,0),0) -> 0 | BE20: =+IFERROR(VLOOKUP($BE$17,Sheet1!AL2:AO2,3,0),0) -> 0 | BF20: =+IFERROR(VLOOKUP($BF$17,Sheet1!AL2:AO2,3,0),0) -> 0 | BG20: =+IFERROR(VLOOKUP($BG$17,Sheet1!AL2:AO2,3,0),0) -> 0 | BH20: =+IFERROR(VLOOKUP($BH$17,Sheet1!AL2:AO2,3,0),0) -> 0 | BI20: =+IFERROR(VLOOKUP($BI$17,Sheet1!AL2:AO2,3,0),0) -> 177 | BJ20: =+IFERROR(VLOOKUP($BJ$17,Sheet1!AL2:AO2,3,0),0) -> 0 | BK20: =+IFERROR(VLOOKUP($BK$17,Sheet1!AL2:AO2,3,0),0) -> 0 | BL20: =+IFERROR(VLOOKUP($BL$17,Sheet1!AL2:AO2,3,0),0) -> 0 | BM20: =+IFERROR(VLOOKUP($BM$17,Sheet1!AP2:AS2,3,0),0) -> 0 | BN20: =+IFERROR(VLOOKUP($BN$17,Sheet1!AT2:AW2,3,0),0) -> 0 | BO20: =+IFERROR(VLOOKUP($BO$17,Sheet1!AX2:BA2,3,0),0) -> 0 | BP20: =+IFERROR(VLOOKUP($BP$17,Sheet1!BB2:BE2,3,0),0) -> 0 | BQ20: =+IFERROR(VLOOKUP($BQ$17,Sheet1!BF2:BI2,3,0),0) -> 0 | BR20: =+IFERROR(VLOOKUP($BR$17,Sheet1!BJ2:BM2,3,0),0) -> 0 | BS20: =+IFERROR(VLOOKUP($BS$17,Sheet1!BN2:BQ2,3,0),0) -> 0 | BT20: =+IFERROR(VLOOKUP($BT$17,Sheet1!BR2:BU2,3,0),0) -> 0 | BU20: =+IFERROR(VLOOKUP($BU$17,Sheet1!BV2:BY2,3,0),0) -> 0 | BV20: =Sheet1!E2 -> WOOD | BW20: =Sheet1!CV2 -> MD0100066 | BX20: =Sheet1!CW2 -> DRUM - 40 X 15 X 23 X 2 | BY20: =Sheet1!CX2 -> 500 | BZ20: =Sheet1!BZ2 -> 5151.48 | CA20: =SUMPRODUCT($N$18:$BU$18,N20:BU20)+BZ20 -> 116855.48 | CB20: =Sheet1!CB2 -> 0 | CC20: =CA20*CB20 -> 0 | CD20: 0.3 | CE20: =CA20*CD20 -> 35056.644 | CF20: 0 | CG20: =CA20*CF20 -> 0 | CH20: =CA20+CC20+CE20+CG20 -> 151912.12 | CI20: 0.02 | CJ20: =CH20*CI20 -> 3038.2425 | CK20: 0.01 | CL20: =CH20*CK20 -> 1519.1212
E22: Order Quantity | F22: Stnd Length | G22: Truck type | H22: Fare of one truck | I22: No of Drum in one truck | J22: Total length in one Truck | K22: No of Truck | L22: Total Freight | M22: Freight per KM
D23: =D19 -> 4 CORE X 10 SQ. MM. AL/ARD - STRIP (PVC) | E23: =K19 -> 1500 | F23: 0.5 | G23: 16 MT | H23: 20000 | I23: 40 | J23: =F23*I23 -> 20 | K23: =ROUNDUP((E23/J23),0) -> 75 | L23: =M23*E23 -> 1500000 | M23: =(H23*K23)/E23 -> 1000
D24: =D20 -> 4 CORE X 25 SQ. MM. AL/ARD - STRIP (PVC) | E24: =K20 -> 200 | F24: 0.5 | G24: 16 MT | H24: 20000 | I24: 27 | J24: =F24*I24 -> 13.5 | K24: =ROUNDUP((E24/J24),0) -> 15 | L24: =M24*E24 -> 300000 | M24: =(H24*K24)/E24 -> 1500

Sheet PV ON IS
A1: Base Date | B1: 45200
A2: PV Terms(Price Variation Formula) | B2: The price is Variable as per PV Formula of IEEMA with base date 01.10.2023.
A3: PV FORMULA
A4: P = Po + ALF ( Al – Alo ) + CCFAI (Cc – Cco) +FeF (Fe – Feo)
A7: Alf | B7: Variation factor for aluminum.
A8: CCFAI | B8: Variation factor for PVC compound/Polymer for aluminum conductor cable.
A9: Fef | B9: Variation factor for steel
A12: Item | B12: Ex-Work
A13: ='AUTO CALCULATION SHEET (2)'!D19 -> 4 CORE X 10 SQ. MM. AL/ARD - STRIP (PVC) | B13: ='AUTO CALCULATION SHEET (2)'!E19 -> 89782.347
A14: ='AUTO CALCULATION SHEET (2)'!D20 -> 4 CORE X 25 SQ. MM. AL/ARD - STRIP (PVC) | B14: ='AUTO CALCULATION SHEET (2)'!E20 -> 156469.49
A16: Item | B16: Calculation part | C16: Date of Inspection | D16: Applicable Date | H16: BASE DATE | L16: FACTORS | O16: Ex-Work Po | P16: PVC of al | Q16: PVC OF PVC | R16: PVC OF FE | S16: PV/PKM | T16: Billing Price/PKM | U16: VALUE ADDITION CALCULATION
D17: Date | E17: Al | F17: Cc | G17: Fe | H17: Date | I17: Alo | J17: Cco | K17: Feo
L18: Alf | M18: CCFAI | N18: FeF | U18: Alumimium | V18: TYPE A PVC | W18: I/S PVC Type ST-1 | X18: GI FLAT STRIP | Y18: O/s PVC Type ST-1 | Z18: RMC | AA18: Drum | AB18: RMC+Drum | AC18: VA | AD18: Groos VA% | AE18: Mfg % | AF18: Int % | AG18: Ins% | AH18: Net VA
U19: 211 | V19: 70 | W19: 57 | X19: 73 | Y19: 57
A20: =A13 -> 4 CORE X 10 SQ. MM. AL/ARD - STRIP (PVC) | D20: 45274 | E20: 202884.87 | F20: 150825 | G20: 78250 | H20: =$B$1 -> 45200 | I20: 211416 | J20: 154575 | K20: 80250 | L20: 0.116 | M20: 0.277 | N20: 0.293 | O20: =B13 -> 89782.347 | P20: =(L20*(E20-I20)) -> -989.61108 | Q20: =M20*(F20-J20) -> -1038.75 | R20: =N20*(G20-K20) -> -586 | S20: =P20+Q20+R20 -> -2614.3611 | T20: =O20+S20 -> 87167.986 | U20: ='AUTO CALCULATION SHEET (2)'!N19 -> 108 | V20: ='AUTO CALCULATION SHEET (2)'!AH19 -> 98 | W20: ='AUTO CALCULATION SHEET (2)'!AO19 -> 35 | X20: ='AUTO CALCULATION SHEET (2)'!AX19 -> 281 | Y20: ='AUTO CALCULATION SHEET (2)'!BI19 -> 139 | Z20: =SUMPRODUCT(U20:Y20,$U$19:$Y$19) -> 60079 | AA20: ='AUTO CALCULATION SHEET (2)'!BZ19 -> 4610.79 | AB20: =Z20+AA20 -> 64689.79 | AC20: =T20-AB20 -> 22478.196 | AD20: =ROUND((AC20/AB20)*100,2) -> 34.75 | AF20: 2 | AG20: 1 | AH20: =AD20-AE20-AF20-AG20 -> 31.75
A21: =A14 -> 4 CORE X 25 SQ. MM. AL/ARD - STRIP (PVC) | D21: 45274 | E21: 202884.87 | F21: 150825 | G21: 78250 | H21: =$B$1 -> 45200 | I21: 211416 | J21: 154575 | K21: 80250 | L21: 0.292 | M21: 0.466 | N21: 0.382 | O21: =B14 -> 156469.49 | P21: =(L21*(E21-I21)) -> -2491.09 | Q21: =M21*(F21-J21) -> -1747.5 | R21: =N21*(G21-K21) -> -764 | S21: =P21+Q21+R21 -> -5002.59 | T21: =O21+S21 -> 151466.9 | U21: ='AUTO CALCULATION SHEET (2)'!N20 -> 270 | V21: ='AUTO CALCULATION SHEET (2)'!AH20 -> 160 | W21: ='AUTO CALCULATION SHEET (2)'!AO20 -> 47 | X21: ='AUTO CALCULATION SHEET (2)'!AX20 -> 372 | Y21: ='AUTO CALCULATION SHEET (2)'!BI20 -> 177 | Z21: =SUMPRODUCT(U21:Y21,$U$19:$Y$19) -> 108094 | AA21: ='AUTO CALCULATION SHEET (2)'!BZ20 -> 5151.48 | AB21: =Z21+AA21 -> 113245.48 | AC21: =T21-AB21 -> 38221.418 | AD21: =ROUND((AC21/AB21)*100,2) -> 33.75 | AF21: 2 | AG21: 1 | AH21: =AD21-AE21-AF21-AG21 -> 30.75
