Workbook

Sheet Sheet1
A1: DOCKET NO. | B1: Base Date | C1: ITEM CODE | D1: PROPOSE ERP ITEM NAME | E1: Propose Drum Type | F1: Insulation Screening(Metallic) | G1: RM Rate(Insulation Screening(Metallic)) | H1: Weight (Insulation Screening (Metallic)) | I1: Cost Insulation Screening(Metallic) | J1: Conductor | K1: RM Rate(Conductor) | L1: Weight(Conductor) | M1: Cost(Conductor) | N1: AL ALLOY | O1: RM Rate(AL Alloy) | P1: Weight(Al Alloy) | Q1: Cost(AL Alloy) | R1: Insulation Screening(Non-Metallic) | S1: RM Rate(Insulation Screening(Non-Metallic)) | T1: Weight(Insulation Screening(Non-Metallic) | U1: Cost(Insulation Screening(Non-Metallic) | V1: Insulation | W1: RM Rate(Insulation) | X1: Weight(Insulation) | Y1: Cost(Insulation) | Z1: Poly Tape | AA1: RM Rate(Poly Tape) | AB1: Weight(Poly Tape) | AC1: Cost(Poly Tape) | AD1: Inner Sheath | AE1: RM Rate(Inner Sheath) | AF1: Weight(Inner Sheath) | AG1: Cost(Inner Sheath) | AH1: Armouring | AI1: RM Rate(Armouring) | AJ1: Weight(Armouring) | AK1: Cost(Armouring) | AL1: Outer Sheath | AM1: RM Rate(Outer Sheath) | AN1: Weight(Outer Sheath) | AO1: Cost(Outer Sheath) | AP1: Filler | AQ1: RM Rate(Filler) | AR1: Weight(Filler) | AS1: Cost(Filler) | AT1: Grease | AU1: RM Rate(Grease) | AV1: Weight(Grease) | AW1: Cost(Grease) | AX1: Water Swellable Tape | AY1: RM Rate(Water Swellable Tape) | AZ1: Weight(Water Swellable Tape) | BA1: Cost(Water Swellable Tape) | BB1: Semi Conducting Water Swellable Tape | BC1: RM Rate(Semi Conducting Water Swellable Tape) | BD1: Weight(Semi Conducting Water Swellable Tape) | BE1: Cost(Semi Conducting Water Swellable Tape) | BF1: Semicon Tape | BG1: RM Rate(Semicon Tape) | BH1: Weight(Semicon Tape) | BI1: Cost(Semicon Tape) | BJ1: Glass Fiber Tape | BK1: RM Rate(Glass Fiber Tape) | BL1: Weight(Glass Fiber Tape) | BM1: Cost(Glass Fiber Tape) | BN1: Copper Wire 0.8MM | BO1: RM Rate(Copper Wire 0.8MM) | BP1: Weight(Copper Wire 0.8MM) | BQ1: Cost(Copper Wire 0.8MM) | BR1: Rubberized Cotton Tape | BS1: RM Rate(Rubberized Cotton Tape) | BT1: Weight(Rubberized Cotton Tape) | BU1: Cost(Rubberized Cotton Tape) | BV1: Water Tight Compound | BW1: RM Rate(Water Tight Compound) | BX1: Weight(Water Tight Compound) | BY1: Cost(Water Tight Compound) | BZ1: Drum Cost Per KM | CA1: Total RM Cost | CB1: FIRM % | CC1: Firm Value | CD1: MFG% | CE1: MFG Value | CF1: PROF% | CG1: Profit Value | CH1: 1st EX-Works | CI1: Intt % | CJ1: Intt Value | CK1: insp% | CL1: Insp Value | CM1: TTR CHARGES% | CN1: TTR Value | CO1: EX-Works Per KM | CP1: Freight Per KM | CQ1: Price Including Freight Per KM | CR1: GST % | CS1: GST Value | CT1: Price Including GST & Freight Per KM | CU1: QTY | CV1: Unit | CW1: Total Price Of Full QTY(Including Freight&GST) | CX1: DRUM CODE | CY1: DRUM SIZE (FxbXtx Ft) | CZ1: Party Standard Length(MTR)
A2: ENQ-16527-25-26 | C2: FA0900013 | D2: 4 CORE X 16 SQ. MM. ALU/ARD - STRIP (XLPE) | E2: WOOD | H2: 0 | J2: Alumimium | L2: 173 | P2: 0 | T2: 0 | V2: LT-XLPE | X2: 63 | AB2: 0 | AD2: PVC Type ST-2 | AF2: 40 | AH2: Galvanised Steel Flat Strip | AJ2: 300 | AL2: PVC Type ST-2 | AN2: 146 | AR2: 0 | AV2: 0 | AZ2: 0 | BD2: 0 | BH2: 0 | BL2: 0 | BP2: 0 | BR2: RUBBERIZED COTTON TAPE | BT2: 0 | BX2: 0 | BZ2: 5448 | CA2: 5448 | CH2: 5448 | CO2: 5448 | CQ2: 5448 | CR2: 0.18 | CS2: 980.64 | CT2: 6428.64 | CU2: 100 | CV2: KMS | CW2: 642864 | CX2: MD0100066 | CY2: DRUM - 40 X 15 X 23 X 2 | CZ2: 500
A3: ENQ-16527-25-26 | C3: FA0900018 | D3: 4 CORE X 35 SQ. MM. AL/ARD - STRIP (XLPE) | E3: WOOD | H3: 0 | J3: Alumimium | L3: 378 | P3: 0 | T3: 0 | V3: LT-XLPE | X3: 109 | AB3: 0 | AD3: PVC Type ST-2 | AF3: 51 | AH3: Galvanised Steel Flat Strip | AJ3: 407 | AL3: PVC Type ST-2 | AN3: 191 | AR3: 0 | AV3: 0 | AZ3: 0 | BD3: 0 | BH3: 0 | BL3: 0 | BP3: 0 | BR3: RUBBERIZED COTTON TAPE | BT3: 0 | BX3: 0 | BZ3: 8874 | CA3: 8874 | CH3: 8874 | CO3: 8874 | CQ3: 8874 | CR3: 0.18 | CS3: 1597.32 | CT3: 10471.32 | CU3: 60 | CV3: KMS | CW3: 628279 | CX3: MD0100015 | CY3: DRUM - 48 X 20 X 28 X 2.25 - RDSO | CZ3: 500
A4: ENQ-16527-25-26 | C4: FA0900036 | D4: 4 CORE X 50 SQ. MM. ALU/ARD - STRIP (XLPE) | E4: WOOD | H4: 0 | J4: Alumimium | L4: 540 | P4: 0 | T4: 0 | V4: LT-XLPE | X4: 124 | AB4: 0 | AD4: PVC Type ST-2 | AF4: 69 | AH4: Galvanised Steel Flat Strip | AJ4: 457 | AL4: PVC Type ST-2 | AN4: 240 | AR4: 0 | AV4: 0 | AZ4: 0 | BD4: 0 | BH4: 0 | BL4: 0 | BP4: 0 | BR4: RUBBERIZED COTTON TAPE | BT4: 0 | BX4: 0 | BZ4: 8874 | CA4: 8874 | CH4: 8874 | CO4: 8874 | CQ4: 8874 | CR4: 0.18 | CS4: 1597.32 | CT4: 10471.32 | CU4: 60 | CV4: KMS | CW4: 628279 | CX4: MD0100015 | CY4: DRUM - 48 X 20 X 28 X 2.25 - RDSO | CZ4: 500
A5: ENQ-16527-25-26 | C5: FA0900042 | D5: 2 CORE X 10 SQ. MM. ALU/ARD - WIRE (XLPE) | E5: WOOD | H5: 0 | J5: Alumimium | L5: 54 | P5: 0 | T5: 0 | V5: LT-XLPE | X5: 26 | AB5: 0 | AD5: PVC Type ST-2 | AF5: 74 | AH5: Galvanised Steel Round Wire | AJ5: 340 | AL5: PVC Type ST-2 | AN5: 127 | AR5: 0 | AV5: 0 | AZ5: 0 | BD5: 0 | BH5: 0 | BL5: 0 | BP5: 0 | BR5: RUBBERIZED COTTON TAPE | BT5: 0 | BX5: 0 | BZ5: 4313 | CA5: 4313 | CH5: 4313 | CO5: 4313 | CQ5: 4313 | CR5: 0.18 | CS5: 776.34 | CT5: 5089.34 | CU5: 100 | CV5: KMS | CW5: 508934 | CX5: MD0100075 | CY5: DRUM - 42 X 15 X 23 X 2 | CZ5: 1000
A6: ENQ-16527-25-26 | C6: FA1100012 | D6: 4 CORE X 95 SQ. MM. AL/ARD - STRIP (XLPE) | E6: WOOD | H6: 0 | J6: Alumimium | L6: 1026 | P6: 0 | T6: 0 | V6: LT-XLPE | X6: 187 | AB6: 0 | AD6: PVC Type ST-2 | AF6: 93 | AH6: Galvanised Steel Flat Strip | AJ6: 611 | AL6: PVC Type ST-2 | AN6: 348 | AR6: 0 | AV6: 0 | AZ6: 0 | BD6: 0 | BH6: 0 | BL6: 0 | BP6: 0 | BR6: RUBBERIZED COTTON TAPE | BT6: 0 | BX6: 0 | BZ6: 15824 | CA6: 15824 | CH6: 15824 | CO6: 15824 | CQ6: 15824 | CR6: 0.18 | CS6: 2848.32 | CT6: 18672.32 | CU6: 198 | CV6: KMS | CW6: 3697119 | CX6: MD0100061 | CY6: DRUM - 56 X 24 X 32 X 3 | CZ6: 500
A7: ENQ-16527-25-26 | C7: FA1100036 | D7: 4 CORE X 400 SQ. MM. AL/ARD - STRIP (XLPE) | E7: STEEL | H7: 0 | J7: Alumimium | L7: 4320 | P7: 0 | T7: 0 | V7: LT-XLPE | X7: 650 | AB7: 0 | AD7: PVC Type ST-2 | AF7: 308 | AH7: Galvanised Steel Flat Strip | AJ7: 1211 | AL7: PVC Type ST-2 | AN7: 999 | AR7: 0 | AV7: 0 | AZ7: 0 | BD7: 0 | BH7: 0 | BL7: 0 | BP7: 0 | BR7: RUBBERIZED COTTON TAPE | BT7: 0 | BX7: 0 | CR7: 0.18 | CU7: 27 | CV7: KMS | CZ7: 500
A8: ENQ-16527-25-26 | C8: FA1100067 | D8: 4 CORE X 150 SQ. MM. AL/ARD - STRIP (XLPE) | E8: WOOD | H8: 0 | J8: Alumimium | L8: 1620 | P8: 0 | T8: 0 | V8: LT-XLPE | X8: 297 | AB8: 0 | AD8: PVC Type ST-2 | AF8: 138 | AH8: Galvanised Steel Flat Strip | AJ8: 777 | AL8: PVC Type ST-2 | AN8: 479 | AR8: 0 | AV8: 0 | AZ8: 0 | BD8: 0 | BH8: 0 | BL8: 0 | BP8: 0 | BR8: RUBBERIZED COTTON TAPE | BT8: 0 | BX8: 0 | BZ8: 20094 | CA8: 20094 | CH8: 20094 | CO8: 20094 | CQ8: 20094 | CR8: 0.18 | CS8: 3616.92 | CT8: 23710.92 | CU8: 8 | CV8: KMS | CW8: 189687 | CX8: MD0100070 | CY8: DRUM - 68 X 24 X 32 X 3 | CZ8: 500
A9: ENQ-16527-25-26 | C9: FA1300004 | D9: 3 CORE X 300 SQ. MM. AL/ARM - STRIP (XLPE) - 11 KV | E9: STEEL | F9: Copper Tape - 0.04 mm | H9: 88 | J9: Alumimium | L9: 2430 | P9: 0 | R9: Extruded Semiconductive | T9: 337 | V9: HT-XLPE | X9: 802 | AB9: 0 | AD9: PVC Type ST-2 | AF9: 277 | AH9: Galvanised Steel Flat Strip | AJ9: 1125 | AL9: PVC Type ST-2 | AN9: 995 | AP9: FILLER | AR9: 1258 | AV9: 0 | AZ9: 0 | BD9: 0 | BH9: 0 | BL9: 88 | BP9: 0 | BR9: RUBBERIZED COTTON TAPE | BT9: 0 | BX9: 0 | BZ9: 60800 | CA9: 60800 | CH9: 60800 | CO9: 60800 | CQ9: 60800 | CR9: 0.18 | CS9: 10944 | CT9: 71744 | CU9: 111 | CV9: KMS | CW9: 7963584 | CX9: SP0400141 | CY9: CORRUGATED DISPATCH STEEL DRUM 2080 X 1000 X 1400 MM | CZ9: 500
A10: ENQ-16527-25-26 | C10: FA1300006 | D10: 3 CORE X 70 SQ. MM. AL/ARM - STRIP (XLPE) - 11 KV | E10: STEEL | F10: Copper Tape - 0.04 mm | H10: 58 | J10: Alumimium | L10: 567 | P10: 0 | R10: Extruded Semiconductive | T10: 188 | V10: HT-XLPE | X10: 474 | AB10: 0 | AD10: PVC Type ST-2 | AF10: 142 | AH10: Galvanised Steel Flat Strip | AJ10: 750 | AL10: PVC Type ST-2 | AN10: 474 | AP10: FILLER | AR10: 533 | AV10: 0 | AZ10: 0 | BD10: 0 | BH10: 0 | BL10: 0 | BP10: 0 | BR10: RUBBERIZED COTTON TAPE | BT10: 0 | BX10: 0 | CR10: 0.18 | CU10: 3 | CV10: KMS | CX10: SP0400118 | CY10: CORRUGATED DISPATCH STEEL DRUM 1700 X 1000 X 1200 | CZ10: 500

Sheet AUTO CALCULATION SHEET (2)
A2: Chandigarh Power Distribution Limited
A4: TENDER SPECIFICATION NO () | B4: CPDL/FY25-26/HT & LT Cable/008 Dated 08th July 2025
A5: TENDER DESCRIPTION () | B5: 02 Years Rate Contract for the Supply of HT and LT Cables in Chandigarh, CPDL.
A6: Last Date & Time of Submission () | B6: 29.07.2025(Up to 17:00 Hrs)
A7: REVERSE AUCTION | B7: Purchaser reserves the right to use Reverse Auction as an optional tool as an integral part of the entire tendering process. All techno-commercially qualified bidders shall participate in this event.
A8: Price () | B8: Prices quoted by the Bidder shall be variable as per PV clause mentioned in bid document. The price shall be variable and price variation clause shall be as per latest IEEMA price variation formula. All #0# denoted input prices in the formula (Al0, Cu0, Fe0, CC0, PVC0 etc.) shall be as per IEEMA Circulars of June-25 (Published in July 2025).
A9: Validity () | B9: Bids shall remain valid for 120 days from the due date of submission of the Bid & subsequent corrigendum / amendment / extension of due date of submission.
A10: Delivery Period () | B10: For LT Cable: Bidders shall supply material within 6 to 8 Weeks from the date of issuance of LOI / Release Order/manufacturing Clearance against Rate Contract. However, firm delivery dates will be mentioned in the LOI / Order. For HT Cable: Bidders shall supply material within 8 to 10 Weeks from the date of issuance of LOI / Release Order/manufacturing Clearance against Rate Contract. However, firm delivery dates will be mentioned in the LOI / Order.
A11: Payment Terms () | B11: (i) 20% of contract value will be paid as interest free advance against Corporate Guarantee / Advance Bank Guarantee of an Equivalent amount from nationalized / scheduled bank(s) as may be acceptable to the Company, initially valid for a period of nine months from the date of submission. (ii) 70% Payment shall be released on pro-rata basic within 90 days from the receipt of material at CPDL site with complete set of documents as mentioned in order. Supplier should submit the invoices along with all required documents at CPDL Office within 3 days. Any delay in submission of any of these documents will be to your account. It may please be noted that for payment purposes the date of receipt of documents will be considered on the basis of the date of receipt of last document, in case partial documents were received earlier. (iii) The remaining 10% shall be released after submission of Performance Bank Guarantee (PBG).
A12: Standard length () | B12: 11kV 3C X 300 Sq mm = mtr 11kV 3C X 70 Sq mm = 500 mtr+2% (mild steel drum=2489x1270x1295) 1.1 kV 4C X 150 Sq mm = 500 mtr (good Quality wood) 1.1 kV 4C X 95 Sq mm = 500 mtr+/-2% (good Quality wood) 1.1 kV 4C X 400 Sq mm = 500 mtr (non-returnable wooden drum) 1.1 kV 2C X 10sqmm = 1000 mtr+/-5% (good Quality wood) 1.1 kV 4C X 16sqmm = 500 mtr+/-2% (good Quality wood) 1.1 kV 4C X 35sqmm = 500 mtr+/-2% (good Quality wood) 1.1 kV 4C X 50sqmm = 500 mtr+/-2% (good Quality wood)
A13: Packing ()
A14: Technical Specification
N16: Conductor | V16: AL ALLOY | X16: Insulation Screening (Metallic) | AF16: Insulation Screening (Non-Metallic) | AH16: Insulation | AQ16: POLY TAPE | AR16: Inner Sheath | BA16: Armouring | BL16: Outer Sheath | BX16: FILLER | BY16: GREASE | BZ16: Water swellable Tape | CA16: Semi conducting Water Swellable tape | CB16: SEMICON TAPE | CC16: GLASS FIBER TAPE | CD16: COPPER WIRE 0.8 MM | CE16: RUBBERIZED COTTON TAPE | CF16: Water Tight Compound | CG16: DRUM TYPE | CK16: DRUM COST PER KM | CL16: TOTAL RM COST | CM16: EXTRA CONSUMPTION | CN16: EXTRA CONSUMPTION VALUE | CZ16: $A$1
A17: DOCKET NO. | B17: BASE DATE | C17: ITEM CODE | D17: PROPOSE ERP ITEM NAME | E17: EX-WORKS (PER KM) | F17: FREIGHT PER KM | G17: PRICE INCLUDING FREIGHT (PER KM) | H17: GST % | I17: GST VALUE | J17: PRICE INCLUDING GST & FREIGHT (PER KM) | K17: QTY | L17: Unit | M17: TOTAL PRICE OF FULL QTY (INCLUDING FRIGHT & GST) | N17: Alumimium | O17: Alumimium ALLOY | P17: Copper | Q17: AL-59 | R17: AL-4 | S17: AL-7 | T17: Flexible Copper | U17: Galvanized steel wire | V17: Alumimium | W17: Alumimium ALLOY | X17: Coper tape - 0.1 mm | Y17: Copper Tape - 0.03 mm | Z17: Copper Tape - 0.035 mm | AA17: Copper Tape - 0.04 mm | AB17: Copper Tape - 0.045 mm | AC17: Copper Tape - 0.050 mm | AD17: Copper Tape - 0.060 mm | AE17: Copper Tape - 0.075 mm(DOUBLE) | AF17: Extruded semiconductive | AG17: Extruded Semiconductive(Stripable) | AH17: HT-XLPE | AI17: LT-XLPE | AJ17: TR XLPE | AK17: Type A PVC | AL17: Type C PVC (HR) | AM17: Type A PVC-1.45 | AN17: Type A PVC-FR | AO17: Type A PVC-FRLS | AP17: Type A PVC-1.38 | AQ17: POLY TAPE | AR17: FR PVC Type ST-1 | AS17: FR PVC Type ST-2 | AT17: FRLSH PVC Type ST-1 | AU17: FRLSH PVC Type ST-2 | AV17: PVC Type ST-1 | AW17: PVC Type ST-1-PRESSURE EXTRUDED | AX17: PVC Type ST-2 | AY17: PVC COMPOUND 1.48 | AZ17: PVC Type ST-2-PRESSURE EXTRUDED | BA17: ACSR CORE WIRE | BB17: ACSR DOG STEEL WIRE | BC17: Aluminium Flat Strip | BD17: Aluminium Round Wire | BE17: Alumimium Tape | BF17: Double Steel Tape | BG17: Galvanised Steel Flat Strip | BH17: Galvanised Steel Flat Strip (Double) | BI17: Galvanised Steel Flat Strip-B | BJ17: Galvanised Steel Round Wire | BK17: Galvanised Steel Round Wire (Double) | BL17: FR PVC Type ST-1 | BM17: FR PVC Type ST-2 | BN17: FRLSH PVC Type ST-1 | BO17: FRLSH PVC Type ST-2 | BP17: ZHFR | BQ17: PE-ST-3 | BR17: PE-ST-7 | BS17: PVC Type ST-1 | BT17: PVC Type ST-2 | BU17: PVC COMPOUND 1.48 | BV17: PVC Type ST-2-PRESSURE EXTRUDED | BW17: UV & Track Resistant XLPE | BX17: FILLER | BY17: Grease | BZ17: Water swellable Tape | CA17: Semi conducting Water Swellable tape | CB17: SEMICON TAPE | CC17: GLASS FIBER TAPE | CD17: COPPER WIRE 0.8 MM | CE17: RUBBERIZED COTTON TAPE | CF17: Water Tight Compound | CG17: PROPOSE DRUM TYPE | CH17: DRUM CODE | CI17: DRUM SIZE (FxbXtx Ft) | CJ17: PARTY STANDARD LENGTH (MTR) | CO17: MFG% | CP17: MFG VALUE | CQ17: PROF% | CR17: PROFIT VALUE | CS17: 1ST EX-WORKS | CT17: Intt % | CU17: INTT VALUE | CV17: insp% | CW17: INSP VALUE | CX17: TTR Charges% | CY17: TTR Charges VALUE
N18: 255 | O18: =+IFERROR(VLOOKUP($O$17,Sheet1!J:L,2,0),0) -> 0 | P18: =+IFERROR(VLOOKUP($P$17,Sheet1!J:M,2,0),0) -> 0 | Q18: =+IFERROR(VLOOKUP($Q$17,Sheet1!J:M,2,0),0) -> 0 | R18: =+IFERROR(VLOOKUP($R$17,Sheet1!J:M,2,0),0) -> 0 | S18: =+IFERROR(VLOOKUP($S$17,Sheet1!J:M,2,0),0) -> 0 | T18: =+IFERROR(VLOOKUP($T$17,Sheet1!J:M,2,0),0) -> 0 | U18: =+IFERROR(VLOOKUP($U$17,Sheet1!J:M,2,0),0) -> 0 | V18: =+IFERROR(VLOOKUP($V$17,Sheet1!N:Q,2,0),0) -> 0 | W18: =+IFERROR(VLOOKUP($W$17,Sheet1!N:O,2,0),0) -> 0 | X18: =+IFERROR(VLOOKUP($X$17,Sheet1!F:I,2,0),0) -> 0 | Y18: =+IFERROR(VLOOKUP($Y$17,Sheet1!F:I,2,0),0) -> 0 | Z18: =+IFERROR(VLOOKUP($Z$17,Sheet1!F:I,2,0),0) -> 0 | AA18: 1017 | AB18: =+IFERROR(VLOOKUP($AB$17,Sheet1!F:I,2,0),0) -> 0 | AC18: =+IFERROR(VLOOKUP($AC$17,Sheet1!F:I,2,0),0) -> 0 | AD18: =+IFERROR(VLOOKUP($AD$17,Sheet1!F:I,2,0),0) -> 0 | AE18: =+IFERROR(VLOOKUP($AE$17,Sheet1!F:I,2,0),0) -> 0 | AF18: 170 | AG18: =+IFERROR(VLOOKUP($AG$17,Sheet1!R:U,2,0),0) -> 0 | AH18: 142 | AI18: 105 | AJ18: =+IFERROR(VLOOKUP($AJ$17,Sheet1!V:Y,2,0),0) -> 0 | AK18: =+IFERROR(VLOOKUP($AK$17,Sheet1!V:Y,2,0),0) -> 0 | AL18: =+IFERROR(VLOOKUP($AL$17,Sheet1!V:Y,2,0),0) -> 0 | AM18: =+IFERROR(VLOOKUP($AM$17,Sheet1!V:Y,2,0),0) -> 0 | AN18: =+IFERROR(VLOOKUP($AN$17,Sheet1!V:Y,2,0),0) -> 0 | AO18: =+IFERROR(VLOOKUP($AO$17,Sheet1!V:Y,2,0),0) -> 0 | AP18: =+IFERROR(VLOOKUP($AP$17,Sheet1!V:Y,2,0),0) -> 0 | AQ18: =+IFERROR(VLOOKUP($AQ$17,Sheet1!Z2:AA840,2,0),0) -> 0 | AR18: =+IFERROR(VLOOKUP($AR$17,Sheet1!AD2:AG840,2,0),0) -> 0 | AS18: =+IFERROR(VLOOKUP($AS$17,Sheet1!AD2:AG840,2,0),0) -> 0 | AT18: =+IFERROR(VLOOKUP($AT$17,Sheet1!AD2:AG840,2,0),0) -> 0 | AU18: =+IFERROR(VLOOKUP($AU$17,Sheet1!AD2:AG840,2,0),0) -> 0 | AV18: =+IFERROR(VLOOKUP($AV$17,Sheet1!AD2:AG840,2,0),0) -> 0 | AW18: =+IFERROR(VLOOKUP($AW$17,Sheet1!AD2:AG840,2,0),0) -> 0 | AX18: 62 | AY18: =+IFERROR(VLOOKUP($AY$17,Sheet1!AD2:AG840,2,0),0) -> 0 | AZ18: =+IFERROR(VLOOKUP($AZ$17,Sheet1!AD2:AG840,2,0),0) -> 0 | BA18: =+IFERROR(VLOOKUP($BA$17,Sheet1!AH2:AK840,2,0),0) -> 0 | BB18: =+IFERROR(VLOOKUP($BB$17,Sheet1!AH2:AK840,2,0),0) -> 0 | BC18: =+IFERROR(VLOOKUP($BC$17,Sheet1!AH2:AK840,2,0),0) -> 0 | BD18: =+IFERROR(VLOOKUP($BD$17,Sheet1!AH2:AK840,2,0),0) -> 0 | BE18: =+IFERROR(VLOOKUP($BE$17,Sheet1!AH2:AK840,2,0),0) -> 0 | BF18: =+IFERROR(VLOOKUP($BF$17,Sheet1!AH2:AK840,2,0),0) -> 0 | BG18: 74 | BH18: =+IFERROR(VLOOKUP($BH$17,Sheet1!AH2:AK840,2,0),0) -> 0 | BI18: =+IFERROR(VLOOKUP($BI$17,Sheet1!AH2:AK840,2,0),0) -> 0 | BJ18: =+IFERROR(VLOOKUP($BJ$17,Sheet1!AH2:AK840,2,0),0) -> 0 | BK18: =+IFERROR(VLOOKUP($BK$17,Sheet1!AH2:AK840,2,0),0) -> 0 | BL18: =+IFERROR(VLOOKUP($BL$17,Sheet1!AL2:AO840,2,0),0) -> 0 | BM18: =+IFERROR(VLOOKUP($BM$17,Sheet1!AL2:AO840,2,0),0) -> 0 | BN18: =+IFERROR(VLOOKUP($BN$17,Sheet1!AL2:AO840,2,0),0) -> 0 | BO18: =+IFERROR(VLOOKUP($BO$17,Sheet1!AL2:AO840,2,0),0) -> 0 | BP18: =+IFERROR(VLOOKUP($BP$17,Sheet1!AL2:AO840,2,0),0) -> 0 | BQ18: =+IFERROR(VLOOKUP($BQ$17,Sheet1!AL2:AO840,2,0),0) -> 0 | BR18: =+IFERROR(VLOOKUP($BR$17,Sheet1!AL2:AO840,2,0),0) -> 0 | BS18: =+IFERROR(VLOOKUP($BS$17,Sheet1!AL2:AO840,2,0),0) -> 0 | BT18: 62 | BU18: =+IFERROR(VLOOKUP($BU$17,Sheet1!AL2:AO840,2,0),0) -> 0 | BV18: =+IFERROR(VLOOKUP($BV$17,Sheet1!AL2:AO840,2,0),0) -> 0 | BW18: =+IFERROR(VLOOKUP($BW$17,Sheet1!AL2:AO840,2,0),0) -> 0 | BX18: 28 | BY18: =+IFERROR(VLOOKUP($BY$17,Sheet1!AT2:AW840,2,0),0) -> 0 | BZ18: =+IFERROR(VLOOKUP($BZ$17,Sheet1!AX2:BA840,2,0),0) -> 0 | CA18: =+IFERROR(VLOOKUP($CA$17,Sheet1!BB2:BE840,2,0),0) -> 0 | CB18: =+IFERROR(VLOOKUP($CB$17,Sheet1!BF2:BI840,2,0),0) -> 0 | CC18: =+IFERROR(VLOOKUP($CC$17,Sheet1!BJ2:BM840,2,0),0) -> 0 | CD18: =+IFERROR(VLOOKUP($CD$17,Sheet1!BN2:BQ840,2,0),0) -> 0 | CE18: 303 | CF18: =+IFERROR(VLOOKUP($CF$17,Sheet1!BV2:BY840,2,0),0) -> 0
A19: =Sheet1!A9 -> ENQ-16527-25-26 | B19: 45809 | C19: =Sheet1!C9 -> FA1300004 | D19: =Sheet1!D9 -> 3 CORE X 300 SQ. MM. AL/ARM - STRIP (XLPE) - 11 KV | E19: =CS19+CU19+CW19+CY19 -> 1666853.5 | F19: =ROUNDUP(M32,0) -> 54933 | G19: =E19+F19 -> 1721786.5 | H19: =Sheet1!CR9 -> 0.18 | I19: =G19*H19 -> 309921.58 | J19: =G19+I19 -> 2031708.1 | K19: =Sheet1!CU9 -> 111 | L19: =Sheet1!CV9 -> KMS | M19: =J19*K19 -> 2.255196e+08 | N19: =+IFERROR(VLOOKUP($N$17,Sheet1!J9:L9,3,0),0) -> 2430 | O19: =+IFERROR(VLOOKUP($O$17,Sheet1!J9:L9,3,0),0) -> 0 | P19: =+IFERROR(VLOOKUP($P$17,Sheet1!J9:M9,3,0),0) -> 0 | Q19: =+IFERROR(VLOOKUP($Q$17,Sheet1!J9:M9,3,0),0) -> 0 | R19: =+IFERROR(VLOOKUP($R$17,Sheet1!J9:M9,3,0),0) -> 0 | S19: =+IFERROR(VLOOKUP($S$17,Sheet1!J9:M9,3,0),0) -> 0 | T19: =+IFERROR(VLOOKUP($T$17,Sheet1!J9:M9,3,0),0) -> 0 | U19: =+IFERROR(VLOOKUP($U$17,Sheet1!J9:M9,3,0),0) -> 0 | V19: =+IFERROR(VLOOKUP($V$17,Sheet1!N9:Q9,3,0),0) -> 0 | W19: =+IFERROR(VLOOKUP($W$17,Sheet1!N9:Q9,3,0),0) -> 0 | X19: =+IFERROR(VLOOKUP($X$17,Sheet1!F9:I9,3,0),0) -> 0 | Y19: =+IFERROR(VLOOKUP($Y$17,Sheet1!F9:I9,3,0),0) -> 0 | Z19: =+IFERROR(VLOOKUP($Z$17,Sheet1!F9:I9,3,0),0) -> 0 | AA19: 119 | AB19: =+IFERROR(VLOOKUP($AB$17,Sheet1!F9:I9,3,0),0) -> 0 | AC19: =+IFERROR(VLOOKUP($AC$17,Sheet1!F9:I9,3,0),0) -> 0 | AD19: =+IFERROR(VLOOKUP($AD$17,Sheet1!F9:I9,3,0),0) -> 0 | AE19: =+IFERROR(VLOOKUP($AE$17,Sheet1!F9:I9,3,0),0) -> 0 | AF19: 328 | AG19: =+IFERROR(VLOOKUP($AG$17,Sheet1!R9:U9,3,0),0) -> 0 | AH19: 870 | AI19: =+IFERROR(VLOOKUP($AI$17,Sheet1!V9:Y9,3,0),0) -> 0 | AJ19: =+IFERROR(VLOOKUP($AJ$17,Sheet1!V9:Y9,3,0),0) -> 0 | AK19: =+IFERROR(VLOOKUP($AK$17,Sheet1!V9:Y9,3,0),0) -> 0 | AL19: =+IFERROR(VLOOKUP($AL$17,Sheet1!V9:Y9,3,0),0) -> 0 | AM19: =+IFERROR(VLOOKUP($AM$17,Sheet1!V9:Y9,3,0),0) -> 0 | AN19: =+IFERROR(VLOOKUP($AN$17,Sheet1!V9:Y9,3,0),0) -> 0 | AO19: =+IFERROR(VLOOKUP($AO$17,Sheet1!V9:Y9,3,0),0) -> 0 | AP19: =+IFERROR(VLOOKUP($AP$17,Sheet1!V9:Y9,3,0),0) -> 0 | AQ19: =+IFERROR(VLOOKUP($AQ$17,Sheet1!Z9:AB9,3,0),0) -> 0 | AR19: =+IFERROR(VLOOKUP($AR$17,Sheet1!AD9:AG9,3,0),0) -> 0 | AS19: =+IFERROR(VLOOKUP($AS$17,Sheet1!AD9:AG9,3,0),0) -> 0 | AT19: =+IFERROR(VLOOKUP($AT$17,Sheet1!AD9:AG9,3,0),0) -> 0 | AU19: =+IFERROR(VLOOKUP($AU$17,Sheet1!AD9:AG9,3,0),0) -> 0 | AV19: =+IFERROR(VLOOKUP($AV$17,Sheet1!AD9:AG9,3,0),0) -> 0 | AW19: =+IFERROR(VLOOKUP($AW$17,Sheet1!AD9:AG9,3,0),0) -> 0 | AX19: 300 | AY19: =+IFERROR(VLOOKUP($AY$17,Sheet1!AD9:AG9,3,0),0) -> 0 | AZ19: =+IFERROR(VLOOKUP($AZ$17,Sheet1!AD9:AG9,3,0),0) -> 0 | BA19: =+IFERROR(VLOOKUP($BA$17,Sheet1!AH9:AK9,3,0),0) -> 0 | BB19: =+IFERROR(VLOOKUP($BB$17,Sheet1!AH9:AK9,3,0),0) -> 0 | BC19: =+IFERROR(VLOOKUP($BC$17,Sheet1!AH9:AK9,3,0),0) -> 0 | BD19: =+IFERROR(VLOOKUP($BD$17,Sheet1!AH9:AK9,3,0),0) -> 0 | BE19: =+IFERROR(VLOOKUP($BE$17,Sheet1!AH9:AK9,3,0),0) -> 0 | BF19: =+IFERROR(VLOOKUP($BF$17,Sheet1!AH9:AK9,3,0),0) -> 0 | BG19: 1150 | BH19: =+IFERROR(VLOOKUP($BH$17,Sheet1!AH9:AK9,3,0),0) -> 0 | BI19: =+IFERROR(VLOOKUP($BI$17,Sheet1!AH9:AK9,3,0),0) -> 0 | BJ19: =+IFERROR(VLOOKUP($BJ$17,Sheet1!AH9:AK9,3,0),0) -> 0 | BK19: =+IFERROR(VLOOKUP($BK$17,Sheet1!AH9:AK9,3,0),0) -> 0 | BL19: =+IFERROR(VLOOKUP($BL$17,Sheet1!AL9:AO9,3,0),0) -> 0 | BM19: =+IFERROR(VLOOKUP($BM$17,Sheet1!AL9:AO9,3,0),0) -> 0 | BN19: =+IFERROR(VLOOKUP($BN$17,Sheet1!AL9:AO9,3,0),0) -> 0 | BO19: =+IFERROR(VLOOKUP($BO$17,Sheet1!AL9:AO9,3,0),0) -> 0 | BP19: =+IFERROR(VLOOKUP($BP$17,Sheet1!AL9:AO9,3,0),0) -> 0 | BQ19: =+IFERROR(VLOOKUP($BQ$17,Sheet1!AL9:AO9,3,0),0) -> 0 | BR19: =+IFERROR(VLOOKUP($BR$17,Sheet1!AL9:AO9,3,0),0) -> 0 | BS19: =+IFERROR(VLOOKUP($BS$17,Sheet1!AL9:AO9,3,0),0) -> 0 | BT19: 1012 | BU19: =+IFERROR(VLOOKUP($BU$17,Sheet1!AL9:AO9,3,0),0) -> 0 | BV19: =+IFERROR(VLOOKUP($BV$17,Sheet1!AL9:AO9,3,0),0) -> 0 | BW19: =+IFERROR(VLOOKUP($BW$17,Sheet1!AL9:AO9,3,0),0) -> 0 | BX19: 1310 | BY19: =+IFERROR(VLOOKUP($BY$17,Sheet1!AT9:AW9,3,0),0) -> 0 | BZ19: =+IFERROR(VLOOKUP($BZ$17,Sheet1!AX9:BA9,3,0),0) -> 0 | CA19: =+IFERROR(VLOOKUP($CA$17,Sheet1!BB9:BE9,3,0),0) -> 0 | CB19: =+IFERROR(VLOOKUP($CB$17,Sheet1!BF9:BI9,3,0),0) -> 0 | CC19: =+IFERROR(VLOOKUP($CC$17,Sheet1!BJ9:BM9,3,0),0) -> 0 | CD19: =+IFERROR(VLOOKUP($CD$17,Sheet1!BN9:BQ9,3,0),0) -> 0 | CE19: 49 | CF19: =+IFERROR(VLOOKUP($CF$17,Sheet1!BV9:BY9,3,0),0) -> 0 | CG19: =Sheet1!E9 -> STEEL | CH19: =Sheet1!CX9 -> SP0400141 | CI19: =Sheet1!CY9 -> CORRUGATED DISPATCH STEEL DRUM 2080 X 1000 X 1400 MM | CJ19: =Sheet1!CZ9 -> 500 | CK19: =30400/0.5 -> 60800 | CL19: =SUMPRODUCT($N$18:$CF$18,N19:CF19)+CK19 -> 1198744 | CM19: =Sheet1!CB9 -> 0 | CN19: =CL19*CM19 -> 0 | CO19: 0.35 | CP19: =CL19*CO19 -> 419560.4 | CQ19: 0 | CR19: =CL19*CQ19 -> 0 | CS19: =CL19+CN19+CP19+CR19 -> 1618304.4 | CT19: 0.02 | CU19: =CS19*CT19 -> 32366.088 | CV19: 0.01 | CW19: =CS19*CV19 -> 16183.044 | CX19: =Sheet1!CM9 -> 0 | CY19: =CX19*CS19 -> 0
A20: =Sheet1!A10 -> ENQ-16527-25-26 | B20: 45809 | C20: =Sheet1!C10 -> FA1300006 | D20: =Sheet1!D10 -> 3 CORE X 70 SQ. MM. AL/ARM - STRIP (XLPE) - 11 KV | E20: =CS20+CU20+CW20+CY20 -> 694910.72 | F20: =ROUNDUP(M33,0) -> 45167 | G20: =E20+F20 -> 740077.72 | H20: =Sheet1!CR10 -> 0.18 | I20: =G20*H20 -> 133213.99 | J20: =G20+I20 -> 873291.71 | K20: =Sheet1!CU10 -> 3 | L20: =Sheet1!CV10 -> KMS | M20: =J20*K20 -> 2619875.1 | N20: =+IFERROR(VLOOKUP($N$17,Sheet1!J10:L10,3,0),0) -> 567 | O20: =+IFERROR(VLOOKUP($O$17,Sheet1!J10:L10,3,0),0) -> 0 | P20: =+IFERROR(VLOOKUP($P$17,Sheet1!J10:M10,3,0),0) -> 0 | Q20: =+IFERROR(VLOOKUP($Q$17,Sheet1!J10:M10,3,0),0) -> 0 | R20: =+IFERROR(VLOOKUP($R$17,Sheet1!J10:M10,3,0),0) -> 0 | S20: =+IFERROR(VLOOKUP($S$17,Sheet1!J10:M10,3,0),0) -> 0 | T20: =+IFERROR(VLOOKUP($T$17,Sheet1!J10:M10,3,0),0) -> 0 | U20: =+IFERROR(VLOOKUP($U$17,Sheet1!J10:M10,3,0),0) -> 0 | V20: =+IFERROR(VLOOKUP($V$17,Sheet1!N10:Q10,3,0),0) -> 0 | W20: =+IFERROR(VLOOKUP($W$17,Sheet1!N10:Q10,3,0),0) -> 0 | X20: =+IFERROR(VLOOKUP($X$17,Sheet1!F10:I10,3,0),0) -> 0 | Y20: =+IFERROR(VLOOKUP($Y$17,Sheet1!F10:I10,3,0),0) -> 0 | Z20: =+IFERROR(VLOOKUP($Z$17,Sheet1!F10:I10,3,0),0) -> 0 | AA20: 78 | AB20: =+IFERROR(VLOOKUP($AB$17,Sheet1!F10:I10,3,0),0) -> 0 | AC20: =+IFERROR(VLOOKUP($AC$17,Sheet1!F10:I10,3,0),0) -> 0 | AD20: =+IFERROR(VLOOKUP($AD$17,Sheet1!F10:I10,3,0),0) -> 0 | AE20: =+IFERROR(VLOOKUP($AE$17,Sheet1!F10:I10,3,0),0) -> 0 | AF20: 190 | AG20: =+IFERROR(VLOOKUP($AG$17,Sheet1!R10:U10,3,0),0) -> 0 | AH20: 510 | AI20: =+IFERROR(VLOOKUP($AI$17,Sheet1!V10:Y10,3,0),0) -> 0 | AJ20: =+IFERROR(VLOOKUP($AJ$17,Sheet1!V10:Y10,3,0),0) -> 0 | AK20: =+IFERROR(VLOOKUP($AK$17,Sheet1!V10:Y10,3,0),0) -> 0 | AL20: =+IFERROR(VLOOKUP($AL$17,Sheet1!V10:Y10,3,0),0) -> 0 | AM20: =+IFERROR(VLOOKUP($AM$17,Sheet1!V10:Y10,3,0),0) -> 0 | AN20: =+IFERROR(VLOOKUP($AN$17,Sheet1!V10:Y10,3,0),0) -> 0 | AO20: =+IFERROR(VLOOKUP($AO$17,Sheet1!V10:Y10,3,0),0) -> 0 | AP20: =+IFERROR(VLOOKUP($AP$17,Sheet1!V10:Y10,3,0),0) -> 0 | AQ20: =+IFERROR(VLOOKUP($AQ$17,Sheet1!Z10:AB10,3,0),0) -> 0 | AR20: =+IFERROR(VLOOKUP($AR$17,Sheet1!AD10:AG10,3,0),0) -> 0 | AS20: =+IFERROR(VLOOKUP($AS$17,Sheet1!AD10:AG10,3,0),0) -> 0 | AT20: =+IFERROR(VLOOKUP($AT$17,Sheet1!AD10:AG10,3,0),0) -> 0 | AU20: =+IFERROR(VLOOKUP($AU$17,Sheet1!AD10:AG10,3,0),0) -> 0 | AV20: =+IFERROR(VLOOKUP($AV$17,Sheet1!AD10:AG10,3,0),0) -> 0 | AW20: =+IFERROR(VLOOKUP($AW$17,Sheet1!AD10:AG10,3,0),0) -> 0 | AX20: 155 | AY20: =+IFERROR(VLOOKUP($AY$17,Sheet1!AD10:AG10,3,0),0) -> 0 | AZ20: =+IFERROR(VLOOKUP($AZ$17,Sheet1!AD10:AG10,3,0),0) -> 0 | BA20: =+IFERROR(VLOOKUP($BA$17,Sheet1!AH10:AK10,3,0),0) -> 0 | BB20: =+IFERROR(VLOOKUP($BB$17,Sheet1!AH10:AK10,3,0),0) -> 0 | BC20: =+IFERROR(VLOOKUP($BC$17,Sheet1!AH10:AK10,3,0),0) -> 0 | BD20: =+IFERROR(VLOOKUP($BD$17,Sheet1!AH10:AK10,3,0),0) -> 0 | BE20: =+IFERROR(VLOOKUP($BE$17,Sheet1!AH10:AK10,3,0),0) -> 0 | BF20: =+IFERROR(VLOOKUP($BF$17,Sheet1!AH10:AK10,3,0),0) -> 0 | BG20: 775 | BH20: =+IFERROR(VLOOKUP($BH$17,Sheet1!AH10:AK10,3,0),0) -> 0 | BI20: =+IFERROR(VLOOKUP($BI$17,Sheet1!AH10:AK10,3,0),0) -> 0 | BJ20: =+IFERROR(VLOOKUP($BJ$17,Sheet1!AH10:AK10,3,0),0) -> 0 | BK20: =+IFERROR(VLOOKUP($BK$17,Sheet1!AH10:AK10,3,0),0) -> 0 | BL20: =+IFERROR(VLOOKUP($BL$17,Sheet1!AL10:AO10,3,0),0) -> 0 | BM20: =+IFERROR(VLOOKUP($BM$17,Sheet1!AL10:AO10,3,0),0) -> 0 | BN20: =+IFERROR(VLOOKUP($BN$17,Sheet1!AL10:AO10,3,0),0) -> 0 | BO20: =+IFERROR(VLOOKUP($BO$17,Sheet1!AL10:AO10,3,0),0) -> 0 | BP20: =+IFERROR(VLOOKUP($BP$17,Sheet1!AL10:AO10,3,0),0) -> 0 | BQ20: =+IFERROR(VLOOKUP($BQ$17,Sheet1!AL10:AO10,3,0),0) -> 0 | BR20: =+IFERROR(VLOOKUP($BR$17,Sheet1!AL10:AO10,3,0),0) -> 0 | BS20: =+IFERROR(VLOOKUP($BS$17,Sheet1!AL10:AO10,3,0),0) -> 0 | BT20: 490 | BU20: =+IFERROR(VLOOKUP($BU$17,Sheet1!AL10:AO10,3,0),0) -> 0 | BV20: =+IFERROR(VLOOKUP($BV$17,Sheet1!AL10:AO10,3,0),0) -> 0 | BW20: =+IFERROR(VLOOKUP($BW$17,Sheet1!AL10:AO10,3,0),0) -> 0 | BX20: 560 | BY20: =+IFERROR(VLOOKUP($BY$17,Sheet1!AT10:AW10,3,0),0) -> 0 | BZ20: =+IFERROR(VLOOKUP($BZ$17,Sheet1!AX10:BA10,3,0),0) -> 0 | CA20: =+IFERROR(VLOOKUP($CA$17,Sheet1!BB10:BE10,3,0),0) -> 0 | CB20: =+IFERROR(VLOOKUP($CB$17,Sheet1!BF10:BI10,3,0),0) -> 0 | CC20: =+IFERROR(VLOOKUP($CC$17,Sheet1!BJ10:BM10,3,0),0) -> 0 | CD20: =+IFERROR(VLOOKUP($CD$17,Sheet1!BN10:BQ10,3,0),0) -> 0 | CE20: 35 | CF20: =+IFERROR(VLOOKUP($CF$17,Sheet1!BV10:BY10,3,0),0) -> 0 | CG20: =Sheet1!E10 -> STEEL | CH20: =Sheet1!CX10 -> SP0400118 | CI20: =Sheet1!CY10 -> CORRUGATED DISPATCH STEEL DRUM 1700 X 1000 X 1200 | CJ20: =Sheet1!CZ10 -> 500 | CK20: =23750/0.5 -> 47500 | CL20: =SUMPRODUCT($N$18:$CF$18,N20:CF20)+CK20 -> 499756 | CM20: =Sheet1!CB10 -> 0 | CN20: =CL20*CM20 -> 0 | CO20: 0.35 | CP20: =CL20*CO20 -> 174914.6 | CQ20: 0 | CR20: =CL20*CQ20 -> 0 | CS20: =CL20+CN20+CP20+CR20 -> 674670.6 | CT20: 0.02 | CU20: =CS20*CT20 -> 13493.412 | CV20: 0.01 | CW20: =CS20*CV20 -> 6746.706 | CX20: =Sheet1!CM10 -> 0 | CY20: =CX20*CS20 -> 0
A21: =Sheet1!A7 -> ENQ-16527-25-26 | B21: 45809 | C21: =Sheet1!C7 -> FA1100036 | D21: =Sheet1!D7 -> 4 CORE X 400 SQ. MM. AL/ARD - STRIP (XLPE) | E21: =CS21+CU21+CW21+CY21 -> 1968518.3 | F21: =ROUNDUP(M34,0) -> 37686 | G21: =E21+F21 -> 2006204.3 | H21: =Sheet1!CR7 -> 0.18 | I21: =G21*H21 -> 361116.78 | J21: =G21+I21 -> 2367321.1 | K21: =Sheet1!CU7 -> 27 | L21: =Sheet1!CV7 -> KMS | M21: =J21*K21 -> 63917670 | N21: =+IFERROR(VLOOKUP($N$17,Sheet1!J7:L7,3,0),0) -> 4320 | O21: =+IFERROR(VLOOKUP($O$17,Sheet1!J7:L7,3,0),0) -> 0 | P21: =+IFERROR(VLOOKUP($P$17,Sheet1!J7:M7,3,0),0) -> 0 | Q21: =+IFERROR(VLOOKUP($Q$17,Sheet1!J7:M7,3,0),0) -> 0 | R21: =+IFERROR(VLOOKUP($R$17,Sheet1!J7:M7,3,0),0) -> 0 | S21: =+IFERROR(VLOOKUP($S$17,Sheet1!J7:M7,3,0),0) -> 0 | T21: =+IFERROR(VLOOKUP($T$17,Sheet1!J7:M7,3,0),0) -> 0 | U21: =+IFERROR(VLOOKUP($U$17,Sheet1!J7:M7,3,0),0) -> 0 | V21: =+IFERROR(VLOOKUP($V$17,Sheet1!N7:Q7,3,0),0) -> 0 | W21: =+IFERROR(VLOOKUP($W$17,Sheet1!N7:Q7,3,0),0) -> 0 | X21: =+IFERROR(VLOOKUP($X$17,Sheet1!F7:I7,3,0),0) -> 0 | Y21: =+IFERROR(VLOOKUP($Y$17,Sheet1!F7:I7,3,0),0) -> 0 | Z21: =+IFERROR(VLOOKUP($Z$17,Sheet1!F7:I7,3,0),0) -> 0 | AA21: =+IFERROR(VLOOKUP($AA$17,Sheet1!F7:I7,3,0),0) -> 0 | AB21: =+IFERROR(VLOOKUP($AB$17,Sheet1!F7:I7,3,0),0) -> 0 | AC21: =+IFERROR(VLOOKUP($AC$17,Sheet1!F7:I7,3,0),0) -> 0 | AD21: =+IFERROR(VLOOKUP($AD$17,Sheet1!F7:I7,3,0),0) -> 0 | AE21: =+IFERROR(VLOOKUP($AE$17,Sheet1!F7:I7,3,0),0) -> 0 | AF21: =+IFERROR(VLOOKUP($AF$17,Sheet1!R7:U7,3,0),0) -> 0 | AG21: =+IFERROR(VLOOKUP($AG$17,Sheet1!R7:U7,3,0),0) -> 0 | AH21: =+IFERROR(VLOOKUP($AH$17,Sheet1!V7:Y7,3,0),0) -> 0 | AI21: 700 | AJ21: =+IFERROR(VLOOKUP($AJ$17,Sheet1!V7:Y7,3,0),0) -> 0 | AK21: =+IFERROR(VLOOKUP($AK$17,Sheet1!V7:Y7,3,0),0) -> 0 | AL21: =+IFERROR(VLOOKUP($AL$17,Sheet1!V7:Y7,3,0),0) -> 0 | AM21: =+IFERROR(VLOOKUP($AM$17,Sheet1!V7:Y7,3,0),0) -> 0 | AN21: =+IFERROR(VLOOKUP($AN$17,Sheet1!V7:Y7,3,0),0) -> 0 | AO21: =+IFERROR(VLOOKUP($AO$17,Sheet1!V7:Y7,3,0),0) -> 0 | AP21: =+IFERROR(VLOOKUP($AP$17,Sheet1!V7:Y7,3,0),0) -> 0 | AQ21: =+IFERROR(VLOOKUP($AQ$17,Sheet1!Z7:AB7,3,0),0) -> 0 | AR21: =+IFERROR(VLOOKUP($AR$17,Sheet1!AD7:AG7,3,0),0) -> 0 | AS21: =+IFERROR(VLOOKUP($AS$17,Sheet1!AD7:AG7,3,0),0) -> 0 | AT21: =+IFERROR(VLOOKUP($AT$17,Sheet1!AD7:AG7,3,0),0) -> 0 | AU21: =+IFERROR(VLOOKUP($AU$17,Sheet1!AD7:AG7,3,0),0) -> 0 | AV21: =+IFERROR(VLOOKUP($AV$17,Sheet1!AD7:AG7,3,0),0) -> 0 | AW21: =+IFERROR(VLOOKUP($AW$17,Sheet1!AD7:AG7,3,0),0) -> 0 | AX21: 271 | AY21: =+IFERROR(VLOOKUP($AY$17,Sheet1!AD7:AG7,3,0),0) -> 0 | AZ21: =+IFERROR(VLOOKUP($AZ$17,Sheet1!AD7:AG7,3,0),0) -> 0 | BA21: =+IFERROR(VLOOKUP($BA$17,Sheet1!AH7:AK7,3,0),0) -> 0 | BB21: =+IFERROR(VLOOKUP($BB$17,Sheet1!AH7:AK7,3,0),0) -> 0 | BC21: =+IFERROR(VLOOKUP($BC$17,Sheet1!AH7:AK7,3,0),0) -> 0 | BD21: =+IFERROR(VLOOKUP($BD$17,Sheet1!AH7:AK7,3,0),0) -> 0 | BE21: =+IFERROR(VLOOKUP($BE$17,Sheet1!AH7:AK7,3,0),0) -> 0 | BF21: =+IFERROR(VLOOKUP($BF$17,Sheet1!AH7:AK7,3,0),0) -> 0 | BG21: 1102 | BH21: =+IFERROR(VLOOKUP($BH$17,Sheet1!AH7:AK7,3,0),0) -> 0 | BI21: =+IFERROR(VLOOKUP($BI$17,Sheet1!AH7:AK7,3,0),0) -> 0 | BJ21: =+IFERROR(VLOOKUP($BJ$17,Sheet1!AH7:AK7,3,0),0) -> 0 | BK21: =+IFERROR(VLOOKUP($BK$17,Sheet1!AH7:AK7,3,0),0) -> 0 | BL21: =+IFERROR(VLOOKUP($BL$17,Sheet1!AL7:AO7,3,0),0) -> 0 | BM21: =+IFERROR(VLOOKUP($BM$17,Sheet1!AL7:AO7,3,0),0) -> 0 | BN21: =+IFERROR(VLOOKUP($BN$17,Sheet1!AL7:AO7,3,0),0) -> 0 | BO21: =+IFERROR(VLOOKUP($BO$17,Sheet1!AL7:AO7,3,0),0) -> 0 | BP21: =+IFERROR(VLOOKUP($BP$17,Sheet1!AL7:AO7,3,0),0) -> 0 | BQ21: =+IFERROR(VLOOKUP($BQ$17,Sheet1!AL7:AO7,3,0),0) -> 0 | BR21: =+IFERROR(VLOOKUP($BR$17,Sheet1!AL7:AO7,3,0),0) -> 0 | BS21: =+IFERROR(VLOOKUP($BS$17,Sheet1!AL7:AO7,3,0),0) -> 0 | BT21: 940 | BU21: =+IFERROR(VLOOKUP($BU$17,Sheet1!AL7:AO7,3,0),0) -> 0 | BV21: =+IFERROR(VLOOKUP($BV$17,Sheet1!AL7:AO7,3,0),0) -> 0 | BW21: =+IFERROR(VLOOKUP($BW$17,Sheet1!AL7:AO7,3,0),0) -> 0 | BX21: =+IFERROR(VLOOKUP($BX$17,Sheet1!AP7:AS7,3,0),0) -> 0 | BY21: =+IFERROR(VLOOKUP($BY$17,Sheet1!AT7:AW7,3,0),0) -> 0 | BZ21: =+IFERROR(VLOOKUP($BZ$17,Sheet1!AX7:BA7,3,0),0) -> 0 | CA21: =+IFERROR(VLOOKUP($CA$17,Sheet1!BB7:BE7,3,0),0) -> 0 | CB21: =+IFERROR(VLOOKUP($CB$17,Sheet1!BF7:BI7,3,0),0) -> 0 | CC21: =+IFERROR(VLOOKUP($CC$17,Sheet1!BJ7:BM7,3,0),0) -> 0 | CD21: =+IFERROR(VLOOKUP($CD$17,Sheet1!BN7:BQ7,3,0),0) -> 0 | CE21: 87 | CF21: =+IFERROR(VLOOKUP($CF$17,Sheet1!BV7:BY7,3,0),0) -> 0 | CG21: =Sheet1!E7 -> STEEL | CH21: SP0400107 | CI21: CORRUGATED DISPATCH STEEL DRUM 2150 X 1080 X 1240 MM | CJ21: =Sheet1!CZ7 -> 500 | CK21: =28800/0.5 -> 57600 | CL21: =SUMPRODUCT($N$18:$CF$18,N21:CF21)+CK21 -> 1415691 | CM21: =Sheet1!CB7 -> 0 | CN21: =CL21*CM21 -> 0 | CO21: 0.35 | CP21: =CL21*CO21 -> 495491.85 | CQ21: 0 | CR21: =CL21*CQ21 -> 0 | CS21: =CL21+CN21+CP21+CR21 -> 1911182.9 | CT21: 0.02 | CU21: =CS21*CT21 -> 38223.657 | CV21: 0.01 | CW21: =CS21*CV21 -> 19111.828 | CX21: =Sheet1!CM7 -> 0 | CY21: =CX21*CS21 -> 0
A22: =Sheet1!A8 -> ENQ-16527-25-26 | B22: 45809 | C22: =Sheet1!C8 -> FA1100067 | D22: =Sheet1!D8 -> 4 CORE X 150 SQ. MM. AL/ARD - STRIP (XLPE) | E22: =CS22+CU22+CW22+CY22 -> 803410.04 | F22: =ROUNDUP(M35,0) -> 34688 | G22: =E22+F22 -> 838098.04 | H22: =Sheet1!CR8 -> 0.18 | I22: =G22*H22 -> 150857.65 | J22: =G22+I22 -> 988955.69 | K22: =Sheet1!CU8 -> 8 | L22: =Sheet1!CV8 -> KMS | M22: =J22*K22 -> 7911645.5 | N22: =+IFERROR(VLOOKUP($N$17,Sheet1!J8:L8,3,0),0) -> 1620 | O22: =+IFERROR(VLOOKUP($O$17,Sheet1!J8:L8,3,0),0) -> 0 | P22: =+IFERROR(VLOOKUP($P$17,Sheet1!J8:M8,3,0),0) -> 0 | Q22: =+IFERROR(VLOOKUP($Q$17,Sheet1!J8:M8,3,0),0) -> 0 | R22: =+IFERROR(VLOOKUP($R$17,Sheet1!J8:M8,3,0),0) -> 0 | S22: =+IFERROR(VLOOKUP($S$17,Sheet1!J8:M8,3,0),0) -> 0 | T22: =+IFERROR(VLOOKUP($T$17,Sheet1!J8:M8,3,0),0) -> 0 | U22: =+IFERROR(VLOOKUP($U$17,Sheet1!J8:M8,3,0),0) -> 0 | V22: =+IFERROR(VLOOKUP($V$17,Sheet1!N8:Q8,3,0),0) -> 0 | W22: =+IFERROR(VLOOKUP($W$17,Sheet1!N8:Q8,3,0),0) -> 0 | X22: =+IFERROR(VLOOKUP($X$17,Sheet1!F8:I8,3,0),0) -> 0 | Y22: =+IFERROR(VLOOKUP($Y$17,Sheet1!F8:I8,3,0),0) -> 0 | Z22: =+IFERROR(VLOOKUP($Z$17,Sheet1!F8:I8,3,0),0) -> 0 | AA22: =+IFERROR(VLOOKUP($AA$17,Sheet1!F8:I8,3,0),0) -> 0 | AB22: =+IFERROR(VLOOKUP($AB$17,Sheet1!F8:I8,3,0),0) -> 0 | AC22: =+IFERROR(VLOOKUP($AC$17,Sheet1!F8:I8,3,0),0) -> 0 | AD22: =+IFERROR(VLOOKUP($AD$17,Sheet1!F8:I8,3,0),0) -> 0 | AE22: =+IFERROR(VLOOKUP($AE$17,Sheet1!F8:I8,3,0),0) -> 0 | AF22: =+IFERROR(VLOOKUP($AF$17,Sheet1!R8:U8,3,0),0) -> 0 | AG22: =+IFERROR(VLOOKUP($AG$17,Sheet1!R8:U8,3,0),0) -> 0 | AH22: =+IFERROR(VLOOKUP($AH$17,Sheet1!V8:Y8,3,0),0) -> 0 | AI22: 327 | AJ22: =+IFERROR(VLOOKUP($AJ$17,Sheet1!V8:Y8,3,0),0) -> 0 | AK22: =+IFERROR(VLOOKUP($AK$17,Sheet1!V8:Y8,3,0),0) -> 0 | AL22: =+IFERROR(VLOOKUP($AL$17,Sheet1!V8:Y8,3,0),0) -> 0 | AM22: =+IFERROR(VLOOKUP($AM$17,Sheet1!V8:Y8,3,0),0) -> 0 | AN22: =+IFERROR(VLOOKUP($AN$17,Sheet1!V8:Y8,3,0),0) -> 0 | AO22: =+IFERROR(VLOOKUP($AO$17,Sheet1!V8:Y8,3,0),0) -> 0 | AP22: =+IFERROR(VLOOKUP($AP$17,Sheet1!V8:Y8,3,0),0) -> 0 | AQ22: =+IFERROR(VLOOKUP($AQ$17,Sheet1!Z8:AB8,3,0),0) -> 0 | AR22: =+IFERROR(VLOOKUP($AR$17,Sheet1!AD8:AG8,3,0),0) -> 0 | AS22: =+IFERROR(VLOOKUP($AS$17,Sheet1!AD8:AG8,3,0),0) -> 0 | AT22: =+IFERROR(VLOOKUP($AT$17,Sheet1!AD8:AG8,3,0),0) -> 0 | AU22: =+IFERROR(VLOOKUP($AU$17,Sheet1!AD8:AG8,3,0),0) -> 0 | AV22: =+IFERROR(VLOOKUP($AV$17,Sheet1!AD8:AG8,3,0),0) -> 0 | AW22: =+IFERROR(VLOOKUP($AW$17,Sheet1!AD8:AG8,3,0),0) -> 0 | AX22: 145 | AY22: =+IFERROR(VLOOKUP($AY$17,Sheet1!AD8:AG8,3,0),0) -> 0 | AZ22: =+IFERROR(VLOOKUP($AZ$17,Sheet1!AD8:AG8,3,0),0) -> 0 | BA22: =+IFERROR(VLOOKUP($BA$17,Sheet1!AH8:AK8,3,0),0) -> 0 | BB22: =+IFERROR(VLOOKUP($BB$17,Sheet1!AH8:AK8,3,0),0) -> 0 | BC22: =+IFERROR(VLOOKUP($BC$17,Sheet1!AH8:AK8,3,0),0) -> 0 | BD22: =+IFERROR(VLOOKUP($BD$17,Sheet1!AH8:AK8,3,0),0) -> 0 | BE22: =+IFERROR(VLOOKUP($BE$17,Sheet1!AH8:AK8,3,0),0) -> 0 | BF22: =+IFERROR(VLOOKUP($BF$17,Sheet1!AH8:AK8,3,0),0) -> 0 | BG22: 816 | BH22: =+IFERROR(VLOOKUP($BH$17,Sheet1!AH8:AK8,3,0),0) -> 0 | BI22: =+IFERROR(VLOOKUP($BI$17,Sheet1!AH8:AK8,3,0),0) -> 0 | BJ22: =+IFERROR(VLOOKUP($BJ$17,Sheet1!AH8:AK8,3,0),0) -> 0 | BK22: =+IFERROR(VLOOKUP($BK$17,Sheet1!AH8:AK8,3,0),0) -> 0 | BL22: =+IFERROR(VLOOKUP($BL$17,Sheet1!AL8:AO8,3,0),0) -> 0 | BM22: =+IFERROR(VLOOKUP($BM$17,Sheet1!AL8:AO8,3,0),0) -> 0 | BN22: =+IFERROR(VLOOKUP($BN$17,Sheet1!AL8:AO8,3,0),0) -> 0 | BO22: =+IFERROR(VLOOKUP($BO$17,Sheet1!AL8:AO8,3,0),0) -> 0 | BP22: =+IFERROR(VLOOKUP($BP$17,Sheet1!AL8:AO8,3,0),0) -> 0 | BQ22: =+IFERROR(VLOOKUP($BQ$17,Sheet1!AL8:AO8,3,0),0) -> 0 | BR22: =+IFERROR(VLOOKUP($BR$17,Sheet1!AL8:AO8,3,0),0) -> 0 | BS22: =+IFERROR(VLOOKUP($BS$17,Sheet1!AL8:AO8,3,0),0) -> 0 | BT22: 503 | BU22: =+IFERROR(VLOOKUP($BU$17,Sheet1!AL8:AO8,3,0),0) -> 0 | BV22: =+IFERROR(VLOOKUP($BV$17,Sheet1!AL8:AO8,3,0),0) -> 0 | BW22: =+IFERROR(VLOOKUP($BW$17,Sheet1!AL8:AO8,3,0),0) -> 0 | BX22: =+IFERROR(VLOOKUP($BX$17,Sheet1!AP8:AS8,3,0),0) -> 0 | BY22: =+IFERROR(VLOOKUP($BY$17,Sheet1!AT8:AW8,3,0),0) -> 0 | BZ22: =+IFERROR(VLOOKUP($BZ$17,Sheet1!AX8:BA8,3,0),0) -> 0 | CA22: =+IFERROR(VLOOKUP($CA$17,Sheet1!BB8:BE8,3,0),0) -> 0 | CB22: =+IFERROR(VLOOKUP($CB$17,Sheet1!BF8:BI8,3,0),0) -> 0 | CC22: =+IFERROR(VLOOKUP($CC$17,Sheet1!BJ8:BM8,3,0),0) -> 0 | CD22: =+IFERROR(VLOOKUP($CD$17,Sheet1!BN8:BQ8,3,0),0) -> 0 | CE22: 32 | CF22: =+IFERROR(VLOOKUP($CF$17,Sheet1!BV8:BY8,3,0),0) -> 0 | CG22: =Sheet1!E8 -> WOOD | CH22: =Sheet1!CX8 -> MD0100070 | CI22: =Sheet1!CY8 -> DRUM - 68 X 24 X 32 X 3 | CJ22: =Sheet1!CZ8 -> 500 | CK22: =Sheet1!BZ8 -> 20094 | CL22: =SUMPRODUCT($N$18:$CF$18,N22:CF22)+CK22 -> 577785 | CM22: =Sheet1!CB8 -> 0 | CN22: =CL22*CM22 -> 0 | CO22: 0.35 | CP22: =CL22*CO22 -> 202224.75 | CQ22: 0 | CR22: =CL22*CQ22 -> 0 | CS22: =CL22+CN22+CP22+CR22 -> 780009.75 | CT22: 0.02 | CU22: =CS22*CT22 -> 15600.195 | CV22: 0.01 | CW22: =CS22*CV22 -> 7800.0975 | CX22: =Sheet1!CM8 -> 0 | CY22: =CX22*CS22 -> 0
A23: =Sheet1!A6 -> ENQ-16527-25-26 | B23: 45809 | C23: =Sheet1!C6 -> FA1100012 | D23: =Sheet1!D6 -> 4 CORE X 95 SQ. MM. AL/ARD - STRIP (XLPE) | E23: =CS23+CU23+CW23+CY23 -> 527298.46 | F23: =ROUNDUP(M36,0) -> 18687 | G23: =E23+F23 -> 545985.46 | H23: =Sheet1!CR6 -> 0.18 | I23: =G23*H23 -> 98277.382 | J23: =G23+I23 -> 644262.84 | K23: =Sheet1!CU6 -> 198 | L23: =Sheet1!CV6 -> KMS | M23: =J23*K23 -> 1.2756404e+08 | N23: =+IFERROR(VLOOKUP($N$17,Sheet1!J6:L6,3,0),0) -> 1026 | O23: =+IFERROR(VLOOKUP($O$17,Sheet1!J6:L6,3,0),0) -> 0 | P23: =+IFERROR(VLOOKUP($P$17,Sheet1!J6:M6,3,0),0) -> 0 | Q23: =+IFERROR(VLOOKUP($Q$17,Sheet1!J6:M6,3,0),0) -> 0 | R23: =+IFERROR(VLOOKUP($R$17,Sheet1!J6:M6,3,0),0) -> 0 | S23: =+IFERROR(VLOOKUP($S$17,Sheet1!J6:M6,3,0),0) -> 0 | T23: =+IFERROR(VLOOKUP($T$17,Sheet1!J6:M6,3,0),0) -> 0 | U23: =+IFERROR(VLOOKUP($U$17,Sheet1!J6:M6,3,0),0) -> 0 | V23: =+IFERROR(VLOOKUP($V$17,Sheet1!N6:Q6,3,0),0) -> 0 | W23: =+IFERROR(VLOOKUP($W$17,Sheet1!N6:Q6,3,0),0) -> 0 | X23: =+IFERROR(VLOOKUP($X$17,Sheet1!F6:I6,3,0),0) -> 0 | Y23: =+IFERROR(VLOOKUP($Y$17,Sheet1!F6:I6,3,0),0) -> 0 | Z23: =+IFERROR(VLOOKUP($Z$17,Sheet1!F6:I6,3,0),0) -> 0 | AA23: =+IFERROR(VLOOKUP($AA$17,Sheet1!F6:I6,3,0),0) -> 0 | AB23: =+IFERROR(VLOOKUP($AB$17,Sheet1!F6:I6,3,0),0) -> 0 | AC23: =+IFERROR(VLOOKUP($AC$17,Sheet1!F6:I6,3,0),0) -> 0 | AD23: =+IFERROR(VLOOKUP($AD$17,Sheet1!F6:I6,3,0),0) -> 0 | AE23: =+IFERROR(VLOOKUP($AE$17,Sheet1!F6:I6,3,0),0) -> 0 | AF23: =+IFERROR(VLOOKUP($AF$17,Sheet1!R6:U6,3,0),0) -> 0 | AG23: =+IFERROR(VLOOKUP($AG$17,Sheet1!R6:U6,3,0),0) -> 0 | AH23: =+IFERROR(VLOOKUP($AH$17,Sheet1!V6:Y6,3,0),0) -> 0 | AI23: 200 | AJ23: =+IFERROR(VLOOKUP($AJ$17,Sheet1!V6:Y6,3,0),0) -> 0 | AK23: =+IFERROR(VLOOKUP($AK$17,Sheet1!V6:Y6,3,0),0) -> 0 | AL23: =+IFERROR(VLOOKUP($AL$17,Sheet1!V6:Y6,3,0),0) -> 0 | AM23: =+IFERROR(VLOOKUP($AM$17,Sheet1!V6:Y6,3,0),0) -> 0 | AN23: =+IFERROR(VLOOKUP($AN$17,Sheet1!V6:Y6,3,0),0) -> 0 | AO23: =+IFERROR(VLOOKUP($AO$17,Sheet1!V6:Y6,3,0),0) -> 0 | AP23: =+IFERROR(VLOOKUP($AP$17,Sheet1!V6:Y6,3,0),0) -> 0 | AQ23: =+IFERROR(VLOOKUP($AQ$17,Sheet1!Z6:AB6,3,0),0) -> 0 | AR23: =+IFERROR(VLOOKUP($AR$17,Sheet1!AD6:AG6,3,0),0) -> 0 | AS23: =+IFERROR(VLOOKUP($AS$17,Sheet1!AD6:AG6,3,0),0) -> 0 | AT23: =+IFERROR(VLOOKUP($AT$17,Sheet1!AD6:AG6,3,0),0) -> 0 | AU23: =+IFERROR(VLOOKUP($AU$17,Sheet1!AD6:AG6,3,0),0) -> 0 | AV23: =+IFERROR(VLOOKUP($AV$17,Sheet1!AD6:AG6,3,0),0) -> 0 | AW23: =+IFERROR(VLOOKUP($AW$17,Sheet1!AD6:AG6,3,0),0) -> 0 | AX23: 90 | AY23: =+IFERROR(VLOOKUP($AY$17,Sheet1!AD6:AG6,3,0),0) -> 0 | AZ23: =+IFERROR(VLOOKUP($AZ$17,Sheet1!AD6:AG6,3,0),0) -> 0 | BA23: =+IFERROR(VLOOKUP($BA$17,Sheet1!AH6:AK6,3,0),0) -> 0 | BB23: =+IFERROR(VLOOKUP($BB$17,Sheet1!AH6:AK6,3,0),0) -> 0 | BC23: =+IFERROR(VLOOKUP($BC$17,Sheet1!AH6:AK6,3,0),0) -> 0 | BD23: =+IFERROR(VLOOKUP($BD$17,Sheet1!AH6:AK6,3,0),0) -> 0 | BE23: =+IFERROR(VLOOKUP($BE$17,Sheet1!AH6:AK6,3,0),0) -> 0 | BF23: =+IFERROR(VLOOKUP($BF$17,Sheet1!AH6:AK6,3,0),0) -> 0 | BG23: 577 | BH23: =+IFERROR(VLOOKUP($BH$17,Sheet1!AH6:AK6,3,0),0) -> 0 | BI23: =+IFERROR(VLOOKUP($BI$17,Sheet1!AH6:AK6,3,0),0) -> 0 | BJ23: =+IFERROR(VLOOKUP($BJ$17,Sheet1!AH6:AK6,3,0),0) -> 0 | BK23: =+IFERROR(VLOOKUP($BK$17,Sheet1!AH6:AK6,3,0),0) -> 0 | BL23: =+IFERROR(VLOOKUP($BL$17,Sheet1!AL6:AO6,3,0),0) -> 0 | BM23: =+IFERROR(VLOOKUP($BM$17,Sheet1!AL6:AO6,3,0),0) -> 0 | BN23: =+IFERROR(VLOOKUP($BN$17,Sheet1!AL6:AO6,3,0),0) -> 0 | BO23: =+IFERROR(VLOOKUP($BO$17,Sheet1!AL6:AO6,3,0),0) -> 0 | BP23: =+IFERROR(VLOOKUP($BP$17,Sheet1!AL6:AO6,3,0),0) -> 0 | BQ23: =+IFERROR(VLOOKUP($BQ$17,Sheet1!AL6:AO6,3,0),0) -> 0 | BR23: =+IFERROR(VLOOKUP($BR$17,Sheet1!AL6:AO6,3,0),0) -> 0 | BS23: =+IFERROR(VLOOKUP($BS$17,Sheet1!AL6:AO6,3,0),0) -> 0 | BT23: 304 | BU23: =+IFERROR(VLOOKUP($BU$17,Sheet1!AL6:AO6,3,0),0) -> 0 | BV23: =+IFERROR(VLOOKUP($BV$17,Sheet1!AL6:AO6,3,0),0) -> 0 | BW23: =+IFERROR(VLOOKUP($BW$17,Sheet1!AL6:AO6,3,0),0) -> 0 | BX23: =+IFERROR(VLOOKUP($BX$17,Sheet1!AP6:AS6,3,0),0) -> 0 | BY23: =+IFERROR(VLOOKUP($BY$17,Sheet1!AT6:AW6,3,0),0) -> 0 | BZ23: =+IFERROR(VLOOKUP($BZ$17,Sheet1!AX6:BA6,3,0),0) -> 0 | CA23: =+IFERROR(VLOOKUP($CA$17,Sheet1!BB6:BE6,3,0),0) -> 0 | CB23: =+IFERROR(VLOOKUP($CB$17,Sheet1!BF6:BI6,3,0),0) -> 0 | CC23: =+IFERROR(VLOOKUP($CC$17,Sheet1!BJ6:BM6,3,0),0) -> 0 | CD23: =+IFERROR(VLOOKUP($CD$17,Sheet1!BN6:BQ6,3,0),0) -> 0 | CE23: 45 | CF23: =+IFERROR(VLOOKUP($CF$17,Sheet1!BV6:BY6,3,0),0) -> 0 | CG23: =Sheet1!E6 -> WOOD | CH23: =Sheet1!CX6 -> MD0100061 | CI23: =Sheet1!CY6 -> DRUM - 56 X 24 X 32 X 3 | CJ23: =Sheet1!CZ6 -> 500 | CK23: =Sheet1!BZ6 -> 15824 | CL23: =SUMPRODUCT($N$18:$CF$18,N23:CF23)+CK23 -> 379215 | CM23: =Sheet1!CB6 -> 0 | CN23: =CL23*CM23 -> 0 | CO23: 0.35 | CP23: =CL23*CO23 -> 132725.25 | CQ23: 0 | CR23: =CL23*CQ23 -> 0 | CS23: =CL23+CN23+CP23+CR23 -> 511940.25 | CT23: 0.02 | CU23: =CS23*CT23 -> 10238.805 | CV23: 0.01 | CW23: =CS23*CV23 -> 5119.4025 | CX23: =Sheet1!CM6 -> 0 | CY23: =CX23*CS23 -> 0
A24: =Sheet1!A4 -> ENQ-16527-25-26 | B24: 45809 | C24: =Sheet1!C4 -> FA0900036 | D24: =Sheet1!D4 -> 4 CORE X 50 SQ. MM. ALU/ARD - STRIP (XLPE) | E24: =CS24+CU24+CW24+CY24 -> 303622.63 | F24: =ROUNDUP(M37,0) -> 10792 | G24: =E24+F24 -> 314414.63 | H24: =Sheet1!CR4 -> 0.18 | I24: =G24*H24 -> 56594.633 | J24: =G24+I24 -> 371009.26 | K24: =Sheet1!CU4 -> 60 | L24: =Sheet1!CV4 -> KMS | M24: =J24*K24 -> 22260556 | N24: =+IFERROR(VLOOKUP($N$17,Sheet1!J4:L4,3,0),0) -> 540 | O24: =+IFERROR(VLOOKUP($O$17,Sheet1!J4:L4,3,0),0) -> 0 | P24: =+IFERROR(VLOOKUP($P$17,Sheet1!J4:M4,3,0),0) -> 0 | Q24: =+IFERROR(VLOOKUP($Q$17,Sheet1!J4:M4,3,0),0) -> 0 | R24: =+IFERROR(VLOOKUP($R$17,Sheet1!J4:M4,3,0),0) -> 0 | S24: =+IFERROR(VLOOKUP($S$17,Sheet1!J4:M4,3,0),0) -> 0 | T24: =+IFERROR(VLOOKUP($T$17,Sheet1!J4:M4,3,0),0) -> 0 | U24: =+IFERROR(VLOOKUP($U$17,Sheet1!J4:M4,3,0),0) -> 0 | V24: =+IFERROR(VLOOKUP($V$17,Sheet1!N4:Q4,3,0),0) -> 0 | W24: =+IFERROR(VLOOKUP($W$17,Sheet1!N4:Q4,3,0),0) -> 0 | X24: =+IFERROR(VLOOKUP($X$17,Sheet1!F4:I4,3,0),0) -> 0 | Y24: =+IFERROR(VLOOKUP($Y$17,Sheet1!F4:I4,3,0),0) -> 0 | Z24: =+IFERROR(VLOOKUP($Z$17,Sheet1!F4:I4,3,0),0) -> 0 | AA24: =+IFERROR(VLOOKUP($AA$17,Sheet1!F4:I4,3,0),0) -> 0 | AB24: =+IFERROR(VLOOKUP($AB$17,Sheet1!F4:I4,3,0),0) -> 0 | AC24: =+IFERROR(VLOOKUP($AC$17,Sheet1!F4:I4,3,0),0) -> 0 | AD24: =+IFERROR(VLOOKUP($AD$17,Sheet1!F4:I4,3,0),0) -> 0 | AE24: =+IFERROR(VLOOKUP($AE$17,Sheet1!F4:I4,3,0),0) -> 0 | AF24: =+IFERROR(VLOOKUP($AF$17,Sheet1!R4:U4,3,0),0) -> 0 | AG24: =+IFERROR(VLOOKUP($AG$17,Sheet1!R4:U4,3,0),0) -> 0 | AH24: =+IFERROR(VLOOKUP($AH$17,Sheet1!V4:Y4,3,0),0) -> 0 | AI24: 144 | AJ24: =+IFERROR(VLOOKUP($AJ$17,Sheet1!V4:Y4,3,0),0) -> 0 | AK24: =+IFERROR(VLOOKUP($AK$17,Sheet1!V4:Y4,3,0),0) -> 0 | AL24: =+IFERROR(VLOOKUP($AL$17,Sheet1!V4:Y4,3,0),0) -> 0 | AM24: =+IFERROR(VLOOKUP($AM$17,Sheet1!V4:Y4,3,0),0) -> 0 | AN24: =+IFERROR(VLOOKUP($AN$17,Sheet1!V4:Y4,3,0),0) -> 0 | AO24: =+IFERROR(VLOOKUP($AO$17,Sheet1!V4:Y4,3,0),0) -> 0 | AP24: =+IFERROR(VLOOKUP($AP$17,Sheet1!V4:Y4,3,0),0) -> 0 | AQ24: =+IFERROR(VLOOKUP($AQ$17,Sheet1!Z4:AB4,3,0),0) -> 0 | AR24: =+IFERROR(VLOOKUP($AR$17,Sheet1!AD4:AG4,3,0),0) -> 0 | AS24: =+IFERROR(VLOOKUP($AS$17,Sheet1!AD4:AG4,3,0),0) -> 0 | AT24: =+IFERROR(VLOOKUP($AT$17,Sheet1!AD4:AG4,3,0),0) -> 0 | AU24: =+IFERROR(VLOOKUP($AU$17,Sheet1!AD4:AG4,3,0),0) -> 0 | AV24: =+IFERROR(VLOOKUP($AV$17,Sheet1!AD4:AG4,3,0),0) -> 0 | AW24: =+IFERROR(VLOOKUP($AW$17,Sheet1!AD4:AG4,3,0),0) -> 0 | AX24: =+IFERROR(VLOOKUP($AX$17,Sheet1!AD4:AG4,3,0),0) -> 69 | AY24: =+IFERROR(VLOOKUP($AY$17,Sheet1!AD4:AG4,3,0),0) -> 0 | AZ24: =+IFERROR(VLOOKUP($AZ$17,Sheet1!AD4:AG4,3,0),0) -> 0 | BA24: =+IFERROR(VLOOKUP($BA$17,Sheet1!AH4:AK4,3,0),0) -> 0 | BB24: =+IFERROR(VLOOKUP($BB$17,Sheet1!AH4:AK4,3,0),0) -> 0 | BC24: =+IFERROR(VLOOKUP($BC$17,Sheet1!AH4:AK4,3,0),0) -> 0 | BD24: =+IFERROR(VLOOKUP($BD$17,Sheet1!AH4:AK4,3,0),0) -> 0 | BE24: =+IFERROR(VLOOKUP($BE$17,Sheet1!AH4:AK4,3,0),0) -> 0 | BF24: =+IFERROR(VLOOKUP($BF$17,Sheet1!AH4:AK4,3,0),0) -> 0 | BG24: 425 | BH24: =+IFERROR(VLOOKUP($BH$17,Sheet1!AH4:AK4,3,0),0) -> 0 | BI24: =+IFERROR(VLOOKUP($BI$17,Sheet1!AH4:AK4,3,0),0) -> 0 | BJ24: =+IFERROR(VLOOKUP($BJ$17,Sheet1!AH4:AK4,3,0),0) -> 0 | BK24: =+IFERROR(VLOOKUP($BK$17,Sheet1!AH4:AK4,3,0),0) -> 0 | BL24: =+IFERROR(VLOOKUP($BL$17,Sheet1!AL4:AO4,3,0),0) -> 0 | BM24: =+IFERROR(VLOOKUP($BM$17,Sheet1!AL4:AO4,3,0),0) -> 0 | BN24: =+IFERROR(VLOOKUP($BN$17,Sheet1!AL4:AO4,3,0),0) -> 0 | BO24: =+IFERROR(VLOOKUP($BO$17,Sheet1!AL4:AO4,3,0),0) -> 0 | BP24: =+IFERROR(VLOOKUP($BP$17,Sheet1!AL4:AO4,3,0),0) -> 0 | BQ24: =+IFERROR(VLOOKUP($BQ$17,Sheet1!AL4:AO4,3,0),0) -> 0 | BR24: =+IFERROR(VLOOKUP($BR$17,Sheet1!AL4:AO4,3,0),0) -> 0 | BS24: =+IFERROR(VLOOKUP($BS$17,Sheet1!AL4:AO4,3,0),0) -> 0 | BT24: 235 | BU24: =+IFERROR(VLOOKUP($BU$17,Sheet1!AL4:AO4,3,0),0) -> 0 | BV24: =+IFERROR(VLOOKUP($BV$17,Sheet1!AL4:AO4,3,0),0) -> 0 | BW24: =+IFERROR(VLOOKUP($BW$17,Sheet1!AL4:AO4,3,0),0) -> 0 | BX24: =+IFERROR(VLOOKUP($BX$17,Sheet1!AP4:AS4,3,0),0) -> 0 | BY24: =+IFERROR(VLOOKUP($BY$17,Sheet1!AT4:AW4,3,0),0) -> 0 | BZ24: =+IFERROR(VLOOKUP($BZ$17,Sheet1!AX4:BA4,3,0),0) -> 0 | CA24: =+IFERROR(VLOOKUP($CA$17,Sheet1!BB4:BE4,3,0),0) -> 0 | CB24: =+IFERROR(VLOOKUP($CB$17,Sheet1!BF4:BI4,3,0),0) -> 0 | CC24: =+IFERROR(VLOOKUP($CC$17,Sheet1!BJ4:BM4,3,0),0) -> 0 | CD24: =+IFERROR(VLOOKUP($CD$17,Sheet1!BN4:BQ4,3,0),0) -> 0 | CE24: 21 | CF24: =+IFERROR(VLOOKUP($CF$17,Sheet1!BV4:BY4,3,0),0) -> 0 | CG24: =Sheet1!E4 -> WOOD | CH24: =Sheet1!CX4 -> MD0100015 | CI24: =Sheet1!CY4 -> DRUM - 48 X 20 X 28 X 2.25 - RDSO | CJ24: =Sheet1!CZ4 -> 500 | CK24: =Sheet1!BZ4 -> 8874 | CL24: =SUMPRODUCT($N$18:$CF$18,N24:CF24)+CK24 -> 218355 | CM24: =Sheet1!CB4 -> 0 | CN24: =CL24*CM24 -> 0 | CO24: 0.35 | CP24: =CL24*CO24 -> 76424.25 | CQ24: 0 | CR24: =CL24*CQ24 -> 0 | CS24: =CL24+CN24+CP24+CR24 -> 294779.25 | CT24: 0.02 | CU24: =CS24*CT24 -> 5895.585 | CV24: 0.01 | CW24: =CS24*CV24 -> 2947.7925 | CX24: =Sheet1!CM4 -> 0 | CY24: =CX24*CS24 -> 0
A25: =Sheet1!A3 -> ENQ-16527-25-26 | B25: 45809 | C25: =Sheet1!C3 -> FA0900018 | D25: =Sheet1!D3 -> 4 CORE X 35 SQ. MM. AL/ARD - STRIP (XLPE) | E25: =CS25+CU25+CW25+CY25 -> 237497.4 | F25: =ROUNDUP(M38,0) -> 9250 | G25: =E25+F25 -> 246747.4 | H25: =Sheet1!CR3 -> 0.18 | I25: =G25*H25 -> 44414.532 | J25: =G25+I25 -> 291161.93 | K25: =Sheet1!CU3 -> 60 | L25: =Sheet1!CV3 -> KMS | M25: =J25*K25 -> 17469716 | N25: =+IFERROR(VLOOKUP($N$17,Sheet1!J3:L3,3,0),0) -> 378 | O25: =+IFERROR(VLOOKUP($O$17,Sheet1!J3:L3,3,0),0) -> 0 | P25: =+IFERROR(VLOOKUP($P$17,Sheet1!J3:M3,3,0),0) -> 0 | Q25: =+IFERROR(VLOOKUP($Q$17,Sheet1!J3:M3,3,0),0) -> 0 | R25: =+IFERROR(VLOOKUP($R$17,Sheet1!J3:M3,3,0),0) -> 0 | S25: =+IFERROR(VLOOKUP($S$17,Sheet1!J3:M3,3,0),0) -> 0 | T25: =+IFERROR(VLOOKUP($T$17,Sheet1!J3:M3,3,0),0) -> 0 | U25: =+IFERROR(VLOOKUP($U$17,Sheet1!J3:M3,3,0),0) -> 0 | V25: =+IFERROR(VLOOKUP($V$17,Sheet1!N3:Q3,3,0),0) -> 0 | W25: =+IFERROR(VLOOKUP($W$17,Sheet1!N3:Q3,3,0),0) -> 0 | X25: =+IFERROR(VLOOKUP($X$17,Sheet1!F3:I3,3,0),0) -> 0 | Y25: =+IFERROR(VLOOKUP($Y$17,Sheet1!F3:I3,3,0),0) -> 0 | Z25: =+IFERROR(VLOOKUP($Z$17,Sheet1!F3:I3,3,0),0) -> 0 | AA25: =+IFERROR(VLOOKUP($AA$17,Sheet1!F3:I3,3,0),0) -> 0 | AB25: =+IFERROR(VLOOKUP($AB$17,Sheet1!F3:I3,3,0),0) -> 0 | AC25: =+IFERROR(VLOOKUP($AC$17,Sheet1!F3:I3,3,0),0) -> 0 | AD25: =+IFERROR(VLOOKUP($AD$17,Sheet1!F3:I3,3,0),0) -> 0 | AE25: =+IFERROR(VLOOKUP($AE$17,Sheet1!F3:I3,3,0),0) -> 0 | AF25: =+IFERROR(VLOOKUP($AF$17,Sheet1!R3:U3,3,0),0) -> 0 | AG25: =+IFERROR(VLOOKUP($AG$17,Sheet1!R3:U3,3,0),0) -> 0 | AH25: =+IFERROR(VLOOKUP($AH$17,Sheet1!V3:Y3,3,0),0) -> 0 | AI25: 120 | AJ25: =+IFERROR(VLOOKUP($AJ$17,Sheet1!V3:Y3,3,0),0) -> 0 | AK25: =+IFERROR(VLOOKUP($AK$17,Sheet1!V3:Y3,3,0),0) -> 0 | AL25: =+IFERROR(VLOOKUP($AL$17,Sheet1!V3:Y3,3,0),0) -> 0 | AM25: =+IFERROR(VLOOKUP($AM$17,Sheet1!V3:Y3,3,0),0) -> 0 | AN25: =+IFERROR(VLOOKUP($AN$17,Sheet1!V3:Y3,3,0),0) -> 0 | AO25: =+IFERROR(VLOOKUP($AO$17,Sheet1!V3:Y3,3,0),0) -> 0 | AP25: =+IFERROR(VLOOKUP($AP$17,Sheet1!V3:Y3,3,0),0) -> 0 | AQ25: =+IFERROR(VLOOKUP($AQ$17,Sheet1!Z3:AB3,3,0),0) -> 0 | AR25: =+IFERROR(VLOOKUP($AR$17,Sheet1!AD3:AG3,3,0),0) -> 0 | AS25: =+IFERROR(VLOOKUP($AS$17,Sheet1!AD3:AG3,3,0),0) -> 0 | AT25: =+IFERROR(VLOOKUP($AT$17,Sheet1!AD3:AG3,3,0),0) -> 0 | AU25: =+IFERROR(VLOOKUP($AU$17,Sheet1!AD3:AG3,3,0),0) -> 0 | AV25: =+IFERROR(VLOOKUP($AV$17,Sheet1!AD3:AG3,3,0),0) -> 0 | AW25: =+IFERROR(VLOOKUP($AW$17,Sheet1!AD3:AG3,3,0),0) -> 0 | AX25: 54 | AY25: =+IFERROR(VLOOKUP($AY$17,Sheet1!AD3:AG3,3,0),0) -> 0 | AZ25: =+IFERROR(VLOOKUP($AZ$17,Sheet1!AD3:AG3,3,0),0) -> 0 | BA25: =+IFERROR(VLOOKUP($BA$17,Sheet1!AH3:AK3,3,0),0) -> 0 | BB25: =+IFERROR(VLOOKUP($BB$17,Sheet1!AH3:AK3,3,0),0) -> 0 | BC25: =+IFERROR(VLOOKUP($BC$17,Sheet1!AH3:AK3,3,0),0) -> 0 | BD25: =+IFERROR(VLOOKUP($BD$17,Sheet1!AH3:AK3,3,0),0) -> 0 | BE25: =+IFERROR(VLOOKUP($BE$17,Sheet1!AH3:AK3,3,0),0) -> 0 | BF25: =+IFERROR(VLOOKUP($BF$17,Sheet1!AH3:AK3,3,0),0) -> 0 | BG25: 428 | BH25: =+IFERROR(VLOOKUP($BH$17,Sheet1!AH3:AK3,3,0),0) -> 0 | BI25: =+IFERROR(VLOOKUP($BI$17,Sheet1!AH3:AK3,3,0),0) -> 0 | BJ25: =+IFERROR(VLOOKUP($BJ$17,Sheet1!AH3:AK3,3,0),0) -> 0 | BK25: =+IFERROR(VLOOKUP($BK$17,Sheet1!AH3:AK3,3,0),0) -> 0 | BL25: =+IFERROR(VLOOKUP($BL$17,Sheet1!AL3:AO3,3,0),0) -> 0 | BM25: =+IFERROR(VLOOKUP($BM$17,Sheet1!AL3:AO3,3,0),0) -> 0 | BN25: =+IFERROR(VLOOKUP($BN$17,Sheet1!AL3:AO3,3,0),0) -> 0 | BO25: =+IFERROR(VLOOKUP($BO$17,Sheet1!AL3:AO3,3,0),0) -> 0 | BP25: =+IFERROR(VLOOKUP($BP$17,Sheet1!AL3:AO3,3,0),0) -> 0 | BQ25: =+IFERROR(VLOOKUP($BQ$17,Sheet1!AL3:AO3,3,0),0) -> 0 | BR25: =+IFERROR(VLOOKUP($BR$17,Sheet1!AL3:AO3,3,0),0) -> 0 | BS25: =+IFERROR(VLOOKUP($BS$17,Sheet1!AL3:AO3,3,0),0) -> 0 | BT25: 201 | BU25: =+IFERROR(VLOOKUP($BU$17,Sheet1!AL3:AO3,3,0),0) -> 0 | BV25: =+IFERROR(VLOOKUP($BV$17,Sheet1!AL3:AO3,3,0),0) -> 0 | BW25: =+IFERROR(VLOOKUP($BW$17,Sheet1!AL3:AO3,3,0),0) -> 0 | BX25: =+IFERROR(VLOOKUP($BX$17,Sheet1!AP3:AS3,3,0),0) -> 0 | BY25: =+IFERROR(VLOOKUP($BY$17,Sheet1!AT3:AW3,3,0),0) -> 0 | BZ25: =+IFERROR(VLOOKUP($BZ$17,Sheet1!AX3:BA3,3,0),0) -> 0 | CA25: =+IFERROR(VLOOKUP($CA$17,Sheet1!BB3:BE3,3,0),0) -> 0 | CB25: =+IFERROR(VLOOKUP($CB$17,Sheet1!BF3:BI3,3,0),0) -> 0 | CC25: =+IFERROR(VLOOKUP($CC$17,Sheet1!BJ3:BM3,3,0),0) -> 0 | CD25: =+IFERROR(VLOOKUP($CD$17,Sheet1!BN3:BQ3,3,0),0) -> 0 | CE25: 18 | CF25: =+IFERROR(VLOOKUP($CF$17,Sheet1!BV3:BY3,3,0),0) -> 0 | CG25: =Sheet1!E3 -> WOOD | CH25: =Sheet1!CX3 -> MD0100015 | CI25: =Sheet1!CY3 -> DRUM - 48 X 20 X 28 X 2.25 - RDSO | CJ25: =Sheet1!CZ3 -> 500 | CK25: =Sheet1!BZ3 -> 8874 | CL25: =SUMPRODUCT($N$18:$CF$18,N25:CF25)+CK25 -> 170800 | CM25: =Sheet1!CB3 -> 0 | CN25: =CL25*CM25 -> 0 | CO25: 0.35 | CP25: =CL25*CO25 -> 59780 | CQ25: 0 | CR25: =CL25*CQ25 -> 0 | CS25: =CL25+CN25+CP25+CR25 -> 230580 | CT25: 0.02 | CU25: =CS25*CT25 -> 4611.6 | CV25: 0.01 | CW25: =CS25*CV25 -> 2305.8 | CX25: =Sheet1!CM3 -> 0 | CY25: =CX25*CS25 -> 0
A26: =Sheet1!A2 -> ENQ-16527-25-26 | B26: 45809 | C26: =Sheet1!C2 -> FA0900013 | D26: =Sheet1!D2 -> 4 CORE X 16 SQ. MM. ALU/ARD - STRIP (XLPE) | E26: =CS26+CU26+CW26+CY26 -> 134345.94 | F26: =ROUNDUP(M39,0) -> 6475 | G26: =E26+F26 -> 140820.94 | H26: =Sheet1!CR2 -> 0.18 | I26: =G26*H26 -> 25347.769 | J26: =G26+I26 -> 166168.71 | K26: =Sheet1!CU2 -> 100 | L26: =Sheet1!CV2 -> KMS | M26: =J26*K26 -> 16616871 | N26: =+IFERROR(VLOOKUP($N$17,Sheet1!J2:L2,3,0),0) -> 173 | O26: =+IFERROR(VLOOKUP($O$17,Sheet1!J2:L2,3,0),0) -> 0 | P26: =+IFERROR(VLOOKUP($P$17,Sheet1!J2:M2,3,0),0) -> 0 | Q26: =+IFERROR(VLOOKUP($Q$17,Sheet1!J2:M2,3,0),0) -> 0 | R26: =+IFERROR(VLOOKUP($R$17,Sheet1!J2:M2,3,0),0) -> 0 | S26: =+IFERROR(VLOOKUP($S$17,Sheet1!J2:M2,3,0),0) -> 0 | T26: =+IFERROR(VLOOKUP($T$17,Sheet1!J2:M2,3,0),0) -> 0 | U26: =+IFERROR(VLOOKUP($U$17,Sheet1!J2:M2,3,0),0) -> 0 | V26: =+IFERROR(VLOOKUP($V$17,Sheet1!N2:Q2,3,0),0) -> 0 | W26: =+IFERROR(VLOOKUP($W$17,Sheet1!N2:Q2,3,0),0) -> 0 | X26: =+IFERROR(VLOOKUP($X$17,Sheet1!F2:I2,3,0),0) -> 0 | Y26: =+IFERROR(VLOOKUP($Y$17,Sheet1!F2:I2,3,0),0) -> 0 | Z26: =+IFERROR(VLOOKUP($Z$17,Sheet1!F2:I2,3,0),0) -> 0 | AA26: =+IFERROR(VLOOKUP($AA$17,Sheet1!F2:I2,3,0),0) -> 0 | AB26: =+IFERROR(VLOOKUP($AB$17,Sheet1!F2:I2,3,0),0) -> 0 | AC26: =+IFERROR(VLOOKUP($AC$17,Sheet1!F2:I2,3,0),0) -> 0 | AD26: =+IFERROR(VLOOKUP($AD$17,Sheet1!F2:I2,3,0),0) -> 0 | AE26: =+IFERROR(VLOOKUP($AE$17,Sheet1!F2:I2,3,0),0) -> 0 | AF26: =+IFERROR(VLOOKUP($AF$17,Sheet1!R2:U2,3,0),0) -> 0 | AG26: =+IFERROR(VLOOKUP($AG$17,Sheet1!R2:U2,3,0),0) -> 0 | AH26: =+IFERROR(VLOOKUP($AH$17,Sheet1!V2:Y2,3,0),0) -> 0 | AI26: 70 | AJ26: =+IFERROR(VLOOKUP($AJ$17,Sheet1!V2:Y2,3,0),0) -> 0 | AK26: =+IFERROR(VLOOKUP($AK$17,Sheet1!V2:Y2,3,0),0) -> 0 | AL26: =+IFERROR(VLOOKUP($AL$17,Sheet1!V2:Y2,3,0),0) -> 0 | AM26: =+IFERROR(VLOOKUP($AM$17,Sheet1!V2:Y2,3,0),0) -> 0 | AN26: =+IFERROR(VLOOKUP($AN$17,Sheet1!V2:Y2,3,0),0) -> 0 | AO26: =+IFERROR(VLOOKUP($AO$17,Sheet1!V2:Y2,3,0),0) -> 0 | AP26: =+IFERROR(VLOOKUP($AP$17,Sheet1!V2:Y2,3,0),0) -> 0 | AQ26: =+IFERROR(VLOOKUP($AQ$17,Sheet1!Z2:AB2,3,0),0) -> 0 | AR26: =+IFERROR(VLOOKUP($AR$17,Sheet1!AD2:AG2,3,0),0) -> 0 | AS26: =+IFERROR(VLOOKUP($AS$17,Sheet1!AD2:AG2,3,0),0) -> 0 | AT26: =+IFERROR(VLOOKUP($AT$17,Sheet1!AD2:AG2,3,0),0) -> 0 | AU26: =+IFERROR(VLOOKUP($AU$17,Sheet1!AD2:AG2,3,0),0) -> 0 | AV26: =+IFERROR(VLOOKUP($AV$17,Sheet1!AD2:AG2,3,0),0) -> 0 | AW26: =+IFERROR(VLOOKUP($AW$17,Sheet1!AD2:AG2,3,0),0) -> 0 | AX26: 42 | AY26: =+IFERROR(VLOOKUP($AY$17,Sheet1!AD2:AG2,3,0),0) -> 0 | AZ26: =+IFERROR(VLOOKUP($AZ$17,Sheet1!AD2:AG2,3,0),0) -> 0 | BA26: =+IFERROR(VLOOKUP($BA$17,Sheet1!AH2:AK2,3,0),0) -> 0 | BB26: =+IFERROR(VLOOKUP($BB$17,Sheet1!AH2:AK2,3,0),0) -> 0 | BC26: =+IFERROR(VLOOKUP($BC$17,Sheet1!AH2:AK2,3,0),0) -> 0 | BD26: =+IFERROR(VLOOKUP($BD$17,Sheet1!AH2:AK2,3,0),0) -> 0 | BE26: =+IFERROR(VLOOKUP($BE$17,Sheet1!AH2:AK2,3,0),0) -> 0 | BF26: =+IFERROR(VLOOKUP($BF$17,Sheet1!AH2:AK2,3,0),0) -> 0 | BG26: 315 | BH26: =+IFERROR(VLOOKUP($BH$17,Sheet1!AH2:AK2,3,0),0) -> 0 | BI26: =+IFERROR(VLOOKUP($BI$17,Sheet1!AH2:AK2,3,0),0) -> 0 | BJ26: =+IFERROR(VLOOKUP($BJ$17,Sheet1!AH2:AK2,3,0),0) -> 0 | BK26: =+IFERROR(VLOOKUP($BK$17,Sheet1!AH2:AK2,3,0),0) -> 0 | BL26: =+IFERROR(VLOOKUP($BL$17,Sheet1!AL2:AO2,3,0),0) -> 0 | BM26: =+IFERROR(VLOOKUP($BM$17,Sheet1!AL2:AO2,3,0),0) -> 0 | BN26: =+IFERROR(VLOOKUP($BN$17,Sheet1!AL2:AO2,3,0),0) -> 0 | BO26: =+IFERROR(VLOOKUP($BO$17,Sheet1!AL2:AO2,3,0),0) -> 0 | BP26: =+IFERROR(VLOOKUP($BP$17,Sheet1!AL2:AO2,3,0),0) -> 0 | BQ26: =+IFERROR(VLOOKUP($BQ$17,Sheet1!AL2:AO2,3,0),0) -> 0 | BR26: =+IFERROR(VLOOKUP($BR$17,Sheet1!AL2:AO2,3,0),0) -> 0 | BS26: =+IFERROR(VLOOKUP($BS$17,Sheet1!AL2:AO2,3,0),0) -> 0 | BT26: 154 | BU26: =+IFERROR(VLOOKUP($BU$17,Sheet1!AL2:AO2,3,0),0) -> 0 | BV26: =+IFERROR(VLOOKUP($BV$17,Sheet1!AL2:AO2,3,0),0) -> 0 | BW26: =+IFERROR(VLOOKUP($BW$17,Sheet1!AL2:AO2,3,0),0) -> 0 | BX26: =+IFERROR(VLOOKUP($BX$17,Sheet1!AP2:AS2,3,0),0) -> 0 | BY26: =+IFERROR(VLOOKUP($BY$17,Sheet1!AT2:AW2,3,0),0) -> 0 | BZ26: =+IFERROR(VLOOKUP($BZ$17,Sheet1!AX2:BA2,3,0),0) -> 0 | CA26: =+IFERROR(VLOOKUP($CA$17,Sheet1!BB2:BE2,3,0),0) -> 0 | CB26: =+IFERROR(VLOOKUP($CB$17,Sheet1!BF2:BI2,3,0),0) -> 0 | CC26: =+IFERROR(VLOOKUP($CC$17,Sheet1!BJ2:BM2,3,0),0) -> 0 | CD26: =+IFERROR(VLOOKUP($CD$17,Sheet1!BN2:BQ2,3,0),0) -> 0 | CE26: 14 | CF26: =+IFERROR(VLOOKUP($CF$17,Sheet1!BV2:BY2,3,0),0) -> 0 | CG26: =Sheet1!E2 -> WOOD | CH26: =Sheet1!CX2 -> MD0100066 | CI26: =Sheet1!CY2 -> DRUM - 40 X 15 X 23 X 2 | CJ26: =Sheet1!CZ2 -> 500 | CK26: =Sheet1!BZ2 -> 5448 | CL26: =SUMPRODUCT($N$18:$CF$18,N26:CF26)+CK26 -> 96617 | CM26: =Sheet1!CB2 -> 0 | CN26: =CL26*CM26 -> 0 | CO26: 0.35 | CP26: =CL26*CO26 -> 33815.95 | CQ26: 0 | CR26: =CL26*CQ26 -> 0 | CS26: =CL26+CN26+CP26+CR26 -> 130432.95 | CT26: 0.02 | CU26: =CS26*CT26 -> 2608.659 | CV26: 0.01 | CW26: =CS26*CV26 -> 1304.3295 | CX26: =Sheet1!CM2 -> 0 | CY26: =CX26*CS26 -> 0
A27: =Sheet1!A5 -> ENQ-16527-25-26 | B27: 45809 | C27: =Sheet1!C5 -> FA0900042 | D27: =Sheet1!D5 -> 2 CORE X 10 SQ. MM. ALU/ARD - WIRE (XLPE) | E27: =CS27+CU27+CW27+CY27 -> 89866.624 | F27: =ROUNDUP(M40,0) -> 7400 | G27: =E27+F27 -> 97266.624 | H27: =Sheet1!CR5 -> 0.18 | I27: =G27*H27 -> 17507.992 | J27: =G27+I27 -> 114774.62 | K27: =Sheet1!CU5 -> 100 | L27: =Sheet1!CV5 -> KMS | M27: =J27*K27 -> 11477462 | N27: =+IFERROR(VLOOKUP($N$17,Sheet1!J5:L5,3,0),0) -> 54 | O27: =+IFERROR(VLOOKUP($O$17,Sheet1!J5:L5,3,0),0) -> 0 | P27: =+IFERROR(VLOOKUP($P$17,Sheet1!J5:M5,3,0),0) -> 0 | Q27: =+IFERROR(VLOOKUP($Q$17,Sheet1!J5:M5,3,0),0) -> 0 | R27: =+IFERROR(VLOOKUP($R$17,Sheet1!J5:M5,3,0),0) -> 0 | S27: =+IFERROR(VLOOKUP($S$17,Sheet1!J5:M5,3,0),0) -> 0 | T27: =+IFERROR(VLOOKUP($T$17,Sheet1!J5:M5,3,0),0) -> 0 | U27: =+IFERROR(VLOOKUP($U$17,Sheet1!J5:M5,3,0),0) -> 0 | V27: =+IFERROR(VLOOKUP($V$17,Sheet1!N5:Q5,3,0),0) -> 0 | W27: =+IFERROR(VLOOKUP($W$17,Sheet1!N5:Q5,3,0),0) -> 0 | X27: =+IFERROR(VLOOKUP($X$17,Sheet1!F5:I5,3,0),0) -> 0 | Y27: =+IFERROR(VLOOKUP($Y$17,Sheet1!F5:I5,3,0),0) -> 0 | Z27: =+IFERROR(VLOOKUP($Z$17,Sheet1!F5:I5,3,0),0) -> 0 | AA27: =+IFERROR(VLOOKUP($AA$17,Sheet1!F5:I5,3,0),0) -> 0 | AB27: =+IFERROR(VLOOKUP($AB$17,Sheet1!F5:I5,3,0),0) -> 0 | AC27: =+IFERROR(VLOOKUP($AC$17,Sheet1!F5:I5,3,0),0) -> 0 | AD27: =+IFERROR(VLOOKUP($AD$17,Sheet1!F5:I5,3,0),0) -> 0 | AE27: =+IFERROR(VLOOKUP($AE$17,Sheet1!F5:I5,3,0),0) -> 0 | AF27: =+IFERROR(VLOOKUP($AF$17,Sheet1!R5:U5,3,0),0) -> 0 | AG27: =+IFERROR(VLOOKUP($AG$17,Sheet1!R5:U5,3,0),0) -> 0 | AH27: =+IFERROR(VLOOKUP($AH$17,Sheet1!V5:Y5,3,0),0) -> 0 | AI27: 29 | AJ27: =+IFERROR(VLOOKUP($AJ$17,Sheet1!V5:Y5,3,0),0) -> 0 | AK27: =+IFERROR(VLOOKUP($AK$17,Sheet1!V5:Y5,3,0),0) -> 0 | AL27: =+IFERROR(VLOOKUP($AL$17,Sheet1!V5:Y5,3,0),0) -> 0 | AM27: =+IFERROR(VLOOKUP($AM$17,Sheet1!V5:Y5,3,0),0) -> 0 | AN27: =+IFERROR(VLOOKUP($AN$17,Sheet1!V5:Y5,3,0),0) -> 0 | AO27: =+IFERROR(VLOOKUP($AO$17,Sheet1!V5:Y5,3,0),0) -> 0 | AP27: =+IFERROR(VLOOKUP($AP$17,Sheet1!V5:Y5,3,0),0) -> 0 | AQ27: =+IFERROR(VLOOKUP($AQ$17,Sheet1!Z5:AB5,3,0),0) -> 0 | AR27: =+IFERROR(VLOOKUP($AR$17,Sheet1!AD5:AG5,3,0),0) -> 0 | AS27: =+IFERROR(VLOOKUP($AS$17,Sheet1!AD5:AG5,3,0),0) -> 0 | AT27: =+IFERROR(VLOOKUP($AT$17,Sheet1!AD5:AG5,3,0),0) -> 0 | AU27: =+IFERROR(VLOOKUP($AU$17,Sheet1!AD5:AG5,3,0),0) -> 0 | AV27: =+IFERROR(VLOOKUP($AV$17,Sheet1!AD5:AG5,3,0),0) -> 0 | AW27: =+IFERROR(VLOOKUP($AW$17,Sheet1!AD5:AG5,3,0),0) -> 0 | AX27: 78 | AY27: =+IFERROR(VLOOKUP($AY$17,Sheet1!AD5:AG5,3,0),0) -> 0 | AZ27: =+IFERROR(VLOOKUP($AZ$17,Sheet1!AD5:AG5,3,0),0) -> 0 | BA27: =+IFERROR(VLOOKUP($BA$17,Sheet1!AH5:AK5,3,0),0) -> 0 | BB27: =+IFERROR(VLOOKUP($BB$17,Sheet1!AH5:AK5,3,0),0) -> 0 | BC27: =+IFERROR(VLOOKUP($BC$17,Sheet1!AH5:AK5,3,0),0) -> 0 | BD27: =+IFERROR(VLOOKUP($BD$17,Sheet1!AH5:AK5,3,0),0) -> 0 | BE27: =+IFERROR(VLOOKUP($BE$17,Sheet1!AH5:AK5,3,0),0) -> 0 | BF27: =+IFERROR(VLOOKUP($BF$17,Sheet1!AH5:AK5,3,0),0) -> 0 | BG27: 357 | BH27: =+IFERROR(VLOOKUP($BH$17,Sheet1!AH5:AK5,3,0),0) -> 0 | BI27: =+IFERROR(VLOOKUP($BI$17,Sheet1!AH5:AK5,3,0),0) -> 0 | BJ27: =+IFERROR(VLOOKUP($BJ$17,Sheet1!AH5:AK5,3,0),0) -> 340 | BK27: =+IFERROR(VLOOKUP($BK$17,Sheet1!AH5:AK5,3,0),0) -> 0 | BL27: =+IFERROR(VLOOKUP($BL$17,Sheet1!AL5:AO5,3,0),0) -> 0 | BM27: =+IFERROR(VLOOKUP($BM$17,Sheet1!AL5:AO5,3,0),0) -> 0 | BN27: =+IFERROR(VLOOKUP($BN$17,Sheet1!AL5:AO5,3,0),0) -> 0 | BO27: =+IFERROR(VLOOKUP($BO$17,Sheet1!AL5:AO5,3,0),0) -> 0 | BP27: =+IFERROR(VLOOKUP($BP$17,Sheet1!AL5:AO5,3,0),0) -> 0 | BQ27: =+IFERROR(VLOOKUP($BQ$17,Sheet1!AL5:AO5,3,0),0) -> 0 | BR27: =+IFERROR(VLOOKUP($BR$17,Sheet1!AL5:AO5,3,0),0) -> 0 | BS27: =+IFERROR(VLOOKUP($BS$17,Sheet1!AL5:AO5,3,0),0) -> 0 | BT27: 134 | BU27: =+IFERROR(VLOOKUP($BU$17,Sheet1!AL5:AO5,3,0),0) -> 0 | BV27: =+IFERROR(VLOOKUP($BV$17,Sheet1!AL5:AO5,3,0),0) -> 0 | BW27: =+IFERROR(VLOOKUP($BW$17,Sheet1!AL5:AO5,3,0),0) -> 0 | BX27: =+IFERROR(VLOOKUP($BX$17,Sheet1!AP5:AS5,3,0),0) -> 0 | BY27: =+IFERROR(VLOOKUP($BY$17,Sheet1!AT5:AW5,3,0),0) -> 0 | BZ27: =+IFERROR(VLOOKUP($BZ$17,Sheet1!AX5:BA5,3,0),0) -> 0 | CA27: =+IFERROR(VLOOKUP($CA$17,Sheet1!BB5:BE5,3,0),0) -> 0 | CB27: =+IFERROR(VLOOKUP($CB$17,Sheet1!BF5:BI5,3,0),0) -> 0 | CC27: =+IFERROR(VLOOKUP($CC$17,Sheet1!BJ5:BM5,3,0),0) -> 0 | CD27: =+IFERROR(VLOOKUP($CD$17,Sheet1!BN5:BQ5,3,0),0) -> 0 | CE27: 13 | CF27: =+IFERROR(VLOOKUP($CF$17,Sheet1!BV5:BY5,3,0),0) -> 0 | CG27: =Sheet1!E5 -> WOOD | CH27: =Sheet1!CX5 -> MD0100075 | CI27: =Sheet1!CY5 -> DRUM - 42 X 15 X 23 X 2 | CJ27: =Sheet1!CZ5 -> 1000 | CK27: =Sheet1!BZ5 -> 4313 | CL27: =SUMPRODUCT($N$18:$CF$18,N27:CF27)+CK27 -> 64629 | CM27: =Sheet1!CB5 -> 0 | CN27: =CL27*CM27 -> 0 | CO27: 0.35 | CP27: =CL27*CO27 -> 22620.15 | CQ27: 0 | CR27: =CL27*CQ27 -> 0 | CS27: =CL27+CN27+CP27+CR27 -> 87249.15 | CT27: 0.02 | CU27: =CS27*CT27 -> 1744.983 | CV27: 0.01 | CW27: =CS27*CV27 -> 872.4915 | CX27: =Sheet1!CM5 -> 0 | CY27: =CX27*CS27 -> 0
M28: =SUM(M19:M27) -> 4.9535744e+08
E31: Order Quantity | F31: Stnd Length | G31: Truck type | H31: Fare of one truck | I31: No of Drum in one truck | J31: Total length in one Truck | K31: No of Truck | L31: Total Freight | M31: Freight per KM | AA31: CABLE WEIGHT KG/KM | AF31: DRUM WEIGHT | AH31: CABLE+DRUM WEIGHT | AI31: TRUCK/TRAILOR
D32: =D19 -> 3 CORE X 300 SQ. MM. AL/ARM - STRIP (XLPE) - 11 KV | E32: =K19 -> 111 | F32: =CJ19/1000 -> 0.5 | G32: 25 MT TRAILOR | H32: 135500 | I32: 5 | J32: =F32*I32 -> 2.5 | K32: =ROUNDUP((E32/J32),0) -> 45 | L32: =H32*K32 -> 6097500 | M32: =L32/E32 -> 54932.432 | N32: =CH19 -> SP0400141 | AA32: =SUM(N19:CE19) -> 7568 | AF32: 350 | AH32: =((AA32*F32)+AF32) -> 4134 | AI32: =AH32*I32 -> 20670
D33: =D20 -> 3 CORE X 70 SQ. MM. AL/ARM - STRIP (XLPE) - 11 KV | E33: =K20 -> 3 | F33: =CJ20/1000 -> 0.5 | G33: 25 MT TRAILOR | H33: 135500 | I33: 8 | J33: =F33*I33 -> 4 | K33: =ROUNDUP((E33/J33),0) -> 1 | L33: =H33*K33 -> 135500 | M33: =L33/E33 -> 45166.667 | N33: =CH20 -> SP0400118 | AA33: =SUM(N20:CE20) -> 3360 | AF33: 200 | AH33: =((AA33*F33)+AF33) -> 1880 | AI33: =AH33*I33 -> 15040
D34: =D21 -> 4 CORE X 400 SQ. MM. AL/ARD - STRIP (XLPE) | E34: =K21 -> 27 | F34: =CJ21/1000 -> 0.5 | G34: 16 MT | H34: 92500 | I34: 5 | J34: =F34*I34 -> 2.5 | K34: =ROUNDUP((E34/J34),0) -> 11 | L34: =H34*K34 -> 1017500 | M34: =L34/E34 -> 37685.185 | N34: =CH21 -> SP0400107 | AA34: =SUM(N21:CE21) -> 7420 | AF34: 320 | AH34: =((AA34*F34)+AF34) -> 4030 | AI34: =AH34*I34 -> 20150
D35: =D22 -> 4 CORE X 150 SQ. MM. AL/ARD - STRIP (XLPE) | E35: =K22 -> 8 | F35: =CJ22/1000 -> 0.5 | G35: 16 MT | H35: 92500 | I35: 6 | J35: =F35*I35 -> 3 | K35: =ROUNDUP((E35/J35),0) -> 3 | L35: =H35*K35 -> 277500 | M35: =L35/E35 -> 34687.5 | N35: =CH22 -> MD0100070 | AA35: =SUM(N22:CE22) -> 3443 | AF35: =300+80 -> 380 | AH35: =((AA35*F35)+AF35) -> 2101.5 | AI35: =AH35*I35 -> 12609
D36: =D23 -> 4 CORE X 95 SQ. MM. AL/ARD - STRIP (XLPE) | E36: =K23 -> 198 | F36: =CJ23/1000 -> 0.5 | G36: 16 MT | H36: 92500 | I36: 10 | J36: =F36*I36 -> 5 | K36: =ROUNDUP((E36/J36),0) -> 40 | L36: =H36*K36 -> 3700000 | M36: =L36/E36 -> 18686.869 | N36: =CH23 -> MD0100061 | AA36: =SUM(N23:CE23) -> 2242 | AF36: =190+45 -> 235 | AH36: =((AA36*F36)+AF36) -> 1356 | AI36: =AH36*I36 -> 13560
D37: =D24 -> 4 CORE X 50 SQ. MM. ALU/ARD - STRIP (XLPE) | E37: =K24 -> 60 | F37: =CJ24/1000 -> 0.5 | G37: 16 MT | H37: 92500 | I37: 18 | J37: =F37*I37 -> 9 | K37: =ROUNDUP((E37/J37),0) -> 7 | L37: =H37*K37 -> 647500 | M37: =L37/E37 -> 10791.667 | N37: =CH24 -> MD0100015 | AA37: =SUM(N24:CE24) -> 1434 | AF37: =125+30 -> 155 | AH37: =((AA37*F37)+AF37) -> 872 | AI37: =AH37*I37 -> 15696
D38: =D25 -> 4 CORE X 35 SQ. MM. AL/ARD - STRIP (XLPE) | E38: =K25 -> 60 | F38: =CJ25/1000 -> 0.5 | G38: 16 MT | H38: 92500 | I38: 20 | J38: =F38*I38 -> 10 | K38: =ROUNDUP((E38/J38),0) -> 6 | L38: =H38*K38 -> 555000 | M38: =L38/E38 -> 9250 | N38: =CH25 -> MD0100015 | AA38: =SUM(N25:CE25) -> 1199 | AF38: =125+30 -> 155 | AH38: =((AA38*F38)+AF38) -> 754.5 | AI38: =AH38*I38 -> 15090
D39: =D26 -> 4 CORE X 16 SQ. MM. ALU/ARD - STRIP (XLPE) | E39: =K26 -> 100 | F39: =CJ26/1000 -> 0.5 | G39: 16 MT | H39: 92500 | I39: 30 | J39: =F39*I39 -> 15 | K39: =ROUNDUP((E39/J39),0) -> 7 | L39: =H39*K39 -> 647500 | M39: =L39/E39 -> 6475 | N39: =CH26 -> MD0100066 | AA39: =SUM(N26:CE26) -> 768 | AF39: =75+25 -> 100 | AH39: =((AA39*F39)+AF39) -> 484 | AI39: =AH39*I39 -> 14520
D40: =D27 -> 2 CORE X 10 SQ. MM. ALU/ARD - WIRE (XLPE) | E40: =K27 -> 100 | F40: =CJ27/1000 -> 1 | G40: 16 MT | H40: 92500 | I40: 14 | J40: =F40*I40 -> 14 | K40: =ROUNDUP((E40/J40),0) -> 8 | L40: =H40*K40 -> 740000 | M40: =L40/E40 -> 7400 | N40: =CH27 -> MD0100075 | AA40: =SUM(N27:CE27) -> 1005 | AF40: =75+25 -> 100 | AH40: =((AA40*F40)+AF40) -> 1105 | AI40: =AH40*I40 -> 15470
A44: DOCKET NO. | B44: BASE DATE | C44: ITEM CODE | D44: PROPOSE ERP ITEM NAME | E44: EX-WORKS (PER MTR) | F44: FREIGHT PER MTR | G44: PRICE INCLUDING FREIGHT (PER MTR) | H44: GST % | I44: GST VALUE | J44: PRICE INCLUDING GST & FREIGHT (PER MTR) | K44: QTY | L44: Unit | M44: TOTAL PRICE OF FULL QTY (INCLUDING FRIGHT & GST)
A46: =A19 -> ENQ-16527-25-26 | B46: =B19 -> 45809 | C46: =C19 -> FA1300004 | D46: =D19 -> 3 CORE X 300 SQ. MM. AL/ARM - STRIP (XLPE) - 11 KV | E46: =ROUNDUP(E19/1000,2) -> 1666.86 | F46: =ROUNDUP(F19/1000,2) -> 54.94 | G46: =E46+F46 -> 1721.8 | H46: =H19 -> 0.18 | I46: =ROUND(G46*H46,2) -> 309.92 | J46: =ROUND(G46+I46,2) -> 2031.72 | K46: =K19*1000 -> 111000 | L46: MTR | M46: =J46*K46 -> 225520920
A47: =A20 -> ENQ-16527-25-26 | B47: =B20 -> 45809 | C47: =C20 -> FA1300006 | D47: =D20 -> 3 CORE X 70 SQ. MM. AL/ARM - STRIP (XLPE) - 11 KV | E47: =ROUNDUP(E20/1000,2) -> 694.92 | F47: =ROUNDUP(F20/1000,2) -> 45.17 | G47: =E47+F47 -> 740.09 | H47: =H20 -> 0.18 | I47: =ROUND(G47*H47,2) -> 133.22 | J47: =ROUND(G47+I47,2) -> 873.31 | K47: =K20*1000 -> 3000 | L47: MTR | M47: =J47*K47 -> 2619930
A48: =A21 -> ENQ-16527-25-26 | B48: =B21 -> 45809 | C48: =C21 -> FA1100036 | D48: =D21 -> 4 CORE X 400 SQ. MM. AL/ARD - STRIP (XLPE) | E48: =ROUNDUP(E21/1000,2) -> 1968.52 | F48: =ROUNDUP(F21/1000,2) -> 37.69 | G48: =E48+F48 -> 2006.21 | H48: =H21 -> 0.18 | I48: =ROUND(G48*H48,2) -> 361.12 | J48: =ROUND(G48+I48,2) -> 2367.33 | K48: =K21*1000 -> 27000 | L48: MTR | M48: =J48*K48 -> 63917910
A49: =A22 -> ENQ-16527-25-26 | B49: =B22 -> 45809 | C49: =C22 -> FA1100067 | D49: =D22 -> 4 CORE X 150 SQ. MM. AL/ARD - STRIP (XLPE) | E49: =ROUNDUP(E22/1000,2) -> 803.42 | F49: =ROUNDUP(F22/1000,2) -> 34.69 | G49: =E49+F49 -> 838.11 | H49: =H22 -> 0.18 | I49: =ROUND(G49*H49,2) -> 150.86 | J49: =ROUND(G49+I49,2) -> 988.97 | K49: =K22*1000 -> 8000 | L49: MTR | M49: =J49*K49 -> 7911760
A50: =A23 -> ENQ-16527-25-26 | B50: =B23 -> 45809 | C50: =C23 -> FA1100012 | D50: =D23 -> 4 CORE X 95 SQ. MM. AL/ARD - STRIP (XLPE) | E50: =ROUNDUP(E23/1000,2) -> 527.3 | F50: =ROUNDUP(F23/1000,2) -> 18.69 | G50: =E50+F50 -> 545.99 | H50: =H23 -> 0.18 | I50: =ROUND(G50*H50,2) -> 98.28 | J50: =ROUND(G50+I50,2) -> 644.27 | K50: =K23*1000 -> 198000 | L50: MTR | M50: =J50*K50 -> 127565460
A51: =A24 -> ENQ-16527-25-26 | B51: =B24 -> 45809 | C51: =C24 -> FA0900036 | D51: =D24 -> 4 CORE X 50 SQ. MM. ALU/ARD - STRIP (XLPE) | E51: =ROUNDUP(E24/1000,2) -> 303.63 | F51: =ROUNDUP(F24/1000,2) -> 10.8 | G51: =E51+F51 -> 314.43 | H51: =H24 -> 0.18 | I51: =ROUND(G51*H51,2) -> 56.6 | J51: =ROUND(G51+I51,2) -> 371.03 | K51: =K24*1000 -> 60000 | L51: MTR | M51: =J51*K51 -> 22261800
A52: =A25 -> ENQ-16527-25-26 | B52: =B25 -> 45809 | C52: =C25 -> FA0900018 | D52: =D25 -> 4 CORE X 35 SQ. MM. AL/ARD - STRIP (XLPE) | E52: =ROUNDUP(E25/1000,2) -> 237.5 | F52: =ROUNDUP(F25/1000,2) -> 9.25 | G52: =E52+F52 -> 246.75 | H52: =H25 -> 0.18 | I52: =ROUND(G52*H52,2) -> 44.42 | J52: =ROUND(G52+I52,2) -> 291.17 | K52: =K25*1000 -> 60000 | L52: MTR | M52: =J52*K52 -> 17470200
A53: =A26 -> ENQ-16527-25-26 | B53: =B26 -> 45809 | C53: =C26 -> FA0900013 | D53: =D26 -> 4 CORE X 16 SQ. MM. ALU/ARD - STRIP (XLPE) | E53: =ROUNDUP(E26/1000,2) -> 134.35 | F53: =ROUNDUP(F26/1000,2) -> 6.48 | G53: =E53+F53 -> 140.83 | H53: =H26 -> 0.18 | I53: =ROUND(G53*H53,2) -> 25.35 | J53: =ROUND(G53+I53,2) -> 166.18 | K53: =K26*1000 -> 100000 | L53: MTR | M53: =J53*K53 -> 16618000
A54: =A27 -> ENQ-16527-25-26 | B54: =B27 -> 45809 | C54: =C27 -> FA0900042 | D54: =D27 -> 2 CORE X 10 SQ. MM. ALU/ARD - WIRE (XLPE) | E54: =ROUNDUP(E27/1000,2) -> 89.87 | F54: =ROUNDUP(F27/1000,2) -> 7.4 | G54: =E54+F54 -> 97.27 | H54: =H27 -> 0.18 | I54: =ROUND(G54*H54,2) -> 17.51 | J54: =ROUND(G54+I54,2) -> 114.78 | K54: =K27*1000 -> 100000 | L54: MTR | M54: =J54*K54 -> 11478000
M55: =SUM(M46:M54) -> 495363980
M56: =M55-M28 -> 6542.9954

Sheet PV AUTO CALCULATION SHEET
A1: Base Date | B1: 45809
A2: PV FORMULA
A3: P = Po + AIF (Al–Alo) + XLFAL (CC–Cco) + SMIF (SMIF1–SMIF0) + FeF (FeF1–FeF0) + CCFAI (PVCc–PVCco) P = Po + AIF (Al–Alo) + XLFAL (CC–Cco) + FeF (FeF1–FeF0) + CCFAI (PVCc–PVCco)
AF7: VALUE ADDITION CALCULATION
A8: Item | B8: Calculation part | C8: Date of Inspection | D8: Applicable Date | J8: BASE DATE | P8: FACTORS | W8: Ex-Work Po | X8: PVC of al | Y8: PVC of Cu | Z8: PVC of XLPE | AA8: PVC OF PVC | AB8: PVC OF FE | AC8: PVC OF CU TAPE | AD8: PV/PKM | AE8: Billing Price/PKM
D9: Date | E9: Al | F9: Cu | G9: Cc | H9: PVCc | I9: Fe | J9: Date | K9: Alo | L9: Cuo | M9: Cco | N9: PVCco | O9: Feo | AF9: ='AUTO CALCULATION SHEET (2)'!N17 -> Alumimium | AG9: ='AUTO CALCULATION SHEET (2)'!AA17 -> Copper Tape - 0.04 mm | AH9: ='AUTO CALCULATION SHEET (2)'!AF17 -> Extruded semiconductive | AI9: ='AUTO CALCULATION SHEET (2)'!AH17 -> HT-XLPE | AJ9: ='AUTO CALCULATION SHEET (2)'!AI17 -> LT-XLPE | AK9: ='AUTO CALCULATION SHEET (2)'!AX17 -> PVC Type ST-2 | AL9: ='AUTO CALCULATION SHEET (2)'!BG17 -> Galvanised Steel Flat Strip | AM9: ='AUTO CALCULATION SHEET (2)'!BT17 -> PVC Type ST-2 | AN9: ='AUTO CALCULATION SHEET (2)'!BX17 -> FILLER | AO9: ='AUTO CALCULATION SHEET (2)'!CE17 -> RUBBERIZED COTTON TAPE | AP9: RMC | AQ9: Drum | AR9: RMC+Drum | AS9: VA | AT9: Groos VA% | AU9: Mfg % | AV9: Int % | AW9: Ins% | AX9: Net VA
P10: Alf | Q10: Cu | R10: XLFAL | S10: CCFAI | T10: CCFCu | U10: FeF | V10: Smif | AF10: 269 | AG10: 1021 | AH10: 174 | AI10: 149 | AJ10: 110 | AK10: 65 | AL10: 75 | AM10: 65 | AN10: 27 | AO10: 300
AF11: Kg/Km | AG11: Kg/Km | AH11: Kg/Km | AI11: Kg/Km | AJ11: Kg/Km | AK11: Kg/Km | AL11: Kg/Km | AM11: Kg/Km | AN11: Kg/Km | AO11: Kg/Km
A12: 3 CORE X 300 SQ. MM. AL/ARM - STRIP (XLPE) - 11 KV | C12: PROVISIONAL | D12: 45833 | E12: 260517.35 | F12: 909044.63 | G12: 183840 | H12: 157075 | I12: 81250 | J12: =$B$1 -> 45809 | K12: 255857 | L12: 920211 | M12: 183840 | N12: 157075 | O12: 81250 | P12: 2.635 | R12: 1.167 | S12: 3.161 | U12: 1.318 | V12: 0.11 | W12: ='AUTO CALCULATION SHEET (2)'!E46*1000 -> 1666860 | X12: =(P12*(E12-K12)) -> 12280.022 | Y12: =(Q12*(F12-L12)) -> 0 | Z12: =(R12*(G12-M12)) -> 0 | AA12: =(S12*(H12-N12)) -> 0 | AB12: =(U12*(I12-O12)) -> 0 | AC12: =V12*(F12-L12) -> -1228.3007 | AD12: =X12+Y12+Z12+AA12+AB12+AC12 -> 11051.722 | AE12: =+W12+AD12 -> 1677911.7 | AF12: ='AUTO CALCULATION SHEET (2)'!N19 -> 2430 | AG12: ='AUTO CALCULATION SHEET (2)'!AA19 -> 119 | AH12: ='AUTO CALCULATION SHEET (2)'!AF19 -> 328 | AI12: ='AUTO CALCULATION SHEET (2)'!AH19 -> 870 | AJ12: ='AUTO CALCULATION SHEET (2)'!AI19 -> 0 | AK12: ='AUTO CALCULATION SHEET (2)'!AX19 -> 300 | AL12: ='AUTO CALCULATION SHEET (2)'!BG19 -> 1150 | AM12: ='AUTO CALCULATION SHEET (2)'!BT19 -> 1012 | AN12: ='AUTO CALCULATION SHEET (2)'!BX19 -> 1310 | AO12: ='AUTO CALCULATION SHEET (2)'!CE19 -> 49 | AP12: =SUMPRODUCT(AF12:AO12,$AF$10:$AO$10) -> 1183471 | AQ12: ='AUTO CALCULATION SHEET (2)'!CK19 -> 60800 | AR12: =AP12+AQ12 -> 1244271 | AS12: =AE12-AR12 -> 433640.72 | AT12: =ROUND((AS12/AR12)*100,2) -> 34.85 | AU12: 0 | AV12: 0 | AW12: 0 | AX12: =AT12-AU12-AV12-AW12 -> 34.85
A13: 3 CORE X 70 SQ. MM. AL/ARM - STRIP (XLPE) - 11 KV | C13: PROVISIONAL | D13: 45833 | E13: 260517.35 | F13: 909044.63 | G13: 183840 | H13: 157075 | I13: 81250 | J13: =$B$1 -> 45809 | K13: 255857 | L13: 920211 | M13: 183840 | N13: 157075 | O13: 81250 | P13: 0.593 | R13: 0.679 | S13: 1.396 | U13: 0.849 | V13: 0.071 | W13: ='AUTO CALCULATION SHEET (2)'!E47*1000 -> 694920 | X13: =(P13*(E13-K13)) -> 2763.5876 | Y13: =(Q13*(F13-L13)) -> 0 | Z13: =(R13*(G13-M13)) -> 0 | AA13: =(S13*(H13-N13)) -> 0 | AB13: =(U13*(I13-O13)) -> 0 | AC13: =V13*(F13-L13) -> -792.81227 | AD13: =X13+Y13+Z13+AA13+AB13+AC13 -> 1970.7753 | AE13: =+W13+AD13 -> 696890.78 | AF13: ='AUTO CALCULATION SHEET (2)'!N20 -> 567 | AG13: ='AUTO CALCULATION SHEET (2)'!AA20 -> 78 | AH13: ='AUTO CALCULATION SHEET (2)'!AF20 -> 190 | AI13: ='AUTO CALCULATION SHEET (2)'!AH20 -> 510 | AJ13: ='AUTO CALCULATION SHEET (2)'!AI20 -> 0 | AK13: ='AUTO CALCULATION SHEET (2)'!AX20 -> 155 | AL13: ='AUTO CALCULATION SHEET (2)'!BG20 -> 775 | AM13: ='AUTO CALCULATION SHEET (2)'!BT20 -> 490 | AN13: ='AUTO CALCULATION SHEET (2)'!BX20 -> 560 | AO13: ='AUTO CALCULATION SHEET (2)'!CE20 -> 35 | AP13: =SUMPRODUCT(AF13:AO13,$AF$10:$AO$10) -> 466881 | AQ13: ='AUTO CALCULATION SHEET (2)'!CK20 -> 47500 | AR13: =AP13+AQ13 -> 514381 | AS13: =AE13-AR13 -> 182509.78 | AT13: =ROUND((AS13/AR13)*100,2) -> 35.48 | AU13: 0 | AV13: 0 | AW13: 0 | AX13: =AT13-AU13-AV13-AW13 -> 35.48
A14: 4 CORE X 400 SQ. MM. AL/ARD - STRIP (XLPE) | C14: PROVISIONAL | D14: 45833 | E14: 260517.35 | F14: 909044.63 | G14: 151416 | H14: 156075 | I14: 81250 | J14: =$B$1 -> 45809 | K14: 255857 | L14: 920211 | M14: 151416 | N14: 156075 | O14: 81250 | P14: 4.498 | R14: 0.714 | S14: 1.626 | U14: 1.231 | W14: ='AUTO CALCULATION SHEET (2)'!E48*1000 -> 1968520 | X14: =(P14*(E14-K14)) -> 20962.254 | Y14: =(Q14*(F14-L14)) -> 0 | Z14: =(R14*(G14-M14)) -> 0 | AA14: =(S14*(H14-N14)) -> 0 | AB14: =(U14*(I14-O14)) -> 0 | AC14: =V14*(F14-L14) -> 0 | AD14: =X14+Y14+Z14+AA14+AB14+AC14 -> 20962.254 | AE14: =+W14+AD14 -> 1989482.3 | AF14: ='AUTO CALCULATION SHEET (2)'!N21 -> 4320 | AG14: ='AUTO CALCULATION SHEET (2)'!AA21 -> 0 | AH14: ='AUTO CALCULATION SHEET (2)'!AF21 -> 0 | AI14: ='AUTO CALCULATION SHEET (2)'!AH21 -> 0 | AJ14: ='AUTO CALCULATION SHEET (2)'!AI21 -> 700 | AK14: ='AUTO CALCULATION SHEET (2)'!AX21 -> 271 | AL14: ='AUTO CALCULATION SHEET (2)'!BG21 -> 1102 | AM14: ='AUTO CALCULATION SHEET (2)'!BT21 -> 940 | AN14: ='AUTO CALCULATION SHEET (2)'!BX21 -> 0 | AO14: ='AUTO CALCULATION SHEET (2)'!CE21 -> 87 | AP14: =SUMPRODUCT(AF14:AO14,$AF$10:$AO$10) -> 1426545 | AQ14: ='AUTO CALCULATION SHEET (2)'!CK21 -> 57600 | AR14: =AP14+AQ14 -> 1484145 | AS14: =AE14-AR14 -> 505337.25 | AT14: =ROUND((AS14/AR14)*100,2) -> 34.05 | AU14: 0 | AV14: 0 | AW14: 0 | AX14: =AT14-AU14-AV14-AW14 -> 34.05
A15: 4 CORE X 150 SQ. MM. AL/ARD - STRIP (XLPE) | C15: PROVISIONAL | D15: 45833 | E15: 260517.35 | F15: 909044.63 | G15: 151416 | H15: 156075 | I15: 81250 | J15: =$B$1 -> 45809 | K15: 255857 | L15: 920211 | M15: 151416 | N15: 156075 | O15: 81250 | P15: 1.706 | R15: 0.344 | S15: 0.762 | U15: 0.79 | W15: ='AUTO CALCULATION SHEET (2)'!E49*1000 -> 803420 | X15: =(P15*(E15-K15)) -> 7950.5571 | Y15: =(Q15*(F15-L15)) -> 0 | Z15: =(R15*(G15-M15)) -> 0 | AA15: =(S15*(H15-N15)) -> 0 | AB15: =(U15*(I15-O15)) -> 0 | AC15: =V15*(F15-L15) -> 0 | AD15: =X15+Y15+Z15+AA15+AB15+AC15 -> 7950.5571 | AE15: =+W15+AD15 -> 811370.56 | AF15: ='AUTO CALCULATION SHEET (2)'!N22 -> 1620 | AG15: ='AUTO CALCULATION SHEET (2)'!AA22 -> 0 | AH15: ='AUTO CALCULATION SHEET (2)'!AF22 -> 0 | AI15: ='AUTO CALCULATION SHEET (2)'!AH22 -> 0 | AJ15: ='AUTO CALCULATION SHEET (2)'!AI22 -> 327 | AK15: ='AUTO CALCULATION SHEET (2)'!AX22 -> 145 | AL15: ='AUTO CALCULATION SHEET (2)'!BG22 -> 816 | AM15: ='AUTO CALCULATION SHEET (2)'!BT22 -> 503 | AN15: ='AUTO CALCULATION SHEET (2)'!BX22 -> 0 | AO15: ='AUTO CALCULATION SHEET (2)'!CE22 -> 32 | AP15: =SUMPRODUCT(AF15:AO15,$AF$10:$AO$10) -> 584670 | AQ15: ='AUTO CALCULATION SHEET (2)'!CK22 -> 20094 | AR15: =AP15+AQ15 -> 604764 | AS15: =AE15-AR15 -> 206606.56 | AT15: =ROUND((AS15/AR15)*100,2) -> 34.16 | AU15: 0 | AV15: 0 | AW15: 0 | AX15: =AT15-AU15-AV15-AW15 -> 34.16
A16: 4 CORE X 95 SQ. MM. AL/ARD - STRIP (XLPE) | C16: PROVISIONAL | D16: 45833 | E16: 260517.35 | F16: 909044.63 | G16: 151416 | H16: 156075 | I16: 81250 | J16: =$B$1 -> 45809 | K16: 255857 | L16: 920211 | M16: 151416 | N16: 156075 | O16: 81250 | P16: 1.095 | R16: 0.211 | S16: 0.523 | U16: 0.645 | W16: ='AUTO CALCULATION SHEET (2)'!E50*1000 -> 527300 | X16: =(P16*(E16-K16)) -> 5103.0833 | Y16: =(Q16*(F16-L16)) -> 0 | Z16: =(R16*(G16-M16)) -> 0 | AA16: =(S16*(H16-N16)) -> 0 | AB16: =(U16*(I16-O16)) -> 0 | AC16: =V16*(F16-L16) -> 0 | AD16: =X16+Y16+Z16+AA16+AB16+AC16 -> 5103.0833 | AE16: =+W16+AD16 -> 532403.08 | AF16: ='AUTO CALCULATION SHEET (2)'!N23 -> 1026 | AG16: ='AUTO CALCULATION SHEET (2)'!AA23 -> 0 | AH16: ='AUTO CALCULATION SHEET (2)'!AF23 -> 0 | AI16: ='AUTO CALCULATION SHEET (2)'!AH23 -> 0 | AJ16: ='AUTO CALCULATION SHEET (2)'!AI23 -> 200 | AK16: ='AUTO CALCULATION SHEET (2)'!AX23 -> 90 | AL16: ='AUTO CALCULATION SHEET (2)'!BG23 -> 577 | AM16: ='AUTO CALCULATION SHEET (2)'!BT23 -> 304 | AN16: ='AUTO CALCULATION SHEET (2)'!BX23 -> 0 | AO16: ='AUTO CALCULATION SHEET (2)'!CE23 -> 45 | AP16: =SUMPRODUCT(AF16:AO16,$AF$10:$AO$10) -> 380379 | AQ16: ='AUTO CALCULATION SHEET (2)'!CK23 -> 15824 | AR16: =AP16+AQ16 -> 396203 | AS16: =AE16-AR16 -> 136200.08 | AT16: =ROUND((AS16/AR16)*100,2) -> 34.38 | AU16: 0 | AV16: 0 | AW16: 0 | AX16: =AT16-AU16-AV16-AW16 -> 34.38
A17: 4 CORE X 50 SQ. MM. ALU/ARD - STRIP (XLPE) | C17: PROVISIONAL | D17: 45833 | E17: 260517.35 | F17: 909044.63 | G17: 151416 | H17: 156075 | I17: 81250 | J17: =$B$1 -> 45809 | K17: 255857 | L17: 920211 | M17: 151416 | N17: 156075 | O17: 81250 | P17: 0.547 | R17: 0.144 | S17: 0.394 | U17: 0.499 | W17: ='AUTO CALCULATION SHEET (2)'!E51*1000 -> 303630 | X17: =(P17*(E17-K17)) -> 2549.2115 | Y17: =(Q17*(F17-L17)) -> 0 | Z17: =(R17*(G17-M17)) -> 0 | AA17: =(S17*(H17-N17)) -> 0 | AB17: =(U17*(I17-O17)) -> 0 | AC17: =V17*(F17-L17) -> 0 | AD17: =X17+Y17+Z17+AA17+AB17+AC17 -> 2549.2115 | AE17: =+W17+AD17 -> 306179.21 | AF17: ='AUTO CALCULATION SHEET (2)'!N24 -> 540 | AG17: ='AUTO CALCULATION SHEET (2)'!AA24 -> 0 | AH17: ='AUTO CALCULATION SHEET (2)'!AF24 -> 0 | AI17: ='AUTO CALCULATION SHEET (2)'!AH24 -> 0 | AJ17: ='AUTO CALCULATION SHEET (2)'!AI24 -> 144 | AK17: ='AUTO CALCULATION SHEET (2)'!AX24 -> 69 | AL17: ='AUTO CALCULATION SHEET (2)'!BG24 -> 425 | AM17: ='AUTO CALCULATION SHEET (2)'!BT24 -> 235 | AN17: ='AUTO CALCULATION SHEET (2)'!BX24 -> 0 | AO17: ='AUTO CALCULATION SHEET (2)'!CE24 -> 21 | AP17: =SUMPRODUCT(AF17:AO17,$AF$10:$AO$10) -> 219035 | AQ17: ='AUTO CALCULATION SHEET (2)'!CK24 -> 8874 | AR17: =AP17+AQ17 -> 227909 | AS17: =AE17-AR17 -> 78270.211 | AT17: =ROUND((AS17/AR17)*100,2) -> 34.34 | AU17: 0 | AV17: 0 | AW17: 0 | AX17: =AT17-AU17-AV17-AW17 -> 34.34
A18: 4 CORE X 35 SQ. MM. AL/ARD - STRIP (XLPE) | C18: PROVISIONAL | D18: 45833 | E18: 260517.35 | F18: 909044.63 | G18: 151416 | H18: 156075 | I18: 81250 | J18: =$B$1 -> 45809 | K18: 255857 | L18: 920211 | M18: 151416 | N18: 156075 | O18: 81250 | P18: 0.404 | R18: 0.112 | S18: 0.319 | U18: 0.44 | W18: ='AUTO CALCULATION SHEET (2)'!E52*1000 -> 237500 | X18: =(P18*(E18-K18)) -> 1882.7814 | Y18: =(Q18*(F18-L18)) -> 0 | Z18: =(R18*(G18-M18)) -> 0 | AA18: =(S18*(H18-N18)) -> 0 | AB18: =(U18*(I18-O18)) -> 0 | AC18: =V18*(F18-L18) -> 0 | AD18: =X18+Y18+Z18+AA18+AB18+AC18 -> 1882.7814 | AE18: =+W18+AD18 -> 239382.78 | AF18: ='AUTO CALCULATION SHEET (2)'!N25 -> 378 | AG18: ='AUTO CALCULATION SHEET (2)'!AA25 -> 0 | AH18: ='AUTO CALCULATION SHEET (2)'!AF25 -> 0 | AI18: ='AUTO CALCULATION SHEET (2)'!AH25 -> 0 | AJ18: ='AUTO CALCULATION SHEET (2)'!AI25 -> 120 | AK18: ='AUTO CALCULATION SHEET (2)'!AX25 -> 54 | AL18: ='AUTO CALCULATION SHEET (2)'!BG25 -> 428 | AM18: ='AUTO CALCULATION SHEET (2)'!BT25 -> 201 | AN18: ='AUTO CALCULATION SHEET (2)'!BX25 -> 0 | AO18: ='AUTO CALCULATION SHEET (2)'!CE25 -> 18 | AP18: =SUMPRODUCT(AF18:AO18,$AF$10:$AO$10) -> 168957 | AQ18: ='AUTO CALCULATION SHEET (2)'!CK25 -> 8874 | AR18: =AP18+AQ18 -> 177831 | AS18: =AE18-AR18 -> 61551.781 | AT18: =ROUND((AS18/AR18)*100,2) -> 34.61 | AU18: 0 | AV18: 0 | AW18: 0 | AX18: =AT18-AU18-AV18-AW18 -> 34.61
A19: 4 CORE X 16 SQ. MM. ALU/ARD - STRIP (XLPE) | C19: PROVISIONAL | D19: 45833 | E19: 260517.35 | F19: 909044.63 | G19: 151416 | H19: 156075 | I19: 81250 | J19: =$B$1 -> 45809 | K19: 255857 | L19: 920211 | M19: 151416 | N19: 156075 | O19: 81250 | P19: 0.183 | R19: 0.063 | S19: 0.279 | U19: 0.323 | W19: ='AUTO CALCULATION SHEET (2)'!E53*1000 -> 134350 | X19: =(P19*(E19-K19)) -> 852.84405 | Y19: =(Q19*(F19-L19)) -> 0 | Z19: =(R19*(G19-M19)) -> 0 | AA19: =(S19*(H19-N19)) -> 0 | AB19: =(U19*(I19-O19)) -> 0 | AC19: =V19*(F19-L19) -> 0 | AD19: =X19+Y19+Z19+AA19+AB19+AC19 -> 852.84405 | AE19: =+W19+AD19 -> 135202.84 | AF19: ='AUTO CALCULATION SHEET (2)'!N26 -> 173 | AG19: ='AUTO CALCULATION SHEET (2)'!AA26 -> 0 | AH19: ='AUTO CALCULATION SHEET (2)'!AF26 -> 0 | AI19: ='AUTO CALCULATION SHEET (2)'!AH26 -> 0 | AJ19: ='AUTO CALCULATION SHEET (2)'!AI26 -> 70 | AK19: ='AUTO CALCULATION SHEET (2)'!AX26 -> 42 | AL19: ='AUTO CALCULATION SHEET (2)'!BG26 -> 315 | AM19: ='AUTO CALCULATION SHEET (2)'!BT26 -> 154 | AN19: ='AUTO CALCULATION SHEET (2)'!BX26 -> 0 | AO19: ='AUTO CALCULATION SHEET (2)'!CE26 -> 14 | AP19: =SUMPRODUCT(AF19:AO19,$AF$10:$AO$10) -> 94802 | AQ19: ='AUTO CALCULATION SHEET (2)'!CK26 -> 5448 | AR19: =AP19+AQ19 -> 100250 | AS19: =AE19-AR19 -> 34952.844 | AT19: =ROUND((AS19/AR19)*100,2) -> 34.87 | AU19: 0 | AV19: 0 | AW19: 0 | AX19: =AT19-AU19-AV19-AW19 -> 34.87
A20: 2 CORE X 10 SQ. MM. ALU/ARD - WIRE (XLPE) | C20: PROVISIONAL | D20: 45833 | E20: 260517.35 | F20: 909044.63 | G20: 151416 | H20: 156075 | I20: 80250 | J20: =$B$1 -> 45809 | K20: 255857 | L20: 920211 | M20: 151416 | N20: 156075 | O20: 80250 | P20: 0.053 | R20: 0.025 | S20: 0.28 | U20: 0.392 | W20: ='AUTO CALCULATION SHEET (2)'!E54*1000 -> 89870 | X20: =(P20*(E20-K20)) -> 246.99855 | Y20: =(Q20*(F20-L20)) -> 0 | Z20: =(R20*(G20-M20)) -> 0 | AA20: =(S20*(H20-N20)) -> 0 | AB20: =(U20*(I20-O20)) -> 0 | AC20: =V20*(F20-L20) -> 0 | AD20: =X20+Y20+Z20+AA20+AB20+AC20 -> 246.99855 | AE20: =+W20+AD20 -> 90116.999 | AF20: ='AUTO CALCULATION SHEET (2)'!N27 -> 54 | AG20: ='AUTO CALCULATION SHEET (2)'!AA27 -> 0 | AH20: ='AUTO CALCULATION SHEET (2)'!AF27 -> 0 | AI20: ='AUTO CALCULATION SHEET (2)'!AH27 -> 0 | AJ20: ='AUTO CALCULATION SHEET (2)'!AI27 -> 29 | AK20: ='AUTO CALCULATION SHEET (2)'!AX27 -> 78 | AL20: ='AUTO CALCULATION SHEET (2)'!BG27 -> 357 | AM20: ='AUTO CALCULATION SHEET (2)'!BT27 -> 134 | AN20: ='AUTO CALCULATION SHEET (2)'!BX27 -> 0 | AO20: ='AUTO CALCULATION SHEET (2)'!CE27 -> 13 | AP20: =SUMPRODUCT(AF20:AO20,$AF$10:$AO$10) -> 62171 | AQ20: ='AUTO CALCULATION SHEET (2)'!CK27 -> 4313 | AR20: =AP20+AQ20 -> 66484 | AS20: =AE20-AR20 -> 23632.999 | AT20: =ROUND((AS20/AR20)*100,2) -> 35.55 | AU20: 0 | AV20: 0 | AW20: 0 | AX20: =AT20-AU20-AV20-AW20 -> 35.55

Sheet terms
A1: The quoted prices are on Firm inclusive of packing and forwading but exclusive of GST Statutory levies.
A2: The quoted prices are on VARIABLE basis with PV base Date: DD/MM/YYYY as per "IEEMA", inclusive of packing and forwading but exclusive of GST Statutory levies.
A4: The above prices are quoted on Ex-works basis, where freight will be charged extra.
A5: The above prices are quoted on FOR Destination basis, where freight is included, refer Price offer.
A6: The above prices are quoted on Ex-works+Freight basis.
A8: 20% Advance and Balance against PI (Proforma Invoice) prior to dispatch
A9: 100% against "90 days" LC, where 90 days usance interest will be borne by LPIPL
A10: 100% against "120 days" LC, where 120 days usance interest will be borne by LPIPL
A11: 100% against "45 days" LC, where 45 days usance interest will be borne by LPIPL
A12: 100% against "60 days" LC, where 60 days usance interest will be borne by LPIPL
A13: 100% against "30 days" LC, where 30 days usance interest will be borne by LPIPL
A14: 100% against 60 days PDC from the date of MRC/MRN
... A27: Negotiable
