Workbook

Sheet Sheet1
A1: DOCKET NO. | B1: Base Date | C1: ITEM CODE | D1: PROPOSE ERP ITEM NAME | E1: Propose Drum Type | F1: Insulation Screening(Metallic) | G1: RM Rate(Insulation Screening(Metallic)) | H1: Weight (Insulation Screening (Metallic)) | I1: Cost Insulation Screening(Metallic) | J1: Conductor | K1: RM Rate(Conductor) | L1: Weight(Conductor) | M1: Cost(Conductor) | N1: AL ALLOY | O1: RM Rate(AL Alloy) | P1: Weight(Al Alloy) | Q1: Cost(AL Alloy) | R1: Insulation Screening(Non-Metallic) | S1: RM Rate(Insulation Screening(Non-Metallic)) | T1: Weight(Insulation Screening(Non-Metallic) | U1: Cost(Insulation Screening(Non-Metallic) | V1: Insulation | W1: RM Rate(Insulation) | X1: Weight(Insulation) | Y1: Cost(Insulation) | Z1: Poly Tape | AA1: RM Rate(Poly Tape) | AB1: Weight(Poly Tape) | AC1: Cost(Poly Tape) | AD1: Inner Sheath | AE1: RM Rate(Inner Sheath) | AF1: Weight(Inner Sheath) | AG1: Cost(Inner Sheath) | AH1: Armouring | AI1: RM Rate(Armouring) | AJ1: Weight(Armouring) | AK1: Cost(Armouring) | AL1: Outer Sheath | AM1: RM Rate(Outer Sheath) | AN1: Weight(Outer Sheath) | AO1: Cost(Outer Sheath) | AP1: Filler | AQ1: RM Rate(Filler) | AR1: Weight(Filler) | AS1: Cost(Filler) | AT1: Grease | AU1: RM Rate(Grease) | AV1: Weight(Grease) | AW1: Cost(Grease) | AX1: Water Swellable Tape | AY1: RM Rate(Water Swellable Tape) | AZ1: Weight(Water Swellable Tape) | BA1: Cost(Water Swellable Tape) | BB1: Semi Conducting Water Swellable Tape | BC1: RM Rate(Semi Conducting Water Swellable Tape) | BD1: Weight(Semi Conducting Water Swellable Tape) | BE1: Cost(Semi Conducting Water Swellable Tape) | BF1: Semicon Tape | BG1: RM Rate(Semicon Tape) | BH1: Weight(Semicon Tape) | BI1: Cost(Semicon Tape) | BJ1: Glass Fiber Tape | BK1: RM Rate(Glass Fiber Tape) | BL1: Weight(Glass Fiber Tape) | BM1: Cost(Glass Fiber Tape) | BN1: Copper Wire 0.8MM | BO1: RM Rate(Copper Wire 0.8MM) | BP1: Weight(Copper Wire 0.8MM) | BQ1: Cost(Copper Wire 0.8MM) | BR1: Rubberized Cotton Tape | BS1: RM Rate(Rubberized Cotton Tape) | BT1: Weight(Rubberized Cotton Tape) | BU1: Cost(Rubberized Cotton Tape) | BV1: Water Tight Compound | BW1: RM Rate(Water Tight Compound) | BX1: Weight(Water Tight Compound) | BY1: Cost(Water Tight Compound) | BZ1: Drum Cost Per KM | CA1: Total RM Cost | CB1: FIRM % | CC1: Firm Value | CD1: MFG% | CE1: MFG Value | CF1: PROF% | CG1: Profit Value | CH1: 1st EX-Works | CI1: Intt % | CJ1: Intt Value | CK1: insp% | CL1: Insp Value | CM1: TTR CHARGES% | CN1: TTR Value | CO1: EX-Works Per KM | CP1: Freight Per KM | CQ1: Price Including Freight Per KM | CR1: GST % | CS1: GST Value | CT1: Price Including GST & Freight Per KM | CU1: QTY | CV1: Unit | CW1: Total Price Of Full QTY(Including Freight&GST) | CX1: PARTY LENGTH (IF STANDER LENGTH NOT MATCH WITH PAR | CY1: DRUM CODE | CZ1: DRUM SIZE (FxbXtx Ft)
A2: ENQ-18774-25-26 | C2: FA0700001 | D2: 1 CORE X 120 SQ. MM. AL/ARD (XLPE) | E2: STEEL | H2: 0 | J2: Alumimium | L2: 324 | P2: 0 | T2: 0 | V2: LT-XLPE | X2: 75 | AB2: 0 | AF2: 0 | AH2: Aluminium Round Wire | AJ2: 157 | AL2: FRLSH PVC Type ST-2 | AN2: 165 | AR2: 0 | AV2: 0 | AZ2: 0 | BD2: 0 | BH2: 0 | BL2: 0 | BP2: 0 | BR2: RUBBERIZED COTTON TAPE | BT2: 0 | BX2: 0 | CR2: 0.18 | CU2: 10 | CV2: KMS
A3: ENQ-18774-25-26 | C3: FA0700001 | D3: 1 CORE X 120 SQ. MM. AL/ARD (XLPE) | E3: STEEL | H3: 0 | J3: Alumimium | L3: 324 | P3: 0 | T3: 0 | V3: LT-XLPE | X3: 75 | AB3: 0 | AF3: 0 | AH3: Aluminium Round Wire | AJ3: 157 | AL3: FRLSH PVC Type ST-2 | AN3: 165 | AR3: 0 | AV3: 0 | AZ3: 0 | BD3: 0 | BH3: 0 | BL3: 0 | BP3: 0 | BR3: RUBBERIZED COTTON TAPE | BT3: 0 | BX3: 0 | CR3: 0.18 | CU3: 14 | CV3: KMS | CX3: 500
A4: ENQ-18774-25-26 | C4: FA0700002 | D4: 1 CORE X 630 SQ. MM. AL/ARD (XLPE) | E4: STEEL | H4: 0 | J4: Alumimium | L4: 1701 | P4: 0 | T4: 0 | V4: LT-XLPE | X4: 295 | AB4: 0 | AF4: 0 | AH4: Aluminium Round Wire | AJ4: 431 | AL4: FRLSH PVC Type ST-2 | AN4: 443 | AR4: 0 | AV4: 0 | AZ4: 0 | BD4: 0 | BH4: 0 | BL4: 0 | BP4: 0 | BR4: RUBBERIZED COTTON TAPE | BT4: 0 | BX4: 0 | CR4: 0.18 | CU4: 10 | CV4: KMS | CX4: 500
A5: ENQ-18774-25-26 | C5: FA0700008 | D5: 1 CORE X 300 SQ. MM. AL/ARD. (XLPE) | E5: STEEL | H5: 0 | J5: Alumimium | L5: 810 | P5: 0 | T5: 0 | V5: LT-XLPE | X5: 154 | AB5: 0 | AF5: 0 | AH5: Aluminium Round Wire | AJ5: 238 | AL5: FRLSH PVC Type ST-2 | AN5: 259 | AR5: 0 | AV5: 0 | AZ5: 0 | BD5: 0 | BH5: 0 | BL5: 0 | BP5: 0 | BR5: RUBBERIZED COTTON TAPE | BT5: 0 | BX5: 0 | CR5: 0.18 | CU5: 12 | CV5: KMS | CX5: 500
A6: ENQ-18774-25-26 | C6: FA0900036 | D6: 4 CORE X 50 SQ. MM. ALU/ARD - STRIP (XLPE) | E6: WOOD | H6: 0 | J6: Alumimium | L6: 540 | P6: 0 | T6: 0 | V6: LT-XLPE | X6: 128 | AB6: 0 | AD6: PVC Type ST-2 | AF6: 58 | AH6: Galvanised Steel Flat Strip | AJ6: 425 | AL6: PVC Type ST-2 | AN6: 226 | AR6: 0 | AV6: 0 | AZ6: 0 | BD6: 0 | BH6: 0 | BL6: 0 | BP6: 0 | BR6: RUBBERIZED COTTON TAPE | BT6: 0 | BX6: 0 | BZ6: 8874 | CA6: 8874 | CH6: 8874 | CO6: 8874 | CQ6: 8874 | CR6: 0.18 | CS6: 1597.32 | CT6: 10471.32 | CU6: 140 | CV6: KMS | CW6: 1465985 | CX6: 500 | CY6: MD0100015 | CZ6: DRUM - 48 X 20 X 28 X 2.25 - RDSO
A7: ENQ-18774-25-26 | C7: FA1100012 | D7: 4 CORE X 95 SQ. MM. AL/ARD - STRIP (XLPE) | E7: WOOD | H7: 0 | J7: Alumimium | L7: 1026 | P7: 0 | T7: 0 | V7: LT-XLPE | X7: 187 | AB7: 0 | AD7: PVC Type ST-2 | AF7: 93 | AH7: Galvanised Steel Flat Strip | AJ7: 611 | AL7: PVC Type ST-2 | AN7: 348 | AR7: 0 | AV7: 0 | AZ7: 0 | BD7: 0 | BH7: 0 | BL7: 0 | BP7: 0 | BR7: RUBBERIZED COTTON TAPE | BT7: 0 | BX7: 0 | BZ7: 15824 | CA7: 15824 | CH7: 15824 | CO7: 15824 | CQ7: 15824 | CR7: 0.18 | CS7: 2848.32 | CT7: 18672.32 | CU7: 600 | CV7: KMS | CW7: 11203392 | CX7: 500 | CY7: MD0100061 | CZ7: DRUM - 56 X 24 X 32 X 3
A8: ENQ-18774-25-26 | C8: FA1100025 | D8: 4 CORE X 300 SQ. MM. AL/ARD - STRIP (XLPE) | E8: STEEL | H8: 0 | J8: Alumimium | L8: 3240 | P8: 0 | T8: 0 | V8: LT-XLPE | X8: 518 | AB8: 0 | AD8: PVC Type ST-2 | AF8: 271 | AH8: Galvanised Steel Flat Strip | AJ8: 1070 | AL8: PVC Type ST-2 | AN8: 767 | AR8: 0 | AV8: 0 | AZ8: 0 | BD8: 0 | BH8: 0 | BL8: 0 | BP8: 0 | BR8: RUBBERIZED COTTON TAPE | BT8: 0 | BX8: 0 | CR8: 0.18 | CU8: 50 | CV8: KMS | CX8: 500
A9: ENQ-18774-25-26 | C9: FA1100067 | D9: 4 CORE X 150 SQ. MM. AL/ARD - STRIP (XLPE) | H9: 0 | L9: 1620 | P9: 0 | T9: 0 | X9: 297 | AB9: 0 | AF9: 138 | AJ9: 777 | AN9: 479 | AR9: 0 | AV9: 0 | AZ9: 0 | BD9: 0 | BH9: 0 | BL9: 0 | BP9: 0 | BT9: 0 | BX9: 0 | CR9: 0.18 | CU9: 100 | CV9: KMS | CX9: 500

Sheet AUTO CALCULATION SHEET (2)
A2: Noida Power Company Ltd.
A4: TENDER SPECIFICATION NO () | B4: NPCL/FY25-26/LTCAB/060
A5: TENDER DESCRIPTION () | B5: TENDER NOTIFICATION FOR TWO YEAR RATE CONTRACT OF SUPPLY OF LT ABC & LT CABLES LOT 2
A6: Last Date & Time of Submission () | B6: 18.03.2026 (up to 15:00 hours) OPENING ON '18.03.2026 up to 15:00 Hours
A7: REVERSE AUCTION | B7: Purchaser reserves the right to use Reverse Auction through SAP-SRM as an optional tool as an integral part of the entire tendering process. All techno-commercially qualified bidders shall participate in this event.
A8: Price () | B8: Prices are As per latest IEEMA Price Variation Clause. The prices shall variable be as per Latest IEEMA Price Variation formula as mentioned below; P=Po+AIF(Al-Alo)+XLFAL(Cc-Cco)+CCFAl(PVCc-PVCco)+FeF(Fe-Feo) All #0# denoted input prices in the formula (Al0, CC0, PVCc0, Fe0, etc.) shall be as per IEEMA Circulars of January 2026 (Published in February 2026). The prices shall variable be as per Latest IEEMA Price Variation formula as mentioned below; Formula for LV Aerial Bunch Cables P = P0 + Alph * n* (Al-Al0) + Alm(Al-Al0) + Alsl(Al-Al0) + Aln(Al-Al0) + CCFAlph *n* (CC-Cco)+CCFAlm(CC- Cco)+CCFAlsl (CC-Cco) + CCFAln(CC-Cco) This price shall be as per IEEMA Circulars of January 2026 (Published in February 2026).
A9: Validity () | B9: Bids shall remain valid for 120 days from the due date of submission of the Bid & subsequent corrigendum / amendment / extension of due date of submission.
A10: Delivery Period () | B10: 60 Days from the date of issuance of LOI / Order; however, firm delivery dates will be mentioned in the LOI / Order.
A11: Payment Terms () | B11: 15% Basic value of Release Order payment shall be paid as interest free advance against submission of Advance Bank Guarantee (ABG) of a nationalized/scheduled bank(s) located at State Capital/Delhi NCR, payable at Delhi/Noida / Corporate Guarantee as may be acceptable to the NPCL, for the equal amount valid up to the PO supply completion period plus 3 months claim period. In case of delay, the BG shall be extended suitably by the bidder. Bidder can request to submit Corporate guarantee in place of ABG, Same request can be considered with discretion of NPCL management only. 80% payment shall be released on pro-rata basic within 45 days from the receipt of material at NPCL site with complete set of documents as mentioned in order. Your invoices complete in all respect along with all required documents should reach our office within 3 days. Any delay in submission of any of these documents will be to your account. It may please be noted that for payment purposes the date of receipt of documents will be considered on the basis of the date of receipt of last document, in case partial documents were received earlier. Balance 5% payment shall be released against submission of the Performance Bank Guarantee (PBG) of 5% of PO/Contract value valid till 12 months from the date of commissioning or 18 months from the date of dispatch, whichever is earlier Plus 3 months towards the Claim Period.
A12: Standard length () | B12: 1cx120 = 500mtr+/-2% 3cx120+120+95 = 500mtr+/-2% The cable shall be supplied in continuous standard length of 500 running meters with +2% to tolerance
A13: Packing () | B13: 1cx120 = Good Quality Wood 3cx120+120+95 = the cable shall be supplied on suitable sized wooden non-returnable drum of robust construction for each length of cables as per IS 10418. The cable shall be wound on non-returnable wooden drum of good quality, heavy standard construction conforming to IS:10418:1982
A14: Technical Specification
N18: Conductor | V18: AL ALLOY | X18: Insulation Screening (Metallic) | AF18: Insulation Screening (Non-Metallic) | AH18: Insulation | AQ18: POLY TAPE | AR18: Inner Sheath | BA18: Armouring | BL18: Outer Sheath | BX18: FILLER | BY18: GREASE | BZ18: Water swellable Tape | CA18: Semi conducting Water Swellable tape | CB18: SEMICON TAPE | CC18: GLASS FIBER TAPE | CD18: COPPER WIRE 0.8 MM | CE18: RUBBERIZED COTTON TAPE | CF18: Water Tight Compound | CG18: DRUM TYPE | CK18: DRUM COST PER KM | CL18: TOTAL RM COST | CM18: EXTRA CONSUMPTION | CN18: EXTRA CONSUMPTION VALUE | CZ18: $A$1
A19: DOCKET NO. | B19: BASE DATE | C19: ITEM CODE | D19: PROPOSE ERP ITEM NAME | E19: EX-WORKS (PER KM) | F19: FREIGHT PER KM | G19: PRICE INCLUDING FREIGHT (PER KM) | H19: GST % | I19: GST VALUE | J19: PRICE INCLUDING GST & FREIGHT (PER KM) | K19: QTY | L19: Unit | M19: TOTAL PRICE OF FULL QTY (INCLUDING FRIGHT & GST) | N19: Alumimium | O19: Alumimium ALLOY | P19: Copper | Q19: AL-59 | R19: AL-4 | S19: AL-7 | T19: Flexible Copper | U19: Galvanized steel wire | V19: Alumimium | W19: Alumimium ALLOY | X19: Coper tape - 0.1 mm | Y19: Copper Tape - 0.03 mm | Z19: Copper Tape - 0.035 mm | AA19: Copper Tape - 0.04 mm | AB19: Copper Tape - 0.045 mm | AC19: Copper Tape - 0.050 mm | AD19: Copper Tape - 0.060 mm | AE19: Copper Tape - 0.075 mm(DOUBLE) | AF19: Extruded semiconductive | AG19: Extruded Semiconductive(Stripable) | AH19: HT-XLPE | AI19: LT-XLPE | AJ19: TR XLPE | AK19: Type A PVC | AL19: Type C PVC (HR) | AM19: Type A PVC-1.45 | AN19: Type A PVC-FR | AO19: Type A PVC-FRLS | AP19: Type A PVC-1.38 | AQ19: POLY TAPE | AR19: FR PVC Type ST-1 | AS19: FR PVC Type ST-2 | AT19: FRLSH PVC Type ST-1 | AU19: FRLSH PVC Type ST-2 | AV19: PVC Type ST-1 | AW19: PVC Type ST-1-PRESSURE EXTRUDED | AX19: PVC Type ST-2 | AY19: PVC COMPOUND 1.48 | AZ19: PVC Type ST-2-PRESSURE EXTRUDED | BA19: ACSR CORE WIRE | BB19: ACSR DOG STEEL WIRE | BC19: Aluminium Flat Strip | BD19: Aluminium Round Wire | BE19: Alumimium Tape | BF19: Double Steel Tape | BG19: Galvanised Steel Flat Strip | BH19: Galvanised Steel Flat Strip (Double) | BI19: Galvanised Steel Flat Strip-B | BJ19: Galvanised Steel Round Wire | BK19: Galvanised Steel Round Wire (Double) | BL19: FR PVC Type ST-1 | BM19: FR PVC Type ST-2 | BN19: FRLSH PVC Type ST-1 | BO19: FRLSH PVC Type ST-2 + UV resistance | BP19: ZHFR | BQ19: PE-ST-3 | BR19: PE-ST-7 | BS19: PVC Type ST-2 | BT19: FRLSH PVC Type ST-2 | BU19: PVC COMPOUND 1.48 | BV19: PVC Type ST-2-PRESSURE EXTRUDED | BW19: UV & Track Resistant XLPE | BX19: FILLER | BY19: Grease | BZ19: Water swellable Tape | CA19: Semi conducting Water Swellable tape | CB19: SEMICON TAPE | CC19: GLASS FIBER TAPE | CD19: COPPER WIRE 0.8 MM | CE19: RUBBERIZED COTTON TAPE | CF19: Water Tight Compound | CG19: PROPOSE DRUM TYPE | CH19: DRUM CODE | CI19: DRUM SIZE (FxbXtx Ft) | CJ19: PARTY STANDARD LENGTH (MTR) | CO19: MFG% | CP19: MFG VALUE | CQ19: PROF% | CR19: PROFIT VALUE | CS19: 1ST EX-WORKS | CT19: Intt % | CU19: INTT VALUE | CV19: insp% | CW19: INSP VALUE | CX19: TTR Charges% | CY19: TTR Charges VALUE
N20: 418 | O20: =N20+5 -> 423 | P20: =+IFERROR(VLOOKUP($P$19,Sheet1!J:M,2,0),0) -> 0 | Q20: =+IFERROR(VLOOKUP($Q$19,Sheet1!J:M,2,0),0) -> 0 | R20: =+IFERROR(VLOOKUP($R$19,Sheet1!J:M,2,0),0) -> 0 | S20: =+IFERROR(VLOOKUP($S$19,Sheet1!J:M,2,0),0) -> 0 | T20: =+IFERROR(VLOOKUP($T$19,Sheet1!J:M,2,0),0) -> 0 | U20: =+IFERROR(VLOOKUP($U$19,Sheet1!J:M,2,0),0) -> 0 | V20: =+IFERROR(VLOOKUP($V$19,Sheet1!N:Q,2,0),0) -> 0 | W20: =+IFERROR(VLOOKUP($W$19,Sheet1!N:O,2,0),0) -> 0 | X20: =+IFERROR(VLOOKUP($X$19,Sheet1!F:I,2,0),0) -> 0 | Y20: =+IFERROR(VLOOKUP($Y$19,Sheet1!F:I,2,0),0) -> 0 | Z20: =+IFERROR(VLOOKUP($Z$19,Sheet1!F:I,2,0),0) -> 0 | AA20: =+IFERROR(VLOOKUP($AA$19,Sheet1!F:I,2,0),0) -> 0 | AB20: =+IFERROR(VLOOKUP($AB$19,Sheet1!F:I,2,0),0) -> 0 | AC20: =+IFERROR(VLOOKUP($AC$19,Sheet1!F:I,2,0),0) -> 0 | AD20: =+IFERROR(VLOOKUP($AD$19,Sheet1!F:I,2,0),0) -> 0 | AE20: =+IFERROR(VLOOKUP($AE$19,Sheet1!F:I,2,0),0) -> 0 | AF20: =+IFERROR(VLOOKUP($AF$19,Sheet1!R:U,2,0),0) -> 0 | AG20: =+IFERROR(VLOOKUP($AG$19,Sheet1!R:U,2,0),0) -> 0 | AH20: =+IFERROR(VLOOKUP($AH$19,Sheet1!V:Y,2,0),0) -> 0 | AI20: 150 | AJ20: =+IFERROR(VLOOKUP($AJ$19,Sheet1!V:Y,2,0),0) -> 0 | AK20: =+IFERROR(VLOOKUP($AK$19,Sheet1!V:Y,2,0),0) -> 0 | AL20: =+IFERROR(VLOOKUP($AL$19,Sheet1!V:Y,2,0),0) -> 0 | AM20: =+IFERROR(VLOOKUP($AM$19,Sheet1!V:Y,2,0),0) -> 0 | AN20: =+IFERROR(VLOOKUP($AN$19,Sheet1!V:Y,2,0),0) -> 0 | AO20: =+IFERROR(VLOOKUP($AO$19,Sheet1!V:Y,2,0),0) -> 0 | AP20: =+IFERROR(VLOOKUP($AP$19,Sheet1!V:Y,2,0),0) -> 0 | AQ20: =+IFERROR(VLOOKUP($AQ$19,Sheet1!Z2:AA840,2,0),0) -> 0 | AR20: =+IFERROR(VLOOKUP($AR$19,Sheet1!AD2:AG840,2,0),0) -> 0 | AS20: =+IFERROR(VLOOKUP($AS$19,Sheet1!AD2:AG840,2,0),0) -> 0 | AT20: =+IFERROR(VLOOKUP($AT$19,Sheet1!AD2:AG840,2,0),0) -> 0 | AU20: =+IFERROR(VLOOKUP($AU$19,Sheet1!AD2:AG840,2,0),0) -> 0 | AV20: =+IFERROR(VLOOKUP($AV$19,Sheet1!AD2:AG840,2,0),0) -> 0 | AW20: =+IFERROR(VLOOKUP($AW$19,Sheet1!AD2:AG840,2,0),0) -> 0 | AX20: 59 | AY20: =+IFERROR(VLOOKUP($AY$19,Sheet1!AD2:AG840,2,0),0) -> 0 | AZ20: =+IFERROR(VLOOKUP($AZ$19,Sheet1!AD2:AG840,2,0),0) -> 0 | BA20: =+IFERROR(VLOOKUP($BA$19,Sheet1!AH2:AK840,2,0),0) -> 0 | BB20: =+IFERROR(VLOOKUP($BB$19,Sheet1!AH2:AK840,2,0),0) -> 0 | BC20: =+IFERROR(VLOOKUP($BC$19,Sheet1!AH2:AK840,2,0),0) -> 0 | BD20: =N20+5 -> 423 | BE20: =+IFERROR(VLOOKUP($BE$19,Sheet1!AH2:AK840,2,0),0) -> 0 | BF20: =+IFERROR(VLOOKUP($BF$19,Sheet1!AH2:AK840,2,0),0) -> 0 | BG20: 87 | BH20: =+IFERROR(VLOOKUP($BH$19,Sheet1!AH2:AK840,2,0),0) -> 0 | BI20: =+IFERROR(VLOOKUP($BI$19,Sheet1!AH2:AK840,2,0),0) -> 0 | BJ20: =+IFERROR(VLOOKUP($BJ$19,Sheet1!AH2:AK840,2,0),0) -> 0 | BK20: =+IFERROR(VLOOKUP($BK$19,Sheet1!AH2:AK840,2,0),0) -> 0 | BL20: =+IFERROR(VLOOKUP($BL$19,Sheet1!AL2:AO840,2,0),0) -> 0 | BM20: =+IFERROR(VLOOKUP($BM$19,Sheet1!AL2:AO840,2,0),0) -> 0 | BN20: =+IFERROR(VLOOKUP($BN$19,Sheet1!AL2:AO840,2,0),0) -> 0 | BO20: =98+5 -> 103 | BP20: =+IFERROR(VLOOKUP($BP$19,Sheet1!AL2:AO840,2,0),0) -> 0 | BQ20: =+IFERROR(VLOOKUP($BQ$19,Sheet1!AL2:AO840,2,0),0) -> 0 | BR20: =+IFERROR(VLOOKUP($BR$19,Sheet1!AL2:AO840,2,0),0) -> 0 | BS20: 79 | BT20: 98 | BU20: =+IFERROR(VLOOKUP($BU$19,Sheet1!AL2:AO840,2,0),0) -> 0 | BV20: =+IFERROR(VLOOKUP($BV$19,Sheet1!AL2:AO840,2,0),0) -> 0 | BW20: =+IFERROR(VLOOKUP($BW$19,Sheet1!AL2:AO840,2,0),0) -> 0 | BX20: =+IFERROR(VLOOKUP($BX$19,Sheet1!AP2:AS840,2,0),0) -> 0 | BY20: =+IFERROR(VLOOKUP($BY$19,Sheet1!AT2:AW840,2,0),0) -> 0 | BZ20: =+IFERROR(VLOOKUP($BZ$19,Sheet1!AX2:BA840,2,0),0) -> 0 | CA20: =+IFERROR(VLOOKUP($CA$19,Sheet1!BB2:BE840,2,0),0) -> 0 | CB20: =+IFERROR(VLOOKUP($CB$19,Sheet1!BF2:BI840,2,0),0) -> 0 | CC20: =+IFERROR(VLOOKUP($CC$19,Sheet1!BJ2:BM840,2,0),0) -> 0 | CD20: =+IFERROR(VLOOKUP($CD$19,Sheet1!BN2:BQ840,2,0),0) -> 0 | CE20: 294 | CF20: =+IFERROR(VLOOKUP($CF$19,Sheet1!BV2:BY840,2,0),0) -> 0
A21: =Sheet1!A6 -> ENQ-18774-25-26 | B21: 46143 | C21: =Sheet1!C6 -> FA0900036 | D21: =Sheet1!D6 -> 4 CORE X 50 SQ. MM. ALU/ARD - STRIP (XLPE) | E21: =CS21+CU21+CW21+CY21 -> 438368.97 | F21: =ROUNDUP(M39,0) -> 9643 | G21: =E21+F21 -> 448011.97 | H21: =Sheet1!CR6 -> 0.18 | I21: =G21*H21 -> 80642.155 | J21: =G21+I21 -> 528654.12 | K21: =Sheet1!CU6 -> 140 | L21: =Sheet1!CV6 -> KMS | M21: =J21*K21 -> 74011577 | N21: =+IFERROR(VLOOKUP($N$19,Sheet1!J6:L6,3,0),0) -> 540 | O21: =+IFERROR(VLOOKUP($O$19,Sheet1!J6:L6,3,0),0) -> 0 | P21: =+IFERROR(VLOOKUP($P$19,Sheet1!J6:M6,3,0),0) -> 0 | Q21: =+IFERROR(VLOOKUP($Q$19,Sheet1!J6:M6,3,0),0) -> 0 | R21: =+IFERROR(VLOOKUP($R$19,Sheet1!J6:M6,3,0),0) -> 0 | S21: =+IFERROR(VLOOKUP($S$19,Sheet1!J6:M6,3,0),0) -> 0 | T21: =+IFERROR(VLOOKUP($T$19,Sheet1!J6:M6,3,0),0) -> 0 | U21: =+IFERROR(VLOOKUP($U$19,Sheet1!J6:M6,3,0),0) -> 0 | V21: =+IFERROR(VLOOKUP($V$19,Sheet1!N6:Q6,3,0),0) -> 0 | W21: =+IFERROR(VLOOKUP($W$19,Sheet1!N6:Q6,3,0),0) -> 0 | X21: =+IFERROR(VLOOKUP($X$19,Sheet1!F6:I6,3,0),0) -> 0 | Y21: =+IFERROR(VLOOKUP($Y$19,Sheet1!F6:I6,3,0),0) -> 0 | Z21: =+IFERROR(VLOOKUP($Z$19,Sheet1!F6:I6,3,0),0) -> 0 | AA21: =+IFERROR(VLOOKUP($AA$19,Sheet1!F6:I6,3,0),0) -> 0 | AB21: =+IFERROR(VLOOKUP($AB$19,Sheet1!F6:I6,3,0),0) -> 0 | AC21: =+IFERROR(VLOOKUP($AC$19,Sheet1!F6:I6,3,0),0) -> 0 | AD21: =+IFERROR(VLOOKUP($AD$19,Sheet1!F6:I6,3,0),0) -> 0 | AE21: =+IFERROR(VLOOKUP($AE$19,Sheet1!F6:I6,3,0),0) -> 0 | AF21: =+IFERROR(VLOOKUP($AF$19,Sheet1!R6:U6,3,0),0) -> 0 | AG21: =+IFERROR(VLOOKUP($AG$19,Sheet1!R6:U6,3,0),0) -> 0 | AH21: =+IFERROR(VLOOKUP($AH$19,Sheet1!V6:Y6,3,0),0) -> 0 | AI21: 144 | AJ21: =+IFERROR(VLOOKUP($AJ$19,Sheet1!V6:Y6,3,0),0) -> 0 | AK21: =+IFERROR(VLOOKUP($AK$19,Sheet1!V6:Y6,3,0),0) -> 0 | AL21: =+IFERROR(VLOOKUP($AL$19,Sheet1!V6:Y6,3,0),0) -> 0 | AM21: =+IFERROR(VLOOKUP($AM$19,Sheet1!V6:Y6,3,0),0) -> 0 | AN21: =+IFERROR(VLOOKUP($AN$19,Sheet1!V6:Y6,3,0),0) -> 0 | AO21: =+IFERROR(VLOOKUP($AO$19,Sheet1!V6:Y6,3,0),0) -> 0 | AP21: =+IFERROR(VLOOKUP($AP$19,Sheet1!V6:Y6,3,0),0) -> 0 | AQ21: =+IFERROR(VLOOKUP($AQ$19,Sheet1!Z6:AB6,3,0),0) -> 0 | AR21: =+IFERROR(VLOOKUP($AR$19,Sheet1!AD6:AG6,3,0),0) -> 0 | AS21: =+IFERROR(VLOOKUP($AS$19,Sheet1!AD6:AG6,3,0),0) -> 0 | AT21: =+IFERROR(VLOOKUP($AT$19,Sheet1!AD6:AG6,3,0),0) -> 0 | AU21: =+IFERROR(VLOOKUP($AU$19,Sheet1!AD6:AG6,3,0),0) -> 0 | AV21: =+IFERROR(VLOOKUP($AV$19,Sheet1!AD6:AG6,3,0),0) -> 0 | AW21: =+IFERROR(VLOOKUP($AW$19,Sheet1!AD6:AG6,3,0),0) -> 0 | AX21: 60 | AY21: =+IFERROR(VLOOKUP($AY$19,Sheet1!AD6:AG6,3,0),0) -> 0 | AZ21: =+IFERROR(VLOOKUP($AZ$19,Sheet1!AD6:AG6,3,0),0) -> 0 | BA21: =+IFERROR(VLOOKUP($BA$19,Sheet1!AH6:AK6,3,0),0) -> 0 | BB21: =+IFERROR(VLOOKUP($BB$19,Sheet1!AH6:AK6,3,0),0) -> 0 | BC21: =+IFERROR(VLOOKUP($BC$19,Sheet1!AH6:AK6,3,0),0) -> 0 | BD21: =+IFERROR(VLOOKUP($BD$19,Sheet1!AH6:AK6,3,0),0) -> 0 | BE21: =+IFERROR(VLOOKUP($BE$19,Sheet1!AH6:AK6,3,0),0) -> 0 | BF21: =+IFERROR(VLOOKUP($BF$19,Sheet1!AH6:AK6,3,0),0) -> 0 | BG21: 446 | BH21: =+IFERROR(VLOOKUP($BH$19,Sheet1!AH6:AK6,3,0),0) -> 0 | BI21: =+IFERROR(VLOOKUP($BI$19,Sheet1!AH6:AK6,3,0),0) -> 0 | BJ21: =+IFERROR(VLOOKUP($BJ$19,Sheet1!AH6:AK6,3,0),0) -> 0 | BK21: =+IFERROR(VLOOKUP($BK$19,Sheet1!AH6:AK6,3,0),0) -> 0 | BL21: =+IFERROR(VLOOKUP($BL$19,Sheet1!AL6:AO6,3,0),0) -> 0 | BM21: =+IFERROR(VLOOKUP($BM$19,Sheet1!AL6:AO6,3,0),0) -> 0 | BN21: =+IFERROR(VLOOKUP($BN$19,Sheet1!AL6:AO6,3,0),0) -> 0 | BO21: 245 | BP21: =+IFERROR(VLOOKUP($BP$19,Sheet1!AL6:AO6,3,0),0) -> 0 | BQ21: =+IFERROR(VLOOKUP($BQ$19,Sheet1!AL6:AO6,3,0),0) -> 0 | BR21: =+IFERROR(VLOOKUP($BR$19,Sheet1!AL6:AO6,3,0),0) -> 0 | BU21: =+IFERROR(VLOOKUP($BU$19,Sheet1!AL6:AO6,3,0),0) -> 0 | BV21: =+IFERROR(VLOOKUP($BV$19,Sheet1!AL6:AO6,3,0),0) -> 0 | BW21: =+IFERROR(VLOOKUP($BW$19,Sheet1!AL6:AO6,3,0),0) -> 0 | BX21: =+IFERROR(VLOOKUP($BX$19,Sheet1!AP6:AS6,3,0),0) -> 0 | BY21: =+IFERROR(VLOOKUP($BY$19,Sheet1!AT6:AW6,3,0),0) -> 0 | BZ21: =+IFERROR(VLOOKUP($BZ$19,Sheet1!AX6:BA6,3,0),0) -> 0 | CA21: =+IFERROR(VLOOKUP($CA$19,Sheet1!BB6:BE6,3,0),0) -> 0 | CB21: =+IFERROR(VLOOKUP($CB$19,Sheet1!BF6:BI6,3,0),0) -> 0 | CC21: =+IFERROR(VLOOKUP($CC$19,Sheet1!BJ6:BM6,3,0),0) -> 0 | CD21: =+IFERROR(VLOOKUP($CD$19,Sheet1!BN6:BQ6,3,0),0) -> 0 | CE21: 36 | CF21: =+IFERROR(VLOOKUP($CF$19,Sheet1!BV6:BY6,3,0),0) -> 0 | CG21: =Sheet1!E6 -> WOOD | CH21: =Sheet1!CY6 -> MD0100015 | CI21: =Sheet1!CZ6 -> DRUM - 48 X 20 X 28 X 2.25 - RDSO | CJ21: =Sheet1!CX6 -> 500 | CK21: =2557/0.5 -> 5114 | CL21: =SUMPRODUCT($N$20:$CF$20,N21:CF21)+CK21 -> 330595 | CM21: =Sheet1!CB6 -> 0 | CN21: =CL21*CM21 -> 0 | CO21: 0.3 | CP21: =CL21*CO21 -> 99178.5 | CQ21: 0 | CR21: =CL21*CQ21 -> 0 | CS21: =CL21+CN21+CP21+CR21 -> 429773.5 | CT21: 0.02 | CU21: =CS21*CT21 -> 8595.47 | CV21: =Sheet1!CK6 -> 0 | CW21: =CS21*CV21 -> 0 | CX21: =Sheet1!CM6 -> 0 | CY21: =CX21*CS21 -> 0
A22: =Sheet1!A7 -> ENQ-18774-25-26 | B22: 46143 | C22: =Sheet1!C7 -> FA1100012 | D22: =Sheet1!D7 -> 4 CORE X 95 SQ. MM. AL/ARD - STRIP (XLPE) | E22: =CS22+CU22+CW22+CY22 -> 761698.16 | F22: =ROUNDUP(M40,0) -> 18750 | G22: =E22+F22 -> 780448.16 | H22: =Sheet1!CR7 -> 0.18 | I22: =G22*H22 -> 140480.67 | J22: =G22+I22 -> 920928.83 | K22: =Sheet1!CU7 -> 600 | L22: =Sheet1!CV7 -> KMS | M22: =J22*K22 -> 5.525573e+08 | N22: =+IFERROR(VLOOKUP($N$19,Sheet1!J7:L7,3,0),0) -> 1026 | O22: =+IFERROR(VLOOKUP($O$19,Sheet1!J7:L7,3,0),0) -> 0 | P22: =+IFERROR(VLOOKUP($P$19,Sheet1!J7:M7,3,0),0) -> 0 | Q22: =+IFERROR(VLOOKUP($Q$19,Sheet1!J7:M7,3,0),0) -> 0 | R22: =+IFERROR(VLOOKUP($R$19,Sheet1!J7:M7,3,0),0) -> 0 | S22: =+IFERROR(VLOOKUP($S$19,Sheet1!J7:M7,3,0),0) -> 0 | T22: =+IFERROR(VLOOKUP($T$19,Sheet1!J7:M7,3,0),0) -> 0 | U22: =+IFERROR(VLOOKUP($U$19,Sheet1!J7:M7,3,0),0) -> 0 | V22: =+IFERROR(VLOOKUP($V$19,Sheet1!N7:Q7,3,0),0) -> 0 | W22: =+IFERROR(VLOOKUP($W$19,Sheet1!N7:Q7,3,0),0) -> 0 | X22: =+IFERROR(VLOOKUP($X$19,Sheet1!F7:I7,3,0),0) -> 0 | Y22: =+IFERROR(VLOOKUP($Y$19,Sheet1!F7:I7,3,0),0) -> 0 | Z22: =+IFERROR(VLOOKUP($Z$19,Sheet1!F7:I7,3,0),0) -> 0 | AA22: =+IFERROR(VLOOKUP($AA$19,Sheet1!F7:I7,3,0),0) -> 0 | AB22: =+IFERROR(VLOOKUP($AB$19,Sheet1!F7:I7,3,0),0) -> 0 | AC22: =+IFERROR(VLOOKUP($AC$19,Sheet1!F7:I7,3,0),0) -> 0 | AD22: =+IFERROR(VLOOKUP($AD$19,Sheet1!F7:I7,3,0),0) -> 0 | AE22: =+IFERROR(VLOOKUP($AE$19,Sheet1!F7:I7,3,0),0) -> 0 | AF22: =+IFERROR(VLOOKUP($AF$19,Sheet1!R7:U7,3,0),0) -> 0 | AG22: =+IFERROR(VLOOKUP($AG$19,Sheet1!R7:U7,3,0),0) -> 0 | AH22: =+IFERROR(VLOOKUP($AH$19,Sheet1!V7:Y7,3,0),0) -> 0 | AI22: 204 | AJ22: =+IFERROR(VLOOKUP($AJ$19,Sheet1!V7:Y7,3,0),0) -> 0 | AK22: =+IFERROR(VLOOKUP($AK$19,Sheet1!V7:Y7,3,0),0) -> 0 | AL22: =+IFERROR(VLOOKUP($AL$19,Sheet1!V7:Y7,3,0),0) -> 0 | AM22: =+IFERROR(VLOOKUP($AM$19,Sheet1!V7:Y7,3,0),0) -> 0 | AN22: =+IFERROR(VLOOKUP($AN$19,Sheet1!V7:Y7,3,0),0) -> 0 | AO22: =+IFERROR(VLOOKUP($AO$19,Sheet1!V7:Y7,3,0),0) -> 0 | AP22: =+IFERROR(VLOOKUP($AP$19,Sheet1!V7:Y7,3,0),0) -> 0 | AQ22: =+IFERROR(VLOOKUP($AQ$19,Sheet1!Z7:AB7,3,0),0) -> 0 | AR22: =+IFERROR(VLOOKUP($AR$19,Sheet1!AD7:AG7,3,0),0) -> 0 | AS22: =+IFERROR(VLOOKUP($AS$19,Sheet1!AD7:AG7,3,0),0) -> 0 | AT22: =+IFERROR(VLOOKUP($AT$19,Sheet1!AD7:AG7,3,0),0) -> 0 | AU22: =+IFERROR(VLOOKUP($AU$19,Sheet1!AD7:AG7,3,0),0) -> 0 | AV22: =+IFERROR(VLOOKUP($AV$19,Sheet1!AD7:AG7,3,0),0) -> 0 | AW22: =+IFERROR(VLOOKUP($AW$19,Sheet1!AD7:AG7,3,0),0) -> 0 | AX22: 96 | AY22: =+IFERROR(VLOOKUP($AY$19,Sheet1!AD7:AG7,3,0),0) -> 0 | AZ22: =+IFERROR(VLOOKUP($AZ$19,Sheet1!AD7:AG7,3,0),0) -> 0 | BA22: =+IFERROR(VLOOKUP($BA$19,Sheet1!AH7:AK7,3,0),0) -> 0 | BB22: =+IFERROR(VLOOKUP($BB$19,Sheet1!AH7:AK7,3,0),0) -> 0 | BC22: =+IFERROR(VLOOKUP($BC$19,Sheet1!AH7:AK7,3,0),0) -> 0 | BD22: =+IFERROR(VLOOKUP($BD$19,Sheet1!AH7:AK7,3,0),0) -> 0 | BE22: =+IFERROR(VLOOKUP($BE$19,Sheet1!AH7:AK7,3,0),0) -> 0 | BF22: =+IFERROR(VLOOKUP($BF$19,Sheet1!AH7:AK7,3,0),0) -> 0 | BG22: 577 | BH22: =+IFERROR(VLOOKUP($BH$19,Sheet1!AH7:AK7,3,0),0) -> 0 | BI22: =+IFERROR(VLOOKUP($BI$19,Sheet1!AH7:AK7,3,0),0) -> 0 | BJ22: =+IFERROR(VLOOKUP($BJ$19,Sheet1!AH7:AK7,3,0),0) -> 0 | BK22: =+IFERROR(VLOOKUP($BK$19,Sheet1!AH7:AK7,3,0),0) -> 0 | BL22: =+IFERROR(VLOOKUP($BL$19,Sheet1!AL7:AO7,3,0),0) -> 0 | BM22: =+IFERROR(VLOOKUP($BM$19,Sheet1!AL7:AO7,3,0),0) -> 0 | BN22: =+IFERROR(VLOOKUP($BN$19,Sheet1!AL7:AO7,3,0),0) -> 0 | BO22: 310 | BP22: =+IFERROR(VLOOKUP($BP$19,Sheet1!AL7:AO7,3,0),0) -> 0 | BQ22: =+IFERROR(VLOOKUP($BQ$19,Sheet1!AL7:AO7,3,0),0) -> 0 | BR22: =+IFERROR(VLOOKUP($BR$19,Sheet1!AL7:AO7,3,0),0) -> 0 | BU22: =+IFERROR(VLOOKUP($BU$19,Sheet1!AL7:AO7,3,0),0) -> 0 | BV22: =+IFERROR(VLOOKUP($BV$19,Sheet1!AL7:AO7,3,0),0) -> 0 | BW22: =+IFERROR(VLOOKUP($BW$19,Sheet1!AL7:AO7,3,0),0) -> 0 | BX22: =+IFERROR(VLOOKUP($BX$19,Sheet1!AP7:AS7,3,0),0) -> 0 | BY22: =+IFERROR(VLOOKUP($BY$19,Sheet1!AT7:AW7,3,0),0) -> 0 | BZ22: =+IFERROR(VLOOKUP($BZ$19,Sheet1!AX7:BA7,3,0),0) -> 0 | CA22: =+IFERROR(VLOOKUP($CA$19,Sheet1!BB7:BE7,3,0),0) -> 0 | CB22: =+IFERROR(VLOOKUP($CB$19,Sheet1!BF7:BI7,3,0),0) -> 0 | CC22: =+IFERROR(VLOOKUP($CC$19,Sheet1!BJ7:BM7,3,0),0) -> 0 | CD22: =+IFERROR(VLOOKUP($CD$19,Sheet1!BN7:BQ7,3,0),0) -> 0 | CE22: 47 | CF22: =+IFERROR(VLOOKUP($CF$19,Sheet1!BV7:BY7,3,0),0) -> 0 | CG22: =Sheet1!E7 -> WOOD | CH22: =Sheet1!CY7 -> MD0100061 | CI22: =Sheet1!CZ7 -> DRUM - 56 X 24 X 32 X 3 | CJ22: =Sheet1!CX7 -> 500 | CK22: =6677/0.5 -> 13354 | CL22: =SUMPRODUCT($N$20:$CF$20,N22:CF22)+CK22 -> 574433 | CM22: =Sheet1!CB7 -> 0 | CN22: =CL22*CM22 -> 0 | CO22: 0.3 | CP22: =CL22*CO22 -> 172329.9 | CQ22: 0 | CR22: =CL22*CQ22 -> 0 | CS22: =CL22+CN22+CP22+CR22 -> 746762.9 | CT22: 0.02 | CU22: =CS22*CT22 -> 14935.258 | CV22: =Sheet1!CK7 -> 0 | CW22: =CS22*CV22 -> 0 | CX22: =Sheet1!CM7 -> 0 | CY22: =CX22*CS22 -> 0
A23: =Sheet1!A9 -> ENQ-18774-25-26 | B23: 46143 | C23: =Sheet1!C9 -> FA1100067 | D23: =Sheet1!D9 -> 4 CORE X 150 SQ. MM. AL/ARD - STRIP (XLPE) | E23: =CS23+CU23+CW23+CY23 -> 1166321.8 | F23: =ROUNDUP(M41,0) -> 25500 | G23: =E23+F23 -> 1191821.8 | H23: =Sheet1!CR9 -> 0.18 | I23: =G23*H23 -> 214527.92 | J23: =G23+I23 -> 1406349.7 | K23: =Sheet1!CU9 -> 100 | L23: =Sheet1!CV9 -> KMS | M23: =J23*K23 -> 1.4063497e+08 | N23: 1620 | O23: =+IFERROR(VLOOKUP($O$19,Sheet1!J9:L9,3,0),0) -> 0 | P23: =+IFERROR(VLOOKUP($P$19,Sheet1!J9:M9,3,0),0) -> 0 | Q23: =+IFERROR(VLOOKUP($Q$19,Sheet1!J9:M9,3,0),0) -> 0 | R23: =+IFERROR(VLOOKUP($R$19,Sheet1!J9:M9,3,0),0) -> 0 | S23: =+IFERROR(VLOOKUP($S$19,Sheet1!J9:M9,3,0),0) -> 0 | T23: =+IFERROR(VLOOKUP($T$19,Sheet1!J9:M9,3,0),0) -> 0 | U23: =+IFERROR(VLOOKUP($U$19,Sheet1!J9:M9,3,0),0) -> 0 | V23: =+IFERROR(VLOOKUP($V$19,Sheet1!N9:Q9,3,0),0) -> 0 | W23: =+IFERROR(VLOOKUP($W$19,Sheet1!N9:Q9,3,0),0) -> 0 | X23: =+IFERROR(VLOOKUP($X$19,Sheet1!F9:I9,3,0),0) -> 0 | Y23: =+IFERROR(VLOOKUP($Y$19,Sheet1!F9:I9,3,0),0) -> 0 | Z23: =+IFERROR(VLOOKUP($Z$19,Sheet1!F9:I9,3,0),0) -> 0 | AA23: =+IFERROR(VLOOKUP($AA$19,Sheet1!F9:I9,3,0),0) -> 0 | AB23: =+IFERROR(VLOOKUP($AB$19,Sheet1!F9:I9,3,0),0) -> 0 | AC23: =+IFERROR(VLOOKUP($AC$19,Sheet1!F9:I9,3,0),0) -> 0 | AD23: =+IFERROR(VLOOKUP($AD$19,Sheet1!F9:I9,3,0),0) -> 0 | AE23: =+IFERROR(VLOOKUP($AE$19,Sheet1!F9:I9,3,0),0) -> 0 | AF23: =+IFERROR(VLOOKUP($AF$19,Sheet1!R9:U9,3,0),0) -> 0 | AG23: =+IFERROR(VLOOKUP($AG$19,Sheet1!R9:U9,3,0),0) -> 0 | AH23: =+IFERROR(VLOOKUP($AH$19,Sheet1!V9:Y9,3,0),0) -> 0 | AI23: 315 | AJ23: =+IFERROR(VLOOKUP($AJ$19,Sheet1!V9:Y9,3,0),0) -> 0 | AK23: =+IFERROR(VLOOKUP($AK$19,Sheet1!V9:Y9,3,0),0) -> 0 | AL23: =+IFERROR(VLOOKUP($AL$19,Sheet1!V9:Y9,3,0),0) -> 0 | AM23: =+IFERROR(VLOOKUP($AM$19,Sheet1!V9:Y9,3,0),0) -> 0 | AN23: =+IFERROR(VLOOKUP($AN$19,Sheet1!V9:Y9,3,0),0) -> 0 | AO23: =+IFERROR(VLOOKUP($AO$19,Sheet1!V9:Y9,3,0),0) -> 0 | AP23: =+IFERROR(VLOOKUP($AP$19,Sheet1!V9:Y9,3,0),0) -> 0 | AQ23: =+IFERROR(VLOOKUP($AQ$19,Sheet1!Z9:AB9,3,0),0) -> 0 | AR23: =+IFERROR(VLOOKUP($AR$19,Sheet1!AD9:AG9,3,0),0) -> 0 | AS23: =+IFERROR(VLOOKUP($AS$19,Sheet1!AD9:AG9,3,0),0) -> 0 | AT23: =+IFERROR(VLOOKUP($AT$19,Sheet1!AD9:AG9,3,0),0) -> 0 | AU23: =+IFERROR(VLOOKUP($AU$19,Sheet1!AD9:AG9,3,0),0) -> 0 | AV23: =+IFERROR(VLOOKUP($AV$19,Sheet1!AD9:AG9,3,0),0) -> 0 | AW23: =+IFERROR(VLOOKUP($AW$19,Sheet1!AD9:AG9,3,0),0) -> 0 | AX23: 165 | AY23: =+IFERROR(VLOOKUP($AY$19,Sheet1!AD9:AG9,3,0),0) -> 0 | AZ23: =+IFERROR(VLOOKUP($AZ$19,Sheet1!AD9:AG9,3,0),0) -> 0 | BA23: =+IFERROR(VLOOKUP($BA$19,Sheet1!AH9:AK9,3,0),0) -> 0 | BB23: =+IFERROR(VLOOKUP($BB$19,Sheet1!AH9:AK9,3,0),0) -> 0 | BC23: =+IFERROR(VLOOKUP($BC$19,Sheet1!AH9:AK9,3,0),0) -> 0 | BD23: =+IFERROR(VLOOKUP($BD$19,Sheet1!AH9:AK9,3,0),0) -> 0 | BE23: =+IFERROR(VLOOKUP($BE$19,Sheet1!AH9:AK9,3,0),0) -> 0 | BF23: =+IFERROR(VLOOKUP($BF$19,Sheet1!AH9:AK9,3,0),0) -> 0 | BG23: 735 | BH23: =+IFERROR(VLOOKUP($BH$19,Sheet1!AH9:AK9,3,0),0) -> 0 | BI23: =+IFERROR(VLOOKUP($BI$19,Sheet1!AH9:AK9,3,0),0) -> 0 | BJ23: =+IFERROR(VLOOKUP($BJ$19,Sheet1!AH9:AK9,3,0),0) -> 0 | BK23: =+IFERROR(VLOOKUP($BK$19,Sheet1!AH9:AK9,3,0),0) -> 0 | BL23: =+IFERROR(VLOOKUP($BL$19,Sheet1!AL9:AO9,3,0),0) -> 0 | BM23: =+IFERROR(VLOOKUP($BM$19,Sheet1!AL9:AO9,3,0),0) -> 0 | BN23: =+IFERROR(VLOOKUP($BN$19,Sheet1!AL9:AO9,3,0),0) -> 0 | BO23: 453 | BP23: =+IFERROR(VLOOKUP($BP$19,Sheet1!AL9:AO9,3,0),0) -> 0 | BQ23: =+IFERROR(VLOOKUP($BQ$19,Sheet1!AL9:AO9,3,0),0) -> 0 | BR23: =+IFERROR(VLOOKUP($BR$19,Sheet1!AL9:AO9,3,0),0) -> 0 | BU23: =+IFERROR(VLOOKUP($BU$19,Sheet1!AL9:AO9,3,0),0) -> 0 | BV23: =+IFERROR(VLOOKUP($BV$19,Sheet1!AL9:AO9,3,0),0) -> 0 | BW23: =+IFERROR(VLOOKUP($BW$19,Sheet1!AL9:AO9,3,0),0) -> 0 | BX23: =+IFERROR(VLOOKUP($BX$19,Sheet1!AP9:AS9,3,0),0) -> 0 | BY23: =+IFERROR(VLOOKUP($BY$19,Sheet1!AT9:AW9,3,0),0) -> 0 | BZ23: =+IFERROR(VLOOKUP($BZ$19,Sheet1!AX9:BA9,3,0),0) -> 0 | CA23: =+IFERROR(VLOOKUP($CA$19,Sheet1!BB9:BE9,3,0),0) -> 0 | CB23: =+IFERROR(VLOOKUP($CB$19,Sheet1!BF9:BI9,3,0),0) -> 0 | CC23: =+IFERROR(VLOOKUP($CC$19,Sheet1!BJ9:BM9,3,0),0) -> 0 | CD23: =+IFERROR(VLOOKUP($CD$19,Sheet1!BN9:BQ9,3,0),0) -> 0 | CE23: 58 | CF23: =+IFERROR(VLOOKUP($CF$19,Sheet1!BV9:BY9,3,0),0) -> 0 | CG23: WOOD | CH23: MD0100070 | CI23: DRUM - 68 X 24 X 32 X 3 | CJ23: =Sheet1!CX9 -> 500 | CK23: =8889/0.5 -> 17778 | CL23: =SUMPRODUCT($N$20:$CF$20,N23:CF23)+CK23 -> 879579 | CM23: =Sheet1!CB9 -> 0 | CN23: =CL23*CM23 -> 0 | CO23: 0.3 | CP23: =CL23*CO23 -> 263873.7 | CQ23: 0 | CR23: =CL23*CQ23 -> 0 | CS23: =CL23+CN23+CP23+CR23 -> 1143452.7 | CT23: 0.02 | CU23: =CS23*CT23 -> 22869.054 | CV23: =Sheet1!CK9 -> 0 | CW23: =CS23*CV23 -> 0 | CX23: =Sheet1!CM9 -> 0 | CY23: =CX23*CS23 -> 0
A24: =Sheet1!A8 -> ENQ-18774-25-26 | B24: 46143 | C24: =Sheet1!C8 -> FA1100025 | D24: =Sheet1!D8 -> 4 CORE X 300 SQ. MM. AL/ARD - STRIP (XLPE) | E24: =CS24+CU24+CW24+CY24 -> 2214018.2 | F24: =ROUNDUP(M42,0) -> 45900 | G24: =E24+F24 -> 2259918.2 | H24: =Sheet1!CR8 -> 0.18 | I24: =G24*H24 -> 406785.28 | J24: =G24+I24 -> 2666703.5 | K24: =Sheet1!CU8 -> 50 | L24: =Sheet1!CV8 -> KMS | M24: =J24*K24 -> 1.3333518e+08 | N24: =+IFERROR(VLOOKUP($N$19,Sheet1!J8:L8,3,0),0) -> 3240 | O24: =+IFERROR(VLOOKUP($O$19,Sheet1!J8:L8,3,0),0) -> 0 | P24: =+IFERROR(VLOOKUP($P$19,Sheet1!J8:M8,3,0),0) -> 0 | Q24: =+IFERROR(VLOOKUP($Q$19,Sheet1!J8:M8,3,0),0) -> 0 | R24: =+IFERROR(VLOOKUP($R$19,Sheet1!J8:M8,3,0),0) -> 0 | S24: =+IFERROR(VLOOKUP($S$19,Sheet1!J8:M8,3,0),0) -> 0 | T24: =+IFERROR(VLOOKUP($T$19,Sheet1!J8:M8,3,0),0) -> 0 | U24: =+IFERROR(VLOOKUP($U$19,Sheet1!J8:M8,3,0),0) -> 0 | V24: =+IFERROR(VLOOKUP($V$19,Sheet1!N8:Q8,3,0),0) -> 0 | W24: =+IFERROR(VLOOKUP($W$19,Sheet1!N8:Q8,3,0),0) -> 0 | X24: =+IFERROR(VLOOKUP($X$19,Sheet1!F8:I8,3,0),0) -> 0 | Y24: =+IFERROR(VLOOKUP($Y$19,Sheet1!F8:I8,3,0),0) -> 0 | Z24: =+IFERROR(VLOOKUP($Z$19,Sheet1!F8:I8,3,0),0) -> 0 | AA24: =+IFERROR(VLOOKUP($AA$19,Sheet1!F8:I8,3,0),0) -> 0 | AB24: =+IFERROR(VLOOKUP($AB$19,Sheet1!F8:I8,3,0),0) -> 0 | AC24: =+IFERROR(VLOOKUP($AC$19,Sheet1!F8:I8,3,0),0) -> 0 | AD24: =+IFERROR(VLOOKUP($AD$19,Sheet1!F8:I8,3,0),0) -> 0 | AE24: =+IFERROR(VLOOKUP($AE$19,Sheet1!F8:I8,3,0),0) -> 0 | AF24: =+IFERROR(VLOOKUP($AF$19,Sheet1!R8:U8,3,0),0) -> 0 | AG24: =+IFERROR(VLOOKUP($AG$19,Sheet1!R8:U8,3,0),0) -> 0 | AH24: =+IFERROR(VLOOKUP($AH$19,Sheet1!V8:Y8,3,0),0) -> 0 | AI24: 560 | AJ24: =+IFERROR(VLOOKUP($AJ$19,Sheet1!V8:Y8,3,0),0) -> 0 | AK24: =+IFERROR(VLOOKUP($AK$19,Sheet1!V8:Y8,3,0),0) -> 0 | AL24: =+IFERROR(VLOOKUP($AL$19,Sheet1!V8:Y8,3,0),0) -> 0 | AM24: =+IFERROR(VLOOKUP($AM$19,Sheet1!V8:Y8,3,0),0) -> 0 | AN24: =+IFERROR(VLOOKUP($AN$19,Sheet1!V8:Y8,3,0),0) -> 0 | AO24: =+IFERROR(VLOOKUP($AO$19,Sheet1!V8:Y8,3,0),0) -> 0 | AP24: =+IFERROR(VLOOKUP($AP$19,Sheet1!V8:Y8,3,0),0) -> 0 | AQ24: =+IFERROR(VLOOKUP($AQ$19,Sheet1!Z8:AB8,3,0),0) -> 0 | AR24: =+IFERROR(VLOOKUP($AR$19,Sheet1!AD8:AG8,3,0),0) -> 0 | AS24: =+IFERROR(VLOOKUP($AS$19,Sheet1!AD8:AG8,3,0),0) -> 0 | AT24: =+IFERROR(VLOOKUP($AT$19,Sheet1!AD8:AG8,3,0),0) -> 0 | AU24: =+IFERROR(VLOOKUP($AU$19,Sheet1!AD8:AG8,3,0),0) -> 0 | AV24: =+IFERROR(VLOOKUP($AV$19,Sheet1!AD8:AG8,3,0),0) -> 0 | AW24: =+IFERROR(VLOOKUP($AW$19,Sheet1!AD8:AG8,3,0),0) -> 0 | AX24: 240 | AY24: =+IFERROR(VLOOKUP($AY$19,Sheet1!AD8:AG8,3,0),0) -> 0 | AZ24: =+IFERROR(VLOOKUP($AZ$19,Sheet1!AD8:AG8,3,0),0) -> 0 | BA24: =+IFERROR(VLOOKUP($BA$19,Sheet1!AH8:AK8,3,0),0) -> 0 | BB24: =+IFERROR(VLOOKUP($BB$19,Sheet1!AH8:AK8,3,0),0) -> 0 | BC24: =+IFERROR(VLOOKUP($BC$19,Sheet1!AH8:AK8,3,0),0) -> 0 | BD24: =+IFERROR(VLOOKUP($BD$19,Sheet1!AH8:AK8,3,0),0) -> 0 | BE24: =+IFERROR(VLOOKUP($BE$19,Sheet1!AH8:AK8,3,0),0) -> 0 | BF24: =+IFERROR(VLOOKUP($BF$19,Sheet1!AH8:AK8,3,0),0) -> 0 | BG24: 971 | BH24: =+IFERROR(VLOOKUP($BH$19,Sheet1!AH8:AK8,3,0),0) -> 0 | BI24: =+IFERROR(VLOOKUP($BI$19,Sheet1!AH8:AK8,3,0),0) -> 0 | BJ24: =+IFERROR(VLOOKUP($BJ$19,Sheet1!AH8:AK8,3,0),0) -> 0 | BK24: =+IFERROR(VLOOKUP($BK$19,Sheet1!AH8:AK8,3,0),0) -> 0 | BL24: =+IFERROR(VLOOKUP($BL$19,Sheet1!AL8:AO8,3,0),0) -> 0 | BM24: =+IFERROR(VLOOKUP($BM$19,Sheet1!AL8:AO8,3,0),0) -> 0 | BN24: =+IFERROR(VLOOKUP($BN$19,Sheet1!AL8:AO8,3,0),0) -> 0 | BO24: 740 | BP24: =+IFERROR(VLOOKUP($BP$19,Sheet1!AL8:AO8,3,0),0) -> 0 | BQ24: =+IFERROR(VLOOKUP($BQ$19,Sheet1!AL8:AO8,3,0),0) -> 0 | BR24: =+IFERROR(VLOOKUP($BR$19,Sheet1!AL8:AO8,3,0),0) -> 0 | BU24: =+IFERROR(VLOOKUP($BU$19,Sheet1!AL8:AO8,3,0),0) -> 0 | BV24: =+IFERROR(VLOOKUP($BV$19,Sheet1!AL8:AO8,3,0),0) -> 0 | BW24: =+IFERROR(VLOOKUP($BW$19,Sheet1!AL8:AO8,3,0),0) -> 0 | BX24: =+IFERROR(VLOOKUP($BX$19,Sheet1!AP8:AS8,3,0),0) -> 0 | BY24: =+IFERROR(VLOOKUP($BY$19,Sheet1!AT8:AW8,3,0),0) -> 0 | BZ24: =+IFERROR(VLOOKUP($BZ$19,Sheet1!AX8:BA8,3,0),0) -> 0 | CA24: =+IFERROR(VLOOKUP($CA$19,Sheet1!BB8:BE8,3,0),0) -> 0 | CB24: =+IFERROR(VLOOKUP($CB$19,Sheet1!BF8:BI8,3,0),0) -> 0 | CC24: =+IFERROR(VLOOKUP($CC$19,Sheet1!BJ8:BM8,3,0),0) -> 0 | CD24: =+IFERROR(VLOOKUP($CD$19,Sheet1!BN8:BQ8,3,0),0) -> 0 | CE24: 80 | CF24: =+IFERROR(VLOOKUP($CF$19,Sheet1!BV8:BY8,3,0),0) -> 0 | CG24: =Sheet1!E8 -> STEEL | CH24: SP0400123 | CI24: CORRUGATED DISPATCH STEEL DRUM 2000 X 1000 X 1200 MM | CJ24: =Sheet1!CX8 -> 500 | CK24: =16500/0.5 -> 33000 | CL24: =SUMPRODUCT($N$20:$CF$20,N24:CF24)+CK24 -> 1669697 | CM24: =Sheet1!CB8 -> 0 | CN24: =CL24*CM24 -> 0 | CO24: 0.3 | CP24: =CL24*CO24 -> 500909.1 | CQ24: 0 | CR24: =CL24*CQ24 -> 0 | CS24: =CL24+CN24+CP24+CR24 -> 2170606.1 | CT24: 0.02 | CU24: =CS24*CT24 -> 43412.122 | CV24: =Sheet1!CK8 -> 0 | CW24: =CS24*CV24 -> 0 | CX24: =Sheet1!CM8 -> 0 | CY24: =CX24*CS24 -> 0
A25: ENQ-18774-25-26 | B25: 46143 | C25: =Sheet1!C10 -> 0 | D25: 3 CORE X 120 SQ MM + 1 CORE X 120 SQ MM + 1 CORE X 95 SQ MM (AB CABLES) (Insulated | E25: =CS25+CU25+CW25+CY25 -> 1013619.6 | F25: =ROUNDUP(M43,0) -> 18750 | G25: =E25+F25 -> 1032369.6 | H25: 0.18 | I25: =G25*H25 -> 185826.53 | J25: =G25+I25 -> 1218196.1 | K25: 48 | L25: KMS | M25: =J25*K25 -> 58473414 | N25: 1296 | O25: 270 | P25: =+IFERROR(VLOOKUP($P$19,Sheet1!J10:M10,3,0),0) -> 0 | Q25: =+IFERROR(VLOOKUP($Q$19,Sheet1!J10:M10,3,0),0) -> 0 | R25: =+IFERROR(VLOOKUP($R$19,Sheet1!J10:M10,3,0),0) -> 0 | S25: =+IFERROR(VLOOKUP($S$19,Sheet1!J10:M10,3,0),0) -> 0 | T25: =+IFERROR(VLOOKUP($T$19,Sheet1!J10:M10,3,0),0) -> 0 | U25: =+IFERROR(VLOOKUP($U$19,Sheet1!J10:M10,3,0),0) -> 0 | V25: =+IFERROR(VLOOKUP($V$19,Sheet1!N10:Q10,3,0),0) -> 0 | W25: =+IFERROR(VLOOKUP($W$19,Sheet1!N10:Q10,3,0),0) -> 0 | X25: =+IFERROR(VLOOKUP($X$19,Sheet1!F10:I10,3,0),0) -> 0 | Y25: =+IFERROR(VLOOKUP($Y$19,Sheet1!F10:I10,3,0),0) -> 0 | Z25: =+IFERROR(VLOOKUP($Z$19,Sheet1!F10:I10,3,0),0) -> 0 | AA25: =+IFERROR(VLOOKUP($AA$19,Sheet1!F10:I10,3,0),0) -> 0 | AB25: =+IFERROR(VLOOKUP($AB$19,Sheet1!F10:I10,3,0),0) -> 0 | AC25: =+IFERROR(VLOOKUP($AC$19,Sheet1!F10:I10,3,0),0) -> 0 | AD25: =+IFERROR(VLOOKUP($AD$19,Sheet1!F10:I10,3,0),0) -> 0 | AE25: =+IFERROR(VLOOKUP($AE$19,Sheet1!F10:I10,3,0),0) -> 0 | AF25: =+IFERROR(VLOOKUP($AF$19,Sheet1!R10:U10,3,0),0) -> 0 | AG25: =+IFERROR(VLOOKUP($AG$19,Sheet1!R10:U10,3,0),0) -> 0 | AH25: =+IFERROR(VLOOKUP($AH$19,Sheet1!V10:Y10,3,0),0) -> 0 | AI25: 364 | AJ25: =+IFERROR(VLOOKUP($AJ$19,Sheet1!V10:Y10,3,0),0) -> 0 | AK25: =+IFERROR(VLOOKUP($AK$19,Sheet1!V10:Y10,3,0),0) -> 0 | AL25: =+IFERROR(VLOOKUP($AL$19,Sheet1!V10:Y10,3,0),0) -> 0 | AM25: =+IFERROR(VLOOKUP($AM$19,Sheet1!V10:Y10,3,0),0) -> 0 | AN25: =+IFERROR(VLOOKUP($AN$19,Sheet1!V10:Y10,3,0),0) -> 0 | AO25: =+IFERROR(VLOOKUP($AO$19,Sheet1!V10:Y10,3,0),0) -> 0 | AP25: =+IFERROR(VLOOKUP($AP$19,Sheet1!V10:Y10,3,0),0) -> 0 | AQ25: =+IFERROR(VLOOKUP($AQ$19,Sheet1!Z10:AB10,3,0),0) -> 0 | AR25: =+IFERROR(VLOOKUP($AR$19,Sheet1!AD10:AG10,3,0),0) -> 0 | AS25: =+IFERROR(VLOOKUP($AS$19,Sheet1!AD10:AG10,3,0),0) -> 0 | AT25: =+IFERROR(VLOOKUP($AT$19,Sheet1!AD10:AG10,3,0),0) -> 0 | AU25: =+IFERROR(VLOOKUP($AU$19,Sheet1!AD10:AG10,3,0),0) -> 0 | AV25: =+IFERROR(VLOOKUP($AV$19,Sheet1!AD10:AG10,3,0),0) -> 0 | AW25: =+IFERROR(VLOOKUP($AW$19,Sheet1!AD10:AG10,3,0),0) -> 0 | AX25: =+IFERROR(VLOOKUP($AX$19,Sheet1!AD10:AG10,3,0),0) -> 0 | AY25: =+IFERROR(VLOOKUP($AY$19,Sheet1!AD10:AG10,3,0),0) -> 0 | AZ25: =+IFERROR(VLOOKUP($AZ$19,Sheet1!AD10:AG10,3,0),0) -> 0 | BA25: =+IFERROR(VLOOKUP($BA$19,Sheet1!AH10:AK10,3,0),0) -> 0 | BB25: =+IFERROR(VLOOKUP($BB$19,Sheet1!AH10:AK10,3,0),0) -> 0 | BC25: =+IFERROR(VLOOKUP($BC$19,Sheet1!AH10:AK10,3,0),0) -> 0 | BD25: =+IFERROR(VLOOKUP($BD$19,Sheet1!AH10:AK10,3,0),0) -> 0 | BE25: =+IFERROR(VLOOKUP($BE$19,Sheet1!AH10:AK10,3,0),0) -> 0 | BF25: =+IFERROR(VLOOKUP($BF$19,Sheet1!AH10:AK10,3,0),0) -> 0 | BG25: =+IFERROR(VLOOKUP($BG$19,Sheet1!AH10:AK10,3,0),0) -> 0 | BH25: =+IFERROR(VLOOKUP($BH$19,Sheet1!AH10:AK10,3,0),0) -> 0 | BI25: =+IFERROR(VLOOKUP($BI$19,Sheet1!AH10:AK10,3,0),0) -> 0 | BJ25: =+IFERROR(VLOOKUP($BJ$19,Sheet1!AH10:AK10,3,0),0) -> 0 | BK25: =+IFERROR(VLOOKUP($BK$19,Sheet1!AH10:AK10,3,0),0) -> 0 | BL25: =+IFERROR(VLOOKUP($BL$19,Sheet1!AL10:AO10,3,0),0) -> 0 | BM25: =+IFERROR(VLOOKUP($BM$19,Sheet1!AL10:AO10,3,0),0) -> 0 | BN25: =+IFERROR(VLOOKUP($BN$19,Sheet1!AL10:AO10,3,0),0) -> 0 | BO25: =+IFERROR(VLOOKUP($BO$19,Sheet1!AL10:AO10,3,0),0) -> 0 | BP25: =+IFERROR(VLOOKUP($BP$19,Sheet1!AL10:AO10,3,0),0) -> 0 | BQ25: =+IFERROR(VLOOKUP($BQ$19,Sheet1!AL10:AO10,3,0),0) -> 0 | BR25: =+IFERROR(VLOOKUP($BR$19,Sheet1!AL10:AO10,3,0),0) -> 0 | BS25: 457 | BT25: =+IFERROR(VLOOKUP($BT$19,Sheet1!AL10:AO10,3,0),0) -> 0 | BU25: =+IFERROR(VLOOKUP($BU$19,Sheet1!AL10:AO10,3,0),0) -> 0 | BV25: =+IFERROR(VLOOKUP($BV$19,Sheet1!AL10:AO10,3,0),0) -> 0 | BW25: =+IFERROR(VLOOKUP($BW$19,Sheet1!AL10:AO10,3,0),0) -> 0 | BX25: =+IFERROR(VLOOKUP($BX$19,Sheet1!AP10:AS10,3,0),0) -> 0 | BY25: =+IFERROR(VLOOKUP($BY$19,Sheet1!AT10:AW10,3,0),0) -> 0 | BZ25: =+IFERROR(VLOOKUP($BZ$19,Sheet1!AX10:BA10,3,0),0) -> 0 | CA25: =+IFERROR(VLOOKUP($CA$19,Sheet1!BB10:BE10,3,0),0) -> 0 | CB25: =+IFERROR(VLOOKUP($CB$19,Sheet1!BF10:BI10,3,0),0) -> 0 | CC25: =+IFERROR(VLOOKUP($CC$19,Sheet1!BJ10:BM10,3,0),0) -> 0 | CD25: =+IFERROR(VLOOKUP($CD$19,Sheet1!BN10:BQ10,3,0),0) -> 0 | CE25: =+IFERROR(VLOOKUP($CE$19,Sheet1!BR10:BU10,3,0),0) -> 0 | CF25: =+IFERROR(VLOOKUP($CF$19,Sheet1!BV10:BY10,3,0),0) -> 0 | CG25: WOOD | CH25: MD0100070 | CI25: DRUM - 68 X 24 X 32 X 3 | CJ25: 500 | CK25: =8889/0.5 -> 17778 | CL25: =SUMPRODUCT($N$20:$CF$20,N25:CF25)+CK25 -> 764419 | CM25: =Sheet1!CB10 -> 0 | CN25: =CL25*CM25 -> 0 | CO25: 0.3 | CP25: =CL25*CO25 -> 229325.7 | CQ25: 0 | CR25: =CL25*CQ25 -> 0 | CS25: =CL25+CN25+CP25+CR25 -> 993744.7 | CT25: 0.02 | CU25: =CS25*CT25 -> 19874.894 | CV25: =Sheet1!CK10 -> 0 | CW25: =CS25*CV25 -> 0 | CX25: =Sheet1!CM10 -> 0 | CY25: =CX25*CS25 -> 0
A26: =Sheet1!A2 -> ENQ-18774-25-26 | B26: 46143 | C26: =Sheet1!C2 -> FA0700001 | D26: =Sheet1!D2 -> 1 CORE X 120 SQ. MM. AL/ARD (XLPE) | E26: =CS26+CU26+CW26+CY26 -> 329829.24 | F26: =ROUNDUP(M44,0) -> 10715 | G26: =E26+F26 -> 340544.24 | H26: =Sheet1!CR2 -> 0.18 | I26: =G26*H26 -> 61297.963 | J26: =G26+I26 -> 401842.2 | K26: 14 | L26: =Sheet1!CV2 -> KMS | M26: =J26*K26 -> 5625790.8 | N26: =+IFERROR(VLOOKUP($N$19,Sheet1!J2:L2,3,0),0) -> 324 | O26: =+IFERROR(VLOOKUP($O$19,Sheet1!J2:L2,3,0),0) -> 0 | P26: =+IFERROR(VLOOKUP($P$19,Sheet1!J2:M2,3,0),0) -> 0 | Q26: =+IFERROR(VLOOKUP($Q$19,Sheet1!J2:M2,3,0),0) -> 0 | R26: =+IFERROR(VLOOKUP($R$19,Sheet1!J2:M2,3,0),0) -> 0 | S26: =+IFERROR(VLOOKUP($S$19,Sheet1!J2:M2,3,0),0) -> 0 | T26: =+IFERROR(VLOOKUP($T$19,Sheet1!J2:M2,3,0),0) -> 0 | U26: =+IFERROR(VLOOKUP($U$19,Sheet1!J2:M2,3,0),0) -> 0 | V26: =+IFERROR(VLOOKUP($V$19,Sheet1!N2:Q2,3,0),0) -> 0 | W26: =+IFERROR(VLOOKUP($W$19,Sheet1!N2:Q2,3,0),0) -> 0 | X26: =+IFERROR(VLOOKUP($X$19,Sheet1!F2:I2,3,0),0) -> 0 | Y26: =+IFERROR(VLOOKUP($Y$19,Sheet1!F2:I2,3,0),0) -> 0 | Z26: =+IFERROR(VLOOKUP($Z$19,Sheet1!F2:I2,3,0),0) -> 0 | AA26: =+IFERROR(VLOOKUP($AA$19,Sheet1!F2:I2,3,0),0) -> 0 | AB26: =+IFERROR(VLOOKUP($AB$19,Sheet1!F2:I2,3,0),0) -> 0 | AC26: =+IFERROR(VLOOKUP($AC$19,Sheet1!F2:I2,3,0),0) -> 0 | AD26: =+IFERROR(VLOOKUP($AD$19,Sheet1!F2:I2,3,0),0) -> 0 | AE26: =+IFERROR(VLOOKUP($AE$19,Sheet1!F2:I2,3,0),0) -> 0 | AF26: =+IFERROR(VLOOKUP($AF$19,Sheet1!R2:U2,3,0),0) -> 0 | AG26: =+IFERROR(VLOOKUP($AG$19,Sheet1!R2:U2,3,0),0) -> 0 | AH26: =+IFERROR(VLOOKUP($AH$19,Sheet1!V2:Y2,3,0),0) -> 0 | AI26: =+IFERROR(VLOOKUP($AI$19,Sheet1!V2:Y2,3,0),0) -> 75 | AJ26: =+IFERROR(VLOOKUP($AJ$19,Sheet1!V2:Y2,3,0),0) -> 0 | AK26: =+IFERROR(VLOOKUP($AK$19,Sheet1!V2:Y2,3,0),0) -> 0 | AL26: =+IFERROR(VLOOKUP($AL$19,Sheet1!V2:Y2,3,0),0) -> 0 | AM26: =+IFERROR(VLOOKUP($AM$19,Sheet1!V2:Y2,3,0),0) -> 0 | AN26: =+IFERROR(VLOOKUP($AN$19,Sheet1!V2:Y2,3,0),0) -> 0 | AO26: =+IFERROR(VLOOKUP($AO$19,Sheet1!V2:Y2,3,0),0) -> 0 | AP26: =+IFERROR(VLOOKUP($AP$19,Sheet1!V2:Y2,3,0),0) -> 0 | AQ26: =+IFERROR(VLOOKUP($AQ$19,Sheet1!Z2:AB2,3,0),0) -> 0 | AR26: =+IFERROR(VLOOKUP($AR$19,Sheet1!AD2:AG2,3,0),0) -> 0 | AS26: =+IFERROR(VLOOKUP($AS$19,Sheet1!AD2:AG2,3,0),0) -> 0 | AT26: =+IFERROR(VLOOKUP($AT$19,Sheet1!AD2:AG2,3,0),0) -> 0 | AU26: =+IFERROR(VLOOKUP($AU$19,Sheet1!AD2:AG2,3,0),0) -> 0 | AV26: =+IFERROR(VLOOKUP($AV$19,Sheet1!AD2:AG2,3,0),0) -> 0 | AW26: =+IFERROR(VLOOKUP($AW$19,Sheet1!AD2:AG2,3,0),0) -> 0 | AX26: =+IFERROR(VLOOKUP($AX$19,Sheet1!AD2:AG2,3,0),0) -> 0 | AY26: =+IFERROR(VLOOKUP($AY$19,Sheet1!AD2:AG2,3,0),0) -> 0 | AZ26: =+IFERROR(VLOOKUP($AZ$19,Sheet1!AD2:AG2,3,0),0) -> 0 | BA26: =+IFERROR(VLOOKUP($BA$19,Sheet1!AH2:AK2,3,0),0) -> 0 | BB26: =+IFERROR(VLOOKUP($BB$19,Sheet1!AH2:AK2,3,0),0) -> 0 | BC26: =+IFERROR(VLOOKUP($BC$19,Sheet1!AH2:AK2,3,0),0) -> 0 | BD26: 176 | BE26: =+IFERROR(VLOOKUP($BE$19,Sheet1!AH2:AK2,3,0),0) -> 0 | BF26: =+IFERROR(VLOOKUP($BF$19,Sheet1!AH2:AK2,3,0),0) -> 0 | BG26: =+IFERROR(VLOOKUP($BG$19,Sheet1!AH2:AK2,3,0),0) -> 0 | BH26: =+IFERROR(VLOOKUP($BH$19,Sheet1!AH2:AK2,3,0),0) -> 0 | BI26: =+IFERROR(VLOOKUP($BI$19,Sheet1!AH2:AK2,3,0),0) -> 0 | BJ26: =+IFERROR(VLOOKUP($BJ$19,Sheet1!AH2:AK2,3,0),0) -> 0 | BK26: =+IFERROR(VLOOKUP($BK$19,Sheet1!AH2:AK2,3,0),0) -> 0 | BL26: =+IFERROR(VLOOKUP($BL$19,Sheet1!AL2:AO2,3,0),0) -> 0 | BM26: =+IFERROR(VLOOKUP($BM$19,Sheet1!AL2:AO2,3,0),0) -> 0 | BN26: =+IFERROR(VLOOKUP($BN$19,Sheet1!AL2:AO2,3,0),0) -> 0 | BO26: =+IFERROR(VLOOKUP($BO$19,Sheet1!AL2:AO2,3,0),0) -> 0 | BP26: =+IFERROR(VLOOKUP($BP$19,Sheet1!AL2:AO2,3,0),0) -> 0 | BQ26: =+IFERROR(VLOOKUP($BQ$19,Sheet1!AL2:AO2,3,0),0) -> 0 | BR26: =+IFERROR(VLOOKUP($BR$19,Sheet1!AL2:AO2,3,0),0) -> 0 | BT26: 175 | BU26: =+IFERROR(VLOOKUP($BU$19,Sheet1!AL2:AO2,3,0),0) -> 0 | BV26: =+IFERROR(VLOOKUP($BV$19,Sheet1!AL2:AO2,3,0),0) -> 0 | BW26: =+IFERROR(VLOOKUP($BW$19,Sheet1!AL2:AO2,3,0),0) -> 0 | BX26: =+IFERROR(VLOOKUP($BX$19,Sheet1!AP2:AS2,3,0),0) -> 0 | BY26: =+IFERROR(VLOOKUP($BY$19,Sheet1!AT2:AW2,3,0),0) -> 0 | BZ26: =+IFERROR(VLOOKUP($BZ$19,Sheet1!AX2:BA2,3,0),0) -> 0 | CA26: =+IFERROR(VLOOKUP($CA$19,Sheet1!BB2:BE2,3,0),0) -> 0 | CB26: =+IFERROR(VLOOKUP($CB$19,Sheet1!BF2:BI2,3,0),0) -> 0 | CC26: =+IFERROR(VLOOKUP($CC$19,Sheet1!BJ2:BM2,3,0),0) -> 0 | CD26: =+IFERROR(VLOOKUP($CD$19,Sheet1!BN2:BQ2,3,0),0) -> 0 | CE26: 15 | CF26: =+IFERROR(VLOOKUP($CF$19,Sheet1!BV2:BY2,3,0),0) -> 0 | CG26: =Sheet1!E2 -> STEEL | CH26: MD0200017 | CI26: STEEL DRUM 42" X 18 X 23 | CJ26: 500 | CK26: =3025/0.5 -> 6050 | CL26: =SUMPRODUCT($N$20:$CF$20,N26:CF26)+CK26 -> 248740 | CM26: =Sheet1!CB2 -> 0 | CN26: =CL26*CM26 -> 0 | CO26: 0.3 | CP26: =CL26*CO26 -> 74622 | CQ26: 0 | CR26: =CL26*CQ26 -> 0 | CS26: =CL26+CN26+CP26+CR26 -> 323362 | CT26: 0.02 | CU26: =CS26*CT26 -> 6467.24 | CV26: =Sheet1!CK2 -> 0 | CW26: =CS26*CV26 -> 0 | CX26: =Sheet1!CM2 -> 0 | CY26: =CX26*CS26 -> 0
A27: =Sheet1!A3 -> ENQ-18774-25-26 | B27: 46143 | C27: FA0600003 | D27: 1 CORE X 120 SQ. MM. ALU/UNARD (XLPE) | E27: =CS27+CU27+CW27+CY27 -> 219442.39 | F27: =ROUNDUP(M45,0) -> 7500 | G27: =E27+F27 -> 226942.39 | H27: =Sheet1!CR3 -> 0.18 | I27: =G27*H27 -> 40849.631 | J27: =G27+I27 -> 267792.02 | K27: 10 | L27: =Sheet1!CV3 -> KMS | M27: =J27*K27 -> 2677920.2 | N27: =+IFERROR(VLOOKUP($N$19,Sheet1!J3:L3,3,0),0) -> 324 | O27: =+IFERROR(VLOOKUP($O$19,Sheet1!J3:L3,3,0),0) -> 0 | P27: =+IFERROR(VLOOKUP($P$19,Sheet1!J3:M3,3,0),0) -> 0 | Q27: =+IFERROR(VLOOKUP($Q$19,Sheet1!J3:M3,3,0),0) -> 0 | R27: =+IFERROR(VLOOKUP($R$19,Sheet1!J3:M3,3,0),0) -> 0 | S27: =+IFERROR(VLOOKUP($S$19,Sheet1!J3:M3,3,0),0) -> 0 | T27: =+IFERROR(VLOOKUP($T$19,Sheet1!J3:M3,3,0),0) -> 0 | U27: =+IFERROR(VLOOKUP($U$19,Sheet1!J3:M3,3,0),0) -> 0 | V27: =+IFERROR(VLOOKUP($V$19,Sheet1!N3:Q3,3,0),0) -> 0 | W27: =+IFERROR(VLOOKUP($W$19,Sheet1!N3:Q3,3,0),0) -> 0 | X27: =+IFERROR(VLOOKUP($X$19,Sheet1!F3:I3,3,0),0) -> 0 | Y27: =+IFERROR(VLOOKUP($Y$19,Sheet1!F3:I3,3,0),0) -> 0 | Z27: =+IFERROR(VLOOKUP($Z$19,Sheet1!F3:I3,3,0),0) -> 0 | AA27: =+IFERROR(VLOOKUP($AA$19,Sheet1!F3:I3,3,0),0) -> 0 | AB27: =+IFERROR(VLOOKUP($AB$19,Sheet1!F3:I3,3,0),0) -> 0 | AC27: =+IFERROR(VLOOKUP($AC$19,Sheet1!F3:I3,3,0),0) -> 0 | AD27: =+IFERROR(VLOOKUP($AD$19,Sheet1!F3:I3,3,0),0) -> 0 | AE27: =+IFERROR(VLOOKUP($AE$19,Sheet1!F3:I3,3,0),0) -> 0 | AF27: =+IFERROR(VLOOKUP($AF$19,Sheet1!R3:U3,3,0),0) -> 0 | AG27: =+IFERROR(VLOOKUP($AG$19,Sheet1!R3:U3,3,0),0) -> 0 | AH27: =+IFERROR(VLOOKUP($AH$19,Sheet1!V3:Y3,3,0),0) -> 0 | AI27: 60 | AJ27: =+IFERROR(VLOOKUP($AJ$19,Sheet1!V3:Y3,3,0),0) -> 0 | AK27: =+IFERROR(VLOOKUP($AK$19,Sheet1!V3:Y3,3,0),0) -> 0 | AL27: =+IFERROR(VLOOKUP($AL$19,Sheet1!V3:Y3,3,0),0) -> 0 | AM27: =+IFERROR(VLOOKUP($AM$19,Sheet1!V3:Y3,3,0),0) -> 0 | AN27: =+IFERROR(VLOOKUP($AN$19,Sheet1!V3:Y3,3,0),0) -> 0 | AO27: =+IFERROR(VLOOKUP($AO$19,Sheet1!V3:Y3,3,0),0) -> 0 | AP27: =+IFERROR(VLOOKUP($AP$19,Sheet1!V3:Y3,3,0),0) -> 0 | AQ27: =+IFERROR(VLOOKUP($AQ$19,Sheet1!Z3:AB3,3,0),0) -> 0 | AR27: =+IFERROR(VLOOKUP($AR$19,Sheet1!AD3:AG3,3,0),0) -> 0 | AS27: =+IFERROR(VLOOKUP($AS$19,Sheet1!AD3:AG3,3,0),0) -> 0 | AT27: =+IFERROR(VLOOKUP($AT$19,Sheet1!AD3:AG3,3,0),0) -> 0 | AU27: =+IFERROR(VLOOKUP($AU$19,Sheet1!AD3:AG3,3,0),0) -> 0 | AV27: =+IFERROR(VLOOKUP($AV$19,Sheet1!AD3:AG3,3,0),0) -> 0 | AW27: =+IFERROR(VLOOKUP($AW$19,Sheet1!AD3:AG3,3,0),0) -> 0 | AX27: =+IFERROR(VLOOKUP($AX$19,Sheet1!AD3:AG3,3,0),0) -> 0 | AY27: =+IFERROR(VLOOKUP($AY$19,Sheet1!AD3:AG3,3,0),0) -> 0 | AZ27: =+IFERROR(VLOOKUP($AZ$19,Sheet1!AD3:AG3,3,0),0) -> 0 | BA27: =+IFERROR(VLOOKUP($BA$19,Sheet1!AH3:AK3,3,0),0) -> 0 | BB27: =+IFERROR(VLOOKUP($BB$19,Sheet1!AH3:AK3,3,0),0) -> 0 | BC27: =+IFERROR(VLOOKUP($BC$19,Sheet1!AH3:AK3,3,0),0) -> 0 | BE27: =+IFERROR(VLOOKUP($BE$19,Sheet1!AH3:AK3,3,0),0) -> 0 | BF27: =+IFERROR(VLOOKUP($BF$19,Sheet1!AH3:AK3,3,0),0) -> 0 | BG27: =+IFERROR(VLOOKUP($BG$19,Sheet1!AH3:AK3,3,0),0) -> 0 | BH27: =+IFERROR(VLOOKUP($BH$19,Sheet1!AH3:AK3,3,0),0) -> 0 | BI27: =+IFERROR(VLOOKUP($BI$19,Sheet1!AH3:AK3,3,0),0) -> 0 | BJ27: =+IFERROR(VLOOKUP($BJ$19,Sheet1!AH3:AK3,3,0),0) -> 0 | BK27: =+IFERROR(VLOOKUP($BK$19,Sheet1!AH3:AK3,3,0),0) -> 0 | BL27: =+IFERROR(VLOOKUP($BL$19,Sheet1!AL3:AO3,3,0),0) -> 0 | BM27: =+IFERROR(VLOOKUP($BM$19,Sheet1!AL3:AO3,3,0),0) -> 0 | BN27: =+IFERROR(VLOOKUP($BN$19,Sheet1!AL3:AO3,3,0),0) -> 0 | BO27: =+IFERROR(VLOOKUP($BO$19,Sheet1!AL3:AO3,3,0),0) -> 0 | BP27: =+IFERROR(VLOOKUP($BP$19,Sheet1!AL3:AO3,3,0),0) -> 0 | BQ27: =+IFERROR(VLOOKUP($BQ$19,Sheet1!AL3:AO3,3,0),0) -> 0 | BR27: =+IFERROR(VLOOKUP($BR$19,Sheet1!AL3:AO3,3,0),0) -> 0 | BT27: 170 | BU27: =+IFERROR(VLOOKUP($BU$19,Sheet1!AL3:AO3,3,0),0) -> 0 | BV27: =+IFERROR(VLOOKUP($BV$19,Sheet1!AL3:AO3,3,0),0) -> 0 | BW27: =+IFERROR(VLOOKUP($BW$19,Sheet1!AL3:AO3,3,0),0) -> 0 | BX27: =+IFERROR(VLOOKUP($BX$19,Sheet1!AP3:AS3,3,0),0) -> 0 | BY27: =+IFERROR(VLOOKUP($BY$19,Sheet1!AT3:AW3,3,0),0) -> 0 | BZ27: =+IFERROR(VLOOKUP($BZ$19,Sheet1!AX3:BA3,3,0),0) -> 0 | CA27: =+IFERROR(VLOOKUP($CA$19,Sheet1!BB3:BE3,3,0),0) -> 0 | CB27: =+IFERROR(VLOOKUP($CB$19,Sheet1!BF3:BI3,3,0),0) -> 0 | CC27: =+IFERROR(VLOOKUP($CC$19,Sheet1!BJ3:BM3,3,0),0) -> 0 | CD27: =+IFERROR(VLOOKUP($CD$19,Sheet1!BN3:BQ3,3,0),0) -> 0 | CE27: =+IFERROR(VLOOKUP($CE$19,Sheet1!BR3:BU3,3,0),0) -> 0 | CF27: =+IFERROR(VLOOKUP($CF$19,Sheet1!BV3:BY3,3,0),0) -> 0 | CG27: WOOD | CH27: MD0100066 | CI27: DRUM - 40 X 15 X 23 X 2 | CJ27: =Sheet1!CX3 -> 500 | CK27: =2200/0.5 -> 4400 | CL27: =SUMPRODUCT($N$20:$CF$20,N27:CF27)+CK27 -> 165492 | CM27: =Sheet1!CB3 -> 0 | CN27: =CL27*CM27 -> 0 | CO27: 0.3 | CP27: =CL27*CO27 -> 49647.6 | CQ27: 0 | CR27: =CL27*CQ27 -> 0 | CS27: =CL27+CN27+CP27+CR27 -> 215139.6 | CT27: 0.02 | CU27: =CS27*CT27 -> 4302.792 | CV27: =Sheet1!CK3 -> 0 | CW27: =CS27*CV27 -> 0 | CX27: =Sheet1!CM3 -> 0 | CY27: =CX27*CS27 -> 0
A28: =Sheet1!A5 -> ENQ-18774-25-26 | B28: 46143 | C28: =Sheet1!C5 -> FA0700008 | D28: =Sheet1!D5 -> 1 CORE X 300 SQ. MM. AL/ARD. (XLPE) | E28: =CS28+CU28+CW28+CY28 -> 683481.4 | F28: =ROUNDUP(M46,0) -> 12500 | G28: =E28+F28 -> 695981.4 | H28: =Sheet1!CR5 -> 0.18 | I28: =G28*H28 -> 125276.65 | J28: =G28+I28 -> 821258.05 | K28: =Sheet1!CU5 -> 12 | L28: =Sheet1!CV5 -> KMS | M28: =J28*K28 -> 9855096.6 | N28: =+IFERROR(VLOOKUP($N$19,Sheet1!J5:L5,3,0),0) -> 810 | O28: =+IFERROR(VLOOKUP($O$19,Sheet1!J5:L5,3,0),0) -> 0 | P28: =+IFERROR(VLOOKUP($P$19,Sheet1!J5:M5,3,0),0) -> 0 | Q28: =+IFERROR(VLOOKUP($Q$19,Sheet1!J5:M5,3,0),0) -> 0 | R28: =+IFERROR(VLOOKUP($R$19,Sheet1!J5:M5,3,0),0) -> 0 | S28: =+IFERROR(VLOOKUP($S$19,Sheet1!J5:M5,3,0),0) -> 0 | T28: =+IFERROR(VLOOKUP($T$19,Sheet1!J5:M5,3,0),0) -> 0 | U28: =+IFERROR(VLOOKUP($U$19,Sheet1!J5:M5,3,0),0) -> 0 | V28: =+IFERROR(VLOOKUP($V$19,Sheet1!N5:Q5,3,0),0) -> 0 | W28: =+IFERROR(VLOOKUP($W$19,Sheet1!N5:Q5,3,0),0) -> 0 | X28: =+IFERROR(VLOOKUP($X$19,Sheet1!F5:I5,3,0),0) -> 0 | Y28: =+IFERROR(VLOOKUP($Y$19,Sheet1!F5:I5,3,0),0) -> 0 | Z28: =+IFERROR(VLOOKUP($Z$19,Sheet1!F5:I5,3,0),0) -> 0 | AA28: =+IFERROR(VLOOKUP($AA$19,Sheet1!F5:I5,3,0),0) -> 0 | AB28: =+IFERROR(VLOOKUP($AB$19,Sheet1!F5:I5,3,0),0) -> 0 | AC28: =+IFERROR(VLOOKUP($AC$19,Sheet1!F5:I5,3,0),0) -> 0 | AD28: =+IFERROR(VLOOKUP($AD$19,Sheet1!F5:I5,3,0),0) -> 0 | AE28: =+IFERROR(VLOOKUP($AE$19,Sheet1!F5:I5,3,0),0) -> 0 | AF28: =+IFERROR(VLOOKUP($AF$19,Sheet1!R5:U5,3,0),0) -> 0 | AG28: =+IFERROR(VLOOKUP($AG$19,Sheet1!R5:U5,3,0),0) -> 0 | AH28: =+IFERROR(VLOOKUP($AH$19,Sheet1!V5:Y5,3,0),0) -> 0 | AI28: 158 | AJ28: =+IFERROR(VLOOKUP($AJ$19,Sheet1!V5:Y5,3,0),0) -> 0 | AK28: =+IFERROR(VLOOKUP($AK$19,Sheet1!V5:Y5,3,0),0) -> 0 | AL28: =+IFERROR(VLOOKUP($AL$19,Sheet1!V5:Y5,3,0),0) -> 0 | AM28: =+IFERROR(VLOOKUP($AM$19,Sheet1!V5:Y5,3,0),0) -> 0 | AN28: =+IFERROR(VLOOKUP($AN$19,Sheet1!V5:Y5,3,0),0) -> 0 | AO28: =+IFERROR(VLOOKUP($AO$19,Sheet1!V5:Y5,3,0),0) -> 0 | AP28: =+IFERROR(VLOOKUP($AP$19,Sheet1!V5:Y5,3,0),0) -> 0 | AQ28: =+IFERROR(VLOOKUP($AQ$19,Sheet1!Z5:AB5,3,0),0) -> 0 | AR28: =+IFERROR(VLOOKUP($AR$19,Sheet1!AD5:AG5,3,0),0) -> 0 | AS28: =+IFERROR(VLOOKUP($AS$19,Sheet1!AD5:AG5,3,0),0) -> 0 | AT28: =+IFERROR(VLOOKUP($AT$19,Sheet1!AD5:AG5,3,0),0) -> 0 | AU28: =+IFERROR(VLOOKUP($AU$19,Sheet1!AD5:AG5,3,0),0) -> 0 | AV28: =+IFERROR(VLOOKUP($AV$19,Sheet1!AD5:AG5,3,0),0) -> 0 | AW28: =+IFERROR(VLOOKUP($AW$19,Sheet1!AD5:AG5,3,0),0) -> 0 | AX28: =+IFERROR(VLOOKUP($AX$19,Sheet1!AD5:AG5,3,0),0) -> 0 | AY28: =+IFERROR(VLOOKUP($AY$19,Sheet1!AD5:AG5,3,0),0) -> 0 | AZ28: =+IFERROR(VLOOKUP($AZ$19,Sheet1!AD5:AG5,3,0),0) -> 0 | BA28: =+IFERROR(VLOOKUP($BA$19,Sheet1!AH5:AK5,3,0),0) -> 0 | BB28: =+IFERROR(VLOOKUP($BB$19,Sheet1!AH5:AK5,3,0),0) -> 0 | BC28: =+IFERROR(VLOOKUP($BC$19,Sheet1!AH5:AK5,3,0),0) -> 0 | BD28: 264 | BE28: =+IFERROR(VLOOKUP($BE$19,Sheet1!AH5:AK5,3,0),0) -> 0 | BF28: =+IFERROR(VLOOKUP($BF$19,Sheet1!AH5:AK5,3,0),0) -> 0 | BG28: =+IFERROR(VLOOKUP($BG$19,Sheet1!AH5:AK5,3,0),0) -> 0 | BH28: =+IFERROR(VLOOKUP($BH$19,Sheet1!AH5:AK5,3,0),0) -> 0 | BI28: =+IFERROR(VLOOKUP($BI$19,Sheet1!AH5:AK5,3,0),0) -> 0 | BJ28: =+IFERROR(VLOOKUP($BJ$19,Sheet1!AH5:AK5,3,0),0) -> 0 | BK28: =+IFERROR(VLOOKUP($BK$19,Sheet1!AH5:AK5,3,0),0) -> 0 | BL28: =+IFERROR(VLOOKUP($BL$19,Sheet1!AL5:AO5,3,0),0) -> 0 | BM28: =+IFERROR(VLOOKUP($BM$19,Sheet1!AL5:AO5,3,0),0) -> 0 | BN28: =+IFERROR(VLOOKUP($BN$19,Sheet1!AL5:AO5,3,0),0) -> 0 | BO28: =+IFERROR(VLOOKUP($BO$19,Sheet1!AL5:AO5,3,0),0) -> 0 | BP28: =+IFERROR(VLOOKUP($BP$19,Sheet1!AL5:AO5,3,0),0) -> 0 | BQ28: =+IFERROR(VLOOKUP($BQ$19,Sheet1!AL5:AO5,3,0),0) -> 0 | BR28: =+IFERROR(VLOOKUP($BR$19,Sheet1!AL5:AO5,3,0),0) -> 0 | BT28: 265 | BU28: =+IFERROR(VLOOKUP($BU$19,Sheet1!AL5:AO5,3,0),0) -> 0 | BV28: =+IFERROR(VLOOKUP($BV$19,Sheet1!AL5:AO5,3,0),0) -> 0 | BW28: =+IFERROR(VLOOKUP($BW$19,Sheet1!AL5:AO5,3,0),0) -> 0 | BX28: =+IFERROR(VLOOKUP($BX$19,Sheet1!AP5:AS5,3,0),0) -> 0 | BY28: =+IFERROR(VLOOKUP($BY$19,Sheet1!AT5:AW5,3,0),0) -> 0 | BZ28: =+IFERROR(VLOOKUP($BZ$19,Sheet1!AX5:BA5,3,0),0) -> 0 | CA28: =+IFERROR(VLOOKUP($CA$19,Sheet1!BB5:BE5,3,0),0) -> 0 | CB28: =+IFERROR(VLOOKUP($CB$19,Sheet1!BF5:BI5,3,0),0) -> 0 | CC28: =+IFERROR(VLOOKUP($CC$19,Sheet1!BJ5:BM5,3,0),0) -> 0 | CD28: =+IFERROR(VLOOKUP($CD$19,Sheet1!BN5:BQ5,3,0),0) -> 0 | CE28: 21 | CF28: =+IFERROR(VLOOKUP($CF$19,Sheet1!BV5:BY5,3,0),0) -> 0 | CG28: =Sheet1!E5 -> STEEL | CH28: MD0200018 | CI28: STEEL DRUM - 48" X 24 X 38 | CJ28: =Sheet1!CX5 -> 500 | CK28: =4675/0.5 -> 9350 | CL28: =SUMPRODUCT($N$20:$CF$20,N28:CF28)+CK28 -> 515446 | CM28: =Sheet1!CB5 -> 0 | CN28: =CL28*CM28 -> 0 | CO28: 0.3 | CP28: =CL28*CO28 -> 154633.8 | CQ28: 0 | CR28: =CL28*CQ28 -> 0 | CS28: =CL28+CN28+CP28+CR28 -> 670079.8 | CT28: 0.02 | CU28: =CS28*CT28 -> 13401.596 | CV28: =Sheet1!CK5 -> 0 | CW28: =CS28*CV28 -> 0 | CX28: =Sheet1!CM5 -> 0 | CY28: =CX28*CS28 -> 0
A29: =Sheet1!A4 -> ENQ-18774-25-26 | B29: 46143 | C29: =Sheet1!C4 -> FA0700002 | D29: =Sheet1!D4 -> 1 CORE X 630 SQ. MM. AL/ARD (XLPE) | E29: =CS29+CU29+CW29+CY29 -> 1348364.3 | F29: =ROUNDUP(M47,0) -> 22500 | G29: =E29+F29 -> 1370864.3 | H29: =Sheet1!CR4 -> 0.18 | I29: =G29*H29 -> 246755.58 | J29: =G29+I29 -> 1617619.9 | K29: =Sheet1!CU4 -> 10 | L29: =Sheet1!CV4 -> KMS | M29: =J29*K29 -> 16176199 | N29: =+IFERROR(VLOOKUP($N$19,Sheet1!J4:L4,3,0),0) -> 1701 | O29: =+IFERROR(VLOOKUP($O$19,Sheet1!J4:L4,3,0),0) -> 0 | P29: =+IFERROR(VLOOKUP($P$19,Sheet1!J4:M4,3,0),0) -> 0 | Q29: =+IFERROR(VLOOKUP($Q$19,Sheet1!J4:M4,3,0),0) -> 0 | R29: =+IFERROR(VLOOKUP($R$19,Sheet1!J4:M4,3,0),0) -> 0 | S29: =+IFERROR(VLOOKUP($S$19,Sheet1!J4:M4,3,0),0) -> 0 | T29: =+IFERROR(VLOOKUP($T$19,Sheet1!J4:M4,3,0),0) -> 0 | U29: =+IFERROR(VLOOKUP($U$19,Sheet1!J4:M4,3,0),0) -> 0 | V29: =+IFERROR(VLOOKUP($V$19,Sheet1!N4:Q4,3,0),0) -> 0 | W29: =+IFERROR(VLOOKUP($W$19,Sheet1!N4:Q4,3,0),0) -> 0 | X29: =+IFERROR(VLOOKUP($X$19,Sheet1!F4:I4,3,0),0) -> 0 | Y29: =+IFERROR(VLOOKUP($Y$19,Sheet1!F4:I4,3,0),0) -> 0 | Z29: =+IFERROR(VLOOKUP($Z$19,Sheet1!F4:I4,3,0),0) -> 0 | AA29: =+IFERROR(VLOOKUP($AA$19,Sheet1!F4:I4,3,0),0) -> 0 | AB29: =+IFERROR(VLOOKUP($AB$19,Sheet1!F4:I4,3,0),0) -> 0 | AC29: =+IFERROR(VLOOKUP($AC$19,Sheet1!F4:I4,3,0),0) -> 0 | AD29: =+IFERROR(VLOOKUP($AD$19,Sheet1!F4:I4,3,0),0) -> 0 | AE29: =+IFERROR(VLOOKUP($AE$19,Sheet1!F4:I4,3,0),0) -> 0 | AF29: =+IFERROR(VLOOKUP($AF$19,Sheet1!R4:U4,3,0),0) -> 0 | AG29: =+IFERROR(VLOOKUP($AG$19,Sheet1!R4:U4,3,0),0) -> 0 | AH29: =+IFERROR(VLOOKUP($AH$19,Sheet1!V4:Y4,3,0),0) -> 0 | AI29: =+IFERROR(VLOOKUP($AI$19,Sheet1!V4:Y4,3,0),0) -> 295 | AJ29: =+IFERROR(VLOOKUP($AJ$19,Sheet1!V4:Y4,3,0),0) -> 0 | AK29: =+IFERROR(VLOOKUP($AK$19,Sheet1!V4:Y4,3,0),0) -> 0 | AL29: =+IFERROR(VLOOKUP($AL$19,Sheet1!V4:Y4,3,0),0) -> 0 | AM29: =+IFERROR(VLOOKUP($AM$19,Sheet1!V4:Y4,3,0),0) -> 0 | AN29: =+IFERROR(VLOOKUP($AN$19,Sheet1!V4:Y4,3,0),0) -> 0 | AO29: =+IFERROR(VLOOKUP($AO$19,Sheet1!V4:Y4,3,0),0) -> 0 | AP29: =+IFERROR(VLOOKUP($AP$19,Sheet1!V4:Y4,3,0),0) -> 0 | AQ29: =+IFERROR(VLOOKUP($AQ$19,Sheet1!Z4:AB4,3,0),0) -> 0 | AR29: =+IFERROR(VLOOKUP($AR$19,Sheet1!AD4:AG4,3,0),0) -> 0 | AS29: =+IFERROR(VLOOKUP($AS$19,Sheet1!AD4:AG4,3,0),0) -> 0 | AT29: =+IFERROR(VLOOKUP($AT$19,Sheet1!AD4:AG4,3,0),0) -> 0 | AU29: =+IFERROR(VLOOKUP($AU$19,Sheet1!AD4:AG4,3,0),0) -> 0 | AV29: =+IFERROR(VLOOKUP($AV$19,Sheet1!AD4:AG4,3,0),0) -> 0 | AW29: =+IFERROR(VLOOKUP($AW$19,Sheet1!AD4:AG4,3,0),0) -> 0 | AX29: =+IFERROR(VLOOKUP($AX$19,Sheet1!AD4:AG4,3,0),0) -> 0 | AY29: =+IFERROR(VLOOKUP($AY$19,Sheet1!AD4:AG4,3,0),0) -> 0 | AZ29: =+IFERROR(VLOOKUP($AZ$19,Sheet1!AD4:AG4,3,0),0) -> 0 | BA29: =+IFERROR(VLOOKUP($BA$19,Sheet1!AH4:AK4,3,0),0) -> 0 | BB29: =+IFERROR(VLOOKUP($BB$19,Sheet1!AH4:AK4,3,0),0) -> 0 | BC29: =+IFERROR(VLOOKUP($BC$19,Sheet1!AH4:AK4,3,0),0) -> 0 | BD29: 464 | BE29: =+IFERROR(VLOOKUP($BE$19,Sheet1!AH4:AK4,3,0),0) -> 0 | BF29: =+IFERROR(VLOOKUP($BF$19,Sheet1!AH4:AK4,3,0),0) -> 0 | BG29: =+IFERROR(VLOOKUP($BG$19,Sheet1!AH4:AK4,3,0),0) -> 0 | BH29: =+IFERROR(VLOOKUP($BH$19,Sheet1!AH4:AK4,3,0),0) -> 0 | BI29: =+IFERROR(VLOOKUP($BI$19,Sheet1!AH4:AK4,3,0),0) -> 0 | BJ29: =+IFERROR(VLOOKUP($BJ$19,Sheet1!AH4:AK4,3,0),0) -> 0 | BK29: =+IFERROR(VLOOKUP($BK$19,Sheet1!AH4:AK4,3,0),0) -> 0 | BL29: =+IFERROR(VLOOKUP($BL$19,Sheet1!AL4:AO4,3,0),0) -> 0 | BM29: =+IFERROR(VLOOKUP($BM$19,Sheet1!AL4:AO4,3,0),0) -> 0 | BN29: =+IFERROR(VLOOKUP($BN$19,Sheet1!AL4:AO4,3,0),0) -> 0 | BO29: =+IFERROR(VLOOKUP($BO$19,Sheet1!AL4:AO4,3,0),0) -> 0 | BP29: =+IFERROR(VLOOKUP($BP$19,Sheet1!AL4:AO4,3,0),0) -> 0 | BQ29: =+IFERROR(VLOOKUP($BQ$19,Sheet1!AL4:AO4,3,0),0) -> 0 | BR29: =+IFERROR(VLOOKUP($BR$19,Sheet1!AL4:AO4,3,0),0) -> 0 | BT29: 400 | BU29: =+IFERROR(VLOOKUP($BU$19,Sheet1!AL4:AO4,3,0),0) -> 0 | BV29: =+IFERROR(VLOOKUP($BV$19,Sheet1!AL4:AO4,3,0),0) -> 0 | BW29: =+IFERROR(VLOOKUP($BW$19,Sheet1!AL4:AO4,3,0),0) -> 0 | BX29: =+IFERROR(VLOOKUP($BX$19,Sheet1!AP4:AS4,3,0),0) -> 0 | BY29: =+IFERROR(VLOOKUP($BY$19,Sheet1!AT4:AW4,3,0),0) -> 0 | BZ29: =+IFERROR(VLOOKUP($BZ$19,Sheet1!AX4:BA4,3,0),0) -> 0 | CA29: =+IFERROR(VLOOKUP($CA$19,Sheet1!BB4:BE4,3,0),0) -> 0 | CB29: =+IFERROR(VLOOKUP($CB$19,Sheet1!BF4:BI4,3,0),0) -> 0 | CC29: =+IFERROR(VLOOKUP($CC$19,Sheet1!BJ4:BM4,3,0),0) -> 0 | CD29: =+IFERROR(VLOOKUP($CD$19,Sheet1!BN4:BQ4,3,0),0) -> 0 | CE29: 29 | CF29: =+IFERROR(VLOOKUP($CF$19,Sheet1!BV4:BY4,3,0),0) -> 0 | CG29: =Sheet1!E4 -> STEEL | CH29: SP0400125 | CI29: CORRUGATED DISPATCH STEEL DRUM 1600 X 700 X 915 MM | CJ29: =Sheet1!CX4 -> 500 | CK29: =8800/0.5 -> 17600 | CL29: =SUMPRODUCT($N$20:$CF$20,N29:CF29)+CK29 -> 1016866 | CM29: =Sheet1!CB4 -> 0 | CN29: =CL29*CM29 -> 0 | CO29: 0.3 | CP29: =CL29*CO29 -> 305059.8 | CQ29: 0 | CR29: =CL29*CQ29 -> 0 | CS29: =CL29+CN29+CP29+CR29 -> 1321925.8 | CT29: 0.02 | CU29: =CS29*CT29 -> 26438.516 | CV29: =Sheet1!CK4 -> 0 | CW29: =CS29*CV29 -> 0 | CX29: =Sheet1!CM4 -> 0 | CY29: =CX29*CS29 -> 0
M30: =SUM(M21:M29) -> 9.9334744e+08
B32: NOTE for sl no 1,2,3,4 | C32: 1) Rate of Al- BALCO / HINDALCO / NALCO / VEDANTA.
C33: 2) Rate of XLPE- DOW / BOREALIS / HANWHA/ KALPANA INDUSTRIES/KLJ POLYMERS AND CHEMICALS
C34: 3) Rate of PVC- SHAKUN / KALPANA / KLJ / DCM SHRIRAM/ UNIVERSAL/ SCJ PLASTIC
C35: 4) Rate of Armour- TATA STEEL / JINDAL STEEL / SAIL / JSW
C36: 5) Please consider the extra Rs.5/KG of outer sheath for UV resistance for all items
B37: NOTE single core | C37: Please consider FRLSH on outer sheath for all items
E38: Order Quantity | F38: Stnd Length | G38: Truck type | H38: Fare of one truck | I38: No of Drum in one truck | J38: Total length in one Truck | K38: No of Truck | L38: Total Freight | M38: Freight per KM | AI38: CABLE WEIGHT KG/KM | AX38: DRUM WEIGHT | BD38: CABLE+DRUM WEIGHT | BG38: TRUCK WEIGHT
D39: =D21 -> 4 CORE X 50 SQ. MM. ALU/ARD - STRIP (XLPE) | E39: =K21 -> 140 | F39: =CJ21/1000 -> 0.5 | G39: 16 MT | H39: 75000 | I39: 16 | J39: =F39*I39 -> 8 | K39: =ROUNDUP((E39/J39),0) -> 18 | L39: =H39*K39 -> 1350000 | M39: =L39/E39 -> 9642.8571 | N39: =CH21 -> MD0100015 | AI39: =SUM(N21:CE21) -> 1471 | AX39: =125+30 -> 155 | BD39: =((AI39*F39)+AX39) -> 890.5 | BG39: =BD39*I39 -> 14248
D40: =D22 -> 4 CORE X 95 SQ. MM. AL/ARD - STRIP (XLPE) | E40: =K22 -> 600 | F40: =CJ22/1000 -> 0.5 | G40: 16 MT | H40: 75000 | I40: 8 | J40: =F40*I40 -> 4 | K40: =ROUNDUP((E40/J40),0) -> 150 | L40: =H40*K40 -> 11250000 | M40: =L40/E40 -> 18750 | N40: =CH22 -> MD0100061 | AI40: =SUM(N22:CE22) -> 2260 | AX40: =190+45 -> 235 | BD40: =((AI40*F40)+AX40) -> 1365 | BG40: =BD40*I40 -> 10920
D41: =D23 -> 4 CORE X 150 SQ. MM. AL/ARD - STRIP (XLPE) | E41: =K23 -> 100 | F41: =CJ23/1000 -> 0.5 | G41: 16 MT | H41: 75000 | I41: 6 | J41: =F41*I41 -> 3 | K41: =ROUNDUP((E41/J41),0) -> 34 | L41: =H41*K41 -> 2550000 | M41: =L41/E41 -> 25500 | N41: =CH23 -> MD0100070 | AI41: =SUM(N23:CE23) -> 3346 | AX41: =300+80 -> 380 | BD41: =((AI41*F41)+AX41) -> 2053 | BG41: =BD41*I41 -> 12318
D42: =D24 -> 4 CORE X 300 SQ. MM. AL/ARD - STRIP (XLPE) | E42: =K24 -> 50 | F42: =CJ24/1000 -> 0.5 | G42: 25 MT TRALOR | H42: 135000 | I42: 6 | J42: =F42*I42 -> 3 | K42: =ROUNDUP((E42/J42),0) -> 17 | L42: =H42*K42 -> 2295000 | M42: =L42/E42 -> 45900 | N42: =CH24 -> SP0400123 | AI42: =SUM(N24:CE24) -> 5831 | AX42: 280 | BD42: =((AI42*F42)+AX42) -> 3195.5 | BG42: =BD42*I42 -> 19173
D43: =D25 -> 3 CORE X 120 SQ MM + 1 CORE X 120 SQ MM + 1 CORE X 95 SQ MM (AB CABLES) (Insulated | E43: =K25 -> 48 | F43: =CJ25/1000 -> 0.5 | G43: 16 MT | H43: 75000 | I43: 8 | J43: =F43*I43 -> 4 | K43: =ROUNDUP((E43/J43),0) -> 12 | L43: =H43*K43 -> 900000 | M43: =L43/E43 -> 18750 | N43: =CH25 -> MD0100070 | AI43: =SUM(N25:CE25) -> 2387 | AX43: =300+80 -> 380 | BD43: =((AI43*F43)+AX43) -> 1573.5 | BG43: =BD43*I43 -> 12588
D44: =D26 -> 1 CORE X 120 SQ. MM. AL/ARD (XLPE) | E44: =K26 -> 14 | F44: =CJ26/1000 -> 0.5 | G44: 16 MT | H44: 75000 | I44: 24 | J44: =F44*I44 -> 12 | K44: =ROUNDUP((E44/J44),0) -> 2 | L44: =H44*K44 -> 150000 | M44: =L44/E44 -> 10714.286 | N44: =CH26 -> MD0200017 | AI44: =SUM(N26:CE26) -> 765 | AX44: 70 | BD44: =((AI44*F44)+AX44) -> 452.5 | BG44: =BD44*I44 -> 10860
D45: =D27 -> 1 CORE X 120 SQ. MM. ALU/UNARD (XLPE) | E45: =K27 -> 10 | F45: =CJ27/1000 -> 0.5 | G45: 16 MT | H45: 75000 | I45: 36 | J45: =F45*I45 -> 18 | K45: =ROUNDUP((E45/J45),0) -> 1 | L45: =H45*K45 -> 75000 | M45: =L45/E45 -> 7500 | N45: =CH27 -> MD0100066 | AI45: =SUM(N27:CE27) -> 554 | AX45: =75+25 -> 100 | BD45: =((AI45*F45)+AX45) -> 377 | BG45: =BD45*I45 -> 13572
D46: =D28 -> 1 CORE X 300 SQ. MM. AL/ARD. (XLPE) | E46: =K28 -> 12 | F46: =CJ28/1000 -> 0.5 | G46: 16 MT | H46: 75000 | I46: 14 | J46: =F46*I46 -> 7 | K46: =ROUNDUP((E46/J46),0) -> 2 | L46: =H46*K46 -> 150000 | M46: =L46/E46 -> 12500 | N46: =CH28 -> MD0200018 | AI46: =SUM(N28:CE28) -> 1518 | AX46: =125+30 -> 155 | BD46: =((AI46*F46)+AX46) -> 914 | BG46: =BD46*I46 -> 12796
D47: =D29 -> 1 CORE X 630 SQ. MM. AL/ARD (XLPE) | E47: =K29 -> 10 | F47: =CJ29/1000 -> 0.5 | G47: 16 MT | H47: 75000 | I47: 8 | J47: =F47*I47 -> 4 | K47: =ROUNDUP((E47/J47),0) -> 3 | L47: =H47*K47 -> 225000 | M47: =L47/E47 -> 22500 | N47: =CH29 -> SP0400125 | AI47: =SUM(N29:CE29) -> 2889 | AX47: 160 | BD47: =((AI47*F47)+AX47) -> 1604.5 | BG47: =BD47*I47 -> 12836
A52: DOCKET NO. | B52: BASE DATE | C52: ITEM CODE | D52: PROPOSE ERP ITEM NAME | E52: EX-WORKS (PER MTR) | F52: FREIGHT PER MTR | G52: PRICE INCLUDING FREIGHT (PER MTR) | H52: GST % | I52: GST VALUE | J52: PRICE INCLUDING GST & FREIGHT (PER MTR) | K52: QTY | L52: Unit | M52: TOTAL PRICE OF FULL QTY (INCLUDING FRIGHT & GST)
A54: =A21 -> ENQ-18774-25-26 | B54: =B21 -> 46143 | C54: =C21 -> FA0900036 | D54: =D21 -> 4 CORE X 50 SQ. MM. ALU/ARD - STRIP (XLPE) | E54: =ROUNDUP(E21/1000,2) -> 438.37 | F54: =ROUNDUP(F21/1000,2) -> 9.65 | G54: =E54+F54 -> 448.02 | H54: =H21 -> 0.18 | I54: =ROUND(G54*H54,2) -> 80.64 | J54: =G54+I54 -> 528.66 | K54: =K21*1000 -> 140000 | L54: MTR | M54: =J54*K54 -> 74012400 | N54: =G54*K54 -> 62722800
A55: =A22 -> ENQ-18774-25-26 | B55: =B22 -> 46143 | C55: =C22 -> FA1100012 | D55: =D22 -> 4 CORE X 95 SQ. MM. AL/ARD - STRIP (XLPE) | E55: =ROUNDUP(E22/1000,2) -> 761.7 | F55: =ROUNDUP(F22/1000,2) -> 18.75 | G55: =E55+F55 -> 780.45 | H55: =H22 -> 0.18 | I55: =ROUND(G55*H55,2) -> 140.48 | J55: =G55+I55 -> 920.93 | K55: =K22*1000 -> 600000 | L55: MTR | M55: =J55*K55 -> 552558000 | N55: =G55*K55 -> 468270000
A56: =A23 -> ENQ-18774-25-26 | B56: =B23 -> 46143 | C56: =C23 -> FA1100067 | D56: =D23 -> 4 CORE X 150 SQ. MM. AL/ARD - STRIP (XLPE) | E56: =ROUNDUP(E23/1000,2) -> 1166.33 | F56: =ROUNDUP(F23/1000,2) -> 25.5 | G56: =E56+F56 -> 1191.83 | H56: =H23 -> 0.18 | I56: =ROUND(G56*H56,2) -> 214.53 | J56: =G56+I56 -> 1406.36 | K56: =K23*1000 -> 100000 | L56: MTR | M56: =J56*K56 -> 140636000 | N56: =G56*K56 -> 119183000
A57: =A24 -> ENQ-18774-25-26 | B57: =B24 -> 46143 | C57: =C24 -> FA1100025 | D57: =D24 -> 4 CORE X 300 SQ. MM. AL/ARD - STRIP (XLPE) | E57: =ROUNDUP(E24/1000,2) -> 2214.02 | F57: =ROUNDUP(F24/1000,2) -> 45.9 | G57: =E57+F57 -> 2259.92 | H57: =H24 -> 0.18 | I57: =ROUND(G57*H57,2) -> 406.79 | J57: =G57+I57 -> 2666.71 | K57: =K24*1000 -> 50000 | L57: MTR | M57: =J57*K57 -> 1.333355e+08 | N57: =G57*K57 -> 1.12996e+08
A58: =A25 -> ENQ-18774-25-26 | B58: =B25 -> 46143 | C58: =C25 -> 0 | D58: =D25 -> 3 CORE X 120 SQ MM + 1 CORE X 120 SQ MM + 1 CORE X 95 SQ MM (AB CABLES) (Insulated | E58: =ROUNDUP(E25/1000,2) -> 1013.62 | F58: =ROUNDUP(F25/1000,2) -> 18.75 | G58: =E58+F58 -> 1032.37 | H58: =H25 -> 0.18 | I58: =ROUND(G58*H58,2) -> 185.83 | J58: =G58+I58 -> 1218.2 | K58: =K25*1000 -> 48000 | L58: MTR | M58: =J58*K58 -> 58473600 | N58: =G58*K58 -> 49553760
A59: =A26 -> ENQ-18774-25-26 | B59: =B26 -> 46143 | C59: =C26 -> FA0700001 | D59: =D26 -> 1 CORE X 120 SQ. MM. AL/ARD (XLPE) | E59: =ROUNDUP(E26/1000,2) -> 329.83 | F59: =ROUNDUP(F26/1000,2) -> 10.72 | G59: =E59+F59 -> 340.55 | H59: =H26 -> 0.18 | I59: =ROUND(G59*H59,2) -> 61.3 | J59: =G59+I59 -> 401.85 | K59: =K26*1000 -> 14000 | L59: MTR | M59: =J59*K59 -> 5625900 | N59: =G59*K59 -> 4767700
A60: =A27 -> ENQ-18774-25-26 | B60: =B27 -> 46143 | C60: =C27 -> FA0600003 | D60: =D27 -> 1 CORE X 120 SQ. MM. ALU/UNARD (XLPE) | E60: =ROUNDUP(E27/1000,2) -> 219.45 | F60: =ROUNDUP(F27/1000,2) -> 7.5 | G60: =E60+F60 -> 226.95 | H60: =H27 -> 0.18 | I60: =ROUND(G60*H60,2) -> 40.85 | J60: =G60+I60 -> 267.8 | K60: =K27*1000 -> 10000 | L60: MTR | M60: =J60*K60 -> 2678000 | N60: =G60*K60 -> 2269500
A61: =A28 -> ENQ-18774-25-26 | B61: =B28 -> 46143 | C61: =C28 -> FA0700008 | D61: =D28 -> 1 CORE X 300 SQ. MM. AL/ARD. (XLPE) | E61: =ROUNDUP(E28/1000,2) -> 683.49 | F61: =ROUNDUP(F28/1000,2) -> 12.5 | G61: =E61+F61 -> 695.99 | H61: =H28 -> 0.18 | I61: =ROUND(G61*H61,2) -> 125.28 | J61: =G61+I61 -> 821.27 | K61: =K28*1000 -> 12000 | L61: MTR | M61: =J61*K61 -> 9855240 | N61: =G61*K61 -> 8351880
A62: =A29 -> ENQ-18774-25-26 | B62: =B29 -> 46143 | C62: =C29 -> FA0700002 | D62: =D29 -> 1 CORE X 630 SQ. MM. AL/ARD (XLPE) | E62: =ROUNDUP(E29/1000,2) -> 1348.37 | F62: =ROUNDUP(F29/1000,2) -> 22.5 | G62: =E62+F62 -> 1370.87 | H62: =H29 -> 0.18 | I62: =ROUND(G62*H62,2) -> 246.76 | J62: =G62+I62 -> 1617.63 | K62: =K29*1000 -> 10000 | L62: MTR | M62: =J62*K62 -> 16176300 | N62: =G62*K62 -> 13708700
M63: =SUM(M54:M62) -> 993350940 | N63: =SUM(N54:N62) -> 841823340
M64: =M63-M30 -> 3504.2513

Sheet PV AUTO CALCULATION-LTABC
A2: Base Date | B2: 46143
A3: PV Terms (IEEMA CIRCULAR)
A4: PV FORMULA (IEEMA)
A5: P = P0 + Alph * n* (Al-Al0) + Alm(Al-Al0) + Alsl(Al-Al0) + Aln(Al-Al0) + CCFAlph *n* (CC-Cco)+CCFAlm(CC- Cco)+CCFAlsl (CC-Cco) + CCFAln(CC-Cco) This price shall be as per IEEMA Circulars of January 2026 (Published in February 2026).
A9: Item | B9: Calculation part | C9: Date of Inspection | D9: Applicable Date | G9: BASE DATE | J9: FACTORS | S9: Ex-Work Po | T9: PVC of Al | U9: PVC of AlM | V9: PVC of Aln | W9: PVC of Alsl | X9: PVC of CCFAIph | Y9: PVC of CCFAIm | Z9: PVC of CCFAIn | AA9: PVC of CCFAIsl | AB9: PV/PKM | AC9: Billing Price/PKM | AD9: VALUE ADDITION CALCULATION WITH RESPECT TO PERCENTAGE
D10: Date | E10: Al | F10: CC | G10: Date | H10: Alo | I10: Cco
J11: n | K11: Alph | L11: Alm | M11: Aln | N11: Alsl | O11: CCFAIph | P11: CCFAIm | Q11: CCFAIn | R11: CCFAIsl | AD11: ='AUTO CALCULATION SHEET (2)'!N19 -> Alumimium | AE11: ='AUTO CALCULATION SHEET (2)'!O19 -> Alumimium ALLOY | AF11: ='AUTO CALCULATION SHEET (2)'!AI19 -> LT-XLPE | AG11: RMC | AH11: Drum | AI11: RMC+Drum | AJ11: VA | AK11: Groos VA% | AL11: Mfg % | AM11: Int % | AN11: Ins% | AO11: Net VA %
AD12: 403 | AE12: =AD12+5 -> 408 | AF12: 147
A13: ='AUTO CALCULATION SHEET (2)'!D25 -> 3 CORE X 120 SQ MM + 1 CORE X 120 SQ MM + 1 CORE X 95 SQ MM (AB CABLES) (Insulated | C13: PROVISIONAL | D13: 46185 | E13: 422899.8 | F13: 219178 | G13: =$B$2 -> 46143 | H13: 418401 | I13: 219178 | J13: 3 | K13: 0.346 | L13: 0.346 | M13: 0.274 | O13: 0.073 | P13: 0.077 | Q13: 0.063 | S13: ='AUTO CALCULATION SHEET (2)'!E58*1000 -> 1013620 | T13: =(K13*J13*(E13-H13)) -> 4669.7544 | U13: =L13*(E13-H13) -> 1556.5848 | V13: =M13*(E13-H13) -> 1232.6712 | W13: =N13*(E13-H13) -> 0 | X13: =(O13*J13*(F13-I13)) -> 0 | Y13: =P13*(F13-I13) -> 0 | Z13: =Q13*(F13-I13) -> 0 | AA13: =R13*(F13-I13) -> 0 | AB13: =T13+U13+V13+W13+X13+Y13+Z13+AA13 -> 7459.0104 | AC13: =S13+AB13 -> 1021079 | AD13: ='AUTO CALCULATION SHEET (2)'!N25 -> 1296 | AE13: ='AUTO CALCULATION SHEET (2)'!O25 -> 270 | AF13: ='AUTO CALCULATION SHEET (2)'!AI25 -> 364 | AG13: =SUMPRODUCT($AD$12:$AF$12,AD13:AF13) -> 685956 | AH13: ='AUTO CALCULATION SHEET (2)'!CK25 -> 17778 | AI13: =+AG13+AH13 -> 703734 | AJ13: =+AC13-AI13 -> 317345.01 | AK13: =+AJ13/AI13 -> 0.45094455 | AM13: 0.02 | AO13: =+AK13-(AL13+AM13+AN13) -> 0.43094455

Sheet PV AUTO CALCULATION-LTPC
A1: Base Date | B1: 46143
A2: PV FORMULA
A3: P=Po+AIF(Al-Alo)+XLFAL(Cc-Cco)+CCFAl(PVCc-PVCco)+FeF(Fe-Feo) This price shall be as per IEEMA Circulars of January 2026 (Published in February 2026).
AF7: VALUE ADDITION CALCULATION
A8: Item | B8: Calculation part | C8: Date of Inspection | D8: Applicable Date | J8: BASE DATE | P8: FACTORS | W8: Ex-Work Po | X8: PVC of al | Y8: PVC of Cu | Z8: PVC of XLPE | AA8: PVC OF PVC | AB8: PVC OF FE | AC8: PVC OF CU TAPE | AD8: PV/PKM | AE8: Billing Price/PKM
D9: Date | E9: Al | F9: Cu | G9: Cc | H9: PVCc | I9: Fe | J9: Date | K9: Alo | L9: Cuo | M9: Cco | N9: PVCco | O9: Feo | AF9: ='AUTO CALCULATION SHEET (2)'!N19 -> Alumimium | AG9: ='AUTO CALCULATION SHEET (2)'!AI19 -> LT-XLPE | AH9: ='AUTO CALCULATION SHEET (2)'!AX19 -> PVC Type ST-2 | AI9: ='AUTO CALCULATION SHEET (2)'!BD19 -> Aluminium Round Wire | AJ9: ='AUTO CALCULATION SHEET (2)'!BG19 -> Galvanised Steel Flat Strip | AK9: ='AUTO CALCULATION SHEET (2)'!BO19 -> FRLSH PVC Type ST-2 + UV resistance | AL9: ='AUTO CALCULATION SHEET (2)'!BT19 -> FRLSH PVC Type ST-2 | AM9: ='AUTO CALCULATION SHEET (2)'!CE19 -> RUBBERIZED COTTON TAPE | AN9: RMC | AO9: Drum | AP9: RMC+Drum | AQ9: VA | AR9: Groos VA% | AS9: Mfg % | AT9: Int % | AU9: Ins% | AV9: Net VA
P10: Alf | Q10: Cu | R10: XLFAL | S10: CCFAI | T10: CCFCu | U10: FeF | V10: Smif | AF10: 403 | AG10: 147 | AH10: 77 | AI10: 408 | AJ10: 87 | AK10: =97+5 -> 102 | AL10: 97 | AM10: 280
AF11: Kg/Km | AG11: Kg/Km | AH11: Kg/Km | AI11: Kg/Km | AJ11: Kg/Km | AK11: Kg/Km | AL11: Kg/Km | AM11: Kg/Km
A12: ='AUTO CALCULATION SHEET (2)'!D21 -> 4 CORE X 50 SQ. MM. ALU/ARD - STRIP (XLPE) | C12: PROVISIONAL | D12: 46185 | E12: 422899.8 | G12: 219178 | H12: 178375 | I12: 89250 | J12: =$B$1 -> 46143 | K12: 418401 | M12: 219178 | N12: 178375 | O12: 89250 | P12: 0.547 | R12: 0.144 | S12: 0.394 | U12: 0.499 | W12: ='AUTO CALCULATION SHEET (2)'!E54*1000 -> 438370 | X12: =(P12*(E12-K12)) -> 2460.8436 | Y12: =(Q12*(F12-L12)) -> 0 | Z12: =(R12*(G12-M12)) -> 0 | AA12: =(S12*(H12-N12)) -> 0 | AB12: =(U12*(I12-O12)) -> 0 | AC12: =V12*(F12-L12) -> 0 | AD12: =X12+Y12+Z12+AA12+AB12+AC12 -> 2460.8436 | AE12: =+W12+AD12 -> 440830.84 | AF12: ='AUTO CALCULATION SHEET (2)'!N21 -> 540 | AG12: ='AUTO CALCULATION SHEET (2)'!AI21 -> 144 | AH12: ='AUTO CALCULATION SHEET (2)'!AX21 -> 60 | AI12: ='AUTO CALCULATION SHEET (2)'!BD21 -> 0 | AJ12: ='AUTO CALCULATION SHEET (2)'!BG21 -> 446 | AK12: ='AUTO CALCULATION SHEET (2)'!BO21 -> 245 | AL12: ='AUTO CALCULATION SHEET (2)'!BT21 -> 0 | AM12: ='AUTO CALCULATION SHEET (2)'!CE21 -> 36 | AN12: =SUMPRODUCT(AF12:AM12,$AF$10:$AM$10) -> 317280 | AO12: ='AUTO CALCULATION SHEET (2)'!CK21 -> 5114 | AP12: =AN12+AO12 -> 322394 | AQ12: =AE12-AP12 -> 118436.84 | AR12: =ROUND((AQ12/AP12)*100,2) -> 36.74 | AS12: 0 | AT12: 2 | AU12: 0 | AV12: =AR12-AS12-AT12-AU12 -> 34.74
A13: ='AUTO CALCULATION SHEET (2)'!D22 -> 4 CORE X 95 SQ. MM. AL/ARD - STRIP (XLPE) | C13: PROVISIONAL | D13: 46185 | E13: 422899.8 | G13: 219178 | H13: 178375 | I13: 89250 | J13: =$B$1 -> 46143 | K13: 418401 | M13: 219178 | N13: 178375 | O13: 89250 | P13: 1.095 | R13: 0.211 | S13: 0.523 | U13: 0.645 | W13: ='AUTO CALCULATION SHEET (2)'!E55*1000 -> 761700 | X13: =(P13*(E13-K13)) -> 4926.186 | Y13: =(Q13*(F13-L13)) -> 0 | Z13: =(R13*(G13-M13)) -> 0 | AA13: =(S13*(H13-N13)) -> 0 | AB13: =(U13*(I13-O13)) -> 0 | AC13: =V13*(F13-L13) -> 0 | AD13: =X13+Y13+Z13+AA13+AB13+AC13 -> 4926.186 | AE13: =+W13+AD13 -> 766626.19 | AF13: ='AUTO CALCULATION SHEET (2)'!N22 -> 1026 | AG13: ='AUTO CALCULATION SHEET (2)'!AI22 -> 204 | AH13: ='AUTO CALCULATION SHEET (2)'!AX22 -> 96 | AI13: ='AUTO CALCULATION SHEET (2)'!BD22 -> 0 | AJ13: ='AUTO CALCULATION SHEET (2)'!BG22 -> 577 | AK13: ='AUTO CALCULATION SHEET (2)'!BO22 -> 310 | AL13: ='AUTO CALCULATION SHEET (2)'!BT22 -> 0 | AM13: ='AUTO CALCULATION SHEET (2)'!CE22 -> 47 | AN13: =SUMPRODUCT(AF13:AM13,$AF$10:$AM$10) -> 545837 | AO13: ='AUTO CALCULATION SHEET (2)'!CK22 -> 13354 | AP13: =AN13+AO13 -> 559191 | AQ13: =AE13-AP13 -> 207435.19 | AR13: =ROUND((AQ13/AP13)*100,2) -> 37.1 | AS13: 0 | AT13: 2 | AU13: 0 | AV13: =AR13-AS13-AT13-AU13 -> 35.1
A14: ='AUTO CALCULATION SHEET (2)'!D23 -> 4 CORE X 150 SQ. MM. AL/ARD - STRIP (XLPE) | C14: PROVISIONAL | D14: 46185 | E14: 422899.8 | G14: 219178 | H14: 178375 | I14: 89250 | J14: =$B$1 -> 46143 | K14: 418401 | M14: 219178 | N14: 178375 | O14: 89250 | P14: 1.706 | R14: 0.344 | S14: 0.762 | U14: 0.79 | W14: ='AUTO CALCULATION SHEET (2)'!E56*1000 -> 1166330 | X14: =(P14*(E14-K14)) -> 7674.9528 | Y14: =(Q14*(F14-L14)) -> 0 | Z14: =(R14*(G14-M14)) -> 0 | AA14: =(S14*(H14-N14)) -> 0 | AB14: =(U14*(I14-O14)) -> 0 | AC14: =V14*(F14-L14) -> 0 | AD14: =X14+Y14+Z14+AA14+AB14+AC14 -> 7674.9528 | AE14: =+W14+AD14 -> 1174005 | AF14: ='AUTO CALCULATION SHEET (2)'!N23 -> 1620 | AG14: ='AUTO CALCULATION SHEET (2)'!AI23 -> 315 | AH14: ='AUTO CALCULATION SHEET (2)'!AX23 -> 165 | AI14: ='AUTO CALCULATION SHEET (2)'!BD23 -> 0 | AJ14: ='AUTO CALCULATION SHEET (2)'!BG23 -> 735 | AK14: ='AUTO CALCULATION SHEET (2)'!BO23 -> 453 | AL14: ='AUTO CALCULATION SHEET (2)'!BT23 -> 0 | AM14: ='AUTO CALCULATION SHEET (2)'!CE23 -> 58 | AN14: =SUMPRODUCT(AF14:AM14,$AF$10:$AM$10) -> 838261 | AO14: ='AUTO CALCULATION SHEET (2)'!CK23 -> 17778 | AP14: =AN14+AO14 -> 856039 | AQ14: =AE14-AP14 -> 317965.95 | AR14: =ROUND((AQ14/AP14)*100,2) -> 37.14 | AS14: 0 | AT14: 2 | AU14: 0 | AV14: =AR14-AS14-AT14-AU14 -> 35.14
A15: ='AUTO CALCULATION SHEET (2)'!D24 -> 4 CORE X 300 SQ. MM. AL/ARD - STRIP (XLPE) | C15: PROVISIONAL | D15: 46185 | E15: 422899.8 | G15: 219178 | H15: 178375 | I15: 89250 | J15: =$B$1 -> 46143 | K15: 418401 | M15: 219178 | N15: 178375 | O15: 89250 | P15: 3.514 | R15: 0.62 | S15: 1.414 | U15: 1.113 | W15: ='AUTO CALCULATION SHEET (2)'!E57*1000 -> 2214020 | X15: =(P15*(E15-K15)) -> 15808.783 | Y15: =(Q15*(F15-L15)) -> 0 | Z15: =(R15*(G15-M15)) -> 0 | AA15: =(S15*(H15-N15)) -> 0 | AB15: =(U15*(I15-O15)) -> 0 | AC15: =V15*(F15-L15) -> 0 | AD15: =X15+Y15+Z15+AA15+AB15+AC15 -> 15808.783 | AE15: =+W15+AD15 -> 2229828.8 | AF15: ='AUTO CALCULATION SHEET (2)'!N24 -> 3240 | AG15: ='AUTO CALCULATION SHEET (2)'!AI24 -> 560 | AH15: ='AUTO CALCULATION SHEET (2)'!AX24 -> 240 | AI15: ='AUTO CALCULATION SHEET (2)'!BD24 -> 0 | AJ15: ='AUTO CALCULATION SHEET (2)'!BG24 -> 971 | AK15: ='AUTO CALCULATION SHEET (2)'!BO24 -> 740 | AL15: ='AUTO CALCULATION SHEET (2)'!BT24 -> 0 | AM15: ='AUTO CALCULATION SHEET (2)'!CE24 -> 80 | AN15: =SUMPRODUCT(AF15:AM15,$AF$10:$AM$10) -> 1588877 | AO15: ='AUTO CALCULATION SHEET (2)'!CK24 -> 33000 | AP15: =AN15+AO15 -> 1621877 | AQ15: =AE15-AP15 -> 607951.78 | AR15: =ROUND((AQ15/AP15)*100,2) -> 37.48 | AS15: 0 | AT15: 2 | AU15: 0 | AV15: =AR15-AS15-AT15-AU15 -> 35.48
A16: ='AUTO CALCULATION SHEET (2)'!D26 -> 1 CORE X 120 SQ. MM. AL/ARD (XLPE) | C16: PROVISIONAL | D16: 46185 | E16: 422899.8 | G16: 219178 | H16: 178375 | J16: =$B$1 -> 46143 | K16: 418401 | M16: 219178 | N16: 178375 | P16: 0.5443 | R16: 0.076 | S16: 0.184 | W16: ='AUTO CALCULATION SHEET (2)'!E59*1000 -> 329830 | X16: =(P16*(E16-K16)) -> 2448.6968 | Y16: =(Q16*(F16-L16)) -> 0 | Z16: =(R16*(G16-M16)) -> 0 | AA16: =(S16*(H16-N16)) -> 0 | AB16: =(U16*(I16-O16)) -> 0 | AC16: =V16*(F16-L16) -> 0 | AD16: =X16+Y16+Z16+AA16+AB16+AC16 -> 2448.6968 | AE16: =+W16+AD16 -> 332278.7 | AF16: ='AUTO CALCULATION SHEET (2)'!N26 -> 324 | AG16: ='AUTO CALCULATION SHEET (2)'!AI26 -> 75 | AH16: ='AUTO CALCULATION SHEET (2)'!AX26 -> 0 | AI16: ='AUTO CALCULATION SHEET (2)'!BD26 -> 176 | AJ16: ='AUTO CALCULATION SHEET (2)'!BG26 -> 0 | AK16: ='AUTO CALCULATION SHEET (2)'!BO26 -> 0 | AL16: ='AUTO CALCULATION SHEET (2)'!BT26 -> 175 | AM16: ='AUTO CALCULATION SHEET (2)'!CE26 -> 15 | AN16: =SUMPRODUCT(AF16:AM16,$AF$10:$AM$10) -> 234580 | AO16: ='AUTO CALCULATION SHEET (2)'!CK26 -> 6050 | AP16: =AN16+AO16 -> 240630 | AQ16: =AE16-AP16 -> 91648.697 | AR16: =ROUND((AQ16/AP16)*100,2) -> 38.09 | AS16: 0 | AT16: 2 | AU16: 0 | AV16: =AR16-AS16-AT16-AU16 -> 36.09
A17: ='AUTO CALCULATION SHEET (2)'!D27 -> 1 CORE X 120 SQ. MM. ALU/UNARD (XLPE) | C17: PROVISIONAL | D17: 46185 | E17: 422899.8 | G17: 219178 | H17: 178375 | J17: =$B$1 -> 46143 | K17: 418401 | M17: 219178 | N17: 178375 | P17: 0.345 | R17: 0.06 | S17: 0.176 | W17: ='AUTO CALCULATION SHEET (2)'!E60*1000 -> 219450 | X17: =(P17*(E17-K17)) -> 1552.086 | Y17: =(Q17*(F17-L17)) -> 0 | Z17: =(R17*(G17-M17)) -> 0 | AA17: =(S17*(H17-N17)) -> 0 | AB17: =(U17*(I17-O17)) -> 0 | AC17: =V17*(F17-L17) -> 0 | AD17: =X17+Y17+Z17+AA17+AB17+AC17 -> 1552.086 | AE17: =+W17+AD17 -> 221002.09 | AF17: ='AUTO CALCULATION SHEET (2)'!N27 -> 324 | AG17: ='AUTO CALCULATION SHEET (2)'!AI27 -> 60 | AH17: ='AUTO CALCULATION SHEET (2)'!AX27 -> 0 | AI17: ='AUTO CALCULATION SHEET (2)'!BD27 -> 0 | AJ17: ='AUTO CALCULATION SHEET (2)'!BG27 -> 0 | AK17: ='AUTO CALCULATION SHEET (2)'!BO27 -> 0 | AL17: ='AUTO CALCULATION SHEET (2)'!BT27 -> 170 | AM17: ='AUTO CALCULATION SHEET (2)'!CE27 -> 0 | AN17: =SUMPRODUCT(AF17:AM17,$AF$10:$AM$10) -> 155882 | AO17: ='AUTO CALCULATION SHEET (2)'!CK27 -> 4400 | AP17: =AN17+AO17 -> 160282 | AQ17: =AE17-AP17 -> 60720.086 | AR17: =ROUND((AQ17/AP17)*100,2) -> 37.88 | AS17: 0 | AT17: 2 | AU17: 0 | AV17: =AR17-AS17-AT17-AU17 -> 35.88
A18: ='AUTO CALCULATION SHEET (2)'!D28 -> 1 CORE X 300 SQ. MM. AL/ARD. (XLPE) | C18: PROVISIONAL | D18: 46185 | E18: 422899.8 | G18: 219178 | H18: 178375 | J18: =$B$1 -> 46143 | K18: 418401 | M18: 219178 | N18: 178375 | P18: 1.2582 | R18: 0.164 | S18: 0.301 | W18: ='AUTO CALCULATION SHEET (2)'!E61*1000 -> 683490 | X18: =(P18*(E18-K18)) -> 5660.3902 | Y18: =(Q18*(F18-L18)) -> 0 | Z18: =(R18*(G18-M18)) -> 0 | AA18: =(S18*(H18-N18)) -> 0 | AB18: =(U18*(I18-O18)) -> 0 | AC18: =V18*(F18-L18) -> 0 | AD18: =X18+Y18+Z18+AA18+AB18+AC18 -> 5660.3902 | AE18: =+W18+AD18 -> 689150.39 | AF18: ='AUTO CALCULATION SHEET (2)'!N28 -> 810 | AG18: ='AUTO CALCULATION SHEET (2)'!AI28 -> 158 | AH18: ='AUTO CALCULATION SHEET (2)'!AX28 -> 0 | AI18: ='AUTO CALCULATION SHEET (2)'!BD28 -> 264 | AJ18: ='AUTO CALCULATION SHEET (2)'!BG28 -> 0 | AK18: ='AUTO CALCULATION SHEET (2)'!BO28 -> 0 | AL18: ='AUTO CALCULATION SHEET (2)'!BT28 -> 265 | AM18: ='AUTO CALCULATION SHEET (2)'!CE28 -> 21 | AN18: =SUMPRODUCT(AF18:AM18,$AF$10:$AM$10) -> 488953 | AO18: ='AUTO CALCULATION SHEET (2)'!CK28 -> 9350 | AP18: =AN18+AO18 -> 498303 | AQ18: =AE18-AP18 -> 190847.39 | AR18: =ROUND((AQ18/AP18)*100,2) -> 38.3 | AS18: 0 | AT18: 2 | AU18: 0 | AV18: =AR18-AS18-AT18-AU18 -> 36.3
A19: ='AUTO CALCULATION SHEET (2)'!D29 -> 1 CORE X 630 SQ. MM. AL/ARD (XLPE) | C19: PROVISIONAL | D19: 46185 | E19: 422899.8 | G19: 219178 | H19: 178375 | J19: =$B$1 -> 46143 | K19: 418401 | M19: 219178 | N19: 178375 | P19: 2.365 | R19: 0.0318 | S19: 0.497 | W19: ='AUTO CALCULATION SHEET (2)'!E62*1000 -> 1348370 | X19: =(P19*(E19-K19)) -> 10639.662 | Y19: =(Q19*(F19-L19)) -> 0 | Z19: =(R19*(G19-M19)) -> 0 | AA19: =(S19*(H19-N19)) -> 0 | AB19: =(U19*(I19-O19)) -> 0 | AC19: =V19*(F19-L19) -> 0 | AD19: =X19+Y19+Z19+AA19+AB19+AC19 -> 10639.662 | AE19: =+W19+AD19 -> 1359009.7 | AF19: ='AUTO CALCULATION SHEET (2)'!N29 -> 1701 | AG19: ='AUTO CALCULATION SHEET (2)'!AI29 -> 295 | AH19: ='AUTO CALCULATION SHEET (2)'!AX29 -> 0 | AI19: ='AUTO CALCULATION SHEET (2)'!BD29 -> 464 | AJ19: ='AUTO CALCULATION SHEET (2)'!BG29 -> 0 | AK19: ='AUTO CALCULATION SHEET (2)'!BO29 -> 0 | AL19: ='AUTO CALCULATION SHEET (2)'!BT29 -> 400 | AM19: ='AUTO CALCULATION SHEET (2)'!CE29 -> 29 | AN19: =SUMPRODUCT(AF19:AM19,$AF$10:$AM$10) -> 965100 | AO19: ='AUTO CALCULATION SHEET (2)'!CK29 -> 17600 | AP19: =AN19+AO19 -> 982700 | AQ19: =AE19-AP19 -> 376309.66 | AR19: =ROUND((AQ19/AP19)*100,2) -> 38.29 | AS19: 0 | AT19: 2 | AU19: 0 | AV19: =AR19-AS19-AT19-AU19 -> 36.29

Sheet terms
A1: The quoted prices are on Firm inclusive of packing and forwading but exclusive of GST Statutory levies.
A2: The quoted prices are on VARIABLE basis with PV base Date: DD/MM/YYYY as per "IEEMA", inclusive of packing and forwading but exclusive of GST Statutory levies.
A4: The above prices are quoted on Ex-works basis, where freight will be charged extra.
A5: The above prices are quoted on FOR Destination basis, where freight is included, refer Price offer.
A6: The above prices are quoted on Ex-works+Freight basis.
A8: 20% Advance and Balance against PI (Proforma Invoice) prior to dispatch
A9: 100% against "90 days" LC, where 90 days usance interest will be borne by LPIPL
A10: 100% against "120 days" LC, where 120 days usance interest will be borne by LPIPL
A11: 100% against "45 days" LC, where 45 days usance interest will be borne by LPIPL
A12: 100% against "60 days" LC, where 60 days usance interest will be borne by LPIPL
A13: 100% against "30 days" LC, where 30 days usance interest will be borne by LPIPL
A14: 100% against 60 days PDC from the date of MRC/MRN
... A27: Negotiable
