Workbook

Sheet Sheet1
A1: DOCKET NO. | B1: Base Date | C1: ITEM CODE | D1: PROPOSE ERP ITEM NAME | E1: PROPOSE DRUM TYPE | F1: Insulation Screening (Metallic) | G1: Sum of RM RATE (Insulation Screening (Metallic)) | H1: Weight (Insulation Screening (Metallic)) | I1: COST(Insulation Screening (Metallic)) | J1: Conductor | K1: Sum of RM RATE(Conductor) | L1: WEIGHT(Conductor) | M1: COST(Conductor) | N1: AL ALLOY | O1: Sum of RM RATE(Alu Alloy) | P1: WEIGHT(Alu Alloy) | Q1: COST(Alu Alloy) | R1: Insulation Screening (Non-Metallic) | S1: Sum of RM RATE(Insulation Screening (Non-Metallic)) | T1: WEIGHT(Insulation Screening (Non-Metallic)) | U1: COST(Insulation Screening (Non-Metallic)) | V1: Insulation | W1: Sum of RM RATE(Insulation) | X1: WEIGHT(Insulation) | Y1: COST(Insulation) | Z1: POLY TAPE | AA1: Sum of RM RATE (Poly Tape) | AB1: WEIGHT (Poly Tape) | AC1: COST(Poly Tape) | AD1: Inner Sheath | AE1: Sum of RM RATE(Inner Sheath) | AF1: WEIGHT(Inner Sheath) | AG1: COST(Inner Sheath) | AH1: Armouring | AI1: Sum of RM RATE(Armouring) | AJ1: WEIGHT(Armouring) | AK1: COST(Armouring) | AL1: Outer Sheath | AM1: Sum of RM RATE(Outer Sheath) | AN1: WEIGHT(Outer Sheath) | AO1: COST(Outer Sheath) | AP1: FILLER | AQ1: Sum of RM RATE(Filler) | AR1: WEIGHT(Filler) | AS1: COST(Filler) | AT1: GREASE | AU1: Sum of RM RATE(Grease) | AV1: WEIGHT(Grease) | AW1: COST(Grease) | AX1: Water swellable Tape | AY1: Sum of RM RATE(Water swellable Tape) | AZ1: WEIGHT(Water swellable Tape) | BA1: COST(Water swellable Tape) | BB1: Semi conducting Water Swellable tape | BC1: Sum of RM RATE(Semi conducting Water Swellable tape) | BD1: WEIGHT(Semi conducting Water Swellable tape) | BE1: COST(Semi conducting Water Swellable tape) | BF1: SEMICON TAPE | BG1: Sum of RM RATE(SEMICON TAPE) | BH1: WEIGHT(SEMICON TAPE) | BI1: COST(SEMICON TAPE) | BJ1: GLASS FIBER TAPE | BK1: Sum of RM RATE(GLASS FIBER TAPE) | BL1: WEIGHT(GLASS FIBER TAPE) | BM1: COST(GLASS FIBER TAPE) | BN1: COPPER WIRE 0.8 MM | BO1: Sum of RM RATE(COPPER WIRE 0.8 MM) | BP1: WEIGHT(COPPER WIRE 0.8 MM) | BQ1: COST(COPPER WIRE 0.8 MM) | BR1: RUBBERIZED COTTON TAPE | BS1: Sum of RM RATE(RUBBERIZED COTTON TAPE) | BT1: WEIGHT(RUBBERIZED COTTON TAPE) | BU1: COST(RUBBERIZED COTTON TAPE) | BV1: Water Tight Compound | BW1: Sum of RM RATE(Water Tight Compound) | BX1: WEIGHT(Water Tight Compound) | BY1: COST(Water Tight Compound) | BZ1: DRUM COST PER KM | CA1: TOTAL RM COST | CB1: FIRM % | CC1: FIRM VALUE | CD1: MFG% | CE1: MFG VALUE | CF1: PROF% | CG1: PROFIT VALUE | CH1: 1ST EX-WORKS | CI1: Intt % | CJ1: INTT VALUE | CK1: insp% | CL1: INSP VALUE | CM1: EX-WORKS (PER KM) | CN1: FREIGHT PER KM | CO1: PRICE INCLUDING FREIGHT (PER KM) | CP1: GST % | CQ1: GST VALUE | CR1: PRICE INCLUDING GST & FREIGHT (PER KM) | CS1: QTY | CT1: Unit | CU1: TOTAL PRICE OF FULL QTY (INCLUDING FRIGHT & GST) | CV1: DRUM CODE | CW1: DRUM SIZE (FxbXtx Ft) | CX1: PARTY STANDARD LENGTH (MTR)
A2: ENQ-10886-22-23 | B2: 45078 | C2: FA0100109 | D2: 3 CORE X 150 SQ MM + 1 CORE X 16 SQ MM + 1 CORE X 95 SQ MM (AB CABLES) (BARE) | E2: WOOD | J2: Alumimium | K2: 221 | L2: 1259 | M2: 278239 | N2: Alumimium Alloy | O2: 228 | P2: 262 | Q2: 59736 | T2: 0 | V2: LT-XLPE | W2: 115.7 | X2: 302 | Y2: 34941.4 | AB2: 0 | AF2: 0 | AJ2: 0 | AN2: 0 | AR2: 0 | AV2: 0 | AZ2: 0 | BD2: 0 | BH2: 0 | BL2: 0 | BP2: 0 | BT2: 0 | BX2: 0 | BZ2: 14697.63 | CA2: 387614.03 | CH2: 387614.03 | CM2: 387614.03 | CO2: 387614.03 | CP2: 0.18 | CQ2: 69770.53 | CR2: 457384.56 | CS2: 160 | CT2: KMS | CU2: 73181529 | CV2: MD0100078 | CW2: DRUM - 60 X 22 X 38 X 2.5 | CX2: 500

Sheet AUTO CALCULATION SHEET (2)
A2: M.P. MADHYA KSHETRA VIDYUT VITARAN CO. LTD., BHOPAL
A4: TENDER SPECIFICATION NO () | B4: MD/MK/04/950
A5: TENDER DESCRIPTION () | B5: Supply of LT AB Cable.
A6: Last Date & Time of Submission () | B6: 01.08.23 at 15:00 hrs.
A7: REVERSE AUCTION | B7: Not Mention.
A8: Price () | B8: The ex-works prices of LT XLPE Aerial Bunch Cable shall be Variable as per relevant IEEMA Price Variation formula, both on plus & minus side without any ceiling. The basic price of the material and indices used shall be as published by IEEMA prevailing as on first working day of the month, one month prior to the date of opening of tender.
A9: Validity () | B9: Offers should be kept open for acceptance for at least 180 days from the date of opening. Those who do not agree for a validity of 180 days will do so at their own risk and no request for extending the validity is likely to be made from this office.
A10: Delivery Period () | B10: The bidder shall require to complete the delivery in following installment. The first lot / installment shall be supplied within 70 days from the date of issue of order (including date of issue) sent through email and subsequent lot(s) within next 45 days thereafter as under: 1st Lot - Percentage of ordered quantity - 25% -To be supplied within 70 days from the date of receipt of order 2nd Lot - Percentage of ordered quantity - 25% -To be supplied within 45 days from the date of receipt of order 3rd Lot - Percentage of ordered quantity - 25% -To be supplied within 45 days from the date of receipt of order 4th Lot - Percentage of ordered quantity - 25% -To be supplied within 45 days from the date of receipt of order
A11: Payment Terms () | B11: Subject to completion of all contractual formalities 100% payment along with taxes corresponding to the consignment would generally be made within 45 working days from the date of DRR on acceptance of material by the Area Stores after successful testing at NABL Lab.
A12: Standard length () | B12: The standard length of cable shall be 500 Mtrs./1000 Mtrs. with Plus Minus 5% tolerance.
A13: Packing () | B13: The cable shall be wound on a drum (refer-IS:10418-1982) of suitable size and packed. The packing shall be robust enough for rough handling that is occasioned during transportation by Rail/Road. The ends of the cable shall be sealed by means of non-hygroscopic sealing material.
A14: Technical Specification
N16: =Sheet1!J1 -> Conductor | S16: AL ALLOY | U16: Insulation Screening (Metallic) | AC16: Insulation Screening (Non-Metallic) | AE16: Insulation | AK16: POLY TAPE | AL16: Inner Sheath | AS16: Armouring | BC16: Outer Sheath | BM16: FILLER | BN16: GREASE | BO16: Water swellable Tape | BP16: Semi conducting Water Swellable tape | BQ16: SEMICON TAPE | BR16: GLASS FIBER TAPE | BS16: COPPER WIRE 0.8 MM | BT16: RUBBERIZED COTTON TAPE | BU16: Water Tight Compound | BZ16: DRUM COST PER KM | CA16: TOTAL RM COST | CB16: EXTRA CONSUMPTION | CC16: EXTRA CONSUMPTION VALUE
A17: DOCKET NO. | B17: =Sheet1!B1 -> Base Date | C17: ITEM CODE | D17: PROPOSE ERP ITEM NAME | E17: EX-WORKS (PER KM) | F17: FREIGHT PER KM | G17: PRICE INCLUDING FREIGHT (PER KM) | H17: GST % | I17: GST VALUE | J17: PRICE INCLUDING GST & FREIGHT (PER KM) | K17: QTY | L17: Unit | M17: TOTAL PRICE OF FULL QTY (INCLUDING FRIGHT & GST) | N17: Alumimium | O17: Alumimium ALLOY | P17: Copper | Q17: Flexible Copper | R17: Galvanized steel wire | S17: Alumimium | T17: Alumimium ALLOY | U17: Coper tape - 0.1 mm | V17: Copper Tape - 0.03 mm | W17: Copper Tape - 0.035 mm | X17: Copper Tape - 0.04 mm | Y17: Copper Tape - 0.045 mm | Z17: Copper Tape - 0.050 mm | AA17: Copper Tape - 0.060 mm | AB17: Copper Tape - 0.075 mm(DOUBLE) | AC17: Extruded semiconductive | AD17: Extruded Semiconductive(Stripable) | AE17: HT-XLPE | AF17: LT-XLPE | AG17: TR XLPE | AH17: Type A PVC | AI17: Type C PVC (HR) | AJ17: XLPE | AK17: POLY TAPE | AL17: FR PVC Type ST-1 | AM17: FR PVC Type ST-2 | AN17: FRLSH PVC Type ST-2 | AO17: PVC Type ST-1 | AP17: PVC Type ST-1-PRESSURE EXTRUDED | AQ17: PVC Type ST-2 | AR17: PVC Type ST-2-PRESSURE EXTRUDED | AS17: ACSR CORE WIRE | AT17: ACSR DOG STEEL WIRE | AU17: Aluminium Flat Strip | AV17: Aluminium Round Wire | AW17: Double Steel Tape | AX17: Galvanised Steel Flat Strip | AY17: Galvanised Steel Flat Strip (Double) | AZ17: Galvanised Steel Flat Strip-B | BA17: Galvanised Steel Round Wire | BB17: Galvanised Steel Round Wire (Double) | BC17: FR PVC Type ST-1 | BD17: FR PVC Type ST-2 | BE17: FRLSH PVC Type ST-1 | BF17: FRLSH PVC Type ST-2 | BG17: PE, ST-3 | BH17: PE, ST-7 | BI17: PVC Type ST-1 | BJ17: PVC Type ST-2 | BK17: PVC Type ST-2-PRESSURE EXTRUDED | BL17: UV & Track Resistant XLPE | BM17: FILLER | BN17: Grease | BO17: Water swellable Tape | BP17: Semi conducting Water Swellable tape | BQ17: SEMICON TAPE | BR17: GLASS FIBER TAPE | BS17: COPPER WIRE 0.8 MM | BT17: RUBBERIZED COTTON TAPE | BU17: Water Tight Compound | BV17: =Sheet1!E1 -> PROPOSE DRUM TYPE | BW17: =Sheet1!CV1 -> DRUM CODE | BX17: =Sheet1!CW1 -> DRUM SIZE (FxbXtx Ft) | BY17: =Sheet1!CX1 -> PARTY STANDARD LENGTH (MTR) | CD17: MFG% | CE17: MFG VALUE | CF17: PROF% | CG17: PROFIT VALUE | CH17: 1ST EX-WORKS | CI17: Intt % | CJ17: INTT VALUE | CK17: insp% | CL17: INSP VALUE
N18: 209 | O18: =+IFERROR(VLOOKUP($O$17,Sheet1!J:L,2,0),0) -> 0 | P18: =+IFERROR(VLOOKUP($P$17,Sheet1!J:M,2,0),0) -> 0 | Q18: =+IFERROR(VLOOKUP($Q$17,Sheet1!J:M,2,0),0) -> 0 | R18: =+IFERROR(VLOOKUP($R$17,Sheet1!J:M,2,0),0) -> 0 | S18: =+IFERROR(VLOOKUP($S$17,Sheet1!N:Q,2,0),0) -> 0 | T18: =N18+7 -> 216 | U18: =+IFERROR(VLOOKUP($U$17,Sheet1!F:I,2,0),0) -> 0 | V18: =+IFERROR(VLOOKUP($V$17,Sheet1!F:I,2,0),0) -> 0 | W18: =+IFERROR(VLOOKUP($W$17,Sheet1!F:I,2,0),0) -> 0 | X18: =+IFERROR(VLOOKUP($X$17,Sheet1!F:I,2,0),0) -> 0 | Y18: =+IFERROR(VLOOKUP($Y$17,Sheet1!F:I,2,0),0) -> 0 | Z18: =+IFERROR(VLOOKUP($Z$17,Sheet1!F:I,2,0),0) -> 0 | AA18: =+IFERROR(VLOOKUP($AA$17,Sheet1!F:I,2,0),0) -> 0 | AB18: =+IFERROR(VLOOKUP($AB$17,Sheet1!F:I,2,0),0) -> 0 | AC18: =+IFERROR(VLOOKUP($AC$17,Sheet1!R:U,2,0),0) -> 0 | AD18: =+IFERROR(VLOOKUP($AD$17,Sheet1!R:U,2,0),0) -> 0 | AE18: =+IFERROR(VLOOKUP($AE$17,Sheet1!V:Y,2,0),0) -> 0 | AF18: 110 | AG18: =+IFERROR(VLOOKUP($AG$17,Sheet1!V:Y,2,0),0) -> 0 | AH18: =+IFERROR(VLOOKUP($AH$17,Sheet1!V:Y,2,0),0) -> 0 | AI18: =+IFERROR(VLOOKUP($AI$17,Sheet1!V:Y,2,0),0) -> 0 | AJ18: =+IFERROR(VLOOKUP($AJ$17,Sheet1!V:Y,2,0),0) -> 0 | AK18: =+IFERROR(VLOOKUP($AK$17,Sheet1!Z2:AA840,2,0),0) -> 0 | AL18: =+IFERROR(VLOOKUP($AL$17,Sheet1!AD2:AG840,2,0),0) -> 0 | AM18: =+IFERROR(VLOOKUP($AM$17,Sheet1!AD2:AG840,2,0),0) -> 0 | AN18: =+IFERROR(VLOOKUP($AN$17,Sheet1!AD2:AG840,2,0),0) -> 0 | AO18: =+IFERROR(VLOOKUP($AO$17,Sheet1!AD2:AG840,2,0),0) -> 0 | AP18: =+IFERROR(VLOOKUP($AP$17,Sheet1!AD2:AG840,2,0),0) -> 0 | AQ18: =+IFERROR(VLOOKUP($AQ$17,Sheet1!AD2:AG840,2,0),0) -> 0 | AR18: =+IFERROR(VLOOKUP($AR$17,Sheet1!AD2:AG840,2,0),0) -> 0 | AS18: =+IFERROR(VLOOKUP($AS$17,Sheet1!AH2:AK840,2,0),0) -> 0 | AT18: =+IFERROR(VLOOKUP($AT$17,Sheet1!AH2:AK840,2,0),0) -> 0 | AU18: =+IFERROR(VLOOKUP($AU$17,Sheet1!AH2:AK840,2,0),0) -> 0 | AV18: =+IFERROR(VLOOKUP($AV$17,Sheet1!AH2:AK840,2,0),0) -> 0 | AW18: =+IFERROR(VLOOKUP($AW$17,Sheet1!AH2:AK840,2,0),0) -> 0 | AX18: =+IFERROR(VLOOKUP($AX$17,Sheet1!AH2:AK840,2,0),0) -> 0 | AY18: =+IFERROR(VLOOKUP($AY$17,Sheet1!AH2:AK840,2,0),0) -> 0 | AZ18: =+IFERROR(VLOOKUP($AZ$17,Sheet1!AH2:AK840,2,0),0) -> 0 | BA18: =+IFERROR(VLOOKUP($BA$17,Sheet1!AH2:AK840,2,0),0) -> 0 | BB18: =+IFERROR(VLOOKUP($BB$17,Sheet1!AH2:AK840,2,0),0) -> 0 | BC18: =+IFERROR(VLOOKUP($BC$17,Sheet1!AL2:AO840,2,0),0) -> 0 | BD18: =+IFERROR(VLOOKUP($BD$17,Sheet1!AL2:AO840,2,0),0) -> 0 | BE18: =+IFERROR(VLOOKUP($BE$17,Sheet1!AL2:AO840,2,0),0) -> 0 | BF18: =+IFERROR(VLOOKUP($BF$17,Sheet1!AL2:AO840,2,0),0) -> 0 | BG18: =+IFERROR(VLOOKUP($BG$17,Sheet1!AL2:AO840,2,0),0) -> 0 | BH18: =+IFERROR(VLOOKUP($BH$17,Sheet1!AL2:AO840,2,0),0) -> 0 | BI18: =+IFERROR(VLOOKUP($BI$17,Sheet1!AL2:AO840,2,0),0) -> 0 | BJ18: =+IFERROR(VLOOKUP($BJ$17,Sheet1!AL2:AO840,2,0),0) -> 0 | BK18: =+IFERROR(VLOOKUP($BK$17,Sheet1!AL2:AO840,2,0),0) -> 0 | BL18: =+IFERROR(VLOOKUP($BL$17,Sheet1!AL2:AO840,2,0),0) -> 0 | BM18: =+IFERROR(VLOOKUP($BM$17,Sheet1!AP2:AS840,2,0),0) -> 0 | BN18: =+IFERROR(VLOOKUP($BN$17,Sheet1!AT2:AW840,2,0),0) -> 0 | BO18: =+IFERROR(VLOOKUP($BO$17,Sheet1!AX2:BA840,2,0),0) -> 0 | BP18: =+IFERROR(VLOOKUP($BP$17,Sheet1!BB2:BE840,2,0),0) -> 0 | BQ18: =+IFERROR(VLOOKUP($BQ$17,Sheet1!BF2:BI840,2,0),0) -> 0 | BR18: =+IFERROR(VLOOKUP($BR$17,Sheet1!BJ2:BM840,2,0),0) -> 0 | BS18: =+IFERROR(VLOOKUP($BS$17,Sheet1!BN2:BQ840,2,0),0) -> 0 | BT18: =+IFERROR(VLOOKUP($BT$17,Sheet1!BR2:BU840,2,0),0) -> 0 | BU18: =+IFERROR(VLOOKUP($BU$17,Sheet1!BV2:BY840,2,0),0) -> 0
A19: =Sheet1!A2 -> ENQ-10886-22-23 | B19: 45108 | C19: =Sheet1!C2 -> FA0100109 | D19: =Sheet1!D2 -> 3 CORE X 150 SQ MM + 1 CORE X 16 SQ MM + 1 CORE X 95 SQ MM (AB CABLES) (BARE) | E19: =CH19+CJ19+CL19 -> 457959.96 | F19: =ROUNDUP(M22,0) -> 16875 | G19: =E19+F19 -> 474834.96 | H19: =Sheet1!CP2 -> 0.18 | I19: =G19*H19 -> 85470.293 | J19: =G19+I19 -> 560305.25 | K19: =Sheet1!CS2 -> 160 | L19: =Sheet1!CT2 -> KMS | M19: =J19*K19 -> 89648841 | N19: =+IFERROR(VLOOKUP($N$17,Sheet1!J2:L2,3,0),0) -> 1259 | O19: =+IFERROR(VLOOKUP($O$17,Sheet1!J2:L2,3,0),0) -> 0 | P19: =+IFERROR(VLOOKUP($P$17,Sheet1!J2:M2,3,0),0) -> 0 | Q19: =+IFERROR(VLOOKUP($Q$17,Sheet1!J2:M2,3,0),0) -> 0 | R19: =+IFERROR(VLOOKUP($R$17,Sheet1!J2:M2,3,0),0) -> 0 | S19: =+IFERROR(VLOOKUP($S$17,Sheet1!N2:Q2,3,0),0) -> 0 | T19: =+IFERROR(VLOOKUP($T$17,Sheet1!N2:Q2,3,0),0) -> 262 | U19: =+IFERROR(VLOOKUP($U$17,Sheet1!F2:I2,3,0),0) -> 0 | V19: =+IFERROR(VLOOKUP($V$17,Sheet1!F2:I2,3,0),0) -> 0 | W19: =+IFERROR(VLOOKUP($W$17,Sheet1!F2:I2,3,0),0) -> 0 | X19: =+IFERROR(VLOOKUP($X$17,Sheet1!F2:I2,3,0),0) -> 0 | Y19: =+IFERROR(VLOOKUP($Y$17,Sheet1!F2:I2,3,0),0) -> 0 | Z19: =+IFERROR(VLOOKUP($Z$17,Sheet1!F2:I2,3,0),0) -> 0 | AA19: =+IFERROR(VLOOKUP($AA$17,Sheet1!F2:I2,3,0),0) -> 0 | AB19: =+IFERROR(VLOOKUP($AB$17,Sheet1!F2:I2,3,0),0) -> 0 | AC19: =+IFERROR(VLOOKUP($AC$17,Sheet1!R2:U2,3,0),0) -> 0 | AD19: =+IFERROR(VLOOKUP($AD$17,Sheet1!R2:U2,2,0),0) -> 0 | AE19: =+IFERROR(VLOOKUP($AE$17,Sheet1!V2:Y2,3,0),0) -> 0 | AF19: 320 | AG19: =+IFERROR(VLOOKUP($AG$17,Sheet1!V2:Y2,3,0),0) -> 0 | AH19: =+IFERROR(VLOOKUP($AH$17,Sheet1!V2:Y2,3,0),0) -> 0 | AI19: =+IFERROR(VLOOKUP($AI$17,Sheet1!V2:Y2,3,0),0) -> 0 | AJ19: =+IFERROR(VLOOKUP($AJ$17,Sheet1!V2:Y2,3,0),0) -> 0 | AK19: =+IFERROR(VLOOKUP($AK$17,Sheet1!Z2:AB2,3,0),0) -> 0 | AL19: =+IFERROR(VLOOKUP($AL$17,Sheet1!AD2:AG2,3,0),0) -> 0 | AM19: =+IFERROR(VLOOKUP($AM$17,Sheet1!AD2:AG2,3,0),0) -> 0 | AN19: =+IFERROR(VLOOKUP($AN$17,Sheet1!AD2:AG2,3,0),0) -> 0 | AO19: =+IFERROR(VLOOKUP($AO$17,Sheet1!AD2:AG2,3,0),0) -> 0 | AP19: =+IFERROR(VLOOKUP($AP$17,Sheet1!AD2:AG2,3,0),0) -> 0 | AQ19: =+IFERROR(VLOOKUP($AQ$17,Sheet1!AD2:AG2,3,0),0) -> 0 | AR19: =+IFERROR(VLOOKUP($AR$17,Sheet1!AD2:AG2,3,0),0) -> 0 | AS19: =+IFERROR(VLOOKUP($AS$17,Sheet1!AH2:AK2,3,0),0) -> 0 | AT19: =+IFERROR(VLOOKUP($AT$17,Sheet1!AH2:AK2,3,0),0) -> 0 | AU19: =+IFERROR(VLOOKUP($AU$17,Sheet1!AH2:AK2,3,0),0) -> 0 | AV19: =+IFERROR(VLOOKUP($AV$17,Sheet1!AH2:AK2,3,0),0) -> 0 | AW19: =+IFERROR(VLOOKUP($AW$17,Sheet1!AH2:AK2,3,0),0) -> 0 | AX19: =+IFERROR(VLOOKUP($AX$17,Sheet1!AH2:AK2,3,0),0) -> 0 | AY19: =+IFERROR(VLOOKUP($AY$17,Sheet1!AH2:AK2,3,0),0) -> 0 | AZ19: =+IFERROR(VLOOKUP($AZ$17,Sheet1!AH2:AK2,3,0),0) -> 0 | BA19: =+IFERROR(VLOOKUP($BA$17,Sheet1!AH2:AK2,3,0),0) -> 0 | BB19: =+IFERROR(VLOOKUP($BB$17,Sheet1!AH2:AK2,3,0),0) -> 0 | BC19: =+IFERROR(VLOOKUP($BC$17,Sheet1!AL2:AO2,3,0),0) -> 0 | BD19: =+IFERROR(VLOOKUP($BD$17,Sheet1!AL2:AO2,3,0),0) -> 0 | BE19: =+IFERROR(VLOOKUP($BE$17,Sheet1!AL2:AO2,3,0),0) -> 0 | BF19: =+IFERROR(VLOOKUP($BF$17,Sheet1!AL2:AO2,3,0),0) -> 0 | BG19: =+IFERROR(VLOOKUP($BG$17,Sheet1!AL2:AO2,3,0),0) -> 0 | BH19: =+IFERROR(VLOOKUP($BH$17,Sheet1!AL2:AO2,3,0),0) -> 0 | BI19: =+IFERROR(VLOOKUP($BI$17,Sheet1!AL2:AO2,3,0),0) -> 0 | BJ19: =+IFERROR(VLOOKUP($BJ$17,Sheet1!AL2:AO2,3,0),0) -> 0 | BK19: =+IFERROR(VLOOKUP($BK$17,Sheet1!AL2:AO2,3,0),0) -> 0 | BL19: =+IFERROR(VLOOKUP($BL$17,Sheet1!AL2:AO2,3,0),0) -> 0 | BM19: =+IFERROR(VLOOKUP($BM$17,Sheet1!AP2:AS2,3,0),0) -> 0 | BN19: =+IFERROR(VLOOKUP($BN$17,Sheet1!AT2:AW2,3,0),0) -> 0 | BO19: =+IFERROR(VLOOKUP($BO$17,Sheet1!AX2:BA2,3,0),0) -> 0 | BP19: =+IFERROR(VLOOKUP($BP$17,Sheet1!BB2:BE2,3,0),0) -> 0 | BQ19: =+IFERROR(VLOOKUP($BQ$17,Sheet1!BF2:BI2,3,0),0) -> 0 | BR19: =+IFERROR(VLOOKUP($BR$17,Sheet1!BJ2:BM2,3,0),0) -> 0 | BS19: =+IFERROR(VLOOKUP($BS$17,Sheet1!BN2:BQ2,3,0),0) -> 0 | BT19: =+IFERROR(VLOOKUP($BT$17,Sheet1!BR2:BU2,3,0),0) -> 0 | BU19: =+IFERROR(VLOOKUP($BU$17,Sheet1!BV2:BY2,3,0),0) -> 0 | BV19: =Sheet1!E2 -> WOOD | BW19: =Sheet1!CV2 -> MD0100078 | BX19: =Sheet1!CW2 -> DRUM - 60 X 22 X 38 X 2.5 | BY19: =Sheet1!CX2 -> 500 | BZ19: =Sheet1!BZ2 -> 14697.63 | CA19: =SUMPRODUCT($N$18:$BU$18,N19:BU19)+BZ19 -> 369620.63 | CB19: =Sheet1!CB2 -> 0 | CC19: =CA19*CB19 -> 0 | CD19: 0.18 | CE19: =CA19*CD19 -> 66531.713 | CF19: 0 | CG19: =CA19*CF19 -> 0 | CH19: =CA19+CC19+CE19+CG19 -> 436152.34 | CI19: 0.02 | CJ19: =CH19*CI19 -> 8723.0469 | CK19: 0.03 | CL19: =CH19*CK19 -> 13084.57
E21: Order Quantity | F21: Stnd Length | G21: Truck type | H21: Fare of one truck | I21: No of Drum in one truck | J21: Total length in one Truck | K21: No of Truck | L21: Total Freight | M21: Freight per KM
E22: =K19 -> 160 | F22: 0.5 | G22: 16 MT | H22: 75000 | I22: 9 | J22: =F22*I22 -> 4.5 | K22: =ROUNDUP((E22/J22),0) -> 36 | L22: =M22*E22 -> 2700000 | M22: =(H22*K22)/E22 -> 16875

Sheet LT ABC
A1: MP
A2: The basic price of the material and indices used shall be as published by IEEMA prevailing as on first working day of the month, one month prior to the date of opening of tender. The basic price of the material and indices used shall be as published by IEEMA prevailing as on first working day of the month, one month prior to the date of opening of tender.
A3: Base Date | B3: 45108
A4: PV Terms()
A5: PV FORMULA (IEEMA)
A6: P = Po + AIph*n* (Al – Alo)+ AIm (Al – Alo)+ AIsl (Al – Alo)+CCFAIph*n*(CC-CCo)+CCFAIm(CC-CCo)+ CCFAIsl(CC-CCo)
A9: n | B9: No. of Phase Conductor
A10: Alph | B10: Aluminium factor for phase conductor
A11: Alm | B11: Aluminium factor for messenger conductor
A12: CCFAIph | B12: XLPE factor for phase conductor
A13: CCFAIm | B13: XLPE factor for messenger conductor (For bare messenger,XLPE factor CCFAIm=0)
A15: Item | B15: Ex-Work
A16: ='AUTO CALCULATION SHEET (2)'!D19 -> 3 CORE X 150 SQ MM + 1 CORE X 16 SQ MM + 1 CORE X 95 SQ MM (AB CABLES) (BARE) | B16: ='AUTO CALCULATION SHEET (2)'!E19 -> 457959.96
A18: Item | B18: Calculation part | C18: Date of Inspection | D18: Applicable Date | G18: BASE DATE | J18: FACTORS | Q18: Ex-Work Po | R18: PVC of Al | S18: PVC of AlM | T18: PVC of Alsl | U18: PVC of CCFAIph | V18: PVC of CCFAIm | W18: PVC of CCFAIsl | X18: PV/PKM | Y18: Billing Price/PKM | Z18: VALUE ADDITION CALCULATION WITH RESPECT TO PERCENTAGE
D19: Date | E19: Al | F19: CC | G19: Date | H19: Alo | I19: Cco
J20: n | K20: Alph | L20: Alm | M20: Alsl | N20: CCFAIph | O20: CCFAIm | P20: CCFAIsl | Z20: Al @ | AA20: alloy | AB20: LT-XLPE | AC20: RMC | AD20: Drum | AE20: RMC+Drum | AF20: VA | AG20: Groos VA% | AH20: Mfg % | AI20: Int % | AJ20: Ins% | AK20: Net VA %
Z21: 211 | AA21: 218 | AB21: 110
A22: =A16 -> 3 CORE X 150 SQ MM + 1 CORE X 16 SQ MM + 1 CORE X 95 SQ MM (AB CABLES) (BARE) | D22: 45137 | E22: 201717.77 | F22: 151990 | G22: 45108 | H22: 201717.77 | I22: 151990 | J22: 3 | K22: 0.425 | L22: 0.274 | M22: 0.046 | N22: 0.085 | P22: 0.024 | Q22: =B16 -> 457959.96 | R22: =(K22*J22*(E22-H22)) -> 0 | S22: =L22*(E22-H22) -> 0 | T22: =M22*(E22-H22) -> 0 | U22: =(N22*J22*(F22-I22)) -> 0 | V22: =O22*(F22-I22) -> 0 | W22: =P22*(F22-I22) -> 0 | X22: =R22+S22+T22+U22+V22+W22 -> 0 | Y22: =Q22+X22 -> 457959.96 | Z22: ='AUTO CALCULATION SHEET (2)'!N19 -> 1259 | AA22: ='AUTO CALCULATION SHEET (2)'!T19 -> 262 | AB22: ='AUTO CALCULATION SHEET (2)'!AF19 -> 320 | AC22: =SUMPRODUCT($Z$21:$AB$21,Z22:AB22) -> 357965 | AD22: ='AUTO CALCULATION SHEET (2)'!BZ19 -> 14697.63 | AE22: =+AC22+AD22 -> 372662.63 | AF22: =+Y22-AE22 -> 85297.331 | AG22: =+AF22/AE22 -> 0.22888619 | AI22: 0.02 | AJ22: 0.03 | AK22: =+AG22-(AH22+AI22+AJ22) -> 0.17888619
